{
  "type": "Feature",
  "properties": {
    "addr:full":"53 Compo Beach Rd Westport CT 06880",
    "addr:housenumber":"53",
    "addr:postcode":"06880",
    "addr:street":"Compo Beach Rd",
    "iso:country":"US",
    "sg:address":"53 Compo Beach Rd",
    "sg:city":"Westport",
    "sg:classifiers":[
        {
            "category":"Professional",
            "subcategory":"Management & Consulting",
            "type":"Services"
        }
    ],
    "sg:phone":"+1   ",
    "sg:postcode":"06880",
    "sg:province":"CT",
    "wof:name":"Luther & Co Inc",
    "wof:placetype":"venue"
},
  "geometry": {"coordinates":[-73.354286,41.107168],"type":"Point"}
}