{
  "type": "Feature",
  "properties": {
    "addr:full":"124 Clapboard Ridge Rd Greenwich CT 06830",
    "addr:housenumber":"124",
    "addr:postcode":"06830",
    "addr:street":"Clapboard Ridge Rd",
    "iso:country":"US",
    "sg:address":"124 Clapboard Ridge Rd",
    "sg:city":"Greenwich",
    "sg:classifiers":[
        {
            "category":"Communications",
            "subcategory":"Film & Video Production",
            "type":"Services"
        }
    ],
    "sg:phone":"+1   ",
    "sg:postcode":"06830",
    "sg:province":"CT",
    "sg:tags":[
        "motion",
        "picture"
    ],
    "wof:name":"Foreign Management LLC",
    "wof:placetype":"venue"
},
  "geometry": {"coordinates":[-73.639893,41.076269],"type":"Point"}
}