{
  "type": "Feature",
  "properties": {
    "addr:full":"11 Poplar St Stamford CT 06907",
    "addr:housenumber":"11",
    "addr:postcode":"06907",
    "addr:street":"Poplar St",
    "iso:country":"US",
    "sg:address":"11 Poplar St",
    "sg:city":"Stamford",
    "sg:classifiers":[
        {
            "category":"Building & Trades",
            "subcategory":"Construction",
            "type":"Services"
        }
    ],
    "sg:phone":"+1 203 357 1414",
    "sg:postcode":"06907",
    "sg:province":"CT",
    "sg:tags":[
        "excavating",
        "contractor"
    ],
    "wof:name":"Drenckhahn Excavating Inc",
    "wof:placetype":"venue"
},
  "geometry": {"coordinates":[-73.518862,41.07888],"type":"Point"}
}