{
  "type": "Feature",
  "properties": {
    "addr:full":"239 Golden Hill St Bridgeport CT 06604",
    "addr:housenumber":"239",
    "addr:postcode":"06604",
    "addr:street":"Golden;St",
    "iso:country":"US",
    "sg:address":"239 Golden Hill St",
    "sg:city":"Bridgeport",
    "sg:classifiers":[
        {
            "category":"Professional",
            "subcategory":"Lawyer & Legal Services",
            "type":"Services"
        }
    ],
    "sg:phone":"+1 203 334 1656",
    "sg:postcode":"06604",
    "sg:province":"CT",
    "sg:tags":[
        "attorney"
    ],
    "sg:website":"www.ctdwi.com",
    "wof:name":"James O Gaston Law Offices",
    "wof:placetype":"venue"
},
  "geometry": {"coordinates":[-73.193816,41.179326],"type":"Point"}
}