{
  "type": "Feature",
  "properties": {
    "iso:country":"US",
    "sg:address":"26 Center St",
    "sg:city":"Winsted",
    "sg:classifiers":[
        {
            "category":"Professional",
            "subcategory":"Accounting & Tax Preparation",
            "type":"Services"
        }
    ],
    "sg:phone":"+1   ",
    "sg:postcode":"06098",
    "sg:province":"CT",
    "wof:name":"Gail A Dimaggio CPA",
    "wof:placetype":"venue"
},
  "geometry": {"coordinates":[-73.069565,41.92189],"type":"Point"}
}