{
  "type": "Feature",
  "properties": {
    "addr:full":"55 Thompson St New Haven CT 06513",
    "addr:housenumber":"55",
    "addr:postcode":"06513",
    "addr:street":"Thompson St",
    "iso:country":"US",
    "sg:address":"55 Thompson St",
    "sg:city":"New Haven",
    "sg:classifiers":[
        {
            "category":"Building & Trades",
            "subcategory":"Plumbing",
            "type":"Services"
        }
    ],
    "sg:phone":"+1 203 467 9710",
    "sg:postcode":"06513",
    "sg:province":"CT",
    "sg:tags":[
        "contractor"
    ],
    "wof:name":"Unique Heating & Cooling",
    "wof:placetype":"venue"
},
  "geometry": {"coordinates":[-72.85081599999999,41.32278],"type":"Point"}
}