{
  "type": "Feature",
  "properties": {
    "iso:country":"US",
    "sg:address":"73 E Main St",
    "sg:city":"Plainville",
    "sg:classifiers":[
        {
            "category":"Health Services",
            "subcategory":"Health Practitioner",
            "type":"Services"
        }
    ],
    "sg:phone":"+1   ",
    "sg:postcode":"06062",
    "sg:province":"CT",
    "wof:name":"Heart and Hlth Massage Therapy",
    "wof:placetype":"venue"
},
  "geometry": {"coordinates":[-72.862622,41.672878],"type":"Point"}
}