{
  "type": "Feature",
  "properties": {
    "iso:country":"US",
    "sg:address":"8 Savage St",
    "sg:city":"Plantsville",
    "sg:classifiers":[
        {
            "category":"Personal",
            "type":"Services"
        }
    ],
    "sg:phone":"+1   ",
    "sg:postcode":"06479",
    "sg:province":"CT",
    "wof:name":"Complete Residential Service",
    "wof:placetype":"venue"
},
  "geometry": {"coordinates":[-72.87068499999999,41.565268],"type":"Point"}
}