{
  "type": "Feature",
  "properties": {
    "iso:country":"US",
    "sg:address":"999 Foxon Rd",
    "sg:city":"North Branford",
    "sg:classifiers":[
        {
            "category":"Personal",
            "subcategory":"Beauty Salon",
            "type":"Services"
        }
    ],
    "sg:phone":"+1 203 484 9166",
    "sg:postcode":"06471",
    "sg:province":"CT",
    "wof:name":"A Fahrenheit Hair Salon",
    "wof:placetype":"venue"
},
  "geometry": {"coordinates":[-72.789393,41.330403],"type":"Point"}
}