{
  "type": "Feature",
  "properties": {
    "iso:country":"US",
    "sg:address":"115 New Canaan Ave",
    "sg:city":"Norwalk",
    "sg:classifiers":[
        {
            "category":"Restaurant",
            "type":"Food & Drink"
        }
    ],
    "sg:phone":"+1 203 847 8681",
    "sg:postcode":"06850",
    "sg:province":"CT",
    "sg:tags":[
        "eating"
    ],
    "wof:name":"Pizza Galore",
    "wof:placetype":"venue"
},
  "geometry": {"coordinates":[-73.432636,41.12722],"type":"Point"}
}