{
  "type": "Feature",
  "properties": {
    "addr:full":"70 Smith St Stamford CT 06902",
    "addr:housenumber":"70",
    "addr:postcode":"06902",
    "addr:street":"Smith St",
    "iso:country":"US",
    "sg:address":"70 Smith St",
    "sg:city":"Stamford",
    "sg:classifiers":[
        {
            "category":"Restaurant",
            "type":"Food & Drink"
        }
    ],
    "sg:phone":"+1 203 975 8211",
    "sg:postcode":"06902",
    "sg:province":"CT",
    "wof:name":"Scotty's Fish & Chips",
    "wof:placetype":"venue"
},
  "geometry": {"coordinates":[-73.54906699999999,41.052296],"type":"Point"}
}