{
  "type": "Feature",
  "properties": {
    "addr:full":"11 W High St East Hampton CT 06424",
    "addr:housenumber":"11",
    "addr:postcode":"06424",
    "addr:street":"W High St East Hampton Ct",
    "iso:country":"US",
    "sg:address":"11 W High St",
    "sg:city":"East Hampton",
    "sg:classifiers":[
        {
            "category":"Professional",
            "subcategory":"Engineering",
            "type":"Services"
        }
    ],
    "sg:phone":"+1   ",
    "sg:postcode":"06424",
    "sg:province":"CT",
    "wof:name":"R P Dimmock Associates",
    "wof:placetype":"venue"
},
  "geometry": {"coordinates":[-72.50721,41.581584],"type":"Point"}
}