{
  "type": "Feature",
  "properties": {
    "addr:full":"12 Stephen Dr Enfield CT 06082",
    "addr:housenumber":"12",
    "addr:postcode":"06082",
    "addr:street":"Stephen Dr",
    "iso:country":"US",
    "sg:address":"12 Stephen Dr",
    "sg:city":"Enfield",
    "sg:classifiers":[
        {
            "category":"Building & Trades",
            "subcategory":"Landscaping Services",
            "type":"Services"
        }
    ],
    "sg:phone":"+1 860 745 3264",
    "sg:postcode":"06082",
    "sg:province":"CT",
    "wof:name":"Bill & Pats Diversified Svcs",
    "wof:placetype":"venue"
},
  "geometry": {"coordinates":[-72.598258,42.019562],"type":"Point"}
}