{
  "type": "Feature",
  "properties": {
    "iso:country":"US",
    "sg:address":"14 Outer Rd",
    "sg:city":"Norwalk",
    "sg:classifiers":[
        {
            "category":"Professional",
            "subcategory":"Art Services",
            "type":"Services"
        }
    ],
    "sg:phone":"+1 203 854 9512",
    "sg:postcode":"06854",
    "sg:province":"CT",
    "sg:tags":[
        "graphic",
        "designer"
    ],
    "wof:name":"Blowtorch Studios",
    "wof:placetype":"venue"
},
  "geometry": {"coordinates":[-73.41789900000001,41.07745],"type":"Point"}
}