{
  "type": "Feature",
  "properties": {
    "addr:full":"555 Lordship Blvd Stratford CT 06615",
    "addr:housenumber":"555",
    "addr:postcode":"06615",
    "addr:street":"Lordship Blvd",
    "iso:country":"US",
    "sg:address":"555 Lordship Blvd",
    "sg:city":"Stratford",
    "sg:classifiers":[
        {
            "category":"Health Services",
            "subcategory":"Doctor",
            "type":"Services"
        }
    ],
    "sg:phone":"+1 203 380 5945",
    "sg:postcode":"06615",
    "sg:province":"CT",
    "sg:tags":[
        "physician",
        "surgeon"
    ],
    "wof:name":"Concentra Medical Ctr",
    "wof:placetype":"venue"
},
  "geometry": {"coordinates":[-73.150682,41.169989],"type":"Point"}
}