{
  "type": "Feature",
  "properties": {
    "addr:full":"33 Pine St Columbia CT 06237",
    "addr:housenumber":"33",
    "addr:postcode":"06237",
    "addr:street":"Pine St",
    "iso:country":"US",
    "sg:address":"33 Pine St",
    "sg:city":"Columbia",
    "sg:classifiers":[
        {
            "category":"Building & Trades",
            "subcategory":"Construction",
            "type":"Services"
        }
    ],
    "sg:phone":"+1 860 228 9696",
    "sg:postcode":"06237",
    "sg:province":"CT",
    "sg:tags":[
        "residential",
        "commercial",
        "renovation"
    ],
    "wof:name":"Able Builders Corporation",
    "wof:placetype":"venue"
},
  "geometry": {"coordinates":[-72.30864,41.685852],"type":"Point"}
}