{
  "type": "Feature",
  "properties": {
    "addr:full":"77 Old Ridgefield Rd Wilton CT 06897",
    "addr:housenumber":"77",
    "addr:postcode":"06897",
    "addr:street":"Old Ridgefield Rd Wilton Ct",
    "iso:country":"US",
    "sg:address":"77 Old Ridgefield Rd",
    "sg:city":"Wilton",
    "sg:classifiers":[
        {
            "category":"Real Estate",
            "subcategory":"Real Estate Agent",
            "type":"Services"
        }
    ],
    "sg:phone":"+1 203 762 8666",
    "sg:postcode":"06897",
    "sg:province":"CT",
    "sg:tags":[
        "advisory",
        "s",
        "investment"
    ],
    "wof:name":"Coldwell Banker",
    "wof:placetype":"venue"
},
  "geometry": {"coordinates":[-73.43281399999999,41.194264],"type":"Point"}
}