{
  "type": "Feature",
  "properties": {
    "addr:full":"109 Bell St Middletown CT 06457",
    "addr:housenumber":"109",
    "addr:postcode":"06457",
    "addr:street":"Bell St",
    "iso:country":"US",
    "sg:address":"109 Bell St",
    "sg:city":"Middletown",
    "sg:classifiers":[
        {
            "category":"Education",
            "subcategory":"Special Training",
            "type":"Public Place"
        }
    ],
    "sg:phone":"+1   ",
    "sg:postcode":"06457",
    "sg:province":"CT",
    "wof:name":"Master Hypnotist",
    "wof:placetype":"venue"
},
  "geometry": {"coordinates":[-72.731253,41.574271],"type":"Point"}
}