{
  "type": "Feature",
  "properties": {
    "addr:full":"71 Marsh Rd Groton CT 06340",
    "addr:housenumber":"71",
    "addr:postcode":"06340",
    "addr:street":"Marsh Rd Groton Ct",
    "iso:country":"US",
    "sg:address":"71 Marsh Rd",
    "sg:city":"Groton",
    "sg:classifiers":[
        {
            "category":"Manufacturing",
            "subcategory":"Watercraft",
            "type":"Manufacturing & Wholesale Goods"
        }
    ],
    "sg:phone":"+1 860 572 7414",
    "sg:postcode":"06340",
    "sg:province":"CT",
    "wof:name":"Yacht Aid-Custom Wood Tech",
    "wof:placetype":"venue"
},
  "geometry": {"coordinates":[-71.990644,41.324769],"type":"Point"}
}