{
  "type": "Feature",
  "properties": {
    "addr:full":"26 Orchard Dr New Canaan NY 06840",
    "addr:housenumber":"26",
    "addr:postcode":"06840",
    "addr:street":"Orchard Dr",
    "iso:country":"US",
    "sg:address":"26 Orchard Dr",
    "sg:city":"New Canaan",
    "sg:classifiers":[
        {
            "category":"Building & Trades",
            "subcategory":"Construction",
            "type":"Services"
        }
    ],
    "sg:phone":"+1 203 966 7417",
    "sg:postcode":"06840",
    "sg:province":"NY",
    "sg:tags":[
        "house",
        "architectural"
    ],
    "wof:name":"Mannetti Design Association",
    "wof:placetype":"venue"
},
  "geometry": {"coordinates":[-73.489406,41.135509],"type":"Point"}
}