{
  "type": "Feature",
  "properties": {
    "iso:country":"US",
    "sg:address":"1525 E Putnam Ave",
    "sg:city":"Old Greenwich",
    "sg:classifiers":[
        {
            "category":"Professional",
            "subcategory":"Business Services",
            "type":"Services"
        }
    ],
    "sg:phone":"+1   ",
    "sg:postcode":"06870",
    "sg:province":"CT",
    "wof:name":"Techmark Group",
    "wof:placetype":"venue"
},
  "geometry": {"coordinates":[-73.567341,41.048043],"type":"Point"}
}