{
  "type": "Feature",
  "properties": {
    "iso:country":"US",
    "sg:address":"1244 N Main St",
    "sg:city":"Hartford",
    "sg:classifiers":[
        {
            "category":"Education",
            "subcategory":"School",
            "type":"Public Place"
        }
    ],
    "sg:phone":"+1   ",
    "sg:postcode":"06117",
    "sg:province":"CT",
    "wof:name":"Hebrew High School of Neng",
    "wof:placetype":"venue"
},
  "geometry": {"coordinates":[-72.750258,41.802091],"type":"Point"}
}