{
  "type": "Feature",
  "properties": {
    "addr:full":"1077 Bridgeport Ave Shelton CT 06484",
    "addr:housenumber":"1077",
    "addr:postcode":"06484",
    "addr:street":"Bridgeport Ave",
    "iso:country":"US",
    "sg:address":"1077 Bridgeport Ave",
    "sg:city":"Shelton",
    "sg:classifiers":[
        {
            "category":"Professional",
            "subcategory":"Lawyer & Legal Services",
            "type":"Services"
        }
    ],
    "sg:phone":"+1   ",
    "sg:postcode":"06484",
    "sg:province":"CT",
    "wof:name":"Lapera Patrick J",
    "wof:placetype":"venue"
},
  "geometry": {"coordinates":[-73.146089,41.257171],"type":"Point"}
}