{
  "type": "Feature",
  "properties": {
    "iso:country":"US",
    "sg:address":"164 Newington Rd",
    "sg:city":"Hartford",
    "sg:classifiers":[
        {
            "category":"Real Estate",
            "subcategory":"Real Estate Agent",
            "type":"Services"
        }
    ],
    "sg:phone":"+1 860 523 1515",
    "sg:postcode":"06110",
    "sg:province":"CT",
    "sg:tags":[
        "broker"
    ],
    "wof:name":"Golden Rule Realty",
    "wof:placetype":"venue"
},
  "geometry": {"coordinates":[-72.733397,41.726744],"type":"Point"}
}