{
  "type": "Feature",
  "properties": {
    "addr:full":"203 E Wakefield Blvd Winsted CT 06098",
    "addr:housenumber":"203",
    "addr:postcode":"06098",
    "addr:street":"E Wakefield Blvd",
    "iso:country":"US",
    "sg:address":"203 E Wakefield Blvd",
    "sg:city":"Winsted",
    "sg:classifiers":[
        {
            "category":"Building & Trades",
            "subcategory":"Construction",
            "type":"Services"
        }
    ],
    "sg:phone":"+1 860 379 7028",
    "sg:postcode":"06098",
    "sg:province":"CT",
    "sg:tags":[
        "system",
        "contractor",
        "air conditioning"
    ],
    "wof:name":"Walter A Decker",
    "wof:placetype":"venue"
},
  "geometry": {"coordinates":[-73.08474,41.916431],"type":"Point"}
}