{
  "type": "Feature",
  "properties": {
    "addr:full":"139 Allings Crossing Rd West Haven CT 06516",
    "addr:housenumber":"139",
    "addr:postcode":"06516",
    "addr:street":"Allings Crossing Rd;Haven",
    "iso:country":"US",
    "sg:address":"139 Allings Crossing Rd",
    "sg:city":"West Haven",
    "sg:classifiers":[
        {
            "category":"Wholesale",
            "subcategory":"Chemicals & Plastics",
            "type":"Manufacturing & Wholesale Goods"
        }
    ],
    "sg:phone":"+1 203 932 2489",
    "sg:postcode":"06516",
    "sg:province":"CT",
    "sg:website":"www.citychemical.com",
    "wof:name":"City Chemicals LLC",
    "wof:placetype":"venue"
},
  "geometry": {"coordinates":[-72.974316,41.265832],"type":"Point"}
}