{
  "type": "Feature",
  "properties": {
    "addr:full":"56 E Main St Ste 4 Avon CT 06001",
    "addr:housenumber":"56",
    "addr:postcode":"06001",
    "addr:street":"E Main St Ste 4 Avon Ct",
    "iso:country":"US",
    "sg:address":"56 E Main St Ste 4",
    "sg:city":"Avon",
    "sg:classifiers":[
        {
            "category":"Banks & Credit Unions",
            "subcategory":"Atm",
            "type":"Services"
        }
    ],
    "sg:phone":"+1 860 677 6277",
    "sg:postcode":"06001",
    "sg:province":"CT",
    "sg:tags":[
        "bankruptcy"
    ],
    "sg:website":"www.stmclaw.com",
    "wof:name":"Steier & McCormick Llc",
    "wof:placetype":"venue"
},
  "geometry": {"coordinates":[-72.825487,41.807935],"type":"Point"}
}