{
  "type": "Feature",
  "properties": {
    "iso:country":"US",
    "sg:address":"27 Laura Ln",
    "sg:city":"East Haven",
    "sg:classifiers":[
        {
            "category":"Utilities",
            "subcategory":"Fuel Oil & Lpg",
            "type":"Services"
        }
    ],
    "sg:phone":"+1   ",
    "sg:postcode":"06512",
    "sg:province":"CT",
    "sg:tags":[
        "repair",
        "retail",
        "conditioning",
        "air"
    ],
    "wof:name":"Blue Flame Oil Co Inc",
    "wof:placetype":"venue"
},
  "geometry": {"coordinates":[-72.888193,41.277276],"type":"Point"}
}