{
  "type": "Feature",
  "properties": {
    "addr:full":"10 Mayfair Pl Trumbull CT 06611",
    "addr:housenumber":"10",
    "addr:postcode":"06611",
    "addr:street":"Mayfair Pl",
    "iso:country":"US",
    "sg:address":"10 Mayfair Pl",
    "sg:city":"Trumbull",
    "sg:classifiers":[
        {
            "category":"Shopping",
            "subcategory":"Clothing, Apparel, & Fashions",
            "type":"Retail Goods"
        }
    ],
    "sg:phone":"+1 203 452 7883",
    "sg:postcode":"06611",
    "sg:province":"CT",
    "sg:tags":[
        "shop",
        "dress"
    ],
    "wof:name":"Teen Scene",
    "wof:placetype":"venue"
},
  "geometry": {"coordinates":[-73.24911899999999,41.280545],"type":"Point"}
}