{
  "type": "Feature",
  "properties": {
    "addr:full":"366 Federal Rd Brookfield CT 06804",
    "addr:housenumber":"366",
    "addr:postcode":"06804",
    "addr:street":"Federal Rd",
    "iso:country":"US",
    "sg:address":"366 Federal Rd",
    "sg:city":"Brookfield",
    "sg:classifiers":[
        {
            "category":"Personal",
            "subcategory":"Beauty Salon",
            "type":"Services"
        }
    ],
    "sg:phone":"+1   ",
    "sg:postcode":"06804",
    "sg:province":"CT",
    "sg:tags":[
        "shop"
    ],
    "wof:name":"Claras",
    "wof:placetype":"venue"
},
  "geometry": {"coordinates":[-73.402835,41.454174],"type":"Point"}
}