{
  "type": "Feature",
  "properties": {
    "addr:full":"133 Nash St New Haven CT 06511",
    "addr:housenumber":"133",
    "addr:postcode":"06511",
    "addr:street":"Nash St",
    "iso:country":"US",
    "sg:address":"133 Nash St",
    "sg:city":"New Haven",
    "sg:classifiers":[
        {
            "category":"Education",
            "subcategory":"School",
            "type":"Public Place"
        }
    ],
    "sg:phone":"+1 203 946 8867",
    "sg:postcode":"06511",
    "sg:province":"CT",
    "sg:tags":[
        "executive"
    ],
    "wof:name":"East Rock Magnet School",
    "wof:placetype":"venue"
},
  "geometry": {"coordinates":[-72.907402,41.31999],"type":"Point"}
}