{
  "type": "Feature",
  "properties": {
    "iso:country":"US",
    "sg:address":"1034 Main St N",
    "sg:city":"Southbury",
    "sg:classifiers":[
        {
            "category":"Health Services",
            "subcategory":"Health Practitioner",
            "type":"Services"
        }
    ],
    "sg:phone":"+1 203 264 7744",
    "sg:postcode":"06488",
    "sg:province":"CT",
    "sg:tags":[
        "psychologist"
    ],
    "sg:website":"www.drhoule.com",
    "wof:name":"Houle Psychology Clinic",
    "wof:placetype":"venue"
},
  "geometry": {"coordinates":[-73.20994899999999,41.505261],"type":"Point"}
}