{
  "type": "Feature",
  "properties": {
    "iso:country":"US",
    "sg:address":"18 Hilltop Dr",
    "sg:city":"Wolcott",
    "sg:classifiers":[
        {
            "category":"Communications",
            "subcategory":"Newspaper",
            "type":"Services"
        },
        {
            "category":"Wholesale",
            "subcategory":"Books, Periodicals, & Newspapers",
            "type":"Manufacturing & Wholesale Goods"
        }
    ],
    "sg:phone":"+1 203 879 3900",
    "sg:postcode":"06716",
    "sg:province":"CT",
    "sg:tags":[
        "dealers-wholesale",
        "news"
    ],
    "wof:name":"Wolcott Community News Ll",
    "wof:placetype":"venue"
},
  "geometry": {"coordinates":[-72.979173,41.61735],"type":"Point"}
}