{
  "type": "Feature",
  "properties": {
    "iso:country":"US",
    "sg:address":"20 Marshall St",
    "sg:city":"Old Greenwich",
    "sg:classifiers":[
        {
            "category":"Health Services",
            "subcategory":"Health Practitioner",
            "type":"Services"
        }
    ],
    "sg:phone":"+1   ",
    "sg:postcode":"06870",
    "sg:province":"CT",
    "wof:name":"Julia Winston LLC",
    "wof:placetype":"venue"
},
  "geometry": {"coordinates":[-73.56938700000001,41.053945],"type":"Point"}
}