{
  "type": "Feature",
  "properties": {
    "addr:full":"1872 E Main St Waterbury CT 06705",
    "addr:housenumber":"1872",
    "addr:postcode":"06705",
    "addr:street":"E Main St",
    "iso:country":"US",
    "sg:address":"1872 E Main St",
    "sg:city":"Waterbury",
    "sg:classifiers":[
        {
            "category":"Organizations",
            "subcategory":"Religious Organization",
            "type":"Services"
        }
    ],
    "sg:phone":"+1   ",
    "sg:postcode":"06705",
    "sg:province":"CT",
    "wof:name":"Agape Fith Vctory Temple Cmnty",
    "wof:placetype":"venue"
},
  "geometry": {"coordinates":[-73.01194099999999,41.544925],"type":"Point"}
}