{
  "type": "Feature",
  "properties": {
    "addr:full":"157 Sheephill Rd Riverside CT 06878",
    "addr:housenumber":"157",
    "addr:postcode":"06878",
    "addr:street":"Sheephill Rd Riverside Ct",
    "iso:country":"US",
    "sg:address":"157 Sheephill Rd",
    "sg:city":"Riverside",
    "sg:classifiers":[
        {
            "category":"Home & Garden",
            "subcategory":"Household Appliances",
            "type":"Retail Goods"
        }
    ],
    "sg:phone":"+1 203 978 1575",
    "sg:postcode":"06878",
    "sg:province":"CT",
    "sg:tags":[
        "refrigerator",
        "freezer"
    ],
    "wof:name":"Central Refrigeration Co",
    "wof:placetype":"venue"
},
  "geometry": {"coordinates":[-73.581294,41.057389],"type":"Point"}
}