{
  "type": "Feature",
  "properties": {
    "addr:full":"55 Clark Rd Bolton CT 06043",
    "addr:housenumber":"55",
    "addr:postcode":"06043",
    "addr:street":"Clark Rd",
    "iso:country":"US",
    "sg:address":"55 Clark Rd",
    "sg:city":"Bolton",
    "sg:classifiers":[
        {
            "category":"Shopping",
            "type":"Retail Goods"
        }
    ],
    "sg:phone":"+1 860 649 2241",
    "sg:postcode":"06043",
    "sg:province":"CT",
    "sg:tags":[
        "merchandise"
    ],
    "wof:name":"Restoration Parts Outlet",
    "wof:placetype":"venue"
},
  "geometry": {"coordinates":[-72.442476,41.765376],"type":"Point"}
}