{
  "type": "Feature",
  "properties": {
    "addr:full":"355 Hope St Stamford CT 06906",
    "addr:housenumber":"355",
    "addr:postcode":"06906",
    "addr:street":"Hope St",
    "iso:country":"US",
    "sg:address":"355 Hope St",
    "sg:city":"Stamford",
    "sg:classifiers":[
        {
            "category":"Wholesale",
            "subcategory":"Jewelry",
            "type":"Manufacturing & Wholesale Goods"
        }
    ],
    "sg:phone":"+1 203 595 0454",
    "sg:postcode":"06906",
    "sg:province":"CT",
    "sg:tags":[
        "stone",
        "metal",
        "precious",
        "mfg"
    ],
    "wof:name":"Nevelyns Fine Jewelry LLC",
    "wof:placetype":"venue"
},
  "geometry": {"coordinates":[-73.52323699999999,41.072326],"type":"Point"}
}