{
  "type": "Feature",
  "properties": {
    "iso:country":"US",
    "sg:address":"46 Tracy Ave",
    "sg:city":"Waterbury",
    "sg:classifiers":[
        {
            "category":"Recreation",
            "type":"Entertainment"
        }
    ],
    "sg:phone":"+1 203 573 8378",
    "sg:postcode":"06706",
    "sg:province":"CT",
    "sg:tags":[
        "astrologer"
    ],
    "wof:name":"Joann De Nardis & Quantum Optn",
    "wof:placetype":"venue"
},
  "geometry": {"coordinates":[-73.03144500000001,41.531924],"type":"Point"}
}