{
  "type": "Feature",
  "properties": {
    "addr:full":"376 Redstone Dr Cheshire CT 06410",
    "addr:housenumber":"376",
    "addr:postcode":"06410",
    "addr:street":"Redstone Dr",
    "iso:country":"US",
    "sg:address":"376 Redstone Dr",
    "sg:city":"Cheshire",
    "sg:classifiers":[
        {
            "category":"Professional",
            "subcategory":"Engineering",
            "type":"Services"
        }
    ],
    "sg:phone":"+1   ",
    "sg:postcode":"06410",
    "sg:province":"CT",
    "wof:name":"Lawrence A Cross Jr",
    "wof:placetype":"venue"
},
  "geometry": {"coordinates":[-72.88150899999999,41.523731],"type":"Point"}
}