{
  "type": "Feature",
  "properties": {
    "addr:full":"33 Broad St Danielson CT 06239",
    "addr:housenumber":"33",
    "addr:postcode":"06239",
    "addr:street":"Broad St",
    "iso:country":"US",
    "sg:address":"33 Broad St",
    "sg:city":"Danielson",
    "sg:classifiers":[
        {
            "category":"Professional",
            "subcategory":"Lawyer & Legal Services",
            "type":"Services"
        }
    ],
    "sg:phone":"+1 860 774 4591",
    "sg:postcode":"06239",
    "sg:province":"CT",
    "sg:tags":[
        "attorney",
        "trust",
        "family",
        "estate",
        "divorce",
        "wills",
        "planning",
        "criminal",
        "law"
    ],
    "sg:website":"http://www.normapiercearel.com",
    "wof:name":"Arel Norma Pierce",
    "wof:placetype":"venue"
},
  "geometry": {"coordinates":[-71.88018,41.798519],"type":"Point"}
}