{
  "type": "Feature",
  "properties": {
    "addr:full":"23 Paugussett Rd Sandy Hook CT 06482",
    "addr:housenumber":"23",
    "addr:postcode":"06482",
    "addr:street":"Paugussett Rd;Hook Ct",
    "iso:country":"US",
    "sg:address":"23 Paugussett Rd",
    "sg:city":"Sandy Hook",
    "sg:classifiers":[
        {
            "category":"Manufacturing",
            "subcategory":"Watercraft",
            "type":"Manufacturing & Wholesale Goods"
        }
    ],
    "sg:phone":"+1 203 426 7914",
    "sg:postcode":"06482",
    "sg:province":"CT",
    "wof:name":"D M Boatworks",
    "wof:placetype":"venue"
},
  "geometry": {"coordinates":[-73.215019,41.394852],"type":"Point"}
}