{
  "type": "Feature",
  "properties": {
    "iso:country":"US",
    "sg:address":"50 Whittlesey Dr",
    "sg:city":"Bethel",
    "sg:classifiers":[
        {
            "category":"Manufacturing",
            "subcategory":"Retail Goods",
            "type":"Manufacturing & Wholesale Goods"
        }
    ],
    "sg:phone":"+1 203 794 0346",
    "sg:postcode":"06801",
    "sg:province":"CT",
    "sg:tags":[
        "manufacturer"
    ],
    "wof:name":"Shaw Manufacturing",
    "wof:placetype":"venue"
},
  "geometry": {"coordinates":[-73.394384,41.379335],"type":"Point"}
}