{
  "type": "Feature",
  "properties": {
    "iso:country":"US",
    "sg:address":"45 Colony St",
    "sg:city":"Stratford",
    "sg:classifiers":[
        {
            "category":"Home & Garden",
            "subcategory":"Building Materials",
            "type":"Retail Goods"
        }
    ],
    "sg:phone":"+1 203 380 9664",
    "sg:postcode":"06615",
    "sg:province":"CT",
    "sg:tags":[
        "window"
    ],
    "wof:name":"Sutai Windows And Doors",
    "wof:placetype":"venue"
},
  "geometry": {"coordinates":[-73.138036,41.191445],"type":"Point"}
}