{
  "type": "Feature",
  "properties": {
    "iso:country":"US",
    "sg:address":"42 Bailey Rd",
    "sg:city":"Andover",
    "sg:classifiers":[
        {
            "category":"Professional",
            "subcategory":"Computer Services",
            "type":"Services"
        }
    ],
    "sg:phone":"+1   ",
    "sg:postcode":"06232",
    "sg:province":"CT",
    "sg:tags":[
        "programing",
        "custom"
    ],
    "wof:name":"East Point Systems LLC",
    "wof:placetype":"venue"
},
  "geometry": {"coordinates":[-72.40939,41.761675],"type":"Point"}
}