{
  "type": "Feature",
  "properties": {
    "addr:full":"1281 E Main St Stamford CT 06902",
    "addr:housenumber":"1281",
    "addr:postcode":"06902",
    "addr:street":"E Main St",
    "iso:country":"US",
    "sg:address":"1281 E Main St",
    "sg:city":"Stamford",
    "sg:classifiers":[
        {
            "category":"Professional",
            "subcategory":"Advertising",
            "type":"Services"
        }
    ],
    "sg:phone":"+1   ",
    "sg:postcode":"06902",
    "sg:province":"CT",
    "sg:tags":[
        "lithographic",
        "commercial",
        "representative"
    ],
    "wof:name":"Ad Ink LLC",
    "wof:placetype":"venue"
},
  "geometry": {"coordinates":[-73.50743799999999,41.060841],"type":"Point"}
}