{
  "type": "Feature",
  "properties": {
    "iso:country":"US",
    "sg:address":"55 Spring St",
    "sg:city":"Naugatuck",
    "sg:classifiers":[
        {
            "category":"Home & Garden",
            "subcategory":"Garden Supply",
            "type":"Retail Goods"
        }
    ],
    "sg:phone":"+1 203 729 0012",
    "sg:postcode":"06770",
    "sg:province":"CT",
    "sg:tags":[
        "lawn",
        "mower"
    ],
    "wof:name":"Santos Power Equipment",
    "wof:placetype":"venue"
},
  "geometry": {"coordinates":[-73.05260699999999,41.501769],"type":"Point"}
}