{
  "type": "Feature",
  "properties": {
    "addr:full":"146 Warsaw St Fairfield CT 06417",
    "addr:housenumber":"146",
    "addr:postcode":"06417",
    "addr:street":"Warsaw St",
    "iso:country":"US",
    "sg:address":"146 Warsaw St",
    "sg:city":"Fairfield",
    "sg:classifiers":[
        {
            "category":"Personal",
            "subcategory":"Beauty Salon",
            "type":"Services"
        }
    ],
    "sg:phone":"+1   ",
    "sg:postcode":"06417",
    "sg:province":"CT",
    "sg:tags":[
        "shop"
    ],
    "wof:name":"One Step Solutions To Success",
    "wof:placetype":"venue"
},
  "geometry": {"coordinates":[-72.44937400000001,41.364371],"type":"Point"}
}