{
  "type": "Feature",
  "properties": {
    "iso:country":"US",
    "sg:address":"374 Slater St",
    "sg:city":"South Windsor",
    "sg:classifiers":[
        {
            "category":"Farming",
            "subcategory":"Farm",
            "type":"Manufacturing & Wholesale Goods"
        }
    ],
    "sg:phone":"+1 860 644 1860",
    "sg:postcode":"06074",
    "sg:province":"CT",
    "sg:tags":[
        "crop",
        "general"
    ],
    "wof:name":"Robert A Wodal",
    "wof:placetype":"venue"
},
  "geometry": {"coordinates":[-72.535512,41.81304],"type":"Point"}
}