{
  "type": "Feature",
  "properties": {
    "addr:full":"1031 Post Rd Darien CT 06820",
    "addr:housenumber":"1031",
    "addr:postcode":"06820",
    "addr:street":"Post Rd",
    "iso:country":"US",
    "sg:address":"1031 Post Rd",
    "sg:city":"Darien",
    "sg:classifiers":[
        {
            "category":"Insurance",
            "subcategory":"Insurance Agent",
            "type":"Services"
        }
    ],
    "sg:phone":"+1 203 966 9859",
    "sg:postcode":"06820",
    "sg:province":"CT",
    "wof:name":"Massachusetts Mutual-Blue Chip",
    "wof:placetype":"venue"
},
  "geometry": {"coordinates":[-73.471912,41.075665],"type":"Point"}
}