{
  "type": "Feature",
  "properties": {
    "iso:country":"US",
    "sg:address":"219 Henry St",
    "sg:city":"Stamford",
    "sg:classifiers":[
        {
            "category":"Professional",
            "subcategory":"Art Services",
            "type":"Services"
        }
    ],
    "sg:phone":"+1   ",
    "sg:postcode":"06902",
    "sg:province":"CT",
    "sg:tags":[
        "commercial",
        "photography",
        "design"
    ],
    "wof:name":"Shooters",
    "wof:placetype":"venue"
},
  "geometry": {"coordinates":[-73.537082,41.043887],"type":"Point"}
}