{
  "type": "Feature",
  "properties": {
    "iso:country":"US",
    "sg:address":"45 Laurel Ln",
    "sg:city":"Windham",
    "sg:classifiers":[
        {
            "category":"Organizations",
            "subcategory":"Labor Organization",
            "type":"Services"
        }
    ],
    "sg:phone":"+1   ",
    "sg:postcode":"06280",
    "sg:province":"CT",
    "wof:name":"United Paperworks Inter",
    "wof:placetype":"venue"
},
  "geometry": {"coordinates":[-72.178276,41.711318],"type":"Point"}
}