{
  "type": "Feature",
  "properties": {
    "addr:full":"17 Basking Ridge Rd Shelton CT 06484",
    "addr:housenumber":"17",
    "addr:postcode":"06484",
    "addr:street":"Basking Ridge Rd",
    "iso:country":"US",
    "sg:address":"17 Basking Ridge Rd",
    "sg:city":"Shelton",
    "sg:classifiers":[
        {
            "category":"Professional",
            "subcategory":"Business Services",
            "type":"Services"
        }
    ],
    "sg:phone":"+1   ",
    "sg:postcode":"06484",
    "sg:province":"CT",
    "wof:name":"Wsw Enterprises LLC",
    "wof:placetype":"venue"
},
  "geometry": {"coordinates":[-73.117317,41.308792],"type":"Point"}
}