{
  "type": "Feature",
  "properties": {
    "addr:full":"870 E Main St Stamford CT 06902",
    "addr:housenumber":"870",
    "addr:postcode":"06902",
    "addr:street":"E Main St",
    "iso:country":"US",
    "sg:address":"870 E Main St",
    "sg:city":"Stamford",
    "sg:classifiers":[
        {
            "category":"Building & Trades",
            "subcategory":"Equipment Rental",
            "type":"Services"
        }
    ],
    "sg:phone":"+1 203 978 0053",
    "sg:postcode":"06902",
    "sg:province":"CT",
    "sg:tags":[
        "yard"
    ],
    "wof:name":"Rent-A-Center",
    "wof:placetype":"venue"
},
  "geometry": {"coordinates":[-73.525426,41.055669],"type":"Point"}
}