{
  "type": "Feature",
  "properties": {
    "addr:full":"349 Main Salisbury CT 06068",
    "addr:housenumber":"349",
    "addr:postcode":"06068",
    "addr:street":"Main Salisbury Ct",
    "iso:country":"US",
    "sg:address":"349 Main",
    "sg:city":"Salisbury",
    "sg:classifiers":[
        {
            "category":"Restaurant",
            "type":"Food & Drink"
        }
    ],
    "sg:phone":"+1 860 435 2111",
    "sg:postcode":"06068",
    "sg:province":"CT",
    "wof:name":"Boathouse At Lakeville the",
    "wof:placetype":"venue"
},
  "geometry": {"coordinates":[-73.424599,42.005299],"type":"Point"}
}