{
  "type": "Feature",
  "properties": {
    "iso:country":"US",
    "sg:address":"156 Knickerbocker Ave",
    "sg:city":"Stamford",
    "sg:classifiers":[
        {
            "category":"Professional",
            "type":"Services"
        }
    ],
    "sg:phone":"+1 203 357 0360",
    "sg:postcode":"06907",
    "sg:province":"CT",
    "wof:name":"Advanced Professional Care",
    "wof:placetype":"venue"
},
  "geometry": {"coordinates":[-73.51926,41.090551],"type":"Point"}
}