{
  "type": "Feature",
  "properties": {
    "iso:country":"US",
    "sg:address":"15 Lockwood Dr",
    "sg:city":"Watertown",
    "sg:classifiers":[
        {
            "category":"Building & Trades",
            "subcategory":"Landscaping Services",
            "type":"Services"
        }
    ],
    "sg:phone":"+1 860 274 1070",
    "sg:postcode":"06795",
    "sg:province":"CT",
    "sg:tags":[
        "landscape"
    ],
    "wof:name":"Ameriscape Landscaping",
    "wof:placetype":"venue"
},
  "geometry": {"coordinates":[-73.11773100000001,41.593338],"type":"Point"}
}