{
  "type": "Feature",
  "properties": {
    "addr:full":"50 Kelly Rd South Windsor CT 06074",
    "addr:housenumber":"50",
    "addr:postcode":"06074",
    "addr:street":"Kelly Rd",
    "iso:country":"US",
    "sg:address":"50 Kelly Rd",
    "sg:city":"South Windsor",
    "sg:classifiers":[
        {
            "category":"Professional",
            "type":"Services"
        }
    ],
    "sg:phone":"+1 860 644 1459",
    "sg:postcode":"06074",
    "sg:province":"CT",
    "wof:name":"Joseph Pitts",
    "wof:placetype":"venue"
},
  "geometry": {"coordinates":[-72.515111,41.827206],"type":"Point"}
}