{
  "type": "Feature",
  "properties": {
    "addr:full":"95 Storrs Rd Ste 17 Willimantic CT 06226",
    "addr:housenumber":"95",
    "addr:postcode":"06226",
    "addr:street":"Storrs Rd Ste 17",
    "iso:country":"US",
    "sg:address":"95 Storrs Rd Ste 17",
    "sg:city":"Willimantic",
    "sg:classifiers":[
        {
            "category":"Insurance",
            "subcategory":"Health Insurance",
            "type":"Services"
        }
    ],
    "sg:phone":"+1 860 450 0404",
    "sg:postcode":"06226",
    "sg:province":"CT",
    "sg:tags":[
        "market"
    ],
    "wof:name":"General Nutrition Centers Inc",
    "wof:placetype":"venue"
},
  "geometry": {"coordinates":[-72.199681,41.734622],"type":"Point"}
}