{
  "type": "Feature",
  "properties": {
    "addr:full":"417 Washington Ave North Haven CT 06473",
    "addr:housenumber":"417",
    "addr:postcode":"06473",
    "addr:street":"Washington Ave;Haven",
    "iso:country":"US",
    "sg:address":"417 Washington Ave",
    "sg:city":"North Haven",
    "sg:classifiers":[
        {
            "category":"Building & Trades",
            "subcategory":"Construction",
            "type":"Services"
        }
    ],
    "sg:phone":"+1 203 234 2268",
    "sg:postcode":"06473",
    "sg:province":"CT",
    "sg:tags":[
        "tile",
        "dealer"
    ],
    "wof:name":"Elegance Tile Marble & Granite",
    "wof:placetype":"venue"
},
  "geometry": {"coordinates":[-72.84369,41.409277],"type":"Point"}
}