{
  "type": "Feature",
  "properties": {
    "addr:full":"89 Main St Broad Brook CT 06016",
    "addr:housenumber":"89",
    "addr:postcode":"06016",
    "addr:street":"Main St Broad Brook Ct",
    "iso:country":"US",
    "sg:address":"89 Main St",
    "sg:city":"Broad Brook",
    "sg:classifiers":[
        {
            "category":"Professional",
            "subcategory":"Management & Consulting",
            "type":"Services"
        }
    ],
    "sg:phone":"+1   ",
    "sg:postcode":"06016",
    "sg:province":"CT",
    "sg:tags":[
        "business"
    ],
    "wof:name":"Systems Consulting",
    "wof:placetype":"venue"
},
  "geometry": {"coordinates":[-72.545956,41.918408],"type":"Point"}
}