{
  "type": "Feature",
  "properties": {
    "addr:full":"3200 Madison Ave Bridgeport CT 06606",
    "addr:housenumber":"3200",
    "addr:postcode":"06606",
    "addr:street":"Madison Ave",
    "iso:country":"US",
    "sg:address":"3200 Madison Ave",
    "sg:city":"Bridgeport",
    "sg:classifiers":[
        {
            "category":"Building & Trades",
            "subcategory":"Construction",
            "type":"Services"
        }
    ],
    "sg:phone":"+1 203 846 8077",
    "sg:postcode":"06606",
    "sg:province":"CT",
    "sg:tags":[
        "painter"
    ],
    "wof:name":"C Marshall Painting",
    "wof:placetype":"venue"
},
  "geometry": {"coordinates":[-73.226921,41.217779],"type":"Point"}
}