{
  "type": "Feature",
  "properties": {
    "addr:full":"31 Sycamore St Glastonbury CT 06033",
    "addr:housenumber":"31",
    "addr:postcode":"06033",
    "addr:street":"Sycamore St",
    "iso:country":"US",
    "sg:address":"31 Sycamore St",
    "sg:city":"Glastonbury",
    "sg:classifiers":[
        {
            "category":"Health Services",
            "subcategory":"Clinic",
            "type":"Services"
        }
    ],
    "sg:phone":"+1   ",
    "sg:postcode":"06033",
    "sg:province":"CT",
    "wof:name":"Woodland Womens Health Assoc",
    "wof:placetype":"venue"
},
  "geometry": {"coordinates":[-72.601198,41.709469],"type":"Point"}
}