{
  "type": "Feature",
  "properties": {
    "iso:country":"US",
    "sg:address":"28 Pierce Rd",
    "sg:city":"Riverside",
    "sg:classifiers":[
        {
            "category":"Professional",
            "type":"Services"
        }
    ],
    "sg:phone":"+1 203 637 1244",
    "sg:postcode":"06878",
    "sg:province":"CT",
    "sg:tags":[
        "establishment"
    ],
    "wof:name":"Mary Kay Cosmetics Independent",
    "wof:placetype":"venue"
},
  "geometry": {"coordinates":[-73.58856,41.03522],"type":"Point"}
}