{
  "type": "Feature",
  "properties": {
    "addr:full":"264 Barn Hill Rd Monroe CT 06468",
    "addr:housenumber":"264",
    "addr:postcode":"06468",
    "addr:street":"Barn Hill Rd",
    "iso:country":"US",
    "sg:address":"264 Barn Hill Rd",
    "sg:city":"Monroe",
    "sg:classifiers":[
        {
            "category":"Building & Trades",
            "subcategory":"Construction",
            "type":"Services"
        }
    ],
    "sg:phone":"+1 203 261 4478",
    "sg:postcode":"06468",
    "sg:province":"CT",
    "sg:tags":[
        "general",
        "contractor"
    ],
    "wof:name":"Action Construction Management",
    "wof:placetype":"venue"
},
  "geometry": {"coordinates":[-73.184984,41.345474],"type":"Point"}
}