{
  "type": "Feature",
  "properties": {
    "addr:full":"8 Wickett St., #Y Pine Meadow CT 06061",
    "addr:housenumber":"8",
    "addr:postcode":"06061",
    "addr:street":"Wickett St. # Y Pine Meadow Ct",
    "iso:country":"US",
    "sg:address":"8 Wickett St., #Y",
    "sg:city":"Pine Meadow",
    "sg:classifiers":[
        {
            "category":"Bakery",
            "type":"Food & Drink"
        }
    ],
    "sg:phone":"+1 860 238 7691",
    "sg:postcode":"06061",
    "sg:province":"CT",
    "sg:website":"www.collinsvillebaking.com",
    "wof:name":"Collinsville Baking Company",
    "wof:placetype":"venue"
},
  "geometry": {"coordinates":[-72.965692,41.875092],"type":"Point"}
}