{
  "type": "Feature",
  "properties": {
    "addr:full":"15 Wood Creek Rd New Fairfield CT 06812",
    "addr:housenumber":"15",
    "addr:postcode":"06812",
    "addr:street":"Wood Creek Rd;Fairfield Ct",
    "iso:country":"US",
    "sg:address":"15 Wood Creek Rd",
    "sg:city":"New Fairfield",
    "sg:classifiers":[
        {
            "category":"Professional",
            "subcategory":"Engineering",
            "type":"Services"
        }
    ],
    "sg:phone":"+1   ",
    "sg:postcode":"06812",
    "sg:province":"CT",
    "wof:name":"Society of Women Engineers",
    "wof:placetype":"venue"
},
  "geometry": {"coordinates":[-73.465479,41.465439],"type":"Point"}
}