{
  "type": "Feature",
  "properties": {
    "addr:full":"316 Elm St New Haven CT 06511",
    "addr:housenumber":"316",
    "addr:postcode":"06511",
    "addr:street":"Elm St",
    "iso:country":"US",
    "sg:address":"316 Elm St",
    "sg:city":"New Haven",
    "sg:classifiers":[
        {
            "category":"Restaurant",
            "type":"Food & Drink"
        }
    ],
    "sg:menulink":"http://www.allmenus.com/ct/new-haven/257121-ivy-noodle/menu/",
    "sg:phone":"+1 203 562 9933",
    "sg:postcode":"06511",
    "sg:province":"CT",
    "sg:tags":[
        "noodle",
        "bar",
        "asian",
        "chinese"
    ],
    "wof:name":"Ivy Noodle",
    "wof:placetype":"venue"
},
  "geometry": {"coordinates":[-72.931437,41.311092],"type":"Point"}
}