{
  "type": "Feature",
  "properties": {
    "iso:country":"US",
    "sg:address":"12 Mott Ave",
    "sg:city":"Norwalk",
    "sg:classifiers":[
        {
            "category":"Retail",
            "subcategory":"Repair Shop",
            "type":"Services"
        }
    ],
    "sg:phone":"+1 203 846 9500",
    "sg:postcode":"06850",
    "sg:province":"CT",
    "sg:tags":[
        "repairing",
        "piano",
        "refinishing"
    ],
    "wof:name":"Isaac Halsey Piano Tuning Svc",
    "wof:placetype":"venue"
},
  "geometry": {"coordinates":[-73.4161,41.116491],"type":"Point"}
}