{
  "type": "Feature",
  "properties": {
    "iso:country":"US",
    "sg:address":"52 Ridgecrest Dr",
    "sg:city":"Ridgefield",
    "sg:classifiers":[
        {
            "category":"Building & Trades",
            "subcategory":"Plumbing",
            "type":"Services"
        }
    ],
    "sg:phone":"+1 203 431 3257",
    "sg:postcode":"06877",
    "sg:province":"CT",
    "sg:tags":[
        "contractor"
    ],
    "wof:name":"Hillside Plumbing",
    "wof:placetype":"venue"
},
  "geometry": {"coordinates":[-73.499833,41.301031],"type":"Point"}
}