{
  "type": "Feature",
  "properties": {
    "addr:full":"231 N Main St Winsted CT 06098",
    "addr:housenumber":"231",
    "addr:postcode":"06098",
    "addr:street":"N Main St",
    "iso:country":"US",
    "sg:address":"231 N Main St",
    "sg:city":"Winsted",
    "sg:classifiers":[
        {
            "category":"Health Services",
            "subcategory":"Clinic",
            "type":"Services"
        }
    ],
    "sg:phone":"+1 860 738 1616",
    "sg:postcode":"06098",
    "sg:province":"CT",
    "sg:tags":[
        "information",
        "alcoholism",
        "treatment"
    ],
    "wof:name":"Mccall Foundation, Inc.",
    "wof:placetype":"venue"
},
  "geometry": {"coordinates":[-73.059265,41.928434],"type":"Point"}
}