{
  "type": "Feature",
  "properties": {
    "addr:full":"70 Essex St New Haven CT 06513",
    "addr:housenumber":"70",
    "addr:postcode":"06513",
    "addr:street":"Essex St",
    "iso:country":"US",
    "sg:address":"70 Essex St",
    "sg:city":"New Haven",
    "sg:classifiers":[
        {
            "category":"Retail",
            "subcategory":"Repair Shop",
            "type":"Services"
        }
    ],
    "sg:phone":"+1   ",
    "sg:postcode":"06513",
    "sg:province":"CT",
    "sg:tags":[
        "television",
        "radio"
    ],
    "wof:name":"Gabes Electronics",
    "wof:placetype":"venue"
},
  "geometry": {"coordinates":[-72.874222,41.318326],"type":"Point"}
}