{
  "type": "Feature",
  "properties": {
    "iso:country":"US",
    "sg:address":"100 Woodmont Rd",
    "sg:city":"Milford",
    "sg:classifiers":[
        {
            "category":"Home & Garden",
            "subcategory":"Furniture",
            "type":"Retail Goods"
        }
    ],
    "sg:phone":"+1 203 874 2205",
    "sg:postcode":"06460",
    "sg:province":"CT",
    "sg:tags":[
        "equipment",
        "kitchen",
        "cabinet"
    ],
    "wof:name":"Mauro & Co",
    "wof:placetype":"venue"
},
  "geometry": {"coordinates":[-73.02368800000001,41.239452],"type":"Point"}
}