{
  "type": "Feature",
  "properties": {
    "iso:country":"US",
    "sg:address":"13 Judd Sq",
    "sg:city":"Wallingford",
    "sg:classifiers":[
        {
            "category":"Education",
            "subcategory":"Special Training",
            "type":"Public Place"
        }
    ],
    "sg:phone":"+1 203 269 0991",
    "sg:postcode":"06492",
    "sg:province":"CT",
    "sg:tags":[
        "instruction",
        "driving"
    ],
    "wof:name":"Modern Lern Rite Driving Schl",
    "wof:placetype":"venue"
},
  "geometry": {"coordinates":[-72.82830199999999,41.455666],"type":"Point"}
}