{
  "type": "Feature",
  "properties": {
    "addr:full":"10 Fresenius Rd Westport CT 06880",
    "addr:housenumber":"10",
    "addr:postcode":"06880",
    "addr:street":"Fresenius Rd",
    "iso:country":"US",
    "sg:address":"10 Fresenius Rd",
    "sg:city":"Westport",
    "sg:classifiers":[
        {
            "category":"Professional",
            "subcategory":"Computer Services",
            "type":"Services"
        }
    ],
    "sg:phone":"+1   ",
    "sg:postcode":"06880",
    "sg:province":"CT",
    "sg:tags":[
        "related"
    ],
    "wof:name":"Inside Edge Systems Inc",
    "wof:placetype":"venue"
},
  "geometry": {"coordinates":[-73.335938,41.140744],"type":"Point"}
}