{
  "type": "Feature",
  "properties": {
    "addr:full":"2 Willowbrook Rd Cromwell CT 06416",
    "addr:housenumber":"2",
    "addr:postcode":"06416",
    "addr:street":"Willowbrook Rd Cromwell Ct",
    "iso:country":"US",
    "sg:address":"2 Willowbrook Rd",
    "sg:city":"Cromwell",
    "sg:classifiers":[
        {
            "category":"Travel",
            "subcategory":"Travel Agent",
            "type":"Entertainment"
        }
    ],
    "sg:phone":"+1 860 632 0028",
    "sg:postcode":"06416",
    "sg:province":"CT",
    "sg:tags":[
        "agency"
    ],
    "wof:name":"Grand Travel One",
    "wof:placetype":"venue"
},
  "geometry": {"coordinates":[-72.6859,41.60367],"type":"Point"}
}