{
  "type": "Feature",
  "properties": {
    "iso:country":"US",
    "sg:address":"37 Pine Hill Rd",
    "sg:city":"Southbury",
    "sg:classifiers":[
        {
            "category":"Professional",
            "subcategory":"Computer Services",
            "type":"Services"
        }
    ],
    "sg:phone":"+1   ",
    "sg:postcode":"06488",
    "sg:province":"CT",
    "sg:tags":[
        "prepackaged",
        "software"
    ],
    "wof:name":"Corbett Software",
    "wof:placetype":"venue"
},
  "geometry": {"coordinates":[-73.217823,41.485184],"type":"Point"}
}