{
  "type": "Feature",
  "properties": {
    "addr:full":"643 Norwich Rd Plainfield CT 06374",
    "addr:housenumber":"643",
    "addr:postcode":"06374",
    "addr:street":"Norwich Rd",
    "iso:country":"US",
    "sg:address":"643 Norwich Rd",
    "sg:city":"Plainfield",
    "sg:classifiers":[
        {
            "category":"Professional",
            "subcategory":"Lawyer & Legal Services",
            "type":"Services"
        }
    ],
    "sg:phone":"+1 860 564 3351",
    "sg:postcode":"06374",
    "sg:province":"CT",
    "wof:name":"Brennan James F III Atty",
    "wof:placetype":"venue"
},
  "geometry": {"coordinates":[-71.925102,41.660198],"type":"Point"}
}