{
  "type": "Feature",
  "properties": {
    "addr:full":"62 Botsford Hill Rd Roxbury CT 06783",
    "addr:housenumber":"62",
    "addr:postcode":"06783",
    "addr:street":"Botsford Hill Rd",
    "iso:country":"US",
    "sg:address":"62 Botsford Hill Rd",
    "sg:city":"Roxbury",
    "sg:classifiers":[
        {
            "category":"Real Estate",
            "subcategory":"Real Estate Operator",
            "type":"Services"
        }
    ],
    "sg:phone":"+1 860 354 0157",
    "sg:postcode":"06783",
    "sg:province":"CT",
    "sg:tags":[
        "property",
        "lessor"
    ],
    "wof:name":"Aging Children LLC",
    "wof:placetype":"venue"
},
  "geometry": {"coordinates":[-73.33573199999999,41.539297],"type":"Point"}
}