{
  "type": "Feature",
  "properties": {
    "addr:full":"65 High Ridge Rd Stamford CT 06905",
    "addr:housenumber":"65",
    "addr:postcode":"06905",
    "addr:street":"High Ridge Rd",
    "iso:country":"US",
    "sg:address":"65 High Ridge Rd",
    "sg:city":"Stamford",
    "sg:classifiers":[
        {
            "category":"Professional",
            "subcategory":"Art Services",
            "type":"Services"
        }
    ],
    "sg:phone":"+1   ",
    "sg:postcode":"06905",
    "sg:province":"CT",
    "sg:tags":[
        "production"
    ],
    "wof:name":"Sun-Scape Enterprises Ltd",
    "wof:placetype":"venue"
},
  "geometry": {"coordinates":[-73.54884199999999,41.073382],"type":"Point"}
}