{
  "type": "Feature",
  "properties": {
    "iso:country":"US",
    "sg:address":"1 Coventry Rd",
    "sg:city":"Stamford",
    "sg:classifiers":[
        {
            "category":"Professional",
            "subcategory":"Computer Services",
            "type":"Services"
        }
    ],
    "sg:phone":"+1   ",
    "sg:postcode":"06903",
    "sg:province":"CT",
    "sg:tags":[
        "design",
        "system"
    ],
    "wof:name":"Creative Group",
    "wof:placetype":"venue"
},
  "geometry": {"coordinates":[-73.575368,41.169378],"type":"Point"}
}