{
  "type": "Feature",
  "properties": {
    "addr:full":"31 Hoyt St Danbury CT 06810",
    "addr:housenumber":"31",
    "addr:postcode":"06810",
    "addr:street":"Hoyt St",
    "iso:country":"US",
    "sg:address":"31 Hoyt St",
    "sg:city":"Danbury",
    "sg:classifiers":[
        {
            "category":"Building & Trades",
            "subcategory":"Landscaping Services",
            "type":"Services"
        }
    ],
    "sg:phone":"+1 203 778 9040",
    "sg:postcode":"06810",
    "sg:province":"CT",
    "sg:tags":[
        "landscape",
        "contractor"
    ],
    "wof:name":"Gomez Landscape Contractor 3",
    "wof:placetype":"venue"
},
  "geometry": {"coordinates":[-73.466652,41.399152],"type":"Point"}
}