{
  "type": "Feature",
  "properties": {
    "addr:full":"14 Douglas Ln New Fairfield CT 06812",
    "addr:housenumber":"14",
    "addr:postcode":"06812",
    "addr:street":"Douglas Ln New Fairfield Ct",
    "iso:country":"US",
    "sg:address":"14 Douglas Ln",
    "sg:city":"New Fairfield",
    "sg:classifiers":[
        {
            "category":"Professional",
            "type":"Services"
        }
    ],
    "sg:phone":"+1 203 746 7802",
    "sg:postcode":"06812",
    "sg:province":"CT",
    "sg:tags":[
        "establishment"
    ],
    "wof:name":"Netops Corp",
    "wof:placetype":"venue"
},
  "geometry": {"coordinates":[-73.515,41.473754],"type":"Point"}
}