{
  "type": "Feature",
  "properties": {
    "addr:full":"701 Cottage Grove Rd Bloomfield CT 06002",
    "addr:housenumber":"701",
    "addr:postcode":"06002",
    "addr:street":"Cottage Grove Rd Bloomfield Ct",
    "iso:country":"US",
    "sg:address":"701 Cottage Grove Rd",
    "sg:city":"Bloomfield",
    "sg:classifiers":[
        {
            "category":"Shopping",
            "type":"Retail Goods"
        }
    ],
    "sg:phone":"+1 860 242 4645",
    "sg:postcode":"06002",
    "sg:province":"CT",
    "sg:tags":[
        "merchandise"
    ],
    "wof:name":"Carousel Industries Inc",
    "wof:placetype":"venue"
},
  "geometry": {"coordinates":[-72.735342,41.8169],"type":"Point"}
}