{
  "type": "Feature",
  "properties": {
    "addr:full":"110 Town Woods Rd Old Lyme CT 06371",
    "addr:housenumber":"110",
    "addr:postcode":"06371",
    "addr:street":"Town Woods Rd",
    "iso:country":"US",
    "sg:address":"110 Town Woods Rd",
    "sg:city":"Old Lyme",
    "sg:classifiers":[
        {
            "category":"Real Estate",
            "subcategory":"Architect",
            "type":"Services"
        }
    ],
    "sg:phone":"+1   ",
    "sg:postcode":"06371",
    "sg:province":"CT",
    "sg:tags":[
        "architectural"
    ],
    "wof:name":"Sun Assoc",
    "wof:placetype":"venue"
},
  "geometry": {"coordinates":[-72.32343299999999,41.358972],"type":"Point"}
}