{
  "type": "Feature",
  "properties": {
    "iso:country":"US",
    "sg:address":"487 Fan Hill Rd",
    "sg:city":"Monroe",
    "sg:classifiers":[
        {
            "category":"Social Services",
            "subcategory":"Adult Care",
            "type":"Services"
        }
    ],
    "sg:phone":"+1 203 459 4325",
    "sg:postcode":"06468",
    "sg:province":"CT",
    "sg:tags":[
        "home",
        "group"
    ],
    "wof:name":"Hasco Group Home",
    "wof:placetype":"venue"
},
  "geometry": {"coordinates":[-73.233441,41.352611],"type":"Point"}
}