{
  "type": "Feature",
  "properties": {
    "addr:full":"53 Kenyon Rd Lakeside CT 06763",
    "addr:housenumber":"53",
    "addr:postcode":"06763",
    "addr:street":"Kenyon Rd Lakeside Ct",
    "iso:country":"US",
    "sg:address":"53 Kenyon Rd",
    "sg:city":"Lakeside",
    "sg:classifiers":[
        {
            "category":"Manufacturing",
            "subcategory":"Metals",
            "type":"Manufacturing & Wholesale Goods"
        }
    ],
    "sg:phone":"+1   ",
    "sg:postcode":"06763",
    "sg:province":"CT",
    "sg:tags":[
        "repair",
        "product",
        "welding",
        "fabricated",
        "mfg"
    ],
    "wof:name":"Wordens Welding",
    "wof:placetype":"venue"
},
  "geometry": {"coordinates":[-73.23553,41.670045],"type":"Point"}
}