{
  "type": "Feature",
  "properties": {
    "iso:country":"US",
    "sg:address":"449 Mapleton Ave",
    "sg:city":"Suffield",
    "sg:classifiers":[
        {
            "category":"Social Services",
            "subcategory":"Child Care",
            "type":"Services"
        }
    ],
    "sg:phone":"+1   ",
    "sg:postcode":"06078",
    "sg:province":"CT",
    "sg:tags":[
        "day"
    ],
    "wof:name":"Conways Kiddie Kollege",
    "wof:placetype":"venue"
},
  "geometry": {"coordinates":[-72.63646799999999,41.997928],"type":"Point"}
}