{
  "type": "Feature",
  "properties": {
    "iso:country":"US",
    "sg:address":"12 Legendary Cir",
    "sg:city":"Port Chester",
    "sg:classifiers":[
        {
            "category":"Professional",
            "subcategory":"Management & Consulting",
            "type":"Services"
        }
    ],
    "sg:phone":"+1 917 319 1664",
    "sg:postcode":"10573",
    "sg:province":"NY",
    "wof:name":"Dimension Initiative Group",
    "wof:placetype":"venue"
},
  "geometry": {"coordinates":[-73.694016,41.056123],"type":"Point"}
}