{
  "type": "Feature",
  "properties": {
    "addr:full":"923 Main St Manchester CT 06040",
    "addr:housenumber":"923",
    "addr:postcode":"06040",
    "addr:street":"Main St",
    "iso:country":"US",
    "sg:address":"923 Main St",
    "sg:city":"Manchester",
    "sg:classifiers":[
        {
            "category":"Banks & Credit Unions",
            "subcategory":"Investment Brokerage",
            "type":"Services"
        }
    ],
    "sg:phone":"+1 860 533 5040",
    "sg:postcode":"06040",
    "sg:province":"CT",
    "sg:tags":[
        "security"
    ],
    "wof:name":"Connecticut Assn Securities",
    "wof:placetype":"venue"
},
  "geometry": {"coordinates":[-72.520672,41.769392],"type":"Point"}
}