{
  "type": "Feature",
  "properties": {
    "addr:full":"1290 Madison Ave Bridgeport CT 06606",
    "addr:housenumber":"1290",
    "addr:postcode":"06606",
    "addr:street":"Madison Ave",
    "iso:country":"US",
    "sg:address":"1290 Madison Ave",
    "sg:city":"Bridgeport",
    "sg:classifiers":[
        {
            "category":"Home & Garden",
            "subcategory":"Building Materials",
            "type":"Retail Goods"
        }
    ],
    "sg:phone":"+1 203 335 8135",
    "sg:postcode":"06606",
    "sg:province":"CT",
    "wof:name":"Chagas Painting",
    "wof:placetype":"venue"
},
  "geometry": {"coordinates":[-73.209524,41.198273],"type":"Point"}
}