{
  "type": "Feature",
  "properties": {
    "iso:country":"US",
    "sg:address":"39 Selleck St",
    "sg:city":"Stamford",
    "sg:classifiers":[
        {
            "category":"Retail",
            "subcategory":"Auto Repair",
            "type":"Services"
        }
    ],
    "sg:phone":"+1 203 977 7071",
    "sg:postcode":"06902",
    "sg:province":"CT",
    "sg:tags":[
        "repairing",
        "automobile"
    ],
    "wof:name":"CPR Automotive",
    "wof:placetype":"venue"
},
  "geometry": {"coordinates":[-73.5489,41.040442],"type":"Point"}
}