{
  "type": "Feature",
  "properties": {
    "iso:country":"US",
    "sg:address":"41 Warehouse Point Rd",
    "sg:city":"Wallingford",
    "sg:classifiers":[
        {
            "category":"Wholesale",
            "subcategory":"Medical Equipment & Supplies",
            "type":"Manufacturing & Wholesale Goods"
        }
    ],
    "sg:phone":"+1 203 949 9133",
    "sg:postcode":"06492",
    "sg:province":"CT",
    "sg:tags":[
        "hospital"
    ],
    "wof:name":"Sani-Med",
    "wof:placetype":"venue"
},
  "geometry": {"coordinates":[-72.813681,41.489081],"type":"Point"}
}