{
  "type": "Feature",
  "properties": {
    "iso:country":"US",
    "sg:address":"39 W Brother Dr",
    "sg:city":"Greenwich",
    "sg:classifiers":[
        {
            "category":"Airline",
            "type":"Transportation"
        }
    ],
    "sg:phone":"+1 203 422 2963",
    "sg:postcode":"06830",
    "sg:province":"CT",
    "sg:tags":[
        "pilot"
    ],
    "wof:name":"Aero Innovations Inc",
    "wof:placetype":"venue"
},
  "geometry": {"coordinates":[-73.613175,41.033556],"type":"Point"}
}