{
  "type": "Feature",
  "properties": {
    "iso:country":"US",
    "sg:address":"27 Topledge Rd",
    "sg:city":"Redding",
    "sg:classifiers":[
        {
            "category":"Professional",
            "subcategory":"Business Services",
            "type":"Services"
        }
    ],
    "sg:phone":"+1   ",
    "sg:postcode":"06896",
    "sg:province":"CT",
    "wof:name":"Wilfarm National Stock Sites",
    "wof:placetype":"venue"
},
  "geometry": {"coordinates":[-73.447118,41.295653],"type":"Point"}
}