{
  "type": "Feature",
  "properties": {
    "iso:country":"US",
    "sg:address":"195 French St",
    "sg:city":"Watertown",
    "sg:classifiers":[
        {
            "category":"Government",
            "subcategory":"Police Station",
            "type":"Public Place"
        }
    ],
    "sg:phone":"+1 860 945 5200",
    "sg:postcode":"06795",
    "sg:province":"CT",
    "sg:tags":[
        "protection"
    ],
    "wof:name":"Watertown Police Dept",
    "wof:placetype":"venue"
},
  "geometry": {"coordinates":[-73.10959800000001,41.598407],"type":"Point"}
}