{
  "type": "Feature",
  "properties": {
    "iso:country":"US",
    "sg:address":"258 Sisson Ave",
    "sg:city":"Hartford",
    "sg:classifiers":[
        {
            "category":"Communications",
            "subcategory":"Film & Video Production",
            "type":"Services"
        }
    ],
    "sg:phone":"+1   ",
    "sg:postcode":"06105",
    "sg:province":"CT",
    "sg:tags":[
        "motion",
        "picture"
    ],
    "wof:name":"Outlook Film Video Productions",
    "wof:placetype":"venue"
},
  "geometry": {"coordinates":[-72.707212,41.766282],"type":"Point"}
}