{
  "type": "Feature",
  "properties": {
    "addr:full":"928 Old Colchester Rd Oakdale CT 06370",
    "addr:housenumber":"928",
    "addr:postcode":"06370",
    "addr:street":"Old Colchester Rd Oakdale Ct",
    "iso:country":"US",
    "sg:address":"928 Old Colchester Rd",
    "sg:city":"Oakdale",
    "sg:classifiers":[
        {
            "category":"Professional",
            "subcategory":"Computer Services",
            "type":"Services"
        }
    ],
    "sg:phone":"+1   ",
    "sg:postcode":"06370",
    "sg:province":"CT",
    "sg:tags":[
        "programing",
        "custom"
    ],
    "wof:name":"Aquila Systems Inc",
    "wof:placetype":"venue"
},
  "geometry": {"coordinates":[-72.169984,41.462537],"type":"Point"}
}