{
  "type": "Feature",
  "properties": {
    "addr:full":"94 Anthony Dr Bristol CT 06010",
    "addr:housenumber":"94",
    "addr:postcode":"06010",
    "addr:street":"Anthony Dr Bristol Ct",
    "iso:country":"US",
    "sg:address":"94 Anthony Dr",
    "sg:city":"Bristol",
    "sg:classifiers":[
        {
            "category":"Banks & Credit Unions",
            "subcategory":"Bank",
            "type":"Services"
        }
    ],
    "sg:phone":"+1 860 585 6285",
    "sg:postcode":"06010",
    "sg:province":"CT",
    "sg:tags":[
        "broker",
        "mortgage"
    ],
    "wof:name":"American Mortgage Partners LLC",
    "wof:placetype":"venue"
},
  "geometry": {"coordinates":[-72.897111,41.694409],"type":"Point"}
}