{
  "type": "Feature",
  "properties": {
    "addr:full":"34 Prospect St Hartford CT 06103",
    "addr:housenumber":"34",
    "addr:postcode":"06103",
    "addr:street":"Prospect St",
    "iso:country":"US",
    "sg:address":"34 Prospect St",
    "sg:city":"Hartford",
    "sg:classifiers":[
        {
            "category":"Organizations",
            "subcategory":"Community Association",
            "type":"Services"
        }
    ],
    "sg:phone":"+1   ",
    "sg:postcode":"06103",
    "sg:province":"CT",
    "wof:name":"Hartford Lodge No 19 Bpoe Elk",
    "wof:placetype":"venue"
},
  "geometry": {"coordinates":[-72.672684,41.762394],"type":"Point"}
}