{
  "type": "Feature",
  "properties": {
    "addr:full":"1477 Park St Hartford CT 06106",
    "addr:housenumber":"1477",
    "addr:postcode":"06106",
    "addr:street":"Park St",
    "iso:country":"US",
    "sg:address":"1477 Park St",
    "sg:city":"Hartford",
    "sg:classifiers":[
        {
            "category":"Health Services",
            "subcategory":"Clinic",
            "type":"Services"
        }
    ],
    "sg:phone":"+1   ",
    "sg:postcode":"06106",
    "sg:province":"CT",
    "wof:name":"Heights of Wellness",
    "wof:placetype":"venue"
},
  "geometry": {"coordinates":[-72.702861,41.757807],"type":"Point"}
}