{
  "type": "Feature",
  "properties": {
    "addr:full":"295 E Center St Manchester CT 06040",
    "addr:housenumber":"295",
    "addr:postcode":"06040",
    "addr:street":"E Center St",
    "iso:country":"US",
    "sg:address":"295 E Center St",
    "sg:city":"Manchester",
    "sg:classifiers":[
        {
            "category":"Professional",
            "subcategory":"Lawyer & Legal Services",
            "type":"Services"
        }
    ],
    "sg:phone":"+1   ",
    "sg:postcode":"06040",
    "sg:province":"CT",
    "wof:name":"Oliver B Dickins Jr",
    "wof:placetype":"venue"
},
  "geometry": {"coordinates":[-72.509466,41.777894],"type":"Point"}
}