{
  "type": "Feature",
  "properties": {
    "iso:country":"US",
    "sg:address":"316 Shelton Ave",
    "sg:city":"New Haven",
    "sg:classifiers":[
        {
            "category":"Social Services",
            "subcategory":"Child Care",
            "type":"Services"
        }
    ],
    "sg:phone":"+1 203 776 7013",
    "sg:postcode":"06511",
    "sg:province":"CT",
    "wof:name":"Henryhan Inc",
    "wof:placetype":"venue"
},
  "geometry": {"coordinates":[-72.931855,41.331042],"type":"Point"}
}