{
  "type": "Feature",
  "properties": {
    "addr:full":"360 Colt Hwy Farmington CT 06032",
    "addr:housenumber":"360",
    "addr:postcode":"06032",
    "addr:street":"Colt Hwy",
    "iso:country":"US",
    "sg:address":"360 Colt Hwy",
    "sg:city":"Farmington",
    "sg:classifiers":[
        {
            "category":"Farming",
            "subcategory":"Farm",
            "type":"Manufacturing & Wholesale Goods"
        }
    ],
    "sg:phone":"+1 860 677 9326",
    "sg:postcode":"06032",
    "sg:province":"CT",
    "sg:tags":[
        "crop",
        "general"
    ],
    "wof:name":"Eyeworks of Farmington LLC",
    "wof:placetype":"venue"
},
  "geometry": {"coordinates":[-72.805582,41.712999],"type":"Point"}
}