{
  "type": "Feature",
  "properties": {
    "iso:country":"US",
    "sg:address":"124 Oak Ridge Rd",
    "sg:city":"Trumbull",
    "sg:classifiers":[
        {
            "category":"Building & Trades",
            "subcategory":"Construction",
            "type":"Services"
        }
    ],
    "sg:phone":"+1 203 374 7999",
    "sg:postcode":"06611",
    "sg:province":"CT",
    "sg:tags":[
        "house",
        "nonresidential"
    ],
    "wof:name":"D R J Builders Inc",
    "wof:placetype":"venue"
},
  "geometry": {"coordinates":[-73.173266,41.229929],"type":"Point"}
}