{
  "type": "Feature",
  "properties": {
    "addr:full":"463 Jones Hollow Rd Marlborough CT 06447",
    "addr:housenumber":"463",
    "addr:postcode":"06447",
    "addr:street":"Jones Hollow Rd Marlborough Ct",
    "iso:country":"US",
    "sg:address":"463 Jones Hollow Rd",
    "sg:city":"Marlborough",
    "sg:classifiers":[
        {
            "category":"Building & Trades",
            "subcategory":"Construction",
            "type":"Services"
        }
    ],
    "sg:phone":"+1 860 295 8386",
    "sg:postcode":"06447",
    "sg:province":"CT",
    "sg:tags":[
        "builder",
        "operative"
    ],
    "wof:name":"Combs Home Improvement",
    "wof:placetype":"venue"
},
  "geometry": {"coordinates":[-72.451894,41.687194],"type":"Point"}
}