{
  "type": "Feature",
  "properties": {
    "addr:full":"25 Powers Dr Meriden CT 06451",
    "addr:housenumber":"25",
    "addr:postcode":"06451",
    "addr:street":"Powers Dr",
    "iso:country":"US",
    "sg:address":"25 Powers Dr",
    "sg:city":"Meriden",
    "sg:classifiers":[
        {
            "category":"Building & Trades",
            "subcategory":"Construction",
            "type":"Services"
        }
    ],
    "sg:phone":"+1 860 563 5378",
    "sg:postcode":"06451",
    "sg:province":"CT",
    "sg:tags":[
        "residential",
        "general",
        "comm",
        "contractor"
    ],
    "wof:name":"Pelopennessos LLC",
    "wof:placetype":"venue"
},
  "geometry": {"coordinates":[-72.80649099999999,41.530525],"type":"Point"}
}