{
  "type": "Feature",
  "properties": {
    "iso:country":"US",
    "sg:address":"51 Old Windsor Rd",
    "sg:city":"Bloomfield",
    "sg:classifiers":[
        {
            "category":"Building & Trades",
            "subcategory":"Equipment Rental",
            "type":"Services"
        }
    ],
    "sg:phone":"+1   ",
    "sg:postcode":"06002",
    "sg:province":"CT",
    "wof:name":"Don A Gordon Rental of Condos",
    "wof:placetype":"venue"
},
  "geometry": {"coordinates":[-72.69959799999999,41.85931],"type":"Point"}
}