{
  "type": "Feature",
  "properties": {
    "addr:full":"1180 Sherman Ave Hamden CT 06514",
    "addr:housenumber":"1180",
    "addr:postcode":"06514",
    "addr:street":"Sherman Ave",
    "iso:country":"US",
    "sg:address":"1180 Sherman Ave",
    "sg:city":"Hamden",
    "sg:classifiers":[
        {
            "category":"Education",
            "subcategory":"Dance Studio",
            "type":"Public Place"
        }
    ],
    "sg:phone":"+1   ",
    "sg:postcode":"06514",
    "sg:province":"CT",
    "sg:tags":[
        "instruction",
        "gymnastic"
    ],
    "wof:name":"New Era Gymnastics",
    "wof:placetype":"venue"
},
  "geometry": {"coordinates":[-72.919905,41.396895],"type":"Point"}
}