{
  "type": "Feature",
  "properties": {
    "iso:country":"US",
    "sg:address":"65 Hidden Hills Dr",
    "sg:city":"Southington",
    "sg:classifiers":[
        {
            "category":"Building & Trades",
            "subcategory":"Electrical",
            "type":"Services"
        }
    ],
    "sg:phone":"+1 860 479 9054",
    "sg:postcode":"06489",
    "sg:province":"CT",
    "sg:tags":[
        "electrical",
        "contractor"
    ],
    "wof:name":"Copper Line Electrical",
    "wof:placetype":"venue"
},
  "geometry": {"coordinates":[-72.849546,41.64253],"type":"Point"}
}