{
  "type": "Feature",
  "properties": {
    "addr:full":"58 Hilltop Ave Stamford CT 06907",
    "addr:housenumber":"58",
    "addr:postcode":"06907",
    "addr:street":"Hilltop Ave",
    "iso:country":"US",
    "sg:address":"58 Hilltop Ave",
    "sg:city":"Stamford",
    "sg:classifiers":[
        {
            "category":"Building & Trades",
            "subcategory":"Landscaping Services",
            "type":"Services"
        }
    ],
    "sg:phone":"+1 203 595 9659",
    "sg:postcode":"06907",
    "sg:province":"CT",
    "sg:tags":[
        "landscape"
    ],
    "wof:name":"G & J Laria Landscaping",
    "wof:placetype":"venue"
},
  "geometry": {"coordinates":[-73.52927099999999,41.09921],"type":"Point"}
}