{
  "type": "Feature",
  "properties": {
    "iso:country":"US",
    "sg:address":"105 Depot Rd",
    "sg:city":"Mansfield Depot",
    "sg:classifiers":[
        {
            "category":"Organizations",
            "subcategory":"Religious Organization",
            "type":"Services"
        }
    ],
    "sg:phone":"+1   ",
    "sg:postcode":"06238",
    "sg:province":"CT",
    "wof:name":"Christian Mansfield Fellowship",
    "wof:placetype":"venue"
},
  "geometry": {"coordinates":[-72.272312,41.762292],"type":"Point"}
}