{
  "type": "Feature",
  "properties": {
    "iso:country":"US",
    "sg:address":"16 Swifts Ln",
    "sg:city":"Kent",
    "sg:classifiers":[
        {
            "category":"Social Services",
            "type":"Services"
        }
    ],
    "sg:phone":"+1   ",
    "sg:postcode":"06757",
    "sg:province":"CT",
    "wof:name":"Kent Nutrition Porgram",
    "wof:placetype":"venue"
},
  "geometry": {"coordinates":[-73.47632,41.722801],"type":"Point"}
}