{
  "type": "Feature",
  "properties": {
    "addr:full":"147 Water St Torrington CT 06790",
    "addr:housenumber":"147",
    "addr:postcode":"06790",
    "addr:street":"Water St",
    "iso:country":"US",
    "sg:address":"147 Water St",
    "sg:city":"Torrington",
    "sg:classifiers":[
        {
            "category":"Food & Beverages",
            "subcategory":"Fruits & Vegetables",
            "type":"Retail Goods"
        }
    ],
    "sg:phone":"+1 860 482 8091",
    "sg:postcode":"06790",
    "sg:province":"CT",
    "wof:name":"Just Produce",
    "wof:placetype":"venue"
},
  "geometry": {"coordinates":[-73.12492,41.801754],"type":"Point"}
}