{
  "type": "Feature",
  "properties": {
    "addr:full":"13 Wintergreen Hill Rd Danbury CT 06811",
    "addr:housenumber":"13",
    "addr:postcode":"06811",
    "addr:street":"Wintergreen Hill Rd",
    "iso:country":"US",
    "sg:address":"13 Wintergreen Hill Rd",
    "sg:city":"Danbury",
    "sg:classifiers":[
        {
            "category":"Shopping",
            "subcategory":"Clothing, Apparel, & Fashions",
            "type":"Retail Goods"
        }
    ],
    "sg:phone":"+1 203 730 8377",
    "sg:postcode":"06811",
    "sg:province":"CT",
    "sg:tags":[
        "family"
    ],
    "wof:name":"Cutie Ptotie Kids Collectn LLC",
    "wof:placetype":"venue"
},
  "geometry": {"coordinates":[-73.52421,41.40045],"type":"Point"}
}