{
  "type": "Feature",
  "properties": {
    "iso:country":"US",
    "sg:address":"14 Winter Way",
    "sg:city":"Enfield",
    "sg:classifiers":[
        {
            "category":"Arts & Performance",
            "subcategory":"Theater",
            "type":"Entertainment"
        }
    ],
    "sg:phone":"+1   ",
    "sg:postcode":"06082",
    "sg:province":"CT",
    "sg:tags":[
        "theatrical"
    ],
    "wof:name":"Valley Repertory Co Inc",
    "wof:placetype":"venue"
},
  "geometry": {"coordinates":[-72.545051,41.994767],"type":"Point"}
}