{
  "type": "Feature",
  "properties": {
    "addr:full":"993 Federal Rd Brookfield CT 06804",
    "addr:housenumber":"993",
    "addr:postcode":"06804",
    "addr:street":"Federal Rd",
    "iso:country":"US",
    "sg:address":"993 Federal Rd",
    "sg:city":"Brookfield",
    "sg:classifiers":[
        {
            "category":"Manufacturing",
            "subcategory":"Petroleum Products",
            "type":"Manufacturing & Wholesale Goods"
        }
    ],
    "sg:phone":"+1 203 775 1291",
    "sg:postcode":"06804",
    "sg:province":"CT",
    "sg:tags":[
        "lubricant"
    ],
    "sg:website":"www.goldenspectro.com",
    "wof:name":"Intercontinental Lubricants",
    "wof:placetype":"venue"
},
  "geometry": {"coordinates":[-73.41748699999999,41.500317],"type":"Point"}
}