{
  "type": "Feature",
  "properties": {
    "addr:full":"10 Azalea Ter Cos Cob CT 06807",
    "addr:housenumber":"10",
    "addr:postcode":"06807",
    "addr:street":"Azalea Ter Cos Cob Ct",
    "iso:country":"US",
    "sg:address":"10 Azalea Ter",
    "sg:city":"Cos Cob",
    "sg:classifiers":[
        {
            "category":"Shopping",
            "subcategory":"Florist",
            "type":"Retail Goods"
        }
    ],
    "sg:phone":"+1 203 661 5372",
    "sg:postcode":"06807",
    "sg:province":"CT",
    "wof:name":"English Country Gardens",
    "wof:placetype":"venue"
},
  "geometry": {"coordinates":[-73.5812,41.070893],"type":"Point"}
}