{
  "type": "Feature",
  "properties": {
    "iso:country":"US",
    "sg:address":"44 Old State Rd",
    "sg:city":"New Milford",
    "sg:classifiers":[
        {
            "category":"Building & Trades",
            "subcategory":"Plumbing",
            "type":"Services"
        }
    ],
    "sg:phone":"+1 860 354 1896",
    "sg:postcode":"06776",
    "sg:province":"CT",
    "sg:tags":[
        "contractor"
    ],
    "wof:name":"LBJ Plumbing & Heating",
    "wof:placetype":"venue"
},
  "geometry": {"coordinates":[-73.422781,41.537918],"type":"Point"}
}