{
  "type": "Feature",
  "properties": {
    "addr:full":"1 Walnut Hill Rd Bethel CT 06801",
    "addr:housenumber":"1",
    "addr:postcode":"06801",
    "addr:street":"Walnut Hill Rd",
    "iso:country":"US",
    "sg:address":"1 Walnut Hill Rd",
    "sg:city":"Bethel",
    "sg:classifiers":[
        {
            "category":"Restaurant",
            "type":"Food & Drink"
        }
    ],
    "sg:phone":"+1 203 792 3447",
    "sg:postcode":"06801",
    "sg:province":"CT",
    "sg:tags":[
        "delicatessen"
    ],
    "wof:name":"Mia Sophia",
    "wof:placetype":"venue"
},
  "geometry": {"coordinates":[-73.399742,41.386832],"type":"Point"}
}