{
  "type": "Feature",
  "properties": {
    "iso:country":"US",
    "sg:address":"152 Caroline Rd",
    "sg:city":"Bozrah",
    "sg:classifiers":[
        {
            "category":"Building & Trades",
            "subcategory":"Plumbing",
            "type":"Services"
        },
        {
            "category":"Building & Trades",
            "subcategory":"Construction",
            "type":"Services"
        }
    ],
    "sg:phone":"+1 860 859 3310",
    "sg:postcode":"06334",
    "sg:province":"CT",
    "sg:tags":[
        "plumber",
        "industrial",
        "system",
        "specialty",
        "heating",
        "contractors-commercial",
        "contractor",
        "air conditioning"
    ],
    "wof:name":"Vadnais Plumbing Htg & Contg L",
    "wof:placetype":"venue"
},
  "geometry": {"coordinates":[-72.19329399999999,41.523192],"type":"Point"}
}