{
  "type": "Feature",
  "properties": {
    "addr:full":"12 Mead Ave Cos Cob CT 06807",
    "addr:housenumber":"12",
    "addr:postcode":"06807",
    "addr:street":"Mead Ave",
    "iso:country":"US",
    "sg:address":"12 Mead Ave",
    "sg:city":"Cos Cob",
    "sg:classifiers":[
        {
            "category":"Professional",
            "subcategory":"Management & Consulting",
            "type":"Services"
        }
    ],
    "sg:phone":"+1   ",
    "sg:postcode":"06807",
    "sg:province":"CT",
    "wof:name":"Long Group Inc",
    "wof:placetype":"venue"
},
  "geometry": {"coordinates":[-73.59710099999999,41.039176],"type":"Point"}
}