{
  "type": "Feature",
  "properties": {
    "iso:country":"US",
    "sg:address":"88 Danbury Rd",
    "sg:city":"Ridgefield",
    "sg:classifiers":[
        {
            "category":"Building & Trades",
            "subcategory":"Electrical",
            "type":"Services"
        }
    ],
    "sg:phone":"+1 203 431 4704",
    "sg:postcode":"06877",
    "sg:province":"CT",
    "sg:tags":[
        "electrical",
        "electric",
        "contractor"
    ],
    "wof:name":"AP Pavia Electrical Co Inc",
    "wof:placetype":"venue"
},
  "geometry": {"coordinates":[-73.493801,41.291622],"type":"Point"}
}