{
  "type": "Feature",
  "properties": {
    "iso:country":"US",
    "sg:address":"513 Glenbrook Rd",
    "sg:city":"Stamford",
    "sg:classifiers":[
        {
            "category":"Recreation",
            "type":"Entertainment"
        }
    ],
    "sg:phone":"+1 203 965 0696",
    "sg:postcode":"06906",
    "sg:province":"CT",
    "sg:tags":[
        "instruction",
        "yoga"
    ],
    "wof:name":"Yoga Sensations",
    "wof:placetype":"venue"
},
  "geometry": {"coordinates":[-73.520331,41.070568],"type":"Point"}
}