{
  "type": "Feature",
  "properties": {
    "addr:full":"501 Farmington Ave Hartford CT 06105",
    "addr:housenumber":"501",
    "addr:postcode":"06105",
    "addr:street":"Farmington Ave;Ct",
    "iso:country":"US",
    "sg:address":"501 Farmington Ave",
    "sg:city":"Hartford",
    "sg:classifiers":[
        {
            "category":"Restaurant",
            "type":"Food & Drink"
        }
    ],
    "sg:menulink":"http://www.allmenus.com/ct/hartford/189473-kfc---kentucky-fried-chicken/menu/",
    "sg:phone":"+1 860 232 9566",
    "sg:postcode":"06105",
    "sg:province":"CT",
    "sg:tags":[
        "american",
        "chicken"
    ],
    "wof:name":"KFC - Kentucky Fried Chicken",
    "wof:placetype":"venue"
},
  "geometry": {"coordinates":[-72.70827199999999,41.766446],"type":"Point"}
}