{
  "type": "Feature",
  "properties": {
    "addr:full":"193 Rubber Ave Naugatuck CT 06770",
    "addr:housenumber":"193",
    "addr:postcode":"06770",
    "addr:street":"Rubber Ave Naugatuck Ct",
    "iso:country":"US",
    "sg:address":"193 Rubber Ave",
    "sg:city":"Naugatuck",
    "sg:classifiers":[
        {
            "category":"Education",
            "subcategory":"Special Training",
            "type":"Public Place"
        }
    ],
    "sg:phone":"+1   ",
    "sg:postcode":"06770",
    "sg:province":"CT",
    "wof:name":"Bill Rotella Drum Studio",
    "wof:placetype":"venue"
},
  "geometry": {"coordinates":[-73.061572,41.487016],"type":"Point"}
}