{
  "type": "Feature",
  "properties": {
    "addr:full":"377 Chestnut Tree Hill Rd Southbury CT 06488",
    "addr:housenumber":"377",
    "addr:postcode":"06488",
    "addr:street":"Chestnut Tree Hill Rd",
    "iso:country":"US",
    "sg:address":"377 Chestnut Tree Hill Rd",
    "sg:city":"Southbury",
    "sg:classifiers":[
        {
            "category":"Professional",
            "type":"Services"
        }
    ],
    "sg:phone":"+1 203 264 0732",
    "sg:postcode":"06488",
    "sg:province":"CT",
    "sg:tags":[
        "establishment"
    ],
    "wof:name":"Mastroianni & Mastroianni",
    "wof:placetype":"venue"
},
  "geometry": {"coordinates":[-73.196141,41.504292],"type":"Point"}
}