{
  "type": "Feature",
  "properties": {
    "addr:full":"368 Timrod Rd Manchester CT 06040",
    "addr:housenumber":"368",
    "addr:postcode":"06040",
    "addr:street":"Timrod Rd",
    "iso:country":"US",
    "sg:address":"368 Timrod Rd",
    "sg:city":"Manchester",
    "sg:classifiers":[
        {
            "category":"Communications",
            "subcategory":"Radio Station",
            "type":"Services"
        }
    ],
    "sg:phone":"+1 860 647 8010",
    "sg:postcode":"06040",
    "sg:province":"CT",
    "sg:tags":[
        "broadcast"
    ],
    "wof:name":"21st Century Media",
    "wof:placetype":"venue"
},
  "geometry": {"coordinates":[-72.494158,41.754896],"type":"Point"}
}