{
  "type": "Feature",
  "properties": {
    "iso:country":"US",
    "sg:address":"150 Sycamore St",
    "sg:city":"Glastonbury",
    "sg:classifiers":[
        {
            "category":"Insurance",
            "subcategory":"Insurance Agent",
            "type":"Services"
        }
    ],
    "sg:phone":"+1 860 633 7646",
    "sg:postcode":"06033",
    "sg:province":"CT",
    "wof:name":"Hartford Financial Assoc Ltd",
    "wof:placetype":"venue"
},
  "geometry": {"coordinates":[-72.598861,41.71237],"type":"Point"}
}