{
  "type": "Feature",
  "properties": {
    "addr:full":"148 Center St Wallingford CT 06492",
    "addr:housenumber":"148",
    "addr:postcode":"06492",
    "addr:street":"Center St",
    "iso:country":"US",
    "sg:address":"148 Center St",
    "sg:city":"Wallingford",
    "sg:classifiers":[
        {
            "category":"Personal",
            "subcategory":"Beauty Salon",
            "type":"Services"
        }
    ],
    "sg:phone":"+1 203 265 7064",
    "sg:postcode":"06492",
    "sg:province":"CT",
    "sg:tags":[
        "hair",
        "stylist"
    ],
    "wof:name":"Hair By Leanne",
    "wof:placetype":"venue"
},
  "geometry": {"coordinates":[-72.821422,41.455578],"type":"Point"}
}