{
  "type": "Feature",
  "properties": {
    "iso:country":"US",
    "sg:address":"208 Lenore Dr",
    "sg:city":"Shelton",
    "sg:classifiers":[
        {
            "category":"Building & Trades",
            "subcategory":"Landscaping Services",
            "type":"Services"
        }
    ],
    "sg:phone":"+1 203 929 3924",
    "sg:postcode":"06484",
    "sg:province":"CT",
    "wof:name":"Evergreen Landscaping",
    "wof:placetype":"venue"
},
  "geometry": {"coordinates":[-73.156206,41.341148],"type":"Point"}
}