{
  "type": "Feature",
  "properties": {
    "addr:full":"33 Rossotto Dr Hamden CT 06514",
    "addr:housenumber":"33",
    "addr:postcode":"06514",
    "addr:street":"Rossotto Dr",
    "iso:country":"US",
    "sg:address":"33 Rossotto Dr",
    "sg:city":"Hamden",
    "sg:classifiers":[
        {
            "category":"Organizations",
            "subcategory":"Religious Organization",
            "type":"Services"
        }
    ],
    "sg:phone":"+1   ",
    "sg:postcode":"06514",
    "sg:province":"CT",
    "wof:name":"Congregation of Legionaries",
    "wof:placetype":"venue"
},
  "geometry": {"coordinates":[-72.91837599999999,41.394438],"type":"Point"}
}