{
  "type": "Feature",
  "properties": {
    "iso:country":"US",
    "sg:address":"120 Hawley Ln",
    "sg:city":"Trumbull",
    "sg:classifiers":[
        {
            "category":"Insurance",
            "subcategory":"Health Insurance",
            "type":"Services"
        }
    ],
    "sg:phone":"+1 203 381 6400",
    "sg:postcode":"06611",
    "sg:province":"CT",
    "sg:tags":[
        "professional",
        "plan",
        "organization"
    ],
    "wof:name":"Health Net of The Northeast",
    "wof:placetype":"venue"
},
  "geometry": {"coordinates":[-73.150786,41.232256],"type":"Point"}
}