{
  "type": "Feature",
  "properties": {
    "addr:full":"4555 Main St Bridgeport CT 06606",
    "addr:housenumber":"4555",
    "addr:postcode":"06606",
    "addr:street":"Main St",
    "iso:country":"US",
    "sg:address":"4555 Main St",
    "sg:city":"Bridgeport",
    "sg:classifiers":[
        {
            "category":"Food & Beverages",
            "subcategory":"Liquor & Beverages",
            "type":"Retail Goods"
        }
    ],
    "sg:phone":"+1 203 374 7321",
    "sg:postcode":"06606",
    "sg:province":"CT",
    "sg:tags":[
        "alcoholic"
    ],
    "wof:name":"Brookside Package Store Inc",
    "wof:placetype":"venue"
},
  "geometry": {"coordinates":[-73.21816800000001,41.222849],"type":"Point"}
}