{
  "type": "Feature",
  "properties": {
    "addr:full":"1625 Straits Tpke Middlebury CT 06762",
    "addr:housenumber":"1625",
    "addr:postcode":"06762",
    "addr:street":"Straits Tpke",
    "iso:country":"US",
    "sg:address":"1625 Straits Tpke",
    "sg:city":"Middlebury",
    "sg:classifiers":[
        {
            "category":"Health Services",
            "subcategory":"Medical Lab",
            "type":"Services"
        }
    ],
    "sg:phone":"+1 203 577 2299",
    "sg:postcode":"06762",
    "sg:province":"CT",
    "sg:tags":[
        "laboratory"
    ],
    "wof:name":"Waterbury Hospital Blood Drwng",
    "wof:placetype":"venue"
},
  "geometry": {"coordinates":[-73.092088,41.553431],"type":"Point"}
}