{
  "type": "Feature",
  "properties": {
    "addr:full":"8 Wells Ave East Hampton CT 06424",
    "addr:housenumber":"8",
    "addr:postcode":"06424",
    "addr:street":"Wells Ave East Hampton Ct",
    "iso:country":"US",
    "sg:address":"8 Wells Ave",
    "sg:city":"East Hampton",
    "sg:classifiers":[
        {
            "category":"Building & Trades",
            "subcategory":"Construction",
            "type":"Services"
        }
    ],
    "sg:phone":"+1 860 267 1425",
    "sg:postcode":"06424",
    "sg:province":"CT",
    "sg:tags":[
        "hanging",
        "contractor"
    ],
    "wof:name":"Orsini Painters Inc",
    "wof:placetype":"venue"
},
  "geometry": {"coordinates":[-72.505055,41.585623],"type":"Point"}
}