{
  "type": "Feature",
  "properties": {
    "iso:country":"US",
    "sg:address":"122 Calhoun St",
    "sg:city":"Torrington",
    "sg:classifiers":[
        {
            "category":"Building & Trades",
            "subcategory":"Construction",
            "type":"Services"
        }
    ],
    "sg:phone":"+1 860 496 9032",
    "sg:postcode":"06790",
    "sg:province":"CT",
    "sg:tags":[
        "contractor"
    ],
    "wof:name":"Moore & Morrison",
    "wof:placetype":"venue"
},
  "geometry": {"coordinates":[-73.118954,41.813484],"type":"Point"}
}