{
  "type": "Feature",
  "properties": {
    "addr:full":"1 Ferry Ln Westport CT 06880",
    "addr:housenumber":"1",
    "addr:postcode":"06880",
    "addr:street":"Ferry Ln",
    "iso:country":"US",
    "sg:address":"1 Ferry Ln",
    "sg:city":"Westport",
    "sg:classifiers":[
        {
            "category":"Retail",
            "subcategory":"Auto Rental",
            "type":"Services"
        }
    ],
    "sg:phone":"+1 203 227 1232",
    "sg:postcode":"06880",
    "sg:province":"CT",
    "sg:tags":[
        "renting",
        "automobile"
    ],
    "wof:name":"Avis Rent A Car",
    "wof:placetype":"venue"
},
  "geometry": {"coordinates":[-73.37514299999999,41.11752],"type":"Point"}
}