{
  "type": "Feature",
  "properties": {
    "addr:full":"1 Donald Dr Westport CT 06880",
    "addr:housenumber":"1",
    "addr:postcode":"06880",
    "addr:street":"Donald Dr",
    "iso:country":"US",
    "sg:address":"1 Donald Dr",
    "sg:city":"Westport",
    "sg:classifiers":[
        {
            "category":"Banks & Credit Unions",
            "subcategory":"Financial Services",
            "type":"Services"
        }
    ],
    "sg:phone":"+1 203 226 7727",
    "sg:postcode":"06880",
    "sg:province":"CT",
    "sg:tags":[
        "investor"
    ],
    "wof:name":"Frank Rogers Investments LLC",
    "wof:placetype":"venue"
},
  "geometry": {"coordinates":[-73.32243099999999,41.140245],"type":"Point"}
}