{
  "type": "Feature",
  "properties": {
    "addr:full":"64 Hartwell Rd Hartford CT 06117",
    "addr:housenumber":"64",
    "addr:postcode":"06117",
    "addr:street":"Hartwell Rd",
    "iso:country":"US",
    "sg:address":"64 Hartwell Rd",
    "sg:city":"Hartford",
    "sg:classifiers":[
        {
            "category":"Building & Trades",
            "subcategory":"Electrical",
            "type":"Services"
        }
    ],
    "sg:phone":"+1 860 232 9367",
    "sg:postcode":"06117",
    "sg:province":"CT",
    "sg:tags":[
        "electrical",
        "contractor"
    ],
    "wof:name":"West Hartford Electric Inc",
    "wof:placetype":"venue"
},
  "geometry": {"coordinates":[-72.75944200000001,41.793788],"type":"Point"}
}