{
  "type": "Feature",
  "properties": {
    "addr:full":"22 Bayview Ave Stonington CT 06378",
    "addr:housenumber":"22",
    "addr:postcode":"06378",
    "addr:street":"Bayview Ave",
    "iso:country":"US",
    "sg:address":"22 Bayview Ave",
    "sg:city":"Stonington",
    "sg:classifiers":[
        {
            "category":"Professional",
            "subcategory":"Management & Consulting",
            "type":"Services"
        }
    ],
    "sg:phone":"+1   ",
    "sg:postcode":"06378",
    "sg:province":"CT",
    "wof:name":"Benjamin Greenfield & Corp",
    "wof:placetype":"venue"
},
  "geometry": {"coordinates":[-71.89866600000001,41.337675],"type":"Point"}
}