{
  "type": "Feature",
  "properties": {
    "addr:full":"152 S Colony St Meriden CT 06450",
    "addr:housenumber":"152",
    "addr:postcode":"06450",
    "addr:street":"S Colony St",
    "iso:country":"US",
    "sg:address":"152 S Colony St",
    "sg:city":"Meriden",
    "sg:classifiers":[
        {
            "category":"Organizations",
            "subcategory":"Religious Organization",
            "type":"Services"
        }
    ],
    "sg:phone":"+1 203 639 7341",
    "sg:postcode":"06450",
    "sg:province":"CT",
    "sg:tags":[
        "church"
    ],
    "wof:name":"Channelling Youth For Change",
    "wof:placetype":"venue"
},
  "geometry": {"coordinates":[-72.80346400000001,41.534393],"type":"Point"}
}