{
  "type": "Feature",
  "properties": {
    "iso:country":"US",
    "sg:address":"30 Pheasant Run",
    "sg:city":"Oakdale",
    "sg:classifiers":[
        {
            "category":"Professional",
            "subcategory":"Computer Services",
            "type":"Services"
        }
    ],
    "sg:phone":"+1   ",
    "sg:postcode":"06370",
    "sg:province":"CT",
    "sg:tags":[
        "related"
    ],
    "wof:name":"Intertub",
    "wof:placetype":"venue"
},
  "geometry": {"coordinates":[-72.190928,41.460322],"type":"Point"}
}