{
  "type": "Feature",
  "properties": {
    "addr:full":"37 Hawthorne Dr Monroe CT 06468",
    "addr:housenumber":"37",
    "addr:postcode":"06468",
    "addr:street":"Hawthorne Dr Monroe Ct",
    "iso:country":"US",
    "sg:address":"37 Hawthorne Dr",
    "sg:city":"Monroe",
    "sg:classifiers":[
        {
            "category":"Banks & Credit Unions",
            "subcategory":"Financial Services",
            "type":"Services"
        }
    ],
    "sg:phone":"+1 203 268 8897",
    "sg:postcode":"06468",
    "sg:province":"CT",
    "sg:tags":[
        "investor"
    ],
    "wof:name":"Knucklehead Investors LLC",
    "wof:placetype":"venue"
},
  "geometry": {"coordinates":[-73.220855,41.343141],"type":"Point"}
}