{
  "type": "Feature",
  "properties": {
    "addr:full":"6 Brookside Dr Wallingford CT 06492",
    "addr:housenumber":"6",
    "addr:postcode":"06492",
    "addr:street":"Brookside Dr",
    "iso:country":"US",
    "sg:address":"6 Brookside Dr",
    "sg:city":"Wallingford",
    "sg:classifiers":[
        {
            "category":"Manufacturing",
            "subcategory":"Tools & Machinery",
            "type":"Manufacturing & Wholesale Goods"
        }
    ],
    "sg:phone":"+1 203 265 3929",
    "sg:postcode":"06492",
    "sg:province":"CT",
    "sg:tags":[
        "testing",
        "apparatus"
    ],
    "sg:website":"www.udco.com",
    "wof:name":"Unholtz-Dickie Corp",
    "wof:placetype":"venue"
},
  "geometry": {"coordinates":[-72.79899899999999,41.490748],"type":"Point"}
}