{
  "type": "Feature",
  "properties": {
    "addr:full":"9 Nottingham Dr Old Lyme CT 06371",
    "addr:housenumber":"9",
    "addr:postcode":"06371",
    "addr:street":"Nottingham Dr",
    "iso:country":"US",
    "sg:address":"9 Nottingham Dr",
    "sg:city":"Old Lyme",
    "sg:classifiers":[
        {
            "category":"Professional",
            "subcategory":"Employment Agencies",
            "type":"Services"
        }
    ],
    "sg:phone":"+1   ",
    "sg:postcode":"06371",
    "sg:province":"CT",
    "sg:tags":[
        "connecticut",
        "ship",
        "pilot"
    ],
    "wof:name":"Constitution State Pilots",
    "wof:placetype":"venue"
},
  "geometry": {"coordinates":[-72.28002499999999,41.302097],"type":"Point"}
}