{
  "type": "Feature",
  "properties": {
    "addr:full":"163 Birdseye St Bridgeport CT 06604",
    "addr:housenumber":"163",
    "addr:postcode":"06604",
    "addr:street":"Birdseye St",
    "iso:country":"US",
    "sg:address":"163 Birdseye St",
    "sg:city":"Bridgeport",
    "sg:classifiers":[
        {
            "category":"Shopping",
            "subcategory":"Music",
            "type":"Retail Goods"
        }
    ],
    "sg:phone":"+1 203 384 1364",
    "sg:postcode":"06604",
    "sg:province":"CT",
    "wof:name":"Old School Cds",
    "wof:placetype":"venue"
},
  "geometry": {"coordinates":[-73.210618,41.182298],"type":"Point"}
}