{
  "type": "Feature",
  "properties": {
    "iso:country":"US",
    "sg:address":"20 Railroad Ave",
    "sg:city":"West Haven",
    "sg:classifiers":[
        {
            "category":"Professional",
            "subcategory":"Advertising",
            "type":"Services"
        }
    ],
    "sg:phone":"+1 203 562 2266",
    "sg:postcode":"06516",
    "sg:province":"CT",
    "sg:website":"www.bpsbillboards.com",
    "wof:name":"Big Picture Studios",
    "wof:placetype":"venue"
},
  "geometry": {"coordinates":[-72.96229,41.272573],"type":"Point"}
}