{
  "type": "Feature",
  "properties": {
    "addr:full":"161 N Park Ave Easton CT 06612",
    "addr:housenumber":"161",
    "addr:postcode":"06612",
    "addr:street":"N Park Ave",
    "iso:country":"US",
    "sg:address":"161 N Park Ave",
    "sg:city":"Easton",
    "sg:classifiers":[
        {
            "category":"Building & Trades",
            "subcategory":"Construction",
            "type":"Services"
        }
    ],
    "sg:phone":"+1 203 459 0476",
    "sg:postcode":"06612",
    "sg:province":"CT",
    "sg:tags":[
        "foundation",
        "concrete",
        "contractor"
    ],
    "wof:name":"Burdo Carpentry & Concrete LLC",
    "wof:placetype":"venue"
},
  "geometry": {"coordinates":[-73.276523,41.264652],"type":"Point"}
}