{
  "type": "Feature",
  "properties": {
    "iso:country":"US",
    "sg:address":"320 Main St",
    "sg:city":"East Haven",
    "sg:classifiers":[
        {
            "category":"Shopping",
            "subcategory":"Gifts & Souvenirs",
            "type":"Retail Goods"
        }
    ],
    "sg:phone":"+1 203 469 6289",
    "sg:postcode":"06512",
    "sg:province":"CT",
    "sg:tags":[
        "shop"
    ],
    "wof:name":"Madelyn's Imports",
    "wof:placetype":"venue"
},
  "geometry": {"coordinates":[-72.874274,41.278945],"type":"Point"}
}