{
  "type": "Feature",
  "properties": {
    "iso:country":"US",
    "sg:address":"286 W Main St",
    "sg:city":"Meriden",
    "sg:classifiers":[
        {
            "category":"Restaurant",
            "type":"Food & Drink"
        }
    ],
    "sg:phone":"+1 203 630 3421",
    "sg:postcode":"06451",
    "sg:province":"CT",
    "sg:tags":[
        "delicatessen",
        "italian"
    ],
    "wof:name":"Gabriellas Italian Deli",
    "wof:placetype":"venue"
},
  "geometry": {"coordinates":[-72.812584,41.539486],"type":"Point"}
}