{
  "type": "Feature",
  "properties": {
    "iso:country":"US",
    "sg:address":"135 Norwich Ave",
    "sg:city":"Norwich",
    "sg:classifiers":[
        {
            "category":"Freight",
            "type":"Transportation"
        }
    ],
    "sg:phone":"+1 860 889 7301",
    "sg:postcode":"06360",
    "sg:province":"CT",
    "sg:tags":[
        "operator",
        "trucking"
    ],
    "wof:name":"Highpoint Mobile HM Sls & Svc",
    "wof:placetype":"venue"
},
  "geometry": {"coordinates":[-72.05082899999999,41.555303],"type":"Point"}
}