{
  "type": "Feature",
  "properties": {
    "addr:full":"166 Main St Old Saybrook CT 06475",
    "addr:housenumber":"166",
    "addr:postcode":"06475",
    "addr:street":"Main St",
    "iso:country":"US",
    "sg:address":"166 Main St",
    "sg:city":"Old Saybrook",
    "sg:classifiers":[
        {
            "category":"Professional",
            "type":"Services"
        }
    ],
    "sg:phone":"+1 860 395 5459",
    "sg:postcode":"06475",
    "sg:province":"CT",
    "wof:name":"Say Main L L C",
    "wof:placetype":"venue"
},
  "geometry": {"coordinates":[-72.37632600000001,41.293137],"type":"Point"}
}