{
  "type": "Feature",
  "properties": {
    "addr:full":"284 Colonial Ave Waterbury CT 06704",
    "addr:housenumber":"284",
    "addr:postcode":"06704",
    "addr:street":"Colonial Ave",
    "iso:country":"US",
    "sg:address":"284 Colonial Ave",
    "sg:city":"Waterbury",
    "sg:classifiers":[
        {
            "category":"Organizations",
            "subcategory":"Labor Organization",
            "type":"Services"
        }
    ],
    "sg:phone":"+1 203 755 3897",
    "sg:postcode":"06704",
    "sg:province":"CT",
    "wof:name":"Construction & General Laborer",
    "wof:placetype":"venue"
},
  "geometry": {"coordinates":[-73.060688,41.587102],"type":"Point"}
}