{
  "type": "Feature",
  "properties": {
    "iso:country":"US",
    "sg:address":"263 Golden Hill St",
    "sg:city":"Bridgeport",
    "sg:classifiers":[
        {
            "category":"Government",
            "subcategory":"Office",
            "type":"Public Place"
        }
    ],
    "sg:phone":"+1 203 576 7972",
    "sg:postcode":"06604",
    "sg:province":"CT",
    "sg:tags":[
        "city",
        "resource",
        "human"
    ],
    "sg:website":"www.cityofbridgeport.com",
    "wof:name":"Bridgeport Dept Aging",
    "wof:placetype":"venue"
},
  "geometry": {"coordinates":[-73.193529,41.179408],"type":"Point"}
}