{
  "type": "Feature",
  "properties": {
    "addr:full":"635 Lakewood Rd Waterbury CT 06704",
    "addr:housenumber":"635",
    "addr:postcode":"06704",
    "addr:street":"Lakewood Rd",
    "iso:country":"US",
    "sg:address":"635 Lakewood Rd",
    "sg:city":"Waterbury",
    "sg:classifiers":[
        {
            "category":"Shopping",
            "subcategory":"Tobacco",
            "type":"Retail Goods"
        }
    ],
    "sg:phone":"+1 203 573 8488",
    "sg:postcode":"06704",
    "sg:province":"CT",
    "sg:tags":[
        "product"
    ],
    "wof:name":"Sams Disc Cigarette & Cigr",
    "wof:placetype":"venue"
},
  "geometry": {"coordinates":[-73.010249,41.573078],"type":"Point"}
}