{
  "type": "Feature",
  "properties": {
    "iso:country":"US",
    "sg:address":"194 Bassett St",
    "sg:city":"New Haven",
    "sg:classifiers":[
        {
            "category":"Government",
            "subcategory":"Office",
            "type":"Public Place"
        }
    ],
    "sg:phone":"+1 203 789 7993",
    "sg:postcode":"06511",
    "sg:province":"CT",
    "sg:tags":[
        "social"
    ],
    "wof:name":"South Cntl Rgnal Off New Haven",
    "wof:placetype":"venue"
},
  "geometry": {"coordinates":[-72.933318,41.332008],"type":"Point"}
}