{
  "type": "Feature",
  "properties": {
    "addr:full":"2 Norfolk Rd Torrington CT 06790",
    "addr:housenumber":"2",
    "addr:postcode":"06790",
    "addr:street":"Norfolk Rd",
    "iso:country":"US",
    "sg:address":"2 Norfolk Rd",
    "sg:city":"Torrington",
    "sg:classifiers":[
        {
            "category":"Bakery",
            "type":"Food & Drink"
        },
        {
            "category":"Coffee & Tea",
            "type":"Food & Drink"
        },
        {
            "category":"Bagels",
            "type":"Food & Drink"
        },
        {
            "category":"Donuts",
            "type":"Food & Drink"
        }
    ],
    "sg:menulink":"http://www.allmenus.com/ct/torrington/130131-dunkin-donuts/menu/",
    "sg:phone":"+1 860 496 8544",
    "sg:postcode":"06790",
    "sg:province":"CT",
    "sg:tags":[
        "american",
        "diner",
        "pastry"
    ],
    "wof:name":"Dunkin' Donuts",
    "wof:placetype":"venue"
},
  "geometry": {"coordinates":[-73.14509700000001,41.818326],"type":"Point"}
}