{
  "type": "Feature",
  "properties": {
    "addr:full":"367 Bantam Rd Litchfield CT 06759",
    "addr:housenumber":"367",
    "addr:postcode":"06759",
    "addr:street":"Bantam Rd",
    "iso:country":"US",
    "sg:address":"367 Bantam Rd",
    "sg:city":"Litchfield",
    "sg:classifiers":[
        {
            "category":"Retail",
            "subcategory":"Repair Shop",
            "type":"Services"
        }
    ],
    "sg:phone":"+1   ",
    "sg:postcode":"06759",
    "sg:province":"CT",
    "wof:name":"American Heating Service",
    "wof:placetype":"venue"
},
  "geometry": {"coordinates":[-73.209373,41.743742],"type":"Point"}
}