{
  "type": "Feature",
  "properties": {
    "iso:country":"US",
    "sg:address":"826 Worthington Ridge",
    "sg:city":"Berlin",
    "sg:classifiers":[
        {
            "category":"Professional",
            "subcategory":"Lawyer & Legal Services",
            "type":"Services"
        }
    ],
    "sg:phone":"+1   ",
    "sg:postcode":"06037",
    "sg:province":"CT",
    "wof:name":"Olson Edward Jr",
    "wof:placetype":"venue"
},
  "geometry": {"coordinates":[-72.745923,41.621264],"type":"Point"}
}