{
  "type": "Feature",
  "properties": {
    "addr:full":"13 Main St East Hampton CT 06424",
    "addr:housenumber":"13",
    "addr:postcode":"06424",
    "addr:street":"Main St East Hampton Ct",
    "iso:country":"US",
    "sg:address":"13 Main St",
    "sg:city":"East Hampton",
    "sg:classifiers":[
        {
            "category":"Professional",
            "subcategory":"Employment Agencies",
            "type":"Services"
        }
    ],
    "sg:phone":"+1   ",
    "sg:postcode":"06424",
    "sg:province":"CT",
    "wof:name":"First Data",
    "wof:placetype":"venue"
},
  "geometry": {"coordinates":[-72.50565,41.581384],"type":"Point"}
}