{
  "type": "Feature",
  "properties": {
    "addr:full":"350 Roxbury Rd Stamford CT 06902",
    "addr:housenumber":"350",
    "addr:postcode":"06902",
    "addr:street":"Roxbury Rd",
    "iso:country":"US",
    "sg:address":"350 Roxbury Rd",
    "sg:city":"Stamford",
    "sg:classifiers":[
        {
            "category":"Social Services",
            "subcategory":"Child Care",
            "type":"Services"
        }
    ],
    "sg:phone":"+1 203 968 0768",
    "sg:postcode":"06902",
    "sg:province":"CT",
    "sg:tags":[
        "kindergarten",
        "academic",
        "school"
    ],
    "wof:name":"Roxbury Community Nursery Schl",
    "wof:placetype":"venue"
},
  "geometry": {"coordinates":[-73.573994,41.094651],"type":"Point"}
}