{
  "type": "Feature",
  "properties": {
    "iso:country":"US",
    "sg:address":"35 Longview Ave",
    "sg:city":"Stamford",
    "sg:classifiers":[
        {
            "category":"Building & Trades",
            "subcategory":"Cleaning & Sanitation",
            "type":"Services"
        }
    ],
    "sg:phone":"+1   ",
    "sg:postcode":"06905",
    "sg:province":"CT",
    "sg:tags":[
        "maintenance"
    ],
    "wof:name":"Midnight Express Clg Svcs LLC",
    "wof:placetype":"venue"
},
  "geometry": {"coordinates":[-73.549589,41.088353],"type":"Point"}
}