{
  "type": "Feature",
  "properties": {
    "iso:country":"US",
    "sg:address":"98 Hawthorne Mead Dr",
    "sg:city":"Glastonbury",
    "sg:classifiers":[
        {
            "category":"Wholesale",
            "subcategory":"Construction Materials",
            "type":"Manufacturing & Wholesale Goods"
        }
    ],
    "sg:phone":"+1 860 633 5820",
    "sg:postcode":"06033",
    "sg:province":"CT",
    "wof:name":"Fuh International Inc",
    "wof:placetype":"venue"
},
  "geometry": {"coordinates":[-72.549218,41.714332],"type":"Point"}
}