{
  "type": "Feature",
  "properties": {
    "addr:full":"492 Winsted Rd Torrington CT 06790",
    "addr:housenumber":"492",
    "addr:postcode":"06790",
    "addr:street":"Winsted Rd",
    "iso:country":"US",
    "sg:address":"492 Winsted Rd",
    "sg:city":"Torrington",
    "sg:classifiers":[
        {
            "category":"Autos & Motor Vehicles",
            "subcategory":"Automobile Sales",
            "type":"Retail Goods"
        }
    ],
    "sg:phone":"+1   ",
    "sg:postcode":"06790",
    "sg:province":"CT",
    "sg:tags":[
        "car",
        "used",
        "general",
        "repair"
    ],
    "wof:name":"Rocket Motor Sales",
    "wof:placetype":"venue"
},
  "geometry": {"coordinates":[-73.111666,41.826845],"type":"Point"}
}