{
  "type": "Feature",
  "properties": {
    "iso:country":"US",
    "sg:address":"5 Dusty Ln",
    "sg:city":"Newtown",
    "sg:classifiers":[
        {
            "category":"Building & Trades",
            "subcategory":"Construction",
            "type":"Services"
        }
    ],
    "sg:phone":"+1 203 270 1310",
    "sg:postcode":"06470",
    "sg:province":"CT",
    "sg:tags":[
        "general",
        "contractor"
    ],
    "wof:name":"Spath Construction Co Inc",
    "wof:placetype":"venue"
},
  "geometry": {"coordinates":[-73.264139,41.366136],"type":"Point"}
}