{
  "type": "Feature",
  "properties": {
    "iso:country":"US",
    "sg:address":"500 Washington Ave",
    "sg:city":"North Haven",
    "sg:classifiers":[
        {
            "category":"Insurance",
            "subcategory":"Insurance Agent",
            "type":"Services"
        }
    ],
    "sg:phone":"+1 203 234 8178",
    "sg:postcode":"06473",
    "sg:province":"CT",
    "wof:name":"Paris Group",
    "wof:placetype":"venue"
},
  "geometry": {"coordinates":[-72.840603,41.416779],"type":"Point"}
}