{
  "type": "Feature",
  "properties": {
    "addr:full":"495 Union St Waterbury CT 06706",
    "addr:housenumber":"495",
    "addr:postcode":"06706",
    "addr:street":"Union St Waterbury Ct",
    "iso:country":"US",
    "sg:address":"495 Union St",
    "sg:city":"Waterbury",
    "sg:classifiers":[
        {
            "category":"Professional",
            "subcategory":"Accounting & Tax Preparation",
            "type":"Services"
        }
    ],
    "sg:phone":"+1 203 756 1160",
    "sg:postcode":"06706",
    "sg:province":"CT",
    "sg:tags":[
        "return",
        "filing"
    ],
    "wof:name":"H & R Block Tax Svc",
    "wof:placetype":"venue"
},
  "geometry": {"coordinates":[-73.02631100000001,41.546187],"type":"Point"}
}