{
  "type": "Feature",
  "properties": {
    "addr:full":"34 Smith St Norwalk CT 06851",
    "addr:housenumber":"34",
    "addr:postcode":"06851",
    "addr:street":"Smith St",
    "iso:country":"US",
    "sg:address":"34 Smith St",
    "sg:city":"Norwalk",
    "sg:classifiers":[
        {
            "category":"Building & Trades",
            "subcategory":"Landscaping Services",
            "type":"Services"
        }
    ],
    "sg:phone":"+1 203 438 8206",
    "sg:postcode":"06851",
    "sg:province":"CT",
    "wof:name":"Savatree",
    "wof:placetype":"venue"
},
  "geometry": {"coordinates":[-73.410569,41.117902],"type":"Point"}
}