{
  "type": "Feature",
  "properties": {
    "iso:country":"US",
    "sg:address":"27 Driftway Point Rd",
    "sg:city":"Danbury",
    "sg:classifiers":[
        {
            "category":"Personal",
            "type":"Services"
        }
    ],
    "sg:phone":"+1 203 798 7170",
    "sg:postcode":"06811",
    "sg:province":"CT",
    "sg:tags":[
        "program",
        "physical",
        "exercise",
        "fitness"
    ],
    "wof:name":"Ladies Workout Express",
    "wof:placetype":"venue"
},
  "geometry": {"coordinates":[-73.513316,41.404958],"type":"Point"}
}