{
  "type": "Feature",
  "properties": {
    "iso:country":"US",
    "sg:address":"50 Albany Tpke",
    "sg:city":"Canton",
    "sg:classifiers":[
        {
            "category":"Building & Trades",
            "subcategory":"Construction",
            "type":"Services"
        }
    ],
    "sg:phone":"+1 860 693 9464",
    "sg:postcode":"06019",
    "sg:province":"CT",
    "sg:tags":[
        "contractor"
    ],
    "wof:name":"Whitehawk Construction Services",
    "wof:placetype":"venue"
},
  "geometry": {"coordinates":[-72.875944,41.822822],"type":"Point"}
}