{
  "type": "Feature",
  "properties": {
    "iso:country":"US",
    "sg:address":"384 State St",
    "sg:city":"North Haven",
    "sg:classifiers":[
        {
            "category":"Retail",
            "subcategory":"Auto Repair",
            "type":"Services"
        }
    ],
    "sg:phone":"+1 203 288 5867",
    "sg:postcode":"06473",
    "sg:province":"CT",
    "sg:tags":[
        "repairing",
        "automobile"
    ],
    "wof:name":"Select Auto Svc-Mobil Gas",
    "wof:placetype":"venue"
},
  "geometry": {"coordinates":[-72.88742499999999,41.364785],"type":"Point"}
}