{
  "type": "Feature",
  "properties": {
    "iso:country":"US",
    "sg:address":"131 Tremont St",
    "sg:city":"Hartford",
    "sg:classifiers":[
        {
            "category":"Travel",
            "subcategory":"Hotels & Motels",
            "type":"Entertainment"
        }
    ],
    "sg:phone":"+1   ",
    "sg:postcode":"06105",
    "sg:province":"CT",
    "sg:tags":[
        "hostel"
    ],
    "wof:name":"Mark Twain Hostel Inc",
    "wof:placetype":"venue"
},
  "geometry": {"coordinates":[-72.71268600000001,41.767641],"type":"Point"}
}