{
  "type": "Feature",
  "properties": {
    "addr:full":"14 Daventry Hill Ln Suffield CT 06078",
    "addr:housenumber":"14",
    "addr:postcode":"06078",
    "addr:street":"Daventry Hill Ln Suffield Ct",
    "iso:country":"US",
    "sg:address":"14 Daventry Hill Ln",
    "sg:city":"Suffield",
    "sg:classifiers":[
        {
            "category":"Banks & Credit Unions",
            "subcategory":"Investment Brokerage",
            "type":"Services"
        }
    ],
    "sg:phone":"+1 860 668 1881",
    "sg:postcode":"06078",
    "sg:province":"CT",
    "sg:tags":[
        "advisory"
    ],
    "wof:name":"Strategic Financial Growth LLC",
    "wof:placetype":"venue"
},
  "geometry": {"coordinates":[-72.610851,41.990001],"type":"Point"}
}