{
  "type": "Feature",
  "properties": {
    "addr:full":"65 Bainton Rd Hartford CT 06117",
    "addr:housenumber":"65",
    "addr:postcode":"06117",
    "addr:street":"Bainton Rd",
    "iso:country":"US",
    "sg:address":"65 Bainton Rd",
    "sg:city":"Hartford",
    "sg:classifiers":[
        {
            "category":"Shopping",
            "subcategory":"Computers & Home Electronics",
            "type":"Retail Goods"
        }
    ],
    "sg:phone":"+1 860 233 3236",
    "sg:postcode":"06117",
    "sg:province":"CT",
    "wof:name":"Camco Computers",
    "wof:placetype":"venue"
},
  "geometry": {"coordinates":[-72.717921,41.783028],"type":"Point"}
}