{
  "type": "Feature",
  "properties": {
    "addr:full":"1187 Highland Ave Cheshire CT 06410",
    "addr:housenumber":"1187",
    "addr:postcode":"06410",
    "addr:street":"Highland Ave",
    "iso:country":"US",
    "sg:address":"1187 Highland Ave",
    "sg:city":"Cheshire",
    "sg:classifiers":[
        {
            "category":"Manufacturing",
            "subcategory":"Apparel",
            "type":"Manufacturing & Wholesale Goods"
        }
    ],
    "sg:phone":"+1 203 271 1880",
    "sg:postcode":"06410",
    "sg:province":"CT",
    "sg:tags":[
        "closet",
        "accessory"
    ],
    "wof:name":"Closets Inc",
    "wof:placetype":"venue"
},
  "geometry": {"coordinates":[-72.894687,41.53233],"type":"Point"}
}