{
  "type": "Feature",
  "properties": {
    "addr:full":"30 Tory Pl Wilton CT 06897",
    "addr:housenumber":"30",
    "addr:postcode":"06897",
    "addr:street":"Tory Pl",
    "iso:country":"US",
    "sg:address":"30 Tory Pl",
    "sg:city":"Wilton",
    "sg:classifiers":[
        {
            "category":"Shopping",
            "subcategory":"Pharmacy",
            "type":"Retail Goods"
        }
    ],
    "sg:phone":"+1 203 762 0518",
    "sg:postcode":"06897",
    "sg:province":"CT",
    "wof:name":"Chauncey O Johnstone",
    "wof:placetype":"venue"
},
  "geometry": {"coordinates":[-73.44913200000001,41.163857],"type":"Point"}
}