{
  "type": "Feature",
  "properties": {
    "addr:full":"24C Woodward Rd Brooklyn CT 06234",
    "addr:housenumber":"24c",
    "addr:postcode":"06234",
    "addr:street":"Woodward Rd",
    "iso:country":"US",
    "sg:address":"24C Woodward Rd",
    "sg:city":"Brooklyn",
    "sg:classifiers":[
        {
            "category":"Building & Trades",
            "subcategory":"Pest Control",
            "type":"Services"
        }
    ],
    "sg:phone":"+1 401 227 4659",
    "sg:postcode":"06234",
    "sg:province":"CT",
    "sg:website":"http://national.citysearch.com/profile/external/649899240/brooklyn_ct/pioneer_wildlife_services_inc_.html?publisher=yellowpages&reference_id=7&placement=ypwebsitemip",
    "wof:name":"Pioneer Wildlife Services Inc.",
    "wof:placetype":"venue"
},
  "geometry": {"coordinates":[-71.980688,41.803612],"type":"Point"}
}