{
  "type": "Feature",
  "properties": {
    "addr:full":"74 Chester Main Rd North Stonington CT 06359",
    "addr:housenumber":"74",
    "addr:postcode":"06359",
    "addr:street":"Chester Main Rd North Stonington Ct",
    "iso:country":"US",
    "sg:address":"74 Chester Main Rd",
    "sg:city":"North Stonington",
    "sg:classifiers":[
        {
            "category":"Manufacturing",
            "subcategory":"Food",
            "type":"Manufacturing & Wholesale Goods"
        }
    ],
    "sg:phone":"+1 860 535 0202",
    "sg:postcode":"06359",
    "sg:province":"CT",
    "sg:tags":[
        "mfg",
        "wine"
    ],
    "wof:name":"Edwards Jonathan Winery",
    "wof:placetype":"venue"
},
  "geometry": {"coordinates":[-71.87445099999999,41.464858],"type":"Point"}
}