{
  "type": "Feature",
  "properties": {
    "addr:full":"252 Main St Old Saybrook CT 06475",
    "addr:housenumber":"252",
    "addr:postcode":"06475",
    "addr:street":"Main St",
    "iso:country":"US",
    "sg:address":"252 Main St",
    "sg:city":"Old Saybrook",
    "sg:classifiers":[
        {
            "category":"Shopping",
            "subcategory":"Jewelry",
            "type":"Retail Goods"
        }
    ],
    "sg:phone":"+1 860 510 0369",
    "sg:postcode":"06475",
    "sg:province":"CT",
    "wof:name":"A Silver Lining",
    "wof:placetype":"venue"
},
  "geometry": {"coordinates":[-72.37660200000001,41.2925],"type":"Point"}
}