{
  "type": "Feature",
  "properties": {
    "addr:full":"670 Prospect Ave Hartford CT 06105",
    "addr:housenumber":"670",
    "addr:postcode":"06105",
    "addr:street":"Prospect Ave;Ct",
    "iso:country":"US",
    "sg:address":"670 Prospect Ave",
    "sg:city":"Hartford",
    "sg:classifiers":[
        {
            "category":"Professional",
            "subcategory":"Advertising",
            "type":"Services"
        }
    ],
    "sg:phone":"+1   ",
    "sg:postcode":"06105",
    "sg:province":"CT",
    "sg:tags":[
        "agency"
    ],
    "wof:name":"Jonathan & Williams Advg",
    "wof:placetype":"venue"
},
  "geometry": {"coordinates":[-72.7161,41.766105],"type":"Point"}
}