{
  "type": "Feature",
  "properties": {
    "iso:country":"US",
    "sg:address":"1147 Madison Ave",
    "sg:city":"Bridgeport",
    "sg:classifiers":[
        {
            "category":"Restaurant",
            "type":"Food & Drink"
        }
    ],
    "sg:phone":"+1 203 334 1867",
    "sg:postcode":"06606",
    "sg:province":"CT",
    "sg:tags":[
        "caterer"
    ],
    "wof:name":"Smeraglino's Catering",
    "wof:placetype":"venue"
},
  "geometry": {"coordinates":[-73.20732,41.19605],"type":"Point"}
}