{
  "type": "Feature",
  "properties": {
    "iso:country":"US",
    "sg:address":"200 Fairfax Dr",
    "sg:city":"Stratford",
    "sg:classifiers":[
        {
            "category":"Wholesale",
            "subcategory":"Hardware",
            "type":"Manufacturing & Wholesale Goods"
        }
    ],
    "sg:phone":"+1 203 380 1007",
    "sg:postcode":"06614",
    "sg:province":"CT",
    "sg:tags":[
        "purifying",
        "cleaning",
        "air"
    ],
    "wof:name":"Breath Of Life Inc",
    "wof:placetype":"venue"
},
  "geometry": {"coordinates":[-73.145022,41.229996],"type":"Point"}
}