{
  "type": "Feature",
  "properties": {
    "addr:full":"535 Boston Post Rd Orange CT 06477",
    "addr:housenumber":"535",
    "addr:postcode":"06477",
    "addr:street":"Boston Post Rd",
    "iso:country":"US",
    "sg:address":"535 Boston Post Rd",
    "sg:city":"Orange",
    "sg:classifiers":[
        {
            "category":"Home & Garden",
            "subcategory":"Home Furnishings",
            "type":"Retail Goods"
        }
    ],
    "sg:phone":"+1 203 795 3832",
    "sg:postcode":"06477",
    "sg:province":"CT",
    "sg:tags":[
        "pottery"
    ],
    "wof:name":"Melting Pot",
    "wof:placetype":"venue"
},
  "geometry": {"coordinates":[-73.01317299999999,41.257605],"type":"Point"}
}