{
  "type": "Feature",
  "properties": {
    "addr:full":"66 South St Danbury CT 06810",
    "addr:housenumber":"66",
    "addr:postcode":"06810",
    "addr:street":"South St",
    "iso:country":"US",
    "sg:address":"66 South St",
    "sg:city":"Danbury",
    "sg:classifiers":[
        {
            "category":"Local Transit",
            "type":"Transportation"
        }
    ],
    "sg:phone":"+1 203 743 0324",
    "sg:postcode":"06810",
    "sg:province":"CT",
    "sg:tags":[
        "limousine"
    ],
    "wof:name":"Advanced Luxury Limos",
    "wof:placetype":"venue"
},
  "geometry": {"coordinates":[-73.432727,41.388124],"type":"Point"}
}