{
  "type": "Feature",
  "properties": {
    "addr:full":"235 Church St New Haven CT 06510",
    "addr:housenumber":"235",
    "addr:postcode":"06510",
    "addr:street":"Church St",
    "iso:country":"US",
    "sg:address":"235 Church St",
    "sg:city":"New Haven",
    "sg:classifiers":[
        {
            "category":"Education",
            "subcategory":"Library",
            "type":"Public Place"
        }
    ],
    "sg:phone":"+1 203 503 6828",
    "sg:postcode":"06510",
    "sg:province":"CT",
    "sg:tags":[
        "special",
        "interest"
    ],
    "wof:name":"State Law Library",
    "wof:placetype":"venue"
},
  "geometry": {"coordinates":[-72.92259300000001,41.310174],"type":"Point"}
}