{
  "type": "Feature",
  "properties": {
    "addr:full":"107 Danbury Rd Ridgefield CT 06877",
    "addr:housenumber":"107",
    "addr:postcode":"06877",
    "addr:street":"Danbury Rd",
    "iso:country":"US",
    "sg:address":"107 Danbury Rd",
    "sg:city":"Ridgefield",
    "sg:classifiers":[
        {
            "category":"Personal",
            "subcategory":"Beauty Salon",
            "type":"Services"
        }
    ],
    "sg:phone":"+1 203 431 9406",
    "sg:postcode":"06877",
    "sg:province":"CT",
    "sg:tags":[
        "shop"
    ],
    "wof:name":"Di Maggio Hair Design",
    "wof:placetype":"venue"
},
  "geometry": {"coordinates":[-73.493359,41.29265],"type":"Point"}
}