{
  "type": "Feature",
  "properties": {
    "addr:full":"788 Amity Rd Bethany CT 06524",
    "addr:housenumber":"788",
    "addr:postcode":"06524",
    "addr:street":"Amity Rd Bethany Ct",
    "iso:country":"US",
    "sg:address":"788 Amity Rd",
    "sg:city":"Bethany",
    "sg:classifiers":[
        {
            "category":"Organizations",
            "subcategory":"Membership Organization",
            "type":"Services"
        }
    ],
    "sg:phone":"+1   ",
    "sg:postcode":"06524",
    "sg:province":"CT",
    "wof:name":"Connecticut Humane Society",
    "wof:placetype":"venue"
},
  "geometry": {"coordinates":[-72.990555,41.441009],"type":"Point"}
}