{
  "type": "Feature",
  "properties": {
    "addr:full":"380 Whitney Ave New Haven CT 06511",
    "addr:housenumber":"380",
    "addr:postcode":"06511",
    "addr:street":"Whitney Ave",
    "iso:country":"US",
    "sg:address":"380 Whitney Ave",
    "sg:city":"New Haven",
    "sg:classifiers":[
        {
            "category":"Utilities",
            "subcategory":"Mobile Phone",
            "type":"Services"
        }
    ],
    "sg:phone":"+1 203 754 8902",
    "sg:postcode":"06511",
    "sg:province":"CT",
    "sg:tags":[
        "communication",
        "radiotelephone"
    ],
    "wof:name":"Beep First USA",
    "wof:placetype":"venue"
},
  "geometry": {"coordinates":[-72.918274,41.320978],"type":"Point"}
}