{
  "type": "Feature",
  "properties": {
    "iso:country":"US",
    "sg:address":"25 Court St",
    "sg:city":"New Britain",
    "sg:classifiers":[
        {
            "category":"Professional",
            "subcategory":"Lawyer & Legal Services",
            "type":"Services"
        }
    ],
    "sg:phone":"+1   ",
    "sg:postcode":"06051",
    "sg:province":"CT",
    "wof:name":"Friedle Gary A",
    "wof:placetype":"venue"
},
  "geometry": {"coordinates":[-72.783889,41.666513],"type":"Point"}
}