{
  "type": "Feature",
  "properties": {
    "iso:country":"US",
    "sg:address":"31 E Putnam Ave",
    "sg:city":"Cos Cob",
    "sg:classifiers":[
        {
            "category":"Restaurant",
            "type":"Food & Drink"
        }
    ],
    "sg:menulink":"http://www.allmenus.com/ct/greenwich/25419-landmark-diner/menu/",
    "sg:phone":"+1 203 869 0954",
    "sg:postcode":"06807",
    "sg:province":"CT",
    "sg:tags":[
        "american",
        "diner"
    ],
    "wof:name":"Landmark Diner",
    "wof:placetype":"venue"
},
  "geometry": {"coordinates":[-73.60400300000001,41.036688],"type":"Point"}
}