{
  "type": "Feature",
  "properties": {
    "addr:full":"245 Long Close Rd Stamford CT 06902",
    "addr:housenumber":"245",
    "addr:postcode":"06902",
    "addr:street":"Long Close Rd",
    "iso:country":"US",
    "sg:address":"245 Long Close Rd",
    "sg:city":"Stamford",
    "sg:classifiers":[
        {
            "category":"Professional",
            "subcategory":"Management & Consulting",
            "type":"Services"
        }
    ],
    "sg:phone":"+1   ",
    "sg:postcode":"06902",
    "sg:province":"CT",
    "wof:name":"Lbg Assoc",
    "wof:placetype":"venue"
},
  "geometry": {"coordinates":[-73.575565,41.083252],"type":"Point"}
}