{
  "type": "Feature",
  "properties": {
    "addr:full":"3 Arlene Ct Beacon Falls CT 06403",
    "addr:housenumber":"3",
    "addr:postcode":"06403",
    "addr:street":"Arlene Ct;Falls Ct",
    "iso:country":"US",
    "sg:address":"3 Arlene Ct",
    "sg:city":"Beacon Falls",
    "sg:classifiers":[
        {
            "category":"Building & Trades",
            "subcategory":"Landscaping Services",
            "type":"Services"
        }
    ],
    "sg:phone":"+1 203 881 1491",
    "sg:postcode":"06403",
    "sg:province":"CT",
    "wof:name":"Schryvers Tree Lawn Care",
    "wof:placetype":"venue"
},
  "geometry": {"coordinates":[-73.084816,41.414469],"type":"Point"}
}