{
  "type": "Feature",
  "properties": {
    "iso:country":"US",
    "sg:address":"1013 Weid Dr",
    "sg:city":"Naugatuck",
    "sg:classifiers":[
        {
            "category":"Real Estate",
            "subcategory":"Real Estate Agent",
            "type":"Services"
        }
    ],
    "sg:phone":"+1 203 729 0508",
    "sg:postcode":"06770",
    "sg:province":"CT",
    "sg:tags":[
        "authorities",
        "housing"
    ],
    "wof:name":"George B Lewis B2 Project",
    "wof:placetype":"venue"
},
  "geometry": {"coordinates":[-73.031992,41.469818],"type":"Point"}
}