{
  "type": "Feature",
  "properties": {
    "addr:full":"172 Joffre Ave Stamford CT 06905",
    "addr:housenumber":"172",
    "addr:postcode":"06905",
    "addr:street":"Joffre Ave",
    "iso:country":"US",
    "sg:address":"172 Joffre Ave",
    "sg:city":"Stamford",
    "sg:classifiers":[
        {
            "category":"Shopping",
            "subcategory":"Computers & Home Electronics",
            "type":"Retail Goods"
        }
    ],
    "sg:phone":"+1 203 357 9567",
    "sg:postcode":"06905",
    "sg:province":"CT",
    "sg:tags":[
        "software"
    ],
    "wof:name":"BMS Technology Svc",
    "wof:placetype":"venue"
},
  "geometry": {"coordinates":[-73.527687,41.083465],"type":"Point"}
}