{
  "type": "Feature",
  "properties": {
    "addr:full":"24 Cheney Rd Marlborough CT 06447",
    "addr:housenumber":"24",
    "addr:postcode":"06447",
    "addr:street":"Cheney Rd Marlborough Ct",
    "iso:country":"US",
    "sg:address":"24 Cheney Rd",
    "sg:city":"Marlborough",
    "sg:classifiers":[
        {
            "category":"Organizations",
            "subcategory":"Religious Organization",
            "type":"Services"
        }
    ],
    "sg:phone":"+1   ",
    "sg:postcode":"06447",
    "sg:province":"CT",
    "wof:name":"St John Fisher Rectory",
    "wof:placetype":"venue"
},
  "geometry": {"coordinates":[-72.463246,41.636173],"type":"Point"}
}