{
  "type": "Feature",
  "properties": {
    "addr:full":"25 Cliff St Norwalk CT 06854",
    "addr:housenumber":"25",
    "addr:postcode":"06854",
    "addr:street":"Cliff St",
    "iso:country":"US",
    "sg:address":"25 Cliff St",
    "sg:city":"Norwalk",
    "sg:classifiers":[
        {
            "category":"Organizations",
            "subcategory":"Religious Organization",
            "type":"Services"
        }
    ],
    "sg:phone":"+1 203 866 1867",
    "sg:postcode":"06854",
    "sg:province":"CT",
    "sg:tags":[
        "church"
    ],
    "wof:name":"Saint Ladislaus Church",
    "wof:placetype":"venue"
},
  "geometry": {"coordinates":[-73.428809,41.092766],"type":"Point"}
}