{
  "type": "Feature",
  "properties": {
    "iso:country":"US",
    "sg:address":"3 Newfane Rd",
    "sg:city":"New Fairfield",
    "sg:classifiers":[
        {
            "category":"Professional",
            "subcategory":"Management & Consulting",
            "type":"Services"
        }
    ],
    "sg:phone":"+1   ",
    "sg:postcode":"06812",
    "sg:province":"CT",
    "sg:tags":[
        "business"
    ],
    "wof:name":"Blue Gold Consulting Inc",
    "wof:placetype":"venue"
},
  "geometry": {"coordinates":[-73.533985,41.453085],"type":"Point"}
}