{
  "type": "Feature",
  "properties": {
    "addr:full":"21 Kenilworth Ter Greenwich CT 06830",
    "addr:housenumber":"21",
    "addr:postcode":"06830",
    "addr:street":"Kenilworth Ter Greenwich Ct",
    "iso:country":"US",
    "sg:address":"21 Kenilworth Ter",
    "sg:city":"Greenwich",
    "sg:classifiers":[
        {
            "category":"Professional",
            "type":"Services"
        }
    ],
    "sg:phone":"+1 203 661 4561",
    "sg:postcode":"06830",
    "sg:province":"CT",
    "wof:name":"Personal Pro Incorporated",
    "wof:placetype":"venue"
},
  "geometry": {"coordinates":[-73.619338,41.050074],"type":"Point"}
}