{
  "type": "Feature",
  "properties": {
    "iso:country":"US",
    "sg:address":"470 Lewis Ave",
    "sg:city":"Meriden",
    "sg:classifiers":[
        {
            "category":"Home & Garden",
            "subcategory":"Furniture",
            "type":"Retail Goods"
        }
    ],
    "sg:phone":"+1 203 630 1440",
    "sg:postcode":"06451",
    "sg:province":"CT",
    "wof:name":"Total Home",
    "wof:placetype":"venue"
},
  "geometry": {"coordinates":[-72.803605,41.550627],"type":"Point"}
}