{
  "type": "Feature",
  "properties": {
    "addr:full":"51 Wells Rd Hartford CT 06107",
    "addr:housenumber":"51",
    "addr:postcode":"06107",
    "addr:street":"Wells Rd",
    "iso:country":"US",
    "sg:address":"51 Wells Rd",
    "sg:city":"Hartford",
    "sg:classifiers":[
        {
            "category":"Communications",
            "subcategory":"Film & Video Production",
            "type":"Services"
        }
    ],
    "sg:phone":"+1   ",
    "sg:postcode":"06107",
    "sg:province":"CT",
    "sg:tags":[
        "television",
        "or"
    ],
    "wof:name":"Boyd Productions",
    "wof:placetype":"venue"
},
  "geometry": {"coordinates":[-72.754586,41.760472],"type":"Point"}
}