{
  "type": "Feature",
  "properties": {
    "addr:full":"1040 Long Cove Rd Gales Ferry CT 06335",
    "addr:housenumber":"1040",
    "addr:postcode":"06335",
    "addr:street":"Long Cove Rd Gales Ferry Ct",
    "iso:country":"US",
    "sg:address":"1040 Long Cove Rd",
    "sg:city":"Gales Ferry",
    "sg:classifiers":[
        {
            "category":"Professional",
            "subcategory":"Lawyer & Legal Services",
            "type":"Services"
        }
    ],
    "sg:phone":"+1   ",
    "sg:postcode":"06335",
    "sg:province":"CT",
    "wof:name":"Johnson Law Offices LLC",
    "wof:placetype":"venue"
},
  "geometry": {"coordinates":[-72.076542,41.409196],"type":"Point"}
}