{
  "type": "Feature",
  "properties": {
    "iso:country":"US",
    "sg:address":"69 Dyke Ln",
    "sg:city":"Stamford",
    "sg:classifiers":[
        {
            "category":"Organizations",
            "subcategory":"Community Association",
            "type":"Services"
        }
    ],
    "sg:phone":"+1 203 353 8017",
    "sg:postcode":"06902",
    "sg:province":"CT",
    "sg:tags":[
        "environmental",
        "org"
    ],
    "wof:name":"Soundwaters Inc",
    "wof:placetype":"venue"
},
  "geometry": {"coordinates":[-73.540414,41.038309],"type":"Point"}
}