{
  "type": "Feature",
  "properties": {
    "iso:country":"US",
    "sg:address":"30 Pepperidge Rd",
    "sg:city":"Monroe",
    "sg:classifiers":[
        {
            "category":"Building & Trades",
            "subcategory":"Landscaping Services",
            "type":"Services"
        }
    ],
    "sg:phone":"+1 203 445 0219",
    "sg:postcode":"06468",
    "sg:province":"CT",
    "sg:tags":[
        "landscape"
    ],
    "wof:name":"Ernandos Landscaping",
    "wof:placetype":"venue"
},
  "geometry": {"coordinates":[-73.21242100000001,41.313893],"type":"Point"}
}