{
  "type": "Feature",
  "properties": {
    "addr:full":"1089 Post Rd Darien CT 06820",
    "addr:housenumber":"1089",
    "addr:postcode":"06820",
    "addr:street":"Post Rd",
    "iso:country":"US",
    "sg:address":"1089 Post Rd",
    "sg:city":"Darien",
    "sg:classifiers":[
        {
            "category":"Shopping",
            "subcategory":"Used Merchandise",
            "type":"Retail Goods"
        }
    ],
    "sg:phone":"+1 203 655 5439",
    "sg:postcode":"06820",
    "sg:province":"CT",
    "sg:tags":[
        "shop",
        "consignment"
    ],
    "wof:name":"Roundabout Designer Cnsgnmnts",
    "wof:placetype":"venue"
},
  "geometry": {"coordinates":[-73.473961,41.073646],"type":"Point"}
}