{
  "type": "Feature",
  "properties": {
    "iso:country":"US",
    "sg:address":"4 Deer Run Trl",
    "sg:city":"Danbury",
    "sg:classifiers":[
        {
            "category":"Building & Trades",
            "subcategory":"Cleaning & Sanitation",
            "type":"Services"
        }
    ],
    "sg:phone":"+1   ",
    "sg:postcode":"06811",
    "sg:province":"CT",
    "sg:tags":[
        "maintenance"
    ],
    "wof:name":"Helena Cleaning Service",
    "wof:placetype":"venue"
},
  "geometry": {"coordinates":[-73.432002,41.438083],"type":"Point"}
}