{
  "type": "Feature",
  "properties": {
    "addr:full":"18 Central Ave Norwich CT 06360",
    "addr:housenumber":"18",
    "addr:postcode":"06360",
    "addr:street":"Central Ave",
    "iso:country":"US",
    "sg:address":"18 Central Ave",
    "sg:city":"Norwich",
    "sg:classifiers":[
        {
            "category":"Retail",
            "subcategory":"Repair Shop",
            "type":"Services"
        }
    ],
    "sg:phone":"+1   ",
    "sg:postcode":"06360",
    "sg:province":"CT",
    "sg:tags":[
        "stripping",
        "furniture"
    ],
    "wof:name":"Erics Furniture Restorations",
    "wof:placetype":"venue"
},
  "geometry": {"coordinates":[-72.06193,41.52858],"type":"Point"}
}