{
  "type": "Feature",
  "properties": {
    "iso:country":"US",
    "sg:address":"275 Orange St",
    "sg:city":"New Haven",
    "sg:classifiers":[
        {
            "category":"Shopping",
            "type":"Retail Goods"
        }
    ],
    "sg:phone":"+1 203 752 1871",
    "sg:postcode":"06510",
    "sg:province":"CT",
    "sg:tags":[
        "ice"
    ],
    "wof:name":"Disney On Ice",
    "wof:placetype":"venue"
},
  "geometry": {"coordinates":[-72.92262100000001,41.307584],"type":"Point"}
}