{
  "type": "Feature",
  "properties": {
    "addr:full":"525 Wolcott St Waterbury CT 06705",
    "addr:housenumber":"525",
    "addr:postcode":"06705",
    "addr:street":"Wolcott St Waterbury Ct",
    "iso:country":"US",
    "sg:address":"525 Wolcott St",
    "sg:city":"Waterbury",
    "sg:classifiers":[
        {
            "category":"Professional",
            "subcategory":"Business Services",
            "type":"Services"
        }
    ],
    "sg:phone":"+1   ",
    "sg:postcode":"06705",
    "sg:province":"CT",
    "wof:name":"R G I S Inventory Specialists",
    "wof:placetype":"venue"
},
  "geometry": {"coordinates":[-73.013721,41.556584],"type":"Point"}
}