{
  "type": "Feature",
  "properties": {
    "iso:country":"US",
    "sg:address":"955 High Ridge Rd",
    "sg:city":"Stamford",
    "sg:classifiers":[
        {
            "category":"Home & Garden",
            "subcategory":"Furniture",
            "type":"Retail Goods"
        }
    ],
    "sg:phone":"+1 203 968 1507",
    "sg:postcode":"06905",
    "sg:province":"CT",
    "wof:name":"Sleepys Mattress Professional",
    "wof:placetype":"venue"
},
  "geometry": {"coordinates":[-73.548007,41.106253],"type":"Point"}
}