{
  "type": "Feature",
  "properties": {
    "addr:full":"59 Post Rd E Westport CT 06880",
    "addr:housenumber":"59",
    "addr:postcode":"06880",
    "addr:street":"Post Rd E Westport Ct",
    "iso:country":"US",
    "sg:address":"59 Post Rd E",
    "sg:city":"Westport",
    "sg:classifiers":[
        {
            "category":"Organizations",
            "subcategory":"Community Association",
            "type":"Services"
        },
        {
            "category":"Recreation",
            "type":"Entertainment"
        }
    ],
    "sg:phone":"+1 203 226 8981",
    "sg:postcode":"06880",
    "sg:province":"CT",
    "sg:tags":[
        "camps-recreational"
    ],
    "sg:website":"http://www.westporty.org",
    "wof:name":"Westport Weston Family Y",
    "wof:placetype":"venue"
},
  "geometry": {"coordinates":[-73.365645,41.139038],"type":"Point"}
}