{
  "type": "Feature",
  "properties": {
    "addr:full":"12 Hunt Ter Greenwich CT 06831",
    "addr:housenumber":"12",
    "addr:postcode":"06831",
    "addr:street":"Hunt Ter Greenwich Ct",
    "iso:country":"US",
    "sg:address":"12 Hunt Ter",
    "sg:city":"Greenwich",
    "sg:classifiers":[
        {
            "category":"Building & Trades",
            "subcategory":"Equipment Rental",
            "type":"Services"
        }
    ],
    "sg:phone":"+1   ",
    "sg:postcode":"06831",
    "sg:province":"CT",
    "wof:name":"Areomarine Charters",
    "wof:placetype":"venue"
},
  "geometry": {"coordinates":[-73.669809,41.033458],"type":"Point"}
}