{
  "type": "Feature",
  "properties": {
    "iso:country":"US",
    "sg:address":"269 Mountain Rd",
    "sg:city":"Hartford",
    "sg:classifiers":[
        {
            "category":"Real Estate",
            "subcategory":"Developer",
            "type":"Services"
        }
    ],
    "sg:phone":"+1 860 521 0122",
    "sg:postcode":"06107",
    "sg:province":"CT",
    "sg:tags":[
        "company",
        "investment"
    ],
    "wof:name":"Pdpa Inc",
    "wof:placetype":"venue"
},
  "geometry": {"coordinates":[-72.76553,41.762471],"type":"Point"}
}