{
  "type": "Feature",
  "properties": {
    "iso:country":"US",
    "sg:address":"359 Litchfield Rd",
    "sg:city":"New Milford",
    "sg:classifiers":[
        {
            "category":"Government",
            "subcategory":"Fire Station",
            "type":"Public Place"
        }
    ],
    "sg:phone":"+1 860 354 8194",
    "sg:postcode":"06776",
    "sg:province":"CT",
    "sg:tags":[
        "protection"
    ],
    "wof:name":"Northville Fire Department",
    "wof:placetype":"venue"
},
  "geometry": {"coordinates":[-73.39254,41.63213],"type":"Point"}
}