{
  "type": "Feature",
  "properties": {
    "addr:full":"71 Rhodes St New Britain CT 06051",
    "addr:housenumber":"71",
    "addr:postcode":"06051",
    "addr:street":"Rhodes St",
    "iso:country":"US",
    "sg:address":"71 Rhodes St",
    "sg:city":"New Britain",
    "sg:classifiers":[
        {
            "category":"Insurance",
            "subcategory":"Insurance Agent",
            "type":"Services"
        }
    ],
    "sg:phone":"+1 860 826 8939",
    "sg:postcode":"06051",
    "sg:province":"CT",
    "wof:name":"Long Term Care",
    "wof:placetype":"venue"
},
  "geometry": {"coordinates":[-72.763019,41.669717],"type":"Point"}
}