{
  "type": "Feature",
  "properties": {
    "addr:full":"502 Sawmill Rd West Haven CT 06516",
    "addr:housenumber":"502",
    "addr:postcode":"06516",
    "addr:street":"Sawmill Rd;Haven",
    "iso:country":"US",
    "sg:address":"502 Sawmill Rd",
    "sg:city":"West Haven",
    "sg:classifiers":[
        {
            "category":"Recreation",
            "type":"Entertainment"
        }
    ],
    "sg:phone":"+1   ",
    "sg:postcode":"06516",
    "sg:province":"CT",
    "wof:name":"Institute Mrtial Arts Melo LLC",
    "wof:placetype":"venue"
},
  "geometry": {"coordinates":[-72.97064899999999,41.273006],"type":"Point"}
}