{
  "type": "Feature",
  "properties": {
    "addr:full":"71 S Side Ter Wallingford CT 06492",
    "addr:housenumber":"71",
    "addr:postcode":"06492",
    "addr:street":"S Side Ter Wallingford Ct",
    "iso:country":"US",
    "sg:address":"71 S Side Ter",
    "sg:city":"Wallingford",
    "sg:classifiers":[
        {
            "category":"Restaurant",
            "type":"Food & Drink"
        }
    ],
    "sg:phone":"+1 203 269 8003",
    "sg:postcode":"06492",
    "sg:province":"CT",
    "sg:tags":[
        "catering"
    ],
    "wof:name":"Kniess Grmet Ctrers Wllingford",
    "wof:placetype":"venue"
},
  "geometry": {"coordinates":[-72.820722,41.442345],"type":"Point"}
}