{
  "type": "Feature",
  "properties": {
    "iso:country":"US",
    "sg:address":"21 Pershing St",
    "sg:city":"Hamden",
    "sg:classifiers":[
        {
            "category":"Wholesale",
            "subcategory":"Durable Goods & Equipment",
            "type":"Manufacturing & Wholesale Goods"
        }
    ],
    "sg:phone":"+1 203 288 5241",
    "sg:postcode":"06514",
    "sg:province":"CT",
    "sg:tags":[
        "representative",
        "manufacturer"
    ],
    "sg:website":"www.packtor.com",
    "wof:name":"Bernard M Packtor Co",
    "wof:placetype":"venue"
},
  "geometry": {"coordinates":[-72.928348,41.3549],"type":"Point"}
}