{
  "type": "Feature",
  "properties": {
    "iso:country":"US",
    "sg:address":"250 William St",
    "sg:city":"Middletown",
    "sg:classifiers":[
        {
            "category":"Retail",
            "subcategory":"Laundry & Dry Cleaning",
            "type":"Services"
        }
    ],
    "sg:phone":"+1   ",
    "sg:postcode":"06457",
    "sg:province":"CT",
    "sg:tags":[
        "drycleaning",
        "plant"
    ],
    "wof:name":"Forest City Cleaners & Ldrers",
    "wof:placetype":"venue"
},
  "geometry": {"coordinates":[-72.652798,41.55635],"type":"Point"}
}