{
  "type": "Feature",
  "properties": {
    "addr:full":"1786 Bedford St Stamford CT 06905",
    "addr:housenumber":"1786",
    "addr:postcode":"06905",
    "addr:street":"Bedford St",
    "iso:country":"US",
    "sg:address":"1786 Bedford St",
    "sg:city":"Stamford",
    "sg:classifiers":[
        {
            "category":"Professional",
            "subcategory":"Accounting & Tax Preparation",
            "type":"Services"
        }
    ],
    "sg:phone":"+1   ",
    "sg:postcode":"06905",
    "sg:province":"CT",
    "sg:tags":[
        "return"
    ],
    "wof:name":"John Stanise CPA PC",
    "wof:placetype":"venue"
},
  "geometry": {"coordinates":[-73.542041,41.065959],"type":"Point"}
}