{
  "type": "Feature",
  "properties": {
    "addr:full":"120 Myrtle Ave Stamford CT 06902",
    "addr:housenumber":"120",
    "addr:postcode":"06902",
    "addr:street":"Myrtle Ave",
    "iso:country":"US",
    "sg:address":"120 Myrtle Ave",
    "sg:city":"Stamford",
    "sg:classifiers":[
        {
            "category":"Retail",
            "subcategory":"Animal Services",
            "type":"Services"
        }
    ],
    "sg:phone":"+1 203 967 4949",
    "sg:postcode":"06902",
    "sg:province":"CT",
    "wof:name":"Cognetta Funeral Home",
    "wof:placetype":"venue"
},
  "geometry": {"coordinates":[-73.526689,41.051664],"type":"Point"}
}