{
  "type": "Feature",
  "properties": {
    "iso:country":"US",
    "sg:address":"300 Church St",
    "sg:city":"Wallingford",
    "sg:classifiers":[
        {
            "category":"Shopping",
            "type":"Retail Goods"
        }
    ],
    "sg:phone":"+1 203 949 1950",
    "sg:postcode":"06492",
    "sg:province":"CT",
    "sg:tags":[
        "hearing",
        "equipment",
        "supply",
        "impaired"
    ],
    "wof:name":"Precision Hearing Care",
    "wof:placetype":"venue"
},
  "geometry": {"coordinates":[-72.81982000000001,41.491485],"type":"Point"}
}