{
  "type": "Feature",
  "properties": {
    "iso:country":"US",
    "sg:address":"311 State Hwy 12",
    "sg:city":"Groton",
    "sg:classifiers":[
        {
            "category":"Real Estate",
            "subcategory":"Real Estate Agent",
            "type":"Services"
        }
    ],
    "sg:phone":"+1 860 445 8195",
    "sg:postcode":"06340",
    "sg:province":"CT",
    "sg:tags":[
        "manager"
    ],
    "wof:name":"Palmerone & Moriarty RE",
    "wof:placetype":"venue"
},
  "geometry": {"coordinates":[-72.07216699999999,41.371597],"type":"Point"}
}