{
  "type": "Feature",
  "properties": {
    "iso:country":"US",
    "sg:address":"1 Canal Path",
    "sg:city":"Farmington",
    "sg:classifiers":[
        {
            "category":"Shopping",
            "subcategory":"Jewelry",
            "type":"Retail Goods"
        }
    ],
    "sg:phone":"+1 860 676 1075",
    "sg:postcode":"06032",
    "sg:province":"CT",
    "wof:name":"Franklin Jewelers Inc",
    "wof:placetype":"venue"
},
  "geometry": {"coordinates":[-72.82602,41.727664],"type":"Point"}
}