{
  "type": "Feature",
  "properties": {
    "iso:country":"US",
    "sg:address":"143 W Main St",
    "sg:city":"Meriden",
    "sg:classifiers":[
        {
            "category":"Home & Garden",
            "subcategory":"Household Appliances",
            "type":"Retail Goods"
        }
    ],
    "sg:phone":"+1 203 440 2031",
    "sg:postcode":"06451",
    "sg:province":"CT",
    "wof:name":"Crazy Price",
    "wof:placetype":"venue"
},
  "geometry": {"coordinates":[-72.808111,41.538386],"type":"Point"}
}