{
  "type": "Feature",
  "properties": {
    "addr:full":"1 Center St Hartford CT 06109",
    "addr:housenumber":"1",
    "addr:postcode":"06109",
    "addr:street":"Center St",
    "iso:country":"US",
    "sg:address":"1 Center St",
    "sg:city":"Hartford",
    "sg:classifiers":[
        {
            "category":"Shopping",
            "subcategory":"Clothing, Apparel, & Fashions",
            "type":"Retail Goods"
        }
    ],
    "sg:phone":"+1 203 278 2502",
    "sg:postcode":"06109",
    "sg:province":"CT",
    "wof:name":"Caren Charles 661",
    "wof:placetype":"venue"
},
  "geometry": {"coordinates":[-72.656924,41.71188],"type":"Point"}
}