{
  "type": "Feature",
  "properties": {
    "iso:country":"US",
    "sg:address":"34 E Putnam Ave",
    "sg:city":"Greenwich",
    "sg:classifiers":[
        {
            "category":"Health Services",
            "subcategory":"Health Practitioner",
            "type":"Services"
        }
    ],
    "sg:phone":"+1   ",
    "sg:postcode":"06830",
    "sg:province":"CT",
    "wof:name":"Sandra Eagle Lcsw",
    "wof:placetype":"venue"
},
  "geometry": {"coordinates":[-73.62568899999999,41.032191],"type":"Point"}
}