{
  "type": "Feature",
  "properties": {
    "addr:full":"108 Valley Forge Rd Weston CT 06883",
    "addr:housenumber":"108",
    "addr:postcode":"06883",
    "addr:street":"Valley Forge Rd",
    "iso:country":"US",
    "sg:address":"108 Valley Forge Rd",
    "sg:city":"Weston",
    "sg:classifiers":[
        {
            "category":"Retail",
            "subcategory":"Veterinary Services",
            "type":"Services"
        }
    ],
    "sg:phone":"+1 203 227 8811",
    "sg:postcode":"06883",
    "sg:province":"CT",
    "wof:name":"Weston Animal Hospital",
    "wof:placetype":"venue"
},
  "geometry": {"coordinates":[-73.343187,41.240574],"type":"Point"}
}