{
  "type": "Feature",
  "properties": {
    "iso:country":"US",
    "sg:address":"28 Horse Heaven Rd",
    "sg:city":"Washington",
    "sg:classifiers":[
        {
            "category":"Professional",
            "type":"Services"
        }
    ],
    "sg:phone":"+1 860 868 3433",
    "sg:postcode":"06793",
    "sg:province":"CT",
    "wof:name":"Gary Wood",
    "wof:placetype":"venue"
},
  "geometry": {"coordinates":[-73.28462399999999,41.626808],"type":"Point"}
}