{
  "type": "Feature",
  "properties": {
    "addr:full":"135 Day St Newington CT 06111",
    "addr:housenumber":"135",
    "addr:postcode":"06111",
    "addr:street":"Day St",
    "iso:country":"US",
    "sg:address":"135 Day St",
    "sg:city":"Newington",
    "sg:classifiers":[
        {
            "category":"Building & Trades",
            "subcategory":"Construction",
            "type":"Services"
        }
    ],
    "sg:phone":"+1 860 665 7656",
    "sg:postcode":"06111",
    "sg:province":"CT",
    "sg:tags":[
        "roofing",
        "contractor",
        "sheet",
        "metal",
        "carpentry"
    ],
    "wof:name":"New Britain Roofing Company",
    "wof:placetype":"venue"
},
  "geometry": {"coordinates":[-72.733529,41.717443],"type":"Point"}
}