{
  "type": "Feature",
  "properties": {
    "addr:full":"7 Colony Rd East Lyme CT 06333",
    "addr:housenumber":"7",
    "addr:postcode":"06333",
    "addr:street":"Colony Rd East Lyme Ct",
    "iso:country":"US",
    "sg:address":"7 Colony Rd",
    "sg:city":"East Lyme",
    "sg:classifiers":[
        {
            "category":"Professional",
            "type":"Services"
        }
    ],
    "sg:phone":"+1   ",
    "sg:postcode":"06333",
    "sg:province":"CT",
    "wof:name":"Quality Program Services LLC",
    "wof:placetype":"venue"
},
  "geometry": {"coordinates":[-72.215266,41.38251],"type":"Point"}
}