{
  "type": "Feature",
  "properties": {
    "addr:full":"280 Elm St New Canaan NY 06840",
    "addr:housenumber":"280",
    "addr:postcode":"06840",
    "addr:street":"Elm St",
    "iso:country":"US",
    "sg:address":"280 Elm St",
    "sg:city":"New Canaan",
    "sg:classifiers":[
        {
            "category":"Organizations",
            "subcategory":"Membership Organization",
            "type":"Services"
        }
    ],
    "sg:phone":"+1   ",
    "sg:postcode":"06840",
    "sg:province":"NY",
    "wof:name":"Medi-Rec Foundation Inc",
    "wof:placetype":"venue"
},
  "geometry": {"coordinates":[-73.500427,41.145445],"type":"Point"}
}