{
  "type": "Feature",
  "properties": {
    "iso:country":"US",
    "sg:address":"373 W Main St",
    "sg:city":"New Britain",
    "sg:classifiers":[
        {
            "category":"Building & Trades",
            "subcategory":"Construction",
            "type":"Services"
        }
    ],
    "sg:phone":"+1 860 229 7960",
    "sg:postcode":"06052",
    "sg:province":"CT",
    "sg:tags":[
        "contractor"
    ],
    "wof:name":"The Glassman Inc",
    "wof:placetype":"venue"
},
  "geometry": {"coordinates":[-72.792997,41.665614],"type":"Point"}
}