{
  "type": "Feature",
  "properties": {
    "iso:country":"US",
    "sg:address":"28 Cayer Cir",
    "sg:city":"Shelton",
    "sg:classifiers":[
        {
            "category":"Real Estate",
            "subcategory":"Real Estate Agent",
            "type":"Services"
        }
    ],
    "sg:phone":"+1 203 925 9767",
    "sg:postcode":"06484",
    "sg:province":"CT",
    "sg:tags":[
        "appraiser"
    ],
    "wof:name":"Huntington Appraisal Co",
    "wof:placetype":"venue"
},
  "geometry": {"coordinates":[-73.172895,41.31141],"type":"Point"}
}