{
  "type": "Feature",
  "properties": {
    "iso:country":"US",
    "sg:address":"280 Park St",
    "sg:city":"Stratford",
    "sg:classifiers":[
        {
            "category":"Home & Garden",
            "subcategory":"Building Materials",
            "type":"Retail Goods"
        }
    ],
    "sg:phone":"+1 203 377 2044",
    "sg:postcode":"06614",
    "sg:province":"CT",
    "sg:tags":[
        "type",
        "door"
    ],
    "wof:name":"Abbott Overhead Door",
    "wof:placetype":"venue"
},
  "geometry": {"coordinates":[-73.136646,41.208341],"type":"Point"}
}