{
  "type": "Feature",
  "properties": {
    "addr:full":"231 Old Post Rd Fairfield CT 06472",
    "addr:housenumber":"231",
    "addr:postcode":"06472",
    "addr:street":"Old Post Rd",
    "iso:country":"US",
    "sg:address":"231 Old Post Rd",
    "sg:city":"Fairfield",
    "sg:classifiers":[
        {
            "category":"Personal",
            "type":"Services"
        }
    ],
    "sg:phone":"+1 203 454 0005",
    "sg:postcode":"06472",
    "sg:province":"CT",
    "sg:tags":[
        "therapist",
        "massage"
    ],
    "wof:name":"One Touch Massage Studio",
    "wof:placetype":"venue"
},
  "geometry": {"coordinates":[-72.782257,41.406109],"type":"Point"}
}