{
  "type": "Feature",
  "properties": {
    "addr:full":"176 Indian Field Rd Groton CT 06340",
    "addr:housenumber":"176",
    "addr:postcode":"06340",
    "addr:street":"Indian Field Rd Groton Ct",
    "iso:country":"US",
    "sg:address":"176 Indian Field Rd",
    "sg:city":"Groton",
    "sg:classifiers":[
        {
            "category":"Real Estate",
            "subcategory":"Real Estate Agent",
            "type":"Services"
        }
    ],
    "sg:phone":"+1 860 445 2512",
    "sg:postcode":"06340",
    "sg:province":"CT",
    "wof:name":"Alfiero Realty Corporation",
    "wof:placetype":"venue"
},
  "geometry": {"coordinates":[-72.028853,41.350499],"type":"Point"}
}