{
  "type": "Feature",
  "properties": {
    "addr:full":"292 Woodfield Xing Glastonbury CT 06033",
    "addr:housenumber":"292",
    "addr:postcode":"06033",
    "addr:street":"Woodfield Xing",
    "iso:country":"US",
    "sg:address":"292 Woodfield Xing",
    "sg:city":"Glastonbury",
    "sg:classifiers":[
        {
            "category":"Professional",
            "subcategory":"Management & Consulting",
            "type":"Services"
        }
    ],
    "sg:phone":"+1   ",
    "sg:postcode":"06033",
    "sg:province":"CT",
    "wof:name":"Smith DC & Assoc",
    "wof:placetype":"venue"
},
  "geometry": {"coordinates":[-72.543699,41.735793],"type":"Point"}
}