{
  "type": "Feature",
  "properties": {
    "addr:full":"217 Greenwood Ave Bethel CT 06801",
    "addr:housenumber":"217",
    "addr:postcode":"06801",
    "addr:street":"Greenwood Ave Bethel Ct",
    "iso:country":"US",
    "sg:address":"217 Greenwood Ave",
    "sg:city":"Bethel",
    "sg:classifiers":[
        {
            "category":"Shopping",
            "subcategory":"Stationery & Office Supplies",
            "type":"Retail Goods"
        }
    ],
    "sg:phone":"+1 203 744 2858",
    "sg:postcode":"06801",
    "sg:province":"CT",
    "sg:tags":[
        "rubber",
        "stamp",
        "plastic"
    ],
    "wof:name":"Drs Designs",
    "wof:placetype":"venue"
},
  "geometry": {"coordinates":[-73.416016,41.371576],"type":"Point"}
}