{
  "type": "Feature",
  "properties": {
    "addr:full":"2 Gandolfo Dr Canaan CT 06018",
    "addr:housenumber":"2",
    "addr:postcode":"06018",
    "addr:street":"Gandolfo Dr Canaan Ct",
    "iso:country":"US",
    "sg:address":"2 Gandolfo Dr",
    "sg:city":"Canaan",
    "sg:classifiers":[
        {
            "category":"Wholesale",
            "subcategory":"Hardware",
            "type":"Manufacturing & Wholesale Goods"
        },
        {
            "category":"Home & Garden",
            "subcategory":"Garden Supply",
            "type":"Retail Goods"
        },
        {
            "category":"Retail",
            "subcategory":"Repair Shop",
            "type":"Services"
        }
    ],
    "sg:phone":"+1 860 824 1161",
    "sg:postcode":"06018",
    "sg:province":"CT",
    "sg:tags":[
        "renting",
        "lawn",
        "outdoor",
        "power",
        "landscaping",
        "equipment-sales",
        "equipment",
        "saw"
    ],
    "sg:website":"http://www.stihldealer.net/default-dealer-043869.aspx",
    "wof:name":"Stanton Equipment",
    "wof:placetype":"venue"
},
  "geometry": {"coordinates":[-73.327462,42.024934],"type":"Point"}
}