{
  "type": "Feature",
  "properties": {
    "addr:full":"7 Cambridge Dr Trumbull CT 06611",
    "addr:housenumber":"7",
    "addr:postcode":"06611",
    "addr:street":"Cambridge Dr",
    "iso:country":"US",
    "sg:address":"7 Cambridge Dr",
    "sg:city":"Trumbull",
    "sg:classifiers":[
        {
            "category":"Personal",
            "type":"Services"
        }
    ],
    "sg:phone":"+1 203 365 2000",
    "sg:postcode":"06611",
    "sg:province":"CT",
    "sg:tags":[
        "welcoming",
        "newcomer",
        "for"
    ],
    "wof:name":"Welcome Wagon",
    "wof:placetype":"venue"
},
  "geometry": {"coordinates":[-73.198189,41.230221],"type":"Point"}
}