{
  "type": "Feature",
  "properties": {
    "iso:country":"US",
    "sg:address":"1 Torrington Office Plz",
    "sg:city":"Torrington",
    "sg:classifiers":[
        {
            "category":"Health Services",
            "subcategory":"Doctor",
            "type":"Services"
        }
    ],
    "sg:phone":"+1   ",
    "sg:postcode":"06790",
    "sg:province":"CT",
    "wof:name":"Robert A Balla DMD",
    "wof:placetype":"venue"
},
  "geometry": {"coordinates":[-73.109489,41.808983],"type":"Point"}
}