{
  "type": "Feature",
  "properties": {
    "iso:country":"US",
    "sg:address":"247 Forbes Ave",
    "sg:city":"East Haven",
    "sg:classifiers":[
        {
            "category":"Retail",
            "subcategory":"Auto Repair",
            "type":"Services"
        }
    ],
    "sg:phone":"+1   ",
    "sg:postcode":"06512",
    "sg:province":"CT",
    "sg:tags":[
        "body"
    ],
    "wof:name":"Master Performance & Window TI",
    "wof:placetype":"venue"
},
  "geometry": {"coordinates":[-72.89812499999999,41.293727],"type":"Point"}
}