{
  "type": "Feature",
  "properties": {
    "iso:country":"US",
    "sg:address":"52 Leonard St",
    "sg:city":"Port Chester",
    "sg:classifiers":[
        {
            "category":"Building & Trades",
            "subcategory":"Landscaping Services",
            "type":"Services"
        }
    ],
    "sg:phone":"+1 914 939 6538",
    "sg:postcode":"10573",
    "sg:province":"CT",
    "wof:name":"Mario Ferraro Landscaping",
    "wof:placetype":"venue"
},
  "geometry": {"coordinates":[-73.66837700000001,40.991214],"type":"Point"}
}