{
  "type": "Feature",
  "properties": {
    "addr:full":"2600 Park Ave Bridgeport CT 06604",
    "addr:housenumber":"2600",
    "addr:postcode":"06604",
    "addr:street":"Park Ave",
    "iso:country":"US",
    "sg:address":"2600 Park Ave",
    "sg:city":"Bridgeport",
    "sg:classifiers":[
        {
            "category":"Retail",
            "subcategory":"Repair Shop",
            "type":"Services"
        }
    ],
    "sg:phone":"+1 203 331 1020",
    "sg:postcode":"06604",
    "sg:province":"CT",
    "sg:tags":[
        "lock",
        "locksmith"
    ],
    "wof:name":"Champion Locksmiths",
    "wof:placetype":"venue"
},
  "geometry": {"coordinates":[-73.216032,41.194187],"type":"Point"}
}