{
  "type": "Feature",
  "properties": {
    "iso:country":"US",
    "sg:address":"16 Isaac St",
    "sg:city":"Norwalk",
    "sg:classifiers":[
        {
            "category":"Health Services",
            "subcategory":"Doctor",
            "type":"Services"
        }
    ],
    "sg:phone":"+1 203 855 8555",
    "sg:postcode":"06850",
    "sg:province":"CT",
    "sg:tags":[
        "physician",
        "surgeon"
    ],
    "wof:name":"Norwalk Medical Group",
    "wof:placetype":"venue"
},
  "geometry": {"coordinates":[-73.414034,41.116181],"type":"Point"}
}