{
  "type": "Feature",
  "properties": {
    "addr:full":"136 Pembroke Rd Danbury CT 06811",
    "addr:housenumber":"136",
    "addr:postcode":"06811",
    "addr:street":"Pembroke Rd",
    "iso:country":"US",
    "sg:address":"136 Pembroke Rd",
    "sg:city":"Danbury",
    "sg:classifiers":[
        {
            "category":"Building & Trades",
            "subcategory":"Landscaping Services",
            "type":"Services"
        }
    ],
    "sg:phone":"+1 203 312 0557",
    "sg:postcode":"06811",
    "sg:province":"CT",
    "sg:tags":[
        "tree"
    ],
    "wof:name":"Professional Tree Care",
    "wof:placetype":"venue"
},
  "geometry": {"coordinates":[-73.473074,41.447905],"type":"Point"}
}