{
  "type": "Feature",
  "properties": {
    "addr:full":"825 Bridgeport Ave Milford CT 06460",
    "addr:housenumber":"825",
    "addr:postcode":"06460",
    "addr:street":"Bridgeport Ave",
    "iso:country":"US",
    "sg:address":"825 Bridgeport Ave",
    "sg:city":"Milford",
    "sg:classifiers":[
        {
            "category":"Autos & Motor Vehicles",
            "subcategory":"Automobile Sales",
            "type":"Retail Goods"
        },
        {
            "category":"Retail",
            "subcategory":"Auto Repair",
            "type":"Services"
        },
        {
            "category":"Autos & Motor Vehicles",
            "subcategory":"Recreational Vehicle Sales",
            "type":"Retail Goods"
        }
    ],
    "sg:phone":"+1 866 731 3886",
    "sg:postcode":"06460",
    "sg:province":"CT",
    "sg:tags":[
        "vehicles-sports",
        "used",
        "car",
        "atv's",
        "all-terrain",
        "new",
        "utility"
    ],
    "sg:website":"http://www.landroverusa.com",
    "wof:name":"Land Rover Milford",
    "wof:placetype":"venue"
},
  "geometry": {"coordinates":[-73.079151,41.212194],"type":"Point"}
}