{
  "type": "Feature",
  "properties": {
    "iso:country":"US",
    "sg:address":"37 Joes Hill Rd",
    "sg:city":"Danbury",
    "sg:classifiers":[
        {
            "category":"Building & Trades",
            "subcategory":"Construction",
            "type":"Services"
        }
    ],
    "sg:phone":"+1 203 794 0336",
    "sg:postcode":"06811",
    "sg:province":"CT",
    "sg:tags":[
        "ceiling",
        "work",
        "contractor",
        "acoustical",
        "mill",
        "drywall"
    ],
    "wof:name":"Capitol Drywall",
    "wof:placetype":"venue"
},
  "geometry": {"coordinates":[-73.517535,41.396316],"type":"Point"}
}