{
  "type": "Feature",
  "properties": {
    "addr:full":"10 Wintonbury Ave Bloomfield CT 06002",
    "addr:housenumber":"10",
    "addr:postcode":"06002",
    "addr:street":"Wintonbury Ave Bloomfield Ct",
    "iso:country":"US",
    "sg:address":"10 Wintonbury Ave",
    "sg:city":"Bloomfield",
    "sg:classifiers":[
        {
            "category":"Education",
            "subcategory":"Special Training",
            "type":"Public Place"
        }
    ],
    "sg:phone":"+1   ",
    "sg:postcode":"06002",
    "sg:province":"CT",
    "wof:name":"German School of Connecticut",
    "wof:placetype":"venue"
},
  "geometry": {"coordinates":[-72.737167,41.831629],"type":"Point"}
}