{
  "type": "Feature",
  "properties": {
    "addr:full":"385 N Colony St Wallingford CT 06492",
    "addr:housenumber":"385",
    "addr:postcode":"06492",
    "addr:street":"N Colony St",
    "iso:country":"US",
    "sg:address":"385 N Colony St",
    "sg:city":"Wallingford",
    "sg:classifiers":[
        {
            "category":"Shopping",
            "subcategory":"Clothing, Apparel, & Fashions",
            "type":"Retail Goods"
        }
    ],
    "sg:phone":"+1 203 284 9355",
    "sg:postcode":"06492",
    "sg:province":"CT",
    "sg:tags":[
        "uniform"
    ],
    "wof:name":"Uniform Source The",
    "wof:placetype":"venue"
},
  "geometry": {"coordinates":[-72.819897,41.463819],"type":"Point"}
}