{
  "type": "Feature",
  "properties": {
    "iso:country":"US",
    "sg:address":"609 N Washington Ave",
    "sg:city":"Bridgeport",
    "sg:classifiers":[
        {
            "category":"Wholesale",
            "subcategory":"Plants",
            "type":"Manufacturing & Wholesale Goods"
        }
    ],
    "sg:phone":"+1 203 579 2172",
    "sg:postcode":"06604",
    "sg:province":"CT",
    "sg:tags":[
        "florist",
        "cut",
        "flower"
    ],
    "wof:name":"C & C Cut Flowers Inc",
    "wof:placetype":"venue"
},
  "geometry": {"coordinates":[-73.19219,41.192284],"type":"Point"}
}