{
  "type": "Feature",
  "properties": {
    "iso:country":"US",
    "sg:address":"7 Shepard Rd",
    "sg:city":"Woodbridge",
    "sg:classifiers":[
        {
            "category":"Professional",
            "subcategory":"Computer Services",
            "type":"Services"
        }
    ],
    "sg:phone":"+1   ",
    "sg:postcode":"06525",
    "sg:province":"CT",
    "sg:tags":[
        "related"
    ],
    "wof:name":"Mitchel Systems Inc",
    "wof:placetype":"venue"
},
  "geometry": {"coordinates":[-73.040145,41.335573],"type":"Point"}
}