{
  "type": "Feature",
  "properties": {
    "addr:full":"84 Holcomb St Simsbury CT 06070",
    "addr:housenumber":"84",
    "addr:postcode":"06070",
    "addr:street":"Holcomb St Simsbury Ct",
    "iso:country":"US",
    "sg:address":"84 Holcomb St",
    "sg:city":"Simsbury",
    "sg:classifiers":[
        {
            "category":"Building & Trades",
            "subcategory":"Construction",
            "type":"Services"
        }
    ],
    "sg:phone":"+1 860 658 2474",
    "sg:postcode":"06070",
    "sg:province":"CT",
    "sg:tags":[
        "roofing",
        "contractor"
    ],
    "wof:name":"Brian Odonnell Qulty HM Imprvs",
    "wof:placetype":"venue"
},
  "geometry": {"coordinates":[-72.82977700000001,41.910279],"type":"Point"}
}