{
  "type": "Feature",
  "properties": {
    "iso:country":"US",
    "sg:address":"245 Silver Ln",
    "sg:city":"Bridgeport",
    "sg:classifiers":[
        {
            "category":"Professional",
            "subcategory":"Advertising",
            "type":"Services"
        }
    ],
    "sg:phone":"+1 203 371 7224",
    "sg:postcode":"06610",
    "sg:province":"CT",
    "wof:name":"EDS Presentations",
    "wof:placetype":"venue"
},
  "geometry": {"coordinates":[-73.16153,41.223657],"type":"Point"}
}