{
  "type": "Feature",
  "properties": {
    "iso:country":"US",
    "sg:address":"104 Norfield Rd",
    "sg:city":"Weston",
    "sg:classifiers":[
        {
            "category":"Organizations",
            "subcategory":"Community Association",
            "type":"Services"
        }
    ],
    "sg:phone":"+1   ",
    "sg:postcode":"06883",
    "sg:province":"CT",
    "wof:name":"Clubs of Federated Garden",
    "wof:placetype":"venue"
},
  "geometry": {"coordinates":[-73.37120400000001,41.204835],"type":"Point"}
}