{
  "type": "Feature",
  "properties": {
    "addr:full":"935 Georges Hill Rd Southbury CT 06488",
    "addr:housenumber":"935",
    "addr:postcode":"06488",
    "addr:street":"Georges Hill Rd",
    "iso:country":"US",
    "sg:address":"935 Georges Hill Rd",
    "sg:city":"Southbury",
    "sg:classifiers":[
        {
            "category":"Professional",
            "type":"Services"
        }
    ],
    "sg:phone":"+1 203 264 2900",
    "sg:postcode":"06488",
    "sg:province":"CT",
    "sg:tags":[
        "establishment"
    ],
    "wof:name":"Transworld International Inc",
    "wof:placetype":"venue"
},
  "geometry": {"coordinates":[-73.21638799999999,41.440222],"type":"Point"}
}