{
  "type": "Feature",
  "properties": {
    "iso:country":"US",
    "sg:address":"430 Grant St",
    "sg:city":"Bridgeport",
    "sg:classifiers":[
        {
            "category":"Real Estate",
            "subcategory":"Real Estate Operator",
            "type":"Services"
        }
    ],
    "sg:phone":"+1 203 384 9984",
    "sg:postcode":"06610",
    "sg:province":"CT",
    "sg:tags":[
        "building",
        "residential",
        "apartment",
        "care"
    ],
    "wof:name":"Roncalli Apartments",
    "wof:placetype":"venue"
},
  "geometry": {"coordinates":[-73.16203400000001,41.188501],"type":"Point"}
}