{
  "type": "Feature",
  "properties": {
    "iso:country":"US",
    "sg:address":"82 New Haven Ave",
    "sg:city":"Milford",
    "sg:classifiers":[
        {
            "category":"Government",
            "subcategory":"Office",
            "type":"Public Place"
        }
    ],
    "sg:phone":"+1 203 783 3285",
    "sg:postcode":"06460",
    "sg:province":"CT",
    "sg:tags":[
        "administrative",
        "program",
        "health"
    ],
    "wof:name":"Department of Health",
    "wof:placetype":"venue"
},
  "geometry": {"coordinates":[-73.05240499999999,41.223126],"type":"Point"}
}