{
  "type": "Feature",
  "properties": {
    "iso:country":"US",
    "sg:address":"122 Main St",
    "sg:city":"Canton",
    "sg:classifiers":[
        {
            "category":"Building & Trades",
            "subcategory":"Landscaping Services",
            "type":"Services"
        }
    ],
    "sg:phone":"+1 860 693 6765",
    "sg:postcode":"06016",
    "sg:province":"CT",
    "sg:tags":[
        "landscape"
    ],
    "wof:name":"Insite LLC",
    "wof:placetype":"venue"
},
  "geometry": {"coordinates":[-72.545896,41.916425],"type":"Point"}
}