{
  "type": "Feature",
  "properties": {
    "iso:country":"US",
    "sg:address":"45 W Point Ter",
    "sg:city":"Hartford",
    "sg:classifiers":[
        {
            "category":"Professional",
            "subcategory":"Engineering",
            "type":"Services"
        }
    ],
    "sg:phone":"+1   ",
    "sg:postcode":"06107",
    "sg:province":"CT",
    "wof:name":"Donald J Wilkinson",
    "wof:placetype":"venue"
},
  "geometry": {"coordinates":[-72.747967,41.736543],"type":"Point"}
}