{
  "type": "Feature",
  "properties": {
    "iso:country":"US",
    "sg:address":"9 White Rd",
    "sg:city":"Ellington",
    "sg:classifiers":[
        {
            "category":"Real Estate",
            "subcategory":"Real Estate Agent",
            "type":"Services"
        }
    ],
    "sg:phone":"+1 860 870 4242",
    "sg:postcode":"06029",
    "sg:province":"CT",
    "wof:name":"Webber Enterprises Inc",
    "wof:placetype":"venue"
},
  "geometry": {"coordinates":[-72.374889,41.928225],"type":"Point"}
}