{
  "type": "Feature",
  "properties": {
    "addr:full":"5 Isaac St Norwalk CT 06850",
    "addr:housenumber":"5",
    "addr:postcode":"06850",
    "addr:street":"Isaac St",
    "iso:country":"US",
    "sg:address":"5 Isaac St",
    "sg:city":"Norwalk",
    "sg:classifiers":[
        {
            "category":"Organizations",
            "subcategory":"Membership Organization",
            "type":"Services"
        }
    ],
    "sg:phone":"+1   ",
    "sg:postcode":"06850",
    "sg:province":"CT",
    "sg:tags":[
        "foundation",
        "scholarship"
    ],
    "wof:name":"Womans Bd of The Norwalk Hosp",
    "wof:placetype":"venue"
},
  "geometry": {"coordinates":[-73.41381800000001,41.115955],"type":"Point"}
}