{
  "type": "Feature",
  "properties": {
    "addr:full":"3453 Main St Coventry CT 06238",
    "addr:housenumber":"3453",
    "addr:postcode":"06238",
    "addr:street":"Main St",
    "iso:country":"US",
    "sg:address":"3453 Main St",
    "sg:city":"Coventry",
    "sg:classifiers":[
        {
            "category":"Education",
            "subcategory":"School",
            "type":"Public Place"
        }
    ],
    "sg:phone":"+1   ",
    "sg:postcode":"06238",
    "sg:province":"CT",
    "wof:name":"Coventry Grammer School",
    "wof:placetype":"venue"
},
  "geometry": {"coordinates":[-72.369674,41.797087],"type":"Point"}
}