{
  "type": "Feature",
  "properties": {
    "addr:full":"9 Padanaram Rd Danbury CT 06811",
    "addr:housenumber":"9",
    "addr:postcode":"06811",
    "addr:street":"Padanaram Rd",
    "iso:country":"US",
    "sg:address":"9 Padanaram Rd",
    "sg:city":"Danbury",
    "sg:classifiers":[
        {
            "category":"Insurance",
            "subcategory":"Hazard Insurance",
            "type":"Services"
        },
        {
            "category":"Insurance",
            "subcategory":"Insurance Agent",
            "type":"Services"
        },
        {
            "category":"Insurance",
            "subcategory":"Life Insurance",
            "type":"Services"
        }
    ],
    "sg:phone":"+1 203 743 0664",
    "sg:postcode":"06811",
    "sg:province":"CT",
    "sg:tags":[
        "auto"
    ],
    "sg:website":"http://statefarm.mqgroup.com/url.asp?usr=070118",
    "wof:name":"Ordonez, Maria S - State Farm Insurance Agent",
    "wof:placetype":"venue"
},
  "geometry": {"coordinates":[-73.45800800000001,41.413219],"type":"Point"}
}