{
  "type": "Feature",
  "properties": {
    "iso:country":"US",
    "sg:address":"580 S Hoop Pole Rd",
    "sg:city":"Guilford",
    "sg:classifiers":[
        {
            "category":"Real Estate",
            "subcategory":"Real Estate Agent",
            "type":"Services"
        }
    ],
    "sg:phone":"+1 203 457 9670",
    "sg:postcode":"06437",
    "sg:province":"CT",
    "wof:name":"Fredericks Realty",
    "wof:placetype":"venue"
},
  "geometry": {"coordinates":[-72.705906,41.356258],"type":"Point"}
}