{
  "type": "Feature",
  "properties": {
    "iso:country":"US",
    "sg:address":"35 Mason St",
    "sg:city":"Greenwich",
    "sg:classifiers":[
        {
            "category":"Professional",
            "subcategory":"Management & Consulting",
            "type":"Services"
        }
    ],
    "sg:phone":"+1 203 625 0011",
    "sg:postcode":"06830",
    "sg:province":"CT",
    "sg:tags":[
        "consultant",
        "business"
    ],
    "wof:name":"Taylor Capital Management",
    "wof:placetype":"venue"
},
  "geometry": {"coordinates":[-73.62524500000001,41.031553],"type":"Point"}
}