{
  "type": "Feature",
  "properties": {
    "iso:country":"US",
    "sg:address":"12 Old Redding Rd",
    "sg:city":"West Redding",
    "sg:classifiers":[
        {
            "category":"Shopping",
            "subcategory":"Computers & Home Electronics",
            "type":"Retail Goods"
        }
    ],
    "sg:phone":"+1 203 938 6959",
    "sg:postcode":"06896",
    "sg:province":"CT",
    "sg:tags":[
        "software"
    ],
    "wof:name":"Merant Corp",
    "wof:placetype":"venue"
},
  "geometry": {"coordinates":[-73.44853500000001,41.287234],"type":"Point"}
}