{
  "type": "Feature",
  "properties": {
    "iso:country":"US",
    "sg:address":"23 Buena Vista Dr",
    "sg:city":"Greenwich",
    "sg:classifiers":[
        {
            "category":"Professional",
            "type":"Services"
        }
    ],
    "sg:phone":"+1 203 531 6192",
    "sg:postcode":"06831",
    "sg:province":"NY",
    "wof:name":"Acovo Inc",
    "wof:placetype":"venue"
},
  "geometry": {"coordinates":[-73.66462300000001,41.030838],"type":"Point"}
}