{
  "type": "Feature",
  "properties": {
    "addr:full":"23 Mirtl Rd West Willington CT 06279",
    "addr:housenumber":"23",
    "addr:postcode":"06279",
    "addr:street":"Mirtl Rd West Willington Ct",
    "iso:country":"US",
    "sg:address":"23 Mirtl Rd",
    "sg:city":"West Willington",
    "sg:classifiers":[
        {
            "category":"Professional",
            "subcategory":"Management & Consulting",
            "type":"Services"
        }
    ],
    "sg:phone":"+1   ",
    "sg:postcode":"06279",
    "sg:province":"CT",
    "sg:tags":[
        "business"
    ],
    "wof:name":"Ncc Consulting Services LLC",
    "wof:placetype":"venue"
},
  "geometry": {"coordinates":[-72.265702,41.861538],"type":"Point"}
}