{
  "type": "Feature",
  "properties": {
    "iso:country":"US",
    "sg:address":"154 Herbert St",
    "sg:city":"Milford",
    "sg:classifiers":[
        {
            "category":"Professional",
            "subcategory":"Business Services",
            "type":"Services"
        },
        {
            "category":"Professional",
            "subcategory":"Management & Consulting",
            "type":"Services"
        }
    ],
    "sg:phone":"+1 203 876 2822",
    "sg:postcode":"06477",
    "sg:province":"CT",
    "sg:tags":[
        "information",
        "referral",
        "consultant"
    ],
    "sg:website":"www.aquinasconsulting.com",
    "wof:name":"Aquinas Consulting & Staffing",
    "wof:placetype":"venue"
},
  "geometry": {"coordinates":[-73.078489,41.26354],"type":"Point"}
}