{
  "type": "Feature",
  "properties": {
    "iso:country":"US",
    "sg:address":"1484 New Britain Ave",
    "sg:city":"Farmington",
    "sg:classifiers":[
        {
            "category":"Retail",
            "subcategory":"Auto Repair",
            "type":"Services"
        }
    ],
    "sg:phone":"+1   ",
    "sg:postcode":"06032",
    "sg:province":"CT",
    "sg:tags":[
        "general"
    ],
    "wof:name":"Ward Auto Works",
    "wof:placetype":"venue"
},
  "geometry": {"coordinates":[-72.862611,41.716755],"type":"Point"}
}