{
  "type": "Feature",
  "properties": {
    "addr:full":"126 Elm St West Haven CT 06516",
    "addr:housenumber":"126",
    "addr:postcode":"06516",
    "addr:street":"Elm St;Haven",
    "iso:country":"US",
    "sg:address":"126 Elm St",
    "sg:city":"West Haven",
    "sg:classifiers":[
        {
            "category":"Restaurant",
            "type":"Food & Drink"
        }
    ],
    "sg:phone":"+1 203 937 9790",
    "sg:postcode":"06516",
    "sg:province":"CT",
    "sg:tags":[
        "eating"
    ],
    "wof:name":"Seaside Pizza",
    "wof:placetype":"venue"
},
  "geometry": {"coordinates":[-72.94543400000001,41.277846],"type":"Point"}
}