{
  "type": "Feature",
  "properties": {
    "addr:full":"927 Meriden Rd Waterbury CT 06705",
    "addr:housenumber":"927",
    "addr:postcode":"06705",
    "addr:street":"Meriden Rd",
    "iso:country":"US",
    "sg:address":"927 Meriden Rd",
    "sg:city":"Waterbury",
    "sg:classifiers":[
        {
            "category":"Shopping",
            "type":"Retail Goods"
        }
    ],
    "sg:phone":"+1 203 753 0844",
    "sg:postcode":"06705",
    "sg:province":"CT",
    "sg:tags":[
        "gravestone",
        "monument"
    ],
    "wof:name":"Burton's Monument Shop Inc",
    "wof:placetype":"venue"
},
  "geometry": {"coordinates":[-72.989142,41.553283],"type":"Point"}
}