{
  "type": "Feature",
  "properties": {
    "iso:country":"US",
    "sg:address":"20 Stillwell Dr",
    "sg:city":"Plainville",
    "sg:classifiers":[
        {
            "category":"Real Estate",
            "subcategory":"Real Estate Agent",
            "type":"Services"
        }
    ],
    "sg:phone":"+1 860 747 5909",
    "sg:postcode":"06062",
    "sg:province":"CT",
    "wof:name":"Woodmoor Village",
    "wof:placetype":"venue"
},
  "geometry": {"coordinates":[-72.864001,41.663169],"type":"Point"}
}