{
  "type": "Feature",
  "properties": {
    "addr:full":"1304 Boston Post Rd Milford CT 06460",
    "addr:housenumber":"1304",
    "addr:postcode":"06460",
    "addr:street":"Boston Post Rd",
    "iso:country":"US",
    "sg:address":"1304 Boston Post Rd",
    "sg:city":"Milford",
    "sg:classifiers":[
        {
            "category":"Manufacturing",
            "subcategory":"Food",
            "type":"Manufacturing & Wholesale Goods"
        }
    ],
    "sg:phone":"+1 203 878 8304",
    "sg:postcode":"06460",
    "sg:province":"CT",
    "sg:tags":[
        "dry",
        "condensed",
        "evaporated",
        "product"
    ],
    "wof:name":"Blinds To Go Inc",
    "wof:placetype":"venue"
},
  "geometry": {"coordinates":[-73.035146,41.239363],"type":"Point"}
}