{
  "type": "Feature",
  "properties": {
    "iso:country":"US",
    "sg:address":"612 Riverside Ave",
    "sg:city":"Westport",
    "sg:classifiers":[
        {
            "category":"Retail",
            "subcategory":"Auto Repair",
            "type":"Services"
        }
    ],
    "sg:phone":"+1 203 227 3300",
    "sg:postcode":"06880",
    "sg:province":"CT",
    "sg:tags":[
        "repairing",
        "automobile"
    ],
    "wof:name":"IPM Inc",
    "wof:placetype":"venue"
},
  "geometry": {"coordinates":[-73.370501,41.119672],"type":"Point"}
}