{
  "type": "Feature",
  "properties": {
    "iso:country":"US",
    "sg:address":"189 Hattertown Rd",
    "sg:city":"Newtown",
    "sg:classifiers":[
        {
            "category":"Real Estate",
            "subcategory":"Architect",
            "type":"Services"
        }
    ],
    "sg:phone":"+1 203 270 3506",
    "sg:postcode":"06470",
    "sg:province":"CT",
    "sg:tags":[
        "architectural"
    ],
    "wof:name":"Steven Odams Architects LLC",
    "wof:placetype":"venue"
},
  "geometry": {"coordinates":[-73.30930499999999,41.341478],"type":"Point"}
}