{
  "type": "Feature",
  "properties": {
    "iso:country":"US",
    "sg:address":"487 Federal Rd",
    "sg:city":"Brookfield",
    "sg:classifiers":[
        {
            "category":"Professional",
            "subcategory":"Computer Services",
            "type":"Services"
        }
    ],
    "sg:phone":"+1   ",
    "sg:postcode":"06804",
    "sg:province":"CT",
    "sg:tags":[
        "programing",
        "custom"
    ],
    "wof:name":"U S Developers",
    "wof:placetype":"venue"
},
  "geometry": {"coordinates":[-73.405615,41.458856],"type":"Point"}
}