{
  "type": "Feature",
  "properties": {
    "iso:country":"US",
    "sg:address":"9 Dogwood Pl",
    "sg:city":"Milford",
    "sg:classifiers":[
        {
            "category":"Professional",
            "subcategory":"Accounting & Tax Preparation",
            "type":"Services"
        }
    ],
    "sg:phone":"+1 203 783 9856",
    "sg:postcode":"06460",
    "sg:province":"CT",
    "sg:tags":[
        "billing"
    ],
    "wof:name":"Medical Billing Specialists",
    "wof:placetype":"venue"
},
  "geometry": {"coordinates":[-73.105647,41.194385],"type":"Point"}
}