{
  "type": "Feature",
  "properties": {
    "iso:country":"US",
    "sg:address":"116 Logging Trail Rd",
    "sg:city":"Danbury",
    "sg:classifiers":[
        {
            "category":"Professional",
            "type":"Services"
        }
    ],
    "sg:phone":"+1 203 790 1689",
    "sg:postcode":"06811",
    "sg:province":"CT",
    "sg:tags":[
        "establishment"
    ],
    "wof:name":"Advanced Techniques Inc",
    "wof:placetype":"venue"
},
  "geometry": {"coordinates":[-73.42425,41.435386],"type":"Point"}
}