{
  "type": "Feature",
  "properties": {
    "addr:full":"84 Oakwood Dr Madison CT 06443",
    "addr:housenumber":"84",
    "addr:postcode":"06443",
    "addr:street":"Oakwood Dr",
    "iso:country":"US",
    "sg:address":"84 Oakwood Dr",
    "sg:city":"Madison",
    "sg:classifiers":[
        {
            "category":"Professional",
            "subcategory":"Management & Consulting",
            "type":"Services"
        }
    ],
    "sg:phone":"+1   ",
    "sg:postcode":"06443",
    "sg:province":"CT",
    "sg:tags":[
        "business"
    ],
    "wof:name":"Fjl Assoc LLC",
    "wof:placetype":"venue"
},
  "geometry": {"coordinates":[-72.633045,41.347784],"type":"Point"}
}