{
  "type": "Feature",
  "properties": {
    "iso:country":"US",
    "sg:address":"32 4th Avenue Ext",
    "sg:city":"Old Saybrook",
    "sg:classifiers":[
        {
            "category":"Building & Trades",
            "subcategory":"Construction",
            "type":"Services"
        }
    ],
    "sg:phone":"+1 860 388 1275",
    "sg:postcode":"06475",
    "sg:province":"CT",
    "sg:tags":[
        "contractor"
    ],
    "wof:name":"M D C Co Builders & General Contractors",
    "wof:placetype":"venue"
},
  "geometry": {"coordinates":[-72.357697,41.321602],"type":"Point"}
}