{
  "type": "Feature",
  "properties": {
    "addr:full":"33 Highland St New Britain CT 06052",
    "addr:housenumber":"33",
    "addr:postcode":"06052",
    "addr:street":"Highland St",
    "iso:country":"US",
    "sg:address":"33 Highland St",
    "sg:city":"New Britain",
    "sg:classifiers":[
        {
            "category":"Social Services",
            "type":"Services"
        }
    ],
    "sg:phone":"+1   ",
    "sg:postcode":"06052",
    "sg:province":"CT",
    "wof:name":"Lions Galary of Vision Svcs",
    "wof:placetype":"venue"
},
  "geometry": {"coordinates":[-72.788546,41.661138],"type":"Point"}
}