{
  "type": "Feature",
  "properties": {
    "iso:country":"US",
    "sg:address":"138 Goffe St",
    "sg:city":"New Haven",
    "sg:classifiers":[
        {
            "category":"Personal",
            "subcategory":"Beauty Salon",
            "type":"Services"
        }
    ],
    "sg:phone":"+1 203 773 9994",
    "sg:postcode":"06511",
    "sg:province":"CT",
    "wof:name":"Sharper Image Unisex Salon",
    "wof:placetype":"venue"
},
  "geometry": {"coordinates":[-72.935745,41.31635],"type":"Point"}
}