{
  "type": "Feature",
  "properties": {
    "iso:country":"US",
    "sg:address":"199 Main St",
    "sg:city":"Deep River",
    "sg:classifiers":[
        {
            "category":"Shopping",
            "type":"Retail Goods"
        }
    ],
    "sg:phone":"+1 860 526 1763",
    "sg:postcode":"06417",
    "sg:province":"CT",
    "sg:tags":[
        "merchandise"
    ],
    "wof:name":"Deep River Gallery",
    "wof:placetype":"venue"
},
  "geometry": {"coordinates":[-72.435492,41.38493],"type":"Point"}
}