{
  "type": "Feature",
  "properties": {
    "iso:country":"US",
    "sg:address":"23 Clara Dr",
    "sg:city":"Mystic",
    "sg:classifiers":[
        {
            "category":"Health Services",
            "subcategory":"Optometrist",
            "type":"Services"
        }
    ],
    "sg:phone":"+1   ",
    "sg:postcode":"06355",
    "sg:province":"CT",
    "wof:name":"Jacqueline Campisi Od",
    "wof:placetype":"venue"
},
  "geometry": {"coordinates":[-71.954599,41.372262],"type":"Point"}
}