{
  "type": "Feature",
  "properties": {
    "addr:full":"113 Salem Tpke Norwich CT 06360",
    "addr:housenumber":"113",
    "addr:postcode":"06360",
    "addr:street":"Salem Tpke",
    "iso:country":"US",
    "sg:address":"113 Salem Tpke",
    "sg:city":"Norwich",
    "sg:classifiers":[
        {
            "category":"Government",
            "subcategory":"Office",
            "type":"Public Place"
        }
    ],
    "sg:phone":"+1 860 859 5700",
    "sg:postcode":"06360",
    "sg:province":"CT",
    "sg:tags":[
        "audit",
        "field",
        "unit"
    ],
    "wof:name":"Field Audit Unit",
    "wof:placetype":"venue"
},
  "geometry": {"coordinates":[-72.10854399999999,41.513065],"type":"Point"}
}