{
  "type": "Feature",
  "properties": {
    "addr:full":"6 Laurel Trl East Hampton CT 06424",
    "addr:housenumber":"6",
    "addr:postcode":"06424",
    "addr:street":"Laurel Trl East Hampton Ct",
    "iso:country":"US",
    "sg:address":"6 Laurel Trl",
    "sg:city":"East Hampton",
    "sg:classifiers":[
        {
            "category":"Building & Trades",
            "subcategory":"Plumbing",
            "type":"Services"
        }
    ],
    "sg:phone":"+1 860 267 2726",
    "sg:postcode":"06424",
    "sg:province":"CT",
    "sg:tags":[
        "contractor"
    ],
    "wof:name":"Parsons Plumbing Heatin",
    "wof:placetype":"venue"
},
  "geometry": {"coordinates":[-72.491207,41.597362],"type":"Point"}
}