{
  "type": "Feature",
  "properties": {
    "iso:country":"US",
    "sg:address":"112 Elm St",
    "sg:city":"Cheshire",
    "sg:classifiers":[
        {
            "category":"Personal",
            "type":"Services"
        }
    ],
    "sg:phone":"+1 203 272 9212",
    "sg:postcode":"06410",
    "sg:province":"CT",
    "sg:tags":[
        "wear",
        "formal"
    ],
    "wof:name":"Paul's Fine Clothing Inc",
    "wof:placetype":"venue"
},
  "geometry": {"coordinates":[-72.90057899999999,41.497748],"type":"Point"}
}