{
  "type": "Feature",
  "properties": {
    "iso:country":"US",
    "sg:address":"39 Norwich Westerly Rd",
    "sg:city":"Ledyard",
    "sg:classifiers":[
        {
            "category":"Restaurant",
            "type":"Food & Drink"
        }
    ],
    "sg:menulink":"http://www.allmenus.com/ct/ledyard/270045-alta-strada-foxwoods/menu/",
    "sg:phone":"+1 860 312 2582",
    "sg:postcode":"06339",
    "sg:province":"CT",
    "sg:tags":[
        "italian"
    ],
    "wof:name":"Alta Strada Foxwoods",
    "wof:placetype":"venue"
},
  "geometry": {"coordinates":[-71.954998,41.473173],"type":"Point"}
}