{
  "type": "Feature",
  "properties": {
    "iso:country":"US",
    "sg:address":"1278 Durham Rd",
    "sg:city":"Madison",
    "sg:classifiers":[
        {
            "category":"Restaurant",
            "type":"Food & Drink"
        }
    ],
    "sg:phone":"+1 203 421 3434",
    "sg:postcode":"06443",
    "sg:province":"CT",
    "sg:tags":[
        "eating"
    ],
    "wof:name":"Circle Pizza",
    "wof:placetype":"venue"
},
  "geometry": {"coordinates":[-72.63793800000001,41.358465],"type":"Point"}
}