{
  "type": "Feature",
  "properties": {
    "addr:full":"68 Henley Way Avon CT 06001",
    "addr:housenumber":"68",
    "addr:postcode":"06001",
    "addr:street":"Henley Way",
    "iso:country":"US",
    "sg:address":"68 Henley Way",
    "sg:city":"Avon",
    "sg:classifiers":[
        {
            "category":"Retail",
            "subcategory":"Portrait Studio",
            "type":"Services"
        }
    ],
    "sg:phone":"+1   ",
    "sg:postcode":"06001",
    "sg:province":"CT",
    "sg:tags":[
        "photo"
    ],
    "wof:name":"Avon Photography & Video",
    "wof:placetype":"venue"
},
  "geometry": {"coordinates":[-72.88104300000001,41.795037],"type":"Point"}
}