{
  "type": "Feature",
  "properties": {
    "iso:country":"US",
    "sg:address":"447 Quaddick Rd",
    "sg:city":"Thompson",
    "sg:classifiers":[
        {
            "category":"Professional",
            "subcategory":"Business Services",
            "type":"Services"
        }
    ],
    "sg:phone":"+1   ",
    "sg:postcode":"06277",
    "sg:province":"CT",
    "wof:name":"Ne Interiors",
    "wof:placetype":"venue"
},
  "geometry": {"coordinates":[-71.83022200000001,41.941198],"type":"Point"}
}