{
  "type": "Feature",
  "properties": {
    "iso:country":"US",
    "sg:address":"49 Goodhouse Rd",
    "sg:city":"Litchfield",
    "sg:classifiers":[
        {
            "category":"Shopping",
            "subcategory":"Gifts & Souvenirs",
            "type":"Retail Goods"
        }
    ],
    "sg:phone":"+1 860 567 3009",
    "sg:postcode":"06759",
    "sg:province":"CT",
    "sg:tags":[
        "durable"
    ],
    "wof:name":"Kallgren Card",
    "wof:placetype":"venue"
},
  "geometry": {"coordinates":[-73.23922399999999,41.769135],"type":"Point"}
}