{
  "type": "Feature",
  "properties": {
    "addr:full":"244 Middlesex Ave Chester CT 06412",
    "addr:housenumber":"244",
    "addr:postcode":"06412",
    "addr:street":"Middlesex Ave",
    "iso:country":"US",
    "sg:address":"244 Middlesex Ave",
    "sg:city":"Chester",
    "sg:classifiers":[
        {
            "category":"Autos & Motor Vehicles",
            "subcategory":"Automobile Sales",
            "type":"Retail Goods"
        }
    ],
    "sg:phone":"+1 860 526 2060",
    "sg:postcode":"06412",
    "sg:province":"CT",
    "sg:tags":[
        "supp",
        "used",
        "motorcycle"
    ],
    "wof:name":"Essex Motorsports Intl",
    "wof:placetype":"venue"
},
  "geometry": {"coordinates":[-72.449371,41.426719],"type":"Point"}
}