{
  "type": "Feature",
  "properties": {
    "addr:full":"28 Thompson Rd Manchester CT 06040",
    "addr:housenumber":"28",
    "addr:postcode":"06040",
    "addr:street":"Thompson Rd",
    "iso:country":"US",
    "sg:address":"28 Thompson Rd",
    "sg:city":"Manchester",
    "sg:classifiers":[
        {
            "category":"Education",
            "subcategory":"Special Training",
            "type":"Public Place"
        }
    ],
    "sg:phone":"+1   ",
    "sg:postcode":"06040",
    "sg:province":"CT",
    "wof:name":"Wins For Life LLC",
    "wof:placetype":"venue"
},
  "geometry": {"coordinates":[-72.54527299999999,41.773971],"type":"Point"}
}