{
  "type": "Feature",
  "properties": {
    "addr:full":"388 Long Hill Rd Groton CT 06340",
    "addr:housenumber":"388",
    "addr:postcode":"06340",
    "addr:street":"Long Hill Rd Groton Ct",
    "iso:country":"US",
    "sg:address":"388 Long Hill Rd",
    "sg:city":"Groton",
    "sg:classifiers":[
        {
            "category":"Real Estate",
            "subcategory":"Real Estate Agent",
            "type":"Services"
        }
    ],
    "sg:phone":"+1 860 449 8400",
    "sg:postcode":"06340",
    "sg:province":"CT",
    "wof:name":"Nautilus Realty LLC",
    "wof:placetype":"venue"
},
  "geometry": {"coordinates":[-72.06242,41.358052],"type":"Point"}
}