{
  "type": "Feature",
  "properties": {
    "iso:country":"US",
    "sg:address":"199 Post Rd W",
    "sg:city":"Westport",
    "sg:classifiers":[
        {
            "category":"Shopping",
            "subcategory":"Pets & Pet Supplies",
            "type":"Retail Goods"
        },
        {
            "category":"Retail",
            "subcategory":"Animal Services",
            "type":"Services"
        }
    ],
    "sg:phone":"+1 203 222 0384",
    "sg:postcode":"06880",
    "sg:province":"CT",
    "sg:tags":[
        "grooming",
        "dog",
        "cat"
    ],
    "wof:name":"The Grooming Room",
    "wof:placetype":"venue"
},
  "geometry": {"coordinates":[-73.371162,41.136211],"type":"Point"}
}