{
  "type": "Feature",
  "properties": {
    "iso:country":"US",
    "sg:address":"20 Cherokee Ct",
    "sg:city":"Cromwell",
    "sg:classifiers":[
        {
            "category":"Professional",
            "subcategory":"Accounting & Tax Preparation",
            "type":"Services"
        }
    ],
    "sg:phone":"+1   ",
    "sg:postcode":"06416",
    "sg:province":"CT",
    "wof:name":"Barbara H Holstein CPA",
    "wof:placetype":"venue"
},
  "geometry": {"coordinates":[-72.670897,41.611579],"type":"Point"}
}