{
  "type": "Feature",
  "properties": {
    "addr:full":"19 Ponus Ridge New Canaan NY 06840",
    "addr:housenumber":"19",
    "addr:postcode":"06840",
    "addr:street":"Ponus Ridge",
    "iso:country":"US",
    "sg:address":"19 Ponus Ridge",
    "sg:city":"New Canaan",
    "sg:classifiers":[
        {
            "category":"Real Estate",
            "subcategory":"Real Estate Agent",
            "type":"Services"
        }
    ],
    "sg:phone":"+1 203 966 2060",
    "sg:postcode":"06840",
    "sg:province":"NY",
    "wof:name":"Aje Realty LLC",
    "wof:placetype":"venue"
},
  "geometry": {"coordinates":[-73.51611800000001,41.115152],"type":"Point"}
}