{
  "type": "Feature",
  "properties": {
    "iso:country":"US",
    "sg:address":"400 Budding Ridge Rd",
    "sg:city":"Cheshire",
    "sg:classifiers":[
        {
            "category":"Manufacturing",
            "subcategory":"Paper Products",
            "type":"Manufacturing & Wholesale Goods"
        }
    ],
    "sg:phone":"+1 203 272 3873",
    "sg:postcode":"06410",
    "sg:province":"CT",
    "sg:tags":[
        "label"
    ],
    "wof:name":"Fae Labels",
    "wof:placetype":"venue"
},
  "geometry": {"coordinates":[-72.888825,41.510199],"type":"Point"}
}