{
  "type": "Feature",
  "properties": {
    "iso:country":"US",
    "sg:address":"3 Cottage St",
    "sg:city":"Norwalk",
    "sg:classifiers":[
        {
            "category":"Professional",
            "type":"Services"
        }
    ],
    "sg:phone":"+1 203 854 9542",
    "sg:postcode":"06855",
    "sg:province":"CT",
    "wof:name":"Dvden Inc",
    "wof:placetype":"venue"
},
  "geometry": {"coordinates":[-73.405823,41.100691],"type":"Point"}
}