{
  "type": "Feature",
  "properties": {
    "iso:country":"US",
    "sg:address":"6 Preston Ln",
    "sg:city":"Salisbury",
    "sg:classifiers":[
        {
            "category":"Health Services",
            "subcategory":"Doctor",
            "type":"Services"
        }
    ],
    "sg:phone":"+1   ",
    "sg:postcode":"06079",
    "sg:province":"CT",
    "sg:tags":[
        "medical"
    ],
    "wof:name":"Dr Melamed Joel MD",
    "wof:placetype":"venue"
},
  "geometry": {"coordinates":[-73.40147399999999,42.03543],"type":"Point"}
}