{
  "type": "Feature",
  "properties": {
    "iso:country":"US",
    "sg:address":"17 Carriage House Dr",
    "sg:city":"Danbury",
    "sg:classifiers":[
        {
            "category":"Professional",
            "subcategory":"Management & Consulting",
            "type":"Services"
        }
    ],
    "sg:phone":"+1   ",
    "sg:postcode":"06810",
    "sg:province":"CT",
    "sg:tags":[
        "communications",
        "consultant"
    ],
    "wof:name":"Stapleton Communications Inc",
    "wof:placetype":"venue"
},
  "geometry": {"coordinates":[-73.491619,41.36086],"type":"Point"}
}