{
  "type": "Feature",
  "properties": {
    "addr:full":"1234 Summer St Stamford CT 06905",
    "addr:housenumber":"1234",
    "addr:postcode":"06905",
    "addr:street":"Summer St",
    "iso:country":"US",
    "sg:address":"1234 Summer St",
    "sg:city":"Stamford",
    "sg:classifiers":[
        {
            "category":"Banks & Credit Unions",
            "subcategory":"Bank",
            "type":"Services"
        }
    ],
    "sg:phone":"+1 203 975 8563",
    "sg:postcode":"06905",
    "sg:province":"CT",
    "sg:tags":[
        "federal",
        "savings",
        "institution"
    ],
    "wof:name":"Washington Mutual Bank",
    "wof:placetype":"venue"
},
  "geometry": {"coordinates":[-73.541172,41.060815],"type":"Point"}
}