{
  "type": "Feature",
  "properties": {
    "iso:country":"US",
    "sg:address":"5 West St",
    "sg:city":"Cromwell",
    "sg:classifiers":[
        {
            "category":"Government",
            "subcategory":"Police Station",
            "type":"Public Place"
        }
    ],
    "sg:phone":"+1 860 635 2256",
    "sg:postcode":"06416",
    "sg:province":"CT",
    "sg:tags":[
        "protection"
    ],
    "wof:name":"Cromwell Police Department",
    "wof:placetype":"venue"
},
  "geometry": {"coordinates":[-72.646209,41.595925],"type":"Point"}
}