{
  "type": "Feature",
  "properties": {
    "addr:full":"18 Platts Hill Rd Newtown CT 06470",
    "addr:housenumber":"18",
    "addr:postcode":"06470",
    "addr:street":"Platts Hill Rd",
    "iso:country":"US",
    "sg:address":"18 Platts Hill Rd",
    "sg:city":"Newtown",
    "sg:classifiers":[
        {
            "category":"Manufacturing",
            "subcategory":"Tools & Machinery",
            "type":"Manufacturing & Wholesale Goods"
        }
    ],
    "sg:phone":"+1 203 426 9700",
    "sg:postcode":"06470",
    "sg:province":"CT",
    "sg:tags":[
        "industry",
        "aerospace"
    ],
    "wof:name":"Robert Fulton Co",
    "wof:placetype":"venue"
},
  "geometry": {"coordinates":[-73.289242,41.364992],"type":"Point"}
}