{
  "type": "Feature",
  "properties": {
    "addr:full":"21 Fern Dr Torrington CT 06790",
    "addr:housenumber":"21",
    "addr:postcode":"06790",
    "addr:street":"Fern Dr",
    "iso:country":"US",
    "sg:address":"21 Fern Dr",
    "sg:city":"Torrington",
    "sg:classifiers":[
        {
            "category":"Professional",
            "subcategory":"Management & Consulting",
            "type":"Services"
        }
    ],
    "sg:phone":"+1   ",
    "sg:postcode":"06790",
    "sg:province":"CT",
    "sg:tags":[
        "business"
    ],
    "wof:name":"Professional School of Driving",
    "wof:placetype":"venue"
},
  "geometry": {"coordinates":[-73.109013,41.810353],"type":"Point"}
}