{
  "type": "Feature",
  "properties": {
    "addr:full":"29 High St Niantic CT 06357",
    "addr:housenumber":"29",
    "addr:postcode":"06357",
    "addr:street":"High St",
    "iso:country":"US",
    "sg:address":"29 High St",
    "sg:city":"Niantic",
    "sg:classifiers":[
        {
            "category":"Professional",
            "subcategory":"Business Services",
            "type":"Services"
        }
    ],
    "sg:phone":"+1   ",
    "sg:postcode":"06357",
    "sg:province":"CT",
    "wof:name":"Workplace Interiors",
    "wof:placetype":"venue"
},
  "geometry": {"coordinates":[-72.18740699999999,41.335627],"type":"Point"}
}