{
  "type": "Feature",
  "properties": {
    "iso:country":"US",
    "sg:address":"8 Sunny Ln",
    "sg:city":"Westport",
    "sg:classifiers":[
        {
            "category":"Professional",
            "subcategory":"Management & Consulting",
            "type":"Services"
        }
    ],
    "sg:phone":"+1 203 226 0344",
    "sg:postcode":"06880",
    "sg:province":"CT",
    "sg:tags":[
        "marketing",
        "program"
    ],
    "wof:name":"Retail Marketing Inc",
    "wof:placetype":"venue"
},
  "geometry": {"coordinates":[-73.370662,41.162709],"type":"Point"}
}