{
  "type": "Feature",
  "properties": {
    "iso:country":"US",
    "sg:address":"1087 Broad St",
    "sg:city":"Bridgeport",
    "sg:classifiers":[
        {
            "category":"Banks & Credit Unions",
            "subcategory":"Financial Services",
            "type":"Services"
        }
    ],
    "sg:phone":"+1 203 367 8383",
    "sg:postcode":"06604",
    "sg:province":"CT",
    "sg:tags":[
        "co",
        "bank",
        "holding"
    ],
    "wof:name":"Urban Financial Group Inc",
    "wof:placetype":"venue"
},
  "geometry": {"coordinates":[-73.190832,41.177527],"type":"Point"}
}