{
  "type": "Feature",
  "properties": {
    "addr:full":"28 High St Chester CT 06412",
    "addr:housenumber":"28",
    "addr:postcode":"06412",
    "addr:street":"High St",
    "iso:country":"US",
    "sg:address":"28 High St",
    "sg:city":"Chester",
    "sg:classifiers":[
        {
            "category":"Professional",
            "subcategory":"Business Services",
            "type":"Services"
        }
    ],
    "sg:phone":"+1   ",
    "sg:postcode":"06412",
    "sg:province":"CT",
    "wof:name":"Empire Systems Design LLC",
    "wof:placetype":"venue"
},
  "geometry": {"coordinates":[-72.453608,41.404444],"type":"Point"}
}