{
  "type": "Feature",
  "properties": {
    "iso:country":"US",
    "sg:address":"2 Sherman St",
    "sg:city":"Fairfield",
    "sg:classifiers":[
        {
            "category":"Recreation",
            "type":"Entertainment"
        }
    ],
    "sg:phone":"+1 203 319 0627",
    "sg:postcode":"06475",
    "sg:province":"CT",
    "sg:tags":[
        "club",
        "baseball"
    ],
    "wof:name":"Fairfield National Little Lge",
    "wof:placetype":"venue"
},
  "geometry": {"coordinates":[-72.37604399999999,41.281983],"type":"Point"}
}