{
  "type": "Feature",
  "properties": {
    "addr:full":"893 Whalley Ave New Haven CT 06515",
    "addr:housenumber":"893",
    "addr:postcode":"06515",
    "addr:street":"Whalley Ave",
    "iso:country":"US",
    "sg:address":"893 Whalley Ave",
    "sg:city":"New Haven",
    "sg:classifiers":[
        {
            "category":"Shopping",
            "subcategory":"Clothing, Apparel, & Fashions",
            "type":"Retail Goods"
        }
    ],
    "sg:phone":"+1 203 389 9432",
    "sg:postcode":"06515",
    "sg:province":"CT",
    "wof:name":"Continental Moda",
    "wof:placetype":"venue"
},
  "geometry": {"coordinates":[-72.960258,41.32732],"type":"Point"}
}