{
  "type": "Feature",
  "properties": {
    "addr:full":"19 Woodpond Rd Hartford CT 06107",
    "addr:housenumber":"19",
    "addr:postcode":"06107",
    "addr:street":"Woodpond Rd",
    "iso:country":"US",
    "sg:address":"19 Woodpond Rd",
    "sg:city":"Hartford",
    "sg:classifiers":[
        {
            "category":"Education",
            "subcategory":"School",
            "type":"Public Place"
        }
    ],
    "sg:phone":"+1   ",
    "sg:postcode":"06107",
    "sg:province":"CT",
    "wof:name":"Unified Theater Inc",
    "wof:placetype":"venue"
},
  "geometry": {"coordinates":[-72.76204,41.732856],"type":"Point"}
}