{
  "type": "Feature",
  "properties": {
    "addr:full":"787 Nut Plains Rd Guilford CT 06437",
    "addr:housenumber":"787",
    "addr:postcode":"06437",
    "addr:street":"Nut Plains Rd",
    "iso:country":"US",
    "sg:address":"787 Nut Plains Rd",
    "sg:city":"Guilford",
    "sg:classifiers":[
        {
            "category":"Building & Trades",
            "subcategory":"Construction",
            "type":"Services"
        }
    ],
    "sg:phone":"+1 203 453 6115",
    "sg:postcode":"06437",
    "sg:province":"CT",
    "sg:tags":[
        "contractor"
    ],
    "wof:name":"RCK Builders Inc",
    "wof:placetype":"venue"
},
  "geometry": {"coordinates":[-72.687254,41.323223],"type":"Point"}
}