{
  "type": "Feature",
  "properties": {
    "iso:country":"US",
    "sg:address":"432 N Main St",
    "sg:city":"Port Chester",
    "sg:classifiers":[
        {
            "category":"Retail",
            "subcategory":"Veterinary Services",
            "type":"Services"
        }
    ],
    "sg:phone":"+1 914 939 2388",
    "sg:postcode":"10573",
    "sg:province":"CT",
    "wof:name":"Howard B Levy",
    "wof:placetype":"venue"
},
  "geometry": {"coordinates":[-73.656446,41.009663],"type":"Point"}
}