{
  "type": "Feature",
  "properties": {
    "iso:country":"US",
    "sg:address":"384 Stillson Rd",
    "sg:city":"Waterbury",
    "sg:classifiers":[
        {
            "category":"Personal",
            "subcategory":"Beauty Salon",
            "type":"Services"
        }
    ],
    "sg:phone":"+1   ",
    "sg:postcode":"06705",
    "sg:province":"CT",
    "sg:tags":[
        "shop"
    ],
    "wof:name":"Omni Hair Design",
    "wof:placetype":"venue"
},
  "geometry": {"coordinates":[-73.008466,41.565005],"type":"Point"}
}