{
  "type": "Feature",
  "properties": {
    "addr:full":"225 Slater St Manchester CT 06042",
    "addr:housenumber":"225",
    "addr:postcode":"06042",
    "addr:street":"Slater St",
    "iso:country":"US",
    "sg:address":"225 Slater St",
    "sg:city":"Manchester",
    "sg:classifiers":[
        {
            "category":"Professional",
            "subcategory":"Management & Consulting",
            "type":"Services"
        }
    ],
    "sg:phone":"+1   ",
    "sg:postcode":"06042",
    "sg:province":"CT",
    "wof:name":"Courtyard by Marriott Hartford",
    "wof:placetype":"venue"
},
  "geometry": {"coordinates":[-72.53556399999999,41.812971],"type":"Point"}
}