{
  "type": "Feature",
  "properties": {
    "addr:full":"33 E Cedar St Newington CT 06111",
    "addr:housenumber":"33",
    "addr:postcode":"06111",
    "addr:street":"E Cedar St",
    "iso:country":"US",
    "sg:address":"33 E Cedar St",
    "sg:city":"Newington",
    "sg:classifiers":[
        {
            "category":"Shopping",
            "subcategory":"Clothing, Apparel, & Fashions",
            "type":"Retail Goods"
        }
    ],
    "sg:phone":"+1 860 666 9813",
    "sg:postcode":"06111",
    "sg:province":"CT",
    "wof:name":"Anthony Romas Custom Tailoring",
    "wof:placetype":"venue"
},
  "geometry": {"coordinates":[-72.721174,41.698118],"type":"Point"}
}