{
  "type": "Feature",
  "properties": {
    "addr:full":"257 Hart St Bristol CT 06010",
    "addr:housenumber":"257",
    "addr:postcode":"06010",
    "addr:street":"Hart St",
    "iso:country":"US",
    "sg:address":"257 Hart St",
    "sg:city":"Bristol",
    "sg:classifiers":[
        {
            "category":"Retail",
            "subcategory":"Portrait Studio",
            "type":"Services"
        }
    ],
    "sg:phone":"+1   ",
    "sg:postcode":"06010",
    "sg:province":"CT",
    "sg:tags":[
        "photo"
    ],
    "wof:name":"Dinneen Photography LLC",
    "wof:placetype":"venue"
},
  "geometry": {"coordinates":[-72.95759200000001,41.70831],"type":"Point"}
}