{
  "type": "Feature",
  "properties": {
    "addr:full":"1327 King St Greenwich CT 06831",
    "addr:housenumber":"1327",
    "addr:postcode":"06831",
    "addr:street":"King St Greenwich Ct",
    "iso:country":"US",
    "sg:address":"1327 King St",
    "sg:city":"Greenwich",
    "sg:classifiers":[
        {
            "category":"Health Services",
            "subcategory":"Doctor",
            "type":"Services"
        }
    ],
    "sg:phone":"+1 203 531 3271",
    "sg:postcode":"06831",
    "sg:province":"CT",
    "sg:tags":[
        "clinic"
    ],
    "wof:name":"Greenwich Emergency Med Svc",
    "wof:placetype":"venue"
},
  "geometry": {"coordinates":[-73.704399,41.077213],"type":"Point"}
}