{
  "type": "Feature",
  "properties": {
    "addr:full":"62 Gerik Rd Stamford CT 06905",
    "addr:housenumber":"62",
    "addr:postcode":"06905",
    "addr:street":"Gerik Rd",
    "iso:country":"US",
    "sg:address":"62 Gerik Rd",
    "sg:city":"Stamford",
    "sg:classifiers":[
        {
            "category":"Professional",
            "subcategory":"Computer Services",
            "type":"Services"
        }
    ],
    "sg:phone":"+1   ",
    "sg:postcode":"06905",
    "sg:province":"CT",
    "sg:tags":[
        "datum"
    ],
    "wof:name":"Bryanas Boutique",
    "wof:placetype":"venue"
},
  "geometry": {"coordinates":[-73.54634299999999,41.105296],"type":"Point"}
}