{
  "type": "Feature",
  "properties": {
    "addr:full":"72 Compo Rd S Westport CT 06880",
    "addr:housenumber":"72",
    "addr:postcode":"06880",
    "addr:street":"Compo Rd S",
    "iso:country":"US",
    "sg:address":"72 Compo Rd S",
    "sg:city":"Westport",
    "sg:classifiers":[
        {
            "category":"Real Estate",
            "subcategory":"Real Estate Operator",
            "type":"Services"
        }
    ],
    "sg:phone":"+1 917 697 0173",
    "sg:postcode":"06880",
    "sg:province":"CT",
    "sg:tags":[
        "building",
        "nonresidential"
    ],
    "wof:name":"Sarex CT Properties LLC",
    "wof:placetype":"venue"
},
  "geometry": {"coordinates":[-73.35372,41.138988],"type":"Point"}
}