{
  "type": "Feature",
  "properties": {
    "addr:full":"1362 Bank St Waterbury CT 06708",
    "addr:housenumber":"1362",
    "addr:postcode":"06708",
    "addr:street":"Bank St Waterbury Ct",
    "iso:country":"US",
    "sg:address":"1362 Bank St",
    "sg:city":"Waterbury",
    "sg:classifiers":[
        {
            "category":"Professional",
            "type":"Services"
        }
    ],
    "sg:phone":"+1 203 591 1841",
    "sg:postcode":"06708",
    "sg:province":"CT",
    "wof:name":"Spartan Services",
    "wof:placetype":"venue"
},
  "geometry": {"coordinates":[-73.047746,41.539366],"type":"Point"}
}