{
  "type": "Feature",
  "properties": {
    "iso:country":"US",
    "sg:address":"294 Noble Ave",
    "sg:city":"Bridgeport",
    "sg:classifiers":[
        {
            "category":"Organizations",
            "subcategory":"Religious Organization",
            "type":"Services"
        }
    ],
    "sg:phone":"+1   ",
    "sg:postcode":"06608",
    "sg:province":"CT",
    "wof:name":"Chaste & C Outreach Ministries",
    "wof:placetype":"venue"
},
  "geometry": {"coordinates":[-73.18448100000001,41.185162],"type":"Point"}
}