{
  "type": "Feature",
  "properties": {
    "addr:full":"8 Sojo Rd Brookfield CT 06804",
    "addr:housenumber":"8",
    "addr:postcode":"06804",
    "addr:street":"Sojo Rd",
    "iso:country":"US",
    "sg:address":"8 Sojo Rd",
    "sg:city":"Brookfield",
    "sg:classifiers":[
        {
            "category":"Professional",
            "subcategory":"Business Services",
            "type":"Services"
        }
    ],
    "sg:phone":"+1 203 740 7970",
    "sg:postcode":"06804",
    "sg:province":"CT",
    "sg:tags":[
        "convention",
        "meeting",
        "facility"
    ],
    "wof:name":"Group Meetings Inc",
    "wof:placetype":"venue"
},
  "geometry": {"coordinates":[-73.405681,41.500819],"type":"Point"}
}