{
  "type": "Feature",
  "properties": {
    "addr:full":"720 Hopmeadow St Simsbury CT 06070",
    "addr:housenumber":"720",
    "addr:postcode":"06070",
    "addr:street":"Hopmeadow St Simsbury Ct",
    "iso:country":"US",
    "sg:address":"720 Hopmeadow St",
    "sg:city":"Simsbury",
    "sg:classifiers":[
        {
            "category":"Health Services",
            "subcategory":"Doctor",
            "type":"Services"
        }
    ],
    "sg:phone":"+1 860 651 3519",
    "sg:postcode":"06070",
    "sg:province":"CT",
    "wof:name":"Cappadona John T MD",
    "wof:placetype":"venue"
},
  "geometry": {"coordinates":[-72.80259700000001,41.872299],"type":"Point"}
}