{
  "type": "Feature",
  "properties": {
    "addr:full":"45 Avery Hill Rd Ledyard CT 06339",
    "addr:housenumber":"45",
    "addr:postcode":"06339",
    "addr:street":"Avery Hill Rd Ledyard Ct",
    "iso:country":"US",
    "sg:address":"45 Avery Hill Rd",
    "sg:city":"Ledyard",
    "sg:classifiers":[
        {
            "category":"Personal",
            "subcategory":"Beauty Salon",
            "type":"Services"
        }
    ],
    "sg:phone":"+1   ",
    "sg:postcode":"06339",
    "sg:province":"CT",
    "sg:tags":[
        "shop"
    ],
    "wof:name":"Headlines Hair & Skin Design",
    "wof:placetype":"venue"
},
  "geometry": {"coordinates":[-72.046673,41.454732],"type":"Point"}
}