{
  "type": "Feature",
  "properties": {
    "addr:full":"61 W Hartford Rd East Hartford CT 06111",
    "addr:housenumber":"61",
    "addr:postcode":"06111",
    "addr:street":"W Hartford Rd East;Ct",
    "iso:country":"US",
    "sg:address":"61 W Hartford Rd",
    "sg:city":"East Hartford",
    "sg:classifiers":[
        {
            "category":"Professional",
            "subcategory":"Lawyer & Legal Services",
            "type":"Services"
        }
    ],
    "sg:phone":"+1   ",
    "sg:postcode":"06111",
    "sg:province":"CT",
    "sg:tags":[
        "law"
    ],
    "wof:name":"McCarthy Donald J Jr",
    "wof:placetype":"venue"
},
  "geometry": {"coordinates":[-72.74284900000001,41.71712],"type":"Point"}
}