{
  "type": "Feature",
  "properties": {
    "addr:full":"162 Oaklawn Ave Stamford CT 06905",
    "addr:housenumber":"162",
    "addr:postcode":"06905",
    "addr:street":"Oaklawn Ave",
    "iso:country":"US",
    "sg:address":"162 Oaklawn Ave",
    "sg:city":"Stamford",
    "sg:classifiers":[
        {
            "category":"Professional",
            "subcategory":"Business Services",
            "type":"Services"
        }
    ],
    "sg:phone":"+1   ",
    "sg:postcode":"06905",
    "sg:province":"CT",
    "wof:name":"David Salvino",
    "wof:placetype":"venue"
},
  "geometry": {"coordinates":[-73.539936,41.07947],"type":"Point"}
}