{
  "type": "Feature",
  "properties": {
    "addr:full":"77 Hemlock Ridge Berlin CT 06037",
    "addr:housenumber":"77",
    "addr:postcode":"06037",
    "addr:street":"Hemlock Ridge",
    "iso:country":"US",
    "sg:address":"77 Hemlock Ridge",
    "sg:city":"Berlin",
    "sg:classifiers":[
        {
            "category":"Professional",
            "subcategory":"Engineering",
            "type":"Services"
        }
    ],
    "sg:phone":"+1   ",
    "sg:postcode":"06037",
    "sg:province":"CT",
    "wof:name":"Polaske R T & Associates LLC",
    "wof:placetype":"venue"
},
  "geometry": {"coordinates":[-72.794735,41.621522],"type":"Point"}
}