{
  "type": "Feature",
  "properties": {
    "iso:country":"US",
    "sg:address":"2 Society Rd",
    "sg:city":"Niantic",
    "sg:classifiers":[
        {
            "category":"Home & Garden",
            "subcategory":"Garden Supply",
            "type":"Retail Goods"
        },
        {
            "category":"Manufacturing",
            "subcategory":"Paper Products",
            "type":"Manufacturing & Wholesale Goods"
        }
    ],
    "sg:phone":"+1 860 739 6881",
    "sg:postcode":"06357",
    "sg:province":"CT",
    "sg:tags":[
        "bamboo"
    ],
    "wof:name":"Clauson's Nursery",
    "wof:placetype":"venue"
},
  "geometry": {"coordinates":[-72.209732,41.346779],"type":"Point"}
}