{
  "type": "Feature",
  "properties": {
    "addr:full":"75 Highland Ave Bridgeport CT 06604",
    "addr:housenumber":"75",
    "addr:postcode":"06604",
    "addr:street":"Highland Ave",
    "iso:country":"US",
    "sg:address":"75 Highland Ave",
    "sg:city":"Bridgeport",
    "sg:classifiers":[
        {
            "category":"Communications",
            "subcategory":"Film & Video Production",
            "type":"Services"
        }
    ],
    "sg:phone":"+1   ",
    "sg:postcode":"06604",
    "sg:province":"CT",
    "sg:tags":[
        "motion"
    ],
    "wof:name":"Sainvil Mirlande",
    "wof:placetype":"venue"
},
  "geometry": {"coordinates":[-73.196325,41.183232],"type":"Point"}
}