{
  "type": "Feature",
  "properties": {
    "iso:country":"US",
    "sg:address":"61 E Albert St",
    "sg:city":"Torrington",
    "sg:classifiers":[
        {
            "category":"Recreation",
            "type":"Entertainment"
        }
    ],
    "sg:phone":"+1   ",
    "sg:postcode":"06790",
    "sg:province":"CT",
    "wof:name":"Torrington Parks & Recreation",
    "wof:placetype":"venue"
},
  "geometry": {"coordinates":[-73.119128,41.79587],"type":"Point"}
}