{
  "type": "Feature",
  "properties": {
    "iso:country":"US",
    "sg:address":"75 Glen Rd",
    "sg:city":"Sandy Hook",
    "sg:classifiers":[
        {
            "category":"Professional",
            "subcategory":"Accounting & Tax Preparation",
            "type":"Services"
        }
    ],
    "sg:phone":"+1 203 426 7834",
    "sg:postcode":"06482",
    "sg:province":"CT",
    "sg:tags":[
        "bookkeeping",
        "general"
    ],
    "wof:name":"Eastern Account System Inc",
    "wof:placetype":"venue"
},
  "geometry": {"coordinates":[-73.275572,41.432175],"type":"Point"}
}