{
  "type": "Feature",
  "properties": {
    "addr:full":"273 Lexington Ave Bridgeport CT 06604",
    "addr:housenumber":"273",
    "addr:postcode":"06604",
    "addr:street":"Lexington Ave",
    "iso:country":"US",
    "sg:address":"273 Lexington Ave",
    "sg:city":"Bridgeport",
    "sg:classifiers":[
        {
            "category":"Restaurant",
            "type":"Food & Drink"
        }
    ],
    "sg:phone":"+1 203 336 5611",
    "sg:postcode":"06604",
    "sg:province":"CT",
    "sg:tags":[
        "pizza"
    ],
    "wof:name":"Pizza Valley",
    "wof:placetype":"venue"
},
  "geometry": {"coordinates":[-73.1985,41.184311],"type":"Point"}
}