{
  "type": "Feature",
  "properties": {
    "iso:country":"US",
    "sg:address":"140 Pine St",
    "sg:city":"Bristol",
    "sg:classifiers":[
        {
            "category":"Professional",
            "subcategory":"Management & Consulting",
            "type":"Services"
        }
    ],
    "sg:phone":"+1   ",
    "sg:postcode":"06010",
    "sg:province":"CT",
    "wof:name":"Medical Arts Hlth & Ntrtn Ctr",
    "wof:placetype":"venue"
},
  "geometry": {"coordinates":[-72.916291,41.668088],"type":"Point"}
}