{
  "type": "Feature",
  "properties": {
    "addr:full":"8 S Kent Rd South Kent CT 06785",
    "addr:housenumber":"8",
    "addr:postcode":"06785",
    "addr:street":"S Kent Rd South Kent Ct",
    "iso:country":"US",
    "sg:address":"8 S Kent Rd",
    "sg:city":"South Kent",
    "sg:classifiers":[
        {
            "category":"Retail",
            "subcategory":"Portrait Studio",
            "type":"Services"
        }
    ],
    "sg:phone":"+1   ",
    "sg:postcode":"06785",
    "sg:province":"CT",
    "sg:tags":[
        "photo"
    ],
    "wof:name":"Richard Felber Photographor",
    "wof:placetype":"venue"
},
  "geometry": {"coordinates":[-73.47531499999999,41.710441],"type":"Point"}
}