{
  "type": "Feature",
  "properties": {
    "addr:full":"232 Mill St Greenwich CT 06830",
    "addr:housenumber":"232",
    "addr:postcode":"06830",
    "addr:street":"Mill St Greenwich Ct",
    "iso:country":"US",
    "sg:address":"232 Mill St",
    "sg:city":"Greenwich",
    "sg:classifiers":[
        {
            "category":"Personal",
            "subcategory":"Beauty Salon",
            "type":"Services"
        }
    ],
    "sg:phone":"+1   ",
    "sg:postcode":"06830",
    "sg:province":"CT",
    "sg:tags":[
        "shop"
    ],
    "wof:name":"Mane Event",
    "wof:placetype":"venue"
},
  "geometry": {"coordinates":[-73.657563,41.00369],"type":"Point"}
}