{
  "type": "Feature",
  "properties": {
    "iso:country":"US",
    "sg:address":"52 Santo Ct",
    "sg:city":"New Britain",
    "sg:classifiers":[
        {
            "category":"Restaurant",
            "type":"Food & Drink"
        }
    ],
    "sg:phone":"+1 860 223 8282",
    "sg:postcode":"06053",
    "sg:province":"CT",
    "sg:tags":[
        "eating"
    ],
    "wof:name":"Fortuna Gourmet Caterers",
    "wof:placetype":"venue"
},
  "geometry": {"coordinates":[-72.783219,41.695909],"type":"Point"}
}