{
  "type": "Feature",
  "properties": {
    "iso:country":"US",
    "sg:address":"1041 Poquonnock Rd",
    "sg:city":"Groton",
    "sg:classifiers":[
        {
            "category":"Organizations",
            "subcategory":"Religious Organization",
            "type":"Services"
        }
    ],
    "sg:phone":"+1   ",
    "sg:postcode":"06340",
    "sg:province":"CT",
    "wof:name":"Stedfast Baptist Church",
    "wof:placetype":"venue"
},
  "geometry": {"coordinates":[-72.047899,41.34627],"type":"Point"}
}