{
  "type": "Feature",
  "properties": {
    "addr:full":"2624 Main St Bridgeport CT 06606",
    "addr:housenumber":"2624",
    "addr:postcode":"06606",
    "addr:street":"Main St",
    "iso:country":"US",
    "sg:address":"2624 Main St",
    "sg:city":"Bridgeport",
    "sg:classifiers":[
        {
            "category":"Retail",
            "subcategory":"Laundry & Dry Cleaning",
            "type":"Services"
        }
    ],
    "sg:phone":"+1   ",
    "sg:postcode":"06606",
    "sg:province":"CT",
    "wof:name":"Family Tailor Shop",
    "wof:placetype":"venue"
},
  "geometry": {"coordinates":[-73.20142,41.198424],"type":"Point"}
}