{
  "type": "Feature",
  "properties": {
    "addr:full":"99 Cedar Grove Rd Southbury CT 06488",
    "addr:housenumber":"99",
    "addr:postcode":"06488",
    "addr:street":"Cedar Grove Rd",
    "iso:country":"US",
    "sg:address":"99 Cedar Grove Rd",
    "sg:city":"Southbury",
    "sg:classifiers":[
        {
            "category":"Education",
            "subcategory":"School",
            "type":"Public Place"
        }
    ],
    "sg:phone":"+1   ",
    "sg:postcode":"06488",
    "sg:province":"CT",
    "wof:name":"Eddie Wilson Special Educ",
    "wof:placetype":"venue"
},
  "geometry": {"coordinates":[-73.199173,41.505856],"type":"Point"}
}