{
  "type": "Feature",
  "properties": {
    "addr:full":"6 Hickory Ln Seymour CT 06483",
    "addr:housenumber":"6",
    "addr:postcode":"06483",
    "addr:street":"Hickory Ln",
    "iso:country":"US",
    "sg:address":"6 Hickory Ln",
    "sg:city":"Seymour",
    "sg:classifiers":[
        {
            "category":"Building & Trades",
            "subcategory":"Cleaning & Sanitation",
            "type":"Services"
        }
    ],
    "sg:phone":"+1   ",
    "sg:postcode":"06483",
    "sg:province":"CT",
    "sg:tags":[
        "maintenance"
    ],
    "wof:name":"Eagle Cleaning Service",
    "wof:placetype":"venue"
},
  "geometry": {"coordinates":[-73.067419,41.380504],"type":"Point"}
}