{
  "type": "Feature",
  "properties": {
    "iso:country":"US",
    "sg:address":"1207 Main St",
    "sg:city":"Glastonbury",
    "sg:classifiers":[
        {
            "category":"Shopping",
            "type":"Retail Goods"
        }
    ],
    "sg:phone":"+1 860 657 4709",
    "sg:postcode":"06033",
    "sg:province":"CT",
    "sg:tags":[
        "specialty",
        "merchandise",
        "mfg"
    ],
    "wof:name":"Swahn Engraving LLC",
    "wof:placetype":"venue"
},
  "geometry": {"coordinates":[-72.598831,41.678597],"type":"Point"}
}