{
  "type": "Feature",
  "properties": {
    "iso:country":"US",
    "sg:address":"5 Amity Rd",
    "sg:city":"Bethany",
    "sg:classifiers":[
        {
            "category":"Farming",
            "subcategory":"Farm",
            "type":"Manufacturing & Wholesale Goods"
        }
    ],
    "sg:phone":"+1 203 393 3403",
    "sg:postcode":"06524",
    "sg:province":"CT",
    "wof:name":"Nova Farms",
    "wof:placetype":"venue"
},
  "geometry": {"coordinates":[-73.000563,41.391024],"type":"Point"}
}