{
  "type": "Feature",
  "properties": {
    "iso:country":"US",
    "sg:address":"355 Rainbow Rd",
    "sg:city":"Windsor",
    "sg:classifiers":[
        {
            "category":"Professional",
            "type":"Services"
        }
    ],
    "sg:phone":"+1 860 688 8123",
    "sg:postcode":"06095",
    "sg:province":"CT",
    "wof:name":"Whisperwood Inc",
    "wof:placetype":"venue"
},
  "geometry": {"coordinates":[-72.697399,41.918561],"type":"Point"}
}