{
  "type": "Feature",
  "properties": {
    "addr:full":"46 Ebony Ln Ivoryton CT 06442",
    "addr:housenumber":"46",
    "addr:postcode":"06442",
    "addr:street":"Ebony Ln Ivoryton Ct",
    "iso:country":"US",
    "sg:address":"46 Ebony Ln",
    "sg:city":"Ivoryton",
    "sg:classifiers":[
        {
            "category":"Professional",
            "subcategory":"Management & Consulting",
            "type":"Services"
        }
    ],
    "sg:phone":"+1   ",
    "sg:postcode":"06442",
    "sg:province":"CT",
    "wof:name":"Creative Marketing Services",
    "wof:placetype":"venue"
},
  "geometry": {"coordinates":[-72.45394,41.347003],"type":"Point"}
}