{
  "type": "Feature",
  "properties": {
    "iso:country":"US",
    "sg:address":"335 W Main St",
    "sg:city":"Stamford",
    "sg:classifiers":[
        {
            "category":"Food & Beverages",
            "subcategory":"Groceries & Convenience Stores",
            "type":"Retail Goods"
        }
    ],
    "sg:phone":"+1 203 327 9560",
    "sg:postcode":"06902",
    "sg:province":"CT",
    "wof:name":"En-Bas-Marche-En-Bas",
    "wof:placetype":"venue"
},
  "geometry": {"coordinates":[-73.552779,41.048165],"type":"Point"}
}