{
  "type": "Feature",
  "properties": {
    "addr:full":"58 Broad St Torrington CT 06790",
    "addr:housenumber":"58",
    "addr:postcode":"06790",
    "addr:street":"Broad St",
    "iso:country":"US",
    "sg:address":"58 Broad St",
    "sg:city":"Torrington",
    "sg:classifiers":[
        {
            "category":"Utilities",
            "subcategory":"Refuse",
            "type":"Services"
        }
    ],
    "sg:phone":"+1 860 626 0394",
    "sg:postcode":"06790",
    "sg:province":"CT",
    "sg:tags":[
        "system"
    ],
    "wof:name":"Mr Canman Hauling & Recycling",
    "wof:placetype":"venue"
},
  "geometry": {"coordinates":[-73.123012,41.791581],"type":"Point"}
}