{
  "type": "Feature",
  "properties": {
    "iso:country":"US",
    "sg:address":"45 Church St Suite 302F",
    "sg:city":"Stamford",
    "sg:classifiers":[
        {
            "category":"Social Services",
            "type":"Services"
        },
        {
            "category":"Health Services",
            "subcategory":"Nursing And Care Facility",
            "type":"Services"
        },
        {
            "category":"Health Services",
            "subcategory":"Health Practitioner",
            "type":"Services"
        },
        {
            "category":"Social Services",
            "subcategory":"Adult Care",
            "type":"Services"
        }
    ],
    "sg:phone":"+1 203 883 8560",
    "sg:postcode":"06906",
    "sg:province":"CT",
    "sg:tags":[
        "living",
        "consulting",
        "geriatric",
        "alzheimer's",
        "assisted",
        "elder",
        "home",
        "nurse",
        "eldercare-home"
    ],
    "sg:website":"http://www.brightstarcare.com/find-a-location/ct/greenwich/",
    "wof:name":"BrightStar - Greenwich",
    "wof:placetype":"venue"
},
  "geometry": {"coordinates":[-73.52179599999999,41.071081],"type":"Point"}
}