{
  "type": "Feature",
  "properties": {
    "addr:full":"38 Walnut Grove Rd Ridgefield CT 06877",
    "addr:housenumber":"38",
    "addr:postcode":"06877",
    "addr:street":"Walnut Grove Rd",
    "iso:country":"US",
    "sg:address":"38 Walnut Grove Rd",
    "sg:city":"Ridgefield",
    "sg:classifiers":[
        {
            "category":"Health Services",
            "subcategory":"Health Practitioner",
            "type":"Services"
        }
    ],
    "sg:phone":"+1   ",
    "sg:postcode":"06877",
    "sg:province":"CT",
    "wof:name":"Richfield Podiatrist Assoc",
    "wof:placetype":"venue"
},
  "geometry": {"coordinates":[-73.473158,41.294005],"type":"Point"}
}