{
  "type": "Feature",
  "properties": {
    "addr:full":"433 Little City Rd Higganum CT 06441",
    "addr:housenumber":"433",
    "addr:postcode":"06441",
    "addr:street":"Little City Rd Higganum Ct",
    "iso:country":"US",
    "sg:address":"433 Little City Rd",
    "sg:city":"Higganum",
    "sg:classifiers":[
        {
            "category":"Building & Trades",
            "subcategory":"Construction",
            "type":"Services"
        }
    ],
    "sg:phone":"+1 860 345 4516",
    "sg:postcode":"06441",
    "sg:province":"CT",
    "sg:tags":[
        "hanging",
        "contractor"
    ],
    "wof:name":"Patrick T Daly Painting Co",
    "wof:placetype":"venue"
},
  "geometry": {"coordinates":[-72.590929,41.447541],"type":"Point"}
}