{
  "type": "Feature",
  "properties": {
    "addr:full":"22 Ellery Ln Westport CT 06880",
    "addr:housenumber":"22",
    "addr:postcode":"06880",
    "addr:street":"Ellery Ln",
    "iso:country":"US",
    "sg:address":"22 Ellery Ln",
    "sg:city":"Westport",
    "sg:classifiers":[
        {
            "category":"Professional",
            "type":"Services"
        }
    ],
    "sg:phone":"+1 203 227 1032",
    "sg:postcode":"06880",
    "sg:province":"CT",
    "wof:name":"Distatec LLC",
    "wof:placetype":"venue"
},
  "geometry": {"coordinates":[-73.33960999999999,41.133332],"type":"Point"}
}