{
  "type": "Feature",
  "properties": {
    "addr:full":"56 Elm St Danbury CT 06810",
    "addr:housenumber":"56",
    "addr:postcode":"06810",
    "addr:street":"Elm St",
    "iso:country":"US",
    "sg:address":"56 Elm St",
    "sg:city":"Danbury",
    "sg:classifiers":[
        {
            "category":"Autos & Motor Vehicles",
            "subcategory":"Auto Supplies",
            "type":"Retail Goods"
        }
    ],
    "sg:phone":"+1 203 744 0351",
    "sg:postcode":"06810",
    "sg:province":"CT",
    "sg:tags":[
        "automobile",
        "stereo",
        "radio"
    ],
    "wof:name":"J J Audio",
    "wof:placetype":"venue"
},
  "geometry": {"coordinates":[-73.456712,41.395704],"type":"Point"}
}