{
  "type": "Feature",
  "properties": {
    "addr:full":"1080 Main St S Woodbury CT 06798",
    "addr:housenumber":"1080",
    "addr:postcode":"06798",
    "addr:street":"Main St S Woodbury Ct",
    "iso:country":"US",
    "sg:address":"1080 Main St S",
    "sg:city":"Woodbury",
    "sg:classifiers":[
        {
            "category":"Social Services",
            "type":"Services"
        }
    ],
    "sg:phone":"+1   ",
    "sg:postcode":"06798",
    "sg:province":"CT",
    "wof:name":"David Vanhandel Lcsw",
    "wof:placetype":"venue"
},
  "geometry": {"coordinates":[-73.204503,41.513456],"type":"Point"}
}