{
  "type": "Feature",
  "properties": {
    "iso:country":"US",
    "sg:address":"101 Belden Hill Rd",
    "sg:city":"Wilton",
    "sg:classifiers":[
        {
            "category":"Building & Trades",
            "subcategory":"Cleaning & Sanitation",
            "type":"Services"
        }
    ],
    "sg:phone":"+1 203 762 0351",
    "sg:postcode":"06897",
    "sg:province":"CT",
    "sg:tags":[
        "window"
    ],
    "wof:name":"American Window Cleaning",
    "wof:placetype":"venue"
},
  "geometry": {"coordinates":[-73.442213,41.190871],"type":"Point"}
}