{
  "type": "Feature",
  "properties": {
    "addr:full":"1 Station Pl Stamford CT 06902",
    "addr:housenumber":"1",
    "addr:postcode":"06902",
    "addr:street":"Station Pl",
    "iso:country":"US",
    "sg:address":"1 Station Pl",
    "sg:city":"Stamford",
    "sg:classifiers":[
        {
            "category":"Professional",
            "subcategory":"Advertising",
            "type":"Services"
        }
    ],
    "sg:phone":"+1 203 967 3100",
    "sg:postcode":"06902",
    "sg:province":"CT",
    "sg:website":"www.mni.com",
    "wof:name":"MEDIA Networks Inc",
    "wof:placetype":"venue"
},
  "geometry": {"coordinates":[-73.539349,41.047354],"type":"Point"}
}