{
  "type": "Feature",
  "properties": {
    "iso:country":"US",
    "sg:address":"26 Jefferson Rd",
    "sg:city":"Branford",
    "sg:classifiers":[
        {
            "category":"Organizations",
            "subcategory":"Religious Organization",
            "type":"Services"
        }
    ],
    "sg:phone":"+1 203 483 0629",
    "sg:postcode":"06405",
    "sg:province":"CT",
    "sg:tags":[
        "church"
    ],
    "wof:name":"New Life Apostolic Church",
    "wof:placetype":"venue"
},
  "geometry": {"coordinates":[-72.845502,41.278848],"type":"Point"}
}