{
  "type": "Feature",
  "properties": {
    "iso:country":"US",
    "sg:address":"560 Newfield Ave",
    "sg:city":"Bridgeport",
    "sg:classifiers":[
        {
            "category":"Organizations",
            "subcategory":"Community Association",
            "type":"Services"
        }
    ],
    "sg:phone":"+1   ",
    "sg:postcode":"06607",
    "sg:province":"CT",
    "wof:name":"Improved Benevolent & Pro",
    "wof:placetype":"venue"
},
  "geometry": {"coordinates":[-73.166982,41.176133],"type":"Point"}
}