{
  "type": "Feature",
  "properties": {
    "iso:country":"US",
    "sg:address":"5 Quarry Rd",
    "sg:city":"Milford",
    "sg:classifiers":[
        {
            "category":"Professional",
            "subcategory":"Management & Consulting",
            "type":"Services"
        }
    ],
    "sg:phone":"+1 203 877 5504",
    "sg:postcode":"06460",
    "sg:province":"CT",
    "sg:tags":[
        "personnel",
        "consultant"
    ],
    "wof:name":"Contemporary Personnel Svc Inc",
    "wof:placetype":"venue"
},
  "geometry": {"coordinates":[-73.016963,41.246541],"type":"Point"}
}