{
  "type": "Feature",
  "properties": {
    "iso:country":"US",
    "sg:address":"1426 Meriden Ave",
    "sg:city":"Milldale",
    "sg:classifiers":[
        {
            "category":"Shopping",
            "subcategory":"Bicycles & Sporting Goods",
            "type":"Retail Goods"
        }
    ],
    "sg:phone":"+1 860 621 8281",
    "sg:postcode":"06489",
    "sg:province":"CT",
    "wof:name":"Atlantic Wholesale Bait Co",
    "wof:placetype":"venue"
},
  "geometry": {"coordinates":[-72.852886,41.563608],"type":"Point"}
}