{
  "type": "Feature",
  "properties": {
    "iso:country":"US",
    "sg:address":"333 Vincellette St",
    "sg:city":"Bridgeport",
    "sg:classifiers":[
        {
            "category":"Professional",
            "subcategory":"Art Services",
            "type":"Services"
        }
    ],
    "sg:phone":"+1   ",
    "sg:postcode":"06606",
    "sg:province":"CT",
    "sg:tags":[
        "commercial",
        "design"
    ],
    "wof:name":"Wilhelm Gdale Elzabeth Designs",
    "wof:placetype":"venue"
},
  "geometry": {"coordinates":[-73.21943400000001,41.214854],"type":"Point"}
}