{
  "type": "Feature",
  "properties": {
    "addr:full":"5 Darina Pl Milford CT 06460",
    "addr:housenumber":"5",
    "addr:postcode":"06460",
    "addr:street":"Darina Pl",
    "iso:country":"US",
    "sg:address":"5 Darina Pl",
    "sg:city":"Milford",
    "sg:classifiers":[
        {
            "category":"Building & Trades",
            "subcategory":"Construction",
            "type":"Services"
        }
    ],
    "sg:phone":"+1 203 878 9164",
    "sg:postcode":"06460",
    "sg:province":"CT",
    "sg:tags":[
        "roofing",
        "contractor"
    ],
    "wof:name":"Pioneer Contractors LLC",
    "wof:placetype":"venue"
},
  "geometry": {"coordinates":[-73.05804500000001,41.223913],"type":"Point"}
}