{
  "type": "Feature",
  "properties": {
    "addr:full":"21 Dairy Farm Dr Brookfield CT 06804",
    "addr:housenumber":"21",
    "addr:postcode":"06804",
    "addr:street":"Dairy Farm Dr",
    "iso:country":"US",
    "sg:address":"21 Dairy Farm Dr",
    "sg:city":"Brookfield",
    "sg:classifiers":[
        {
            "category":"Shopping",
            "subcategory":"Clothing, Apparel, & Fashions",
            "type":"Retail Goods"
        }
    ],
    "sg:phone":"+1 203 470 8940",
    "sg:postcode":"06804",
    "sg:province":"CT",
    "sg:tags":[
        "family"
    ],
    "wof:name":"Thehuskyanglercom",
    "wof:placetype":"venue"
},
  "geometry": {"coordinates":[-73.376679,41.430809],"type":"Point"}
}