{
  "type": "Feature",
  "properties": {
    "addr:full":"1297 Park Ave Bridgeport CT 06604",
    "addr:housenumber":"1297",
    "addr:postcode":"06604",
    "addr:street":"Park Ave",
    "iso:country":"US",
    "sg:address":"1297 Park Ave",
    "sg:city":"Bridgeport",
    "sg:classifiers":[
        {
            "category":"Wholesale",
            "subcategory":"Office Equipment",
            "type":"Manufacturing & Wholesale Goods"
        }
    ],
    "sg:phone":"+1 203 367 7734",
    "sg:postcode":"06604",
    "sg:province":"CT",
    "sg:tags":[
        "accounting",
        "bookkeeping",
        "system"
    ],
    "sg:website":"www.computerpayroll.com",
    "wof:name":"Computer Payroll Svc",
    "wof:placetype":"venue"
},
  "geometry": {"coordinates":[-73.202618,41.179086],"type":"Point"}
}