{
  "type": "Feature",
  "properties": {
    "iso:country":"US",
    "sg:address":"100 Center St",
    "sg:city":"Shelton",
    "sg:classifiers":[
        {
            "category":"Professional",
            "type":"Services"
        }
    ],
    "sg:phone":"+1 203 924 2622",
    "sg:postcode":"06484",
    "sg:province":"CT",
    "sg:tags":[
        "establishment"
    ],
    "wof:name":"Center Stage On Ctr Street",
    "wof:placetype":"venue"
},
  "geometry": {"coordinates":[-73.09394399999999,41.31618],"type":"Point"}
}