{
  "type": "Feature",
  "properties": {
    "addr:full":"960 S Main St Plantsville CT 06479",
    "addr:housenumber":"960",
    "addr:postcode":"06479",
    "addr:street":"S Main St",
    "iso:country":"US",
    "sg:address":"960 S Main St",
    "sg:city":"Plantsville",
    "sg:classifiers":[
        {
            "category":"Professional",
            "subcategory":"Business Services",
            "type":"Services"
        }
    ],
    "sg:phone":"+1   ",
    "sg:postcode":"06479",
    "sg:province":"CT",
    "wof:name":"Rsl Solutions LLC",
    "wof:placetype":"venue"
},
  "geometry": {"coordinates":[-72.892645,41.58379],"type":"Point"}
}