{
  "type": "Feature",
  "properties": {
    "addr:full":"231 Boston Post Rd East Lyme CT 06333",
    "addr:housenumber":"231",
    "addr:postcode":"06333",
    "addr:street":"Boston Post Rd East Lyme Ct",
    "iso:country":"US",
    "sg:address":"231 Boston Post Rd",
    "sg:city":"East Lyme",
    "sg:classifiers":[
        {
            "category":"Professional",
            "subcategory":"Art Services",
            "type":"Services"
        }
    ],
    "sg:phone":"+1   ",
    "sg:postcode":"06333",
    "sg:province":"CT",
    "sg:tags":[
        "commercial",
        "design",
        "typesetting"
    ],
    "wof:name":"Sk Systems",
    "wof:placetype":"venue"
},
  "geometry": {"coordinates":[-72.22182100000001,41.368473],"type":"Point"}
}