{
  "type": "Feature",
  "properties": {
    "addr:full":"236 Maple St Litchfield CT 06759",
    "addr:housenumber":"236",
    "addr:postcode":"06759",
    "addr:street":"Maple St",
    "iso:country":"US",
    "sg:address":"236 Maple St",
    "sg:city":"Litchfield",
    "sg:classifiers":[
        {
            "category":"Professional",
            "subcategory":"Business Services",
            "type":"Services"
        }
    ],
    "sg:phone":"+1   ",
    "sg:postcode":"06759",
    "sg:province":"CT",
    "wof:name":"J Galt Design",
    "wof:placetype":"venue"
},
  "geometry": {"coordinates":[-73.23736599999999,41.739929],"type":"Point"}
}