{
  "type": "Feature",
  "properties": {
    "addr:full":"441 Washington Ave North Haven CT 06473",
    "addr:housenumber":"441",
    "addr:postcode":"06473",
    "addr:street":"Washington Ave;Haven",
    "iso:country":"US",
    "sg:address":"441 Washington Ave",
    "sg:city":"North Haven",
    "sg:classifiers":[
        {
            "category":"Professional",
            "subcategory":"Advertising",
            "type":"Services"
        }
    ],
    "sg:phone":"+1 203 234 8300",
    "sg:postcode":"06473",
    "sg:province":"CT",
    "sg:tags":[
        "mail"
    ],
    "wof:name":"Connecticut Direct Mail",
    "wof:placetype":"venue"
},
  "geometry": {"coordinates":[-72.842394,41.411102],"type":"Point"}
}