{
  "type": "Feature",
  "properties": {
    "iso:country":"US",
    "sg:address":"434 Garfield Ave",
    "sg:city":"Bridgeport",
    "sg:classifiers":[
        {
            "category":"Personal",
            "subcategory":"Beauty Salon",
            "type":"Services"
        }
    ],
    "sg:phone":"+1 203 335 8422",
    "sg:postcode":"06606",
    "sg:province":"CT",
    "wof:name":"Crystal Hair Salon",
    "wof:placetype":"venue"
},
  "geometry": {"coordinates":[-73.209306,41.193392],"type":"Point"}
}