{
  "type": "Feature",
  "properties": {
    "addr:full":"2 Ives St Danbury CT 06810",
    "addr:housenumber":"2",
    "addr:postcode":"06810",
    "addr:street":"Ives St",
    "iso:country":"US",
    "sg:address":"2 Ives St",
    "sg:city":"Danbury",
    "sg:classifiers":[
        {
            "category":"Real Estate",
            "subcategory":"Developer",
            "type":"Services"
        }
    ],
    "sg:phone":"+1 203 790 8083",
    "sg:postcode":"06810",
    "sg:province":"CT",
    "wof:name":"R J Enterprises",
    "wof:placetype":"venue"
},
  "geometry": {"coordinates":[-73.453158,41.396598],"type":"Point"}
}