{
  "type": "Feature",
  "properties": {
    "addr:full":"74 Beachdale Ave Voluntown CT 06384",
    "addr:housenumber":"74",
    "addr:postcode":"06384",
    "addr:street":"Beachdale Ave Voluntown Ct",
    "iso:country":"US",
    "sg:address":"74 Beachdale Ave",
    "sg:city":"Voluntown",
    "sg:classifiers":[
        {
            "category":"Retail",
            "subcategory":"Funeral Services",
            "type":"Services"
        }
    ],
    "sg:phone":"+1   ",
    "sg:postcode":"06384",
    "sg:province":"CT",
    "wof:name":"Eternity At Sea Corporation",
    "wof:placetype":"venue"
},
  "geometry": {"coordinates":[-71.861745,41.577454],"type":"Point"}
}