{
  "type": "Feature",
  "properties": {
    "addr:full":"35 Fairview Dr Danbury CT 06810",
    "addr:housenumber":"35",
    "addr:postcode":"06810",
    "addr:street":"Fairview Dr",
    "iso:country":"US",
    "sg:address":"35 Fairview Dr",
    "sg:city":"Danbury",
    "sg:classifiers":[
        {
            "category":"Building & Trades",
            "subcategory":"Landscaping Services",
            "type":"Services"
        }
    ],
    "sg:phone":"+1 203 792 9588",
    "sg:postcode":"06810",
    "sg:province":"CT",
    "wof:name":"J&S Lawn & Landscape",
    "wof:placetype":"venue"
},
  "geometry": {"coordinates":[-73.46162,41.385084],"type":"Point"}
}