{
  "type": "Feature",
  "properties": {
    "iso:country":"US",
    "sg:address":"25 Boston Post Rd",
    "sg:city":"Madison",
    "sg:classifiers":[
        {
            "category":"Personal",
            "subcategory":"Beauty Salon",
            "type":"Services"
        }
    ],
    "sg:phone":"+1   ",
    "sg:postcode":"06443",
    "sg:province":"CT",
    "sg:tags":[
        "shop"
    ],
    "wof:name":"Hands Down",
    "wof:placetype":"venue"
},
  "geometry": {"coordinates":[-72.645246,41.285757],"type":"Point"}
}