{
  "type": "Feature",
  "properties": {
    "addr:full":"78 Railroad St New Milford CT 06776",
    "addr:housenumber":"78",
    "addr:postcode":"06776",
    "addr:street":"Railroad St",
    "iso:country":"US",
    "sg:address":"78 Railroad St",
    "sg:city":"New Milford",
    "sg:classifiers":[
        {
            "category":"Retail",
            "subcategory":"Laundry & Dry Cleaning",
            "type":"Services"
        }
    ],
    "sg:phone":"+1   ",
    "sg:postcode":"06776",
    "sg:province":"CT",
    "sg:tags":[
        "drycleaning",
        "plant"
    ],
    "wof:name":"Tommys Cleaners",
    "wof:placetype":"venue"
},
  "geometry": {"coordinates":[-73.413048,41.577781],"type":"Point"}
}