{
  "type": "Feature",
  "properties": {
    "iso:country":"US",
    "sg:address":"198 Main St",
    "sg:city":"Danbury",
    "sg:classifiers":[
        {
            "category":"Health Services",
            "subcategory":"Doctor",
            "type":"Services"
        }
    ],
    "sg:phone":"+1 203 748 6188",
    "sg:postcode":"06810",
    "sg:province":"CT",
    "sg:tags":[
        "clinic"
    ],
    "sg:website":"www.americares.org",
    "wof:name":"Americares Free Clinic",
    "wof:placetype":"venue"
},
  "geometry": {"coordinates":[-73.45236800000001,41.394514],"type":"Point"}
}