{
  "type": "Feature",
  "properties": {
    "addr:full":"4 Sylvester Ct Norwalk CT 06855",
    "addr:housenumber":"4",
    "addr:postcode":"06855",
    "addr:street":"Sylvester Ct",
    "iso:country":"US",
    "sg:address":"4 Sylvester Ct",
    "sg:city":"Norwalk",
    "sg:classifiers":[
        {
            "category":"Professional",
            "type":"Services"
        }
    ],
    "sg:phone":"+1 203 855 0895",
    "sg:postcode":"06855",
    "sg:province":"CT",
    "sg:tags":[
        "establishment"
    ],
    "wof:name":"Boone Associates",
    "wof:placetype":"venue"
},
  "geometry": {"coordinates":[-73.400198,41.089563],"type":"Point"}
}