{
  "type": "Feature",
  "properties": {
    "addr:full":"140 Gloucester Ct Newington CT 06111",
    "addr:housenumber":"140",
    "addr:postcode":"06111",
    "addr:street":"Gloucester Ct",
    "iso:country":"US",
    "sg:address":"140 Gloucester Ct",
    "sg:city":"Newington",
    "sg:classifiers":[
        {
            "category":"Building & Trades",
            "subcategory":"Cleaning & Sanitation",
            "type":"Services"
        }
    ],
    "sg:phone":"+1   ",
    "sg:postcode":"06111",
    "sg:province":"CT",
    "sg:tags":[
        "maintenance"
    ],
    "wof:name":"Silco Management",
    "wof:placetype":"venue"
},
  "geometry": {"coordinates":[-72.72457,41.662462],"type":"Point"}
}