{
  "type": "Feature",
  "properties": {
    "addr:full":"59 Broadway New Haven CT 06511",
    "addr:housenumber":"59",
    "addr:postcode":"06511",
    "addr:street":"Broadway",
    "iso:country":"US",
    "sg:address":"59 Broadway",
    "sg:city":"New Haven",
    "sg:classifiers":[
        {
            "category":"Home & Garden",
            "subcategory":"Carpets & Floor Coverings",
            "type":"Retail Goods"
        }
    ],
    "sg:phone":"+1 203 865 1665",
    "sg:postcode":"06511",
    "sg:province":"CT",
    "wof:name":"Kilim Co",
    "wof:placetype":"venue"
},
  "geometry": {"coordinates":[-72.929998,41.310663],"type":"Point"}
}