{
  "type": "Feature",
  "properties": {
    "addr:full":"797 Farmington Ave Hartford CT 06119",
    "addr:housenumber":"797",
    "addr:postcode":"06119",
    "addr:street":"Farmington Ave;Ct",
    "iso:country":"US",
    "sg:address":"797 Farmington Ave",
    "sg:city":"Hartford",
    "sg:classifiers":[
        {
            "category":"Health Services",
            "subcategory":"Doctor",
            "type":"Services"
        }
    ],
    "sg:phone":"+1   ",
    "sg:postcode":"06119",
    "sg:province":"CT",
    "wof:name":"M M Goodman DDS",
    "wof:placetype":"venue"
},
  "geometry": {"coordinates":[-72.728971,41.764683],"type":"Point"}
}