{
  "type": "Feature",
  "properties": {
    "addr:full":"50 Locust Ave New Canaan NY 06840",
    "addr:housenumber":"50",
    "addr:postcode":"06840",
    "addr:street":"Locust Ave",
    "iso:country":"US",
    "sg:address":"50 Locust Ave",
    "sg:city":"New Canaan",
    "sg:classifiers":[
        {
            "category":"Banks & Credit Unions",
            "subcategory":"Investment Brokerage",
            "type":"Services"
        }
    ],
    "sg:phone":"+1 203 966 0005",
    "sg:postcode":"06840",
    "sg:province":"NY",
    "sg:tags":[
        "advisory",
        "financial"
    ],
    "sg:website":"www.jmlummis.com",
    "wof:name":"J M Lummis Securities Inc",
    "wof:placetype":"venue"
},
  "geometry": {"coordinates":[-73.491478,41.149345],"type":"Point"}
}