{
  "type": "Feature",
  "properties": {
    "addr:full":"91 Portland St New Haven CT 06513",
    "addr:housenumber":"91",
    "addr:postcode":"06513",
    "addr:street":"Portland St",
    "iso:country":"US",
    "sg:address":"91 Portland St",
    "sg:city":"New Haven",
    "sg:classifiers":[
        {
            "category":"Retail",
            "subcategory":"Repair Shop",
            "type":"Services"
        }
    ],
    "sg:phone":"+1   ",
    "sg:postcode":"06513",
    "sg:province":"CT",
    "wof:name":"Jake Snake Pipe Drain Clg Svc",
    "wof:placetype":"venue"
},
  "geometry": {"coordinates":[-72.86918,41.332022],"type":"Point"}
}