{
  "type": "Feature",
  "properties": {
    "iso:country":"US",
    "sg:address":"39 Lake Ave Exn",
    "sg:city":"Danbury",
    "sg:classifiers":[
        {
            "category":"Restaurant",
            "type":"Food & Drink"
        }
    ],
    "sg:phone":"+1 203 744 6885",
    "sg:postcode":"06811",
    "sg:province":"CT",
    "sg:website":"www.kabuki-house.com",
    "wof:name":"Kabuki Japanese Steak House",
    "wof:placetype":"venue"
},
  "geometry": {"coordinates":[-73.481875,41.384711],"type":"Point"}
}