{
  "type": "Feature",
  "properties": {
    "addr:full":"1984 Boston Post Rd Guilford CT 06437",
    "addr:housenumber":"1984",
    "addr:postcode":"06437",
    "addr:street":"Boston Post Rd",
    "iso:country":"US",
    "sg:address":"1984 Boston Post Rd",
    "sg:city":"Guilford",
    "sg:classifiers":[
        {
            "category":"Retail",
            "subcategory":"Auto Repair",
            "type":"Services"
        }
    ],
    "sg:phone":"+1 203 453 6244",
    "sg:postcode":"06437",
    "sg:province":"CT",
    "sg:tags":[
        "general",
        "supply"
    ],
    "wof:name":"Auto Associates",
    "wof:placetype":"venue"
},
  "geometry": {"coordinates":[-72.711426,41.304518],"type":"Point"}
}