{
  "type": "Feature",
  "properties": {
    "iso:country":"US",
    "sg:address":"204 Hope St",
    "sg:city":"Stamford",
    "sg:classifiers":[
        {
            "category":"Building & Trades",
            "subcategory":"Construction",
            "type":"Services"
        }
    ],
    "sg:phone":"+1 203 961 9129",
    "sg:postcode":"06906",
    "sg:province":"CT",
    "sg:tags":[
        "contractor"
    ],
    "wof:name":"Terra Contractors",
    "wof:placetype":"venue"
},
  "geometry": {"coordinates":[-73.526743,41.06844],"type":"Point"}
}