{
  "type": "Feature",
  "properties": {
    "addr:full":"105 N Lake Dr Stamford CT 06903",
    "addr:housenumber":"105",
    "addr:postcode":"06903",
    "addr:street":"N Lake Dr",
    "iso:country":"US",
    "sg:address":"105 N Lake Dr",
    "sg:city":"Stamford",
    "sg:classifiers":[
        {
            "category":"Shopping",
            "subcategory":"Optical Goods",
            "type":"Retail Goods"
        }
    ],
    "sg:phone":"+1 203 329 0163",
    "sg:postcode":"06903",
    "sg:province":"CT",
    "wof:name":"Opt Enterprise LLC",
    "wof:placetype":"venue"
},
  "geometry": {"coordinates":[-73.60389600000001,41.154838],"type":"Point"}
}