{
  "type": "Feature",
  "properties": {
    "addr:full":"215 Ely Ave Norwalk CT 06854",
    "addr:housenumber":"215",
    "addr:postcode":"06854",
    "addr:street":"Ely Ave",
    "iso:country":"US",
    "sg:address":"215 Ely Ave",
    "sg:city":"Norwalk",
    "sg:classifiers":[
        {
            "category":"Home & Garden",
            "subcategory":"Home Furnishings",
            "type":"Retail Goods"
        }
    ],
    "sg:phone":"+1 203 866 9481",
    "sg:postcode":"06854",
    "sg:province":"CT",
    "sg:tags":[
        "venetian",
        "blind"
    ],
    "wof:name":"Blind Man",
    "wof:placetype":"venue"
},
  "geometry": {"coordinates":[-73.424888,41.088347],"type":"Point"}
}