{
  "type": "Feature",
  "properties": {
    "addr:full":"3 Enterprise Dr Shelton CT 06484",
    "addr:housenumber":"3",
    "addr:postcode":"06484",
    "addr:street":"Enterprise Dr",
    "iso:country":"US",
    "sg:address":"3 Enterprise Dr",
    "sg:city":"Shelton",
    "sg:classifiers":[
        {
            "category":"Food & Beverages",
            "subcategory":"Bakery",
            "type":"Retail Goods"
        }
    ],
    "sg:phone":"+1 203 929 8630",
    "sg:postcode":"06484",
    "sg:province":"CT",
    "sg:tags":[
        "baker"
    ],
    "wof:name":"Bakery Engineering Winkler",
    "wof:placetype":"venue"
},
  "geometry": {"coordinates":[-73.12379199999999,41.277261],"type":"Point"}
}