{
  "type": "Feature",
  "properties": {
    "addr:full":"10 Heron Rd Norwalk CT 06855",
    "addr:housenumber":"10",
    "addr:postcode":"06855",
    "addr:street":"Heron Rd",
    "iso:country":"US",
    "sg:address":"10 Heron Rd",
    "sg:city":"Norwalk",
    "sg:classifiers":[
        {
            "category":"Professional",
            "subcategory":"Business Services",
            "type":"Services"
        }
    ],
    "sg:phone":"+1   ",
    "sg:postcode":"06855",
    "sg:province":"CT",
    "wof:name":"Red Rock Power Partners LLC",
    "wof:placetype":"venue"
},
  "geometry": {"coordinates":[-73.38464399999999,41.109392],"type":"Point"}
}