{
  "type": "Feature",
  "properties": {
    "addr:full":"7 Brentwood Dr Bloomfield CT 06002",
    "addr:housenumber":"7",
    "addr:postcode":"06002",
    "addr:street":"Brentwood Dr Bloomfield Ct",
    "iso:country":"US",
    "sg:address":"7 Brentwood Dr",
    "sg:city":"Bloomfield",
    "sg:classifiers":[
        {
            "category":"Organizations",
            "subcategory":"Religious Organization",
            "type":"Services"
        }
    ],
    "sg:phone":"+1   ",
    "sg:postcode":"06002",
    "sg:province":"CT",
    "wof:name":"Weep Tent Crusade",
    "wof:placetype":"venue"
},
  "geometry": {"coordinates":[-72.73201899999999,41.831585],"type":"Point"}
}