{
  "type": "Feature",
  "properties": {
    "addr:full":"24 Llewellyn Dr New Canaan NY 06840",
    "addr:housenumber":"24",
    "addr:postcode":"06840",
    "addr:street":"Llewellyn Dr",
    "iso:country":"US",
    "sg:address":"24 Llewellyn Dr",
    "sg:city":"New Canaan",
    "sg:classifiers":[
        {
            "category":"Building & Trades",
            "subcategory":"Equipment Rental",
            "type":"Services"
        }
    ],
    "sg:phone":"+1 203 966 6679",
    "sg:postcode":"06840",
    "sg:province":"NY",
    "sg:tags":[
        "aircraft",
        "leasing",
        "charter"
    ],
    "wof:name":"Helicopter Flight Svc",
    "wof:placetype":"venue"
},
  "geometry": {"coordinates":[-73.51387200000001,41.140467],"type":"Point"}
}