{
  "type": "Feature",
  "properties": {
    "addr:full":"555 Boston Post Rd Orange CT 06477",
    "addr:housenumber":"555",
    "addr:postcode":"06477",
    "addr:street":"Boston Post Rd",
    "iso:country":"US",
    "sg:address":"555 Boston Post Rd",
    "sg:city":"Orange",
    "sg:classifiers":[
        {
            "category":"Home & Garden",
            "subcategory":"Furniture",
            "type":"Retail Goods"
        }
    ],
    "sg:phone":"+1 203 795 3781",
    "sg:postcode":"06477",
    "sg:province":"CT",
    "wof:name":"Futon Gallery",
    "wof:placetype":"venue"
},
  "geometry": {"coordinates":[-73.020866,41.251244],"type":"Point"}
}