{
  "type": "Feature",
  "properties": {
    "addr:full":"344 Leonard Rd Middlebury CT 06762",
    "addr:housenumber":"344",
    "addr:postcode":"06762",
    "addr:street":"Leonard Rd Middlebury Ct",
    "iso:country":"US",
    "sg:address":"344 Leonard Rd",
    "sg:city":"Middlebury",
    "sg:classifiers":[
        {
            "category":"Building & Trades",
            "subcategory":"Landscaping Services",
            "type":"Services"
        }
    ],
    "sg:phone":"+1 203 758 9130",
    "sg:postcode":"06762",
    "sg:province":"CT",
    "wof:name":"Matt S Lawn Care",
    "wof:placetype":"venue"
},
  "geometry": {"coordinates":[-73.097537,41.518832],"type":"Point"}
}