{
  "type": "Feature",
  "properties": {
    "addr:full":"140 Simsbury Rd Avon CT 06001",
    "addr:housenumber":"140",
    "addr:postcode":"06001",
    "addr:street":"Simsbury Rd",
    "iso:country":"US",
    "sg:address":"140 Simsbury Rd",
    "sg:city":"Avon",
    "sg:classifiers":[
        {
            "category":"Arts & Performance",
            "subcategory":"Arts Center",
            "type":"Entertainment"
        }
    ],
    "sg:phone":"+1 860 674 9089",
    "sg:postcode":"06001",
    "sg:province":"CT",
    "sg:tags":[
        "performing"
    ],
    "sg:website":"www.terryschoolofdance.com",
    "wof:name":"Terry's School of Dance",
    "wof:placetype":"venue"
},
  "geometry": {"coordinates":[-72.830597,41.8125],"type":"Point"}
}