{
  "type": "Feature",
  "properties": {
    "iso:country":"US",
    "sg:address":"14 Douglas Dr",
    "sg:city":"Oxford",
    "sg:classifiers":[
        {
            "category":"Shopping",
            "subcategory":"Computers & Home Electronics",
            "type":"Retail Goods"
        },
        {
            "category":"Professional",
            "subcategory":"Computer Services",
            "type":"Services"
        }
    ],
    "sg:phone":"+1 203 881 9660",
    "sg:postcode":"06478",
    "sg:province":"CT",
    "sg:tags":[
        "measuring",
        "repair",
        "electrical",
        "mfg"
    ],
    "wof:name":"Advanced Business Group Inc",
    "wof:placetype":"venue"
},
  "geometry": {"coordinates":[-73.114071,41.463654],"type":"Point"}
}