{
  "type": "Feature",
  "properties": {
    "addr:full":"17 Old Kings Hwy Weston CT 06883",
    "addr:housenumber":"17",
    "addr:postcode":"06883",
    "addr:street":"Old Kings Hwy",
    "iso:country":"US",
    "sg:address":"17 Old Kings Hwy",
    "sg:city":"Weston",
    "sg:classifiers":[
        {
            "category":"Building & Trades",
            "subcategory":"Landscaping Services",
            "type":"Services"
        }
    ],
    "sg:phone":"+1 203 222 1359",
    "sg:postcode":"06883",
    "sg:province":"CT",
    "sg:tags":[
        "tree"
    ],
    "wof:name":"Eastern Tree Svc",
    "wof:placetype":"venue"
},
  "geometry": {"coordinates":[-73.334672,41.209566],"type":"Point"}
}