{
  "type": "Feature",
  "properties": {
    "iso:country":"US",
    "sg:address":"51 River St",
    "sg:city":"Milford",
    "sg:classifiers":[
        {
            "category":"Health Services",
            "subcategory":"Clinic",
            "type":"Services"
        }
    ],
    "sg:phone":"+1 203 878 9642",
    "sg:postcode":"06460",
    "sg:province":"CT",
    "sg:tags":[
        "wellness",
        "program"
    ],
    "wof:name":"Not Just Yoga Women's Wellness",
    "wof:placetype":"venue"
},
  "geometry": {"coordinates":[-73.05745,41.223897],"type":"Point"}
}