{
  "type": "Feature",
  "properties": {
    "addr:full":"60 Sawmill Rd New Fairfield CT 06812",
    "addr:housenumber":"60",
    "addr:postcode":"06812",
    "addr:street":"Sawmill Rd;Fairfield Ct",
    "iso:country":"US",
    "sg:address":"60 Sawmill Rd",
    "sg:city":"New Fairfield",
    "sg:classifiers":[
        {
            "category":"Building & Trades",
            "subcategory":"Construction",
            "type":"Services"
        }
    ],
    "sg:phone":"+1 203 746 1810",
    "sg:postcode":"06812",
    "sg:province":"CT",
    "sg:tags":[
        "general",
        "contractor"
    ],
    "wof:name":"Richard T Johnson Contractor",
    "wof:placetype":"venue"
},
  "geometry": {"coordinates":[-73.47463999999999,41.466722],"type":"Point"}
}