{
  "type": "Feature",
  "properties": {
    "addr:full":"30 Corbin Dr Darien CT 06820",
    "addr:housenumber":"30",
    "addr:postcode":"06820",
    "addr:street":"Corbin Dr Darien Ct",
    "iso:country":"US",
    "sg:address":"30 Corbin Dr",
    "sg:city":"Darien",
    "sg:classifiers":[
        {
            "category":"Government",
            "subcategory":"Post Office",
            "type":"Public Place"
        }
    ],
    "sg:phone":"+1 203 655 2595",
    "sg:postcode":"06820",
    "sg:province":"CT",
    "wof:name":"US Post Office",
    "wof:placetype":"venue"
},
  "geometry": {"coordinates":[-73.47138099999999,41.074537],"type":"Point"}
}