{
  "type": "Feature",
  "properties": {
    "iso:country":"US",
    "sg:address":"31 Beacher Rd",
    "sg:city":"Milford",
    "sg:classifiers":[
        {
            "category":"Professional",
            "subcategory":"Art Services",
            "type":"Services"
        }
    ],
    "sg:phone":"+1 203 878 2065",
    "sg:postcode":"06460",
    "sg:province":"CT",
    "sg:tags":[
        "photographer"
    ],
    "sg:website":"www.zavalishin.com",
    "wof:name":"Zavalishin Studio",
    "wof:placetype":"venue"
},
  "geometry": {"coordinates":[-73.008788,41.213238],"type":"Point"}
}