{
  "type": "Feature",
  "properties": {
    "iso:country":"US",
    "sg:address":"19 Brandy Ln",
    "sg:city":"Bridgewater",
    "sg:classifiers":[
        {
            "category":"Professional",
            "subcategory":"Lawyer & Legal Services",
            "type":"Services"
        }
    ],
    "sg:phone":"+1   ",
    "sg:postcode":"06752",
    "sg:province":"CT",
    "wof:name":"Weston Mitchell Law Office",
    "wof:placetype":"venue"
},
  "geometry": {"coordinates":[-73.358221,41.54938],"type":"Point"}
}