{
  "type": "Feature",
  "properties": {
    "addr:full":"8 Shannon Ridge Rd Danbury CT 06810",
    "addr:housenumber":"8",
    "addr:postcode":"06810",
    "addr:street":"Shannon Ridge Rd",
    "iso:country":"US",
    "sg:address":"8 Shannon Ridge Rd",
    "sg:city":"Danbury",
    "sg:classifiers":[
        {
            "category":"Building & Trades",
            "subcategory":"Construction",
            "type":"Services"
        }
    ],
    "sg:phone":"+1 203 744 5865",
    "sg:postcode":"06810",
    "sg:province":"CT",
    "sg:tags":[
        "contractor"
    ],
    "wof:name":"A&D Casimiro Masonry",
    "wof:placetype":"venue"
},
  "geometry": {"coordinates":[-73.474174,41.389276],"type":"Point"}
}