{
  "type": "Feature",
  "properties": {
    "addr:full":"730 Danbury Rd Ridgefield CT 06877",
    "addr:housenumber":"730",
    "addr:postcode":"06877",
    "addr:street":"Danbury Rd",
    "iso:country":"US",
    "sg:address":"730 Danbury Rd",
    "sg:city":"Ridgefield",
    "sg:classifiers":[
        {
            "category":"Home & Garden",
            "subcategory":"Building Materials",
            "type":"Retail Goods"
        }
    ],
    "sg:phone":"+1 203 740 1300",
    "sg:postcode":"06877",
    "sg:province":"CT",
    "sg:tags":[
        "door"
    ],
    "wof:name":"Ridgefield Overhead Doors",
    "wof:placetype":"venue"
},
  "geometry": {"coordinates":[-73.47324,41.329571],"type":"Point"}
}