{
  "type": "Feature",
  "properties": {
    "iso:country":"US",
    "sg:address":"386 Main St",
    "sg:city":"Middletown",
    "sg:classifiers":[
        {
            "category":"Shopping",
            "subcategory":"Jewelry",
            "type":"Retail Goods"
        }
    ],
    "sg:phone":"+1 860 344 9159",
    "sg:postcode":"06457",
    "sg:province":"CT",
    "wof:name":"P J Jewelers",
    "wof:placetype":"venue"
},
  "geometry": {"coordinates":[-72.649514,41.560238],"type":"Point"}
}