{
  "type": "Feature",
  "properties": {
    "iso:country":"US",
    "sg:address":"461 Voluntown Rd",
    "sg:city":"Jewett City",
    "sg:classifiers":[
        {
            "category":"Shopping",
            "subcategory":"Books",
            "type":"Retail Goods"
        }
    ],
    "sg:phone":"+1 860 376 1760",
    "sg:postcode":"06351",
    "sg:province":"CT",
    "wof:name":"Booktales",
    "wof:placetype":"venue"
},
  "geometry": {"coordinates":[-71.96755899999999,41.592187],"type":"Point"}
}