{
  "type": "Feature",
  "properties": {
    "addr:full":"1675 Mountain Rd Torrington CT 06790",
    "addr:housenumber":"1675",
    "addr:postcode":"06790",
    "addr:street":"Mountain Rd",
    "iso:country":"US",
    "sg:address":"1675 Mountain Rd",
    "sg:city":"Torrington",
    "sg:classifiers":[
        {
            "category":"Building & Trades",
            "subcategory":"Landscaping Services",
            "type":"Services"
        }
    ],
    "sg:phone":"+1 860 626 8368",
    "sg:postcode":"06790",
    "sg:province":"CT",
    "sg:tags":[
        "landscape"
    ],
    "wof:name":"C Markey Landscaping",
    "wof:placetype":"venue"
},
  "geometry": {"coordinates":[-73.137501,41.841273],"type":"Point"}
}