{
  "type": "Feature",
  "properties": {
    "addr:full":"69 Old Dyke Rd Trumbull CT 06611",
    "addr:housenumber":"69",
    "addr:postcode":"06611",
    "addr:street":"Old Dyke Rd",
    "iso:country":"US",
    "sg:address":"69 Old Dyke Rd",
    "sg:city":"Trumbull",
    "sg:classifiers":[
        {
            "category":"Real Estate",
            "subcategory":"Real Estate Agent",
            "type":"Services"
        }
    ],
    "sg:phone":"+1 203 502 7653",
    "sg:postcode":"06611",
    "sg:province":"CT",
    "wof:name":"Judy Szablak Realtor",
    "wof:placetype":"venue"
},
  "geometry": {"coordinates":[-73.179546,41.261387],"type":"Point"}
}