{
  "type": "Feature",
  "properties": {
    "addr:full":"2852 Fairfield Ave Bridgeport CT 06605",
    "addr:housenumber":"2852",
    "addr:postcode":"06605",
    "addr:street":"Fairfield Ave",
    "iso:country":"US",
    "sg:address":"2852 Fairfield Ave",
    "sg:city":"Bridgeport",
    "sg:classifiers":[
        {
            "category":"Personal",
            "subcategory":"Beauty Salon",
            "type":"Services"
        }
    ],
    "sg:phone":"+1 203 366 1466",
    "sg:postcode":"06605",
    "sg:province":"CT",
    "sg:tags":[
        "manicuring"
    ],
    "wof:name":"Pro Nails",
    "wof:placetype":"venue"
},
  "geometry": {"coordinates":[-73.227062,41.15715],"type":"Point"}
}