{
  "type": "Feature",
  "properties": {
    "addr:full":"30 Morse Ave West Haven CT 06516",
    "addr:housenumber":"30",
    "addr:postcode":"06516",
    "addr:street":"Morse Ave",
    "iso:country":"US",
    "sg:address":"30 Morse Ave",
    "sg:city":"West Haven",
    "sg:classifiers":[
        {
            "category":"Wholesale",
            "subcategory":"Durable Goods & Equipment",
            "type":"Manufacturing & Wholesale Goods"
        }
    ],
    "sg:phone":"+1 203 387 3278",
    "sg:postcode":"06516",
    "sg:province":"CT",
    "sg:tags":[
        "importer"
    ],
    "wof:name":"East Ocean Enterprise Corp",
    "wof:placetype":"venue"
},
  "geometry": {"coordinates":[-72.936549,41.260683],"type":"Point"}
}