{
  "type": "Feature",
  "properties": {
    "addr:full":"63 Ethan Allen Ln Stamford CT 06903",
    "addr:housenumber":"63",
    "addr:postcode":"06903",
    "addr:street":"Ethan Allen Ln",
    "iso:country":"US",
    "sg:address":"63 Ethan Allen Ln",
    "sg:city":"Stamford",
    "sg:classifiers":[
        {
            "category":"Real Estate",
            "subcategory":"Real Estate Operator",
            "type":"Services"
        }
    ],
    "sg:phone":"+1 203 274 6788",
    "sg:postcode":"06903",
    "sg:province":"CT",
    "sg:tags":[
        "apartment"
    ],
    "wof:name":"Jars Company",
    "wof:placetype":"venue"
},
  "geometry": {"coordinates":[-73.561875,41.129744],"type":"Point"}
}