{
  "type": "Feature",
  "properties": {
    "iso:country":"US",
    "sg:address":"700 Canal St",
    "sg:city":"Stamford",
    "sg:classifiers":[
        {
            "category":"Arts & Performance",
            "subcategory":"Theater",
            "type":"Entertainment"
        }
    ],
    "sg:phone":"+1   ",
    "sg:postcode":"06902",
    "sg:province":"CT",
    "sg:tags":[
        "gaming",
        "sport"
    ],
    "wof:name":"Luckygolfercom",
    "wof:placetype":"venue"
},
  "geometry": {"coordinates":[-73.532608,41.045159],"type":"Point"}
}