{
  "type": "Feature",
  "properties": {
    "addr:full":"9 Frog Pond Ln Stratford CT 06614",
    "addr:housenumber":"9",
    "addr:postcode":"06614",
    "addr:street":"Frog Pond Ln",
    "iso:country":"US",
    "sg:address":"9 Frog Pond Ln",
    "sg:city":"Stratford",
    "sg:classifiers":[
        {
            "category":"Retail",
            "subcategory":"Animal Services",
            "type":"Services"
        },
        {
            "category":"Government",
            "subcategory":"Police Station",
            "type":"Public Place"
        }
    ],
    "sg:phone":"+1 203 385 4068",
    "sg:postcode":"06614",
    "sg:province":"CT",
    "sg:tags":[
        "department"
    ],
    "wof:name":"Stratford Police-Dog Warden",
    "wof:placetype":"venue"
},
  "geometry": {"coordinates":[-73.121005,41.204337],"type":"Point"}
}