{
  "type": "Feature",
  "properties": {
    "iso:country":"US",
    "sg:address":"164 White St",
    "sg:city":"Danbury",
    "sg:classifiers":[
        {
            "category":"Building & Trades",
            "subcategory":"Equipment Rental",
            "type":"Services"
        }
    ],
    "sg:phone":"+1   ",
    "sg:postcode":"06810",
    "sg:province":"CT",
    "wof:name":"Connecticut Casino Supply",
    "wof:placetype":"venue"
},
  "geometry": {"coordinates":[-73.446247,41.399323],"type":"Point"}
}