{
  "type": "Feature",
  "properties": {
    "iso:country":"US",
    "sg:address":"36 Mill Plain Rd",
    "sg:city":"Danbury",
    "sg:classifiers":[
        {
            "category":"Professional",
            "subcategory":"Management & Consulting",
            "type":"Services"
        }
    ],
    "sg:phone":"+1 203 798 8377",
    "sg:postcode":"06811",
    "sg:province":"CT",
    "sg:tags":[
        "marketing",
        "consultant"
    ],
    "wof:name":"Choicepoint Precision Mktg Inc",
    "wof:placetype":"venue"
},
  "geometry": {"coordinates":[-73.498508,41.38907],"type":"Point"}
}