{
  "type": "Feature",
  "properties": {
    "iso:country":"US",
    "sg:address":"2 Palmer Neck Rd",
    "sg:city":"Pawcatuck",
    "sg:classifiers":[
        {
            "category":"Retail",
            "subcategory":"Auto Repair",
            "type":"Services"
        }
    ],
    "sg:phone":"+1   ",
    "sg:postcode":"06379",
    "sg:province":"CT",
    "sg:tags":[
        "body"
    ],
    "wof:name":"Coastal Painting & Campus",
    "wof:placetype":"venue"
},
  "geometry": {"coordinates":[-71.877239,41.358574],"type":"Point"}
}