{
  "type": "Feature",
  "properties": {
    "addr:full":"32 Elizabeth St Shelton CT 06484",
    "addr:housenumber":"32",
    "addr:postcode":"06484",
    "addr:street":"Elizabeth St",
    "iso:country":"US",
    "sg:address":"32 Elizabeth St",
    "sg:city":"Shelton",
    "sg:classifiers":[
        {
            "category":"Professional",
            "type":"Services"
        }
    ],
    "sg:phone":"+1 203 929 0755",
    "sg:postcode":"06484",
    "sg:province":"CT",
    "wof:name":"Lynard I LLC",
    "wof:placetype":"venue"
},
  "geometry": {"coordinates":[-73.157678,41.283145],"type":"Point"}
}