{
  "type": "Feature",
  "properties": {
    "iso:country":"US",
    "sg:address":"2260 State St",
    "sg:city":"Hamden",
    "sg:classifiers":[
        {
            "category":"Retail",
            "subcategory":"Auto Repair",
            "type":"Services"
        }
    ],
    "sg:phone":"+1 203 248 4808",
    "sg:postcode":"06517",
    "sg:province":"CT",
    "sg:tags":[
        "repairing",
        "automobile"
    ],
    "wof:name":"Dougan Automotive LLC",
    "wof:placetype":"venue"
},
  "geometry": {"coordinates":[-72.895561,41.341698],"type":"Point"}
}