{
  "type": "Feature",
  "properties": {
    "addr:full":"6 Patricia Ln Danbury CT 06811",
    "addr:housenumber":"6",
    "addr:postcode":"06811",
    "addr:street":"Patricia Ln",
    "iso:country":"US",
    "sg:address":"6 Patricia Ln",
    "sg:city":"Danbury",
    "sg:classifiers":[
        {
            "category":"Building & Trades",
            "subcategory":"Cleaning & Sanitation",
            "type":"Services"
        }
    ],
    "sg:phone":"+1   ",
    "sg:postcode":"06811",
    "sg:province":"CT",
    "sg:tags":[
        "maintenance"
    ],
    "wof:name":"Trueclean",
    "wof:placetype":"venue"
},
  "geometry": {"coordinates":[-73.465659,41.412559],"type":"Point"}
}