{
  "type": "Feature",
  "properties": {
    "iso:country":"US",
    "sg:address":"153 Main St",
    "sg:city":"Danbury",
    "sg:classifiers":[
        {
            "category":"Insurance",
            "subcategory":"Insurance Agent",
            "type":"Services"
        }
    ],
    "sg:phone":"+1 203 797 9001",
    "sg:postcode":"06810",
    "sg:province":"CT",
    "wof:name":"United Insurance Assn LLC",
    "wof:placetype":"venue"
},
  "geometry": {"coordinates":[-73.451155,41.393534],"type":"Point"}
}