{
  "type": "Feature",
  "properties": {
    "iso:country":"US",
    "sg:address":"132 Middle Beach Rd",
    "sg:city":"Madison",
    "sg:classifiers":[
        {
            "category":"Building & Trades",
            "subcategory":"Construction",
            "type":"Services"
        }
    ],
    "sg:phone":"+1 203 245 8155",
    "sg:postcode":"06443",
    "sg:province":"CT",
    "sg:tags":[
        "contractor"
    ],
    "wof:name":"Peter Smith Building Co",
    "wof:placetype":"venue"
},
  "geometry": {"coordinates":[-72.586145,41.271988],"type":"Point"}
}