{
  "type": "Feature",
  "properties": {
    "addr:full":"1 Milbank Ave Greenwich CT 06830",
    "addr:housenumber":"1",
    "addr:postcode":"06830",
    "addr:street":"Milbank Ave",
    "iso:country":"US",
    "sg:address":"1 Milbank Ave",
    "sg:city":"Greenwich",
    "sg:classifiers":[
        {
            "category":"Professional",
            "subcategory":"Business Services",
            "type":"Services"
        }
    ],
    "sg:phone":"+1   ",
    "sg:postcode":"06830",
    "sg:province":"CT",
    "wof:name":"Elena Houser Interiors",
    "wof:placetype":"venue"
},
  "geometry": {"coordinates":[-73.622429,41.033148],"type":"Point"}
}