{
  "type": "Feature",
  "properties": {
    "addr:full":"60 Tremont St New Britain CT 06051",
    "addr:housenumber":"60",
    "addr:postcode":"06051",
    "addr:street":"Tremont St",
    "iso:country":"US",
    "sg:address":"60 Tremont St",
    "sg:city":"New Britain",
    "sg:classifiers":[
        {
            "category":"Organizations",
            "subcategory":"Religious Organization",
            "type":"Services"
        }
    ],
    "sg:phone":"+1   ",
    "sg:postcode":"06051",
    "sg:province":"CT",
    "wof:name":"New Bethel Fbh Church",
    "wof:placetype":"venue"
},
  "geometry": {"coordinates":[-72.77789300000001,41.675359],"type":"Point"}
}