{
  "type": "Feature",
  "properties": {
    "addr:full":"354 New Haven Ave Milford CT 06460",
    "addr:housenumber":"354",
    "addr:postcode":"06460",
    "addr:street":"New Haven Ave",
    "iso:country":"US",
    "sg:address":"354 New Haven Ave",
    "sg:city":"Milford",
    "sg:classifiers":[
        {
            "category":"Shopping",
            "subcategory":"Gifts & Souvenirs",
            "type":"Retail Goods"
        }
    ],
    "sg:phone":"+1 203 874 3371",
    "sg:postcode":"06460",
    "sg:province":"CT",
    "sg:tags":[
        "balloon",
        "artist"
    ],
    "wof:name":"Bayview Beach Balloons",
    "wof:placetype":"venue"
},
  "geometry": {"coordinates":[-73.041026,41.223503],"type":"Point"}
}