{
  "type": "Feature",
  "properties": {
    "addr:full":"26 Pearl St Norwalk CT 06850",
    "addr:housenumber":"26",
    "addr:postcode":"06850",
    "addr:street":"Pearl St",
    "iso:country":"US",
    "sg:address":"26 Pearl St",
    "sg:city":"Norwalk",
    "sg:classifiers":[
        {
            "category":"Professional",
            "subcategory":"Computer Services",
            "type":"Services"
        }
    ],
    "sg:phone":"+1   ",
    "sg:postcode":"06850",
    "sg:province":"CT",
    "sg:tags":[
        "datum"
    ],
    "wof:name":"Teller Tab Services",
    "wof:placetype":"venue"
},
  "geometry": {"coordinates":[-73.428102,41.137749],"type":"Point"}
}