{
  "type": "Feature",
  "properties": {
    "iso:country":"US",
    "sg:address":"260 Greenwich Ave",
    "sg:city":"Greenwich",
    "sg:classifiers":[
        {
            "category":"Shopping",
            "subcategory":"Clothing, Apparel, & Fashions",
            "type":"Retail Goods"
        }
    ],
    "sg:phone":"+1 203 869 8018",
    "sg:postcode":"06830",
    "sg:province":"CT",
    "sg:tags":[
        "woman",
        "store"
    ],
    "wof:name":"Le Chat",
    "wof:placetype":"venue"
},
  "geometry": {"coordinates":[-73.625981,41.026381],"type":"Point"}
}