{
  "type": "Feature",
  "properties": {
    "iso:country":"US",
    "sg:address":"968 Farmington Ave",
    "sg:city":"Hartford",
    "sg:classifiers":[
        {
            "category":"Professional",
            "subcategory":"Secretarial Services",
            "type":"Services"
        }
    ],
    "sg:phone":"+1   ",
    "sg:postcode":"06107",
    "sg:province":"CT",
    "sg:tags":[
        "reporting"
    ],
    "wof:name":"Professional Resume Plus",
    "wof:placetype":"venue"
},
  "geometry": {"coordinates":[-72.744136,41.761413],"type":"Point"}
}