{
  "type": "Feature",
  "properties": {
    "addr:full":"621 Judd Rd Southbury CT 06488",
    "addr:housenumber":"621",
    "addr:postcode":"06488",
    "addr:street":"Judd Rd",
    "iso:country":"US",
    "sg:address":"621 Judd Rd",
    "sg:city":"Southbury",
    "sg:classifiers":[
        {
            "category":"Personal",
            "subcategory":"Barber",
            "type":"Services"
        }
    ],
    "sg:phone":"+1   ",
    "sg:postcode":"06488",
    "sg:province":"CT",
    "sg:tags":[
        "shop"
    ],
    "wof:name":"His Light Inc",
    "wof:placetype":"venue"
},
  "geometry": {"coordinates":[-73.158885,41.512215],"type":"Point"}
}