{
  "type": "Feature",
  "properties": {
    "addr:full":"27 Joyce Ct Milford CT 06461",
    "addr:housenumber":"27",
    "addr:postcode":"06461",
    "addr:street":"Joyce Ct",
    "iso:country":"US",
    "sg:address":"27 Joyce Ct",
    "sg:city":"Milford",
    "sg:classifiers":[
        {
            "category":"Organizations",
            "subcategory":"Community Association",
            "type":"Services"
        }
    ],
    "sg:phone":"+1 203 878 6460",
    "sg:postcode":"06461",
    "sg:province":"CT",
    "sg:tags":[
        "club"
    ],
    "wof:name":"Connecticut Women's Bowling",
    "wof:placetype":"venue"
},
  "geometry": {"coordinates":[-73.074572,41.231789],"type":"Point"}
}