{
  "type": "Feature",
  "properties": {
    "addr:full":"30 Beachside Ave Westport CT 06880",
    "addr:housenumber":"30",
    "addr:postcode":"06880",
    "addr:street":"Beachside Ave",
    "iso:country":"US",
    "sg:address":"30 Beachside Ave",
    "sg:city":"Westport",
    "sg:classifiers":[
        {
            "category":"Arts & Performance",
            "subcategory":"Theater",
            "type":"Entertainment"
        }
    ],
    "sg:phone":"+1   ",
    "sg:postcode":"06880",
    "sg:province":"CT",
    "sg:tags":[
        "company",
        "production"
    ],
    "wof:name":"Screaming Nnsqitor Productions",
    "wof:placetype":"venue"
},
  "geometry": {"coordinates":[-73.303496,41.121155],"type":"Point"}
}