{
  "type": "Feature",
  "properties": {
    "iso:country":"US",
    "sg:address":"1617 Fairfield Ave",
    "sg:city":"Bridgeport",
    "sg:classifiers":[
        {
            "category":"Building & Trades",
            "subcategory":"Landscaping Services",
            "type":"Services"
        }
    ],
    "sg:phone":"+1 203 333 2867",
    "sg:postcode":"06605",
    "sg:province":"CT",
    "wof:name":"Bill Manns Tree Service",
    "wof:placetype":"venue"
},
  "geometry": {"coordinates":[-73.212622,41.170858],"type":"Point"}
}