{
  "type": "Feature",
  "properties": {
    "iso:country":"US",
    "sg:address":"22 Eagle Rd",
    "sg:city":"Danbury",
    "sg:classifiers":[
        {
            "category":"Manufacturing",
            "subcategory":"Printing",
            "type":"Manufacturing & Wholesale Goods"
        }
    ],
    "sg:phone":"+1 203 730 1004",
    "sg:postcode":"06810",
    "sg:province":"CT",
    "sg:tags":[
        "publisher"
    ],
    "wof:name":"Nouvelles Images Inc",
    "wof:placetype":"venue"
},
  "geometry": {"coordinates":[-73.419826,41.412253],"type":"Point"}
}