{
  "type": "Feature",
  "properties": {
    "iso:country":"US",
    "sg:address":"52 S Main St",
    "sg:city":"East Windsor",
    "sg:classifiers":[
        {
            "category":"Professional",
            "type":"Services"
        }
    ],
    "sg:phone":"+1   ",
    "sg:postcode":"06088",
    "sg:province":"CT",
    "wof:name":"Dealer Remarketing Services",
    "wof:placetype":"venue"
},
  "geometry": {"coordinates":[-72.612916,41.904456],"type":"Point"}
}