{
  "type": "Feature",
  "properties": {
    "addr:full":"31 Savi Ave Waterford CT 06385",
    "addr:housenumber":"31",
    "addr:postcode":"06385",
    "addr:street":"Savi Ave",
    "iso:country":"US",
    "sg:address":"31 Savi Ave",
    "sg:city":"Waterford",
    "sg:classifiers":[
        {
            "category":"Real Estate",
            "subcategory":"Real Estate Services",
            "type":"Services"
        },
        {
            "category":"Real Estate",
            "subcategory":"Real Estate Agent",
            "type":"Services"
        }
    ],
    "sg:phone":"+1 860 443 2736",
    "sg:postcode":"06385",
    "sg:province":"CT",
    "sg:tags":[
        "buyer",
        "broker"
    ],
    "wof:name":"Sr Bank Street Realty",
    "wof:placetype":"venue"
},
  "geometry": {"coordinates":[-72.13404800000001,41.346692],"type":"Point"}
}