{
  "type": "Feature",
  "properties": {
    "addr:full":"199 Asylum St Bridgeport CT 06610",
    "addr:housenumber":"199",
    "addr:postcode":"06610",
    "addr:street":"Asylum St",
    "iso:country":"US",
    "sg:address":"199 Asylum St",
    "sg:city":"Bridgeport",
    "sg:classifiers":[
        {
            "category":"Shopping",
            "type":"Retail Goods"
        }
    ],
    "sg:phone":"+1 203 335 4934",
    "sg:postcode":"06610",
    "sg:province":"CT",
    "sg:tags":[
        "ice"
    ],
    "wof:name":"A & B Ice",
    "wof:placetype":"venue"
},
  "geometry": {"coordinates":[-73.173984,41.200087],"type":"Point"}
}