{
  "type": "Feature",
  "properties": {
    "iso:country":"US",
    "sg:address":"739 Kensington Rd",
    "sg:city":"Berlin",
    "sg:classifiers":[
        {
            "category":"Wholesale",
            "subcategory":"Machinery & Supplies",
            "type":"Manufacturing & Wholesale Goods"
        }
    ],
    "sg:phone":"+1 860 828 4836",
    "sg:postcode":"06037",
    "sg:province":"CT",
    "sg:tags":[
        "equipment",
        "industrial"
    ],
    "wof:name":"Acculift Inc",
    "wof:placetype":"venue"
},
  "geometry": {"coordinates":[-72.770235,41.621815],"type":"Point"}
}