{
  "type": "Feature",
  "properties": {
    "addr:full":"1095 High Ridge Rd Stamford CT 06905",
    "addr:housenumber":"1095",
    "addr:postcode":"06905",
    "addr:street":"High Ridge Rd",
    "iso:country":"US",
    "sg:address":"1095 High Ridge Rd",
    "sg:city":"Stamford",
    "sg:classifiers":[
        {
            "category":"Shopping",
            "subcategory":"Clothing, Apparel, & Fashions",
            "type":"Retail Goods"
        }
    ],
    "sg:phone":"+1 203 322 7277",
    "sg:postcode":"06905",
    "sg:province":"CT",
    "wof:name":"Designers For Less",
    "wof:placetype":"venue"
},
  "geometry": {"coordinates":[-73.54719,41.109109],"type":"Point"}
}