{
  "type": "Feature",
  "properties": {
    "iso:country":"US",
    "sg:address":"54 Springfield Rd",
    "sg:city":"Somers",
    "sg:classifiers":[
        {
            "category":"Manufacturing",
            "subcategory":"Food",
            "type":"Manufacturing & Wholesale Goods"
        },
        {
            "category":"Food & Beverages",
            "subcategory":"Specialty",
            "type":"Retail Goods"
        },
        {
            "category":"Food & Beverages",
            "subcategory":"Fruits & Vegetables",
            "type":"Retail Goods"
        }
    ],
    "sg:phone":"+1 860 749 0839",
    "sg:postcode":"06071",
    "sg:province":"CT",
    "sg:tags":[
        "product",
        "herb",
        "diet",
        "spices-wholesale",
        "health",
        "spice",
        "manufacturer"
    ],
    "wof:name":"Kassandra Herbs Unlimited",
    "wof:placetype":"venue"
},
  "geometry": {"coordinates":[-72.44773499999999,41.989544],"type":"Point"}
}