{
  "type": "Feature",
  "properties": {
    "iso:country":"US",
    "sg:address":"450 New Britain Ave",
    "sg:city":"Hartford",
    "sg:classifiers":[
        {
            "category":"Shopping",
            "subcategory":"Gifts & Souvenirs",
            "type":"Retail Goods"
        },
        {
            "category":"Shopping",
            "subcategory":"Florist",
            "type":"Retail Goods"
        }
    ],
    "sg:phone":"+1 860 206 9666",
    "sg:postcode":"06106",
    "sg:province":"CT",
    "sg:tags":[
        "shop"
    ],
    "wof:name":"Emily's Florist Gift Shop And Imprint",
    "wof:placetype":"venue"
},
  "geometry": {"coordinates":[-72.69770800000001,41.739271],"type":"Point"}
}