{
  "type": "Feature",
  "properties": {
    "iso:country":"US",
    "sg:address":"115 Circle Beach Rd",
    "sg:city":"Madison",
    "sg:classifiers":[
        {
            "category":"Professional",
            "subcategory":"Business Services",
            "type":"Services"
        }
    ],
    "sg:phone":"+1   ",
    "sg:postcode":"06443",
    "sg:province":"CT",
    "wof:name":"Linda Carr Inc",
    "wof:placetype":"venue"
},
  "geometry": {"coordinates":[-72.65167700000001,41.266719],"type":"Point"}
}