{
  "type": "Feature",
  "properties": {
    "iso:country":"US",
    "sg:address":"34 N Elm St",
    "sg:city":"Torrington",
    "sg:classifiers":[
        {
            "category":"Building & Trades",
            "subcategory":"Construction",
            "type":"Services"
        }
    ],
    "sg:phone":"+1 860 489 7659",
    "sg:postcode":"06790",
    "sg:province":"CT",
    "sg:tags":[
        "house"
    ],
    "wof:name":"Rosinski Stash Construction",
    "wof:placetype":"venue"
},
  "geometry": {"coordinates":[-73.122192,41.812353],"type":"Point"}
}