{
  "type": "Feature",
  "properties": {
    "addr:full":"3715 Main St Bridgeport CT 06606",
    "addr:housenumber":"3715",
    "addr:postcode":"06606",
    "addr:street":"Main St",
    "iso:country":"US",
    "sg:address":"3715 Main St",
    "sg:city":"Bridgeport",
    "sg:classifiers":[
        {
            "category":"Health Services",
            "subcategory":"Doctor",
            "type":"Services"
        }
    ],
    "sg:phone":"+1 203 371 0111",
    "sg:postcode":"06606",
    "sg:province":"CT",
    "sg:tags":[
        "physician",
        "surgeon"
    ],
    "wof:name":"Claudio Borghesan MD",
    "wof:placetype":"venue"
},
  "geometry": {"coordinates":[-73.210295,41.211742],"type":"Point"}
}