{
  "type": "Feature",
  "properties": {
    "addr:full":"62 Mountainview Dr Waterbury CT 06706",
    "addr:housenumber":"62",
    "addr:postcode":"06706",
    "addr:street":"Mountainview Dr",
    "iso:country":"US",
    "sg:address":"62 Mountainview Dr",
    "sg:city":"Waterbury",
    "sg:classifiers":[
        {
            "category":"Professional",
            "subcategory":"Business Services",
            "type":"Services"
        }
    ],
    "sg:phone":"+1   ",
    "sg:postcode":"06706",
    "sg:province":"CT",
    "wof:name":"Elite Enterprises",
    "wof:placetype":"venue"
},
  "geometry": {"coordinates":[-73.017399,41.524683],"type":"Point"}
}