{
  "type": "Feature",
  "properties": {
    "iso:country":"US",
    "sg:address":"121 Great Hill Rd",
    "sg:city":"Portland",
    "sg:classifiers":[
        {
            "category":"Building & Trades",
            "subcategory":"Plumbing",
            "type":"Services"
        }
    ],
    "sg:phone":"+1 860 342 0276",
    "sg:postcode":"06480",
    "sg:province":"CT",
    "sg:tags":[
        "plumbing",
        "contractor"
    ],
    "wof:name":"Philip R Olson",
    "wof:placetype":"venue"
},
  "geometry": {"coordinates":[-72.573002,41.596199],"type":"Point"}
}