{
  "type": "Feature",
  "properties": {
    "addr:full":"60 Acorn Rd Deep River CT 06417",
    "addr:housenumber":"60",
    "addr:postcode":"06417",
    "addr:street":"Acorn Rd",
    "iso:country":"US",
    "sg:address":"60 Acorn Rd",
    "sg:city":"Deep River",
    "sg:classifiers":[
        {
            "category":"Professional",
            "subcategory":"Employment Agencies",
            "type":"Services"
        }
    ],
    "sg:phone":"+1   ",
    "sg:postcode":"06417",
    "sg:province":"CT",
    "wof:name":"Galen Giles Group",
    "wof:placetype":"venue"
},
  "geometry": {"coordinates":[-72.48853099999999,41.351309],"type":"Point"}
}