{
  "type": "Feature",
  "properties": {
    "addr:full":"151 Farmington Ave Hartford CT 06105",
    "addr:housenumber":"151",
    "addr:postcode":"06105",
    "addr:street":"Farmington Ave;Ct",
    "iso:country":"US",
    "sg:address":"151 Farmington Ave",
    "sg:city":"Hartford",
    "sg:classifiers":[
        {
            "category":"Professional",
            "subcategory":"Advertising",
            "type":"Services"
        }
    ],
    "sg:phone":"+1   ",
    "sg:postcode":"06105",
    "sg:province":"CT",
    "sg:tags":[
        "mail",
        "direct"
    ],
    "wof:name":"Xerox",
    "wof:placetype":"venue"
},
  "geometry": {"coordinates":[-72.690383,41.767936],"type":"Point"}
}