{
  "type": "Feature",
  "properties": {
    "addr:full":"72 Shaker Rd Enfield CT 06082",
    "addr:housenumber":"72",
    "addr:postcode":"06082",
    "addr:street":"Shaker Rd",
    "iso:country":"US",
    "sg:address":"72 Shaker Rd",
    "sg:city":"Enfield",
    "sg:classifiers":[
        {
            "category":"Autos & Motor Vehicles",
            "subcategory":"Auto Supplies",
            "type":"Retail Goods"
        }
    ],
    "sg:phone":"+1 860 749 7080",
    "sg:postcode":"06082",
    "sg:province":"CT",
    "sg:tags":[
        "automobile",
        "part",
        "accessory"
    ],
    "sg:website":"http://www.autopartinti.com",
    "wof:name":"Autopart International",
    "wof:placetype":"venue"
},
  "geometry": {"coordinates":[-72.557023,42.005327],"type":"Point"}
}