{
  "type": "Feature",
  "properties": {
    "addr:full":"6 N Pearl St Port Chester CT 10573",
    "addr:housenumber":"6",
    "addr:postcode":"10573",
    "addr:street":"N Pearl St Port Chester Ct",
    "iso:country":"US",
    "sg:address":"6 N Pearl St",
    "sg:city":"Port Chester",
    "sg:classifiers":[
        {
            "category":"Manufacturing",
            "subcategory":"Tools & Machinery",
            "type":"Manufacturing & Wholesale Goods"
        },
        {
            "category":"Wholesale",
            "subcategory":"Auto Parts",
            "type":"Manufacturing & Wholesale Goods"
        }
    ],
    "sg:phone":"+1 914 690 1068",
    "sg:postcode":"10573",
    "sg:province":"CT",
    "sg:tags":[
        "turbochargers",
        "machine",
        "shop"
    ],
    "wof:name":"Cheetah Turbo",
    "wof:placetype":"venue"
},
  "geometry": {"coordinates":[-73.665447,41.002226],"type":"Point"}
}