{
  "type": "Feature",
  "properties": {
    "iso:country":"US",
    "sg:address":"62 Walnut Hill Rd",
    "sg:city":"Bethel",
    "sg:classifiers":[
        {
            "category":"Communications",
            "subcategory":"Newspaper",
            "type":"Services"
        }
    ],
    "sg:phone":"+1 203 798 2120",
    "sg:postcode":"06801",
    "sg:province":"CT",
    "sg:website":"http://www.elcanillita.com",
    "wof:name":"El Canillita",
    "wof:placetype":"venue"
},
  "geometry": {"coordinates":[-73.396652,41.396858],"type":"Point"}
}