{
  "type": "Feature",
  "properties": {
    "addr:full":"153 Boston Post Rd Orange CT 06477",
    "addr:housenumber":"153",
    "addr:postcode":"06477",
    "addr:street":"Boston Post Rd",
    "iso:country":"US",
    "sg:address":"153 Boston Post Rd",
    "sg:city":"Orange",
    "sg:classifiers":[
        {
            "category":"Banks & Credit Unions",
            "subcategory":"Bank",
            "type":"Services"
        }
    ],
    "sg:phone":"+1 203 795 0236",
    "sg:postcode":"06477",
    "sg:province":"CT",
    "sg:tags":[
        "depository",
        "banking",
        "check",
        "cashing"
    ],
    "wof:name":"Connecticut State Check Cashin",
    "wof:placetype":"venue"
},
  "geometry": {"coordinates":[-72.99383899999999,41.273173],"type":"Point"}
}