{
  "type": "Feature",
  "properties": {
    "addr:full":"336 Torrington Rd Litchfield CT 06759",
    "addr:housenumber":"336",
    "addr:postcode":"06759",
    "addr:street":"Torrington Rd",
    "iso:country":"US",
    "sg:address":"336 Torrington Rd",
    "sg:city":"Litchfield",
    "sg:classifiers":[
        {
            "category":"Real Estate",
            "subcategory":"Real Estate Agent",
            "type":"Services"
        }
    ],
    "sg:phone":"+1 860 567 4611",
    "sg:postcode":"06759",
    "sg:province":"CT",
    "wof:name":"Litchfield Realestate",
    "wof:placetype":"venue"
},
  "geometry": {"coordinates":[-73.177876,41.764219],"type":"Point"}
}