{
  "type": "Feature",
  "properties": {
    "iso:country":"US",
    "sg:address":"762 Overhill Dr",
    "sg:city":"Suffield",
    "sg:classifiers":[
        {
            "category":"Recreation",
            "type":"Entertainment"
        }
    ],
    "sg:phone":"+1   ",
    "sg:postcode":"06078",
    "sg:province":"CT",
    "wof:name":"Integrity Martial Arts",
    "wof:placetype":"venue"
},
  "geometry": {"coordinates":[-72.620667,41.986436],"type":"Point"}
}