{
  "type": "Feature",
  "properties": {
    "iso:country":"US",
    "sg:address":"151 Platt St",
    "sg:city":"Milford",
    "sg:classifiers":[
        {
            "category":"Wholesale",
            "subcategory":"Groceries",
            "type":"Manufacturing & Wholesale Goods"
        }
    ],
    "sg:phone":"+1 203 878 7788",
    "sg:postcode":"06460",
    "sg:province":"CT",
    "sg:tags":[
        "general"
    ],
    "wof:name":"C S Brokers",
    "wof:placetype":"venue"
},
  "geometry": {"coordinates":[-73.02018099999999,41.210192],"type":"Point"}
}