{
  "type": "Feature",
  "properties": {
    "addr:full":"26 Short Beach Rd Branford CT 06405",
    "addr:housenumber":"26",
    "addr:postcode":"06405",
    "addr:street":"Short Beach Rd",
    "iso:country":"US",
    "sg:address":"26 Short Beach Rd",
    "sg:city":"Branford",
    "sg:classifiers":[
        {
            "category":"Shopping",
            "subcategory":"Pharmacy",
            "type":"Retail Goods"
        }
    ],
    "sg:phone":"+1 203 488 4372",
    "sg:postcode":"06405",
    "sg:province":"CT",
    "wof:name":"CVS Pharmacy",
    "wof:placetype":"venue"
},
  "geometry": {"coordinates":[-72.829864,41.272154],"type":"Point"}
}