{
  "type": "Feature",
  "properties": {
    "iso:country":"US",
    "sg:address":"63 Goshen Rd",
    "sg:city":"Waterford",
    "sg:classifiers":[
        {
            "category":"Government",
            "subcategory":"Fire Station",
            "type":"Public Place"
        }
    ],
    "sg:phone":"+1 860 443 6260",
    "sg:postcode":"06385",
    "sg:province":"CT",
    "sg:tags":[
        "protection"
    ],
    "wof:name":"Goshen Fire Department",
    "wof:placetype":"venue"
},
  "geometry": {"coordinates":[-72.14240599999999,41.310335],"type":"Point"}
}