{
  "type": "Feature",
  "properties": {
    "addr:full":"1419 Whalley Ave New Haven CT 06515",
    "addr:housenumber":"1419",
    "addr:postcode":"06515",
    "addr:street":"Whalley Ave",
    "iso:country":"US",
    "sg:address":"1419 Whalley Ave",
    "sg:city":"New Haven",
    "sg:classifiers":[
        {
            "category":"Health Services",
            "subcategory":"Clinic",
            "type":"Services"
        }
    ],
    "sg:phone":"+1 203 777 2482",
    "sg:postcode":"06515",
    "sg:province":"CT",
    "sg:tags":[
        "home"
    ],
    "wof:name":"Family Care VNA & Home Care",
    "wof:placetype":"venue"
},
  "geometry": {"coordinates":[-72.975953,41.333676],"type":"Point"}
}