{
  "type": "Feature",
  "properties": {
    "addr:full":"22 Duke Dr Stamford CT 06905",
    "addr:housenumber":"22",
    "addr:postcode":"06905",
    "addr:street":"Duke Dr",
    "iso:country":"US",
    "sg:address":"22 Duke Dr",
    "sg:city":"Stamford",
    "sg:classifiers":[
        {
            "category":"Organizations",
            "subcategory":"Religious Organization",
            "type":"Services"
        }
    ],
    "sg:phone":"+1 203 322 5493",
    "sg:postcode":"06905",
    "sg:province":"CT",
    "sg:tags":[
        "clergy"
    ],
    "wof:name":"Lorenzo M Robinson",
    "wof:placetype":"venue"
},
  "geometry": {"coordinates":[-73.556201,41.103716],"type":"Point"}
}