{
  "type": "Feature",
  "properties": {
    "addr:full":"26 Fitch St Norwalk CT 06855",
    "addr:housenumber":"26",
    "addr:postcode":"06855",
    "addr:street":"Fitch St",
    "iso:country":"US",
    "sg:address":"26 Fitch St",
    "sg:city":"Norwalk",
    "sg:classifiers":[
        {
            "category":"Wholesale",
            "subcategory":"Office Equipment",
            "type":"Manufacturing & Wholesale Goods"
        },
        {
            "category":"Personal",
            "type":"Services"
        },
        {
            "category":"Home & Garden",
            "subcategory":"Hardware",
            "type":"Retail Goods"
        },
        {
            "category":"Building & Trades",
            "subcategory":"Construction",
            "type":"Services"
        },
        {
            "category":"Food & Beverages",
            "subcategory":"Groceries & Convenience Stores",
            "type":"Retail Goods"
        }
    ],
    "sg:phone":"+1 203 838 9089",
    "sg:postcode":"06855",
    "sg:province":"CT",
    "sg:tags":[
        "cabinet",
        "closet",
        "altering",
        "contractor",
        "garage",
        "designing",
        "organizer",
        "accessory",
        "remodeling",
        "furniture"
    ],
    "sg:website":"http://www.ctcloset.com",
    "wof:name":"Connecticut Closet And Shelf",
    "wof:placetype":"venue"
},
  "geometry": {"coordinates":[-73.403358,41.105389],"type":"Point"}
}