{
  "type": "Feature",
  "properties": {
    "addr:full":"80 Burbank Rd Wethersfield CT 06109",
    "addr:housenumber":"80",
    "addr:postcode":"06109",
    "addr:street":"Burbank Rd",
    "iso:country":"US",
    "sg:address":"80 Burbank Rd",
    "sg:city":"Wethersfield",
    "sg:phone":"+1 860 529 3299",
    "sg:postcode":"06109",
    "sg:province":"CT",
    "sg:tags":[
        "product",
        "petroleum"
    ],
    "wof:name":"Northeast Petroleum",
    "wof:placetype":"venue"
},
  "geometry": {"coordinates":[-72.64918299999999,41.718211],"type":"Point"}
}