{
  "type": "Feature",
  "properties": {
    "iso:country":"US",
    "sg:address":"88 Union St",
    "sg:city":"Waterbury",
    "sg:classifiers":[
        {
            "category":"Utilities",
            "subcategory":"Cable",
            "type":"Services"
        }
    ],
    "sg:phone":"+1 203 757 9850",
    "sg:postcode":"06706",
    "sg:province":"CT",
    "sg:tags":[
        "television"
    ],
    "wof:name":"Lodge Net Entertainment",
    "wof:placetype":"venue"
},
  "geometry": {"coordinates":[-73.036536,41.552042],"type":"Point"}
}