{
  "type": "Feature",
  "properties": {
    "addr:full":"105 Stagecoach Rd Windsor CT 06095",
    "addr:housenumber":"105",
    "addr:postcode":"06095",
    "addr:street":"Stagecoach Rd",
    "iso:country":"US",
    "sg:address":"105 Stagecoach Rd",
    "sg:city":"Windsor",
    "sg:classifiers":[
        {
            "category":"Retail",
            "subcategory":"Portrait Studio",
            "type":"Services"
        }
    ],
    "sg:phone":"+1   ",
    "sg:postcode":"06095",
    "sg:province":"CT",
    "sg:tags":[
        "photo"
    ],
    "wof:name":"Cirelli Dese Photography",
    "wof:placetype":"venue"
},
  "geometry": {"coordinates":[-72.66993100000001,41.907947],"type":"Point"}
}