{
  "type": "Feature",
  "properties": {
    "iso:country":"US",
    "sg:address":"1 Hale Rd",
    "sg:city":"Portland",
    "sg:classifiers":[
        {
            "category":"Autos & Motor Vehicles",
            "subcategory":"Fuel & Gas Station",
            "type":"Retail Goods"
        }
    ],
    "sg:phone":"+1   ",
    "sg:postcode":"06480",
    "sg:province":"CT",
    "sg:tags":[
        "automotive",
        "station",
        "gasoline"
    ],
    "wof:name":"Lamore Enterprises Inc",
    "wof:placetype":"venue"
},
  "geometry": {"coordinates":[-72.623684,41.596284],"type":"Point"}
}