{
  "type": "Feature",
  "properties": {
    "iso:country":"US",
    "sg:address":"8 Crown Ave",
    "sg:city":"Norwalk",
    "sg:classifiers":[
        {
            "category":"Building & Trades",
            "subcategory":"Cleaning & Sanitation",
            "type":"Services"
        }
    ],
    "sg:phone":"+1   ",
    "sg:postcode":"06854",
    "sg:province":"CT",
    "sg:tags":[
        "maintenance"
    ],
    "wof:name":"A1 Elite Cleaning Service",
    "wof:placetype":"venue"
},
  "geometry": {"coordinates":[-73.43052299999999,41.101312],"type":"Point"}
}