{
  "type": "Feature",
  "properties": {
    "iso:country":"US",
    "sg:address":"50 Obtuse Rd",
    "sg:city":"Newtown",
    "sg:classifiers":[
        {
            "category":"Professional",
            "subcategory":"Business Services",
            "type":"Services"
        }
    ],
    "sg:phone":"+1   ",
    "sg:postcode":"06470",
    "sg:province":"CT",
    "wof:name":"Iwpr Group LLC",
    "wof:placetype":"venue"
},
  "geometry": {"coordinates":[-73.35442399999999,41.447749],"type":"Point"}
}