{
  "type": "Feature",
  "properties": {
    "addr:full":"6 Huntington Dr Somers CT 06071",
    "addr:housenumber":"6",
    "addr:postcode":"06071",
    "addr:street":"Huntington Dr Somers Ct",
    "iso:country":"US",
    "sg:address":"6 Huntington Dr",
    "sg:city":"Somers",
    "sg:classifiers":[
        {
            "category":"Building & Trades",
            "subcategory":"Plumbing",
            "type":"Services"
        }
    ],
    "sg:phone":"+1 860 698 9696",
    "sg:postcode":"06071",
    "sg:province":"CT",
    "sg:tags":[
        "heat",
        "air",
        "conditioning",
        "contractor"
    ],
    "wof:name":"D & D Heating & AC",
    "wof:placetype":"venue"
},
  "geometry": {"coordinates":[-72.43561200000001,42.01328],"type":"Point"}
}