{
  "type": "Feature",
  "properties": {
    "iso:country":"US",
    "sg:address":"454 E Main St",
    "sg:city":"Branford",
    "sg:classifiers":[
        {
            "category":"Wholesale",
            "subcategory":"Petroleum",
            "type":"Manufacturing & Wholesale Goods"
        }
    ],
    "sg:phone":"+1 203 488 1800",
    "sg:postcode":"06405",
    "sg:province":"CT",
    "sg:tags":[
        "pipe",
        "line",
        "company"
    ],
    "sg:website":"www.islandereastpipeline.com",
    "wof:name":"Islander East",
    "wof:placetype":"venue"
},
  "geometry": {"coordinates":[-72.774002,41.298364],"type":"Point"}
}