{
  "type": "Feature",
  "properties": {
    "addr:full":"30 Elmwood Ct Newington CT 06111",
    "addr:housenumber":"30",
    "addr:postcode":"06111",
    "addr:street":"Elmwood Ct",
    "iso:country":"US",
    "sg:address":"30 Elmwood Ct",
    "sg:city":"Newington",
    "sg:classifiers":[
        {
            "category":"Organizations",
            "subcategory":"Labor Organization",
            "type":"Services"
        }
    ],
    "sg:phone":"+1   ",
    "sg:postcode":"06111",
    "sg:province":"CT",
    "wof:name":"U A W Local 376",
    "wof:placetype":"venue"
},
  "geometry": {"coordinates":[-72.71499300000001,41.722907],"type":"Point"}
}