{
  "type": "Feature",
  "properties": {
    "iso:country":"US",
    "sg:address":"1011 Hope St",
    "sg:city":"Stamford",
    "sg:classifiers":[
        {
            "category":"Professional",
            "type":"Services"
        }
    ],
    "sg:phone":"+1 203 363 0447",
    "sg:postcode":"06907",
    "sg:province":"CT",
    "sg:tags":[
        "establishment"
    ],
    "wof:name":"Fast Shuttle",
    "wof:placetype":"venue"
},
  "geometry": {"coordinates":[-73.518102,41.094396],"type":"Point"}
}