{
  "type": "Feature",
  "properties": {
    "addr:full":"97 Waterbury Rd Prospect CT 06712",
    "addr:housenumber":"97",
    "addr:postcode":"06712",
    "addr:street":"Waterbury Rd",
    "iso:country":"US",
    "sg:address":"97 Waterbury Rd",
    "sg:city":"Prospect",
    "sg:classifiers":[
        {
            "category":"Retail",
            "subcategory":"Car Wash",
            "type":"Services"
        }
    ],
    "sg:phone":"+1 203 527 9700",
    "sg:postcode":"06712",
    "sg:province":"CT",
    "sg:tags":[
        "polishing",
        "carwash",
        "washing"
    ],
    "wof:name":"Personal Touch Car Wash & Fast",
    "wof:placetype":"venue"
},
  "geometry": {"coordinates":[-72.988393,41.516959],"type":"Point"}
}