{
  "type": "Feature",
  "properties": {
    "iso:country":"US",
    "sg:address":"29 Quintard Ave",
    "sg:city":"Norwalk",
    "sg:classifiers":[
        {
            "category":"Building & Trades",
            "subcategory":"Construction",
            "type":"Services"
        }
    ],
    "sg:phone":"+1 203 838 5714",
    "sg:postcode":"06854",
    "sg:province":"CT",
    "sg:tags":[
        "painting",
        "contractor"
    ],
    "wof:name":"Koukidis Painting",
    "wof:placetype":"venue"
},
  "geometry": {"coordinates":[-73.413235,41.089341],"type":"Point"}
}