{
  "type": "Feature",
  "properties": {
    "iso:country":"US",
    "sg:address":"22 Kindle Ln",
    "sg:city":"Derby",
    "sg:classifiers":[
        {
            "category":"Government",
            "subcategory":"Court House",
            "type":"Public Place"
        }
    ],
    "sg:phone":"+1 203 734 3673",
    "sg:postcode":"06418",
    "sg:province":"CT",
    "sg:tags":[
        "justice",
        "peace"
    ],
    "wof:name":"Arlene Defeo",
    "wof:placetype":"venue"
},
  "geometry": {"coordinates":[-73.074067,41.313653],"type":"Point"}
}