{
  "type": "Feature",
  "properties": {
    "iso:country":"US",
    "sg:address":"2 Sodom Ln",
    "sg:city":"Derby",
    "sg:classifiers":[
        {
            "category":"Personal",
            "type":"Services"
        }
    ],
    "sg:phone":"+1 203 370 4977",
    "sg:postcode":"06418",
    "sg:province":"CT",
    "sg:tags":[
        "therapist",
        "massage"
    ],
    "wof:name":"Coastal Wellness",
    "wof:placetype":"venue"
},
  "geometry": {"coordinates":[-73.04761499999999,41.312208],"type":"Point"}
}