{
  "type": "Feature",
  "properties": {
    "addr:full":"95 Maple St Winsted CT 06098",
    "addr:housenumber":"95",
    "addr:postcode":"06098",
    "addr:street":"Maple St Winsted Ct",
    "iso:country":"US",
    "sg:address":"95 Maple St",
    "sg:city":"Winsted",
    "sg:classifiers":[
        {
            "category":"Home & Garden",
            "subcategory":"Garden Supply",
            "type":"Retail Goods"
        }
    ],
    "sg:phone":"+1 860 738 0440",
    "sg:postcode":"06098",
    "sg:province":"CT",
    "sg:tags":[
        "equipment",
        "lawn"
    ],
    "wof:name":"Argus Inc",
    "wof:placetype":"venue"
},
  "geometry": {"coordinates":[-73.066883,41.919758],"type":"Point"}
}