{
  "type": "Feature",
  "properties": {
    "addr:full":"208 Adams Rd Easton CT 06612",
    "addr:housenumber":"208",
    "addr:postcode":"06612",
    "addr:street":"Adams Rd",
    "iso:country":"US",
    "sg:address":"208 Adams Rd",
    "sg:city":"Easton",
    "sg:classifiers":[
        {
            "category":"Professional",
            "subcategory":"Engineering",
            "type":"Services"
        }
    ],
    "sg:phone":"+1   ",
    "sg:postcode":"06612",
    "sg:province":"CT",
    "wof:name":"Ochman Associates Inc",
    "wof:placetype":"venue"
},
  "geometry": {"coordinates":[-73.27654099999999,41.263279],"type":"Point"}
}