{
  "type": "Feature",
  "properties": {
    "addr:full":"755 Boston Post Rd Westbrook CT 06498",
    "addr:housenumber":"755",
    "addr:postcode":"06498",
    "addr:street":"Boston Post Rd",
    "iso:country":"US",
    "sg:address":"755 Boston Post Rd",
    "sg:city":"Westbrook",
    "sg:classifiers":[
        {
            "category":"Shopping",
            "subcategory":"Used Merchandise",
            "type":"Retail Goods"
        }
    ],
    "sg:phone":"+1 860 399 3475",
    "sg:postcode":"06498",
    "sg:province":"CT",
    "wof:name":"Wooden Wheelbarrow Antiques",
    "wof:placetype":"venue"
},
  "geometry": {"coordinates":[-72.460691,41.2793],"type":"Point"}
}