{
  "type": "Feature",
  "properties": {
    "iso:country":"US",
    "sg:address":"316 Turtle Back Rd",
    "sg:city":"New Canaan",
    "sg:classifiers":[
        {
            "category":"Professional",
            "type":"Services"
        },
        {
            "category":"Shopping",
            "subcategory":"Gifts & Souvenirs",
            "type":"Retail Goods"
        }
    ],
    "sg:phone":"+1 203 966 1533",
    "sg:postcode":"06840",
    "sg:province":"NY",
    "sg:tags":[
        "establishment"
    ],
    "wof:name":"Affiliated Opportunities Inc",
    "wof:placetype":"venue"
},
  "geometry": {"coordinates":[-73.528524,41.175288],"type":"Point"}
}