{
  "type": "Feature",
  "properties": {
    "addr:full":"130 Westbrook Rd Essex CT 06426",
    "addr:housenumber":"130",
    "addr:postcode":"06426",
    "addr:street":"Westbrook Rd",
    "iso:country":"US",
    "sg:address":"130 Westbrook Rd",
    "sg:city":"Essex",
    "sg:classifiers":[
        {
            "category":"Insurance",
            "subcategory":"Insurance Agent",
            "type":"Services"
        }
    ],
    "sg:phone":"+1 860 767 4586",
    "sg:postcode":"06426",
    "sg:province":"CT",
    "wof:name":"R F P Inc",
    "wof:placetype":"venue"
},
  "geometry": {"coordinates":[-72.418497,41.336103],"type":"Point"}
}