{
  "type": "Feature",
  "properties": {
    "addr:full":"325 Fairlea Rd Orange CT 06477",
    "addr:housenumber":"325",
    "addr:postcode":"06477",
    "addr:street":"Fairlea Rd",
    "iso:country":"US",
    "sg:address":"325 Fairlea Rd",
    "sg:city":"Orange",
    "sg:classifiers":[
        {
            "category":"Building & Trades",
            "subcategory":"Construction",
            "type":"Services"
        }
    ],
    "sg:phone":"+1 203 799 2500",
    "sg:postcode":"06477",
    "sg:province":"CT",
    "sg:tags":[
        "contractor"
    ],
    "wof:name":"Colonna Masnry Con & Asp Pavin",
    "wof:placetype":"venue"
},
  "geometry": {"coordinates":[-73.019817,41.260163],"type":"Point"}
}