{
  "type": "Feature",
  "properties": {
    "iso:country":"US",
    "sg:address":"69 Mount Pleasant St",
    "sg:city":"Derby",
    "sg:classifiers":[
        {
            "category":"Building & Trades",
            "subcategory":"Landscaping Services",
            "type":"Services"
        }
    ],
    "sg:phone":"+1 203 430 9864",
    "sg:postcode":"06418",
    "sg:province":"CT",
    "sg:tags":[
        "landscape",
        "contractor"
    ],
    "wof:name":"EMP Pinto's Landscaping",
    "wof:placetype":"venue"
},
  "geometry": {"coordinates":[-73.080136,41.323041],"type":"Point"}
}