{
  "type": "Feature",
  "properties": {
    "iso:country":"US",
    "sg:address":"49 Broad St",
    "sg:city":"Plainville",
    "sg:classifiers":[
        {
            "category":"Professional",
            "subcategory":"Lawyer & Legal Services",
            "type":"Services"
        }
    ],
    "sg:phone":"+1 860 747 5745",
    "sg:postcode":"06062",
    "sg:province":"CT",
    "sg:tags":[
        "attorney",
        "injury",
        "personal",
        "divorce",
        "real estate",
        "law",
        "bankruptcy"
    ],
    "wof:name":"Thompson Vollon And Donovan LLC",
    "wof:placetype":"venue"
},
  "geometry": {"coordinates":[-72.866091,41.667998],"type":"Point"}
}