{
  "type": "Feature",
  "properties": {
    "addr:full":"1044 Main St Watertown CT 06795",
    "addr:housenumber":"1044",
    "addr:postcode":"06795",
    "addr:street":"Main St",
    "iso:country":"US",
    "sg:address":"1044 Main St",
    "sg:city":"Watertown",
    "sg:classifiers":[
        {
            "category":"Cinema",
            "subcategory":"Movie Rental",
            "type":"Entertainment"
        }
    ],
    "sg:phone":"+1   ",
    "sg:postcode":"06795",
    "sg:province":"CT",
    "sg:tags":[
        "video",
        "store"
    ],
    "wof:name":"Hollywood Home Video",
    "wof:placetype":"venue"
},
  "geometry": {"coordinates":[-73.11122400000001,41.594799],"type":"Point"}
}