{
  "type": "Feature",
  "properties": {
    "addr:full":"105 Maywood Rd Norwalk CT 06850",
    "addr:housenumber":"105",
    "addr:postcode":"06850",
    "addr:street":"Maywood Rd",
    "iso:country":"US",
    "sg:address":"105 Maywood Rd",
    "sg:city":"Norwalk",
    "sg:classifiers":[
        {
            "category":"Real Estate",
            "subcategory":"Real Estate Agent",
            "type":"Services"
        }
    ],
    "sg:phone":"+1 203 854 9500",
    "sg:postcode":"06850",
    "sg:province":"CT",
    "wof:name":"Ashton Group LLC",
    "wof:placetype":"venue"
},
  "geometry": {"coordinates":[-73.460369,41.103661],"type":"Point"}
}