{
  "type": "Feature",
  "properties": {
    "iso:country":"US",
    "sg:address":"15 Woodchuck Hill Rd",
    "sg:city":"West Simsbury",
    "sg:classifiers":[
        {
            "category":"Building & Trades",
            "subcategory":"Landscaping Services",
            "type":"Services"
        }
    ],
    "sg:phone":"+1 860 651 7281",
    "sg:postcode":"06092",
    "sg:province":"CT",
    "sg:tags":[
        "landscape",
        "contractor"
    ],
    "wof:name":"Brookescape Inc",
    "wof:placetype":"venue"
},
  "geometry": {"coordinates":[-72.868601,41.880081],"type":"Point"}
}