{
  "type": "Feature",
  "properties": {
    "iso:country":"US",
    "sg:address":"890 Wintergreen Ave",
    "sg:city":"Hamden",
    "sg:classifiers":[
        {
            "category":"Manufacturing",
            "subcategory":"Motor Vehicles & Parts",
            "type":"Manufacturing & Wholesale Goods"
        }
    ],
    "sg:phone":"+1 203 982 8150",
    "sg:postcode":"06514",
    "sg:province":"CT",
    "sg:tags":[
        "fluid",
        "power",
        "mfg"
    ],
    "wof:name":"Scrape Alot Productions",
    "wof:placetype":"venue"
},
  "geometry": {"coordinates":[-72.96616899999999,41.350527],"type":"Point"}
}