{
  "type": "Feature",
  "properties": {
    "iso:country":"US",
    "sg:address":"625 Harbor View Rd",
    "sg:city":"Orange",
    "sg:classifiers":[
        {
            "category":"Professional",
            "type":"Services"
        }
    ],
    "sg:phone":"+1 203 387 9149",
    "sg:postcode":"06477",
    "sg:province":"CT",
    "wof:name":"Kvk LLC",
    "wof:placetype":"venue"
},
  "geometry": {"coordinates":[-72.988604,41.29302],"type":"Point"}
}