{
  "type": "Feature",
  "properties": {
    "addr:full":"1231 Washington St Middletown CT 06457",
    "addr:housenumber":"1231",
    "addr:postcode":"06457",
    "addr:street":"Washington St",
    "iso:country":"US",
    "sg:address":"1231 Washington St",
    "sg:city":"Middletown",
    "sg:classifiers":[
        {
            "category":"Professional",
            "subcategory":"Business Services",
            "type":"Services"
        }
    ],
    "sg:phone":"+1   ",
    "sg:postcode":"06457",
    "sg:province":"CT",
    "wof:name":"Wilson Literary Agency",
    "wof:placetype":"venue"
},
  "geometry": {"coordinates":[-72.692033,41.549603],"type":"Point"}
}