{
  "type": "Feature",
  "properties": {
    "addr:full":"109 Chase Ave Waterbury CT 06704",
    "addr:housenumber":"109",
    "addr:postcode":"06704",
    "addr:street":"Chase Ave",
    "iso:country":"US",
    "sg:address":"109 Chase Ave",
    "sg:city":"Waterbury",
    "sg:classifiers":[
        {
            "category":"Personal",
            "subcategory":"Beauty Salon",
            "type":"Services"
        }
    ],
    "sg:phone":"+1 203 754 0041",
    "sg:postcode":"06704",
    "sg:province":"CT",
    "wof:name":"Cut N Up",
    "wof:placetype":"venue"
},
  "geometry": {"coordinates":[-73.03183300000001,41.580036],"type":"Point"}
}