{
  "type": "Feature",
  "properties": {
    "iso:country":"US",
    "sg:address":"132 Hut Hill Rd",
    "sg:city":"Bridgewater",
    "sg:classifiers":[
        {
            "category":"Social Services",
            "subcategory":"Adult Care",
            "type":"Services"
        }
    ],
    "sg:phone":"+1   ",
    "sg:postcode":"06752",
    "sg:province":"CT",
    "sg:tags":[
        "residential"
    ],
    "wof:name":"McDonaugh House",
    "wof:placetype":"venue"
},
  "geometry": {"coordinates":[-73.35766599999999,41.525506],"type":"Point"}
}