{
  "type": "Feature",
  "properties": {
    "iso:country":"US",
    "sg:address":"73 Mile Creek Rd",
    "sg:city":"Old Lyme",
    "sg:classifiers":[
        {
            "category":"Professional",
            "subcategory":"Business Services",
            "type":"Services"
        }
    ],
    "sg:phone":"+1   ",
    "sg:postcode":"06371",
    "sg:province":"CT",
    "wof:name":"Black Hall Yacht Sales LLC",
    "wof:placetype":"venue"
},
  "geometry": {"coordinates":[-72.307839,41.304973],"type":"Point"}
}