{
  "type": "Feature",
  "properties": {
    "iso:country":"US",
    "sg:address":"110 New Hartford Rd",
    "sg:city":"Barkhamsted",
    "sg:phone":"+1 860 379 8937",
    "sg:postcode":"06063",
    "sg:province":"CT",
    "wof:name":"Log House Restaurant",
    "wof:placetype":"venue"
},
  "geometry": {"coordinates":[-72.99612399999999,41.903302],"type":"Point"}
}