{
  "type": "Feature",
  "properties": {
    "addr:full":"16 Universal Dr N North Haven CT 06473",
    "addr:housenumber":"16",
    "addr:postcode":"06473",
    "addr:street":"Universal Dr N;Haven",
    "iso:country":"US",
    "sg:address":"16 Universal Dr N",
    "sg:city":"North Haven",
    "sg:classifiers":[
        {
            "category":"Shopping",
            "subcategory":"Computers & Home Electronics",
            "type":"Retail Goods"
        }
    ],
    "sg:phone":"+1 203 772 2273",
    "sg:postcode":"06473",
    "sg:province":"CT",
    "sg:tags":[
        "equipment",
        "electronic",
        "supply"
    ],
    "wof:name":"Circuit City",
    "wof:placetype":"venue"
},
  "geometry": {"coordinates":[-72.868543,41.351112],"type":"Point"}
}