{
  "type": "Feature",
  "properties": {
    "iso:country":"US",
    "sg:address":"25 Kimberly Pl",
    "sg:city":"New Canaan",
    "sg:classifiers":[
        {
            "category":"Professional",
            "subcategory":"Management & Consulting",
            "type":"Services"
        }
    ],
    "sg:phone":"+1 203 972 1889",
    "sg:postcode":"06840",
    "sg:province":"NY",
    "sg:tags":[
        "consultant",
        "educational"
    ],
    "wof:name":"Ruth Smithers Ed Conslnt",
    "wof:placetype":"venue"
},
  "geometry": {"coordinates":[-73.504324,41.148595],"type":"Point"}
}