{
  "type": "Feature",
  "properties": {
    "addr:full":"24 Westmont Rd Wethersfield CT 06109",
    "addr:housenumber":"24",
    "addr:postcode":"06109",
    "addr:street":"Westmont Rd",
    "iso:country":"US",
    "sg:address":"24 Westmont Rd",
    "sg:city":"Wethersfield",
    "sg:classifiers":[
        {
            "category":"Professional",
            "subcategory":"Computer Services",
            "type":"Services"
        }
    ],
    "sg:phone":"+1   ",
    "sg:postcode":"06109",
    "sg:province":"CT",
    "sg:tags":[
        "related"
    ],
    "wof:name":"Hipoint Consulting Group LLC",
    "wof:placetype":"venue"
},
  "geometry": {"coordinates":[-72.699533,41.676686],"type":"Point"}
}