{
  "type": "Feature",
  "properties": {
    "addr:full":"26 High Rise Rd Danbury CT 06811",
    "addr:housenumber":"26",
    "addr:postcode":"06811",
    "addr:street":"High Rise Rd",
    "iso:country":"US",
    "sg:address":"26 High Rise Rd",
    "sg:city":"Danbury",
    "sg:classifiers":[
        {
            "category":"Professional",
            "subcategory":"Management & Consulting",
            "type":"Services"
        }
    ],
    "sg:phone":"+1   ",
    "sg:postcode":"06811",
    "sg:province":"CT",
    "sg:tags":[
        "consultant"
    ],
    "wof:name":"Ellen Farrar",
    "wof:placetype":"venue"
},
  "geometry": {"coordinates":[-73.449423,41.435714],"type":"Point"}
}