{
  "type": "Feature",
  "properties": {
    "iso:country":"US",
    "sg:address":"520 Success Ave",
    "sg:city":"Bridgeport",
    "sg:classifiers":[
        {
            "category":"Building & Trades",
            "subcategory":"Electrical",
            "type":"Services"
        }
    ],
    "sg:phone":"+1 203 330 1592",
    "sg:postcode":"06610",
    "sg:province":"CT",
    "sg:tags":[
        "booth",
        "equipment",
        "telephone",
        "pay"
    ],
    "wof:name":"New England Telecommunications",
    "wof:placetype":"venue"
},
  "geometry": {"coordinates":[-73.15647800000001,41.199586],"type":"Point"}
}