{
  "type": "Feature",
  "properties": {
    "addr:full":"11 Henry Dr Shelton CT 06484",
    "addr:housenumber":"11",
    "addr:postcode":"06484",
    "addr:street":"Henry Dr",
    "iso:country":"US",
    "sg:address":"11 Henry Dr",
    "sg:city":"Shelton",
    "sg:classifiers":[
        {
            "category":"Professional",
            "subcategory":"Business Services",
            "type":"Services"
        }
    ],
    "sg:phone":"+1   ",
    "sg:postcode":"06484",
    "sg:province":"CT",
    "wof:name":"Power & Network Solutions LLC",
    "wof:placetype":"venue"
},
  "geometry": {"coordinates":[-73.15423,41.342693],"type":"Point"}
}