{
  "type": "Feature",
  "properties": {
    "addr:full":"1528 Farmington Ave Berlin CT 06037",
    "addr:housenumber":"1528",
    "addr:postcode":"06037",
    "addr:street":"Farmington Ave",
    "iso:country":"US",
    "sg:address":"1528 Farmington Ave",
    "sg:city":"Berlin",
    "sg:classifiers":[
        {
            "category":"Education",
            "subcategory":"School",
            "type":"Public Place"
        }
    ],
    "sg:phone":"+1   ",
    "sg:postcode":"06037",
    "sg:province":"CT",
    "wof:name":"Worthington School",
    "wof:placetype":"venue"
},
  "geometry": {"coordinates":[-72.746567,41.622154],"type":"Point"}
}