{
  "type": "Feature",
  "properties": {
    "iso:country":"US",
    "sg:address":"985 Watertown Ave",
    "sg:city":"Waterbury",
    "sg:classifiers":[
        {
            "category":"Banks & Credit Unions",
            "subcategory":"Bank",
            "type":"Services"
        }
    ],
    "sg:phone":"+1 203 753 1874",
    "sg:postcode":"06708",
    "sg:province":"CT",
    "sg:tags":[
        "depository",
        "banking"
    ],
    "wof:name":"Thomaston Savings Bank",
    "wof:placetype":"venue"
},
  "geometry": {"coordinates":[-73.06720300000001,41.574299],"type":"Point"}
}