{
  "type": "Feature",
  "properties": {
    "iso:country":"US",
    "sg:address":"191 Main St",
    "sg:city":"Norwalk",
    "sg:classifiers":[
        {
            "category":"Autos & Motor Vehicles",
            "subcategory":"Automobile Sales",
            "type":"Retail Goods"
        }
    ],
    "sg:phone":"+1 203 750 9555",
    "sg:postcode":"06851",
    "sg:province":"CT",
    "sg:tags":[
        "used"
    ],
    "wof:name":"International Motors",
    "wof:placetype":"venue"
},
  "geometry": {"coordinates":[-73.421284,41.126569],"type":"Point"}
}