{
  "type": "Feature",
  "properties": {
    "addr:full":"24 Lakeview Rd Brookfield CT 06804",
    "addr:housenumber":"24",
    "addr:postcode":"06804",
    "addr:street":"Lakeview Rd",
    "iso:country":"US",
    "sg:address":"24 Lakeview Rd",
    "sg:city":"Brookfield",
    "sg:classifiers":[
        {
            "category":"Building & Trades",
            "subcategory":"Construction",
            "type":"Services"
        }
    ],
    "sg:phone":"+1 203 740 9114",
    "sg:postcode":"06804",
    "sg:province":"CT",
    "sg:tags":[
        "glazing",
        "contractor"
    ],
    "wof:name":"Glass By Design",
    "wof:placetype":"venue"
},
  "geometry": {"coordinates":[-73.432238,41.471926],"type":"Point"}
}