{
  "type": "Feature",
  "properties": {
    "addr:full":"21 Montauk Ave New London CT 06320",
    "addr:housenumber":"21",
    "addr:postcode":"06320",
    "addr:street":"Montauk Ave New London Ct",
    "iso:country":"US",
    "sg:address":"21 Montauk Ave",
    "sg:city":"New London",
    "sg:classifiers":[
        {
            "category":"Health Services",
            "subcategory":"Doctor",
            "type":"Services"
        }
    ],
    "sg:phone":"+1   ",
    "sg:postcode":"06320",
    "sg:province":"CT",
    "sg:tags":[
        "medical"
    ],
    "wof:name":"John Peter Bigos MD",
    "wof:placetype":"venue"
},
  "geometry": {"coordinates":[-72.105755,41.34905],"type":"Point"}
}