{
  "type": "Feature",
  "properties": {
    "addr:full":"76 Lake Ave Danbury CT 06810",
    "addr:housenumber":"76",
    "addr:postcode":"06810",
    "addr:street":"Lake Ave",
    "iso:country":"US",
    "sg:address":"76 Lake Ave",
    "sg:city":"Danbury",
    "sg:classifiers":[
        {
            "category":"Shopping",
            "subcategory":"Jewelry",
            "type":"Retail Goods"
        }
    ],
    "sg:phone":"+1 203 748 3886",
    "sg:postcode":"06810",
    "sg:province":"CT",
    "sg:tags":[
        "store"
    ],
    "wof:name":"Prata Jewelers",
    "wof:placetype":"venue"
},
  "geometry": {"coordinates":[-73.469309,41.388661],"type":"Point"}
}