{
  "type": "Feature",
  "properties": {
    "addr:full":"200 Riverside Ave Bristol CT 06010",
    "addr:housenumber":"200",
    "addr:postcode":"06010",
    "addr:street":"Riverside Ave Bristol Ct",
    "iso:country":"US",
    "sg:address":"200 Riverside Ave",
    "sg:city":"Bristol",
    "sg:classifiers":[
        {
            "category":"Food & Beverages",
            "subcategory":"Groceries & Convenience Stores",
            "type":"Retail Goods"
        }
    ],
    "sg:phone":"+1 860 583 1579",
    "sg:postcode":"06010",
    "sg:province":"CT",
    "wof:name":"7-Eleven",
    "wof:placetype":"venue"
},
  "geometry": {"coordinates":[-72.935114,41.670135],"type":"Point"}
}