{
  "type": "Feature",
  "properties": {
    "addr:full":"19 E Granby Rd Granby CT 06035",
    "addr:housenumber":"19",
    "addr:postcode":"06035",
    "addr:street":"E Granby Rd",
    "iso:country":"US",
    "sg:address":"19 E Granby Rd",
    "sg:city":"Granby",
    "sg:classifiers":[
        {
            "category":"Organizations",
            "subcategory":"Community Association",
            "type":"Services"
        }
    ],
    "sg:phone":"+1   ",
    "sg:postcode":"06035",
    "sg:province":"CT",
    "wof:name":"Saint Marks Mason Lodge",
    "wof:placetype":"venue"
},
  "geometry": {"coordinates":[-72.787519,41.953777],"type":"Point"}
}