{
  "type": "Feature",
  "properties": {
    "iso:country":"US",
    "sg:address":"279 New Milford Tpke",
    "sg:city":"Marble Dale",
    "sg:classifiers":[
        {
            "category":"Building & Trades",
            "subcategory":"Construction",
            "type":"Services"
        }
    ],
    "sg:phone":"+1 860 868 7268",
    "sg:postcode":"06777",
    "sg:province":"CT",
    "sg:tags":[
        "heavy"
    ],
    "wof:name":"J & S Blasting Inc",
    "wof:placetype":"venue"
},
  "geometry": {"coordinates":[-73.37424,41.659999],"type":"Point"}
}