{
  "type": "Feature",
  "properties": {
    "addr:full":"72 Spruce St Stamford CT 06902",
    "addr:housenumber":"72",
    "addr:postcode":"06902",
    "addr:street":"Spruce St",
    "iso:country":"US",
    "sg:address":"72 Spruce St",
    "sg:city":"Stamford",
    "sg:classifiers":[
        {
            "category":"Real Estate",
            "subcategory":"Real Estate Operator",
            "type":"Services"
        }
    ],
    "sg:phone":"+1 203 327 9913",
    "sg:postcode":"06902",
    "sg:province":"CT",
    "sg:tags":[
        "building",
        "apartment"
    ],
    "wof:name":"Coleman Twers Tnnts Asociation",
    "wof:placetype":"venue"
},
  "geometry": {"coordinates":[-73.549885,41.050396],"type":"Point"}
}