{
  "type": "Feature",
  "properties": {
    "addr:full":"25 Great Pond Dr Windsor CT 06095",
    "addr:housenumber":"25",
    "addr:postcode":"06095",
    "addr:street":"Great Pond Dr",
    "iso:country":"US",
    "sg:address":"25 Great Pond Dr",
    "sg:city":"Windsor",
    "sg:classifiers":[
        {
            "category":"Professional",
            "subcategory":"Advertising",
            "type":"Services"
        }
    ],
    "sg:phone":"+1   ",
    "sg:postcode":"06095",
    "sg:province":"CT",
    "sg:tags":[
        "mail",
        "direct"
    ],
    "wof:name":"Advo Inc",
    "wof:placetype":"venue"
},
  "geometry": {"coordinates":[-72.71897800000001,41.873702],"type":"Point"}
}