{
  "type": "Feature",
  "properties": {
    "addr:full":"1027 Worthington Ridge Berlin CT 06037",
    "addr:housenumber":"1027",
    "addr:postcode":"06037",
    "addr:street":"Worthington Ridge",
    "iso:country":"US",
    "sg:address":"1027 Worthington Ridge",
    "sg:city":"Berlin",
    "sg:classifiers":[
        {
            "category":"Insurance",
            "subcategory":"Insurance Agent",
            "type":"Services"
        }
    ],
    "sg:phone":"+1 860 828 1222",
    "sg:postcode":"06037",
    "sg:province":"CT",
    "wof:name":"Connetticuit Business Brokers",
    "wof:placetype":"venue"
},
  "geometry": {"coordinates":[-72.746764,41.616129],"type":"Point"}
}