{
  "type": "Feature",
  "properties": {
    "addr:full":"65 Whittlesey Brook Rd Deep River CT 06417",
    "addr:housenumber":"65",
    "addr:postcode":"06417",
    "addr:street":"Whittlesey Brook Rd",
    "iso:country":"US",
    "sg:address":"65 Whittlesey Brook Rd",
    "sg:city":"Deep River",
    "sg:classifiers":[
        {
            "category":"Education",
            "subcategory":"Dance Studio",
            "type":"Public Place"
        }
    ],
    "sg:phone":"+1   ",
    "sg:postcode":"06417",
    "sg:province":"CT",
    "wof:name":"Dancing Deer Development LLC",
    "wof:placetype":"venue"
},
  "geometry": {"coordinates":[-72.437923,41.363207],"type":"Point"}
}