{
  "type": "Feature",
  "properties": {
    "addr:full":"2 Lindsley Dr Wolcott CT 06716",
    "addr:housenumber":"2",
    "addr:postcode":"06716",
    "addr:street":"Lindsley Dr",
    "iso:country":"US",
    "sg:address":"2 Lindsley Dr",
    "sg:city":"Wolcott",
    "sg:classifiers":[
        {
            "category":"Wholesale",
            "subcategory":"Books, Periodicals, & Newspapers",
            "type":"Manufacturing & Wholesale Goods"
        }
    ],
    "sg:phone":"+1 203 591 1724",
    "sg:postcode":"06716",
    "sg:province":"CT",
    "wof:name":"Mg Educational RES Dev Pubg Co",
    "wof:placetype":"venue"
},
  "geometry": {"coordinates":[-72.95858699999999,41.607493],"type":"Point"}
}