{
  "type": "Feature",
  "properties": {
    "iso:country":"US",
    "sg:address":"54 Berlin St",
    "sg:city":"East Berlin",
    "sg:classifiers":[
        {
            "category":"Manufacturing",
            "subcategory":"Tools & Machinery",
            "type":"Manufacturing & Wholesale Goods"
        }
    ],
    "sg:phone":"+1 860 828 6949",
    "sg:postcode":"06023",
    "sg:province":"CT",
    "sg:tags":[
        "machine",
        "shop"
    ],
    "wof:name":"B & S Machine Inc",
    "wof:placetype":"venue"
},
  "geometry": {"coordinates":[-72.724953,41.617007],"type":"Point"}
}