{
  "type": "Feature",
  "properties": {
    "addr:full":"111 Oak St Hartford CT 06106",
    "addr:housenumber":"111",
    "addr:postcode":"06106",
    "addr:street":"Oak St",
    "iso:country":"US",
    "sg:address":"111 Oak St",
    "sg:city":"Hartford",
    "sg:classifiers":[
        {
            "category":"Professional",
            "subcategory":"Lawyer & Legal Services",
            "type":"Services"
        }
    ],
    "sg:phone":"+1   ",
    "sg:postcode":"06106",
    "sg:province":"CT",
    "wof:name":"Kaatz & Peikes",
    "wof:placetype":"venue"
},
  "geometry": {"coordinates":[-72.68451,41.7606],"type":"Point"}
}