{
  "type": "Feature",
  "properties": {
    "iso:country":"US",
    "sg:address":"131 E Elm St",
    "sg:city":"Greenwich",
    "sg:classifiers":[
        {
            "category":"Real Estate",
            "subcategory":"Architect",
            "type":"Services"
        }
    ],
    "sg:phone":"+1   ",
    "sg:postcode":"06830",
    "sg:province":"CT",
    "sg:tags":[
        "architectural"
    ],
    "wof:name":"Currie Associates",
    "wof:placetype":"venue"
},
  "geometry": {"coordinates":[-73.619963,41.027744],"type":"Point"}
}