{
  "type": "Feature",
  "properties": {
    "iso:country":"US",
    "sg:address":"533 S Broad St",
    "sg:city":"Meriden",
    "sg:classifiers":[
        {
            "category":"Shopping",
            "subcategory":"Optical Goods",
            "type":"Retail Goods"
        },
        {
            "category":"Health Services",
            "subcategory":"Optometrist",
            "type":"Services"
        }
    ],
    "sg:phone":"+1 203 238 4150",
    "sg:postcode":"06450",
    "sg:province":"CT",
    "wof:name":"Vision Partners LLC",
    "wof:placetype":"venue"
},
  "geometry": {"coordinates":[-72.808312,41.508936],"type":"Point"}
}