{
  "type": "Feature",
  "properties": {
    "addr:full":"12 Oakwood Ave Norwalk CT 06850",
    "addr:housenumber":"12",
    "addr:postcode":"06850",
    "addr:street":"Oakwood Ave",
    "iso:country":"US",
    "sg:address":"12 Oakwood Ave",
    "sg:city":"Norwalk",
    "sg:classifiers":[
        {
            "category":"Professional",
            "subcategory":"Business Services",
            "type":"Services"
        }
    ],
    "sg:phone":"+1 203 750 8712",
    "sg:postcode":"06850",
    "sg:province":"CT",
    "sg:tags":[
        "paging",
        "answering"
    ],
    "wof:name":"Telephone Answering Svc",
    "wof:placetype":"venue"
},
  "geometry": {"coordinates":[-73.42920599999999,41.150008],"type":"Point"}
}