{
  "type": "Feature",
  "properties": {
    "iso:country":"US",
    "sg:address":"530 Park Ave",
    "sg:city":"Windsor",
    "sg:classifiers":[
        {
            "category":"Education",
            "subcategory":"School",
            "type":"Public Place"
        }
    ],
    "sg:phone":"+1 860 687 2060",
    "sg:postcode":"06095",
    "sg:province":"CT",
    "sg:tags":[
        "executive"
    ],
    "wof:name":"John F Kennedy Elementary Schl",
    "wof:placetype":"venue"
},
  "geometry": {"coordinates":[-72.67434799999999,41.836791],"type":"Point"}
}