{
  "type": "Feature",
  "properties": {
    "addr:full":"15 Renwick St Stamford CT 06902",
    "addr:housenumber":"15",
    "addr:postcode":"06902",
    "addr:street":"Renwick St",
    "iso:country":"US",
    "sg:address":"15 Renwick St",
    "sg:city":"Stamford",
    "sg:classifiers":[
        {
            "category":"Professional",
            "subcategory":"Detective & Security Services",
            "type":"Services"
        }
    ],
    "sg:phone":"+1 914 841 6507",
    "sg:postcode":"06902",
    "sg:province":"CT",
    "sg:tags":[
        "expert",
        "fingerprint"
    ],
    "wof:name":"Dorothy House Clean",
    "wof:placetype":"venue"
},
  "geometry": {"coordinates":[-73.544107,41.05793],"type":"Point"}
}