{
  "type": "Feature",
  "properties": {
    "addr:full":"10 Joan Rd Stamford CT 06905",
    "addr:housenumber":"10",
    "addr:postcode":"06905",
    "addr:street":"Joan Rd",
    "iso:country":"US",
    "sg:address":"10 Joan Rd",
    "sg:city":"Stamford",
    "sg:classifiers":[
        {
            "category":"Retail",
            "subcategory":"Laundry & Dry Cleaning",
            "type":"Services"
        }
    ],
    "sg:phone":"+1   ",
    "sg:postcode":"06905",
    "sg:province":"CT",
    "sg:tags":[
        "repair",
        "tears",
        "upholstery",
        "clothing",
        "weave"
    ],
    "wof:name":"G M Weavers",
    "wof:placetype":"venue"
},
  "geometry": {"coordinates":[-73.53713399999999,41.104632],"type":"Point"}
}