{
  "type": "Feature",
  "properties": {
    "iso:country":"US",
    "sg:address":"15 Barber St",
    "sg:city":"Windsor",
    "sg:classifiers":[
        {
            "category":"Professional",
            "type":"Services"
        }
    ],
    "sg:phone":"+1 860 246 2144",
    "sg:postcode":"06095",
    "sg:province":"CT",
    "wof:name":"Ely Beryl & Doris Penn Inc",
    "wof:placetype":"venue"
},
  "geometry": {"coordinates":[-72.660501,41.814296],"type":"Point"}
}