{
  "type": "Feature",
  "properties": {
    "iso:country":"US",
    "sg:address":"296 Mile Ln",
    "sg:city":"Middletown",
    "sg:classifiers":[
        {
            "category":"Building & Trades",
            "subcategory":"Electrical",
            "type":"Services"
        }
    ],
    "sg:phone":"+1 860 632 1974",
    "sg:postcode":"06457",
    "sg:province":"CT",
    "sg:tags":[
        "general",
        "electrical",
        "contractor"
    ],
    "wof:name":"Eu Electric Unlimited Inc",
    "wof:placetype":"venue"
},
  "geometry": {"coordinates":[-72.679298,41.582885],"type":"Point"}
}