{
  "type": "Feature",
  "properties": {
    "addr:full":"25 Collins Rd Bristol CT 06010",
    "addr:housenumber":"25",
    "addr:postcode":"06010",
    "addr:street":"Collins Rd",
    "iso:country":"US",
    "sg:address":"25 Collins Rd",
    "sg:city":"Bristol",
    "sg:classifiers":[
        {
            "category":"Health Services",
            "subcategory":"Doctor",
            "type":"Services"
        }
    ],
    "sg:phone":"+1   ",
    "sg:postcode":"06010",
    "sg:province":"CT",
    "sg:tags":[
        "medical"
    ],
    "wof:name":"Bristol Radiology Center",
    "wof:placetype":"venue"
},
  "geometry": {"coordinates":[-72.91032300000001,41.69739],"type":"Point"}
}