{
  "type": "Feature",
  "properties": {
    "iso:country":"US",
    "sg:address":"22 S Whittlesey Ave",
    "sg:city":"Wallingford",
    "sg:classifiers":[
        {
            "category":"Insurance",
            "subcategory":"Hazard Insurance",
            "type":"Services"
        }
    ],
    "sg:phone":"+1 203 269 3313",
    "sg:postcode":"06492",
    "sg:province":"CT",
    "sg:tags":[
        "carrier"
    ],
    "wof:name":"Zurich Insurance",
    "wof:placetype":"venue"
},
  "geometry": {"coordinates":[-72.82058499999999,41.454085],"type":"Point"}
}