{
  "type": "Feature",
  "properties": {
    "addr:full":"462 Main St Middlefield CT 06455",
    "addr:housenumber":"462",
    "addr:postcode":"06455",
    "addr:street":"Main St",
    "iso:country":"US",
    "sg:address":"462 Main St",
    "sg:city":"Middlefield",
    "sg:classifiers":[
        {
            "category":"Personal",
            "subcategory":"Beauty Salon",
            "type":"Services"
        }
    ],
    "sg:phone":"+1   ",
    "sg:postcode":"06455",
    "sg:province":"CT",
    "sg:tags":[
        "shop"
    ],
    "wof:name":"Rochelle Carabetta Permanent",
    "wof:placetype":"venue"
},
  "geometry": {"coordinates":[-72.7122,41.513129],"type":"Point"}
}