{
  "type": "Feature",
  "properties": {
    "iso:country":"US",
    "sg:address":"97 Spencer Hill Rd",
    "sg:city":"Winsted",
    "sg:classifiers":[
        {
            "category":"Retail",
            "subcategory":"Repair Shop",
            "type":"Services"
        }
    ],
    "sg:phone":"+1   ",
    "sg:postcode":"06098",
    "sg:province":"CT",
    "sg:tags":[
        "engine"
    ],
    "wof:name":"Daves Engine Repair",
    "wof:placetype":"venue"
},
  "geometry": {"coordinates":[-73.07496399999999,41.932162],"type":"Point"}
}