{
  "type": "Feature",
  "properties": {
    "iso:country":"US",
    "sg:address":"67 Federal Rd",
    "sg:city":"Brookfield",
    "sg:classifiers":[
        {
            "category":"Home & Garden",
            "subcategory":"Furniture",
            "type":"Retail Goods"
        }
    ],
    "sg:phone":"+1 203 740 0014",
    "sg:postcode":"06804",
    "sg:province":"CT",
    "wof:name":"Recreation Showroom",
    "wof:placetype":"venue"
},
  "geometry": {"coordinates":[-73.41117300000001,41.433571],"type":"Point"}
}