{
  "type": "Feature",
  "properties": {
    "addr:full":"108 High Hill Rd Wallingford CT 06492",
    "addr:housenumber":"108",
    "addr:postcode":"06492",
    "addr:street":"High Hill Rd",
    "iso:country":"US",
    "sg:address":"108 High Hill Rd",
    "sg:city":"Wallingford",
    "sg:classifiers":[
        {
            "category":"Health Services",
            "subcategory":"Clinic",
            "type":"Services"
        }
    ],
    "sg:phone":"+1 203 679 0820",
    "sg:postcode":"06492",
    "sg:province":"CT",
    "sg:tags":[
        "home"
    ],
    "wof:name":"Home Helpers",
    "wof:placetype":"venue"
},
  "geometry": {"coordinates":[-72.754976,41.479999],"type":"Point"}
}