{
  "type": "Feature",
  "properties": {
    "addr:full":"24 West St Middlefield CT 06455",
    "addr:housenumber":"24",
    "addr:postcode":"06455",
    "addr:street":"West St Middlefield Ct",
    "iso:country":"US",
    "sg:address":"24 West St",
    "sg:city":"Middlefield",
    "sg:classifiers":[
        {
            "category":"Shopping",
            "subcategory":"Used Merchandise",
            "type":"Retail Goods"
        }
    ],
    "sg:phone":"+1 860 349 0165",
    "sg:postcode":"06455",
    "sg:province":"CT",
    "wof:name":"Country Depot Antiques",
    "wof:placetype":"venue"
},
  "geometry": {"coordinates":[-72.71968200000001,41.502616],"type":"Point"}
}