{
  "type": "Feature",
  "properties": {
    "iso:country":"US",
    "sg:address":"95 Dixwell Ave",
    "sg:city":"New Haven",
    "sg:classifiers":[
        {
            "category":"Retail",
            "subcategory":"Funeral Services",
            "type":"Services"
        }
    ],
    "sg:phone":"+1 203 786 4732",
    "sg:postcode":"06511",
    "sg:province":"CT",
    "sg:tags":[
        "plan"
    ],
    "wof:name":"Mc Clam Funeral Home",
    "wof:placetype":"venue"
},
  "geometry": {"coordinates":[-72.93284300000001,41.315398],"type":"Point"}
}