{
  "type": "Feature",
  "properties": {
    "addr:full":"62 Farmington Ave Farmington CT 06032",
    "addr:housenumber":"62",
    "addr:postcode":"06032",
    "addr:street":"Farmington Ave",
    "iso:country":"US",
    "sg:address":"62 Farmington Ave",
    "sg:city":"Farmington",
    "sg:classifiers":[
        {
            "category":"Retail",
            "subcategory":"Repair Shop",
            "type":"Services"
        }
    ],
    "sg:phone":"+1   ",
    "sg:postcode":"06032",
    "sg:province":"CT",
    "sg:tags":[
        "equipment",
        "bicycle",
        "power"
    ],
    "wof:name":"Central Wheel",
    "wof:placetype":"venue"
},
  "geometry": {"coordinates":[-72.781228,41.746086],"type":"Point"}
}