{
  "type": "Feature",
  "properties": {
    "iso:country":"US",
    "sg:address":"97 Broad St",
    "sg:city":"Plainville",
    "sg:classifiers":[
        {
            "category":"Organizations",
            "subcategory":"Religious Organization",
            "type":"Services"
        }
    ],
    "sg:phone":"+1   ",
    "sg:postcode":"06062",
    "sg:province":"CT",
    "wof:name":"7th Day Adventist Church",
    "wof:placetype":"venue"
},
  "geometry": {"coordinates":[-72.87107899999999,41.667462],"type":"Point"}
}