{
  "type": "Feature",
  "properties": {
    "iso:country":"US",
    "sg:address":"5 Rainbow Ct",
    "sg:city":"Hamden",
    "sg:classifiers":[
        {
            "category":"Insurance",
            "subcategory":"Insurance Agent",
            "type":"Services"
        }
    ],
    "sg:phone":"+1 203 287 1242",
    "sg:postcode":"06514",
    "sg:province":"CT",
    "wof:name":"Limousine Insurance Center LLC",
    "wof:placetype":"venue"
},
  "geometry": {"coordinates":[-72.917097,41.408117],"type":"Point"}
}