{
  "type": "Feature",
  "properties": {
    "iso:country":"US",
    "sg:address":"1362 New Haven Ave",
    "sg:city":"Milford",
    "sg:classifiers":[
        {
            "category":"Insurance",
            "subcategory":"Insurance Agent",
            "type":"Services"
        }
    ],
    "sg:phone":"+1 203 301 0409",
    "sg:postcode":"06460",
    "sg:province":"CT",
    "wof:name":"Burns Insurance Associates",
    "wof:placetype":"venue"
},
  "geometry": {"coordinates":[-72.99589899999999,41.228853],"type":"Point"}
}