{
  "type": "Feature",
  "properties": {
    "iso:country":"US",
    "sg:address":"581 Chase Ave",
    "sg:city":"Waterbury",
    "sg:classifiers":[
        {
            "category":"Deli",
            "type":"Food & Drink"
        },
        {
            "category":"Restaurant",
            "type":"Food & Drink"
        }
    ],
    "sg:phone":"+1 203 755 2624",
    "sg:postcode":"06704",
    "sg:province":"CT",
    "sg:tags":[
        "delicatessen",
        "pizza"
    ],
    "wof:name":"Amalfi Pizza & Deli",
    "wof:placetype":"venue"
},
  "geometry": {"coordinates":[-73.040553,41.584556],"type":"Point"}
}