{
  "type": "Feature",
  "properties": {
    "addr:full":"246 Old Post Rd Fairfield CT 06413",
    "addr:housenumber":"246",
    "addr:postcode":"06413",
    "addr:street":"Old Post Rd",
    "iso:country":"US",
    "sg:address":"246 Old Post Rd",
    "sg:city":"Fairfield",
    "sg:classifiers":[
        {
            "category":"Professional",
            "subcategory":"Management & Consulting",
            "type":"Services"
        }
    ],
    "sg:phone":"+1   ",
    "sg:postcode":"06413",
    "sg:province":"CT",
    "wof:name":"Southport Remediation LLC",
    "wof:placetype":"venue"
},
  "geometry": {"coordinates":[-72.49263500000001,41.286756],"type":"Point"}
}