{
  "type": "Feature",
  "properties": {
    "addr:full":"31 Putnam Ave Port Chester CT 10573",
    "addr:housenumber":"31",
    "addr:postcode":"10573",
    "addr:street":"Putnam Ave;Chester",
    "iso:country":"US",
    "sg:address":"31 Putnam Ave",
    "sg:city":"Port Chester",
    "sg:classifiers":[
        {
            "category":"Shopping",
            "subcategory":"Stationery & Office Supplies",
            "type":"Retail Goods"
        }
    ],
    "sg:phone":"+1 914 937 4630",
    "sg:postcode":"10573",
    "sg:province":"CT",
    "sg:tags":[
        "stationer"
    ],
    "wof:name":"B J Cards & Gifts",
    "wof:placetype":"venue"
},
  "geometry": {"coordinates":[-73.659263,41.013017],"type":"Point"}
}