{
  "type": "Feature",
  "properties": {
    "iso:country":"US",
    "sg:address":"75 Old Turnpike Rd",
    "sg:city":"Beacon Falls",
    "sg:classifiers":[
        {
            "category":"Autos & Motor Vehicles",
            "subcategory":"Motorcycle Sales",
            "type":"Retail Goods"
        }
    ],
    "sg:phone":"+1 203 888 3517",
    "sg:postcode":"06403",
    "sg:province":"CT",
    "sg:tags":[
        "automotive",
        "repair"
    ],
    "wof:name":"L&L Auto Service",
    "wof:placetype":"venue"
},
  "geometry": {"coordinates":[-73.06975,41.420411],"type":"Point"}
}