{
  "type": "Feature",
  "properties": {
    "iso:country":"US",
    "sg:address":"1188 New Litchfield St",
    "sg:city":"Torrington",
    "sg:classifiers":[
        {
            "category":"Real Estate",
            "subcategory":"Real Estate Agent",
            "type":"Services"
        }
    ],
    "sg:phone":"+1 860 482 1961",
    "sg:postcode":"06790",
    "sg:province":"CT",
    "wof:name":"J-D Realty of Torrington",
    "wof:placetype":"venue"
},
  "geometry": {"coordinates":[-73.146664,41.786229],"type":"Point"}
}