{
  "type": "Feature",
  "properties": {
    "addr:full":"309 Saint Ronan St New Haven CT 06511",
    "addr:housenumber":"309",
    "addr:postcode":"06511",
    "addr:street":"Saint Ronan St",
    "iso:country":"US",
    "sg:address":"309 Saint Ronan St",
    "sg:city":"New Haven",
    "sg:classifiers":[
        {
            "category":"Professional",
            "subcategory":"Lawyer & Legal Services",
            "type":"Services"
        }
    ],
    "sg:phone":"+1   ",
    "sg:postcode":"06511",
    "sg:province":"CT",
    "wof:name":"Melinda A Agsten Atty",
    "wof:placetype":"venue"
},
  "geometry": {"coordinates":[-72.91916500000001,41.322955],"type":"Point"}
}