{
  "type": "Feature",
  "properties": {
    "iso:country":"US",
    "sg:address":"15 Roberts St",
    "sg:city":"Newington",
    "sg:classifiers":[
        {
            "category":"Building & Trades",
            "subcategory":"Construction",
            "type":"Services"
        }
    ],
    "sg:phone":"+1 860 666 0178",
    "sg:postcode":"06111",
    "sg:province":"CT",
    "sg:tags":[
        "general",
        "contractor"
    ],
    "wof:name":"Consoldted Cnstr Cnneticut Inc",
    "wof:placetype":"venue"
},
  "geometry": {"coordinates":[-72.747958,41.674421],"type":"Point"}
}