{
  "type": "Feature",
  "properties": {
    "addr:full":"173 Montowese St Branford CT 06405",
    "addr:housenumber":"173",
    "addr:postcode":"06405",
    "addr:street":"Montowese St",
    "iso:country":"US",
    "sg:address":"173 Montowese St",
    "sg:city":"Branford",
    "sg:classifiers":[
        {
            "category":"Personal",
            "subcategory":"Beauty Salon",
            "type":"Services"
        }
    ],
    "sg:phone":"+1   ",
    "sg:postcode":"06405",
    "sg:province":"CT",
    "sg:tags":[
        "shop"
    ],
    "wof:name":"Branford Nail Care",
    "wof:placetype":"venue"
},
  "geometry": {"coordinates":[-72.809122,41.281518],"type":"Point"}
}