{
  "type": "Feature",
  "properties": {
    "addr:full":"206 Mather St Hartford CT 06112",
    "addr:housenumber":"206",
    "addr:postcode":"06112",
    "addr:street":"Mather St",
    "iso:country":"US",
    "sg:address":"206 Mather St",
    "sg:city":"Hartford",
    "sg:classifiers":[
        {
            "category":"Food & Beverages",
            "subcategory":"Groceries & Convenience Stores",
            "type":"Retail Goods"
        }
    ],
    "sg:phone":"+1 860 560 3043",
    "sg:postcode":"06112",
    "sg:province":"CT",
    "wof:name":"Mathers Deli",
    "wof:placetype":"venue"
},
  "geometry": {"coordinates":[-72.684877,41.780419],"type":"Point"}
}