{
  "type": "Feature",
  "properties": {
    "addr:full":"39 Adam Dr Torrington CT 06790",
    "addr:housenumber":"39",
    "addr:postcode":"06790",
    "addr:street":"Adam Dr",
    "iso:country":"US",
    "sg:address":"39 Adam Dr",
    "sg:city":"Torrington",
    "sg:classifiers":[
        {
            "category":"Building & Trades",
            "subcategory":"Construction",
            "type":"Services"
        }
    ],
    "sg:phone":"+1 860 379 3028",
    "sg:postcode":"06790",
    "sg:province":"CT",
    "sg:tags":[
        "house"
    ],
    "wof:name":"A & S Construction Svcs LLC",
    "wof:placetype":"venue"
},
  "geometry": {"coordinates":[-73.14924000000001,41.805425],"type":"Point"}
}