{
  "type": "Feature",
  "properties": {
    "addr:full":"8 Carothers Ln Norwalk CT 06851",
    "addr:housenumber":"8",
    "addr:postcode":"06851",
    "addr:street":"Carothers Ln",
    "iso:country":"US",
    "sg:address":"8 Carothers Ln",
    "sg:city":"Norwalk",
    "sg:classifiers":[
        {
            "category":"Building & Trades",
            "subcategory":"Equipment Rental",
            "type":"Services"
        }
    ],
    "sg:phone":"+1   ",
    "sg:postcode":"06851",
    "sg:province":"CT",
    "wof:name":"Norwalk Tent Co",
    "wof:placetype":"venue"
},
  "geometry": {"coordinates":[-73.385429,41.124717],"type":"Point"}
}