{
  "type": "Feature",
  "properties": {
    "addr:full":"1 Alpine Rd Greenwich CT 06830",
    "addr:housenumber":"1",
    "addr:postcode":"06830",
    "addr:street":"Alpine Rd",
    "iso:country":"US",
    "sg:address":"1 Alpine Rd",
    "sg:city":"Greenwich",
    "sg:classifiers":[
        {
            "category":"Professional",
            "type":"Services"
        }
    ],
    "sg:phone":"+1 203 625 0711",
    "sg:postcode":"06830",
    "sg:province":"CT",
    "sg:tags":[
        "establishment"
    ],
    "wof:name":"Clifton Group Inc",
    "wof:placetype":"venue"
},
  "geometry": {"coordinates":[-73.63081099999999,41.086928],"type":"Point"}
}