{
  "type": "Feature",
  "properties": {
    "iso:country":"US",
    "sg:address":"40 Sullivan Rd",
    "sg:city":"New Milford",
    "sg:classifiers":[
        {
            "category":"Retail",
            "subcategory":"Auto Rental",
            "type":"Services"
        }
    ],
    "sg:phone":"+1   ",
    "sg:postcode":"06776",
    "sg:province":"CT",
    "sg:tags":[
        "equipment",
        "leasing"
    ],
    "wof:name":"Equip Corporation",
    "wof:placetype":"venue"
},
  "geometry": {"coordinates":[-73.42855,41.530292],"type":"Point"}
}