{
  "type": "Feature",
  "properties": {
    "addr:full":"40 NE Industrial Dr Branford CT 06405",
    "addr:housenumber":"40",
    "addr:postcode":"06405",
    "addr:street":"Ne Industrial Dr",
    "iso:country":"US",
    "sg:address":"40 NE Industrial Dr",
    "sg:city":"Branford",
    "sg:classifiers":[
        {
            "category":"Home & Garden",
            "subcategory":"Building Materials",
            "type":"Retail Goods"
        }
    ],
    "sg:phone":"+1 203 481 4505",
    "sg:postcode":"06405",
    "sg:province":"CT",
    "sg:tags":[
        "lumber"
    ],
    "wof:name":"Wood Rack",
    "wof:placetype":"venue"
},
  "geometry": {"coordinates":[-72.770055,41.300014],"type":"Point"}
}