{
  "type": "Feature",
  "properties": {
    "addr:full":"192 W Main St Avon CT 06001",
    "addr:housenumber":"192",
    "addr:postcode":"06001",
    "addr:street":"W Main St",
    "iso:country":"US",
    "sg:address":"192 W Main St",
    "sg:city":"Avon",
    "sg:classifiers":[
        {
            "category":"Arena",
            "subcategory":"Sports Club",
            "type":"Entertainment"
        }
    ],
    "sg:phone":"+1 860 677 5425",
    "sg:postcode":"06001",
    "sg:province":"CT",
    "sg:tags":[
        "martial art"
    ],
    "wof:name":"Goms Taekwondo Center",
    "wof:placetype":"venue"
},
  "geometry": {"coordinates":[-72.847542,41.811884],"type":"Point"}
}