{
  "type": "Feature",
  "properties": {
    "iso:country":"US",
    "sg:address":"26 Imperial Ave",
    "sg:city":"Westport",
    "sg:classifiers":[
        {
            "category":"Health Services",
            "subcategory":"Health Practitioner",
            "type":"Services"
        }
    ],
    "sg:phone":"+1 203 952 5202",
    "sg:postcode":"06880",
    "sg:province":"CT",
    "sg:tags":[
        "psychotherapist"
    ],
    "wof:name":"Belkis B Bottfeld",
    "wof:placetype":"venue"
},
  "geometry": {"coordinates":[-73.35809399999999,41.141466],"type":"Point"}
}