{
  "type": "Feature",
  "properties": {
    "iso:country":"US",
    "sg:address":"27 Bedford St",
    "sg:city":"Stamford",
    "sg:classifiers":[
        {
            "category":"Shopping",
            "type":"Retail Goods"
        }
    ],
    "sg:phone":"+1 203 353 3357",
    "sg:postcode":"06901",
    "sg:province":"CT",
    "sg:tags":[
        "repair",
        "merchandise"
    ],
    "wof:name":"Wireless & Internet Solutions",
    "wof:placetype":"venue"
},
  "geometry": {"coordinates":[-73.53764099999999,41.055817],"type":"Point"}
}