{
  "type": "Feature",
  "properties": {
    "iso:country":"US",
    "sg:address":"161 Clay Hill Rd",
    "sg:city":"Stamford",
    "sg:classifiers":[
        {
            "category":"Building & Trades",
            "subcategory":"Construction",
            "type":"Services"
        }
    ],
    "sg:phone":"+1 203 322 0354",
    "sg:postcode":"06905",
    "sg:province":"CT",
    "sg:tags":[
        "contractor"
    ],
    "wof:name":"Thaler Construction LLC",
    "wof:placetype":"venue"
},
  "geometry": {"coordinates":[-73.55849000000001,41.09914],"type":"Point"}
}