{
  "type": "Feature",
  "properties": {
    "addr:full":"360 Boston Post Rd Old Saybrook CT 06475",
    "addr:housenumber":"360",
    "addr:postcode":"06475",
    "addr:street":"Boston Post Rd Old Saybrook Ct",
    "iso:country":"US",
    "sg:address":"360 Boston Post Rd",
    "sg:city":"Old Saybrook",
    "sg:classifiers":[
        {
            "category":"Autos & Motor Vehicles",
            "subcategory":"Automobile Sales",
            "type":"Retail Goods"
        },
        {
            "category":"Retail",
            "subcategory":"Auto Repair",
            "type":"Services"
        }
    ],
    "sg:phone":"+1 860 388 4445",
    "sg:postcode":"06475",
    "sg:province":"CT",
    "sg:tags":[
        "car"
    ],
    "wof:name":"Chrysler-Plymouth Agency",
    "wof:placetype":"venue"
},
  "geometry": {"coordinates":[-72.370499,41.3064],"type":"Point"}
}