{
  "type": "Feature",
  "properties": {
    "addr:full":"57 Revonah Ave Stamford CT 06905",
    "addr:housenumber":"57",
    "addr:postcode":"06905",
    "addr:street":"Revonah Ave",
    "iso:country":"US",
    "sg:address":"57 Revonah Ave",
    "sg:city":"Stamford",
    "sg:classifiers":[
        {
            "category":"Organizations",
            "subcategory":"Religious Organization",
            "type":"Services"
        }
    ],
    "sg:phone":"+1   ",
    "sg:postcode":"06905",
    "sg:province":"CT",
    "wof:name":"Chabad",
    "wof:placetype":"venue"
},
  "geometry": {"coordinates":[-73.53924499999999,41.06784],"type":"Point"}
}