{
  "type": "Feature",
  "properties": {
    "iso:country":"US",
    "sg:address":"93 Park Ave",
    "sg:city":"Danbury",
    "sg:classifiers":[
        {
            "category":"Professional",
            "subcategory":"Computer Services",
            "type":"Services"
        }
    ],
    "sg:phone":"+1   ",
    "sg:postcode":"06810",
    "sg:province":"CT",
    "sg:tags":[
        "agency",
        "employment",
        "related",
        "secretarial"
    ],
    "wof:name":"Executive Profiles",
    "wof:placetype":"venue"
},
  "geometry": {"coordinates":[-73.46305700000001,41.386474],"type":"Point"}
}