{
  "type": "Feature",
  "properties": {
    "iso:country":"US",
    "sg:address":"282 Joshuatown Rd",
    "sg:city":"Old Lyme",
    "sg:classifiers":[
        {
            "category":"Real Estate",
            "subcategory":"Architect",
            "type":"Services"
        }
    ],
    "sg:phone":"+1 860 526 1004",
    "sg:postcode":"06371",
    "sg:province":"CT",
    "wof:name":"Hoyt Charles Architect",
    "wof:placetype":"venue"
},
  "geometry": {"coordinates":[-72.38291599999999,41.394976],"type":"Point"}
}