{
  "type": "Feature",
  "properties": {
    "addr:full":"323 Main St West Haven CT 06516",
    "addr:housenumber":"323",
    "addr:postcode":"06516",
    "addr:street":"Main St",
    "iso:country":"US",
    "sg:address":"323 Main St",
    "sg:city":"West Haven",
    "sg:classifiers":[
        {
            "category":"Health Services",
            "subcategory":"Doctor",
            "type":"Services"
        }
    ],
    "sg:phone":"+1 203 937 7181",
    "sg:postcode":"06516",
    "sg:province":"CT",
    "sg:tags":[
        "dentist"
    ],
    "wof:name":"Ctoms",
    "wof:placetype":"venue"
},
  "geometry": {"coordinates":[-72.94927300000001,41.272705],"type":"Point"}
}