{
  "type": "Feature",
  "properties": {
    "iso:country":"US",
    "sg:address":"216 Field Rd",
    "sg:city":"Somers",
    "sg:classifiers":[
        {
            "category":"Building & Trades",
            "subcategory":"Landscaping Services",
            "type":"Services"
        }
    ],
    "sg:phone":"+1 860 741 6600",
    "sg:postcode":"06071",
    "sg:province":"CT",
    "sg:tags":[
        "lawn",
        "fertilizing"
    ],
    "wof:name":"Green Carpet Lawn Care LLC",
    "wof:placetype":"venue"
},
  "geometry": {"coordinates":[-72.45595,41.967674],"type":"Point"}
}