{
  "type": "Feature",
  "properties": {
    "addr:full":"415 Main St Monroe CT 06468",
    "addr:housenumber":"415",
    "addr:postcode":"06468",
    "addr:street":"Main St",
    "iso:country":"US",
    "sg:address":"415 Main St",
    "sg:city":"Monroe",
    "sg:classifiers":[
        {
            "category":"Professional",
            "type":"Services"
        }
    ],
    "sg:phone":"+1 203 459 9800",
    "sg:postcode":"06468",
    "sg:province":"CT",
    "sg:tags":[
        "establishment"
    ],
    "wof:name":"Vazzy's Osteria",
    "wof:placetype":"venue"
},
  "geometry": {"coordinates":[-73.262519,41.31936],"type":"Point"}
}