{
  "type": "Feature",
  "properties": {
    "iso:country":"US",
    "sg:address":"1535 Albany Ave",
    "sg:city":"Hartford",
    "sg:classifiers":[
        {
            "category":"Retail",
            "subcategory":"Car Wash",
            "type":"Services"
        }
    ],
    "sg:phone":"+1   ",
    "sg:postcode":"06112",
    "sg:province":"CT",
    "sg:tags":[
        "carwash"
    ],
    "wof:name":"Jiffy Car Wash",
    "wof:placetype":"venue"
},
  "geometry": {"coordinates":[-72.70358899999999,41.784343],"type":"Point"}
}