{
  "type": "Feature",
  "properties": {
    "addr:full":"277 White St Danbury CT 06810",
    "addr:housenumber":"277",
    "addr:postcode":"06810",
    "addr:street":"White St",
    "iso:country":"US",
    "sg:address":"277 White St",
    "sg:city":"Danbury",
    "sg:classifiers":[
        {
            "category":"Health Services",
            "subcategory":"Optometrist",
            "type":"Services"
        }
    ],
    "sg:phone":"+1   ",
    "sg:postcode":"06810",
    "sg:province":"CT",
    "wof:name":"Woronick Michael",
    "wof:placetype":"venue"
},
  "geometry": {"coordinates":[-73.433452,41.399438],"type":"Point"}
}