{
  "type": "Feature",
  "properties": {
    "iso:country":"US",
    "sg:address":"4 Post Office Sq",
    "sg:city":"Clinton",
    "sg:classifiers":[
        {
            "category":"Arena",
            "subcategory":"Sports Club",
            "type":"Entertainment"
        }
    ],
    "sg:phone":"+1   ",
    "sg:postcode":"06413",
    "sg:province":"CT",
    "sg:tags":[
        "marketing",
        "promotion",
        "financing"
    ],
    "wof:name":"Atherton Communications LP",
    "wof:placetype":"venue"
},
  "geometry": {"coordinates":[-72.527008,41.279124],"type":"Point"}
}