{
  "type": "Feature",
  "properties": {
    "iso:country":"US",
    "sg:address":"275 Jarvis St",
    "sg:city":"Cheshire",
    "sg:classifiers":[
        {
            "category":"Government",
            "subcategory":"Jail",
            "type":"Public Place"
        }
    ],
    "sg:phone":"+1 203 271 5100",
    "sg:postcode":"06410",
    "sg:province":"CT",
    "sg:tags":[
        "training",
        "correctional",
        "guard",
        "for"
    ],
    "wof:name":"Maloney Center For Training",
    "wof:placetype":"venue"
},
  "geometry": {"coordinates":[-72.90342699999999,41.526359],"type":"Point"}
}