{
  "type": "Feature",
  "properties": {
    "iso:country":"US",
    "sg:address":"496 E Main St",
    "sg:city":"Bridgeport",
    "sg:classifiers":[
        {
            "category":"Restaurant",
            "type":"Food & Drink"
        }
    ],
    "sg:phone":"+1 203 366 0171",
    "sg:postcode":"06608",
    "sg:province":"CT",
    "sg:tags":[
        "parlor",
        "ice",
        "cream"
    ],
    "wof:name":"El Coquito",
    "wof:placetype":"venue"
},
  "geometry": {"coordinates":[-73.181,41.181122],"type":"Point"}
}