{
  "type": "Feature",
  "properties": {
    "addr:full":"185 W Newberry Rd Bloomfield CT 06002",
    "addr:housenumber":"185",
    "addr:postcode":"06002",
    "addr:street":"W Newberry Rd Bloomfield Ct",
    "iso:country":"US",
    "sg:address":"185 W Newberry Rd",
    "sg:city":"Bloomfield",
    "sg:classifiers":[
        {
            "category":"Building & Trades",
            "subcategory":"Plumbing",
            "type":"Services"
        }
    ],
    "sg:phone":"+1 860 286 8338",
    "sg:postcode":"06002",
    "sg:province":"CT",
    "sg:tags":[
        "tank",
        "septic"
    ],
    "wof:name":"Advance Septic Tank Service",
    "wof:placetype":"venue"
},
  "geometry": {"coordinates":[-72.73275099999999,41.869645],"type":"Point"}
}