{
  "type": "Feature",
  "properties": {
    "addr:full":"8 Gaffney Rd New Milford CT 06776",
    "addr:housenumber":"8",
    "addr:postcode":"06776",
    "addr:street":"Gaffney Rd",
    "iso:country":"US",
    "sg:address":"8 Gaffney Rd",
    "sg:city":"New Milford",
    "sg:classifiers":[
        {
            "category":"Building & Trades",
            "subcategory":"Landscaping Services",
            "type":"Services"
        }
    ],
    "sg:phone":"+1 860 355 5465",
    "sg:postcode":"06776",
    "sg:province":"CT",
    "wof:name":"Sunset Lawn Care",
    "wof:placetype":"venue"
},
  "geometry": {"coordinates":[-73.461434,41.658455],"type":"Point"}
}