{
  "type": "Feature",
  "properties": {
    "addr:full":"245 Lawrence St New Haven CT 06511",
    "addr:housenumber":"245",
    "addr:postcode":"06511",
    "addr:street":"Lawrence St",
    "iso:country":"US",
    "sg:address":"245 Lawrence St",
    "sg:city":"New Haven",
    "sg:classifiers":[
        {
            "category":"Professional",
            "subcategory":"Management & Consulting",
            "type":"Services"
        }
    ],
    "sg:phone":"+1   ",
    "sg:postcode":"06511",
    "sg:province":"CT",
    "sg:tags":[
        "business"
    ],
    "wof:name":"P G I C",
    "wof:placetype":"venue"
},
  "geometry": {"coordinates":[-72.91727299999999,41.320186],"type":"Point"}
}