{
  "type": "Feature",
  "properties": {
    "addr:full":"117 Catherine St Middletown CT 06457",
    "addr:housenumber":"117",
    "addr:postcode":"06457",
    "addr:street":"Catherine St",
    "iso:country":"US",
    "sg:address":"117 Catherine St",
    "sg:city":"Middletown",
    "sg:classifiers":[
        {
            "category":"Professional",
            "subcategory":"Business Services",
            "type":"Services"
        }
    ],
    "sg:phone":"+1   ",
    "sg:postcode":"06457",
    "sg:province":"CT",
    "wof:name":"Donic Sales Inc",
    "wof:placetype":"venue"
},
  "geometry": {"coordinates":[-72.66368799999999,41.569491],"type":"Point"}
}