{
  "type": "Feature",
  "properties": {
    "addr:full":"6 Reynolds St Norwalk CT 06855",
    "addr:housenumber":"6",
    "addr:postcode":"06855",
    "addr:street":"Reynolds St",
    "iso:country":"US",
    "sg:address":"6 Reynolds St",
    "sg:city":"Norwalk",
    "sg:classifiers":[
        {
            "category":"Retail",
            "subcategory":"Auto Repair",
            "type":"Services"
        }
    ],
    "sg:phone":"+1 203 857 0313",
    "sg:postcode":"06855",
    "sg:province":"CT",
    "wof:name":"SBC Restoration",
    "wof:placetype":"venue"
},
  "geometry": {"coordinates":[-73.40951800000001,41.102829],"type":"Point"}
}