{
  "type": "Feature",
  "properties": {
    "iso:country":"US",
    "sg:address":"1163 Boston Post Rd",
    "sg:city":"Madison",
    "sg:classifiers":[
        {
            "category":"Organizations",
            "subcategory":"Community Association",
            "type":"Services"
        }
    ],
    "sg:phone":"+1 203 245 3146",
    "sg:postcode":"06443",
    "sg:province":"CT",
    "sg:tags":[
        "fraternal"
    ],
    "wof:name":"Madison Lodge",
    "wof:placetype":"venue"
},
  "geometry": {"coordinates":[-72.57221699999999,41.274162],"type":"Point"}
}