{
  "type": "Feature",
  "properties": {
    "iso:country":"US",
    "sg:address":"348 Boston Post Rd",
    "sg:city":"Orange",
    "sg:classifiers":[
        {
            "category":"Restaurant",
            "type":"Food & Drink"
        }
    ],
    "sg:menulink":"http://www.allmenus.com/ct/orange/75341-tgi-fridays/menu/",
    "sg:phone":"+1 203 799 0800",
    "sg:postcode":"06477",
    "sg:province":"CT",
    "sg:tags":[
        "american"
    ],
    "wof:name":"T.G.I. Friday's",
    "wof:placetype":"venue"
},
  "geometry": {"coordinates":[-73.006502,41.262597],"type":"Point"}
}