{
  "type": "Feature",
  "properties": {
    "addr:full":"433 Main St Ridgefield CT 06877",
    "addr:housenumber":"433",
    "addr:postcode":"06877",
    "addr:street":"Main St",
    "iso:country":"US",
    "sg:address":"433 Main St",
    "sg:city":"Ridgefield",
    "sg:classifiers":[
        {
            "category":"Personal",
            "subcategory":"Barber",
            "type":"Services"
        }
    ],
    "sg:phone":"+1   ",
    "sg:postcode":"06877",
    "sg:province":"CT",
    "sg:tags":[
        "shop",
        "beauty"
    ],
    "wof:name":"Bills Haircutters",
    "wof:placetype":"venue"
},
  "geometry": {"coordinates":[-73.498525,41.282355],"type":"Point"}
}