{
  "type": "Feature",
  "properties": {
    "addr:full":"480 Hayden Station Rd Windsor CT 06095",
    "addr:housenumber":"480",
    "addr:postcode":"06095",
    "addr:street":"Hayden Station Rd",
    "iso:country":"US",
    "sg:address":"480 Hayden Station Rd",
    "sg:city":"Windsor",
    "sg:classifiers":[
        {
            "category":"Wholesale",
            "subcategory":"Durable Goods & Equipment",
            "type":"Manufacturing & Wholesale Goods"
        }
    ],
    "sg:phone":"+1 860 683 2199",
    "sg:postcode":"06095",
    "sg:province":"CT",
    "sg:tags":[
        "professional"
    ],
    "wof:name":"Crown Optical Co Inc",
    "wof:placetype":"venue"
},
  "geometry": {"coordinates":[-72.650987,41.900973],"type":"Point"}
}