{
  "type": "Feature",
  "properties": {
    "addr:full":"10 Wicks End Ln Wilton CT 06897",
    "addr:housenumber":"10",
    "addr:postcode":"06897",
    "addr:street":"Wicks End Ln",
    "iso:country":"US",
    "sg:address":"10 Wicks End Ln",
    "sg:city":"Wilton",
    "sg:classifiers":[
        {
            "category":"Professional",
            "subcategory":"Art Services",
            "type":"Services"
        }
    ],
    "sg:phone":"+1   ",
    "sg:postcode":"06897",
    "sg:province":"CT",
    "sg:tags":[
        "commercial",
        "design"
    ],
    "wof:name":"Design Services",
    "wof:placetype":"venue"
},
  "geometry": {"coordinates":[-73.411332,41.215397],"type":"Point"}
}