{
  "type": "Feature",
  "properties": {
    "addr:full":"16 Southwind Dr Norwalk CT 06854",
    "addr:housenumber":"16",
    "addr:postcode":"06854",
    "addr:street":"Southwind Dr",
    "iso:country":"US",
    "sg:address":"16 Southwind Dr",
    "sg:city":"Norwalk",
    "sg:classifiers":[
        {
            "category":"Real Estate",
            "subcategory":"Real Estate Agent",
            "type":"Services"
        }
    ],
    "sg:phone":"+1 203 866 1014",
    "sg:postcode":"06854",
    "sg:province":"CT",
    "sg:tags":[
        "appraiser"
    ],
    "wof:name":"Morales Real Estate Assoc LLC",
    "wof:placetype":"venue"
},
  "geometry": {"coordinates":[-73.436385,41.112683],"type":"Point"}
}