{
  "type": "Feature",
  "properties": {
    "iso:country":"US",
    "sg:address":"100 Newberry Rd",
    "sg:city":"East Windsor",
    "sg:classifiers":[
        {
            "category":"Retail",
            "subcategory":"Auto Repair",
            "type":"Services"
        }
    ],
    "sg:phone":"+1   ",
    "sg:postcode":"06088",
    "sg:province":"CT",
    "sg:tags":[
        "body"
    ],
    "wof:name":"Bettern Most LLC",
    "wof:placetype":"venue"
},
  "geometry": {"coordinates":[-72.592536,41.921383],"type":"Point"}
}