{
  "type": "Feature",
  "properties": {
    "iso:country":"US",
    "sg:address":"558 Connecticut Ave",
    "sg:city":"Norwalk",
    "sg:classifiers":[
        {
            "category":"Retail",
            "subcategory":"Laundry & Dry Cleaning",
            "type":"Services"
        }
    ],
    "sg:phone":"+1 203 853 2888",
    "sg:postcode":"06854",
    "sg:province":"CT",
    "sg:tags":[
        "cleaners",
        "plant",
        "power",
        "drycleaning"
    ],
    "wof:name":"Michael's Cleaners",
    "wof:placetype":"venue"
},
  "geometry": {"coordinates":[-73.44609199999999,41.096963],"type":"Point"}
}