{
  "type": "Feature",
  "properties": {
    "iso:country":"US",
    "sg:address":"14 Frontage Rd",
    "sg:city":"East Haven",
    "sg:classifiers":[
        {
            "category":"Autos & Motor Vehicles",
            "subcategory":"Recreational Vehicle Sales",
            "type":"Retail Goods"
        }
    ],
    "sg:phone":"+1 203 469 7723",
    "sg:postcode":"06512",
    "sg:province":"CT",
    "wof:name":"TPM Assoc Inc",
    "wof:placetype":"venue"
},
  "geometry": {"coordinates":[-72.874775,41.284442],"type":"Point"}
}