{
  "type": "Feature",
  "properties": {
    "iso:country":"US",
    "sg:address":"38 Tunxis Ave",
    "sg:city":"Bloomfield",
    "sg:classifiers":[
        {
            "category":"Retail",
            "subcategory":"Laundry & Dry Cleaning",
            "type":"Services"
        }
    ],
    "sg:phone":"+1   ",
    "sg:postcode":"06002",
    "sg:province":"CT",
    "sg:tags":[
        "garment",
        "plant",
        "agent",
        "drycleaning"
    ],
    "wof:name":"Tunxis Cleaners",
    "wof:placetype":"venue"
},
  "geometry": {"coordinates":[-72.737216,41.834284],"type":"Point"}
}