{
  "type": "Feature",
  "properties": {
    "iso:country":"US",
    "sg:address":"103 South Ave",
    "sg:city":"New Canaan",
    "sg:classifiers":[
        {
            "category":"Real Estate",
            "subcategory":"Real Estate Agent",
            "type":"Services"
        }
    ],
    "sg:phone":"+1 203 972 8567",
    "sg:postcode":"06840",
    "sg:province":"NY",
    "sg:tags":[
        "relocation"
    ],
    "wof:name":"Exclusive Relocation",
    "wof:placetype":"venue"
},
  "geometry": {"coordinates":[-73.492516,41.143886],"type":"Point"}
}