{
  "type": "Feature",
  "properties": {
    "addr:full":"9 Eastview Dr Farmington CT 06032",
    "addr:housenumber":"9",
    "addr:postcode":"06032",
    "addr:street":"Eastview Dr",
    "iso:country":"US",
    "sg:address":"9 Eastview Dr",
    "sg:city":"Farmington",
    "sg:classifiers":[
        {
            "category":"Manufacturing",
            "subcategory":"Aerospace",
            "type":"Manufacturing & Wholesale Goods"
        }
    ],
    "sg:phone":"+1 860 409 7880",
    "sg:postcode":"06032",
    "sg:province":"CT",
    "sg:tags":[
        "aircraft",
        "mfg"
    ],
    "wof:name":"Teledyne",
    "wof:placetype":"venue"
},
  "geometry": {"coordinates":[-72.85742500000001,41.749631],"type":"Point"}
}