{
  "type": "Feature",
  "properties": {
    "addr:full":"25 Bidwell St East Hartford CT 06108",
    "addr:housenumber":"25",
    "addr:postcode":"06108",
    "addr:street":"Bidwell St East;Ct",
    "iso:country":"US",
    "sg:address":"25 Bidwell St",
    "sg:city":"East Hartford",
    "sg:classifiers":[
        {
            "category":"Retail",
            "subcategory":"Animal Services",
            "type":"Services"
        }
    ],
    "sg:phone":"+1 860 528 2336",
    "sg:postcode":"06108",
    "sg:province":"CT",
    "wof:name":"Classy Clipper",
    "wof:placetype":"venue"
},
  "geometry": {"coordinates":[-72.62451,41.777878],"type":"Point"}
}