{
  "type": "Feature",
  "properties": {
    "iso:country":"US",
    "sg:address":"46 Library St",
    "sg:city":"Salisbury",
    "sg:classifiers":[
        {
            "category":"Personal",
            "subcategory":"Beauty Salon",
            "type":"Services"
        }
    ],
    "sg:phone":"+1   ",
    "sg:postcode":"06068",
    "sg:province":"CT",
    "sg:tags":[
        "shop"
    ],
    "wof:name":"Daryl Avery Salon",
    "wof:placetype":"venue"
},
  "geometry": {"coordinates":[-73.42011599999999,41.980286],"type":"Point"}
}