{
  "type": "Feature",
  "properties": {
    "addr:full":"67 Hemmelskamp Rd Wilton CT 06897",
    "addr:housenumber":"67",
    "addr:postcode":"06897",
    "addr:street":"Hemmelskamp Rd Wilton Ct",
    "iso:country":"US",
    "sg:address":"67 Hemmelskamp Rd",
    "sg:city":"Wilton",
    "sg:classifiers":[
        {
            "category":"Professional",
            "subcategory":"Management & Consulting",
            "type":"Services"
        }
    ],
    "sg:phone":"+1   ",
    "sg:postcode":"06897",
    "sg:province":"CT",
    "sg:tags":[
        "business"
    ],
    "wof:name":"Richard J Dubow Consulting Svc",
    "wof:placetype":"venue"
},
  "geometry": {"coordinates":[-73.44551199999999,41.218237],"type":"Point"}
}