{
  "type": "Feature",
  "properties": {
    "addr:full":"3 Lathrop Ln Norwich CT 06360",
    "addr:housenumber":"3",
    "addr:postcode":"06360",
    "addr:street":"Lathrop Ln",
    "iso:country":"US",
    "sg:address":"3 Lathrop Ln",
    "sg:city":"Norwich",
    "sg:classifiers":[
        {
            "category":"Farming",
            "subcategory":"Farm",
            "type":"Manufacturing & Wholesale Goods"
        }
    ],
    "sg:phone":"+1 860 889 9899",
    "sg:postcode":"06360",
    "sg:province":"CT",
    "sg:tags":[
        "crop",
        "general"
    ],
    "wof:name":"Old Holbrook Farm LLC",
    "wof:placetype":"venue"
},
  "geometry": {"coordinates":[-72.08661499999999,41.547539],"type":"Point"}
}