{
  "type": "Feature",
  "properties": {
    "iso:country":"US",
    "sg:address":"308 Hazard Ave",
    "sg:city":"Enfield",
    "sg:classifiers":[
        {
            "category":"Wholesale",
            "subcategory":"Construction Materials",
            "type":"Manufacturing & Wholesale Goods"
        }
    ],
    "sg:phone":"+1 860 763 4890",
    "sg:postcode":"06082",
    "sg:province":"CT",
    "sg:tags":[
        "design",
        "kitchen"
    ],
    "wof:name":"Tangernes Cstm Dsgned Kitchens",
    "wof:placetype":"venue"
},
  "geometry": {"coordinates":[-72.54086700000001,41.986498],"type":"Point"}
}