{
  "type": "Feature",
  "properties": {
    "addr:full":"184 Red Oak Hill Rd Farmington CT 06032",
    "addr:housenumber":"184",
    "addr:postcode":"06032",
    "addr:street":"Red Oak Hill Rd",
    "iso:country":"US",
    "sg:address":"184 Red Oak Hill Rd",
    "sg:city":"Farmington",
    "sg:classifiers":[
        {
            "category":"Farming",
            "subcategory":"Fish & Marine Products",
            "type":"Manufacturing & Wholesale Goods"
        }
    ],
    "sg:phone":"+1 860 677 0128",
    "sg:postcode":"06032",
    "sg:province":"CT",
    "sg:tags":[
        "management"
    ],
    "wof:name":"Farmington Game Club Inc",
    "wof:placetype":"venue"
},
  "geometry": {"coordinates":[-72.874076,41.733874],"type":"Point"}
}