{
  "type": "Feature",
  "properties": {
    "addr:full":"146 White St Danbury CT 06810",
    "addr:housenumber":"146",
    "addr:postcode":"06810",
    "addr:street":"White St",
    "iso:country":"US",
    "sg:address":"146 White St",
    "sg:city":"Danbury",
    "sg:classifiers":[
        {
            "category":"Government",
            "subcategory":"Court House",
            "type":"Public Place"
        }
    ],
    "sg:phone":"+1 203 207 8650",
    "sg:postcode":"06810",
    "sg:province":"CT",
    "sg:tags":[
        "state",
        "counsel"
    ],
    "wof:name":"Public Defender",
    "wof:placetype":"venue"
},
  "geometry": {"coordinates":[-73.449516,41.398613],"type":"Point"}
}