{
  "type": "Feature",
  "properties": {
    "iso:country":"US",
    "sg:address":"11 Asylum St",
    "sg:city":"Hartford",
    "sg:classifiers":[
        {
            "category":"Professional",
            "subcategory":"Management & Consulting",
            "type":"Services"
        }
    ],
    "sg:phone":"+1   ",
    "sg:postcode":"06103",
    "sg:province":"CT",
    "sg:tags":[
        "business"
    ],
    "wof:name":"Lushington & Associates",
    "wof:placetype":"venue"
},
  "geometry": {"coordinates":[-72.673919,41.766617],"type":"Point"}
}