{
  "type": "Feature",
  "properties": {
    "iso:country":"US",
    "sg:address":"114 Hebron St",
    "sg:city":"Hartford",
    "sg:classifiers":[
        {
            "category":"Organizations",
            "subcategory":"Religious Organization",
            "type":"Services"
        }
    ],
    "sg:phone":"+1   ",
    "sg:postcode":"06112",
    "sg:province":"CT",
    "wof:name":"Joseph A Little Rev",
    "wof:placetype":"venue"
},
  "geometry": {"coordinates":[-72.703981,41.790277],"type":"Point"}
}