{
  "type": "Feature",
  "properties": {
    "addr:full":"548 Willett Ave Port Chester CT 10573",
    "addr:housenumber":"548",
    "addr:postcode":"10573",
    "addr:street":"Willett Ave;Chester",
    "iso:country":"US",
    "sg:address":"548 Willett Ave",
    "sg:city":"Port Chester",
    "sg:classifiers":[
        {
            "category":"Shopping",
            "subcategory":"Pharmacy",
            "type":"Retail Goods"
        },
        {
            "category":"Manufacturing",
            "subcategory":"Tools & Machinery",
            "type":"Manufacturing & Wholesale Goods"
        }
    ],
    "sg:phone":"+1 914 939 1820",
    "sg:postcode":"10573",
    "sg:province":"CT",
    "sg:tags":[
        "equipment",
        "hospital",
        "supply"
    ],
    "wof:name":"Lyon Park Pharmacy Inc",
    "wof:placetype":"venue"
},
  "geometry": {"coordinates":[-73.659795,41.012619],"type":"Point"}
}