{
  "type": "Feature",
  "properties": {
    "iso:country":"US",
    "sg:address":"462 New Haven Ave",
    "sg:city":"Derby",
    "sg:classifiers":[
        {
            "category":"Building & Trades",
            "subcategory":"Landscaping Services",
            "type":"Services"
        }
    ],
    "sg:phone":"+1 203 734 6336",
    "sg:postcode":"06418",
    "sg:province":"CT",
    "wof:name":"Emp Pintos Landscaping",
    "wof:placetype":"venue"
},
  "geometry": {"coordinates":[-73.059138,41.311619],"type":"Point"}
}