{
  "type": "Feature",
  "properties": {
    "iso:country":"US",
    "sg:address":"150 James St",
    "sg:city":"New Haven",
    "sg:classifiers":[
        {
            "category":"Education",
            "subcategory":"School",
            "type":"Public Place"
        }
    ],
    "sg:phone":"+1 203 946 8657",
    "sg:postcode":"06513",
    "sg:province":"CT",
    "wof:name":"Strong School",
    "wof:placetype":"venue"
},
  "geometry": {"coordinates":[-72.90295399999999,41.306194],"type":"Point"}
}