{
  "type": "Feature",
  "properties": {
    "iso:country":"US",
    "sg:address":"85 Brownson Dr",
    "sg:city":"Shelton",
    "sg:classifiers":[
        {
            "category":"Building & Trades",
            "subcategory":"Construction",
            "type":"Services"
        }
    ],
    "sg:phone":"+1   ",
    "sg:postcode":"06484",
    "sg:province":"CT",
    "sg:tags":[
        "residential",
        "repair"
    ],
    "wof:name":"Homeowner Services",
    "wof:placetype":"venue"
},
  "geometry": {"coordinates":[-73.150766,41.306075],"type":"Point"}
}