{
  "type": "Feature",
  "properties": {
    "iso:country":"US",
    "sg:address":"7 Rye Ridge Plz",
    "sg:city":"Rye Brook",
    "sg:classifiers":[
        {
            "category":"Restaurant",
            "type":"Food & Drink"
        }
    ],
    "sg:phone":"+1 914 939 3475",
    "sg:postcode":"10573",
    "sg:province":"CT",
    "wof:name":"Club Sandwich Of Rye Brook",
    "wof:placetype":"venue"
},
  "geometry": {"coordinates":[-73.681591,41.003272],"type":"Point"}
}