{
  "type": "Feature",
  "properties": {
    "iso:country":"US",
    "sg:address":"77 Hazard Ave",
    "sg:city":"Enfield",
    "sg:classifiers":[
        {
            "category":"Food & Beverages",
            "subcategory":"Liquor & Beverages",
            "type":"Retail Goods"
        }
    ],
    "sg:phone":"+1 860 745 0015",
    "sg:postcode":"06082",
    "sg:province":"CT",
    "sg:tags":[
        "alcoholic"
    ],
    "wof:name":"Robert D Smyth",
    "wof:placetype":"venue"
},
  "geometry": {"coordinates":[-72.572411,41.989621],"type":"Point"}
}