{
  "type": "Feature",
  "properties": {
    "addr:full":"20 E Creek Cir Guilford CT 06437",
    "addr:housenumber":"20",
    "addr:postcode":"06437",
    "addr:street":"E Creek Cir",
    "iso:country":"US",
    "sg:address":"20 E Creek Cir",
    "sg:city":"Guilford",
    "sg:classifiers":[
        {
            "category":"Professional",
            "subcategory":"Management & Consulting",
            "type":"Services"
        }
    ],
    "sg:phone":"+1   ",
    "sg:postcode":"06437",
    "sg:province":"CT",
    "wof:name":"Norton Consulting",
    "wof:placetype":"venue"
},
  "geometry": {"coordinates":[-72.667265,41.280653],"type":"Point"}
}