{
  "type": "Feature",
  "properties": {
    "iso:country":"US",
    "sg:address":"12 Coogan Blvd",
    "sg:city":"Mystic",
    "sg:classifiers":[
        {
            "category":"Fast Food",
            "type":"Food & Drink"
        },
        {
            "category":"Restaurant",
            "type":"Food & Drink"
        }
    ],
    "sg:phone":"+1 860 572 9991",
    "sg:postcode":"06355",
    "sg:province":"CT",
    "sg:tags":[
        "take"
    ],
    "sg:website":"http://www.pekingtokyomystic.com",
    "wof:name":"Peking Tokyo",
    "wof:placetype":"venue"
},
  "geometry": {"coordinates":[-71.95674099999999,41.372589],"type":"Point"}
}