{
  "type": "Feature",
  "properties": {
    "addr:full":"35 John St Bridgeport CT 06604",
    "addr:housenumber":"35",
    "addr:postcode":"06604",
    "addr:street":"John St",
    "iso:country":"US",
    "sg:address":"35 John St",
    "sg:city":"Bridgeport",
    "sg:classifiers":[
        {
            "category":"Restaurant",
            "type":"Food & Drink"
        }
    ],
    "sg:phone":"+1 203 336 3010",
    "sg:postcode":"06604",
    "sg:province":"CT",
    "sg:tags":[
        "cafe"
    ],
    "wof:name":"Travel Cafe",
    "wof:placetype":"venue"
},
  "geometry": {"coordinates":[-73.188973,41.177742],"type":"Point"}
}