{
  "type": "Feature",
  "properties": {
    "addr:full":"222 Barbour St Hartford CT 06120",
    "addr:housenumber":"222",
    "addr:postcode":"06120",
    "addr:street":"Barbour St",
    "iso:country":"US",
    "sg:address":"222 Barbour St",
    "sg:city":"Hartford",
    "sg:classifiers":[
        {
            "category":"Organizations",
            "subcategory":"Religious Organization",
            "type":"Services"
        }
    ],
    "sg:phone":"+1   ",
    "sg:postcode":"06120",
    "sg:province":"CT",
    "wof:name":"Mount Moriah Baptist Church",
    "wof:placetype":"venue"
},
  "geometry": {"coordinates":[-72.677937,41.790618],"type":"Point"}
}