{
  "type": "Feature",
  "properties": {
    "iso:country":"US",
    "sg:address":"5 Covlee Dr",
    "sg:city":"Westport",
    "sg:classifiers":[
        {
            "category":"Professional",
            "subcategory":"Computer Services",
            "type":"Services"
        }
    ],
    "sg:phone":"+1 203 226 8603",
    "sg:postcode":"06880",
    "sg:province":"CT",
    "sg:tags":[
        "internet"
    ],
    "wof:name":"Leadgenesis LLC",
    "wof:placetype":"venue"
},
  "geometry": {"coordinates":[-73.382423,41.102335],"type":"Point"}
}