{
  "type": "Feature",
  "properties": {
    "addr:full":"2277 Main St Glastonbury CT 06033",
    "addr:housenumber":"2277",
    "addr:postcode":"06033",
    "addr:street":"Main St",
    "iso:country":"US",
    "sg:address":"2277 Main St",
    "sg:city":"Glastonbury",
    "sg:phone":"+1 860 633 3639",
    "sg:postcode":"06033",
    "sg:province":"CT",
    "sg:website":"http://www.bridestobe-cons.com",
    "wof:name":"Brides To Be",
    "wof:placetype":"venue"
},
  "geometry": {"coordinates":[-72.608204,41.711085],"type":"Point"}
}