{
  "type": "Feature",
  "properties": {
    "addr:full":"45 Mimosa Ct Ridgefield CT 06877",
    "addr:housenumber":"45",
    "addr:postcode":"06877",
    "addr:street":"Mimosa Ct",
    "iso:country":"US",
    "sg:address":"45 Mimosa Ct",
    "sg:city":"Ridgefield",
    "sg:classifiers":[
        {
            "category":"Professional",
            "subcategory":"Management & Consulting",
            "type":"Services"
        }
    ],
    "sg:phone":"+1 203 431 6565",
    "sg:postcode":"06877",
    "sg:province":"CT",
    "sg:tags":[
        "marketing",
        "program"
    ],
    "sg:website":"www.directexec.com",
    "wof:name":"Madison Executive Search'",
    "wof:placetype":"venue"
},
  "geometry": {"coordinates":[-73.497997,41.313609],"type":"Point"}
}