{
  "type": "Feature",
  "properties": {
    "addr:full":"1044 Barnes Rd Wallingford CT 06492",
    "addr:housenumber":"1044",
    "addr:postcode":"06492",
    "addr:street":"Barnes Rd",
    "iso:country":"US",
    "sg:address":"1044 Barnes Rd",
    "sg:city":"Wallingford",
    "sg:classifiers":[
        {
            "category":"Manufacturing",
            "subcategory":"Printing",
            "type":"Manufacturing & Wholesale Goods"
        }
    ],
    "sg:phone":"+1 203 265 3169",
    "sg:postcode":"06492",
    "sg:province":"CT",
    "sg:tags":[
        "printer"
    ],
    "wof:name":"Eager Prints",
    "wof:placetype":"venue"
},
  "geometry": {"coordinates":[-72.774413,41.482336],"type":"Point"}
}