{
  "type": "Feature",
  "properties": {
    "addr:full":"29 Aiken St Norwalk CT 06851",
    "addr:housenumber":"29",
    "addr:postcode":"06851",
    "addr:street":"Aiken St",
    "iso:country":"US",
    "sg:address":"29 Aiken St",
    "sg:city":"Norwalk",
    "sg:classifiers":[
        {
            "category":"Building & Trades",
            "subcategory":"Cleaning & Sanitation",
            "type":"Services"
        }
    ],
    "sg:phone":"+1   ",
    "sg:postcode":"06851",
    "sg:province":"CT",
    "sg:tags":[
        "maintenance"
    ],
    "wof:name":"Trepovich Handyman Services",
    "wof:placetype":"venue"
},
  "geometry": {"coordinates":[-73.42187800000001,41.131346],"type":"Point"}
}