{
  "type": "Feature",
  "properties": {
    "addr:full":"23 Mona Ave Fairfield CT 06405",
    "addr:housenumber":"23",
    "addr:postcode":"06405",
    "addr:street":"Mona Ave",
    "iso:country":"US",
    "sg:address":"23 Mona Ave",
    "sg:city":"Fairfield",
    "sg:classifiers":[
        {
            "category":"Education",
            "subcategory":"Special Training",
            "type":"Public Place"
        }
    ],
    "sg:phone":"+1   ",
    "sg:postcode":"06405",
    "sg:province":"CT",
    "wof:name":"Personal Driving Service",
    "wof:placetype":"venue"
},
  "geometry": {"coordinates":[-72.84495699999999,41.281482],"type":"Point"}
}