{
  "type": "Feature",
  "properties": {
    "iso:country":"US",
    "sg:address":"2400 Foxon Rd",
    "sg:city":"North Branford",
    "sg:classifiers":[
        {
            "category":"Home & Garden",
            "subcategory":"Carpets & Floor Coverings",
            "type":"Retail Goods"
        }
    ],
    "sg:phone":"+1 203 488 9955",
    "sg:postcode":"06471",
    "sg:province":"CT",
    "sg:tags":[
        "dealer",
        "rug"
    ],
    "wof:name":"Unique Carpet Shop",
    "wof:placetype":"venue"
},
  "geometry": {"coordinates":[-72.74966999999999,41.3413],"type":"Point"}
}