{
  "type": "Feature",
  "properties": {
    "iso:country":"US",
    "sg:address":"24 Hyde Ave",
    "sg:city":"Vernon Rockville",
    "sg:classifiers":[
        {
            "category":"Government",
            "subcategory":"Office",
            "type":"Public Place"
        }
    ],
    "sg:phone":"+1 860 875 3881",
    "sg:postcode":"06066",
    "sg:province":"CT",
    "sg:tags":[
        "conservation"
    ],
    "wof:name":"West Engineering Office",
    "wof:placetype":"venue"
},
  "geometry": {"coordinates":[-72.429266,41.860822],"type":"Point"}
}