{
  "type": "Feature",
  "properties": {
    "iso:country":"US",
    "sg:address":"448 East St",
    "sg:city":"Plainville",
    "sg:classifiers":[
        {
            "category":"Retail",
            "subcategory":"Repair Shop",
            "type":"Services"
        }
    ],
    "sg:phone":"+1   ",
    "sg:postcode":"06062",
    "sg:province":"CT",
    "wof:name":"Atlas Upholstering",
    "wof:placetype":"venue"
},
  "geometry": {"coordinates":[-72.87018999999999,41.651364],"type":"Point"}
}