{
  "type": "Feature",
  "properties": {
    "addr:full":"170 Flood Bridge Rd Southbury CT 06488",
    "addr:housenumber":"170",
    "addr:postcode":"06488",
    "addr:street":"Flood Bridge Rd",
    "iso:country":"US",
    "sg:address":"170 Flood Bridge Rd",
    "sg:city":"Southbury",
    "sg:classifiers":[
        {
            "category":"Home & Garden",
            "subcategory":"Household Appliances",
            "type":"Retail Goods"
        }
    ],
    "sg:phone":"+1 203 264 2772",
    "sg:postcode":"06488",
    "sg:province":"CT",
    "sg:tags":[
        "repair",
        "electrical"
    ],
    "wof:name":"Williams Appliance",
    "wof:placetype":"venue"
},
  "geometry": {"coordinates":[-73.243681,41.467695],"type":"Point"}
}