{
  "type": "Feature",
  "properties": {
    "iso:country":"US",
    "sg:address":"599 West Ave",
    "sg:city":"Norwalk",
    "sg:classifiers":[
        {
            "category":"Autos & Motor Vehicles",
            "subcategory":"Auto Supplies",
            "type":"Retail Goods"
        }
    ],
    "sg:phone":"+1 203 866 0775",
    "sg:postcode":"06850",
    "sg:province":"CT",
    "wof:name":"Currie Tire",
    "wof:placetype":"venue"
},
  "geometry": {"coordinates":[-73.41614,41.112384],"type":"Point"}
}