{
  "type": "Feature",
  "properties": {
    "iso:country":"US",
    "sg:address":"606 Enfield St",
    "sg:city":"Enfield",
    "sg:classifiers":[
        {
            "category":"Shopping",
            "subcategory":"Tobacco",
            "type":"Retail Goods"
        }
    ],
    "sg:phone":"+1 860 253 0441",
    "sg:postcode":"06082",
    "sg:province":"CT",
    "sg:tags":[
        "store"
    ],
    "wof:name":"Carolina Tobacco Emporium",
    "wof:placetype":"venue"
},
  "geometry": {"coordinates":[-72.59284700000001,42.00758],"type":"Point"}
}