{
  "type": "Feature",
  "properties": {
    "iso:country":"US",
    "sg:address":"141 Great Hill Rd",
    "sg:city":"Seymour",
    "sg:classifiers":[
        {
            "category":"Organizations",
            "subcategory":"Community Association",
            "type":"Services"
        }
    ],
    "sg:phone":"+1   ",
    "sg:postcode":"06483",
    "sg:province":"CT",
    "wof:name":"Living Spgs Chrstn Fellowship",
    "wof:placetype":"venue"
},
  "geometry": {"coordinates":[-73.115047,41.36124],"type":"Point"}
}