{
  "type": "Feature",
  "properties": {
    "addr:full":"1412 Albany Ave Hartford CT 06112",
    "addr:housenumber":"1412",
    "addr:postcode":"06112",
    "addr:street":"Albany Ave;Ct",
    "iso:country":"US",
    "sg:address":"1412 Albany Ave",
    "sg:city":"Hartford",
    "sg:classifiers":[
        {
            "category":"Wholesale",
            "subcategory":"Machinery & Supplies",
            "type":"Manufacturing & Wholesale Goods"
        }
    ],
    "sg:phone":"+1 860 727 1122",
    "sg:postcode":"06112",
    "sg:province":"CT",
    "sg:tags":[
        "equipment",
        "establishment"
    ],
    "wof:name":"Stanley Beauty & Barber Suppli",
    "wof:placetype":"venue"
},
  "geometry": {"coordinates":[-72.69932900000001,41.783301],"type":"Point"}
}