{
  "type": "Feature",
  "properties": {
    "addr:full":"32 Cook Ln Beacon Falls CT 06403",
    "addr:housenumber":"32",
    "addr:postcode":"06403",
    "addr:street":"Cook Ln;Falls Ct",
    "iso:country":"US",
    "sg:address":"32 Cook Ln",
    "sg:city":"Beacon Falls",
    "sg:classifiers":[
        {
            "category":"Wholesale",
            "subcategory":"Groceries",
            "type":"Manufacturing & Wholesale Goods"
        }
    ],
    "sg:phone":"+1 203 723 0696",
    "sg:postcode":"06403",
    "sg:province":"CT",
    "wof:name":"Double J Beverages Inc",
    "wof:placetype":"venue"
},
  "geometry": {"coordinates":[-73.04427099999999,41.446789],"type":"Point"}
}