{
  "type": "Feature",
  "properties": {
    "addr:full":"21 Winesap Rd Berlin CT 06037",
    "addr:housenumber":"21",
    "addr:postcode":"06037",
    "addr:street":"Winesap Rd",
    "iso:country":"US",
    "sg:address":"21 Winesap Rd",
    "sg:city":"Berlin",
    "sg:classifiers":[
        {
            "category":"Organizations",
            "subcategory":"Membership Organization",
            "type":"Services"
        }
    ],
    "sg:phone":"+1   ",
    "sg:postcode":"06037",
    "sg:province":"CT",
    "wof:name":"Robert C Vance Foundation",
    "wof:placetype":"venue"
},
  "geometry": {"coordinates":[-72.791641,41.610302],"type":"Point"}
}