{
  "type": "Feature",
  "properties": {
    "addr:full":"51 Shunpike Rd Cromwell CT 06416",
    "addr:housenumber":"51",
    "addr:postcode":"06416",
    "addr:street":"Shunpike Rd Cromwell Ct",
    "iso:country":"US",
    "sg:address":"51 Shunpike Rd",
    "sg:city":"Cromwell",
    "sg:classifiers":[
        {
            "category":"Shopping",
            "subcategory":"Clothing, Apparel, & Fashions",
            "type":"Retail Goods"
        }
    ],
    "sg:phone":"+1 860 632 7801",
    "sg:postcode":"06416",
    "sg:province":"CT",
    "wof:name":"Fashion Bug",
    "wof:placetype":"venue"
},
  "geometry": {"coordinates":[-72.676714,41.60637],"type":"Point"}
}