{
  "type": "Feature",
  "properties": {
    "addr:full":"57 Main St Ridgefield CT 06877",
    "addr:housenumber":"57",
    "addr:postcode":"06877",
    "addr:street":"Main St",
    "iso:country":"US",
    "sg:address":"57 Main St",
    "sg:city":"Ridgefield",
    "sg:classifiers":[
        {
            "category":"Professional",
            "subcategory":"Management & Consulting",
            "type":"Services"
        },
        {
            "category":"Health Services",
            "subcategory":"Clinic",
            "type":"Services"
        }
    ],
    "sg:phone":"+1 203 894 1412",
    "sg:postcode":"06877",
    "sg:province":"CT",
    "wof:name":"Fred Hyde & Associates Inc",
    "wof:placetype":"venue"
},
  "geometry": {"coordinates":[-73.496224,41.270862],"type":"Point"}
}