{
  "type": "Feature",
  "properties": {
    "iso:country":"US",
    "sg:address":"148 US Hwy 1",
    "sg:city":"Norwalk",
    "sg:classifiers":[
        {
            "category":"Professional",
            "type":"Services"
        }
    ],
    "sg:phone":"+1 203 838 0535",
    "sg:postcode":"06851",
    "sg:province":"CT",
    "sg:tags":[
        "actuary"
    ],
    "wof:name":"Robert W Grathwohl Assoc Inc",
    "wof:placetype":"venue"
},
  "geometry": {"coordinates":[-73.39988700000001,41.123813],"type":"Point"}
}