{
  "type": "Feature",
  "properties": {
    "addr:full":"188 Honey Hill Rd Watertown CT 06795",
    "addr:housenumber":"188",
    "addr:postcode":"06795",
    "addr:street":"Honey Hill Rd",
    "iso:country":"US",
    "sg:address":"188 Honey Hill Rd",
    "sg:city":"Watertown",
    "sg:classifiers":[
        {
            "category":"Manufacturing",
            "subcategory":"Toys & Sporting Goods",
            "type":"Manufacturing & Wholesale Goods"
        }
    ],
    "sg:phone":"+1 860 417 2370",
    "sg:postcode":"06795",
    "sg:province":"CT",
    "sg:tags":[
        "toys-wholesale",
        "manufacturer"
    ],
    "wof:name":"Kg Box Games",
    "wof:placetype":"venue"
},
  "geometry": {"coordinates":[-73.12556600000001,41.630986],"type":"Point"}
}