{
  "type": "Feature",
  "properties": {
    "iso:country":"US",
    "sg:address":"108 Water St",
    "sg:city":"Stonington",
    "sg:classifiers":[
        {
            "category":"Professional",
            "subcategory":"Management & Consulting",
            "type":"Services"
        }
    ],
    "sg:phone":"+1 860 535 8364",
    "sg:postcode":"06378",
    "sg:province":"CT",
    "sg:tags":[
        "real estate"
    ],
    "wof:name":"Seaboard Hotel and Resort Brkg",
    "wof:placetype":"venue"
},
  "geometry": {"coordinates":[-71.90684299999999,41.333849],"type":"Point"}
}