{
  "type": "Feature",
  "properties": {
    "addr:full":"252 Maplewood Ave Bridgeport CT 06605",
    "addr:housenumber":"252",
    "addr:postcode":"06605",
    "addr:street":"Maplewood Ave",
    "iso:country":"US",
    "sg:address":"252 Maplewood Ave",
    "sg:city":"Bridgeport",
    "sg:classifiers":[
        {
            "category":"Social Services",
            "type":"Services"
        }
    ],
    "sg:phone":"+1 203 366 2551",
    "sg:postcode":"06605",
    "sg:province":"CT",
    "sg:tags":[
        "organization",
        "welfare"
    ],
    "wof:name":"ABCD Clothing Ctr",
    "wof:placetype":"venue"
},
  "geometry": {"coordinates":[-73.208274,41.178868],"type":"Point"}
}