{
  "type": "Feature",
  "properties": {
    "iso:country":"US",
    "sg:address":"23 Bloomer Rd",
    "sg:city":"Ridgefield",
    "sg:classifiers":[
        {
            "category":"Wholesale",
            "subcategory":"Toys & Hobbies",
            "type":"Manufacturing & Wholesale Goods"
        }
    ],
    "sg:phone":"+1 203 438 1712",
    "sg:postcode":"06877",
    "sg:province":"CT",
    "sg:tags":[
        "wholesaler"
    ],
    "wof:name":"V Russo Seafood",
    "wof:placetype":"venue"
},
  "geometry": {"coordinates":[-73.468599,41.269068],"type":"Point"}
}