{
  "type": "Feature",
  "properties": {
    "iso:country":"US",
    "sg:address":"116 Willard Ave",
    "sg:city":"Newington",
    "sg:classifiers":[
        {
            "category":"Building & Trades",
            "subcategory":"Landscaping Services",
            "type":"Services"
        }
    ],
    "sg:phone":"+1 860 232 3807",
    "sg:postcode":"06111",
    "sg:province":"CT",
    "sg:tags":[
        "lawn",
        "landscape",
        "maintenance"
    ],
    "wof:name":"Errico Brothers Landscaping LP",
    "wof:placetype":"venue"
},
  "geometry": {"coordinates":[-72.737314,41.717546],"type":"Point"}
}