{
  "type": "Feature",
  "properties": {
    "addr:full":"169 Albany Tpke Canton CT 06019",
    "addr:housenumber":"169",
    "addr:postcode":"06019",
    "addr:street":"Albany Tpke Canton Ct",
    "iso:country":"US",
    "sg:address":"169 Albany Tpke",
    "sg:city":"Canton",
    "sg:classifiers":[
        {
            "category":"Wholesale",
            "subcategory":"Machinery & Supplies",
            "type":"Manufacturing & Wholesale Goods"
        }
    ],
    "sg:phone":"+1 860 693 2339",
    "sg:postcode":"06019",
    "sg:province":"CT",
    "sg:tags":[
        "equipment",
        "establishment"
    ],
    "wof:name":"Donnas Head Quarters",
    "wof:placetype":"venue"
},
  "geometry": {"coordinates":[-72.893766,41.824593],"type":"Point"}
}