{
  "type": "Feature",
  "properties": {
    "iso:country":"US",
    "sg:address":"17 Cardinal Ct",
    "sg:city":"Ridgefield",
    "sg:classifiers":[
        {
            "category":"Banks & Credit Unions",
            "subcategory":"Bank",
            "type":"Services"
        },
        {
            "category":"Banks & Credit Unions",
            "subcategory":"Financial Services",
            "type":"Services"
        }
    ],
    "sg:phone":"+1 203 431 3672",
    "sg:postcode":"06877",
    "sg:province":"CT",
    "sg:tags":[
        "loan",
        "saving"
    ],
    "wof:name":"Diane Ugolyn",
    "wof:placetype":"venue"
},
  "geometry": {"coordinates":[-73.52198,41.287477],"type":"Point"}
}