{
  "type": "Feature",
  "properties": {
    "iso:country":"US",
    "sg:address":"428 Main St",
    "sg:city":"East Haven",
    "sg:classifiers":[
        {
            "category":"Shopping",
            "subcategory":"Jewelry",
            "type":"Retail Goods"
        }
    ],
    "sg:phone":"+1 203 469 7553",
    "sg:postcode":"06512",
    "sg:province":"CT",
    "sg:tags":[
        "store",
        "jeweler"
    ],
    "wof:name":"Palmer's Jewelers & Mfrs",
    "wof:placetype":"venue"
},
  "geometry": {"coordinates":[-72.877297,41.281804],"type":"Point"}
}