{
  "type": "Feature",
  "properties": {
    "addr:full":"35 Ledgewood Dr Norwalk CT 06850",
    "addr:housenumber":"35",
    "addr:postcode":"06850",
    "addr:street":"Ledgewood Dr",
    "iso:country":"US",
    "sg:address":"35 Ledgewood Dr",
    "sg:city":"Norwalk",
    "sg:classifiers":[
        {
            "category":"Professional",
            "type":"Services"
        }
    ],
    "sg:phone":"+1   ",
    "sg:postcode":"06850",
    "sg:province":"CT",
    "wof:name":"Lightning Racing Products",
    "wof:placetype":"venue"
},
  "geometry": {"coordinates":[-73.446084,41.127542],"type":"Point"}
}