{
  "type": "Feature",
  "properties": {
    "addr:full":"14 Zora Ln Stamford CT 06903",
    "addr:housenumber":"14",
    "addr:postcode":"06903",
    "addr:street":"Zora Ln",
    "iso:country":"US",
    "sg:address":"14 Zora Ln",
    "sg:city":"Stamford",
    "sg:classifiers":[
        {
            "category":"Shopping",
            "subcategory":"Clothing, Apparel, & Fashions",
            "type":"Retail Goods"
        }
    ],
    "sg:phone":"+1 203 327 5740",
    "sg:postcode":"06903",
    "sg:province":"CT",
    "sg:tags":[
        "infant",
        "wear"
    ],
    "wof:name":"Fashion Lounge",
    "wof:placetype":"venue"
},
  "geometry": {"coordinates":[-73.53254699999999,41.125171],"type":"Point"}
}