{
  "type": "Feature",
  "properties": {
    "addr:full":"29 Rte 37 S Sherman CT 06784",
    "addr:housenumber":"29",
    "addr:postcode":"06784",
    "addr:street":"Rte 37 S Sherman Ct",
    "iso:country":"US",
    "sg:address":"29 Rte 37 S",
    "sg:city":"Sherman",
    "sg:classifiers":[
        {
            "category":"Government",
            "subcategory":"Post Office",
            "type":"Public Place"
        }
    ],
    "sg:phone":"+1 860 354 6191",
    "sg:postcode":"06784",
    "sg:province":"CT",
    "sg:website":"www.usps.com",
    "wof:name":"US Post Office",
    "wof:placetype":"venue"
},
  "geometry": {"coordinates":[-73.501099,41.572284],"type":"Point"}
}