{
  "type": "Feature",
  "properties": {
    "iso:country":"US",
    "sg:address":"44 Miller Rd",
    "sg:city":"Colchester",
    "sg:classifiers":[
        {
            "category":"Professional",
            "subcategory":"Business Services",
            "type":"Services"
        }
    ],
    "sg:phone":"+1   ",
    "sg:postcode":"06415",
    "sg:province":"CT",
    "wof:name":"Nvision Technologies LLC",
    "wof:placetype":"venue"
},
  "geometry": {"coordinates":[-72.352126,41.589256],"type":"Point"}
}