{
  "type": "Feature",
  "properties": {
    "iso:country":"US",
    "sg:address":"1180 Boulevard",
    "sg:city":"Hartford",
    "sg:classifiers":[
        {
            "category":"Education",
            "subcategory":"Dance Studio",
            "type":"Public Place"
        }
    ],
    "sg:phone":"+1   ",
    "sg:postcode":"06119",
    "sg:province":"CT",
    "wof:name":"Griffith Academy Inc",
    "wof:placetype":"venue"
},
  "geometry": {"coordinates":[-72.721281,41.759812],"type":"Point"}
}