{
  "type": "Feature",
  "properties": {
    "iso:country":"US",
    "sg:address":"427 Franklin Ave",
    "sg:city":"Hartford",
    "sg:classifiers":[
        {
            "category":"Organizations",
            "subcategory":"Non-profit Organization",
            "type":"Services"
        }
    ],
    "sg:phone":"+1   ",
    "sg:postcode":"06114",
    "sg:province":"CT",
    "sg:tags":[
        "social"
    ],
    "wof:name":"South End Community Services",
    "wof:placetype":"venue"
},
  "geometry": {"coordinates":[-72.6754,41.737245],"type":"Point"}
}