{
  "type": "Feature",
  "properties": {
    "addr:full":"30 Station Pl Stamford CT 06902",
    "addr:housenumber":"30",
    "addr:postcode":"06902",
    "addr:street":"Station Pl",
    "iso:country":"US",
    "sg:address":"30 Station Pl",
    "sg:city":"Stamford",
    "sg:classifiers":[
        {
            "category":"Food & Beverages",
            "subcategory":"Liquor & Beverages",
            "type":"Retail Goods"
        }
    ],
    "sg:phone":"+1 203 487 0894",
    "sg:postcode":"06902",
    "sg:province":"CT",
    "wof:name":"Cellar",
    "wof:placetype":"venue"
},
  "geometry": {"coordinates":[-73.540463,41.047228],"type":"Point"}
}