{
  "type": "Feature",
  "properties": {
    "iso:country":"US",
    "sg:address":"3 Golf Ct",
    "sg:city":"Ridgefield",
    "sg:classifiers":[
        {
            "category":"Building & Trades",
            "subcategory":"Construction",
            "type":"Services"
        }
    ],
    "sg:phone":"+1 203 431 8198",
    "sg:postcode":"06877",
    "sg:province":"CT",
    "sg:tags":[
        "home",
        "builder"
    ],
    "wof:name":"Lecher Development",
    "wof:placetype":"venue"
},
  "geometry": {"coordinates":[-73.50734300000001,41.268239],"type":"Point"}
}