{
  "type": "Feature",
  "properties": {
    "addr:full":"528 N Main St Stonington CT 06378",
    "addr:housenumber":"528",
    "addr:postcode":"06378",
    "addr:street":"N Main St",
    "iso:country":"US",
    "sg:address":"528 N Main St",
    "sg:city":"Stonington",
    "sg:classifiers":[
        {
            "category":"Professional",
            "subcategory":"Business Services",
            "type":"Services"
        }
    ],
    "sg:phone":"+1   ",
    "sg:postcode":"06378",
    "sg:province":"CT",
    "wof:name":"Harvey Assoc Inc",
    "wof:placetype":"venue"
},
  "geometry": {"coordinates":[-71.903758,41.361132],"type":"Point"}
}