{
  "type": "Feature",
  "properties": {
    "iso:country":"US",
    "sg:address":"26 Grenhart Rd",
    "sg:city":"Stamford",
    "sg:classifiers":[
        {
            "category":"Taxi",
            "type":"Transportation"
        }
    ],
    "sg:phone":"+1 203 325 2611",
    "sg:postcode":"06902",
    "sg:province":"CT",
    "sg:tags":[
        "taxicab"
    ],
    "wof:name":"Stamford Taxi Inc",
    "wof:placetype":"venue"
},
  "geometry": {"coordinates":[-73.559842,41.045227],"type":"Point"}
}