{
  "type": "Feature",
  "properties": {
    "iso:country":"US",
    "sg:address":"829 Wilbur Cross Hwy",
    "sg:city":"Berlin",
    "sg:classifiers":[
        {
            "category":"Travel",
            "subcategory":"Hotels & Motels",
            "type":"Entertainment"
        }
    ],
    "sg:phone":"+1   ",
    "sg:postcode":"06037",
    "sg:province":"CT",
    "sg:tags":[
        "operation"
    ],
    "wof:name":"Salburys Motel",
    "wof:placetype":"venue"
},
  "geometry": {"coordinates":[-72.73934199999999,41.628693],"type":"Point"}
}