{
  "type": "Feature",
  "properties": {
    "iso:country":"US",
    "sg:address":"49 Gallivan Ln",
    "sg:city":"Uncasville",
    "sg:classifiers":[
        {
            "category":"Professional",
            "type":"Services"
        }
    ],
    "sg:phone":"+1 860 848 4515",
    "sg:postcode":"06382",
    "sg:province":"CT",
    "wof:name":"Silver Sugar",
    "wof:placetype":"venue"
},
  "geometry": {"coordinates":[-72.10169,41.48567],"type":"Point"}
}