{
  "type": "Feature",
  "properties": {
    "iso:country":"US",
    "sg:address":"467 E Carriage Dr",
    "sg:city":"Glastonbury",
    "sg:classifiers":[
        {
            "category":"Social Services",
            "subcategory":"Child Care",
            "type":"Services"
        }
    ],
    "sg:phone":"+1   ",
    "sg:postcode":"06033",
    "sg:province":"CT",
    "sg:tags":[
        "school",
        "nursery"
    ],
    "wof:name":"Cathys Nursery School",
    "wof:placetype":"venue"
},
  "geometry": {"coordinates":[-72.578075,41.696287],"type":"Point"}
}