{
  "type": "Feature",
  "properties": {
    "iso:country":"US",
    "sg:address":"34 E Industrial Dr",
    "sg:city":"Branford",
    "sg:classifiers":[
        {
            "category":"Health Services",
            "subcategory":"Hospital",
            "type":"Services"
        }
    ],
    "sg:phone":"+1 203 315 8113",
    "sg:postcode":"06405",
    "sg:province":"CT",
    "sg:tags":[
        "medical",
        "center"
    ],
    "wof:name":"St Raphael Dialysis/Bradford",
    "wof:placetype":"venue"
},
  "geometry": {"coordinates":[-72.762805,41.297222],"type":"Point"}
}