{
  "type": "Feature",
  "properties": {
    "addr:full":"8 Satkowski Dr Stafford Springs CT 06076",
    "addr:housenumber":"8",
    "addr:postcode":"06076",
    "addr:street":"Satkowski Dr",
    "iso:country":"US",
    "sg:address":"8 Satkowski Dr",
    "sg:city":"Stafford Springs",
    "sg:classifiers":[
        {
            "category":"Personal",
            "subcategory":"Beauty Salon",
            "type":"Services"
        }
    ],
    "sg:phone":"+1   ",
    "sg:postcode":"06076",
    "sg:province":"CT",
    "sg:tags":[
        "shop"
    ],
    "wof:name":"Beautiful Nails Boutique",
    "wof:placetype":"venue"
},
  "geometry": {"coordinates":[-72.27533,41.994762],"type":"Point"}
}