{
  "type": "Feature",
  "properties": {
    "iso:country":"US",
    "sg:address":"949 Huntington Rd",
    "sg:city":"Bridgeport",
    "sg:classifiers":[
        {
            "category":"Restaurant",
            "type":"Food & Drink"
        },
        {
            "category":"Ice Cream",
            "type":"Food & Drink"
        }
    ],
    "sg:menulink":"http://www.allmenus.com/ct/bridgeport/165052-dairy-queen/menu/",
    "sg:phone":"+1 203 333 4000",
    "sg:postcode":"06610",
    "sg:province":"CT",
    "sg:tags":[
        "burger",
        "american",
        "ice",
        "cream"
    ],
    "wof:name":"Dairy Queen",
    "wof:placetype":"venue"
},
  "geometry": {"coordinates":[-73.17921699999999,41.205201],"type":"Point"}
}