{
  "type": "Feature",
  "properties": {
    "iso:country":"US",
    "sg:address":"16 Muller Ave",
    "sg:city":"Norwalk",
    "sg:classifiers":[
        {
            "category":"Home & Garden",
            "subcategory":"Building Materials",
            "type":"Retail Goods"
        }
    ],
    "sg:phone":"+1 203 229 0448",
    "sg:postcode":"06851",
    "sg:province":"CT",
    "wof:name":"New Castle Building Products",
    "wof:placetype":"venue"
},
  "geometry": {"coordinates":[-73.42737,41.132673],"type":"Point"}
}