{
  "type": "Feature",
  "properties": {
    "iso:country":"US",
    "sg:address":"641 New London Tpke",
    "sg:city":"Norwich",
    "sg:classifiers":[
        {
            "category":"Recreation",
            "type":"Entertainment"
        }
    ],
    "sg:phone":"+1   ",
    "sg:postcode":"06360",
    "sg:province":"CT",
    "sg:tags":[
        "eating"
    ],
    "wof:name":"Norwich Ice Rink",
    "wof:placetype":"venue"
},
  "geometry": {"coordinates":[-72.102356,41.502743],"type":"Point"}
}