{
  "type": "Feature",
  "properties": {
    "addr:full":"23 Chesterfield Rd East Lyme CT 06333",
    "addr:housenumber":"23",
    "addr:postcode":"06333",
    "addr:street":"Chesterfield Rd East Lyme Ct",
    "iso:country":"US",
    "sg:address":"23 Chesterfield Rd",
    "sg:city":"East Lyme",
    "sg:classifiers":[
        {
            "category":"Manufacturing",
            "subcategory":"Tools & Machinery",
            "type":"Manufacturing & Wholesale Goods"
        }
    ],
    "sg:phone":"+1 860 739 3983",
    "sg:postcode":"06333",
    "sg:province":"CT",
    "sg:tags":[
        "equipment",
        "lighting",
        "emergency"
    ],
    "wof:name":"Emergency Equipment Whse LLC",
    "wof:placetype":"venue"
},
  "geometry": {"coordinates":[-72.21007,41.367503],"type":"Point"}
}