{
  "type": "Feature",
  "properties": {
    "addr:full":"86 Mitchell St Stamford CT 06902",
    "addr:housenumber":"86",
    "addr:postcode":"06902",
    "addr:street":"Mitchell St",
    "iso:country":"US",
    "sg:address":"86 Mitchell St",
    "sg:city":"Stamford",
    "sg:classifiers":[
        {
            "category":"Building & Trades",
            "subcategory":"Construction",
            "type":"Services"
        }
    ],
    "sg:phone":"+1 203 327 3611",
    "sg:postcode":"06902",
    "sg:province":"CT",
    "sg:tags":[
        "industrial"
    ],
    "wof:name":"Brennan Exteriors LLC",
    "wof:placetype":"venue"
},
  "geometry": {"coordinates":[-73.527562,41.03531],"type":"Point"}
}