{
  "type": "Feature",
  "properties": {
    "iso:country":"US",
    "sg:address":"109 Main St",
    "sg:city":"Canaan",
    "sg:classifiers":[
        {
            "category":"Health Services",
            "subcategory":"Doctor",
            "type":"Services"
        }
    ],
    "sg:phone":"+1 860 824 0753",
    "sg:postcode":"06018",
    "sg:province":"CT",
    "sg:tags":[
        "practice",
        "family"
    ],
    "wof:name":"Kobylarz Dennis MD",
    "wof:placetype":"venue"
},
  "geometry": {"coordinates":[-73.328003,42.025799],"type":"Point"}
}