{
  "type": "Feature",
  "properties": {
    "addr:full":"1387 New Haven Ave Milford CT 06460",
    "addr:housenumber":"1387",
    "addr:postcode":"06460",
    "addr:street":"New Haven Ave",
    "iso:country":"US",
    "sg:address":"1387 New Haven Ave",
    "sg:city":"Milford",
    "sg:classifiers":[
        {
            "category":"Shopping",
            "subcategory":"Pharmacy",
            "type":"Retail Goods"
        }
    ],
    "sg:phone":"+1 203 877 8548",
    "sg:postcode":"06460",
    "sg:province":"CT",
    "wof:name":"Brooks Pharmacy",
    "wof:placetype":"venue"
},
  "geometry": {"coordinates":[-72.996618,41.228528],"type":"Point"}
}