{
  "type": "Feature",
  "properties": {
    "addr:full":"467 Winsted Rd Torrington CT 06790",
    "addr:housenumber":"467",
    "addr:postcode":"06790",
    "addr:street":"Winsted Rd",
    "iso:country":"US",
    "sg:address":"467 Winsted Rd",
    "sg:city":"Torrington",
    "sg:classifiers":[
        {
            "category":"Personal",
            "type":"Services"
        }
    ],
    "sg:phone":"+1   ",
    "sg:postcode":"06790",
    "sg:province":"CT",
    "wof:name":"I Do Faces-Dee Mahony",
    "wof:placetype":"venue"
},
  "geometry": {"coordinates":[-73.11196700000001,41.826648],"type":"Point"}
}