{
  "type": "Feature",
  "properties": {
    "iso:country":"US",
    "sg:address":"18 Clark Rd",
    "sg:city":"Colchester",
    "sg:classifiers":[
        {
            "category":"Retail",
            "subcategory":"Repair Shop",
            "type":"Services"
        }
    ],
    "sg:phone":"+1   ",
    "sg:postcode":"06415",
    "sg:province":"CT",
    "wof:name":"Hunters Ridge Taxidermy",
    "wof:placetype":"venue"
},
  "geometry": {"coordinates":[-72.35760500000001,41.552621],"type":"Point"}
}