{
  "type": "Feature",
  "properties": {
    "iso:country":"US",
    "sg:address":"34 Dell Manor Dr",
    "sg:city":"Bristol",
    "sg:classifiers":[
        {
            "category":"Communications",
            "subcategory":"Film & Video Production",
            "type":"Services"
        }
    ],
    "sg:phone":"+1   ",
    "sg:postcode":"06010",
    "sg:province":"CT",
    "sg:tags":[
        "post"
    ],
    "wof:name":"Anderson Productions",
    "wof:placetype":"venue"
},
  "geometry": {"coordinates":[-72.907481,41.651323],"type":"Point"}
}