{
  "type": "Feature",
  "properties": {
    "iso:country":"US",
    "sg:address":"119 South Rd",
    "sg:city":"Winsted",
    "sg:classifiers":[
        {
            "category":"Recreation",
            "subcategory":"Picnic Area",
            "type":"Entertainment"
        },
        {
            "category":"Recreation",
            "type":"Entertainment"
        }
    ],
    "sg:phone":"+1 860 379 5472",
    "sg:postcode":"06098",
    "sg:province":"CT",
    "sg:tags":[
        "amusement",
        "place",
        "entertainers-family",
        "arcade",
        "business"
    ],
    "wof:name":"Shut-In Music",
    "wof:placetype":"venue"
},
  "geometry": {"coordinates":[-73.127932,41.8932],"type":"Point"}
}