{
  "type": "Feature",
  "properties": {
    "addr:full":"14 Keron Dr Shelton CT 06484",
    "addr:housenumber":"14",
    "addr:postcode":"06484",
    "addr:street":"Keron Dr",
    "iso:country":"US",
    "sg:address":"14 Keron Dr",
    "sg:city":"Shelton",
    "sg:classifiers":[
        {
            "category":"Government",
            "subcategory":"Office",
            "type":"Public Place"
        }
    ],
    "sg:phone":"+1 203 924 1757",
    "sg:postcode":"06484",
    "sg:province":"CT",
    "wof:name":"Representative Richard Belden",
    "wof:placetype":"venue"
},
  "geometry": {"coordinates":[-73.097024,41.294805],"type":"Point"}
}