{
  "type": "Feature",
  "properties": {
    "iso:country":"US",
    "sg:address":"56 Kensington Rd",
    "sg:city":"Stamford",
    "sg:classifiers":[
        {
            "category":"Real Estate",
            "subcategory":"Real Estate Agent",
            "type":"Services"
        }
    ],
    "sg:phone":"+1 203 968 0800",
    "sg:postcode":"06905",
    "sg:province":"CT",
    "wof:name":"L & S Realty",
    "wof:placetype":"venue"
},
  "geometry": {"coordinates":[-73.53728599999999,41.087009],"type":"Point"}
}