{
  "type": "Feature",
  "properties": {
    "iso:country":"US",
    "sg:address":"28 Broadway St",
    "sg:city":"Waterbury",
    "sg:classifiers":[
        {
            "category":"Retail",
            "subcategory":"Repair Shop",
            "type":"Services"
        },
        {
            "category":"Building & Trades",
            "subcategory":"Construction",
            "type":"Services"
        }
    ],
    "sg:phone":"+1 203 753 6988",
    "sg:postcode":"06705",
    "sg:province":"CT",
    "sg:tags":[
        "railing",
        "welding"
    ],
    "wof:name":"General Welding Company Inc",
    "wof:placetype":"venue"
},
  "geometry": {"coordinates":[-72.981458,41.541647],"type":"Point"}
}