{
  "type": "Feature",
  "properties": {
    "addr:full":"860 Stafford Rd Storrs Mansfield CT 06268",
    "addr:housenumber":"860",
    "addr:postcode":"06268",
    "addr:street":"Stafford Rd;Mansfield Ct",
    "iso:country":"US",
    "sg:address":"860 Stafford Rd",
    "sg:city":"Storrs Mansfield",
    "sg:classifiers":[
        {
            "category":"Retail",
            "subcategory":"Auto Repair",
            "type":"Services"
        }
    ],
    "sg:phone":"+1   ",
    "sg:postcode":"06268",
    "sg:province":"CT",
    "sg:tags":[
        "automotive",
        "general"
    ],
    "wof:name":"Eagleville Garage",
    "wof:placetype":"venue"
},
  "geometry": {"coordinates":[-72.27634399999999,41.781883],"type":"Point"}
}