{
  "type": "Feature",
  "properties": {
    "addr:full":"7 Elm St Terryville CT 06786",
    "addr:housenumber":"7",
    "addr:postcode":"06786",
    "addr:street":"Elm St Terryville Ct",
    "iso:country":"US",
    "sg:address":"7 Elm St",
    "sg:city":"Terryville",
    "sg:classifiers":[
        {
            "category":"Home & Garden",
            "subcategory":"Carpets & Floor Coverings",
            "type":"Retail Goods"
        }
    ],
    "sg:phone":"+1 860 585 5399",
    "sg:postcode":"06786",
    "sg:province":"CT",
    "sg:tags":[
        "laying",
        "contractor"
    ],
    "wof:name":"Gagnons Carpet",
    "wof:placetype":"venue"
},
  "geometry": {"coordinates":[-73.018322,41.679059],"type":"Point"}
}