{
  "type": "Feature",
  "properties": {
    "iso:country":"US",
    "sg:address":"42 Grand Blvd",
    "sg:city":"Ellington",
    "sg:classifiers":[
        {
            "category":"Professional",
            "subcategory":"Advertising",
            "type":"Services"
        }
    ],
    "sg:phone":"+1 860 648 8948",
    "sg:postcode":"06029",
    "sg:province":"CT",
    "sg:tags":[
        "product",
        "advertising-promotional",
        "specialty"
    ],
    "sg:website":"http://www.actionlogos.com",
    "wof:name":"Action Lgos Prmtons Invtations",
    "wof:placetype":"venue"
},
  "geometry": {"coordinates":[-72.478111,41.869733],"type":"Point"}
}