{
  "type": "Feature",
  "properties": {
    "iso:country":"US",
    "sg:address":"80 Main St",
    "sg:city":"New Canaan",
    "sg:classifiers":[
        {
            "category":"Building & Trades",
            "subcategory":"Construction",
            "type":"Services"
        }
    ],
    "sg:phone":"+1 203 972 3366",
    "sg:postcode":"06840",
    "sg:province":"NY",
    "sg:tags":[
        "contractor"
    ],
    "sg:website":"www.karpassoc.com",
    "wof:name":"KARP Associates Inc",
    "wof:placetype":"venue"
},
  "geometry": {"coordinates":[-73.493071,41.148268],"type":"Point"}
}