{
  "type": "Feature",
  "properties": {
    "addr:full":"1110 E Main St Stamford CT 06902",
    "addr:housenumber":"1110",
    "addr:postcode":"06902",
    "addr:street":"E Main St",
    "iso:country":"US",
    "sg:address":"1110 E Main St",
    "sg:city":"Stamford",
    "sg:classifiers":[
        {
            "category":"Retail",
            "subcategory":"Veterinary Services",
            "type":"Services"
        }
    ],
    "sg:phone":"+1 203 327 7220",
    "sg:postcode":"06902",
    "sg:province":"CT",
    "sg:tags":[
        "pet",
        "hospital",
        "store"
    ],
    "wof:name":"Bolotin David Dr",
    "wof:placetype":"venue"
},
  "geometry": {"coordinates":[-73.51565100000001,41.057553],"type":"Point"}
}