{
  "type": "Feature",
  "properties": {
    "iso:country":"US",
    "sg:address":"2191 Berlin Tpke",
    "sg:city":"Newington",
    "sg:classifiers":[
        {
            "category":"Social Services",
            "subcategory":"Child Care",
            "type":"Services"
        }
    ],
    "sg:phone":"+1   ",
    "sg:postcode":"06111",
    "sg:province":"CT",
    "sg:tags":[
        "day"
    ],
    "wof:name":"Kidco Inc",
    "wof:placetype":"venue"
},
  "geometry": {"coordinates":[-72.705749,41.692708],"type":"Point"}
}