{
  "type": "Feature",
  "properties": {
    "addr:full":"173 Marshall St Winsted CT 06098",
    "addr:housenumber":"173",
    "addr:postcode":"06098",
    "addr:street":"Marshall St Winsted Ct",
    "iso:country":"US",
    "sg:address":"173 Marshall St",
    "sg:city":"Winsted",
    "sg:classifiers":[
        {
            "category":"Building & Trades",
            "subcategory":"Electrical",
            "type":"Services"
        }
    ],
    "sg:phone":"+1 860 379 5078",
    "sg:postcode":"06098",
    "sg:province":"CT",
    "sg:tags":[
        "electrician"
    ],
    "wof:name":"Stephen E Veronesi",
    "wof:placetype":"venue"
},
  "geometry": {"coordinates":[-73.089673,41.958509],"type":"Point"}
}