{
  "type": "Feature",
  "properties": {
    "iso:country":"US",
    "sg:address":"1073 Shippan Ave",
    "sg:city":"Stamford",
    "sg:classifiers":[
        {
            "category":"Professional",
            "subcategory":"Computer Services",
            "type":"Services"
        }
    ],
    "sg:phone":"+1   ",
    "sg:postcode":"06902",
    "sg:province":"CT",
    "sg:tags":[
        "related"
    ],
    "wof:name":"Bivona Systems Consultant",
    "wof:placetype":"venue"
},
  "geometry": {"coordinates":[-73.52766,41.037088],"type":"Point"}
}