{
  "type": "Feature",
  "properties": {
    "iso:country":"US",
    "sg:address":"170 Post Rd W",
    "sg:city":"Westport",
    "sg:classifiers":[
        {
            "category":"Shopping",
            "subcategory":"Bicycles & Sporting Goods",
            "type":"Retail Goods"
        }
    ],
    "sg:phone":"+1 203 227 4377",
    "sg:postcode":"06880",
    "sg:province":"CT",
    "sg:tags":[
        "tackle",
        "fishing"
    ],
    "wof:name":"Compact Fishing Gear",
    "wof:placetype":"venue"
},
  "geometry": {"coordinates":[-73.371252,41.13612],"type":"Point"}
}