{
  "type": "Feature",
  "properties": {
    "addr:full":"100 Yale St Bridgeport CT 06605",
    "addr:housenumber":"100",
    "addr:postcode":"06605",
    "addr:street":"Yale St",
    "iso:country":"US",
    "sg:address":"100 Yale St",
    "sg:city":"Bridgeport",
    "sg:classifiers":[
        {
            "category":"Organizations",
            "subcategory":"Professional Association",
            "type":"Services"
        }
    ],
    "sg:phone":"+1 203 576 8830",
    "sg:postcode":"06605",
    "sg:province":"CT",
    "wof:name":"Mutual Housing Assn",
    "wof:placetype":"venue"
},
  "geometry": {"coordinates":[-73.205668,41.173719],"type":"Point"}
}