{
  "type": "Feature",
  "properties": {
    "iso:country":"US",
    "sg:address":"4 Holiday Point Rd",
    "sg:city":"Sherman",
    "sg:classifiers":[
        {
            "category":"Building & Trades",
            "subcategory":"Plumbing",
            "type":"Services"
        }
    ],
    "sg:phone":"+1 860 350 3183",
    "sg:postcode":"06784",
    "sg:province":"CT",
    "sg:tags":[
        "heating",
        "contractor"
    ],
    "wof:name":"Faust PLUMBING-Heating-AC",
    "wof:placetype":"venue"
},
  "geometry": {"coordinates":[-73.49081700000001,41.57987],"type":"Point"}
}