{
  "type": "Feature",
  "properties": {
    "iso:country":"US",
    "sg:address":"1470 Barnum Ave",
    "sg:city":"Bridgeport",
    "sg:classifiers":[
        {
            "category":"Professional",
            "subcategory":"Computer Services",
            "type":"Services"
        }
    ],
    "sg:phone":"+1 203 333 2473",
    "sg:postcode":"06610",
    "sg:province":"CT",
    "sg:tags":[
        "home",
        "consulting",
        "page",
        "dev",
        "internet"
    ],
    "wof:name":"Net Marketing",
    "wof:placetype":"venue"
},
  "geometry": {"coordinates":[-73.16349599999999,41.18687],"type":"Point"}
}