{
  "type": "Feature",
  "properties": {
    "iso:country":"US",
    "sg:address":"125 Columbus Blvd",
    "sg:city":"New Britain",
    "sg:classifiers":[
        {
            "category":"Organizations",
            "subcategory":"Labor Organization",
            "type":"Services"
        }
    ],
    "sg:phone":"+1   ",
    "sg:postcode":"06051",
    "sg:province":"CT",
    "wof:name":"Police Local 1165 Inc",
    "wof:placetype":"venue"
},
  "geometry": {"coordinates":[-72.77610900000001,41.66661],"type":"Point"}
}