{
  "type": "Feature",
  "properties": {
    "addr:full":"731 Hopmeadow St Simsbury CT 06070",
    "addr:housenumber":"731",
    "addr:postcode":"06070",
    "addr:street":"Hopmeadow St Simsbury Ct",
    "iso:country":"US",
    "sg:address":"731 Hopmeadow St",
    "sg:city":"Simsbury",
    "sg:classifiers":[
        {
            "category":"Travel",
            "subcategory":"Hotels & Motels",
            "type":"Entertainment"
        },
        {
            "category":"Restaurant",
            "type":"Food & Drink"
        }
    ],
    "sg:phone":"+1 860 658 7658",
    "sg:postcode":"06070",
    "sg:province":"CT",
    "wof:name":"Simsbury 1820 House",
    "wof:placetype":"venue"
},
  "geometry": {"coordinates":[-72.80259700000001,41.872898],"type":"Point"}
}