{
  "type": "Feature",
  "properties": {
    "addr:full":"430 Huntington Tpke Bridgeport CT 06610",
    "addr:housenumber":"430",
    "addr:postcode":"06610",
    "addr:street":"Huntington Tpke Bridgeport Ct",
    "iso:country":"US",
    "sg:address":"430 Huntington Tpke",
    "sg:city":"Bridgeport",
    "sg:classifiers":[
        {
            "category":"Food & Beverages",
            "subcategory":"Liquor & Beverages",
            "type":"Retail Goods"
        }
    ],
    "sg:phone":"+1 203 371 6680",
    "sg:postcode":"06610",
    "sg:province":"CT",
    "wof:name":"Stop & Save Warehouse Liquors",
    "wof:placetype":"venue"
},
  "geometry": {"coordinates":[-73.173385,41.215267],"type":"Point"}
}