{
  "type": "Feature",
  "properties": {
    "addr:full":"456 Main St Ridgefield CT 06877",
    "addr:housenumber":"456",
    "addr:postcode":"06877",
    "addr:street":"Main St",
    "iso:country":"US",
    "sg:address":"456 Main St",
    "sg:city":"Ridgefield",
    "sg:classifiers":[
        {
            "category":"Manufacturing",
            "subcategory":"Printing",
            "type":"Manufacturing & Wholesale Goods"
        }
    ],
    "sg:phone":"+1 203 894 8509",
    "sg:postcode":"06877",
    "sg:province":"CT",
    "wof:name":"Acg Holdings Inc",
    "wof:placetype":"venue"
},
  "geometry": {"coordinates":[-73.49841000000001,41.282925],"type":"Point"}
}