{
  "type": "Feature",
  "properties": {
    "iso:country":"US",
    "sg:address":"560 Congress Ave",
    "sg:city":"New Haven",
    "sg:classifiers":[
        {
            "category":"Restaurant",
            "type":"Food & Drink"
        }
    ],
    "sg:phone":"+1 203 776 2963",
    "sg:postcode":"06519",
    "sg:province":"CT",
    "wof:name":"Caribbean Family Pot",
    "wof:placetype":"venue"
},
  "geometry": {"coordinates":[-72.93806600000001,41.300513],"type":"Point"}
}