{
  "type": "Feature",
  "properties": {
    "addr:full":"52 Rainbow Rd East Granby CT 06026",
    "addr:housenumber":"52",
    "addr:postcode":"06026",
    "addr:street":"Rainbow Rd East Granby Ct",
    "iso:country":"US",
    "sg:address":"52 Rainbow Rd",
    "sg:city":"East Granby",
    "sg:classifiers":[
        {
            "category":"Personal",
            "subcategory":"Beauty Salon",
            "type":"Services"
        }
    ],
    "sg:phone":"+1   ",
    "sg:postcode":"06026",
    "sg:province":"CT",
    "sg:tags":[
        "shop"
    ],
    "wof:name":"Timothy Richards",
    "wof:placetype":"venue"
},
  "geometry": {"coordinates":[-72.720479,41.940405],"type":"Point"}
}