{
  "type": "Feature",
  "properties": {
    "addr:full":"27 Hospital Ave Danbury CT 06810",
    "addr:housenumber":"27",
    "addr:postcode":"06810",
    "addr:street":"Hospital Ave",
    "iso:country":"US",
    "sg:address":"27 Hospital Ave",
    "sg:city":"Danbury",
    "sg:classifiers":[
        {
            "category":"Health Services",
            "subcategory":"Doctor",
            "type":"Services"
        },
        {
            "category":"Banks & Credit Unions",
            "subcategory":"Investment Brokerage",
            "type":"Services"
        }
    ],
    "sg:phone":"+1 203 798 0500",
    "sg:postcode":"06810",
    "sg:province":"CT",
    "sg:tags":[
        "physician",
        "urology",
        "infertility",
        "gynecology",
        "surgeons",
        "obstetrics",
        "counseling",
        "surgeon"
    ],
    "sg:website":"http://www.wha-ct.com",
    "wof:name":"Womens Health Associates",
    "wof:placetype":"venue"
},
  "geometry": {"coordinates":[-73.446777,41.405949],"type":"Point"}
}