{
  "type": "Feature",
  "properties": {
    "iso:country":"US",
    "sg:address":"181 Edwards St",
    "sg:city":"New Haven",
    "sg:classifiers":[
        {
            "category":"Professional",
            "subcategory":"Lawyer & Legal Services",
            "type":"Services"
        }
    ],
    "sg:phone":"+1   ",
    "sg:postcode":"06511",
    "sg:province":"CT",
    "wof:name":"Levinson & Cusanelli Attys",
    "wof:placetype":"venue"
},
  "geometry": {"coordinates":[-72.91599600000001,41.318697],"type":"Point"}
}