{
  "type": "Feature",
  "properties": {
    "iso:country":"US",
    "sg:address":"7 Towpath Ln",
    "sg:city":"Avon",
    "sg:classifiers":[
        {
            "category":"Professional",
            "subcategory":"Management & Consulting",
            "type":"Services"
        }
    ],
    "sg:phone":"+1   ",
    "sg:postcode":"06001",
    "sg:province":"CT",
    "sg:tags":[
        "communication",
        "consultant"
    ],
    "wof:name":"Williams & House",
    "wof:placetype":"venue"
},
  "geometry": {"coordinates":[-72.828238,41.808365],"type":"Point"}
}