{
  "type": "Feature",
  "properties": {
    "addr:full":"39 Jennings Rd Hartford CT 06120",
    "addr:housenumber":"39",
    "addr:postcode":"06120",
    "addr:street":"Jennings Rd",
    "iso:country":"US",
    "sg:address":"39 Jennings Rd",
    "sg:city":"Hartford",
    "sg:classifiers":[
        {
            "category":"Professional",
            "subcategory":"Business Services",
            "type":"Services"
        }
    ],
    "sg:phone":"+1   ",
    "sg:postcode":"06120",
    "sg:province":"CT",
    "wof:name":"Budget Bail Bonds",
    "wof:placetype":"venue"
},
  "geometry": {"coordinates":[-72.653925,41.786198],"type":"Point"}
}