{
  "type": "Feature",
  "properties": {
    "iso:country":"US",
    "sg:address":"150 Westport Rd",
    "sg:city":"Wilton",
    "sg:classifiers":[
        {
            "category":"Health Services",
            "subcategory":"Podiatrist",
            "type":"Services"
        }
    ],
    "sg:phone":"+1 203 834 1233",
    "sg:postcode":"06897",
    "sg:province":"CT",
    "wof:name":"Nancy C Gamer DPM",
    "wof:placetype":"venue"
},
  "geometry": {"coordinates":[-73.40225700000001,41.178535],"type":"Point"}
}