{
  "type": "Feature",
  "properties": {
    "addr:full":"4 Lincoln Rd Newtown CT 06470",
    "addr:housenumber":"4",
    "addr:postcode":"06470",
    "addr:street":"Lincoln Rd",
    "iso:country":"US",
    "sg:address":"4 Lincoln Rd",
    "sg:city":"Newtown",
    "sg:classifiers":[
        {
            "category":"Professional",
            "subcategory":"Accounting & Tax Preparation",
            "type":"Services"
        }
    ],
    "sg:phone":"+1 203 426 4250",
    "sg:postcode":"06470",
    "sg:province":"CT",
    "sg:tags":[
        "return",
        "filing"
    ],
    "wof:name":"Rushefski Accounting & Tax Ser",
    "wof:placetype":"venue"
},
  "geometry": {"coordinates":[-73.31197299999999,41.405574],"type":"Point"}
}