{
  "type": "Feature",
  "properties": {
    "iso:country":"US",
    "sg:address":"10 State St",
    "sg:city":"Hartford",
    "sg:classifiers":[
        {
            "category":"Banks & Credit Unions",
            "subcategory":"Bank",
            "type":"Services"
        }
    ],
    "sg:phone":"+1 860 247 2311",
    "sg:postcode":"06103",
    "sg:province":"CT",
    "sg:tags":[
        "company",
        "premium",
        "finance"
    ],
    "wof:name":"American Phoenix",
    "wof:placetype":"venue"
},
  "geometry": {"coordinates":[-72.671549,41.765944],"type":"Point"}
}