{
  "type": "Feature",
  "properties": {
    "iso:country":"US",
    "sg:address":"23 Town View Dr",
    "sg:city":"New Milford",
    "sg:classifiers":[
        {
            "category":"Banks & Credit Unions",
            "subcategory":"Financial Services",
            "type":"Services"
        }
    ],
    "sg:phone":"+1 860 354 9047",
    "sg:postcode":"06776",
    "sg:province":"CT",
    "sg:tags":[
        "investor"
    ],
    "wof:name":"Investments Strategic Asso",
    "wof:placetype":"venue"
},
  "geometry": {"coordinates":[-73.418873,41.569534],"type":"Point"}
}