{
  "type": "Feature",
  "properties": {
    "addr:full":"845 W Main St Branford CT 06405",
    "addr:housenumber":"845",
    "addr:postcode":"06405",
    "addr:street":"W Main St",
    "iso:country":"US",
    "sg:address":"845 W Main St",
    "sg:city":"Branford",
    "sg:classifiers":[
        {
            "category":"Health Services",
            "subcategory":"Optometrist",
            "type":"Services"
        }
    ],
    "sg:phone":"+1   ",
    "sg:postcode":"06405",
    "sg:province":"CT",
    "wof:name":"Bertolli E Robert Dr",
    "wof:placetype":"venue"
},
  "geometry": {"coordinates":[-72.83896799999999,41.27743],"type":"Point"}
}