{
  "type": "Feature",
  "properties": {
    "iso:country":"US",
    "sg:address":"31 Coral Dr",
    "sg:city":"Waterbury",
    "sg:classifiers":[
        {
            "category":"Professional",
            "type":"Services"
        }
    ],
    "sg:phone":"+1 203 596 0428",
    "sg:postcode":"06705",
    "sg:province":"CT",
    "wof:name":"Momena Intl Corporation",
    "wof:placetype":"venue"
},
  "geometry": {"coordinates":[-72.995816,41.557654],"type":"Point"}
}