{
  "type": "Feature",
  "properties": {
    "addr:full":"54 Candlewood Rd Fairfield CT 06477",
    "addr:housenumber":"54",
    "addr:postcode":"06477",
    "addr:street":"Candlewood Rd",
    "iso:country":"US",
    "sg:address":"54 Candlewood Rd",
    "sg:city":"Fairfield",
    "sg:classifiers":[
        {
            "category":"Building & Trades",
            "subcategory":"Electrical",
            "type":"Services"
        }
    ],
    "sg:phone":"+1 203 368 0596",
    "sg:postcode":"06477",
    "sg:province":"CT",
    "sg:tags":[
        "electrical",
        "contractor"
    ],
    "wof:name":"Joseph Russo",
    "wof:placetype":"venue"
},
  "geometry": {"coordinates":[-73.02694099999999,41.251134],"type":"Point"}
}