{
  "type": "Feature",
  "properties": {
    "addr:full":"495 Post Rd E Westport CT 06880",
    "addr:housenumber":"495",
    "addr:postcode":"06880",
    "addr:street":"Post Rd E Westport Ct",
    "iso:country":"US",
    "sg:address":"495 Post Rd E",
    "sg:city":"Westport",
    "sg:classifiers":[
        {
            "category":"Banks & Credit Unions",
            "subcategory":"Investment Brokerage",
            "type":"Services"
        }
    ],
    "sg:phone":"+1 203 557 1430",
    "sg:postcode":"06880",
    "sg:province":"CT",
    "wof:name":"Investments Marblehead",
    "wof:placetype":"venue"
},
  "geometry": {"coordinates":[-73.34908299999999,41.13983],"type":"Point"}
}