{
  "type": "Feature",
  "properties": {
    "addr:full":"121 Grassy Plain St Bethel CT 06801",
    "addr:housenumber":"121",
    "addr:postcode":"06801",
    "addr:street":"Grassy Plain St Bethel Ct",
    "iso:country":"US",
    "sg:address":"121 Grassy Plain St",
    "sg:city":"Bethel",
    "sg:classifiers":[
        {
            "category":"Building & Trades",
            "subcategory":"Construction",
            "type":"Services"
        }
    ],
    "sg:phone":"+1 203 798 8099",
    "sg:postcode":"06801",
    "sg:province":"CT",
    "sg:tags":[
        "painter"
    ],
    "sg:website":"www.acmepainting.com",
    "wof:name":"Acme Painting",
    "wof:placetype":"venue"
},
  "geometry": {"coordinates":[-73.421717,41.364758],"type":"Point"}
}