{
  "type": "Feature",
  "properties": {
    "iso:country":"US",
    "sg:address":"236 Main St",
    "sg:city":"Portland",
    "sg:classifiers":[
        {
            "category":"Banks & Credit Unions",
            "subcategory":"Investment Brokerage",
            "type":"Services"
        }
    ],
    "sg:phone":"+1 860 342 2486",
    "sg:postcode":"06480",
    "sg:province":"CT",
    "sg:tags":[
        "security"
    ],
    "wof:name":"Edward Jones 12807",
    "wof:placetype":"venue"
},
  "geometry": {"coordinates":[-72.64008800000001,41.573733],"type":"Point"}
}