{
  "type": "Feature",
  "properties": {
    "iso:country":"US",
    "sg:address":"1 Station Pl",
    "sg:city":"Stamford",
    "sg:classifiers":[
        {
            "category":"Professional",
            "subcategory":"Computer Services",
            "type":"Services"
        }
    ],
    "sg:phone":"+1 203 978 9496",
    "sg:postcode":"06902",
    "sg:province":"CT",
    "sg:tags":[
        "processing",
        "datum"
    ],
    "wof:name":"Uunet",
    "wof:placetype":"venue"
},
  "geometry": {"coordinates":[-73.539349,41.047354],"type":"Point"}
}