{
  "type": "Feature",
  "properties": {
    "addr:full":"40 Foxon Hill Rd New Haven CT 06513",
    "addr:housenumber":"40",
    "addr:postcode":"06513",
    "addr:street":"Foxon Hill Rd",
    "iso:country":"US",
    "sg:address":"40 Foxon Hill Rd",
    "sg:city":"New Haven",
    "sg:classifiers":[
        {
            "category":"Communications",
            "subcategory":"Film & Video Production",
            "type":"Services"
        }
    ],
    "sg:phone":"+1 203 469 5400",
    "sg:postcode":"06513",
    "sg:province":"CT",
    "sg:tags":[
        "taping"
    ],
    "wof:name":"Fonseca Azpiri Video Prdctns",
    "wof:placetype":"venue"
},
  "geometry": {"coordinates":[-72.853897,41.327966],"type":"Point"}
}