{
  "type": "Feature",
  "properties": {
    "addr:full":"25 Lynwood Dr Cheshire CT 06410",
    "addr:housenumber":"25",
    "addr:postcode":"06410",
    "addr:street":"Lynwood Dr",
    "iso:country":"US",
    "sg:address":"25 Lynwood Dr",
    "sg:city":"Cheshire",
    "sg:classifiers":[
        {
            "category":"Building & Trades",
            "subcategory":"Electrical",
            "type":"Services"
        }
    ],
    "sg:phone":"+1 203 439 0834",
    "sg:postcode":"06410",
    "sg:province":"CT",
    "sg:tags":[
        "electrical",
        "contractor"
    ],
    "wof:name":"Triumph Electric LLC",
    "wof:placetype":"venue"
},
  "geometry": {"coordinates":[-72.92171500000001,41.514022],"type":"Point"}
}