{
  "type": "Feature",
  "properties": {
    "addr:full":"132 Doolittle Rd Stamford CT 06902",
    "addr:housenumber":"132",
    "addr:postcode":"06902",
    "addr:street":"Doolittle Rd",
    "iso:country":"US",
    "sg:address":"132 Doolittle Rd",
    "sg:city":"Stamford",
    "sg:classifiers":[
        {
            "category":"Professional",
            "type":"Services"
        }
    ],
    "sg:phone":"+1 203 329 9761",
    "sg:postcode":"06902",
    "sg:province":"CT",
    "sg:tags":[
        "establishment"
    ],
    "wof:name":"C & T Partners",
    "wof:placetype":"venue"
},
  "geometry": {"coordinates":[-73.569198,41.096993],"type":"Point"}
}