{
  "type": "Feature",
  "properties": {
    "iso:country":"US",
    "sg:address":"94 Dunne Ave",
    "sg:city":"Canton",
    "sg:classifiers":[
        {
            "category":"Building & Trades",
            "subcategory":"Cleaning & Sanitation",
            "type":"Services"
        }
    ],
    "sg:phone":"+1   ",
    "sg:postcode":"06022",
    "sg:province":"CT",
    "sg:tags":[
        "window"
    ],
    "wof:name":"Above and Beyond Window Clean",
    "wof:placetype":"venue"
},
  "geometry": {"coordinates":[-72.92946000000001,41.811971],"type":"Point"}
}