{
  "type": "Feature",
  "properties": {
    "iso:country":"US",
    "sg:address":"538 Branchville Rd",
    "sg:city":"Ridgefield",
    "sg:classifiers":[
        {
            "category":"Organizations",
            "subcategory":"Professional Association",
            "type":"Services"
        }
    ],
    "sg:phone":"+1 203 438 5740",
    "sg:postcode":"06877",
    "sg:province":"CT",
    "wof:name":"National Education Assn",
    "wof:placetype":"venue"
},
  "geometry": {"coordinates":[-73.45584100000001,41.270208],"type":"Point"}
}