{
  "type": "Feature",
  "properties": {
    "iso:country":"US",
    "sg:address":"114 W Rutland Rd",
    "sg:city":"Milford",
    "sg:classifiers":[
        {
            "category":"Insurance",
            "subcategory":"Insurance Agent",
            "type":"Services"
        }
    ],
    "sg:phone":"+1 203 877 3710",
    "sg:postcode":"06461",
    "sg:province":"CT",
    "sg:tags":[
        "processing"
    ],
    "wof:name":"Rycon Medical Claims Prcssng",
    "wof:placetype":"venue"
},
  "geometry": {"coordinates":[-73.085825,41.230491],"type":"Point"}
}