{
  "type": "Feature",
  "properties": {
    "iso:country":"US",
    "sg:address":"241 Grandview Ave",
    "sg:city":"Hamden",
    "sg:classifiers":[
        {
            "category":"Professional",
            "type":"Services"
        }
    ],
    "sg:phone":"+1 203 288 6144",
    "sg:postcode":"06514",
    "sg:province":"CT",
    "sg:tags":[
        "establishment"
    ],
    "wof:name":"David J D'Agostino Freelance",
    "wof:placetype":"venue"
},
  "geometry": {"coordinates":[-72.929393,41.360512],"type":"Point"}
}