{
  "type": "Feature",
  "properties": {
    "iso:country":"US",
    "sg:address":"410 Ridge Rd",
    "sg:city":"Middletown",
    "sg:classifiers":[
        {
            "category":"Professional",
            "subcategory":"Business Services",
            "type":"Services"
        }
    ],
    "sg:phone":"+1   ",
    "sg:postcode":"06457",
    "sg:province":"CT",
    "wof:name":"McGan Technology Inc",
    "wof:placetype":"venue"
},
  "geometry": {"coordinates":[-72.64241199999999,41.536442],"type":"Point"}
}