{
  "type": "Feature",
  "properties": {
    "addr:full":"10 Great Hill Rd Naugatuck CT 06770",
    "addr:housenumber":"10",
    "addr:postcode":"06770",
    "addr:street":"Great Hill Rd Naugatuck Ct",
    "iso:country":"US",
    "sg:address":"10 Great Hill Rd",
    "sg:city":"Naugatuck",
    "sg:classifiers":[
        {
            "category":"Manufacturing",
            "subcategory":"Glass & Minerals",
            "type":"Manufacturing & Wholesale Goods"
        }
    ],
    "sg:phone":"+1 203 723 6681",
    "sg:postcode":"06770",
    "sg:province":"CT",
    "sg:tags":[
        "container"
    ],
    "wof:name":"Lerman Container Corp",
    "wof:placetype":"venue"
},
  "geometry": {"coordinates":[-73.02163,41.505153],"type":"Point"}
}