{
  "type": "Feature",
  "properties": {
    "iso:country":"US",
    "sg:address":"285 Congress St",
    "sg:city":"Bridgeport",
    "sg:classifiers":[
        {
            "category":"Professional",
            "subcategory":"Business Services",
            "type":"Services"
        }
    ],
    "sg:phone":"+1   ",
    "sg:postcode":"06604",
    "sg:province":"CT",
    "wof:name":"Curcio Bail Bonds",
    "wof:placetype":"venue"
},
  "geometry": {"coordinates":[-73.192649,41.181261],"type":"Point"}
}