{
  "type": "Feature",
  "properties": {
    "addr:full":"1244 Storrs Rd Storrs Mansfield CT 06268",
    "addr:housenumber":"1244",
    "addr:postcode":"06268",
    "addr:street":"Storrs Rd;Mansfield Ct",
    "iso:country":"US",
    "sg:address":"1244 Storrs Rd",
    "sg:city":"Storrs Mansfield",
    "sg:classifiers":[
        {
            "category":"Sports & Exercise",
            "subcategory":"Gym",
            "type":"Entertainment"
        }
    ],
    "sg:phone":"+1   ",
    "sg:postcode":"06268",
    "sg:province":"CT",
    "sg:tags":[
        "fitness",
        "physical",
        "facility"
    ],
    "wof:name":"Curves For Wmen Strrs-Mnsfield",
    "wof:placetype":"venue"
},
  "geometry": {"coordinates":[-72.24397,41.804781],"type":"Point"}
}