{
  "type": "Feature",
  "properties": {
    "addr:full":"465 S Main St Cheshire CT 06410",
    "addr:housenumber":"465",
    "addr:postcode":"06410",
    "addr:street":"S Main St",
    "iso:country":"US",
    "sg:address":"465 S Main St",
    "sg:city":"Cheshire",
    "sg:classifiers":[
        {
            "category":"Professional",
            "subcategory":"Management & Consulting",
            "type":"Services"
        }
    ],
    "sg:phone":"+1   ",
    "sg:postcode":"06410",
    "sg:province":"CT",
    "sg:tags":[
        "consultant",
        "real estate"
    ],
    "wof:name":"Bernice A Hill Realtor",
    "wof:placetype":"venue"
},
  "geometry": {"coordinates":[-72.90449700000001,41.490814],"type":"Point"}
}