{
  "type": "Feature",
  "properties": {
    "iso:country":"US",
    "sg:address":"2 Amity Rd",
    "sg:city":"New Haven",
    "sg:classifiers":[
        {
            "category":"Retail",
            "subcategory":"Auto Rental",
            "type":"Services"
        }
    ],
    "sg:phone":"+1 203 397 4999",
    "sg:postcode":"06515",
    "sg:province":"CT",
    "sg:tags":[
        "renting",
        "automobile"
    ],
    "wof:name":"Enterprise Rent-A-Car",
    "wof:placetype":"venue"
},
  "geometry": {"coordinates":[-72.97709399999999,41.33488],"type":"Point"}
}