{
  "type": "Feature",
  "properties": {
    "addr:full":"59 Highland St Hartford CT 06119",
    "addr:housenumber":"59",
    "addr:postcode":"06119",
    "addr:street":"Highland St",
    "iso:country":"US",
    "sg:address":"59 Highland St",
    "sg:city":"Hartford",
    "sg:classifiers":[
        {
            "category":"Personal",
            "subcategory":"Beauty Salon",
            "type":"Services"
        }
    ],
    "sg:phone":"+1   ",
    "sg:postcode":"06119",
    "sg:province":"CT",
    "sg:tags":[
        "shop"
    ],
    "wof:name":"Merrymakers Event Experts Ll",
    "wof:placetype":"venue"
},
  "geometry": {"coordinates":[-72.718052,41.765499],"type":"Point"}
}