{
  "type": "Feature",
  "properties": {
    "iso:country":"US",
    "sg:address":"15 Nott Ln",
    "sg:city":"Essex",
    "sg:classifiers":[
        {
            "category":"Professional",
            "subcategory":"Business Services",
            "type":"Services"
        }
    ],
    "sg:phone":"+1   ",
    "sg:postcode":"06426",
    "sg:province":"CT",
    "wof:name":"Richardson Nncy N Jwly Apprser",
    "wof:placetype":"venue"
},
  "geometry": {"coordinates":[-72.390114,41.351511],"type":"Point"}
}