{
  "type": "Feature",
  "properties": {
    "addr:full":"6 N Branch Rd Newtown CT 06470",
    "addr:housenumber":"6",
    "addr:postcode":"06470",
    "addr:street":"N Branch Rd",
    "iso:country":"US",
    "sg:address":"6 N Branch Rd",
    "sg:city":"Newtown",
    "sg:classifiers":[
        {
            "category":"Professional",
            "subcategory":"Management & Consulting",
            "type":"Services"
        }
    ],
    "sg:phone":"+1 203 426 4097",
    "sg:postcode":"06470",
    "sg:province":"CT",
    "sg:tags":[
        "consultant",
        "business"
    ],
    "wof:name":"North Branch Resources LLC",
    "wof:placetype":"venue"
},
  "geometry": {"coordinates":[-73.334744,41.377315],"type":"Point"}
}