{
  "type": "Feature",
  "properties": {
    "iso:country":"US",
    "sg:address":"938 King St",
    "sg:city":"Rye Brook",
    "sg:classifiers":[
        {
            "category":"Government",
            "subcategory":"Office",
            "type":"Public Place"
        }
    ],
    "sg:phone":"+1 914 939 1257",
    "sg:postcode":"10573",
    "sg:province":"CT",
    "sg:tags":[
        "city",
        "taxation"
    ],
    "wof:name":"Rye Brook Treasurer",
    "wof:placetype":"venue"
},
  "geometry": {"coordinates":[-73.67084800000001,41.029233],"type":"Point"}
}