{
  "type": "Feature",
  "properties": {
    "iso:country":"US",
    "sg:address":"21 Toelles Rd",
    "sg:city":"Wallingford",
    "sg:classifiers":[
        {
            "category":"Manufacturing",
            "subcategory":"Metals",
            "type":"Manufacturing & Wholesale Goods"
        }
    ],
    "sg:phone":"+1 203 265 6731",
    "sg:postcode":"06492",
    "sg:province":"CT",
    "sg:tags":[
        "rolling",
        "extruding",
        "drawing"
    ],
    "sg:website":"www.ametekmetals.com",
    "wof:name":"Ametek",
    "wof:placetype":"venue"
},
  "geometry": {"coordinates":[-72.840171,41.428944],"type":"Point"}
}