{
  "type": "Feature",
  "properties": {
    "addr:full":"70 Bradley Rd Woodbridge CT 06525",
    "addr:housenumber":"70",
    "addr:postcode":"06525",
    "addr:street":"Bradley Rd",
    "iso:country":"US",
    "sg:address":"70 Bradley Rd",
    "sg:city":"Woodbridge",
    "sg:classifiers":[
        {
            "category":"Restaurant",
            "type":"Food & Drink"
        }
    ],
    "sg:phone":"+1 203 387 0299",
    "sg:postcode":"06525",
    "sg:province":"CT",
    "sg:tags":[
        "caterer"
    ],
    "wof:name":"Sholom Caterers LTD",
    "wof:placetype":"venue"
},
  "geometry": {"coordinates":[-72.978179,41.344541],"type":"Point"}
}