{
  "type": "Feature",
  "properties": {
    "addr:full":"120 Old W Mountain Rd Ridgefield CT 06877",
    "addr:housenumber":"120",
    "addr:postcode":"06877",
    "addr:street":"Old W Mountain Rd",
    "iso:country":"US",
    "sg:address":"120 Old W Mountain Rd",
    "sg:city":"Ridgefield",
    "sg:classifiers":[
        {
            "category":"Professional",
            "type":"Services"
        },
        {
            "category":"Professional",
            "subcategory":"Computer Services",
            "type":"Services"
        }
    ],
    "sg:phone":"+1 203 431 2920",
    "sg:postcode":"06877",
    "sg:province":"CT",
    "sg:tags":[
        "establishment",
        "related"
    ],
    "wof:name":"West Mountain Systems Inc",
    "wof:placetype":"venue"
},
  "geometry": {"coordinates":[-73.52913599999999,41.303489],"type":"Point"}
}