{
  "type": "Feature",
  "properties": {
    "addr:full":"2984 Fairfield Ave Bridgeport CT 06605",
    "addr:housenumber":"2984",
    "addr:postcode":"06605",
    "addr:street":"Fairfield Ave",
    "iso:country":"US",
    "sg:address":"2984 Fairfield Ave",
    "sg:city":"Bridgeport",
    "sg:classifiers":[
        {
            "category":"Shopping",
            "subcategory":"Clothing, Apparel, & Fashions",
            "type":"Retail Goods"
        }
    ],
    "sg:phone":"+1 203 333 6308",
    "sg:postcode":"06605",
    "sg:province":"CT",
    "sg:tags":[
        "item",
        "boutique"
    ],
    "wof:name":"Arts & Flowers On The Avenue",
    "wof:placetype":"venue"
},
  "geometry": {"coordinates":[-73.228877,41.155999],"type":"Point"}
}