{
  "type": "Feature",
  "properties": {
    "iso:country":"US",
    "sg:address":"28 Cassway Rd",
    "sg:city":"Woodbridge",
    "sg:classifiers":[
        {
            "category":"Building & Trades",
            "subcategory":"Construction",
            "type":"Services"
        }
    ],
    "sg:phone":"+1 203 393 0649",
    "sg:postcode":"06525",
    "sg:province":"CT",
    "sg:tags":[
        "painter"
    ],
    "wof:name":"DRI Contract Svc",
    "wof:placetype":"venue"
},
  "geometry": {"coordinates":[-73.000896,41.38027],"type":"Point"}
}