{
  "type": "Feature",
  "properties": {
    "iso:country":"US",
    "sg:address":"1468 Baldwin St",
    "sg:city":"Waterbury",
    "sg:classifiers":[
        {
            "category":"Professional",
            "subcategory":"Computer Services",
            "type":"Services"
        }
    ],
    "sg:phone":"+1 203 755 5541",
    "sg:postcode":"06706",
    "sg:province":"CT",
    "sg:tags":[
        "repair"
    ],
    "wof:name":"Don Carlos Peripherel's",
    "wof:placetype":"venue"
},
  "geometry": {"coordinates":[-73.035144,41.532555],"type":"Point"}
}