{
  "type": "Feature",
  "properties": {
    "iso:country":"US",
    "sg:address":"110 Whitney Ave",
    "sg:city":"New Haven",
    "sg:classifiers":[
        {
            "category":"Health Services",
            "subcategory":"Health Practitioner",
            "type":"Services"
        }
    ],
    "sg:phone":"+1   ",
    "sg:postcode":"06510",
    "sg:province":"CT",
    "wof:name":"Charkow Carol Lcsw",
    "wof:placetype":"venue"
},
  "geometry": {"coordinates":[-72.921755,41.313423],"type":"Point"}
}