{
  "type": "Feature",
  "properties": {
    "addr:full":"243 Grahaber Rd Tolland CT 06084",
    "addr:housenumber":"243",
    "addr:postcode":"06084",
    "addr:street":"Grahaber Rd Tolland Ct",
    "iso:country":"US",
    "sg:address":"243 Grahaber Rd",
    "sg:city":"Tolland",
    "sg:classifiers":[
        {
            "category":"Health Services",
            "subcategory":"Clinic",
            "type":"Services"
        }
    ],
    "sg:phone":"+1   ",
    "sg:postcode":"06084",
    "sg:province":"CT",
    "sg:tags":[
        "home",
        "care"
    ],
    "wof:name":"Angels Visiting",
    "wof:placetype":"venue"
},
  "geometry": {"coordinates":[-72.42783799999999,41.908103],"type":"Point"}
}