{
  "type": "Feature",
  "properties": {
    "addr:full":"108 Geer Ave Norwich CT 06360",
    "addr:housenumber":"108",
    "addr:postcode":"06360",
    "addr:street":"Geer Ave",
    "iso:country":"US",
    "sg:address":"108 Geer Ave",
    "sg:city":"Norwich",
    "sg:classifiers":[
        {
            "category":"Social Services",
            "type":"Services"
        }
    ],
    "sg:phone":"+1   ",
    "sg:postcode":"06360",
    "sg:province":"CT",
    "wof:name":"Order of Alhambra",
    "wof:placetype":"venue"
},
  "geometry": {"coordinates":[-72.08859099999999,41.514514],"type":"Point"}
}