{
  "type": "Feature",
  "properties": {
    "addr:full":"15 International Dr East Granby CT 06026",
    "addr:housenumber":"15",
    "addr:postcode":"06026",
    "addr:street":"International Dr",
    "iso:country":"US",
    "sg:address":"15 International Dr",
    "sg:city":"East Granby",
    "sg:classifiers":[
        {
            "category":"Freight",
            "type":"Transportation"
        }
    ],
    "sg:phone":"+1 860 653 3450",
    "sg:postcode":"06026",
    "sg:province":"CT",
    "sg:tags":[
        "arrangement"
    ],
    "wof:name":"A N Deringer Inc",
    "wof:placetype":"venue"
},
  "geometry": {"coordinates":[-72.711276,41.92724],"type":"Point"}
}