{
  "type": "Feature",
  "properties": {
    "iso:country":"US",
    "sg:address":"124 Costello Rd",
    "sg:city":"Newington",
    "sg:classifiers":[
        {
            "category":"Wholesale",
            "subcategory":"Metals & Minerals",
            "type":"Manufacturing & Wholesale Goods"
        }
    ],
    "sg:phone":"+1 860 666 5634",
    "sg:postcode":"06111",
    "sg:province":"CT",
    "sg:tags":[
        "water",
        "works",
        "supply"
    ],
    "wof:name":"E P P C O A Ferguson Entp",
    "wof:placetype":"venue"
},
  "geometry": {"coordinates":[-72.72083600000001,41.656798],"type":"Point"}
}