{
  "type": "Feature",
  "properties": {
    "addr:full":"850 Hartford Tpke Waterford CT 06385",
    "addr:housenumber":"850",
    "addr:postcode":"06385",
    "addr:street":"Hartford Tpke Waterford Ct",
    "iso:country":"US",
    "sg:address":"850 Hartford Tpke",
    "sg:city":"Waterford",
    "sg:classifiers":[
        {
            "category":"Restaurant",
            "type":"Food & Drink"
        }
    ],
    "sg:menulink":"http://www.allmenus.com/ct/waterford/91050-dangelo-sandwich-shops/menu/",
    "sg:phone":"+1 860 444 1706",
    "sg:postcode":"06385",
    "sg:province":"CT",
    "sg:tags":[
        "wrap",
        "soup",
        "american",
        "sandwich",
        "salad"
    ],
    "wof:name":"D'Angelo Sandwich Shops",
    "wof:placetype":"venue"
},
  "geometry": {"coordinates":[-72.13932200000001,41.373381],"type":"Point"}
}