{
  "type": "Feature",
  "properties": {
    "addr:full":"284 Racebrook Rd Orange CT 06477",
    "addr:housenumber":"284",
    "addr:postcode":"06477",
    "addr:street":"Racebrook Rd",
    "iso:country":"US",
    "sg:address":"284 Racebrook Rd",
    "sg:city":"Orange",
    "sg:classifiers":[
        {
            "category":"Insurance",
            "subcategory":"Insurance Agent",
            "type":"Services"
        }
    ],
    "sg:phone":"+1 203 795 7080",
    "sg:postcode":"06477",
    "sg:province":"CT",
    "wof:name":"Leavitt Insurance Group Inc",
    "wof:placetype":"venue"
},
  "geometry": {"coordinates":[-72.999278,41.267226],"type":"Point"}
}