{
  "type": "Feature",
  "properties": {
    "addr:full":"17 Cedar St Stamford CT 06902",
    "addr:housenumber":"17",
    "addr:postcode":"06902",
    "addr:street":"Cedar St",
    "iso:country":"US",
    "sg:address":"17 Cedar St",
    "sg:city":"Stamford",
    "sg:classifiers":[
        {
            "category":"Professional",
            "subcategory":"Management & Consulting",
            "type":"Services"
        }
    ],
    "sg:phone":"+1   ",
    "sg:postcode":"06902",
    "sg:province":"CT",
    "wof:name":"Bev Max International Inc",
    "wof:placetype":"venue"
},
  "geometry": {"coordinates":[-73.53476499999999,41.043445],"type":"Point"}
}