{
  "type": "Feature",
  "properties": {
    "iso:country":"US",
    "sg:address":"24 Skyline Dr",
    "sg:city":"Farmington",
    "sg:classifiers":[
        {
            "category":"Building & Trades",
            "subcategory":"Construction",
            "type":"Services"
        }
    ],
    "sg:phone":"+1 860 232 9066",
    "sg:postcode":"06032",
    "sg:province":"CT",
    "sg:tags":[
        "nonresidential"
    ],
    "wof:name":"G & G Distributors",
    "wof:placetype":"venue"
},
  "geometry": {"coordinates":[-72.778075,41.728826],"type":"Point"}
}