{
  "type": "Feature",
  "properties": {
    "addr:full":"8 Apache Trl Westport CT 06880",
    "addr:housenumber":"8",
    "addr:postcode":"06880",
    "addr:street":"Apache Trl",
    "iso:country":"US",
    "sg:address":"8 Apache Trl",
    "sg:city":"Westport",
    "sg:classifiers":[
        {
            "category":"Professional",
            "subcategory":"Management & Consulting",
            "type":"Services"
        }
    ],
    "sg:phone":"+1   ",
    "sg:postcode":"06880",
    "sg:province":"CT",
    "sg:tags":[
        "consultant",
        "financial"
    ],
    "wof:name":"Goldfinger Investments LLC",
    "wof:placetype":"venue"
},
  "geometry": {"coordinates":[-73.336592,41.172592],"type":"Point"}
}