{
  "type": "Feature",
  "properties": {
    "iso:country":"US",
    "sg:address":"520 Hartford Tpke",
    "sg:city":"Vernon Rockville",
    "sg:classifiers":[
        {
            "category":"Health Services",
            "subcategory":"Health Practitioner",
            "type":"Services"
        }
    ],
    "sg:phone":"+1   ",
    "sg:postcode":"06066",
    "sg:province":"CT",
    "wof:name":"Integrated Rehabilitation",
    "wof:placetype":"venue"
},
  "geometry": {"coordinates":[-72.474834,41.831831],"type":"Point"}
}