{
  "type": "Feature",
  "properties": {
    "iso:country":"US",
    "sg:address":"5 Brinsmade Rd",
    "sg:city":"Hamden",
    "sg:classifiers":[
        {
            "category":"Professional",
            "subcategory":"Secretarial Services",
            "type":"Services"
        }
    ],
    "sg:phone":"+1   ",
    "sg:postcode":"06514",
    "sg:province":"CT",
    "sg:tags":[
        "reporting"
    ],
    "wof:name":"L Rainey",
    "wof:placetype":"venue"
},
  "geometry": {"coordinates":[-72.953754,41.366728],"type":"Point"}
}