{
  "type": "Feature",
  "properties": {
    "iso:country":"US",
    "sg:address":"667 Field St",
    "sg:city":"Naugatuck",
    "sg:classifiers":[
        {
            "category":"Building & Trades",
            "subcategory":"Construction",
            "type":"Services"
        }
    ],
    "sg:phone":"+1 203 729 6018",
    "sg:postcode":"06770",
    "sg:province":"CT",
    "sg:tags":[
        "concrete",
        "contractor"
    ],
    "wof:name":"1 & P Concrete Co",
    "wof:placetype":"venue"
},
  "geometry": {"coordinates":[-73.07744099999999,41.498027],"type":"Point"}
}