{
  "type": "Feature",
  "properties": {
    "addr:full":"3 Washington Ave Sandy Hook CT 06482",
    "addr:housenumber":"3",
    "addr:postcode":"06482",
    "addr:street":"Washington Ave;Hook Ct",
    "iso:country":"US",
    "sg:address":"3 Washington Ave",
    "sg:city":"Sandy Hook",
    "sg:classifiers":[
        {
            "category":"Retail",
            "subcategory":"Repair Shop",
            "type":"Services"
        }
    ],
    "sg:phone":"+1   ",
    "sg:postcode":"06482",
    "sg:province":"CT",
    "wof:name":"Grey Horse Gallery",
    "wof:placetype":"venue"
},
  "geometry": {"coordinates":[-73.280823,41.418828],"type":"Point"}
}