{
  "type": "Feature",
  "properties": {
    "iso:country":"US",
    "sg:address":"45 Maple St",
    "sg:city":"Seymour",
    "sg:classifiers":[
        {
            "category":"Food & Beverages",
            "subcategory":"Groceries & Convenience Stores",
            "type":"Retail Goods"
        },
        {
            "category":"Restaurant",
            "type":"Food & Drink"
        }
    ],
    "sg:phone":"+1 203 881 2591",
    "sg:postcode":"06483",
    "sg:province":"CT",
    "sg:tags":[
        "independent",
        "delicatessen"
    ],
    "wof:name":"John's Deli",
    "wof:placetype":"venue"
},
  "geometry": {"coordinates":[-73.071072,41.3886],"type":"Point"}
}