{
  "type": "Feature",
  "properties": {
    "iso:country":"US",
    "sg:address":"850 High Ridge Rd",
    "sg:city":"Stamford",
    "sg:classifiers":[
        {
            "category":"Home & Garden",
            "subcategory":"Home Furnishings",
            "type":"Retail Goods"
        }
    ],
    "sg:phone":"+1 203 329 0155",
    "sg:postcode":"06905",
    "sg:province":"CT",
    "sg:tags":[
        "floor",
        "covering"
    ],
    "wof:name":"Window Concepts LLC",
    "wof:placetype":"venue"
},
  "geometry": {"coordinates":[-73.547895,41.101143],"type":"Point"}
}