{
  "type": "Feature",
  "properties": {
    "addr:full":"481 Gold Star Hwy Groton CT 06340",
    "addr:housenumber":"481",
    "addr:postcode":"06340",
    "addr:street":"Gold Star Hwy Groton Ct",
    "iso:country":"US",
    "sg:address":"481 Gold Star Hwy",
    "sg:city":"Groton",
    "sg:classifiers":[
        {
            "category":"Professional",
            "subcategory":"Engineering",
            "type":"Services"
        }
    ],
    "sg:phone":"+1   ",
    "sg:postcode":"06340",
    "sg:province":"CT",
    "sg:tags":[
        "technical"
    ],
    "wof:name":"G P Federal Systems",
    "wof:placetype":"venue"
},
  "geometry": {"coordinates":[-72.05399300000001,41.372021],"type":"Point"}
}