{
  "type": "Feature",
  "properties": {
    "addr:full":"799 E Main St Stamford CT 06902",
    "addr:housenumber":"799",
    "addr:postcode":"06902",
    "addr:street":"E Main St",
    "iso:country":"US",
    "sg:address":"799 E Main St",
    "sg:city":"Stamford",
    "sg:classifiers":[
        {
            "category":"Autos & Motor Vehicles",
            "subcategory":"Auto Supplies",
            "type":"Retail Goods"
        }
    ],
    "sg:phone":"+1 203 406 1327",
    "sg:postcode":"06902",
    "sg:province":"CT",
    "sg:tags":[
        "automobile",
        "parts"
    ],
    "wof:name":"Autozone",
    "wof:placetype":"venue"
},
  "geometry": {"coordinates":[-73.529685,41.055334],"type":"Point"}
}