{
  "type": "Feature",
  "properties": {
    "addr:full":"11 Galilee Way Newtown CT 06470",
    "addr:housenumber":"11",
    "addr:postcode":"06470",
    "addr:street":"Galilee Way",
    "iso:country":"US",
    "sg:address":"11 Galilee Way",
    "sg:city":"Newtown",
    "sg:classifiers":[
        {
            "category":"Professional",
            "subcategory":"Management & Consulting",
            "type":"Services"
        }
    ],
    "sg:phone":"+1   ",
    "sg:postcode":"06470",
    "sg:province":"CT",
    "wof:name":"T3health",
    "wof:placetype":"venue"
},
  "geometry": {"coordinates":[-73.31505799999999,41.373811],"type":"Point"}
}