{
  "type": "Feature",
  "properties": {
    "iso:country":"US",
    "sg:address":"1785 Berlin Tpke",
    "sg:city":"Wethersfield",
    "sg:classifiers":[
        {
            "category":"Professional",
            "type":"Services"
        }
    ],
    "sg:phone":"+1 860 436 9991",
    "sg:postcode":"06109",
    "sg:province":"CT",
    "wof:name":"A & M-1 LLC",
    "wof:placetype":"venue"
},
  "geometry": {"coordinates":[-72.70216499999999,41.705121],"type":"Point"}
}