{
  "type": "Feature",
  "properties": {
    "addr:full":"96 Winsted Rd Torrington CT 06790",
    "addr:housenumber":"96",
    "addr:postcode":"06790",
    "addr:street":"Winsted Rd",
    "iso:country":"US",
    "sg:address":"96 Winsted Rd",
    "sg:city":"Torrington",
    "sg:classifiers":[
        {
            "category":"Professional",
            "subcategory":"Management & Consulting",
            "type":"Services"
        }
    ],
    "sg:phone":"+1   ",
    "sg:postcode":"06790",
    "sg:province":"CT",
    "wof:name":"Rich Armista Meterolgist",
    "wof:placetype":"venue"
},
  "geometry": {"coordinates":[-73.11853499999999,41.822326],"type":"Point"}
}