{
  "type": "Feature",
  "properties": {
    "addr:full":"464 Wolcott Rd Wolcott CT 06716",
    "addr:housenumber":"464",
    "addr:postcode":"06716",
    "addr:street":"Wolcott Rd Wolcott Ct",
    "iso:country":"US",
    "sg:address":"464 Wolcott Rd",
    "sg:city":"Wolcott",
    "sg:classifiers":[
        {
            "category":"Health Services",
            "subcategory":"Podiatrist",
            "type":"Services"
        }
    ],
    "sg:phone":"+1 203 879 3646",
    "sg:postcode":"06716",
    "sg:province":"CT",
    "wof:name":"Mc Hugh & Assoc",
    "wof:placetype":"venue"
},
  "geometry": {"coordinates":[-72.98968600000001,41.591551],"type":"Point"}
}