{
  "type": "Feature",
  "properties": {
    "iso:country":"US",
    "sg:address":"146 Danbury Rd",
    "sg:city":"Wilton",
    "sg:classifiers":[
        {
            "category":"Shopping",
            "subcategory":"Used Merchandise",
            "type":"Retail Goods"
        }
    ],
    "sg:phone":"+1 203 762 8359",
    "sg:postcode":"06897",
    "sg:province":"CT",
    "sg:tags":[
        "antique"
    ],
    "wof:name":"Old & New Collectibles",
    "wof:placetype":"venue"
},
  "geometry": {"coordinates":[-73.416051,41.180793],"type":"Point"}
}