{
  "type": "Feature",
  "properties": {
    "iso:country":"US",
    "sg:address":"136 Tower Rd",
    "sg:city":"White Plains",
    "sg:classifiers":[
        {
            "category":"Airport",
            "type":"Transportation"
        }
    ],
    "sg:phone":"+1   ",
    "sg:postcode":"10604",
    "sg:province":"NY",
    "sg:tags":[
        "repair",
        "airplane"
    ],
    "wof:name":"US Flight Service",
    "wof:placetype":"venue"
},
  "geometry": {"coordinates":[-73.716644,41.060685],"type":"Point"}
}