{
  "type": "Feature",
  "properties": {
    "iso:country":"US",
    "sg:address":"40 Commerce Park",
    "sg:city":"Milford",
    "sg:classifiers":[
        {
            "category":"Health Services",
            "subcategory":"Doctor",
            "type":"Services"
        }
    ],
    "sg:phone":"+1 203 876 1159",
    "sg:postcode":"06460",
    "sg:province":"CT",
    "sg:tags":[
        "physician",
        "surgeon"
    ],
    "wof:name":"Ear Nose & Throat Specialists",
    "wof:placetype":"venue"
},
  "geometry": {"coordinates":[-73.047787,41.228641],"type":"Point"}
}