{
  "type": "Feature",
  "properties": {
    "addr:full":"494 Union St Waterbury CT 06706",
    "addr:housenumber":"494",
    "addr:postcode":"06706",
    "addr:street":"Union St Waterbury Ct",
    "iso:country":"US",
    "sg:address":"494 Union St",
    "sg:city":"Waterbury",
    "sg:classifiers":[
        {
            "category":"Health Services",
            "subcategory":"Medical Lab",
            "type":"Services"
        }
    ],
    "sg:phone":"+1 203 575 0730",
    "sg:postcode":"06706",
    "sg:province":"CT",
    "sg:tags":[
        "laboratory"
    ],
    "wof:name":"Be Well Ctr",
    "wof:placetype":"venue"
},
  "geometry": {"coordinates":[-73.026459,41.546157],"type":"Point"}
}