{
  "type": "Feature",
  "properties": {
    "addr:full":"202 Salem Tpke Norwich CT 06360",
    "addr:housenumber":"202",
    "addr:postcode":"06360",
    "addr:street":"Salem Tpke",
    "iso:country":"US",
    "sg:address":"202 Salem Tpke",
    "sg:city":"Norwich",
    "sg:classifiers":[
        {
            "category":"Banks & Credit Unions",
            "subcategory":"Bank",
            "type":"Services"
        }
    ],
    "sg:phone":"+1 860 889 3246",
    "sg:postcode":"06360",
    "sg:province":"CT",
    "sg:tags":[
        "federal"
    ],
    "wof:name":"Norwich CT Federal Credit Un",
    "wof:placetype":"venue"
},
  "geometry": {"coordinates":[-72.11893999999999,41.508721],"type":"Point"}
}