{
  "type": "Feature",
  "properties": {
    "iso:country":"US",
    "sg:address":"16 Sudbury Way",
    "sg:city":"Avon",
    "sg:classifiers":[
        {
            "category":"Professional",
            "subcategory":"Management & Consulting",
            "type":"Services"
        }
    ],
    "sg:phone":"+1   ",
    "sg:postcode":"06001",
    "sg:province":"CT",
    "wof:name":"Martell Management LLC",
    "wof:placetype":"venue"
},
  "geometry": {"coordinates":[-72.861898,41.780794],"type":"Point"}
}