{
  "type": "Feature",
  "properties": {
    "iso:country":"US",
    "sg:address":"38 Country Ln",
    "sg:city":"Meriden",
    "sg:classifiers":[
        {
            "category":"Professional",
            "subcategory":"Management & Consulting",
            "type":"Services"
        }
    ],
    "sg:phone":"+1   ",
    "sg:postcode":"06451",
    "sg:province":"CT",
    "sg:tags":[
        "business"
    ],
    "wof:name":"Andre Inspires",
    "wof:placetype":"venue"
},
  "geometry": {"coordinates":[-72.85202,41.543638],"type":"Point"}
}