{
  "type": "Feature",
  "properties": {
    "iso:country":"US",
    "sg:address":"1651 E Main St",
    "sg:city":"Waterbury",
    "sg:classifiers":[
        {
            "category":"Professional",
            "type":"Services"
        }
    ],
    "sg:phone":"+1 203 841 0376",
    "sg:postcode":"06705",
    "sg:province":"CT",
    "wof:name":"East Side Wear",
    "wof:placetype":"venue"
},
  "geometry": {"coordinates":[-73.014235,41.546076],"type":"Point"}
}