{
  "type": "Feature",
  "properties": {
    "iso:country":"US",
    "sg:address":"47 Huckleberry Hill Rd",
    "sg:city":"Wilton",
    "sg:classifiers":[
        {
            "category":"Professional",
            "type":"Services"
        }
    ],
    "sg:phone":"+1 203 563 9445",
    "sg:postcode":"06897",
    "sg:province":"CT",
    "wof:name":"Digital Techniques LLC",
    "wof:placetype":"venue"
},
  "geometry": {"coordinates":[-73.452376,41.173455],"type":"Point"}
}