{
  "type": "Feature",
  "properties": {
    "iso:country":"US",
    "sg:address":"58 Cotswold Close",
    "sg:city":"Glastonbury",
    "sg:classifiers":[
        {
            "category":"Professional",
            "subcategory":"Business Services",
            "type":"Services"
        }
    ],
    "sg:phone":"+1   ",
    "sg:postcode":"06033",
    "sg:province":"CT",
    "wof:name":"Dlc Ventures LLC",
    "wof:placetype":"venue"
},
  "geometry": {"coordinates":[-72.578068,41.680238],"type":"Point"}
}