{
  "type": "Feature",
  "properties": {
    "addr:full":"22 Maple St Exn Darien CT 06820",
    "addr:housenumber":"22",
    "addr:postcode":"06820",
    "addr:street":"Maple St Exn Darien Ct",
    "iso:country":"US",
    "sg:address":"22 Maple St Exn",
    "sg:city":"Darien",
    "sg:classifiers":[
        {
            "category":"Building & Trades",
            "subcategory":"Construction",
            "type":"Services"
        }
    ],
    "sg:phone":"+1 203 655 6246",
    "sg:postcode":"06820",
    "sg:province":"CT",
    "sg:tags":[
        "plastering",
        "contractor"
    ],
    "wof:name":"Data Lath",
    "wof:placetype":"venue"
},
  "geometry": {"coordinates":[-73.490195,41.067197],"type":"Point"}
}