{
  "type": "Feature",
  "properties": {
    "addr:full":"185 Byram Shore Rd Greenwich CT 06830",
    "addr:housenumber":"185",
    "addr:postcode":"06830",
    "addr:street":"Byram Shore Rd",
    "iso:country":"US",
    "sg:address":"185 Byram Shore Rd",
    "sg:city":"Greenwich",
    "sg:classifiers":[
        {
            "category":"Real Estate",
            "subcategory":"Architect",
            "type":"Services"
        }
    ],
    "sg:phone":"+1 203 531 8540",
    "sg:postcode":"06830",
    "sg:province":"CT",
    "wof:name":"Robert C Mock & Assoc",
    "wof:placetype":"venue"
},
  "geometry": {"coordinates":[-73.65657299999999,40.989353],"type":"Point"}
}