{
  "type": "Feature",
  "properties": {
    "iso:country":"US",
    "sg:address":"238 S Water St",
    "sg:city":"Greenwich",
    "sg:classifiers":[
        {
            "category":"Manufacturing",
            "subcategory":"Metals",
            "type":"Manufacturing & Wholesale Goods"
        },
        {
            "category":"Manufacturing",
            "subcategory":"Jewelry",
            "type":"Manufacturing & Wholesale Goods"
        }
    ],
    "sg:phone":"+1 203 531 7902",
    "sg:postcode":"06830",
    "sg:province":"CT",
    "sg:tags":[
        "platinum",
        "buyer",
        "metals-precious",
        "silver",
        "gold"
    ],
    "wof:name":"Gpm International Inc",
    "wof:placetype":"venue"
},
  "geometry": {"coordinates":[-73.658823,40.995238],"type":"Point"}
}