{
  "type": "Feature",
  "properties": {
    "iso:country":"US",
    "sg:address":"15 Jobs Gate 1",
    "sg:city":"Portland",
    "sg:classifiers":[
        {
            "category":"Professional",
            "type":"Services"
        }
    ],
    "sg:phone":"+1 860 342 4123",
    "sg:postcode":"06480",
    "sg:province":"CT",
    "wof:name":"High Seas LLC",
    "wof:placetype":"venue"
},
  "geometry": {"coordinates":[-72.592598,41.567903],"type":"Point"}
}