{
  "type": "Feature",
  "properties": {
    "addr:full":"6 Stephanies Way Manchester CT 06040",
    "addr:housenumber":"6",
    "addr:postcode":"06040",
    "addr:street":"Stephanies Way",
    "iso:country":"US",
    "sg:address":"6 Stephanies Way",
    "sg:city":"Manchester",
    "sg:classifiers":[
        {
            "category":"Professional",
            "subcategory":"Computer Services",
            "type":"Services"
        }
    ],
    "sg:phone":"+1   ",
    "sg:postcode":"06040",
    "sg:province":"CT",
    "sg:tags":[
        "related"
    ],
    "wof:name":"Marx Consulting",
    "wof:placetype":"venue"
},
  "geometry": {"coordinates":[-72.496725,41.78149],"type":"Point"}
}