{
  "type": "Feature",
  "properties": {
    "addr:full":"1305 Post Rd Fairfield CT 06824",
    "addr:housenumber":"1305",
    "addr:postcode":"06824",
    "addr:street":"Post Rd",
    "iso:country":"US",
    "sg:address":"1305 Post Rd",
    "sg:city":"Fairfield",
    "sg:classifiers":[
        {
            "category":"Health Services",
            "subcategory":"Doctor",
            "type":"Services"
        }
    ],
    "sg:phone":"+1 203 259 7709",
    "sg:postcode":"06824",
    "sg:province":"CT",
    "sg:tags":[
        "hair",
        "replacement"
    ],
    "sg:website":"http://www.dricohen.com",
    "wof:name":"Ivan S Cohen M.D.",
    "wof:placetype":"venue"
},
  "geometry": {"coordinates":[-73.255194,41.142607],"type":"Point"}
}