{
  "type": "Feature",
  "properties": {
    "addr:full":"117 Boston Post Rd Waterford CT 06385",
    "addr:housenumber":"117",
    "addr:postcode":"06385",
    "addr:street":"Boston Post Rd",
    "iso:country":"US",
    "sg:address":"117 Boston Post Rd",
    "sg:city":"Waterford",
    "sg:classifiers":[
        {
            "category":"Wholesale",
            "subcategory":"Machinery & Supplies",
            "type":"Manufacturing & Wholesale Goods"
        }
    ],
    "sg:phone":"+1 860 437 3944",
    "sg:postcode":"06385",
    "sg:province":"CT",
    "sg:tags":[
        "equipment"
    ],
    "wof:name":"Essex Newbury North Contg",
    "wof:placetype":"venue"
},
  "geometry": {"coordinates":[-72.12533500000001,41.342085],"type":"Point"}
}