{
  "type": "Feature",
  "properties": {
    "iso:country":"US",
    "sg:address":"178 Main St",
    "sg:city":"Norwalk",
    "sg:classifiers":[
        {
            "category":"Shopping",
            "subcategory":"Discount & Variety Stores",
            "type":"Retail Goods"
        }
    ],
    "sg:phone":"+1 203 847 5694",
    "sg:postcode":"06851",
    "sg:province":"CT",
    "wof:name":"In & Out Varieties",
    "wof:placetype":"venue"
},
  "geometry": {"coordinates":[-73.419664,41.125896],"type":"Point"}
}