{
  "type": "Feature",
  "properties": {
    "iso:country":"US",
    "sg:address":"80 S Orchard St",
    "sg:city":"Wallingford",
    "sg:classifiers":[
        {
            "category":"Education",
            "subcategory":"Special Training",
            "type":"Public Place"
        }
    ],
    "sg:phone":"+1   ",
    "sg:postcode":"06492",
    "sg:province":"CT",
    "sg:tags":[
        "consulting",
        "business"
    ],
    "wof:name":"Partners In Education",
    "wof:placetype":"venue"
},
  "geometry": {"coordinates":[-72.822337,41.453962],"type":"Point"}
}