{
  "type": "Feature",
  "properties": {
    "addr:full":"98 W Hill Rd Stamford CT 06902",
    "addr:housenumber":"98",
    "addr:postcode":"06902",
    "addr:street":"W Hill Rd",
    "iso:country":"US",
    "sg:address":"98 W Hill Rd",
    "sg:city":"Stamford",
    "sg:classifiers":[
        {
            "category":"Professional",
            "subcategory":"Advertising",
            "type":"Services"
        }
    ],
    "sg:phone":"+1   ",
    "sg:postcode":"06902",
    "sg:province":"CT",
    "sg:tags":[
        "outdoor"
    ],
    "wof:name":"Transpad",
    "wof:placetype":"venue"
},
  "geometry": {"coordinates":[-73.56580200000001,41.068168],"type":"Point"}
}