{
  "type": "Feature",
  "properties": {
    "iso:country":"US",
    "sg:address":"23 Grennan Rd",
    "sg:city":"Hartford",
    "sg:classifiers":[
        {
            "category":"Professional",
            "type":"Services"
        }
    ],
    "sg:phone":"+1 860 521 2958",
    "sg:postcode":"06107",
    "sg:province":"CT",
    "wof:name":"Bateau Channel LLC",
    "wof:placetype":"venue"
},
  "geometry": {"coordinates":[-72.750207,41.760442],"type":"Point"}
}