{
  "type": "Feature",
  "properties": {
    "addr:full":"451 Meriden Rd Waterbury CT 06705",
    "addr:housenumber":"451",
    "addr:postcode":"06705",
    "addr:street":"Meriden Rd",
    "iso:country":"US",
    "sg:address":"451 Meriden Rd",
    "sg:city":"Waterbury",
    "sg:classifiers":[
        {
            "category":"Real Estate",
            "subcategory":"Real Estate Agent",
            "type":"Services"
        }
    ],
    "sg:phone":"+1 203 759 0939",
    "sg:postcode":"06705",
    "sg:province":"CT",
    "sg:website":"www.911home.com",
    "wof:name":"A Home Connection",
    "wof:placetype":"venue"
},
  "geometry": {"coordinates":[-73.003839,41.552432],"type":"Point"}
}