{
  "type": "Feature",
  "properties": {
    "addr:full":"31 Ceil Rd Trumbull CT 06611",
    "addr:housenumber":"31",
    "addr:postcode":"06611",
    "addr:street":"Ceil Rd",
    "iso:country":"US",
    "sg:address":"31 Ceil Rd",
    "sg:city":"Trumbull",
    "sg:classifiers":[
        {
            "category":"Real Estate",
            "subcategory":"Real Estate Agent",
            "type":"Services"
        }
    ],
    "sg:phone":"+1 203 374 9542",
    "sg:postcode":"06611",
    "sg:province":"CT",
    "sg:tags":[
        "appraiser"
    ],
    "wof:name":"Harriet Busker",
    "wof:placetype":"venue"
},
  "geometry": {"coordinates":[-73.244309,41.231931],"type":"Point"}
}