{
  "type": "Feature",
  "properties": {
    "addr:full":"480 Wolcott St Bristol CT 06010",
    "addr:housenumber":"480",
    "addr:postcode":"06010",
    "addr:street":"Wolcott St",
    "iso:country":"US",
    "sg:address":"480 Wolcott St",
    "sg:city":"Bristol",
    "sg:classifiers":[
        {
            "category":"Education",
            "subcategory":"School",
            "type":"Public Place"
        }
    ],
    "sg:phone":"+1 860 584 7732",
    "sg:postcode":"06010",
    "sg:province":"CT",
    "sg:tags":[
        "high"
    ],
    "wof:name":"Bristol Central High School",
    "wof:placetype":"venue"
},
  "geometry": {"coordinates":[-72.959012,41.660241],"type":"Point"}
}