{
  "type": "Feature",
  "properties": {
    "addr:full":"533 Allyndale Dr Stratford CT 06614",
    "addr:housenumber":"533",
    "addr:postcode":"06614",
    "addr:street":"Allyndale Dr",
    "iso:country":"US",
    "sg:address":"533 Allyndale Dr",
    "sg:city":"Stratford",
    "sg:classifiers":[
        {
            "category":"Professional",
            "subcategory":"Business Services",
            "type":"Services"
        }
    ],
    "sg:phone":"+1   ",
    "sg:postcode":"06614",
    "sg:province":"CT",
    "wof:name":"Er Strategic Solutions LLC",
    "wof:placetype":"venue"
},
  "geometry": {"coordinates":[-73.128332,41.208586],"type":"Point"}
}