{
  "type": "Feature",
  "properties": {
    "iso:country":"US",
    "sg:address":"1 Mohegan Rd",
    "sg:city":"Uncasville",
    "sg:classifiers":[
        {
            "category":"Shopping",
            "subcategory":"Clothing, Apparel, & Fashions",
            "type":"Retail Goods"
        }
    ],
    "sg:phone":"+1 860 889 4080",
    "sg:postcode":"06340",
    "sg:province":"CT",
    "sg:tags":[
        "family"
    ],
    "wof:name":"Nostalgia LLC",
    "wof:placetype":"venue"
},
  "geometry": {"coordinates":[-72.00054299999999,41.328177],"type":"Point"}
}