{
  "type": "Feature",
  "properties": {
    "iso:country":"US",
    "sg:address":"115 Mountain Rd",
    "sg:city":"Suffield",
    "sg:classifiers":[
        {
            "category":"Autos & Motor Vehicles",
            "subcategory":"Automobile Sales",
            "type":"Retail Goods"
        }
    ],
    "sg:phone":"+1 860 668 8892",
    "sg:postcode":"06078",
    "sg:province":"CT",
    "sg:tags":[
        "used"
    ],
    "wof:name":"Suffield Auto Sales Inc",
    "wof:placetype":"venue"
},
  "geometry": {"coordinates":[-72.65207100000001,41.982155],"type":"Point"}
}