{
  "type": "Feature",
  "properties": {
    "iso:country":"US",
    "sg:address":"1943 Asylum Ave",
    "sg:city":"Hartford",
    "sg:classifiers":[
        {
            "category":"Education",
            "subcategory":"School",
            "type":"Public Place"
        }
    ],
    "sg:phone":"+1 860 233 1234",
    "sg:postcode":"06117",
    "sg:province":"CT",
    "sg:tags":[
        "executive"
    ],
    "wof:name":"Bugbee Elementary School",
    "wof:placetype":"venue"
},
  "geometry": {"coordinates":[-72.753789,41.778945],"type":"Point"}
}