{
  "type": "Feature",
  "properties": {
    "iso:country":"US",
    "sg:address":"21 Montauk Ave",
    "sg:city":"New London",
    "sg:classifiers":[
        {
            "category":"Health Services",
            "subcategory":"Doctor",
            "type":"Services"
        }
    ],
    "sg:phone":"+1   ",
    "sg:postcode":"06320",
    "sg:province":"CT",
    "sg:tags":[
        "physician"
    ],
    "wof:name":"Urologic Associates P C",
    "wof:placetype":"venue"
},
  "geometry": {"coordinates":[-72.105755,41.34905],"type":"Point"}
}