{
  "type": "Feature",
  "properties": {
    "iso:country":"US",
    "sg:address":"180 Boston Ave",
    "sg:city":"Bridgeport",
    "sg:classifiers":[
        {
            "category":"Organizations",
            "subcategory":"Religious Organization",
            "type":"Services"
        }
    ],
    "sg:phone":"+1 203 330 1676",
    "sg:postcode":"06610",
    "sg:province":"CT",
    "sg:tags":[
        "church"
    ],
    "wof:name":"Christian Greater Bridgeport",
    "wof:placetype":"venue"
},
  "geometry": {"coordinates":[-73.187191,41.202113],"type":"Point"}
}