{
  "type": "Feature",
  "properties": {
    "iso:country":"US",
    "sg:address":"372 Greenwich Ave",
    "sg:city":"Greenwich",
    "sg:classifiers":[
        {
            "category":"Restaurant",
            "type":"Food & Drink"
        }
    ],
    "sg:menulink":"http://www.allmenus.com/ct/greenwich/25538-figaro-bistro/menu/",
    "sg:phone":"+1 203 622 0018",
    "sg:postcode":"06830",
    "sg:province":"CT",
    "sg:tags":[
        "italian"
    ],
    "wof:name":"Figaro Bistro",
    "wof:placetype":"venue"
},
  "geometry": {"coordinates":[-73.62501399999999,41.022755],"type":"Point"}
}