{
  "type": "Feature",
  "properties": {
    "addr:full":"4 Bradley Ln Westport CT 06880",
    "addr:housenumber":"4",
    "addr:postcode":"06880",
    "addr:street":"Bradley Ln",
    "iso:country":"US",
    "sg:address":"4 Bradley Ln",
    "sg:city":"Westport",
    "sg:classifiers":[
        {
            "category":"Manufacturing",
            "subcategory":"Building Materials",
            "type":"Manufacturing & Wholesale Goods"
        }
    ],
    "sg:phone":"+1 203 227 0203",
    "sg:postcode":"06880",
    "sg:province":"CT",
    "sg:tags":[
        "mfg",
        "kitchen",
        "cabinet"
    ],
    "wof:name":"Bradley Barn",
    "wof:placetype":"venue"
},
  "geometry": {"coordinates":[-73.37478900000001,41.122156],"type":"Point"}
}