{
  "type": "Feature",
  "properties": {
    "iso:country":"US",
    "sg:address":"67 Stonehedge Dr S",
    "sg:city":"Greenwich",
    "sg:classifiers":[
        {
            "category":"Shopping",
            "subcategory":"Clothing, Apparel, & Fashions",
            "type":"Retail Goods"
        }
    ],
    "sg:phone":"+1 203 532 1888",
    "sg:postcode":"06831",
    "sg:province":"CT",
    "wof:name":"Little Lacey Childrens Wear",
    "wof:placetype":"venue"
},
  "geometry": {"coordinates":[-73.673998,41.042613],"type":"Point"}
}