{
  "type": "Feature",
  "properties": {
    "iso:country":"US",
    "sg:address":"3 Prospect Ct",
    "sg:city":"Brookfield",
    "sg:classifiers":[
        {
            "category":"Real Estate",
            "subcategory":"Real Estate Agent",
            "type":"Services"
        }
    ],
    "sg:phone":"+1 203 792 0000",
    "sg:postcode":"06804",
    "sg:province":"CT",
    "wof:name":"Morey Associates Inc",
    "wof:placetype":"venue"
},
  "geometry": {"coordinates":[-73.40688,41.490412],"type":"Point"}
}