{
  "type": "Feature",
  "properties": {
    "iso:country":"US",
    "sg:address":"750 Main St",
    "sg:city":"Hartford",
    "sg:classifiers":[
        {
            "category":"Professional",
            "subcategory":"Computer Services",
            "type":"Services"
        }
    ],
    "sg:phone":"+1   ",
    "sg:postcode":"06103",
    "sg:province":"CT",
    "sg:tags":[
        "related",
        "programing",
        "custom"
    ],
    "wof:name":"Case Partners Inc",
    "wof:placetype":"venue"
},
  "geometry": {"coordinates":[-72.673857,41.764126],"type":"Point"}
}