{
  "type": "Feature",
  "properties": {
    "addr:full":"269 Main Ave Norwalk CT 06851",
    "addr:housenumber":"269",
    "addr:postcode":"06851",
    "addr:street":"Main Ave",
    "iso:country":"US",
    "sg:address":"269 Main Ave",
    "sg:city":"Norwalk",
    "sg:classifiers":[
        {
            "category":"Retail",
            "subcategory":"Auto Repair",
            "type":"Services"
        }
    ],
    "sg:phone":"+1 203 849 1000",
    "sg:postcode":"06851",
    "sg:province":"CT",
    "sg:tags":[
        "repairing",
        "automotive",
        "provides",
        "automobile"
    ],
    "wof:name":"Monro Muffler Brake & Svc",
    "wof:placetype":"venue"
},
  "geometry": {"coordinates":[-73.424414,41.134054],"type":"Point"}
}