{
  "type": "Feature",
  "properties": {
    "addr:full":"1 School St Bethel CT 06801",
    "addr:housenumber":"1",
    "addr:postcode":"06801",
    "addr:street":"School St Bethel Ct",
    "iso:country":"US",
    "sg:address":"1 School St",
    "sg:city":"Bethel",
    "sg:classifiers":[
        {
            "category":"Government",
            "subcategory":"Office",
            "type":"Public Place"
        }
    ],
    "sg:phone":"+1 203 794 8540",
    "sg:postcode":"06801",
    "sg:province":"CT",
    "sg:tags":[
        "city",
        "general",
        "program",
        "economic",
        "adm",
        "administrative"
    ],
    "wof:name":"Bethel Economic Development",
    "wof:placetype":"venue"
},
  "geometry": {"coordinates":[-73.414081,41.372194],"type":"Point"}
}