{
  "type": "Feature",
  "properties": {
    "iso:country":"US",
    "sg:address":"104 Waterbury Rd",
    "sg:city":"Prospect",
    "sg:classifiers":[
        {
            "category":"Personal",
            "type":"Services"
        }
    ],
    "sg:phone":"+1 203 758 6686",
    "sg:postcode":"06712",
    "sg:province":"CT",
    "sg:tags":[
        "program",
        "physical",
        "exercise",
        "fitness"
    ],
    "wof:name":"Curves For Women",
    "wof:placetype":"venue"
},
  "geometry": {"coordinates":[-72.989321,41.518001],"type":"Point"}
}