{
  "type": "Feature",
  "properties": {
    "addr:full":"104 Waterbury Rd Prospect CT 06712",
    "addr:housenumber":"104",
    "addr:postcode":"06712",
    "addr:street":"Waterbury Rd",
    "iso:country":"US",
    "sg:address":"104 Waterbury Rd",
    "sg:city":"Prospect",
    "sg:classifiers":[
        {
            "category":"Personal",
            "type":"Services"
        }
    ],
    "sg:phone":"+1 203 758 6686",
    "sg:postcode":"06712",
    "sg:province":"CT",
    "sg:tags":[
        "program",
        "physical",
        "exercise",
        "fitness"
    ],
    "wof:name":"Curves For Women",
    "wof:placetype":"venue"
},
  "geometry": {"coordinates":[-72.989321,41.518001],"type":"Point"}
}