{
  "type": "Feature",
  "properties": {
    "addr:full":"1 Whitman Dr Granby CT 06035",
    "addr:housenumber":"1",
    "addr:postcode":"06035",
    "addr:street":"Whitman Dr",
    "iso:country":"US",
    "sg:address":"1 Whitman Dr",
    "sg:city":"Granby",
    "sg:classifiers":[
        {
            "category":"Professional",
            "subcategory":"Computer Services",
            "type":"Services"
        }
    ],
    "sg:phone":"+1   ",
    "sg:postcode":"06035",
    "sg:province":"CT",
    "sg:tags":[
        "related"
    ],
    "wof:name":"Datacore Systems",
    "wof:placetype":"venue"
},
  "geometry": {"coordinates":[-72.800747,41.924561],"type":"Point"}
}