{
  "type": "Feature",
  "properties": {
    "addr:full":"466 Storrs Rd Mansfield Center CT 06250",
    "addr:housenumber":"466",
    "addr:postcode":"06250",
    "addr:street":"Storrs Rd Mansfield Center Ct",
    "iso:country":"US",
    "sg:address":"466 Storrs Rd",
    "sg:city":"Mansfield Center",
    "sg:classifiers":[
        {
            "category":"Restaurant",
            "type":"Food & Drink"
        }
    ],
    "sg:phone":"+1 860 450 1685",
    "sg:postcode":"06250",
    "sg:province":"CT",
    "sg:tags":[
        "pizza"
    ],
    "wof:name":"Roma Restaurant",
    "wof:placetype":"venue"
},
  "geometry": {"coordinates":[-72.193901,41.755901],"type":"Point"}
}