{
  "type": "Feature",
  "properties": {
    "iso:country":"US",
    "sg:address":"2 Forest Park Dr",
    "sg:city":"Farmington",
    "sg:classifiers":[
        {
            "category":"Insurance",
            "subcategory":"Insurance Agent",
            "type":"Services"
        }
    ],
    "sg:phone":"+1 860 674 0795",
    "sg:postcode":"06032",
    "sg:province":"CT",
    "wof:name":"Life Designs",
    "wof:placetype":"venue"
},
  "geometry": {"coordinates":[-72.83770800000001,41.736771],"type":"Point"}
}