{
  "type": "Feature",
  "properties": {
    "iso:country":"US",
    "sg:address":"33 Cornfield Rd",
    "sg:city":"Trumbull",
    "sg:classifiers":[
        {
            "category":"Real Estate",
            "subcategory":"Real Estate Agent",
            "type":"Services"
        }
    ],
    "sg:phone":"+1 203 377 6661",
    "sg:postcode":"06611",
    "sg:province":"CT",
    "wof:name":"Elmer R Craw Realtors",
    "wof:placetype":"venue"
},
  "geometry": {"coordinates":[-73.16232100000001,41.246038],"type":"Point"}
}