{
  "type": "Feature",
  "properties": {
    "addr:full":"162 Governor Trumbull Way Trumbull CT 06611",
    "addr:housenumber":"162",
    "addr:postcode":"06611",
    "addr:street":"Governor Trumbull Way",
    "iso:country":"US",
    "sg:address":"162 Governor Trumbull Way",
    "sg:city":"Trumbull",
    "sg:classifiers":[
        {
            "category":"Professional",
            "subcategory":"Business Services",
            "type":"Services"
        }
    ],
    "sg:phone":"+1   ",
    "sg:postcode":"06611",
    "sg:province":"CT",
    "wof:name":"Gw Enterprises LLC",
    "wof:placetype":"venue"
},
  "geometry": {"coordinates":[-73.23155300000001,41.275562],"type":"Point"}
}