{
  "type": "Feature",
  "properties": {
    "iso:country":"US",
    "sg:address":"17 Edlie Ave",
    "sg:city":"Norwalk",
    "sg:classifiers":[
        {
            "category":"Real Estate",
            "subcategory":"Real Estate Agent",
            "type":"Services"
        }
    ],
    "sg:phone":"+1 203 853 3126",
    "sg:postcode":"06855",
    "sg:province":"CT",
    "wof:name":"Ross Realty",
    "wof:placetype":"venue"
},
  "geometry": {"coordinates":[-73.407494,41.106302],"type":"Point"}
}