{
  "type": "Feature",
  "properties": {
    "iso:country":"US",
    "sg:address":"2044 Boston Ave",
    "sg:city":"Bridgeport",
    "sg:classifiers":[
        {
            "category":"Manufacturing",
            "subcategory":"Printing",
            "type":"Manufacturing & Wholesale Goods"
        }
    ],
    "sg:phone":"+1 203 366 4413",
    "sg:postcode":"06610",
    "sg:province":"CT",
    "sg:tags":[
        "commercial"
    ],
    "wof:name":"Action Signs",
    "wof:placetype":"venue"
},
  "geometry": {"coordinates":[-73.15581400000001,41.192505],"type":"Point"}
}