{
  "type": "Feature",
  "properties": {
    "iso:country":"US",
    "sg:address":"330 Middle St",
    "sg:city":"Bristol",
    "sg:classifiers":[
        {
            "category":"Autos & Motor Vehicles",
            "subcategory":"Fuel & Gas Station",
            "type":"Retail Goods"
        }
    ],
    "sg:phone":"+1 860 583 2200",
    "sg:postcode":"06010",
    "sg:province":"CT",
    "sg:tags":[
        "station",
        "gasoline"
    ],
    "wof:name":"Sport City Mobil",
    "wof:placetype":"venue"
},
  "geometry": {"coordinates":[-72.919151,41.66253],"type":"Point"}
}