{
  "type": "Feature",
  "properties": {
    "addr:full":"219 Dewey St Stratford CT 06615",
    "addr:housenumber":"219",
    "addr:postcode":"06615",
    "addr:street":"Dewey St",
    "iso:country":"US",
    "sg:address":"219 Dewey St",
    "sg:city":"Stratford",
    "sg:classifiers":[
        {
            "category":"Social Services",
            "type":"Services"
        }
    ],
    "sg:phone":"+1   ",
    "sg:postcode":"06615",
    "sg:province":"CT",
    "wof:name":"First Blessing Day Care",
    "wof:placetype":"venue"
},
  "geometry": {"coordinates":[-73.13992,41.177369],"type":"Point"}
}