{
  "type": "Feature",
  "properties": {
    "addr:full":"515 Cow Hill Rd Mystic CT 06355",
    "addr:housenumber":"515",
    "addr:postcode":"06355",
    "addr:street":"Cow Hill Rd",
    "iso:country":"US",
    "sg:address":"515 Cow Hill Rd",
    "sg:city":"Mystic",
    "sg:classifiers":[
        {
            "category":"Building & Trades",
            "subcategory":"Landscaping Services",
            "type":"Services"
        }
    ],
    "sg:phone":"+1 860 245 0257",
    "sg:postcode":"06355",
    "sg:province":"CT",
    "wof:name":"A C K Services",
    "wof:placetype":"venue"
},
  "geometry": {"coordinates":[-71.978416,41.38308],"type":"Point"}
}