{
  "type": "Feature",
  "properties": {
    "iso:country":"US",
    "sg:address":"252 White St",
    "sg:city":"Danbury",
    "sg:classifiers":[
        {
            "category":"Retail",
            "subcategory":"Auto Repair",
            "type":"Services"
        }
    ],
    "sg:phone":"+1   ",
    "sg:postcode":"06810",
    "sg:province":"CT",
    "sg:tags":[
        "automotive"
    ],
    "wof:name":"Colonial Auto Repair",
    "wof:placetype":"venue"
},
  "geometry": {"coordinates":[-73.436967,41.399444],"type":"Point"}
}