{
  "type": "Feature",
  "properties": {
    "iso:country":"US",
    "sg:address":"69 Prospect",
    "sg:city":"Plainfield",
    "sg:classifiers":[
        {
            "category":"Bakery",
            "type":"Food & Drink"
        }
    ],
    "sg:phone":"+1 860 564 4594",
    "sg:postcode":"06374",
    "sg:province":"CT",
    "wof:name":"Moosup Fruit & Produce",
    "wof:placetype":"venue"
},
  "geometry": {"coordinates":[-71.91770200000001,41.676399],"type":"Point"}
}