{
  "type": "Feature",
  "properties": {
    "addr:full":"44 Birchwood Dr Greenwich CT 06831",
    "addr:housenumber":"44",
    "addr:postcode":"06831",
    "addr:street":"Birchwood Dr",
    "iso:country":"US",
    "sg:address":"44 Birchwood Dr",
    "sg:city":"Greenwich",
    "sg:classifiers":[
        {
            "category":"Education",
            "subcategory":"Vocational School",
            "type":"Public Place"
        }
    ],
    "sg:phone":"+1   ",
    "sg:postcode":"06831",
    "sg:province":"CT",
    "sg:tags":[
        "processing",
        "datum"
    ],
    "wof:name":"Computer Guru",
    "wof:placetype":"venue"
},
  "geometry": {"coordinates":[-73.65486199999999,41.086704],"type":"Point"}
}