{
  "type": "Feature",
  "properties": {
    "iso:country":"US",
    "sg:address":"603 Steamboat Rd",
    "sg:city":"Greenwich",
    "sg:classifiers":[
        {
            "category":"Professional",
            "subcategory":"Business Services",
            "type":"Services"
        }
    ],
    "sg:phone":"+1 203 869 6612",
    "sg:postcode":"06830",
    "sg:province":"CT",
    "wof:name":"Winslow Associates",
    "wof:placetype":"venue"
},
  "geometry": {"coordinates":[-73.62212599999999,41.012644],"type":"Point"}
}