{
  "type": "Feature",
  "properties": {
    "addr:full":"78 Main St Enfield CT 06082",
    "addr:housenumber":"78",
    "addr:postcode":"06082",
    "addr:street":"Main St",
    "iso:country":"US",
    "sg:address":"78 Main St",
    "sg:city":"Enfield",
    "sg:classifiers":[
        {
            "category":"Bars & Pubs",
            "type":"Food & Drink"
        }
    ],
    "sg:phone":"+1 860 745 3009",
    "sg:postcode":"06082",
    "sg:province":"CT",
    "sg:tags":[
        "membership",
        "bar"
    ],
    "wof:name":"Greys",
    "wof:placetype":"venue"
},
  "geometry": {"coordinates":[-72.602182,41.998891],"type":"Point"}
}