{
  "type": "Feature",
  "properties": {
    "addr:full":"100 Grand St New Britain CT 06052",
    "addr:housenumber":"100",
    "addr:postcode":"06052",
    "addr:street":"Grand St",
    "iso:country":"US",
    "sg:address":"100 Grand St",
    "sg:city":"New Britain",
    "sg:classifiers":[
        {
            "category":"Health Services",
            "subcategory":"Health Practitioner",
            "type":"Services"
        }
    ],
    "sg:phone":"+1   ",
    "sg:postcode":"06052",
    "sg:province":"CT",
    "wof:name":"Family Planning Clinic",
    "wof:placetype":"venue"
},
  "geometry": {"coordinates":[-72.78713399999999,41.66197],"type":"Point"}
}