{
  "type": "Feature",
  "properties": {
    "addr:full":"2 Pine River Rd Wallingford CT 06492",
    "addr:housenumber":"2",
    "addr:postcode":"06492",
    "addr:street":"Pine River Rd",
    "iso:country":"US",
    "sg:address":"2 Pine River Rd",
    "sg:city":"Wallingford",
    "sg:classifiers":[
        {
            "category":"Real Estate",
            "subcategory":"Real Estate Agent",
            "type":"Services"
        }
    ],
    "sg:phone":"+1 203 269 3621",
    "sg:postcode":"06492",
    "sg:province":"CT",
    "wof:name":"Agents Real Estate",
    "wof:placetype":"venue"
},
  "geometry": {"coordinates":[-72.800686,41.408764],"type":"Point"}
}