{
  "type": "Feature",
  "properties": {
    "iso:country":"US",
    "sg:address":"205 Storrs Rd",
    "sg:city":"Mansfield Center",
    "sg:classifiers":[
        {
            "category":"Recreation",
            "subcategory":"Amusement Park",
            "type":"Entertainment"
        }
    ],
    "sg:phone":"+1 860 450 7565",
    "sg:postcode":"06250",
    "sg:province":"CT",
    "wof:name":"Excelsior Gaming Inc",
    "wof:placetype":"venue"
},
  "geometry": {"coordinates":[-72.2015,41.728699],"type":"Point"}
}