{
  "type": "Feature",
  "properties": {
    "iso:country":"US",
    "sg:address":"65 Locust Ave",
    "sg:city":"New Canaan",
    "sg:classifiers":[
        {
            "category":"Shopping",
            "subcategory":"Pharmacy",
            "type":"Retail Goods"
        }
    ],
    "sg:phone":"+1 800 253 4656",
    "sg:postcode":"06840",
    "sg:province":"NY",
    "wof:name":"Phar Express",
    "wof:placetype":"venue"
},
  "geometry": {"coordinates":[-73.490904,41.15007],"type":"Point"}
}