{
  "type": "Feature",
  "properties": {
    "addr:full":"288 Christian St Oxford CT 06478",
    "addr:housenumber":"288",
    "addr:postcode":"06478",
    "addr:street":"Christian St",
    "iso:country":"US",
    "sg:address":"288 Christian St",
    "sg:city":"Oxford",
    "sg:classifiers":[
        {
            "category":"Autos & Motor Vehicles",
            "subcategory":"Automobile Sales",
            "type":"Retail Goods"
        }
    ],
    "sg:phone":"+1 203 264 1101",
    "sg:postcode":"06478",
    "sg:province":"CT",
    "wof:name":"J P Associates",
    "wof:placetype":"venue"
},
  "geometry": {"coordinates":[-73.14088599999999,41.47705],"type":"Point"}
}