{
  "type": "Feature",
  "properties": {
    "iso:country":"US",
    "sg:address":"40 Herman Ave",
    "sg:city":"Darien",
    "sg:classifiers":[
        {
            "category":"Retail",
            "subcategory":"Animal Services",
            "type":"Services"
        }
    ],
    "sg:phone":"+1 203 655 3448",
    "sg:postcode":"06820",
    "sg:province":"CT",
    "wof:name":"Top Pup",
    "wof:placetype":"venue"
},
  "geometry": {"coordinates":[-73.48833399999999,41.074828],"type":"Point"}
}