{
  "type": "Feature",
  "properties": {
    "addr:full":"87 Greenwich Ave Greenwich CT 06830",
    "addr:housenumber":"87",
    "addr:postcode":"06830",
    "addr:street":"Greenwich Ave",
    "iso:country":"US",
    "sg:address":"87 Greenwich Ave",
    "sg:city":"Greenwich",
    "sg:classifiers":[
        {
            "category":"Shopping",
            "subcategory":"Optical Goods",
            "type":"Retail Goods"
        }
    ],
    "sg:phone":"+1 203 552 1072",
    "sg:postcode":"06830",
    "sg:province":"CT",
    "wof:name":"Trapp Optical",
    "wof:placetype":"venue"
},
  "geometry": {"coordinates":[-73.626289,41.02913],"type":"Point"}
}