{
  "type": "Feature",
  "properties": {
    "iso:country":"US",
    "sg:address":"55 Fotch St",
    "sg:city":"Stratford",
    "sg:classifiers":[
        {
            "category":"Education",
            "subcategory":"College",
            "type":"Public Place"
        },
        {
            "category":"Education",
            "subcategory":"School",
            "type":"Public Place"
        }
    ],
    "sg:phone":"+1 203 385 4188",
    "sg:postcode":"06615",
    "sg:province":"CT",
    "sg:website":"www.stratford.k12.ct.us",
    "wof:name":"Stratford Academy School",
    "wof:placetype":"venue"
},
  "geometry": {"coordinates":[-73.14318799999999,41.180201],"type":"Point"}
}