{
  "type": "Feature",
  "properties": {
    "iso:country":"US",
    "sg:address":"1300 Main St",
    "sg:city":"Watertown",
    "sg:classifiers":[
        {
            "category":"Restaurant",
            "type":"Food & Drink"
        }
    ],
    "sg:phone":"+1 860 274 1462",
    "sg:postcode":"06795",
    "sg:province":"CT",
    "sg:tags":[
        "eating",
        "product",
        "dairy"
    ],
    "wof:name":"Carvel Ice Cream",
    "wof:placetype":"venue"
},
  "geometry": {"coordinates":[-73.099981,41.58953],"type":"Point"}
}