{
  "type": "Feature",
  "properties": {
    "iso:country":"US",
    "sg:address":"75 Linden Ave",
    "sg:city":"Branford",
    "sg:classifiers":[
        {
            "category":"Professional",
            "subcategory":"Computer Services",
            "type":"Services"
        }
    ],
    "sg:phone":"+1   ",
    "sg:postcode":"06405",
    "sg:province":"CT",
    "sg:tags":[
        "information",
        "product",
        "distributes",
        "technology"
    ],
    "wof:name":"Independent Services Group Isg",
    "wof:placetype":"venue"
},
  "geometry": {"coordinates":[-72.80685099999999,41.256026],"type":"Point"}
}