{
  "type": "Feature",
  "properties": {
    "addr:full":"19 Elderberry Ln Shelton CT 06484",
    "addr:housenumber":"19",
    "addr:postcode":"06484",
    "addr:street":"Elderberry Ln",
    "iso:country":"US",
    "sg:address":"19 Elderberry Ln",
    "sg:city":"Shelton",
    "sg:classifiers":[
        {
            "category":"Professional",
            "subcategory":"Business Services",
            "type":"Services"
        }
    ],
    "sg:phone":"+1   ",
    "sg:postcode":"06484",
    "sg:province":"CT",
    "wof:name":"Cda Associates LLC",
    "wof:placetype":"venue"
},
  "geometry": {"coordinates":[-73.14849700000001,41.282212],"type":"Point"}
}