{
  "type": "Feature",
  "properties": {
    "iso:country":"US",
    "sg:address":"304 W Main St",
    "sg:city":"Avon",
    "sg:classifiers":[
        {
            "category":"Home & Garden",
            "subcategory":"Home Furnishings",
            "type":"Retail Goods"
        }
    ],
    "sg:phone":"+1 860 676 0524",
    "sg:postcode":"06001",
    "sg:province":"CT",
    "wof:name":"New England Traditions Ltd",
    "wof:placetype":"venue"
},
  "geometry": {"coordinates":[-72.855186,41.813043],"type":"Point"}
}