{
  "type": "Feature",
  "properties": {
    "addr:full":"19 Rimmon Hill Rd Woodbridge CT 06525",
    "addr:housenumber":"19",
    "addr:postcode":"06525",
    "addr:street":"Rimmon Hill Rd",
    "iso:country":"US",
    "sg:address":"19 Rimmon Hill Rd",
    "sg:city":"Woodbridge",
    "sg:classifiers":[
        {
            "category":"Communications",
            "type":"Services"
        }
    ],
    "sg:phone":"+1 203 407 8773",
    "sg:postcode":"06525",
    "sg:province":"CT",
    "wof:name":"Northeastern Sales Comm",
    "wof:placetype":"venue"
},
  "geometry": {"coordinates":[-73.040312,41.359537],"type":"Point"}
}