{
  "type": "Feature",
  "properties": {
    "addr:full":"52 Pocahontas Rd Redding CT 06896",
    "addr:housenumber":"52",
    "addr:postcode":"06896",
    "addr:street":"Pocahontas Rd",
    "iso:country":"US",
    "sg:address":"52 Pocahontas Rd",
    "sg:city":"Redding",
    "sg:classifiers":[
        {
            "category":"Building & Trades",
            "subcategory":"Landscaping Services",
            "type":"Services"
        }
    ],
    "sg:phone":"+1 203 938 3621",
    "sg:postcode":"06896",
    "sg:province":"CT",
    "wof:name":"Shade Trees",
    "wof:placetype":"venue"
},
  "geometry": {"coordinates":[-73.372012,41.344564],"type":"Point"}
}