{
  "type": "Feature",
  "properties": {
    "iso:country":"US",
    "sg:address":"25 Norwich-Westerly Rd",
    "sg:city":"North Stonington",
    "sg:classifiers":[
        {
            "category":"Personal",
            "type":"Services"
        }
    ],
    "sg:phone":"+1 860 396 3100",
    "sg:postcode":"06359",
    "sg:province":"CT",
    "sg:tags":[
        "management",
        "real estate"
    ],
    "wof:name":"Mashantcket Pquot Trbal Nation",
    "wof:placetype":"venue"
},
  "geometry": {"coordinates":[-71.856454,41.415821],"type":"Point"}
}