{
  "type": "Feature",
  "properties": {
    "addr:full":"130 US Hwy 6 Manchester CT 06040",
    "addr:housenumber":"130",
    "addr:postcode":"06040",
    "addr:street":"Us Hwy 6",
    "iso:country":"US",
    "sg:address":"130 US Hwy 6",
    "sg:city":"Manchester",
    "sg:classifiers":[
        {
            "category":"Wholesale",
            "subcategory":"Metals & Minerals",
            "type":"Manufacturing & Wholesale Goods"
        }
    ],
    "sg:phone":"+1   ",
    "sg:postcode":"06040",
    "sg:province":"CT",
    "sg:tags":[
        "distributor",
        "finished",
        "product",
        "semi",
        "manufacturer"
    ],
    "wof:name":"Aerospace Alloys Inc",
    "wof:placetype":"venue"
},
  "geometry": {"coordinates":[-72.51921299999999,41.776489],"type":"Point"}
}