{
  "type": "Feature",
  "properties": {
    "iso:country":"US",
    "sg:address":"144 Broad St",
    "sg:city":"Milford",
    "sg:classifiers":[
        {
            "category":"Personal",
            "subcategory":"Beauty Salon",
            "type":"Services"
        }
    ],
    "sg:phone":"+1   ",
    "sg:postcode":"06460",
    "sg:province":"CT",
    "wof:name":"Princess Hair Designers",
    "wof:placetype":"venue"
},
  "geometry": {"coordinates":[-73.061843,41.219528],"type":"Point"}
}