{
  "type": "Feature",
  "properties": {
    "addr:full":"16 Mashamoquet Rd Pomfret Center CT 06259",
    "addr:housenumber":"16",
    "addr:postcode":"06259",
    "addr:street":"Mashamoquet Rd Pomfret Center Ct",
    "iso:country":"US",
    "sg:address":"16 Mashamoquet Rd",
    "sg:city":"Pomfret Center",
    "sg:classifiers":[
        {
            "category":"Restaurant",
            "type":"Food & Drink"
        }
    ],
    "sg:phone":"+1 860 928 5566",
    "sg:postcode":"06259",
    "sg:province":"CT",
    "sg:tags":[
        "pizza"
    ],
    "wof:name":"Pizzaria 101 & Family Restaurant",
    "wof:placetype":"venue"
},
  "geometry": {"coordinates":[-72.046402,41.864399],"type":"Point"}
}