{
  "type": "Feature",
  "properties": {
    "iso:country":"US",
    "sg:address":"36 Perkins Rd",
    "sg:city":"Bethany",
    "sg:classifiers":[
        {
            "category":"Education",
            "subcategory":"Vocational School",
            "type":"Public Place"
        },
        {
            "category":"Shopping",
            "subcategory":"Computers & Home Electronics",
            "type":"Retail Goods"
        }
    ],
    "sg:phone":"+1 203 393 3006",
    "sg:postcode":"06524",
    "sg:province":"CT",
    "sg:tags":[
        "prepackaged",
        "training",
        "cu",
        "software"
    ],
    "sg:website":"www.tutorsandcomputers.com",
    "wof:name":"Tutors & Computers Inc",
    "wof:placetype":"venue"
},
  "geometry": {"coordinates":[-72.98070199999999,41.443249],"type":"Point"}
}