{
  "type": "Feature",
  "properties": {
    "iso:country":"US",
    "sg:address":"400 Quinnipiac Ave",
    "sg:city":"New Haven",
    "sg:classifiers":[
        {
            "category":"Wholesale",
            "subcategory":"Petroleum",
            "type":"Manufacturing & Wholesale Goods"
        }
    ],
    "sg:phone":"+1 203 469 6496",
    "sg:postcode":"06513",
    "sg:province":"CT",
    "sg:tags":[
        "pipe",
        "line",
        "company"
    ],
    "wof:name":"Buckeye Pipeline Co",
    "wof:placetype":"venue"
},
  "geometry": {"coordinates":[-72.88937,41.302312],"type":"Point"}
}