{
  "type": "Feature",
  "properties": {
    "addr:full":"138 Amity Rd New Haven CT 06525",
    "addr:housenumber":"138",
    "addr:postcode":"06525",
    "addr:street":"Amity Rd",
    "iso:country":"US",
    "sg:address":"138 Amity Rd",
    "sg:city":"New Haven",
    "sg:classifiers":[
        {
            "category":"Restaurant",
            "type":"Food & Drink"
        }
    ],
    "sg:menulink":"http://www.allmenus.com/ct/new-haven/258003-amity-brick-oven-pizza/menu/",
    "sg:phone":"+1 203 397 9300",
    "sg:postcode":"06525",
    "sg:province":"CT",
    "sg:tags":[
        "american",
        "pizza"
    ],
    "wof:name":"Amity Brick Oven Pizza",
    "wof:placetype":"venue"
},
  "geometry": {"coordinates":[-72.9802,41.338227],"type":"Point"}
}