{
  "type": "Feature",
  "properties": {
    "addr:full":"19 Geneva Rd Norwalk CT 06850",
    "addr:housenumber":"19",
    "addr:postcode":"06850",
    "addr:street":"Geneva Rd",
    "iso:country":"US",
    "sg:address":"19 Geneva Rd",
    "sg:city":"Norwalk",
    "sg:classifiers":[
        {
            "category":"Manufacturing",
            "subcategory":"Printing",
            "type":"Manufacturing & Wholesale Goods"
        }
    ],
    "sg:phone":"+1 203 838 4984",
    "sg:postcode":"06850",
    "sg:province":"CT",
    "sg:tags":[
        "multimedia"
    ],
    "wof:name":"Mc Glenagham Media Inc",
    "wof:placetype":"venue"
},
  "geometry": {"coordinates":[-73.45106,41.110309],"type":"Point"}
}