{
  "type": "Feature",
  "properties": {
    "iso:country":"US",
    "sg:address":"1066 Norwich-New London Tpke",
    "sg:city":"Uncasville",
    "sg:classifiers":[
        {
            "category":"Retail",
            "subcategory":"Repair Shop",
            "type":"Services"
        }
    ],
    "sg:phone":"+1   ",
    "sg:postcode":"06382",
    "sg:province":"CT",
    "sg:tags":[
        "equipment",
        "musical"
    ],
    "wof:name":"The Audio Clinic",
    "wof:placetype":"venue"
},
  "geometry": {"coordinates":[-72.107102,41.452652],"type":"Point"}
}