{
  "type": "Feature",
  "properties": {
    "iso:country":"US",
    "sg:address":"1066 Post Rd",
    "sg:city":"Darien",
    "sg:classifiers":[
        {
            "category":"Personal",
            "subcategory":"Beauty Salon",
            "type":"Services"
        }
    ],
    "sg:phone":"+1   ",
    "sg:postcode":"06820",
    "sg:province":"CT",
    "sg:tags":[
        "shop"
    ],
    "wof:name":"Williams & Warren",
    "wof:placetype":"venue"
},
  "geometry": {"coordinates":[-73.473568,41.073435],"type":"Point"}
}