{
  "type": "Feature",
  "properties": {
    "iso:country":"US",
    "sg:address":"415 Broad St",
    "sg:city":"Manchester",
    "sg:classifiers":[
        {
            "category":"Personal",
            "subcategory":"Beauty Salon",
            "type":"Services"
        }
    ],
    "sg:phone":"+1   ",
    "sg:postcode":"06040",
    "sg:province":"CT",
    "sg:tags":[
        "shop"
    ],
    "wof:name":"Regis Corporation",
    "wof:placetype":"venue"
},
  "geometry": {"coordinates":[-72.53313300000001,41.772859],"type":"Point"}
}