{
  "type": "Feature",
  "properties": {
    "addr:full":"255 Treadwell St Hamden CT 06517",
    "addr:housenumber":"255",
    "addr:postcode":"06517",
    "addr:street":"Treadwell St",
    "iso:country":"US",
    "sg:address":"255 Treadwell St",
    "sg:city":"Hamden",
    "sg:classifiers":[
        {
            "category":"Manufacturing",
            "subcategory":"Building Materials",
            "type":"Manufacturing & Wholesale Goods"
        }
    ],
    "sg:phone":"+1 203 288 4695",
    "sg:postcode":"06517",
    "sg:province":"CT",
    "sg:tags":[
        "mfg"
    ],
    "wof:name":"Wr Frohlich Woodworks",
    "wof:placetype":"venue"
},
  "geometry": {"coordinates":[-72.922217,41.352528],"type":"Point"}
}