{
  "type": "Feature",
  "properties": {
    "iso:country":"US",
    "sg:address":"48 Candlewood Mountain Rd",
    "sg:city":"New Milford",
    "sg:classifiers":[
        {
            "category":"Professional",
            "subcategory":"Management & Consulting",
            "type":"Services"
        }
    ],
    "sg:phone":"+1   ",
    "sg:postcode":"06776",
    "sg:province":"CT",
    "sg:tags":[
        "business"
    ],
    "wof:name":"Sterling Dimmitt Consulting",
    "wof:placetype":"venue"
},
  "geometry": {"coordinates":[-73.46145799999999,41.588449],"type":"Point"}
}