{
  "type": "Feature",
  "properties": {
    "iso:country":"US",
    "sg:address":"1 Highland Dr",
    "sg:city":"Danbury",
    "sg:classifiers":[
        {
            "category":"Retail",
            "subcategory":"Repair Shop",
            "type":"Services"
        }
    ],
    "sg:phone":"+1   ",
    "sg:postcode":"06811",
    "sg:province":"CT",
    "wof:name":"S O S Cleaning Service",
    "wof:placetype":"venue"
},
  "geometry": {"coordinates":[-73.48570599999999,41.426277],"type":"Point"}
}