{
  "type": "Feature",
  "properties": {
    "addr:full":"7100 Main St Trumbull CT 06611",
    "addr:housenumber":"7100",
    "addr:postcode":"06611",
    "addr:street":"Main St",
    "iso:country":"US",
    "sg:address":"7100 Main St",
    "sg:city":"Trumbull",
    "sg:classifiers":[
        {
            "category":"Professional",
            "subcategory":"Management & Consulting",
            "type":"Services"
        }
    ],
    "sg:phone":"+1   ",
    "sg:postcode":"06611",
    "sg:province":"CT",
    "sg:tags":[
        "nonphysical",
        "commercial",
        "business",
        "res"
    ],
    "wof:name":"Preusser Research Group Inc",
    "wof:placetype":"venue"
},
  "geometry": {"coordinates":[-73.24453099999999,41.293775],"type":"Point"}
}