{
  "type": "Feature",
  "properties": {
    "addr:full":"49 Laurel Ln Ridgefield CT 06877",
    "addr:housenumber":"49",
    "addr:postcode":"06877",
    "addr:street":"Laurel Ln",
    "iso:country":"US",
    "sg:address":"49 Laurel Ln",
    "sg:city":"Ridgefield",
    "sg:classifiers":[
        {
            "category":"Building & Trades",
            "subcategory":"Landscaping Services",
            "type":"Services"
        }
    ],
    "sg:phone":"+1 203 438 5477",
    "sg:postcode":"06877",
    "sg:province":"CT",
    "sg:tags":[
        "tree"
    ],
    "wof:name":"Edwin Backman Tree Service",
    "wof:placetype":"venue"
},
  "geometry": {"coordinates":[-73.471361,41.324899],"type":"Point"}
}