{
  "type": "Feature",
  "properties": {
    "addr:full":"701 N Colony Rd Wallingford CT 06492",
    "addr:housenumber":"701",
    "addr:postcode":"06492",
    "addr:street":"N Colony Rd",
    "iso:country":"US",
    "sg:address":"701 N Colony Rd",
    "sg:city":"Wallingford",
    "sg:classifiers":[
        {
            "category":"Food & Beverages",
            "subcategory":"Liquor & Beverages",
            "type":"Retail Goods"
        }
    ],
    "sg:phone":"+1 203 284 8776",
    "sg:postcode":"06492",
    "sg:province":"CT",
    "wof:name":"Wallingford Wine & Spirit Co",
    "wof:placetype":"venue"
},
  "geometry": {"coordinates":[-72.813458,41.475141],"type":"Point"}
}