{
  "type": "Feature",
  "properties": {
    "iso:country":"US",
    "sg:address":"4 Hoyt Rd",
    "sg:city":"Bethel",
    "sg:classifiers":[
        {
            "category":"Wholesale",
            "subcategory":"Machinery & Supplies",
            "type":"Manufacturing & Wholesale Goods"
        }
    ],
    "sg:phone":"+1 203 748 9233",
    "sg:postcode":"06801",
    "sg:province":"CT",
    "sg:tags":[
        "mason",
        "contractor"
    ],
    "wof:name":"B J Dolan Co Inc",
    "wof:placetype":"venue"
},
  "geometry": {"coordinates":[-73.388509,41.394005],"type":"Point"}
}