{
  "type": "Feature",
  "properties": {
    "iso:country":"US",
    "sg:address":"1 Fort Hill Rd",
    "sg:city":"Groton",
    "sg:classifiers":[
        {
            "category":"Personal",
            "subcategory":"Beauty Salon",
            "type":"Services"
        }
    ],
    "sg:phone":"+1   ",
    "sg:postcode":"06340",
    "sg:province":"CT",
    "sg:tags":[
        "shop"
    ],
    "wof:name":"Miracles Hair Salon",
    "wof:placetype":"venue"
},
  "geometry": {"coordinates":[-72.037684,41.346688],"type":"Point"}
}