{
  "type": "Feature",
  "properties": {
    "addr:full":"633 Clinton Ave Bridgeport CT 06605",
    "addr:housenumber":"633",
    "addr:postcode":"06605",
    "addr:street":"Clinton Ave",
    "iso:country":"US",
    "sg:address":"633 Clinton Ave",
    "sg:city":"Bridgeport",
    "sg:classifiers":[
        {
            "category":"Health Services",
            "subcategory":"Doctor",
            "type":"Services"
        }
    ],
    "sg:phone":"+1   ",
    "sg:postcode":"06605",
    "sg:province":"CT",
    "wof:name":"Shelton Dental",
    "wof:placetype":"venue"
},
  "geometry": {"coordinates":[-73.211793,41.176192],"type":"Point"}
}