{
  "type": "Feature",
  "properties": {
    "addr:full":"87 Whitfield St Guilford CT 06437",
    "addr:housenumber":"87",
    "addr:postcode":"06437",
    "addr:street":"Whitfield St",
    "iso:country":"US",
    "sg:address":"87 Whitfield St",
    "sg:city":"Guilford",
    "sg:classifiers":[
        {
            "category":"Professional",
            "subcategory":"Employment Agencies",
            "type":"Services"
        }
    ],
    "sg:phone":"+1   ",
    "sg:postcode":"06437",
    "sg:province":"CT",
    "wof:name":"Dunsmore & Associates Limited",
    "wof:placetype":"venue"
},
  "geometry": {"coordinates":[-72.683043,41.284017],"type":"Point"}
}