{
  "type": "Feature",
  "properties": {
    "addr:full":"26 Evergreen Rd Torrington CT 06790",
    "addr:housenumber":"26",
    "addr:postcode":"06790",
    "addr:street":"Evergreen Rd",
    "iso:country":"US",
    "sg:address":"26 Evergreen Rd",
    "sg:city":"Torrington",
    "sg:classifiers":[
        {
            "category":"Professional",
            "type":"Services"
        }
    ],
    "sg:phone":"+1 860 482 3617",
    "sg:postcode":"06790",
    "sg:province":"CT",
    "wof:name":"Technotherm International",
    "wof:placetype":"venue"
},
  "geometry": {"coordinates":[-73.103459,41.871944],"type":"Point"}
}