{
  "type": "Feature",
  "properties": {
    "addr:full":"20 Hale St Waterbury CT 06708",
    "addr:housenumber":"20",
    "addr:postcode":"06708",
    "addr:street":"Hale St Waterbury Ct",
    "iso:country":"US",
    "sg:address":"20 Hale St",
    "sg:city":"Waterbury",
    "sg:phone":"+1 203 754 7601",
    "sg:postcode":"06708",
    "sg:province":"CT",
    "sg:tags":[
        "gas"
    ],
    "wof:name":"Hocon Industrial Gas Inc",
    "wof:placetype":"venue"
},
  "geometry": {"coordinates":[-73.061289,41.562124],"type":"Point"}
}