{
  "type": "Feature",
  "properties": {
    "addr:full":"104 Fairmont Ave New Haven CT 06513",
    "addr:housenumber":"104",
    "addr:postcode":"06513",
    "addr:street":"Fairmont Ave",
    "iso:country":"US",
    "sg:address":"104 Fairmont Ave",
    "sg:city":"New Haven",
    "sg:classifiers":[
        {
            "category":"Organizations",
            "subcategory":"Religious Organization",
            "type":"Services"
        }
    ],
    "sg:phone":"+1 203 469 5134",
    "sg:postcode":"06513",
    "sg:province":"CT",
    "sg:tags":[
        "church"
    ],
    "sg:website":"www.walkoffaithchurch.com",
    "wof:name":"Walk Of Faith Church",
    "wof:placetype":"venue"
},
  "geometry": {"coordinates":[-72.893815,41.295245],"type":"Point"}
}