{
  "type": "Feature",
  "properties": {
    "addr:full":"540 Barnum Ave Bridgeport CT 06608",
    "addr:housenumber":"540",
    "addr:postcode":"06608",
    "addr:street":"Barnum Ave",
    "iso:country":"US",
    "sg:address":"540 Barnum Ave",
    "sg:city":"Bridgeport",
    "sg:classifiers":[
        {
            "category":"Autos & Motor Vehicles",
            "subcategory":"Boat Sales",
            "type":"Retail Goods"
        }
    ],
    "sg:phone":"+1 203 345 0114",
    "sg:postcode":"06608",
    "sg:province":"CT",
    "sg:tags":[
        "engine"
    ],
    "sg:website":"www.outboardelectric.org",
    "wof:name":"Outboard Electric Corp",
    "wof:placetype":"venue"
},
  "geometry": {"coordinates":[-73.17850799999999,41.186941],"type":"Point"}
}