{
  "type": "Feature",
  "properties": {
    "iso:country":"US",
    "sg:address":"54 Buckingham St",
    "sg:city":"Hartford",
    "sg:classifiers":[
        {
            "category":"Professional",
            "subcategory":"Management & Consulting",
            "type":"Services"
        }
    ],
    "sg:phone":"+1   ",
    "sg:postcode":"06106",
    "sg:province":"CT",
    "wof:name":"Pite Plus Marketing",
    "wof:placetype":"venue"
},
  "geometry": {"coordinates":[-72.67631,41.76016],"type":"Point"}
}