{
  "type": "Feature",
  "properties": {
    "addr:full":"39 Hazard Ave Enfield CT 06082",
    "addr:housenumber":"39",
    "addr:postcode":"06082",
    "addr:street":"Hazard Ave",
    "iso:country":"US",
    "sg:address":"39 Hazard Ave",
    "sg:city":"Enfield",
    "sg:classifiers":[
        {
            "category":"Restaurant",
            "type":"Food & Drink"
        },
        {
            "category":"Retail",
            "subcategory":"Event Space",
            "type":"Services"
        }
    ],
    "sg:phone":"+1 860 239 0004",
    "sg:postcode":"06082",
    "sg:province":"CT",
    "sg:tags":[
        "grill",
        "bar",
        "facility",
        "hall",
        "reception",
        "banquet"
    ],
    "sg:website":"http://www.hazardgrille.com",
    "wof:name":"Hazard Grille",
    "wof:placetype":"venue"
},
  "geometry": {"coordinates":[-72.577663,41.989718],"type":"Point"}
}