{
  "type": "Feature",
  "properties": {
    "addr:full":"20 Heritage Rd Southbury CT 06488",
    "addr:housenumber":"20",
    "addr:postcode":"06488",
    "addr:street":"Heritage Rd",
    "iso:country":"US",
    "sg:address":"20 Heritage Rd",
    "sg:city":"Southbury",
    "sg:classifiers":[
        {
            "category":"Personal",
            "type":"Services"
        }
    ],
    "sg:phone":"+1   ",
    "sg:postcode":"06488",
    "sg:province":"CT",
    "wof:name":"Whalley & Greenwood",
    "wof:placetype":"venue"
},
  "geometry": {"coordinates":[-73.22487599999999,41.488452],"type":"Point"}
}