{
  "type": "Feature",
  "properties": {
    "addr:full":"413 Grove Beach Rd N Westbrook CT 06498",
    "addr:housenumber":"413",
    "addr:postcode":"06498",
    "addr:street":"Grove Beach Rd N",
    "iso:country":"US",
    "sg:address":"413 Grove Beach Rd N",
    "sg:city":"Westbrook",
    "sg:classifiers":[
        {
            "category":"Recreation",
            "type":"Entertainment"
        }
    ],
    "sg:phone":"+1   ",
    "sg:postcode":"06498",
    "sg:province":"CT",
    "sg:tags":[
        "club",
        "membership"
    ],
    "wof:name":"Maintenance Department",
    "wof:placetype":"venue"
},
  "geometry": {"coordinates":[-72.488536,41.283702],"type":"Point"}
}