{
  "type": "Feature",
  "properties": {
    "iso:country":"US",
    "sg:address":"83 East Ave",
    "sg:city":"Norwalk",
    "sg:classifiers":[
        {
            "category":"Manufacturing",
            "subcategory":"Printing",
            "type":"Manufacturing & Wholesale Goods"
        }
    ],
    "sg:phone":"+1 203 855 8603",
    "sg:postcode":"06851",
    "sg:province":"CT",
    "sg:tags":[
        "multimedia"
    ],
    "wof:name":"Ivillage Integrated Media",
    "wof:placetype":"venue"
},
  "geometry": {"coordinates":[-73.407912,41.118323],"type":"Point"}
}