{
  "type": "Feature",
  "properties": {
    "iso:country":"US",
    "sg:address":"15 Martin Rd",
    "sg:city":"East Haven",
    "sg:classifiers":[
        {
            "category":"Building & Trades",
            "subcategory":"Equipment Rental",
            "type":"Services"
        }
    ],
    "sg:phone":"+1 203 469 5867",
    "sg:postcode":"06512",
    "sg:province":"CT",
    "sg:tags":[
        "party",
        "supply"
    ],
    "wof:name":"Party Zone",
    "wof:placetype":"venue"
},
  "geometry": {"coordinates":[-72.863319,41.275054],"type":"Point"}
}