{
  "type": "Feature",
  "properties": {
    "iso:country":"US",
    "sg:address":"237 Grassy Hill Rd",
    "sg:city":"Old Lyme",
    "sg:classifiers":[
        {
            "category":"Farming",
            "subcategory":"Farm",
            "type":"Manufacturing & Wholesale Goods"
        }
    ],
    "sg:phone":"+1 860 434 7302",
    "sg:postcode":"06371",
    "sg:province":"CT",
    "sg:tags":[
        "crop",
        "general"
    ],
    "wof:name":"Foxglove Farm LLC",
    "wof:placetype":"venue"
},
  "geometry": {"coordinates":[-72.290227,41.375463],"type":"Point"}
}