{
  "type": "Feature",
  "properties": {
    "iso:country":"US",
    "sg:address":"2165 Boston Ave",
    "sg:city":"Bridgeport",
    "sg:classifiers":[
        {
            "category":"Banks & Credit Unions",
            "subcategory":"Bank",
            "type":"Services"
        }
    ],
    "sg:phone":"+1 203 382 9670",
    "sg:postcode":"06610",
    "sg:province":"CT",
    "sg:tags":[
        "cashing",
        "check"
    ],
    "wof:name":"Connecticut State Check",
    "wof:placetype":"venue"
},
  "geometry": {"coordinates":[-73.155192,41.192629],"type":"Point"}
}