{
  "type": "Feature",
  "properties": {
    "iso:country":"US",
    "sg:address":"347 E Main St",
    "sg:city":"Wallingford",
    "sg:classifiers":[
        {
            "category":"Building & Trades",
            "subcategory":"Construction",
            "type":"Services"
        },
        {
            "category":"Utilities",
            "type":"Services"
        }
    ],
    "sg:phone":"+1 203 284 1196",
    "sg:postcode":"06492",
    "sg:province":"CT",
    "sg:tags":[
        "repairing",
        "sanitary",
        "remodeling",
        "contractor"
    ],
    "wof:name":"R Quinn Builders Inc",
    "wof:placetype":"venue"
},
  "geometry": {"coordinates":[-72.79362399999999,41.470135],"type":"Point"}
}