{
  "type": "Feature",
  "properties": {
    "addr:full":"326 W Main St Milford CT 06460",
    "addr:housenumber":"326",
    "addr:postcode":"06460",
    "addr:street":"W Main St",
    "iso:country":"US",
    "sg:address":"326 W Main St",
    "sg:city":"Milford",
    "sg:classifiers":[
        {
            "category":"Professional",
            "type":"Services"
        }
    ],
    "sg:phone":"+1 203 874 0637",
    "sg:postcode":"06460",
    "sg:province":"CT",
    "sg:tags":[
        "establishment"
    ],
    "wof:name":"Jordan Associates",
    "wof:placetype":"venue"
},
  "geometry": {"coordinates":[-73.071078,41.223336],"type":"Point"}
}