{
  "type": "Feature",
  "properties": {
    "iso:country":"US",
    "sg:address":"55 Oak St",
    "sg:city":"Glastonbury",
    "sg:classifiers":[
        {
            "category":"Food & Beverages",
            "subcategory":"Groceries & Convenience Stores",
            "type":"Retail Goods"
        }
    ],
    "sg:phone":"+1 860 652 8925",
    "sg:postcode":"06033",
    "sg:province":"CT",
    "wof:name":"Stop & Shop Supermarket",
    "wof:placetype":"venue"
},
  "geometry": {"coordinates":[-72.59374699999999,41.706264],"type":"Point"}
}