{
  "type": "Feature",
  "properties": {
    "addr:full":"1469 Boston Post Rd Milford CT 06460",
    "addr:housenumber":"1469",
    "addr:postcode":"06460",
    "addr:street":"Boston Post Rd",
    "iso:country":"US",
    "sg:address":"1469 Boston Post Rd",
    "sg:city":"Milford",
    "sg:classifiers":[
        {
            "category":"Shopping",
            "subcategory":"Clothing, Apparel, & Fashions",
            "type":"Retail Goods"
        }
    ],
    "sg:phone":"+1 203 878 8903",
    "sg:postcode":"06460",
    "sg:province":"CT",
    "sg:tags":[
        "m"
    ],
    "wof:name":"Giannis",
    "wof:placetype":"venue"
},
  "geometry": {"coordinates":[-73.028336,41.244783],"type":"Point"}
}