{
  "type": "Feature",
  "properties": {
    "addr:full":"160 Connecticut Ave Norwalk CT 06854",
    "addr:housenumber":"160",
    "addr:postcode":"06854",
    "addr:street":"Connecticut Ave",
    "iso:country":"US",
    "sg:address":"160 Connecticut Ave",
    "sg:city":"Norwalk",
    "sg:classifiers":[
        {
            "category":"Freight",
            "type":"Transportation"
        }
    ],
    "sg:phone":"+1 203 866 1150",
    "sg:postcode":"06854",
    "sg:province":"CT",
    "sg:tags":[
        "mover"
    ],
    "wof:name":"Van Guard Moving & Storage",
    "wof:placetype":"venue"
},
  "geometry": {"coordinates":[-73.43230699999999,41.10421],"type":"Point"}
}