{
  "type": "Feature",
  "properties": {
    "iso:country":"US",
    "sg:address":"920 Hopmeadow St",
    "sg:city":"Simsbury",
    "sg:classifiers":[
        {
            "category":"Real Estate",
            "subcategory":"Real Estate Agent",
            "type":"Services"
        }
    ],
    "sg:phone":"+1 860 651 3191",
    "sg:postcode":"06070",
    "sg:province":"CT",
    "wof:name":"Susan B Arsenault",
    "wof:placetype":"venue"
},
  "geometry": {"coordinates":[-72.799825,41.881008],"type":"Point"}
}