{
  "type": "Feature",
  "properties": {
    "addr:full":"16 Eno Hill Rd Winsted CT 06098",
    "addr:housenumber":"16",
    "addr:postcode":"06098",
    "addr:street":"Eno Hill Rd Winsted Ct",
    "iso:country":"US",
    "sg:address":"16 Eno Hill Rd",
    "sg:city":"Winsted",
    "sg:classifiers":[
        {
            "category":"Professional",
            "subcategory":"Business Services",
            "type":"Services"
        }
    ],
    "sg:phone":"+1   ",
    "sg:postcode":"06098",
    "sg:province":"CT",
    "wof:name":"Design Services LLC",
    "wof:placetype":"venue"
},
  "geometry": {"coordinates":[-73.043685,41.982782],"type":"Point"}
}