{
  "type": "Feature",
  "properties": {
    "iso:country":"US",
    "sg:address":"361 Savoy St",
    "sg:city":"Bridgeport",
    "sg:classifiers":[
        {
            "category":"Professional",
            "subcategory":"Business Services",
            "type":"Services"
        }
    ],
    "sg:phone":"+1 203 372 1175",
    "sg:postcode":"06606",
    "sg:province":"CT",
    "sg:tags":[
        "translator",
        "interpreter"
    ],
    "wof:name":"MHF Translation & Intrprttn",
    "wof:placetype":"venue"
},
  "geometry": {"coordinates":[-73.21222299999999,41.203414],"type":"Point"}
}