{
  "type": "Feature",
  "properties": {
    "iso:country":"US",
    "sg:address":"37 Brookside Dr",
    "sg:city":"Greenwich",
    "sg:classifiers":[
        {
            "category":"Banks & Credit Unions",
            "subcategory":"Financial Services",
            "type":"Services"
        }
    ],
    "sg:phone":"+1 203 422 5380",
    "sg:postcode":"06830",
    "sg:province":"CT",
    "sg:tags":[
        "company",
        "holding"
    ],
    "wof:name":"Mkg Holdings LLC",
    "wof:placetype":"venue"
},
  "geometry": {"coordinates":[-73.630798,41.02504],"type":"Point"}
}