{
  "type": "Feature",
  "properties": {
    "iso:country":"US",
    "sg:address":"106 New Hanover Ave",
    "sg:city":"Meriden",
    "sg:classifiers":[
        {
            "category":"Home & Garden",
            "subcategory":"Building Materials",
            "type":"Retail Goods"
        }
    ],
    "sg:phone":"+1 203 238 2552",
    "sg:postcode":"06451",
    "sg:province":"CT",
    "sg:tags":[
        "glass",
        "window",
        "plate"
    ],
    "wof:name":"Windshield Works",
    "wof:placetype":"venue"
},
  "geometry": {"coordinates":[-72.811493,41.526344],"type":"Point"}
}