{
  "type": "Feature",
  "properties": {
    "addr:full":"19 E Putnam Ave Greenwich CT 06830",
    "addr:housenumber":"19",
    "addr:postcode":"06830",
    "addr:street":"E Putnam Ave",
    "iso:country":"US",
    "sg:address":"19 E Putnam Ave",
    "sg:city":"Greenwich",
    "sg:classifiers":[
        {
            "category":"Shopping",
            "subcategory":"Jewelry",
            "type":"Retail Goods"
        }
    ],
    "sg:phone":"+1 203 861 2531",
    "sg:postcode":"06830",
    "sg:province":"CT",
    "sg:tags":[
        "jeweler"
    ],
    "wof:name":"Femmegems",
    "wof:placetype":"venue"
},
  "geometry": {"coordinates":[-73.626144,41.031915],"type":"Point"}
}