{
  "type": "Feature",
  "properties": {
    "iso:country":"US",
    "sg:address":"112 Frank St",
    "sg:city":"New Haven",
    "sg:classifiers":[
        {
            "category":"Organizations",
            "subcategory":"Religious Organization",
            "type":"Services"
        }
    ],
    "sg:phone":"+1   ",
    "sg:postcode":"06519",
    "sg:province":"CT",
    "wof:name":"Bethel Temple Church Of God",
    "wof:placetype":"venue"
},
  "geometry": {"coordinates":[-72.93956900000001,41.296004],"type":"Point"}
}