{
  "type": "Feature",
  "properties": {
    "iso:country":"US",
    "sg:address":"220 Main St",
    "sg:city":"Danbury",
    "sg:classifiers":[
        {
            "category":"Banks & Credit Unions",
            "subcategory":"Bank",
            "type":"Services"
        }
    ],
    "sg:phone":"+1 203 743 3849",
    "sg:postcode":"06810",
    "sg:province":"CT",
    "sg:website":"www.sbdanbury.com",
    "wof:name":"Savings Bank Of Danbury",
    "wof:placetype":"venue"
},
  "geometry": {"coordinates":[-73.453346,41.395206],"type":"Point"}
}