{
  "type": "Feature",
  "properties": {
    "iso:country":"US",
    "sg:address":"70 Sugar Hollow Rd",
    "sg:city":"Danbury",
    "sg:classifiers":[
        {
            "category":"Autos & Motor Vehicles",
            "subcategory":"Fuel & Gas Station",
            "type":"Retail Goods"
        }
    ],
    "sg:phone":"+1 203 743 4246",
    "sg:postcode":"06810",
    "sg:province":"CT",
    "sg:tags":[
        "station",
        "gasoline"
    ],
    "wof:name":"Morrells Service Inc",
    "wof:placetype":"venue"
},
  "geometry": {"coordinates":[-73.469014,41.347328],"type":"Point"}
}