{
  "type": "Feature",
  "properties": {
    "iso:country":"US",
    "sg:address":"100 Kenna Dr",
    "sg:city":"North Haven",
    "sg:classifiers":[
        {
            "category":"Manufacturing",
            "subcategory":"Metals",
            "type":"Manufacturing & Wholesale Goods"
        }
    ],
    "sg:phone":"+1 203 239 3197",
    "sg:postcode":"06473",
    "sg:province":"CT",
    "sg:tags":[
        "gun",
        "manufacturer"
    ],
    "wof:name":"BIC Credit Union",
    "wof:placetype":"venue"
},
  "geometry": {"coordinates":[-72.86555199999999,41.379418],"type":"Point"}
}