{
  "type": "Feature",
  "properties": {
    "iso:country":"US",
    "sg:address":"36 Watson St",
    "sg:city":"Willimantic",
    "sg:classifiers":[
        {
            "category":"Health Services",
            "subcategory":"Doctor",
            "type":"Services"
        }
    ],
    "sg:phone":"+1   ",
    "sg:postcode":"06226",
    "sg:province":"CT",
    "sg:tags":[
        "medical"
    ],
    "wof:name":"Eastern Connecticut Ear Nose",
    "wof:placetype":"venue"
},
  "geometry": {"coordinates":[-72.22161800000001,41.714434],"type":"Point"}
}