{
  "type": "Feature",
  "properties": {
    "addr:full":"497 Main St Ansonia CT 06401",
    "addr:housenumber":"497",
    "addr:postcode":"06401",
    "addr:street":"Main St",
    "iso:country":"US",
    "sg:address":"497 Main St",
    "sg:city":"Ansonia",
    "sg:classifiers":[
        {
            "category":"Health Services",
            "subcategory":"Doctor",
            "type":"Services"
        }
    ],
    "sg:phone":"+1   ",
    "sg:postcode":"06401",
    "sg:province":"CT",
    "sg:tags":[
        "child",
        "day",
        "care"
    ],
    "wof:name":"Dentistry For Chldren Adlscnts",
    "wof:placetype":"venue"
},
  "geometry": {"coordinates":[-73.077833,41.338674],"type":"Point"}
}