{
  "type": "Feature",
  "properties": {
    "addr:full":"137 E Post Rd Cos Cob CT 06807",
    "addr:housenumber":"137",
    "addr:postcode":"06807",
    "addr:street":"E Post Rd;Cob Ct",
    "iso:country":"US",
    "sg:address":"137 E Post Rd",
    "sg:city":"Cos Cob",
    "sg:classifiers":[
        {
            "category":"Insurance",
            "subcategory":"Insurance Agent",
            "type":"Services"
        }
    ],
    "sg:phone":"+1 203 629 8222",
    "sg:postcode":"06807",
    "sg:province":"CT",
    "wof:name":"Griffith E Harris Ins LLC",
    "wof:placetype":"venue"
},
  "geometry": {"coordinates":[-73.59989400000001,41.037723],"type":"Point"}
}