{
  "type": "Feature",
  "properties": {
    "addr:full":"33 Sand St Milford CT 06460",
    "addr:housenumber":"33",
    "addr:postcode":"06460",
    "addr:street":"Sand St",
    "iso:country":"US",
    "sg:address":"33 Sand St",
    "sg:city":"Milford",
    "sg:classifiers":[
        {
            "category":"Building & Trades",
            "subcategory":"Equipment Rental",
            "type":"Services"
        }
    ],
    "sg:phone":"+1   ",
    "sg:postcode":"06460",
    "sg:province":"CT",
    "sg:tags":[
        "center"
    ],
    "wof:name":"Lanier Worldwide Inc",
    "wof:placetype":"venue"
},
  "geometry": {"coordinates":[-73.097947,41.178633],"type":"Point"}
}