{
  "type": "Feature",
  "properties": {
    "iso:country":"US",
    "sg:address":"10 Federal Rd",
    "sg:city":"Brookfield",
    "sg:classifiers":[
        {
            "category":"Retail",
            "subcategory":"Car Wash",
            "type":"Services"
        }
    ],
    "sg:phone":"+1 203 775 9867",
    "sg:postcode":"06804",
    "sg:province":"CT",
    "sg:tags":[
        "polishing",
        "carwash",
        "washing"
    ],
    "wof:name":"Federal Road Car Wash",
    "wof:placetype":"venue"
},
  "geometry": {"coordinates":[-73.415401,41.430959],"type":"Point"}
}