{
  "type": "Feature",
  "properties": {
    "addr:full":"12 Tallwood Rd Woodbridge CT 06525",
    "addr:housenumber":"12",
    "addr:postcode":"06525",
    "addr:street":"Tallwood Rd",
    "iso:country":"US",
    "sg:address":"12 Tallwood Rd",
    "sg:city":"Woodbridge",
    "sg:classifiers":[
        {
            "category":"Farming",
            "subcategory":"Livestock Farm",
            "type":"Manufacturing & Wholesale Goods"
        }
    ],
    "sg:phone":"+1 203 389 2620",
    "sg:postcode":"06525",
    "sg:province":"CT",
    "sg:tags":[
        "equine"
    ],
    "wof:name":"G & M Equus LLC",
    "wof:placetype":"venue"
},
  "geometry": {"coordinates":[-73.02319799999999,41.331843],"type":"Point"}
}