{
  "type": "Feature",
  "properties": {
    "addr:full":"53 Parker St Wallingford CT 06492",
    "addr:housenumber":"53",
    "addr:postcode":"06492",
    "addr:street":"Parker St",
    "iso:country":"US",
    "sg:address":"53 Parker St",
    "sg:city":"Wallingford",
    "sg:classifiers":[
        {
            "category":"Organizations",
            "subcategory":"Community Association",
            "type":"Services"
        }
    ],
    "sg:phone":"+1   ",
    "sg:postcode":"06492",
    "sg:province":"CT",
    "sg:tags":[
        "condominium"
    ],
    "wof:name":"Parker Place Condo Association",
    "wof:placetype":"venue"
},
  "geometry": {"coordinates":[-72.821917,41.462872],"type":"Point"}
}