{
  "type": "Feature",
  "properties": {
    "iso:country":"US",
    "sg:address":"777 Enfield St",
    "sg:city":"Enfield",
    "sg:classifiers":[
        {
            "category":"Retail",
            "subcategory":"Repair Shop",
            "type":"Services"
        }
    ],
    "sg:phone":"+1   ",
    "sg:postcode":"06082",
    "sg:province":"CT",
    "wof:name":"Desco",
    "wof:placetype":"venue"
},
  "geometry": {"coordinates":[-72.593524,42.001519],"type":"Point"}
}