{
  "type": "Feature",
  "properties": {
    "addr:full":"15 Heather Ln Wilton CT 06897",
    "addr:housenumber":"15",
    "addr:postcode":"06897",
    "addr:street":"Heather Ln",
    "iso:country":"US",
    "sg:address":"15 Heather Ln",
    "sg:city":"Wilton",
    "sg:classifiers":[
        {
            "category":"Building & Trades",
            "subcategory":"Landscaping Services",
            "type":"Services"
        }
    ],
    "sg:phone":"+1 203 762 7704",
    "sg:postcode":"06897",
    "sg:province":"CT",
    "sg:tags":[
        "landscape",
        "contractor"
    ],
    "wof:name":"Tobey's Landscaping-Excavating",
    "wof:placetype":"venue"
},
  "geometry": {"coordinates":[-73.39879500000001,41.185243],"type":"Point"}
}