{
  "type": "Feature",
  "properties": {
    "addr:full":"547 W Main St Canaan CT 06018",
    "addr:housenumber":"547",
    "addr:postcode":"06018",
    "addr:street":"W Main St",
    "iso:country":"US",
    "sg:address":"547 W Main St",
    "sg:city":"Canaan",
    "sg:classifiers":[
        {
            "category":"Airport",
            "type":"Transportation"
        }
    ],
    "sg:phone":"+1 860 824 7680",
    "sg:postcode":"06018",
    "sg:province":"CT",
    "wof:name":"Canaan Airport",
    "wof:placetype":"venue"
},
  "geometry": {"coordinates":[-73.33674499999999,42.046362],"type":"Point"}
}