{
  "type": "Feature",
  "properties": {
    "iso:country":"US",
    "sg:address":"55 Ayer Rd",
    "sg:city":"North Franklin",
    "sg:classifiers":[
        {
            "category":"Farming",
            "subcategory":"Livestock Farm",
            "type":"Manufacturing & Wholesale Goods"
        }
    ],
    "sg:phone":"+1 860 642 7205",
    "sg:postcode":"06254",
    "sg:province":"CT",
    "sg:tags":[
        "equine"
    ],
    "wof:name":"Ayer Mountain Farm Inc",
    "wof:placetype":"venue"
},
  "geometry": {"coordinates":[-72.13056400000001,41.63368],"type":"Point"}
}