{
  "type": "Feature",
  "properties": {
    "iso:country":"US",
    "sg:address":"252 Post Rd E",
    "sg:city":"Westport",
    "sg:classifiers":[
        {
            "category":"Shopping",
            "subcategory":"Used Merchandise",
            "type":"Retail Goods"
        }
    ],
    "sg:phone":"+1 203 227 7480",
    "sg:postcode":"06880",
    "sg:province":"CT",
    "wof:name":"Swedish Simplicity LLC",
    "wof:placetype":"venue"
},
  "geometry": {"coordinates":[-73.356145,41.141016],"type":"Point"}
}