{
  "type": "Feature",
  "properties": {
    "addr:full":"1008 Bank St New London CT 06320",
    "addr:housenumber":"1008",
    "addr:postcode":"06320",
    "addr:street":"Bank St New London Ct",
    "iso:country":"US",
    "sg:address":"1008 Bank St",
    "sg:city":"New London",
    "sg:classifiers":[
        {
            "category":"Retail",
            "subcategory":"Auto Repair",
            "type":"Services"
        }
    ],
    "sg:phone":"+1   ",
    "sg:postcode":"06320",
    "sg:province":"CT",
    "sg:tags":[
        "automotive"
    ],
    "wof:name":"Big Als Custom Auto Detailing",
    "wof:placetype":"venue"
},
  "geometry": {"coordinates":[-72.113223,41.343772],"type":"Point"}
}