{
  "type": "Feature",
  "properties": {
    "addr:full":"244 Academy Rd Cheshire CT 06410",
    "addr:housenumber":"244",
    "addr:postcode":"06410",
    "addr:street":"Academy Rd",
    "iso:country":"US",
    "sg:address":"244 Academy Rd",
    "sg:city":"Cheshire",
    "sg:classifiers":[
        {
            "category":"Wholesale",
            "subcategory":"Electrical",
            "type":"Manufacturing & Wholesale Goods"
        }
    ],
    "sg:phone":"+1 203 271 0457",
    "sg:postcode":"06410",
    "sg:province":"CT",
    "sg:tags":[
        "equipment"
    ],
    "wof:name":"JC Electronic",
    "wof:placetype":"venue"
},
  "geometry": {"coordinates":[-72.89767999999999,41.498751],"type":"Point"}
}