{
  "type": "Feature",
  "properties": {
    "addr:full":"49 Dandy Dr Cos Cob CT 06807",
    "addr:housenumber":"49",
    "addr:postcode":"06807",
    "addr:street":"Dandy Dr",
    "iso:country":"US",
    "sg:address":"49 Dandy Dr",
    "sg:city":"Cos Cob",
    "sg:classifiers":[
        {
            "category":"Communications",
            "type":"Services"
        }
    ],
    "sg:phone":"+1 203 618 0256",
    "sg:postcode":"06807",
    "sg:province":"CT",
    "sg:tags":[
        "communication"
    ],
    "wof:name":"Green Witch Media LLC",
    "wof:placetype":"venue"
},
  "geometry": {"coordinates":[-73.590829,41.053056],"type":"Point"}
}