{
  "type": "Feature",
  "properties": {
    "addr:full":"17 Kimberly Ave West Haven CT 06516",
    "addr:housenumber":"17",
    "addr:postcode":"06516",
    "addr:street":"Kimberly Ave",
    "iso:country":"US",
    "sg:address":"17 Kimberly Ave",
    "sg:city":"West Haven",
    "sg:classifiers":[
        {
            "category":"Shopping",
            "subcategory":"Bicycles & Sporting Goods",
            "type":"Retail Goods"
        }
    ],
    "sg:phone":"+1 203 933 2002",
    "sg:postcode":"06516",
    "sg:province":"CT",
    "sg:tags":[
        "tackle",
        "fishing"
    ],
    "wof:name":"Some-Things Fishy",
    "wof:placetype":"venue"
},
  "geometry": {"coordinates":[-72.93937,41.280764],"type":"Point"}
}