{
  "type": "Feature",
  "properties": {
    "addr:full":"28 Laurel Ledge Ct Stamford CT 06903",
    "addr:housenumber":"28",
    "addr:postcode":"06903",
    "addr:street":"Laurel Ledge Ct",
    "iso:country":"US",
    "sg:address":"28 Laurel Ledge Ct",
    "sg:city":"Stamford",
    "sg:classifiers":[
        {
            "category":"Arts & Performance",
            "subcategory":"Theater",
            "type":"Entertainment"
        }
    ],
    "sg:phone":"+1   ",
    "sg:postcode":"06903",
    "sg:province":"CT",
    "sg:tags":[
        "group"
    ],
    "wof:name":"Cotillion Club Inc",
    "wof:placetype":"venue"
},
  "geometry": {"coordinates":[-73.59865499999999,41.141661],"type":"Point"}
}