{
  "type": "Feature",
  "properties": {
    "addr:full":"150 W Main St Branford CT 06405",
    "addr:housenumber":"150",
    "addr:postcode":"06405",
    "addr:street":"W Main St",
    "iso:country":"US",
    "sg:address":"150 W Main St",
    "sg:city":"Branford",
    "sg:classifiers":[
        {
            "category":"Professional",
            "subcategory":"Lawyer & Legal Services",
            "type":"Services"
        }
    ],
    "sg:phone":"+1   ",
    "sg:postcode":"06405",
    "sg:province":"CT",
    "wof:name":"Ghiroli Albert",
    "wof:placetype":"venue"
},
  "geometry": {"coordinates":[-72.85427900000001,41.278252],"type":"Point"}
}