{
  "type": "Feature",
  "properties": {
    "addr:full":"2 Old Mill Ct Storrs Mansfield CT 06268",
    "addr:housenumber":"2",
    "addr:postcode":"06268",
    "addr:street":"Old Mill Ct;Mansfield Ct",
    "iso:country":"US",
    "sg:address":"2 Old Mill Ct",
    "sg:city":"Storrs Mansfield",
    "sg:classifiers":[
        {
            "category":"Shopping",
            "subcategory":"Discount & Variety Stores",
            "type":"Retail Goods"
        }
    ],
    "sg:phone":"+1 860 429 1144",
    "sg:postcode":"06268",
    "sg:province":"CT",
    "sg:tags":[
        "merchandise",
        "general"
    ],
    "wof:name":"Champlions General Store",
    "wof:placetype":"venue"
},
  "geometry": {"coordinates":[-72.27860699999999,41.785664],"type":"Point"}
}