{
  "type": "Feature",
  "properties": {
    "addr:full":"1556 Main St Newington CT 06111",
    "addr:housenumber":"1556",
    "addr:postcode":"06111",
    "addr:street":"Main St",
    "iso:country":"US",
    "sg:address":"1556 Main St",
    "sg:city":"Newington",
    "sg:classifiers":[
        {
            "category":"Building & Trades",
            "subcategory":"Construction",
            "type":"Services"
        }
    ],
    "sg:phone":"+1 860 523 7102",
    "sg:postcode":"06111",
    "sg:province":"CT",
    "sg:tags":[
        "nonresidential"
    ],
    "wof:name":"True Colors Painting LLC",
    "wof:placetype":"venue"
},
  "geometry": {"coordinates":[-72.721717,41.690258],"type":"Point"}
}