{
  "type": "Feature",
  "properties": {
    "iso:country":"US",
    "sg:address":"1 Village Green",
    "sg:city":"Southbury",
    "sg:classifiers":[
        {
            "category":"Personal",
            "subcategory":"Beauty Salon",
            "type":"Services"
        }
    ],
    "sg:phone":"+1   ",
    "sg:postcode":"06488",
    "sg:province":"CT",
    "sg:tags":[
        "shop"
    ],
    "wof:name":"Pattys of Southbury",
    "wof:placetype":"venue"
},
  "geometry": {"coordinates":[-73.22346899999999,41.488925],"type":"Point"}
}