{
  "type": "Feature",
  "properties": {
    "iso:country":"US",
    "sg:address":"548 Hope St",
    "sg:city":"Stamford",
    "sg:classifiers":[
        {
            "category":"Building & Trades",
            "subcategory":"Pest Control",
            "type":"Services"
        }
    ],
    "sg:phone":"+1 203 348 7111",
    "sg:postcode":"06907",
    "sg:province":"CT",
    "wof:name":"All-State Exterminating Co",
    "wof:placetype":"venue"
},
  "geometry": {"coordinates":[-73.522531,41.077618],"type":"Point"}
}