{
  "type": "Feature",
  "properties": {
    "addr:full":"68 Cooke St Plainville CT 06062",
    "addr:housenumber":"68",
    "addr:postcode":"06062",
    "addr:street":"Cooke St",
    "iso:country":"US",
    "sg:address":"68 Cooke St",
    "sg:city":"Plainville",
    "sg:classifiers":[
        {
            "category":"Real Estate",
            "subcategory":"Real Estate Operator",
            "type":"Services"
        }
    ],
    "sg:phone":"+1 860 747 6881",
    "sg:postcode":"06062",
    "sg:province":"CT",
    "sg:tags":[
        "mobile",
        "home",
        "parks"
    ],
    "wof:name":"Liberty Mobilehome Sales Inc",
    "wof:placetype":"venue"
},
  "geometry": {"coordinates":[-72.846795,41.67862],"type":"Point"}
}