{
  "type": "Feature",
  "properties": {
    "iso:country":"US",
    "sg:address":"510 Oak Bluff Ave",
    "sg:city":"Stratford",
    "sg:classifiers":[
        {
            "category":"Shopping",
            "subcategory":"Computers & Home Electronics",
            "type":"Retail Goods"
        }
    ],
    "sg:phone":"+1 203 378 7767",
    "sg:postcode":"06615",
    "sg:province":"CT",
    "sg:tags":[
        "equipment",
        "dealer"
    ],
    "wof:name":"P & L Personal Computers",
    "wof:placetype":"venue"
},
  "geometry": {"coordinates":[-73.132068,41.153031],"type":"Point"}
}