{
  "type": "Feature",
  "properties": {
    "iso:country":"US",
    "sg:address":"107 North Ave",
    "sg:city":"Westport",
    "sg:classifiers":[
        {
            "category":"Banks & Credit Unions",
            "subcategory":"Investment Brokerage",
            "type":"Services"
        }
    ],
    "sg:phone":"+1 203 227 8922",
    "sg:postcode":"06880",
    "sg:province":"CT",
    "sg:tags":[
        "trading",
        "commodity"
    ],
    "wof:name":"Michael Gantz",
    "wof:placetype":"venue"
},
  "geometry": {"coordinates":[-73.335329,41.159109],"type":"Point"}
}