{
  "type": "Feature",
  "properties": {
    "addr:full":"42 Jefferson Dr Ridgefield CT 06877",
    "addr:housenumber":"42",
    "addr:postcode":"06877",
    "addr:street":"Jefferson Dr",
    "iso:country":"US",
    "sg:address":"42 Jefferson Dr",
    "sg:city":"Ridgefield",
    "sg:classifiers":[
        {
            "category":"Social Services",
            "subcategory":"Job Training",
            "type":"Services"
        }
    ],
    "sg:phone":"+1   ",
    "sg:postcode":"06877",
    "sg:province":"CT",
    "wof:name":"Professional Dynamics LLC",
    "wof:placetype":"venue"
},
  "geometry": {"coordinates":[-73.47726900000001,41.271829],"type":"Point"}
}