{
  "type": "Feature",
  "properties": {
    "iso:country":"US",
    "sg:address":"319 N Windham Rd",
    "sg:city":"North Windham",
    "sg:classifiers":[
        {
            "category":"Professional",
            "subcategory":"Business Services",
            "type":"Services"
        }
    ],
    "sg:phone":"+1   ",
    "sg:postcode":"06256",
    "sg:province":"CT",
    "sg:tags":[
        "design"
    ],
    "wof:name":"Design Center East LLC",
    "wof:placetype":"venue"
},
  "geometry": {"coordinates":[-72.167247,41.724257],"type":"Point"}
}