{
  "type": "Feature",
  "properties": {
    "addr:full":"144 Poquonock Ave Windsor CT 06095",
    "addr:housenumber":"144",
    "addr:postcode":"06095",
    "addr:street":"Poquonock Ave",
    "iso:country":"US",
    "sg:address":"144 Poquonock Ave",
    "sg:city":"Windsor",
    "sg:classifiers":[
        {
            "category":"Home & Garden",
            "subcategory":"Hardware",
            "type":"Retail Goods"
        }
    ],
    "sg:phone":"+1 860 688 6287",
    "sg:postcode":"06095",
    "sg:province":"CT",
    "sg:tags":[
        "small",
        "paint",
        "household",
        "electrical",
        "store"
    ],
    "wof:name":"Larsens Hardware Inc",
    "wof:placetype":"venue"
},
  "geometry": {"coordinates":[-72.648049,41.854963],"type":"Point"}
}