{
  "type": "Feature",
  "properties": {
    "iso:country":"US",
    "sg:address":"16 Shore Rd",
    "sg:city":"Danbury",
    "sg:classifiers":[
        {
            "category":"Professional",
            "subcategory":"Business Services",
            "type":"Services"
        }
    ],
    "sg:phone":"+1   ",
    "sg:postcode":"06811",
    "sg:province":"CT",
    "wof:name":"Mf Enterprises Inc",
    "wof:placetype":"venue"
},
  "geometry": {"coordinates":[-73.42821000000001,41.458458],"type":"Point"}
}