{
  "type": "Feature",
  "properties": {
    "addr:full":"69 Sand Pit Rd Danbury CT 06810",
    "addr:housenumber":"69",
    "addr:postcode":"06810",
    "addr:street":"Sand Pit Rd",
    "iso:country":"US",
    "sg:address":"69 Sand Pit Rd",
    "sg:city":"Danbury",
    "sg:classifiers":[
        {
            "category":"Health Services",
            "subcategory":"Doctor",
            "type":"Services"
        }
    ],
    "sg:phone":"+1   ",
    "sg:postcode":"06810",
    "sg:province":"CT",
    "sg:tags":[
        "medical"
    ],
    "wof:name":"Surgical Associates",
    "wof:placetype":"venue"
},
  "geometry": {"coordinates":[-73.43248199999999,41.414134],"type":"Point"}
}