{
  "type": "Feature",
  "properties": {
    "iso:country":"US",
    "sg:address":"1 Cranberry Ln",
    "sg:city":"Brookfield",
    "sg:classifiers":[
        {
            "category":"Professional",
            "subcategory":"Business Services",
            "type":"Services"
        }
    ],
    "sg:phone":"+1 203 775 1830",
    "sg:postcode":"06804",
    "sg:province":"CT",
    "sg:tags":[
        "plant",
        "design",
        "maintenance"
    ],
    "wof:name":"Plants & Pictures",
    "wof:placetype":"venue"
},
  "geometry": {"coordinates":[-73.43384,41.475887],"type":"Point"}
}