{
  "type": "Feature",
  "properties": {
    "addr:full":"75 Old State Rd Southbury CT 06489",
    "addr:housenumber":"75",
    "addr:postcode":"06489",
    "addr:street":"Old State Rd",
    "iso:country":"US",
    "sg:address":"75 Old State Rd",
    "sg:city":"Southbury",
    "sg:classifiers":[
        {
            "category":"Building & Trades",
            "subcategory":"Construction",
            "type":"Services"
        }
    ],
    "sg:phone":"+1 203 264 5383",
    "sg:postcode":"06489",
    "sg:province":"CT",
    "wof:name":"Bureau Of Highways",
    "wof:placetype":"venue"
},
  "geometry": {"coordinates":[-72.84593099999999,41.598346],"type":"Point"}
}