{
  "type": "Feature",
  "properties": {
    "iso:country":"US",
    "sg:address":"695 West Ave",
    "sg:city":"Milford",
    "sg:classifiers":[
        {
            "category":"Wholesale",
            "subcategory":"Chemicals & Plastics",
            "type":"Manufacturing & Wholesale Goods"
        }
    ],
    "sg:phone":"+1 203 876 0682",
    "sg:postcode":"06461",
    "sg:province":"CT",
    "wof:name":"Quant Chemicals",
    "wof:placetype":"venue"
},
  "geometry": {"coordinates":[-73.077022,41.215956],"type":"Point"}
}