{
  "type": "Feature",
  "properties": {
    "iso:country":"US",
    "sg:address":"228 Boston Tpke",
    "sg:city":"Bolton",
    "sg:classifiers":[
        {
            "category":"Personal",
            "subcategory":"Beauty Salon",
            "type":"Services"
        }
    ],
    "sg:phone":"+1   ",
    "sg:postcode":"06043",
    "sg:province":"CT",
    "sg:tags":[
        "shop"
    ],
    "wof:name":"Looking Good Hair Styling LLC",
    "wof:placetype":"venue"
},
  "geometry": {"coordinates":[-72.46107600000001,41.784561],"type":"Point"}
}