{
  "type": "Feature",
  "properties": {
    "addr:full":"33 Indian Ledge Rd Monroe CT 06468",
    "addr:housenumber":"33",
    "addr:postcode":"06468",
    "addr:street":"Indian Ledge Rd Monroe Ct",
    "iso:country":"US",
    "sg:address":"33 Indian Ledge Rd",
    "sg:city":"Monroe",
    "sg:classifiers":[
        {
            "category":"Professional",
            "subcategory":"Art Services",
            "type":"Services"
        }
    ],
    "sg:phone":"+1 203 261 2615",
    "sg:postcode":"06468",
    "sg:province":"CT",
    "sg:tags":[
        "graphic",
        "designer"
    ],
    "sg:website":"www.feeneydesign.com",
    "wof:name":"Feeney Design Assoc",
    "wof:placetype":"venue"
},
  "geometry": {"coordinates":[-73.27683399999999,41.32496],"type":"Point"}
}