{
  "type": "Feature",
  "properties": {
    "iso:country":"US",
    "sg:address":"24 Carriage Dr",
    "sg:city":"Oxford",
    "sg:classifiers":[
        {
            "category":"Building & Trades",
            "subcategory":"Construction",
            "type":"Services"
        }
    ],
    "sg:phone":"+1 203 888 3224",
    "sg:postcode":"06478",
    "sg:province":"CT",
    "sg:tags":[
        "contractor"
    ],
    "wof:name":"Steven J Yellen Builders",
    "wof:placetype":"venue"
},
  "geometry": {"coordinates":[-73.14644800000001,41.388677],"type":"Point"}
}