{
  "type": "Feature",
  "properties": {
    "addr:full":"304 Hazard Ave Enfield CT 06082",
    "addr:housenumber":"304",
    "addr:postcode":"06082",
    "addr:street":"Hazard Ave",
    "iso:country":"US",
    "sg:address":"304 Hazard Ave",
    "sg:city":"Enfield",
    "sg:classifiers":[
        {
            "category":"Shopping",
            "subcategory":"Clothing, Apparel, & Fashions",
            "type":"Retail Goods"
        }
    ],
    "sg:phone":"+1 860 749 6157",
    "sg:postcode":"06082",
    "sg:province":"CT",
    "wof:name":"Sams T Shirt",
    "wof:placetype":"venue"
},
  "geometry": {"coordinates":[-72.540351,41.986447],"type":"Point"}
}