{
  "type": "Feature",
  "properties": {
    "iso:country":"US",
    "sg:address":"187 Bunnell St",
    "sg:city":"Bridgeport",
    "sg:classifiers":[
        {
            "category":"Building & Trades",
            "subcategory":"Electrical",
            "type":"Services"
        }
    ],
    "sg:phone":"+1 203 333 0221",
    "sg:postcode":"06607",
    "sg:province":"CT",
    "sg:tags":[
        "electric",
        "contractor"
    ],
    "wof:name":"Compare Electrical Contractors",
    "wof:placetype":"venue"
},
  "geometry": {"coordinates":[-73.16738100000001,41.181029],"type":"Point"}
}