{
  "type": "Feature",
  "properties": {
    "iso:country":"US",
    "sg:address":"377 Main St",
    "sg:city":"New Canaan",
    "sg:classifiers":[
        {
            "category":"Professional",
            "type":"Services"
        }
    ],
    "sg:phone":"+1 203 972 6500",
    "sg:postcode":"06840",
    "sg:province":"NY",
    "sg:tags":[
        "establishment"
    ],
    "wof:name":"Britt Sovich-Voyages",
    "wof:placetype":"venue"
},
  "geometry": {"coordinates":[-73.483606,41.140502],"type":"Point"}
}