{
  "type": "Feature",
  "properties": {
    "iso:country":"US",
    "sg:address":"108 Sycamore St",
    "sg:city":"Bristol",
    "sg:classifiers":[
        {
            "category":"Organizations",
            "subcategory":"Religious Organization",
            "type":"Services"
        }
    ],
    "sg:phone":"+1   ",
    "sg:postcode":"06010",
    "sg:province":"CT",
    "wof:name":"Alden Barnes Rev",
    "wof:placetype":"venue"
},
  "geometry": {"coordinates":[-72.91086,41.667599],"type":"Point"}
}