{
  "type": "Feature",
  "properties": {
    "iso:country":"US",
    "sg:address":"15 Marshall St",
    "sg:city":"Putnam",
    "sg:classifiers":[
        {
            "category":"Organizations",
            "subcategory":"Religious Organization",
            "type":"Services"
        }
    ],
    "sg:phone":"+1   ",
    "sg:postcode":"06260",
    "sg:province":"CT",
    "wof:name":"St Marys Church of Visitation",
    "wof:placetype":"venue"
},
  "geometry": {"coordinates":[-71.91244,41.924034],"type":"Point"}
}