{
  "type": "Feature",
  "properties": {
    "addr:full":"22 Olive St Meriden CT 06450",
    "addr:housenumber":"22",
    "addr:postcode":"06450",
    "addr:street":"Olive St",
    "iso:country":"US",
    "sg:address":"22 Olive St",
    "sg:city":"Meriden",
    "sg:classifiers":[
        {
            "category":"Food & Beverages",
            "subcategory":"Groceries & Convenience Stores",
            "type":"Retail Goods"
        }
    ],
    "sg:phone":"+1 203 639 0404",
    "sg:postcode":"06450",
    "sg:province":"CT",
    "sg:tags":[
        "grocer"
    ],
    "wof:name":"Stephanie's Grocery",
    "wof:placetype":"venue"
},
  "geometry": {"coordinates":[-72.80295099999999,41.533429],"type":"Point"}
}