{
  "type": "Feature",
  "properties": {
    "addr:full":"14 Wall St Norwalk CT 06850",
    "addr:housenumber":"14",
    "addr:postcode":"06850",
    "addr:street":"Wall St",
    "iso:country":"US",
    "sg:address":"14 Wall St",
    "sg:city":"Norwalk",
    "sg:classifiers":[
        {
            "category":"Organizations",
            "subcategory":"Religious Organization",
            "type":"Services"
        }
    ],
    "sg:phone":"+1   ",
    "sg:postcode":"06850",
    "sg:province":"CT",
    "wof:name":"Living Bred Lfee Vnglistic Mis",
    "wof:placetype":"venue"
},
  "geometry": {"coordinates":[-73.411992,41.11857],"type":"Point"}
}