{
  "type": "Feature",
  "properties": {
    "addr:full":"18 E Hill Rd Canton CT 06019",
    "addr:housenumber":"18",
    "addr:postcode":"06019",
    "addr:street":"E Hill Rd",
    "iso:country":"US",
    "sg:address":"18 E Hill Rd",
    "sg:city":"Canton",
    "sg:classifiers":[
        {
            "category":"Autos & Motor Vehicles",
            "subcategory":"Motorcycle Sales",
            "type":"Retail Goods"
        }
    ],
    "sg:phone":"+1 860 693 9229",
    "sg:postcode":"06019",
    "sg:province":"CT",
    "wof:name":"Hunter Cycle",
    "wof:placetype":"venue"
},
  "geometry": {"coordinates":[-72.910464,41.826845],"type":"Point"}
}