{
  "type": "Feature",
  "properties": {
    "iso:country":"US",
    "sg:address":"178 State St",
    "sg:city":"North Haven",
    "sg:classifiers":[
        {
            "category":"Building & Trades",
            "subcategory":"Cleaning & Sanitation",
            "type":"Services"
        }
    ],
    "sg:phone":"+1   ",
    "sg:postcode":"06473",
    "sg:province":"CT",
    "sg:tags":[
        "maintenance"
    ],
    "wof:name":"Crystal Restoration Service",
    "wof:placetype":"venue"
},
  "geometry": {"coordinates":[-72.87908299999999,41.379078],"type":"Point"}
}