{
  "type": "Feature",
  "properties": {
    "iso:country":"US",
    "sg:address":"197 S King St",
    "sg:city":"Danbury",
    "sg:classifiers":[
        {
            "category":"Organizations",
            "subcategory":"Religious Organization",
            "type":"Services"
        }
    ],
    "sg:phone":"+1 203 748 6653",
    "sg:postcode":"06811",
    "sg:province":"CT",
    "sg:tags":[
        "clergy"
    ],
    "wof:name":"United Church Of Christ Parsng",
    "wof:placetype":"venue"
},
  "geometry": {"coordinates":[-73.49763400000001,41.420593],"type":"Point"}
}