{
  "type": "Feature",
  "properties": {
    "addr:full":"113 Torrington Rd Goshen CT 06756",
    "addr:housenumber":"113",
    "addr:postcode":"06756",
    "addr:street":"Torrington Rd",
    "iso:country":"US",
    "sg:address":"113 Torrington Rd",
    "sg:city":"Goshen",
    "sg:classifiers":[
        {
            "category":"Shopping",
            "type":"Retail Goods"
        }
    ],
    "sg:phone":"+1 860 491 2767",
    "sg:postcode":"06756",
    "sg:province":"CT",
    "sg:tags":[
        "merchandise"
    ],
    "wof:name":"Frames & Furnishings",
    "wof:placetype":"venue"
},
  "geometry": {"coordinates":[-73.21688899999999,41.835701],"type":"Point"}
}