{
  "type": "Feature",
  "properties": {
    "iso:country":"US",
    "sg:address":"3295 Whitney Ave",
    "sg:city":"Hamden",
    "sg:classifiers":[
        {
            "category":"Personal",
            "subcategory":"Beauty Salon",
            "type":"Services"
        },
        {
            "category":"Personal",
            "subcategory":"Barber",
            "type":"Services"
        }
    ],
    "sg:phone":"+1 203 407 8341",
    "sg:postcode":"06518",
    "sg:province":"CT",
    "sg:tags":[
        "hair"
    ],
    "wof:name":"Carlo's Hair Connection",
    "wof:placetype":"venue"
},
  "geometry": {"coordinates":[-72.901262,41.411787],"type":"Point"}
}