{
  "type": "Feature",
  "properties": {
    "iso:country":"US",
    "sg:address":"18 Holly Ct",
    "sg:city":"Fairfield",
    "sg:classifiers":[
        {
            "category":"Building & Trades",
            "subcategory":"Cleaning & Sanitation",
            "type":"Services"
        }
    ],
    "sg:phone":"+1   ",
    "sg:postcode":"06416",
    "sg:province":"CT",
    "wof:name":"Merry Maids",
    "wof:placetype":"venue"
},
  "geometry": {"coordinates":[-72.68262199999999,41.604306],"type":"Point"}
}