{
  "type": "Feature",
  "properties": {
    "iso:country":"US",
    "sg:address":"411 Bridgeport Ave",
    "sg:city":"Shelton",
    "sg:classifiers":[
        {
            "category":"Manufacturing",
            "subcategory":"Rubber & Plastics",
            "type":"Manufacturing & Wholesale Goods"
        }
    ],
    "sg:phone":"+1 203 929 2282",
    "sg:postcode":"06484",
    "sg:province":"CT",
    "sg:tags":[
        "product",
        "foam"
    ],
    "wof:name":"Blister Solutions LLC",
    "wof:placetype":"venue"
},
  "geometry": {"coordinates":[-73.109843,41.294382],"type":"Point"}
}