{
  "type": "Feature",
  "properties": {
    "iso:country":"US",
    "sg:address":"550 Spring St",
    "sg:city":"Naugatuck",
    "sg:classifiers":[
        {
            "category":"Manufacturing",
            "subcategory":"Metals",
            "type":"Manufacturing & Wholesale Goods"
        }
    ],
    "sg:phone":"+1 203 723 8887",
    "sg:postcode":"06770",
    "sg:province":"CT",
    "sg:tags":[
        "machine",
        "screw",
        "product"
    ],
    "wof:name":"Multi-Metal Mfg",
    "wof:placetype":"venue"
},
  "geometry": {"coordinates":[-73.058764,41.512086],"type":"Point"}
}