{
  "type": "Feature",
  "properties": {
    "addr:full":"85 Kozey Rd Eastford CT 06242",
    "addr:housenumber":"85",
    "addr:postcode":"06242",
    "addr:street":"Kozey Rd Eastford Ct",
    "iso:country":"US",
    "sg:address":"85 Kozey Rd",
    "sg:city":"Eastford",
    "sg:classifiers":[
        {
            "category":"Retail",
            "subcategory":"Auto Repair",
            "type":"Services"
        }
    ],
    "sg:phone":"+1   ",
    "sg:postcode":"06242",
    "sg:province":"CT",
    "sg:tags":[
        "body"
    ],
    "wof:name":"Kozeys Classic Body and Paint",
    "wof:placetype":"venue"
},
  "geometry": {"coordinates":[-72.126526,41.920691],"type":"Point"}
}