{
  "type": "Feature",
  "properties": {
    "addr:full":"80 E Main St Stafford Springs CT 06076",
    "addr:housenumber":"80",
    "addr:postcode":"06076",
    "addr:street":"E Main St",
    "iso:country":"US",
    "sg:address":"80 E Main St",
    "sg:city":"Stafford Springs",
    "sg:classifiers":[
        {
            "category":"Food & Beverages",
            "subcategory":"Specialty",
            "type":"Retail Goods"
        }
    ],
    "sg:phone":"+1 860 684 3622",
    "sg:postcode":"06076",
    "sg:province":"CT",
    "wof:name":"Ginger Brook Herbs LLC",
    "wof:placetype":"venue"
},
  "geometry": {"coordinates":[-72.295833,41.955768],"type":"Point"}
}