{
  "type": "Feature",
  "properties": {
    "iso:country":"US",
    "sg:address":"701 Enfield St",
    "sg:city":"Enfield",
    "sg:classifiers":[
        {
            "category":"Health Services",
            "subcategory":"Doctor",
            "type":"Services"
        }
    ],
    "sg:phone":"+1   ",
    "sg:postcode":"06082",
    "sg:province":"CT",
    "sg:tags":[
        "internal"
    ],
    "wof:name":"Springfield Medical Associates",
    "wof:placetype":"venue"
},
  "geometry": {"coordinates":[-72.592697,42.003907],"type":"Point"}
}