{
  "type": "Feature",
  "properties": {
    "iso:country":"US",
    "sg:address":"26 Deer Park Dr",
    "sg:city":"Greenwich",
    "sg:classifiers":[
        {
            "category":"Organizations",
            "subcategory":"Community Association",
            "type":"Services"
        }
    ],
    "sg:phone":"+1   ",
    "sg:postcode":"06830",
    "sg:province":"CT",
    "wof:name":"Friends of South African",
    "wof:placetype":"venue"
},
  "geometry": {"coordinates":[-73.63103,41.040882],"type":"Point"}
}