{
  "type": "Feature",
  "properties": {
    "addr:full":"40 Hart Ter New Britain CT 06052",
    "addr:housenumber":"40",
    "addr:postcode":"06052",
    "addr:street":"Hart Ter New Britain Ct",
    "iso:country":"US",
    "sg:address":"40 Hart Ter",
    "sg:city":"New Britain",
    "sg:classifiers":[
        {
            "category":"Health Services",
            "subcategory":"Doctor",
            "type":"Services"
        }
    ],
    "sg:phone":"+1   ",
    "sg:postcode":"06052",
    "sg:province":"CT",
    "sg:tags":[
        "medical"
    ],
    "wof:name":"Patrick M Rocco MD",
    "wof:placetype":"venue"
},
  "geometry": {"coordinates":[-72.79106,41.662193],"type":"Point"}
}