{
  "type": "Feature",
  "properties": {
    "iso:country":"US",
    "sg:address":"322 South St",
    "sg:city":"Plymouth",
    "sg:classifiers":[
        {
            "category":"Banks & Credit Unions",
            "subcategory":"Financial Services",
            "type":"Services"
        }
    ],
    "sg:phone":"+1 860 283 8522",
    "sg:postcode":"06782",
    "sg:province":"CT",
    "sg:tags":[
        "investor"
    ],
    "wof:name":"Cla Investment Group LLC",
    "wof:placetype":"venue"
},
  "geometry": {"coordinates":[-73.05216299999999,41.652595],"type":"Point"}
}