{
  "type": "Feature",
  "properties": {
    "iso:country":"US",
    "sg:address":"27 Fulton St",
    "sg:city":"New Haven",
    "sg:classifiers":[
        {
            "category":"Autos & Motor Vehicles",
            "subcategory":"Auto Supplies",
            "type":"Retail Goods"
        }
    ],
    "sg:phone":"+1 203 468 9188",
    "sg:postcode":"06513",
    "sg:province":"CT",
    "sg:tags":[
        "automobile",
        "parts"
    ],
    "wof:name":"Car Parts Intl",
    "wof:placetype":"venue"
},
  "geometry": {"coordinates":[-72.89685900000001,41.294206],"type":"Point"}
}