{
  "type": "Feature",
  "properties": {
    "addr:full":"159 Fieldwood Rd Waterbury CT 06704",
    "addr:housenumber":"159",
    "addr:postcode":"06704",
    "addr:street":"Fieldwood Rd",
    "iso:country":"US",
    "sg:address":"159 Fieldwood Rd",
    "sg:city":"Waterbury",
    "sg:classifiers":[
        {
            "category":"Organizations",
            "subcategory":"Religious Organization",
            "type":"Services"
        }
    ],
    "sg:phone":"+1   ",
    "sg:postcode":"06704",
    "sg:province":"CT",
    "wof:name":"Kenneth R Mason",
    "wof:placetype":"venue"
},
  "geometry": {"coordinates":[-73.03523,41.603584],"type":"Point"}
}