{
  "type": "Feature",
  "properties": {
    "addr:full":"1775 Middletown Ave Northford CT 06472",
    "addr:housenumber":"1775",
    "addr:postcode":"06472",
    "addr:street":"Middletown Ave Northford Ct",
    "iso:country":"US",
    "sg:address":"1775 Middletown Ave",
    "sg:city":"Northford",
    "sg:phone":"+1 203 484 2431",
    "sg:postcode":"06472",
    "sg:province":"CT",
    "sg:tags":[
        "farm",
        "field",
        "crop"
    ],
    "wof:name":"Schanz Farm",
    "wof:placetype":"venue"
},
  "geometry": {"coordinates":[-72.77180199999999,41.409266],"type":"Point"}
}