{
  "type": "Feature",
  "properties": {
    "iso:country":"US",
    "sg:address":"103 Hosford St",
    "sg:city":"Wallingford",
    "sg:classifiers":[
        {
            "category":"Building & Trades",
            "subcategory":"Cleaning & Sanitation",
            "type":"Services"
        }
    ],
    "sg:phone":"+1   ",
    "sg:postcode":"06492",
    "sg:province":"CT",
    "sg:tags":[
        "maintenance"
    ],
    "wof:name":"Splish Splash Pow-R-Wash",
    "wof:placetype":"venue"
},
  "geometry": {"coordinates":[-72.823297,41.466283],"type":"Point"}
}