{
  "type": "Feature",
  "properties": {
    "addr:full":"520 Boswell Ave Norwich CT 06360",
    "addr:housenumber":"520",
    "addr:postcode":"06360",
    "addr:street":"Boswell Ave",
    "iso:country":"US",
    "sg:address":"520 Boswell Ave",
    "sg:city":"Norwich",
    "sg:classifiers":[
        {
            "category":"Shopping",
            "subcategory":"Florist",
            "type":"Retail Goods"
        }
    ],
    "sg:phone":"+1 860 887 2479",
    "sg:postcode":"06360",
    "sg:province":"CT",
    "sg:tags":[
        "fresh",
        "artificial"
    ],
    "wof:name":"Mc Kennas Flowers & Plants",
    "wof:placetype":"venue"
},
  "geometry": {"coordinates":[-72.055938,41.539306],"type":"Point"}
}