{
  "type": "Feature",
  "properties": {
    "iso:country":"US",
    "sg:address":"271 Pequot Ave",
    "sg:city":"New London",
    "sg:classifiers":[
        {
            "category":"Social Services",
            "type":"Services"
        }
    ],
    "sg:phone":"+1   ",
    "sg:postcode":"06320",
    "sg:province":"CT",
    "wof:name":"Key Service Systems Inc",
    "wof:placetype":"venue"
},
  "geometry": {"coordinates":[-72.097402,41.333887],"type":"Point"}
}