{
  "type": "Feature",
  "properties": {
    "iso:country":"US",
    "sg:address":"175 Pine St",
    "sg:city":"Columbia",
    "sg:classifiers":[
        {
            "category":"Building & Trades",
            "subcategory":"Electrical",
            "type":"Services"
        }
    ],
    "sg:phone":"+1 860 228 3814",
    "sg:postcode":"06237",
    "sg:province":"CT",
    "sg:tags":[
        "electrical",
        "contractor"
    ],
    "wof:name":"Parla & Sons Electrical",
    "wof:placetype":"venue"
},
  "geometry": {"coordinates":[-72.305623,41.667019],"type":"Point"}
}