{
  "type": "Feature",
  "properties": {
    "iso:country":"US",
    "sg:address":"382 Wolcott Rd",
    "sg:city":"Wolcott",
    "sg:classifiers":[
        {
            "category":"Retail",
            "subcategory":"Laundry & Dry Cleaning",
            "type":"Services"
        }
    ],
    "sg:phone":"+1 203 879 6195",
    "sg:postcode":"06716",
    "sg:province":"CT",
    "sg:tags":[
        "cleaners",
        "rug",
        "carpet"
    ],
    "wof:name":"Wolcott Vacuum Doctor",
    "wof:placetype":"venue"
},
  "geometry": {"coordinates":[-72.99159899999999,41.589072],"type":"Point"}
}