{
  "type": "Feature",
  "properties": {
    "addr:full":"14 Wildman St Danbury CT 06810",
    "addr:housenumber":"14",
    "addr:postcode":"06810",
    "addr:street":"Wildman St",
    "iso:country":"US",
    "sg:address":"14 Wildman St",
    "sg:city":"Danbury",
    "sg:classifiers":[
        {
            "category":"Building & Trades",
            "subcategory":"Construction",
            "type":"Services"
        }
    ],
    "sg:phone":"+1 203 792 3882",
    "sg:postcode":"06810",
    "sg:province":"CT",
    "sg:tags":[
        "general",
        "contractor"
    ],
    "wof:name":"DDS Construction Svc LLC",
    "wof:placetype":"venue"
},
  "geometry": {"coordinates":[-73.43942199999999,41.397211],"type":"Point"}
}