{
  "type": "Feature",
  "properties": {
    "iso:country":"US",
    "sg:address":"888 Washington Blvd",
    "sg:city":"Stamford",
    "sg:classifiers":[
        {
            "category":"Government",
            "subcategory":"Office",
            "type":"Public Place"
        }
    ],
    "sg:phone":"+1 203 977 4699",
    "sg:postcode":"06901",
    "sg:province":"CT",
    "sg:tags":[
        "policy"
    ],
    "wof:name":"Finance Board",
    "wof:placetype":"venue"
},
  "geometry": {"coordinates":[-73.54232500000001,41.052571],"type":"Point"}
}