{
  "type": "Feature",
  "properties": {
    "addr:full":"109 Springdale Ave Meriden CT 06451",
    "addr:housenumber":"109",
    "addr:postcode":"06451",
    "addr:street":"Springdale Ave",
    "iso:country":"US",
    "sg:address":"109 Springdale Ave",
    "sg:city":"Meriden",
    "sg:classifiers":[
        {
            "category":"Professional",
            "type":"Services"
        }
    ],
    "sg:phone":"+1 203 558 1167",
    "sg:postcode":"06451",
    "sg:province":"CT",
    "wof:name":"L & M Handymen",
    "wof:placetype":"venue"
},
  "geometry": {"coordinates":[-72.807834,41.542608],"type":"Point"}
}