{
  "type": "Feature",
  "properties": {
    "addr:full":"25 High St West Haven CT 06516",
    "addr:housenumber":"25",
    "addr:postcode":"06516",
    "addr:street":"High St",
    "iso:country":"US",
    "sg:address":"25 High St",
    "sg:city":"West Haven",
    "sg:classifiers":[
        {
            "category":"Manufacturing",
            "subcategory":"Retail Goods",
            "type":"Manufacturing & Wholesale Goods"
        }
    ],
    "sg:phone":"+1 203 931 9550",
    "sg:postcode":"06516",
    "sg:province":"CT",
    "sg:tags":[
        "manufacturer"
    ],
    "wof:name":"K & D Prec Mfg",
    "wof:placetype":"venue"
},
  "geometry": {"coordinates":[-72.954082,41.291134],"type":"Point"}
}