{
  "type": "Feature",
  "properties": {
    "iso:country":"US",
    "sg:address":"7 Sanrico Dr",
    "sg:city":"Manchester",
    "sg:classifiers":[
        {
            "category":"Wholesale",
            "subcategory":"Machinery & Supplies",
            "type":"Manufacturing & Wholesale Goods"
        }
    ],
    "sg:phone":"+1 860 643 9103",
    "sg:postcode":"06042",
    "sg:province":"CT",
    "sg:tags":[
        "equipment",
        "industrial"
    ],
    "wof:name":"Welding Equipment & Supply",
    "wof:placetype":"venue"
},
  "geometry": {"coordinates":[-72.506776,41.806208],"type":"Point"}
}