{
  "type": "Feature",
  "properties": {
    "iso:country":"US",
    "sg:address":"115 Main St",
    "sg:city":"Meriden",
    "sg:classifiers":[
        {
            "category":"Professional",
            "subcategory":"Lawyer & Legal Services",
            "type":"Services"
        }
    ],
    "sg:phone":"+1 203 237 7784",
    "sg:postcode":"06451",
    "sg:province":"CT",
    "sg:tags":[
        "attorney"
    ],
    "wof:name":"Vitello Law Firm PC",
    "wof:placetype":"venue"
},
  "geometry": {"coordinates":[-72.83099199999999,41.519188],"type":"Point"}
}