{
  "type": "Feature",
  "properties": {
    "addr:full":"381 Hopmeadow St Weatogue CT 06089",
    "addr:housenumber":"381",
    "addr:postcode":"06089",
    "addr:street":"Hopmeadow St Weatogue Ct",
    "iso:country":"US",
    "sg:address":"381 Hopmeadow St",
    "sg:city":"Weatogue",
    "sg:classifiers":[
        {
            "category":"Health Services",
            "subcategory":"Dentist",
            "type":"Services"
        }
    ],
    "sg:phone":"+1 860 658 7548",
    "sg:postcode":"06089",
    "sg:province":"CT",
    "sg:tags":[
        "pediatric"
    ],
    "wof:name":"Simsbury Pediatric & Adolescent Dentistry Llc",
    "wof:placetype":"venue"
},
  "geometry": {"coordinates":[-72.81300400000001,41.8507],"type":"Point"}
}