{
  "type": "Feature",
  "properties": {
    "iso:country":"US",
    "sg:address":"250 Calhoun St",
    "sg:city":"Washington Depot",
    "sg:classifiers":[
        {
            "category":"Manufacturing",
            "subcategory":"Lumber",
            "type":"Manufacturing & Wholesale Goods"
        }
    ],
    "sg:phone":"+1 860 868 2777",
    "sg:postcode":"06794",
    "sg:province":"CT",
    "sg:tags":[
        "operation",
        "timber",
        "tract"
    ],
    "wof:name":"Averill Farm",
    "wof:placetype":"venue"
},
  "geometry": {"coordinates":[-73.34067400000001,41.663689],"type":"Point"}
}