{
  "type": "Feature",
  "properties": {
    "addr:full":"100 Helmsford Way Windsor CT 06095",
    "addr:housenumber":"100",
    "addr:postcode":"06095",
    "addr:street":"Helmsford Way",
    "iso:country":"US",
    "sg:address":"100 Helmsford Way",
    "sg:city":"Windsor",
    "sg:classifiers":[
        {
            "category":"Wholesale",
            "subcategory":"Machinery & Supplies",
            "type":"Manufacturing & Wholesale Goods"
        }
    ],
    "sg:phone":"+1 860 298 3200",
    "sg:postcode":"06095",
    "sg:province":"CT",
    "sg:tags":[
        "equipment",
        "industrial"
    ],
    "wof:name":"Paper Plus",
    "wof:placetype":"venue"
},
  "geometry": {"coordinates":[-72.684945,41.869317],"type":"Point"}
}