{
  "type": "Feature",
  "properties": {
    "addr:full":"262 Skiff St Hamden CT 06517",
    "addr:housenumber":"262",
    "addr:postcode":"06517",
    "addr:street":"Skiff St",
    "iso:country":"US",
    "sg:address":"262 Skiff St",
    "sg:city":"Hamden",
    "sg:classifiers":[
        {
            "category":"Restaurant",
            "type":"Food & Drink"
        }
    ],
    "sg:menulink":"http://www.allmenus.com/ct/hamden/97166-ihop/menu/",
    "sg:phone":"+1 203 281 0022",
    "sg:postcode":"06517",
    "sg:province":"CT",
    "sg:tags":[
        "sandwich",
        "salad",
        "burger",
        "soup",
        "american",
        "steakhouse",
        "wrap"
    ],
    "wof:name":"IHOP",
    "wof:placetype":"venue"
},
  "geometry": {"coordinates":[-72.90736200000001,41.371501],"type":"Point"}
}