{
  "type": "Feature",
  "properties": {
    "iso:country":"US",
    "sg:address":"18 Pelham Ln",
    "sg:city":"Wilton",
    "sg:classifiers":[
        {
            "category":"Professional",
            "type":"Services"
        }
    ],
    "sg:phone":"+1   ",
    "sg:postcode":"06897",
    "sg:province":"CT",
    "wof:name":"Clifford Strategic Services LL",
    "wof:placetype":"venue"
},
  "geometry": {"coordinates":[-73.468251,41.249563],"type":"Point"}
}