{
  "type": "Feature",
  "properties": {
    "iso:country":"US",
    "sg:address":"37 Timber Trl",
    "sg:city":"Milford",
    "sg:classifiers":[
        {
            "category":"Professional",
            "subcategory":"Management & Consulting",
            "type":"Services"
        }
    ],
    "sg:phone":"+1   ",
    "sg:postcode":"06460",
    "sg:province":"CT",
    "sg:tags":[
        "business"
    ],
    "wof:name":"Occupational Safety Specialist",
    "wof:placetype":"venue"
},
  "geometry": {"coordinates":[-73.016988,41.230746],"type":"Point"}
}