{
  "type": "Feature",
  "properties": {
    "iso:country":"US",
    "sg:address":"47 W High St",
    "sg:city":"East Hampton",
    "sg:classifiers":[
        {
            "category":"Organizations",
            "subcategory":"Religious Organization",
            "type":"Services"
        }
    ],
    "sg:phone":"+1   ",
    "sg:postcode":"06424",
    "sg:province":"CT",
    "wof:name":"St Patrick Church",
    "wof:placetype":"venue"
},
  "geometry": {"coordinates":[-72.510634,41.579522],"type":"Point"}
}