{
  "type": "Feature",
  "properties": {
    "addr:full":"40 Wood Pond Rd Glastonbury CT 06033",
    "addr:housenumber":"40",
    "addr:postcode":"06033",
    "addr:street":"Wood Pond Rd",
    "iso:country":"US",
    "sg:address":"40 Wood Pond Rd",
    "sg:city":"Glastonbury",
    "sg:classifiers":[
        {
            "category":"Professional",
            "subcategory":"Engineering",
            "type":"Services"
        }
    ],
    "sg:phone":"+1   ",
    "sg:postcode":"06033",
    "sg:province":"CT",
    "wof:name":"Charles M Robinson",
    "wof:placetype":"venue"
},
  "geometry": {"coordinates":[-72.56871,41.681176],"type":"Point"}
}