{
  "type": "Feature",
  "properties": {
    "addr:full":"462 E Main St Torrington CT 06790",
    "addr:housenumber":"462",
    "addr:postcode":"06790",
    "addr:street":"E Main St",
    "iso:country":"US",
    "sg:address":"462 E Main St",
    "sg:city":"Torrington",
    "sg:classifiers":[
        {
            "category":"Ice Cream",
            "type":"Food & Drink"
        }
    ],
    "sg:menulink":"http://www.allmenus.com/ct/torrington/99029-friendlys/menu/",
    "sg:phone":"+1 860 489 4228",
    "sg:postcode":"06790",
    "sg:province":"CT",
    "sg:tags":[
        "burger",
        "american"
    ],
    "wof:name":"Friendly's",
    "wof:placetype":"venue"
},
  "geometry": {"coordinates":[-73.11165099999999,41.80662],"type":"Point"}
}