{
  "type": "Feature",
  "properties": {
    "addr:full":"19 Willard Rd Norwalk CT 06851",
    "addr:housenumber":"19",
    "addr:postcode":"06851",
    "addr:street":"Willard Rd",
    "iso:country":"US",
    "sg:address":"19 Willard Rd",
    "sg:city":"Norwalk",
    "sg:classifiers":[
        {
            "category":"Professional",
            "subcategory":"Business Services",
            "type":"Services"
        }
    ],
    "sg:phone":"+1 203 842 0226",
    "sg:postcode":"06851",
    "sg:province":"CT",
    "sg:tags":[
        "embroidery"
    ],
    "wof:name":"Let's Get Personal",
    "wof:placetype":"venue"
},
  "geometry": {"coordinates":[-73.387799,41.12896],"type":"Point"}
}