{
  "type": "Feature",
  "properties": {
    "iso:country":"US",
    "sg:address":"77 Wooster St",
    "sg:city":"Bethel",
    "sg:classifiers":[
        {
            "category":"Building & Trades",
            "subcategory":"Construction",
            "type":"Services"
        }
    ],
    "sg:phone":"+1 203 792 7450",
    "sg:postcode":"06801",
    "sg:province":"CT",
    "sg:tags":[
        "general",
        "contractor"
    ],
    "wof:name":"Cyr & Son Robert P",
    "wof:placetype":"venue"
},
  "geometry": {"coordinates":[-73.416606,41.379301],"type":"Point"}
}