{
  "type": "Feature",
  "properties": {
    "addr:full":"34 Wallingford Rd Cheshire CT 06410",
    "addr:housenumber":"34",
    "addr:postcode":"06410",
    "addr:street":"Wallingford Rd",
    "iso:country":"US",
    "sg:address":"34 Wallingford Rd",
    "sg:city":"Cheshire",
    "sg:classifiers":[
        {
            "category":"Shopping",
            "subcategory":"Gifts & Souvenirs",
            "type":"Retail Goods"
        }
    ],
    "sg:phone":"+1 203 269 4341",
    "sg:postcode":"06410",
    "sg:province":"CT",
    "sg:tags":[
        "shop"
    ],
    "wof:name":"Matilda Bear Co",
    "wof:placetype":"venue"
},
  "geometry": {"coordinates":[-72.900142,41.496648],"type":"Point"}
}