{
  "type": "Feature",
  "properties": {
    "addr:full":"156 Bloomfield Ave Windsor CT 06095",
    "addr:housenumber":"156",
    "addr:postcode":"06095",
    "addr:street":"Bloomfield Ave",
    "iso:country":"US",
    "sg:address":"156 Bloomfield Ave",
    "sg:city":"Windsor",
    "sg:classifiers":[
        {
            "category":"Government",
            "subcategory":"Office",
            "type":"Public Place"
        }
    ],
    "sg:phone":"+1 860 285 8090",
    "sg:postcode":"06095",
    "sg:province":"CT",
    "sg:tags":[
        "federal",
        "state",
        "program",
        "housing",
        "administers"
    ],
    "wof:name":"Windsor Housing",
    "wof:placetype":"venue"
},
  "geometry": {"coordinates":[-72.65148499999999,41.852267],"type":"Point"}
}