{
  "type": "Feature",
  "properties": {
    "iso:country":"US",
    "sg:address":"19 Crawford Rd",
    "sg:city":"Westport",
    "sg:classifiers":[
        {
            "category":"Shopping",
            "type":"Retail Goods"
        }
    ],
    "sg:phone":"+1 203 454 1222",
    "sg:postcode":"06880",
    "sg:province":"CT",
    "sg:tags":[
        "art",
        "gallery",
        "dealer"
    ],
    "wof:name":"Barret Fifield Art Consultants",
    "wof:placetype":"venue"
},
  "geometry": {"coordinates":[-73.385588,41.156907],"type":"Point"}
}