{
  "type": "Feature",
  "properties": {
    "addr:full":"62 Riverside Ave Westport CT 06880",
    "addr:housenumber":"62",
    "addr:postcode":"06880",
    "addr:street":"Riverside Ave",
    "iso:country":"US",
    "sg:address":"62 Riverside Ave",
    "sg:city":"Westport",
    "sg:classifiers":[
        {
            "category":"Professional",
            "subcategory":"Management & Consulting",
            "type":"Services"
        }
    ],
    "sg:phone":"+1   ",
    "sg:postcode":"06880",
    "sg:province":"CT",
    "wof:name":"Solar Connecticut-South",
    "wof:placetype":"venue"
},
  "geometry": {"coordinates":[-73.363966,41.138115],"type":"Point"}
}