{
  "type": "Feature",
  "properties": {
    "iso:country":"US",
    "sg:address":"73 Great Plain Rd",
    "sg:city":"Danbury",
    "sg:classifiers":[
        {
            "category":"Health Services",
            "subcategory":"Health Practitioner",
            "type":"Services"
        },
        {
            "category":"Health Services",
            "subcategory":"Doctor",
            "type":"Services"
        }
    ],
    "sg:phone":"+1 203 748 8107",
    "sg:postcode":"06811",
    "sg:province":"CT",
    "sg:tags":[
        "acupuncture",
        "medical"
    ],
    "wof:name":"Chinese Healing Arts Center",
    "wof:placetype":"venue"
},
  "geometry": {"coordinates":[-73.439707,41.424347],"type":"Point"}
}