{
  "type": "Feature",
  "properties": {
    "addr:full":"29 Town Farm Rd Wallingford CT 06492",
    "addr:housenumber":"29",
    "addr:postcode":"06492",
    "addr:street":"Town Farm Rd",
    "iso:country":"US",
    "sg:address":"29 Town Farm Rd",
    "sg:city":"Wallingford",
    "sg:classifiers":[
        {
            "category":"Building & Trades",
            "subcategory":"Construction",
            "type":"Services"
        }
    ],
    "sg:phone":"+1 203 294 2105",
    "sg:postcode":"06492",
    "sg:province":"CT",
    "sg:tags":[
        "marking",
        "maintenance",
        "parking"
    ],
    "wof:name":"Wallingford Public Works Dept",
    "wof:placetype":"venue"
},
  "geometry": {"coordinates":[-72.833314,41.472325],"type":"Point"}
}