{
  "type": "Feature",
  "properties": {
    "iso:country":"US",
    "sg:address":"31 Brookside Dr",
    "sg:city":"Greenwich",
    "sg:classifiers":[
        {
            "category":"Real Estate",
            "subcategory":"Real Estate Agent",
            "type":"Services"
        }
    ],
    "sg:phone":"+1 203 622 8555",
    "sg:postcode":"06830",
    "sg:province":"CT",
    "wof:name":"Noble Welch Real Estate",
    "wof:placetype":"venue"
},
  "geometry": {"coordinates":[-73.630903,41.025141],"type":"Point"}
}