{
  "type": "Feature",
  "properties": {
    "iso:country":"US",
    "sg:address":"871 Newfield St",
    "sg:city":"Middletown",
    "sg:classifiers":[
        {
            "category":"Professional",
            "subcategory":"Employment Agencies",
            "type":"Services"
        }
    ],
    "sg:phone":"+1   ",
    "sg:postcode":"06457",
    "sg:province":"CT",
    "wof:name":"Lighthouse Group",
    "wof:placetype":"venue"
},
  "geometry": {"coordinates":[-72.67315000000001,41.582849],"type":"Point"}
}