{
  "type": "Feature",
  "properties": {
    "addr:full":"369 Black Rock Tpke Easton CT 06612",
    "addr:housenumber":"369",
    "addr:postcode":"06612",
    "addr:street":"Black Rock Tpke",
    "iso:country":"US",
    "sg:address":"369 Black Rock Tpke",
    "sg:city":"Easton",
    "sg:classifiers":[
        {
            "category":"Recreation",
            "type":"Entertainment"
        }
    ],
    "sg:phone":"+1 203 268 0410",
    "sg:postcode":"06612",
    "sg:province":"CT",
    "sg:tags":[
        "place",
        "arcade",
        "amusement"
    ],
    "wof:name":"Toth Park Pool House",
    "wof:placetype":"venue"
},
  "geometry": {"coordinates":[-73.32117599999999,41.23255],"type":"Point"}
}