{
  "type": "Feature",
  "properties": {
    "addr:full":"470 Straits Tpke Watertown CT 06795",
    "addr:housenumber":"470",
    "addr:postcode":"06795",
    "addr:street":"Straits Tpke",
    "iso:country":"US",
    "sg:address":"470 Straits Tpke",
    "sg:city":"Watertown",
    "sg:classifiers":[
        {
            "category":"Travel",
            "subcategory":"Bed & Breakfast",
            "type":"Entertainment"
        }
    ],
    "sg:phone":"+1   ",
    "sg:postcode":"06795",
    "sg:province":"CT",
    "sg:tags":[
        "house"
    ],
    "wof:name":"Brookwood Manor Inc",
    "wof:placetype":"venue"
},
  "geometry": {"coordinates":[-73.100734,41.579674],"type":"Point"}
}