{
  "type": "Feature",
  "properties": {
    "iso:country":"US",
    "sg:address":"201 Platt St",
    "sg:city":"Milford",
    "sg:classifiers":[
        {
            "category":"Professional",
            "subcategory":"Business Services",
            "type":"Services"
        }
    ],
    "sg:phone":"+1   ",
    "sg:postcode":"06460",
    "sg:province":"CT",
    "wof:name":"8016 Glenwood Avenue Assoc Ltd",
    "wof:placetype":"venue"
},
  "geometry": {"coordinates":[-73.01826199999999,41.213073],"type":"Point"}
}