{
  "type": "Feature",
  "properties": {
    "addr:full":"37 Old Wheeler Ct Avon CT 06001",
    "addr:housenumber":"37",
    "addr:postcode":"06001",
    "addr:street":"Old Wheeler Ct",
    "iso:country":"US",
    "sg:address":"37 Old Wheeler Ct",
    "sg:city":"Avon",
    "sg:classifiers":[
        {
            "category":"Real Estate",
            "subcategory":"Real Estate Agent",
            "type":"Services"
        }
    ],
    "sg:phone":"+1 860 673 0107",
    "sg:postcode":"06001",
    "sg:province":"CT",
    "wof:name":"Owe Assoc Inc",
    "wof:placetype":"venue"
},
  "geometry": {"coordinates":[-72.889106,41.793791],"type":"Point"}
}