{
  "type": "Feature",
  "properties": {
    "iso:country":"US",
    "sg:address":"80 Phoenix Ave",
    "sg:city":"Waterbury",
    "sg:classifiers":[
        {
            "category":"Health Services",
            "subcategory":"Doctor",
            "type":"Services"
        }
    ],
    "sg:phone":"+1 203 757 9336",
    "sg:postcode":"06702",
    "sg:province":"CT",
    "sg:tags":[
        "physician",
        "surgeon",
        "medical"
    ],
    "wof:name":"Decio M De Escobar MD",
    "wof:placetype":"venue"
},
  "geometry": {"coordinates":[-73.03968,41.555772],"type":"Point"}
}