{
  "type": "Feature",
  "properties": {
    "iso:country":"US",
    "sg:address":"99 Colony St",
    "sg:city":"Meriden",
    "sg:classifiers":[
        {
            "category":"Professional",
            "subcategory":"Management & Consulting",
            "type":"Services"
        }
    ],
    "sg:phone":"+1 203 235 3241",
    "sg:postcode":"06451",
    "sg:province":"CT",
    "sg:tags":[
        "construction"
    ],
    "wof:name":"Hylwa Inc",
    "wof:placetype":"venue"
},
  "geometry": {"coordinates":[-72.801265,41.540124],"type":"Point"}
}