{
  "type": "Feature",
  "properties": {
    "addr:full":"20 Strawberry Ln Southington CT 06489",
    "addr:housenumber":"20",
    "addr:postcode":"06489",
    "addr:street":"Strawberry Ln",
    "iso:country":"US",
    "sg:address":"20 Strawberry Ln",
    "sg:city":"Southington",
    "sg:classifiers":[
        {
            "category":"Professional",
            "subcategory":"Employment Agencies",
            "type":"Services"
        }
    ],
    "sg:phone":"+1   ",
    "sg:postcode":"06489",
    "sg:province":"CT",
    "sg:tags":[
        "help",
        "supply"
    ],
    "wof:name":"S & S Transport Inc",
    "wof:placetype":"venue"
},
  "geometry": {"coordinates":[-72.86891799999999,41.582805],"type":"Point"}
}