{
  "type": "Feature",
  "properties": {
    "iso:country":"US",
    "sg:address":"1548 Wood Ave",
    "sg:city":"Bridgeport",
    "sg:classifiers":[
        {
            "category":"Arts & Performance",
            "subcategory":"Theater",
            "type":"Entertainment"
        }
    ],
    "sg:phone":"+1 203 336 4875",
    "sg:postcode":"06604",
    "sg:province":"CT",
    "sg:tags":[
        "musician"
    ],
    "wof:name":"Royalty Steel Pan",
    "wof:placetype":"venue"
},
  "geometry": {"coordinates":[-73.21943899999999,41.191118],"type":"Point"}
}