{
  "type": "Feature",
  "properties": {
    "addr:full":"334 Ella Grasso Tpke Windsor Locks CT 06096",
    "addr:housenumber":"334",
    "addr:postcode":"06096",
    "addr:street":"Ella Grasso Tpke;Locks Ct",
    "iso:country":"US",
    "sg:address":"334 Ella Grasso Tpke",
    "sg:city":"Windsor Locks",
    "sg:classifiers":[
        {
            "category":"Manufacturing",
            "subcategory":"Metals",
            "type":"Manufacturing & Wholesale Goods"
        }
    ],
    "sg:phone":"+1 860 627 8489",
    "sg:postcode":"06096",
    "sg:province":"CT",
    "sg:tags":[
        "blast",
        "furnace",
        "works"
    ],
    "wof:name":"Blasland Bouck & Lee Inc",
    "wof:placetype":"venue"
},
  "geometry": {"coordinates":[-72.671064,41.940861],"type":"Point"}
}