{
  "type": "Feature",
  "properties": {
    "iso:country":"US",
    "sg:address":"3 Zinn Rd",
    "sg:city":"Danbury",
    "sg:classifiers":[
        {
            "category":"Real Estate",
            "subcategory":"Real Estate Agent",
            "type":"Services"
        }
    ],
    "sg:phone":"+1 203 794 1881",
    "sg:postcode":"06811",
    "sg:province":"CT",
    "wof:name":"Arlington Woods Sales Ctr",
    "wof:placetype":"venue"
},
  "geometry": {"coordinates":[-73.483659,41.421337],"type":"Point"}
}