{
  "type": "Feature",
  "properties": {
    "iso:country":"US",
    "sg:address":"35 Higgins Dr",
    "sg:city":"Milford",
    "sg:classifiers":[
        {
            "category":"Wholesale",
            "subcategory":"Construction Materials",
            "type":"Manufacturing & Wholesale Goods"
        }
    ],
    "sg:phone":"+1 203 876 8606",
    "sg:postcode":"06460",
    "sg:province":"CT",
    "sg:tags":[
        "marble"
    ],
    "sg:website":"www.newenglandstone.com",
    "wof:name":"New England Stone",
    "wof:placetype":"venue"
},
  "geometry": {"coordinates":[-73.01602099999999,41.236309],"type":"Point"}
}