{
  "type": "Feature",
  "properties": {
    "iso:country":"US",
    "sg:address":"26 S Alton St",
    "sg:city":"Manchester",
    "sg:classifiers":[
        {
            "category":"Building & Trades",
            "subcategory":"Electrical",
            "type":"Services"
        }
    ],
    "sg:phone":"+1 860 432 0855",
    "sg:postcode":"06040",
    "sg:province":"CT",
    "sg:tags":[
        "electrical",
        "contractor"
    ],
    "wof:name":"Clear Electrical Solutions LLC",
    "wof:placetype":"venue"
},
  "geometry": {"coordinates":[-72.52894499999999,41.780518],"type":"Point"}
}