{
  "type": "Feature",
  "properties": {
    "addr:full":"23 Knollwood Ave Stamford CT 06905",
    "addr:housenumber":"23",
    "addr:postcode":"06905",
    "addr:street":"Knollwood Ave",
    "iso:country":"US",
    "sg:address":"23 Knollwood Ave",
    "sg:city":"Stamford",
    "sg:classifiers":[
        {
            "category":"Building & Trades",
            "subcategory":"Construction",
            "type":"Services"
        }
    ],
    "sg:phone":"+1 203 322 8638",
    "sg:postcode":"06905",
    "sg:province":"CT",
    "sg:tags":[
        "demolition",
        "contractor"
    ],
    "wof:name":"Connecticut Dismantling Co",
    "wof:placetype":"venue"
},
  "geometry": {"coordinates":[-73.550394,41.089368],"type":"Point"}
}