{
  "type": "Feature",
  "properties": {
    "iso:country":"US",
    "sg:address":"1 Railroad Ave",
    "sg:city":"Essex",
    "sg:classifiers":[
        {
            "category":"Restaurant",
            "type":"Food & Drink"
        }
    ],
    "sg:phone":"+1 860 767 0103",
    "sg:postcode":"06426",
    "sg:province":"CT",
    "wof:name":"Connecticut Valley Railroad Company the",
    "wof:placetype":"venue"
},
  "geometry": {"coordinates":[-72.41330000000001,41.340099],"type":"Point"}
}