{
  "type": "Feature",
  "properties": {
    "addr:full":"610 W Main St Meriden CT 06451",
    "addr:housenumber":"610",
    "addr:postcode":"06451",
    "addr:street":"W Main St",
    "iso:country":"US",
    "sg:address":"610 W Main St",
    "sg:city":"Meriden",
    "sg:classifiers":[
        {
            "category":"Shopping",
            "subcategory":"Clothing, Apparel, & Fashions",
            "type":"Retail Goods"
        }
    ],
    "sg:phone":"+1 203 238 3677",
    "sg:postcode":"06451",
    "sg:province":"CT",
    "sg:tags":[
        "tailor"
    ],
    "wof:name":"Gionfriddo Tailors",
    "wof:placetype":"venue"
},
  "geometry": {"coordinates":[-72.82329,41.540762],"type":"Point"}
}