{
  "type": "Feature",
  "properties": {
    "iso:country":"US",
    "sg:address":"411 W Putnam Ave",
    "sg:city":"Greenwich",
    "sg:classifiers":[
        {
            "category":"Banks & Credit Unions",
            "subcategory":"Financial Services",
            "type":"Services"
        },
        {
            "category":"Professional",
            "subcategory":"Management & Consulting",
            "type":"Services"
        }
    ],
    "sg:phone":"+1 203 485 8585",
    "sg:postcode":"06830",
    "sg:province":"CT",
    "sg:tags":[
        "fuel",
        "fund",
        "hedge"
    ],
    "wof:name":"Grange Park Capital Mgmt LP",
    "wof:placetype":"venue"
},
  "geometry": {"coordinates":[-73.641907,41.020596],"type":"Point"}
}