{
  "type": "Feature",
  "properties": {
    "addr:full":"67 Sylvan Ave Hartford CT 06107",
    "addr:housenumber":"67",
    "addr:postcode":"06107",
    "addr:street":"Sylvan Ave;Ct",
    "iso:country":"US",
    "sg:address":"67 Sylvan Ave",
    "sg:city":"Hartford",
    "sg:classifiers":[
        {
            "category":"Professional",
            "type":"Services"
        }
    ],
    "sg:phone":"+1 860 229 9500",
    "sg:postcode":"06107",
    "sg:province":"CT",
    "wof:name":"Rick Green",
    "wof:placetype":"venue"
},
  "geometry": {"coordinates":[-72.744192,41.766805],"type":"Point"}
}