{
  "type": "Feature",
  "properties": {
    "addr:full":"12 Starr Ave Danbury CT 06810",
    "addr:housenumber":"12",
    "addr:postcode":"06810",
    "addr:street":"Starr Ave",
    "iso:country":"US",
    "sg:address":"12 Starr Ave",
    "sg:city":"Danbury",
    "sg:classifiers":[
        {
            "category":"Education",
            "subcategory":"Special Training",
            "type":"Public Place"
        }
    ],
    "sg:phone":"+1   ",
    "sg:postcode":"06810",
    "sg:province":"CT",
    "wof:name":"Christina Rovics Vocal Studio",
    "wof:placetype":"venue"
},
  "geometry": {"coordinates":[-73.46426700000001,41.400313],"type":"Point"}
}