{
  "type": "Feature",
  "properties": {
    "iso:country":"US",
    "sg:address":"20 Commerce Rd",
    "sg:city":"Newtown",
    "sg:classifiers":[
        {
            "category":"Professional",
            "type":"Services"
        }
    ],
    "sg:phone":"+1 203 426 2521",
    "sg:postcode":"06470",
    "sg:province":"CT",
    "sg:tags":[
        "establishment"
    ],
    "wof:name":"Gypsum Specialists",
    "wof:placetype":"venue"
},
  "geometry": {"coordinates":[-73.284094,41.414684],"type":"Point"}
}