{
  "type": "Feature",
  "properties": {
    "addr:full":"883 Robert Treat Exd Orange CT 06477",
    "addr:housenumber":"883",
    "addr:postcode":"06477",
    "addr:street":"Robert Treat Exd",
    "iso:country":"US",
    "sg:address":"883 Robert Treat Exd",
    "sg:city":"Orange",
    "sg:classifiers":[
        {
            "category":"Health Services",
            "subcategory":"Clinic",
            "type":"Services"
        }
    ],
    "sg:phone":"+1   ",
    "sg:postcode":"06477",
    "sg:province":"CT",
    "wof:name":"Connecticut Health Direct LLC",
    "wof:placetype":"venue"
},
  "geometry": {"coordinates":[-73.037205,41.29727],"type":"Point"}
}