{
  "type": "Feature",
  "properties": {
    "iso:country":"US",
    "sg:address":"1379 Boston Post Rd",
    "sg:city":"Old Saybrook",
    "sg:classifiers":[
        {
            "category":"Retail",
            "subcategory":"Auto Repair",
            "type":"Services"
        }
    ],
    "sg:phone":"+1 860 395 1290",
    "sg:postcode":"06475",
    "sg:province":"CT",
    "sg:tags":[
        "motorcycle"
    ],
    "wof:name":"A & E American Legends Llc",
    "wof:placetype":"venue"
},
  "geometry": {"coordinates":[-72.404099,41.287201],"type":"Point"}
}