{
  "type": "Feature",
  "properties": {
    "addr:full":"909 Whalley Ave New Haven CT 06515",
    "addr:housenumber":"909",
    "addr:postcode":"06515",
    "addr:street":"Whalley Ave",
    "iso:country":"US",
    "sg:address":"909 Whalley Ave",
    "sg:city":"New Haven",
    "sg:classifiers":[
        {
            "category":"Social Services",
            "type":"Services"
        }
    ],
    "sg:phone":"+1 203 387 7670",
    "sg:postcode":"06515",
    "sg:province":"CT",
    "sg:tags":[
        "counselor",
        "marriage",
        "family"
    ],
    "wof:name":"Hubbard Dianetics Foundation",
    "wof:placetype":"venue"
},
  "geometry": {"coordinates":[-72.960069,41.327067],"type":"Point"}
}