{
  "type": "Feature",
  "properties": {
    "addr:full":"2441 Berlin Tpke Newington CT 06111",
    "addr:housenumber":"2441",
    "addr:postcode":"06111",
    "addr:street":"Berlin Tpke",
    "iso:country":"US",
    "sg:address":"2441 Berlin Tpke",
    "sg:city":"Newington",
    "sg:classifiers":[
        {
            "category":"Manufacturing",
            "subcategory":"Chemicals & Compounds",
            "type":"Manufacturing & Wholesale Goods"
        }
    ],
    "sg:phone":"+1 860 665 9500",
    "sg:postcode":"06111",
    "sg:province":"CT",
    "sg:tags":[
        "preparation",
        "mfg"
    ],
    "wof:name":"Island Fireworks",
    "wof:placetype":"venue"
},
  "geometry": {"coordinates":[-72.708578,41.685427],"type":"Point"}
}