{
  "type": "Feature",
  "properties": {
    "iso:country":"US",
    "sg:address":"82 Parry Rd",
    "sg:city":"Stamford",
    "sg:classifiers":[
        {
            "category":"Building & Trades",
            "subcategory":"Landscaping Services",
            "type":"Services"
        }
    ],
    "sg:phone":"+1 203 329 8875",
    "sg:postcode":"06907",
    "sg:province":"CT",
    "wof:name":"A Loglisci Landscaping",
    "wof:placetype":"venue"
},
  "geometry": {"coordinates":[-73.52292,41.116811],"type":"Point"}
}