{
  "type": "Feature",
  "properties": {
    "iso:country":"US",
    "sg:address":"77 River Edge Farms Rd",
    "sg:city":"Madison",
    "sg:classifiers":[
        {
            "category":"Restaurant",
            "type":"Food & Drink"
        }
    ],
    "sg:phone":"+1   ",
    "sg:postcode":"06443",
    "sg:province":"CT",
    "sg:tags":[
        "motel"
    ],
    "wof:name":"Dolly Madison Inn Inc",
    "wof:placetype":"venue"
},
  "geometry": {"coordinates":[-72.637725,41.275669],"type":"Point"}
}