{
  "type": "Feature",
  "properties": {
    "iso:country":"US",
    "sg:address":"1926 Main St",
    "sg:city":"Bridgeport",
    "sg:classifiers":[
        {
            "category":"Autos & Motor Vehicles",
            "subcategory":"Automobile Sales",
            "type":"Retail Goods"
        }
    ],
    "sg:phone":"+1 203 579 0360",
    "sg:postcode":"06604",
    "sg:province":"CT",
    "sg:tags":[
        "car",
        "used",
        "dealer"
    ],
    "wof:name":"Tuozzoli Brothers Auto Sales",
    "wof:placetype":"venue"
},
  "geometry": {"coordinates":[-73.195751,41.18989],"type":"Point"}
}