{
  "type": "Feature",
  "properties": {
    "iso:country":"US",
    "sg:address":"9 Union St",
    "sg:city":"Southbury",
    "sg:classifiers":[
        {
            "category":"Professional",
            "subcategory":"Business Services",
            "type":"Services"
        }
    ],
    "sg:phone":"+1   ",
    "sg:postcode":"06483",
    "sg:province":"CT",
    "wof:name":"Buisiness and Shipping Center",
    "wof:placetype":"venue"
},
  "geometry": {"coordinates":[-73.06871700000001,41.387969],"type":"Point"}
}