{
  "type": "Feature",
  "properties": {
    "iso:country":"US",
    "sg:address":"12 Mill Plain Rd",
    "sg:city":"Danbury",
    "sg:classifiers":[
        {
            "category":"Building & Trades",
            "subcategory":"Construction",
            "type":"Services"
        },
        {
            "category":"Home & Garden",
            "subcategory":"Home Furnishings",
            "type":"Retail Goods"
        }
    ],
    "sg:phone":"+1 203 748 5289",
    "sg:postcode":"06811",
    "sg:province":"CT",
    "sg:tags":[
        "bathroom",
        "kitchen",
        "fixture",
        "remodels",
        "accessory"
    ],
    "wof:name":"Rucon Custom Kitchens",
    "wof:placetype":"venue"
},
  "geometry": {"coordinates":[-73.493036,41.387035],"type":"Point"}
}