{
  "type": "Feature",
  "properties": {
    "addr:full":"48 Railroad Pl Westport CT 06880",
    "addr:housenumber":"48",
    "addr:postcode":"06880",
    "addr:street":"Railroad Pl",
    "iso:country":"US",
    "sg:address":"48 Railroad Pl",
    "sg:city":"Westport",
    "sg:classifiers":[
        {
            "category":"Professional",
            "subcategory":"Accounting & Tax Preparation",
            "type":"Services"
        }
    ],
    "sg:phone":"+1   ",
    "sg:postcode":"06880",
    "sg:province":"CT",
    "sg:tags":[
        "return"
    ],
    "wof:name":"Straczek Johanna Co",
    "wof:placetype":"venue"
},
  "geometry": {"coordinates":[-73.37130000000001,41.119131],"type":"Point"}
}