{
  "type": "Feature",
  "properties": {
    "iso:country":"US",
    "sg:address":"201 E Main St",
    "sg:city":"Branford",
    "sg:classifiers":[
        {
            "category":"Retail",
            "subcategory":"Veterinary Services",
            "type":"Services"
        }
    ],
    "sg:phone":"+1 203 488 3949",
    "sg:postcode":"06405",
    "sg:province":"CT",
    "wof:name":"Branford Veterinary Hospital",
    "wof:placetype":"venue"
},
  "geometry": {"coordinates":[-72.804186,41.287981],"type":"Point"}
}