{
  "type": "Feature",
  "properties": {
    "addr:full":"1397 Wood Ave Bridgeport CT 06604",
    "addr:housenumber":"1397",
    "addr:postcode":"06604",
    "addr:street":"Wood Ave",
    "iso:country":"US",
    "sg:address":"1397 Wood Ave",
    "sg:city":"Bridgeport",
    "sg:classifiers":[
        {
            "category":"Professional",
            "subcategory":"Lawyer & Legal Services",
            "type":"Services"
        }
    ],
    "sg:phone":"+1   ",
    "sg:postcode":"06604",
    "sg:province":"CT",
    "wof:name":"P A Barone Consultg",
    "wof:placetype":"venue"
},
  "geometry": {"coordinates":[-73.21852199999999,41.189795],"type":"Point"}
}