{
  "type": "Feature",
  "properties": {
    "iso:country":"US",
    "sg:address":"27 Bridge St",
    "sg:city":"Greenwich",
    "sg:classifiers":[
        {
            "category":"Professional",
            "type":"Services"
        }
    ],
    "sg:phone":"+1 203 912 3586",
    "sg:postcode":"06830",
    "sg:province":"CT",
    "wof:name":"Vhikusnii",
    "wof:placetype":"venue"
},
  "geometry": {"coordinates":[-73.633342,41.022088],"type":"Point"}
}