{
  "type": "Feature",
  "properties": {
    "iso:country":"US",
    "sg:address":"21 Garden St",
    "sg:city":"Branford",
    "sg:classifiers":[
        {
            "category":"Banks & Credit Unions",
            "subcategory":"Bank",
            "type":"Services"
        }
    ],
    "sg:phone":"+1 203 488 6084",
    "sg:postcode":"06405",
    "sg:province":"CT",
    "sg:tags":[
        "broker",
        "mortgage"
    ],
    "wof:name":"Branford Financial LLC",
    "wof:placetype":"venue"
},
  "geometry": {"coordinates":[-72.808099,41.268847],"type":"Point"}
}