{
  "type": "Feature",
  "properties": {
    "iso:country":"US",
    "sg:address":"55 Meloy Rd",
    "sg:city":"West Haven",
    "sg:classifiers":[
        {
            "category":"Building & Trades",
            "subcategory":"Construction",
            "type":"Services"
        }
    ],
    "sg:phone":"+1 203 931 9680",
    "sg:postcode":"06516",
    "sg:province":"CT",
    "sg:tags":[
        "tile",
        "dealer"
    ],
    "wof:name":"Amel Tile & Marble",
    "wof:placetype":"venue"
},
  "geometry": {"coordinates":[-72.973001,41.274232],"type":"Point"}
}