{
  "type": "Feature",
  "properties": {
    "iso:country":"US",
    "sg:address":"22 Prospect St",
    "sg:city":"Ridgefield",
    "sg:classifiers":[
        {
            "category":"Health Services",
            "subcategory":"Doctor",
            "type":"Services"
        }
    ],
    "sg:phone":"+1 203 438 4640",
    "sg:postcode":"06877",
    "sg:province":"CT",
    "sg:tags":[
        "dentist"
    ],
    "wof:name":"A P Dental Care",
    "wof:placetype":"venue"
},
  "geometry": {"coordinates":[-73.497798,41.283275],"type":"Point"}
}