{
  "type": "Feature",
  "properties": {
    "addr:full":"1205 Old Colony Rd Wallingford CT 06492",
    "addr:housenumber":"1205",
    "addr:postcode":"06492",
    "addr:street":"Old Colony Rd",
    "iso:country":"US",
    "sg:address":"1205 Old Colony Rd",
    "sg:city":"Wallingford",
    "sg:classifiers":[
        {
            "category":"Professional",
            "type":"Services"
        }
    ],
    "sg:phone":"+1 203 269 1128",
    "sg:postcode":"06492",
    "sg:province":"CT",
    "wof:name":"Susan Klavins Ind Hergali",
    "wof:placetype":"venue"
},
  "geometry": {"coordinates":[-72.81648,41.508552],"type":"Point"}
}