{
  "type": "Feature",
  "properties": {
    "addr:full":"794 Federal Rd Brookfield CT 06804",
    "addr:housenumber":"794",
    "addr:postcode":"06804",
    "addr:street":"Federal Rd",
    "iso:country":"US",
    "sg:address":"794 Federal Rd",
    "sg:city":"Brookfield",
    "sg:classifiers":[
        {
            "category":"Autos & Motor Vehicles",
            "subcategory":"Auto Supplies",
            "type":"Retail Goods"
        },
        {
            "category":"Retail",
            "subcategory":"Auto Repair",
            "type":"Services"
        }
    ],
    "sg:phone":"+1 203 775 1976",
    "sg:postcode":"06804",
    "sg:province":"CT",
    "sg:tags":[
        "wheel",
        "absorber",
        "oil",
        "tire",
        "shock",
        "lube",
        "strut",
        "servicing-automotive",
        "balancing",
        "axle",
        "wheels-aligning",
        "alignment-frame",
        "brake"
    ],
    "wof:name":"Best Buy Discount Tires Inc.",
    "wof:placetype":"venue"
},
  "geometry": {"coordinates":[-73.409282,41.481337],"type":"Point"}
}