{
  "type": "Feature",
  "properties": {
    "iso:country":"US",
    "sg:address":"20 Ocean View Dr",
    "sg:city":"Stamford",
    "sg:classifiers":[
        {
            "category":"Building & Trades",
            "subcategory":"Equipment Rental",
            "type":"Services"
        }
    ],
    "sg:phone":"+1 203 327 1867",
    "sg:postcode":"06902",
    "sg:province":"CT",
    "sg:tags":[
        "credit",
        "business"
    ],
    "wof:name":"Ocean View Funding Inc",
    "wof:placetype":"venue"
},
  "geometry": {"coordinates":[-73.51924099999999,41.027019],"type":"Point"}
}