{
  "type": "Feature",
  "properties": {
    "addr:full":"53 Skyline Dr Brookfield CT 06804",
    "addr:housenumber":"53",
    "addr:postcode":"06804",
    "addr:street":"Skyline Dr",
    "iso:country":"US",
    "sg:address":"53 Skyline Dr",
    "sg:city":"Brookfield",
    "sg:classifiers":[
        {
            "category":"Professional",
            "type":"Services"
        }
    ],
    "sg:phone":"+1 203 740 7132",
    "sg:postcode":"06804",
    "sg:province":"CT",
    "wof:name":"Blue Ridge Systems LLC",
    "wof:placetype":"venue"
},
  "geometry": {"coordinates":[-73.438327,41.478412],"type":"Point"}
}