{
  "type": "Feature",
  "properties": {
    "addr:full":"8 Branford Rd North Branford CT 06471",
    "addr:housenumber":"8",
    "addr:postcode":"06471",
    "addr:street":"Branford Rd North Branford Ct",
    "iso:country":"US",
    "sg:address":"8 Branford Rd",
    "sg:city":"North Branford",
    "sg:classifiers":[
        {
            "category":"Real Estate",
            "subcategory":"Real Estate Agent",
            "type":"Services"
        },
        {
            "category":"Social Services",
            "subcategory":"Child Care",
            "type":"Services"
        }
    ],
    "sg:phone":"+1 203 315 9901",
    "sg:postcode":"06471",
    "sg:province":"CT",
    "sg:tags":[
        "agency",
        "rental",
        "day"
    ],
    "wof:name":"New Start Rentals LLC",
    "wof:placetype":"venue"
},
  "geometry": {"coordinates":[-72.770937,41.305494],"type":"Point"}
}