{
  "type": "Feature",
  "properties": {
    "iso:country":"US",
    "sg:address":"631 Brandy Hill Rd",
    "sg:city":"Torrington",
    "sg:classifiers":[
        {
            "category":"Social Services",
            "type":"Services"
        }
    ],
    "sg:phone":"+1   ",
    "sg:postcode":"06790",
    "sg:province":"CT",
    "wof:name":"Carolyn Scholz",
    "wof:placetype":"venue"
},
  "geometry": {"coordinates":[-73.16644599999999,41.848203],"type":"Point"}
}