{
  "type": "Feature",
  "properties": {
    "addr:full":"31 River Dr Norwalk CT 06855",
    "addr:housenumber":"31",
    "addr:postcode":"06855",
    "addr:street":"River Dr",
    "iso:country":"US",
    "sg:address":"31 River Dr",
    "sg:city":"Norwalk",
    "sg:classifiers":[
        {
            "category":"Professional",
            "subcategory":"Business Services",
            "type":"Services"
        }
    ],
    "sg:phone":"+1   ",
    "sg:postcode":"06855",
    "sg:province":"CT",
    "wof:name":"PMG Ad Group",
    "wof:placetype":"venue"
},
  "geometry": {"coordinates":[-73.400333,41.091492],"type":"Point"}
}