{
  "type": "Feature",
  "properties": {
    "addr:full":"640 Davis St Exd Watertown CT 06795",
    "addr:housenumber":"640",
    "addr:postcode":"06795",
    "addr:street":"Davis St Exd",
    "iso:country":"US",
    "sg:address":"640 Davis St Exd",
    "sg:city":"Watertown",
    "sg:classifiers":[
        {
            "category":"Health Services",
            "subcategory":"Health Practitioner",
            "type":"Services"
        }
    ],
    "sg:phone":"+1   ",
    "sg:postcode":"06795",
    "sg:province":"CT",
    "wof:name":"Joseph R Gugliotti",
    "wof:placetype":"venue"
},
  "geometry": {"coordinates":[-73.103683,41.578716],"type":"Point"}
}