{
  "type": "Feature",
  "properties": {
    "iso:country":"US",
    "sg:address":"23 Seemans Ln",
    "sg:city":"Milford",
    "sg:classifiers":[
        {
            "category":"Retail",
            "subcategory":"Car Wash",
            "type":"Services"
        }
    ],
    "sg:phone":"+1 203 877 1114",
    "sg:postcode":"06460",
    "sg:province":"CT",
    "sg:tags":[
        "automobile",
        "detail",
        "clean"
    ],
    "wof:name":"Super Shine Of Milford",
    "wof:placetype":"venue"
},
  "geometry": {"coordinates":[-73.073699,41.210056],"type":"Point"}
}