{
  "type": "Feature",
  "properties": {
    "addr:full":"800 Summer St Stamford CT 06901",
    "addr:housenumber":"800",
    "addr:postcode":"06901",
    "addr:street":"Summer St",
    "iso:country":"US",
    "sg:address":"800 Summer St",
    "sg:city":"Stamford",
    "sg:classifiers":[
        {
            "category":"Real Estate",
            "subcategory":"Real Estate Agent",
            "type":"Services"
        }
    ],
    "sg:phone":"+1 203 977 1615",
    "sg:postcode":"06901",
    "sg:province":"CT",
    "sg:tags":[
        "management"
    ],
    "wof:name":"Preferred Property Mgmt Inc",
    "wof:placetype":"venue"
},
  "geometry": {"coordinates":[-73.54010599999999,41.05833],"type":"Point"}
}