{
  "type": "Feature",
  "properties": {
    "iso:country":"US",
    "sg:address":"55 King St",
    "sg:city":"Danbury",
    "sg:classifiers":[
        {
            "category":"Professional",
            "subcategory":"Advertising",
            "type":"Services"
        }
    ],
    "sg:phone":"+1 203 748 9298",
    "sg:postcode":"06811",
    "sg:province":"CT",
    "sg:tags":[
        "designer",
        "display",
        "producer"
    ],
    "wof:name":"Downing Displays Diers Group",
    "wof:placetype":"venue"
},
  "geometry": {"coordinates":[-73.513543,41.432408],"type":"Point"}
}