{
  "type": "Feature",
  "properties": {
    "iso:country":"US",
    "sg:address":"24 Highland Ave",
    "sg:city":"Ansonia",
    "sg:classifiers":[
        {
            "category":"Professional",
            "subcategory":"Detective & Security Services",
            "type":"Services"
        }
    ],
    "sg:phone":"+1 203 734 5344",
    "sg:postcode":"06401",
    "sg:province":"CT",
    "sg:tags":[
        "system"
    ],
    "wof:name":"B & B Security Systems",
    "wof:placetype":"venue"
},
  "geometry": {"coordinates":[-73.06691600000001,41.341502],"type":"Point"}
}