{
  "type": "Feature",
  "properties": {
    "addr:full":"11 Prospect Hill Deep River CT 06417",
    "addr:housenumber":"11",
    "addr:postcode":"06417",
    "addr:street":"Prospect Hill",
    "iso:country":"US",
    "sg:address":"11 Prospect Hill",
    "sg:city":"Deep River",
    "sg:classifiers":[
        {
            "category":"Professional",
            "subcategory":"Business Services",
            "type":"Services"
        }
    ],
    "sg:phone":"+1   ",
    "sg:postcode":"06417",
    "sg:province":"CT",
    "wof:name":"Diversified Business Systems",
    "wof:placetype":"venue"
},
  "geometry": {"coordinates":[-72.436707,41.389921],"type":"Point"}
}