{
  "type": "Feature",
  "properties": {
    "iso:country":"US",
    "sg:address":"412 State Hwy 165",
    "sg:city":"Preston",
    "sg:classifiers":[
        {
            "category":"Government",
            "subcategory":"Fire Station",
            "type":"Public Place"
        }
    ],
    "sg:phone":"+1 860 887 4815",
    "sg:postcode":"06365",
    "sg:province":"CT",
    "sg:tags":[
        "protection"
    ],
    "wof:name":"Preston City Fire Dept",
    "wof:placetype":"venue"
},
  "geometry": {"coordinates":[-71.971344,41.530966],"type":"Point"}
}