{
  "type": "Feature",
  "properties": {
    "addr:full":"54 N Hill Rd North Haven CT 06473",
    "addr:housenumber":"54",
    "addr:postcode":"06473",
    "addr:street":"N Hill Rd;Haven",
    "iso:country":"US",
    "sg:address":"54 N Hill Rd",
    "sg:city":"North Haven",
    "sg:classifiers":[
        {
            "category":"Farming",
            "subcategory":"Farm",
            "type":"Manufacturing & Wholesale Goods"
        }
    ],
    "sg:phone":"+1 203 239 7237",
    "sg:postcode":"06473",
    "sg:province":"CT",
    "sg:tags":[
        "ornamental",
        "nursery",
        "crop",
        "general"
    ],
    "wof:name":"Valentino Farms",
    "wof:placetype":"venue"
},
  "geometry": {"coordinates":[-72.836566,41.366328],"type":"Point"}
}