{
  "type": "Feature",
  "properties": {
    "addr:full":"333 Ridge Rd Orange CT 06477",
    "addr:housenumber":"333",
    "addr:postcode":"06477",
    "addr:street":"Ridge Rd",
    "iso:country":"US",
    "sg:address":"333 Ridge Rd",
    "sg:city":"Orange",
    "sg:classifiers":[
        {
            "category":"Bars & Pubs",
            "type":"Food & Drink"
        }
    ],
    "sg:phone":"+1 203 795 3006",
    "sg:postcode":"06477",
    "sg:province":"CT",
    "sg:tags":[
        "drinking"
    ],
    "wof:name":"Outer Limits",
    "wof:placetype":"venue"
},
  "geometry": {"coordinates":[-73.043952,41.260055],"type":"Point"}
}