{
  "type": "Feature",
  "properties": {
    "addr:full":"57 Danbury Rd Wilton CT 06897",
    "addr:housenumber":"57",
    "addr:postcode":"06897",
    "addr:street":"Danbury Rd Wilton Ct",
    "iso:country":"US",
    "sg:address":"57 Danbury Rd",
    "sg:city":"Wilton",
    "sg:classifiers":[
        {
            "category":"Real Estate",
            "subcategory":"Real Estate Operator",
            "type":"Services"
        }
    ],
    "sg:phone":"+1 203 762 1233",
    "sg:postcode":"06897",
    "sg:province":"CT",
    "sg:tags":[
        "building",
        "agency",
        "advertising",
        "nonresidential"
    ],
    "wof:name":"John Frieda Hair Care",
    "wof:placetype":"venue"
},
  "geometry": {"coordinates":[-73.417456,41.166322],"type":"Point"}
}