{
  "type": "Feature",
  "properties": {
    "addr:full":"10 Rockwell St Norwich CT 06360",
    "addr:housenumber":"10",
    "addr:postcode":"06360",
    "addr:street":"Rockwell St Norwich Ct",
    "iso:country":"US",
    "sg:address":"10 Rockwell St",
    "sg:city":"Norwich",
    "sg:classifiers":[
        {
            "category":"Wholesale",
            "subcategory":"Non-durable Goods",
            "type":"Manufacturing & Wholesale Goods"
        }
    ],
    "sg:phone":"+1 860 859 2078",
    "sg:postcode":"06360",
    "sg:province":"CT",
    "wof:name":"C & C Enterprises",
    "wof:placetype":"venue"
},
  "geometry": {"coordinates":[-72.079848,41.534404],"type":"Point"}
}