{
  "type": "Feature",
  "properties": {
    "addr:full":"3 Washington Ridge Rd East Granby CT 06026",
    "addr:housenumber":"3",
    "addr:postcode":"06026",
    "addr:street":"Washington Ridge Rd East Granby Ct",
    "iso:country":"US",
    "sg:address":"3 Washington Ridge Rd",
    "sg:city":"East Granby",
    "sg:classifiers":[
        {
            "category":"Insurance",
            "subcategory":"Life Insurance",
            "type":"Services"
        }
    ],
    "sg:phone":"+1 860 408 9669",
    "sg:postcode":"06026",
    "sg:province":"CT",
    "sg:tags":[
        "carrier"
    ],
    "wof:name":"Management Research Assoc",
    "wof:placetype":"venue"
},
  "geometry": {"coordinates":[-72.760043,41.932021],"type":"Point"}
}