{
  "type": "Feature",
  "properties": {
    "addr:full":"39 Hilldale Ct Milford CT 06460",
    "addr:housenumber":"39",
    "addr:postcode":"06460",
    "addr:street":"Hilldale Ct",
    "iso:country":"US",
    "sg:address":"39 Hilldale Ct",
    "sg:city":"Milford",
    "sg:classifiers":[
        {
            "category":"Health Services",
            "subcategory":"Doctor",
            "type":"Services"
        }
    ],
    "sg:phone":"+1   ",
    "sg:postcode":"06460",
    "sg:province":"CT",
    "sg:tags":[
        "medical"
    ],
    "wof:name":"Kalvin H Block",
    "wof:placetype":"venue"
},
  "geometry": {"coordinates":[-73.012263,41.208718],"type":"Point"}
}