{
  "type": "Feature",
  "properties": {
    "iso:country":"US",
    "sg:address":"70 Hartford Tpke",
    "sg:city":"Tolland",
    "sg:classifiers":[
        {
            "category":"Retail",
            "subcategory":"Veterinary Services",
            "type":"Services"
        }
    ],
    "sg:phone":"+1 860 875 5748",
    "sg:postcode":"06084",
    "sg:province":"CT",
    "sg:tags":[
        "veterinarian",
        "specialty"
    ],
    "wof:name":"Abo, Patricia J",
    "wof:placetype":"venue"
},
  "geometry": {"coordinates":[-72.411552,41.869041],"type":"Point"}
}