{
  "type": "Feature",
  "properties": {
    "addr:full":"955 S Main St Middletown CT 06457",
    "addr:housenumber":"955",
    "addr:postcode":"06457",
    "addr:street":"S Main St",
    "iso:country":"US",
    "sg:address":"955 S Main St",
    "sg:city":"Middletown",
    "sg:classifiers":[
        {
            "category":"Health Services",
            "subcategory":"Doctor",
            "type":"Services"
        }
    ],
    "sg:phone":"+1   ",
    "sg:postcode":"06457",
    "sg:province":"CT",
    "sg:tags":[
        "dentist"
    ],
    "wof:name":"Michelle S Lacey DMD",
    "wof:placetype":"venue"
},
  "geometry": {"coordinates":[-72.658631,41.532097],"type":"Point"}
}