{
  "type": "Feature",
  "properties": {
    "iso:country":"US",
    "sg:address":"1585 Cheshire St",
    "sg:city":"Cheshire",
    "sg:classifiers":[
        {
            "category":"Building & Trades",
            "subcategory":"Construction",
            "type":"Services"
        }
    ],
    "sg:phone":"+1 203 272 4348",
    "sg:postcode":"06410",
    "sg:province":"CT",
    "sg:tags":[
        "contractor"
    ],
    "wof:name":"Pierce & Sons Construction Inc",
    "wof:placetype":"venue"
},
  "geometry": {"coordinates":[-72.867784,41.539968],"type":"Point"}
}