{
  "type": "Feature",
  "properties": {
    "iso:country":"US",
    "sg:address":"1 1st St",
    "sg:city":"Seymour",
    "sg:classifiers":[
        {
            "category":"Government",
            "subcategory":"Office",
            "type":"Public Place"
        }
    ],
    "sg:phone":"+1 203 888 2511",
    "sg:postcode":"06483",
    "sg:province":"CT",
    "sg:tags":[
        "village"
    ],
    "sg:website":"www.seymourct.org",
    "wof:name":"Seymour Selectmen's Office",
    "wof:placetype":"venue"
},
  "geometry": {"coordinates":[-73.073965,41.39414],"type":"Point"}
}