{
  "type": "Feature",
  "properties": {
    "iso:country":"US",
    "sg:address":"58 Farmbrook Dr",
    "sg:city":"Tolland",
    "sg:classifiers":[
        {
            "category":"Professional",
            "subcategory":"Management & Consulting",
            "type":"Services"
        }
    ],
    "sg:phone":"+1   ",
    "sg:postcode":"06084",
    "sg:province":"CT",
    "wof:name":"Simply Lean LLC",
    "wof:placetype":"venue"
},
  "geometry": {"coordinates":[-72.3531,41.873834],"type":"Point"}
}