{
  "type": "Feature",
  "properties": {
    "addr:full":"220 W Main St Avon CT 06001",
    "addr:housenumber":"220",
    "addr:postcode":"06001",
    "addr:street":"W Main St",
    "iso:country":"US",
    "sg:address":"220 W Main St",
    "sg:city":"Avon",
    "sg:classifiers":[
        {
            "category":"Building & Trades",
            "subcategory":"Cleaning & Sanitation",
            "type":"Services"
        }
    ],
    "sg:phone":"+1 860 284 9405",
    "sg:postcode":"06001",
    "sg:province":"CT",
    "sg:tags":[
        "home"
    ],
    "sg:website":"www.maidpro.com",
    "wof:name":"Maidpro",
    "wof:placetype":"venue"
},
  "geometry": {"coordinates":[-72.8489,41.811798],"type":"Point"}
}