{
  "type": "Feature",
  "properties": {
    "iso:country":"US",
    "sg:address":"129 Berlin St",
    "sg:city":"East Berlin",
    "sg:classifiers":[
        {
            "category":"Professional",
            "subcategory":"Management & Consulting",
            "type":"Services"
        }
    ],
    "sg:phone":"+1   ",
    "sg:postcode":"06023",
    "sg:province":"CT",
    "sg:tags":[
        "business"
    ],
    "wof:name":"Ssrt Consultants LLC",
    "wof:placetype":"venue"
},
  "geometry": {"coordinates":[-72.721976,41.617611],"type":"Point"}
}