{
  "type": "Feature",
  "properties": {
    "addr:full":"20 Ridge Dr Westport CT 06880",
    "addr:housenumber":"20",
    "addr:postcode":"06880",
    "addr:street":"Ridge Dr",
    "iso:country":"US",
    "sg:address":"20 Ridge Dr",
    "sg:city":"Westport",
    "sg:classifiers":[
        {
            "category":"Shopping",
            "type":"Retail Goods"
        }
    ],
    "sg:phone":"+1 203 227 3583",
    "sg:postcode":"06880",
    "sg:province":"CT",
    "sg:tags":[
        "art",
        "gallery",
        "dealer"
    ],
    "wof:name":"Corporate Properties Inc",
    "wof:placetype":"venue"
},
  "geometry": {"coordinates":[-73.36543500000001,41.125591],"type":"Point"}
}