{
  "type": "Feature",
  "properties": {
    "addr:full":"520 Watertown Ave Waterbury CT 06708",
    "addr:housenumber":"520",
    "addr:postcode":"06708",
    "addr:street":"Watertown Ave",
    "iso:country":"US",
    "sg:address":"520 Watertown Ave",
    "sg:city":"Waterbury",
    "sg:classifiers":[
        {
            "category":"Retail",
            "subcategory":"Auto Repair",
            "type":"Services"
        }
    ],
    "sg:phone":"+1   ",
    "sg:postcode":"06708",
    "sg:province":"CT",
    "sg:tags":[
        "general"
    ],
    "wof:name":"William D Strakosch",
    "wof:placetype":"venue"
},
  "geometry": {"coordinates":[-73.05940099999999,41.565],"type":"Point"}
}