{
  "type": "Feature",
  "properties": {
    "iso:country":"US",
    "sg:address":"43 Wethersfield Ave",
    "sg:city":"Hartford",
    "sg:classifiers":[
        {
            "category":"Retail",
            "subcategory":"Funeral Services",
            "type":"Services"
        }
    ],
    "sg:phone":"+1 860 246 1413",
    "sg:postcode":"06114",
    "sg:province":"CT",
    "sg:tags":[
        "director"
    ],
    "wof:name":"South Green Memorial Home Inc",
    "wof:placetype":"venue"
},
  "geometry": {"coordinates":[-72.674857,41.754835],"type":"Point"}
}