{
  "type": "Feature",
  "properties": {
    "iso:country":"US",
    "sg:address":"114 W Main St",
    "sg:city":"New Britain",
    "sg:classifiers":[
        {
            "category":"Professional",
            "subcategory":"Employment Agencies",
            "type":"Services"
        }
    ],
    "sg:phone":"+1   ",
    "sg:postcode":"06052",
    "sg:province":"CT",
    "wof:name":"Accounting Principals",
    "wof:placetype":"venue"
},
  "geometry": {"coordinates":[-72.784768,41.667164],"type":"Point"}
}