{
  "type": "Feature",
  "properties": {
    "addr:full":"79 Isinglass Rd Shelton CT 06484",
    "addr:housenumber":"79",
    "addr:postcode":"06484",
    "addr:street":"Isinglass Rd",
    "iso:country":"US",
    "sg:address":"79 Isinglass Rd",
    "sg:city":"Shelton",
    "sg:classifiers":[
        {
            "category":"Home & Garden",
            "subcategory":"Garden Supply",
            "type":"Retail Goods"
        },
        {
            "category":"Building & Trades",
            "subcategory":"Landscaping Services",
            "type":"Services"
        }
    ],
    "sg:phone":"+1 203 925 0716",
    "sg:postcode":"06484",
    "sg:province":"CT",
    "sg:tags":[
        "underground",
        "sprinkler",
        "lawn",
        "system",
        "shrub"
    ],
    "wof:name":"Automatic Rain Inc",
    "wof:placetype":"venue"
},
  "geometry": {"coordinates":[-73.159081,41.281662],"type":"Point"}
}