{
  "type": "Feature",
  "properties": {
    "addr:full":"426 Colman St New London CT 06320",
    "addr:housenumber":"426",
    "addr:postcode":"06320",
    "addr:street":"Colman St New London Ct",
    "iso:country":"US",
    "sg:address":"426 Colman St",
    "sg:city":"New London",
    "sg:classifiers":[
        {
            "category":"Retail",
            "subcategory":"Auto Repair",
            "type":"Services"
        }
    ],
    "sg:phone":"+1   ",
    "sg:postcode":"06320",
    "sg:province":"CT",
    "sg:tags":[
        "automotive"
    ],
    "wof:name":"Colman Street Quick Lube",
    "wof:placetype":"venue"
},
  "geometry": {"coordinates":[-72.116303,41.363569],"type":"Point"}
}