{
  "type": "Feature",
  "properties": {
    "iso:country":"US",
    "sg:address":"90 S Park St",
    "sg:city":"Willimantic",
    "sg:classifiers":[
        {
            "category":"Freight",
            "type":"Transportation"
        }
    ],
    "sg:phone":"+1 860 423 6362",
    "sg:postcode":"06226",
    "sg:province":"CT",
    "sg:tags":[
        "general"
    ],
    "wof:name":"Textron Fastening Systems",
    "wof:placetype":"venue"
},
  "geometry": {"coordinates":[-72.211467,41.707612],"type":"Point"}
}