{
  "type": "Feature",
  "properties": {
    "addr:full":"2234 Silas Deane Hwy Rocky Hill CT 06067",
    "addr:housenumber":"2234",
    "addr:postcode":"06067",
    "addr:street":"Silas Deane Hwy Rocky Hill Ct",
    "iso:country":"US",
    "sg:address":"2234 Silas Deane Hwy",
    "sg:city":"Rocky Hill",
    "sg:classifiers":[
        {
            "category":"Bakery",
            "type":"Food & Drink"
        },
        {
            "category":"Coffee & Tea",
            "type":"Food & Drink"
        },
        {
            "category":"Bagels",
            "type":"Food & Drink"
        },
        {
            "category":"Donuts",
            "type":"Food & Drink"
        }
    ],
    "sg:menulink":"http://www.allmenus.com/ct/rocky-hill/130037-dunkin-donuts/menu/",
    "sg:phone":"+1 860 258 0674",
    "sg:postcode":"06067",
    "sg:province":"CT",
    "sg:tags":[
        "american",
        "diner",
        "pastry"
    ],
    "wof:name":"Dunkin' Donuts",
    "wof:placetype":"venue"
},
  "geometry": {"coordinates":[-72.64131500000001,41.667554],"type":"Point"}
}