{
  "type": "Feature",
  "properties": {
    "addr:full":"191 Post Rd W Westport CT 06880",
    "addr:housenumber":"191",
    "addr:postcode":"06880",
    "addr:street":"Post Rd W Westport Ct",
    "iso:country":"US",
    "sg:address":"191 Post Rd W",
    "sg:city":"Westport",
    "sg:classifiers":[
        {
            "category":"Shopping",
            "subcategory":"Gifts & Souvenirs",
            "type":"Retail Goods"
        }
    ],
    "sg:phone":"+1 203 221 2737",
    "sg:postcode":"06880",
    "sg:province":"CT",
    "sg:tags":[
        "shop"
    ],
    "wof:name":"Stellar Collectibles",
    "wof:placetype":"venue"
},
  "geometry": {"coordinates":[-73.37073100000001,41.136375],"type":"Point"}
}