{
  "type": "Feature",
  "properties": {
    "addr:full":"14 Cambridge St Meriden CT 06450",
    "addr:housenumber":"14",
    "addr:postcode":"06450",
    "addr:street":"Cambridge St",
    "iso:country":"US",
    "sg:address":"14 Cambridge St",
    "sg:city":"Meriden",
    "sg:classifiers":[
        {
            "category":"Building & Trades",
            "subcategory":"Construction",
            "type":"Services"
        }
    ],
    "sg:phone":"+1 203 630 2063",
    "sg:postcode":"06450",
    "sg:province":"CT",
    "sg:tags":[
        "concrete",
        "contractor"
    ],
    "wof:name":"Bazinet Paving",
    "wof:placetype":"venue"
},
  "geometry": {"coordinates":[-72.78734799999999,41.551512],"type":"Point"}
}