{
  "type": "Feature",
  "properties": {
    "addr:full":"666 Orchard St New Haven CT 06511",
    "addr:housenumber":"666",
    "addr:postcode":"06511",
    "addr:street":"Orchard St",
    "iso:country":"US",
    "sg:address":"666 Orchard St",
    "sg:city":"New Haven",
    "sg:classifiers":[
        {
            "category":"Organizations",
            "subcategory":"Religious Organization",
            "type":"Services"
        }
    ],
    "sg:phone":"+1   ",
    "sg:postcode":"06511",
    "sg:province":"CT",
    "wof:name":"Word God Through Jesus Christ",
    "wof:placetype":"venue"
},
  "geometry": {"coordinates":[-72.93718699999999,41.318642],"type":"Point"}
}