{
  "type": "Feature",
  "properties": {
    "addr:full":"23 Washington Ave Westport CT 06880",
    "addr:housenumber":"23",
    "addr:postcode":"06880",
    "addr:street":"Washington Ave",
    "iso:country":"US",
    "sg:address":"23 Washington Ave",
    "sg:city":"Westport",
    "sg:classifiers":[
        {
            "category":"Professional",
            "subcategory":"Management & Consulting",
            "type":"Services"
        }
    ],
    "sg:phone":"+1 203 226 5390",
    "sg:postcode":"06880",
    "sg:province":"CT",
    "sg:tags":[
        "counselor",
        "public",
        "relations"
    ],
    "wof:name":"Lorraine Abelow",
    "wof:placetype":"venue"
},
  "geometry": {"coordinates":[-73.358002,41.146699],"type":"Point"}
}