{
  "type": "Feature",
  "properties": {
    "iso:country":"US",
    "sg:address":"80 Ferry Blvd",
    "sg:city":"Stratford",
    "sg:classifiers":[
        {
            "category":"Social Services",
            "type":"Services"
        }
    ],
    "sg:phone":"+1   ",
    "sg:postcode":"06615",
    "sg:province":"CT",
    "sg:tags":[
        "clinic",
        "specialty",
        "outpatient"
    ],
    "wof:name":"Child Guidance Clinic",
    "wof:placetype":"venue"
},
  "geometry": {"coordinates":[-73.124178,41.18971],"type":"Point"}
}