{
  "type": "Feature",
  "properties": {
    "addr:full":"146 Wright Rd Canton CT 06022",
    "addr:housenumber":"146",
    "addr:postcode":"06022",
    "addr:street":"Wright Rd",
    "iso:country":"US",
    "sg:address":"146 Wright Rd",
    "sg:city":"Canton",
    "sg:classifiers":[
        {
            "category":"Professional",
            "type":"Services"
        }
    ],
    "sg:phone":"+1 860 693 8807",
    "sg:postcode":"06022",
    "sg:province":"CT",
    "wof:name":"Doug Morneault",
    "wof:placetype":"venue"
},
  "geometry": {"coordinates":[-72.91491000000001,41.889507],"type":"Point"}
}