{
  "type": "Feature",
  "properties": {
    "iso:country":"US",
    "sg:address":"114 Olivia St",
    "sg:city":"Derby",
    "sg:classifiers":[
        {
            "category":"Building & Trades",
            "subcategory":"Construction",
            "type":"Services"
        }
    ],
    "sg:phone":"+1 203 445 0530",
    "sg:postcode":"06418",
    "sg:province":"CT",
    "sg:tags":[
        "house"
    ],
    "wof:name":"Titan Enterprises Inc",
    "wof:placetype":"venue"
},
  "geometry": {"coordinates":[-73.090481,41.322114],"type":"Point"}
}