{
  "type": "Feature",
  "properties": {
    "iso:country":"US",
    "sg:address":"15 Deerfield Dr",
    "sg:city":"Ashford",
    "sg:classifiers":[
        {
            "category":"Professional",
            "subcategory":"Business Services",
            "type":"Services"
        }
    ],
    "sg:phone":"+1   ",
    "sg:postcode":"06278",
    "sg:province":"CT",
    "wof:name":"Boni Family Ltd Partnership",
    "wof:placetype":"venue"
},
  "geometry": {"coordinates":[-72.20061800000001,41.940124],"type":"Point"}
}