{
  "type": "Feature",
  "properties": {
    "iso:country":"US",
    "sg:address":"28 Birdsey Ave",
    "sg:city":"Middletown",
    "sg:classifiers":[
        {
            "category":"Building & Trades",
            "subcategory":"Landscaping Services",
            "type":"Services"
        }
    ],
    "sg:phone":"+1 860 347 2391",
    "sg:postcode":"06457",
    "sg:province":"CT",
    "sg:tags":[
        "landscape"
    ],
    "wof:name":"Louis Catalano",
    "wof:placetype":"venue"
},
  "geometry": {"coordinates":[-72.64953,41.546771],"type":"Point"}
}