{
  "type": "Feature",
  "properties": {
    "iso:country":"US",
    "sg:address":"1231 E Main St",
    "sg:city":"Meriden",
    "sg:classifiers":[
        {
            "category":"Personal",
            "subcategory":"Beauty Salon",
            "type":"Services"
        }
    ],
    "sg:phone":"+1 203 238 3330",
    "sg:postcode":"06450",
    "sg:province":"CT",
    "sg:tags":[
        "shop",
        "manicuring"
    ],
    "wof:name":"Nail Art 1",
    "wof:placetype":"venue"
},
  "geometry": {"coordinates":[-72.762575,41.525348],"type":"Point"}
}