{
  "type": "Feature",
  "properties": {
    "iso:country":"US",
    "sg:address":"123 Walnut St",
    "sg:city":"Southington",
    "sg:classifiers":[
        {
            "category":"Professional",
            "subcategory":"Business Services",
            "type":"Services"
        }
    ],
    "sg:phone":"+1   ",
    "sg:postcode":"06479",
    "sg:province":"CT",
    "wof:name":"Whatever Enterprises LLC",
    "wof:placetype":"venue"
},
  "geometry": {"coordinates":[-72.89404999999999,41.596309],"type":"Point"}
}