{
  "type": "Feature",
  "properties": {
    "iso:country":"US",
    "sg:address":"293 Mitchell St",
    "sg:city":"Groton",
    "sg:classifiers":[
        {
            "category":"Shopping",
            "subcategory":"Gifts & Souvenirs",
            "type":"Retail Goods"
        }
    ],
    "sg:phone":"+1 800 992 3577",
    "sg:postcode":"06340",
    "sg:province":"CT",
    "sg:tags":[
        "shop",
        "basket"
    ],
    "wof:name":"Tommy's Flowers Ltd.",
    "wof:placetype":"venue"
},
  "geometry": {"coordinates":[-72.075866,41.348712],"type":"Point"}
}