{
  "type": "Feature",
  "properties": {
    "addr:full":"95 Ballard Dr Hartford CT 06119",
    "addr:housenumber":"95",
    "addr:postcode":"06119",
    "addr:street":"Ballard Dr",
    "iso:country":"US",
    "sg:address":"95 Ballard Dr",
    "sg:city":"Hartford",
    "sg:classifiers":[
        {
            "category":"Professional",
            "type":"Services"
        }
    ],
    "sg:phone":"+1 860 232 4004",
    "sg:postcode":"06119",
    "sg:province":"CT",
    "wof:name":"Netjar LLC",
    "wof:placetype":"venue"
},
  "geometry": {"coordinates":[-72.73560000000001,41.770478],"type":"Point"}
}