{
  "type": "Feature",
  "properties": {
    "iso:country":"US",
    "sg:address":"1043 Buckley Hwy",
    "sg:city":"Stafford Springs",
    "sg:classifiers":[
        {
            "category":"Government",
            "subcategory":"Office",
            "type":"Public Place"
        }
    ],
    "sg:phone":"+1 860 684 5705",
    "sg:postcode":"06076",
    "sg:province":"CT",
    "sg:tags":[
        "policy"
    ],
    "wof:name":"Union Assessors Office",
    "wof:placetype":"venue"
},
  "geometry": {"coordinates":[-72.14891,42.003547],"type":"Point"}
}