{
  "type": "Feature",
  "properties": {
    "addr:full":"244 E Rocks Rd Norwalk CT 06851",
    "addr:housenumber":"244",
    "addr:postcode":"06851",
    "addr:street":"E Rocks Rd",
    "iso:country":"US",
    "sg:address":"244 E Rocks Rd",
    "sg:city":"Norwalk",
    "sg:classifiers":[
        {
            "category":"Real Estate",
            "subcategory":"Real Estate Agent",
            "type":"Services"
        }
    ],
    "sg:phone":"+1 203 847 3814",
    "sg:postcode":"06851",
    "sg:province":"CT",
    "wof:name":"Barbara Atkinson Realty",
    "wof:placetype":"venue"
},
  "geometry": {"coordinates":[-73.41291699999999,41.154246],"type":"Point"}
}