{
  "type": "Feature",
  "properties": {
    "iso:country":"US",
    "sg:address":"11 Forest St",
    "sg:city":"Seymour",
    "sg:classifiers":[
        {
            "category":"Education",
            "subcategory":"Vocational School",
            "type":"Public Place"
        }
    ],
    "sg:phone":"+1   ",
    "sg:postcode":"06483",
    "sg:province":"CT",
    "sg:tags":[
        "training",
        "computer"
    ],
    "wof:name":"Butterfelds Tech Solutions LLC",
    "wof:placetype":"venue"
},
  "geometry": {"coordinates":[-73.103436,41.380543],"type":"Point"}
}