{
  "type": "Feature",
  "properties": {
    "addr:full":"979 Post Rd E Westport CT 06880",
    "addr:housenumber":"979",
    "addr:postcode":"06880",
    "addr:street":"Post Rd E Westport Ct",
    "iso:country":"US",
    "sg:address":"979 Post Rd E",
    "sg:city":"Westport",
    "sg:classifiers":[
        {
            "category":"Professional",
            "subcategory":"Advertising",
            "type":"Services"
        }
    ],
    "sg:phone":"+1   ",
    "sg:postcode":"06880",
    "sg:province":"CT",
    "sg:tags":[
        "agency"
    ],
    "wof:name":"Worlds Smallest Ad Agency",
    "wof:placetype":"venue"
},
  "geometry": {"coordinates":[-73.328221,41.138859],"type":"Point"}
}