{
  "type": "Feature",
  "properties": {
    "iso:country":"US",
    "sg:address":"70 Humphrey St",
    "sg:city":"Seymour",
    "sg:classifiers":[
        {
            "category":"Building & Trades",
            "subcategory":"Landscaping Services",
            "type":"Services"
        }
    ],
    "sg:phone":"+1 203 888 9851",
    "sg:postcode":"06483",
    "sg:province":"CT",
    "wof:name":"Jacouzzi Landscaping",
    "wof:placetype":"venue"
},
  "geometry": {"coordinates":[-73.071344,41.395951],"type":"Point"}
}