{
  "type": "Feature",
  "properties": {
    "iso:country":"US",
    "sg:address":"9 Echo Dr",
    "sg:city":"Darien",
    "sg:classifiers":[
        {
            "category":"Building & Trades",
            "subcategory":"Construction",
            "type":"Services"
        }
    ],
    "sg:phone":"+1 203 324 4392",
    "sg:postcode":"06820",
    "sg:province":"CT",
    "sg:tags":[
        "repairing",
        "remodeling",
        "contractor"
    ],
    "wof:name":"A J Sandor Renovations",
    "wof:placetype":"venue"
},
  "geometry": {"coordinates":[-73.51294799999999,41.082189],"type":"Point"}
}