{
  "type": "Feature",
  "properties": {
    "addr:full":"435 New Haven Ave Derby CT 06418",
    "addr:housenumber":"435",
    "addr:postcode":"06418",
    "addr:street":"New Haven Ave",
    "iso:country":"US",
    "sg:address":"435 New Haven Ave",
    "sg:city":"Derby",
    "sg:classifiers":[
        {
            "category":"Professional",
            "subcategory":"Research",
            "type":"Services"
        }
    ],
    "sg:phone":"+1 203 736 4660",
    "sg:postcode":"06418",
    "sg:province":"CT",
    "sg:tags":[
        "nonphysical",
        "commercial",
        "market",
        "analysis"
    ],
    "wof:name":"Leferman Associates Inc",
    "wof:placetype":"venue"
},
  "geometry": {"coordinates":[-73.063046,41.309591],"type":"Point"}
}