{
  "type": "Feature",
  "properties": {
    "iso:country":"US",
    "sg:address":"1 Dodgingtown Rd",
    "sg:city":"Newtown",
    "sg:classifiers":[
        {
            "category":"Restaurant",
            "type":"Food & Drink"
        }
    ],
    "sg:phone":"+1 203 426 2715",
    "sg:postcode":"06470",
    "sg:province":"CT",
    "wof:name":"George's Pizza & Restaurant",
    "wof:placetype":"venue"
},
  "geometry": {"coordinates":[-73.34750099999999,41.376013],"type":"Point"}
}