{
  "type": "Feature",
  "properties": {
    "iso:country":"US",
    "sg:address":"20 Red Bird Rd",
    "sg:city":"Stamford",
    "sg:classifiers":[
        {
            "category":"Professional",
            "subcategory":"Business Services",
            "type":"Services"
        }
    ],
    "sg:phone":"+1   ",
    "sg:postcode":"06905",
    "sg:province":"CT",
    "wof:name":"Hiller and Hiller Financial",
    "wof:placetype":"venue"
},
  "geometry": {"coordinates":[-73.537773,41.094651],"type":"Point"}
}