{
  "type": "Feature",
  "properties": {
    "iso:country":"US",
    "sg:address":"40 Laurel Rd",
    "sg:city":"New Haven",
    "sg:classifiers":[
        {
            "category":"Professional",
            "type":"Services"
        }
    ],
    "sg:phone":"+1 203 397 8700",
    "sg:postcode":"06515",
    "sg:province":"CT",
    "wof:name":"Splar Foundation Inc",
    "wof:placetype":"venue"
},
  "geometry": {"coordinates":[-72.971217,41.322899],"type":"Point"}
}