{
  "type": "Feature",
  "properties": {
    "iso:country":"US",
    "sg:address":"234 Foxon Rd",
    "sg:city":"New Haven",
    "sg:classifiers":[
        {
            "category":"Retail",
            "subcategory":"Funeral Services",
            "type":"Services"
        }
    ],
    "sg:phone":"+1   ",
    "sg:postcode":"06513",
    "sg:province":"CT",
    "wof:name":"Porto Funeral Homes",
    "wof:placetype":"venue"
},
  "geometry": {"coordinates":[-72.82689499999999,41.32454],"type":"Point"}
}