{
  "type": "Feature",
  "properties": {
    "iso:country":"US",
    "sg:address":"10 Munson Rd",
    "sg:city":"Bethany",
    "sg:classifiers":[
        {
            "category":"Organizations",
            "subcategory":"Professional Association",
            "type":"Services"
        }
    ],
    "sg:phone":"+1 203 393 2056",
    "sg:postcode":"06524",
    "sg:province":"CT",
    "wof:name":"Bethany Athletic Assoc",
    "wof:placetype":"venue"
},
  "geometry": {"coordinates":[-72.989778,41.440753],"type":"Point"}
}