{
  "type": "Feature",
  "properties": {
    "addr:full":"388 Main St Winsted CT 06098",
    "addr:housenumber":"388",
    "addr:postcode":"06098",
    "addr:street":"Main St",
    "iso:country":"US",
    "sg:address":"388 Main St",
    "sg:city":"Winsted",
    "sg:classifiers":[
        {
            "category":"Shopping",
            "subcategory":"Clothing, Apparel, & Fashions",
            "type":"Retail Goods"
        }
    ],
    "sg:phone":"+1 860 379 5305",
    "sg:postcode":"06098",
    "sg:province":"CT",
    "sg:tags":[
        "ready",
        "accessory"
    ],
    "wof:name":"Rose Sullivan Shoppe Inc",
    "wof:placetype":"venue"
},
  "geometry": {"coordinates":[-72.966807,41.874765],"type":"Point"}
}