{
  "type": "Feature",
  "properties": {
    "addr:full":"31 Haven St West Haven CT 06513",
    "addr:housenumber":"31",
    "addr:postcode":"06513",
    "addr:street":"Haven St",
    "iso:country":"US",
    "sg:address":"31 Haven St",
    "sg:city":"West Haven",
    "sg:classifiers":[
        {
            "category":"Wholesale",
            "subcategory":"Hardware",
            "type":"Manufacturing & Wholesale Goods"
        }
    ],
    "sg:phone":"+1 203 937 1246",
    "sg:postcode":"06513",
    "sg:province":"CT",
    "sg:tags":[
        "refrigerating"
    ],
    "wof:name":"Refrigeration Unlimited",
    "wof:placetype":"venue"
},
  "geometry": {"coordinates":[-72.903971,41.307784],"type":"Point"}
}