{
  "type": "Feature",
  "properties": {
    "addr:full":"1472 Baldwin St Waterbury CT 06706",
    "addr:housenumber":"1472",
    "addr:postcode":"06706",
    "addr:street":"Baldwin St Waterbury Ct",
    "iso:country":"US",
    "sg:address":"1472 Baldwin St",
    "sg:city":"Waterbury",
    "sg:classifiers":[
        {
            "category":"Building & Trades",
            "subcategory":"Construction",
            "type":"Services"
        }
    ],
    "sg:phone":"+1 203 509 2131",
    "sg:postcode":"06706",
    "sg:province":"CT",
    "sg:tags":[
        "floor",
        "laying",
        "contractor"
    ],
    "wof:name":"J A Flooring Concept LLC",
    "wof:placetype":"venue"
},
  "geometry": {"coordinates":[-73.035128,41.532608],"type":"Point"}
}