{
  "type": "Feature",
  "properties": {
    "iso:country":"US",
    "sg:address":"220 Elm St",
    "sg:city":"New Canaan",
    "sg:classifiers":[
        {
            "category":"Real Estate",
            "subcategory":"Developer",
            "type":"Services"
        }
    ],
    "sg:phone":"+1 203 801 3300",
    "sg:postcode":"06840",
    "sg:province":"NY",
    "wof:name":"Avalon Properties Inc",
    "wof:placetype":"venue"
},
  "geometry": {"coordinates":[-73.497357,41.146048],"type":"Point"}
}