{
  "type": "Feature",
  "properties": {
    "iso:country":"US",
    "sg:address":"22 Canterbury Ln",
    "sg:city":"Wilton",
    "sg:classifiers":[
        {
            "category":"Education",
            "subcategory":"Special Training",
            "type":"Public Place"
        }
    ],
    "sg:phone":"+1   ",
    "sg:postcode":"06897",
    "sg:province":"CT",
    "wof:name":"Case Haviland Ltd",
    "wof:placetype":"venue"
},
  "geometry": {"coordinates":[-73.402905,41.187529],"type":"Point"}
}