{
  "type": "Feature",
  "properties": {
    "iso:country":"US",
    "sg:address":"3 Strawbridge Ln",
    "sg:city":"Greenwich",
    "sg:classifiers":[
        {
            "category":"Professional",
            "type":"Services"
        }
    ],
    "sg:phone":"+1 203 531 5418",
    "sg:postcode":"06831",
    "sg:province":"NY",
    "sg:tags":[
        "scientist"
    ],
    "wof:name":"Sophisticomp Inc",
    "wof:placetype":"venue"
},
  "geometry": {"coordinates":[-73.657229,41.029699],"type":"Point"}
}