{
  "type": "Feature",
  "properties": {
    "iso:country":"US",
    "sg:address":"570 High St",
    "sg:city":"Naugatuck",
    "sg:classifiers":[
        {
            "category":"Real Estate",
            "subcategory":"Architect",
            "type":"Services"
        }
    ],
    "sg:phone":"+1   ",
    "sg:postcode":"06770",
    "sg:province":"CT",
    "sg:tags":[
        "architectural"
    ],
    "wof:name":"Hollis Architectural",
    "wof:placetype":"venue"
},
  "geometry": {"coordinates":[-73.049154,41.494136],"type":"Point"}
}