{
  "type": "Feature",
  "properties": {
    "addr:full":"7 Partridge Hill Ln Essex CT 06426",
    "addr:housenumber":"7",
    "addr:postcode":"06426",
    "addr:street":"Partridge Hill Ln",
    "iso:country":"US",
    "sg:address":"7 Partridge Hill Ln",
    "sg:city":"Essex",
    "sg:classifiers":[
        {
            "category":"Organizations",
            "subcategory":"Religious Organization",
            "type":"Services"
        }
    ],
    "sg:phone":"+1   ",
    "sg:postcode":"06426",
    "sg:province":"CT",
    "wof:name":"Jesus Has Called ME Ministry",
    "wof:placetype":"venue"
},
  "geometry": {"coordinates":[-72.397879,41.347541],"type":"Point"}
}