{
  "type": "Feature",
  "properties": {
    "addr:full":"23 Elm St New Canaan CT 06840",
    "addr:housenumber":"23",
    "addr:postcode":"06840",
    "addr:street":"Elm St New Canaan Ct",
    "iso:country":"US",
    "sg:address":"23 Elm St",
    "sg:city":"New Canaan",
    "sg:classifiers":[
        {
            "category":"Restaurant",
            "type":"Food & Drink"
        }
    ],
    "sg:menulink":"http://www.allmenus.com/ct/new-canaan/25283-hunan/menu/",
    "sg:phone":"+1 203 966 2338",
    "sg:postcode":"06840",
    "sg:province":"CT",
    "sg:tags":[
        "asian",
        "chinese"
    ],
    "wof:name":"Hunan",
    "wof:placetype":"venue"
},
  "geometry": {"coordinates":[-73.49264100000001,41.146997],"type":"Point"}
}