{
  "type": "Feature",
  "properties": {
    "addr:full":"295 Erskine Rd Stamford CT 06903",
    "addr:housenumber":"295",
    "addr:postcode":"06903",
    "addr:street":"Erskine Rd",
    "iso:country":"US",
    "sg:address":"295 Erskine Rd",
    "sg:city":"Stamford",
    "sg:classifiers":[
        {
            "category":"Education",
            "subcategory":"Special Training",
            "type":"Public Place"
        }
    ],
    "sg:phone":"+1   ",
    "sg:postcode":"06903",
    "sg:province":"CT",
    "wof:name":"Freeborn Foundation Inc",
    "wof:placetype":"venue"
},
  "geometry": {"coordinates":[-73.60106399999999,41.142139],"type":"Point"}
}