{
  "type": "Feature",
  "properties": {
    "addr:full":"56 Clifton Ave Ansonia CT 06401",
    "addr:housenumber":"56",
    "addr:postcode":"06401",
    "addr:street":"Clifton Ave",
    "iso:country":"US",
    "sg:address":"56 Clifton Ave",
    "sg:city":"Ansonia",
    "sg:classifiers":[
        {
            "category":"Retail",
            "subcategory":"Auto Repair",
            "type":"Services"
        }
    ],
    "sg:phone":"+1 203 734 5333",
    "sg:postcode":"06401",
    "sg:province":"CT",
    "sg:tags":[
        "body",
        "automobile",
        "top",
        "upholstery",
        "go"
    ],
    "wof:name":"Jim's Auto Top & Upholstery",
    "wof:placetype":"venue"
},
  "geometry": {"coordinates":[-73.08374499999999,41.336629],"type":"Point"}
}