{
  "type": "Feature",
  "properties": {
    "addr:full":"23 Finch Rd Wolcott CT 06716",
    "addr:housenumber":"23",
    "addr:postcode":"06716",
    "addr:street":"Finch Rd Wolcott Ct",
    "iso:country":"US",
    "sg:address":"23 Finch Rd",
    "sg:city":"Wolcott",
    "sg:classifiers":[
        {
            "category":"Health Services",
            "subcategory":"Health Practitioner",
            "type":"Services"
        }
    ],
    "sg:phone":"+1 203 879 2063",
    "sg:postcode":"06716",
    "sg:province":"CT",
    "sg:tags":[
        "nurse",
        "registry"
    ],
    "wof:name":"William J Albino",
    "wof:placetype":"venue"
},
  "geometry": {"coordinates":[-72.987208,41.569777],"type":"Point"}
}