{
  "type": "Feature",
  "properties": {
    "iso:country":"US",
    "sg:address":"45 Macarthur Rd",
    "sg:city":"Plainville",
    "sg:classifiers":[
        {
            "category":"Organizations",
            "subcategory":"Community Association",
            "type":"Services"
        }
    ],
    "sg:phone":"+1   ",
    "sg:postcode":"06062",
    "sg:province":"CT",
    "wof:name":"Art League of Plainville",
    "wof:placetype":"venue"
},
  "geometry": {"coordinates":[-72.849103,41.666469],"type":"Point"}
}