{
  "type": "Feature",
  "properties": {
    "iso:country":"US",
    "sg:address":"23 Deerfield Rd",
    "sg:city":"Waterford",
    "sg:classifiers":[
        {
            "category":"Professional",
            "type":"Services"
        }
    ],
    "sg:phone":"+1 860 442 9011",
    "sg:postcode":"06385",
    "sg:province":"CT",
    "wof:name":"Robert Rossi",
    "wof:placetype":"venue"
},
  "geometry": {"coordinates":[-72.13842200000001,41.327166],"type":"Point"}
}