{
  "type": "Feature",
  "properties": {
    "iso:country":"US",
    "sg:address":"633 Middlesex Tpke Ste 107",
    "sg:city":"Old Saybrook",
    "sg:classifiers":[
        {
            "category":"Health Services",
            "subcategory":"Optometrist",
            "type":"Services"
        }
    ],
    "sg:phone":"+1 860 388 4242",
    "sg:postcode":"06475",
    "sg:province":"CT",
    "wof:name":"Shoreline Eye Group PC",
    "wof:placetype":"venue"
},
  "geometry": {"coordinates":[-72.37875099999999,41.321667],"type":"Point"}
}