{
  "type": "Feature",
  "properties": {
    "iso:country":"US",
    "sg:address":"596 Clubhouse Rd",
    "sg:city":"Lebanon",
    "sg:classifiers":[
        {
            "category":"Education",
            "subcategory":"Vocational School",
            "type":"Public Place"
        }
    ],
    "sg:phone":"+1   ",
    "sg:postcode":"06249",
    "sg:province":"CT",
    "sg:tags":[
        "processing",
        "datum"
    ],
    "wof:name":"Lebaonon Life",
    "wof:placetype":"venue"
},
  "geometry": {"coordinates":[-72.26767100000001,41.623198],"type":"Point"}
}