{
  "type": "Feature",
  "properties": {
    "iso:country":"US",
    "sg:address":"3308 Whitney Ave",
    "sg:city":"Hamden",
    "sg:classifiers":[
        {
            "category":"Professional",
            "subcategory":"Lawyer & Legal Services",
            "type":"Services"
        }
    ],
    "sg:phone":"+1 203 248 6440",
    "sg:postcode":"06518",
    "sg:province":"CT",
    "sg:tags":[
        "attorney"
    ],
    "wof:name":"Bender Anderson Barba",
    "wof:placetype":"venue"
},
  "geometry": {"coordinates":[-72.902325,41.414282],"type":"Point"}
}