{
  "type": "Feature",
  "properties": {
    "addr:full":"191 Providence St Putnam CT 06260",
    "addr:housenumber":"191",
    "addr:postcode":"06260",
    "addr:street":"Providence St Putnam Ct",
    "iso:country":"US",
    "sg:address":"191 Providence St",
    "sg:city":"Putnam",
    "sg:classifiers":[
        {
            "category":"Home & Garden",
            "subcategory":"Household Appliances",
            "type":"Retail Goods"
        }
    ],
    "sg:phone":"+1   ",
    "sg:postcode":"06260",
    "sg:province":"CT",
    "sg:tags":[
        "repair",
        "for"
    ],
    "wof:name":"La Bonte & Mercik",
    "wof:placetype":"venue"
},
  "geometry": {"coordinates":[-71.910144,41.923969],"type":"Point"}
}