{
  "type": "Feature",
  "properties": {
    "addr:full":"50 Grace St Hartford CT 06106",
    "addr:housenumber":"50",
    "addr:postcode":"06106",
    "addr:street":"Grace St",
    "iso:country":"US",
    "sg:address":"50 Grace St",
    "sg:city":"Hartford",
    "sg:classifiers":[
        {
            "category":"Building & Trades",
            "subcategory":"Electrical",
            "type":"Services"
        }
    ],
    "sg:phone":"+1 860 232 3175",
    "sg:postcode":"06106",
    "sg:province":"CT",
    "sg:tags":[
        "electrical",
        "contractor"
    ],
    "wof:name":"Clapis Associates",
    "wof:placetype":"venue"
},
  "geometry": {"coordinates":[-72.708234,41.755449],"type":"Point"}
}