{
  "type": "Feature",
  "properties": {
    "addr:full":"324 Bridgeport Ave Milford CT 06460",
    "addr:housenumber":"324",
    "addr:postcode":"06460",
    "addr:street":"Bridgeport Ave",
    "iso:country":"US",
    "sg:address":"324 Bridgeport Ave",
    "sg:city":"Milford",
    "sg:classifiers":[
        {
            "category":"Retail",
            "subcategory":"Auto Repair",
            "type":"Services"
        }
    ],
    "sg:phone":"+1 203 878 4353",
    "sg:postcode":"06460",
    "sg:province":"CT",
    "sg:tags":[
        "repairing",
        "automobile",
        "general"
    ],
    "wof:name":"Sandoval H Foreign Car Inc",
    "wof:placetype":"venue"
},
  "geometry": {"coordinates":[-73.097437,41.203866],"type":"Point"}
}