{
  "type": "Feature",
  "properties": {
    "addr:full":"134 Wilson St Bridgeport CT 06605",
    "addr:housenumber":"134",
    "addr:postcode":"06605",
    "addr:street":"Wilson St",
    "iso:country":"US",
    "sg:address":"134 Wilson St",
    "sg:city":"Bridgeport",
    "sg:classifiers":[
        {
            "category":"Retail",
            "subcategory":"Laundry & Dry Cleaning",
            "type":"Services"
        }
    ],
    "sg:phone":"+1 203 384 1787",
    "sg:postcode":"06605",
    "sg:province":"CT",
    "sg:tags":[
        "cleaner",
        "rug",
        "carpet"
    ],
    "wof:name":"Conn Southern Carpet Cleaning Co",
    "wof:placetype":"venue"
},
  "geometry": {"coordinates":[-73.228551,41.158079],"type":"Point"}
}