{
  "type": "Feature",
  "properties": {
    "addr:full":"154 N Lake Shore Dr Brookfield CT 06804",
    "addr:housenumber":"154",
    "addr:postcode":"06804",
    "addr:street":"N Lake Shore Dr",
    "iso:country":"US",
    "sg:address":"154 N Lake Shore Dr",
    "sg:city":"Brookfield",
    "sg:classifiers":[
        {
            "category":"Professional",
            "type":"Services"
        }
    ],
    "sg:phone":"+1 203 740 8448",
    "sg:postcode":"06804",
    "sg:province":"CT",
    "wof:name":"Bronte North America",
    "wof:placetype":"venue"
},
  "geometry": {"coordinates":[-73.4423,41.478746],"type":"Point"}
}