{
  "type": "Feature",
  "properties": {
    "addr:full":"169 Greenwich Ave Greenwich CT 06830",
    "addr:housenumber":"169",
    "addr:postcode":"06830",
    "addr:street":"Greenwich Ave",
    "iso:country":"US",
    "sg:address":"169 Greenwich Ave",
    "sg:city":"Greenwich",
    "sg:classifiers":[
        {
            "category":"Shopping",
            "subcategory":"Jewelry",
            "type":"Retail Goods"
        }
    ],
    "sg:phone":"+1 203 629 0900",
    "sg:postcode":"06830",
    "sg:province":"CT",
    "sg:tags":[
        "jeweler"
    ],
    "wof:name":"Lux Bond & Green",
    "wof:placetype":"venue"
},
  "geometry": {"coordinates":[-73.625981,41.027581],"type":"Point"}
}