{
  "type": "Feature",
  "properties": {
    "iso:country":"US",
    "sg:address":"8 Ridge Rd",
    "sg:city":"Seymour",
    "sg:classifiers":[
        {
            "category":"Building & Trades",
            "subcategory":"Cleaning & Sanitation",
            "type":"Services"
        }
    ],
    "sg:phone":"+1   ",
    "sg:postcode":"06483",
    "sg:province":"CT",
    "sg:tags":[
        "co",
        "maintenance",
        "hanging"
    ],
    "wof:name":"Jga Painting & Powerwashing",
    "wof:placetype":"venue"
},
  "geometry": {"coordinates":[-73.086105,41.38539],"type":"Point"}
}