{
  "type": "Feature",
  "properties": {
    "iso:country":"US",
    "sg:address":"22 1st St",
    "sg:city":"Stamford",
    "sg:classifiers":[
        {
            "category":"Professional",
            "subcategory":"Engineering",
            "type":"Services"
        }
    ],
    "sg:phone":"+1 203 327 0500",
    "sg:postcode":"06905",
    "sg:province":"CT",
    "sg:tags":[
        "engineer"
    ],
    "sg:website":"www.redniss-mead.com",
    "wof:name":"REDNISS & Mead Inc",
    "wof:placetype":"venue"
},
  "geometry": {"coordinates":[-73.54095100000001,41.062946],"type":"Point"}
}