{
  "type": "Feature",
  "properties": {
    "addr:full":"48 N Plains Industrial Rd Wallingford CT 06492",
    "addr:housenumber":"48",
    "addr:postcode":"06492",
    "addr:street":"N Plains Industrial Rd",
    "iso:country":"US",
    "sg:address":"48 N Plains Industrial Rd",
    "sg:city":"Wallingford",
    "sg:classifiers":[
        {
            "category":"Freight",
            "type":"Transportation"
        }
    ],
    "sg:phone":"+1 203 265 6100",
    "sg:postcode":"06492",
    "sg:province":"CT",
    "sg:tags":[
        "broker",
        "trucking"
    ],
    "sg:website":"www.bemaktraffic.com",
    "wof:name":"Bemak Traffic Svc",
    "wof:placetype":"venue"
},
  "geometry": {"coordinates":[-72.816045,41.483585],"type":"Point"}
}