{
  "type": "Feature",
  "properties": {
    "addr:full":"37 Executive Dr Danbury CT 06810",
    "addr:housenumber":"37",
    "addr:postcode":"06810",
    "addr:street":"Executive Dr",
    "iso:country":"US",
    "sg:address":"37 Executive Dr",
    "sg:city":"Danbury",
    "sg:classifiers":[
        {
            "category":"Manufacturing",
            "subcategory":"Tools & Machinery",
            "type":"Manufacturing & Wholesale Goods"
        }
    ],
    "sg:phone":"+1   ",
    "sg:postcode":"06810",
    "sg:province":"CT",
    "sg:tags":[
        "laboratory",
        "testing",
        "photographic",
        "mfg"
    ],
    "wof:name":"Pitney Bowes",
    "wof:placetype":"venue"
},
  "geometry": {"coordinates":[-73.41740799999999,41.415128],"type":"Point"}
}