{
  "type": "Feature",
  "properties": {
    "iso:country":"US",
    "sg:address":"911 Durham Rd",
    "sg:city":"Wallingford",
    "sg:classifiers":[
        {
            "category":"Organizations",
            "subcategory":"Professional Association",
            "type":"Services"
        }
    ],
    "sg:phone":"+1 203 284 1562",
    "sg:postcode":"06492",
    "sg:province":"CT",
    "wof:name":"YMCA Wallingford Family",
    "wof:placetype":"venue"
},
  "geometry": {"coordinates":[-72.78713,41.459826],"type":"Point"}
}