{
  "type": "Feature",
  "properties": {
    "addr:full":"186 W Cornwall Rd West Cornwall CT 06796",
    "addr:housenumber":"186",
    "addr:postcode":"06796",
    "addr:street":"W Cornwall Rd West Cornwall Ct",
    "iso:country":"US",
    "sg:address":"186 W Cornwall Rd",
    "sg:city":"West Cornwall",
    "sg:classifiers":[
        {
            "category":"Wholesale",
            "subcategory":"Sporting Goods",
            "type":"Manufacturing & Wholesale Goods"
        }
    ],
    "sg:phone":"+1 860 672 6264",
    "sg:postcode":"06796",
    "sg:province":"CT",
    "sg:tags":[
        "deer",
        "repellent"
    ],
    "wof:name":"Deer No No Inc",
    "wof:placetype":"venue"
},
  "geometry": {"coordinates":[-73.377591,41.863883],"type":"Point"}
}