{
  "type": "Feature",
  "properties": {
    "iso:country":"US",
    "sg:address":"11 Industrial Rd",
    "sg:city":"Prospect",
    "sg:classifiers":[
        {
            "category":"Manufacturing",
            "subcategory":"Electronics",
            "type":"Manufacturing & Wholesale Goods"
        }
    ],
    "sg:phone":"+1 203 758 4401",
    "sg:postcode":"06712",
    "sg:province":"CT",
    "sg:tags":[
        "equipment",
        "electronic",
        "supply"
    ],
    "sg:website":"www.esielect.com",
    "wof:name":"ESI Electronic Products Inc",
    "wof:placetype":"venue"
},
  "geometry": {"coordinates":[-72.999059,41.508279],"type":"Point"}
}