{
  "type": "Feature",
  "properties": {
    "addr:full":"500 Middletown Ave North Haven CT 06473",
    "addr:housenumber":"500",
    "addr:postcode":"06473",
    "addr:street":"Middletown Ave;Haven",
    "iso:country":"US",
    "sg:address":"500 Middletown Ave",
    "sg:city":"North Haven",
    "sg:classifiers":[
        {
            "category":"Farming",
            "subcategory":"Nursery",
            "type":"Manufacturing & Wholesale Goods"
        }
    ],
    "sg:phone":"+1 203 239 5671",
    "sg:postcode":"06473",
    "sg:province":"CT",
    "sg:tags":[
        "greenhouse"
    ],
    "wof:name":"Lexington Gardens of N Haven",
    "wof:placetype":"venue"
},
  "geometry": {"coordinates":[-72.84309399999999,41.35543],"type":"Point"}
}