{
  "type": "Feature",
  "properties": {
    "addr:full":"91 North St Hebron CT 06248",
    "addr:housenumber":"91",
    "addr:postcode":"06248",
    "addr:street":"North St Hebron Ct",
    "iso:country":"US",
    "sg:address":"91 North St",
    "sg:city":"Hebron",
    "sg:classifiers":[
        {
            "category":"Sports & Exercise",
            "subcategory":"Golf",
            "type":"Entertainment"
        }
    ],
    "sg:phone":"+1   ",
    "sg:postcode":"06248",
    "sg:province":"CT",
    "sg:tags":[
        "snack",
        "bar",
        "driving",
        "course",
        "range",
        "public"
    ],
    "wof:name":"Tallwood Country Club LLC",
    "wof:placetype":"venue"
},
  "geometry": {"coordinates":[-72.437094,41.696096],"type":"Point"}
}