{
  "type": "Feature",
  "properties": {
    "addr:full":"111 Shore Dr Branford CT 06405",
    "addr:housenumber":"111",
    "addr:postcode":"06405",
    "addr:street":"Shore Dr",
    "iso:country":"US",
    "sg:address":"111 Shore Dr",
    "sg:city":"Branford",
    "sg:classifiers":[
        {
            "category":"Professional",
            "type":"Services"
        }
    ],
    "sg:phone":"+1 203 483 6678",
    "sg:postcode":"06405",
    "sg:province":"CT",
    "sg:tags":[
        "establishment"
    ],
    "sg:website":"www.starprompt.com",
    "wof:name":"Starprompt",
    "wof:placetype":"venue"
},
  "geometry": {"coordinates":[-72.848466,41.258221],"type":"Point"}
}