{
  "type": "Feature",
  "properties": {
    "addr:full":"383 Whalley Ave New Haven CT 06511",
    "addr:housenumber":"383",
    "addr:postcode":"06511",
    "addr:street":"Whalley Ave",
    "iso:country":"US",
    "sg:address":"383 Whalley Ave",
    "sg:city":"New Haven",
    "sg:classifiers":[
        {
            "category":"Restaurant",
            "type":"Food & Drink"
        }
    ],
    "sg:phone":"+1 203 281 6786",
    "sg:postcode":"06511",
    "sg:province":"CT",
    "wof:name":"AAA Pizza",
    "wof:placetype":"venue"
},
  "geometry": {"coordinates":[-72.94476400000001,41.317575],"type":"Point"}
}