{
  "type": "Feature",
  "properties": {
    "addr:full":"109 Commerce St Glastonbury CT 06033",
    "addr:housenumber":"109",
    "addr:postcode":"06033",
    "addr:street":"Commerce St",
    "iso:country":"US",
    "sg:address":"109 Commerce St",
    "sg:city":"Glastonbury",
    "sg:classifiers":[
        {
            "category":"Retail",
            "subcategory":"Repair Shop",
            "type":"Services"
        }
    ],
    "sg:phone":"+1   ",
    "sg:postcode":"06033",
    "sg:province":"CT",
    "sg:tags":[
        "television",
        "radio"
    ],
    "wof:name":"Edward Bagot",
    "wof:placetype":"venue"
},
  "geometry": {"coordinates":[-72.589299,41.709526],"type":"Point"}
}