{
  "type": "Feature",
  "properties": {
    "iso:country":"US",
    "sg:address":"1664 Park Ave",
    "sg:city":"Bridgeport",
    "sg:classifiers":[
        {
            "category":"Restaurant",
            "type":"Food & Drink"
        }
    ],
    "sg:phone":"+1 203 367 1206",
    "sg:postcode":"06604",
    "sg:province":"CT",
    "wof:name":"Kings Wok Chinese Restaurant",
    "wof:placetype":"venue"
},
  "geometry": {"coordinates":[-73.205988,41.182489],"type":"Point"}
}