{
  "type": "Feature",
  "properties": {
    "iso:country":"US",
    "sg:address":"12 Farrell Rd",
    "sg:city":"Weston",
    "sg:classifiers":[
        {
            "category":"Professional",
            "type":"Services"
        }
    ],
    "sg:phone":"+1 203 222 8746",
    "sg:postcode":"06883",
    "sg:province":"CT",
    "wof:name":"Mark & Margaret Cannon",
    "wof:placetype":"venue"
},
  "geometry": {"coordinates":[-73.36418500000001,41.208307],"type":"Point"}
}