{
  "type": "Feature",
  "properties": {
    "addr:full":"12 Vintner Pl Enfield CT 06082",
    "addr:housenumber":"12",
    "addr:postcode":"06082",
    "addr:street":"Vintner Pl",
    "iso:country":"US",
    "sg:address":"12 Vintner Pl",
    "sg:city":"Enfield",
    "sg:classifiers":[
        {
            "category":"Professional",
            "subcategory":"Business Services",
            "type":"Services"
        }
    ],
    "sg:phone":"+1   ",
    "sg:postcode":"06082",
    "sg:province":"CT",
    "wof:name":"AAA Bail Bonds",
    "wof:placetype":"venue"
},
  "geometry": {"coordinates":[-72.57055,41.956884],"type":"Point"}
}