{
  "type": "Feature",
  "properties": {
    "iso:country":"US",
    "sg:address":"38 Gerry St",
    "sg:city":"Greenwich",
    "sg:classifiers":[
        {
            "category":"Retail",
            "subcategory":"Repair Shop",
            "type":"Services"
        },
        {
            "category":"Building & Trades",
            "subcategory":"Plumbing",
            "type":"Services"
        }
    ],
    "sg:phone":"+1 203 629 3273",
    "sg:postcode":"06830",
    "sg:province":"CT",
    "sg:tags":[
        "septic"
    ],
    "wof:name":"Pendergast Septic Svce Inc",
    "wof:placetype":"venue"
},
  "geometry": {"coordinates":[-73.642135,41.0178],"type":"Point"}
}