{
  "type": "Feature",
  "properties": {
    "iso:country":"US",
    "sg:address":"26 Broad St",
    "sg:city":"Milford",
    "sg:classifiers":[
        {
            "category":"Professional",
            "subcategory":"Lawyer & Legal Services",
            "type":"Services"
        }
    ],
    "sg:phone":"+1   ",
    "sg:postcode":"06460",
    "sg:province":"CT",
    "wof:name":"Anita Steenson Flannigant ATT",
    "wof:placetype":"venue"
},
  "geometry": {"coordinates":[-73.057507,41.221837],"type":"Point"}
}