{
  "type": "Feature",
  "properties": {
    "addr:full":"711 Middletown Rd Colchester CT 06415",
    "addr:housenumber":"711",
    "addr:postcode":"06415",
    "addr:street":"Middletown Rd",
    "iso:country":"US",
    "sg:address":"711 Middletown Rd",
    "sg:city":"Colchester",
    "sg:classifiers":[
        {
            "category":"Banks & Credit Unions",
            "subcategory":"Bank",
            "type":"Services"
        }
    ],
    "sg:phone":"+1 860 365 0000",
    "sg:postcode":"06415",
    "sg:province":"CT",
    "sg:tags":[
        "mortgage"
    ],
    "wof:name":"Amston Mortgage Company Inc",
    "wof:placetype":"venue"
},
  "geometry": {"coordinates":[-72.399111,41.548399],"type":"Point"}
}