{
  "type": "Feature",
  "properties": {
    "addr:full":"956 Dixwell Ave Hamden CT 06514",
    "addr:housenumber":"956",
    "addr:postcode":"06514",
    "addr:street":"Dixwell Ave",
    "iso:country":"US",
    "sg:address":"956 Dixwell Ave",
    "sg:city":"Hamden",
    "sg:classifiers":[
        {
            "category":"Autos & Motor Vehicles",
            "subcategory":"Auto Supplies",
            "type":"Retail Goods"
        }
    ],
    "sg:phone":"+1 203 865 1181",
    "sg:postcode":"06514",
    "sg:province":"CT",
    "sg:tags":[
        "automobile",
        "accessory"
    ],
    "wof:name":"All Parts & Trucks Inc",
    "wof:placetype":"venue"
},
  "geometry": {"coordinates":[-72.93523,41.338636],"type":"Point"}
}