{
  "type": "Feature",
  "properties": {
    "addr:full":"226 Thayer Pond Rd Wilton CT 06897",
    "addr:housenumber":"226",
    "addr:postcode":"06897",
    "addr:street":"Thayer Pond Rd",
    "iso:country":"US",
    "sg:address":"226 Thayer Pond Rd",
    "sg:city":"Wilton",
    "sg:classifiers":[
        {
            "category":"Professional",
            "type":"Services"
        }
    ],
    "sg:phone":"+1 203 762 1276",
    "sg:postcode":"06897",
    "sg:province":"CT",
    "wof:name":"Bourbon Street",
    "wof:placetype":"venue"
},
  "geometry": {"coordinates":[-73.470614,41.18325],"type":"Point"}
}