{
  "type": "Feature",
  "properties": {
    "addr:full":"205 Birge Park Rd Harwinton CT 06791",
    "addr:housenumber":"205",
    "addr:postcode":"06791",
    "addr:street":"Birge Park Rd Harwinton Ct",
    "iso:country":"US",
    "sg:address":"205 Birge Park Rd",
    "sg:city":"Harwinton",
    "sg:classifiers":[
        {
            "category":"Retail",
            "subcategory":"Auto Repair",
            "type":"Services"
        }
    ],
    "sg:phone":"+1   ",
    "sg:postcode":"06791",
    "sg:province":"CT",
    "sg:tags":[
        "a",
        "station",
        "used",
        "gasoline",
        "general"
    ],
    "wof:name":"Ifflands Colonial Service Stn",
    "wof:placetype":"venue"
},
  "geometry": {"coordinates":[-73.068876,41.777052],"type":"Point"}
}