{
  "type": "Feature",
  "properties": {
    "addr:full":"361 Boston Post Rd North Windham CT 06256",
    "addr:housenumber":"361",
    "addr:postcode":"06256",
    "addr:street":"Boston Post Rd North Windham Ct",
    "iso:country":"US",
    "sg:address":"361 Boston Post Rd",
    "sg:city":"North Windham",
    "sg:classifiers":[
        {
            "category":"Banks & Credit Unions",
            "subcategory":"Bank",
            "type":"Services"
        }
    ],
    "sg:phone":"+1 860 423 1601",
    "sg:postcode":"06256",
    "sg:province":"CT",
    "wof:name":"Northeast Family Federal Credit Union",
    "wof:placetype":"venue"
},
  "geometry": {"coordinates":[-72.179604,41.739101],"type":"Point"}
}