{
  "type": "Feature",
  "properties": {
    "iso:country":"US",
    "sg:address":"80 Washington St",
    "sg:city":"Middletown",
    "sg:classifiers":[
        {
            "category":"Cinema",
            "subcategory":"Movie Rental",
            "type":"Entertainment"
        }
    ],
    "sg:phone":"+1   ",
    "sg:postcode":"06457",
    "sg:province":"CT",
    "sg:tags":[
        "video",
        "tape"
    ],
    "wof:name":"Mizpah Christian Videos",
    "wof:placetype":"venue"
},
  "geometry": {"coordinates":[-72.6504,41.562589],"type":"Point"}
}