{
  "type": "Feature",
  "properties": {
    "iso:country":"US",
    "sg:address":"10 Talcott Notch Rd",
    "sg:city":"Farmington",
    "sg:classifiers":[
        {
            "category":"Health Services",
            "subcategory":"Health Practitioner",
            "type":"Services"
        }
    ],
    "sg:phone":"+1   ",
    "sg:postcode":"06032",
    "sg:province":"CT",
    "sg:tags":[
        "therapy",
        "physical"
    ],
    "wof:name":"Health South Regional Bus Off",
    "wof:placetype":"venue"
},
  "geometry": {"coordinates":[-72.791935,41.739046],"type":"Point"}
}