{
  "type": "Feature",
  "properties": {
    "iso:country":"US",
    "sg:address":"13 Willow St",
    "sg:city":"Milford",
    "sg:classifiers":[
        {
            "category":"Arts & Performance",
            "subcategory":"Theater",
            "type":"Entertainment"
        }
    ],
    "sg:phone":"+1   ",
    "sg:postcode":"06460",
    "sg:province":"CT",
    "sg:tags":[
        "group"
    ],
    "wof:name":"Jammie The Gentle Clown",
    "wof:placetype":"venue"
},
  "geometry": {"coordinates":[-73.059468,41.210804],"type":"Point"}
}