{
  "type": "Feature",
  "properties": {
    "iso:country":"US",
    "sg:address":"825 Cromwell Ave",
    "sg:city":"Rocky Hill",
    "sg:classifiers":[
        {
            "category":"Restaurant",
            "type":"Food & Drink"
        }
    ],
    "sg:phone":"+1 860 513 0165",
    "sg:postcode":"06067",
    "sg:province":"CT",
    "sg:tags":[
        "eating"
    ],
    "wof:name":"Asahi Japanese Restaurant",
    "wof:placetype":"venue"
},
  "geometry": {"coordinates":[-72.678313,41.64839],"type":"Point"}
}