{
  "type": "Feature",
  "properties": {
    "addr:full":"75 Butler St Torrington CT 06790",
    "addr:housenumber":"75",
    "addr:postcode":"06790",
    "addr:street":"Butler St",
    "iso:country":"US",
    "sg:address":"75 Butler St",
    "sg:city":"Torrington",
    "sg:classifiers":[
        {
            "category":"Retail",
            "subcategory":"Repair Shop",
            "type":"Services"
        }
    ],
    "sg:phone":"+1   ",
    "sg:postcode":"06790",
    "sg:province":"CT",
    "wof:name":"Touch Class Housecleaning LLC",
    "wof:placetype":"venue"
},
  "geometry": {"coordinates":[-73.12886,41.810692],"type":"Point"}
}