{
  "type": "Feature",
  "properties": {
    "iso:country":"US",
    "sg:address":"975 Hartford Pike",
    "sg:city":"Dayville",
    "sg:classifiers":[
        {
            "category":"Recreation",
            "type":"Entertainment"
        }
    ],
    "sg:phone":"+1   ",
    "sg:postcode":"06241",
    "sg:province":"CT",
    "wof:name":"A Diamond Ranch",
    "wof:placetype":"venue"
},
  "geometry": {"coordinates":[-71.848783,41.841348],"type":"Point"}
}