{
  "type": "Feature",
  "properties": {
    "addr:full":"99 Essex Rd Old Saybrook CT 06475",
    "addr:housenumber":"99",
    "addr:postcode":"06475",
    "addr:street":"Essex Rd Old Saybrook Ct",
    "iso:country":"US",
    "sg:address":"99 Essex Rd",
    "sg:city":"Old Saybrook",
    "sg:classifiers":[
        {
            "category":"Restaurant",
            "type":"Food & Drink"
        }
    ],
    "sg:menulink":"http://www.allmenus.com/ct/old-saybrook/47501-vinnies-fish-house/menu/",
    "sg:phone":"+1 860 388 4836",
    "sg:postcode":"06475",
    "sg:province":"CT",
    "sg:tags":[
        "seafood",
        "american"
    ],
    "wof:name":"Vinnies Fish House",
    "wof:placetype":"venue"
},
  "geometry": {"coordinates":[-72.35919,41.318788],"type":"Point"}
}