{
  "type": "Feature",
  "properties": {
    "iso:country":"US",
    "sg:address":"473 Washington Ave",
    "sg:city":"North Haven",
    "sg:classifiers":[
        {
            "category":"Retail",
            "subcategory":"Repair Shop",
            "type":"Services"
        }
    ],
    "sg:phone":"+1 203 877 9898",
    "sg:postcode":"06473",
    "sg:province":"CT",
    "sg:tags":[
        "refinishing",
        "furniture"
    ],
    "wof:name":"Jewell Brook Woodworks",
    "wof:placetype":"venue"
},
  "geometry": {"coordinates":[-72.84154700000001,41.413019],"type":"Point"}
}