{
  "type": "Feature",
  "properties": {
    "iso:country":"US",
    "sg:address":"347 Gilead St",
    "sg:city":"Hebron",
    "sg:classifiers":[
        {
            "category":"Professional",
            "type":"Services"
        }
    ],
    "sg:phone":"+1 860 228 4623",
    "sg:postcode":"06248",
    "sg:province":"CT",
    "wof:name":"Dean & Flynn Fiesta Shows",
    "wof:placetype":"venue"
},
  "geometry": {"coordinates":[-72.385842,41.672516],"type":"Point"}
}