{
  "type": "Feature",
  "properties": {
    "iso:country":"US",
    "sg:address":"9 Covey Rd",
    "sg:city":"Burlington",
    "sg:classifiers":[
        {
            "category":"Arts & Performance",
            "subcategory":"Arts Center",
            "type":"Entertainment"
        }
    ],
    "sg:phone":"+1 860 675 3212",
    "sg:postcode":"06013",
    "sg:province":"CT",
    "sg:tags":[
        "performing"
    ],
    "wof:name":"Infinity Music & Entertainment Inc",
    "wof:placetype":"venue"
},
  "geometry": {"coordinates":[-72.962181,41.769124],"type":"Point"}
}