{
  "type": "Feature",
  "properties": {
    "addr:full":"4 Summit St Danbury CT 06810",
    "addr:housenumber":"4",
    "addr:postcode":"06810",
    "addr:street":"Summit St",
    "iso:country":"US",
    "sg:address":"4 Summit St",
    "sg:city":"Danbury",
    "sg:classifiers":[
        {
            "category":"Social Services",
            "subcategory":"Child Care",
            "type":"Services"
        }
    ],
    "sg:phone":"+1   ",
    "sg:postcode":"06810",
    "sg:province":"CT",
    "sg:tags":[
        "day"
    ],
    "wof:name":"Joy of World Daycare",
    "wof:placetype":"venue"
},
  "geometry": {"coordinates":[-73.452015,41.402692],"type":"Point"}
}