{
  "type": "Feature",
  "properties": {
    "addr:full":"120 High St New Haven CT 06511",
    "addr:housenumber":"120",
    "addr:postcode":"06511",
    "addr:street":"High St",
    "iso:country":"US",
    "sg:address":"120 High St",
    "sg:city":"New Haven",
    "sg:classifiers":[
        {
            "category":"Manufacturing",
            "subcategory":"Printing",
            "type":"Manufacturing & Wholesale Goods"
        }
    ],
    "sg:phone":"+1 203 432 1753",
    "sg:postcode":"06511",
    "sg:province":"CT",
    "sg:tags":[
        "lithographic",
        "commercial"
    ],
    "wof:name":"Wings",
    "wof:placetype":"venue"
},
  "geometry": {"coordinates":[-72.928404,41.310598],"type":"Point"}
}