{
  "type": "Feature",
  "properties": {
    "iso:country":"US",
    "sg:address":"137 Rowayton Ave",
    "sg:city":"Norwalk",
    "sg:classifiers":[
        {
            "category":"Professional",
            "subcategory":"Management & Consulting",
            "type":"Services"
        }
    ],
    "sg:phone":"+1 203 656 8600",
    "sg:postcode":"06853",
    "sg:province":"CT",
    "sg:tags":[
        "counselor",
        "public",
        "relations"
    ],
    "wof:name":"CGPR",
    "wof:placetype":"venue"
},
  "geometry": {"coordinates":[-73.44385800000001,41.066929],"type":"Point"}
}