{
  "type": "Feature",
  "properties": {
    "addr:full":"61 S Main St Torrington CT 06790",
    "addr:housenumber":"61",
    "addr:postcode":"06790",
    "addr:street":"S Main St",
    "iso:country":"US",
    "sg:address":"61 S Main St",
    "sg:city":"Torrington",
    "sg:classifiers":[
        {
            "category":"Shopping",
            "subcategory":"Gifts & Souvenirs",
            "type":"Retail Goods"
        }
    ],
    "sg:phone":"+1 860 626 7393",
    "sg:postcode":"06790",
    "sg:province":"CT",
    "wof:name":"Yagar LLC",
    "wof:placetype":"venue"
},
  "geometry": {"coordinates":[-73.121161,41.798922],"type":"Point"}
}