{
  "type": "Feature",
  "properties": {
    "addr:full":"96 Winding Rd Madison CT 06443",
    "addr:housenumber":"96",
    "addr:postcode":"06443",
    "addr:street":"Winding Rd",
    "iso:country":"US",
    "sg:address":"96 Winding Rd",
    "sg:city":"Madison",
    "sg:classifiers":[
        {
            "category":"Shopping",
            "type":"Retail Goods"
        }
    ],
    "sg:phone":"+1 203 421 4805",
    "sg:postcode":"06443",
    "sg:province":"CT",
    "sg:tags":[
        "art",
        "gallery",
        "dealer"
    ],
    "wof:name":"Jane Cunha Assoc",
    "wof:placetype":"venue"
},
  "geometry": {"coordinates":[-72.648489,41.339226],"type":"Point"}
}