{
  "type": "Feature",
  "properties": {
    "addr:full":"233 Bennett St Bridgeport CT 06605",
    "addr:housenumber":"233",
    "addr:postcode":"06605",
    "addr:street":"Bennett St",
    "iso:country":"US",
    "sg:address":"233 Bennett St",
    "sg:city":"Bridgeport",
    "sg:classifiers":[
        {
            "category":"Social Services",
            "subcategory":"Child Care",
            "type":"Services"
        }
    ],
    "sg:phone":"+1 203 335 4200",
    "sg:postcode":"06605",
    "sg:province":"CT",
    "wof:name":"Black Rock Preschool & Child",
    "wof:placetype":"venue"
},
  "geometry": {"coordinates":[-73.229192,41.156554],"type":"Point"}
}