{
  "type": "Feature",
  "properties": {
    "addr:full":"36 Park Dr E Branford CT 06405",
    "addr:housenumber":"36",
    "addr:postcode":"06405",
    "addr:street":"Park Dr E;Ct",
    "iso:country":"US",
    "sg:address":"36 Park Dr E",
    "sg:city":"Branford",
    "sg:classifiers":[
        {
            "category":"Professional",
            "subcategory":"Computer Services",
            "type":"Services"
        },
        {
            "category":"Shopping",
            "subcategory":"Computers & Home Electronics",
            "type":"Retail Goods"
        }
    ],
    "sg:phone":"+1 203 488 4775",
    "sg:postcode":"06405",
    "sg:province":"CT",
    "sg:tags":[
        "development",
        "application",
        "software"
    ],
    "wof:name":"Applied Management Systems Inc",
    "wof:placetype":"venue"
},
  "geometry": {"coordinates":[-72.759474,41.298245],"type":"Point"}
}