{
  "type": "Feature",
  "properties": {
    "addr:full":"148 Eden Dr Danbury CT 06810",
    "addr:housenumber":"148",
    "addr:postcode":"06810",
    "addr:street":"Eden Dr",
    "iso:country":"US",
    "sg:address":"148 Eden Dr",
    "sg:city":"Danbury",
    "sg:classifiers":[
        {
            "category":"Real Estate",
            "subcategory":"Real Estate Agent",
            "type":"Services"
        }
    ],
    "sg:phone":"+1 203 744 6533",
    "sg:postcode":"06810",
    "sg:province":"CT",
    "sg:tags":[
        "authorities",
        "housing"
    ],
    "wof:name":"Danbury Housing Authority",
    "wof:placetype":"venue"
},
  "geometry": {"coordinates":[-73.421299,41.401602],"type":"Point"}
}