{
  "type": "Feature",
  "properties": {
    "addr:full":"47 High Ridge Rd Brookfield CT 06804",
    "addr:housenumber":"47",
    "addr:postcode":"06804",
    "addr:street":"High Ridge Rd",
    "iso:country":"US",
    "sg:address":"47 High Ridge Rd",
    "sg:city":"Brookfield",
    "sg:classifiers":[
        {
            "category":"Professional",
            "subcategory":"Computer Services",
            "type":"Services"
        }
    ],
    "sg:phone":"+1   ",
    "sg:postcode":"06804",
    "sg:province":"CT",
    "sg:tags":[
        "related"
    ],
    "wof:name":"Cybernet Associates",
    "wof:placetype":"venue"
},
  "geometry": {"coordinates":[-73.37153000000001,41.458484],"type":"Point"}
}