{
  "type": "Feature",
  "properties": {
    "addr:full":"53 Cobb St Oakville CT 06779",
    "addr:housenumber":"53",
    "addr:postcode":"06779",
    "addr:street":"Cobb St",
    "iso:country":"US",
    "sg:address":"53 Cobb St",
    "sg:city":"Oakville",
    "sg:classifiers":[
        {
            "category":"Social Services",
            "subcategory":"Child Care",
            "type":"Services"
        }
    ],
    "sg:phone":"+1   ",
    "sg:postcode":"06779",
    "sg:province":"CT",
    "sg:tags":[
        "day"
    ],
    "wof:name":"Tiny Tots Lori Dimaria",
    "wof:placetype":"venue"
},
  "geometry": {"coordinates":[-73.08335099999999,41.602522],"type":"Point"}
}