{
  "type": "Feature",
  "properties": {
    "iso:country":"US",
    "sg:address":"41 Ferncliff Dr",
    "sg:city":"Fairfield",
    "sg:classifiers":[
        {
            "category":"Banks & Credit Unions",
            "subcategory":"Bank",
            "type":"Services"
        }
    ],
    "sg:phone":"+1 203 371 4950",
    "sg:postcode":"06489",
    "sg:province":"CT",
    "sg:tags":[
        "mortgage"
    ],
    "wof:name":"Camden Mortgage Co",
    "wof:placetype":"venue"
},
  "geometry": {"coordinates":[-72.848654,41.571324],"type":"Point"}
}