{
  "type": "Feature",
  "properties": {
    "iso:country":"US",
    "sg:address":"1432 North Rd",
    "sg:city":"Groton",
    "sg:classifiers":[
        {
            "category":"Real Estate",
            "subcategory":"Real Estate Agent",
            "type":"Services"
        }
    ],
    "sg:phone":"+1 860 449 8660",
    "sg:postcode":"06340",
    "sg:province":"CT",
    "wof:name":"Cooper Property Management",
    "wof:placetype":"venue"
},
  "geometry": {"coordinates":[-72.027444,41.391402],"type":"Point"}
}