{
  "type": "Feature",
  "properties": {
    "addr:full":"69 Kenosia Ave Ste 1 Danbury CT 06810",
    "addr:housenumber":"69",
    "addr:postcode":"06810",
    "addr:street":"Kenosia Ave Ste 1 Danbury Ct",
    "iso:country":"US",
    "sg:address":"69 Kenosia Ave Ste 1",
    "sg:city":"Danbury",
    "sg:classifiers":[
        {
            "category":"Social Services",
            "type":"Services"
        },
        {
            "category":"Organizations",
            "subcategory":"Religious Organization",
            "type":"Services"
        }
    ],
    "sg:phone":"+1 203 792 6353",
    "sg:postcode":"06810",
    "sg:province":"CT",
    "wof:name":"The Jewish Federation",
    "wof:placetype":"venue"
},
  "geometry": {"coordinates":[-73.506066,41.387194],"type":"Point"}
}