{
  "type": "Feature",
  "properties": {
    "addr:full":"14 Shelter Rock Rd Danbury CT 06810",
    "addr:housenumber":"14",
    "addr:postcode":"06810",
    "addr:street":"Shelter Rock Rd",
    "iso:country":"US",
    "sg:address":"14 Shelter Rock Rd",
    "sg:city":"Danbury",
    "sg:classifiers":[
        {
            "category":"Recreation",
            "type":"Entertainment"
        }
    ],
    "sg:phone":"+1 203 794 8501",
    "sg:postcode":"06810",
    "sg:province":"CT",
    "sg:tags":[
        "parks"
    ],
    "wof:name":"Bennett Memorial Park",
    "wof:placetype":"venue"
},
  "geometry": {"coordinates":[-73.431577,41.390223],"type":"Point"}
}