{
  "type": "Feature",
  "properties": {
    "iso:country":"US",
    "sg:address":"26 Center St",
    "sg:city":"Canton",
    "sg:classifiers":[
        {
            "category":"Professional",
            "subcategory":"Lawyer & Legal Services",
            "type":"Services"
        }
    ],
    "sg:phone":"+1 860 693 6961",
    "sg:postcode":"06019",
    "sg:province":"CT",
    "wof:name":"Burns & Lovejoy Llc",
    "wof:placetype":"venue"
},
  "geometry": {"coordinates":[-72.920616,41.81125],"type":"Point"}
}