{
  "type": "Feature",
  "properties": {
    "iso:country":"US",
    "sg:address":"4 Caisson Dr",
    "sg:city":"Danbury",
    "sg:classifiers":[
        {
            "category":"Professional",
            "subcategory":"Advertising",
            "type":"Services"
        }
    ],
    "sg:phone":"+1   ",
    "sg:postcode":"06810",
    "sg:province":"CT",
    "sg:tags":[
        "mail",
        "direct"
    ],
    "wof:name":"Persuasive Communications",
    "wof:placetype":"venue"
},
  "geometry": {"coordinates":[-73.490849,41.364695],"type":"Point"}
}