{
  "type": "Feature",
  "properties": {
    "addr:full":"2 Gray Rd Unionville CT 06057",
    "addr:housenumber":"2",
    "addr:postcode":"06057",
    "addr:street":"Gray Rd Unionville Ct",
    "iso:country":"US",
    "sg:address":"2 Gray Rd",
    "sg:city":"Unionville",
    "sg:classifiers":[
        {
            "category":"Professional",
            "subcategory":"Advertising",
            "type":"Services"
        }
    ],
    "sg:phone":"+1   ",
    "sg:postcode":"06057",
    "sg:province":"CT",
    "sg:tags":[
        "ad",
        "mail",
        "management",
        "publishing",
        "direct"
    ],
    "wof:name":"Sourceone",
    "wof:placetype":"venue"
},
  "geometry": {"coordinates":[-73.013452,41.843835],"type":"Point"}
}