{
  "type": "Feature",
  "properties": {
    "iso:country":"US",
    "sg:address":"129 Industrial Park Rd",
    "sg:city":"Middletown",
    "sg:classifiers":[
        {
            "category":"Manufacturing",
            "subcategory":"Metals",
            "type":"Manufacturing & Wholesale Goods"
        }
    ],
    "sg:phone":"+1   ",
    "sg:postcode":"06457",
    "sg:province":"CT",
    "sg:tags":[
        "specializing",
        "fabricator",
        "work",
        "sheet"
    ],
    "wof:name":"Labco Welding Inc",
    "wof:placetype":"venue"
},
  "geometry": {"coordinates":[-72.713753,41.590728],"type":"Point"}
}