{
  "type": "Feature",
  "properties": {
    "addr:full":"41 Roanoak Ave Willimantic CT 06226",
    "addr:housenumber":"41",
    "addr:postcode":"06226",
    "addr:street":"Roanoak Ave",
    "iso:country":"US",
    "sg:address":"41 Roanoak Ave",
    "sg:city":"Willimantic",
    "sg:classifiers":[
        {
            "category":"Organizations",
            "subcategory":"Membership Organization",
            "type":"Services"
        }
    ],
    "sg:phone":"+1   ",
    "sg:postcode":"06226",
    "sg:province":"CT",
    "wof:name":"Gold Wing Road Riders Assn",
    "wof:placetype":"venue"
},
  "geometry": {"coordinates":[-72.228202,41.727676],"type":"Point"}
}