{
  "type": "Feature",
  "properties": {
    "addr:full":"101 Groton Long Point Rd Groton CT 06340",
    "addr:housenumber":"101",
    "addr:postcode":"06340",
    "addr:street":"Groton Long Point Rd Groton Ct",
    "iso:country":"US",
    "sg:address":"101 Groton Long Point Rd",
    "sg:city":"Groton",
    "sg:classifiers":[
        {
            "category":"Education",
            "subcategory":"School",
            "type":"Public Place"
        }
    ],
    "sg:phone":"+1 860 449 7200",
    "sg:postcode":"06340",
    "sg:province":"CT",
    "sg:tags":[
        "executive"
    ],
    "wof:name":"Robert E Fitch Sr High School",
    "wof:placetype":"venue"
},
  "geometry": {"coordinates":[-72.01115799999999,41.343659],"type":"Point"}
}