{
  "type": "Feature",
  "properties": {
    "iso:country":"US",
    "sg:address":"57 Borglum Rd",
    "sg:city":"Wilton",
    "sg:classifiers":[
        {
            "category":"Building & Trades",
            "subcategory":"Construction",
            "type":"Services"
        }
    ],
    "sg:phone":"+1 203 966 4508",
    "sg:postcode":"06897",
    "sg:province":"CT",
    "sg:tags":[
        "repairing",
        "remodeling",
        "contractor"
    ],
    "wof:name":"Borglum & Meek Inc",
    "wof:placetype":"venue"
},
  "geometry": {"coordinates":[-73.446769,41.162559],"type":"Point"}
}