{
  "type": "Feature",
  "properties": {
    "iso:country":"US",
    "sg:address":"405 S Main St",
    "sg:city":"Seymour",
    "sg:classifiers":[
        {
            "category":"Shopping",
            "type":"Retail Goods"
        }
    ],
    "sg:phone":"+1 203 881 2270",
    "sg:postcode":"06483",
    "sg:province":"CT",
    "sg:tags":[
        "merchandise"
    ],
    "wof:name":"Art-Rageous Appeal",
    "wof:placetype":"venue"
},
  "geometry": {"coordinates":[-73.081941,41.370824],"type":"Point"}
}