{
  "type": "Feature",
  "properties": {
    "iso:country":"US",
    "sg:address":"1 Dock St",
    "sg:city":"Stamford",
    "sg:classifiers":[
        {
            "category":"Professional",
            "subcategory":"Research",
            "type":"Services"
        }
    ],
    "sg:phone":"+1 203 973 1353",
    "sg:postcode":"06902",
    "sg:province":"CT",
    "sg:tags":[
        "environmental",
        "ecological"
    ],
    "wof:name":"MGP Environmental Partners",
    "wof:placetype":"venue"
},
  "geometry": {"coordinates":[-73.535926,41.04775],"type":"Point"}
}