{
  "type": "Feature",
  "properties": {
    "iso:country":"US",
    "sg:address":"187 Christian St",
    "sg:city":"Oxford",
    "sg:classifiers":[
        {
            "category":"Utilities",
            "type":"Services"
        }
    ],
    "sg:phone":"+1 203 888 3031",
    "sg:postcode":"06478",
    "sg:province":"CT",
    "sg:tags":[
        "sweeping"
    ],
    "wof:name":"De Santis Inc",
    "wof:placetype":"venue"
},
  "geometry": {"coordinates":[-73.137749,41.47006],"type":"Point"}
}