{
  "type": "Feature",
  "properties": {
    "addr:full":"22 Maynard Rd New Haven CT 06513",
    "addr:housenumber":"22",
    "addr:postcode":"06513",
    "addr:street":"Maynard Rd",
    "iso:country":"US",
    "sg:address":"22 Maynard Rd",
    "sg:city":"New Haven",
    "sg:classifiers":[
        {
            "category":"Education",
            "subcategory":"School",
            "type":"Public Place"
        }
    ],
    "sg:phone":"+1   ",
    "sg:postcode":"06513",
    "sg:province":"CT",
    "wof:name":"Dominick Ferrara School",
    "wof:placetype":"venue"
},
  "geometry": {"coordinates":[-72.85106399999999,41.334256],"type":"Point"}
}