{
  "type": "Feature",
  "properties": {
    "iso:country":"US",
    "sg:address":"174 Larkspur Rd",
    "sg:city":"Stamford",
    "sg:classifiers":[
        {
            "category":"Shopping",
            "type":"Retail Goods"
        }
    ],
    "sg:phone":"+1 203 322 4518",
    "sg:postcode":"06903",
    "sg:province":"CT",
    "sg:tags":[
        "product",
        "wood"
    ],
    "sg:website":"www.adirondackwoodproducts.com",
    "wof:name":"Adirondack Wood Products",
    "wof:placetype":"venue"
},
  "geometry": {"coordinates":[-73.550693,41.137071],"type":"Point"}
}