{
  "type": "Feature",
  "properties": {
    "addr:full":"1416 Bedford St Stamford CT 06905",
    "addr:housenumber":"1416",
    "addr:postcode":"06905",
    "addr:street":"Bedford St",
    "iso:country":"US",
    "sg:address":"1416 Bedford St",
    "sg:city":"Stamford",
    "sg:classifiers":[
        {
            "category":"Health Services",
            "subcategory":"Doctor",
            "type":"Services"
        }
    ],
    "sg:phone":"+1   ",
    "sg:postcode":"06905",
    "sg:province":"CT",
    "sg:tags":[
        "medical"
    ],
    "wof:name":"Chan-Kook Rha MD PC",
    "wof:placetype":"venue"
},
  "geometry": {"coordinates":[-73.540728,41.063939],"type":"Point"}
}