{
  "type": "Feature",
  "properties": {
    "iso:country":"US",
    "sg:address":"1592 N Broad St",
    "sg:city":"Meriden",
    "sg:classifiers":[
        {
            "category":"Home & Garden",
            "subcategory":"Home Furnishings",
            "type":"Retail Goods"
        }
    ],
    "sg:phone":"+1   ",
    "sg:postcode":"06450",
    "sg:province":"CT",
    "sg:tags":[
        "a",
        "oil",
        "stove",
        "gas",
        "wood",
        "including",
        "pellet"
    ],
    "wof:name":"Buck Stoves Of Meriden",
    "wof:placetype":"venue"
},
  "geometry": {"coordinates":[-72.77577599999999,41.561161],"type":"Point"}
}