{
  "type": "Feature",
  "properties": {
    "addr:full":"49 Butterfield Rd Newtown CT 06470",
    "addr:housenumber":"49",
    "addr:postcode":"06470",
    "addr:street":"Butterfield Rd",
    "iso:country":"US",
    "sg:address":"49 Butterfield Rd",
    "sg:city":"Newtown",
    "sg:classifiers":[
        {
            "category":"Building & Trades",
            "subcategory":"Construction",
            "type":"Services"
        }
    ],
    "sg:phone":"+1 203 270 9854",
    "sg:postcode":"06470",
    "sg:province":"CT",
    "sg:tags":[
        "project"
    ],
    "wof:name":"Wm A Mangold Construction",
    "wof:placetype":"venue"
},
  "geometry": {"coordinates":[-73.33331200000001,41.444663],"type":"Point"}
}