{
  "type": "Feature",
  "properties": {
    "addr:full":"1165 Boston Post Rd West Haven CT 06516",
    "addr:housenumber":"1165",
    "addr:postcode":"06516",
    "addr:street":"Boston Post Rd;Haven",
    "iso:country":"US",
    "sg:address":"1165 Boston Post Rd",
    "sg:city":"West Haven",
    "sg:classifiers":[
        {
            "category":"Home & Garden",
            "subcategory":"Hardware",
            "type":"Retail Goods"
        }
    ],
    "sg:phone":"+1 203 934 8606",
    "sg:postcode":"06516",
    "sg:province":"CT",
    "sg:tags":[
        "building",
        "material"
    ],
    "wof:name":"Orange True Value",
    "wof:placetype":"venue"
},
  "geometry": {"coordinates":[-72.983963,41.280757],"type":"Point"}
}