{
  "type": "Feature",
  "properties": {
    "addr:full":"114 Commerce Dr Fairfield CT 06484",
    "addr:housenumber":"114",
    "addr:postcode":"06484",
    "addr:street":"Commerce Dr",
    "iso:country":"US",
    "sg:address":"114 Commerce Dr",
    "sg:city":"Fairfield",
    "sg:classifiers":[
        {
            "category":"Retail",
            "subcategory":"Auto Rental",
            "type":"Services"
        }
    ],
    "sg:phone":"+1 203 330 1399",
    "sg:postcode":"06484",
    "sg:province":"CT",
    "sg:tags":[
        "renting",
        "automobile"
    ],
    "wof:name":"Enterprise Rent-A-Car",
    "wof:placetype":"venue"
},
  "geometry": {"coordinates":[-73.121996,41.277134],"type":"Point"}
}