{
  "type": "Feature",
  "properties": {
    "iso:country":"US",
    "sg:address":"88 Fairy Lake Rd",
    "sg:city":"Salem",
    "sg:classifiers":[
        {
            "category":"Building & Trades",
            "subcategory":"Plumbing",
            "type":"Services"
        }
    ],
    "sg:phone":"+1 860 859 2097",
    "sg:postcode":"06420",
    "sg:province":"CT",
    "sg:tags":[
        "plumbing",
        "contractor"
    ],
    "wof:name":"Muscarlla Jseph T Plbg Htg Inc",
    "wof:placetype":"venue"
},
  "geometry": {"coordinates":[-72.242672,41.464801],"type":"Point"}
}