{
  "type": "Feature",
  "properties": {
    "iso:country":"US",
    "sg:address":"9 Windy Ridge",
    "sg:city":"Ridgefield",
    "sg:classifiers":[
        {
            "category":"Retail",
            "subcategory":"Laundry & Dry Cleaning",
            "type":"Services"
        }
    ],
    "sg:phone":"+1 203 431 0832",
    "sg:postcode":"06877",
    "sg:province":"CT",
    "sg:tags":[
        "cleaners",
        "rug",
        "carpet"
    ],
    "wof:name":"Kain Carpet Cleaning",
    "wof:placetype":"venue"
},
  "geometry": {"coordinates":[-73.499994,41.256774],"type":"Point"}
}