{
  "type": "Feature",
  "properties": {
    "iso:country":"US",
    "sg:address":"39 Great Hill Rd",
    "sg:city":"Derby",
    "sg:classifiers":[
        {
            "category":"Communications",
            "subcategory":"Radio Station",
            "type":"Services"
        }
    ],
    "sg:phone":"+1 203 735 4606",
    "sg:postcode":"06418",
    "sg:province":"CT",
    "sg:tags":[
        "company",
        "broadcasting"
    ],
    "wof:name":"WADS",
    "wof:placetype":"venue"
},
  "geometry": {"coordinates":[-73.1139,41.343961],"type":"Point"}
}