{
  "type": "Feature",
  "properties": {
    "addr:full":"281 Campbell Ave West Haven CT 06516",
    "addr:housenumber":"281",
    "addr:postcode":"06516",
    "addr:street":"Campbell Ave",
    "iso:country":"US",
    "sg:address":"281 Campbell Ave",
    "sg:city":"West Haven",
    "sg:classifiers":[
        {
            "category":"Shopping",
            "subcategory":"Florist",
            "type":"Retail Goods"
        }
    ],
    "sg:phone":"+1 203 934 0522",
    "sg:postcode":"06516",
    "sg:province":"CT",
    "wof:name":"Fitzgerald's Florist",
    "wof:placetype":"venue"
},
  "geometry": {"coordinates":[-72.948001,41.267059],"type":"Point"}
}