{
  "type": "Feature",
  "properties": {
    "iso:country":"US",
    "sg:address":"15 E Putnam Ave",
    "sg:city":"Greenwich",
    "sg:classifiers":[
        {
            "category":"Professional",
            "subcategory":"Business Services",
            "type":"Services"
        }
    ],
    "sg:phone":"+1 203 622 1114",
    "sg:postcode":"06830",
    "sg:province":"CT",
    "sg:tags":[
        "communications",
        "telegraph",
        "photocopying"
    ],
    "wof:name":"Mail Boxes Etc",
    "wof:placetype":"venue"
},
  "geometry": {"coordinates":[-73.62606700000001,41.031988],"type":"Point"}
}