{
  "type": "Feature",
  "properties": {
    "addr:full":"8 Prospect Ave Trumbull CT 06611",
    "addr:housenumber":"8",
    "addr:postcode":"06611",
    "addr:street":"Prospect Ave",
    "iso:country":"US",
    "sg:address":"8 Prospect Ave",
    "sg:city":"Trumbull",
    "sg:classifiers":[
        {
            "category":"Building & Trades",
            "subcategory":"Construction",
            "type":"Services"
        }
    ],
    "sg:phone":"+1 203 268 6099",
    "sg:postcode":"06611",
    "sg:province":"CT",
    "sg:tags":[
        "coping",
        "plastering",
        "tiling",
        "pool",
        "swimming"
    ],
    "wof:name":"Vinmor Pools Co",
    "wof:placetype":"venue"
},
  "geometry": {"coordinates":[-73.236906,41.236943],"type":"Point"}
}