{
  "type": "Feature",
  "properties": {
    "addr:full":"37 Orchard Pl New Haven CT 06511",
    "addr:housenumber":"37",
    "addr:postcode":"06511",
    "addr:street":"Orchard Pl",
    "iso:country":"US",
    "sg:address":"37 Orchard Pl",
    "sg:city":"New Haven",
    "sg:classifiers":[
        {
            "category":"Real Estate",
            "subcategory":"Real Estate Operator",
            "type":"Services"
        },
        {
            "category":"Building & Trades",
            "subcategory":"Construction",
            "type":"Services"
        }
    ],
    "sg:phone":"+1 203 865 5778",
    "sg:postcode":"06511",
    "sg:province":"CT",
    "sg:tags":[
        "residential",
        "builder",
        "property",
        "home"
    ],
    "wof:name":"Florence Virtue Homes Inc",
    "wof:placetype":"venue"
},
  "geometry": {"coordinates":[-72.936573,41.318281],"type":"Point"}
}