{
  "type": "Feature",
  "properties": {
    "addr:full":"335 Wolcott Hill Rd Wethersfield CT 06109",
    "addr:housenumber":"335",
    "addr:postcode":"06109",
    "addr:street":"Wolcott Hill Rd",
    "iso:country":"US",
    "sg:address":"335 Wolcott Hill Rd",
    "sg:city":"Wethersfield",
    "sg:classifiers":[
        {
            "category":"Social Services",
            "type":"Services"
        }
    ],
    "sg:phone":"+1   ",
    "sg:postcode":"06109",
    "sg:province":"CT",
    "wof:name":"Otis Family Lld",
    "wof:placetype":"venue"
},
  "geometry": {"coordinates":[-72.669207,41.710912],"type":"Point"}
}