{
  "type": "Feature",
  "properties": {
    "iso:country":"US",
    "sg:address":"28 Perry Ave",
    "sg:city":"Norwich",
    "sg:classifiers":[
        {
            "category":"Retail",
            "subcategory":"Repair Shop",
            "type":"Services"
        }
    ],
    "sg:phone":"+1   ",
    "sg:postcode":"06360",
    "sg:province":"CT",
    "sg:tags":[
        "printer",
        "sales"
    ],
    "wof:name":"M & J Printers",
    "wof:placetype":"venue"
},
  "geometry": {"coordinates":[-72.089122,41.507982],"type":"Point"}
}