{
  "type": "Feature",
  "properties": {
    "iso:country":"US",
    "sg:address":"70 Church St",
    "sg:city":"Naugatuck",
    "sg:classifiers":[
        {
            "category":"Shopping",
            "subcategory":"Shoes",
            "type":"Retail Goods"
        }
    ],
    "sg:phone":"+1 203 729 8425",
    "sg:postcode":"06770",
    "sg:province":"CT",
    "wof:name":"Rossi's Shoes",
    "wof:placetype":"venue"
},
  "geometry": {"coordinates":[-73.05623300000001,41.487789],"type":"Point"}
}