{
  "type": "Feature",
  "properties": {
    "addr:full":"83 River Rd Collinsville CT 06019",
    "addr:housenumber":"83",
    "addr:postcode":"06019",
    "addr:street":"River Rd Collinsville Ct",
    "iso:country":"US",
    "sg:address":"83 River Rd",
    "sg:city":"Collinsville",
    "sg:classifiers":[
        {
            "category":"Retail",
            "subcategory":"Auto Repair",
            "type":"Services"
        }
    ],
    "sg:phone":"+1 860 693 1910",
    "sg:postcode":"06019",
    "sg:province":"CT",
    "wof:name":"River Road Automotive",
    "wof:placetype":"venue"
},
  "geometry": {"coordinates":[-72.925301,41.8255],"type":"Point"}
}