{
  "type": "Feature",
  "properties": {
    "addr:full":"475 Jones Hill Rd West Haven CT 06516",
    "addr:housenumber":"475",
    "addr:postcode":"06516",
    "addr:street":"Jones Hill Rd;Haven",
    "iso:country":"US",
    "sg:address":"475 Jones Hill Rd",
    "sg:city":"West Haven",
    "sg:classifiers":[
        {
            "category":"Building & Trades",
            "subcategory":"Landscaping Services",
            "type":"Services"
        }
    ],
    "sg:phone":"+1 203 934 7011",
    "sg:postcode":"06516",
    "sg:province":"CT",
    "sg:tags":[
        "landscape"
    ],
    "wof:name":"Dan Shine Landscaping LLC",
    "wof:placetype":"venue"
},
  "geometry": {"coordinates":[-72.97707800000001,41.249158],"type":"Point"}
}