{
  "type": "Feature",
  "properties": {
    "addr:full":"800 Village Walk Guilford CT 06437",
    "addr:housenumber":"800",
    "addr:postcode":"06437",
    "addr:street":"Village Walk",
    "iso:country":"US",
    "sg:address":"800 Village Walk",
    "sg:city":"Guilford",
    "sg:classifiers":[
        {
            "category":"Retail",
            "subcategory":"Photofinishing",
            "type":"Services"
        }
    ],
    "sg:phone":"+1   ",
    "sg:postcode":"06437",
    "sg:province":"CT",
    "sg:tags":[
        "laboratory"
    ],
    "wof:name":"In Photo Corp",
    "wof:placetype":"venue"
},
  "geometry": {"coordinates":[-72.674751,41.288191],"type":"Point"}
}