{
  "type": "Feature",
  "properties": {
    "addr:full":"1202 Silver Ln East Hartford CT 06118",
    "addr:housenumber":"1202",
    "addr:postcode":"06118",
    "addr:street":"Silver Ln;Hartford",
    "iso:country":"US",
    "sg:address":"1202 Silver Ln",
    "sg:city":"East Hartford",
    "sg:classifiers":[
        {
            "category":"Building & Trades",
            "subcategory":"Landscaping Services",
            "type":"Services"
        }
    ],
    "sg:phone":"+1 860 569 4391",
    "sg:postcode":"06118",
    "sg:province":"CT",
    "wof:name":"Rons Prof Lawn Care Svc",
    "wof:placetype":"venue"
},
  "geometry": {"coordinates":[-72.590802,41.766071],"type":"Point"}
}