{
  "type": "Feature",
  "properties": {
    "addr:full":"9 King Arthur Dr Niantic CT 06357",
    "addr:housenumber":"9",
    "addr:postcode":"06357",
    "addr:street":"King Arthur Dr",
    "iso:country":"US",
    "sg:address":"9 King Arthur Dr",
    "sg:city":"Niantic",
    "sg:classifiers":[
        {
            "category":"Freight",
            "type":"Transportation"
        }
    ],
    "sg:phone":"+1 860 739 3386",
    "sg:postcode":"06357",
    "sg:province":"CT",
    "sg:tags":[
        "general"
    ],
    "wof:name":"Rent-A-Space",
    "wof:placetype":"venue"
},
  "geometry": {"coordinates":[-72.206627,41.359505],"type":"Point"}
}