{
  "type": "Feature",
  "properties": {
    "addr:full":"1456 Whalley Ave New Haven CT 06515",
    "addr:housenumber":"1456",
    "addr:postcode":"06515",
    "addr:street":"Whalley Ave",
    "iso:country":"US",
    "sg:address":"1456 Whalley Ave",
    "sg:city":"New Haven",
    "sg:classifiers":[
        {
            "category":"Retail",
            "subcategory":"Laundry & Dry Cleaning",
            "type":"Services"
        }
    ],
    "sg:phone":"+1   ",
    "sg:postcode":"06515",
    "sg:province":"CT",
    "sg:tags":[
        "drycleaning",
        "plant"
    ],
    "wof:name":"VIP Dry Cleaners",
    "wof:placetype":"venue"
},
  "geometry": {"coordinates":[-72.976613,41.334346],"type":"Point"}
}