{
  "type": "Feature",
  "properties": {
    "iso:country":"US",
    "sg:address":"208 Pine Hill Rd",
    "sg:city":"New Fairfield",
    "sg:classifiers":[
        {
            "category":"Building & Trades",
            "subcategory":"Construction",
            "type":"Services"
        }
    ],
    "sg:phone":"+1 203 746 4386",
    "sg:postcode":"06812",
    "sg:province":"CT",
    "sg:tags":[
        "contractor"
    ],
    "wof:name":"New England Tile",
    "wof:placetype":"venue"
},
  "geometry": {"coordinates":[-73.50523,41.508926],"type":"Point"}
}