{
  "type": "Feature",
  "properties": {
    "addr:full":"213 Pixlee Pl Bridgeport CT 06610",
    "addr:housenumber":"213",
    "addr:postcode":"06610",
    "addr:street":"Pixlee Pl",
    "iso:country":"US",
    "sg:address":"213 Pixlee Pl",
    "sg:city":"Bridgeport",
    "sg:classifiers":[
        {
            "category":"Professional",
            "subcategory":"Business Services",
            "type":"Services"
        }
    ],
    "sg:phone":"+1   ",
    "sg:postcode":"06610",
    "sg:province":"CT",
    "wof:name":"Affordable Bail Bonds",
    "wof:placetype":"venue"
},
  "geometry": {"coordinates":[-73.159999,41.188742],"type":"Point"}
}