{
  "type": "Feature",
  "properties": {
    "addr:full":"17 Heronvue Rd Greenwich CT 06831",
    "addr:housenumber":"17",
    "addr:postcode":"06831",
    "addr:street":"Heronvue Rd",
    "iso:country":"US",
    "sg:address":"17 Heronvue Rd",
    "sg:city":"Greenwich",
    "sg:classifiers":[
        {
            "category":"Social Services",
            "subcategory":"Adult Care",
            "type":"Services"
        }
    ],
    "sg:phone":"+1 203 629 9694",
    "sg:postcode":"06831",
    "sg:province":"CT",
    "sg:tags":[
        "home",
        "residential"
    ],
    "wof:name":"Assisted Living Assoc LLC",
    "wof:placetype":"venue"
},
  "geometry": {"coordinates":[-73.69609,41.082478],"type":"Point"}
}