{
  "type": "Feature",
  "properties": {
    "addr:full":"1080 Elm St Rocky Hill CT 06067",
    "addr:housenumber":"1080",
    "addr:postcode":"06067",
    "addr:street":"Elm St",
    "iso:country":"US",
    "sg:address":"1080 Elm St",
    "sg:city":"Rocky Hill",
    "sg:classifiers":[
        {
            "category":"Personal",
            "type":"Services"
        }
    ],
    "sg:phone":"+1   ",
    "sg:postcode":"06067",
    "sg:province":"CT",
    "wof:name":"Distefano Medical Group",
    "wof:placetype":"venue"
},
  "geometry": {"coordinates":[-72.67826599999999,41.658162],"type":"Point"}
}