{
  "type": "Feature",
  "properties": {
    "addr:full":"30 Silvermine Ave Norwalk CT 06850",
    "addr:housenumber":"30",
    "addr:postcode":"06850",
    "addr:street":"Silvermine Ave",
    "iso:country":"US",
    "sg:address":"30 Silvermine Ave",
    "sg:city":"Norwalk",
    "sg:classifiers":[
        {
            "category":"Building & Trades",
            "subcategory":"Construction",
            "type":"Services"
        }
    ],
    "sg:phone":"+1 203 846 6762",
    "sg:postcode":"06850",
    "sg:province":"CT",
    "sg:tags":[
        "driveway"
    ],
    "wof:name":"Santaniello Driveway Sealers",
    "wof:placetype":"venue"
},
  "geometry": {"coordinates":[-73.432135,41.128305],"type":"Point"}
}