{
  "type": "Feature",
  "properties": {
    "addr:full":"190 Ruby Rd West Willington CT 06279",
    "addr:housenumber":"190",
    "addr:postcode":"06279",
    "addr:street":"Ruby Rd West Willington Ct",
    "iso:country":"US",
    "sg:address":"190 Ruby Rd",
    "sg:city":"West Willington",
    "sg:classifiers":[
        {
            "category":"Building & Trades",
            "subcategory":"Construction",
            "type":"Services"
        }
    ],
    "sg:phone":"+1 860 684 3372",
    "sg:postcode":"06279",
    "sg:province":"CT",
    "sg:tags":[
        "residential"
    ],
    "wof:name":"Lytwyn Construction LLC",
    "wof:placetype":"venue"
},
  "geometry": {"coordinates":[-72.267785,41.892074],"type":"Point"}
}