{
  "type": "Feature",
  "properties": {
    "iso:country":"US",
    "sg:address":"585 Windsor St",
    "sg:city":"Hartford",
    "sg:classifiers":[
        {
            "category":"Building & Trades",
            "subcategory":"Construction",
            "type":"Services"
        }
    ],
    "sg:phone":"+1 860 947 9948",
    "sg:postcode":"06120",
    "sg:province":"CT",
    "sg:tags":[
        "contractor"
    ],
    "wof:name":"CT Specialists LLC",
    "wof:placetype":"venue"
},
  "geometry": {"coordinates":[-72.671481,41.782327],"type":"Point"}
}