{
  "type": "Feature",
  "properties": {
    "addr:full":"90 N Ridge St Port Chester CT 10573",
    "addr:housenumber":"90",
    "addr:postcode":"10573",
    "addr:street":"N Ridge St Port Chester Ct",
    "iso:country":"US",
    "sg:address":"90 N Ridge St",
    "sg:city":"Port Chester",
    "sg:classifiers":[
        {
            "category":"Real Estate",
            "subcategory":"Real Estate Agent",
            "type":"Services"
        }
    ],
    "sg:phone":"+1 914 937 4572",
    "sg:postcode":"10573",
    "sg:province":"CT",
    "wof:name":"Young Estate LLC",
    "wof:placetype":"venue"
},
  "geometry": {"coordinates":[-73.68110799999999,41.013114],"type":"Point"}
}