{
  "type": "Feature",
  "properties": {
    "iso:country":"US",
    "sg:address":"1177 High Ridge Rd",
    "sg:city":"Stamford",
    "sg:classifiers":[
        {
            "category":"Professional",
            "subcategory":"Advertising",
            "type":"Services"
        }
    ],
    "sg:phone":"+1   ",
    "sg:postcode":"06905",
    "sg:province":"CT",
    "sg:tags":[
        "promotion",
        "public",
        "relations",
        "sales"
    ],
    "wof:name":"High Tech Pr Inc",
    "wof:placetype":"venue"
},
  "geometry": {"coordinates":[-73.547023,41.109643],"type":"Point"}
}