{
  "type": "Feature",
  "properties": {
    "iso:country":"US",
    "sg:address":"2425 Morehouse Hwy",
    "sg:city":"Fairfield",
    "sg:classifiers":[
        {
            "category":"Sports & Exercise",
            "subcategory":"Golf",
            "type":"Entertainment"
        }
    ],
    "sg:phone":"+1 203 255 7302",
    "sg:postcode":"06824",
    "sg:province":"CT",
    "sg:tags":[
        "course"
    ],
    "wof:name":"Munipality Of Town Of Fairfiel",
    "wof:placetype":"venue"
},
  "geometry": {"coordinates":[-73.270157,41.2209],"type":"Point"}
}