{
  "type": "Feature",
  "properties": {
    "addr:full":"40 Crosshill Rd Hartford CT 06107",
    "addr:housenumber":"40",
    "addr:postcode":"06107",
    "addr:street":"Crosshill Rd",
    "iso:country":"US",
    "sg:address":"40 Crosshill Rd",
    "sg:city":"Hartford",
    "sg:classifiers":[
        {
            "category":"Manufacturing",
            "subcategory":"Tools & Machinery",
            "type":"Manufacturing & Wholesale Goods"
        }
    ],
    "sg:phone":"+1 860 519 0555",
    "sg:postcode":"06107",
    "sg:province":"CT",
    "sg:tags":[
        "filter",
        "equipment",
        "furnace",
        "conditioning",
        "air"
    ],
    "wof:name":"Environmental Filter Service",
    "wof:placetype":"venue"
},
  "geometry": {"coordinates":[-72.74216699999999,41.739912],"type":"Point"}
}