{
  "type": "Feature",
  "properties": {
    "addr:full":"64 Windmill Hill Wethersfield CT 06109",
    "addr:housenumber":"64",
    "addr:postcode":"06109",
    "addr:street":"Windmill Hill Wethersfield Ct",
    "iso:country":"US",
    "sg:address":"64 Windmill Hill",
    "sg:city":"Wethersfield",
    "sg:classifiers":[
        {
            "category":"Manufacturing",
            "subcategory":"Tools & Machinery",
            "type":"Manufacturing & Wholesale Goods"
        }
    ],
    "sg:phone":"+1 860 529 2544",
    "sg:postcode":"06109",
    "sg:province":"CT",
    "sg:tags":[
        "conductive",
        "wiring",
        "devices",
        "mfg"
    ],
    "wof:name":"Hubbell Incorporated",
    "wof:placetype":"venue"
},
  "geometry": {"coordinates":[-72.69150999999999,41.694582],"type":"Point"}
}