{
  "type": "Feature",
  "properties": {
    "iso:country":"US",
    "sg:address":"198 Ledyard St",
    "sg:city":"Hartford",
    "sg:classifiers":[
        {
            "category":"Building & Trades",
            "subcategory":"Construction",
            "type":"Services"
        },
        {
            "category":"Utilities",
            "subcategory":"Sewage",
            "type":"Services"
        }
    ],
    "sg:phone":"+1 860 296 3448",
    "sg:postcode":"06114",
    "sg:province":"CT",
    "sg:tags":[
        "excavation",
        "contractor",
        "sewer",
        "paving",
        "demolition",
        "driveway"
    ],
    "sg:website":"http://www.rcrizzoconstruction.com",
    "wof:name":"Rizzo Construction Company Inc",
    "wof:placetype":"venue"
},
  "geometry": {"coordinates":[-72.669641,41.742593],"type":"Point"}
}