{
  "type": "Feature",
  "properties": {
    "iso:country":"US",
    "sg:address":"38 Cottage Grove Cir",
    "sg:city":"Bloomfield",
    "sg:classifiers":[
        {
            "category":"Retail",
            "subcategory":"Repair Shop",
            "type":"Services"
        }
    ],
    "sg:phone":"+1   ",
    "sg:postcode":"06002",
    "sg:province":"CT",
    "sg:tags":[
        "elevator"
    ],
    "wof:name":"Samuel T Kelley",
    "wof:placetype":"venue"
},
  "geometry": {"coordinates":[-72.718721,41.820314],"type":"Point"}
}