{
  "type": "Feature",
  "properties": {
    "addr:full":"26 Middlefield Rd Oxford CT 06478",
    "addr:housenumber":"26",
    "addr:postcode":"06478",
    "addr:street":"Middlefield Rd",
    "iso:country":"US",
    "sg:address":"26 Middlefield Rd",
    "sg:city":"Oxford",
    "sg:classifiers":[
        {
            "category":"Banks & Credit Unions",
            "subcategory":"Financial Services",
            "type":"Services"
        }
    ],
    "sg:phone":"+1 203 266 6180",
    "sg:postcode":"06478",
    "sg:province":"CT",
    "sg:tags":[
        "trust",
        "nonprofit",
        "management"
    ],
    "wof:name":"Mazaika Family Foundation",
    "wof:placetype":"venue"
},
  "geometry": {"coordinates":[-73.096339,41.405791],"type":"Point"}
}