{
  "type": "Feature",
  "properties": {
    "addr:full":"246 Berkshire Rd Sandy Hook CT 06482",
    "addr:housenumber":"246",
    "addr:postcode":"06482",
    "addr:street":"Berkshire Rd;Hook Ct",
    "iso:country":"US",
    "sg:address":"246 Berkshire Rd",
    "sg:city":"Sandy Hook",
    "sg:classifiers":[
        {
            "category":"Building & Trades",
            "subcategory":"Landscaping Services",
            "type":"Services"
        }
    ],
    "sg:phone":"+1 203 426 5437",
    "sg:postcode":"06482",
    "sg:province":"CT",
    "sg:tags":[
        "tree"
    ],
    "wof:name":"Northeast Tree Service LLC",
    "wof:placetype":"venue"
},
  "geometry": {"coordinates":[-73.20679699999999,41.386219],"type":"Point"}
}