{
  "type": "Feature",
  "properties": {
    "iso:country":"US",
    "sg:address":"50 Nye Rd",
    "sg:city":"Glastonbury",
    "sg:classifiers":[
        {
            "category":"Professional",
            "subcategory":"Advertising",
            "type":"Services"
        }
    ],
    "sg:phone":"+1   ",
    "sg:postcode":"06033",
    "sg:province":"CT",
    "sg:tags":[
        "se",
        "public",
        "direct",
        "relations",
        "digital"
    ],
    "wof:name":"Cronin and Company Inc",
    "wof:placetype":"venue"
},
  "geometry": {"coordinates":[-72.60074400000001,41.719469],"type":"Point"}
}