{
  "type": "Feature",
  "properties": {
    "iso:country":"US",
    "sg:address":"9 1st St",
    "sg:city":"Norwalk",
    "sg:classifiers":[
        {
            "category":"Real Estate",
            "subcategory":"Real Estate Agent",
            "type":"Services"
        }
    ],
    "sg:phone":"+1 203 855 0406",
    "sg:postcode":"06855",
    "sg:province":"CT",
    "wof:name":"Palotay Real Estate",
    "wof:placetype":"venue"
},
  "geometry": {"coordinates":[-73.40534100000001,41.097979],"type":"Point"}
}