{
  "type": "Feature",
  "properties": {
    "addr:full":"1379 Boston Ave Bridgeport CT 06610",
    "addr:housenumber":"1379",
    "addr:postcode":"06610",
    "addr:street":"Boston Ave",
    "iso:country":"US",
    "sg:address":"1379 Boston Ave",
    "sg:city":"Bridgeport",
    "sg:classifiers":[
        {
            "category":"Personal",
            "subcategory":"Beauty Salon",
            "type":"Services"
        }
    ],
    "sg:phone":"+1   ",
    "sg:postcode":"06610",
    "sg:province":"CT",
    "sg:tags":[
        "shop"
    ],
    "wof:name":"Princess Nails",
    "wof:placetype":"venue"
},
  "geometry": {"coordinates":[-73.16781899999999,41.193446],"type":"Point"}
}