{
  "type": "Feature",
  "properties": {
    "iso:country":"US",
    "sg:address":"49 Welles St",
    "sg:city":"Glastonbury",
    "sg:classifiers":[
        {
            "category":"Social Services",
            "subcategory":"Adult Care",
            "type":"Services"
        }
    ],
    "sg:phone":"+1   ",
    "sg:postcode":"06033",
    "sg:province":"CT",
    "sg:tags":[
        "management",
        "disability"
    ],
    "wof:name":"Crawford & Company 579",
    "wof:placetype":"venue"
},
  "geometry": {"coordinates":[-72.60744699999999,41.713951],"type":"Point"}
}