{
  "type": "Feature",
  "properties": {
    "addr:full":"366 Old Colchester Rd Amston CT 06231",
    "addr:housenumber":"366",
    "addr:postcode":"06231",
    "addr:street":"Old Colchester Rd Amston Ct",
    "iso:country":"US",
    "sg:address":"366 Old Colchester Rd",
    "sg:city":"Amston",
    "sg:classifiers":[
        {
            "category":"Professional",
            "subcategory":"Art Services",
            "type":"Services"
        }
    ],
    "sg:phone":"+1   ",
    "sg:postcode":"06231",
    "sg:province":"CT",
    "sg:tags":[
        "commercial",
        "design"
    ],
    "wof:name":"Robert Italiano",
    "wof:placetype":"venue"
},
  "geometry": {"coordinates":[-72.357444,41.616186],"type":"Point"}
}