{
  "type": "Feature",
  "properties": {
    "iso:country":"US",
    "sg:address":"55 Rhode Island Line Rd",
    "sg:city":"Putnam",
    "sg:classifiers":[
        {
            "category":"Retail",
            "subcategory":"Repair Shop",
            "type":"Services"
        }
    ],
    "sg:phone":"+1   ",
    "sg:postcode":"06260",
    "sg:province":"CT",
    "wof:name":"Fitzgeralds Repair",
    "wof:placetype":"venue"
},
  "geometry": {"coordinates":[-71.804873,41.917451],"type":"Point"}
}