{
  "type": "Feature",
  "properties": {
    "addr:full":"20 Hunt Ln East Haven CT 06512",
    "addr:housenumber":"20",
    "addr:postcode":"06512",
    "addr:street":"Hunt Ln",
    "iso:country":"US",
    "sg:address":"20 Hunt Ln",
    "sg:city":"East Haven",
    "sg:classifiers":[
        {
            "category":"Professional",
            "subcategory":"Computer Services",
            "type":"Services"
        }
    ],
    "sg:phone":"+1   ",
    "sg:postcode":"06512",
    "sg:province":"CT",
    "sg:tags":[
        "prepackaged",
        "software"
    ],
    "wof:name":"Higgins Sftwr Consulting LLC",
    "wof:placetype":"venue"
},
  "geometry": {"coordinates":[-72.843243,41.323233],"type":"Point"}
}