{
  "type": "Feature",
  "properties": {
    "iso:country":"US",
    "sg:address":"50 Stanford Dr",
    "sg:city":"Farmington",
    "sg:classifiers":[
        {
            "category":"Professional",
            "subcategory":"Computer Services",
            "type":"Services"
        }
    ],
    "sg:phone":"+1   ",
    "sg:postcode":"06032",
    "sg:province":"CT",
    "sg:tags":[
        "programing",
        "custom"
    ],
    "wof:name":"Tsr Inc",
    "wof:placetype":"venue"
},
  "geometry": {"coordinates":[-72.814257,41.710363],"type":"Point"}
}