{
  "type": "Feature",
  "properties": {
    "addr:full":"30 Bargate Rd Guilford CT 06437",
    "addr:housenumber":"30",
    "addr:postcode":"06437",
    "addr:street":"Bargate Rd",
    "iso:country":"US",
    "sg:address":"30 Bargate Rd",
    "sg:city":"Guilford",
    "sg:classifiers":[
        {
            "category":"Professional",
            "subcategory":"Business Services",
            "type":"Services"
        }
    ],
    "sg:phone":"+1   ",
    "sg:postcode":"06437",
    "sg:province":"CT",
    "wof:name":"Michael Macris",
    "wof:placetype":"venue"
},
  "geometry": {"coordinates":[-72.638144,41.30143],"type":"Point"}
}