{
  "type": "Feature",
  "properties": {
    "iso:country":"US",
    "sg:address":"20 Plains Rd",
    "sg:city":"Essex",
    "sg:classifiers":[
        {
            "category":"Organizations",
            "subcategory":"Professional Association",
            "type":"Services"
        }
    ],
    "sg:phone":"+1   ",
    "sg:postcode":"06426",
    "sg:province":"CT",
    "sg:tags":[
        "for",
        "industry",
        "trade",
        "boating",
        "fishing",
        "marine"
    ],
    "wof:name":"Connecticut Marine Trains Assn",
    "wof:placetype":"venue"
},
  "geometry": {"coordinates":[-72.40307799999999,41.350399],"type":"Point"}
}