{
  "type": "Feature",
  "properties": {
    "iso:country":"US",
    "sg:address":"42 Lakewood Dr",
    "sg:city":"Trumbull",
    "sg:classifiers":[
        {
            "category":"Building & Trades",
            "subcategory":"Pest Control",
            "type":"Services"
        }
    ],
    "sg:phone":"+1   ",
    "sg:postcode":"06611",
    "sg:province":"CT",
    "wof:name":"Arrow Pest Control Inc",
    "wof:placetype":"venue"
},
  "geometry": {"coordinates":[-73.219281,41.263231],"type":"Point"}
}