{
  "type": "Feature",
  "properties": {
    "addr:full":"8 Jefferson St Plainville CT 06062",
    "addr:housenumber":"8",
    "addr:postcode":"06062",
    "addr:street":"Jefferson St",
    "iso:country":"US",
    "sg:address":"8 Jefferson St",
    "sg:city":"Plainville",
    "sg:classifiers":[
        {
            "category":"Organizations",
            "subcategory":"Religious Organization",
            "type":"Services"
        }
    ],
    "sg:phone":"+1   ",
    "sg:postcode":"06062",
    "sg:province":"CT",
    "wof:name":"David & Edie Chandler",
    "wof:placetype":"venue"
},
  "geometry": {"coordinates":[-72.855029,41.67795],"type":"Point"}
}