{
  "type": "Feature",
  "properties": {
    "addr:full":"92 Vine St New Britain CT 06052",
    "addr:housenumber":"92",
    "addr:postcode":"06052",
    "addr:street":"Vine St",
    "iso:country":"US",
    "sg:address":"92 Vine St",
    "sg:city":"New Britain",
    "sg:classifiers":[
        {
            "category":"Social Services",
            "type":"Services"
        }
    ],
    "sg:phone":"+1   ",
    "sg:postcode":"06052",
    "sg:province":"CT",
    "sg:tags":[
        "agency"
    ],
    "wof:name":"Family Services Central Conn I",
    "wof:placetype":"venue"
},
  "geometry": {"coordinates":[-72.79411399999999,41.663256],"type":"Point"}
}