{
  "type": "Feature",
  "properties": {
    "iso:country":"US",
    "sg:address":"15 Meadowpark Ave W",
    "sg:city":"Stamford",
    "sg:classifiers":[
        {
            "category":"Retail",
            "subcategory":"Laundry & Dry Cleaning",
            "type":"Services"
        }
    ],
    "sg:phone":"+1   ",
    "sg:postcode":"06905",
    "sg:province":"CT",
    "sg:tags":[
        "drycleaning",
        "plant"
    ],
    "wof:name":"Staten Island Cleaning & Dyg",
    "wof:placetype":"venue"
},
  "geometry": {"coordinates":[-73.55492,41.091269],"type":"Point"}
}