{
  "type": "Feature",
  "properties": {
    "addr:full":"2 Corporate Dr Trumbull CT 06611",
    "addr:housenumber":"2",
    "addr:postcode":"06611",
    "addr:street":"Corporate Dr",
    "iso:country":"US",
    "sg:address":"2 Corporate Dr",
    "sg:city":"Trumbull",
    "sg:classifiers":[
        {
            "category":"Professional",
            "subcategory":"Accounting & Tax Preparation",
            "type":"Services"
        }
    ],
    "sg:phone":"+1 203 268 1060",
    "sg:postcode":"06611",
    "sg:province":"CT",
    "sg:tags":[
        "accountant"
    ],
    "wof:name":"Kordish & Co",
    "wof:placetype":"venue"
},
  "geometry": {"coordinates":[-73.227789,41.292671],"type":"Point"}
}