{
  "type": "Feature",
  "properties": {
    "addr:full":"60 Butternut Ln Stratford CT 06614",
    "addr:housenumber":"60",
    "addr:postcode":"06614",
    "addr:street":"Butternut Ln",
    "iso:country":"US",
    "sg:address":"60 Butternut Ln",
    "sg:city":"Stratford",
    "sg:classifiers":[
        {
            "category":"Shopping",
            "subcategory":"Photographic Equipment",
            "type":"Retail Goods"
        }
    ],
    "sg:phone":"+1 203 377 8997",
    "sg:postcode":"06614",
    "sg:province":"CT",
    "sg:tags":[
        "supply"
    ],
    "wof:name":"That Cat Camera Support LLC",
    "wof:placetype":"venue"
},
  "geometry": {"coordinates":[-73.122512,41.230666],"type":"Point"}
}