{
  "type": "Feature",
  "properties": {
    "addr:full":"556 Main St East Haven CT 06512",
    "addr:housenumber":"556",
    "addr:postcode":"06512",
    "addr:street":"Main St",
    "iso:country":"US",
    "sg:address":"556 Main St",
    "sg:city":"East Haven",
    "sg:classifiers":[
        {
            "category":"Retail",
            "subcategory":"Auto Repair",
            "type":"Services"
        }
    ],
    "sg:phone":"+1 203 467 7406",
    "sg:postcode":"06512",
    "sg:province":"CT",
    "sg:tags":[
        "body",
        "automobile",
        "painting"
    ],
    "wof:name":"Granco Auto Ctr",
    "wof:placetype":"venue"
},
  "geometry": {"coordinates":[-72.880977,41.283182],"type":"Point"}
}