{
  "type": "Feature",
  "properties": {
    "iso:country":"US",
    "sg:address":"37 Secor Rd",
    "sg:city":"Brookfield",
    "sg:classifiers":[
        {
            "category":"Professional",
            "type":"Services"
        }
    ],
    "sg:phone":"+1 203 798 8447",
    "sg:postcode":"06804",
    "sg:province":"CT",
    "sg:tags":[
        "establishment"
    ],
    "wof:name":"Ancheril Associates",
    "wof:placetype":"venue"
},
  "geometry": {"coordinates":[-73.38051400000001,41.429514],"type":"Point"}
}