{
  "type": "Feature",
  "properties": {
    "addr:full":"5 Norton Ter Ansonia CT 06401",
    "addr:housenumber":"5",
    "addr:postcode":"06401",
    "addr:street":"Norton Ter Ansonia Ct",
    "iso:country":"US",
    "sg:address":"5 Norton Ter",
    "sg:city":"Ansonia",
    "sg:classifiers":[
        {
            "category":"Home & Garden",
            "subcategory":"Carpets & Floor Coverings",
            "type":"Retail Goods"
        }
    ],
    "sg:phone":"+1 203 734 3461",
    "sg:postcode":"06401",
    "sg:province":"CT",
    "wof:name":"Dimick Floor Covering",
    "wof:placetype":"venue"
},
  "geometry": {"coordinates":[-73.046618,41.326783],"type":"Point"}
}