{
  "type": "Feature",
  "properties": {
    "iso:country":"US",
    "sg:address":"99 N Granby Rd",
    "sg:city":"Granby",
    "sg:classifiers":[
        {
            "category":"Insurance",
            "subcategory":"Hazard Insurance",
            "type":"Services"
        }
    ],
    "sg:phone":"+1 860 844 8553",
    "sg:postcode":"06035",
    "sg:province":"CT",
    "sg:tags":[
        "carrier"
    ],
    "wof:name":"Firemans Fund",
    "wof:placetype":"venue"
},
  "geometry": {"coordinates":[-72.801818,41.963426],"type":"Point"}
}