{
  "type": "Feature",
  "properties": {
    "iso:country":"US",
    "sg:address":"120 School St",
    "sg:city":"Danielson",
    "sg:classifiers":[
        {
            "category":"Professional",
            "subcategory":"Management & Consulting",
            "type":"Services"
        }
    ],
    "sg:phone":"+1   ",
    "sg:postcode":"06239",
    "sg:province":"CT",
    "wof:name":"Meridian MGT Danielson CT",
    "wof:placetype":"venue"
},
  "geometry": {"coordinates":[-71.882216,41.803424],"type":"Point"}
}