{
  "type": "Feature",
  "properties": {
    "iso:country":"US",
    "sg:address":"815 N Colony Rd",
    "sg:city":"Wallingford",
    "sg:classifiers":[
        {
            "category":"Shopping",
            "subcategory":"Computers & Home Electronics",
            "type":"Retail Goods"
        }
    ],
    "sg:phone":"+1 203 269 0180",
    "sg:postcode":"06492",
    "sg:province":"CT",
    "sg:tags":[
        "equipment",
        "electronic",
        "supply"
    ],
    "wof:name":"Radio Shack",
    "wof:placetype":"venue"
},
  "geometry": {"coordinates":[-72.81085,41.480154],"type":"Point"}
}