{
  "type": "Feature",
  "properties": {
    "addr:full":"1280 Hopmeadow St Simsbury CT 06070",
    "addr:housenumber":"1280",
    "addr:postcode":"06070",
    "addr:street":"Hopmeadow St Simsbury Ct",
    "iso:country":"US",
    "sg:address":"1280 Hopmeadow St",
    "sg:city":"Simsbury",
    "sg:classifiers":[
        {
            "category":"Education",
            "subcategory":"Dance Studio",
            "type":"Public Place"
        }
    ],
    "sg:phone":"+1   ",
    "sg:postcode":"06070",
    "sg:province":"CT",
    "wof:name":"Terpischore Dance Theatre LLC",
    "wof:placetype":"venue"
},
  "geometry": {"coordinates":[-72.786203,41.901459],"type":"Point"}
}