{
  "type": "Feature",
  "properties": {
    "iso:country":"US",
    "sg:address":"1 Commerce Rd",
    "sg:city":"Newtown",
    "sg:classifiers":[
        {
            "category":"Banks & Credit Unions",
            "subcategory":"Bank",
            "type":"Services"
        }
    ],
    "sg:phone":"+1 203 270 6658",
    "sg:postcode":"06470",
    "sg:province":"CT",
    "sg:tags":[
        "mutual",
        "savings"
    ],
    "wof:name":"Union Savings Bank",
    "wof:placetype":"venue"
},
  "geometry": {"coordinates":[-73.28691499999999,41.414816],"type":"Point"}
}