{
  "type": "Feature",
  "properties": {
    "iso:country":"US",
    "sg:address":"238 Willimantic Rd",
    "sg:city":"Chaplin",
    "sg:classifiers":[
        {
            "category":"Organizations",
            "subcategory":"Community Association",
            "type":"Services"
        }
    ],
    "sg:phone":"+1   ",
    "sg:postcode":"06235",
    "sg:province":"CT",
    "wof:name":"Loyal Order of The Moose 1440",
    "wof:placetype":"venue"
},
  "geometry": {"coordinates":[-72.14612099999999,41.75773],"type":"Point"}
}