{
  "type": "Feature",
  "properties": {
    "iso:country":"US",
    "sg:address":"1 Annie Pl",
    "sg:city":"Stamford",
    "sg:classifiers":[
        {
            "category":"Manufacturing",
            "subcategory":"Metals",
            "type":"Manufacturing & Wholesale Goods"
        }
    ],
    "sg:phone":"+1 203 348 8865",
    "sg:postcode":"06902",
    "sg:province":"CT",
    "sg:tags":[
        "lock",
        "safe",
        "coin",
        "vault"
    ],
    "sg:website":"www.accurate.to",
    "wof:name":"Accurate Lock & Hardware",
    "wof:placetype":"venue"
},
  "geometry": {"coordinates":[-73.556387,41.04705],"type":"Point"}
}