{
  "type": "Feature",
  "properties": {
    "iso:country":"US",
    "sg:address":"18 Gilbert Ave",
    "sg:city":"Hamden",
    "sg:classifiers":[
        {
            "category":"Freight",
            "type":"Transportation"
        }
    ],
    "sg:phone":"+1 203 230 1996",
    "sg:postcode":"06514",
    "sg:province":"CT",
    "sg:tags":[
        "operator",
        "local",
        "trucking"
    ],
    "wof:name":"William Brooks Trucking",
    "wof:placetype":"venue"
},
  "geometry": {"coordinates":[-72.937023,41.357181],"type":"Point"}
}