{
  "type": "Feature",
  "properties": {
    "addr:full":"716 Beaumont Hwy Lebanon CT 06249",
    "addr:housenumber":"716",
    "addr:postcode":"06249",
    "addr:street":"Beaumont Hwy Lebanon Ct",
    "iso:country":"US",
    "sg:address":"716 Beaumont Hwy",
    "sg:city":"Lebanon",
    "sg:classifiers":[
        {
            "category":"Real Estate",
            "subcategory":"Real Estate Agent",
            "type":"Services"
        }
    ],
    "sg:phone":"+1 860 887 5000",
    "sg:postcode":"06249",
    "sg:province":"CT",
    "sg:tags":[
        "brokerage"
    ],
    "wof:name":"Lyman",
    "wof:placetype":"venue"
},
  "geometry": {"coordinates":[-72.226874,41.660333],"type":"Point"}
}