{
  "type": "Feature",
  "properties": {
    "iso:country":"US",
    "sg:address":"201 Spring Valley Rd",
    "sg:city":"Ridgefield",
    "sg:classifiers":[
        {
            "category":"Professional",
            "subcategory":"Computer Services",
            "type":"Services"
        }
    ],
    "sg:phone":"+1 203 431 0489",
    "sg:postcode":"06877",
    "sg:province":"CT",
    "sg:tags":[
        "leasing"
    ],
    "wof:name":"Tradewell Corp",
    "wof:placetype":"venue"
},
  "geometry": {"coordinates":[-73.540401,41.34486],"type":"Point"}
}