{
  "type": "Feature",
  "properties": {
    "addr:full":"223 W Main St Meriden CT 06451",
    "addr:housenumber":"223",
    "addr:postcode":"06451",
    "addr:street":"W Main St",
    "iso:country":"US",
    "sg:address":"223 W Main St",
    "sg:city":"Meriden",
    "sg:classifiers":[
        {
            "category":"Autos & Motor Vehicles",
            "subcategory":"Auto Supplies",
            "type":"Retail Goods"
        }
    ],
    "sg:phone":"+1 203 630 2224",
    "sg:postcode":"06451",
    "sg:province":"CT",
    "wof:name":"Tire Exchange",
    "wof:placetype":"venue"
},
  "geometry": {"coordinates":[-72.811154,41.539242],"type":"Point"}
}