{
  "type": "Feature",
  "properties": {
    "iso:country":"US",
    "sg:address":"1 Balsam Rd",
    "sg:city":"Wallingford",
    "sg:classifiers":[
        {
            "category":"Building & Trades",
            "subcategory":"Plumbing",
            "type":"Services"
        }
    ],
    "sg:phone":"+1 203 284 2317",
    "sg:postcode":"06492",
    "sg:province":"CT",
    "sg:tags":[
        "air",
        "conditioning",
        "heating"
    ],
    "wof:name":"Kevin McGauley",
    "wof:placetype":"venue"
},
  "geometry": {"coordinates":[-72.827196,41.429241],"type":"Point"}
}