{
  "type": "Feature",
  "properties": {
    "iso:country":"US",
    "sg:address":"11 Middle Rd",
    "sg:city":"Preston",
    "sg:classifiers":[
        {
            "category":"Building & Trades",
            "subcategory":"Plumbing",
            "type":"Services"
        },
        {
            "category":"Building & Trades",
            "subcategory":"Construction",
            "type":"Services"
        }
    ],
    "sg:phone":"+1 860 886 6857",
    "sg:postcode":"06365",
    "sg:province":"CT",
    "sg:tags":[
        "plumber",
        "industrial",
        "system",
        "specialty",
        "heating",
        "contractors-commercial",
        "contractor",
        "air conditioning"
    ],
    "wof:name":"4m Plumbing & Heating",
    "wof:placetype":"venue"
},
  "geometry": {"coordinates":[-72.045754,41.489911],"type":"Point"}
}