{
  "type": "Feature",
  "properties": {
    "addr:full":"32 Wall St Norwalk CT 06850",
    "addr:housenumber":"32",
    "addr:postcode":"06850",
    "addr:street":"Wall St",
    "iso:country":"US",
    "sg:address":"32 Wall St",
    "sg:city":"Norwalk",
    "sg:classifiers":[
        {
            "category":"Personal",
            "subcategory":"Beauty Salon",
            "type":"Services"
        }
    ],
    "sg:phone":"+1 203 831 0194",
    "sg:postcode":"06850",
    "sg:province":"CT",
    "wof:name":"Beauty By Aijah",
    "wof:placetype":"venue"
},
  "geometry": {"coordinates":[-73.413096,41.118013],"type":"Point"}
}