{
  "type": "Feature",
  "properties": {
    "addr:full":"45 Mill Rock Road East Old Saybrook CT 06475",
    "addr:housenumber":"45",
    "addr:postcode":"06475",
    "addr:street":"Mill Rock Road East Old Saybrook Ct",
    "iso:country":"US",
    "sg:address":"45 Mill Rock Road East",
    "sg:city":"Old Saybrook",
    "sg:classifiers":[
        {
            "category":"Restaurant",
            "type":"Food & Drink"
        }
    ],
    "sg:phone":"+1 860 388 5400",
    "sg:postcode":"06475",
    "sg:province":"CT",
    "wof:name":"Som Siam East",
    "wof:placetype":"venue"
},
  "geometry": {"coordinates":[-72.376785,41.302636],"type":"Point"}
}