{
  "type": "Feature",
  "properties": {
    "addr:full":"10 Liberty Way Niantic CT 06357",
    "addr:housenumber":"10",
    "addr:postcode":"06357",
    "addr:street":"Liberty Way",
    "iso:country":"US",
    "sg:address":"10 Liberty Way",
    "sg:city":"Niantic",
    "sg:classifiers":[
        {
            "category":"Professional",
            "type":"Services"
        }
    ],
    "sg:phone":"+1   ",
    "sg:postcode":"06357",
    "sg:province":"CT",
    "wof:name":"Five Star Property Services LL",
    "wof:placetype":"venue"
},
  "geometry": {"coordinates":[-72.244291,41.317128],"type":"Point"}
}