{
  "type": "Feature",
  "properties": {
    "addr:full":"74 W Park Pl Stamford CT 06901",
    "addr:housenumber":"74",
    "addr:postcode":"06901",
    "addr:street":"W Park Pl",
    "iso:country":"US",
    "sg:address":"74 W Park Pl",
    "sg:city":"Stamford",
    "sg:classifiers":[
        {
            "category":"Shopping",
            "subcategory":"Computers & Home Electronics",
            "type":"Retail Goods"
        }
    ],
    "sg:phone":"+1 203 324 9495",
    "sg:postcode":"06901",
    "sg:province":"CT",
    "sg:tags":[
        "renting",
        "equipment",
        "leasing"
    ],
    "wof:name":"Scg Capital Corporation",
    "wof:placetype":"venue"
},
  "geometry": {"coordinates":[-73.541988,41.053314],"type":"Point"}
}