{
  "type": "Feature",
  "properties": {
    "iso:country":"US",
    "sg:address":"1 Parky Dr",
    "sg:city":"Enfield",
    "sg:classifiers":[
        {
            "category":"Professional",
            "type":"Services"
        }
    ],
    "sg:phone":"+1 860 741 6462",
    "sg:postcode":"06082",
    "sg:province":"CT",
    "wof:name":"Society For Preservation",
    "wof:placetype":"venue"
},
  "geometry": {"coordinates":[-72.574557,41.944642],"type":"Point"}
}