{
  "type": "Feature",
  "properties": {
    "iso:country":"US",
    "sg:address":"14 Granger Cir",
    "sg:city":"East Granby",
    "sg:classifiers":[
        {
            "category":"Professional",
            "subcategory":"Business Services",
            "type":"Services"
        }
    ],
    "sg:phone":"+1   ",
    "sg:postcode":"06026",
    "sg:province":"CT",
    "wof:name":"Portmarnock Partners LLC",
    "wof:placetype":"venue"
},
  "geometry": {"coordinates":[-72.765489,41.95244],"type":"Point"}
}