{
  "type": "Feature",
  "properties": {
    "iso:country":"US",
    "sg:address":"170 Flanders Rd",
    "sg:city":"Niantic",
    "sg:classifiers":[
        {
            "category":"Food & Beverages",
            "subcategory":"Meat & Fish",
            "type":"Retail Goods"
        }
    ],
    "sg:phone":"+1 860 739 5557",
    "sg:postcode":"06357",
    "sg:province":"CT",
    "wof:name":"Toms Choice Meats",
    "wof:placetype":"venue"
},
  "geometry": {"coordinates":[-72.21019699999999,41.34943],"type":"Point"}
}