{
  "type": "Feature",
  "properties": {
    "iso:country":"US",
    "sg:address":"20 Pin Oak Ct",
    "sg:city":"Westport",
    "sg:classifiers":[
        {
            "category":"Organizations",
            "subcategory":"Non-profit Organization",
            "type":"Services"
        }
    ],
    "sg:phone":"+1 203 226 6454",
    "sg:postcode":"06880",
    "sg:province":"CT",
    "wof:name":"Japan Us Society",
    "wof:placetype":"venue"
},
  "geometry": {"coordinates":[-73.378562,41.170114],"type":"Point"}
}