{
  "type": "Feature",
  "properties": {
    "addr:full":"85 Kitts Ln Newington CT 06111",
    "addr:housenumber":"85",
    "addr:postcode":"06111",
    "addr:street":"Kitts Ln",
    "iso:country":"US",
    "sg:address":"85 Kitts Ln",
    "sg:city":"Newington",
    "sg:classifiers":[
        {
            "category":"Organizations",
            "subcategory":"Community Association",
            "type":"Services"
        }
    ],
    "sg:phone":"+1   ",
    "sg:postcode":"06111",
    "sg:province":"CT",
    "wof:name":"VFW Dept of Connecticut L",
    "wof:placetype":"venue"
},
  "geometry": {"coordinates":[-72.710049,41.685294],"type":"Point"}
}