{
  "type": "Feature",
  "properties": {
    "addr:full":"805 Sherman Ave Hamden CT 06514",
    "addr:housenumber":"805",
    "addr:postcode":"06514",
    "addr:street":"Sherman Ave",
    "iso:country":"US",
    "sg:address":"805 Sherman Ave",
    "sg:city":"Hamden",
    "sg:classifiers":[
        {
            "category":"Wholesale",
            "subcategory":"Construction Materials",
            "type":"Manufacturing & Wholesale Goods"
        }
    ],
    "sg:phone":"+1 203 288 7112",
    "sg:postcode":"06514",
    "sg:province":"CT",
    "sg:tags":[
        "marble"
    ],
    "wof:name":"Presidential Marble & Granite",
    "wof:placetype":"venue"
},
  "geometry": {"coordinates":[-72.91518499999999,41.401016],"type":"Point"}
}