{
  "type": "Feature",
  "properties": {
    "addr:full":"8 Depot St Watertown CT 06795",
    "addr:housenumber":"8",
    "addr:postcode":"06795",
    "addr:street":"Depot St",
    "iso:country":"US",
    "sg:address":"8 Depot St",
    "sg:city":"Watertown",
    "sg:classifiers":[
        {
            "category":"Professional",
            "subcategory":"Accounting & Tax Preparation",
            "type":"Services"
        }
    ],
    "sg:phone":"+1 860 274 6623",
    "sg:postcode":"06795",
    "sg:province":"CT",
    "sg:tags":[
        "return",
        "preparation-business"
    ],
    "wof:name":"Kalita Joseph S",
    "wof:placetype":"venue"
},
  "geometry": {"coordinates":[-73.114762,41.601947],"type":"Point"}
}