{
  "type": "Feature",
  "properties": {
    "iso:country":"US",
    "sg:address":"680 Boston Post Rd",
    "sg:city":"Milford",
    "sg:classifiers":[
        {
            "category":"Education",
            "subcategory":"Dance Studio",
            "type":"Public Place"
        }
    ],
    "sg:phone":"+1 203 876 1919",
    "sg:postcode":"06460",
    "sg:province":"CT",
    "sg:tags":[
        "instruction",
        "dancing"
    ],
    "sg:website":"www.creativemovements.com",
    "wof:name":"Creative Movements Dance Co",
    "wof:placetype":"venue"
},
  "geometry": {"coordinates":[-73.059834,41.23222],"type":"Point"}
}