{
  "type": "Feature",
  "properties": {
    "addr:full":"260 Mountain Rd Suffield CT 06078",
    "addr:housenumber":"260",
    "addr:postcode":"06078",
    "addr:street":"Mountain Rd",
    "iso:country":"US",
    "sg:address":"260 Mountain Rd",
    "sg:city":"Suffield",
    "sg:classifiers":[
        {
            "category":"Education",
            "subcategory":"School",
            "type":"Public Place"
        }
    ],
    "sg:phone":"+1   ",
    "sg:postcode":"06078",
    "sg:province":"CT",
    "sg:tags":[
        "high",
        "junior"
    ],
    "wof:name":"McAlister Middle School",
    "wof:placetype":"venue"
},
  "geometry": {"coordinates":[-72.660788,41.983764],"type":"Point"}
}