{
  "type": "Feature",
  "properties": {
    "iso:country":"US",
    "sg:address":"208 Hunting Ridge Rd",
    "sg:city":"Stamford",
    "sg:classifiers":[
        {
            "category":"Building & Trades",
            "subcategory":"Landscaping Services",
            "type":"Services"
        }
    ],
    "sg:phone":"+1 203 322 3883",
    "sg:postcode":"06903",
    "sg:province":"CT",
    "sg:tags":[
        "tree"
    ],
    "wof:name":"Tree Care Consultants",
    "wof:placetype":"venue"
},
  "geometry": {"coordinates":[-73.57767699999999,41.132795],"type":"Point"}
}