{
  "type": "Feature",
  "properties": {
    "iso:country":"US",
    "sg:address":"81 Greenway Close",
    "sg:city":"Port Chester",
    "sg:classifiers":[
        {
            "category":"Real Estate",
            "subcategory":"Real Estate Agent",
            "type":"Services"
        }
    ],
    "sg:phone":"+1 914 937 0421",
    "sg:postcode":"10573",
    "sg:province":"CT",
    "wof:name":"US Realty Services",
    "wof:placetype":"venue"
},
  "geometry": {"coordinates":[-73.67657,41.02881],"type":"Point"}
}