{
  "type": "Feature",
  "properties": {
    "addr:full":"1266 E Main St Stamford CT 06902",
    "addr:housenumber":"1266",
    "addr:postcode":"06902",
    "addr:street":"E Main St",
    "iso:country":"US",
    "sg:address":"1266 E Main St",
    "sg:city":"Stamford",
    "sg:classifiers":[
        {
            "category":"Banks & Credit Unions",
            "subcategory":"Investment Brokerage",
            "type":"Services"
        }
    ],
    "sg:phone":"+1 203 425 2070",
    "sg:postcode":"06902",
    "sg:province":"CT",
    "sg:tags":[
        "advisory",
        "financial"
    ],
    "wof:name":"Stamford Capital Group Inc",
    "wof:placetype":"venue"
},
  "geometry": {"coordinates":[-73.509433,41.060032],"type":"Point"}
}