{
  "type": "Feature",
  "properties": {
    "addr:full":"6 Old Line Ln Canton CT 06019",
    "addr:housenumber":"6",
    "addr:postcode":"06019",
    "addr:street":"Old Line Ln Canton Ct",
    "iso:country":"US",
    "sg:address":"6 Old Line Ln",
    "sg:city":"Canton",
    "sg:classifiers":[
        {
            "category":"Banks & Credit Unions",
            "subcategory":"Investment Brokerage",
            "type":"Services"
        }
    ],
    "sg:phone":"+1 860 693 6330",
    "sg:postcode":"06019",
    "sg:province":"CT",
    "sg:tags":[
        "advisory"
    ],
    "wof:name":"M L Gueret & Company",
    "wof:placetype":"venue"
},
  "geometry": {"coordinates":[-72.91764499999999,41.831731],"type":"Point"}
}