{
  "type": "Feature",
  "properties": {
    "addr:full":"312 Village Hill Rd Lebanon CT 06249",
    "addr:housenumber":"312",
    "addr:postcode":"06249",
    "addr:street":"Village Hill Rd",
    "iso:country":"US",
    "sg:address":"312 Village Hill Rd",
    "sg:city":"Lebanon",
    "sg:classifiers":[
        {
            "category":"Social Services",
            "subcategory":"Child Care",
            "type":"Services"
        }
    ],
    "sg:phone":"+1   ",
    "sg:postcode":"06249",
    "sg:province":"CT",
    "sg:tags":[
        "day"
    ],
    "wof:name":"Red Sneakers Day Care Center",
    "wof:placetype":"venue"
},
  "geometry": {"coordinates":[-72.239667,41.68437],"type":"Point"}
}