{
  "type": "Feature",
  "properties": {
    "iso:country":"US",
    "sg:address":"50 Sage Park Rd",
    "sg:city":"Windsor",
    "sg:classifiers":[
        {
            "category":"Education",
            "subcategory":"School",
            "type":"Public Place"
        }
    ],
    "sg:phone":"+1 860 687 2020",
    "sg:postcode":"06095",
    "sg:province":"CT",
    "sg:tags":[
        "executive"
    ],
    "wof:name":"Windsor High School",
    "wof:placetype":"venue"
},
  "geometry": {"coordinates":[-72.656446,41.841712],"type":"Point"}
}