{
  "type": "Feature",
  "properties": {
    "iso:country":"US",
    "sg:address":"635 Broad St",
    "sg:city":"New London",
    "sg:classifiers":[
        {
            "category":"Food & Beverages",
            "subcategory":"Fruits & Vegetables",
            "type":"Retail Goods"
        }
    ],
    "sg:phone":"+1 860 442 3185",
    "sg:postcode":"06320",
    "sg:province":"CT",
    "sg:tags":[
        "stand"
    ],
    "wof:name":"Jacques Fruite Store",
    "wof:placetype":"venue"
},
  "geometry": {"coordinates":[-72.12477699999999,41.367246],"type":"Point"}
}