{
  "type": "Feature",
  "properties": {
    "iso:country":"US",
    "sg:address":"34 1/2 Pembroke Rd",
    "sg:city":"Danbury",
    "sg:classifiers":[
        {
            "category":"Education",
            "subcategory":"Special Training",
            "type":"Public Place"
        },
        {
            "category":"Education",
            "subcategory":"Preschool",
            "type":"Public Place"
        },
        {
            "category":"Education",
            "subcategory":"School",
            "type":"Public Place"
        },
        {
            "category":"Government",
            "subcategory":"Office",
            "type":"Public Place"
        }
    ],
    "sg:phone":"+1 203 797 4751",
    "sg:postcode":"06811",
    "sg:province":"CT",
    "sg:tags":[
        "kindergarten",
        "educational",
        "elementary"
    ],
    "wof:name":"Pembroke Elementary School",
    "wof:placetype":"venue"
},
  "geometry": {"coordinates":[-73.47374000000001,41.433367],"type":"Point"}
}