{
  "type": "Feature",
  "properties": {
    "addr:full":"36 Mill Plain Rd Suite 201 Danbury CT 06811",
    "addr:housenumber":"36",
    "addr:postcode":"06811",
    "addr:street":"Mill Plain Rd Suite 201",
    "iso:country":"US",
    "sg:address":"36 Mill Plain Rd Suite 201",
    "sg:city":"Danbury",
    "sg:classifiers":[
        {
            "category":"Insurance",
            "subcategory":"Hazard Insurance",
            "type":"Services"
        },
        {
            "category":"Insurance",
            "subcategory":"Insurance Agent",
            "type":"Services"
        },
        {
            "category":"Insurance",
            "subcategory":"Life Insurance",
            "type":"Services"
        }
    ],
    "sg:phone":"+1 203 617 0640",
    "sg:postcode":"06811",
    "sg:province":"CT",
    "sg:tags":[
        "auto"
    ],
    "sg:website":"http://statefarm.mqgroup.com/url.asp?usr=070101",
    "wof:name":"Huse, Thomas G - State Farm Insurance Agent",
    "wof:placetype":"venue"
},
  "geometry": {"coordinates":[-73.497353,41.388889],"type":"Point"}
}