{
  "type": "Feature",
  "properties": {
    "addr:full":"280 Boston Ave Bridgeport CT 06610",
    "addr:housenumber":"280",
    "addr:postcode":"06610",
    "addr:street":"Boston Ave",
    "iso:country":"US",
    "sg:address":"280 Boston Ave",
    "sg:city":"Bridgeport",
    "sg:classifiers":[
        {
            "category":"Restaurant",
            "type":"Food & Drink"
        }
    ],
    "sg:phone":"+1 203 366 7486",
    "sg:postcode":"06610",
    "sg:province":"CT",
    "wof:name":"White's Diner",
    "wof:placetype":"venue"
},
  "geometry": {"coordinates":[-73.18532500000001,41.201229],"type":"Point"}
}