{
  "type": "Feature",
  "properties": {
    "addr:full":"60 Old Town Park Rd New Milford CT 06776",
    "addr:housenumber":"60",
    "addr:postcode":"06776",
    "addr:street":"Old Town Park Rd",
    "iso:country":"US",
    "sg:address":"60 Old Town Park Rd",
    "sg:city":"New Milford",
    "sg:classifiers":[
        {
            "category":"Education",
            "subcategory":"School",
            "type":"Public Place"
        }
    ],
    "sg:phone":"+1   ",
    "sg:postcode":"06776",
    "sg:province":"CT",
    "sg:tags":[
        "child",
        "day",
        "care"
    ],
    "wof:name":"Hill and Plain Elementary Schl",
    "wof:placetype":"venue"
},
  "geometry": {"coordinates":[-73.43258299999999,41.533751],"type":"Point"}
}