{
  "type": "Feature",
  "properties": {
    "addr:full":"15 E Main St Waterbury CT 06702",
    "addr:housenumber":"15",
    "addr:postcode":"06702",
    "addr:street":"E Main St",
    "iso:country":"US",
    "sg:address":"15 E Main St",
    "sg:city":"Waterbury",
    "sg:classifiers":[
        {
            "category":"Shopping",
            "subcategory":"Gifts & Souvenirs",
            "type":"Retail Goods"
        }
    ],
    "sg:phone":"+1 203 757 6155",
    "sg:postcode":"06702",
    "sg:province":"CT",
    "sg:tags":[
        "party",
        "supply"
    ],
    "wof:name":"Merengue Party Shop",
    "wof:placetype":"venue"
},
  "geometry": {"coordinates":[-73.03970099999999,41.55565],"type":"Point"}
}