{
  "type": "Feature",
  "properties": {
    "addr:full":"2001 W Main St Stamford CT 06902",
    "addr:housenumber":"2001",
    "addr:postcode":"06902",
    "addr:street":"W Main St",
    "iso:country":"US",
    "sg:address":"2001 W Main St",
    "sg:city":"Stamford",
    "sg:classifiers":[
        {
            "category":"Social Services",
            "type":"Services"
        }
    ],
    "sg:phone":"+1 203 912 8222",
    "sg:postcode":"06902",
    "sg:province":"CT",
    "sg:tags":[
        "counselor",
        "marriage",
        "family"
    ],
    "wof:name":"Agape Christian Counseling",
    "wof:placetype":"venue"
},
  "geometry": {"coordinates":[-73.563479,41.048911],"type":"Point"}
}