{
  "type": "Feature",
  "properties": {
    "addr:full":"749 N Stone St West Suffield CT 06093",
    "addr:housenumber":"749",
    "addr:postcode":"06093",
    "addr:street":"N Stone St West Suffield Ct",
    "iso:country":"US",
    "sg:address":"749 N Stone St",
    "sg:city":"West Suffield",
    "sg:classifiers":[
        {
            "category":"Farming",
            "subcategory":"Farm",
            "type":"Manufacturing & Wholesale Goods"
        }
    ],
    "sg:phone":"+1 860 668 7013",
    "sg:postcode":"06093",
    "sg:province":"CT",
    "sg:tags":[
        "crop",
        "general"
    ],
    "wof:name":"Pamela Berry",
    "wof:placetype":"venue"
},
  "geometry": {"coordinates":[-72.711313,42.014164],"type":"Point"}
}