{
  "type": "Feature",
  "properties": {
    "addr:full":"112 Montowese St Branford CT 06405",
    "addr:housenumber":"112",
    "addr:postcode":"06405",
    "addr:street":"Montowese St",
    "iso:country":"US",
    "sg:address":"112 Montowese St",
    "sg:city":"Branford",
    "sg:classifiers":[
        {
            "category":"Professional",
            "subcategory":"Business Services",
            "type":"Services"
        }
    ],
    "sg:phone":"+1 203 315 1948",
    "sg:postcode":"06405",
    "sg:province":"CT",
    "sg:tags":[
        "interior",
        "consultant",
        "design",
        "decorator"
    ],
    "wof:name":"Metaphore",
    "wof:placetype":"venue"
},
  "geometry": {"coordinates":[-72.80714399999999,41.278653],"type":"Point"}
}