{
  "type": "Feature",
  "properties": {
    "iso:country":"US",
    "sg:address":"40 Industry Ln",
    "sg:city":"Waterbury",
    "sg:classifiers":[
        {
            "category":"Manufacturing",
            "subcategory":"Food",
            "type":"Manufacturing & Wholesale Goods"
        }
    ],
    "sg:phone":"+1 203 753 0515",
    "sg:postcode":"06704",
    "sg:province":"CT",
    "sg:tags":[
        "cocoa",
        "chocolate"
    ],
    "sg:website":"www.fasciaschocolates.com",
    "wof:name":"Fascia's Chocolates",
    "wof:placetype":"venue"
},
  "geometry": {"coordinates":[-73.00734300000001,41.572579],"type":"Point"}
}