{
  "type": "Feature",
  "properties": {
    "addr:full":"429 Colman St New London CT 06320",
    "addr:housenumber":"429",
    "addr:postcode":"06320",
    "addr:street":"Colman St New London Ct",
    "iso:country":"US",
    "sg:address":"429 Colman St",
    "sg:city":"New London",
    "sg:classifiers":[
        {
            "category":"Restaurant",
            "type":"Food & Drink"
        }
    ],
    "sg:menulink":"http://www.allmenus.com/ct/new-london/166737-burger-king/menu/",
    "sg:phone":"+1 860 447 2706",
    "sg:postcode":"06320",
    "sg:province":"CT",
    "sg:tags":[
        "burger",
        "american"
    ],
    "wof:name":"Burger King",
    "wof:placetype":"venue"
},
  "geometry": {"coordinates":[-72.116077,41.360747],"type":"Point"}
}