{
  "type": "Feature",
  "properties": {
    "addr:full":"15 Leonard St Stamford CT 06906",
    "addr:housenumber":"15",
    "addr:postcode":"06906",
    "addr:street":"Leonard St",
    "iso:country":"US",
    "sg:address":"15 Leonard St",
    "sg:city":"Stamford",
    "sg:classifiers":[
        {
            "category":"Wholesale",
            "subcategory":"Machinery & Supplies",
            "type":"Manufacturing & Wholesale Goods"
        }
    ],
    "sg:phone":"+1 203 325 4120",
    "sg:postcode":"06906",
    "sg:province":"CT",
    "wof:name":"Living Lawns & Great Gardens L",
    "wof:placetype":"venue"
},
  "geometry": {"coordinates":[-73.530851,41.077096],"type":"Point"}
}