{
  "type": "Feature",
  "properties": {
    "iso:country":"US",
    "sg:address":"91 Rosewood Rd",
    "sg:city":"Avon",
    "sg:classifiers":[
        {
            "category":"Organizations",
            "subcategory":"Community Association",
            "type":"Services"
        }
    ],
    "sg:phone":"+1   ",
    "sg:postcode":"06001",
    "sg:province":"CT",
    "wof:name":"Lions Club of Avon Inc",
    "wof:placetype":"venue"
},
  "geometry": {"coordinates":[-72.837793,41.819444],"type":"Point"}
}