{
  "type": "Feature",
  "properties": {
    "addr:full":"101 S Plains Rd Southington CT 06489",
    "addr:housenumber":"101",
    "addr:postcode":"06489",
    "addr:street":"S Plains Rd",
    "iso:country":"US",
    "sg:address":"101 S Plains Rd",
    "sg:city":"Southington",
    "sg:classifiers":[
        {
            "category":"Professional",
            "subcategory":"Computer Services",
            "type":"Services"
        }
    ],
    "sg:phone":"+1   ",
    "sg:postcode":"06489",
    "sg:province":"CT",
    "sg:tags":[
        "datum"
    ],
    "wof:name":"CT Web Consulting",
    "wof:placetype":"venue"
},
  "geometry": {"coordinates":[-72.863462,41.579345],"type":"Point"}
}