{
  "type": "Feature",
  "properties": {
    "addr:full":"701 Dixwell Ave New Haven CT 06511",
    "addr:housenumber":"701",
    "addr:postcode":"06511",
    "addr:street":"Dixwell Ave",
    "iso:country":"US",
    "sg:address":"701 Dixwell Ave",
    "sg:city":"New Haven",
    "sg:classifiers":[
        {
            "category":"Restaurant",
            "type":"Food & Drink"
        }
    ],
    "sg:phone":"+1 203 777 0378",
    "sg:postcode":"06511",
    "sg:province":"CT",
    "sg:tags":[
        "eating"
    ],
    "wof:name":"Chinese Kitchen",
    "wof:placetype":"venue"
},
  "geometry": {"coordinates":[-72.935149,41.33347],"type":"Point"}
}