{
  "type": "Feature",
  "properties": {
    "iso:country":"US",
    "sg:address":"221 Bull Hill Ln",
    "sg:city":"West Haven",
    "sg:classifiers":[
        {
            "category":"Shopping",
            "subcategory":"Department Store",
            "type":"Retail Goods"
        }
    ],
    "sg:phone":"+1 203 934 4747",
    "sg:postcode":"06516",
    "sg:province":"CT",
    "wof:name":"Lucky Dollar Value",
    "wof:placetype":"venue"
},
  "geometry": {"coordinates":[-72.986272,41.272988],"type":"Point"}
}