{
  "type": "Feature",
  "properties": {
    "addr:full":"97 Five Field Rd Madison CT 06443",
    "addr:housenumber":"97",
    "addr:postcode":"06443",
    "addr:street":"Five Field Rd",
    "iso:country":"US",
    "sg:address":"97 Five Field Rd",
    "sg:city":"Madison",
    "sg:classifiers":[
        {
            "category":"Manufacturing",
            "subcategory":"Aerospace",
            "type":"Manufacturing & Wholesale Goods"
        }
    ],
    "sg:phone":"+1 203 245 3733",
    "sg:postcode":"06443",
    "sg:province":"CT",
    "sg:tags":[
        "aircraft",
        "mfg"
    ],
    "wof:name":"Avcraft USA",
    "wof:placetype":"venue"
},
  "geometry": {"coordinates":[-72.576359,41.300099],"type":"Point"}
}