{
  "type": "Feature",
  "properties": {
    "addr:full":"875 W Main St Branford CT 06405",
    "addr:housenumber":"875",
    "addr:postcode":"06405",
    "addr:street":"W Main St",
    "iso:country":"US",
    "sg:address":"875 W Main St",
    "sg:city":"Branford",
    "sg:classifiers":[
        {
            "category":"Professional",
            "type":"Services"
        },
        {
            "category":"Food & Beverages",
            "subcategory":"Meat & Fish",
            "type":"Retail Goods"
        }
    ],
    "sg:phone":"+1 203 483 9775",
    "sg:postcode":"06405",
    "sg:province":"CT",
    "sg:tags":[
        "seafood"
    ],
    "wof:name":"Flying Fish LLC",
    "wof:placetype":"venue"
},
  "geometry": {"coordinates":[-72.83478599999999,41.275818],"type":"Point"}
}