{
  "type": "Feature",
  "properties": {
    "iso:country":"US",
    "sg:address":"27 Lasalle Rd",
    "sg:city":"Hartford",
    "sg:classifiers":[
        {
            "category":"Shopping",
            "subcategory":"Jewelry",
            "type":"Retail Goods"
        }
    ],
    "sg:phone":"+1 860 232 3300",
    "sg:postcode":"06107",
    "sg:province":"CT",
    "sg:tags":[
        "fine"
    ],
    "wof:name":"Davis Diamond Co",
    "wof:placetype":"venue"
},
  "geometry": {"coordinates":[-72.744528,41.760031],"type":"Point"}
}