{
  "type": "Feature",
  "properties": {
    "iso:country":"US",
    "sg:address":"607 Main Ave",
    "sg:city":"Norwalk",
    "sg:classifiers":[
        {
            "category":"Shopping",
            "subcategory":"Bicycles & Sporting Goods",
            "type":"Retail Goods"
        }
    ],
    "sg:phone":"+1 203 847 6788",
    "sg:postcode":"06851",
    "sg:province":"CT",
    "sg:tags":[
        "equipment",
        "exercise"
    ],
    "wof:name":"Omni Fitness Equip Specialists",
    "wof:placetype":"venue"
},
  "geometry": {"coordinates":[-73.421443,41.15767],"type":"Point"}
}