{
  "type": "Feature",
  "properties": {
    "addr:full":"349 Meriden Rd Waterbury CT 06705",
    "addr:housenumber":"349",
    "addr:postcode":"06705",
    "addr:street":"Meriden Rd",
    "iso:country":"US",
    "sg:address":"349 Meriden Rd",
    "sg:city":"Waterbury",
    "sg:classifiers":[
        {
            "category":"Personal",
            "subcategory":"Beauty Salon",
            "type":"Services"
        },
        {
            "category":"Personal",
            "subcategory":"Barber",
            "type":"Services"
        }
    ],
    "sg:phone":"+1 203 756 7083",
    "sg:postcode":"06705",
    "sg:province":"CT",
    "sg:tags":[
        "shop"
    ],
    "wof:name":"Totally Yours Hair Styling Sln",
    "wof:placetype":"venue"
},
  "geometry": {"coordinates":[-73.00465699999999,41.552426],"type":"Point"}
}