{
  "type": "Feature",
  "properties": {
    "iso:country":"US",
    "sg:address":"625 Palisado Ave",
    "sg:city":"Windsor",
    "sg:classifiers":[
        {
            "category":"Social Services",
            "subcategory":"Adult Care",
            "type":"Services"
        }
    ],
    "sg:phone":"+1   ",
    "sg:postcode":"06095",
    "sg:province":"CT",
    "sg:tags":[
        "residential"
    ],
    "wof:name":"Delamere Woods",
    "wof:placetype":"venue"
},
  "geometry": {"coordinates":[-72.62711899999999,41.874841],"type":"Point"}
}