{
  "type": "Feature",
  "properties": {
    "iso:country":"US",
    "sg:address":"862 Burlington Ave",
    "sg:city":"Bristol",
    "sg:classifiers":[
        {
            "category":"Building & Trades",
            "subcategory":"Pest Control",
            "type":"Services"
        }
    ],
    "sg:phone":"+1   ",
    "sg:postcode":"06010",
    "sg:province":"CT",
    "wof:name":"Nu Vision Pest Elimination",
    "wof:placetype":"venue"
},
  "geometry": {"coordinates":[-72.947227,41.704181],"type":"Point"}
}