{
  "type": "Feature",
  "properties": {
    "iso:country":"US",
    "sg:address":"500 State Hwy 80",
    "sg:city":"Guilford",
    "sg:classifiers":[
        {
            "category":"Travel",
            "subcategory":"Hotels & Motels",
            "type":"Entertainment"
        }
    ],
    "sg:phone":"+1 203 457 0587",
    "sg:postcode":"06437",
    "sg:province":"CT",
    "wof:name":"Valley Motel",
    "wof:placetype":"venue"
},
  "geometry": {"coordinates":[-72.69095900000001,41.352104],"type":"Point"}
}