{
  "type": "Feature",
  "properties": {
    "iso:country":"US",
    "sg:address":"599 Research Pkwy",
    "sg:city":"Meriden",
    "sg:classifiers":[
        {
            "category":"Utilities",
            "subcategory":"Mobile Phone",
            "type":"Services"
        }
    ],
    "sg:phone":"+1 203 630 8802",
    "sg:postcode":"06450",
    "sg:province":"CT",
    "sg:tags":[
        "communication",
        "radiotelephone"
    ],
    "wof:name":"Verizon",
    "wof:placetype":"venue"
},
  "geometry": {"coordinates":[-72.767292,41.510418],"type":"Point"}
}