{
  "type": "Feature",
  "properties": {
    "addr:full":"19 Twin Lakes Dr Waterford CT 06385",
    "addr:housenumber":"19",
    "addr:postcode":"06385",
    "addr:street":"Twin Lakes Dr",
    "iso:country":"US",
    "sg:address":"19 Twin Lakes Dr",
    "sg:city":"Waterford",
    "sg:classifiers":[
        {
            "category":"Professional",
            "subcategory":"Accounting & Tax Preparation",
            "type":"Services"
        }
    ],
    "sg:phone":"+1 860 443 0066",
    "sg:postcode":"06385",
    "sg:province":"CT",
    "sg:tags":[
        "advisory",
        "return",
        "investment"
    ],
    "wof:name":"Morton & Associates",
    "wof:placetype":"venue"
},
  "geometry": {"coordinates":[-72.13966000000001,41.391039],"type":"Point"}
}