{
  "type": "Feature",
  "properties": {
    "addr:full":"99 Grand Ave New Haven CT 06513",
    "addr:housenumber":"99",
    "addr:postcode":"06513",
    "addr:street":"Grand Ave",
    "iso:country":"US",
    "sg:address":"99 Grand Ave",
    "sg:city":"New Haven",
    "sg:classifiers":[
        {
            "category":"Restaurant",
            "type":"Food & Drink"
        }
    ],
    "sg:phone":"+1 203 752 1402",
    "sg:postcode":"06513",
    "sg:province":"CT",
    "wof:name":"El Boricua Restaurant",
    "wof:placetype":"venue"
},
  "geometry": {"coordinates":[-72.890607,41.309414],"type":"Point"}
}