{
  "type": "Feature",
  "properties": {
    "iso:country":"US",
    "sg:address":"108 Main St N",
    "sg:city":"Southbury",
    "sg:classifiers":[
        {
            "category":"Banks & Credit Unions",
            "subcategory":"Investment Brokerage",
            "type":"Services"
        }
    ],
    "sg:phone":"+1 203 264 1155",
    "sg:postcode":"06488",
    "sg:province":"CT",
    "sg:tags":[
        "stock",
        "bond"
    ],
    "wof:name":"Merrill Lynch",
    "wof:placetype":"venue"
},
  "geometry": {"coordinates":[-73.21338,41.479689],"type":"Point"}
}