{
  "type": "Feature",
  "properties": {
    "iso:country":"US",
    "sg:address":"94 Brickyard Rd",
    "sg:city":"Farmington",
    "sg:classifiers":[
        {
            "category":"Shopping",
            "subcategory":"Bicycles & Sporting Goods",
            "type":"Retail Goods"
        }
    ],
    "sg:phone":"+1 860 677 2489",
    "sg:postcode":"06032",
    "sg:province":"CT",
    "sg:tags":[
        "equipment",
        "tennis"
    ],
    "wof:name":"Racquets Unlimited Inc",
    "wof:placetype":"venue"
},
  "geometry": {"coordinates":[-72.85392400000001,41.745667],"type":"Point"}
}