{
  "type": "Feature",
  "properties": {
    "iso:country":"US",
    "sg:address":"385 Woodridge",
    "sg:city":"Shelton",
    "sg:classifiers":[
        {
            "category":"Manufacturing",
            "subcategory":"Printing",
            "type":"Manufacturing & Wholesale Goods"
        }
    ],
    "sg:phone":"+1 203 944 0926",
    "sg:postcode":"06484",
    "sg:province":"CT",
    "sg:tags":[
        "commercial"
    ],
    "wof:name":"All Things Crystal LLC",
    "wof:placetype":"venue"
},
  "geometry": {"coordinates":[-73.132336,41.293816],"type":"Point"}
}