{
  "type": "Feature",
  "properties": {
    "iso:country":"US",
    "sg:address":"4 Corporate Drive",
    "sg:city":"Shelton",
    "sg:classifiers":[
        {
            "category":"Professional",
            "subcategory":"Research",
            "type":"Services"
        }
    ],
    "sg:phone":"+1 203 332 7060",
    "sg:postcode":"06484",
    "sg:province":"CT",
    "sg:website":"http://www.imedx.com/",
    "wof:name":"iMedX",
    "wof:placetype":"venue"
},
  "geometry": {"coordinates":[-73.128592,41.276441],"type":"Point"}
}