{
  "type": "Feature",
  "properties": {
    "iso:country":"US",
    "sg:address":"23 State St",
    "sg:city":"North Haven",
    "sg:classifiers":[
        {
            "category":"Personal",
            "subcategory":"Beauty Salon",
            "type":"Services"
        }
    ],
    "sg:phone":"+1   ",
    "sg:postcode":"06473",
    "sg:province":"CT",
    "sg:tags":[
        "shop"
    ],
    "wof:name":"A Strand Salon",
    "wof:placetype":"venue"
},
  "geometry": {"coordinates":[-72.871842,41.391716],"type":"Point"}
}