{
  "type": "Feature",
  "properties": {
    "addr:full":"70 Cedar St Stratford CT 06615",
    "addr:housenumber":"70",
    "addr:postcode":"06615",
    "addr:street":"Cedar St",
    "iso:country":"US",
    "sg:address":"70 Cedar St",
    "sg:city":"Stratford",
    "sg:classifiers":[
        {
            "category":"Professional",
            "subcategory":"Management & Consulting",
            "type":"Services"
        }
    ],
    "sg:phone":"+1   ",
    "sg:postcode":"06615",
    "sg:province":"CT",
    "sg:tags":[
        "business"
    ],
    "wof:name":"JD Mitola Inc",
    "wof:placetype":"venue"
},
  "geometry": {"coordinates":[-73.124405,41.15603],"type":"Point"}
}