{
  "type": "Feature",
  "properties": {
    "iso:country":"US",
    "sg:address":"411 New Park Ave",
    "sg:city":"Hartford",
    "sg:classifiers":[
        {
            "category":"Retail",
            "subcategory":"Auto Repair",
            "type":"Services"
        }
    ],
    "sg:phone":"+1   ",
    "sg:postcode":"06106",
    "sg:province":"CT",
    "sg:tags":[
        "engine"
    ],
    "wof:name":"Connecticut Engine Co Inc",
    "wof:placetype":"venue"
},
  "geometry": {"coordinates":[-72.71265699999999,41.748062],"type":"Point"}
}