{
  "type": "Feature",
  "properties": {
    "iso:country":"US",
    "sg:address":"29 S Main St",
    "sg:city":"Hartford",
    "sg:classifiers":[
        {
            "category":"Professional",
            "subcategory":"Lawyer & Legal Services",
            "type":"Services"
        }
    ],
    "sg:phone":"+1   ",
    "sg:postcode":"06107",
    "sg:province":"CT",
    "wof:name":"Kroll McNamara & Evans",
    "wof:placetype":"venue"
},
  "geometry": {"coordinates":[-72.74271400000001,41.758684],"type":"Point"}
}