{
  "type": "Feature",
  "properties": {
    "iso:country":"US",
    "sg:address":"223 Broad St",
    "sg:city":"New Britain",
    "sg:classifiers":[
        {
            "category":"Banks & Credit Unions",
            "subcategory":"Bank",
            "type":"Services"
        }
    ],
    "sg:phone":"+1 860 224 2433",
    "sg:postcode":"06053",
    "sg:province":"CT",
    "sg:tags":[
        "lending",
        "company",
        "for",
        "redevelopment"
    ],
    "wof:name":"Neighborhood Housing",
    "wof:placetype":"venue"
},
  "geometry": {"coordinates":[-72.791477,41.672943],"type":"Point"}
}