{
  "type": "Feature",
  "properties": {
    "addr:full":"5 Greenwich Hills Dr Greenwich CT 06831",
    "addr:housenumber":"5",
    "addr:postcode":"06831",
    "addr:street":"Greenwich Hills Dr",
    "iso:country":"US",
    "sg:address":"5 Greenwich Hills Dr",
    "sg:city":"Greenwich",
    "sg:classifiers":[
        {
            "category":"Restaurant",
            "type":"Food & Drink"
        }
    ],
    "sg:phone":"+1 203 861 7275",
    "sg:postcode":"06831",
    "sg:province":"CT",
    "sg:tags":[
        "cafe"
    ],
    "wof:name":"Park Cafe",
    "wof:placetype":"venue"
},
  "geometry": {"coordinates":[-73.665046,41.02611],"type":"Point"}
}