{
  "type": "Feature",
  "properties": {
    "iso:country":"US",
    "sg:address":"110 Bartholomew Ave",
    "sg:city":"Hartford",
    "sg:classifiers":[
        {
            "category":"Government",
            "subcategory":"Jail",
            "type":"Public Place"
        }
    ],
    "sg:phone":"+1 860 951 8867",
    "sg:postcode":"06106",
    "sg:province":"CT",
    "sg:tags":[
        "correctional",
        "institution"
    ],
    "wof:name":"Connectcut Crrctonal Ombudsman",
    "wof:placetype":"venue"
},
  "geometry": {"coordinates":[-72.70245300000001,41.75787],"type":"Point"}
}