{
  "type": "Feature",
  "properties": {
    "iso:country":"US",
    "sg:address":"147 Highline Trl",
    "sg:city":"Stamford",
    "sg:classifiers":[
        {
            "category":"Arts & Performance",
            "subcategory":"Theater",
            "type":"Entertainment"
        }
    ],
    "sg:phone":"+1 203 358 0242",
    "sg:postcode":"06902",
    "sg:province":"CT",
    "wof:name":"G W George Co",
    "wof:placetype":"venue"
},
  "geometry": {"coordinates":[-73.58404400000001,41.0878],"type":"Point"}
}