{
  "type": "Feature",
  "properties": {
    "iso:country":"US",
    "sg:address":"122 Doral Greens Dr W",
    "sg:city":"Port Chester",
    "sg:classifiers":[
        {
            "category":"Food & Beverages",
            "subcategory":"Groceries & Convenience Stores",
            "type":"Retail Goods"
        }
    ],
    "sg:phone":"+1   ",
    "sg:postcode":"10573",
    "sg:province":"CT",
    "wof:name":"Dlb Food Corp",
    "wof:placetype":"venue"
},
  "geometry": {"coordinates":[-73.687489,41.045679],"type":"Point"}
}