{
  "type": "Feature",
  "properties": {
    "iso:country":"US",
    "sg:address":"129 Musket Ridge Rd",
    "sg:city":"Norwalk",
    "sg:classifiers":[
        {
            "category":"Organizations",
            "subcategory":"Membership Organization",
            "type":"Services"
        }
    ],
    "sg:phone":"+1 203 762 3984",
    "sg:postcode":"06850",
    "sg:province":"CT",
    "wof:name":"Daphne Seybolt Culpeper Memori",
    "wof:placetype":"venue"
},
  "geometry": {"coordinates":[-73.438164,41.1559],"type":"Point"}
}