{
  "type": "Feature",
  "properties": {
    "iso:country":"US",
    "sg:address":"150 Stebbins Rd",
    "sg:city":"Somers",
    "sg:classifiers":[
        {
            "category":"Building & Trades",
            "subcategory":"Landscaping Services",
            "type":"Services"
        }
    ],
    "sg:phone":"+1 860 749 8661",
    "sg:postcode":"06071",
    "sg:province":"CT",
    "sg:tags":[
        "tree",
        "stump",
        "grinding",
        "removal"
    ],
    "wof:name":"Beaver Tree Service and Stump Removal",
    "wof:placetype":"venue"
},
  "geometry": {"coordinates":[-72.43677599999999,41.993245],"type":"Point"}
}