{
  "type": "Feature",
  "properties": {
    "iso:country":"US",
    "sg:address":"192 Willow St",
    "sg:city":"Waterbury",
    "sg:classifiers":[
        {
            "category":"Organizations",
            "subcategory":"Religious Organization",
            "type":"Services"
        }
    ],
    "sg:phone":"+1   ",
    "sg:postcode":"06710",
    "sg:province":"CT",
    "wof:name":"Iglesia Del Dios Viviente",
    "wof:placetype":"venue"
},
  "geometry": {"coordinates":[-73.04782,41.562784],"type":"Point"}
}