{
  "type": "Feature",
  "properties": {
    "addr:full":"594 Federal Rd Brookfield CT 06804",
    "addr:housenumber":"594",
    "addr:postcode":"06804",
    "addr:street":"Federal Rd",
    "iso:country":"US",
    "sg:address":"594 Federal Rd",
    "sg:city":"Brookfield",
    "sg:classifiers":[
        {
            "category":"Professional",
            "subcategory":"Employment Agencies",
            "type":"Services"
        }
    ],
    "sg:phone":"+1 203 775 8661",
    "sg:postcode":"06804",
    "sg:province":"CT",
    "sg:tags":[
        "opportunity"
    ],
    "wof:name":"Automotive Career Consultants",
    "wof:placetype":"venue"
},
  "geometry": {"coordinates":[-73.410175,41.467795],"type":"Point"}
}