{
  "type": "Feature",
  "properties": {
    "addr:full":"264 Delavan Ave Greenwich CT 06830",
    "addr:housenumber":"264",
    "addr:postcode":"06830",
    "addr:street":"Delavan Ave",
    "iso:country":"US",
    "sg:address":"264 Delavan Ave",
    "sg:city":"Greenwich",
    "sg:classifiers":[
        {
            "category":"Government",
            "subcategory":"Fire Station",
            "type":"Public Place"
        }
    ],
    "sg:phone":"+1 203 532 9807",
    "sg:postcode":"06830",
    "sg:province":"CT",
    "sg:tags":[
        "protection"
    ],
    "wof:name":"Byram Volunteer Fire Dept",
    "wof:placetype":"venue"
},
  "geometry": {"coordinates":[-73.655554,41.00269],"type":"Point"}
}