{
  "type": "Feature",
  "properties": {
    "addr:full":"13 Brookmoor Rd Tolland CT 06084",
    "addr:housenumber":"13",
    "addr:postcode":"06084",
    "addr:street":"Brookmoor Rd Tolland Ct",
    "iso:country":"US",
    "sg:address":"13 Brookmoor Rd",
    "sg:city":"Tolland",
    "sg:classifiers":[
        {
            "category":"Freight",
            "type":"Transportation"
        }
    ],
    "sg:phone":"+1 860 875 8417",
    "sg:postcode":"06084",
    "sg:province":"CT",
    "sg:tags":[
        "operator",
        "local",
        "trucking"
    ],
    "wof:name":"STS Trucking Company Inc",
    "wof:placetype":"venue"
},
  "geometry": {"coordinates":[-72.379588,41.895812],"type":"Point"}
}