{
  "type": "Feature",
  "properties": {
    "iso:country":"US",
    "sg:address":"2600 Berlin Tpke",
    "sg:city":"Newington",
    "sg:classifiers":[
        {
            "category":"Real Estate",
            "subcategory":"Real Estate Agent",
            "type":"Services"
        }
    ],
    "sg:phone":"+1 860 665 0850",
    "sg:postcode":"06111",
    "sg:province":"CT",
    "wof:name":"Re/Max",
    "wof:placetype":"venue"
},
  "geometry": {"coordinates":[-72.71212199999999,41.679818],"type":"Point"}
}