{
  "type": "Feature",
  "properties": {
    "iso:country":"US",
    "sg:address":"24 Lincoln Ave",
    "sg:city":"Bristol",
    "sg:classifiers":[
        {
            "category":"Retail",
            "subcategory":"Funeral Services",
            "type":"Services"
        }
    ],
    "sg:phone":"+1   ",
    "sg:postcode":"06010",
    "sg:province":"CT",
    "wof:name":"OBrien Funeral Home",
    "wof:placetype":"venue"
},
  "geometry": {"coordinates":[-72.895931,41.669544],"type":"Point"}
}