{
  "type": "Feature",
  "properties": {
    "iso:country":"US",
    "sg:address":"317 High St",
    "sg:city":"Willimantic",
    "sg:classifiers":[
        {
            "category":"Professional",
            "type":"Services"
        }
    ],
    "sg:phone":"+1 860 423 0346",
    "sg:postcode":"06226",
    "sg:province":"CT",
    "wof:name":"Fraser Post & Beam LLC",
    "wof:placetype":"venue"
},
  "geometry": {"coordinates":[-72.21584199999999,41.722176],"type":"Point"}
}