{
  "type": "Feature",
  "properties": {
    "addr:full":"4 Quail Run Dr Danbury CT 06811",
    "addr:housenumber":"4",
    "addr:postcode":"06811",
    "addr:street":"Quail Run Dr",
    "iso:country":"US",
    "sg:address":"4 Quail Run Dr",
    "sg:city":"Danbury",
    "sg:classifiers":[
        {
            "category":"Health Services",
            "subcategory":"Health Practitioner",
            "type":"Services"
        }
    ],
    "sg:phone":"+1   ",
    "sg:postcode":"06811",
    "sg:province":"CT",
    "wof:name":"Health and Horizens Unlimited",
    "wof:placetype":"venue"
},
  "geometry": {"coordinates":[-73.501835,41.393375],"type":"Point"}
}