{
  "type": "Feature",
  "properties": {
    "addr:full":"4 West St New Haven CT 06519",
    "addr:housenumber":"4",
    "addr:postcode":"06519",
    "addr:street":"West St",
    "iso:country":"US",
    "sg:address":"4 West St",
    "sg:city":"New Haven",
    "sg:classifiers":[
        {
            "category":"Organizations",
            "subcategory":"Religious Organization",
            "type":"Services"
        }
    ],
    "sg:phone":"+1   ",
    "sg:postcode":"06519",
    "sg:province":"CT",
    "wof:name":"Holy Nation Tabernacle Praise",
    "wof:placetype":"venue"
},
  "geometry": {"coordinates":[-72.938957,41.295371],"type":"Point"}
}