{
  "type": "Feature",
  "properties": {
    "addr:full":"80 Lincoln Ave Stamford CT 06902",
    "addr:housenumber":"80",
    "addr:postcode":"06902",
    "addr:street":"Lincoln Ave",
    "iso:country":"US",
    "sg:address":"80 Lincoln Ave",
    "sg:city":"Stamford",
    "sg:classifiers":[
        {
            "category":"Building & Trades",
            "subcategory":"Landscaping Services",
            "type":"Services"
        }
    ],
    "sg:phone":"+1 203 834 7977",
    "sg:postcode":"06902",
    "sg:province":"CT",
    "wof:name":"New England Tree & Shrub",
    "wof:placetype":"venue"
},
  "geometry": {"coordinates":[-73.521529,41.057038],"type":"Point"}
}