{
  "type": "Feature",
  "properties": {
    "iso:country":"US",
    "sg:address":"2987 Berlin Tpke",
    "sg:city":"Newington",
    "sg:classifiers":[
        {
            "category":"Real Estate",
            "subcategory":"Developer",
            "type":"Services"
        }
    ],
    "sg:phone":"+1 860 665 0497",
    "sg:postcode":"06111",
    "sg:province":"CT",
    "wof:name":"Konover Job Site",
    "wof:placetype":"venue"
},
  "geometry": {"coordinates":[-72.71835299999999,41.66911],"type":"Point"}
}