{
  "type": "Feature",
  "properties": {
    "iso:country":"US",
    "sg:address":"100 Seymour Rd",
    "sg:city":"Woodbridge",
    "sg:classifiers":[
        {
            "category":"Real Estate",
            "subcategory":"Architect",
            "type":"Services"
        }
    ],
    "sg:phone":"+1   ",
    "sg:postcode":"06525",
    "sg:province":"CT",
    "sg:tags":[
        "architectural"
    ],
    "wof:name":"Andrew K Robinson",
    "wof:placetype":"venue"
},
  "geometry": {"coordinates":[-73.016801,41.384859],"type":"Point"}
}