{
  "type": "Feature",
  "properties": {
    "iso:country":"US",
    "sg:address":"43 Cherry St",
    "sg:city":"Milford",
    "sg:classifiers":[
        {
            "category":"Banks & Credit Unions",
            "subcategory":"Investment Brokerage",
            "type":"Services"
        },
        {
            "category":"Professional",
            "subcategory":"Management & Consulting",
            "type":"Services"
        }
    ],
    "sg:phone":"+1 203 882 8907",
    "sg:postcode":"06460",
    "sg:province":"CT",
    "sg:tags":[
        "advisory",
        "financial"
    ],
    "wof:name":"Shebar Financial Services LLC",
    "wof:placetype":"venue"
},
  "geometry": {"coordinates":[-73.05439,41.226661],"type":"Point"}
}