{
  "type": "Feature",
  "properties": {
    "iso:country":"US",
    "sg:address":"30 Rentschler St",
    "sg:city":"East Hartford",
    "sg:classifiers":[
        {
            "category":"Building & Trades",
            "subcategory":"Construction",
            "type":"Services"
        }
    ],
    "sg:phone":"+1 860 568 9550",
    "sg:postcode":"06118",
    "sg:province":"CT",
    "sg:tags":[
        "addition",
        "home",
        "remodeling",
        "contractor"
    ],
    "wof:name":"Nutmeg Home Improvement Inc",
    "wof:placetype":"venue"
},
  "geometry": {"coordinates":[-72.603514,41.746181],"type":"Point"}
}