{
  "type": "Feature",
  "properties": {
    "iso:country":"US",
    "sg:address":"730 Hopmeadow St",
    "sg:city":"Simsbury",
    "sg:classifiers":[
        {
            "category":"Organizations",
            "subcategory":"Community Association",
            "type":"Services"
        }
    ],
    "sg:phone":"+1   ",
    "sg:postcode":"06070",
    "sg:province":"CT",
    "sg:tags":[
        "body",
        "auto"
    ],
    "wof:name":"Farmington Valley Branch YMCA",
    "wof:placetype":"venue"
},
  "geometry": {"coordinates":[-72.802414,41.872904],"type":"Point"}
}