{
  "type": "Feature",
  "properties": {
    "addr:full":"49 Deerfield Ln Portland CT 06480",
    "addr:housenumber":"49",
    "addr:postcode":"06480",
    "addr:street":"Deerfield Ln",
    "iso:country":"US",
    "sg:address":"49 Deerfield Ln",
    "sg:city":"Portland",
    "sg:classifiers":[
        {
            "category":"Wholesale",
            "subcategory":"Metals & Minerals",
            "type":"Manufacturing & Wholesale Goods"
        }
    ],
    "sg:phone":"+1 860 342 3080",
    "sg:postcode":"06480",
    "sg:province":"CT",
    "sg:tags":[
        "sheet",
        "for",
        "machined",
        "broker",
        "fabricated",
        "mfr",
        "part"
    ],
    "wof:name":"A G Metals LLC",
    "wof:placetype":"venue"
},
  "geometry": {"coordinates":[-72.57454199999999,41.573474],"type":"Point"}
}