{
  "type": "Feature",
  "properties": {
    "addr:full":"141 Summer St Southington CT 06489",
    "addr:housenumber":"141",
    "addr:postcode":"06489",
    "addr:street":"Summer St",
    "iso:country":"US",
    "sg:address":"141 Summer St",
    "sg:city":"Southington",
    "sg:classifiers":[
        {
            "category":"Building & Trades",
            "subcategory":"Cleaning & Sanitation",
            "type":"Services"
        },
        {
            "category":"Home & Garden",
            "subcategory":"Building Materials",
            "type":"Retail Goods"
        },
        {
            "category":"Building & Trades",
            "subcategory":"Construction",
            "type":"Services"
        }
    ],
    "sg:phone":"+1 860 620 0687",
    "sg:postcode":"06489",
    "sg:province":"CT",
    "sg:tags":[
        "heater",
        "systems-repairing",
        "duct",
        "system",
        "specialty",
        "water",
        "equipment",
        "heating",
        "contractor",
        "repair",
        "air conditioning"
    ],
    "sg:website":"http://www.bosseheating.com",
    "wof:name":"Bosse Heating & Air Conditioning",
    "wof:placetype":"venue"
},
  "geometry": {"coordinates":[-72.88721099999999,41.596549],"type":"Point"}
}