{
  "type": "Feature",
  "properties": {
    "iso:country":"US",
    "sg:address":"101 Main St",
    "sg:city":"Norwalk",
    "sg:classifiers":[
        {
            "category":"Professional",
            "type":"Services"
        }
    ],
    "sg:phone":"+1 203 846 2143",
    "sg:postcode":"06851",
    "sg:province":"CT",
    "sg:tags":[
        "establishment"
    ],
    "wof:name":"Merritt 7 Maintenace Dept",
    "wof:placetype":"venue"
},
  "geometry": {"coordinates":[-73.41366499999999,41.121604],"type":"Point"}
}