{
  "type": "Feature",
  "properties": {
    "iso:country":"US",
    "sg:address":"409 Swanson Cres",
    "sg:city":"Milford",
    "sg:classifiers":[
        {
            "category":"Professional",
            "subcategory":"Business Services",
            "type":"Services"
        }
    ],
    "sg:phone":"+1   ",
    "sg:postcode":"06461",
    "sg:province":"CT",
    "wof:name":"Mary Chalupsky",
    "wof:placetype":"venue"
},
  "geometry": {"coordinates":[-73.033902,41.246563],"type":"Point"}
}