{
  "type": "Feature",
  "properties": {
    "addr:full":"136 Westbrook Rd Essex CT 06426",
    "addr:housenumber":"136",
    "addr:postcode":"06426",
    "addr:street":"Westbrook Rd",
    "iso:country":"US",
    "sg:address":"136 Westbrook Rd",
    "sg:city":"Essex",
    "sg:classifiers":[
        {
            "category":"Shopping",
            "subcategory":"Florist",
            "type":"Retail Goods"
        }
    ],
    "sg:phone":"+1 860 767 8936",
    "sg:postcode":"06426",
    "sg:province":"CT",
    "sg:website":"www.essexflowershoppe.com",
    "wof:name":"Essex Flower Shoppe",
    "wof:placetype":"venue"
},
  "geometry": {"coordinates":[-72.417297,41.3531],"type":"Point"}
}