{
  "type": "Feature",
  "properties": {
    "addr:full":"321 Broad St Bristol CT 06010",
    "addr:housenumber":"321",
    "addr:postcode":"06010",
    "addr:street":"Broad St",
    "iso:country":"US",
    "sg:address":"321 Broad St",
    "sg:city":"Bristol",
    "sg:classifiers":[
        {
            "category":"Autos & Motor Vehicles",
            "subcategory":"Auto Supplies",
            "type":"Retail Goods"
        }
    ],
    "sg:phone":"+1 860 584 5665",
    "sg:postcode":"06010",
    "sg:province":"CT",
    "wof:name":"Performance Edge",
    "wof:placetype":"venue"
},
  "geometry": {"coordinates":[-72.908753,41.671889],"type":"Point"}
}