{
  "type": "Feature",
  "properties": {
    "iso:country":"US",
    "sg:address":"722 River Rd",
    "sg:city":"Shelton",
    "sg:classifiers":[
        {
            "category":"Autos & Motor Vehicles",
            "subcategory":"Boat Sales",
            "type":"Retail Goods"
        }
    ],
    "sg:phone":"+1 203 929 7444",
    "sg:postcode":"06484",
    "sg:province":"CT",
    "wof:name":"Beacon Point North",
    "wof:placetype":"venue"
},
  "geometry": {"coordinates":[-73.09155199999999,41.27034],"type":"Point"}
}