{
  "type": "Feature",
  "properties": {
    "addr:full":"670 Bread and Milk St Coventry CT 06238",
    "addr:housenumber":"670",
    "addr:postcode":"06238",
    "addr:street":"Bread;St",
    "iso:country":"US",
    "sg:address":"670 Bread and Milk St",
    "sg:city":"Coventry",
    "sg:classifiers":[
        {
            "category":"Retail",
            "subcategory":"Self-service Laundry",
            "type":"Services"
        }
    ],
    "sg:phone":"+1   ",
    "sg:postcode":"06238",
    "sg:province":"CT",
    "sg:tags":[
        "coin"
    ],
    "wof:name":"Park Plaza Laundromat LLC",
    "wof:placetype":"venue"
},
  "geometry": {"coordinates":[-72.396483,41.81513],"type":"Point"}
}