{
  "type": "Feature",
  "properties": {
    "addr:full":"46 South St Danbury CT 06810",
    "addr:housenumber":"46",
    "addr:postcode":"06810",
    "addr:street":"South St",
    "iso:country":"US",
    "sg:address":"46 South St",
    "sg:city":"Danbury",
    "sg:classifiers":[
        {
            "category":"Autos & Motor Vehicles",
            "subcategory":"Fuel & Gas Station",
            "type":"Retail Goods"
        }
    ],
    "sg:phone":"+1 203 743 9488",
    "sg:postcode":"06810",
    "sg:province":"CT",
    "sg:tags":[
        "station",
        "gasoline"
    ],
    "wof:name":"KBRO Wholesale Gasoline",
    "wof:placetype":"venue"
},
  "geometry": {"coordinates":[-73.42975199999999,41.386102],"type":"Point"}
}