{
  "type": "Feature",
  "properties": {
    "addr:full":"25 Libby Ln Darien CT 06820",
    "addr:housenumber":"25",
    "addr:postcode":"06820",
    "addr:street":"Libby Ln Darien Ct",
    "iso:country":"US",
    "sg:address":"25 Libby Ln",
    "sg:city":"Darien",
    "sg:classifiers":[
        {
            "category":"Professional",
            "subcategory":"Management & Consulting",
            "type":"Services"
        }
    ],
    "sg:phone":"+1 203 655 6815",
    "sg:postcode":"06820",
    "sg:province":"CT",
    "sg:tags":[
        "consultant"
    ],
    "wof:name":"Wallace Offutt Consulting",
    "wof:placetype":"venue"
},
  "geometry": {"coordinates":[-73.490341,41.079536],"type":"Point"}
}