{
  "type": "Feature",
  "properties": {
    "iso:country":"US",
    "sg:address":"723 Rock Rimmon Rd",
    "sg:city":"Stamford",
    "sg:classifiers":[
        {
            "category":"Professional",
            "subcategory":"Business Services",
            "type":"Services"
        }
    ],
    "sg:phone":"+1 203 353 1673",
    "sg:postcode":"06903",
    "sg:province":"CT",
    "sg:tags":[
        "medical",
        "administration"
    ],
    "wof:name":"Mdk Health Care Mgt",
    "wof:placetype":"venue"
},
  "geometry": {"coordinates":[-73.574663,41.155516],"type":"Point"}
}