{
  "type": "Feature",
  "properties": {
    "addr:full":"5 N Main St Southington CT 06489",
    "addr:housenumber":"5",
    "addr:postcode":"06489",
    "addr:street":"N Main St",
    "iso:country":"US",
    "sg:address":"5 N Main St",
    "sg:city":"Southington",
    "sg:classifiers":[
        {
            "category":"Building & Trades",
            "subcategory":"Landscaping Services",
            "type":"Services"
        }
    ],
    "sg:phone":"+1 860 628 4099",
    "sg:postcode":"06489",
    "sg:province":"CT",
    "wof:name":"Blue Hills Ldscpg & Lawn Care",
    "wof:placetype":"venue"
},
  "geometry": {"coordinates":[-72.878224,41.603099],"type":"Point"}
}