{
  "type": "Feature",
  "properties": {
    "iso:country":"US",
    "sg:address":"8 N Main St",
    "sg:city":"Hartford",
    "sg:classifiers":[
        {
            "category":"Professional",
            "subcategory":"Management & Consulting",
            "type":"Services"
        }
    ],
    "sg:phone":"+1   ",
    "sg:postcode":"06107",
    "sg:province":"CT",
    "sg:tags":[
        "consultant",
        "business"
    ],
    "wof:name":"Kirby The Group LLC",
    "wof:placetype":"venue"
},
  "geometry": {"coordinates":[-72.741863,41.762809],"type":"Point"}
}