{
  "type": "Feature",
  "properties": {
    "addr:full":"533 Pacific St Stamford CT 06902",
    "addr:housenumber":"533",
    "addr:postcode":"06902",
    "addr:street":"Pacific St",
    "iso:country":"US",
    "sg:address":"533 Pacific St",
    "sg:city":"Stamford",
    "sg:classifiers":[
        {
            "category":"Professional",
            "subcategory":"Business Services",
            "type":"Services"
        }
    ],
    "sg:phone":"+1   ",
    "sg:postcode":"06902",
    "sg:province":"CT",
    "wof:name":"Interiors Haberdashery LLC",
    "wof:placetype":"venue"
},
  "geometry": {"coordinates":[-73.537404,41.047496],"type":"Point"}
}