{
  "type": "Feature",
  "properties": {
    "addr:full":"47 William Henry Dr Monroe CT 06468",
    "addr:housenumber":"47",
    "addr:postcode":"06468",
    "addr:street":"William Henry Dr Monroe Ct",
    "iso:country":"US",
    "sg:address":"47 William Henry Dr",
    "sg:city":"Monroe",
    "sg:classifiers":[
        {
            "category":"Shopping",
            "subcategory":"Computers & Home Electronics",
            "type":"Retail Goods"
        }
    ],
    "sg:phone":"+1 203 445 9825",
    "sg:postcode":"06468",
    "sg:province":"CT",
    "sg:tags":[
        "software"
    ],
    "wof:name":"Fascor",
    "wof:placetype":"venue"
},
  "geometry": {"coordinates":[-73.18772300000001,41.332179],"type":"Point"}
}