{
  "type": "Feature",
  "properties": {
    "addr:full":"10 Rainbow Dr Greenwich CT 06877",
    "addr:housenumber":"10",
    "addr:postcode":"06877",
    "addr:street":"Rainbow Dr",
    "iso:country":"US",
    "sg:address":"10 Rainbow Dr",
    "sg:city":"Greenwich",
    "sg:classifiers":[
        {
            "category":"Professional",
            "type":"Services"
        }
    ],
    "sg:phone":"+1 203 698 9089",
    "sg:postcode":"06877",
    "sg:province":"CT",
    "sg:tags":[
        "establishment"
    ],
    "wof:name":"Vc Solutions Inc",
    "wof:placetype":"venue"
},
  "geometry": {"coordinates":[-73.492357,41.337411],"type":"Point"}
}