{
  "type": "Feature",
  "properties": {
    "iso:country":"US",
    "sg:address":"555 Lakewood Rd",
    "sg:city":"Waterbury",
    "sg:classifiers":[
        {
            "category":"Retail",
            "subcategory":"Auto Repair",
            "type":"Services"
        }
    ],
    "sg:phone":"+1   ",
    "sg:postcode":"06704",
    "sg:province":"CT",
    "sg:tags":[
        "general"
    ],
    "wof:name":"SNET Motor Vehicle",
    "wof:placetype":"venue"
},
  "geometry": {"coordinates":[-73.012353,41.575125],"type":"Point"}
}