{
  "type": "Feature",
  "properties": {
    "addr:full":"26 Scott St Hamden CT 06514",
    "addr:housenumber":"26",
    "addr:postcode":"06514",
    "addr:street":"Scott St",
    "iso:country":"US",
    "sg:address":"26 Scott St",
    "sg:city":"Hamden",
    "sg:classifiers":[
        {
            "category":"Shopping",
            "subcategory":"Music",
            "type":"Retail Goods"
        }
    ],
    "sg:phone":"+1 203 281 1928",
    "sg:postcode":"06514",
    "sg:province":"CT",
    "sg:tags":[
        "record"
    ],
    "wof:name":"Diamond Records",
    "wof:placetype":"venue"
},
  "geometry": {"coordinates":[-72.93337699999999,41.348396],"type":"Point"}
}