{
  "type": "Feature",
  "properties": {
    "addr:full":"102 Woodbridge Ave New Haven CT 06515",
    "addr:housenumber":"102",
    "addr:postcode":"06515",
    "addr:street":"Woodbridge Ave",
    "iso:country":"US",
    "sg:address":"102 Woodbridge Ave",
    "sg:city":"New Haven",
    "sg:classifiers":[
        {
            "category":"Organizations",
            "subcategory":"Religious Organization",
            "type":"Services"
        }
    ],
    "sg:phone":"+1 203 389 2244",
    "sg:postcode":"06515",
    "sg:province":"CT",
    "sg:tags":[
        "clergy"
    ],
    "wof:name":"William T Lee",
    "wof:placetype":"venue"
},
  "geometry": {"coordinates":[-72.969087,41.322207],"type":"Point"}
}