{
  "type": "Feature",
  "properties": {
    "iso:country":"US",
    "sg:address":"19 Palisado Ave",
    "sg:city":"Windsor",
    "sg:classifiers":[
        {
            "category":"Personal",
            "subcategory":"Barber",
            "type":"Services"
        }
    ],
    "sg:phone":"+1   ",
    "sg:postcode":"06095",
    "sg:province":"CT",
    "sg:tags":[
        "shop"
    ],
    "wof:name":"International Barber Salon",
    "wof:placetype":"venue"
},
  "geometry": {"coordinates":[-72.640716,41.855189],"type":"Point"}
}