{
  "type": "Feature",
  "properties": {
    "iso:country":"US",
    "sg:address":"465 Meriden Rd",
    "sg:city":"Waterbury",
    "sg:classifiers":[
        {
            "category":"Wholesale",
            "subcategory":"Motor Vehicles",
            "type":"Manufacturing & Wholesale Goods"
        }
    ],
    "sg:phone":"+1 203 757 2336",
    "sg:postcode":"06705",
    "sg:province":"CT",
    "wof:name":"Galaxy Motors",
    "wof:placetype":"venue"
},
  "geometry": {"coordinates":[-73.00447699999999,41.552362],"type":"Point"}
}