{
  "type": "Feature",
  "properties": {
    "iso:country":"US",
    "sg:address":"7 Vista Dr",
    "sg:city":"Brookfield",
    "sg:classifiers":[
        {
            "category":"Health Services",
            "subcategory":"Clinic",
            "type":"Services"
        }
    ],
    "sg:phone":"+1 203 775 4686",
    "sg:postcode":"06804",
    "sg:province":"CT",
    "sg:tags":[
        "wellness",
        "program"
    ],
    "wof:name":"North East WELLNESS-New Grp",
    "wof:placetype":"venue"
},
  "geometry": {"coordinates":[-73.42845199999999,41.474751],"type":"Point"}
}