{
  "type": "Feature",
  "properties": {
    "iso:country":"US",
    "sg:address":"245 Mansfield Grove Rd",
    "sg:city":"East Haven",
    "sg:classifiers":[
        {
            "category":"Building & Trades",
            "subcategory":"Plumbing",
            "type":"Services"
        }
    ],
    "sg:phone":"+1 203 468 1073",
    "sg:postcode":"06512",
    "sg:province":"CT",
    "sg:tags":[
        "contractor"
    ],
    "wof:name":"B&M Plumbing & Heating LLC",
    "wof:placetype":"venue"
},
  "geometry": {"coordinates":[-72.86236599999999,41.253048],"type":"Point"}
}