{
  "type": "Feature",
  "properties": {
    "addr:full":"1006 Hancock Dr Danbury CT 06811",
    "addr:housenumber":"1006",
    "addr:postcode":"06811",
    "addr:street":"Hancock Dr",
    "iso:country":"US",
    "sg:address":"1006 Hancock Dr",
    "sg:city":"Danbury",
    "sg:classifiers":[
        {
            "category":"Health Services",
            "subcategory":"Medical Lab",
            "type":"Services"
        }
    ],
    "sg:phone":"+1   ",
    "sg:postcode":"06811",
    "sg:province":"CT",
    "sg:tags":[
        "laboratory"
    ],
    "wof:name":"Ea Clinical Research Consultan",
    "wof:placetype":"venue"
},
  "geometry": {"coordinates":[-73.423266,41.434382],"type":"Point"}
}