{
  "type": "Feature",
  "properties": {
    "iso:country":"US",
    "sg:address":"15 Rockwood Ln",
    "sg:city":"Greenwich",
    "sg:classifiers":[
        {
            "category":"Professional",
            "type":"Services"
        }
    ],
    "sg:phone":"+1 203 869 2185",
    "sg:postcode":"06830",
    "sg:province":"CT",
    "wof:name":"Constantine Dadakis",
    "wof:placetype":"venue"
},
  "geometry": {"coordinates":[-73.63553,41.05844],"type":"Point"}
}