{
  "type": "Feature",
  "properties": {
    "iso:country":"US",
    "sg:address":"40 Granby Farms Rd",
    "sg:city":"Granby",
    "sg:classifiers":[
        {
            "category":"Communications",
            "subcategory":"Film & Video Production",
            "type":"Services"
        }
    ],
    "sg:phone":"+1   ",
    "sg:postcode":"06035",
    "sg:province":"CT",
    "sg:tags":[
        "motion"
    ],
    "wof:name":"Prestige Productions",
    "wof:placetype":"venue"
},
  "geometry": {"coordinates":[-72.80880000000001,41.955269],"type":"Point"}
}