{
  "type": "Feature",
  "properties": {
    "addr:full":"1093 E Main St Bridgeport CT 06608",
    "addr:housenumber":"1093",
    "addr:postcode":"06608",
    "addr:street":"E Main St",
    "iso:country":"US",
    "sg:address":"1093 E Main St",
    "sg:city":"Bridgeport",
    "sg:classifiers":[
        {
            "category":"Shopping",
            "type":"Retail Goods"
        }
    ],
    "sg:phone":"+1 203 367 0338",
    "sg:postcode":"06608",
    "sg:province":"CT",
    "sg:tags":[
        "telephone",
        "cellular"
    ],
    "wof:name":"3 M Communications",
    "wof:placetype":"venue"
},
  "geometry": {"coordinates":[-73.180682,41.189826],"type":"Point"}
}