{
  "type": "Feature",
  "properties": {
    "iso:country":"US",
    "sg:address":"3000 Dixwell Ave",
    "sg:city":"Hamden",
    "sg:classifiers":[
        {
            "category":"Health Services",
            "subcategory":"Doctor",
            "type":"Services"
        }
    ],
    "sg:phone":"+1 203 288 0003",
    "sg:postcode":"06518",
    "sg:province":"CT",
    "sg:tags":[
        "laboratory",
        "medical",
        "surgeon",
        "physician"
    ],
    "wof:name":"Yale-New Haven Ambulatory Svc",
    "wof:placetype":"venue"
},
  "geometry": {"coordinates":[-72.90030299999999,41.38339],"type":"Point"}
}