{
  "type": "Feature",
  "properties": {
    "addr:full":"14 Southwest Rd Seymour CT 06483",
    "addr:housenumber":"14",
    "addr:postcode":"06483",
    "addr:street":"Southwest Rd",
    "iso:country":"US",
    "sg:address":"14 Southwest Rd",
    "sg:city":"Seymour",
    "sg:classifiers":[
        {
            "category":"Professional",
            "subcategory":"Computer Services",
            "type":"Services"
        }
    ],
    "sg:phone":"+1   ",
    "sg:postcode":"06483",
    "sg:province":"CT",
    "sg:tags":[
        "programing",
        "custom"
    ],
    "wof:name":"Strategic Business System LLC",
    "wof:placetype":"venue"
},
  "geometry": {"coordinates":[-73.111195,41.350645],"type":"Point"}
}