{
  "type": "Feature",
  "properties": {
    "iso:country":"US",
    "sg:address":"70 Polster Rd",
    "sg:city":"West Willington",
    "sg:classifiers":[
        {
            "category":"Professional",
            "subcategory":"Business Services",
            "type":"Services"
        }
    ],
    "sg:phone":"+1   ",
    "sg:postcode":"06279",
    "sg:province":"CT",
    "wof:name":"McClellan Partners LLC",
    "wof:placetype":"venue"
},
  "geometry": {"coordinates":[-72.258482,41.931358],"type":"Point"}
}