{
  "type": "Feature",
  "properties": {
    "addr:full":"25 Van Zant St Norwalk CT 06855",
    "addr:housenumber":"25",
    "addr:postcode":"06855",
    "addr:street":"Van Zant St",
    "iso:country":"US",
    "sg:address":"25 Van Zant St",
    "sg:city":"Norwalk",
    "sg:classifiers":[
        {
            "category":"Health Services",
            "subcategory":"Clinic",
            "type":"Services"
        },
        {
            "category":"Health Services",
            "subcategory":"Health Practitioner",
            "type":"Services"
        }
    ],
    "sg:phone":"+1 203 853 1331",
    "sg:postcode":"06855",
    "sg:province":"CT",
    "sg:tags":[
        "agency",
        "registry",
        "home",
        "nurse",
        "employment",
        "care"
    ],
    "wof:name":"New England Home Care Inc",
    "wof:placetype":"venue"
},
  "geometry": {"coordinates":[-73.407988,41.101337],"type":"Point"}
}