{
  "type": "Feature",
  "properties": {
    "addr:full":"56 Tumblebrook Rd Milford CT 06450",
    "addr:housenumber":"56",
    "addr:postcode":"06450",
    "addr:street":"Tumblebrook Rd",
    "iso:country":"US",
    "sg:address":"56 Tumblebrook Rd",
    "sg:city":"Milford",
    "sg:classifiers":[
        {
            "category":"Education",
            "subcategory":"Special Training",
            "type":"Public Place"
        }
    ],
    "sg:phone":"+1   ",
    "sg:postcode":"06450",
    "sg:province":"CT",
    "wof:name":"Pop Warner Little Scholar",
    "wof:placetype":"venue"
},
  "geometry": {"coordinates":[-72.763972,41.531666],"type":"Point"}
}