{
  "type": "Feature",
  "properties": {
    "addr:full":"110 Elm St Bridgeport CT 06604",
    "addr:housenumber":"110",
    "addr:postcode":"06604",
    "addr:street":"Elm St",
    "iso:country":"US",
    "sg:address":"110 Elm St",
    "sg:city":"Bridgeport",
    "sg:classifiers":[
        {
            "category":"Building & Trades",
            "subcategory":"Construction",
            "type":"Services"
        }
    ],
    "sg:phone":"+1 203 895 7193",
    "sg:postcode":"06604",
    "sg:province":"CT",
    "sg:tags":[
        "fence",
        "contractor"
    ],
    "wof:name":"Mc Carthy's Fence Co",
    "wof:placetype":"venue"
},
  "geometry": {"coordinates":[-73.189649,41.180082],"type":"Point"}
}