{
  "type": "Feature",
  "properties": {
    "addr:full":"280 Branford Rd North Branford CT 06471",
    "addr:housenumber":"280",
    "addr:postcode":"06471",
    "addr:street":"Branford Rd North Branford Ct",
    "iso:country":"US",
    "sg:address":"280 Branford Rd",
    "sg:city":"North Branford",
    "sg:classifiers":[
        {
            "category":"Government",
            "subcategory":"Post Office",
            "type":"Public Place"
        }
    ],
    "sg:phone":"+1 203 488 5541",
    "sg:postcode":"06471",
    "sg:province":"CT",
    "wof:name":"US Post Office",
    "wof:placetype":"venue"
},
  "geometry": {"coordinates":[-72.77055799999999,41.323299],"type":"Point"}
}