{
  "type": "Feature",
  "properties": {
    "addr:full":"343 Hilltop Rd Orange CT 06477",
    "addr:housenumber":"343",
    "addr:postcode":"06477",
    "addr:street":"Hilltop Rd",
    "iso:country":"US",
    "sg:address":"343 Hilltop Rd",
    "sg:city":"Orange",
    "sg:classifiers":[
        {
            "category":"Building & Trades",
            "subcategory":"Construction",
            "type":"Services"
        }
    ],
    "sg:phone":"+1 203 799 6873",
    "sg:postcode":"06477",
    "sg:province":"CT",
    "sg:tags":[
        "excavation",
        "concrete",
        "contractor"
    ],
    "wof:name":"Raccio Robert E Con Form Co",
    "wof:placetype":"venue"
},
  "geometry": {"coordinates":[-73.046464,41.297724],"type":"Point"}
}