{
  "type": "Feature",
  "properties": {
    "iso:country":"US",
    "sg:address":"236 Boston Post Rd",
    "sg:city":"Orange",
    "sg:classifiers":[
        {
            "category":"Professional",
            "subcategory":"Accounting & Tax Preparation",
            "type":"Services"
        }
    ],
    "sg:phone":"+1 203 795 3566",
    "sg:postcode":"06477",
    "sg:province":"CT",
    "sg:tags":[
        "accountant"
    ],
    "wof:name":"Annunziata & Co",
    "wof:placetype":"venue"
},
  "geometry": {"coordinates":[-72.999251,41.268524],"type":"Point"}
}