{
  "type": "Feature",
  "properties": {
    "addr:full":"1 Sylvan Rd N Westport CT 06880",
    "addr:housenumber":"1",
    "addr:postcode":"06880",
    "addr:street":"Sylvan Rd N",
    "iso:country":"US",
    "sg:address":"1 Sylvan Rd N",
    "sg:city":"Westport",
    "sg:classifiers":[
        {
            "category":"Education",
            "subcategory":"School",
            "type":"Public Place"
        }
    ],
    "sg:phone":"+1 203 226 1891",
    "sg:postcode":"06880",
    "sg:province":"CT",
    "wof:name":"Pierrepont School",
    "wof:placetype":"venue"
},
  "geometry": {"coordinates":[-73.37441,41.135383],"type":"Point"}
}