{
  "type": "Feature",
  "properties": {
    "iso:country":"US",
    "sg:address":"15 Settlers Ln",
    "sg:city":"Clinton",
    "sg:classifiers":[
        {
            "category":"Professional",
            "subcategory":"Management & Consulting",
            "type":"Services"
        }
    ],
    "sg:phone":"+1   ",
    "sg:postcode":"06413",
    "sg:province":"CT",
    "sg:tags":[
        "business"
    ],
    "wof:name":"Crew Training International",
    "wof:placetype":"venue"
},
  "geometry": {"coordinates":[-72.510383,41.281288],"type":"Point"}
}