{
  "type": "Feature",
  "properties": {
    "addr:full":"1120 S Main St Cheshire CT 06410",
    "addr:housenumber":"1120",
    "addr:postcode":"06410",
    "addr:street":"S Main St",
    "iso:country":"US",
    "sg:address":"1120 S Main St",
    "sg:city":"Cheshire",
    "sg:classifiers":[
        {
            "category":"Professional",
            "subcategory":"Lawyer & Legal Services",
            "type":"Services"
        }
    ],
    "sg:phone":"+1 203 271 2661",
    "sg:postcode":"06410",
    "sg:province":"CT",
    "sg:tags":[
        "attorney"
    ],
    "wof:name":"Andrew D Coleman Atty",
    "wof:placetype":"venue"
},
  "geometry": {"coordinates":[-72.906408,41.474355],"type":"Point"}
}