{
  "type": "Feature",
  "properties": {
    "iso:country":"US",
    "sg:address":"11 Novelty Ln",
    "sg:city":"Essex",
    "sg:classifiers":[
        {
            "category":"Restaurant",
            "type":"Food & Drink"
        }
    ],
    "sg:phone":"+1 860 767 9950",
    "sg:postcode":"06426",
    "sg:province":"CT",
    "wof:name":"Abby's Catering Company",
    "wof:placetype":"venue"
},
  "geometry": {"coordinates":[-72.385779,41.349654],"type":"Point"}
}