{
  "type": "Feature",
  "properties": {
    "addr:full":"859 Congress Ave New Haven CT 06519",
    "addr:housenumber":"859",
    "addr:postcode":"06519",
    "addr:street":"Congress Ave",
    "iso:country":"US",
    "sg:address":"859 Congress Ave",
    "sg:city":"New Haven",
    "sg:classifiers":[
        {
            "category":"Retail",
            "subcategory":"Auto Repair",
            "type":"Services"
        }
    ],
    "sg:phone":"+1 203 787 6746",
    "sg:postcode":"06519",
    "sg:province":"CT",
    "sg:tags":[
        "automobile",
        "electric"
    ],
    "wof:name":"Clark-Son Co",
    "wof:placetype":"venue"
},
  "geometry": {"coordinates":[-72.94761200000001,41.297988],"type":"Point"}
}