{
  "type": "Feature",
  "properties": {
    "iso:country":"US",
    "sg:address":"17 Sanford St",
    "sg:city":"Fairfield",
    "sg:classifiers":[
        {
            "category":"Shopping",
            "subcategory":"Clothing, Apparel, & Fashions",
            "type":"Retail Goods"
        }
    ],
    "sg:phone":"+1 203 254 6686",
    "sg:postcode":"06483",
    "sg:province":"CT",
    "sg:tags":[
        "wear"
    ],
    "wof:name":"Precious Cargo",
    "wof:placetype":"venue"
},
  "geometry": {"coordinates":[-73.06987700000001,41.395654],"type":"Point"}
}