{
  "type": "Feature",
  "properties": {
    "iso:country":"US",
    "sg:address":"3 Macbean Dr",
    "sg:city":"New Fairfield",
    "sg:classifiers":[
        {
            "category":"Organizations",
            "subcategory":"Religious Organization",
            "type":"Services"
        }
    ],
    "sg:phone":"+1   ",
    "sg:postcode":"06812",
    "sg:province":"CT",
    "wof:name":"Saint Edwrds Off Fith Frmation",
    "wof:placetype":"venue"
},
  "geometry": {"coordinates":[-73.489431,41.457341],"type":"Point"}
}