{
  "type": "Feature",
  "properties": {
    "iso:country":"US",
    "sg:address":"940 Federal Rd",
    "sg:city":"Brookfield",
    "sg:classifiers":[
        {
            "category":"Professional",
            "subcategory":"Business Services",
            "type":"Services"
        }
    ],
    "sg:phone":"+1 203 853 4642",
    "sg:postcode":"06804",
    "sg:province":"CT",
    "sg:tags":[
        "packaging"
    ],
    "wof:name":"Transport Moving & Storage Inc",
    "wof:placetype":"venue"
},
  "geometry": {"coordinates":[-73.410673,41.484247],"type":"Point"}
}