{
  "type": "Feature",
  "properties": {
    "addr:full":"15 E Putnam Ave Greenwich CT 06830",
    "addr:housenumber":"15",
    "addr:postcode":"06830",
    "addr:street":"E Putnam Ave",
    "iso:country":"US",
    "sg:address":"15 E Putnam Ave",
    "sg:city":"Greenwich",
    "sg:classifiers":[
        {
            "category":"Health Services",
            "subcategory":"Doctor",
            "type":"Services"
        }
    ],
    "sg:phone":"+1   ",
    "sg:postcode":"06830",
    "sg:province":"CT",
    "sg:tags":[
        "medical"
    ],
    "wof:name":"Alliance In Breast Cancer",
    "wof:placetype":"venue"
},
  "geometry": {"coordinates":[-73.62606700000001,41.031988],"type":"Point"}
}