{
  "type": "Feature",
  "properties": {
    "addr:full":"1212 Main St Willimantic CT 06226",
    "addr:housenumber":"1212",
    "addr:postcode":"06226",
    "addr:street":"Main St",
    "iso:country":"US",
    "sg:address":"1212 Main St",
    "sg:city":"Willimantic",
    "sg:classifiers":[
        {
            "category":"Autos & Motor Vehicles",
            "subcategory":"Auto Supplies",
            "type":"Retail Goods"
        }
    ],
    "sg:phone":"+1 860 456 1766",
    "sg:postcode":"06226",
    "sg:province":"CT",
    "wof:name":"Midas Muffler",
    "wof:placetype":"venue"
},
  "geometry": {"coordinates":[-72.22589499999999,41.714047],"type":"Point"}
}