{
  "type": "Feature",
  "properties": {
    "addr:full":"610 Maple St Wethersfield CT 06109",
    "addr:housenumber":"610",
    "addr:postcode":"06109",
    "addr:street":"Maple St",
    "iso:country":"US",
    "sg:address":"610 Maple St",
    "sg:city":"Wethersfield",
    "sg:classifiers":[
        {
            "category":"Professional",
            "subcategory":"Management & Consulting",
            "type":"Services"
        }
    ],
    "sg:phone":"+1   ",
    "sg:postcode":"06109",
    "sg:province":"CT",
    "sg:tags":[
        "business"
    ],
    "wof:name":"Advanced Purchasing Cons",
    "wof:placetype":"venue"
},
  "geometry": {"coordinates":[-72.66436299999999,41.684053],"type":"Point"}
}