{
  "type": "Feature",
  "properties": {
    "iso:country":"US",
    "sg:address":"92 Candlewood Lake Rd N",
    "sg:city":"New Milford",
    "sg:classifiers":[
        {
            "category":"Professional",
            "type":"Services"
        }
    ],
    "sg:phone":"+1 860 354 5431",
    "sg:postcode":"06776",
    "sg:province":"CT",
    "wof:name":"George R Wetmore Memorial",
    "wof:placetype":"venue"
},
  "geometry": {"coordinates":[-73.436182,41.57363],"type":"Point"}
}