{
  "type": "Feature",
  "properties": {
    "addr:full":"70 Ingleside Dr Hamden CT 06514",
    "addr:housenumber":"70",
    "addr:postcode":"06514",
    "addr:street":"Ingleside Dr",
    "iso:country":"US",
    "sg:address":"70 Ingleside Dr",
    "sg:city":"Hamden",
    "sg:classifiers":[
        {
            "category":"Organizations",
            "subcategory":"Religious Organization",
            "type":"Services"
        }
    ],
    "sg:phone":"+1   ",
    "sg:postcode":"06514",
    "sg:province":"CT",
    "wof:name":"Faith Family Christian",
    "wof:placetype":"venue"
},
  "geometry": {"coordinates":[-72.94664299999999,41.364083],"type":"Point"}
}