{
  "type": "Feature",
  "properties": {
    "addr:full":"427 Heritage Rd Southbury CT 06488",
    "addr:housenumber":"427",
    "addr:postcode":"06488",
    "addr:street":"Heritage Rd",
    "iso:country":"US",
    "sg:address":"427 Heritage Rd",
    "sg:city":"Southbury",
    "sg:classifiers":[
        {
            "category":"Banks & Credit Unions",
            "subcategory":"Financial Services",
            "type":"Services"
        }
    ],
    "sg:phone":"+1 203 264 4770",
    "sg:postcode":"06488",
    "sg:province":"CT",
    "sg:tags":[
        "trust",
        "management"
    ],
    "wof:name":"Madolyn Sboudreau Trust",
    "wof:placetype":"venue"
},
  "geometry": {"coordinates":[-73.224783,41.487456],"type":"Point"}
}