{
  "type": "Feature",
  "properties": {
    "iso:country":"US",
    "sg:address":"14 Diane Dr",
    "sg:city":"Monroe",
    "sg:classifiers":[
        {
            "category":"Professional",
            "type":"Services"
        }
    ],
    "sg:phone":"+1 203 261 4097",
    "sg:postcode":"06468",
    "sg:province":"CT",
    "wof:name":"Patrick McMahon",
    "wof:placetype":"venue"
},
  "geometry": {"coordinates":[-73.226957,41.346585],"type":"Point"}
}