{
  "type": "Feature",
  "properties": {
    "iso:country":"US",
    "sg:address":"75 Crystal Ave",
    "sg:city":"New London",
    "sg:classifiers":[
        {
            "category":"Real Estate",
            "subcategory":"Real Estate Operator",
            "type":"Services"
        }
    ],
    "sg:phone":"+1 860 447 8370",
    "sg:postcode":"06320",
    "sg:province":"CT",
    "sg:tags":[
        "building",
        "nonresidential"
    ],
    "wof:name":"Thames River Properties LLC",
    "wof:placetype":"venue"
},
  "geometry": {"coordinates":[-72.096766,41.361619],"type":"Point"}
}