{
  "type": "Feature",
  "properties": {
    "iso:country":"US",
    "sg:address":"148 Webbs Hill Rd",
    "sg:city":"Stamford",
    "sg:classifiers":[
        {
            "category":"Social Services",
            "type":"Services"
        }
    ],
    "sg:phone":"+1   ",
    "sg:postcode":"06903",
    "sg:province":"CT",
    "wof:name":"Freire",
    "wof:placetype":"venue"
},
  "geometry": {"coordinates":[-73.567592,41.106552],"type":"Point"}
}