{
  "type": "Feature",
  "properties": {
    "addr:full":"8 Hawkins Rd Oxford CT 06478",
    "addr:housenumber":"8",
    "addr:postcode":"06478",
    "addr:street":"Hawkins Rd",
    "iso:country":"US",
    "sg:address":"8 Hawkins Rd",
    "sg:city":"Oxford",
    "sg:classifiers":[
        {
            "category":"Wholesale",
            "subcategory":"Machinery & Supplies",
            "type":"Manufacturing & Wholesale Goods"
        }
    ],
    "sg:phone":"+1 203 888 0062",
    "sg:postcode":"06478",
    "sg:province":"CT",
    "sg:tags":[
        "shop",
        "equipment",
        "establishment",
        "beauty"
    ],
    "wof:name":"Hair Loft",
    "wof:placetype":"venue"
},
  "geometry": {"coordinates":[-73.15746,41.422522],"type":"Point"}
}