{
  "type": "Feature",
  "properties": {
    "iso:country":"US",
    "sg:address":"464 Lime Rock Rd",
    "sg:city":"Lakeville",
    "sg:classifiers":[
        {
            "category":"Professional",
            "type":"Services"
        }
    ],
    "sg:phone":"+1 860 435 9425",
    "sg:postcode":"06039",
    "sg:province":"CT",
    "wof:name":"Hermitage St Antony The Desert",
    "wof:placetype":"venue"
},
  "geometry": {"coordinates":[-73.38233,41.931642],"type":"Point"}
}