{
  "type": "Feature",
  "properties": {
    "iso:country":"US",
    "sg:address":"1231 Whitney Ave",
    "sg:city":"Hamden",
    "sg:classifiers":[
        {
            "category":"Food & Beverages",
            "subcategory":"Bakery",
            "type":"Retail Goods"
        }
    ],
    "sg:phone":"+1 203 288 2232",
    "sg:postcode":"06517",
    "sg:province":"CT",
    "wof:name":"Patisserie Normande",
    "wof:placetype":"venue"
},
  "geometry": {"coordinates":[-72.91211,41.344309],"type":"Point"}
}