{
  "type": "Feature",
  "properties": {
    "addr:full":"99 Saugatuck Ave Westport CT 06880",
    "addr:housenumber":"99",
    "addr:postcode":"06880",
    "addr:street":"Saugatuck Ave",
    "iso:country":"US",
    "sg:address":"99 Saugatuck Ave",
    "sg:city":"Westport",
    "sg:classifiers":[
        {
            "category":"Insurance",
            "subcategory":"Insurance Agent",
            "type":"Services"
        }
    ],
    "sg:phone":"+1 203 454 0045",
    "sg:postcode":"06880",
    "sg:province":"CT",
    "wof:name":"Fiscal Strategies LLC",
    "wof:placetype":"venue"
},
  "geometry": {"coordinates":[-73.372801,41.122735],"type":"Point"}
}