{
  "type": "Feature",
  "properties": {
    "addr:full":"276 Sharon Tpke Goshen CT 06756",
    "addr:housenumber":"276",
    "addr:postcode":"06756",
    "addr:street":"Sharon Tpke",
    "iso:country":"US",
    "sg:address":"276 Sharon Tpke",
    "sg:city":"Goshen",
    "sg:classifiers":[
        {
            "category":"Personal",
            "subcategory":"Beauty Salon",
            "type":"Services"
        }
    ],
    "sg:phone":"+1 860 491 5997",
    "sg:postcode":"06756",
    "sg:province":"CT",
    "wof:name":"Grosclaude Robert",
    "wof:placetype":"venue"
},
  "geometry": {"coordinates":[-73.25107800000001,41.827747],"type":"Point"}
}