{
  "type": "Feature",
  "properties": {
    "iso:country":"US",
    "sg:address":"20 Research Pkwy",
    "sg:city":"Old Saybrook",
    "sg:classifiers":[
        {
            "category":"Health Services",
            "subcategory":"Clinic",
            "type":"Services"
        }
    ],
    "sg:phone":"+1 800 370 3651",
    "sg:postcode":"06475",
    "sg:province":"CT",
    "sg:tags":[
        "counseling",
        "mental"
    ],
    "sg:website":"www.medoptionsinc.com",
    "wof:name":"Medoptions",
    "wof:placetype":"venue"
},
  "geometry": {"coordinates":[-72.38470599999999,41.300787],"type":"Point"}
}