{
  "type": "Feature",
  "properties": {
    "addr:full":"96 Central St Ansonia CT 06401",
    "addr:housenumber":"96",
    "addr:postcode":"06401",
    "addr:street":"Central St",
    "iso:country":"US",
    "sg:address":"96 Central St",
    "sg:city":"Ansonia",
    "sg:classifiers":[
        {
            "category":"Organizations",
            "subcategory":"Religious Organization",
            "type":"Services"
        }
    ],
    "sg:phone":"+1 203 735 9073",
    "sg:postcode":"06401",
    "sg:province":"CT",
    "sg:tags":[
        "church"
    ],
    "wof:name":"Clinton AME Zion Church",
    "wof:placetype":"venue"
},
  "geometry": {"coordinates":[-73.07316899999999,41.340373],"type":"Point"}
}