{
  "type": "Feature",
  "properties": {
    "iso:country":"US",
    "sg:address":"718 Griswold St",
    "sg:city":"Glastonbury",
    "sg:classifiers":[
        {
            "category":"Wholesale",
            "subcategory":"Construction Materials",
            "type":"Manufacturing & Wholesale Goods"
        }
    ],
    "sg:phone":"+1 860 430 1023",
    "sg:postcode":"06033",
    "sg:province":"CT",
    "wof:name":"New England Seal Coat & Paveme",
    "wof:placetype":"venue"
},
  "geometry": {"coordinates":[-72.581908,41.726664],"type":"Point"}
}