{
  "type": "Feature",
  "properties": {
    "iso:country":"US",
    "sg:address":"1046 Blue Hills Ave",
    "sg:city":"Bloomfield",
    "sg:classifiers":[
        {
            "category":"Shopping",
            "subcategory":"Pets & Pet Supplies",
            "type":"Retail Goods"
        },
        {
            "category":"Retail",
            "subcategory":"Animal Services",
            "type":"Services"
        }
    ],
    "sg:phone":"+1 860 286 0575",
    "sg:postcode":"06002",
    "sg:province":"CT",
    "sg:tags":[
        "grooming",
        "dog",
        "cat"
    ],
    "wof:name":"Apple Crest Dog Grooming",
    "wof:placetype":"venue"
},
  "geometry": {"coordinates":[-72.696129,41.822479],"type":"Point"}
}