{
  "type": "Feature",
  "properties": {
    "addr:full":"63 Geneva Ave Hartford CT 06107",
    "addr:housenumber":"63",
    "addr:postcode":"06107",
    "addr:street":"Geneva Ave;Ct",
    "iso:country":"US",
    "sg:address":"63 Geneva Ave",
    "sg:city":"Hartford",
    "sg:classifiers":[
        {
            "category":"Real Estate",
            "subcategory":"Architect",
            "type":"Services"
        }
    ],
    "sg:phone":"+1   ",
    "sg:postcode":"06107",
    "sg:province":"CT",
    "sg:tags":[
        "architectural"
    ],
    "wof:name":"Neil S Rosoff",
    "wof:placetype":"venue"
},
  "geometry": {"coordinates":[-72.77537,41.749033],"type":"Point"}
}