{
  "type": "Feature",
  "properties": {
    "addr:full":"5 Leslie Ln Westport CT 06880",
    "addr:housenumber":"5",
    "addr:postcode":"06880",
    "addr:street":"Leslie Ln",
    "iso:country":"US",
    "sg:address":"5 Leslie Ln",
    "sg:city":"Westport",
    "sg:classifiers":[
        {
            "category":"Professional",
            "subcategory":"Management & Consulting",
            "type":"Services"
        }
    ],
    "sg:phone":"+1   ",
    "sg:postcode":"06880",
    "sg:province":"CT",
    "sg:tags":[
        "corporate",
        "premium",
        "incentive"
    ],
    "wof:name":"Crystal Impressions",
    "wof:placetype":"venue"
},
  "geometry": {"coordinates":[-73.34085,41.154028],"type":"Point"}
}