{
  "type": "Feature",
  "properties": {
    "addr:full":"5 Ivanhoe Ln Westport CT 06880",
    "addr:housenumber":"5",
    "addr:postcode":"06880",
    "addr:street":"Ivanhoe Ln",
    "iso:country":"US",
    "sg:address":"5 Ivanhoe Ln",
    "sg:city":"Westport",
    "sg:classifiers":[
        {
            "category":"Professional",
            "type":"Services"
        }
    ],
    "sg:phone":"+1 203 227 7548",
    "sg:postcode":"06880",
    "sg:province":"CT",
    "wof:name":"Maxb LLC",
    "wof:placetype":"venue"
},
  "geometry": {"coordinates":[-73.360861,41.126372],"type":"Point"}
}