{
  "type": "Feature",
  "properties": {
    "addr:full":"223 Meadow St Naugatuck CT 06770",
    "addr:housenumber":"223",
    "addr:postcode":"06770",
    "addr:street":"Meadow St Naugatuck Ct",
    "iso:country":"US",
    "sg:address":"223 Meadow St",
    "sg:city":"Naugatuck",
    "sg:classifiers":[
        {
            "category":"Professional",
            "subcategory":"Engineering",
            "type":"Services"
        }
    ],
    "sg:phone":"+1 203 729 4841",
    "sg:postcode":"06770",
    "sg:province":"CT",
    "sg:tags":[
        "engineer"
    ],
    "wof:name":"JSB Consulting Engineers",
    "wof:placetype":"venue"
},
  "geometry": {"coordinates":[-73.055755,41.493323],"type":"Point"}
}