{
  "type": "Feature",
  "properties": {
    "iso:country":"US",
    "sg:address":"975 Moss Farms Rd",
    "sg:city":"Cheshire",
    "sg:classifiers":[
        {
            "category":"Communications",
            "subcategory":"Film & Video Production",
            "type":"Services"
        }
    ],
    "sg:phone":"+1   ",
    "sg:postcode":"06410",
    "sg:province":"CT",
    "sg:tags":[
        "sound",
        "engineering"
    ],
    "wof:name":"Fred J Napolitano",
    "wof:placetype":"venue"
},
  "geometry": {"coordinates":[-72.92067299999999,41.532349],"type":"Point"}
}