{
  "type": "Feature",
  "properties": {
    "addr:full":"181 State St Bridgeport CT 06604",
    "addr:housenumber":"181",
    "addr:postcode":"06604",
    "addr:street":"State St",
    "iso:country":"US",
    "sg:address":"181 State St",
    "sg:city":"Bridgeport",
    "sg:classifiers":[
        {
            "category":"Professional",
            "type":"Services"
        }
    ],
    "sg:phone":"+1 203 334 3773",
    "sg:postcode":"06604",
    "sg:province":"CT",
    "sg:tags":[
        "establishment"
    ],
    "wof:name":"Silver Lining",
    "wof:placetype":"venue"
},
  "geometry": {"coordinates":[-73.189126,41.176678],"type":"Point"}
}