{
  "type": "Feature",
  "properties": {
    "addr:full":"240 Fairfield Ave Bridgeport CT 06604",
    "addr:housenumber":"240",
    "addr:postcode":"06604",
    "addr:street":"Fairfield Ave",
    "iso:country":"US",
    "sg:address":"240 Fairfield Ave",
    "sg:city":"Bridgeport",
    "sg:classifiers":[
        {
            "category":"Government",
            "subcategory":"Jail",
            "type":"Public Place"
        }
    ],
    "sg:phone":"+1 203 579 6120",
    "sg:postcode":"06604",
    "sg:province":"CT",
    "sg:tags":[
        "govt",
        "state",
        "institution"
    ],
    "wof:name":"Corrections Dept",
    "wof:placetype":"venue"
},
  "geometry": {"coordinates":[-73.193004,41.178237],"type":"Point"}
}