{
  "type": "Feature",
  "properties": {
    "addr:full":"67 N Main St Essex CT 06426",
    "addr:housenumber":"67",
    "addr:postcode":"06426",
    "addr:street":"N Main St",
    "iso:country":"US",
    "sg:address":"67 N Main St",
    "sg:city":"Essex",
    "sg:classifiers":[
        {
            "category":"Health Services",
            "subcategory":"Doctor",
            "type":"Services"
        }
    ],
    "sg:phone":"+1 860 767 1034",
    "sg:postcode":"06426",
    "sg:province":"CT",
    "wof:name":"Lian Gary G MD PHD",
    "wof:placetype":"venue"
},
  "geometry": {"coordinates":[-72.394897,41.358101],"type":"Point"}
}