{
  "type": "Feature",
  "properties": {
    "addr:full":"143 School St Danielson CT 06239",
    "addr:housenumber":"143",
    "addr:postcode":"06239",
    "addr:street":"School St",
    "iso:country":"US",
    "sg:address":"143 School St",
    "sg:city":"Danielson",
    "sg:classifiers":[
        {
            "category":"Professional",
            "subcategory":"Lawyer & Legal Services",
            "type":"Services"
        }
    ],
    "sg:phone":"+1   ",
    "sg:postcode":"06239",
    "sg:province":"CT",
    "wof:name":"Sarantopoulos & Sarantopoulos",
    "wof:placetype":"venue"
},
  "geometry": {"coordinates":[-71.881874,41.805791],"type":"Point"}
}