{
  "type": "Feature",
  "properties": {
    "addr:full":"357 Bank St New London CT 06320",
    "addr:housenumber":"357",
    "addr:postcode":"06320",
    "addr:street":"Bank St New London Ct",
    "iso:country":"US",
    "sg:address":"357 Bank St",
    "sg:city":"New London",
    "sg:classifiers":[
        {
            "category":"Food & Beverages",
            "subcategory":"Groceries & Convenience Stores",
            "type":"Retail Goods"
        }
    ],
    "sg:phone":"+1 860 442 1515",
    "sg:postcode":"06320",
    "sg:province":"CT",
    "wof:name":"India Food LLC",
    "wof:placetype":"venue"
},
  "geometry": {"coordinates":[-72.100649,41.350418],"type":"Point"}
}