{
  "type": "Feature",
  "properties": {
    "iso:country":"US",
    "sg:address":"167 Frederick St",
    "sg:city":"Torrington",
    "sg:classifiers":[
        {
            "category":"Wholesale",
            "subcategory":"Machinery & Supplies",
            "type":"Manufacturing & Wholesale Goods"
        }
    ],
    "sg:phone":"+1 860 489 5408",
    "sg:postcode":"06790",
    "sg:province":"CT",
    "sg:tags":[
        "industrial"
    ],
    "wof:name":"Wire-Cut Corporation",
    "wof:placetype":"venue"
},
  "geometry": {"coordinates":[-73.102887,41.803328],"type":"Point"}
}