{
  "type": "Feature",
  "properties": {
    "addr:full":"646 Long Hill Rd Groton CT 06340",
    "addr:housenumber":"646",
    "addr:postcode":"06340",
    "addr:street":"Long Hill Rd Groton Ct",
    "iso:country":"US",
    "sg:address":"646 Long Hill Rd",
    "sg:city":"Groton",
    "sg:classifiers":[
        {
            "category":"Social Services",
            "subcategory":"Child Care",
            "type":"Services"
        }
    ],
    "sg:phone":"+1   ",
    "sg:postcode":"06340",
    "sg:province":"CT",
    "sg:tags":[
        "day"
    ],
    "wof:name":"Gymboree Play & Music",
    "wof:placetype":"venue"
},
  "geometry": {"coordinates":[-72.056844,41.350865],"type":"Point"}
}