{
  "type": "Feature",
  "properties": {
    "iso:country":"US",
    "sg:address":"80 Glastonbury Blvd",
    "sg:city":"Glastonbury",
    "sg:classifiers":[
        {
            "category":"Real Estate",
            "subcategory":"Architect",
            "type":"Services"
        }
    ],
    "sg:phone":"+1 860 657 8077",
    "sg:postcode":"06033",
    "sg:province":"CT",
    "sg:tags":[
        "interior",
        "engineering",
        "architectural",
        "structural"
    ],
    "wof:name":"S/L/A/M Collaborative Inc",
    "wof:placetype":"venue"
},
  "geometry": {"coordinates":[-72.61663900000001,41.721929],"type":"Point"}
}