{
  "type": "Feature",
  "properties": {
    "iso:country":"US",
    "sg:address":"43 Church Dr",
    "sg:city":"Cheshire",
    "sg:classifiers":[
        {
            "category":"Organizations",
            "subcategory":"Membership Organization",
            "type":"Services"
        }
    ],
    "sg:phone":"+1 203 272 2574",
    "sg:postcode":"06410",
    "sg:province":"CT",
    "wof:name":"Cheshire Historical Society",
    "wof:placetype":"venue"
},
  "geometry": {"coordinates":[-72.902658,41.497605],"type":"Point"}
}