{
  "type": "Feature",
  "properties": {
    "iso:country":"US",
    "sg:address":"27 Wayne Rd",
    "sg:city":"Monroe",
    "sg:classifiers":[
        {
            "category":"Social Services",
            "subcategory":"Child Care",
            "type":"Services"
        }
    ],
    "sg:phone":"+1   ",
    "sg:postcode":"06468",
    "sg:province":"CT",
    "sg:tags":[
        "day"
    ],
    "wof:name":"Childrens Corner Monroe LLC",
    "wof:placetype":"venue"
},
  "geometry": {"coordinates":[-73.19780900000001,41.315019],"type":"Point"}
}