{
  "type": "Feature",
  "properties": {
    "iso:country":"US",
    "sg:address":"246 New Haven Ave",
    "sg:city":"Milford",
    "sg:classifiers":[
        {
            "category":"Personal",
            "subcategory":"Barber",
            "type":"Services"
        }
    ],
    "sg:phone":"+1   ",
    "sg:postcode":"06460",
    "sg:province":"CT",
    "sg:tags":[
        "shop"
    ],
    "wof:name":"Head Company",
    "wof:placetype":"venue"
},
  "geometry": {"coordinates":[-73.04523399999999,41.222913],"type":"Point"}
}