{
  "type": "Feature",
  "properties": {
    "addr:full":"106 Elizabeth St Derby CT 06418",
    "addr:housenumber":"106",
    "addr:postcode":"06418",
    "addr:street":"Elizabeth St",
    "iso:country":"US",
    "sg:address":"106 Elizabeth St",
    "sg:city":"Derby",
    "sg:classifiers":[
        {
            "category":"Government",
            "subcategory":"Police Station",
            "type":"Public Place"
        }
    ],
    "sg:phone":"+1 203 735 9366",
    "sg:postcode":"06418",
    "sg:province":"CT",
    "sg:tags":[
        "state"
    ],
    "wof:name":"Sheriff's Dept",
    "wof:placetype":"venue"
},
  "geometry": {"coordinates":[-73.089579,41.322492],"type":"Point"}
}