{
  "type": "Feature",
  "properties": {
    "addr:full":"7 E Hayestown Rd Danbury CT 06811",
    "addr:housenumber":"7",
    "addr:postcode":"06811",
    "addr:street":"E Hayestown Rd",
    "iso:country":"US",
    "sg:address":"7 E Hayestown Rd",
    "sg:city":"Danbury",
    "sg:classifiers":[
        {
            "category":"Government",
            "subcategory":"Office",
            "type":"Public Place"
        }
    ],
    "sg:phone":"+1 203 797 4536",
    "sg:postcode":"06811",
    "sg:province":"CT",
    "sg:tags":[
        "village"
    ],
    "wof:name":"Danbury Tree Dept",
    "wof:placetype":"venue"
},
  "geometry": {"coordinates":[-73.452022,41.423134],"type":"Point"}
}