{
  "type": "Feature",
  "properties": {
    "iso:country":"US",
    "sg:address":"1200 Post Rd E",
    "sg:city":"Westport",
    "sg:classifiers":[
        {
            "category":"Health Services",
            "subcategory":"Doctor",
            "type":"Services"
        }
    ],
    "sg:phone":"+1 203 281 5468",
    "sg:postcode":"06880",
    "sg:province":"CT",
    "sg:tags":[
        "physician",
        "surgeon",
        "medical"
    ],
    "wof:name":"Ted Strayer Do",
    "wof:placetype":"venue"
},
  "geometry": {"coordinates":[-73.32247599999999,41.138797],"type":"Point"}
}