{
  "type": "Feature",
  "properties": {
    "addr:full":"160 Moffitt St Bridgeport CT 06606",
    "addr:housenumber":"160",
    "addr:postcode":"06606",
    "addr:street":"Moffitt St",
    "iso:country":"US",
    "sg:address":"160 Moffitt St",
    "sg:city":"Bridgeport",
    "sg:classifiers":[
        {
            "category":"Building & Trades",
            "subcategory":"Construction",
            "type":"Services"
        }
    ],
    "sg:phone":"+1 203 372 5582",
    "sg:postcode":"06606",
    "sg:province":"CT",
    "sg:tags":[
        "contractor"
    ],
    "wof:name":"M & M Gutters",
    "wof:placetype":"venue"
},
  "geometry": {"coordinates":[-73.19507,41.212676],"type":"Point"}
}