{
  "type": "Feature",
  "properties": {
    "addr:full":"10 Fairfield Blvd Wallingford CT 06492",
    "addr:housenumber":"10",
    "addr:postcode":"06492",
    "addr:street":"Fairfield Blvd",
    "iso:country":"US",
    "sg:address":"10 Fairfield Blvd",
    "sg:city":"Wallingford",
    "sg:classifiers":[
        {
            "category":"Professional",
            "subcategory":"Computer Services",
            "type":"Services"
        }
    ],
    "sg:phone":"+1 203 265 5612",
    "sg:postcode":"06492",
    "sg:province":"CT",
    "sg:tags":[
        "internet"
    ],
    "wof:name":"Pairgain Wallingford Design",
    "wof:placetype":"venue"
},
  "geometry": {"coordinates":[-72.78870000000001,41.48357],"type":"Point"}
}