{
  "type": "Feature",
  "properties": {
    "addr:full":"36 Main St Unionville CT 06085",
    "addr:housenumber":"36",
    "addr:postcode":"06085",
    "addr:street":"Main St Unionville Ct",
    "iso:country":"US",
    "sg:address":"36 Main St",
    "sg:city":"Unionville",
    "sg:classifiers":[
        {
            "category":"Health Services",
            "subcategory":"Doctor",
            "type":"Services"
        }
    ],
    "sg:phone":"+1 860 673 9770",
    "sg:postcode":"06085",
    "sg:province":"CT",
    "sg:tags":[
        "dentist"
    ],
    "wof:name":"Cooley Dawn DMD",
    "wof:placetype":"venue"
},
  "geometry": {"coordinates":[-72.887901,41.758999],"type":"Point"}
}