{
  "type": "Feature",
  "properties": {
    "addr:full":"134 Williams St New London CT 06320",
    "addr:housenumber":"134",
    "addr:postcode":"06320",
    "addr:street":"Williams St New London Ct",
    "iso:country":"US",
    "sg:address":"134 Williams St",
    "sg:city":"New London",
    "sg:classifiers":[
        {
            "category":"Education",
            "subcategory":"School",
            "type":"Public Place"
        }
    ],
    "sg:phone":"+1   ",
    "sg:postcode":"06320",
    "sg:province":"CT",
    "sg:tags":[
        "system"
    ],
    "wof:name":"New London Public School Dst",
    "wof:placetype":"venue"
},
  "geometry": {"coordinates":[-72.105509,41.357756],"type":"Point"}
}