{
  "type": "Feature",
  "properties": {
    "addr:full":"60 Inwood Rd Darien CT 06820",
    "addr:housenumber":"60",
    "addr:postcode":"06820",
    "addr:street":"Inwood Rd",
    "iso:country":"US",
    "sg:address":"60 Inwood Rd",
    "sg:city":"Darien",
    "sg:classifiers":[
        {
            "category":"Professional",
            "subcategory":"Business Services",
            "type":"Services"
        }
    ],
    "sg:phone":"+1   ",
    "sg:postcode":"06820",
    "sg:province":"CT",
    "wof:name":"Nemec Enterprises LLC",
    "wof:placetype":"venue"
},
  "geometry": {"coordinates":[-73.49963099999999,41.100319],"type":"Point"}
}