{
  "type": "Feature",
  "properties": {
    "addr:full":"1 Evergreen Ave Hamden CT 06518",
    "addr:housenumber":"1",
    "addr:postcode":"06518",
    "addr:street":"Evergreen Ave",
    "iso:country":"US",
    "sg:address":"1 Evergreen Ave",
    "sg:city":"Hamden",
    "sg:classifiers":[
        {
            "category":"Professional",
            "subcategory":"Accounting & Tax Preparation",
            "type":"Services"
        }
    ],
    "sg:phone":"+1 203 281 3231",
    "sg:postcode":"06518",
    "sg:province":"CT",
    "sg:tags":[
        "accountant"
    ],
    "wof:name":"Lye & Lye",
    "wof:placetype":"venue"
},
  "geometry": {"coordinates":[-72.906882,41.385208],"type":"Point"}
}