{
  "type": "Feature",
  "properties": {
    "iso:country":"US",
    "sg:address":"74 Fresh Meadow Dr",
    "sg:city":"Trumbull",
    "sg:classifiers":[
        {
            "category":"Communications",
            "subcategory":"Film & Video Production",
            "type":"Services"
        }
    ],
    "sg:phone":"+1   ",
    "sg:postcode":"06611",
    "sg:province":"CT",
    "sg:tags":[
        "motion"
    ],
    "wof:name":"Vintage Video",
    "wof:placetype":"venue"
},
  "geometry": {"coordinates":[-73.26005600000001,41.28297],"type":"Point"}
}