{
  "type": "Feature",
  "properties": {
    "iso:country":"US",
    "sg:address":"39 Nichols Ave",
    "sg:city":"Shelton",
    "sg:classifiers":[
        {
            "category":"Building & Trades",
            "subcategory":"Plumbing",
            "type":"Services"
        }
    ],
    "sg:phone":"+1 203 925 0228",
    "sg:postcode":"06484",
    "sg:province":"CT",
    "sg:tags":[
        "plumbing",
        "contractor"
    ],
    "wof:name":"W R Bronson Inc",
    "wof:placetype":"venue"
},
  "geometry": {"coordinates":[-73.14773700000001,41.294115],"type":"Point"}
}