{
  "type": "Feature",
  "properties": {
    "addr:full":"70 Hoffman Rd Ellington CT 06029",
    "addr:housenumber":"70",
    "addr:postcode":"06029",
    "addr:street":"Hoffman Rd Ellington Ct",
    "iso:country":"US",
    "sg:address":"70 Hoffman Rd",
    "sg:city":"Ellington",
    "sg:classifiers":[
        {
            "category":"Building & Trades",
            "subcategory":"Landscaping Services",
            "type":"Services"
        }
    ],
    "sg:phone":"+1 860 871 9010",
    "sg:postcode":"06029",
    "sg:province":"CT",
    "sg:tags":[
        "landscape"
    ],
    "wof:name":"Elite",
    "wof:placetype":"venue"
},
  "geometry": {"coordinates":[-72.465783,41.93036],"type":"Point"}
}