{
  "type": "Feature",
  "properties": {
    "iso:country":"US",
    "sg:address":"1676 Huntington Tpke",
    "sg:city":"Trumbull",
    "sg:classifiers":[
        {
            "category":"Real Estate",
            "subcategory":"Real Estate Agent",
            "type":"Services"
        }
    ],
    "sg:phone":"+1 203 377 1588",
    "sg:postcode":"06611",
    "sg:province":"CT",
    "sg:tags":[
        "manager",
        "or"
    ],
    "wof:name":"William Raveis Real Estate Inc",
    "wof:placetype":"venue"
},
  "geometry": {"coordinates":[-73.1615,41.238773],"type":"Point"}
}