{
  "type": "Feature",
  "properties": {
    "iso:country":"US",
    "sg:address":"5 Blind Brook Rd",
    "sg:city":"Westport",
    "sg:classifiers":[
        {
            "category":"Building & Trades",
            "subcategory":"Construction",
            "type":"Services"
        }
    ],
    "sg:phone":"+1 203 454 1965",
    "sg:postcode":"06880",
    "sg:province":"CT",
    "sg:tags":[
        "home",
        "remodeling"
    ],
    "wof:name":"Madorsky Inc Phyllis",
    "wof:placetype":"venue"
},
  "geometry": {"coordinates":[-73.37915099999999,41.141459],"type":"Point"}
}