{
  "type": "Feature",
  "properties": {
    "iso:country":"US",
    "sg:address":"14 Railroad Ave",
    "sg:city":"Meriden",
    "sg:classifiers":[
        {
            "category":"Sports & Exercise",
            "subcategory":"Gym",
            "type":"Entertainment"
        }
    ],
    "sg:phone":"+1 203 686 1639",
    "sg:postcode":"06451",
    "sg:province":"CT",
    "sg:tags":[
        "gymnasium"
    ],
    "wof:name":"Beat The Street Community Ctr",
    "wof:placetype":"venue"
},
  "geometry": {"coordinates":[-72.801733,41.539039],"type":"Point"}
}