{
  "type": "Feature",
  "properties": {
    "iso:country":"US",
    "sg:address":"10 Nashville Rd Exd",
    "sg:city":"Bethel",
    "sg:classifiers":[
        {
            "category":"Social Services",
            "subcategory":"Child Care",
            "type":"Services"
        }
    ],
    "sg:phone":"+1 203 797 9758",
    "sg:postcode":"06801",
    "sg:province":"CT",
    "wof:name":"Brian's Friends",
    "wof:placetype":"venue"
},
  "geometry": {"coordinates":[-73.40752500000001,41.359077],"type":"Point"}
}