{
  "type": "Feature",
  "properties": {
    "iso:country":"US",
    "sg:address":"831 Huntington Tpke",
    "sg:city":"Bridgeport",
    "sg:classifiers":[
        {
            "category":"Social Services",
            "subcategory":"Adult Care",
            "type":"Services"
        }
    ],
    "sg:phone":"+1 203 371 4880",
    "sg:postcode":"06610",
    "sg:province":"CT",
    "sg:tags":[
        "home",
        "group"
    ],
    "wof:name":"Weicker House",
    "wof:placetype":"venue"
},
  "geometry": {"coordinates":[-73.16909699999999,41.221465],"type":"Point"}
}