{
  "type": "Feature",
  "properties": {
    "iso:country":"US",
    "sg:address":"19 French Cir",
    "sg:city":"Thomaston",
    "sg:classifiers":[
        {
            "category":"Utilities",
            "subcategory":"Water",
            "type":"Services"
        },
        {
            "category":"Building & Trades",
            "subcategory":"Plumbing",
            "type":"Services"
        },
        {
            "category":"Home & Garden",
            "subcategory":"Hardware",
            "type":"Retail Goods"
        }
    ],
    "sg:phone":"+1 860 283 6736",
    "sg:postcode":"06787",
    "sg:province":"CT",
    "sg:tags":[
        "plumber",
        "industrial",
        "filtration",
        "softening",
        "supply",
        "work",
        "purification",
        "equipment",
        "conditioning",
        "contractors-commercial"
    ],
    "wof:name":"Phillips Robert & Maria",
    "wof:placetype":"venue"
},
  "geometry": {"coordinates":[-73.11594700000001,41.674477],"type":"Point"}
}