{
  "type": "Feature",
  "properties": {
    "iso:country":"US",
    "sg:address":"58 Littlefield Rd",
    "sg:city":"New Milford",
    "sg:classifiers":[
        {
            "category":"Professional",
            "subcategory":"Business Services",
            "type":"Services"
        }
    ],
    "sg:phone":"+1   ",
    "sg:postcode":"06776",
    "sg:province":"CT",
    "wof:name":"Jag Enterprises",
    "wof:placetype":"venue"
},
  "geometry": {"coordinates":[-73.383647,41.609155],"type":"Point"}
}