{
  "type": "Feature",
  "properties": {
    "iso:country":"US",
    "sg:address":"7 Progress Dr",
    "sg:city":"Cromwell",
    "sg:classifiers":[
        {
            "category":"Insurance",
            "subcategory":"Insurance Agent",
            "type":"Services"
        }
    ],
    "sg:phone":"+1 860 635 1400",
    "sg:postcode":"06416",
    "sg:province":"CT",
    "sg:tags":[
        "agency"
    ],
    "wof:name":"York Insurance Agency Inc",
    "wof:placetype":"venue"
},
  "geometry": {"coordinates":[-72.711203,41.615426],"type":"Point"}
}