{
  "type": "Feature",
  "properties": {
    "addr:full":"511 Orange St New Haven CT 06511",
    "addr:housenumber":"511",
    "addr:postcode":"06511",
    "addr:street":"Orange St",
    "iso:country":"US",
    "sg:address":"511 Orange St",
    "sg:city":"New Haven",
    "sg:classifiers":[
        {
            "category":"Insurance",
            "subcategory":"Insurance Agent",
            "type":"Services"
        }
    ],
    "sg:phone":"+1 203 776 4998",
    "sg:postcode":"06511",
    "sg:province":"CT",
    "wof:name":"A & S Insurance",
    "wof:placetype":"venue"
},
  "geometry": {"coordinates":[-72.917536,41.31421],"type":"Point"}
}