{
  "type": "Feature",
  "properties": {
    "addr:full":"51 Rte 39 S Sherman CT 06784",
    "addr:housenumber":"51",
    "addr:postcode":"06784",
    "addr:street":"Rte 39 S Sherman Ct",
    "iso:country":"US",
    "sg:address":"51 Rte 39 S",
    "sg:city":"Sherman",
    "sg:classifiers":[
        {
            "category":"Professional",
            "subcategory":"Computer Services",
            "type":"Services"
        }
    ],
    "sg:phone":"+1 860 350 8844",
    "sg:postcode":"06784",
    "sg:province":"CT",
    "sg:tags":[
        "consultant",
        "designer"
    ],
    "sg:website":"www.theremustbe.com",
    "wof:name":"There Must Be A Better Way",
    "wof:placetype":"venue"
},
  "geometry": {"coordinates":[-73.48890299999999,41.55589],"type":"Point"}
}