{
  "type": "Feature",
  "properties": {
    "addr:full":"23 Middlefield Rd Oxford CT 06478",
    "addr:housenumber":"23",
    "addr:postcode":"06478",
    "addr:street":"Middlefield Rd",
    "iso:country":"US",
    "sg:address":"23 Middlefield Rd",
    "sg:city":"Oxford",
    "sg:classifiers":[
        {
            "category":"Retail",
            "subcategory":"Repair Shop",
            "type":"Services"
        }
    ],
    "sg:phone":"+1   ",
    "sg:postcode":"06478",
    "sg:province":"CT",
    "sg:tags":[
        "electrical"
    ],
    "wof:name":"Zonas Enterprises LLC",
    "wof:placetype":"venue"
},
  "geometry": {"coordinates":[-73.096811,41.406138],"type":"Point"}
}