{
  "type": "Feature",
  "properties": {
    "addr:full":"45 Long Meadow Hill Rd Brookfield CT 06804",
    "addr:housenumber":"45",
    "addr:postcode":"06804",
    "addr:street":"Long Meadow Hill Rd",
    "iso:country":"US",
    "sg:address":"45 Long Meadow Hill Rd",
    "sg:city":"Brookfield",
    "sg:classifiers":[
        {
            "category":"Education",
            "subcategory":"School",
            "type":"Public Place"
        }
    ],
    "sg:phone":"+1   ",
    "sg:postcode":"06804",
    "sg:province":"CT",
    "wof:name":"Brookfield High School",
    "wof:placetype":"venue"
},
  "geometry": {"coordinates":[-73.390961,41.478557],"type":"Point"}
}