{
  "type": "Feature",
  "properties": {
    "addr:full":"400 Bayonet St New London CT 06320",
    "addr:housenumber":"400",
    "addr:postcode":"06320",
    "addr:street":"Bayonet St New London Ct",
    "iso:country":"US",
    "sg:address":"400 Bayonet St",
    "sg:city":"New London",
    "sg:classifiers":[
        {
            "category":"Real Estate",
            "subcategory":"Real Estate Agent",
            "type":"Services"
        }
    ],
    "sg:phone":"+1 860 444 1617",
    "sg:postcode":"06320",
    "sg:province":"CT",
    "sg:tags":[
        "management"
    ],
    "wof:name":"Boyer Realty Management",
    "wof:placetype":"venue"
},
  "geometry": {"coordinates":[-72.117986,41.374188],"type":"Point"}
}