{
  "type": "Feature",
  "properties": {
    "addr:full":"17 Fern Valley Rd Weston CT 06883",
    "addr:housenumber":"17",
    "addr:postcode":"06883",
    "addr:street":"Fern Valley Rd",
    "iso:country":"US",
    "sg:address":"17 Fern Valley Rd",
    "sg:city":"Weston",
    "sg:classifiers":[
        {
            "category":"Professional",
            "subcategory":"Computer Services",
            "type":"Services"
        }
    ],
    "sg:phone":"+1   ",
    "sg:postcode":"06883",
    "sg:province":"CT",
    "sg:tags":[
        "prepackaged",
        "business",
        "software"
    ],
    "wof:name":"Round Hill",
    "wof:placetype":"venue"
},
  "geometry": {"coordinates":[-73.35089600000001,41.223009],"type":"Point"}
}