{
  "type": "Feature",
  "properties": {
    "addr:full":"28 Crestwood Rd Ansonia CT 06401",
    "addr:housenumber":"28",
    "addr:postcode":"06401",
    "addr:street":"Crestwood Rd",
    "iso:country":"US",
    "sg:address":"28 Crestwood Rd",
    "sg:city":"Ansonia",
    "sg:classifiers":[
        {
            "category":"Communications",
            "subcategory":"Film & Video Production",
            "type":"Services"
        }
    ],
    "sg:phone":"+1 203 734 1206",
    "sg:postcode":"06401",
    "sg:province":"CT",
    "wof:name":"Lisa Unlimited Video Productions",
    "wof:placetype":"venue"
},
  "geometry": {"coordinates":[-73.06286900000001,41.325928],"type":"Point"}
}