{
  "type": "Feature",
  "properties": {
    "addr:full":"282 S Main St Naugatuck CT 06770",
    "addr:housenumber":"282",
    "addr:postcode":"06770",
    "addr:street":"S Main St Naugatuck Ct",
    "iso:country":"US",
    "sg:address":"282 S Main St",
    "sg:city":"Naugatuck",
    "sg:classifiers":[
        {
            "category":"Autos & Motor Vehicles",
            "subcategory":"Fuel & Gas Station",
            "type":"Retail Goods"
        }
    ],
    "sg:phone":"+1 203 723 4554",
    "sg:postcode":"06770",
    "sg:province":"CT",
    "sg:tags":[
        "oil"
    ],
    "wof:name":"Mobil",
    "wof:placetype":"venue"
},
  "geometry": {"coordinates":[-73.051491,41.4871],"type":"Point"}
}