{
  "type": "Feature",
  "properties": {
    "addr:full":"430 Chapel Hill Rd Oakdale CT 06370",
    "addr:housenumber":"430",
    "addr:postcode":"06370",
    "addr:street":"Chapel Hill Rd Oakdale Ct",
    "iso:country":"US",
    "sg:address":"430 Chapel Hill Rd",
    "sg:city":"Oakdale",
    "sg:classifiers":[
        {
            "category":"Restaurant",
            "type":"Food & Drink"
        }
    ],
    "sg:phone":"+1 860 859 0533",
    "sg:postcode":"06370",
    "sg:province":"CT",
    "sg:tags":[
        "eating"
    ],
    "wof:name":"Great Wall Chinese Restaurant",
    "wof:placetype":"venue"
},
  "geometry": {"coordinates":[-72.20502399999999,41.47241],"type":"Point"}
}