{
  "type": "Feature",
  "properties": {
    "iso:country":"US",
    "sg:address":"1140 Chapel St",
    "sg:city":"New Haven",
    "sg:classifiers":[
        {
            "category":"Real Estate",
            "subcategory":"Architect",
            "type":"Services"
        }
    ],
    "sg:phone":"+1 203 773 5057",
    "sg:postcode":"06511",
    "sg:province":"CT",
    "wof:name":"Charney Architects",
    "wof:placetype":"venue"
},
  "geometry": {"coordinates":[-72.933578,41.308848],"type":"Point"}
}