{
  "type": "Feature",
  "properties": {
    "iso:country":"US",
    "sg:address":"22 Broad St",
    "sg:city":"Norwalk",
    "sg:phone":"+1 203 847 2357",
    "sg:postcode":"06851",
    "sg:province":"CT",
    "sg:tags":[
        "equipment",
        "supply"
    ],
    "wof:name":"Powerline Equipment Co",
    "wof:placetype":"venue"
},
  "geometry": {"coordinates":[-73.427103,41.130981],"type":"Point"}
}