{
  "type": "Feature",
  "properties": {
    "iso:country":"US",
    "sg:address":"17 Loyal Ledge Ln",
    "sg:city":"Guilford",
    "sg:classifiers":[
        {
            "category":"Personal",
            "subcategory":"Beauty Salon",
            "type":"Services"
        }
    ],
    "sg:phone":"+1   ",
    "sg:postcode":"06437",
    "sg:province":"CT",
    "sg:tags":[
        "shop"
    ],
    "wof:name":"Make A Difference Inc",
    "wof:placetype":"venue"
},
  "geometry": {"coordinates":[-72.706042,41.244523],"type":"Point"}
}