{
  "type": "Feature",
  "properties": {
    "addr:full":"3851 Main St Bridgeport CT 06606",
    "addr:housenumber":"3851",
    "addr:postcode":"06606",
    "addr:street":"Main St",
    "iso:country":"US",
    "sg:address":"3851 Main St",
    "sg:city":"Bridgeport",
    "sg:classifiers":[
        {
            "category":"Professional",
            "type":"Services"
        }
    ],
    "sg:phone":"+1 203 372 1022",
    "sg:postcode":"06606",
    "sg:province":"CT",
    "sg:tags":[
        "establishment"
    ],
    "wof:name":"3851 Main Street Corp",
    "wof:placetype":"venue"
},
  "geometry": {"coordinates":[-73.21115,41.212974],"type":"Point"}
}