{
  "type": "Feature",
  "properties": {
    "addr:full":"361 Meadowside Rd Milford CT 06460",
    "addr:housenumber":"361",
    "addr:postcode":"06460",
    "addr:street":"Meadowside Rd",
    "iso:country":"US",
    "sg:address":"361 Meadowside Rd",
    "sg:city":"Milford",
    "sg:classifiers":[
        {
            "category":"Building & Trades",
            "subcategory":"Landscaping Services",
            "type":"Services"
        }
    ],
    "sg:phone":"+1 203 301 0136",
    "sg:postcode":"06460",
    "sg:province":"CT",
    "sg:tags":[
        "landscape"
    ],
    "wof:name":"Affordable Landscaping",
    "wof:placetype":"venue"
},
  "geometry": {"coordinates":[-73.07576899999999,41.208394],"type":"Point"}
}