{
  "type": "Feature",
  "properties": {
    "addr:full":"825 E Main St Meriden CT 06450",
    "addr:housenumber":"825",
    "addr:postcode":"06450",
    "addr:street":"E Main St",
    "iso:country":"US",
    "sg:address":"825 E Main St",
    "sg:city":"Meriden",
    "sg:classifiers":[
        {
            "category":"Restaurant",
            "type":"Food & Drink"
        }
    ],
    "sg:phone":"+1 203 237 7005",
    "sg:postcode":"06450",
    "sg:province":"CT",
    "wof:name":"Burger King",
    "wof:placetype":"venue"
},
  "geometry": {"coordinates":[-72.777463,41.529045],"type":"Point"}
}