{
  "type": "Feature",
  "properties": {
    "iso:country":"US",
    "sg:address":"86 N Main St",
    "sg:city":"Jewett City",
    "sg:classifiers":[
        {
            "category":"Retail",
            "subcategory":"Repair Shop",
            "type":"Services"
        }
    ],
    "sg:phone":"+1   ",
    "sg:postcode":"06351",
    "sg:province":"CT",
    "sg:tags":[
        "electrical"
    ],
    "wof:name":"Keiths Appliance",
    "wof:placetype":"venue"
},
  "geometry": {"coordinates":[-71.98042700000001,41.609634],"type":"Point"}
}