{
  "type": "Feature",
  "properties": {
    "iso:country":"US",
    "sg:address":"219 Old Salt Works Rd",
    "sg:city":"Westbrook",
    "sg:classifiers":[
        {
            "category":"Building & Trades",
            "subcategory":"Construction",
            "type":"Services"
        }
    ],
    "sg:phone":"+1   ",
    "sg:postcode":"06498",
    "sg:province":"CT",
    "sg:tags":[
        "maintenance",
        "contractor"
    ],
    "wof:name":"Master Blaster",
    "wof:placetype":"venue"
},
  "geometry": {"coordinates":[-72.42716799999999,41.275803],"type":"Point"}
}