{
  "type": "Feature",
  "properties": {
    "addr:full":"10 Wood Dr Enfield CT 06082",
    "addr:housenumber":"10",
    "addr:postcode":"06082",
    "addr:street":"Wood Dr",
    "iso:country":"US",
    "sg:address":"10 Wood Dr",
    "sg:city":"Enfield",
    "sg:classifiers":[
        {
            "category":"Professional",
            "subcategory":"Engineering",
            "type":"Services"
        }
    ],
    "sg:phone":"+1   ",
    "sg:postcode":"06082",
    "sg:province":"CT",
    "wof:name":"Danny Gelbar",
    "wof:placetype":"venue"
},
  "geometry": {"coordinates":[-72.561699,42.029203],"type":"Point"}
}