{
  "type": "Feature",
  "properties": {
    "addr:full":"30 Maple Ln Westport CT 06880",
    "addr:housenumber":"30",
    "addr:postcode":"06880",
    "addr:street":"Maple Ln",
    "iso:country":"US",
    "sg:address":"30 Maple Ln",
    "sg:city":"Westport",
    "sg:classifiers":[
        {
            "category":"Fast Food",
            "type":"Food & Drink"
        },
        {
            "category":"Restaurant",
            "type":"Food & Drink"
        }
    ],
    "sg:phone":"+1 203 637 8800",
    "sg:postcode":"06880",
    "sg:province":"CT",
    "sg:tags":[
        "take"
    ],
    "wof:name":"Riverside Deli",
    "wof:placetype":"venue"
},
  "geometry": {"coordinates":[-73.310807,41.122623],"type":"Point"}
}