{
  "type": "Feature",
  "properties": {
    "addr:full":"16 Cambridge Dr Madison CT 06443",
    "addr:housenumber":"16",
    "addr:postcode":"06443",
    "addr:street":"Cambridge Dr",
    "iso:country":"US",
    "sg:address":"16 Cambridge Dr",
    "sg:city":"Madison",
    "sg:classifiers":[
        {
            "category":"Professional",
            "type":"Services"
        }
    ],
    "sg:phone":"+1 203 245 5951",
    "sg:postcode":"06443",
    "sg:province":"CT",
    "wof:name":"Arthur and Myra Mahon Cha",
    "wof:placetype":"venue"
},
  "geometry": {"coordinates":[-72.597571,41.275237],"type":"Point"}
}