{
  "type": "Feature",
  "properties": {
    "addr:full":"100 Union City Rd Prospect CT 06712",
    "addr:housenumber":"100",
    "addr:postcode":"06712",
    "addr:street":"Union City Rd",
    "iso:country":"US",
    "sg:address":"100 Union City Rd",
    "sg:city":"Prospect",
    "sg:classifiers":[
        {
            "category":"Manufacturing",
            "subcategory":"Tools & Machinery",
            "type":"Manufacturing & Wholesale Goods"
        }
    ],
    "sg:phone":"+1 203 758 0784",
    "sg:postcode":"06712",
    "sg:province":"CT",
    "sg:tags":[
        "equipment",
        "system",
        "automation"
    ],
    "wof:name":"Micro Engineering & Mfg LLC",
    "wof:placetype":"venue"
},
  "geometry": {"coordinates":[-72.99745900000001,41.506196],"type":"Point"}
}