{
  "type": "Feature",
  "properties": {
    "addr:full":"70 Nichols Ter Bridgeport CT 06614",
    "addr:housenumber":"70",
    "addr:postcode":"06614",
    "addr:street":"Nichols Ter Bridgeport Ct",
    "iso:country":"US",
    "sg:address":"70 Nichols Ter",
    "sg:city":"Bridgeport",
    "sg:classifiers":[
        {
            "category":"Building & Trades",
            "subcategory":"Construction",
            "type":"Services"
        }
    ],
    "sg:phone":"+1 203 371 5003",
    "sg:postcode":"06614",
    "sg:province":"CT",
    "sg:tags":[
        "home",
        "builder"
    ],
    "wof:name":"Goncalves Development",
    "wof:placetype":"venue"
},
  "geometry": {"coordinates":[-73.14239999999999,41.205334],"type":"Point"}
}