{
  "type": "Feature",
  "properties": {
    "addr:full":"89 Kent Ave Bridgeport CT 06610",
    "addr:housenumber":"89",
    "addr:postcode":"06610",
    "addr:street":"Kent Ave",
    "iso:country":"US",
    "sg:address":"89 Kent Ave",
    "sg:city":"Bridgeport",
    "sg:classifiers":[
        {
            "category":"Education",
            "subcategory":"School",
            "type":"Public Place"
        }
    ],
    "sg:phone":"+1   ",
    "sg:postcode":"06610",
    "sg:province":"CT",
    "wof:name":"Hall Sch Parents Advsry Councl",
    "wof:placetype":"venue"
},
  "geometry": {"coordinates":[-73.15657400000001,41.191336],"type":"Point"}
}