{
  "type": "Feature",
  "properties": {
    "iso:country":"US",
    "sg:address":"1 Padanaram Rd",
    "sg:city":"Danbury",
    "sg:classifiers":[
        {
            "category":"Retail",
            "subcategory":"Laundry & Dry Cleaning",
            "type":"Services"
        }
    ],
    "sg:phone":"+1 203 790 9451",
    "sg:postcode":"06811",
    "sg:province":"CT",
    "sg:tags":[
        "cleaners"
    ],
    "wof:name":"Z-Best Cleaners",
    "wof:placetype":"venue"
},
  "geometry": {"coordinates":[-73.458736,41.413847],"type":"Point"}
}