{
  "type": "Feature",
  "properties": {
    "addr:full":"85 Lower Church Hill Rd Washington Depot CT 06794",
    "addr:housenumber":"85",
    "addr:postcode":"06794",
    "addr:street":"Lower Church Hill Rd;Depot Ct",
    "iso:country":"US",
    "sg:address":"85 Lower Church Hill Rd",
    "sg:city":"Washington Depot",
    "sg:classifiers":[
        {
            "category":"Real Estate",
            "subcategory":"Developer",
            "type":"Services"
        }
    ],
    "sg:phone":"+1 860 868 9392",
    "sg:postcode":"06794",
    "sg:province":"CT",
    "wof:name":"North Star Development Corp",
    "wof:placetype":"venue"
},
  "geometry": {"coordinates":[-73.333629,41.619866],"type":"Point"}
}