{
  "type": "Feature",
  "properties": {
    "iso:country":"US",
    "sg:address":"748 Boston Post Rd",
    "sg:city":"Darien",
    "sg:classifiers":[
        {
            "category":"Shopping",
            "subcategory":"Used Merchandise",
            "type":"Retail Goods"
        }
    ],
    "sg:phone":"+1 203 655 8406",
    "sg:postcode":"06820",
    "sg:province":"CT",
    "wof:name":"Yellow Balloon",
    "wof:placetype":"venue"
},
  "geometry": {"coordinates":[-73.46786,41.079414],"type":"Point"}
}