{
  "type": "Feature",
  "properties": {
    "addr:full":"35 Ward St Middletown CT 06457",
    "addr:housenumber":"35",
    "addr:postcode":"06457",
    "addr:street":"Ward St",
    "iso:country":"US",
    "sg:address":"35 Ward St",
    "sg:city":"Middletown",
    "sg:classifiers":[
        {
            "category":"Education",
            "subcategory":"Dance Studio",
            "type":"Public Place"
        }
    ],
    "sg:phone":"+1   ",
    "sg:postcode":"06457",
    "sg:province":"CT",
    "sg:tags":[
        "coin",
        "laundry"
    ],
    "wof:name":"Home Style Laundry",
    "wof:placetype":"venue"
},
  "geometry": {"coordinates":[-72.655547,41.540441],"type":"Point"}
}