{
  "type": "Feature",
  "properties": {
    "addr:full":"7 Lighthouse Point Ter New Haven CT 06512",
    "addr:housenumber":"7",
    "addr:postcode":"06512",
    "addr:street":"Lighthouse Point Ter;Haven",
    "iso:country":"US",
    "sg:address":"7 Lighthouse Point Ter",
    "sg:city":"New Haven",
    "sg:classifiers":[
        {
            "category":"Government",
            "subcategory":"Court House",
            "type":"Public Place"
        }
    ],
    "sg:phone":"+1 203 469 8152",
    "sg:postcode":"06512",
    "sg:province":"CT",
    "sg:tags":[
        "justice",
        "peace"
    ],
    "wof:name":"Christopher Canali",
    "wof:placetype":"venue"
},
  "geometry": {"coordinates":[-72.89136000000001,41.251958],"type":"Point"}
}