{
  "type": "Feature",
  "properties": {
    "iso:country":"US",
    "sg:address":"80 Audubon St",
    "sg:city":"New Haven",
    "sg:classifiers":[
        {
            "category":"Organizations",
            "subcategory":"Non-profit Organization",
            "type":"Services"
        }
    ],
    "sg:phone":"+1 203 562 4927",
    "sg:postcode":"06510",
    "sg:province":"CT",
    "sg:website":"www.creativeartsworkshop.org",
    "wof:name":"Creative Arts Workshop",
    "wof:placetype":"venue"
},
  "geometry": {"coordinates":[-72.92090399999999,41.311138],"type":"Point"}
}