{
  "type": "Feature",
  "properties": {
    "addr:full":"50 Grand Ave New Haven CT 06513",
    "addr:housenumber":"50",
    "addr:postcode":"06513",
    "addr:street":"Grand Ave",
    "iso:country":"US",
    "sg:address":"50 Grand Ave",
    "sg:city":"New Haven",
    "sg:classifiers":[
        {
            "category":"Real Estate",
            "subcategory":"Real Estate Operator",
            "type":"Services"
        }
    ],
    "sg:phone":"+1 203 782 6688",
    "sg:postcode":"06513",
    "sg:province":"CT",
    "sg:tags":[
        "building",
        "apartment"
    ],
    "wof:name":"River Run Apartments",
    "wof:placetype":"venue"
},
  "geometry": {"coordinates":[-72.89053699999999,41.309346],"type":"Point"}
}