{
  "type": "Feature",
  "properties": {
    "addr:full":"37 St Andrews Glastonbury CT 06033",
    "addr:housenumber":"37",
    "addr:postcode":"06033",
    "addr:street":"St Andrews",
    "iso:country":"US",
    "sg:address":"37 St Andrews",
    "sg:city":"Glastonbury",
    "sg:classifiers":[
        {
            "category":"Organizations",
            "subcategory":"Membership Organization",
            "type":"Services"
        }
    ],
    "sg:phone":"+1   ",
    "sg:postcode":"06033",
    "sg:province":"CT",
    "wof:name":"Conneticut Tamil Sangam",
    "wof:placetype":"venue"
},
  "geometry": {"coordinates":[-72.519794,41.731908],"type":"Point"}
}