{
  "type": "Feature",
  "properties": {
    "iso:country":"US",
    "sg:address":"248 Davenport St",
    "sg:city":"Bridgeport",
    "sg:classifiers":[
        {
            "category":"Arts & Performance",
            "subcategory":"Theater",
            "type":"Entertainment"
        }
    ],
    "sg:phone":"+1 203 338 0501",
    "sg:postcode":"06607",
    "sg:province":"CT",
    "sg:tags":[
        "live",
        "music"
    ],
    "wof:name":"Rock Your World DJ Entrtn",
    "wof:placetype":"venue"
},
  "geometry": {"coordinates":[-73.15907,41.180503],"type":"Point"}
}