{
  "type": "Feature",
  "properties": {
    "addr:full":"5 Washington Ave Sandy Hook CT 06482",
    "addr:housenumber":"5",
    "addr:postcode":"06482",
    "addr:street":"Washington Ave;Hook Ct",
    "iso:country":"US",
    "sg:address":"5 Washington Ave",
    "sg:city":"Sandy Hook",
    "sg:classifiers":[
        {
            "category":"Organizations",
            "subcategory":"Religious Organization",
            "type":"Services"
        }
    ],
    "sg:phone":"+1 203 426 9938",
    "sg:postcode":"06482",
    "sg:province":"CT",
    "sg:tags":[
        "church"
    ],
    "wof:name":"St John's Episcopal Church",
    "wof:placetype":"venue"
},
  "geometry": {"coordinates":[-73.28093,41.419109],"type":"Point"}
}