{
  "type": "Feature",
  "properties": {
    "iso:country":"US",
    "sg:address":"45 E Main St",
    "sg:city":"Avon",
    "sg:phone":"+1 860 677 0047",
    "sg:postcode":"06001",
    "sg:province":"CT",
    "wof:name":"Cuts For Peanuts",
    "wof:placetype":"venue"
},
  "geometry": {"coordinates":[-72.826582,41.808141],"type":"Point"}
}