{
  "type": "Feature",
  "properties": {
    "iso:country":"US",
    "sg:address":"117 Sharon Rd",
    "sg:city":"Waterbury",
    "sg:classifiers":[
        {
            "category":"Personal",
            "subcategory":"Beauty Salon",
            "type":"Services"
        }
    ],
    "sg:phone":"+1 203 596 8287",
    "sg:postcode":"06705",
    "sg:province":"CT",
    "wof:name":"Renate's Flair",
    "wof:placetype":"venue"
},
  "geometry": {"coordinates":[-73.000905,41.569353],"type":"Point"}
}