{
  "type": "Feature",
  "properties": {
    "iso:country":"US",
    "sg:address":"119 Sachem St",
    "sg:city":"Norwich",
    "sg:classifiers":[
        {
            "category":"Health Services",
            "subcategory":"Doctor",
            "type":"Services"
        }
    ],
    "sg:phone":"+1   ",
    "sg:postcode":"06360",
    "sg:province":"CT",
    "sg:tags":[
        "medical"
    ],
    "wof:name":"Internal Medicine Assoc Nor",
    "wof:placetype":"venue"
},
  "geometry": {"coordinates":[-72.089248,41.535822],"type":"Point"}
}