{
  "type": "Feature",
  "properties": {
    "addr:full":"432 Lasalle St New Britain CT 06051",
    "addr:housenumber":"432",
    "addr:postcode":"06051",
    "addr:street":"Lasalle St",
    "iso:country":"US",
    "sg:address":"432 Lasalle St",
    "sg:city":"New Britain",
    "sg:classifiers":[
        {
            "category":"Professional",
            "type":"Services"
        }
    ],
    "sg:phone":"+1 860 223 5958",
    "sg:postcode":"06051",
    "sg:province":"CT",
    "wof:name":"Internationl Education Recruit",
    "wof:placetype":"venue"
},
  "geometry": {"coordinates":[-72.770724,41.682446],"type":"Point"}
}