{
  "type": "Feature",
  "properties": {
    "addr:full":"44 Gelding Hill Rd Sandy Hook CT 06482",
    "addr:housenumber":"44",
    "addr:postcode":"06482",
    "addr:street":"Gelding Hill Rd;Hook Ct",
    "iso:country":"US",
    "sg:address":"44 Gelding Hill Rd",
    "sg:city":"Sandy Hook",
    "sg:classifiers":[
        {
            "category":"Building & Trades",
            "subcategory":"Landscaping Services",
            "type":"Services"
        }
    ],
    "sg:phone":"+1 203 270 9108",
    "sg:postcode":"06482",
    "sg:province":"CT",
    "wof:name":"Rolands Lawn Service",
    "wof:placetype":"venue"
},
  "geometry": {"coordinates":[-73.234228,41.420166],"type":"Point"}
}