{
  "type": "Feature",
  "properties": {
    "addr:full":"2251 High Ridge Rd Stamford CT 06903",
    "addr:housenumber":"2251",
    "addr:postcode":"06903",
    "addr:street":"High Ridge Rd",
    "iso:country":"US",
    "sg:address":"2251 High Ridge Rd",
    "sg:city":"Stamford",
    "sg:classifiers":[
        {
            "category":"Manufacturing",
            "subcategory":"Tools & Machinery",
            "type":"Manufacturing & Wholesale Goods"
        }
    ],
    "sg:phone":"+1 203 322 8290",
    "sg:postcode":"06903",
    "sg:province":"CT",
    "sg:tags":[
        "connector"
    ],
    "wof:name":"Surface Mount Devices Inc",
    "wof:placetype":"venue"
},
  "geometry": {"coordinates":[-73.55126199999999,41.148404],"type":"Point"}
}