{
  "type": "Feature",
  "properties": {
    "iso:country":"US",
    "sg:address":"13 Salem Rd",
    "sg:city":"Woodbridge",
    "sg:classifiers":[
        {
            "category":"Wholesale",
            "subcategory":"Machinery & Supplies",
            "type":"Manufacturing & Wholesale Goods"
        }
    ],
    "sg:phone":"+1 203 389 8750",
    "sg:postcode":"06525",
    "sg:province":"CT",
    "sg:tags":[
        "machine",
        "tool"
    ],
    "wof:name":"St Arrag Heckert Inc",
    "wof:placetype":"venue"
},
  "geometry": {"coordinates":[-73.00784299999999,41.325511],"type":"Point"}
}