{
  "type": "Feature",
  "properties": {
    "iso:country":"US",
    "sg:address":"10 Old Village Rd",
    "sg:city":"Bloomfield",
    "sg:classifiers":[
        {
            "category":"Organizations",
            "subcategory":"Religious Organization",
            "type":"Services"
        }
    ],
    "sg:phone":"+1   ",
    "sg:postcode":"06002",
    "sg:province":"CT",
    "wof:name":"James G Hicks Rev",
    "wof:placetype":"venue"
},
  "geometry": {"coordinates":[-72.727932,41.839454],"type":"Point"}
}