{
  "type": "Feature",
  "properties": {
    "iso:country":"US",
    "sg:address":"4 Research Dr",
    "sg:city":"Shelton",
    "sg:classifiers":[
        {
            "category":"Real Estate",
            "subcategory":"Real Estate Agent",
            "type":"Services"
        }
    ],
    "sg:phone":"+1 203 225 0333",
    "sg:postcode":"06484",
    "sg:province":"CT",
    "sg:tags":[
        "relocation"
    ],
    "sg:website":"www.reloaction.com",
    "wof:name":"Hewitt Associates",
    "wof:placetype":"venue"
},
  "geometry": {"coordinates":[-73.134812,41.274348],"type":"Point"}
}