{
  "type": "Feature",
  "properties": {
    "iso:country":"US",
    "sg:address":"112 Whitman Ave",
    "sg:city":"Hartford",
    "sg:classifiers":[
        {
            "category":"Building & Trades",
            "subcategory":"Construction",
            "type":"Services"
        }
    ],
    "sg:phone":"+1 860 521 3681",
    "sg:postcode":"06107",
    "sg:province":"CT",
    "sg:tags":[
        "house"
    ],
    "wof:name":"Whitman Renovation Design LLC",
    "wof:placetype":"venue"
},
  "geometry": {"coordinates":[-72.74749,41.764849],"type":"Point"}
}