{
  "type": "Feature",
  "properties": {
    "iso:country":"US",
    "sg:address":"114 Main St",
    "sg:city":"Hampton",
    "sg:classifiers":[
        {
            "category":"Building & Trades",
            "subcategory":"Landscaping Services",
            "type":"Services"
        }
    ],
    "sg:phone":"+1 860 455 9979",
    "sg:postcode":"06247",
    "sg:province":"CT",
    "sg:tags":[
        "landscape"
    ],
    "wof:name":"Anne Christie Landscape Design",
    "wof:placetype":"venue"
},
  "geometry": {"coordinates":[-72.05496100000001,41.783204],"type":"Point"}
}