{
  "type": "Feature",
  "properties": {
    "addr:full":"40 Main St Bethel CT 06801",
    "addr:housenumber":"40",
    "addr:postcode":"06801",
    "addr:street":"Main St Bethel Ct",
    "iso:country":"US",
    "sg:address":"40 Main St",
    "sg:city":"Bethel",
    "sg:classifiers":[
        {
            "category":"Organizations",
            "subcategory":"Community Association",
            "type":"Services"
        }
    ],
    "sg:phone":"+1   ",
    "sg:postcode":"06801",
    "sg:province":"CT",
    "wof:name":"Bethel VFW Post 935",
    "wof:placetype":"venue"
},
  "geometry": {"coordinates":[-73.40841399999999,41.372942],"type":"Point"}
}