{
  "type": "Feature",
  "properties": {
    "addr:full":"1595 Baldwin St Waterbury CT 06706",
    "addr:housenumber":"1595",
    "addr:postcode":"06706",
    "addr:street":"Baldwin St Waterbury Ct",
    "iso:country":"US",
    "sg:address":"1595 Baldwin St",
    "sg:city":"Waterbury",
    "sg:classifiers":[
        {
            "category":"Restaurant",
            "type":"Food & Drink"
        }
    ],
    "sg:phone":"+1 203 575 9051",
    "sg:postcode":"06706",
    "sg:province":"CT",
    "sg:tags":[
        "delicatessen"
    ],
    "wof:name":"Ann's Deli",
    "wof:placetype":"venue"
},
  "geometry": {"coordinates":[-73.03660600000001,41.530885],"type":"Point"}
}