{
  "type": "Feature",
  "properties": {
    "addr:full":"55 N Reeves Ave Guilford CT 06437",
    "addr:housenumber":"55",
    "addr:postcode":"06437",
    "addr:street":"N Reeves Ave",
    "iso:country":"US",
    "sg:address":"55 N Reeves Ave",
    "sg:city":"Guilford",
    "sg:classifiers":[
        {
            "category":"Wholesale",
            "subcategory":"Apparel",
            "type":"Manufacturing & Wholesale Goods"
        }
    ],
    "sg:phone":"+1 203 453 4605",
    "sg:postcode":"06437",
    "sg:province":"CT",
    "sg:tags":[
        "piece"
    ],
    "wof:name":"New England Threads Inc",
    "wof:placetype":"venue"
},
  "geometry": {"coordinates":[-72.68657399999999,41.25765],"type":"Point"}
}