{
  "type": "Feature",
  "properties": {
    "addr:full":"172 Andrews Rd Wolcott CT 06716",
    "addr:housenumber":"172",
    "addr:postcode":"06716",
    "addr:street":"Andrews Rd Wolcott Ct",
    "iso:country":"US",
    "sg:address":"172 Andrews Rd",
    "sg:city":"Wolcott",
    "sg:classifiers":[
        {
            "category":"Real Estate",
            "subcategory":"Real Estate Agent",
            "type":"Services"
        }
    ],
    "sg:phone":"+1 203 879 1201",
    "sg:postcode":"06716",
    "sg:province":"CT",
    "wof:name":"C & G Partnership",
    "wof:placetype":"venue"
},
  "geometry": {"coordinates":[-73.01127,41.623719],"type":"Point"}
}