{
  "type": "Feature",
  "properties": {
    "iso:country":"US",
    "sg:address":"88 Howard St",
    "sg:city":"New London",
    "sg:classifiers":[
        {
            "category":"Real Estate",
            "subcategory":"Developer",
            "type":"Services"
        }
    ],
    "sg:phone":"+1 860 447 8055",
    "sg:postcode":"06320",
    "sg:province":"CT",
    "wof:name":"Eastern Conn Hsing Opprtunitie",
    "wof:placetype":"venue"
},
  "geometry": {"coordinates":[-72.101248,41.348062],"type":"Point"}
}