{
  "type": "Feature",
  "properties": {
    "addr:full":"20 Village Ln Harwinton CT 06791",
    "addr:housenumber":"20",
    "addr:postcode":"06791",
    "addr:street":"Village Ln Harwinton Ct",
    "iso:country":"US",
    "sg:address":"20 Village Ln",
    "sg:city":"Harwinton",
    "sg:classifiers":[
        {
            "category":"Building & Trades",
            "subcategory":"Plumbing",
            "type":"Services"
        }
    ],
    "sg:phone":"+1 860 485 1885",
    "sg:postcode":"06791",
    "sg:province":"CT",
    "sg:tags":[
        "air",
        "heating",
        "conditioning",
        "contractor"
    ],
    "wof:name":"Barry S Patterson",
    "wof:placetype":"venue"
},
  "geometry": {"coordinates":[-73.056656,41.766783],"type":"Point"}
}