{
  "type": "Feature",
  "properties": {
    "iso:country":"US",
    "sg:address":"927 Park Ave",
    "sg:city":"Bridgeport",
    "sg:classifiers":[
        {
            "category":"Autos & Motor Vehicles",
            "subcategory":"Fuel & Gas Station",
            "type":"Retail Goods"
        }
    ],
    "sg:phone":"+1 203 368 3117",
    "sg:postcode":"06604",
    "sg:province":"CT",
    "sg:tags":[
        "station",
        "gasoline"
    ],
    "wof:name":"Maham Service Station",
    "wof:placetype":"venue"
},
  "geometry": {"coordinates":[-73.19832700000001,41.174421],"type":"Point"}
}