{
  "type": "Feature",
  "properties": {
    "addr:full":"500 Main St East Hartford CT 06118",
    "addr:housenumber":"500",
    "addr:postcode":"06118",
    "addr:street":"Main St",
    "iso:country":"US",
    "sg:address":"500 Main St",
    "sg:city":"East Hartford",
    "sg:classifiers":[
        {
            "category":"Professional",
            "subcategory":"Lawyer & Legal Services",
            "type":"Services"
        }
    ],
    "sg:phone":"+1   ",
    "sg:postcode":"06118",
    "sg:province":"CT",
    "wof:name":"Krzys Robert J Attorney At Law",
    "wof:placetype":"venue"
},
  "geometry": {"coordinates":[-72.64294599999999,41.756672],"type":"Point"}
}