{
  "type": "Feature",
  "properties": {
    "iso:country":"US",
    "sg:address":"28 Nod Rd",
    "sg:city":"Ridgefield",
    "sg:classifiers":[
        {
            "category":"Professional",
            "subcategory":"Business Services",
            "type":"Services"
        }
    ],
    "sg:phone":"+1   ",
    "sg:postcode":"06877",
    "sg:province":"CT",
    "wof:name":"Olga Adler Interiors LLC",
    "wof:placetype":"venue"
},
  "geometry": {"coordinates":[-73.472014,41.252327],"type":"Point"}
}