{
  "type": "Feature",
  "properties": {
    "addr:full":"11 E Main St Canaan CT 06018",
    "addr:housenumber":"11",
    "addr:postcode":"06018",
    "addr:street":"E Main St",
    "iso:country":"US",
    "sg:address":"11 E Main St",
    "sg:city":"Canaan",
    "sg:classifiers":[
        {
            "category":"Shopping",
            "subcategory":"Department Store",
            "type":"Retail Goods"
        }
    ],
    "sg:phone":"+1 860 824 7556",
    "sg:postcode":"06018",
    "sg:province":"CT",
    "sg:tags":[
        "variety"
    ],
    "sg:website":"http://www.familydollar.com",
    "wof:name":"Family Dollar",
    "wof:placetype":"venue"
},
  "geometry": {"coordinates":[-73.322503,42.023884],"type":"Point"}
}