{
  "type": "Feature",
  "properties": {
    "addr:full":"120 Cliff St Norwich CT 06360",
    "addr:housenumber":"120",
    "addr:postcode":"06360",
    "addr:street":"Cliff St",
    "iso:country":"US",
    "sg:address":"120 Cliff St",
    "sg:city":"Norwich",
    "sg:classifiers":[
        {
            "category":"Education",
            "subcategory":"School",
            "type":"Public Place"
        }
    ],
    "sg:phone":"+1   ",
    "sg:postcode":"06360",
    "sg:province":"CT",
    "sg:tags":[
        "organization",
        "religious"
    ],
    "wof:name":"Saint Josephs Parish Center",
    "wof:placetype":"venue"
},
  "geometry": {"coordinates":[-72.066892,41.527556],"type":"Point"}
}