{
  "type": "Feature",
  "properties": {
    "addr:full":"2480 Whitney Ave Hamden CT 06518",
    "addr:housenumber":"2480",
    "addr:postcode":"06518",
    "addr:street":"Whitney Ave",
    "iso:country":"US",
    "sg:address":"2480 Whitney Ave",
    "sg:city":"Hamden",
    "sg:classifiers":[
        {
            "category":"Personal",
            "type":"Services"
        }
    ],
    "sg:phone":"+1   ",
    "sg:postcode":"06518",
    "sg:province":"CT",
    "wof:name":"Todd Gutheil",
    "wof:placetype":"venue"
},
  "geometry": {"coordinates":[-72.900367,41.38792],"type":"Point"}
}