{
  "type": "Feature",
  "properties": {
    "iso:country":"US",
    "sg:address":"5 Hodio Dr",
    "sg:city":"Ansonia",
    "sg:classifiers":[
        {
            "category":"Building & Trades",
            "subcategory":"Construction",
            "type":"Services"
        }
    ],
    "sg:phone":"+1   ",
    "sg:postcode":"06401",
    "sg:province":"CT",
    "sg:tags":[
        "hanging",
        "business",
        "contractor"
    ],
    "wof:name":"Alex Diakoumis Intr & Exterior",
    "wof:placetype":"venue"
},
  "geometry": {"coordinates":[-73.05752,41.346598],"type":"Point"}
}