{
  "type": "Feature",
  "properties": {
    "iso:country":"US",
    "sg:address":"13 Winthrop Rd",
    "sg:city":"Bethel",
    "sg:classifiers":[
        {
            "category":"Professional",
            "subcategory":"Management & Consulting",
            "type":"Services"
        }
    ],
    "sg:phone":"+1   ",
    "sg:postcode":"06801",
    "sg:province":"CT",
    "sg:tags":[
        "public",
        "relations"
    ],
    "wof:name":"Consumer Contact Company",
    "wof:placetype":"venue"
},
  "geometry": {"coordinates":[-73.396812,41.367557],"type":"Point"}
}