{
  "type": "Feature",
  "properties": {
    "addr:full":"340 Quinnipiac St Wallingford CT 06492",
    "addr:housenumber":"340",
    "addr:postcode":"06492",
    "addr:street":"Quinnipiac St",
    "iso:country":"US",
    "sg:address":"340 Quinnipiac St",
    "sg:city":"Wallingford",
    "sg:classifiers":[
        {
            "category":"Building & Trades",
            "subcategory":"Construction",
            "type":"Services"
        }
    ],
    "sg:phone":"+1 203 265 4744",
    "sg:postcode":"06492",
    "sg:province":"CT",
    "sg:tags":[
        "home",
        "improvement"
    ],
    "wof:name":"ABR Construction Inc",
    "wof:placetype":"venue"
},
  "geometry": {"coordinates":[-72.835679,41.457973],"type":"Point"}
}