{
  "type": "Feature",
  "properties": {
    "iso:country":"US",
    "sg:address":"808 S Main St",
    "sg:city":"Seymour",
    "sg:classifiers":[
        {
            "category":"Freight",
            "type":"Transportation"
        }
    ],
    "sg:phone":"+1 203 888 8810",
    "sg:postcode":"06483",
    "sg:province":"CT",
    "sg:tags":[
        "general"
    ],
    "wof:name":"A Space Center",
    "wof:placetype":"venue"
},
  "geometry": {"coordinates":[-73.082987,41.365873],"type":"Point"}
}