{
  "type": "Feature",
  "properties": {
    "addr:full":"675 State St New Haven CT 06511",
    "addr:housenumber":"675",
    "addr:postcode":"06511",
    "addr:street":"State St",
    "iso:country":"US",
    "sg:address":"675 State St",
    "sg:city":"New Haven",
    "sg:classifiers":[
        {
            "category":"Government",
            "subcategory":"Office",
            "type":"Public Place"
        }
    ],
    "sg:phone":"+1 203 946 6072",
    "sg:postcode":"06511",
    "sg:province":"CT",
    "sg:tags":[
        "justice",
        "criminal",
        "statistics",
        "center"
    ],
    "wof:name":"South Central Criminal Justice",
    "wof:placetype":"venue"
},
  "geometry": {"coordinates":[-72.91793,41.310169],"type":"Point"}
}