{
  "type": "Feature",
  "properties": {
    "addr:full":"12 Mills St Norwalk CT 06850",
    "addr:housenumber":"12",
    "addr:postcode":"06850",
    "addr:street":"Mills St",
    "iso:country":"US",
    "sg:address":"12 Mills St",
    "sg:city":"Norwalk",
    "sg:classifiers":[
        {
            "category":"Wholesale",
            "subcategory":"Furniture",
            "type":"Manufacturing & Wholesale Goods"
        }
    ],
    "sg:phone":"+1 203 846 6550",
    "sg:postcode":"06850",
    "sg:province":"CT",
    "wof:name":"Artech Church Interiors",
    "wof:placetype":"venue"
},
  "geometry": {"coordinates":[-73.43513400000001,41.130275],"type":"Point"}
}