{
  "type": "Feature",
  "properties": {
    "iso:country":"US",
    "sg:address":"777 Long Ridge Rd",
    "sg:city":"Stamford",
    "sg:classifiers":[
        {
            "category":"Professional",
            "subcategory":"Management & Consulting",
            "type":"Services"
        }
    ],
    "sg:phone":"+1 203 614 2089",
    "sg:postcode":"06902",
    "sg:province":"CT",
    "sg:tags":[
        "consultant",
        "business"
    ],
    "wof:name":"Osiris Management",
    "wof:placetype":"venue"
},
  "geometry": {"coordinates":[-73.564168,41.097014],"type":"Point"}
}