{
  "type": "Feature",
  "properties": {
    "iso:country":"US",
    "sg:address":"283 Huntington St",
    "sg:city":"Shelton",
    "sg:classifiers":[
        {
            "category":"Professional",
            "subcategory":"Management & Consulting",
            "type":"Services"
        }
    ],
    "sg:phone":"+1   ",
    "sg:postcode":"06484",
    "sg:province":"CT",
    "wof:name":"Sns Assoc",
    "wof:placetype":"venue"
},
  "geometry": {"coordinates":[-73.138533,41.283199],"type":"Point"}
}