{
  "type": "Feature",
  "properties": {
    "iso:country":"US",
    "sg:address":"206 Sharp Hill Rd",
    "sg:city":"Wilton",
    "sg:classifiers":[
        {
            "category":"Professional",
            "type":"Services"
        }
    ],
    "sg:phone":"+1   ",
    "sg:postcode":"06897",
    "sg:province":"CT",
    "wof:name":"Tim Geaney Photography In",
    "wof:placetype":"venue"
},
  "geometry": {"coordinates":[-73.408832,41.198881],"type":"Point"}
}