{
  "type": "Feature",
  "properties": {
    "addr:full":"2 Anderson Rd E Sherman CT 06784",
    "addr:housenumber":"2",
    "addr:postcode":"06784",
    "addr:street":"Anderson Rd E Sherman Ct",
    "iso:country":"US",
    "sg:address":"2 Anderson Rd E",
    "sg:city":"Sherman",
    "sg:classifiers":[
        {
            "category":"Professional",
            "subcategory":"Management & Consulting",
            "type":"Services"
        }
    ],
    "sg:phone":"+1   ",
    "sg:postcode":"06784",
    "sg:province":"CT",
    "sg:tags":[
        "business"
    ],
    "wof:name":"Change Tech International",
    "wof:placetype":"venue"
},
  "geometry": {"coordinates":[-73.51687,41.639721],"type":"Point"}
}