{
  "type": "Feature",
  "properties": {
    "addr:full":"78 Main St Newtown CT 06470",
    "addr:housenumber":"78",
    "addr:postcode":"06470",
    "addr:street":"Main St",
    "iso:country":"US",
    "sg:address":"78 Main St",
    "sg:city":"Newtown",
    "sg:classifiers":[
        {
            "category":"Building & Trades",
            "subcategory":"Construction",
            "type":"Services"
        }
    ],
    "sg:phone":"+1 203 364 9229",
    "sg:postcode":"06470",
    "sg:province":"CT",
    "sg:tags":[
        "contractor"
    ],
    "wof:name":"Bryant Builders LLC",
    "wof:placetype":"venue"
},
  "geometry": {"coordinates":[-73.311909,41.417438],"type":"Point"}
}