{
  "type": "Feature",
  "properties": {
    "iso:country":"US",
    "sg:address":"181 Blue Ridge Dr",
    "sg:city":"Vernon Rockville",
    "sg:classifiers":[
        {
            "category":"Professional",
            "subcategory":"Management & Consulting",
            "type":"Services"
        }
    ],
    "sg:phone":"+1   ",
    "sg:postcode":"06066",
    "sg:province":"CT",
    "wof:name":"Claim Management Services LLC",
    "wof:placetype":"venue"
},
  "geometry": {"coordinates":[-72.46437299999999,41.822259],"type":"Point"}
}