{
  "type": "Feature",
  "properties": {
    "addr:full":"136 Chapel St New Haven CT 06513",
    "addr:housenumber":"136",
    "addr:postcode":"06513",
    "addr:street":"Chapel St",
    "iso:country":"US",
    "sg:address":"136 Chapel St",
    "sg:city":"New Haven",
    "sg:classifiers":[
        {
            "category":"Restaurant",
            "type":"Food & Drink"
        }
    ],
    "sg:phone":"+1 203 562 1330",
    "sg:postcode":"06513",
    "sg:province":"CT",
    "wof:name":"El Caribe Restaurants Inc",
    "wof:placetype":"venue"
},
  "geometry": {"coordinates":[-72.89764700000001,41.304006],"type":"Point"}
}