{
  "type": "Feature",
  "properties": {
    "iso:country":"US",
    "sg:address":"114 S Main St",
    "sg:city":"Cheshire",
    "sg:classifiers":[
        {
            "category":"Wholesale",
            "subcategory":"Hardware",
            "type":"Manufacturing & Wholesale Goods"
        }
    ],
    "sg:phone":"+1 203 271 2222",
    "sg:postcode":"06410",
    "sg:province":"CT",
    "sg:tags":[
        "refrigerating"
    ],
    "wof:name":"Reliable Refrigeration",
    "wof:placetype":"venue"
},
  "geometry": {"coordinates":[-72.902208,41.497243],"type":"Point"}
}