{
  "type": "Feature",
  "properties": {
    "addr:full":"10 Bayberry Dr Brookfield CT 06804",
    "addr:housenumber":"10",
    "addr:postcode":"06804",
    "addr:street":"Bayberry Dr",
    "iso:country":"US",
    "sg:address":"10 Bayberry Dr",
    "sg:city":"Brookfield",
    "sg:classifiers":[
        {
            "category":"Professional",
            "type":"Services"
        }
    ],
    "sg:phone":"+1 203 740 2542",
    "sg:postcode":"06804",
    "sg:province":"CT",
    "sg:tags":[
        "establishment"
    ],
    "sg:website":"www.greatbuys.com",
    "wof:name":"GREATBUYS.COM",
    "wof:placetype":"venue"
},
  "geometry": {"coordinates":[-73.424082,41.471181],"type":"Point"}
}