{
  "type": "Feature",
  "properties": {
    "addr:full":"456 Glenbrook Rd Stamford CT 06906",
    "addr:housenumber":"456",
    "addr:postcode":"06906",
    "addr:street":"Glenbrook Rd",
    "iso:country":"US",
    "sg:address":"456 Glenbrook Rd",
    "sg:city":"Stamford",
    "sg:classifiers":[
        {
            "category":"Manufacturing",
            "subcategory":"Electronics",
            "type":"Manufacturing & Wholesale Goods"
        }
    ],
    "sg:phone":"+1 203 964 8360",
    "sg:postcode":"06906",
    "sg:province":"CT",
    "sg:tags":[
        "equipment",
        "mfg",
        "communications"
    ],
    "wof:name":"F-P Displays",
    "wof:placetype":"venue"
},
  "geometry": {"coordinates":[-73.52035100000001,41.069699],"type":"Point"}
}