{
  "type": "Feature",
  "properties": {
    "iso:country":"US",
    "sg:address":"136 Colebrook Rd",
    "sg:city":"Norfolk",
    "sg:classifiers":[
        {
            "category":"Building & Trades",
            "subcategory":"Construction",
            "type":"Services"
        }
    ],
    "sg:phone":"+1 860 542 6860",
    "sg:postcode":"06058",
    "sg:province":"CT",
    "sg:tags":[
        "contractor"
    ],
    "wof:name":"Stonecraft Ne Inc",
    "wof:placetype":"venue"
},
  "geometry": {"coordinates":[-73.143505,41.988582],"type":"Point"}
}