{
  "type": "Feature",
  "properties": {
    "addr:full":"6 Keene Rd Westport CT 06880",
    "addr:housenumber":"6",
    "addr:postcode":"06880",
    "addr:street":"Keene Rd",
    "iso:country":"US",
    "sg:address":"6 Keene Rd",
    "sg:city":"Westport",
    "sg:classifiers":[
        {
            "category":"Professional",
            "subcategory":"Management & Consulting",
            "type":"Services"
        }
    ],
    "sg:phone":"+1   ",
    "sg:postcode":"06880",
    "sg:province":"CT",
    "sg:tags":[
        "business"
    ],
    "wof:name":"R D Consultants Inc",
    "wof:placetype":"venue"
},
  "geometry": {"coordinates":[-73.32897699999999,41.141756],"type":"Point"}
}