{
  "type": "Feature",
  "properties": {
    "addr:full":"906 Whalley Ave New Haven CT 06515",
    "addr:housenumber":"906",
    "addr:postcode":"06515",
    "addr:street":"Whalley Ave",
    "iso:country":"US",
    "sg:address":"906 Whalley Ave",
    "sg:city":"New Haven",
    "sg:classifiers":[
        {
            "category":"Personal",
            "subcategory":"Beauty Salon",
            "type":"Services"
        }
    ],
    "sg:phone":"+1 203 397 2860",
    "sg:postcode":"06515",
    "sg:province":"CT",
    "sg:tags":[
        "shop"
    ],
    "wof:name":"Village Hair Design LLC",
    "wof:placetype":"venue"
},
  "geometry": {"coordinates":[-72.959908,41.326768],"type":"Point"}
}