{
  "type": "Feature",
  "properties": {
    "addr:full":"6 Tipping Dr Branford CT 06405",
    "addr:housenumber":"6",
    "addr:postcode":"06405",
    "addr:street":"Tipping Dr",
    "iso:country":"US",
    "sg:address":"6 Tipping Dr",
    "sg:city":"Branford",
    "sg:classifiers":[
        {
            "category":"Manufacturing",
            "subcategory":"Printing",
            "type":"Manufacturing & Wholesale Goods"
        }
    ],
    "sg:phone":"+1 203 488 0429",
    "sg:postcode":"06405",
    "sg:province":"CT",
    "sg:tags":[
        "printer"
    ],
    "wof:name":"S K Graphics",
    "wof:placetype":"venue"
},
  "geometry": {"coordinates":[-72.768028,41.303686],"type":"Point"}
}