{
  "type": "Feature",
  "properties": {
    "addr:full":"258 Boston Post Rd Milford CT 06460",
    "addr:housenumber":"258",
    "addr:postcode":"06460",
    "addr:street":"Boston Post Rd",
    "iso:country":"US",
    "sg:address":"258 Boston Post Rd",
    "sg:city":"Milford",
    "sg:classifiers":[
        {
            "category":"Shopping",
            "type":"Retail Goods"
        }
    ],
    "sg:phone":"+1 203 877 2776",
    "sg:postcode":"06460",
    "sg:province":"CT",
    "sg:tags":[
        "plant",
        "flower",
        "tree",
        "artificial"
    ],
    "sg:website":"www.gloriasgardencenter.com",
    "wof:name":"Gloria's Garden Ctr",
    "wof:placetype":"venue"
},
  "geometry": {"coordinates":[-73.072968,41.222464],"type":"Point"}
}