{
  "type": "Feature",
  "properties": {
    "iso:country":"US",
    "sg:address":"257 Walnut Tree Hill Rd",
    "sg:city":"Shelton",
    "sg:classifiers":[
        {
            "category":"Professional",
            "subcategory":"Engineering",
            "type":"Services"
        }
    ],
    "sg:phone":"+1   ",
    "sg:postcode":"06484",
    "sg:province":"CT",
    "wof:name":"James Hummel",
    "wof:placetype":"venue"
},
  "geometry": {"coordinates":[-73.166314,41.305894],"type":"Point"}
}