{
  "type": "Feature",
  "properties": {
    "addr:full":"370 High St New Britain CT 06051",
    "addr:housenumber":"370",
    "addr:postcode":"06051",
    "addr:street":"High St",
    "iso:country":"US",
    "sg:address":"370 High St",
    "sg:city":"New Britain",
    "sg:classifiers":[
        {
            "category":"Real Estate",
            "subcategory":"Real Estate Operator",
            "type":"Services"
        }
    ],
    "sg:phone":"+1 860 224 6823",
    "sg:postcode":"06051",
    "sg:province":"CT",
    "sg:tags":[
        "building",
        "apartment"
    ],
    "wof:name":"Washington School Apts",
    "wof:placetype":"venue"
},
  "geometry": {"coordinates":[-72.788353,41.678794],"type":"Point"}
}