{
  "type": "Feature",
  "properties": {
    "iso:country":"US",
    "sg:address":"760 Queen St",
    "sg:city":"Southington",
    "sg:classifiers":[
        {
            "category":"Shopping",
            "subcategory":"Pets & Pet Supplies",
            "type":"Retail Goods"
        },
        {
            "category":"Retail",
            "subcategory":"Animal Services",
            "type":"Services"
        },
        {
            "category":"Museum",
            "subcategory":"Aquarium",
            "type":"Entertainment"
        }
    ],
    "sg:phone":"+1 860 620 6667",
    "sg:postcode":"06489",
    "sg:province":"CT",
    "sg:tags":[
        "food",
        "dog",
        "cat",
        "furnishing",
        "grooming",
        "store"
    ],
    "sg:website":"http://www.petco.com",
    "wof:name":"PETCO",
    "wof:placetype":"venue"
},
  "geometry": {"coordinates":[-72.873768,41.636814],"type":"Point"}
}