{
  "type": "Feature",
  "properties": {
    "addr:full":"2 Butternut Dr Bloomfield CT 06002",
    "addr:housenumber":"2",
    "addr:postcode":"06002",
    "addr:street":"Butternut Dr Bloomfield Ct",
    "iso:country":"US",
    "sg:address":"2 Butternut Dr",
    "sg:city":"Bloomfield",
    "sg:classifiers":[
        {
            "category":"Professional",
            "subcategory":"Engineering",
            "type":"Services"
        }
    ],
    "sg:phone":"+1   ",
    "sg:postcode":"06002",
    "sg:province":"CT",
    "wof:name":"Barry J Berson",
    "wof:placetype":"venue"
},
  "geometry": {"coordinates":[-72.76329699999999,41.85141],"type":"Point"}
}