{
  "type": "Feature",
  "properties": {
    "iso:country":"US",
    "sg:address":"725 New Britain Ave",
    "sg:city":"Newington",
    "sg:classifiers":[
        {
            "category":"Retail",
            "subcategory":"Veterinary Services",
            "type":"Services"
        }
    ],
    "sg:phone":"+1 860 665 1314",
    "sg:postcode":"06111",
    "sg:province":"CT",
    "wof:name":"Twin City Animal Hospital",
    "wof:placetype":"venue"
},
  "geometry": {"coordinates":[-72.752987,41.672309],"type":"Point"}
}