{
  "type": "Feature",
  "properties": {
    "addr:full":"21 Kings Hwy Chester CT 06412",
    "addr:housenumber":"21",
    "addr:postcode":"06412",
    "addr:street":"Kings Hwy",
    "iso:country":"US",
    "sg:address":"21 Kings Hwy",
    "sg:city":"Chester",
    "sg:classifiers":[
        {
            "category":"Building & Trades",
            "subcategory":"Cleaning & Sanitation",
            "type":"Services"
        }
    ],
    "sg:phone":"+1   ",
    "sg:postcode":"06412",
    "sg:province":"CT",
    "sg:tags":[
        "maintenance"
    ],
    "wof:name":"All American Chimney Sweep",
    "wof:placetype":"venue"
},
  "geometry": {"coordinates":[-72.446714,41.41449],"type":"Point"}
}