{
  "type": "Feature",
  "properties": {
    "iso:country":"US",
    "sg:address":"108 Steep Hill Rd",
    "sg:city":"Weston",
    "sg:classifiers":[
        {
            "category":"Wholesale",
            "subcategory":"Apparel",
            "type":"Manufacturing & Wholesale Goods"
        }
    ],
    "sg:phone":"+1 203 227 1150",
    "sg:postcode":"06883",
    "sg:province":"CT",
    "sg:tags":[
        "piece"
    ],
    "wof:name":"S F Joyce Assoc Inc",
    "wof:placetype":"venue"
},
  "geometry": {"coordinates":[-73.359841,41.217149],"type":"Point"}
}