{
  "type": "Feature",
  "properties": {
    "addr:full":"110 Old Easton Tpke Weston CT 06883",
    "addr:housenumber":"110",
    "addr:postcode":"06883",
    "addr:street":"Old Easton Tpke",
    "iso:country":"US",
    "sg:address":"110 Old Easton Tpke",
    "sg:city":"Weston",
    "sg:classifiers":[
        {
            "category":"Restaurant",
            "type":"Food & Drink"
        }
    ],
    "sg:phone":"+1 203 221 0024",
    "sg:postcode":"06883",
    "sg:province":"CT",
    "sg:tags":[
        "house",
        "steak"
    ],
    "wof:name":"Porterhouse Restaurant",
    "wof:placetype":"venue"
},
  "geometry": {"coordinates":[-73.331062,41.213453],"type":"Point"}
}