{
  "type": "Feature",
  "properties": {
    "addr:full":"3622 Main St Bridgeport CT 06606",
    "addr:housenumber":"3622",
    "addr:postcode":"06606",
    "addr:street":"Main St",
    "iso:country":"US",
    "sg:address":"3622 Main St",
    "sg:city":"Bridgeport",
    "sg:classifiers":[
        {
            "category":"Retail",
            "subcategory":"Portrait Studio",
            "type":"Services"
        }
    ],
    "sg:phone":"+1 203 374 9119",
    "sg:postcode":"06606",
    "sg:province":"CT",
    "sg:tags":[
        "photographer",
        "photo"
    ],
    "wof:name":"Benedettos Photo Studio",
    "wof:placetype":"venue"
},
  "geometry": {"coordinates":[-73.20898099999999,41.210231],"type":"Point"}
}