{
  "type": "Feature",
  "properties": {
    "iso:country":"US",
    "sg:address":"71 Catlin St",
    "sg:city":"Meriden",
    "sg:classifiers":[
        {
            "category":"Social Services",
            "type":"Services"
        }
    ],
    "sg:phone":"+1 203 238 0071",
    "sg:postcode":"06450",
    "sg:province":"CT",
    "sg:tags":[
        "organization",
        "welfare"
    ],
    "wof:name":"Carabetta Management Director",
    "wof:placetype":"venue"
},
  "geometry": {"coordinates":[-72.79717100000001,41.538847],"type":"Point"}
}