{
  "type": "Feature",
  "properties": {
    "addr:full":"597 Campbell Ave West Haven CT 06516",
    "addr:housenumber":"597",
    "addr:postcode":"06516",
    "addr:street":"Campbell Ave",
    "iso:country":"US",
    "sg:address":"597 Campbell Ave",
    "sg:city":"West Haven",
    "sg:classifiers":[
        {
            "category":"Banks & Credit Unions",
            "subcategory":"Bank",
            "type":"Services"
        }
    ],
    "sg:phone":"+1 203 934 7953",
    "sg:postcode":"06516",
    "sg:province":"CT",
    "sg:tags":[
        "savings",
        "institution"
    ],
    "wof:name":"Wachovia Bank National Assn",
    "wof:placetype":"venue"
},
  "geometry": {"coordinates":[-72.95081399999999,41.273656],"type":"Point"}
}