{
  "type": "Feature",
  "properties": {
    "iso:country":"US",
    "sg:address":"10 Aspen Dr",
    "sg:city":"Madison",
    "sg:classifiers":[
        {
            "category":"Professional",
            "type":"Services"
        }
    ],
    "sg:phone":"+1 203 421 3286",
    "sg:postcode":"06443",
    "sg:province":"CT",
    "wof:name":"215 Elm Street LLC",
    "wof:placetype":"venue"
},
  "geometry": {"coordinates":[-72.63648000000001,41.367697],"type":"Point"}
}