{
  "type": "Feature",
  "properties": {
    "addr:full":"361 Shore Rd Greenwich CT 06830",
    "addr:housenumber":"361",
    "addr:postcode":"06830",
    "addr:street":"Shore Rd",
    "iso:country":"US",
    "sg:address":"361 Shore Rd",
    "sg:city":"Greenwich",
    "sg:classifiers":[
        {
            "category":"Professional",
            "type":"Services"
        }
    ],
    "sg:phone":"+1 203 661 2559",
    "sg:postcode":"06830",
    "sg:province":"CT",
    "sg:tags":[
        "establishment"
    ],
    "wof:name":"CBP Co",
    "wof:placetype":"venue"
},
  "geometry": {"coordinates":[-73.63220699999999,41.012357],"type":"Point"}
}