{
  "type": "Feature",
  "properties": {
    "addr:full":"58 Laurel Dr Easton CT 06612",
    "addr:housenumber":"58",
    "addr:postcode":"06612",
    "addr:street":"Laurel Dr",
    "iso:country":"US",
    "sg:address":"58 Laurel Dr",
    "sg:city":"Easton",
    "sg:classifiers":[
        {
            "category":"Professional",
            "subcategory":"Business Services",
            "type":"Services"
        }
    ],
    "sg:phone":"+1   ",
    "sg:postcode":"06612",
    "sg:province":"CT",
    "wof:name":"Gary M Mendell",
    "wof:placetype":"venue"
},
  "geometry": {"coordinates":[-73.27848,41.236083],"type":"Point"}
}