{
  "type": "Feature",
  "properties": {
    "iso:country":"US",
    "sg:address":"225 King Philip Dr",
    "sg:city":"Hartford",
    "sg:classifiers":[
        {
            "category":"Education",
            "subcategory":"School",
            "type":"Public Place"
        }
    ],
    "sg:phone":"+1   ",
    "sg:postcode":"06117",
    "sg:province":"CT",
    "wof:name":"Saint Timothy Middle School",
    "wof:placetype":"venue"
},
  "geometry": {"coordinates":[-72.746751,41.801151],"type":"Point"}
}