{
  "type": "Feature",
  "properties": {
    "addr:full":"29 N Plains Hwy Wallingford CT 06492",
    "addr:housenumber":"29",
    "addr:postcode":"06492",
    "addr:street":"N Plains Hwy",
    "iso:country":"US",
    "sg:address":"29 N Plains Hwy",
    "sg:city":"Wallingford",
    "sg:classifiers":[
        {
            "category":"Building & Trades",
            "subcategory":"Electrical",
            "type":"Services"
        }
    ],
    "sg:phone":"+1 203 269 9663",
    "sg:postcode":"06492",
    "sg:province":"CT",
    "sg:tags":[
        "electrical",
        "contractor"
    ],
    "wof:name":"M N D Universal LLC",
    "wof:placetype":"venue"
},
  "geometry": {"coordinates":[-72.82110400000001,41.475238],"type":"Point"}
}