{
  "type": "Feature",
  "properties": {
    "iso:country":"US",
    "sg:address":"146 Water St",
    "sg:city":"Guilford",
    "sg:classifiers":[
        {
            "category":"Building & Trades",
            "subcategory":"Construction",
            "type":"Services"
        }
    ],
    "sg:phone":"+1 203 458 8111",
    "sg:postcode":"06437",
    "sg:province":"CT",
    "sg:tags":[
        "repairing",
        "remodeling",
        "contractor"
    ],
    "wof:name":"West River Renovations",
    "wof:placetype":"venue"
},
  "geometry": {"coordinates":[-72.686902,41.27922],"type":"Point"}
}