{
  "type": "Feature",
  "properties": {
    "addr:full":"540 Washington Ave North Haven CT 06473",
    "addr:housenumber":"540",
    "addr:postcode":"06473",
    "addr:street":"Washington Ave;Haven",
    "iso:country":"US",
    "sg:address":"540 Washington Ave",
    "sg:city":"North Haven",
    "sg:classifiers":[
        {
            "category":"Building & Trades",
            "subcategory":"Construction",
            "type":"Services"
        },
        {
            "category":"Wholesale",
            "subcategory":"Metals & Minerals",
            "type":"Manufacturing & Wholesale Goods"
        }
    ],
    "sg:phone":"+1 203 239 4634",
    "sg:postcode":"06473",
    "sg:province":"CT",
    "sg:tags":[
        "steel",
        "center"
    ],
    "wof:name":"N E Detailers",
    "wof:placetype":"venue"
},
  "geometry": {"coordinates":[-72.840288,41.418219],"type":"Point"}
}