{
  "type": "Feature",
  "properties": {
    "iso:country":"US",
    "sg:address":"1 Gilbert Hill Rd",
    "sg:city":"Chester",
    "sg:classifiers":[
        {
            "category":"Professional",
            "subcategory":"Management & Consulting",
            "type":"Services"
        }
    ],
    "sg:phone":"+1   ",
    "sg:postcode":"06412",
    "sg:province":"CT",
    "sg:tags":[
        "marketing",
        "consultant"
    ],
    "wof:name":"Fox & Company Inc",
    "wof:placetype":"venue"
},
  "geometry": {"coordinates":[-72.441478,41.399494],"type":"Point"}
}