{
  "type": "Feature",
  "properties": {
    "addr:full":"110 Good Hill Rd Weston CT 06883",
    "addr:housenumber":"110",
    "addr:postcode":"06883",
    "addr:street":"Good Hill Rd",
    "iso:country":"US",
    "sg:address":"110 Good Hill Rd",
    "sg:city":"Weston",
    "sg:classifiers":[
        {
            "category":"Arts & Performance",
            "subcategory":"Theater",
            "type":"Entertainment"
        }
    ],
    "sg:phone":"+1   ",
    "sg:postcode":"06883",
    "sg:province":"CT",
    "sg:tags":[
        "group"
    ],
    "wof:name":"Pleskow Entertainment Inc",
    "wof:placetype":"venue"
},
  "geometry": {"coordinates":[-73.35882100000001,41.197866],"type":"Point"}
}