{
  "type": "Feature",
  "properties": {
    "addr:full":"801 Hartford Rd Manchester CT 06040",
    "addr:housenumber":"801",
    "addr:postcode":"06040",
    "addr:street":"Hartford Rd",
    "iso:country":"US",
    "sg:address":"801 Hartford Rd",
    "sg:city":"Manchester",
    "sg:classifiers":[
        {
            "category":"Recreation",
            "type":"Entertainment"
        }
    ],
    "sg:phone":"+1 860 533 9565",
    "sg:postcode":"06040",
    "sg:province":"CT",
    "sg:tags":[
        "sporting"
    ],
    "wof:name":"Aquatic Adventures Inc",
    "wof:placetype":"venue"
},
  "geometry": {"coordinates":[-72.55480300000001,41.766301],"type":"Point"}
}