{
  "type": "Feature",
  "properties": {
    "addr:full":"84 Oxford Rd Oxford CT 06478",
    "addr:housenumber":"84",
    "addr:postcode":"06478",
    "addr:street":"Oxford Rd",
    "iso:country":"US",
    "sg:address":"84 Oxford Rd",
    "sg:city":"Oxford",
    "sg:classifiers":[
        {
            "category":"Restaurant",
            "type":"Food & Drink"
        }
    ],
    "sg:menulink":"http://www.allmenus.com/ct/oxford/124678-quiznos-sub/menu/",
    "sg:phone":"+1 203 888 9771",
    "sg:postcode":"06478",
    "sg:province":"CT",
    "sg:tags":[
        "wrap",
        "american",
        "sandwich"
    ],
    "wof:name":"Quiznos Sub",
    "wof:placetype":"venue"
},
  "geometry": {"coordinates":[-73.093204,41.406173],"type":"Point"}
}