{
  "type": "Feature",
  "properties": {
    "iso:country":"US",
    "sg:address":"6 Midway Oval",
    "sg:city":"Groton",
    "sg:classifiers":[
        {
            "category":"Retail",
            "subcategory":"Auto Repair",
            "type":"Services"
        }
    ],
    "sg:phone":"+1   ",
    "sg:postcode":"06340",
    "sg:province":"CT",
    "sg:tags":[
        "general"
    ],
    "wof:name":"Alis Garage Sale Co LLC",
    "wof:placetype":"venue"
},
  "geometry": {"coordinates":[-72.027845,41.341928],"type":"Point"}
}