{
  "type": "Feature",
  "properties": {
    "iso:country":"US",
    "sg:address":"688 Main St",
    "sg:city":"Stamford",
    "sg:classifiers":[
        {
            "category":"Organizations",
            "subcategory":"Community Association",
            "type":"Services"
        }
    ],
    "sg:phone":"+1   ",
    "sg:postcode":"06901",
    "sg:province":"CT",
    "wof:name":"Foe 579",
    "wof:placetype":"venue"
},
  "geometry": {"coordinates":[-73.532781,41.05395],"type":"Point"}
}