{
  "type": "Feature",
  "properties": {
    "iso:country":"US",
    "sg:address":"37 Birchwood Dr",
    "sg:city":"Greenwich",
    "sg:classifiers":[
        {
            "category":"Banks & Credit Unions",
            "subcategory":"Investment Brokerage",
            "type":"Services"
        }
    ],
    "sg:phone":"+1 203 661 7482",
    "sg:postcode":"06831",
    "sg:province":"NY",
    "sg:tags":[
        "advisory"
    ],
    "wof:name":"Aquarii Capital Management LLC",
    "wof:placetype":"venue"
},
  "geometry": {"coordinates":[-73.65481800000001,41.086985],"type":"Point"}
}