{
  "type": "Feature",
  "properties": {
    "addr:full":"720 Broad St Hartford CT 06106",
    "addr:housenumber":"720",
    "addr:postcode":"06106",
    "addr:street":"Broad St",
    "iso:country":"US",
    "sg:address":"720 Broad St",
    "sg:city":"Hartford",
    "sg:classifiers":[
        {
            "category":"Food & Beverages",
            "subcategory":"Groceries & Convenience Stores",
            "type":"Retail Goods"
        }
    ],
    "sg:phone":"+1 860 246 1461",
    "sg:postcode":"06106",
    "sg:province":"CT",
    "wof:name":"Isabellas Market",
    "wof:placetype":"venue"
},
  "geometry": {"coordinates":[-72.686778,41.761374],"type":"Point"}
}