{
  "type": "Feature",
  "properties": {
    "addr:full":"3478 Whitney Ave Hamden CT 06518",
    "addr:housenumber":"3478",
    "addr:postcode":"06518",
    "addr:street":"Whitney Ave",
    "iso:country":"US",
    "sg:address":"3478 Whitney Ave",
    "sg:city":"Hamden",
    "sg:classifiers":[
        {
            "category":"Personal",
            "subcategory":"Beauty Salon",
            "type":"Services"
        }
    ],
    "sg:phone":"+1 203 230 3295",
    "sg:postcode":"06518",
    "sg:province":"CT",
    "wof:name":"Hair On Broadway",
    "wof:placetype":"venue"
},
  "geometry": {"coordinates":[-72.902613,41.414896],"type":"Point"}
}