{
  "type": "Feature",
  "properties": {
    "iso:country":"US",
    "sg:address":"96 Myrtle Ave",
    "sg:city":"Westport",
    "sg:classifiers":[
        {
            "category":"Banks & Credit Unions",
            "subcategory":"Financial Services",
            "type":"Services"
        }
    ],
    "sg:phone":"+1 203 227 5614",
    "sg:postcode":"06880",
    "sg:province":"CT",
    "sg:tags":[
        "investor"
    ],
    "wof:name":"Melco Investments Co Ltd Partn",
    "wof:placetype":"venue"
},
  "geometry": {"coordinates":[-73.36083000000001,41.146004],"type":"Point"}
}