{
  "type": "Feature",
  "properties": {
    "iso:country":"US",
    "sg:address":"15 Red Maple Ln",
    "sg:city":"Trumbull",
    "sg:classifiers":[
        {
            "category":"Professional",
            "subcategory":"Management & Consulting",
            "type":"Services"
        }
    ],
    "sg:phone":"+1 203 268 9879",
    "sg:postcode":"06611",
    "sg:province":"CT",
    "sg:tags":[
        "retail",
        "direct",
        "sales"
    ],
    "wof:name":"Norwalk Beauty Supplies",
    "wof:placetype":"venue"
},
  "geometry": {"coordinates":[-73.202231,41.259457],"type":"Point"}
}