{
  "type": "Feature",
  "properties": {
    "addr:full":"8 N Main St Hartford CT 06107",
    "addr:housenumber":"8",
    "addr:postcode":"06107",
    "addr:street":"N Main St",
    "iso:country":"US",
    "sg:address":"8 N Main St",
    "sg:city":"Hartford",
    "sg:classifiers":[
        {
            "category":"Travel",
            "subcategory":"Travel Agent",
            "type":"Entertainment"
        }
    ],
    "sg:phone":"+1 860 521 0882",
    "sg:postcode":"06107",
    "sg:province":"CT",
    "sg:tags":[
        "agency"
    ],
    "wof:name":"Travel Innovations",
    "wof:placetype":"venue"
},
  "geometry": {"coordinates":[-72.741863,41.762809],"type":"Point"}
}