{
  "type": "Feature",
  "properties": {
    "addr:full":"1806 Broad St Hartford CT 06114",
    "addr:housenumber":"1806",
    "addr:postcode":"06114",
    "addr:street":"Broad St",
    "iso:country":"US",
    "sg:address":"1806 Broad St",
    "sg:city":"Hartford",
    "sg:classifiers":[
        {
            "category":"Building & Trades",
            "subcategory":"Construction",
            "type":"Services"
        }
    ],
    "sg:phone":"+1 860 727 9181",
    "sg:postcode":"06114",
    "sg:province":"CT",
    "sg:tags":[
        "masonry",
        "contractor"
    ],
    "wof:name":"GMC Mason Contractors Inc",
    "wof:placetype":"venue"
},
  "geometry": {"coordinates":[-72.687102,41.743535],"type":"Point"}
}