{
  "type": "Feature",
  "properties": {
    "iso:country":"US",
    "sg:address":"360 New Haven Ave",
    "sg:city":"Milford",
    "sg:classifiers":[
        {
            "category":"Building & Trades",
            "subcategory":"Cleaning & Sanitation",
            "type":"Services"
        }
    ],
    "sg:phone":"+1 203 878 0638",
    "sg:postcode":"06460",
    "sg:province":"CT",
    "sg:tags":[
        "janitor"
    ],
    "sg:website":"www.pmiclean.com",
    "wof:name":"Premier Maintenance",
    "wof:placetype":"venue"
},
  "geometry": {"coordinates":[-73.04120500000001,41.223463],"type":"Point"}
}