{
  "type": "Feature",
  "properties": {
    "iso:country":"US",
    "sg:address":"4 Ridge Rd",
    "sg:city":"Newtown",
    "sg:classifiers":[
        {
            "category":"Banks & Credit Unions",
            "subcategory":"Financial Services",
            "type":"Services"
        }
    ],
    "sg:phone":"+1 203 426 5836",
    "sg:postcode":"06470",
    "sg:province":"CT",
    "sg:tags":[
        "company",
        "holding"
    ],
    "wof:name":"Campbell Holding LLC",
    "wof:placetype":"venue"
},
  "geometry": {"coordinates":[-73.31043200000001,41.395497],"type":"Point"}
}