{
  "type": "Feature",
  "properties": {
    "addr:full":"331 Westport Ave Norwalk CT 06851",
    "addr:housenumber":"331",
    "addr:postcode":"06851",
    "addr:street":"Westport Ave",
    "iso:country":"US",
    "sg:address":"331 Westport Ave",
    "sg:city":"Norwalk",
    "sg:classifiers":[
        {
            "category":"Home & Garden",
            "subcategory":"Hardware",
            "type":"Retail Goods"
        }
    ],
    "sg:phone":"+1 203 847 8224",
    "sg:postcode":"06851",
    "sg:province":"CT",
    "wof:name":"Carlyn Paint & Hardware",
    "wof:placetype":"venue"
},
  "geometry": {"coordinates":[-73.392472,41.12568],"type":"Point"}
}