{
  "type": "Feature",
  "properties": {
    "addr:full":"12 Tomac Ct Old Greenwich CT 06870",
    "addr:housenumber":"12",
    "addr:postcode":"06870",
    "addr:street":"Tomac Ct",
    "iso:country":"US",
    "sg:address":"12 Tomac Ct",
    "sg:city":"Old Greenwich",
    "sg:classifiers":[
        {
            "category":"Shopping",
            "subcategory":"Catalog Store",
            "type":"Retail Goods"
        }
    ],
    "sg:phone":"+1 203 240 9182",
    "sg:postcode":"06870",
    "sg:province":"CT",
    "sg:tags":[
        "mail",
        "house"
    ],
    "wof:name":"T S Johnson Co",
    "wof:placetype":"venue"
},
  "geometry": {"coordinates":[-73.5575,41.026769],"type":"Point"}
}