{
  "type": "Feature",
  "properties": {
    "iso:country":"US",
    "sg:address":"1121 S Britain Rd",
    "sg:city":"Southbury",
    "sg:classifiers":[
        {
            "category":"Retail",
            "subcategory":"Repair Shop",
            "type":"Services"
        }
    ],
    "sg:phone":"+1   ",
    "sg:postcode":"06488",
    "sg:province":"CT",
    "sg:tags":[
        "restoration",
        "furniture"
    ],
    "wof:name":"CAM-Fine Furniture Restoration",
    "wof:placetype":"venue"
},
  "geometry": {"coordinates":[-73.25734799999999,41.481799],"type":"Point"}
}