{
  "type": "Feature",
  "properties": {
    "iso:country":"US",
    "sg:address":"23 Alton St",
    "sg:city":"Waterbury",
    "sg:classifiers":[
        {
            "category":"Building & Trades",
            "subcategory":"Landscaping Services",
            "type":"Services"
        }
    ],
    "sg:phone":"+1 203 575 9282",
    "sg:postcode":"06705",
    "sg:province":"CT",
    "wof:name":"B & D Contractor",
    "wof:placetype":"venue"
},
  "geometry": {"coordinates":[-72.99950200000001,41.540866],"type":"Point"}
}