{
  "type": "Feature",
  "properties": {
    "iso:country":"US",
    "sg:address":"25 Hillside Dr",
    "sg:city":"New Fairfield",
    "sg:classifiers":[
        {
            "category":"Insurance",
            "subcategory":"Insurance Agent",
            "type":"Services"
        }
    ],
    "sg:phone":"+1 203 312 0410",
    "sg:postcode":"06812",
    "sg:province":"CT",
    "wof:name":"St Paul Fire & Marine Insur Co",
    "wof:placetype":"venue"
},
  "geometry": {"coordinates":[-73.490818,41.476279],"type":"Point"}
}