{
  "type": "Feature",
  "properties": {
    "addr:full":"10 Mill Plain Rd Danbury CT 06811",
    "addr:housenumber":"10",
    "addr:postcode":"06811",
    "addr:street":"Mill Plain Rd",
    "iso:country":"US",
    "sg:address":"10 Mill Plain Rd",
    "sg:city":"Danbury",
    "sg:classifiers":[
        {
            "category":"Home & Garden",
            "subcategory":"Garden Supply",
            "type":"Retail Goods"
        }
    ],
    "sg:phone":"+1 203 748 5601",
    "sg:postcode":"06811",
    "sg:province":"CT",
    "sg:tags":[
        "equipment",
        "lawn",
        "stove",
        "power",
        "mower"
    ],
    "wof:name":"Nutmeg Power Equipment Co Inc",
    "wof:placetype":"venue"
},
  "geometry": {"coordinates":[-73.493363,41.387139],"type":"Point"}
}