{
  "type": "Feature",
  "properties": {
    "iso:country":"US",
    "sg:address":"710 Daniels Farm Rd",
    "sg:city":"Trumbull",
    "sg:classifiers":[
        {
            "category":"Education",
            "subcategory":"School",
            "type":"Public Place"
        },
        {
            "category":"Organizations",
            "subcategory":"Community Association",
            "type":"Services"
        }
    ],
    "sg:phone":"+1 203 452 4388",
    "sg:postcode":"06611",
    "sg:province":"CT",
    "wof:name":"Daniels Farm School Pta",
    "wof:placetype":"venue"
},
  "geometry": {"coordinates":[-73.200374,41.270381],"type":"Point"}
}