{
  "type": "Feature",
  "properties": {
    "iso:country":"US",
    "sg:address":"86 Litchfield Rd",
    "sg:city":"Morris",
    "sg:classifiers":[
        {
            "category":"Professional",
            "subcategory":"Management & Consulting",
            "type":"Services"
        }
    ],
    "sg:phone":"+1   ",
    "sg:postcode":"06763",
    "sg:province":"CT",
    "sg:tags":[
        "business"
    ],
    "wof:name":"E A C Education & Consulting",
    "wof:placetype":"venue"
},
  "geometry": {"coordinates":[-73.182715,41.694873],"type":"Point"}
}