{
  "type": "Feature",
  "properties": {
    "iso:country":"US",
    "sg:address":"235 Sorgham Mill Dr",
    "sg:city":"Cheshire",
    "sg:classifiers":[
        {
            "category":"Government",
            "subcategory":"Office",
            "type":"Public Place"
        }
    ],
    "sg:phone":"+1 203 272 9701",
    "sg:postcode":"06410",
    "sg:province":"CT",
    "wof:name":"Representative Alfred Adinolfi",
    "wof:placetype":"venue"
},
  "geometry": {"coordinates":[-72.930407,41.490923],"type":"Point"}
}