{
  "type": "Feature",
  "properties": {
    "iso:country":"US",
    "sg:address":"36 Parkview Ave",
    "sg:city":"Bridgeport",
    "sg:classifiers":[
        {
            "category":"Wholesale",
            "subcategory":"Machinery & Supplies",
            "type":"Manufacturing & Wholesale Goods"
        }
    ],
    "sg:phone":"+1 203 556 2574",
    "sg:postcode":"06606",
    "sg:province":"CT",
    "sg:tags":[
        "industrial"
    ],
    "wof:name":"Evelin of America Corporation",
    "wof:placetype":"venue"
},
  "geometry": {"coordinates":[-73.185934,41.212698],"type":"Point"}
}