{
  "type": "Feature",
  "properties": {
    "addr:full":"275 Old Hartford Rd Colchester CT 06415",
    "addr:housenumber":"275",
    "addr:postcode":"06415",
    "addr:street":"Old Hartford Rd",
    "iso:country":"US",
    "sg:address":"275 Old Hartford Rd",
    "sg:city":"Colchester",
    "sg:classifiers":[
        {
            "category":"Building & Trades",
            "subcategory":"Equipment Rental",
            "type":"Services"
        }
    ],
    "sg:phone":"+1   ",
    "sg:postcode":"06415",
    "sg:province":"CT",
    "wof:name":"Ryder",
    "wof:placetype":"venue"
},
  "geometry": {"coordinates":[-72.360834,41.582985],"type":"Point"}
}