{
  "type": "Feature",
  "properties": {
    "addr:full":"416 Good Hill Rd Woodbury CT 06798",
    "addr:housenumber":"416",
    "addr:postcode":"06798",
    "addr:street":"Good Hill Rd",
    "iso:country":"US",
    "sg:address":"416 Good Hill Rd",
    "sg:city":"Woodbury",
    "sg:classifiers":[
        {
            "category":"Professional",
            "subcategory":"Computer Services",
            "type":"Services"
        }
    ],
    "sg:phone":"+1   ",
    "sg:postcode":"06798",
    "sg:province":"CT",
    "sg:tags":[
        "added",
        "value",
        "reseller"
    ],
    "wof:name":"Big Chip Inc",
    "wof:placetype":"venue"
},
  "geometry": {"coordinates":[-73.251997,41.55546],"type":"Point"}
}