{
  "type": "Feature",
  "properties": {
    "addr:full":"207 Christian St Oxford CT 06478",
    "addr:housenumber":"207",
    "addr:postcode":"06478",
    "addr:street":"Christian St",
    "iso:country":"US",
    "sg:address":"207 Christian St",
    "sg:city":"Oxford",
    "sg:classifiers":[
        {
            "category":"Shopping",
            "subcategory":"Pharmacy",
            "type":"Retail Goods"
        }
    ],
    "sg:phone":"+1 203 881 3500",
    "sg:postcode":"06478",
    "sg:province":"CT",
    "wof:name":"Rxcare Pharmacies",
    "wof:placetype":"venue"
},
  "geometry": {"coordinates":[-73.13880899999999,41.472114],"type":"Point"}
}