{
  "type": "Feature",
  "properties": {
    "addr:full":"45 Abbott Rd Ellington CT 06029",
    "addr:housenumber":"45",
    "addr:postcode":"06029",
    "addr:street":"Abbott Rd Ellington Ct",
    "iso:country":"US",
    "sg:address":"45 Abbott Rd",
    "sg:city":"Ellington",
    "sg:classifiers":[
        {
            "category":"Building & Trades",
            "subcategory":"Construction",
            "type":"Services"
        }
    ],
    "sg:phone":"+1 860 875 9115",
    "sg:postcode":"06029",
    "sg:province":"CT",
    "sg:tags":[
        "builder",
        "operative"
    ],
    "wof:name":"Santini Homes Inc",
    "wof:placetype":"venue"
},
  "geometry": {"coordinates":[-72.499156,41.885237],"type":"Point"}
}