{
  "type": "Feature",
  "properties": {
    "addr:full":"3034 Summer St Stamford CT 06905",
    "addr:housenumber":"3034",
    "addr:postcode":"06905",
    "addr:street":"Summer St",
    "iso:country":"US",
    "sg:address":"3034 Summer St",
    "sg:city":"Stamford",
    "sg:classifiers":[
        {
            "category":"Health Services",
            "subcategory":"Optometrist",
            "type":"Services"
        }
    ],
    "sg:phone":"+1   ",
    "sg:postcode":"06905",
    "sg:province":"CT",
    "wof:name":"Nemser Geoffrey L Od",
    "wof:placetype":"venue"
},
  "geometry": {"coordinates":[-73.549347,41.071409],"type":"Point"}
}