{
  "type": "Feature",
  "properties": {
    "addr:full":"5 Hill St Norwalk CT 06850",
    "addr:housenumber":"5",
    "addr:postcode":"06850",
    "addr:street":"Hill St",
    "iso:country":"US",
    "sg:address":"5 Hill St",
    "sg:city":"Norwalk",
    "sg:classifiers":[
        {
            "category":"Building & Trades",
            "subcategory":"Construction",
            "type":"Services"
        }
    ],
    "sg:phone":"+1 203 847 2722",
    "sg:postcode":"06850",
    "sg:province":"CT",
    "sg:tags":[
        "roofing",
        "contractor"
    ],
    "wof:name":"Aaron Roofing",
    "wof:placetype":"venue"
},
  "geometry": {"coordinates":[-73.424767,41.120786],"type":"Point"}
}