{
  "type": "Feature",
  "properties": {
    "addr:full":"90 Halls Rd Old Lyme CT 06371",
    "addr:housenumber":"90",
    "addr:postcode":"06371",
    "addr:street":"Halls Rd",
    "iso:country":"US",
    "sg:address":"90 Halls Rd",
    "sg:city":"Old Lyme",
    "sg:classifiers":[
        {
            "category":"Restaurant",
            "type":"Food & Drink"
        }
    ],
    "sg:menulink":"http://www.allmenus.com/ct/old-lyme/47519-boom-restaurant/menu/",
    "sg:phone":"+1 860 434 0075",
    "sg:postcode":"06371",
    "sg:province":"CT",
    "sg:tags":[
        "american"
    ],
    "wof:name":"Boom Restaurant",
    "wof:placetype":"venue"
},
  "geometry": {"coordinates":[-72.336327,41.323805],"type":"Point"}
}