{
  "type": "Feature",
  "properties": {
    "addr:full":"21 Country Way Bethel CT 06801",
    "addr:housenumber":"21",
    "addr:postcode":"06801",
    "addr:street":"Country Way Bethel Ct",
    "iso:country":"US",
    "sg:address":"21 Country Way",
    "sg:city":"Bethel",
    "sg:classifiers":[
        {
            "category":"Professional",
            "subcategory":"Credit Reporting & Collection",
            "type":"Services"
        }
    ],
    "sg:phone":"+1   ",
    "sg:postcode":"06801",
    "sg:province":"CT",
    "sg:tags":[
        "refund",
        "air",
        "package"
    ],
    "wof:name":"Recovery Specialist",
    "wof:placetype":"venue"
},
  "geometry": {"coordinates":[-73.39085799999999,41.349681],"type":"Point"}
}