{
  "type": "Feature",
  "properties": {
    "iso:country":"US",
    "sg:address":"24 Monroe St",
    "sg:city":"Norwalk",
    "sg:classifiers":[
        {
            "category":"Shopping",
            "subcategory":"Pharmacy",
            "type":"Retail Goods"
        }
    ],
    "sg:phone":"+1 203 866 4567",
    "sg:postcode":"06854",
    "sg:province":"CT",
    "wof:name":"Drug Hotline",
    "wof:placetype":"venue"
},
  "geometry": {"coordinates":[-73.423326,41.096693],"type":"Point"}
}