{
  "type": "Feature",
  "properties": {
    "addr:full":"210 George St Hartford CT 06114",
    "addr:housenumber":"210",
    "addr:postcode":"06114",
    "addr:street":"George St",
    "iso:country":"US",
    "sg:address":"210 George St",
    "sg:city":"Hartford",
    "sg:classifiers":[
        {
            "category":"Health Services",
            "subcategory":"Nursing And Care Facility",
            "type":"Services"
        }
    ],
    "sg:phone":"+1   ",
    "sg:postcode":"06114",
    "sg:province":"CT",
    "sg:tags":[
        "home",
        "continuous",
        "convalescent"
    ],
    "wof:name":"Ellis Manor",
    "wof:placetype":"venue"
},
  "geometry": {"coordinates":[-72.678398,41.731649],"type":"Point"}
}