{
  "type": "Feature",
  "properties": {
    "iso:country":"US",
    "sg:address":"5 Lost Lodge Rd",
    "sg:city":"Westport",
    "sg:classifiers":[
        {
            "category":"Professional",
            "subcategory":"Business Services",
            "type":"Services"
        }
    ],
    "sg:phone":"+1 203 221 1481",
    "sg:postcode":"06880",
    "sg:province":"CT",
    "sg:tags":[
        "interior",
        "consultant",
        "design",
        "decorator",
        "firm"
    ],
    "wof:name":"Holzman Interiors Inc",
    "wof:placetype":"venue"
},
  "geometry": {"coordinates":[-73.344482,41.152151],"type":"Point"}
}