{
  "type": "Feature",
  "properties": {
    "iso:country":"US",
    "sg:address":"220 Hollywood Ave",
    "sg:city":"Stratford",
    "sg:classifiers":[
        {
            "category":"Recreation",
            "type":"Entertainment"
        }
    ],
    "sg:phone":"+1   ",
    "sg:postcode":"06614",
    "sg:province":"CT",
    "wof:name":"Chang Won Martial Arts Academy",
    "wof:placetype":"venue"
},
  "geometry": {"coordinates":[-73.13420600000001,41.216737],"type":"Point"}
}