{
  "type": "Feature",
  "properties": {
    "iso:country":"US",
    "sg:address":"189 Black Hill Rd",
    "sg:city":"Plainfield",
    "sg:classifiers":[
        {
            "category":"Building & Trades",
            "subcategory":"Construction",
            "type":"Services"
        }
    ],
    "sg:phone":"+1 860 564 7047",
    "sg:postcode":"06374",
    "sg:province":"CT",
    "sg:tags":[
        "industrial",
        "construct",
        "contractor"
    ],
    "wof:name":"All Seasons Roofing",
    "wof:placetype":"venue"
},
  "geometry": {"coordinates":[-71.942908,41.706966],"type":"Point"}
}