{
  "type": "Feature",
  "properties": {
    "iso:country":"US",
    "sg:address":"238 Danbury Rd",
    "sg:city":"Wilton",
    "sg:classifiers":[
        {
            "category":"Government",
            "subcategory":"Office",
            "type":"Public Place"
        }
    ],
    "sg:phone":"+1 203 563 0177",
    "sg:postcode":"06897",
    "sg:province":"CT",
    "sg:tags":[
        "village"
    ],
    "wof:name":"Wilton Building Inspector",
    "wof:placetype":"venue"
},
  "geometry": {"coordinates":[-73.42527800000001,41.188325],"type":"Point"}
}