{
  "type": "Feature",
  "properties": {
    "iso:country":"US",
    "sg:address":"237 E Center St",
    "sg:city":"Manchester",
    "sg:classifiers":[
        {
            "category":"Professional",
            "subcategory":"Management & Consulting",
            "type":"Services"
        }
    ],
    "sg:phone":"+1   ",
    "sg:postcode":"06040",
    "sg:province":"CT",
    "wof:name":"Mc Cavanagh Property MGT LLC",
    "wof:placetype":"venue"
},
  "geometry": {"coordinates":[-72.512377,41.777563],"type":"Point"}
}