{
  "type": "Feature",
  "properties": {
    "addr:full":"193 State St North Haven CT 06473",
    "addr:housenumber":"193",
    "addr:postcode":"06473",
    "addr:street":"State St;Haven",
    "iso:country":"US",
    "sg:address":"193 State St",
    "sg:city":"North Haven",
    "sg:classifiers":[
        {
            "category":"Organizations",
            "subcategory":"Labor Organization",
            "type":"Services"
        }
    ],
    "sg:phone":"+1 203 288 3440",
    "sg:postcode":"06473",
    "sg:province":"CT",
    "wof:name":"Communications Workers-America",
    "wof:placetype":"venue"
},
  "geometry": {"coordinates":[-72.877667,41.379745],"type":"Point"}
}