{
  "type": "Feature",
  "properties": {
    "addr:full":"1200 Broad St Bridgeport CT 06604",
    "addr:housenumber":"1200",
    "addr:postcode":"06604",
    "addr:street":"Broad St",
    "iso:country":"US",
    "sg:address":"1200 Broad St",
    "sg:city":"Bridgeport",
    "sg:classifiers":[
        {
            "category":"Parking",
            "type":"Transportation"
        }
    ],
    "sg:phone":"+1   ",
    "sg:postcode":"06604",
    "sg:province":"CT",
    "sg:tags":[
        "automobile"
    ],
    "wof:name":"Central Parking System",
    "wof:placetype":"venue"
},
  "geometry": {"coordinates":[-73.19143099999999,41.178813],"type":"Point"}
}