{
  "type": "Feature",
  "properties": {
    "addr:full":"35 Nutmeg Dr Trumbull CT 06611",
    "addr:housenumber":"35",
    "addr:postcode":"06611",
    "addr:street":"Nutmeg Dr",
    "iso:country":"US",
    "sg:address":"35 Nutmeg Dr",
    "sg:city":"Trumbull",
    "sg:classifiers":[
        {
            "category":"Manufacturing",
            "subcategory":"Printing",
            "type":"Manufacturing & Wholesale Goods"
        }
    ],
    "sg:phone":"+1 203 380 6600",
    "sg:postcode":"06611",
    "sg:province":"CT",
    "sg:tags":[
        "publisher"
    ],
    "wof:name":"Connecticut Magazine",
    "wof:placetype":"venue"
},
  "geometry": {"coordinates":[-73.149269,41.241255],"type":"Point"}
}