{
  "type": "Feature",
  "properties": {
    "iso:country":"US",
    "sg:address":"17 Sedgwick Rd",
    "sg:city":"Hartford",
    "sg:classifiers":[
        {
            "category":"Retail",
            "subcategory":"Laundry & Dry Cleaning",
            "type":"Services"
        }
    ],
    "sg:phone":"+1   ",
    "sg:postcode":"06107",
    "sg:province":"CT",
    "sg:tags":[
        "cleaners"
    ],
    "wof:name":"Sedegwick Cleaners Inc",
    "wof:placetype":"venue"
},
  "geometry": {"coordinates":[-72.74592699999999,41.752587],"type":"Point"}
}