{
  "type": "Feature",
  "properties": {
    "addr:full":"25 Bostwick St Lakeville CT 06039",
    "addr:housenumber":"25",
    "addr:postcode":"06039",
    "addr:street":"Bostwick St",
    "iso:country":"US",
    "sg:address":"25 Bostwick St",
    "sg:city":"Lakeville",
    "sg:classifiers":[
        {
            "category":"Professional",
            "subcategory":"Art Services",
            "type":"Services"
        }
    ],
    "sg:phone":"+1   ",
    "sg:postcode":"06039",
    "sg:province":"CT",
    "sg:tags":[
        "commercial",
        "design"
    ],
    "wof:name":"Manning Graphic Design LLC",
    "wof:placetype":"venue"
},
  "geometry": {"coordinates":[-73.43677700000001,41.967188],"type":"Point"}
}