{
  "type": "Feature",
  "properties": {
    "addr:full":"6 The Green Canton CT 06022",
    "addr:housenumber":"6",
    "addr:postcode":"06022",
    "addr:street":"The Green Canton Ct",
    "iso:country":"US",
    "sg:address":"6 The Green",
    "sg:city":"Canton",
    "sg:classifiers":[
        {
            "category":"Health Services",
            "subcategory":"Health Practitioner",
            "type":"Services"
        }
    ],
    "sg:phone":"+1   ",
    "sg:postcode":"06022",
    "sg:province":"CT",
    "wof:name":"Karel Rubinstein PHD",
    "wof:placetype":"venue"
},
  "geometry": {"coordinates":[-72.921243,41.809984],"type":"Point"}
}