{
  "type": "Feature",
  "properties": {
    "addr:full":"11 Riverbend Dr S Stamford CT 06907",
    "addr:housenumber":"11",
    "addr:postcode":"06907",
    "addr:street":"Riverbend Dr S",
    "iso:country":"US",
    "sg:address":"11 Riverbend Dr S",
    "sg:city":"Stamford",
    "sg:classifiers":[
        {
            "category":"Professional",
            "subcategory":"Accounting & Tax Preparation",
            "type":"Services"
        }
    ],
    "sg:phone":"+1 203 973 1050",
    "sg:postcode":"06907",
    "sg:province":"CT",
    "sg:tags":[
        "payroll"
    ],
    "wof:name":"Paychex Inc",
    "wof:placetype":"venue"
},
  "geometry": {"coordinates":[-73.51853800000001,41.082595],"type":"Point"}
}