{
  "type": "Feature",
  "properties": {
    "addr:full":"41 Parker Ave Meriden CT 06450",
    "addr:housenumber":"41",
    "addr:postcode":"06450",
    "addr:street":"Parker Ave",
    "iso:country":"US",
    "sg:address":"41 Parker Ave",
    "sg:city":"Meriden",
    "sg:classifiers":[
        {
            "category":"Government",
            "subcategory":"Post Office",
            "type":"Public Place"
        }
    ],
    "sg:phone":"+1 203 235 5184",
    "sg:postcode":"06450",
    "sg:province":"CT",
    "sg:tags":[
        "postal",
        "us"
    ],
    "wof:name":"Station A",
    "wof:placetype":"venue"
},
  "geometry": {"coordinates":[-72.790831,41.531978],"type":"Point"}
}