{
  "type": "Feature",
  "properties": {
    "iso:country":"US",
    "sg:address":"1420 Meriden Rd",
    "sg:city":"Waterbury",
    "sg:classifiers":[
        {
            "category":"Real Estate",
            "subcategory":"Real Estate Agent",
            "type":"Services"
        }
    ],
    "sg:phone":"+1 203 574 1118",
    "sg:postcode":"06705",
    "sg:province":"CT",
    "wof:name":"ERA Innovative Realty",
    "wof:placetype":"venue"
},
  "geometry": {"coordinates":[-72.96947900000001,41.553728],"type":"Point"}
}