{
  "type": "Feature",
  "properties": {
    "addr:full":"634 Popes Island Rd Milford CT 06460",
    "addr:housenumber":"634",
    "addr:postcode":"06460",
    "addr:street":"Popes Island Rd",
    "iso:country":"US",
    "sg:address":"634 Popes Island Rd",
    "sg:city":"Milford",
    "sg:classifiers":[
        {
            "category":"Retail",
            "subcategory":"Portrait Studio",
            "type":"Services"
        }
    ],
    "sg:phone":"+1   ",
    "sg:postcode":"06460",
    "sg:province":"CT",
    "sg:tags":[
        "photo",
        "health"
    ],
    "wof:name":"Portraits By Alex",
    "wof:placetype":"venue"
},
  "geometry": {"coordinates":[-73.10439700000001,41.220499],"type":"Point"}
}