{
  "type": "Feature",
  "properties": {
    "addr:full":"291 Vine Rd Stamford CT 06905",
    "addr:housenumber":"291",
    "addr:postcode":"06905",
    "addr:street":"Vine Rd",
    "iso:country":"US",
    "sg:address":"291 Vine Rd",
    "sg:city":"Stamford",
    "sg:classifiers":[
        {
            "category":"Professional",
            "subcategory":"Lawyer & Legal Services",
            "type":"Services"
        }
    ],
    "sg:phone":"+1   ",
    "sg:postcode":"06905",
    "sg:province":"CT",
    "wof:name":"Biro Steven G M",
    "wof:placetype":"venue"
},
  "geometry": {"coordinates":[-73.53724200000001,41.098147],"type":"Point"}
}