{
  "type": "Feature",
  "properties": {
    "iso:country":"US",
    "sg:address":"29 Railroad Ave",
    "sg:city":"Plainfield",
    "sg:classifiers":[
        {
            "category":"Food & Beverages",
            "subcategory":"Groceries & Convenience Stores",
            "type":"Retail Goods"
        }
    ],
    "sg:phone":"+1 860 230 0394",
    "sg:postcode":"06374",
    "sg:province":"CT",
    "wof:name":"Super Convenience Store",
    "wof:placetype":"venue"
},
  "geometry": {"coordinates":[-71.918098,41.679901],"type":"Point"}
}