{
  "type": "Feature",
  "properties": {
    "addr:full":"30 Old Quarry Rd Ridgefield CT 06877",
    "addr:housenumber":"30",
    "addr:postcode":"06877",
    "addr:street":"Old Quarry Rd",
    "iso:country":"US",
    "sg:address":"30 Old Quarry Rd",
    "sg:city":"Ridgefield",
    "sg:classifiers":[
        {
            "category":"Shopping",
            "subcategory":"Computers & Home Electronics",
            "type":"Retail Goods"
        },
        {
            "category":"Professional",
            "subcategory":"Computer Services",
            "type":"Services"
        }
    ],
    "sg:phone":"+1 203 431 1341",
    "sg:postcode":"06877",
    "sg:province":"CT",
    "sg:tags":[
        "networking",
        "technology",
        "dealer",
        "equipment"
    ],
    "wof:name":"Cor Cystems Inc",
    "wof:placetype":"venue"
},
  "geometry": {"coordinates":[-73.49323099999999,41.287827],"type":"Point"}
}