{
  "type": "Feature",
  "properties": {
    "addr:full":"80 Old Meadow Plain Rd Weatogue CT 06089",
    "addr:housenumber":"80",
    "addr:postcode":"06089",
    "addr:street":"Old Meadow Plain Rd Weatogue Ct",
    "iso:country":"US",
    "sg:address":"80 Old Meadow Plain Rd",
    "sg:city":"Weatogue",
    "sg:classifiers":[
        {
            "category":"Home & Garden",
            "subcategory":"Building Materials",
            "type":"Retail Goods"
        }
    ],
    "sg:phone":"+1 860 658 6121",
    "sg:postcode":"06089",
    "sg:province":"CT",
    "wof:name":"All American Glass & Rmdlg",
    "wof:placetype":"venue"
},
  "geometry": {"coordinates":[-72.837183,41.831271],"type":"Point"}
}