{
  "type": "Feature",
  "properties": {
    "addr:full":"263 Broadway Milford CT 06460",
    "addr:housenumber":"263",
    "addr:postcode":"06460",
    "addr:street":"Broadway",
    "iso:country":"US",
    "sg:address":"263 Broadway",
    "sg:city":"Milford",
    "sg:classifiers":[
        {
            "category":"Insurance",
            "subcategory":"Insurance Agent",
            "type":"Services"
        }
    ],
    "sg:phone":"+1 203 701 0284",
    "sg:postcode":"06460",
    "sg:province":"CT",
    "wof:name":"Legacy Squared",
    "wof:placetype":"venue"
},
  "geometry": {"coordinates":[-73.090853,41.186179],"type":"Point"}
}