{
  "type": "Feature",
  "properties": {
    "iso:country":"US",
    "sg:address":"652 Glenbrook Rd",
    "sg:city":"Stamford",
    "sg:classifiers":[
        {
            "category":"Professional",
            "subcategory":"Business Services",
            "type":"Services"
        }
    ],
    "sg:phone":"+1 203 323 3790",
    "sg:postcode":"06906",
    "sg:province":"CT",
    "sg:tags":[
        "embroidery"
    ],
    "wof:name":"Arrow Creative Intl",
    "wof:placetype":"venue"
},
  "geometry": {"coordinates":[-73.518117,41.073249],"type":"Point"}
}