{
  "type": "Feature",
  "properties": {
    "iso:country":"US",
    "sg:address":"26 Goodell Rd",
    "sg:city":"Stafford Springs",
    "sg:classifiers":[
        {
            "category":"Professional",
            "type":"Services"
        }
    ],
    "sg:phone":"+1 860 684 4328",
    "sg:postcode":"06076",
    "sg:province":"CT",
    "wof:name":"Jaime J Mack",
    "wof:placetype":"venue"
},
  "geometry": {"coordinates":[-72.27832600000001,41.974063],"type":"Point"}
}