{
  "type": "Feature",
  "properties": {
    "iso:country":"US",
    "sg:address":"250 Research Dr",
    "sg:city":"Milford",
    "sg:classifiers":[
        {
            "category":"Freight",
            "type":"Transportation"
        }
    ],
    "sg:phone":"+1 203 795 5939",
    "sg:postcode":"06460",
    "sg:province":"CT",
    "sg:tags":[
        "trucking"
    ],
    "wof:name":"Fed Ex Freight",
    "wof:placetype":"venue"
},
  "geometry": {"coordinates":[-73.012649,41.2418],"type":"Point"}
}