{
  "type": "Feature",
  "properties": {
    "iso:country":"US",
    "sg:address":"143 Palmers Hill Rd",
    "sg:city":"Stamford",
    "sg:classifiers":[
        {
            "category":"Professional",
            "subcategory":"Management & Consulting",
            "type":"Services"
        }
    ],
    "sg:phone":"+1   ",
    "sg:postcode":"06902",
    "sg:province":"CT",
    "wof:name":"Bernard Eichwald",
    "wof:placetype":"venue"
},
  "geometry": {"coordinates":[-73.56379200000001,41.059367],"type":"Point"}
}