{
  "type": "Feature",
  "properties": {
    "addr:full":"46 New St Danbury CT 06810",
    "addr:housenumber":"46",
    "addr:postcode":"06810",
    "addr:street":"New St",
    "iso:country":"US",
    "sg:address":"46 New St",
    "sg:city":"Danbury",
    "sg:classifiers":[
        {
            "category":"Real Estate",
            "subcategory":"Real Estate Agent",
            "type":"Services"
        }
    ],
    "sg:phone":"+1 203 743 4688",
    "sg:postcode":"06810",
    "sg:province":"CT",
    "wof:name":"Pandolfi Properties Inc",
    "wof:placetype":"venue"
},
  "geometry": {"coordinates":[-73.456447,41.394524],"type":"Point"}
}