{
  "type": "Feature",
  "properties": {
    "iso:country":"US",
    "sg:address":"285 Kelly Rd",
    "sg:city":"Middlebury",
    "sg:classifiers":[
        {
            "category":"Utilities",
            "subcategory":"Water",
            "type":"Services"
        }
    ],
    "sg:phone":"+1 203 758 9209",
    "sg:postcode":"06762",
    "sg:province":"CT",
    "sg:tags":[
        "company",
        "sewage"
    ],
    "wof:name":"Town Of Middlebury Water Pump",
    "wof:placetype":"venue"
},
  "geometry": {"coordinates":[-73.098119,41.543668],"type":"Point"}
}