{
  "type": "Feature",
  "properties": {
    "iso:country":"US",
    "sg:address":"132 Charter Oak Ave",
    "sg:city":"East Haven",
    "sg:classifiers":[
        {
            "category":"Real Estate",
            "subcategory":"Real Estate Agent",
            "type":"Services"
        }
    ],
    "sg:phone":"+1 203 469 5358",
    "sg:postcode":"06512",
    "sg:province":"CT",
    "wof:name":"General Real Estate Co",
    "wof:placetype":"venue"
},
  "geometry": {"coordinates":[-72.884283,41.281988],"type":"Point"}
}