{
  "type": "Feature",
  "properties": {
    "addr:full":"749 Boston Post Rd Milford CT 06460",
    "addr:housenumber":"749",
    "addr:postcode":"06460",
    "addr:street":"Boston Post Rd",
    "iso:country":"US",
    "sg:address":"749 Boston Post Rd",
    "sg:city":"Milford",
    "sg:classifiers":[
        {
            "category":"Professional",
            "type":"Services"
        }
    ],
    "sg:phone":"+1 203 783 9849",
    "sg:postcode":"06460",
    "sg:province":"CT",
    "wof:name":"Fit 20",
    "wof:placetype":"venue"
},
  "geometry": {"coordinates":[-73.059201,41.23218],"type":"Point"}
}