{
  "type": "Feature",
  "properties": {
    "addr:full":"421 Janet Ln Orange CT 06477",
    "addr:housenumber":"421",
    "addr:postcode":"06477",
    "addr:street":"Janet Ln",
    "iso:country":"US",
    "sg:address":"421 Janet Ln",
    "sg:city":"Orange",
    "sg:classifiers":[
        {
            "category":"Banks & Credit Unions",
            "subcategory":"Financial Services",
            "type":"Services"
        }
    ],
    "sg:phone":"+1 203 799 7061",
    "sg:postcode":"06477",
    "sg:province":"CT",
    "sg:tags":[
        "company",
        "holding"
    ],
    "wof:name":"Endeavor Holdings LLC",
    "wof:placetype":"venue"
},
  "geometry": {"coordinates":[-73.04485,41.265505],"type":"Point"}
}