{
  "type": "Feature",
  "properties": {
    "addr:full":"156 Montauk Ave New London CT 06320",
    "addr:housenumber":"156",
    "addr:postcode":"06320",
    "addr:street":"Montauk Ave New London Ct",
    "iso:country":"US",
    "sg:address":"156 Montauk Ave",
    "sg:city":"New London",
    "sg:classifiers":[
        {
            "category":"Building & Trades",
            "subcategory":"Construction",
            "type":"Services"
        }
    ],
    "sg:phone":"+1 860 442 3336",
    "sg:postcode":"06320",
    "sg:province":"CT",
    "sg:tags":[
        "contractor"
    ],
    "wof:name":"Niantic Roofing",
    "wof:placetype":"venue"
},
  "geometry": {"coordinates":[-72.105017,41.343559],"type":"Point"}
}