{
  "type": "Feature",
  "properties": {
    "iso:country":"US",
    "sg:address":"24 Clemens Ave",
    "sg:city":"Trumbull",
    "sg:classifiers":[
        {
            "category":"Real Estate",
            "subcategory":"Real Estate Agent",
            "type":"Services"
        }
    ],
    "sg:phone":"+1 203 261 5459",
    "sg:postcode":"06611",
    "sg:province":"CT",
    "wof:name":"Douglas Honychurch",
    "wof:placetype":"venue"
},
  "geometry": {"coordinates":[-73.229907,41.270198],"type":"Point"}
}