{
  "type": "Feature",
  "properties": {
    "addr:full":"202 Scotland Rd Windham CT 06280",
    "addr:housenumber":"202",
    "addr:postcode":"06280",
    "addr:street":"Scotland Rd",
    "iso:country":"US",
    "sg:address":"202 Scotland Rd",
    "sg:city":"Windham",
    "sg:classifiers":[
        {
            "category":"Organizations",
            "subcategory":"Religious Organization",
            "type":"Services"
        }
    ],
    "sg:phone":"+1   ",
    "sg:postcode":"06280",
    "sg:province":"CT",
    "wof:name":"Gilead Development Co",
    "wof:placetype":"venue"
},
  "geometry": {"coordinates":[-72.14034700000001,41.699936],"type":"Point"}
}