{
  "type": "Feature",
  "properties": {
    "addr:full":"227 Church St New Haven CT 06510",
    "addr:housenumber":"227",
    "addr:postcode":"06510",
    "addr:street":"Church St",
    "iso:country":"US",
    "sg:address":"227 Church St",
    "sg:city":"New Haven",
    "sg:classifiers":[
        {
            "category":"Health Services",
            "subcategory":"Doctor",
            "type":"Services"
        }
    ],
    "sg:phone":"+1   ",
    "sg:postcode":"06510",
    "sg:province":"CT",
    "sg:tags":[
        "medical"
    ],
    "wof:name":"Frank L Provato MD",
    "wof:placetype":"venue"
},
  "geometry": {"coordinates":[-72.923982,41.308252],"type":"Point"}
}