{
  "type": "Feature",
  "properties": {
    "addr:full":"68 Pinnacle Rd Ellington CT 06029",
    "addr:housenumber":"68",
    "addr:postcode":"06029",
    "addr:street":"Pinnacle Rd Ellington Ct",
    "iso:country":"US",
    "sg:address":"68 Pinnacle Rd",
    "sg:city":"Ellington",
    "sg:classifiers":[
        {
            "category":"Personal",
            "subcategory":"Beauty Salon",
            "type":"Services"
        }
    ],
    "sg:phone":"+1   ",
    "sg:postcode":"06029",
    "sg:province":"CT",
    "sg:tags":[
        "shop"
    ],
    "wof:name":"Hot Tips Salon",
    "wof:placetype":"venue"
},
  "geometry": {"coordinates":[-72.445228,41.905158],"type":"Point"}
}