{
  "type": "Feature",
  "properties": {
    "iso:country":"US",
    "sg:address":"379 Chestnut Tree Hill Rd",
    "sg:city":"Southbury",
    "sg:classifiers":[
        {
            "category":"Building & Trades",
            "subcategory":"Cleaning & Sanitation",
            "type":"Services"
        }
    ],
    "sg:phone":"+1 203 264 6796",
    "sg:postcode":"06488",
    "sg:province":"CT",
    "sg:tags":[
        "janitor"
    ],
    "wof:name":"Work Enders Inc",
    "wof:placetype":"venue"
},
  "geometry": {"coordinates":[-73.1961,41.504327],"type":"Point"}
}