{
  "type": "Feature",
  "properties": {
    "addr:full":"73 Southfield Ave Stamford CT 06902",
    "addr:housenumber":"73",
    "addr:postcode":"06902",
    "addr:street":"Southfield Ave",
    "iso:country":"US",
    "sg:address":"73 Southfield Ave",
    "sg:city":"Stamford",
    "sg:classifiers":[
        {
            "category":"Retail",
            "subcategory":"Car Wash",
            "type":"Services"
        }
    ],
    "sg:phone":"+1 203 359 2242",
    "sg:postcode":"06902",
    "sg:province":"CT",
    "sg:tags":[
        "carwash",
        "polishing",
        "washing"
    ],
    "wof:name":"Look Car Appearance Center",
    "wof:placetype":"venue"
},
  "geometry": {"coordinates":[-73.547758,41.038362],"type":"Point"}
}