{
  "type": "Feature",
  "properties": {
    "addr:full":"105 Fieldstone Dr Windsor CT 06095",
    "addr:housenumber":"105",
    "addr:postcode":"06095",
    "addr:street":"Fieldstone Dr",
    "iso:country":"US",
    "sg:address":"105 Fieldstone Dr",
    "sg:city":"Windsor",
    "sg:classifiers":[
        {
            "category":"Professional",
            "type":"Services"
        }
    ],
    "sg:phone":"+1 860 687 1218",
    "sg:postcode":"06095",
    "sg:province":"CT",
    "wof:name":"Firstrends LLC",
    "wof:placetype":"venue"
},
  "geometry": {"coordinates":[-72.699404,41.892869],"type":"Point"}
}