{
  "type": "Feature",
  "properties": {
    "iso:country":"US",
    "sg:address":"23 Padanaram Rd",
    "sg:city":"Danbury",
    "sg:classifiers":[
        {
            "category":"Personal",
            "subcategory":"Beauty Salon",
            "type":"Services"
        }
    ],
    "sg:phone":"+1 203 797 0053",
    "sg:postcode":"06811",
    "sg:province":"CT",
    "wof:name":"Hair Clinic Salon",
    "wof:placetype":"venue"
},
  "geometry": {"coordinates":[-73.45992699999999,41.414708],"type":"Point"}
}