{
  "type": "Feature",
  "properties": {
    "iso:country":"US",
    "sg:address":"509 Westport Ave",
    "sg:city":"Norwalk",
    "sg:classifiers":[
        {
            "category":"Shopping",
            "subcategory":"Catalog Store",
            "type":"Retail Goods"
        }
    ],
    "sg:phone":"+1 203 750 1000",
    "sg:postcode":"06851",
    "sg:province":"CT",
    "sg:tags":[
        "e"
    ],
    "wof:name":"Cyber Opticlabs Inc",
    "wof:placetype":"venue"
},
  "geometry": {"coordinates":[-73.385068,41.127493],"type":"Point"}
}