{
  "type": "Feature",
  "properties": {
    "addr:full":"23 S Willington Rd West Willington CT 06279",
    "addr:housenumber":"23",
    "addr:postcode":"06279",
    "addr:street":"S Willington Rd West Willington Ct",
    "iso:country":"US",
    "sg:address":"23 S Willington Rd",
    "sg:city":"West Willington",
    "sg:classifiers":[
        {
            "category":"Building & Trades",
            "subcategory":"Construction",
            "type":"Services"
        }
    ],
    "sg:phone":"+1 860 684 7196",
    "sg:postcode":"06279",
    "sg:province":"CT",
    "sg:tags":[
        "house"
    ],
    "wof:name":"Progressive Improvements LLC",
    "wof:placetype":"venue"
},
  "geometry": {"coordinates":[-72.27137399999999,41.861873],"type":"Point"}
}