{
  "type": "Feature",
  "properties": {
    "addr:full":"996 Post Rd Darien CT 06820",
    "addr:housenumber":"996",
    "addr:postcode":"06820",
    "addr:street":"Post Rd",
    "iso:country":"US",
    "sg:address":"996 Post Rd",
    "sg:city":"Darien",
    "sg:classifiers":[
        {
            "category":"Shopping",
            "subcategory":"Used Merchandise",
            "type":"Retail Goods"
        }
    ],
    "sg:phone":"+1 203 655 4552",
    "sg:postcode":"06820",
    "sg:province":"CT",
    "sg:tags":[
        "shop",
        "thrift"
    ],
    "wof:name":"Thrift Shop-Darien Community",
    "wof:placetype":"venue"
},
  "geometry": {"coordinates":[-73.47112,41.076273],"type":"Point"}
}