{
  "type": "Feature",
  "properties": {
    "addr:full":"55 Marsh Hill Rd Orange CT 06477",
    "addr:housenumber":"55",
    "addr:postcode":"06477",
    "addr:street":"Marsh Hill Rd",
    "iso:country":"US",
    "sg:address":"55 Marsh Hill Rd",
    "sg:city":"Orange",
    "sg:classifiers":[
        {
            "category":"Wholesale",
            "subcategory":"Beer",
            "type":"Manufacturing & Wholesale Goods"
        }
    ],
    "sg:phone":"+1 203 891 2100",
    "sg:postcode":"06477",
    "sg:province":"CT",
    "sg:tags":[
        "ale"
    ],
    "sg:website":"www.dichello.com",
    "wof:name":"Dichello Distributors",
    "wof:placetype":"venue"
},
  "geometry": {"coordinates":[-72.999636,41.250703],"type":"Point"}
}