{
  "type": "Feature",
  "properties": {
    "iso:country":"US",
    "sg:address":"71 Center St",
    "sg:city":"Wethersfield",
    "sg:classifiers":[
        {
            "category":"Shopping",
            "subcategory":"Gifts & Souvenirs",
            "type":"Retail Goods"
        }
    ],
    "sg:phone":"+1 860 563 9656",
    "sg:postcode":"06109",
    "sg:province":"CT",
    "wof:name":"Arteffects Gallery",
    "wof:placetype":"venue"
},
  "geometry": {"coordinates":[-72.654118,41.710295],"type":"Point"}
}