{
  "type": "Feature",
  "properties": {
    "addr:full":"98 S Main St Newtown CT 06470",
    "addr:housenumber":"98",
    "addr:postcode":"06470",
    "addr:street":"S Main St",
    "iso:country":"US",
    "sg:address":"98 S Main St",
    "sg:city":"Newtown",
    "sg:classifiers":[
        {
            "category":"Retail",
            "subcategory":"Veterinary Services",
            "type":"Services"
        }
    ],
    "sg:phone":"+1 203 426 2777",
    "sg:postcode":"06470",
    "sg:province":"CT",
    "sg:tags":[
        "veterinarian"
    ],
    "wof:name":"Newtown Animal Clinic PC",
    "wof:placetype":"venue"
},
  "geometry": {"coordinates":[-73.29176,41.394425],"type":"Point"}
}