{
  "type": "Feature",
  "properties": {
    "iso:country":"US",
    "sg:address":"31 Adams Dr",
    "sg:city":"Norwich",
    "sg:classifiers":[
        {
            "category":"Banks & Credit Unions",
            "subcategory":"Financial Services",
            "type":"Services"
        }
    ],
    "sg:phone":"+1 860 887 0198",
    "sg:postcode":"06360",
    "sg:province":"CT",
    "sg:tags":[
        "company",
        "holding"
    ],
    "wof:name":"Pine Tree Holdings LLC",
    "wof:placetype":"venue"
},
  "geometry": {"coordinates":[-72.081926,41.576083],"type":"Point"}
}