{
  "type": "Feature",
  "properties": {
    "addr:full":"633 Post Rd E Westport CT 06880",
    "addr:housenumber":"633",
    "addr:postcode":"06880",
    "addr:street":"Post Rd E Westport Ct",
    "iso:country":"US",
    "sg:address":"633 Post Rd E",
    "sg:city":"Westport",
    "sg:classifiers":[
        {
            "category":"Personal",
            "subcategory":"Beauty Salon",
            "type":"Services"
        }
    ],
    "sg:phone":"+1   ",
    "sg:postcode":"06880",
    "sg:province":"CT",
    "sg:tags":[
        "shop"
    ],
    "wof:name":"Plaza Nail",
    "wof:placetype":"venue"
},
  "geometry": {"coordinates":[-73.34463700000001,41.138777],"type":"Point"}
}