{
  "type": "Feature",
  "properties": {
    "iso:country":"US",
    "sg:address":"89 Sunrise Dr",
    "sg:city":"Manchester",
    "sg:classifiers":[
        {
            "category":"Professional",
            "subcategory":"Secretarial Services",
            "type":"Services"
        }
    ],
    "sg:phone":"+1   ",
    "sg:postcode":"06040",
    "sg:province":"CT",
    "sg:tags":[
        "court",
        "monitor"
    ],
    "wof:name":"Alison M Thomas",
    "wof:placetype":"venue"
},
  "geometry": {"coordinates":[-72.536171,41.746486],"type":"Point"}
}