{
  "type": "Feature",
  "properties": {
    "iso:country":"US",
    "sg:address":"28 Stone Wall Dr",
    "sg:city":"Stamford",
    "sg:classifiers":[
        {
            "category":"Building & Trades",
            "subcategory":"Landscaping Services",
            "type":"Services"
        }
    ],
    "sg:phone":"+1 203 322 4833",
    "sg:postcode":"06905",
    "sg:province":"CT",
    "sg:tags":[
        "landscape"
    ],
    "wof:name":"G & C Ldscpg Property Maint",
    "wof:placetype":"venue"
},
  "geometry": {"coordinates":[-73.55072699999999,41.085611],"type":"Point"}
}