{
  "type": "Feature",
  "properties": {
    "addr:full":"129 Zion St Hartford CT 06106",
    "addr:housenumber":"129",
    "addr:postcode":"06106",
    "addr:street":"Zion St",
    "iso:country":"US",
    "sg:address":"129 Zion St",
    "sg:city":"Hartford",
    "sg:classifiers":[
        {
            "category":"Shopping",
            "type":"Retail Goods"
        }
    ],
    "sg:phone":"+1 860 246 1678",
    "sg:postcode":"06106",
    "sg:province":"CT",
    "sg:tags":[
        "merchandise"
    ],
    "wof:name":"Tag Sale Store",
    "wof:placetype":"venue"
},
  "geometry": {"coordinates":[-72.694165,41.743904],"type":"Point"}
}