{
  "type": "Feature",
  "properties": {
    "iso:country":"US",
    "sg:address":"30 Holmes Ave",
    "sg:city":"Waterbury",
    "sg:classifiers":[
        {
            "category":"Organizations",
            "subcategory":"Non-profit Organization",
            "type":"Services"
        }
    ],
    "sg:phone":"+1 203 755 0175",
    "sg:postcode":"06710",
    "sg:province":"CT",
    "wof:name":"Western Connecticut Ind Inc",
    "wof:placetype":"venue"
},
  "geometry": {"coordinates":[-73.04499800000001,41.557371],"type":"Point"}
}