{
  "type": "Feature",
  "properties": {
    "iso:country":"US",
    "sg:address":"300 East St",
    "sg:city":"New Haven",
    "sg:classifiers":[
        {
            "category":"Manufacturing",
            "subcategory":"Tools & Machinery",
            "type":"Manufacturing & Wholesale Goods"
        }
    ],
    "sg:phone":"+1 203 781 8020",
    "sg:postcode":"06511",
    "sg:province":"CT",
    "sg:tags":[
        "machine",
        "shop"
    ],
    "sg:website":"www.space-craft.com",
    "wof:name":"Space Craft Mfg Inc",
    "wof:placetype":"venue"
},
  "geometry": {"coordinates":[-72.90995599999999,41.308132],"type":"Point"}
}