{
  "type": "Feature",
  "properties": {
    "addr:full":"28 Sachem Rd Greenwich CT 06830",
    "addr:housenumber":"28",
    "addr:postcode":"06830",
    "addr:street":"Sachem Rd",
    "iso:country":"US",
    "sg:address":"28 Sachem Rd",
    "sg:city":"Greenwich",
    "sg:classifiers":[
        {
            "category":"Professional",
            "subcategory":"Business Services",
            "type":"Services"
        }
    ],
    "sg:phone":"+1   ",
    "sg:postcode":"06830",
    "sg:province":"CT",
    "sg:tags":[
        "translation"
    ],
    "wof:name":"Global Language Management",
    "wof:placetype":"venue"
},
  "geometry": {"coordinates":[-73.60317499999999,41.030429],"type":"Point"}
}