{
  "type": "Feature",
  "properties": {
    "addr:full":"1661 Main St Hartford CT 06120",
    "addr:housenumber":"1661",
    "addr:postcode":"06120",
    "addr:street":"Main St",
    "iso:country":"US",
    "sg:address":"1661 Main St",
    "sg:city":"Hartford",
    "sg:classifiers":[
        {
            "category":"Food & Beverages",
            "subcategory":"Liquor & Beverages",
            "type":"Retail Goods"
        }
    ],
    "sg:phone":"+1 860 246 1681",
    "sg:postcode":"06120",
    "sg:province":"CT",
    "sg:tags":[
        "alcoholic"
    ],
    "wof:name":"Mundo Package Store",
    "wof:placetype":"venue"
},
  "geometry": {"coordinates":[-72.676661,41.77666],"type":"Point"}
}