{
  "type": "Feature",
  "properties": {
    "iso:country":"US",
    "sg:address":"29 Leavenworth St",
    "sg:city":"Waterbury",
    "sg:classifiers":[
        {
            "category":"Banks & Credit Unions",
            "subcategory":"Investment Brokerage",
            "type":"Services"
        }
    ],
    "sg:phone":"+1 203 757 3650",
    "sg:postcode":"06702",
    "sg:province":"CT",
    "wof:name":"Transamerica Investment Mgmt",
    "wof:placetype":"venue"
},
  "geometry": {"coordinates":[-73.042395,41.55552],"type":"Point"}
}