{
  "type": "Feature",
  "properties": {
    "iso:country":"US",
    "sg:address":"223 E Center St",
    "sg:city":"Manchester",
    "sg:classifiers":[
        {
            "category":"Professional",
            "subcategory":"Business Services",
            "type":"Services"
        }
    ],
    "sg:phone":"+1   ",
    "sg:postcode":"06040",
    "sg:province":"CT",
    "wof:name":"Theresa Mc Connell",
    "wof:placetype":"venue"
},
  "geometry": {"coordinates":[-72.51314000000001,41.777472],"type":"Point"}
}