{
  "type": "Feature",
  "properties": {
    "iso:country":"US",
    "sg:address":"37 Fairchild Dr",
    "sg:city":"Bethel",
    "sg:classifiers":[
        {
            "category":"Building & Trades",
            "subcategory":"Construction",
            "type":"Services"
        }
    ],
    "sg:phone":"+1 203 792 8453",
    "sg:postcode":"06801",
    "sg:province":"CT",
    "sg:tags":[
        "excavating",
        "contractor"
    ],
    "wof:name":"D & M Mc Levy Contractors",
    "wof:placetype":"venue"
},
  "geometry": {"coordinates":[-73.424903,41.364182],"type":"Point"}
}