{
  "type": "Feature",
  "properties": {
    "addr:full":"2 River Rd Jewett City CT 06351",
    "addr:housenumber":"2",
    "addr:postcode":"06351",
    "addr:street":"River Rd Jewett City Ct",
    "iso:country":"US",
    "sg:address":"2 River Rd",
    "sg:city":"Jewett City",
    "sg:classifiers":[
        {
            "category":"Wholesale",
            "subcategory":"Auto Parts",
            "type":"Manufacturing & Wholesale Goods"
        }
    ],
    "sg:phone":"+1 860 376 2553",
    "sg:postcode":"06351",
    "sg:province":"CT",
    "sg:tags":[
        "supply"
    ],
    "wof:name":"Ikes Auto Supply Inc",
    "wof:placetype":"venue"
},
  "geometry": {"coordinates":[-71.98718100000001,41.602091],"type":"Point"}
}