{
  "type": "Feature",
  "properties": {
    "addr:full":"80 Goose Hill Rd Chester CT 06412",
    "addr:housenumber":"80",
    "addr:postcode":"06412",
    "addr:street":"Goose Hill Rd",
    "iso:country":"US",
    "sg:address":"80 Goose Hill Rd",
    "sg:city":"Chester",
    "sg:classifiers":[
        {
            "category":"Health Services",
            "subcategory":"Health Practitioner",
            "type":"Services"
        }
    ],
    "sg:phone":"+1   ",
    "sg:postcode":"06412",
    "sg:province":"CT",
    "wof:name":"Ives DOE Persich Lcsw",
    "wof:placetype":"venue"
},
  "geometry": {"coordinates":[-72.451654,41.415015],"type":"Point"}
}