{
  "type": "Feature",
  "properties": {
    "iso:country":"US",
    "sg:address":"2 Laura St",
    "sg:city":"Norwalk",
    "sg:classifiers":[
        {
            "category":"Building & Trades",
            "subcategory":"Construction",
            "type":"Services"
        }
    ],
    "sg:phone":"+1 203 838 5980",
    "sg:postcode":"06854",
    "sg:province":"CT",
    "sg:tags":[
        "installs",
        "garage",
        "opener",
        "door",
        "electric"
    ],
    "wof:name":"County Door Sales",
    "wof:placetype":"venue"
},
  "geometry": {"coordinates":[-73.42456199999999,41.089907],"type":"Point"}
}