{
  "type": "Feature",
  "properties": {
    "iso:country":"US",
    "sg:address":"28 Main St",
    "sg:city":"Essex",
    "sg:classifiers":[
        {
            "category":"Real Estate",
            "subcategory":"Architect",
            "type":"Services"
        }
    ],
    "sg:phone":"+1 860 767 2765",
    "sg:postcode":"06426",
    "sg:province":"CT",
    "wof:name":"Bergin Joseph Architect PC",
    "wof:placetype":"venue"
},
  "geometry": {"coordinates":[-72.38802699999999,41.351814],"type":"Point"}
}