{
  "type": "Feature",
  "properties": {
    "iso:country":"US",
    "sg:address":"281 Hamilton Ave",
    "sg:city":"Norwich",
    "sg:classifiers":[
        {
            "category":"Real Estate",
            "subcategory":"Real Estate Agent",
            "type":"Services"
        }
    ],
    "sg:phone":"+1 860 887 4912",
    "sg:postcode":"06360",
    "sg:province":"CT",
    "sg:tags":[
        "manager"
    ],
    "wof:name":"Hamilton Park APT",
    "wof:placetype":"venue"
},
  "geometry": {"coordinates":[-72.05284899999999,41.529617],"type":"Point"}
}