{
  "type": "Feature",
  "properties": {
    "addr:full":"41 Woodford Ave Plainville CT 06062",
    "addr:housenumber":"41",
    "addr:postcode":"06062",
    "addr:street":"Woodford Ave",
    "iso:country":"US",
    "sg:address":"41 Woodford Ave",
    "sg:city":"Plainville",
    "sg:classifiers":[
        {
            "category":"Manufacturing",
            "subcategory":"Tools & Machinery",
            "type":"Manufacturing & Wholesale Goods"
        }
    ],
    "sg:phone":"+1   ",
    "sg:postcode":"06062",
    "sg:province":"CT",
    "sg:tags":[
        "conductive",
        "agency",
        "employment",
        "mfg"
    ],
    "wof:name":"GE",
    "wof:placetype":"venue"
},
  "geometry": {"coordinates":[-72.843383,41.668777],"type":"Point"}
}