{
  "type": "Feature",
  "properties": {
    "iso:country":"US",
    "sg:address":"44 Gorman St",
    "sg:city":"Naugatuck",
    "sg:classifiers":[
        {
            "category":"Manufacturing",
            "subcategory":"Tools & Machinery",
            "type":"Manufacturing & Wholesale Goods"
        }
    ],
    "sg:phone":"+1 203 723 5600",
    "sg:postcode":"06770",
    "sg:province":"CT",
    "sg:tags":[
        "physician",
        "surgeon"
    ],
    "wof:name":"Made Rite Rocker Inc",
    "wof:placetype":"venue"
},
  "geometry": {"coordinates":[-73.057258,41.483169],"type":"Point"}
}