{
  "type": "Feature",
  "properties": {
    "addr:full":"99 E Main St Waterbury CT 06702",
    "addr:housenumber":"99",
    "addr:postcode":"06702",
    "addr:street":"E Main St",
    "iso:country":"US",
    "sg:address":"99 E Main St",
    "sg:city":"Waterbury",
    "sg:classifiers":[
        {
            "category":"Professional",
            "subcategory":"Management & Consulting",
            "type":"Services"
        }
    ],
    "sg:phone":"+1 203 236 9933",
    "sg:postcode":"06702",
    "sg:province":"CT",
    "sg:tags":[
        "consultant",
        "business"
    ],
    "wof:name":"Ct Small Bus Development Ctr",
    "wof:placetype":"venue"
},
  "geometry": {"coordinates":[-73.040211,41.555804],"type":"Point"}
}