{
  "type": "Feature",
  "properties": {
    "addr:full":"276 Post Rd E Westport CT 06880",
    "addr:housenumber":"276",
    "addr:postcode":"06880",
    "addr:street":"Post Rd E Westport Ct",
    "iso:country":"US",
    "sg:address":"276 Post Rd E",
    "sg:city":"Westport",
    "sg:classifiers":[
        {
            "category":"Banks & Credit Unions",
            "subcategory":"Investment Brokerage",
            "type":"Services"
        }
    ],
    "sg:phone":"+1 203 341 7800",
    "sg:postcode":"06880",
    "sg:province":"CT",
    "sg:tags":[
        "advisory"
    ],
    "wof:name":"Iridian Asset Management LLC",
    "wof:placetype":"venue"
},
  "geometry": {"coordinates":[-73.356689,41.141091],"type":"Point"}
}