{
  "type": "Feature",
  "properties": {
    "iso:country":"US",
    "sg:address":"163 Albany Tpke",
    "sg:city":"Canton",
    "sg:classifiers":[
        {
            "category":"Retail",
            "subcategory":"Portrait Studio",
            "type":"Services"
        }
    ],
    "sg:phone":"+1 860 693 1414",
    "sg:postcode":"06019",
    "sg:province":"CT",
    "sg:tags":[
        "wide",
        "format",
        "photography",
        "custom",
        "framing",
        "digital"
    ],
    "wof:name":"Artistic Images of Canton",
    "wof:placetype":"venue"
},
  "geometry": {"coordinates":[-72.88830299999999,41.823949],"type":"Point"}
}