{
  "type": "Feature",
  "properties": {
    "iso:country":"US",
    "sg:address":"10 Winter Village Rd",
    "sg:city":"Granby",
    "sg:classifiers":[
        {
            "category":"Professional",
            "subcategory":"Business Services",
            "type":"Services"
        }
    ],
    "sg:phone":"+1   ",
    "sg:postcode":"06035",
    "sg:province":"CT",
    "wof:name":"Jack Brinegar",
    "wof:placetype":"venue"
},
  "geometry": {"coordinates":[-72.783467,41.998157],"type":"Point"}
}