{
  "type": "Feature",
  "properties": {
    "addr:full":"290 Pratt St Meriden CT 06450",
    "addr:housenumber":"290",
    "addr:postcode":"06450",
    "addr:street":"Pratt St",
    "iso:country":"US",
    "sg:address":"290 Pratt St",
    "sg:city":"Meriden",
    "sg:classifiers":[
        {
            "category":"Manufacturing",
            "subcategory":"Metals",
            "type":"Manufacturing & Wholesale Goods"
        },
        {
            "category":"Manufacturing",
            "subcategory":"Tools & Machinery",
            "type":"Manufacturing & Wholesale Goods"
        }
    ],
    "sg:phone":"+1 203 630 9171",
    "sg:postcode":"06450",
    "sg:province":"CT",
    "sg:tags":[
        "manufacture",
        "copper",
        "ornamental",
        "work",
        "custom",
        "weather",
        "vane"
    ],
    "sg:website":"www.skyartstudio.com",
    "wof:name":"Skyart Studio and Gallery",
    "wof:placetype":"venue"
},
  "geometry": {"coordinates":[-72.79332599999999,41.540497],"type":"Point"}
}