{
  "type": "Feature",
  "properties": {
    "addr:full":"744 George Washington Tpke Burlington CT 06013",
    "addr:housenumber":"744",
    "addr:postcode":"06013",
    "addr:street":"George Washington Tpke",
    "iso:country":"US",
    "sg:address":"744 George Washington Tpke",
    "sg:city":"Burlington",
    "sg:classifiers":[
        {
            "category":"Building & Trades",
            "subcategory":"Construction",
            "type":"Services"
        }
    ],
    "sg:phone":"+1 860 673 6516",
    "sg:postcode":"06013",
    "sg:province":"CT",
    "sg:tags":[
        "contractor"
    ],
    "wof:name":"P B Tile Repair",
    "wof:placetype":"venue"
},
  "geometry": {"coordinates":[-72.961978,41.767884],"type":"Point"}
}