{
  "type": "Feature",
  "properties": {
    "addr:full":"1179 E Main St Meriden CT 06450",
    "addr:housenumber":"1179",
    "addr:postcode":"06450",
    "addr:street":"E Main St",
    "iso:country":"US",
    "sg:address":"1179 E Main St",
    "sg:city":"Meriden",
    "sg:classifiers":[
        {
            "category":"Autos & Motor Vehicles",
            "subcategory":"Automobile Sales",
            "type":"Retail Goods"
        }
    ],
    "sg:phone":"+1 203 238 1100",
    "sg:postcode":"06450",
    "sg:province":"CT",
    "sg:tags":[
        "car",
        "dealer"
    ],
    "sg:website":"www.colonyford.com",
    "wof:name":"Colony Ford LLC",
    "wof:placetype":"venue"
},
  "geometry": {"coordinates":[-72.761837,41.52538],"type":"Point"}
}