{
  "type": "Feature",
  "properties": {
    "addr:full":"306 Southford Rd Southbury CT 06488",
    "addr:housenumber":"306",
    "addr:postcode":"06488",
    "addr:street":"Southford Rd",
    "iso:country":"US",
    "sg:address":"306 Southford Rd",
    "sg:city":"Southbury",
    "sg:classifiers":[
        {
            "category":"Autos & Motor Vehicles",
            "subcategory":"Auto Supplies",
            "type":"Retail Goods"
        }
    ],
    "sg:phone":"+1 203 262 0569",
    "sg:postcode":"06488",
    "sg:province":"CT",
    "wof:name":"Daniel Jacobs LLC",
    "wof:placetype":"venue"
},
  "geometry": {"coordinates":[-73.20056599999999,41.476062],"type":"Point"}
}