{
  "type": "Feature",
  "properties": {
    "iso:country":"US",
    "sg:address":"362 New Haven Ave",
    "sg:city":"Milford",
    "sg:classifiers":[
        {
            "category":"Personal",
            "type":"Services"
        }
    ],
    "sg:phone":"+1   ",
    "sg:postcode":"06460",
    "sg:province":"CT",
    "wof:name":"Full Throttle Tattoo LLC",
    "wof:placetype":"venue"
},
  "geometry": {"coordinates":[-73.041264,41.223449],"type":"Point"}
}