{
  "type": "Feature",
  "properties": {
    "addr:full":"109 Danbury Rd Ridgefield CT 06877",
    "addr:housenumber":"109",
    "addr:postcode":"06877",
    "addr:street":"Danbury Rd",
    "iso:country":"US",
    "sg:address":"109 Danbury Rd",
    "sg:city":"Ridgefield",
    "sg:classifiers":[
        {
            "category":"Shopping",
            "subcategory":"Clothing, Apparel, & Fashions",
            "type":"Retail Goods"
        }
    ],
    "sg:phone":"+1 203 438 6989",
    "sg:postcode":"06877",
    "sg:province":"CT",
    "sg:tags":[
        "clothing",
        "men's",
        "sale",
        "wear",
        "rental",
        "boys'",
        "formal"
    ],
    "sg:website":"http://www.huttons.com",
    "wof:name":"Hutton's",
    "wof:placetype":"venue"
},
  "geometry": {"coordinates":[-73.49301800000001,41.293414],"type":"Point"}
}