{
  "type": "Feature",
  "properties": {
    "addr:full":"160 Ferry St New Haven CT 06513",
    "addr:housenumber":"160",
    "addr:postcode":"06513",
    "addr:street":"Ferry St",
    "iso:country":"US",
    "sg:address":"160 Ferry St",
    "sg:city":"New Haven",
    "sg:classifiers":[
        {
            "category":"Social Services",
            "type":"Services"
        }
    ],
    "sg:phone":"+1 203 865 6385",
    "sg:postcode":"06513",
    "sg:province":"CT",
    "sg:tags":[
        "organization",
        "welfare"
    ],
    "wof:name":"Fair Haven Parents Ministry",
    "wof:placetype":"venue"
},
  "geometry": {"coordinates":[-72.894403,41.303601],"type":"Point"}
}