{
  "type": "Feature",
  "properties": {
    "addr:full":"16 Rickey Ln Norwalk CT 06854",
    "addr:housenumber":"16",
    "addr:postcode":"06854",
    "addr:street":"Rickey Ln",
    "iso:country":"US",
    "sg:address":"16 Rickey Ln",
    "sg:city":"Norwalk",
    "sg:classifiers":[
        {
            "category":"Arts & Performance",
            "subcategory":"Theater",
            "type":"Entertainment"
        }
    ],
    "sg:phone":"+1 203 854 9487",
    "sg:postcode":"06854",
    "sg:province":"CT",
    "sg:tags":[
        "live",
        "music"
    ],
    "wof:name":"Party Time Entertainment",
    "wof:placetype":"venue"
},
  "geometry": {"coordinates":[-73.42922900000001,41.093693],"type":"Point"}
}