{
  "type": "Feature",
  "properties": {
    "iso:country":"US",
    "sg:address":"158 Brushy Hill Rd",
    "sg:city":"Newtown",
    "sg:classifiers":[
        {
            "category":"Professional",
            "subcategory":"Management & Consulting",
            "type":"Services"
        }
    ],
    "sg:phone":"+1   ",
    "sg:postcode":"06470",
    "sg:province":"CT",
    "sg:tags":[
        "consultant",
        "telecommunication",
        "broker"
    ],
    "wof:name":"Dvp Technologies LLC",
    "wof:placetype":"venue"
},
  "geometry": {"coordinates":[-73.29882000000001,41.370051],"type":"Point"}
}