{
  "type": "Feature",
  "properties": {
    "addr:full":"14 Old Ln Washington CT 06783",
    "addr:housenumber":"14",
    "addr:postcode":"06783",
    "addr:street":"Old Ln Washington Ct",
    "iso:country":"US",
    "sg:address":"14 Old Ln",
    "sg:city":"Washington",
    "sg:classifiers":[
        {
            "category":"Professional",
            "subcategory":"Research",
            "type":"Services"
        }
    ],
    "sg:phone":"+1   ",
    "sg:postcode":"06783",
    "sg:province":"CT",
    "sg:tags":[
        "nonphysical",
        "commercial"
    ],
    "wof:name":"H I V Research",
    "wof:placetype":"venue"
},
  "geometry": {"coordinates":[-73.337568,41.552088],"type":"Point"}
}