{
  "type": "Feature",
  "properties": {
    "iso:country":"US",
    "sg:address":"1500 Bedford St",
    "sg:city":"Stamford",
    "sg:classifiers":[
        {
            "category":"Health Services",
            "subcategory":"Doctor",
            "type":"Services"
        }
    ],
    "sg:phone":"+1 203 386 1543",
    "sg:postcode":"06905",
    "sg:province":"CT",
    "sg:tags":[
        "physician",
        "surgeon"
    ],
    "wof:name":"International Medical Products",
    "wof:placetype":"venue"
},
  "geometry": {"coordinates":[-73.54090100000001,41.064253],"type":"Point"}
}