{
  "type": "Feature",
  "properties": {
    "addr:full":"920 Boston Post Rd Milford CT 06460",
    "addr:housenumber":"920",
    "addr:postcode":"06460",
    "addr:street":"Boston Post Rd",
    "iso:country":"US",
    "sg:address":"920 Boston Post Rd",
    "sg:city":"Milford",
    "sg:classifiers":[
        {
            "category":"Retail",
            "subcategory":"Auto Rental",
            "type":"Services"
        }
    ],
    "sg:phone":"+1 203 876 2620",
    "sg:postcode":"06460",
    "sg:province":"CT",
    "sg:tags":[
        "renting",
        "automobile"
    ],
    "wof:name":"Enterprise Rent-A-Car",
    "wof:placetype":"venue"
},
  "geometry": {"coordinates":[-73.048461,41.231866],"type":"Point"}
}