{
  "type": "Feature",
  "properties": {
    "addr:full":"38 Owenoke Park Westport CT 06880",
    "addr:housenumber":"38",
    "addr:postcode":"06880",
    "addr:street":"Owenoke Park Westport Ct",
    "iso:country":"US",
    "sg:address":"38 Owenoke Park",
    "sg:city":"Westport",
    "sg:classifiers":[
        {
            "category":"Professional",
            "subcategory":"Management & Consulting",
            "type":"Services"
        }
    ],
    "sg:phone":"+1 203 662 3900",
    "sg:postcode":"06880",
    "sg:province":"CT",
    "sg:tags":[
        "consultant"
    ],
    "wof:name":"Knight Tallman & Co LLC",
    "wof:placetype":"venue"
},
  "geometry": {"coordinates":[-73.36053099999999,41.106852],"type":"Point"}
}