{
  "type": "Feature",
  "properties": {
    "iso:country":"US",
    "sg:address":"60 Providence Pike",
    "sg:city":"Putnam",
    "sg:classifiers":[
        {
            "category":"Food & Beverages",
            "subcategory":"Groceries & Convenience Stores",
            "type":"Retail Goods"
        }
    ],
    "sg:phone":"+1 860 963 2642",
    "sg:postcode":"06260",
    "sg:province":"CT",
    "wof:name":"Stop & Shop Pharmacy",
    "wof:placetype":"venue"
},
  "geometry": {"coordinates":[-71.872997,41.925628],"type":"Point"}
}