{
  "type": "Feature",
  "properties": {
    "addr:full":"86 Farmington Chase Cres Farmington CT 06032",
    "addr:housenumber":"86",
    "addr:postcode":"06032",
    "addr:street":"Farmington Chase Cres",
    "iso:country":"US",
    "sg:address":"86 Farmington Chase Cres",
    "sg:city":"Farmington",
    "sg:classifiers":[
        {
            "category":"Home & Garden",
            "subcategory":"Home Furnishings",
            "type":"Retail Goods"
        }
    ],
    "sg:phone":"+1 860 674 9382",
    "sg:postcode":"06032",
    "sg:province":"CT",
    "wof:name":"Something Extra Special",
    "wof:placetype":"venue"
},
  "geometry": {"coordinates":[-72.88307500000001,41.700863],"type":"Point"}
}