{
  "type": "Feature",
  "properties": {
    "addr:full":"56 Richmondville Ave Westport CT 06880",
    "addr:housenumber":"56",
    "addr:postcode":"06880",
    "addr:street":"Richmondville Ave",
    "iso:country":"US",
    "sg:address":"56 Richmondville Ave",
    "sg:city":"Westport",
    "sg:classifiers":[
        {
            "category":"Building & Trades",
            "subcategory":"Landscaping Services",
            "type":"Services"
        }
    ],
    "sg:phone":"+1 203 227 9601",
    "sg:postcode":"06880",
    "sg:province":"CT",
    "sg:tags":[
        "lawn",
        "complete",
        "care"
    ],
    "wof:name":"J & H Commercial Maintenance",
    "wof:placetype":"venue"
},
  "geometry": {"coordinates":[-73.365888,41.155655],"type":"Point"}
}