{
  "type": "Feature",
  "properties": {
    "addr:full":"18 Huckleberry Rd Redding CT 06896",
    "addr:housenumber":"18",
    "addr:postcode":"06896",
    "addr:street":"Huckleberry Rd",
    "iso:country":"US",
    "sg:address":"18 Huckleberry Rd",
    "sg:city":"Redding",
    "sg:classifiers":[
        {
            "category":"Professional",
            "subcategory":"Business Services",
            "type":"Services"
        }
    ],
    "sg:phone":"+1   ",
    "sg:postcode":"06896",
    "sg:province":"CT",
    "wof:name":"Foward Motion Design LLC",
    "wof:placetype":"venue"
},
  "geometry": {"coordinates":[-73.362512,41.293507],"type":"Point"}
}