{
  "type": "Feature",
  "properties": {
    "addr:full":"321 Grandview Ave Waterbury CT 06708",
    "addr:housenumber":"321",
    "addr:postcode":"06708",
    "addr:street":"Grandview Ave",
    "iso:country":"US",
    "sg:address":"321 Grandview Ave",
    "sg:city":"Waterbury",
    "sg:classifiers":[
        {
            "category":"Wholesale",
            "subcategory":"Chemicals & Plastics",
            "type":"Manufacturing & Wholesale Goods"
        }
    ],
    "sg:phone":"+1 203 753 4505",
    "sg:postcode":"06708",
    "sg:province":"CT",
    "sg:tags":[
        "sealer",
        "concrete"
    ],
    "wof:name":"Edwards Pavement Care",
    "wof:placetype":"venue"
},
  "geometry": {"coordinates":[-73.062878,41.565439],"type":"Point"}
}