{
  "type": "Feature",
  "properties": {
    "addr:full":"262 Westbrook Rd Essex CT 06426",
    "addr:housenumber":"262",
    "addr:postcode":"06426",
    "addr:street":"Westbrook Rd",
    "iso:country":"US",
    "sg:address":"262 Westbrook Rd",
    "sg:city":"Essex",
    "sg:classifiers":[
        {
            "category":"Professional",
            "subcategory":"Business Services",
            "type":"Services"
        }
    ],
    "sg:phone":"+1   ",
    "sg:postcode":"06426",
    "sg:province":"CT",
    "wof:name":"R&R Product Design Inc",
    "wof:placetype":"venue"
},
  "geometry": {"coordinates":[-72.428371,41.327254],"type":"Point"}
}