{
  "type": "Feature",
  "properties": {
    "iso:country":"US",
    "sg:address":"522 Heritage Rd",
    "sg:city":"Southbury",
    "sg:classifiers":[
        {
            "category":"Shopping",
            "subcategory":"Florist",
            "type":"Retail Goods"
        }
    ],
    "sg:phone":"+1 203 264 9700",
    "sg:postcode":"06488",
    "sg:province":"CT",
    "wof:name":"O'Rourke & Birch Florists Inc",
    "wof:placetype":"venue"
},
  "geometry": {"coordinates":[-73.224745,41.488544],"type":"Point"}
}