{
  "type": "Feature",
  "properties": {
    "addr:full":"293 Courtland Ave Stamford CT 06906",
    "addr:housenumber":"293",
    "addr:postcode":"06906",
    "addr:street":"Courtland Ave",
    "iso:country":"US",
    "sg:address":"293 Courtland Ave",
    "sg:city":"Stamford",
    "sg:classifiers":[
        {
            "category":"Building & Trades",
            "subcategory":"Plumbing",
            "type":"Services"
        }
    ],
    "sg:phone":"+1 203 967 2548",
    "sg:postcode":"06906",
    "sg:province":"CT",
    "sg:tags":[
        "plumbing",
        "air",
        "heating",
        "conditioning",
        "contractor"
    ],
    "wof:name":"Bill Magyari Plumbing & Heatin",
    "wof:placetype":"venue"
},
  "geometry": {"coordinates":[-73.51569600000001,41.067611],"type":"Point"}
}