{
  "type": "Feature",
  "properties": {
    "addr:full":"112 Clapboard Ridge Rd Danbury CT 06811",
    "addr:housenumber":"112",
    "addr:postcode":"06811",
    "addr:street":"Clapboard Ridge Rd",
    "iso:country":"US",
    "sg:address":"112 Clapboard Ridge Rd",
    "sg:city":"Danbury",
    "sg:classifiers":[
        {
            "category":"Professional",
            "subcategory":"Business Services",
            "type":"Services"
        }
    ],
    "sg:phone":"+1   ",
    "sg:postcode":"06811",
    "sg:province":"CT",
    "wof:name":"JM Group Contracting",
    "wof:placetype":"venue"
},
  "geometry": {"coordinates":[-73.49373199999999,41.433123],"type":"Point"}
}