{
  "type": "Feature",
  "properties": {
    "addr:full":"36 Cedar Hill Rd Gaylordsville CT 06755",
    "addr:housenumber":"36",
    "addr:postcode":"06755",
    "addr:street":"Cedar Hill Rd Gaylordsville Ct",
    "iso:country":"US",
    "sg:address":"36 Cedar Hill Rd",
    "sg:city":"Gaylordsville",
    "sg:classifiers":[
        {
            "category":"Professional",
            "subcategory":"Computer Services",
            "type":"Services"
        }
    ],
    "sg:phone":"+1   ",
    "sg:postcode":"06755",
    "sg:province":"CT",
    "sg:tags":[
        "prepackaged",
        "software"
    ],
    "wof:name":"Genesys Dtp",
    "wof:placetype":"venue"
},
  "geometry": {"coordinates":[-73.47971099999999,41.635273],"type":"Point"}
}