{
  "type": "Feature",
  "properties": {
    "iso:country":"US",
    "sg:address":"57 Lyme St",
    "sg:city":"Old Lyme",
    "sg:classifiers":[
        {
            "category":"Social Services",
            "subcategory":"Child Care",
            "type":"Services"
        }
    ],
    "sg:phone":"+1 860 434 1728",
    "sg:postcode":"06371",
    "sg:province":"CT",
    "sg:tags":[
        "day"
    ],
    "wof:name":"Old Lyme Children's Learning Center Inc",
    "wof:placetype":"venue"
},
  "geometry": {"coordinates":[-72.3293,41.318802],"type":"Point"}
}