{
  "type": "Feature",
  "properties": {
    "iso:country":"US",
    "sg:address":"113 Mill Plain Rd",
    "sg:city":"Danbury",
    "sg:classifiers":[
        {
            "category":"Coffee & Tea",
            "type":"Food & Drink"
        }
    ],
    "sg:menulink":"http://www.allmenus.com/ct/danbury/108458-starbucks-coffee/menu/",
    "sg:phone":"+1 203 778 0203",
    "sg:postcode":"06811",
    "sg:province":"CT",
    "sg:tags":[
        "american"
    ],
    "wof:name":"Starbucks Coffee",
    "wof:placetype":"venue"
},
  "geometry": {"coordinates":[-73.520245,41.392339],"type":"Point"}
}