{
  "type": "Feature",
  "properties": {
    "addr:full":"88 State Hwy 37 New Fairfield CT 06812",
    "addr:housenumber":"88",
    "addr:postcode":"06812",
    "addr:street":"State Hwy 37 New Fairfield Ct",
    "iso:country":"US",
    "sg:address":"88 State Hwy 37",
    "sg:city":"New Fairfield",
    "sg:classifiers":[
        {
            "category":"Home & Garden",
            "subcategory":"Furniture",
            "type":"Retail Goods"
        }
    ],
    "sg:phone":"+1 203 746 8058",
    "sg:postcode":"06812",
    "sg:province":"CT",
    "sg:tags":[
        "equipment",
        "kitchen",
        "cabinet"
    ],
    "wof:name":"Designs Plus Kitchen & Bath",
    "wof:placetype":"venue"
},
  "geometry": {"coordinates":[-73.486948,41.467029],"type":"Point"}
}