{
  "type": "Feature",
  "properties": {
    "iso:country":"US",
    "sg:address":"97 East St",
    "sg:city":"Bethlehem",
    "sg:classifiers":[
        {
            "category":"Health Services",
            "subcategory":"Chiropractor",
            "type":"Services"
        }
    ],
    "sg:phone":"+1   ",
    "sg:postcode":"06751",
    "sg:province":"CT",
    "wof:name":"Ralph A Santora Dr",
    "wof:placetype":"venue"
},
  "geometry": {"coordinates":[-73.198789,41.639929],"type":"Point"}
}