{
  "type": "Feature",
  "properties": {
    "iso:country":"US",
    "sg:address":"40 High Rock Rd",
    "sg:city":"Groton",
    "sg:classifiers":[
        {
            "category":"Social Services",
            "subcategory":"Child Care",
            "type":"Services"
        }
    ],
    "sg:phone":"+1   ",
    "sg:postcode":"06340",
    "sg:province":"CT",
    "sg:tags":[
        "day"
    ],
    "wof:name":"Warburg Dillon Read Childcare",
    "wof:placetype":"venue"
},
  "geometry": {"coordinates":[-72.055836,41.340516],"type":"Point"}
}