{
  "type": "Feature",
  "properties": {
    "addr:full":"116 W Broad St Stamford CT 06902",
    "addr:housenumber":"116",
    "addr:postcode":"06902",
    "addr:street":"W Broad St",
    "iso:country":"US",
    "sg:address":"116 W Broad St",
    "sg:city":"Stamford",
    "sg:classifiers":[
        {
            "category":"Restaurant",
            "type":"Food & Drink"
        }
    ],
    "sg:menulink":"http://www.allmenus.com/ct/stamford/83146-dominos-pizza/menu/",
    "sg:phone":"+1 203 324 5600",
    "sg:postcode":"06902",
    "sg:province":"CT",
    "sg:tags":[
        "american",
        "wing",
        "pizza"
    ],
    "wof:name":"Domino's Pizza",
    "wof:placetype":"venue"
},
  "geometry": {"coordinates":[-73.549824,41.055885],"type":"Point"}
}