{
  "type": "Feature",
  "properties": {
    "iso:country":"US",
    "sg:address":"140 Greenwich Ave",
    "sg:city":"Greenwich",
    "sg:classifiers":[
        {
            "category":"Professional",
            "subcategory":"Management & Consulting",
            "type":"Services"
        }
    ],
    "sg:phone":"+1 203 861 7809",
    "sg:postcode":"06830",
    "sg:province":"CT",
    "sg:tags":[
        "consultant"
    ],
    "wof:name":"Greenwich Asset Parters",
    "wof:placetype":"venue"
},
  "geometry": {"coordinates":[-73.626064,41.027053],"type":"Point"}
}