{
  "type": "Feature",
  "properties": {
    "addr:full":"325 Congress St Bridgeport CT 06604",
    "addr:housenumber":"325",
    "addr:postcode":"06604",
    "addr:street":"Congress St",
    "iso:country":"US",
    "sg:address":"325 Congress St",
    "sg:city":"Bridgeport",
    "sg:classifiers":[
        {
            "category":"Government",
            "subcategory":"Office",
            "type":"Public Place"
        }
    ],
    "sg:phone":"+1 203 576 7164",
    "sg:postcode":"06604",
    "sg:province":"CT",
    "sg:tags":[
        "policy"
    ],
    "wof:name":"Tax Collector",
    "wof:placetype":"venue"
},
  "geometry": {"coordinates":[-73.19340800000001,41.180958],"type":"Point"}
}