{
  "type": "Feature",
  "properties": {
    "iso:country":"US",
    "sg:address":"14 Kellee Dr",
    "sg:city":"Norwalk",
    "sg:classifiers":[
        {
            "category":"Professional",
            "subcategory":"Management & Consulting",
            "type":"Services"
        }
    ],
    "sg:phone":"+1 203 831 8522",
    "sg:postcode":"06854",
    "sg:province":"CT",
    "sg:tags":[
        "employment",
        "screening"
    ],
    "wof:name":"Dynamic Athletic Profiles",
    "wof:placetype":"venue"
},
  "geometry": {"coordinates":[-73.442657,41.103902],"type":"Point"}
}