{
  "type": "Feature",
  "properties": {
    "addr:full":"71 Sunnyside Ave Stamford CT 06902",
    "addr:housenumber":"71",
    "addr:postcode":"06902",
    "addr:street":"Sunnyside Ave",
    "iso:country":"US",
    "sg:address":"71 Sunnyside Ave",
    "sg:city":"Stamford",
    "sg:classifiers":[
        {
            "category":"Utilities",
            "subcategory":"Refuse",
            "type":"Services"
        }
    ],
    "sg:phone":"+1 203 325 2635",
    "sg:postcode":"06902",
    "sg:province":"CT",
    "sg:tags":[
        "garbage",
        "collection"
    ],
    "wof:name":"Independent Refuse Svc Inc",
    "wof:placetype":"venue"
},
  "geometry": {"coordinates":[-73.549618,41.037781],"type":"Point"}
}