{
  "type": "Feature",
  "properties": {
    "addr:full":"349 New Haven Ave Milford CT 06460",
    "addr:housenumber":"349",
    "addr:postcode":"06460",
    "addr:street":"New Haven Ave",
    "iso:country":"US",
    "sg:address":"349 New Haven Ave",
    "sg:city":"Milford",
    "sg:classifiers":[
        {
            "category":"Manufacturing",
            "subcategory":"Printing",
            "type":"Manufacturing & Wholesale Goods"
        }
    ],
    "sg:phone":"+1 203 789 5200",
    "sg:postcode":"06460",
    "sg:province":"CT",
    "sg:tags":[
        "newspaper"
    ],
    "sg:website":"www.ctcentral.com",
    "wof:name":"Elm City Newspapers",
    "wof:placetype":"venue"
},
  "geometry": {"coordinates":[-73.041336,41.223279],"type":"Point"}
}