{
  "type": "Feature",
  "properties": {
    "iso:country":"US",
    "sg:address":"51 Alpine St",
    "sg:city":"Bridgeport",
    "sg:classifiers":[
        {
            "category":"Building & Trades",
            "subcategory":"Cleaning & Sanitation",
            "type":"Services"
        }
    ],
    "sg:phone":"+1 203 522 4406",
    "sg:postcode":"06610",
    "sg:province":"CT",
    "sg:tags":[
        "fire",
        "water",
        "restoration",
        "damage"
    ],
    "wof:name":"Defeat Restoration",
    "wof:placetype":"venue"
},
  "geometry": {"coordinates":[-73.18301700000001,41.206199],"type":"Point"}
}