{
  "type": "Feature",
  "properties": {
    "iso:country":"US",
    "sg:address":"87 Ten Rod Rd",
    "sg:city":"Voluntown",
    "sg:classifiers":[
        {
            "category":"Building & Trades",
            "subcategory":"Landscaping Services",
            "type":"Services"
        }
    ],
    "sg:phone":"+1 860 376 4510",
    "sg:postcode":"06384",
    "sg:province":"CT",
    "sg:tags":[
        "excavation",
        "contractor"
    ],
    "wof:name":"Eccleston Landscaping Inc",
    "wof:placetype":"venue"
},
  "geometry": {"coordinates":[-71.811368,41.577018],"type":"Point"}
}