{
  "type": "Feature",
  "properties": {
    "iso:country":"US",
    "sg:address":"83 Wooster Hts",
    "sg:city":"Danbury",
    "sg:classifiers":[
        {
            "category":"Manufacturing",
            "subcategory":"Chemicals & Compounds",
            "type":"Manufacturing & Wholesale Goods"
        }
    ],
    "sg:phone":"+1 203 744 6720",
    "sg:postcode":"06810",
    "sg:province":"CT",
    "sg:website":"www.lastra-america.com",
    "wof:name":"Lastra America",
    "wof:placetype":"venue"
},
  "geometry": {"coordinates":[-73.46705300000001,41.375035],"type":"Point"}
}