{
  "type": "Feature",
  "properties": {
    "iso:country":"US",
    "sg:address":"105 Charter Oak Ave",
    "sg:city":"East Haven",
    "sg:classifiers":[
        {
            "category":"Building & Trades",
            "subcategory":"Electrical",
            "type":"Services"
        }
    ],
    "sg:phone":"+1 203 901 4363",
    "sg:postcode":"06512",
    "sg:province":"CT",
    "sg:tags":[
        "electric",
        "contractor"
    ],
    "wof:name":"DSP Electric",
    "wof:placetype":"venue"
},
  "geometry": {"coordinates":[-72.884664,41.281077],"type":"Point"}
}