{
  "type": "Feature",
  "properties": {
    "addr:full":"511 W Main St Meriden CT 06451",
    "addr:housenumber":"511",
    "addr:postcode":"06451",
    "addr:street":"W Main St",
    "iso:country":"US",
    "sg:address":"511 W Main St",
    "sg:city":"Meriden",
    "sg:classifiers":[
        {
            "category":"Restaurant",
            "type":"Food & Drink"
        }
    ],
    "sg:phone":"+1 203 238 4144",
    "sg:postcode":"06451",
    "sg:province":"CT",
    "wof:name":"Subway Sandwiches & Salads",
    "wof:placetype":"venue"
},
  "geometry": {"coordinates":[-72.821325,41.540566],"type":"Point"}
}