{
  "type": "Feature",
  "properties": {
    "iso:country":"US",
    "sg:address":"1066 N Colony St",
    "sg:city":"Meriden",
    "sg:classifiers":[
        {
            "category":"Freight",
            "type":"Transportation"
        }
    ],
    "sg:phone":"+1 203 237 5572",
    "sg:postcode":"06450",
    "sg:province":"CT",
    "sg:tags":[
        "commercial",
        "storage"
    ],
    "wof:name":"G P Self Storage",
    "wof:placetype":"venue"
},
  "geometry": {"coordinates":[-72.783002,41.563284],"type":"Point"}
}