{
  "type": "Feature",
  "properties": {
    "iso:country":"US",
    "sg:address":"1761 Post Rd E",
    "sg:city":"Westport",
    "sg:classifiers":[
        {
            "category":"Wholesale",
            "subcategory":"Seafood",
            "type":"Manufacturing & Wholesale Goods"
        }
    ],
    "sg:phone":"+1 203 259 2153",
    "sg:postcode":"06880",
    "sg:province":"CT",
    "wof:name":"Westfair Fish Market Inc",
    "wof:placetype":"venue"
},
  "geometry": {"coordinates":[-73.300085,41.138291],"type":"Point"}
}