{
  "type": "Feature",
  "properties": {
    "iso:country":"US",
    "sg:address":"168 Irving Ave",
    "sg:city":"Port Chester",
    "sg:classifiers":[
        {
            "category":"Wholesale",
            "subcategory":"Apparel",
            "type":"Manufacturing & Wholesale Goods"
        },
        {
            "category":"Manufacturing",
            "subcategory":"Printing",
            "type":"Manufacturing & Wholesale Goods"
        }
    ],
    "sg:phone":"+1 914 937 5959",
    "sg:postcode":"10573",
    "sg:province":"CT",
    "sg:tags":[
        "ready",
        "screen",
        "clothing",
        "f"
    ],
    "wof:name":"Vellone Enterprises Inc",
    "wof:placetype":"venue"
},
  "geometry": {"coordinates":[-73.66579400000001,41.002563],"type":"Point"}
}