{
  "type": "Feature",
  "properties": {
    "iso:country":"US",
    "sg:address":"230 Depot Rd",
    "sg:city":"Milford",
    "sg:classifiers":[
        {
            "category":"Manufacturing",
            "subcategory":"Tools & Machinery",
            "type":"Manufacturing & Wholesale Goods"
        }
    ],
    "sg:phone":"+1 203 878 4648",
    "sg:postcode":"06460",
    "sg:province":"CT",
    "sg:tags":[
        "pump"
    ],
    "sg:website":"www.interfacedevices.com",
    "wof:name":"Interface Devices Inc",
    "wof:placetype":"venue"
},
  "geometry": {"coordinates":[-73.002872,41.242396],"type":"Point"}
}