{
  "type": "Feature",
  "properties": {
    "iso:country":"US",
    "sg:address":"40 Barton Dr",
    "sg:city":"North Haven",
    "sg:classifiers":[
        {
            "category":"Building & Trades",
            "subcategory":"Construction",
            "type":"Services"
        }
    ],
    "sg:phone":"+1 203 288 0735",
    "sg:postcode":"06473",
    "sg:province":"CT",
    "sg:tags":[
        "house",
        "general",
        "contractor"
    ],
    "wof:name":"William D Frame & Son Inc",
    "wof:placetype":"venue"
},
  "geometry": {"coordinates":[-72.896953,41.38153],"type":"Point"}
}