{
  "type": "Feature",
  "properties": {
    "addr:full":"3 Davenport Ave Westport CT 06880",
    "addr:housenumber":"3",
    "addr:postcode":"06880",
    "addr:street":"Davenport Ave",
    "iso:country":"US",
    "sg:address":"3 Davenport Ave",
    "sg:city":"Westport",
    "sg:classifiers":[
        {
            "category":"Building & Trades",
            "subcategory":"Landscaping Services",
            "type":"Services"
        }
    ],
    "sg:phone":"+1 203 226 9395",
    "sg:postcode":"06880",
    "sg:province":"CT",
    "sg:tags":[
        "landscape",
        "contractor"
    ],
    "wof:name":"Palmieri & Sons Nurseries",
    "wof:placetype":"venue"
},
  "geometry": {"coordinates":[-73.37817,41.118304],"type":"Point"}
}