{
  "type": "Feature",
  "properties": {
    "addr:full":"461 E Main St Waterbury CT 06702",
    "addr:housenumber":"461",
    "addr:postcode":"06702",
    "addr:street":"E Main St",
    "iso:country":"US",
    "sg:address":"461 E Main St",
    "sg:city":"Waterbury",
    "sg:classifiers":[
        {
            "category":"Retail",
            "subcategory":"Auto Repair",
            "type":"Services"
        }
    ],
    "sg:phone":"+1   ",
    "sg:postcode":"06702",
    "sg:province":"CT",
    "sg:tags":[
        "general"
    ],
    "wof:name":"Super Soto Performance & Auto",
    "wof:placetype":"venue"
},
  "geometry": {"coordinates":[-73.033658,41.554525],"type":"Point"}
}