{
  "type": "Feature",
  "properties": {
    "iso:country":"US",
    "sg:address":"267 Sport Hill Rd",
    "sg:city":"Easton",
    "sg:classifiers":[
        {
            "category":"Health Services",
            "subcategory":"Chiropractor",
            "type":"Services"
        }
    ],
    "sg:phone":"+1 203 371 6004",
    "sg:postcode":"06612",
    "sg:province":"CT",
    "wof:name":"Sport Hill Chiropractic LLC",
    "wof:placetype":"venue"
},
  "geometry": {"coordinates":[-73.26907,41.238022],"type":"Point"}
}