{
  "type": "Feature",
  "properties": {
    "iso:country":"US",
    "sg:address":"12 Ridge Rd",
    "sg:city":"Ellington",
    "sg:classifiers":[
        {
            "category":"Professional",
            "subcategory":"Computer Services",
            "type":"Services"
        }
    ],
    "sg:phone":"+1   ",
    "sg:postcode":"06029",
    "sg:province":"CT",
    "sg:tags":[
        "related"
    ],
    "wof:name":"Cyber Guard Corporation",
    "wof:placetype":"venue"
},
  "geometry": {"coordinates":[-72.43606800000001,41.902643],"type":"Point"}
}