{
  "type": "Feature",
  "properties": {
    "iso:country":"US",
    "sg:address":"26 Whitney Ave",
    "sg:city":"New Haven",
    "sg:classifiers":[
        {
            "category":"Shopping",
            "subcategory":"Florist",
            "type":"Retail Goods"
        }
    ],
    "sg:phone":"+1 203 772 2229",
    "sg:postcode":"06510",
    "sg:province":"CT",
    "sg:website":"www.michaelsflowersltd.com",
    "wof:name":"Michael's Flowers LTD",
    "wof:placetype":"venue"
},
  "geometry": {"coordinates":[-72.92263,41.310512],"type":"Point"}
}