{
  "type": "Feature",
  "properties": {
    "iso:country":"US",
    "sg:address":"2 S Forest Cir",
    "sg:city":"West Haven",
    "sg:classifiers":[
        {
            "category":"Shopping",
            "subcategory":"Florist",
            "type":"Retail Goods"
        }
    ],
    "sg:phone":"+1 203 933 7444",
    "sg:postcode":"06516",
    "sg:province":"CT",
    "wof:name":"A Secret Garden",
    "wof:placetype":"venue"
},
  "geometry": {"coordinates":[-72.974121,41.308173],"type":"Point"}
}