{
  "type": "Feature",
  "properties": {
    "iso:country":"US",
    "sg:address":"139 Main St",
    "sg:city":"Seymour",
    "sg:classifiers":[
        {
            "category":"Personal",
            "subcategory":"Beauty Salon",
            "type":"Services"
        },
        {
            "category":"Personal",
            "subcategory":"Barber",
            "type":"Services"
        }
    ],
    "sg:phone":"+1 203 888 7400",
    "sg:postcode":"06483",
    "sg:province":"CT",
    "sg:tags":[
        "shop"
    ],
    "wof:name":"Valenti's Cut & Style",
    "wof:placetype":"venue"
},
  "geometry": {"coordinates":[-73.07350099999999,41.394125],"type":"Point"}
}