{
  "type": "Feature",
  "properties": {
    "addr:full":"191 N Main St Norwich CT 06360",
    "addr:housenumber":"191",
    "addr:postcode":"06360",
    "addr:street":"N Main St",
    "iso:country":"US",
    "sg:address":"191 N Main St",
    "sg:city":"Norwich",
    "sg:classifiers":[
        {
            "category":"Retail",
            "subcategory":"Auto Repair",
            "type":"Services"
        }
    ],
    "sg:phone":"+1   ",
    "sg:postcode":"06360",
    "sg:province":"CT",
    "sg:tags":[
        "transmission"
    ],
    "wof:name":"Smith Brothers Transmissions",
    "wof:placetype":"venue"
},
  "geometry": {"coordinates":[-72.06395500000001,41.527552],"type":"Point"}
}