{
  "type": "Feature",
  "properties": {
    "addr:full":"799 Peck Ln Cheshire CT 06410",
    "addr:housenumber":"799",
    "addr:postcode":"06410",
    "addr:street":"Peck Ln",
    "iso:country":"US",
    "sg:address":"799 Peck Ln",
    "sg:city":"Cheshire",
    "sg:classifiers":[
        {
            "category":"Building & Trades",
            "subcategory":"Construction",
            "type":"Services"
        }
    ],
    "sg:phone":"+1 203 272 9417",
    "sg:postcode":"06410",
    "sg:province":"CT",
    "sg:tags":[
        "carpentry",
        "contractor"
    ],
    "wof:name":"Bouteiller Carpentry",
    "wof:placetype":"venue"
},
  "geometry": {"coordinates":[-72.914585,41.522746],"type":"Point"}
}