{
  "type": "Feature",
  "properties": {
    "iso:country":"US",
    "sg:address":"58 Kent Rd",
    "sg:city":"Wilton",
    "sg:classifiers":[
        {
            "category":"Real Estate",
            "subcategory":"Real Estate Agent",
            "type":"Services"
        }
    ],
    "sg:phone":"+1 203 563 9282",
    "sg:postcode":"06897",
    "sg:province":"CT",
    "wof:name":"John Kantzas Realty LLC",
    "wof:placetype":"venue"
},
  "geometry": {"coordinates":[-73.42451699999999,41.162332],"type":"Point"}
}