{
  "type": "Feature",
  "properties": {
    "addr:full":"10 Carter Hill Rd Fairfield CT 06413",
    "addr:housenumber":"10",
    "addr:postcode":"06413",
    "addr:street":"Carter Hill Rd",
    "iso:country":"US",
    "sg:address":"10 Carter Hill Rd",
    "sg:city":"Fairfield",
    "sg:classifiers":[
        {
            "category":"Real Estate",
            "subcategory":"Developer",
            "type":"Services"
        }
    ],
    "sg:phone":"+1 203 256 4000",
    "sg:postcode":"06413",
    "sg:province":"CT",
    "sg:website":"www.starwoodceruzzi.com",
    "wof:name":"Starwood Ceruzzi LLC",
    "wof:placetype":"venue"
},
  "geometry": {"coordinates":[-72.50560400000001,41.307341],"type":"Point"}
}