{
  "type": "Feature",
  "properties": {
    "addr:full":"145 N Ridge St Port Chester CT 10573",
    "addr:housenumber":"145",
    "addr:postcode":"10573",
    "addr:street":"N Ridge St Port Chester Ct",
    "iso:country":"US",
    "sg:address":"145 N Ridge St",
    "sg:city":"Port Chester",
    "sg:classifiers":[
        {
            "category":"Personal",
            "subcategory":"Beauty Salon",
            "type":"Services"
        }
    ],
    "sg:phone":"+1   ",
    "sg:postcode":"10573",
    "sg:province":"CT",
    "sg:tags":[
        "shop"
    ],
    "wof:name":"La Petite Inc",
    "wof:placetype":"venue"
},
  "geometry": {"coordinates":[-73.681451,41.016385],"type":"Point"}
}