{
  "type": "Feature",
  "properties": {
    "iso:country":"US",
    "sg:address":"322 Wells St",
    "sg:city":"Bridgeport",
    "sg:classifiers":[
        {
            "category":"Education",
            "subcategory":"School",
            "type":"Public Place"
        }
    ],
    "sg:phone":"+1   ",
    "sg:postcode":"06606",
    "sg:province":"CT",
    "wof:name":"Maplewood Annex",
    "wof:placetype":"venue"
},
  "geometry": {"coordinates":[-73.196111,41.193749],"type":"Point"}
}