{
  "type": "Feature",
  "properties": {
    "addr:full":"311 Edws Blvd Long Beach NY 11561",
    "addr:housenumber":"311",
    "addr:postcode":"11561",
    "addr:street":"Edws Blvd",
    "iso:country":"US",
    "sg:address":"311 Edws Blvd",
    "sg:city":"Long Beach",
    "sg:classifiers":[
        {
            "category":"Food & Beverages",
            "subcategory":"Liquor & Beverages",
            "type":"Retail Goods"
        }
    ],
    "sg:phone":"+1 516 431 0808",
    "sg:postcode":"11561",
    "sg:province":"NY",
    "sg:tags":[
        "beer",
        "spirit",
        "wine"
    ],
    "wof:name":"Lafayette Liquor Store",
    "wof:placetype":"venue"
},
  "geometry": {"coordinates":[-72.50925599999999,41.301059],"type":"Point"}
}