{
  "type": "Feature",
  "properties": {
    "iso:country":"US",
    "sg:address":"102 New Haven Ave",
    "sg:city":"Milford",
    "sg:classifiers":[
        {
            "category":"Social Services",
            "type":"Services"
        }
    ],
    "sg:phone":"+1 203 878 3897",
    "sg:postcode":"06460",
    "sg:province":"CT",
    "sg:tags":[
        "care",
        "center",
        "day"
    ],
    "wof:name":"Kennedy Center Project Bridge",
    "wof:placetype":"venue"
},
  "geometry": {"coordinates":[-73.053122,41.223192],"type":"Point"}
}