{
  "type": "Feature",
  "properties": {
    "iso:country":"US",
    "sg:address":"27 Garden Hill Cir",
    "sg:city":"Waterbury",
    "sg:classifiers":[
        {
            "category":"Building & Trades",
            "subcategory":"Construction",
            "type":"Services"
        }
    ],
    "sg:phone":"+1 203 755 0791",
    "sg:postcode":"06704",
    "sg:province":"CT",
    "sg:tags":[
        "house"
    ],
    "wof:name":"Ecolumbia Mason LLC",
    "wof:placetype":"venue"
},
  "geometry": {"coordinates":[-73.01757600000001,41.569014],"type":"Point"}
}