{
  "type": "Feature",
  "properties": {
    "iso:country":"US",
    "sg:address":"70 US Hwy 5",
    "sg:city":"East Hartford",
    "sg:classifiers":[
        {
            "category":"Building & Trades",
            "subcategory":"Landscaping Services",
            "type":"Services"
        }
    ],
    "sg:phone":"+1 860 528 6666",
    "sg:postcode":"06108",
    "sg:province":"CT",
    "sg:tags":[
        "landscape"
    ],
    "wof:name":"Central Property Services",
    "wof:placetype":"venue"
},
  "geometry": {"coordinates":[-72.626232,41.792362],"type":"Point"}
}