{
  "type": "Feature",
  "properties": {
    "iso:country":"US",
    "sg:address":"475 S Main St",
    "sg:city":"Cheshire",
    "sg:classifiers":[
        {
            "category":"Health Services",
            "subcategory":"Health Practitioner",
            "type":"Services"
        }
    ],
    "sg:phone":"+1 203 271 2928",
    "sg:postcode":"06410",
    "sg:province":"CT",
    "sg:tags":[
        "therapist",
        "physical"
    ],
    "wof:name":"Cheshire Physical Therapy",
    "wof:placetype":"venue"
},
  "geometry": {"coordinates":[-72.90449599999999,41.490543],"type":"Point"}
}