{
  "type": "Feature",
  "properties": {
    "iso:country":"US",
    "sg:address":"865 Branch Rd",
    "sg:city":"Suffield",
    "sg:classifiers":[
        {
            "category":"Retail",
            "subcategory":"Repair Shop",
            "type":"Services"
        }
    ],
    "sg:phone":"+1   ",
    "sg:postcode":"06078",
    "sg:province":"CT",
    "wof:name":"Bruce Engel",
    "wof:placetype":"venue"
},
  "geometry": {"coordinates":[-72.62846500000001,41.960231],"type":"Point"}
}