{
  "type": "Feature",
  "properties": {
    "iso:country":"US",
    "sg:address":"148 Rowayton Ave",
    "sg:city":"Norwalk",
    "sg:classifiers":[
        {
            "category":"Restaurant",
            "type":"Food & Drink"
        }
    ],
    "sg:phone":"+1 203 854 0860",
    "sg:postcode":"06853",
    "sg:province":"CT",
    "wof:name":"River Cat Grill",
    "wof:placetype":"venue"
},
  "geometry": {"coordinates":[-73.44347,41.068127],"type":"Point"}
}