{
  "type": "Feature",
  "properties": {
    "iso:country":"US",
    "sg:address":"2 Meeting House Ln",
    "sg:city":"Enfield",
    "sg:classifiers":[
        {
            "category":"Structure",
            "subcategory":"Office Building",
            "type":"Public Place"
        }
    ],
    "sg:phone":"+1 860 745 9456",
    "sg:postcode":"06082",
    "sg:province":"CT",
    "sg:tags":[
        "park"
    ],
    "wof:name":"Select 1 Properties",
    "wof:placetype":"venue"
},
  "geometry": {"coordinates":[-72.599677,41.974244],"type":"Point"}
}