{
  "type": "Feature",
  "properties": {
    "iso:country":"US",
    "sg:address":"2300 Dixwell Ave",
    "sg:city":"Hamden",
    "sg:classifiers":[
        {
            "category":"Health Services",
            "subcategory":"Optometrist",
            "type":"Services"
        }
    ],
    "sg:phone":"+1   ",
    "sg:postcode":"06514",
    "sg:province":"CT",
    "wof:name":"Conrod Thomas",
    "wof:placetype":"venue"
},
  "geometry": {"coordinates":[-72.91751600000001,41.371892],"type":"Point"}
}