{
  "type": "Feature",
  "properties": {
    "addr:full":"301 Main St Ansonia CT 06401",
    "addr:housenumber":"301",
    "addr:postcode":"06401",
    "addr:street":"Main St",
    "iso:country":"US",
    "sg:address":"301 Main St",
    "sg:city":"Ansonia",
    "sg:classifiers":[
        {
            "category":"Professional",
            "subcategory":"Credit Reporting & Collection",
            "type":"Services"
        }
    ],
    "sg:phone":"+1 203 735 6443",
    "sg:postcode":"06401",
    "sg:province":"CT",
    "sg:tags":[
        "agency"
    ],
    "wof:name":"Ansonia Credit Bureau Inc",
    "wof:placetype":"venue"
},
  "geometry": {"coordinates":[-73.07831299999999,41.341989],"type":"Point"}
}