{
  "type": "Feature",
  "properties": {
    "addr:full":"69 Jackson Cove Rd Oxford CT 06478",
    "addr:housenumber":"69",
    "addr:postcode":"06478",
    "addr:street":"Jackson Cove Rd",
    "iso:country":"US",
    "sg:address":"69 Jackson Cove Rd",
    "sg:city":"Oxford",
    "sg:classifiers":[
        {
            "category":"Building & Trades",
            "subcategory":"Plumbing",
            "type":"Services"
        }
    ],
    "sg:phone":"+1 203 888 4860",
    "sg:postcode":"06478",
    "sg:province":"CT",
    "sg:tags":[
        "air",
        "heating",
        "conditioning",
        "contractor"
    ],
    "wof:name":"Peter N Mitchell",
    "wof:placetype":"venue"
},
  "geometry": {"coordinates":[-73.190611,41.415609],"type":"Point"}
}