{
  "type": "Feature",
  "properties": {
    "addr:full":"18 Mario Ct East Haven CT 06512",
    "addr:housenumber":"18",
    "addr:postcode":"06512",
    "addr:street":"Mario Ct",
    "iso:country":"US",
    "sg:address":"18 Mario Ct",
    "sg:city":"East Haven",
    "sg:classifiers":[
        {
            "category":"Health Services",
            "subcategory":"Health Practitioner",
            "type":"Services"
        }
    ],
    "sg:phone":"+1   ",
    "sg:postcode":"06512",
    "sg:province":"CT",
    "wof:name":"Wellness Center",
    "wof:placetype":"venue"
},
  "geometry": {"coordinates":[-72.854765,41.308215],"type":"Point"}
}