{
  "type": "Feature",
  "properties": {
    "addr:full":"40 Ripton Rd Shelton CT 06484",
    "addr:housenumber":"40",
    "addr:postcode":"06484",
    "addr:street":"Ripton Rd",
    "iso:country":"US",
    "sg:address":"40 Ripton Rd",
    "sg:city":"Shelton",
    "sg:classifiers":[
        {
            "category":"Health Services",
            "subcategory":"Doctor",
            "type":"Services"
        }
    ],
    "sg:phone":"+1 203 929 2007",
    "sg:postcode":"06484",
    "sg:province":"CT",
    "sg:tags":[
        "physician",
        "surgeon"
    ],
    "wof:name":"Pri-Med",
    "wof:placetype":"venue"
},
  "geometry": {"coordinates":[-73.152608,41.297142],"type":"Point"}
}