{
  "type": "Feature",
  "properties": {
    "iso:country":"US",
    "sg:address":"27 Quarry St",
    "sg:city":"Willimantic",
    "sg:classifiers":[
        {
            "category":"Professional",
            "subcategory":"Business Services",
            "type":"Services"
        }
    ],
    "sg:phone":"+1   ",
    "sg:postcode":"06226",
    "sg:province":"CT",
    "wof:name":"Rs Residential Solutions LLC",
    "wof:placetype":"venue"
},
  "geometry": {"coordinates":[-72.227069,41.721395],"type":"Point"}
}