{
  "type": "Feature",
  "properties": {
    "addr:full":"2 Sylvia Ln Windsor CT 06095",
    "addr:housenumber":"2",
    "addr:postcode":"06095",
    "addr:street":"Sylvia Ln",
    "iso:country":"US",
    "sg:address":"2 Sylvia Ln",
    "sg:city":"Windsor",
    "sg:classifiers":[
        {
            "category":"Health Services",
            "subcategory":"Health Practitioner",
            "type":"Services"
        }
    ],
    "sg:phone":"+1   ",
    "sg:postcode":"06095",
    "sg:province":"CT",
    "wof:name":"Center Fr Psychthrpy & Hmn",
    "wof:placetype":"venue"
},
  "geometry": {"coordinates":[-72.669701,41.860224],"type":"Point"}
}