{
  "type": "Feature",
  "properties": {
    "iso:country":"US",
    "sg:address":"377 Sackett Point Rd",
    "sg:city":"North Haven",
    "sg:classifiers":[
        {
            "category":"Building & Trades",
            "subcategory":"Construction",
            "type":"Services"
        }
    ],
    "sg:phone":"+1 203 288 2361",
    "sg:postcode":"06473",
    "sg:province":"CT",
    "sg:tags":[
        "product",
        "material",
        "c",
        "asphalt"
    ],
    "wof:name":"Tilcon Connecticut Inc",
    "wof:placetype":"venue"
},
  "geometry": {"coordinates":[-72.87909500000001,41.36771],"type":"Point"}
}