{
  "type": "Feature",
  "properties": {
    "iso:country":"US",
    "sg:address":"401 Noble Ave",
    "sg:city":"Bridgeport",
    "sg:classifiers":[
        {
            "category":"Freight",
            "type":"Transportation"
        }
    ],
    "sg:phone":"+1 203 336 6977",
    "sg:postcode":"06608",
    "sg:province":"CT",
    "sg:tags":[
        "mover"
    ],
    "wof:name":"Moving Time",
    "wof:placetype":"venue"
},
  "geometry": {"coordinates":[-73.184575,41.186128],"type":"Point"}
}