{
  "type": "Feature",
  "properties": {
    "iso:country":"US",
    "sg:address":"291 Farmington Ave",
    "sg:city":"Farmington",
    "sg:classifiers":[
        {
            "category":"Health Services",
            "subcategory":"Medical Lab",
            "type":"Services"
        }
    ],
    "sg:phone":"+1   ",
    "sg:postcode":"06032",
    "sg:province":"CT",
    "sg:tags":[
        "laboratory",
        "dental"
    ],
    "wof:name":"Hansen Dental Lab",
    "wof:placetype":"venue"
},
  "geometry": {"coordinates":[-72.79742299999999,41.733114],"type":"Point"}
}