{
  "type": "Feature",
  "properties": {
    "iso:country":"US",
    "sg:address":"35 Wyman St",
    "sg:city":"Waterbury",
    "sg:classifiers":[
        {
            "category":"Building & Trades",
            "subcategory":"Electrical",
            "type":"Services"
        }
    ],
    "sg:phone":"+1 203 755 7625",
    "sg:postcode":"06710",
    "sg:province":"CT",
    "sg:tags":[
        "electric",
        "contractor"
    ],
    "wof:name":"Star Electric Co",
    "wof:placetype":"venue"
},
  "geometry": {"coordinates":[-73.050684,41.56388],"type":"Point"}
}