{
  "type": "Feature",
  "properties": {
    "addr:full":"73 Old Colchester Rd Amston CT 06231",
    "addr:housenumber":"73",
    "addr:postcode":"06231",
    "addr:street":"Old Colchester Rd Amston Ct",
    "iso:country":"US",
    "sg:address":"73 Old Colchester Rd",
    "sg:city":"Amston",
    "sg:classifiers":[
        {
            "category":"Professional",
            "type":"Services"
        }
    ],
    "sg:phone":"+1   ",
    "sg:postcode":"06231",
    "sg:province":"CT",
    "wof:name":"ECL Forensics LLC",
    "wof:placetype":"venue"
},
  "geometry": {"coordinates":[-72.357298,41.63585],"type":"Point"}
}