{
  "type": "Feature",
  "properties": {
    "addr:full":"60 Columbus Blvd Hartford CT 06103",
    "addr:housenumber":"60",
    "addr:postcode":"06103",
    "addr:street":"Columbus Blvd;Ct",
    "iso:country":"US",
    "sg:address":"60 Columbus Blvd",
    "sg:city":"Hartford",
    "sg:classifiers":[
        {
            "category":"Utilities",
            "subcategory":"Natural Gas",
            "type":"Services"
        }
    ],
    "sg:phone":"+1 860 548 7350",
    "sg:postcode":"06103",
    "sg:province":"CT",
    "sg:tags":[
        "pipeline"
    ],
    "wof:name":"Ten Transmission Company",
    "wof:placetype":"venue"
},
  "geometry": {"coordinates":[-72.670377,41.761346],"type":"Point"}
}