{
  "type": "Feature",
  "properties": {
    "addr:full":"150 Greenwood Dr Manchester CT 06042",
    "addr:housenumber":"150",
    "addr:postcode":"06042",
    "addr:street":"Greenwood Dr",
    "iso:country":"US",
    "sg:address":"150 Greenwood Dr",
    "sg:city":"Manchester",
    "sg:classifiers":[
        {
            "category":"Freight",
            "type":"Transportation"
        }
    ],
    "sg:phone":"+1 860 645 7461",
    "sg:postcode":"06042",
    "sg:province":"CT",
    "sg:tags":[
        "operator",
        "local",
        "trucking"
    ],
    "wof:name":"Tourville Trucking",
    "wof:placetype":"venue"
},
  "geometry": {"coordinates":[-72.48978700000001,41.79326],"type":"Point"}
}