{
  "type": "Feature",
  "properties": {
    "iso:country":"US",
    "sg:address":"41 Shuba Ln",
    "sg:city":"Chaplin",
    "sg:classifiers":[
        {
            "category":"Banks & Credit Unions",
            "subcategory":"Financial Services",
            "type":"Services"
        }
    ],
    "sg:phone":"+1 860 455 9358",
    "sg:postcode":"06235",
    "sg:province":"CT",
    "sg:tags":[
        "investor"
    ],
    "wof:name":"Pogia Investment Property Mana",
    "wof:placetype":"venue"
},
  "geometry": {"coordinates":[-72.15414800000001,41.767326],"type":"Point"}
}