{
  "type": "Feature",
  "properties": {
    "iso:country":"US",
    "sg:address":"15 Putnam Ln",
    "sg:city":"Enfield",
    "sg:classifiers":[
        {
            "category":"Professional",
            "subcategory":"Business Services",
            "type":"Services"
        }
    ],
    "sg:phone":"+1   ",
    "sg:postcode":"06082",
    "sg:province":"CT",
    "wof:name":"Callahan Plumbing & Heating",
    "wof:placetype":"venue"
},
  "geometry": {"coordinates":[-72.509799,41.996377],"type":"Point"}
}