{
  "type": "Feature",
  "properties": {
    "iso:country":"US",
    "sg:address":"51 Hillhouse Ave",
    "sg:city":"New Haven",
    "sg:classifiers":[
        {
            "category":"Professional",
            "subcategory":"Management & Consulting",
            "type":"Services"
        }
    ],
    "sg:phone":"+1   ",
    "sg:postcode":"06511",
    "sg:province":"CT",
    "sg:tags":[
        "business"
    ],
    "wof:name":"Richard Lawler",
    "wof:placetype":"venue"
},
  "geometry": {"coordinates":[-72.92305500000001,41.314375],"type":"Point"}
}