{
  "type": "Feature",
  "properties": {
    "iso:country":"US",
    "sg:address":"320 Coram Ave",
    "sg:city":"Shelton",
    "sg:classifiers":[
        {
            "category":"Banks & Credit Unions",
            "subcategory":"Bank",
            "type":"Services"
        }
    ],
    "sg:phone":"+1 203 924 5300",
    "sg:postcode":"06484",
    "sg:province":"CT",
    "sg:tags":[
        "federal",
        "savings",
        "institution"
    ],
    "wof:name":"Wachovia Bank National Assn",
    "wof:placetype":"venue"
},
  "geometry": {"coordinates":[-73.09374,41.316031],"type":"Point"}
}