{
  "type": "Feature",
  "properties": {
    "iso:country":"US",
    "sg:address":"12 Wynwood Ct",
    "sg:city":"Goshen",
    "sg:classifiers":[
        {
            "category":"Health Services",
            "subcategory":"Doctor",
            "type":"Services"
        }
    ],
    "sg:phone":"+1   ",
    "sg:postcode":"06756",
    "sg:province":"CT",
    "sg:tags":[
        "medical"
    ],
    "wof:name":"Joseph Rechtschaffen Dr",
    "wof:placetype":"venue"
},
  "geometry": {"coordinates":[-73.251121,41.793986],"type":"Point"}
}