{
  "type": "Feature",
  "properties": {
    "iso:country":"US",
    "sg:address":"68 Peters Cir",
    "sg:city":"Southington",
    "sg:classifiers":[
        {
            "category":"Building & Trades",
            "subcategory":"Pest Control",
            "type":"Services"
        }
    ],
    "sg:phone":"+1   ",
    "sg:postcode":"06489",
    "sg:province":"CT",
    "wof:name":"Pest Control 2000 LLC",
    "wof:placetype":"venue"
},
  "geometry": {"coordinates":[-72.863696,41.594208],"type":"Point"}
}