{
  "type": "Feature",
  "properties": {
    "addr:full":"23 Commerce Rd Newtown CT 06470",
    "addr:housenumber":"23",
    "addr:postcode":"06470",
    "addr:street":"Commerce Rd",
    "iso:country":"US",
    "sg:address":"23 Commerce Rd",
    "sg:city":"Newtown",
    "sg:classifiers":[
        {
            "category":"Sports & Exercise",
            "subcategory":"Gym",
            "type":"Entertainment"
        }
    ],
    "sg:phone":"+1 203 426 8591",
    "sg:postcode":"06470",
    "sg:province":"CT",
    "sg:tags":[
        "club",
        "health",
        "studio",
        "gymnasium"
    ],
    "wof:name":"Gym At Newtown",
    "wof:placetype":"venue"
},
  "geometry": {"coordinates":[-73.284143,41.414764],"type":"Point"}
}