{
  "type": "Feature",
  "properties": {
    "addr:full":"11 Mountainville Ave Danbury CT 06810",
    "addr:housenumber":"11",
    "addr:postcode":"06810",
    "addr:street":"Mountainville Ave",
    "iso:country":"US",
    "sg:address":"11 Mountainville Ave",
    "sg:city":"Danbury",
    "sg:classifiers":[
        {
            "category":"Professional",
            "type":"Services"
        }
    ],
    "sg:phone":"+1 203 739 0157",
    "sg:postcode":"06810",
    "sg:province":"CT",
    "wof:name":"Celb LLC",
    "wof:placetype":"venue"
},
  "geometry": {"coordinates":[-73.44535500000001,41.384253],"type":"Point"}
}