{
  "type": "Feature",
  "properties": {
    "addr:full":"20 Nunnawauk Rd Newtown CT 06470",
    "addr:housenumber":"20",
    "addr:postcode":"06470",
    "addr:street":"Nunnawauk Rd",
    "iso:country":"US",
    "sg:address":"20 Nunnawauk Rd",
    "sg:city":"Newtown",
    "sg:classifiers":[
        {
            "category":"Professional",
            "type":"Services"
        }
    ],
    "sg:phone":"+1 203 426 9956",
    "sg:postcode":"06470",
    "sg:province":"CT",
    "wof:name":"Michael Leonard Svc",
    "wof:placetype":"venue"
},
  "geometry": {"coordinates":[-73.278719,41.395665],"type":"Point"}
}