{
  "type": "Feature",
  "properties": {
    "iso:country":"US",
    "sg:address":"236 Carriage Way",
    "sg:city":"Windsor",
    "sg:classifiers":[
        {
            "category":"Building & Trades",
            "subcategory":"Landscaping Services",
            "type":"Services"
        },
        {
            "category":"Professional",
            "type":"Services"
        },
        {
            "category":"Building & Trades",
            "subcategory":"Construction",
            "type":"Services"
        }
    ],
    "sg:phone":"+1 866 493 1398",
    "sg:postcode":"06095",
    "sg:province":"CT",
    "sg:tags":[
        "lawn",
        "designer",
        "installation",
        "consultant",
        "sprinklers-garden",
        "tree",
        "fertilizing",
        "industrial",
        "contractors-commercial",
        "maintenance",
        "arborist",
        "masonry",
        "landscape"
    ],
    "wof:name":"Green Streak Landscape and Garden Service",
    "wof:placetype":"venue"
},
  "geometry": {"coordinates":[-72.629791,41.87957],"type":"Point"}
}