{
  "type": "Feature",
  "properties": {
    "addr:full":"765 S End Rd Plantsville CT 06479",
    "addr:housenumber":"765",
    "addr:postcode":"06479",
    "addr:street":"S End Rd",
    "iso:country":"US",
    "sg:address":"765 S End Rd",
    "sg:city":"Plantsville",
    "sg:classifiers":[
        {
            "category":"Retail",
            "subcategory":"Veterinary Services",
            "type":"Services"
        }
    ],
    "sg:phone":"+1 860 276 8553",
    "sg:postcode":"06479",
    "sg:province":"CT",
    "sg:tags":[
        "hospital",
        "animal"
    ],
    "wof:name":"Mountain Lore Animal Hospital",
    "wof:placetype":"venue"
},
  "geometry": {"coordinates":[-72.870329,41.557131],"type":"Point"}
}