{
  "type": "Feature",
  "properties": {
    "iso:country":"US",
    "sg:address":"15 Parker Farms Rd",
    "sg:city":"Wallingford",
    "sg:classifiers":[
        {
            "category":"Food & Beverages",
            "subcategory":"Groceries & Convenience Stores",
            "type":"Retail Goods"
        }
    ],
    "sg:phone":"+1 203 294 0323",
    "sg:postcode":"06492",
    "sg:province":"CT",
    "sg:tags":[
        "bakery"
    ],
    "wof:name":"Lyman Bagels",
    "wof:placetype":"venue"
},
  "geometry": {"coordinates":[-72.833369,41.476413],"type":"Point"}
}