{
  "type": "Feature",
  "properties": {
    "addr:full":"668 Bank St New London CT 06320",
    "addr:housenumber":"668",
    "addr:postcode":"06320",
    "addr:street":"Bank St New London Ct",
    "iso:country":"US",
    "sg:address":"668 Bank St",
    "sg:city":"New London",
    "sg:classifiers":[
        {
            "category":"Banks & Credit Unions",
            "subcategory":"Bank",
            "type":"Services"
        }
    ],
    "sg:phone":"+1 860 437 4366",
    "sg:postcode":"06320",
    "sg:province":"CT",
    "sg:tags":[
        "commercial"
    ],
    "wof:name":"Dime Savings Bank",
    "wof:placetype":"venue"
},
  "geometry": {"coordinates":[-72.103967,41.349532],"type":"Point"}
}