{
  "type": "Feature",
  "properties": {
    "iso:country":"US",
    "sg:address":"110 Cedar Rd",
    "sg:city":"Wilton",
    "sg:classifiers":[
        {
            "category":"Professional",
            "subcategory":"Business Services",
            "type":"Services"
        }
    ],
    "sg:phone":"+1   ",
    "sg:postcode":"06897",
    "sg:province":"CT",
    "wof:name":"Landmark Strategy Group LLC",
    "wof:placetype":"venue"
},
  "geometry": {"coordinates":[-73.393489,41.198332],"type":"Point"}
}