{
  "type": "Feature",
  "properties": {
    "addr:full":"51 Cathole Rd Bantam CT 06750",
    "addr:housenumber":"51",
    "addr:postcode":"06750",
    "addr:street":"Cathole Rd Bantam Ct",
    "iso:country":"US",
    "sg:address":"51 Cathole Rd",
    "sg:city":"Bantam",
    "sg:classifiers":[
        {
            "category":"Professional",
            "type":"Services"
        }
    ],
    "sg:phone":"+1 860 567 8457",
    "sg:postcode":"06750",
    "sg:province":"CT",
    "wof:name":"C Mackenzie Enos",
    "wof:placetype":"venue"
},
  "geometry": {"coordinates":[-73.25020600000001,41.727865],"type":"Point"}
}