{
  "type": "Feature",
  "properties": {
    "addr:full":"110 Albany Tpke Ste 1015 Canton CT 06019",
    "addr:housenumber":"110;1015",
    "addr:postcode":"06019",
    "addr:street":"Albany Tpke Ste;Canton Ct",
    "iso:country":"US",
    "sg:address":"110 Albany Tpke Ste 1015",
    "sg:city":"Canton",
    "sg:classifiers":[
        {
            "category":"Shopping",
            "subcategory":"Hobbies, Toys, & Games",
            "type":"Retail Goods"
        }
    ],
    "sg:phone":"+1 860 693 8014",
    "sg:postcode":"06019",
    "sg:province":"CT",
    "sg:tags":[
        "toy",
        "store"
    ],
    "sg:website":"www.kiddlywinks.com",
    "wof:name":"Kiddly Winks",
    "wof:placetype":"venue"
},
  "geometry": {"coordinates":[-72.883681,41.823803],"type":"Point"}
}