{
  "type": "Feature",
  "properties": {
    "addr:full":"2023 Old Pond Ln Norwich CT 06360",
    "addr:housenumber":"2023",
    "addr:postcode":"06360",
    "addr:street":"Old Pond Ln",
    "iso:country":"US",
    "sg:address":"2023 Old Pond Ln",
    "sg:city":"Norwich",
    "sg:classifiers":[
        {
            "category":"Professional",
            "subcategory":"Business Services",
            "type":"Services"
        }
    ],
    "sg:phone":"+1   ",
    "sg:postcode":"06360",
    "sg:province":"CT",
    "wof:name":"Mystic Sales Design",
    "wof:placetype":"venue"
},
  "geometry": {"coordinates":[-72.096138,41.500974],"type":"Point"}
}