{
  "type": "Feature",
  "properties": {
    "addr:full":"24 Long Pond Rd S Ledyard CT 06339",
    "addr:housenumber":"24",
    "addr:postcode":"06339",
    "addr:street":"Long Pond Rd;Ledyard Ct",
    "iso:country":"US",
    "sg:address":"24 Long Pond Rd S",
    "sg:city":"Ledyard",
    "sg:classifiers":[
        {
            "category":"Building & Trades",
            "subcategory":"Construction",
            "type":"Services"
        }
    ],
    "sg:phone":"+1 860 536 7462",
    "sg:postcode":"06339",
    "sg:province":"CT",
    "sg:tags":[
        "contractor"
    ],
    "wof:name":"Mainly Stone Masonry",
    "wof:placetype":"venue"
},
  "geometry": {"coordinates":[-71.945809,41.43709],"type":"Point"}
}