{
  "type": "Feature",
  "properties": {
    "addr:full":"19 Andrews St Bethel CT 06801",
    "addr:housenumber":"19",
    "addr:postcode":"06801",
    "addr:street":"Andrews St Bethel Ct",
    "iso:country":"US",
    "sg:address":"19 Andrews St",
    "sg:city":"Bethel",
    "sg:classifiers":[
        {
            "category":"Professional",
            "type":"Services"
        }
    ],
    "sg:phone":"+1 203 730 9761",
    "sg:postcode":"06801",
    "sg:province":"CT",
    "wof:name":"Fairwayweb",
    "wof:placetype":"venue"
},
  "geometry": {"coordinates":[-73.400035,41.372665],"type":"Point"}
}