{
  "type": "Feature",
  "properties": {
    "addr:full":"127 Scott Rd Waterbury CT 06705",
    "addr:housenumber":"127",
    "addr:postcode":"06705",
    "addr:street":"Scott Rd",
    "iso:country":"US",
    "sg:address":"127 Scott Rd",
    "sg:city":"Waterbury",
    "sg:classifiers":[
        {
            "category":"Retail",
            "subcategory":"Laundry & Dry Cleaning",
            "type":"Services"
        }
    ],
    "sg:phone":"+1   ",
    "sg:postcode":"06705",
    "sg:province":"CT",
    "sg:tags":[
        "drycleaning",
        "plant"
    ],
    "wof:name":"Chascher Cleaners",
    "wof:placetype":"venue"
},
  "geometry": {"coordinates":[-72.990861,41.537959],"type":"Point"}
}