{
  "type": "Feature",
  "properties": {
    "iso:country":"US",
    "sg:address":"81 State St",
    "sg:city":"New Haven",
    "sg:classifiers":[
        {
            "category":"Professional",
            "subcategory":"Testing Lab",
            "type":"Services"
        }
    ],
    "sg:phone":"+1 203 239 6558",
    "sg:postcode":"06511",
    "sg:province":"CT",
    "sg:tags":[
        "calibration"
    ],
    "wof:name":"Ralco Inc",
    "wof:placetype":"venue"
},
  "geometry": {"coordinates":[-72.92455200000001,41.302201],"type":"Point"}
}