{
  "type": "Feature",
  "properties": {
    "iso:country":"US",
    "sg:address":"375 Bridgeport Ave",
    "sg:city":"Shelton",
    "sg:classifiers":[
        {
            "category":"Professional",
            "subcategory":"Employment Agencies",
            "type":"Services"
        }
    ],
    "sg:phone":"+1   ",
    "sg:postcode":"06484",
    "sg:province":"CT",
    "wof:name":"Jaci Carroll Staffing",
    "wof:placetype":"venue"
},
  "geometry": {"coordinates":[-73.10562,41.299366],"type":"Point"}
}