{
  "type": "Feature",
  "properties": {
    "addr:full":"471 Monroe Tpke Monroe CT 06468",
    "addr:housenumber":"471",
    "addr:postcode":"06468",
    "addr:street":"Monroe Tpke Monroe Ct",
    "iso:country":"US",
    "sg:address":"471 Monroe Tpke",
    "sg:city":"Monroe",
    "sg:classifiers":[
        {
            "category":"Health Services",
            "subcategory":"Optometrist",
            "type":"Services"
        }
    ],
    "sg:phone":"+1 203 261 5783",
    "sg:postcode":"06468",
    "sg:province":"CT",
    "wof:name":"Donald S Fulton OD",
    "wof:placetype":"venue"
},
  "geometry": {"coordinates":[-73.21689499999999,41.315953],"type":"Point"}
}