{
  "type": "Feature",
  "properties": {
    "iso:country":"US",
    "sg:address":"14 Commercial St",
    "sg:city":"Branford",
    "sg:classifiers":[
        {
            "category":"Manufacturing",
            "subcategory":"Metals",
            "type":"Manufacturing & Wholesale Goods"
        }
    ],
    "sg:phone":"+1 203 481 4277",
    "sg:postcode":"06405",
    "sg:province":"CT",
    "sg:tags":[
        "foil",
        "product"
    ],
    "sg:website":"www.delkergrid.com",
    "wof:name":"Delker Corp",
    "wof:placetype":"venue"
},
  "geometry": {"coordinates":[-72.78342600000001,41.298516],"type":"Point"}
}