{
  "type": "Feature",
  "properties": {
    "iso:country":"US",
    "sg:address":"1401 N Colony St",
    "sg:city":"Meriden",
    "sg:classifiers":[
        {
            "category":"Retail",
            "subcategory":"Auto Repair",
            "type":"Services"
        }
    ],
    "sg:phone":"+1 203 237 5595",
    "sg:postcode":"06450",
    "sg:province":"CT",
    "sg:tags":[
        "repairing",
        "tire"
    ],
    "sg:website":"www.berlinbandag.com",
    "wof:name":"Berlin Bandag Inc",
    "wof:placetype":"venue"
},
  "geometry": {"coordinates":[-72.77847199999999,41.56875],"type":"Point"}
}