{
  "type": "Feature",
  "properties": {
    "addr:full":"1150 New Britain Ave West Hartford CT 06110",
    "addr:housenumber":"1150",
    "addr:postcode":"06110",
    "addr:street":"New Britain Ave",
    "iso:country":"US",
    "sg:address":"1150 New Britain Ave",
    "sg:city":"West Hartford",
    "sg:classifiers":[
        {
            "category":"Restaurant",
            "type":"Food & Drink"
        }
    ],
    "sg:menulink":"http://www.allmenus.com/ct/west-hartford/263043-tapas/menu/",
    "sg:phone":"+1 860 521 4609",
    "sg:postcode":"06110",
    "sg:province":"CT",
    "sg:tags":[
        "greek",
        "eastern",
        "mediterranean",
        "french",
        "middle",
        "spanish"
    ],
    "wof:name":"Tapas",
    "wof:placetype":"venue"
},
  "geometry": {"coordinates":[-72.734607,41.732658],"type":"Point"}
}