{
  "type": "Feature",
  "properties": {
    "addr:full":"2618 Long Ridge Rd Stamford CT 06903",
    "addr:housenumber":"2618",
    "addr:postcode":"06903",
    "addr:street":"Long Ridge Rd",
    "iso:country":"US",
    "sg:address":"2618 Long Ridge Rd",
    "sg:city":"Stamford",
    "sg:classifiers":[
        {
            "category":"Arts & Performance",
            "subcategory":"Theater",
            "type":"Entertainment"
        }
    ],
    "sg:phone":"+1 203 461 9544",
    "sg:postcode":"06903",
    "sg:province":"CT",
    "sg:tags":[
        "band",
        "orchestra"
    ],
    "wof:name":"Joe D'Elia The All Star Band",
    "wof:placetype":"venue"
},
  "geometry": {"coordinates":[-73.59132,41.14838],"type":"Point"}
}