{
  "type": "Feature",
  "properties": {
    "addr:full":"15 Homelands Ter Hamden CT 06517",
    "addr:housenumber":"15",
    "addr:postcode":"06517",
    "addr:street":"Homelands Ter Hamden Ct",
    "iso:country":"US",
    "sg:address":"15 Homelands Ter",
    "sg:city":"Hamden",
    "sg:classifiers":[
        {
            "category":"Professional",
            "subcategory":"Management & Consulting",
            "type":"Services"
        }
    ],
    "sg:phone":"+1   ",
    "sg:postcode":"06517",
    "sg:province":"CT",
    "sg:tags":[
        "training"
    ],
    "wof:name":"Good Work Associates Inc",
    "wof:placetype":"venue"
},
  "geometry": {"coordinates":[-72.9222,41.335337],"type":"Point"}
}