{
  "type": "Feature",
  "properties": {
    "iso:country":"US",
    "sg:address":"8 Branford Rd",
    "sg:city":"North Branford",
    "sg:classifiers":[
        {
            "category":"Manufacturing",
            "subcategory":"Rubber & Plastics",
            "type":"Manufacturing & Wholesale Goods"
        }
    ],
    "sg:phone":"+1 203 484 2181",
    "sg:postcode":"06471",
    "sg:province":"CT",
    "sg:tags":[
        "manufacture",
        "reflector",
        "too",
        "injection",
        "lense",
        "molded"
    ],
    "wof:name":"Finest Tool Co",
    "wof:placetype":"venue"
},
  "geometry": {"coordinates":[-72.770937,41.305494],"type":"Point"}
}