{
  "type": "Feature",
  "properties": {
    "addr:full":"9 Emerald St Norwalk CT 06850",
    "addr:housenumber":"9",
    "addr:postcode":"06850",
    "addr:street":"Emerald St",
    "iso:country":"US",
    "sg:address":"9 Emerald St",
    "sg:city":"Norwalk",
    "sg:classifiers":[
        {
            "category":"Wholesale",
            "subcategory":"Electrical",
            "type":"Manufacturing & Wholesale Goods"
        }
    ],
    "sg:phone":"+1 203 847 2992",
    "sg:postcode":"06850",
    "sg:province":"CT",
    "sg:tags":[
        "television"
    ],
    "wof:name":"Security Link From Ameritech",
    "wof:placetype":"venue"
},
  "geometry": {"coordinates":[-73.427363,41.137662],"type":"Point"}
}