{
  "type": "Feature",
  "properties": {
    "addr:full":"35 Buckland Way Windsor CT 06095",
    "addr:housenumber":"35",
    "addr:postcode":"06095",
    "addr:street":"Buckland Way",
    "iso:country":"US",
    "sg:address":"35 Buckland Way",
    "sg:city":"Windsor",
    "sg:classifiers":[
        {
            "category":"Professional",
            "subcategory":"Engineering",
            "type":"Services"
        }
    ],
    "sg:phone":"+1   ",
    "sg:postcode":"06095",
    "sg:province":"CT",
    "wof:name":"Howard E Neuschaefer",
    "wof:placetype":"venue"
},
  "geometry": {"coordinates":[-72.63279799999999,41.868448],"type":"Point"}
}