{
  "type": "Feature",
  "properties": {
    "addr:full":"1055 Summer St Stamford CT 06905",
    "addr:housenumber":"1055",
    "addr:postcode":"06905",
    "addr:street":"Summer St",
    "iso:country":"US",
    "sg:address":"1055 Summer St",
    "sg:city":"Stamford",
    "sg:classifiers":[
        {
            "category":"Real Estate",
            "subcategory":"Real Estate Agent",
            "type":"Services"
        }
    ],
    "sg:phone":"+1 203 327 5050",
    "sg:postcode":"06905",
    "sg:province":"CT",
    "wof:name":"Grubb & Ellis Company",
    "wof:placetype":"venue"
},
  "geometry": {"coordinates":[-73.54003,41.05954],"type":"Point"}
}