{
  "type": "Feature",
  "properties": {
    "addr:full":"125 Cross Rd Waterford CT 06385",
    "addr:housenumber":"125",
    "addr:postcode":"06385",
    "addr:street":"Cross Rd",
    "iso:country":"US",
    "sg:address":"125 Cross Rd",
    "sg:city":"Waterford",
    "sg:classifiers":[
        {
            "category":"Shopping",
            "subcategory":"Discount & Variety Stores",
            "type":"Retail Goods"
        }
    ],
    "sg:phone":"+1 860 437 3100",
    "sg:postcode":"06385",
    "sg:province":"CT",
    "sg:tags":[
        "warehouse",
        "club"
    ],
    "wof:name":"BJs Wholesale Club",
    "wof:placetype":"venue"
},
  "geometry": {"coordinates":[-72.165325,41.36768],"type":"Point"}
}