{
  "type": "Feature",
  "properties": {
    "addr:full":"67 Howe Ave Shelton CT 06484",
    "addr:housenumber":"67",
    "addr:postcode":"06484",
    "addr:street":"Howe Ave",
    "iso:country":"US",
    "sg:address":"67 Howe Ave",
    "sg:city":"Shelton",
    "sg:classifiers":[
        {
            "category":"Restaurant",
            "type":"Food & Drink"
        }
    ],
    "sg:phone":"+1 203 924 2411",
    "sg:postcode":"06484",
    "sg:province":"CT",
    "sg:tags":[
        "pizza"
    ],
    "wof:name":"C J's Pizza & Catering",
    "wof:placetype":"venue"
},
  "geometry": {"coordinates":[-73.082949,41.308801],"type":"Point"}
}