{
  "type": "Feature",
  "properties": {
    "addr:full":"106 Wildcat Rd Madison CT 06443",
    "addr:housenumber":"106",
    "addr:postcode":"06443",
    "addr:street":"Wildcat Rd",
    "iso:country":"US",
    "sg:address":"106 Wildcat Rd",
    "sg:city":"Madison",
    "sg:classifiers":[
        {
            "category":"Health Services",
            "subcategory":"Doctor",
            "type":"Services"
        }
    ],
    "sg:phone":"+1   ",
    "sg:postcode":"06443",
    "sg:province":"CT",
    "sg:tags":[
        "medical"
    ],
    "wof:name":"David Lamberti Dr",
    "wof:placetype":"venue"
},
  "geometry": {"coordinates":[-72.593529,41.294926],"type":"Point"}
}