{
  "type": "Feature",
  "properties": {
    "iso:country":"US",
    "sg:address":"8 Myrtle Rd",
    "sg:city":"Portland",
    "sg:classifiers":[
        {
            "category":"Cinema",
            "subcategory":"Movie Theater",
            "type":"Entertainment"
        }
    ],
    "sg:phone":"+1   ",
    "sg:postcode":"06480",
    "sg:province":"CT",
    "sg:tags":[
        "motion",
        "picture"
    ],
    "wof:name":"Extravaganza Music Theatre Co",
    "wof:placetype":"venue"
},
  "geometry": {"coordinates":[-72.623349,41.57717],"type":"Point"}
}