{
  "type": "Feature",
  "properties": {
    "iso:country":"US",
    "sg:address":"175 Humphrey St",
    "sg:city":"New Haven",
    "sg:classifiers":[
        {
            "category":"Restaurant",
            "type":"Food & Drink"
        }
    ],
    "sg:phone":"+1 203 782 1506",
    "sg:postcode":"06511",
    "sg:province":"CT",
    "wof:name":"Humphrey's East Restaurant",
    "wof:placetype":"venue"
},
  "geometry": {"coordinates":[-72.908236,41.313303],"type":"Point"}
}