{
  "type": "Feature",
  "properties": {
    "iso:country":"US",
    "sg:address":"174 Grand St",
    "sg:city":"Waterbury",
    "sg:classifiers":[
        {
            "category":"Professional",
            "type":"Services"
        }
    ],
    "sg:phone":"+1 203 755 6441",
    "sg:postcode":"06702",
    "sg:province":"CT",
    "sg:tags":[
        "establishment"
    ],
    "wof:name":"Waterbury Republican Town",
    "wof:placetype":"venue"
},
  "geometry": {"coordinates":[-73.04228000000001,41.554012],"type":"Point"}
}