{
  "type": "Feature",
  "properties": {
    "iso:country":"US",
    "sg:address":"820 Boston Post Rd",
    "sg:city":"Old Saybrook",
    "sg:classifiers":[
        {
            "category":"Retail",
            "subcategory":"Auto Repair",
            "type":"Services"
        }
    ],
    "sg:phone":"+1 860 388 2492",
    "sg:postcode":"06475",
    "sg:province":"CT",
    "sg:website":"meineke-oldsaybrook.com",
    "wof:name":"Meineke",
    "wof:placetype":"venue"
},
  "geometry": {"coordinates":[-72.38151499999999,41.293346],"type":"Point"}
}