{
  "type": "Feature",
  "properties": {
    "iso:country":"US",
    "sg:address":"121 Dundee Rd",
    "sg:city":"Stamford",
    "sg:classifiers":[
        {
            "category":"Manufacturing",
            "subcategory":"Printing",
            "type":"Manufacturing & Wholesale Goods"
        }
    ],
    "sg:phone":"+1 203 329 0230",
    "sg:postcode":"06903",
    "sg:province":"CT",
    "sg:tags":[
        "multimedia"
    ],
    "wof:name":"Direct Media",
    "wof:placetype":"venue"
},
  "geometry": {"coordinates":[-73.583568,41.121277],"type":"Point"}
}