{
  "type": "Feature",
  "properties": {
    "addr:full":"93 Antrim Rd Coventry CT 06238",
    "addr:housenumber":"93",
    "addr:postcode":"06238",
    "addr:street":"Antrim Rd",
    "iso:country":"US",
    "sg:address":"93 Antrim Rd",
    "sg:city":"Coventry",
    "sg:classifiers":[
        {
            "category":"Retail",
            "subcategory":"Portrait Studio",
            "type":"Services"
        }
    ],
    "sg:phone":"+1   ",
    "sg:postcode":"06238",
    "sg:province":"CT",
    "sg:tags":[
        "photo"
    ],
    "wof:name":"Artz Hansen Photography",
    "wof:placetype":"venue"
},
  "geometry": {"coordinates":[-72.319785,41.817111],"type":"Point"}
}