{
  "type": "Feature",
  "properties": {
    "iso:country":"US",
    "sg:address":"154 John St",
    "sg:city":"Southport",
    "sg:classifiers":[
        {
            "category":"Building & Trades",
            "subcategory":"Construction",
            "type":"Services"
        }
    ],
    "sg:phone":"+1 203 259 7364",
    "sg:postcode":"06492",
    "sg:province":"CT",
    "sg:tags":[
        "excavating",
        "contractor"
    ],
    "wof:name":"Frank B Dawid Inc",
    "wof:placetype":"venue"
},
  "geometry": {"coordinates":[-72.835466,41.446649],"type":"Point"}
}