{
  "type": "Feature",
  "properties": {
    "iso:country":"US",
    "sg:address":"31 Old Rte 7",
    "sg:city":"Brookfield",
    "sg:classifiers":[
        {
            "category":"Health Services",
            "subcategory":"Health Practitioner",
            "type":"Services"
        }
    ],
    "sg:phone":"+1 203 740 0020",
    "sg:postcode":"06804",
    "sg:province":"CT",
    "sg:tags":[
        "therapist",
        "physical"
    ],
    "sg:website":"www.carlsontherapy.com",
    "wof:name":"Physical Therapy Arts",
    "wof:placetype":"venue"
},
  "geometry": {"coordinates":[-73.408931,41.474623],"type":"Point"}
}