{
  "type": "Feature",
  "properties": {
    "iso:country":"US",
    "sg:address":"1106 New Britain Ave",
    "sg:city":"Hartford",
    "sg:classifiers":[
        {
            "category":"Social Services",
            "subcategory":"Child Care",
            "type":"Services"
        }
    ],
    "sg:phone":"+1   ",
    "sg:postcode":"06110",
    "sg:province":"CT",
    "sg:tags":[
        "day"
    ],
    "wof:name":"Elmwood Day Care Center",
    "wof:placetype":"venue"
},
  "geometry": {"coordinates":[-72.729367,41.731663],"type":"Point"}
}