{
  "type": "Feature",
  "properties": {
    "addr:full":"80 Poquonock Ave Windsor CT 06095",
    "addr:housenumber":"80",
    "addr:postcode":"06095",
    "addr:street":"Poquonock Ave",
    "iso:country":"US",
    "sg:address":"80 Poquonock Ave",
    "sg:city":"Windsor",
    "sg:classifiers":[
        {
            "category":"Personal",
            "subcategory":"Beauty Salon",
            "type":"Services"
        }
    ],
    "sg:phone":"+1   ",
    "sg:postcode":"06095",
    "sg:province":"CT",
    "sg:tags":[
        "shop"
    ],
    "wof:name":"Van Nails",
    "wof:placetype":"venue"
},
  "geometry": {"coordinates":[-72.64710100000001,41.854488],"type":"Point"}
}