{
  "type": "Feature",
  "properties": {
    "iso:country":"US",
    "sg:address":"9 Twilight Pl",
    "sg:city":"Norwalk",
    "sg:classifiers":[
        {
            "category":"Professional",
            "subcategory":"Management & Consulting",
            "type":"Services"
        }
    ],
    "sg:phone":"+1   ",
    "sg:postcode":"06854",
    "sg:province":"CT",
    "sg:tags":[
        "communications",
        "corporate"
    ],
    "wof:name":"Praxis Media Inc",
    "wof:placetype":"venue"
},
  "geometry": {"coordinates":[-73.408153,41.083807],"type":"Point"}
}