{
  "type": "Feature",
  "properties": {
    "addr:full":"69 Mist Hill Dr New Milford CT 06776",
    "addr:housenumber":"69",
    "addr:postcode":"06776",
    "addr:street":"Mist Hill Dr",
    "iso:country":"US",
    "sg:address":"69 Mist Hill Dr",
    "sg:city":"New Milford",
    "sg:classifiers":[
        {
            "category":"Social Services",
            "subcategory":"Child Care",
            "type":"Services"
        }
    ],
    "sg:phone":"+1   ",
    "sg:postcode":"06776",
    "sg:province":"CT",
    "sg:tags":[
        "day"
    ],
    "wof:name":"All About Kids Care",
    "wof:placetype":"venue"
},
  "geometry": {"coordinates":[-73.43487399999999,41.504988],"type":"Point"}
}