{
  "type": "Feature",
  "properties": {
    "iso:country":"US",
    "sg:address":"15 Overlook Dr",
    "sg:city":"Greenwich",
    "sg:classifiers":[
        {
            "category":"Professional",
            "subcategory":"Business Services",
            "type":"Services"
        }
    ],
    "sg:phone":"+1   ",
    "sg:postcode":"06830",
    "sg:province":"CT",
    "wof:name":"Multi Design For People LLC",
    "wof:placetype":"venue"
},
  "geometry": {"coordinates":[-73.613973,41.03651],"type":"Point"}
}