{
  "type": "Feature",
  "properties": {
    "addr:full":"216 Prospect Hill Rd Colchester CT 06415",
    "addr:housenumber":"216",
    "addr:postcode":"06415",
    "addr:street":"Prospect Hill Rd",
    "iso:country":"US",
    "sg:address":"216 Prospect Hill Rd",
    "sg:city":"Colchester",
    "sg:classifiers":[
        {
            "category":"Building & Trades",
            "subcategory":"Construction",
            "type":"Services"
        }
    ],
    "sg:phone":"+1 860 537 1425",
    "sg:postcode":"06415",
    "sg:province":"CT",
    "sg:tags":[
        "nonresidential"
    ],
    "wof:name":"Theodore Reinholtz",
    "wof:placetype":"venue"
},
  "geometry": {"coordinates":[-72.377769,41.566598],"type":"Point"}
}