{
  "type": "Feature",
  "properties": {
    "addr:full":"53 Hemlock Rd Roxbury CT 06783",
    "addr:housenumber":"53",
    "addr:postcode":"06783",
    "addr:street":"Hemlock Rd",
    "iso:country":"US",
    "sg:address":"53 Hemlock Rd",
    "sg:city":"Roxbury",
    "sg:classifiers":[
        {
            "category":"Retail",
            "subcategory":"Animal Services",
            "type":"Services"
        }
    ],
    "sg:phone":"+1 860 355 9039",
    "sg:postcode":"06783",
    "sg:province":"CT",
    "wof:name":"Horse Trainer Instructor",
    "wof:placetype":"venue"
},
  "geometry": {"coordinates":[-73.31912199999999,41.561461],"type":"Point"}
}