{
  "type": "Feature",
  "properties": {
    "addr:full":"411 Cardinal Cir Torrington CT 06790",
    "addr:housenumber":"411",
    "addr:postcode":"06790",
    "addr:street":"Cardinal Cir",
    "iso:country":"US",
    "sg:address":"411 Cardinal Cir",
    "sg:city":"Torrington",
    "sg:classifiers":[
        {
            "category":"Travel",
            "subcategory":"Hotels & Motels",
            "type":"Entertainment"
        }
    ],
    "sg:phone":"+1   ",
    "sg:postcode":"06790",
    "sg:province":"CT",
    "sg:tags":[
        "operation"
    ],
    "wof:name":"Wolverine Resorts",
    "wof:placetype":"venue"
},
  "geometry": {"coordinates":[-73.125355,41.866153],"type":"Point"}
}