{
  "type": "Feature",
  "properties": {
    "iso:country":"US",
    "sg:address":"400 Foxon Blvd",
    "sg:city":"New Haven",
    "sg:classifiers":[
        {
            "category":"Food & Beverages",
            "subcategory":"Groceries & Convenience Stores",
            "type":"Retail Goods"
        }
    ],
    "sg:phone":"+1 203 467 1515",
    "sg:postcode":"06513",
    "sg:province":"CT",
    "wof:name":"7-Eleven",
    "wof:placetype":"venue"
},
  "geometry": {"coordinates":[-72.874003,41.320885],"type":"Point"}
}