{
  "type": "Feature",
  "properties": {
    "addr:full":"695 Seaview Ave Bridgeport CT 06607",
    "addr:housenumber":"695",
    "addr:postcode":"06607",
    "addr:street":"Seaview Ave",
    "iso:country":"US",
    "sg:address":"695 Seaview Ave",
    "sg:city":"Bridgeport",
    "sg:classifiers":[
        {
            "category":"Professional",
            "subcategory":"Business Services",
            "type":"Services"
        }
    ],
    "sg:phone":"+1 203 335 6946",
    "sg:postcode":"06607",
    "sg:province":"CT",
    "sg:tags":[
        "water",
        "treatment"
    ],
    "wof:name":"US Filter",
    "wof:placetype":"venue"
},
  "geometry": {"coordinates":[-73.17126500000001,41.172706],"type":"Point"}
}