{
  "type": "Feature",
  "properties": {
    "iso:country":"US",
    "sg:address":"37 Park Pl",
    "sg:city":"Winsted",
    "sg:classifiers":[
        {
            "category":"Food & Beverages",
            "subcategory":"Groceries & Convenience Stores",
            "type":"Retail Goods"
        }
    ],
    "sg:phone":"+1 860 738 2827",
    "sg:postcode":"06098",
    "sg:province":"CT",
    "wof:name":"Jerrys Deli",
    "wof:placetype":"venue"
},
  "geometry": {"coordinates":[-73.05958200000001,41.92205],"type":"Point"}
}