{
  "type": "Feature",
  "properties": {
    "iso:country":"US",
    "sg:address":"62 Hartford Tpke",
    "sg:city":"Tolland",
    "sg:classifiers":[
        {
            "category":"Banks & Credit Unions",
            "subcategory":"Bank",
            "type":"Services"
        }
    ],
    "sg:phone":"+1 860 896 1993",
    "sg:postcode":"06084",
    "sg:province":"CT",
    "sg:website":"http://www.workersfcu.com",
    "wof:name":"Worker Federal Credit Union",
    "wof:placetype":"venue"
},
  "geometry": {"coordinates":[-72.41115600000001,41.869233],"type":"Point"}
}