{
  "type": "Feature",
  "properties": {
    "addr:full":"366 Williams Rd Wallingford CT 06492",
    "addr:housenumber":"366",
    "addr:postcode":"06492",
    "addr:street":"Williams Rd",
    "iso:country":"US",
    "sg:address":"366 Williams Rd",
    "sg:city":"Wallingford",
    "sg:classifiers":[
        {
            "category":"Building & Trades",
            "subcategory":"Landscaping Services",
            "type":"Services"
        }
    ],
    "sg:phone":"+1 203 284 9647",
    "sg:postcode":"06492",
    "sg:province":"CT",
    "sg:tags":[
        "landscape"
    ],
    "wof:name":"Chuck Sherwood Landscape",
    "wof:placetype":"venue"
},
  "geometry": {"coordinates":[-72.770374,41.459753],"type":"Point"}
}