{
  "type": "Feature",
  "properties": {
    "addr:full":"60 Lovely St Canton CT 06019",
    "addr:housenumber":"60",
    "addr:postcode":"06019",
    "addr:street":"Lovely St",
    "iso:country":"US",
    "sg:address":"60 Lovely St",
    "sg:city":"Canton",
    "sg:classifiers":[
        {
            "category":"Retail",
            "subcategory":"Pet Boarding",
            "type":"Services"
        }
    ],
    "sg:phone":"+1 860 693 0603",
    "sg:postcode":"06019",
    "sg:province":"CT",
    "sg:tags":[
        "boarding/pet",
        "sitting"
    ],
    "wof:name":"Roaring Brook Pet Lodge & Grooming Center",
    "wof:placetype":"venue"
},
  "geometry": {"coordinates":[-72.889503,41.821098],"type":"Point"}
}