{
  "type": "Feature",
  "properties": {
    "addr:full":"25 Vineyard Ln Westport CT 06880",
    "addr:housenumber":"25",
    "addr:postcode":"06880",
    "addr:street":"Vineyard Ln",
    "iso:country":"US",
    "sg:address":"25 Vineyard Ln",
    "sg:city":"Westport",
    "sg:classifiers":[
        {
            "category":"Professional",
            "subcategory":"Employment Agencies",
            "type":"Services"
        }
    ],
    "sg:phone":"+1 203 222 9416",
    "sg:postcode":"06880",
    "sg:province":"CT",
    "sg:tags":[
        "opportunity"
    ],
    "wof:name":"Gloria Ginter Group",
    "wof:placetype":"venue"
},
  "geometry": {"coordinates":[-73.33248399999999,41.168259],"type":"Point"}
}