{
  "type": "Feature",
  "properties": {
    "addr:full":"184 Sound Beach Ave Old Greenwich CT 06870",
    "addr:housenumber":"184",
    "addr:postcode":"06870",
    "addr:street":"Sound Beach Ave",
    "iso:country":"US",
    "sg:address":"184 Sound Beach Ave",
    "sg:city":"Old Greenwich",
    "sg:classifiers":[
        {
            "category":"Banks & Credit Unions",
            "subcategory":"Bank",
            "type":"Services"
        }
    ],
    "sg:phone":"+1 203 698 4119",
    "sg:postcode":"06870",
    "sg:province":"CT",
    "sg:tags":[
        "national",
        "commercial"
    ],
    "wof:name":"Patriot National Bank",
    "wof:placetype":"venue"
},
  "geometry": {"coordinates":[-73.568325,41.03282],"type":"Point"}
}