{
  "type": "Feature",
  "properties": {
    "iso:country":"US",
    "sg:address":"16 Cornell Rd",
    "sg:city":"New Fairfield",
    "sg:classifiers":[
        {
            "category":"Education",
            "subcategory":"Special Training",
            "type":"Public Place"
        }
    ],
    "sg:phone":"+1 203 746 7191",
    "sg:postcode":"06812",
    "sg:province":"CT",
    "sg:tags":[
        "school",
        "language"
    ],
    "wof:name":"Foreign Language Svc",
    "wof:placetype":"venue"
},
  "geometry": {"coordinates":[-73.52696299999999,41.47939],"type":"Point"}
}