{
  "type": "Feature",
  "properties": {
    "iso:country":"US",
    "sg:address":"607 W Main St",
    "sg:city":"Norwich",
    "sg:classifiers":[
        {
            "category":"Restaurant",
            "type":"Food & Drink"
        }
    ],
    "sg:menulink":"http://www.allmenus.com/ct/norwich/69842-papa-ginos/menu/",
    "sg:phone":"+1 860 889 1397",
    "sg:postcode":"06360",
    "sg:province":"CT",
    "sg:tags":[
        "american",
        "pizza"
    ],
    "wof:name":"Papa Gino's",
    "wof:placetype":"venue"
},
  "geometry": {"coordinates":[-72.100815,41.515991],"type":"Point"}
}