{
  "type": "Feature",
  "properties": {
    "iso:country":"US",
    "sg:address":"431 North Trl",
    "sg:city":"Stratford",
    "sg:classifiers":[
        {
            "category":"Real Estate",
            "subcategory":"Real Estate Agent",
            "type":"Services"
        }
    ],
    "sg:phone":"+1 203 375 8330",
    "sg:postcode":"06614",
    "sg:province":"CT",
    "sg:tags":[
        "appraiser"
    ],
    "wof:name":"Larson Associates",
    "wof:placetype":"venue"
},
  "geometry": {"coordinates":[-73.110153,41.251757],"type":"Point"}
}