{
  "type": "Feature",
  "properties": {
    "addr:full":"251 Greene St New Haven CT 06511",
    "addr:housenumber":"251",
    "addr:postcode":"06511",
    "addr:street":"Greene St",
    "iso:country":"US",
    "sg:address":"251 Greene St",
    "sg:city":"New Haven",
    "sg:classifiers":[
        {
            "category":"Building & Trades",
            "subcategory":"Plumbing",
            "type":"Services"
        }
    ],
    "sg:phone":"+1 203 444 3819",
    "sg:postcode":"06511",
    "sg:province":"CT",
    "sg:tags":[
        "plumbing",
        "contractor"
    ],
    "wof:name":"Anchor Plumbing LLC",
    "wof:placetype":"venue"
},
  "geometry": {"coordinates":[-72.91573699999999,41.305617],"type":"Point"}
}