{
  "type": "Feature",
  "properties": {
    "iso:country":"US",
    "sg:address":"1 Muriel St",
    "sg:city":"Norwalk",
    "sg:classifiers":[
        {
            "category":"Real Estate",
            "subcategory":"Real Estate Operator",
            "type":"Services"
        }
    ],
    "sg:phone":"+1 203 847 8346",
    "sg:postcode":"06851",
    "sg:province":"CT",
    "sg:tags":[
        "building",
        "commercial"
    ],
    "wof:name":"Muller Park Realty Co",
    "wof:placetype":"venue"
},
  "geometry": {"coordinates":[-73.40011199999999,41.129639],"type":"Point"}
}