{
  "type": "Feature",
  "properties": {
    "iso:country":"US",
    "sg:address":"84 Evelyn Dr",
    "sg:city":"Naugatuck",
    "sg:classifiers":[
        {
            "category":"Health Services",
            "subcategory":"Hospital",
            "type":"Services"
        }
    ],
    "sg:phone":"+1 203 984 1122",
    "sg:postcode":"06770",
    "sg:province":"CT",
    "sg:tags":[
        "equipment",
        "supply"
    ],
    "wof:name":"Callum Corporation",
    "wof:placetype":"venue"
},
  "geometry": {"coordinates":[-73.09545199999999,41.509062],"type":"Point"}
}