{
  "type": "Feature",
  "properties": {
    "iso:country":"US",
    "sg:address":"32 Bushnell Hollow Rd",
    "sg:city":"Baltic",
    "sg:classifiers":[
        {
            "category":"Utilities",
            "subcategory":"Fuel Oil & Lpg",
            "type":"Services"
        }
    ],
    "sg:phone":"+1 860 822 8011",
    "sg:postcode":"06330",
    "sg:province":"CT",
    "sg:tags":[
        "dealer"
    ],
    "wof:name":"Brodeurs Oil Service Inc",
    "wof:placetype":"venue"
},
  "geometry": {"coordinates":[-72.076121,41.616335],"type":"Point"}
}