{
  "type": "Feature",
  "properties": {
    "addr:full":"55 Greens Farms Rd Westport CT 06880",
    "addr:housenumber":"55",
    "addr:postcode":"06880",
    "addr:street":"Greens Farms Rd",
    "iso:country":"US",
    "sg:address":"55 Greens Farms Rd",
    "sg:city":"Westport",
    "sg:classifiers":[
        {
            "category":"Professional",
            "subcategory":"Management & Consulting",
            "type":"Services"
        }
    ],
    "sg:phone":"+1 203 226 9200",
    "sg:postcode":"06880",
    "sg:province":"CT",
    "sg:tags":[
        "marketing",
        "consultant"
    ],
    "sg:website":"www.thenecg.com",
    "wof:name":"New England Consulting Group",
    "wof:placetype":"venue"
},
  "geometry": {"coordinates":[-73.351923,41.123069],"type":"Point"}
}