{
  "type": "Feature",
  "properties": {
    "iso:country":"US",
    "sg:address":"17 Washington St",
    "sg:city":"Norwalk",
    "sg:classifiers":[
        {
            "category":"Wholesale",
            "subcategory":"Apparel",
            "type":"Manufacturing & Wholesale Goods"
        }
    ],
    "sg:phone":"+1 203 354 3700",
    "sg:postcode":"06854",
    "sg:province":"CT",
    "sg:tags":[
        "clothing"
    ],
    "wof:name":"Madsoul Clothing Company",
    "wof:placetype":"venue"
},
  "geometry": {"coordinates":[-73.42033000000001,41.099107],"type":"Point"}
}