{
  "type": "Feature",
  "properties": {
    "addr:full":"45 Arrowhead Dr Guilford CT 06437",
    "addr:housenumber":"45",
    "addr:postcode":"06437",
    "addr:street":"Arrowhead Dr",
    "iso:country":"US",
    "sg:address":"45 Arrowhead Dr",
    "sg:city":"Guilford",
    "sg:classifiers":[
        {
            "category":"Communications",
            "subcategory":"Film & Video Production",
            "type":"Services"
        },
        {
            "category":"Arts & Performance",
            "subcategory":"Theater",
            "type":"Entertainment"
        }
    ],
    "sg:phone":"+1 203 458 7311",
    "sg:postcode":"06437",
    "sg:province":"CT",
    "sg:tags":[
        "picture",
        "television",
        "producer",
        "motion",
        "program",
        "tape"
    ],
    "wof:name":"Morningside Productions Inc",
    "wof:placetype":"venue"
},
  "geometry": {"coordinates":[-72.699806,41.253387],"type":"Point"}
}