{
  "type": "Feature",
  "properties": {
    "iso:country":"US",
    "sg:address":"31 S Stonybrook Dr",
    "sg:city":"Marlborough",
    "sg:classifiers":[
        {
            "category":"Professional",
            "subcategory":"Accounting & Tax Preparation",
            "type":"Services"
        }
    ],
    "sg:phone":"+1   ",
    "sg:postcode":"06447",
    "sg:province":"CT",
    "wof:name":"Skills On Call Assoc",
    "wof:placetype":"venue"
},
  "geometry": {"coordinates":[-72.460731,41.673688],"type":"Point"}
}