{
  "type": "Feature",
  "properties": {
    "addr:full":"37 River St Milford CT 06460",
    "addr:housenumber":"37",
    "addr:postcode":"06460",
    "addr:street":"River St",
    "iso:country":"US",
    "sg:address":"37 River St",
    "sg:city":"Milford",
    "sg:classifiers":[
        {
            "category":"Shopping",
            "subcategory":"Tobacco",
            "type":"Retail Goods"
        }
    ],
    "sg:phone":"+1 203 876 4744",
    "sg:postcode":"06460",
    "sg:province":"CT",
    "sg:tags":[
        "cigarette",
        "cigar",
        "dealer"
    ],
    "wof:name":"Milford Tobacco Co LTD",
    "wof:placetype":"venue"
},
  "geometry": {"coordinates":[-73.05721200000001,41.223459],"type":"Point"}
}