{
  "type": "Feature",
  "properties": {
    "iso:country":"US",
    "sg:address":"303 Overlook Dr",
    "sg:city":"Greenwich",
    "sg:classifiers":[
        {
            "category":"Banks & Credit Unions",
            "subcategory":"Investment Brokerage",
            "type":"Services"
        }
    ],
    "sg:phone":"+1 203 869 4046",
    "sg:postcode":"06830",
    "sg:province":"CT",
    "sg:tags":[
        "advisory"
    ],
    "wof:name":"Three Lakes Advisors Inc",
    "wof:placetype":"venue"
},
  "geometry": {"coordinates":[-73.615859,41.029849],"type":"Point"}
}