{
  "type": "Feature",
  "properties": {
    "iso:country":"US",
    "sg:address":"355 Prospect St",
    "sg:city":"Torrington",
    "sg:classifiers":[
        {
            "category":"Professional",
            "subcategory":"Lawyer & Legal Services",
            "type":"Services"
        }
    ],
    "sg:phone":"+1 860 482 4451",
    "sg:postcode":"06790",
    "sg:province":"CT",
    "sg:tags":[
        "attorney"
    ],
    "sg:website":"http://www.febblaw.com",
    "wof:name":"Febbroriello John P Law Offices Of",
    "wof:placetype":"venue"
},
  "geometry": {"coordinates":[-73.122716,41.804912],"type":"Point"}
}