{
  "type": "Feature",
  "properties": {
    "iso:country":"US",
    "sg:address":"130 Wilson St",
    "sg:city":"Waterbury",
    "sg:classifiers":[
        {
            "category":"Organizations",
            "subcategory":"Religious Organization",
            "type":"Services"
        }
    ],
    "sg:phone":"+1   ",
    "sg:postcode":"06708",
    "sg:province":"CT",
    "wof:name":"Waterbury Hindu Temple Inc",
    "wof:placetype":"venue"
},
  "geometry": {"coordinates":[-73.055919,41.553246],"type":"Point"}
}