{
  "type": "Feature",
  "properties": {
    "addr:full":"55 Village Pl Glastonbury CT 06033",
    "addr:housenumber":"55",
    "addr:postcode":"06033",
    "addr:street":"Village Pl",
    "iso:country":"US",
    "sg:address":"55 Village Pl",
    "sg:city":"Glastonbury",
    "sg:classifiers":[
        {
            "category":"Building & Trades",
            "subcategory":"Landscaping Services",
            "type":"Services"
        }
    ],
    "sg:phone":"+1 860 659 1438",
    "sg:postcode":"06033",
    "sg:province":"CT",
    "wof:name":"Thompson Landscape Improvement",
    "wof:placetype":"venue"
},
  "geometry": {"coordinates":[-72.573847,41.717974],"type":"Point"}
}