{
  "type": "Feature",
  "properties": {
    "addr:full":"108 Watertown Rd Thomaston CT 06787",
    "addr:housenumber":"108",
    "addr:postcode":"06787",
    "addr:street":"Watertown Rd Thomaston Ct",
    "iso:country":"US",
    "sg:address":"108 Watertown Rd",
    "sg:city":"Thomaston",
    "sg:classifiers":[
        {
            "category":"Health Services",
            "subcategory":"Chiropractor",
            "type":"Services"
        }
    ],
    "sg:phone":"+1   ",
    "sg:postcode":"06787",
    "sg:province":"CT",
    "wof:name":"Timothy R Whelan Dr",
    "wof:placetype":"venue"
},
  "geometry": {"coordinates":[-73.084529,41.658711],"type":"Point"}
}