{
  "type": "Feature",
  "properties": {
    "iso:country":"US",
    "sg:address":"257 Boston Post Rd",
    "sg:city":"Waterford",
    "sg:classifiers":[
        {
            "category":"Farming",
            "subcategory":"Fish & Marine Products",
            "type":"Manufacturing & Wholesale Goods"
        }
    ],
    "sg:phone":"+1 860 439 0018",
    "sg:postcode":"06385",
    "sg:province":"CT",
    "sg:tags":[
        "fishing"
    ],
    "wof:name":"Donald L Foster Fisherman",
    "wof:placetype":"venue"
},
  "geometry": {"coordinates":[-72.144925,41.34807],"type":"Point"}
}