{
  "type": "Feature",
  "properties": {
    "iso:country":"US",
    "sg:address":"157 Quinn St",
    "sg:city":"Naugatuck",
    "sg:classifiers":[
        {
            "category":"Food & Beverages",
            "subcategory":"Meat & Fish",
            "type":"Retail Goods"
        }
    ],
    "sg:phone":"+1 203 729 6898",
    "sg:postcode":"06770",
    "sg:province":"CT",
    "wof:name":"Adrian's Market",
    "wof:placetype":"venue"
},
  "geometry": {"coordinates":[-73.064643,41.501397],"type":"Point"}
}