{
  "type": "Feature",
  "properties": {
    "addr:full":"19 Holmes Ave Waterbury CT 06710",
    "addr:housenumber":"19",
    "addr:postcode":"06710",
    "addr:street":"Holmes Ave",
    "iso:country":"US",
    "sg:address":"19 Holmes Ave",
    "sg:city":"Waterbury",
    "sg:classifiers":[
        {
            "category":"Professional",
            "subcategory":"Lawyer & Legal Services",
            "type":"Services"
        }
    ],
    "sg:phone":"+1   ",
    "sg:postcode":"06710",
    "sg:province":"CT",
    "sg:tags":[
        "firm",
        "law"
    ],
    "wof:name":"Ryan David A Jr",
    "wof:placetype":"venue"
},
  "geometry": {"coordinates":[-73.044946,41.557781],"type":"Point"}
}