{
  "type": "Feature",
  "properties": {
    "iso:country":"US",
    "sg:address":"111 New Haven Ave",
    "sg:city":"Derby",
    "sg:classifiers":[
        {
            "category":"Health Services",
            "subcategory":"Doctor",
            "type":"Services"
        }
    ],
    "sg:phone":"+1   ",
    "sg:postcode":"06418",
    "sg:province":"CT",
    "wof:name":"J Nicholas Anderson DDS",
    "wof:placetype":"venue"
},
  "geometry": {"coordinates":[-73.076126,41.311046],"type":"Point"}
}