{
  "type": "Feature",
  "properties": {
    "addr:full":"132 Federal Rd Brookfield CT 06804",
    "addr:housenumber":"132",
    "addr:postcode":"06804",
    "addr:street":"Federal Rd",
    "iso:country":"US",
    "sg:address":"132 Federal Rd",
    "sg:city":"Brookfield",
    "sg:classifiers":[
        {
            "category":"Real Estate",
            "subcategory":"Real Estate Agent",
            "type":"Services"
        }
    ],
    "sg:phone":"+1 203 775 2413",
    "sg:postcode":"06804",
    "sg:province":"CT",
    "wof:name":"Re/Max",
    "wof:placetype":"venue"
},
  "geometry": {"coordinates":[-73.408452,41.436624],"type":"Point"}
}