{
  "type": "Feature",
  "properties": {
    "addr:full":"21 Pine Hill Ave Norwalk CT 06855",
    "addr:housenumber":"21",
    "addr:postcode":"06855",
    "addr:street":"Pine Hill Ave",
    "iso:country":"US",
    "sg:address":"21 Pine Hill Ave",
    "sg:city":"Norwalk",
    "sg:classifiers":[
        {
            "category":"Banks & Credit Unions",
            "subcategory":"Financial Services",
            "type":"Services"
        }
    ],
    "sg:phone":"+1 203 838 9828",
    "sg:postcode":"06855",
    "sg:province":"CT",
    "sg:tags":[
        "management",
        "open",
        "investment"
    ],
    "wof:name":"Lacroix LLC",
    "wof:placetype":"venue"
},
  "geometry": {"coordinates":[-73.39807399999999,41.099641],"type":"Point"}
}