{
  "type": "Feature",
  "properties": {
    "addr:full":"6 Jacobs Ln Bethel CT 06801",
    "addr:housenumber":"6",
    "addr:postcode":"06801",
    "addr:street":"Jacobs Ln Bethel Ct",
    "iso:country":"US",
    "sg:address":"6 Jacobs Ln",
    "sg:city":"Bethel",
    "sg:classifiers":[
        {
            "category":"Real Estate",
            "subcategory":"Real Estate Agent",
            "type":"Services"
        }
    ],
    "sg:phone":"+1 203 797 9068",
    "sg:postcode":"06801",
    "sg:province":"CT",
    "wof:name":"Riley Appraisal Assc",
    "wof:placetype":"venue"
},
  "geometry": {"coordinates":[-73.375615,41.352702],"type":"Point"}
}