{
  "type": "Feature",
  "properties": {
    "addr:full":"67 Hudson St Berlin CT 06037",
    "addr:housenumber":"67",
    "addr:postcode":"06037",
    "addr:street":"Hudson St",
    "iso:country":"US",
    "sg:address":"67 Hudson St",
    "sg:city":"Berlin",
    "sg:classifiers":[
        {
            "category":"Wholesale",
            "subcategory":"Machinery & Supplies",
            "type":"Manufacturing & Wholesale Goods"
        }
    ],
    "sg:phone":"+1 860 829 9765",
    "sg:postcode":"06037",
    "sg:province":"CT",
    "sg:tags":[
        "equipment"
    ],
    "wof:name":"RMS Forklift LLC",
    "wof:placetype":"venue"
},
  "geometry": {"coordinates":[-72.752483,41.617203],"type":"Point"}
}