{
  "type": "Feature",
  "properties": {
    "iso:country":"US",
    "sg:address":"17 Old Turnpike Rd",
    "sg:city":"Beacon Falls",
    "sg:classifiers":[
        {
            "category":"Manufacturing",
            "subcategory":"Paper Products",
            "type":"Manufacturing & Wholesale Goods"
        }
    ],
    "sg:phone":"+1 203 888 0511",
    "sg:postcode":"06403",
    "sg:province":"CT",
    "sg:tags":[
        "corrugated",
        "solid",
        "fiber",
        "box"
    ],
    "wof:name":"Knapp Container Inc",
    "wof:placetype":"venue"
},
  "geometry": {"coordinates":[-73.069935,41.425615],"type":"Point"}
}