{
  "type": "Feature",
  "properties": {
    "addr:full":"62 Treat St West Haven CT 06516",
    "addr:housenumber":"62",
    "addr:postcode":"06516",
    "addr:street":"Treat St;Haven",
    "iso:country":"US",
    "sg:address":"62 Treat St",
    "sg:city":"West Haven",
    "sg:classifiers":[
        {
            "category":"Real Estate",
            "subcategory":"Real Estate Operator",
            "type":"Services"
        }
    ],
    "sg:phone":"+1 860 529 5158",
    "sg:postcode":"06516",
    "sg:province":"CT",
    "sg:tags":[
        "apartment",
        "complex"
    ],
    "wof:name":"Reiman Associates",
    "wof:placetype":"venue"
},
  "geometry": {"coordinates":[-72.963942,41.284017],"type":"Point"}
}