{
  "type": "Feature",
  "properties": {
    "addr:full":"16 Tannery Hill Rd Ridgefield CT 06877",
    "addr:housenumber":"16",
    "addr:postcode":"06877",
    "addr:street":"Tannery Hill Rd",
    "iso:country":"US",
    "sg:address":"16 Tannery Hill Rd",
    "sg:city":"Ridgefield",
    "sg:classifiers":[
        {
            "category":"Health Services",
            "subcategory":"Clinic",
            "type":"Services"
        }
    ],
    "sg:phone":"+1   ",
    "sg:postcode":"06877",
    "sg:province":"CT",
    "sg:tags":[
        "home",
        "consulting",
        "care"
    ],
    "wof:name":"Healthcare Relocation Systems",
    "wof:placetype":"venue"
},
  "geometry": {"coordinates":[-73.506658,41.311845],"type":"Point"}
}