{
  "type": "Feature",
  "properties": {
    "addr:full":"558 Chase Ave Waterbury CT 06704",
    "addr:housenumber":"558",
    "addr:postcode":"06704",
    "addr:street":"Chase Ave",
    "iso:country":"US",
    "sg:address":"558 Chase Ave",
    "sg:city":"Waterbury",
    "sg:classifiers":[
        {
            "category":"Health Services",
            "subcategory":"Doctor",
            "type":"Services"
        }
    ],
    "sg:phone":"+1 203 757 9627",
    "sg:postcode":"06704",
    "sg:province":"CT",
    "sg:tags":[
        "dentist"
    ],
    "wof:name":"Waterbury Dental Care PC",
    "wof:placetype":"venue"
},
  "geometry": {"coordinates":[-73.040662,41.584709],"type":"Point"}
}