{
  "type": "Feature",
  "properties": {
    "addr:full":"13 Main St Essex CT 06426",
    "addr:housenumber":"13",
    "addr:postcode":"06426",
    "addr:street":"Main St",
    "iso:country":"US",
    "sg:address":"13 Main St",
    "sg:city":"Essex",
    "sg:classifiers":[
        {
            "category":"Shopping",
            "subcategory":"Bicycles & Sporting Goods",
            "type":"Retail Goods"
        }
    ],
    "sg:phone":"+1 860 767 7065",
    "sg:postcode":"06426",
    "sg:province":"CT",
    "sg:tags":[
        "shop",
        "golf"
    ],
    "wof:name":"Essex Golf Shoppes LLC",
    "wof:placetype":"venue"
},
  "geometry": {"coordinates":[-72.390806,41.353294],"type":"Point"}
}