{
  "type": "Feature",
  "properties": {
    "iso:country":"US",
    "sg:address":"164 Mechanic St",
    "sg:city":"Bristol",
    "sg:classifiers":[
        {
            "category":"Banks & Credit Unions",
            "subcategory":"Financial Services",
            "type":"Services"
        }
    ],
    "sg:phone":"+1 860 793 9129",
    "sg:postcode":"06010",
    "sg:province":"CT",
    "sg:tags":[
        "investor"
    ],
    "wof:name":"Masse & Son Realty",
    "wof:placetype":"venue"
},
  "geometry": {"coordinates":[-72.911799,41.67861],"type":"Point"}
}