{
  "type": "Feature",
  "properties": {
    "iso:country":"US",
    "sg:address":"1014 Chapel St",
    "sg:city":"New Haven",
    "sg:classifiers":[
        {
            "category":"Shopping",
            "subcategory":"Jewelry",
            "type":"Retail Goods"
        }
    ],
    "sg:phone":"+1 203 776 2517",
    "sg:postcode":"06510",
    "sg:province":"CT",
    "sg:tags":[
        "jeweler"
    ],
    "sg:website":"www.endleman.com",
    "wof:name":"Endleman Gallery",
    "wof:placetype":"venue"
},
  "geometry": {"coordinates":[-72.93016,41.307747],"type":"Point"}
}