{
  "type": "Feature",
  "properties": {
    "addr:full":"510 Oak Ave Cheshire CT 06410",
    "addr:housenumber":"510",
    "addr:postcode":"06410",
    "addr:street":"Oak Ave",
    "iso:country":"US",
    "sg:address":"510 Oak Ave",
    "sg:city":"Cheshire",
    "sg:classifiers":[
        {
            "category":"Social Services",
            "type":"Services"
        }
    ],
    "sg:phone":"+1 203 439 0911",
    "sg:postcode":"06410",
    "sg:province":"CT",
    "sg:tags":[
        "instruction",
        "health",
        "care"
    ],
    "wof:name":"Wellness Center",
    "wof:placetype":"venue"
},
  "geometry": {"coordinates":[-72.91981,41.489658],"type":"Point"}
}