{
  "type": "Feature",
  "properties": {
    "iso:country":"US",
    "sg:address":"390 Boston Post Rd",
    "sg:city":"Madison",
    "sg:classifiers":[
        {
            "category":"Real Estate",
            "subcategory":"Real Estate Agent",
            "type":"Services"
        }
    ],
    "sg:phone":"+1 203 245 3631",
    "sg:postcode":"06443",
    "sg:province":"CT",
    "sg:tags":[
        "appraiser"
    ],
    "wof:name":"Appraisal Boyle Group",
    "wof:placetype":"venue"
},
  "geometry": {"coordinates":[-72.61471899999999,41.278286],"type":"Point"}
}