{
  "type": "Feature",
  "properties": {
    "addr:full":"56 Maple Vale Dr Woodbridge CT 06525",
    "addr:housenumber":"56",
    "addr:postcode":"06525",
    "addr:street":"Maple Vale Dr",
    "iso:country":"US",
    "sg:address":"56 Maple Vale Dr",
    "sg:city":"Woodbridge",
    "sg:classifiers":[
        {
            "category":"Retail",
            "subcategory":"Portrait Studio",
            "type":"Services"
        }
    ],
    "sg:phone":"+1   ",
    "sg:postcode":"06525",
    "sg:province":"CT",
    "sg:tags":[
        "photo"
    ],
    "wof:name":"Peter Harris Olin Photography",
    "wof:placetype":"venue"
},
  "geometry": {"coordinates":[-73.012384,41.376469],"type":"Point"}
}