{
  "type": "Feature",
  "properties": {
    "iso:country":"US",
    "sg:address":"696 Dixwell Ave",
    "sg:city":"New Haven",
    "sg:classifiers":[
        {
            "category":"Retail",
            "subcategory":"Laundry & Dry Cleaning",
            "type":"Services"
        }
    ],
    "sg:phone":"+1 203 562 8222",
    "sg:postcode":"06511",
    "sg:province":"CT",
    "sg:tags":[
        "r"
    ],
    "wof:name":"Clarence Tailor",
    "wof:placetype":"venue"
},
  "geometry": {"coordinates":[-72.93523999999999,41.332192],"type":"Point"}
}