{
  "type": "Feature",
  "properties": {
    "addr:full":"100 Simsbury Rd Avon CT 06001",
    "addr:housenumber":"100",
    "addr:postcode":"06001",
    "addr:street":"Simsbury Rd",
    "iso:country":"US",
    "sg:address":"100 Simsbury Rd",
    "sg:city":"Avon",
    "sg:classifiers":[
        {
            "category":"Health Services",
            "subcategory":"Doctor",
            "type":"Services"
        }
    ],
    "sg:phone":"+1   ",
    "sg:postcode":"06001",
    "sg:province":"CT",
    "wof:name":"Cosmetic General Dentistry",
    "wof:placetype":"venue"
},
  "geometry": {"coordinates":[-72.82985100000001,41.815285],"type":"Point"}
}