{
  "type": "Feature",
  "properties": {
    "iso:country":"US",
    "sg:address":"190 Old Ridgefield Rd",
    "sg:city":"Wilton",
    "sg:classifiers":[
        {
            "category":"Banks & Credit Unions",
            "subcategory":"Bank",
            "type":"Services"
        }
    ],
    "sg:phone":"+1 203 762 8588",
    "sg:postcode":"06897",
    "sg:province":"CT",
    "wof:name":"Ridgefield Bank",
    "wof:placetype":"venue"
},
  "geometry": {"coordinates":[-73.42988200000001,41.191321],"type":"Point"}
}