{
  "type": "Feature",
  "properties": {
    "addr:full":"5 Acorn Dr Sandy Hook CT 06482",
    "addr:housenumber":"5",
    "addr:postcode":"06482",
    "addr:street":"Acorn Dr",
    "iso:country":"US",
    "sg:address":"5 Acorn Dr",
    "sg:city":"Sandy Hook",
    "sg:classifiers":[
        {
            "category":"Building & Trades",
            "subcategory":"Construction",
            "type":"Services"
        }
    ],
    "sg:phone":"+1 203 426 8989",
    "sg:postcode":"06482",
    "sg:province":"CT",
    "sg:tags":[
        "contractor"
    ],
    "wof:name":"Superior Gutter & Roofing",
    "wof:placetype":"venue"
},
  "geometry": {"coordinates":[-73.281666,41.435382],"type":"Point"}
}