{
  "type": "Feature",
  "properties": {
    "addr:full":"133 Sebethe Dr Cromwell CT 06416",
    "addr:housenumber":"133",
    "addr:postcode":"06416",
    "addr:street":"Sebethe Dr;Ct",
    "iso:country":"US",
    "sg:address":"133 Sebethe Dr",
    "sg:city":"Cromwell",
    "sg:classifiers":[
        {
            "category":"Retail",
            "subcategory":"Auto Repair",
            "type":"Services"
        }
    ],
    "sg:phone":"+1   ",
    "sg:postcode":"06416",
    "sg:province":"CT",
    "sg:tags":[
        "body"
    ],
    "wof:name":"Josephs Auto Body",
    "wof:placetype":"venue"
},
  "geometry": {"coordinates":[-72.70896,41.614522],"type":"Point"}
}