{
  "type": "Feature",
  "properties": {
    "addr:full":"5 Goss St Waterbury CT 06706",
    "addr:housenumber":"5",
    "addr:postcode":"06706",
    "addr:street":"Goss St Waterbury Ct",
    "iso:country":"US",
    "sg:address":"5 Goss St",
    "sg:city":"Waterbury",
    "sg:classifiers":[
        {
            "category":"Professional",
            "type":"Services"
        }
    ],
    "sg:phone":"+1   ",
    "sg:postcode":"06706",
    "sg:province":"CT",
    "wof:name":"Ls Services Inc",
    "wof:placetype":"venue"
},
  "geometry": {"coordinates":[-73.024244,41.540201],"type":"Point"}
}