{
  "type": "Feature",
  "properties": {
    "addr:full":"377 Hubbard St Glastonbury CT 06033",
    "addr:housenumber":"377",
    "addr:postcode":"06033",
    "addr:street":"Hubbard St",
    "iso:country":"US",
    "sg:address":"377 Hubbard St",
    "sg:city":"Glastonbury",
    "sg:classifiers":[
        {
            "category":"Banks & Credit Unions",
            "subcategory":"Bank",
            "type":"Services"
        }
    ],
    "sg:phone":"+1 860 657 9475",
    "sg:postcode":"06033",
    "sg:province":"CT",
    "sg:tags":[
        "mortgage"
    ],
    "wof:name":"Yankee Mortgage Comp",
    "wof:placetype":"venue"
},
  "geometry": {"coordinates":[-72.58875,41.702936],"type":"Point"}
}