{
  "type": "Feature",
  "properties": {
    "addr:full":"48 Old Grays Bridge Rd Brookfield CT 06804",
    "addr:housenumber":"48",
    "addr:postcode":"06804",
    "addr:street":"Old Grays Bridge Rd",
    "iso:country":"US",
    "sg:address":"48 Old Grays Bridge Rd",
    "sg:city":"Brookfield",
    "sg:classifiers":[
        {
            "category":"Wholesale",
            "subcategory":"Furniture",
            "type":"Manufacturing & Wholesale Goods"
        }
    ],
    "sg:phone":"+1 203 775 9539",
    "sg:postcode":"06804",
    "sg:province":"CT",
    "sg:website":"www.743pens.com",
    "wof:name":"Superior Office Furniture",
    "wof:placetype":"venue"
},
  "geometry": {"coordinates":[-73.39913,41.442167],"type":"Point"}
}