{
  "type": "Feature",
  "properties": {
    "addr:full":"20 Laurel Dr Berlin CT 06037",
    "addr:housenumber":"20",
    "addr:postcode":"06037",
    "addr:street":"Laurel Dr",
    "iso:country":"US",
    "sg:address":"20 Laurel Dr",
    "sg:city":"Berlin",
    "sg:classifiers":[
        {
            "category":"Professional",
            "subcategory":"Business Services",
            "type":"Services"
        }
    ],
    "sg:phone":"+1   ",
    "sg:postcode":"06037",
    "sg:province":"CT",
    "wof:name":"Complete Management Inc",
    "wof:placetype":"venue"
},
  "geometry": {"coordinates":[-72.735698,41.625981],"type":"Point"}
}