{
  "type": "Feature",
  "properties": {
    "addr:full":"21 Captains Watch Shelton CT 06484",
    "addr:housenumber":"21",
    "addr:postcode":"06484",
    "addr:street":"Captains Watch Shelton Ct",
    "iso:country":"US",
    "sg:address":"21 Captains Watch",
    "sg:city":"Shelton",
    "sg:classifiers":[
        {
            "category":"Shopping",
            "subcategory":"Bicycles & Sporting Goods",
            "type":"Retail Goods"
        }
    ],
    "sg:phone":"+1 203 926 6822",
    "sg:postcode":"06484",
    "sg:province":"CT",
    "wof:name":"Future Stars Sport Enterp",
    "wof:placetype":"venue"
},
  "geometry": {"coordinates":[-73.13943500000001,41.307621],"type":"Point"}
}