{
  "type": "Feature",
  "properties": {
    "addr:full":"14 South St Danbury CT 06810",
    "addr:housenumber":"14",
    "addr:postcode":"06810",
    "addr:street":"South St",
    "iso:country":"US",
    "sg:address":"14 South St",
    "sg:city":"Danbury",
    "sg:classifiers":[
        {
            "category":"Personal",
            "type":"Services"
        }
    ],
    "sg:phone":"+1   ",
    "sg:postcode":"06810",
    "sg:province":"CT",
    "sg:tags":[
        "home",
        "improvement"
    ],
    "wof:name":"Inside Out Improvements",
    "wof:placetype":"venue"
},
  "geometry": {"coordinates":[-73.425124,41.382893],"type":"Point"}
}