{
  "type": "Feature",
  "properties": {
    "addr:full":"12 Hickory Hill Ln Branford CT 06405",
    "addr:housenumber":"12",
    "addr:postcode":"06405",
    "addr:street":"Hickory Hill Ln;Ct",
    "iso:country":"US",
    "sg:address":"12 Hickory Hill Ln",
    "sg:city":"Branford",
    "sg:classifiers":[
        {
            "category":"Building & Trades",
            "subcategory":"Construction",
            "type":"Services"
        }
    ],
    "sg:phone":"+1 203 481 0140",
    "sg:postcode":"06405",
    "sg:province":"CT",
    "sg:tags":[
        "repairing",
        "remodeling",
        "contractor"
    ],
    "wof:name":"Energy Electric Inc",
    "wof:placetype":"venue"
},
  "geometry": {"coordinates":[-72.799768,41.298605],"type":"Point"}
}