{
  "type": "Feature",
  "properties": {
    "addr:full":"100 Fort Hill Rd Groton CT 06340",
    "addr:housenumber":"100",
    "addr:postcode":"06340",
    "addr:street":"Fort Hill Rd Groton Ct",
    "iso:country":"US",
    "sg:address":"100 Fort Hill Rd",
    "sg:city":"Groton",
    "sg:classifiers":[
        {
            "category":"Health Services",
            "subcategory":"Health Practitioner",
            "type":"Services"
        }
    ],
    "sg:phone":"+1   ",
    "sg:postcode":"06340",
    "sg:province":"CT",
    "sg:tags":[
        "therapist",
        "physical"
    ],
    "wof:name":"Mystic Physcl Therapy Assoc PC",
    "wof:placetype":"venue"
},
  "geometry": {"coordinates":[-72.030511,41.34616],"type":"Point"}
}