{
  "type": "Feature",
  "properties": {
    "addr:full":"45 Mianus Rd Stamford CT 06902",
    "addr:housenumber":"45",
    "addr:postcode":"06902",
    "addr:street":"Mianus Rd",
    "iso:country":"US",
    "sg:address":"45 Mianus Rd",
    "sg:city":"Stamford",
    "sg:classifiers":[
        {
            "category":"Building & Trades",
            "subcategory":"Plumbing",
            "type":"Services"
        }
    ],
    "sg:phone":"+1 203 348 9469",
    "sg:postcode":"06902",
    "sg:province":"CT",
    "sg:tags":[
        "plumbing",
        "contractor"
    ],
    "wof:name":"Heritage Plumbing & Heating",
    "wof:placetype":"venue"
},
  "geometry": {"coordinates":[-73.57533599999999,41.073661],"type":"Point"}
}