{
  "type": "Feature",
  "properties": {
    "iso:country":"US",
    "sg:address":"24 High St",
    "sg:city":"Bethel",
    "sg:classifiers":[
        {
            "category":"Professional",
            "subcategory":"Business Services",
            "type":"Services"
        }
    ],
    "sg:phone":"+1 203 730 1697",
    "sg:postcode":"06801",
    "sg:province":"CT",
    "sg:tags":[
        "merchandise"
    ],
    "wof:name":"Pine Tree Merchants",
    "wof:placetype":"venue"
},
  "geometry": {"coordinates":[-73.41802199999999,41.374385],"type":"Point"}
}