{
  "type": "Feature",
  "properties": {
    "addr:full":"81 Fairfield Ave Stamford CT 06902",
    "addr:housenumber":"81",
    "addr:postcode":"06902",
    "addr:street":"Fairfield Ave",
    "iso:country":"US",
    "sg:address":"81 Fairfield Ave",
    "sg:city":"Stamford",
    "sg:classifiers":[
        {
            "category":"Building & Trades",
            "subcategory":"Equipment Rental",
            "type":"Services"
        }
    ],
    "sg:phone":"+1   ",
    "sg:postcode":"06902",
    "sg:province":"CT",
    "wof:name":"U-Haul",
    "wof:placetype":"venue"
},
  "geometry": {"coordinates":[-73.55149,41.049483],"type":"Point"}
}