{
  "type": "Feature",
  "properties": {
    "iso:country":"US",
    "sg:address":"194 High St",
    "sg:city":"New Britain",
    "sg:classifiers":[
        {
            "category":"Personal",
            "type":"Services"
        }
    ],
    "sg:phone":"+1   ",
    "sg:postcode":"06051",
    "sg:province":"CT",
    "wof:name":"Studio 10",
    "wof:placetype":"venue"
},
  "geometry": {"coordinates":[-72.785797,41.671135],"type":"Point"}
}