{
  "type": "Feature",
  "properties": {
    "iso:country":"US",
    "sg:address":"108 Stadley Rough Rd",
    "sg:city":"Danbury",
    "sg:classifiers":[
        {
            "category":"Manufacturing",
            "subcategory":"Retail Goods",
            "type":"Manufacturing & Wholesale Goods"
        }
    ],
    "sg:phone":"+1 203 778 3239",
    "sg:postcode":"06811",
    "sg:province":"CT",
    "sg:tags":[
        "product",
        "mfg"
    ],
    "wof:name":"ISAAC Industries",
    "wof:placetype":"venue"
},
  "geometry": {"coordinates":[-73.431938,41.441683],"type":"Point"}
}