{
  "type": "Feature",
  "properties": {
    "addr:full":"152 Cypress Ct Torrington CT 06790",
    "addr:housenumber":"152",
    "addr:postcode":"06790",
    "addr:street":"Cypress Ct",
    "iso:country":"US",
    "sg:address":"152 Cypress Ct",
    "sg:city":"Torrington",
    "sg:classifiers":[
        {
            "category":"Professional",
            "subcategory":"Business Services",
            "type":"Services"
        }
    ],
    "sg:phone":"+1   ",
    "sg:postcode":"06790",
    "sg:province":"CT",
    "wof:name":"Whitley Performance Group LLC",
    "wof:placetype":"venue"
},
  "geometry": {"coordinates":[-73.09626,41.836423],"type":"Point"}
}