{
  "type": "Feature",
  "properties": {
    "iso:country":"US",
    "sg:address":"71 Commerce Dr",
    "sg:city":"Brookfield",
    "sg:classifiers":[
        {
            "category":"Sports & Exercise",
            "subcategory":"Gym",
            "type":"Entertainment"
        }
    ],
    "sg:phone":"+1   ",
    "sg:postcode":"06804",
    "sg:province":"CT",
    "sg:tags":[
        "fitness",
        "physical",
        "facility"
    ],
    "wof:name":"Fitness Revolution",
    "wof:placetype":"venue"
},
  "geometry": {"coordinates":[-73.394051,41.453133],"type":"Point"}
}