{
  "type": "Feature",
  "properties": {
    "addr:full":"96 Maple Ave Greenwich CT 06830",
    "addr:housenumber":"96",
    "addr:postcode":"06830",
    "addr:street":"Maple Ave",
    "iso:country":"US",
    "sg:address":"96 Maple Ave",
    "sg:city":"Greenwich",
    "sg:classifiers":[
        {
            "category":"Professional",
            "subcategory":"Lawyer & Legal Services",
            "type":"Services"
        }
    ],
    "sg:phone":"+1 203 622 6577",
    "sg:postcode":"06830",
    "sg:province":"CT",
    "sg:tags":[
        "attorney"
    ],
    "wof:name":"Harry T Constas PC",
    "wof:placetype":"venue"
},
  "geometry": {"coordinates":[-73.622901,41.034978],"type":"Point"}
}