{
  "type": "Feature",
  "properties": {
    "iso:country":"US",
    "sg:address":"56 Rose Cir",
    "sg:city":"Meriden",
    "sg:classifiers":[
        {
            "category":"Real Estate",
            "subcategory":"Real Estate Agent",
            "type":"Services"
        }
    ],
    "sg:phone":"+1 203 440 0598",
    "sg:postcode":"06450",
    "sg:province":"CT",
    "wof:name":"Silver City Redevelopment LLC",
    "wof:placetype":"venue"
},
  "geometry": {"coordinates":[-72.80152099999999,41.507602],"type":"Point"}
}