{
  "type": "Feature",
  "properties": {
    "addr:full":"55 Cherry St Milford CT 06460",
    "addr:housenumber":"55",
    "addr:postcode":"06460",
    "addr:street":"Cherry St",
    "iso:country":"US",
    "sg:address":"55 Cherry St",
    "sg:city":"Milford",
    "sg:classifiers":[
        {
            "category":"Health Services",
            "subcategory":"Doctor",
            "type":"Services"
        }
    ],
    "sg:phone":"+1 203 874 6826",
    "sg:postcode":"06460",
    "sg:province":"CT",
    "sg:tags":[
        "dentist"
    ],
    "wof:name":"R C Adams DDS",
    "wof:placetype":"venue"
},
  "geometry": {"coordinates":[-73.05470200000001,41.226575],"type":"Point"}
}