{
  "type": "Feature",
  "properties": {
    "iso:country":"US",
    "sg:address":"1899 Post Rd",
    "sg:city":"Darien",
    "sg:classifiers":[
        {
            "category":"Banks & Credit Unions",
            "subcategory":"Investment Brokerage",
            "type":"Services"
        }
    ],
    "sg:phone":"+1 203 656 2295",
    "sg:postcode":"06820",
    "sg:province":"CT",
    "sg:tags":[
        "advisory",
        "financial"
    ],
    "wof:name":"Infinex Financial Group",
    "wof:placetype":"venue"
},
  "geometry": {"coordinates":[-73.48475000000001,41.061344],"type":"Point"}
}