{
  "type": "Feature",
  "properties": {
    "addr:full":"72 Greenbriar Rd Meriden CT 06450",
    "addr:housenumber":"72",
    "addr:postcode":"06450",
    "addr:street":"Greenbriar Rd",
    "iso:country":"US",
    "sg:address":"72 Greenbriar Rd",
    "sg:city":"Meriden",
    "sg:classifiers":[
        {
            "category":"Retail",
            "subcategory":"Laundry & Dry Cleaning",
            "type":"Services"
        }
    ],
    "sg:phone":"+1   ",
    "sg:postcode":"06450",
    "sg:province":"CT",
    "wof:name":"L & S Carpet Cleaning L L C",
    "wof:placetype":"venue"
},
  "geometry": {"coordinates":[-72.79358000000001,41.507331],"type":"Point"}
}