{
  "type": "Feature",
  "properties": {
    "iso:country":"US",
    "sg:address":"54 Chamberlain Hwy",
    "sg:city":"Meriden",
    "sg:classifiers":[
        {
            "category":"Insurance",
            "subcategory":"Insurance Agent",
            "type":"Services"
        }
    ],
    "sg:phone":"+1 203 237 7403",
    "sg:postcode":"06451",
    "sg:province":"CT",
    "wof:name":"Suzio Insurance Ctr Inc",
    "wof:placetype":"venue"
},
  "geometry": {"coordinates":[-72.81712400000001,41.540069],"type":"Point"}
}