{
  "type": "Feature",
  "properties": {
    "addr:full":"20 Bridge St Greenwich CT 06830",
    "addr:housenumber":"20",
    "addr:postcode":"06830",
    "addr:street":"Bridge St",
    "iso:country":"US",
    "sg:address":"20 Bridge St",
    "sg:city":"Greenwich",
    "sg:classifiers":[
        {
            "category":"Social Services",
            "type":"Services"
        }
    ],
    "sg:phone":"+1 203 629 2822",
    "sg:postcode":"06830",
    "sg:province":"CT",
    "sg:tags":[
        "counselor",
        "marriage",
        "family"
    ],
    "sg:website":"www.familycenters.org",
    "wof:name":"Family Centers EAP",
    "wof:placetype":"venue"
},
  "geometry": {"coordinates":[-73.632727,41.021989],"type":"Point"}
}