{
  "type": "Feature",
  "properties": {
    "iso:country":"US",
    "sg:address":"261 Bradley St",
    "sg:city":"New Haven",
    "sg:classifiers":[
        {
            "category":"Professional",
            "subcategory":"Lawyer & Legal Services",
            "type":"Services"
        }
    ],
    "sg:phone":"+1   ",
    "sg:postcode":"06510",
    "sg:province":"CT",
    "wof:name":"Rubenstein Allan B",
    "wof:placetype":"venue"
},
  "geometry": {"coordinates":[-72.920226,41.313893],"type":"Point"}
}