{
  "type": "Feature",
  "properties": {
    "addr:full":"828 E Center St Wallingford CT 06492",
    "addr:housenumber":"828",
    "addr:postcode":"06492",
    "addr:street":"E Center St",
    "iso:country":"US",
    "sg:address":"828 E Center St",
    "sg:city":"Wallingford",
    "sg:classifiers":[
        {
            "category":"Home & Garden",
            "subcategory":"Furniture",
            "type":"Retail Goods"
        }
    ],
    "sg:phone":"+1 203 269 2571",
    "sg:postcode":"06492",
    "sg:province":"CT",
    "wof:name":"K & D Home Products",
    "wof:placetype":"venue"
},
  "geometry": {"coordinates":[-72.80063,41.447061],"type":"Point"}
}