{
  "type": "Feature",
  "properties": {
    "iso:country":"US",
    "sg:address":"78 E Main St",
    "sg:city":"Bristol",
    "sg:classifiers":[
        {
            "category":"Real Estate",
            "subcategory":"Real Estate Agent",
            "type":"Services"
        }
    ],
    "sg:phone":"+1 860 583 4433",
    "sg:postcode":"06010",
    "sg:province":"CT",
    "wof:name":"Alliance 1 LLC",
    "wof:placetype":"venue"
},
  "geometry": {"coordinates":[-72.888614,41.672893],"type":"Point"}
}