{
  "type": "Feature",
  "properties": {
    "iso:country":"US",
    "sg:address":"513 Wormwood Hill Rd",
    "sg:city":"Mansfield Center",
    "sg:classifiers":[
        {
            "category":"Farming",
            "subcategory":"Dairy Farm",
            "type":"Manufacturing & Wholesale Goods"
        }
    ],
    "sg:phone":"+1 860 429 9698",
    "sg:postcode":"06250",
    "sg:province":"CT",
    "wof:name":"Thomas Wells",
    "wof:placetype":"venue"
},
  "geometry": {"coordinates":[-72.188546,41.813954],"type":"Point"}
}