{
  "type": "Feature",
  "properties": {
    "addr:full":"1480 Meriden Rd Waterbury CT 06705",
    "addr:housenumber":"1480",
    "addr:postcode":"06705",
    "addr:street":"Meriden Rd",
    "iso:country":"US",
    "sg:address":"1480 Meriden Rd",
    "sg:city":"Waterbury",
    "sg:classifiers":[
        {
            "category":"Retail",
            "subcategory":"Animal Services",
            "type":"Services"
        }
    ],
    "sg:phone":"+1 203 574 2770",
    "sg:postcode":"06705",
    "sg:province":"CT",
    "sg:tags":[
        "training",
        "dog"
    ],
    "wof:name":"Best Paw Forward",
    "wof:placetype":"venue"
},
  "geometry": {"coordinates":[-72.969807,41.553732],"type":"Point"}
}