{
  "type": "Feature",
  "properties": {
    "addr:full":"27 Shaker Rd Enfield CT 06082",
    "addr:housenumber":"27",
    "addr:postcode":"06082",
    "addr:street":"Shaker Rd",
    "iso:country":"US",
    "sg:address":"27 Shaker Rd",
    "sg:city":"Enfield",
    "sg:classifiers":[
        {
            "category":"Education",
            "subcategory":"School",
            "type":"Public Place"
        }
    ],
    "sg:phone":"+1   ",
    "sg:postcode":"06082",
    "sg:province":"CT",
    "sg:tags":[
        "elementary"
    ],
    "wof:name":"Barnard Henry",
    "wof:placetype":"venue"
},
  "geometry": {"coordinates":[-72.56067299999999,42.003657],"type":"Point"}
}