{
  "type": "Feature",
  "properties": {
    "iso:country":"US",
    "sg:address":"117 Sharon Rd",
    "sg:city":"Waterbury",
    "sg:classifiers":[
        {
            "category":"Health Services",
            "subcategory":"Health Practitioner",
            "type":"Services"
        }
    ],
    "sg:phone":"+1   ",
    "sg:postcode":"06705",
    "sg:province":"CT",
    "wof:name":"Rebound Physical Therapy",
    "wof:placetype":"venue"
},
  "geometry": {"coordinates":[-73.0029,41.569744],"type":"Point"}
}