{
  "type": "Feature",
  "properties": {
    "iso:country":"US",
    "sg:address":"268 Stonegate Dr",
    "sg:city":"Southbury",
    "sg:classifiers":[
        {
            "category":"Building & Trades",
            "subcategory":"Construction",
            "type":"Services"
        }
    ],
    "sg:phone":"+1 203 264 2845",
    "sg:postcode":"06488",
    "sg:province":"CT",
    "wof:name":"William B Canfield Gen Contr",
    "wof:placetype":"venue"
},
  "geometry": {"coordinates":[-73.197614,41.444082],"type":"Point"}
}