{
  "type": "Feature",
  "properties": {
    "addr:full":"753 Boston Post Rd Guilford CT 06437",
    "addr:housenumber":"753",
    "addr:postcode":"06437",
    "addr:street":"Boston Post Rd",
    "iso:country":"US",
    "sg:address":"753 Boston Post Rd",
    "sg:city":"Guilford",
    "sg:classifiers":[
        {
            "category":"Manufacturing",
            "subcategory":"Tools & Machinery",
            "type":"Manufacturing & Wholesale Goods"
        }
    ],
    "sg:phone":"+1 203 453 6654",
    "sg:postcode":"06437",
    "sg:province":"CT",
    "sg:tags":[
        "physician",
        "surgeon"
    ],
    "wof:name":"Defibtech L L C",
    "wof:placetype":"venue"
},
  "geometry": {"coordinates":[-72.67996599999999,41.288538],"type":"Point"}
}