{
  "type": "Feature",
  "properties": {
    "iso:country":"US",
    "sg:address":"10 Sun Pond Ln",
    "sg:city":"New Milford",
    "sg:classifiers":[
        {
            "category":"Professional",
            "subcategory":"Business Services",
            "type":"Services"
        }
    ],
    "sg:phone":"+1   ",
    "sg:postcode":"06776",
    "sg:province":"CT",
    "wof:name":"Showcase Auctions",
    "wof:placetype":"venue"
},
  "geometry": {"coordinates":[-73.347785,41.572507],"type":"Point"}
}