{
  "type": "Feature",
  "properties": {
    "addr:full":"15 Hunter's Xing Burlington CT 06013",
    "addr:housenumber":"15",
    "addr:postcode":"06013",
    "addr:street":"Hunter'S Xing",
    "iso:country":"US",
    "sg:address":"15 Hunter's Xing",
    "sg:city":"Burlington",
    "sg:classifiers":[
        {
            "category":"Professional",
            "subcategory":"Management & Consulting",
            "type":"Services"
        }
    ],
    "sg:phone":"+1   ",
    "sg:postcode":"06013",
    "sg:province":"CT",
    "sg:tags":[
        "business"
    ],
    "wof:name":"Smith Alfred",
    "wof:placetype":"venue"
},
  "geometry": {"coordinates":[-72.94376200000001,41.786642],"type":"Point"}
}