{
  "type": "Feature",
  "properties": {
    "addr:full":"42 Susan Ln Meriden CT 06450",
    "addr:housenumber":"42",
    "addr:postcode":"06450",
    "addr:street":"Susan Ln",
    "iso:country":"US",
    "sg:address":"42 Susan Ln",
    "sg:city":"Meriden",
    "sg:classifiers":[
        {
            "category":"Wholesale",
            "subcategory":"Machinery & Supplies",
            "type":"Manufacturing & Wholesale Goods"
        }
    ],
    "sg:phone":"+1 203 235 7838",
    "sg:postcode":"06450",
    "sg:province":"CT",
    "wof:name":"Graver Technologies Inc",
    "wof:placetype":"venue"
},
  "geometry": {"coordinates":[-72.785077,41.512533],"type":"Point"}
}