{
  "type": "Feature",
  "properties": {
    "iso:country":"US",
    "sg:address":"2 Reed Ln",
    "sg:city":"Riverside",
    "sg:classifiers":[
        {
            "category":"Government",
            "subcategory":"Office",
            "type":"Public Place"
        }
    ],
    "sg:phone":"+1 203 637 2791",
    "sg:postcode":"06878",
    "sg:province":"CT",
    "sg:tags":[
        "village"
    ],
    "wof:name":"Greenwich Housing Athrty Mntnc",
    "wof:placetype":"venue"
},
  "geometry": {"coordinates":[-73.575301,41.04463],"type":"Point"}
}