{
  "type": "Feature",
  "properties": {
    "iso:country":"US",
    "sg:address":"112 S Colman Rd",
    "sg:city":"Wolcott",
    "sg:classifiers":[
        {
            "category":"Real Estate",
            "subcategory":"Real Estate Agent",
            "type":"Services"
        }
    ],
    "sg:phone":"+1 203 879 3123",
    "sg:postcode":"06716",
    "sg:province":"CT",
    "wof:name":"Calcagni Assoc",
    "wof:placetype":"venue"
},
  "geometry": {"coordinates":[-72.96258400000001,41.580959],"type":"Point"}
}