{
  "type": "Feature",
  "properties": {
    "iso:country":"US",
    "sg:address":"141 North St",
    "sg:city":"Goshen",
    "sg:classifiers":[
        {
            "category":"Building & Trades",
            "subcategory":"Landscaping Services",
            "type":"Services"
        }
    ],
    "sg:phone":"+1 860 387 3613",
    "sg:postcode":"06756",
    "sg:province":"CT",
    "sg:tags":[
        "lawn",
        "gardener",
        "landscape",
        "contractor"
    ],
    "sg:website":"http://www.oldworldstoneandgarden.com",
    "wof:name":"Old World Stone And Garden",
    "wof:placetype":"venue"
},
  "geometry": {"coordinates":[-73.23251500000001,41.83955],"type":"Point"}
}