{
  "type": "Feature",
  "properties": {
    "addr:full":"100 Windermere Ave Ellington CT 06029",
    "addr:housenumber":"100",
    "addr:postcode":"06029",
    "addr:street":"Windermere Ave Ellington Ct",
    "iso:country":"US",
    "sg:address":"100 Windermere Ave",
    "sg:city":"Ellington",
    "sg:classifiers":[
        {
            "category":"Autos & Motor Vehicles",
            "subcategory":"Auto Supplies",
            "type":"Retail Goods"
        }
    ],
    "sg:phone":"+1 860 872 1932",
    "sg:postcode":"06029",
    "sg:province":"CT",
    "sg:tags":[
        "automobile",
        "part"
    ],
    "sg:website":"http://www.julianos.com",
    "wof:name":"Juliano's Interiors",
    "wof:placetype":"venue"
},
  "geometry": {"coordinates":[-72.47695899999999,41.875881],"type":"Point"}
}