{
  "type": "Feature",
  "properties": {
    "iso:country":"US",
    "sg:address":"513 Frost Rd",
    "sg:city":"Waterbury",
    "sg:classifiers":[
        {
            "category":"Personal",
            "subcategory":"Tanning Parlor",
            "type":"Services"
        }
    ],
    "sg:phone":"+1 203 596 0051",
    "sg:postcode":"06705",
    "sg:province":"CT",
    "sg:tags":[
        "salon"
    ],
    "wof:name":"Tanning Oasis",
    "wof:placetype":"venue"
},
  "geometry": {"coordinates":[-73.000336,41.552743],"type":"Point"}
}