{
  "type": "Feature",
  "properties": {
    "iso:country":"US",
    "sg:address":"555 Winthrop Ave",
    "sg:city":"New Haven",
    "sg:classifiers":[
        {
            "category":"Real Estate",
            "subcategory":"Real Estate Agent",
            "type":"Services"
        }
    ],
    "sg:phone":"+1 203 624 9562",
    "sg:postcode":"06511",
    "sg:province":"CT",
    "wof:name":"I & S Real Estate",
    "wof:placetype":"venue"
},
  "geometry": {"coordinates":[-72.942759,41.320089],"type":"Point"}
}