{
  "type": "Feature",
  "properties": {
    "iso:country":"US",
    "sg:address":"165 Benton St",
    "sg:city":"Stratford",
    "sg:classifiers":[
        {
            "category":"Retail",
            "subcategory":"Repair Shop",
            "type":"Services"
        }
    ],
    "sg:phone":"+1 203 375 5538",
    "sg:postcode":"06615",
    "sg:province":"CT",
    "sg:tags":[
        "plate",
        "work",
        "fabricated",
        "welding",
        "mfg"
    ],
    "wof:name":"Modern Welding Co",
    "wof:placetype":"venue"
},
  "geometry": {"coordinates":[-73.14012700000001,41.17008],"type":"Point"}
}