{
  "type": "Feature",
  "properties": {
    "iso:country":"US",
    "sg:address":"1349 Southford Rd",
    "sg:city":"Southbury",
    "sg:classifiers":[
        {
            "category":"Retail",
            "subcategory":"Auto Repair",
            "type":"Services"
        }
    ],
    "sg:phone":"+1   ",
    "sg:postcode":"06488",
    "sg:province":"CT",
    "sg:tags":[
        "body"
    ],
    "wof:name":"Southbury Auto Body & Painting",
    "wof:placetype":"venue"
},
  "geometry": {"coordinates":[-73.16618699999999,41.465735],"type":"Point"}
}