{
  "type": "Feature",
  "properties": {
    "iso:country":"US",
    "sg:address":"1198 New Britain Ave",
    "sg:city":"Hartford",
    "sg:classifiers":[
        {
            "category":"Professional",
            "subcategory":"Management & Consulting",
            "type":"Services"
        }
    ],
    "sg:phone":"+1   ",
    "sg:postcode":"06110",
    "sg:province":"CT",
    "wof:name":"Hank Cleary Associates LLC",
    "wof:placetype":"venue"
},
  "geometry": {"coordinates":[-72.737662,41.732268],"type":"Point"}
}