{
  "type": "Feature",
  "properties": {
    "addr:full":"51 Main St Groton CT 06340",
    "addr:housenumber":"51",
    "addr:postcode":"06340",
    "addr:street":"Main St",
    "iso:country":"US",
    "sg:address":"51 Main St",
    "sg:city":"Groton",
    "sg:classifiers":[
        {
            "category":"Building & Trades",
            "subcategory":"Landscaping Services",
            "type":"Services"
        }
    ],
    "sg:phone":"+1 860 536 6921",
    "sg:postcode":"06340",
    "sg:province":"CT",
    "sg:tags":[
        "landscape"
    ],
    "wof:name":"Blackers Landscaping LLC",
    "wof:placetype":"venue"
},
  "geometry": {"coordinates":[-71.987426,41.32569],"type":"Point"}
}