{
  "type": "Feature",
  "properties": {
    "iso:country":"US",
    "sg:address":"125 Appletree Ln",
    "sg:city":"Portland",
    "sg:classifiers":[
        {
            "category":"Professional",
            "subcategory":"Management & Consulting",
            "type":"Services"
        }
    ],
    "sg:phone":"+1   ",
    "sg:postcode":"06480",
    "sg:province":"CT",
    "sg:tags":[
        "business"
    ],
    "wof:name":"Tamm Consulting Solution LLC",
    "wof:placetype":"venue"
},
  "geometry": {"coordinates":[-72.59998400000001,41.623742],"type":"Point"}
}