{
  "type": "Feature",
  "properties": {
    "iso:country":"US",
    "sg:address":"1306 State St",
    "sg:city":"New Haven",
    "sg:classifiers":[
        {
            "category":"Food & Beverages",
            "subcategory":"Liquor & Beverages",
            "type":"Retail Goods"
        }
    ],
    "sg:phone":"+1 203 624 7063",
    "sg:postcode":"06511",
    "sg:province":"CT",
    "wof:name":"Marine Package Store",
    "wof:placetype":"venue"
},
  "geometry": {"coordinates":[-72.899315,41.318995],"type":"Point"}
}