{
  "type": "Feature",
  "properties": {
    "addr:full":"315 Main St Southington CT 06489",
    "addr:housenumber":"315",
    "addr:postcode":"06489",
    "addr:street":"Main St",
    "iso:country":"US",
    "sg:address":"315 Main St",
    "sg:city":"Southington",
    "sg:classifiers":[
        {
            "category":"Insurance",
            "subcategory":"Insurance Agent",
            "type":"Services"
        }
    ],
    "sg:phone":"+1 860 628 2200",
    "sg:postcode":"06489",
    "sg:province":"CT",
    "sg:tags":[
        "agency"
    ],
    "wof:name":"Tacinelli Agency Inc",
    "wof:placetype":"venue"
},
  "geometry": {"coordinates":[-72.877813,41.596291],"type":"Point"}
}