{
  "type": "Feature",
  "properties": {
    "iso:country":"US",
    "sg:address":"465 Ironwood Trl",
    "sg:city":"Shelton",
    "sg:classifiers":[
        {
            "category":"Communications",
            "type":"Services"
        }
    ],
    "sg:phone":"+1 203 925 9731",
    "sg:postcode":"06484",
    "sg:province":"CT",
    "sg:tags":[
        "communication"
    ],
    "wof:name":"Cjm Communications LLC",
    "wof:placetype":"venue"
},
  "geometry": {"coordinates":[-73.134798,41.29266],"type":"Point"}
}