{
  "type": "Feature",
  "properties": {
    "iso:country":"US",
    "sg:address":"89 West Rd",
    "sg:city":"Ellington",
    "sg:classifiers":[
        {
            "category":"Home & Garden",
            "subcategory":"Building Materials",
            "type":"Retail Goods"
        }
    ],
    "sg:phone":"+1 860 875 2230",
    "sg:postcode":"06029",
    "sg:province":"CT",
    "sg:tags":[
        "c",
        "door",
        "windows",
        "distribute",
        "cabinet",
        "kitchen"
    ],
    "wof:name":"Advanced Kitchens & Millwork",
    "wof:placetype":"venue"
},
  "geometry": {"coordinates":[-72.46409800000001,41.881311],"type":"Point"}
}