{
  "type": "Feature",
  "properties": {
    "iso:country":"US",
    "sg:address":"144 S Main St",
    "sg:city":"Colchester",
    "sg:classifiers":[
        {
            "category":"Retail",
            "subcategory":"Funeral Services",
            "type":"Services"
        }
    ],
    "sg:phone":"+1   ",
    "sg:postcode":"06415",
    "sg:province":"CT",
    "sg:tags":[
        "home"
    ],
    "wof:name":"Belmont Funeral Home",
    "wof:placetype":"venue"
},
  "geometry": {"coordinates":[-72.33151599999999,41.572006],"type":"Point"}
}