{
  "type": "Feature",
  "properties": {
    "iso:country":"US",
    "sg:address":"45 Whiting St",
    "sg:city":"Plainville",
    "sg:classifiers":[
        {
            "category":"Retail",
            "subcategory":"Laundry & Dry Cleaning",
            "type":"Services"
        }
    ],
    "sg:phone":"+1   ",
    "sg:postcode":"06062",
    "sg:province":"CT",
    "sg:tags":[
        "drycleaning",
        "plant"
    ],
    "wof:name":"Kims Cleaners",
    "wof:placetype":"venue"
},
  "geometry": {"coordinates":[-72.867284,41.667998],"type":"Point"}
}