{
  "type": "Feature",
  "properties": {
    "iso:country":"US",
    "sg:address":"57 North St",
    "sg:city":"Danbury",
    "sg:classifiers":[
        {
            "category":"Health Services",
            "subcategory":"Podiatrist",
            "type":"Services"
        }
    ],
    "sg:phone":"+1 203 743 5009",
    "sg:postcode":"06810",
    "sg:province":"CT",
    "sg:tags":[
        "physician",
        "surgeons"
    ],
    "wof:name":"Jolly, Gary",
    "wof:placetype":"venue"
},
  "geometry": {"coordinates":[-73.456177,41.406528],"type":"Point"}
}