{
  "type": "Feature",
  "properties": {
    "addr:full":"100 Hawley Ln Trumbull CT 06611",
    "addr:housenumber":"100",
    "addr:postcode":"06611",
    "addr:street":"Hawley Ln",
    "iso:country":"US",
    "sg:address":"100 Hawley Ln",
    "sg:city":"Trumbull",
    "sg:classifiers":[
        {
            "category":"Professional",
            "type":"Services"
        }
    ],
    "sg:phone":"+1 203 375 5152",
    "sg:postcode":"06611",
    "sg:province":"CT",
    "sg:tags":[
        "establishment"
    ],
    "wof:name":"Bell & Beep",
    "wof:placetype":"venue"
},
  "geometry": {"coordinates":[-73.15012900000001,41.232868],"type":"Point"}
}