{
  "type": "Feature",
  "properties": {
    "addr:full":"2005 Wilbur Cross Hwy Berlin CT 06037",
    "addr:housenumber":"2005",
    "addr:postcode":"06037",
    "addr:street":"Wilbur Cross Hwy",
    "iso:country":"US",
    "sg:address":"2005 Wilbur Cross Hwy",
    "sg:city":"Berlin",
    "sg:classifiers":[
        {
            "category":"Bakery",
            "type":"Food & Drink"
        },
        {
            "category":"Coffee & Tea",
            "type":"Food & Drink"
        },
        {
            "category":"Bagels",
            "type":"Food & Drink"
        },
        {
            "category":"Donuts",
            "type":"Food & Drink"
        }
    ],
    "sg:menulink":"http://www.allmenus.com/ct/berlin/129768-dunkin-donuts/menu/",
    "sg:phone":"+1 860 828 5885",
    "sg:postcode":"06037",
    "sg:province":"CT",
    "sg:tags":[
        "american",
        "diner",
        "pastry"
    ],
    "wof:name":"Dunkin' Donuts",
    "wof:placetype":"venue"
},
  "geometry": {"coordinates":[-72.75524799999999,41.596312],"type":"Point"}
}