{
  "type": "Feature",
  "properties": {
    "iso:country":"US",
    "sg:address":"801 Whalley Ave",
    "sg:city":"New Haven",
    "sg:classifiers":[
        {
            "category":"Food & Beverages",
            "subcategory":"Groceries & Convenience Stores",
            "type":"Retail Goods"
        }
    ],
    "sg:phone":"+1 203 907 0307",
    "sg:postcode":"06515",
    "sg:province":"CT",
    "wof:name":"AMS Gas & Convenience",
    "wof:placetype":"venue"
},
  "geometry": {"coordinates":[-72.958275,41.325739],"type":"Point"}
}