{
  "type": "Feature",
  "properties": {
    "addr:full":"12 Omega Dr Stamford CT 06907",
    "addr:housenumber":"12",
    "addr:postcode":"06907",
    "addr:street":"Omega Dr",
    "iso:country":"US",
    "sg:address":"12 Omega Dr",
    "sg:city":"Stamford",
    "sg:classifiers":[
        {
            "category":"Utilities",
            "subcategory":"Mobile Phone",
            "type":"Services"
        }
    ],
    "sg:phone":"+1 203 353 0345",
    "sg:postcode":"06907",
    "sg:province":"CT",
    "sg:tags":[
        "telephone",
        "cellular"
    ],
    "wof:name":"Cingular Wireless",
    "wof:placetype":"venue"
},
  "geometry": {"coordinates":[-73.51561,41.085776],"type":"Point"}
}