{
  "type": "Feature",
  "properties": {
    "iso:country":"US",
    "sg:address":"4695 Main St",
    "sg:city":"Bridgeport",
    "sg:classifiers":[
        {
            "category":"Health Services",
            "subcategory":"Podiatrist",
            "type":"Services"
        }
    ],
    "sg:phone":"+1 203 268 4906",
    "sg:postcode":"06606",
    "sg:province":"CT",
    "wof:name":"Affiliated Foot Care-Trumbull",
    "wof:placetype":"venue"
},
  "geometry": {"coordinates":[-73.2183,41.224499],"type":"Point"}
}