{
  "type": "Feature",
  "properties": {
    "iso:country":"US",
    "sg:address":"383 Hazard Ave",
    "sg:city":"Enfield",
    "sg:classifiers":[
        {
            "category":"Organizations",
            "subcategory":"Religious Organization",
            "type":"Services"
        }
    ],
    "sg:phone":"+1   ",
    "sg:postcode":"06082",
    "sg:province":"CT",
    "wof:name":"Ncerm",
    "wof:placetype":"venue"
},
  "geometry": {"coordinates":[-72.534982,41.986216],"type":"Point"}
}