{
  "type": "Feature",
  "properties": {
    "addr:full":"123 Strickland Rd Middlefield CT 06455",
    "addr:housenumber":"123",
    "addr:postcode":"06455",
    "addr:street":"Strickland Rd",
    "iso:country":"US",
    "sg:address":"123 Strickland Rd",
    "sg:city":"Middlefield",
    "sg:classifiers":[
        {
            "category":"Manufacturing",
            "subcategory":"Tools & Machinery",
            "type":"Manufacturing & Wholesale Goods"
        }
    ],
    "sg:phone":"+1   ",
    "sg:postcode":"06455",
    "sg:province":"CT",
    "sg:tags":[
        "small",
        "machine",
        "mfg",
        "fabrication",
        "welding"
    ],
    "wof:name":"A 1 Services",
    "wof:placetype":"venue"
},
  "geometry": {"coordinates":[-72.69893399999999,41.511396],"type":"Point"}
}