{
  "type": "Feature",
  "properties": {
    "iso:country":"US",
    "sg:address":"192 Dixwell Ave",
    "sg:city":"New Haven",
    "sg:classifiers":[
        {
            "category":"Health Services",
            "subcategory":"Doctor",
            "type":"Services"
        }
    ],
    "sg:phone":"+1   ",
    "sg:postcode":"06511",
    "sg:province":"CT",
    "wof:name":"Wm H Pitts DDS",
    "wof:placetype":"venue"
},
  "geometry": {"coordinates":[-72.93386099999999,41.318464],"type":"Point"}
}