{
  "type": "Feature",
  "properties": {
    "iso:country":"US",
    "sg:address":"73 Arch St",
    "sg:city":"Greenwich",
    "sg:classifiers":[
        {
            "category":"Banks & Credit Unions",
            "subcategory":"Investment Brokerage",
            "type":"Services"
        }
    ],
    "sg:phone":"+1 203 863 5400",
    "sg:postcode":"06830",
    "sg:province":"CT",
    "wof:name":"Black Arrow Global Invstmnt",
    "wof:placetype":"venue"
},
  "geometry": {"coordinates":[-73.626887,41.022756],"type":"Point"}
}