{
  "type": "Feature",
  "properties": {
    "addr:full":"335 Rock House Rd Easton CT 06612",
    "addr:housenumber":"335",
    "addr:postcode":"06612",
    "addr:street":"Rock House Rd",
    "iso:country":"US",
    "sg:address":"335 Rock House Rd",
    "sg:city":"Easton",
    "sg:classifiers":[
        {
            "category":"Building & Trades",
            "subcategory":"Construction",
            "type":"Services"
        }
    ],
    "sg:phone":"+1 203 268 4662",
    "sg:postcode":"06612",
    "sg:province":"CT",
    "sg:tags":[
        "concrete",
        "paving",
        "contractor"
    ],
    "wof:name":"Santangeli Construction Inc",
    "wof:placetype":"venue"
},
  "geometry": {"coordinates":[-73.319441,41.290225],"type":"Point"}
}