{
  "type": "Feature",
  "properties": {
    "iso:country":"US",
    "sg:address":"107 North Ave",
    "sg:city":"Westport",
    "sg:classifiers":[
        {
            "category":"Building & Trades",
            "subcategory":"Landscaping Services",
            "type":"Services"
        }
    ],
    "sg:phone":"+1 203 227 6268",
    "sg:postcode":"06880",
    "sg:province":"CT",
    "sg:tags":[
        "landscape",
        "contractor"
    ],
    "wof:name":"Suburban Lawn Svc",
    "wof:placetype":"venue"
},
  "geometry": {"coordinates":[-73.335329,41.159109],"type":"Point"}
}