{
  "type": "Feature",
  "properties": {
    "iso:country":"US",
    "sg:address":"34 Imperial Ave",
    "sg:city":"Westport",
    "sg:classifiers":[
        {
            "category":"Building & Trades",
            "subcategory":"Construction",
            "type":"Services"
        }
    ],
    "sg:phone":"+1 203 226 1000",
    "sg:postcode":"06880",
    "sg:province":"CT",
    "sg:tags":[
        "general",
        "contractor"
    ],
    "wof:name":"Rychlik/Tudor Builders Inc",
    "wof:placetype":"venue"
},
  "geometry": {"coordinates":[-73.358473,41.139421],"type":"Point"}
}