{
  "type": "Feature",
  "properties": {
    "addr:full":"44 Skyline Dr Plainville CT 06062",
    "addr:housenumber":"44",
    "addr:postcode":"06062",
    "addr:street":"Skyline Dr",
    "iso:country":"US",
    "sg:address":"44 Skyline Dr",
    "sg:city":"Plainville",
    "sg:classifiers":[
        {
            "category":"Wholesale",
            "subcategory":"Machinery & Supplies",
            "type":"Manufacturing & Wholesale Goods"
        }
    ],
    "sg:phone":"+1 860 747 2211",
    "sg:postcode":"06062",
    "sg:province":"CT",
    "sg:tags":[
        "equipment",
        "industrial"
    ],
    "wof:name":"Redstone Machinery LLC",
    "wof:placetype":"venue"
},
  "geometry": {"coordinates":[-72.88369899999999,41.657499],"type":"Point"}
}