{
  "type": "Feature",
  "properties": {
    "addr:full":"72 Maple St Bristol CT 06010",
    "addr:housenumber":"72",
    "addr:postcode":"06010",
    "addr:street":"Maple St",
    "iso:country":"US",
    "sg:address":"72 Maple St",
    "sg:city":"Bristol",
    "sg:classifiers":[
        {
            "category":"Retail",
            "subcategory":"Photofinishing",
            "type":"Services"
        }
    ],
    "sg:phone":"+1   ",
    "sg:postcode":"06010",
    "sg:province":"CT",
    "sg:tags":[
        "laboratory"
    ],
    "wof:name":"Dave Norton Photo",
    "wof:placetype":"venue"
},
  "geometry": {"coordinates":[-72.940979,41.679],"type":"Point"}
}