{
  "type": "Feature",
  "properties": {
    "addr:full":"4 Cleveland St Stamford CT 06907",
    "addr:housenumber":"4",
    "addr:postcode":"06907",
    "addr:street":"Cleveland St",
    "iso:country":"US",
    "sg:address":"4 Cleveland St",
    "sg:city":"Stamford",
    "sg:classifiers":[
        {
            "category":"Building & Trades",
            "subcategory":"Construction",
            "type":"Services"
        }
    ],
    "sg:phone":"+1 203 359 4772",
    "sg:postcode":"06907",
    "sg:province":"CT",
    "sg:tags":[
        "contractor"
    ],
    "wof:name":"P&A Masonry LLC",
    "wof:placetype":"venue"
},
  "geometry": {"coordinates":[-73.522882,41.082535],"type":"Point"}
}