{
  "type": "Feature",
  "properties": {
    "addr:full":"1 Joanne Ln Weston CT 06883",
    "addr:housenumber":"1",
    "addr:postcode":"06883",
    "addr:street":"Joanne Ln",
    "iso:country":"US",
    "sg:address":"1 Joanne Ln",
    "sg:city":"Weston",
    "sg:classifiers":[
        {
            "category":"Professional",
            "type":"Services"
        }
    ],
    "sg:phone":"+1 203 227 5599",
    "sg:postcode":"06883",
    "sg:province":"CT",
    "sg:tags":[
        "establishment"
    ],
    "wof:name":"Falcon Group",
    "wof:placetype":"venue"
},
  "geometry": {"coordinates":[-73.37744000000001,41.193284],"type":"Point"}
}