{
  "type": "Feature",
  "properties": {
    "addr:full":"49 Jennings Rd Hartford CT 06120",
    "addr:housenumber":"49",
    "addr:postcode":"06120",
    "addr:street":"Jennings Rd",
    "iso:country":"US",
    "sg:address":"49 Jennings Rd",
    "sg:city":"Hartford",
    "sg:classifiers":[
        {
            "category":"Government",
            "subcategory":"Office",
            "type":"Public Place"
        }
    ],
    "sg:phone":"+1 860 566 3156",
    "sg:postcode":"06120",
    "sg:province":"CT",
    "sg:tags":[
        "garage",
        "transportation",
        "maintenance"
    ],
    "wof:name":"Maintenance Garage Elec Dept",
    "wof:placetype":"venue"
},
  "geometry": {"coordinates":[-72.65420899999999,41.786338],"type":"Point"}
}