{
  "type": "Feature",
  "properties": {
    "iso:country":"US",
    "sg:address":"728 Farmington Ave",
    "sg:city":"Bristol",
    "sg:classifiers":[
        {
            "category":"Home & Garden",
            "subcategory":"Household Appliances",
            "type":"Retail Goods"
        }
    ],
    "sg:phone":"+1 860 589 8222",
    "sg:postcode":"06010",
    "sg:province":"CT",
    "sg:tags":[
        "cleaners",
        "vacuum"
    ],
    "wof:name":"Connecticut Vacuum & Supply",
    "wof:placetype":"venue"
},
  "geometry": {"coordinates":[-72.91827499999999,41.692076],"type":"Point"}
}