{
  "type": "Feature",
  "properties": {
    "iso:country":"US",
    "sg:address":"16 Lanesville Rd",
    "sg:city":"New Milford",
    "sg:classifiers":[
        {
            "category":"Government",
            "subcategory":"Fire Station",
            "type":"Public Place"
        }
    ],
    "sg:phone":"+1 860 354 2952",
    "sg:postcode":"06776",
    "sg:province":"CT",
    "sg:tags":[
        "protection"
    ],
    "wof:name":"Lanesville Fire Dept",
    "wof:placetype":"venue"
},
  "geometry": {"coordinates":[-73.420897,41.536191],"type":"Point"}
}