{
  "type": "Feature",
  "properties": {
    "addr:full":"85 Tower Rd White Plains NY 10604",
    "addr:housenumber":"85",
    "addr:postcode":"10604",
    "addr:street":"Tower Rd",
    "iso:country":"US",
    "sg:address":"85 Tower Rd",
    "sg:city":"White Plains",
    "sg:classifiers":[
        {
            "category":"Airport",
            "type":"Transportation"
        }
    ],
    "sg:phone":"+1 914 428 3730",
    "sg:postcode":"10604",
    "sg:province":"NY",
    "sg:tags":[
        "aircraft",
        "support",
        "ground"
    ],
    "wof:name":"Avitat Westchester",
    "wof:placetype":"venue"
},
  "geometry": {"coordinates":[-73.715205,41.061394],"type":"Point"}
}