{
  "type": "Feature",
  "properties": {
    "iso:country":"US",
    "sg:address":"7 N Valley Rd",
    "sg:city":"New Milford",
    "sg:classifiers":[
        {
            "category":"Building & Trades",
            "subcategory":"Landscaping Services",
            "type":"Services"
        }
    ],
    "sg:phone":"+1 860 354 3221",
    "sg:postcode":"06776",
    "sg:province":"CT",
    "sg:tags":[
        "landscape"
    ],
    "wof:name":"Caselli Landscaping LLC",
    "wof:placetype":"venue"
},
  "geometry": {"coordinates":[-73.43604000000001,41.615219],"type":"Point"}
}