{
  "type": "Feature",
  "properties": {
    "addr:full":"1005 Farmington Ave Hartford CT 06107",
    "addr:housenumber":"1005",
    "addr:postcode":"06107",
    "addr:street":"Farmington Ave;Ct",
    "iso:country":"US",
    "sg:address":"1005 Farmington Ave",
    "sg:city":"Hartford",
    "sg:classifiers":[
        {
            "category":"Health Services",
            "subcategory":"Doctor",
            "type":"Services"
        }
    ],
    "sg:phone":"+1   ",
    "sg:postcode":"06107",
    "sg:province":"CT",
    "wof:name":"Cromwell DMD",
    "wof:placetype":"venue"
},
  "geometry": {"coordinates":[-72.74547099999999,41.760861],"type":"Point"}
}