{
  "type": "Feature",
  "properties": {
    "addr:full":"39 N Turnpike Rd Wallingford CT 06492",
    "addr:housenumber":"39",
    "addr:postcode":"06492",
    "addr:street":"N Turnpike Rd",
    "iso:country":"US",
    "sg:address":"39 N Turnpike Rd",
    "sg:city":"Wallingford",
    "sg:classifiers":[
        {
            "category":"Professional",
            "subcategory":"Employment Agencies",
            "type":"Services"
        }
    ],
    "sg:phone":"+1   ",
    "sg:postcode":"06492",
    "sg:province":"CT",
    "sg:tags":[
        "help",
        "supply"
    ],
    "wof:name":"Kleening Krew",
    "wof:placetype":"venue"
},
  "geometry": {"coordinates":[-72.831757,41.471484],"type":"Point"}
}