{
  "type": "Feature",
  "properties": {
    "addr:full":"44 Laurel Ledge Ct Stamford CT 06903",
    "addr:housenumber":"44",
    "addr:postcode":"06903",
    "addr:street":"Laurel Ledge Ct",
    "iso:country":"US",
    "sg:address":"44 Laurel Ledge Ct",
    "sg:city":"Stamford",
    "sg:classifiers":[
        {
            "category":"Professional",
            "subcategory":"Business Services",
            "type":"Services"
        }
    ],
    "sg:phone":"+1   ",
    "sg:postcode":"06903",
    "sg:province":"CT",
    "sg:tags":[
        "representative"
    ],
    "wof:name":"H Lewis Packaging LLC",
    "wof:placetype":"venue"
},
  "geometry": {"coordinates":[-73.598305,41.141291],"type":"Point"}
}