{
  "type": "Feature",
  "properties": {
    "iso:country":"US",
    "sg:address":"435 Main St",
    "sg:city":"Monroe",
    "sg:classifiers":[
        {
            "category":"Shopping",
            "subcategory":"Clothing, Apparel, & Fashions",
            "type":"Retail Goods"
        }
    ],
    "sg:phone":"+1 203 268 6585",
    "sg:postcode":"06468",
    "sg:province":"CT",
    "sg:tags":[
        "wig",
        "toupee",
        "hairpiece"
    ],
    "wof:name":"LA Coiffure",
    "wof:placetype":"venue"
},
  "geometry": {"coordinates":[-73.26446799999999,41.321737],"type":"Point"}
}