{
  "type": "Feature",
  "properties": {
    "iso:country":"US",
    "sg:address":"592 Haviland Rd",
    "sg:city":"Stamford",
    "sg:classifiers":[
        {
            "category":"Professional",
            "subcategory":"Business Services",
            "type":"Services"
        }
    ],
    "sg:phone":"+1   ",
    "sg:postcode":"06903",
    "sg:province":"CT",
    "wof:name":"Shelbourne Interiors",
    "wof:placetype":"venue"
},
  "geometry": {"coordinates":[-73.577614,41.140303],"type":"Point"}
}