{
  "type": "Feature",
  "properties": {
    "iso:country":"US",
    "sg:address":"37 Griffin Rd",
    "sg:city":"East Granby",
    "sg:classifiers":[
        {
            "category":"Recreation",
            "type":"Entertainment"
        }
    ],
    "sg:phone":"+1   ",
    "sg:postcode":"06026",
    "sg:province":"CT",
    "wof:name":"Copper Hll Glf Acad & Drvg Rge",
    "wof:placetype":"venue"
},
  "geometry": {"coordinates":[-72.752476,41.974087],"type":"Point"}
}