{
  "type": "Feature",
  "properties": {
    "addr:full":"76 Sturges Ridge Rd Wilton CT 06897",
    "addr:housenumber":"76",
    "addr:postcode":"06897",
    "addr:street":"Sturges Ridge Rd Wilton Ct",
    "iso:country":"US",
    "sg:address":"76 Sturges Ridge Rd",
    "sg:city":"Wilton",
    "sg:classifiers":[
        {
            "category":"Shopping",
            "subcategory":"Clothing, Apparel, & Fashions",
            "type":"Retail Goods"
        }
    ],
    "sg:phone":"+1 203 762 5424",
    "sg:postcode":"06897",
    "sg:province":"CT",
    "wof:name":"Tallmadges Wilton Store",
    "wof:placetype":"venue"
},
  "geometry": {"coordinates":[-73.398422,41.202946],"type":"Point"}
}