{
  "type": "Feature",
  "properties": {
    "iso:country":"US",
    "sg:address":"914 E Main St",
    "sg:city":"Stamford",
    "sg:classifiers":[
        {
            "category":"Home & Garden",
            "subcategory":"Furniture",
            "type":"Retail Goods"
        },
        {
            "category":"Home & Garden",
            "subcategory":"Carpets & Floor Coverings",
            "type":"Retail Goods"
        }
    ],
    "sg:phone":"+1 203 327 0450",
    "sg:postcode":"06902",
    "sg:province":"CT",
    "sg:tags":[
        "dealer",
        "rug"
    ],
    "sg:website":"www.jcbdistributors.com",
    "wof:name":"JCB Furniture & Carpet",
    "wof:placetype":"venue"
},
  "geometry": {"coordinates":[-73.52300700000001,41.056058],"type":"Point"}
}