{
  "type": "Feature",
  "properties": {
    "addr:full":"167 Orange St New Haven CT 06510",
    "addr:housenumber":"167",
    "addr:postcode":"06510",
    "addr:street":"Orange St",
    "iso:country":"US",
    "sg:address":"167 Orange St",
    "sg:city":"New Haven",
    "sg:classifiers":[
        {
            "category":"Restaurant",
            "type":"Food & Drink"
        }
    ],
    "sg:phone":"+1 203 787 5289",
    "sg:postcode":"06510",
    "sg:province":"CT",
    "wof:name":"Katz's 2 Go",
    "wof:placetype":"venue"
},
  "geometry": {"coordinates":[-72.924103,41.305537],"type":"Point"}
}