{
  "type": "Feature",
  "properties": {
    "addr:full":"174 W Center St Manchester CT 06040",
    "addr:housenumber":"174",
    "addr:postcode":"06040",
    "addr:street":"W Center St",
    "iso:country":"US",
    "sg:address":"174 W Center St",
    "sg:city":"Manchester",
    "sg:classifiers":[
        {
            "category":"Retail",
            "subcategory":"Auto Repair",
            "type":"Services"
        }
    ],
    "sg:phone":"+1   ",
    "sg:postcode":"06040",
    "sg:province":"CT",
    "sg:tags":[
        "general"
    ],
    "wof:name":"P & P Auto Repair Inc",
    "wof:placetype":"venue"
},
  "geometry": {"coordinates":[-72.542951,41.771033],"type":"Point"}
}