{
  "type": "Feature",
  "properties": {
    "iso:country":"US",
    "sg:address":"17 Starr Ave",
    "sg:city":"Danbury",
    "sg:classifiers":[
        {
            "category":"Professional",
            "subcategory":"Computer Services",
            "type":"Services"
        }
    ],
    "sg:phone":"+1   ",
    "sg:postcode":"06810",
    "sg:province":"CT",
    "sg:tags":[
        "related"
    ],
    "wof:name":"Informatica USA LLC",
    "wof:placetype":"venue"
},
  "geometry": {"coordinates":[-73.464523,41.402388],"type":"Point"}
}