{
  "type": "Feature",
  "properties": {
    "addr:full":"33 Valerie Ln Danbury CT 06811",
    "addr:housenumber":"33",
    "addr:postcode":"06811",
    "addr:street":"Valerie Ln",
    "iso:country":"US",
    "sg:address":"33 Valerie Ln",
    "sg:city":"Danbury",
    "sg:classifiers":[
        {
            "category":"Building & Trades",
            "subcategory":"Plumbing",
            "type":"Services"
        }
    ],
    "sg:phone":"+1 203 744 3456",
    "sg:postcode":"06811",
    "sg:province":"CT",
    "sg:tags":[
        "plumbing",
        "contractor"
    ],
    "wof:name":"Evergreen Earth Products & Svc",
    "wof:placetype":"venue"
},
  "geometry": {"coordinates":[-73.445646,41.41959],"type":"Point"}
}