{
  "type": "Feature",
  "properties": {
    "addr:full":"70 West Ln Greenwich CT 06831",
    "addr:housenumber":"70",
    "addr:postcode":"06831",
    "addr:street":"West Ln",
    "iso:country":"US",
    "sg:address":"70 West Ln",
    "sg:city":"Greenwich",
    "sg:classifiers":[
        {
            "category":"Building & Trades",
            "subcategory":"Construction",
            "type":"Services"
        }
    ],
    "sg:phone":"+1 203 629 8292",
    "sg:postcode":"06831",
    "sg:province":"CT",
    "sg:tags":[
        "painter"
    ],
    "wof:name":"Frank Marino Custom Painting",
    "wof:placetype":"venue"
},
  "geometry": {"coordinates":[-73.702719,41.111198],"type":"Point"}
}