{
  "type": "Feature",
  "properties": {
    "addr:full":"517 Boston Post Rd Port Chester CT 10573",
    "addr:housenumber":"517",
    "addr:postcode":"10573",
    "addr:street":"Boston Post Rd",
    "iso:country":"US",
    "sg:address":"517 Boston Post Rd",
    "sg:city":"Port Chester",
    "sg:classifiers":[
        {
            "category":"Shopping",
            "subcategory":"Shoes",
            "type":"Retail Goods"
        }
    ],
    "sg:phone":"+1   ",
    "sg:postcode":"10573",
    "sg:province":"CT",
    "wof:name":"Payless Shoesource",
    "wof:placetype":"venue"
},
  "geometry": {"coordinates":[-73.67564900000001,40.99324],"type":"Point"}
}