{
  "type": "Feature",
  "properties": {
    "iso:country":"US",
    "sg:address":"400 Prospect St",
    "sg:city":"New Haven",
    "sg:classifiers":[
        {
            "category":"Real Estate",
            "subcategory":"Real Estate Agent",
            "type":"Services"
        }
    ],
    "sg:phone":"+1 203 777 2970",
    "sg:postcode":"06511",
    "sg:province":"CT",
    "wof:name":"Charles Sterling Assoc",
    "wof:placetype":"venue"
},
  "geometry": {"coordinates":[-72.923464,41.322361],"type":"Point"}
}