{
  "type": "Feature",
  "properties": {
    "addr:full":"470 Lewis Ave Meriden CT 06451",
    "addr:housenumber":"470",
    "addr:postcode":"06451",
    "addr:street":"Lewis Ave",
    "iso:country":"US",
    "sg:address":"470 Lewis Ave",
    "sg:city":"Meriden",
    "sg:classifiers":[
        {
            "category":"Utilities",
            "subcategory":"Mobile Phone",
            "type":"Services"
        }
    ],
    "sg:phone":"+1 203 235 2333",
    "sg:postcode":"06451",
    "sg:province":"CT",
    "sg:tags":[
        "telephone",
        "cellular"
    ],
    "wof:name":"SNS Communications Inc",
    "wof:placetype":"venue"
},
  "geometry": {"coordinates":[-72.803605,41.550627],"type":"Point"}
}