{
  "type": "Feature",
  "properties": {
    "iso:country":"US",
    "sg:address":"43 Berlin Rd",
    "sg:city":"Cromwell",
    "sg:classifiers":[
        {
            "category":"Restaurant",
            "type":"Food & Drink"
        }
    ],
    "sg:menulink":"http://www.allmenus.com/ct/cromwell/124465-quiznos-sub/menu/",
    "sg:phone":"+1 860 632 2131",
    "sg:postcode":"06416",
    "sg:province":"CT",
    "sg:tags":[
        "wrap",
        "american",
        "sandwich"
    ],
    "wof:name":"Quiznos Sub",
    "wof:placetype":"venue"
},
  "geometry": {"coordinates":[-72.68486799999999,41.602217],"type":"Point"}
}