{
  "type": "Feature",
  "properties": {
    "iso:country":"US",
    "sg:address":"1275 Summer St",
    "sg:city":"Stamford",
    "sg:classifiers":[
        {
            "category":"Health Services",
            "subcategory":"Doctor",
            "type":"Services"
        }
    ],
    "sg:phone":"+1 203 353 1857",
    "sg:postcode":"06905",
    "sg:province":"CT",
    "sg:tags":[
        "physician",
        "medical",
        "surgeon"
    ],
    "wof:name":"Richard B Weber MD",
    "wof:placetype":"venue"
},
  "geometry": {"coordinates":[-73.54163699999999,41.061956],"type":"Point"}
}