{
  "type": "Feature",
  "properties": {
    "addr:full":"60 East St S Goshen CT 06756",
    "addr:housenumber":"60",
    "addr:postcode":"06756",
    "addr:street":"East St",
    "iso:country":"US",
    "sg:address":"60 East St S",
    "sg:city":"Goshen",
    "sg:classifiers":[
        {
            "category":"Food & Beverages",
            "subcategory":"Groceries & Convenience Stores",
            "type":"Retail Goods"
        }
    ],
    "sg:phone":"+1 860 491 3164",
    "sg:postcode":"06756",
    "sg:province":"CT",
    "wof:name":"T & Ms Village Market LLC",
    "wof:placetype":"venue"
},
  "geometry": {"coordinates":[-73.19624399999999,41.827693],"type":"Point"}
}