{
  "type": "Feature",
  "properties": {
    "addr:full":"116 Wedgemere Rd Stamford CT 06905",
    "addr:housenumber":"116",
    "addr:postcode":"06905",
    "addr:street":"Wedgemere Rd",
    "iso:country":"US",
    "sg:address":"116 Wedgemere Rd",
    "sg:city":"Stamford",
    "sg:classifiers":[
        {
            "category":"Professional",
            "subcategory":"Management & Consulting",
            "type":"Services"
        }
    ],
    "sg:phone":"+1   ",
    "sg:postcode":"06905",
    "sg:province":"CT",
    "sg:tags":[
        "business"
    ],
    "wof:name":"B Cooper Ber Consulting",
    "wof:placetype":"venue"
},
  "geometry": {"coordinates":[-73.532167,41.11291],"type":"Point"}
}