{
  "type": "Feature",
  "properties": {
    "addr:full":"180 School Rd Wilton CT 06897",
    "addr:housenumber":"180",
    "addr:postcode":"06897",
    "addr:street":"School Rd",
    "iso:country":"US",
    "sg:address":"180 School Rd",
    "sg:city":"Wilton",
    "sg:classifiers":[
        {
            "category":"Government",
            "subcategory":"Office",
            "type":"Public Place"
        }
    ],
    "sg:phone":"+1 203 834 6234",
    "sg:postcode":"06897",
    "sg:province":"CT",
    "sg:tags":[
        "conservation"
    ],
    "wof:name":"Parks/Recreation Ofc Comstock",
    "wof:placetype":"venue"
},
  "geometry": {"coordinates":[-73.437113,41.202939],"type":"Point"}
}