{
  "type": "Feature",
  "properties": {
    "iso:country":"US",
    "sg:address":"485 Bridgeport Ave",
    "sg:city":"Milford",
    "sg:classifiers":[
        {
            "category":"Health Services",
            "subcategory":"Optometrist",
            "type":"Services"
        }
    ],
    "sg:phone":"+1 203 874 0707",
    "sg:postcode":"06460",
    "sg:province":"CT",
    "wof:name":"Lifetime Eyecare & Contact Len",
    "wof:placetype":"venue"
},
  "geometry": {"coordinates":[-73.090188,41.206328],"type":"Point"}
}