{
  "type": "Feature",
  "properties": {
    "iso:country":"US",
    "sg:address":"1870 Barnum Ave",
    "sg:city":"Stratford",
    "sg:classifiers":[
        {
            "category":"Freight",
            "type":"Transportation"
        }
    ],
    "sg:phone":"+1 203 377 4795",
    "sg:postcode":"06614",
    "sg:province":"CT",
    "sg:tags":[
        "hauling",
        "trucking"
    ],
    "wof:name":"Bob's Auto Hauling",
    "wof:placetype":"venue"
},
  "geometry": {"coordinates":[-73.145292,41.193602],"type":"Point"}
}