{
  "type": "Feature",
  "properties": {
    "addr:full":"50 Old Barnabus Rd Woodbridge CT 06525",
    "addr:housenumber":"50",
    "addr:postcode":"06525",
    "addr:street":"Old Barnabus Rd",
    "iso:country":"US",
    "sg:address":"50 Old Barnabus Rd",
    "sg:city":"Woodbridge",
    "sg:classifiers":[
        {
            "category":"Building & Trades",
            "subcategory":"Construction",
            "type":"Services"
        }
    ],
    "sg:phone":"+1 203 387 3271",
    "sg:postcode":"06525",
    "sg:province":"CT",
    "sg:tags":[
        "repairing",
        "remodeling",
        "contractor"
    ],
    "wof:name":"Paul E Bello Contracting",
    "wof:placetype":"venue"
},
  "geometry": {"coordinates":[-73.01527299999999,41.333132],"type":"Point"}
}