{
  "type": "Feature",
  "properties": {
    "addr:full":"86 Beth Anne Cir Meriden CT 06450",
    "addr:housenumber":"86",
    "addr:postcode":"06450",
    "addr:street":"Beth Anne Cir",
    "iso:country":"US",
    "sg:address":"86 Beth Anne Cir",
    "sg:city":"Meriden",
    "sg:classifiers":[
        {
            "category":"Health Services",
            "subcategory":"Clinic",
            "type":"Services"
        }
    ],
    "sg:phone":"+1   ",
    "sg:postcode":"06450",
    "sg:province":"CT",
    "wof:name":"Richards Healthcare",
    "wof:placetype":"venue"
},
  "geometry": {"coordinates":[-72.786652,41.506772],"type":"Point"}
}