{
  "type": "Feature",
  "properties": {
    "addr:full":"45 Valley View Dr Wallingford CT 06492",
    "addr:housenumber":"45",
    "addr:postcode":"06492",
    "addr:street":"Valley View Dr",
    "iso:country":"US",
    "sg:address":"45 Valley View Dr",
    "sg:city":"Wallingford",
    "sg:classifiers":[
        {
            "category":"Professional",
            "subcategory":"Lawyer & Legal Services",
            "type":"Services"
        }
    ],
    "sg:phone":"+1 203 269 6713",
    "sg:postcode":"06492",
    "sg:province":"CT",
    "sg:tags":[
        "attorney"
    ],
    "wof:name":"Michael Brodinsky",
    "wof:placetype":"venue"
},
  "geometry": {"coordinates":[-72.750646,41.487854],"type":"Point"}
}