{
  "type": "Feature",
  "properties": {
    "iso:country":"US",
    "sg:address":"8 Bedford Ave",
    "sg:city":"Hamden",
    "sg:classifiers":[
        {
            "category":"Professional",
            "subcategory":"Business Services",
            "type":"Services"
        }
    ],
    "sg:phone":"+1   ",
    "sg:postcode":"06517",
    "sg:province":"CT",
    "wof:name":"Giudice Frank Asid Intr Design",
    "wof:placetype":"venue"
},
  "geometry": {"coordinates":[-72.911552,41.364495],"type":"Point"}
}