{
  "type": "Feature",
  "properties": {
    "iso:country":"US",
    "sg:address":"13 Johnson Rd",
    "sg:city":"North Stonington",
    "sg:classifiers":[
        {
            "category":"Retail",
            "subcategory":"Repair Shop",
            "type":"Services"
        }
    ],
    "sg:phone":"+1   ",
    "sg:postcode":"06359",
    "sg:province":"CT",
    "wof:name":"Decartis LLC",
    "wof:placetype":"venue"
},
  "geometry": {"coordinates":[-71.84165,41.510481],"type":"Point"}
}