{
  "type": "Feature",
  "properties": {
    "iso:country":"US",
    "sg:address":"32 Ferry Ln E",
    "sg:city":"Westport",
    "sg:classifiers":[
        {
            "category":"Banks & Credit Unions",
            "subcategory":"Financial Services",
            "type":"Services"
        }
    ],
    "sg:phone":"+1 203 226 6575",
    "sg:postcode":"06880",
    "sg:province":"CT",
    "sg:tags":[
        "holding",
        "real estate"
    ],
    "wof:name":"LL Holdings LLC",
    "wof:placetype":"venue"
},
  "geometry": {"coordinates":[-73.36701100000001,41.118127],"type":"Point"}
}