{
  "type": "Feature",
  "properties": {
    "iso:country":"US",
    "sg:address":"86 Litchfield St",
    "sg:city":"Torrington",
    "sg:classifiers":[
        {
            "category":"Insurance",
            "subcategory":"Insurance Agent",
            "type":"Services"
        }
    ],
    "sg:phone":"+1 860 482 2916",
    "sg:postcode":"06790",
    "sg:province":"CT",
    "wof:name":"Torrington Insurance Agency",
    "wof:placetype":"venue"
},
  "geometry": {"coordinates":[-73.122675,41.799051],"type":"Point"}
}