{
  "type": "Feature",
  "properties": {
    "iso:country":"US",
    "sg:address":"1746 Quinnipiac Ave",
    "sg:city":"New Haven",
    "sg:classifiers":[
        {
            "category":"Professional",
            "subcategory":"Computer Services",
            "type":"Services"
        }
    ],
    "sg:phone":"+1   ",
    "sg:postcode":"06513",
    "sg:province":"CT",
    "sg:tags":[
        "related"
    ],
    "wof:name":"Tanzolo",
    "wof:placetype":"venue"
},
  "geometry": {"coordinates":[-72.867597,41.333481],"type":"Point"}
}