{
  "type": "Feature",
  "properties": {
    "addr:full":"28 Park Ln E New Milford CT 06776",
    "addr:housenumber":"28",
    "addr:postcode":"06776",
    "addr:street":"Park Ln E New Milford",
    "iso:country":"US",
    "sg:address":"28 Park Ln E",
    "sg:city":"New Milford",
    "sg:classifiers":[
        {
            "category":"Professional",
            "subcategory":"Lawyer & Legal Services",
            "type":"Services"
        }
    ],
    "sg:phone":"+1   ",
    "sg:postcode":"06776",
    "sg:province":"CT",
    "wof:name":"Guendelsberger & Taylor",
    "wof:placetype":"venue"
},
  "geometry": {"coordinates":[-73.404365,41.597394],"type":"Point"}
}