{
  "type": "Feature",
  "properties": {
    "addr:full":"14 W Rock Trl Stamford CT 06902",
    "addr:housenumber":"14",
    "addr:postcode":"06902",
    "addr:street":"W Rock Trl",
    "iso:country":"US",
    "sg:address":"14 W Rock Trl",
    "sg:city":"Stamford",
    "sg:classifiers":[
        {
            "category":"Professional",
            "subcategory":"Research",
            "type":"Services"
        }
    ],
    "sg:phone":"+1 203 357 9550",
    "sg:postcode":"06902",
    "sg:province":"CT",
    "sg:tags":[
        "economic",
        "analysis"
    ],
    "wof:name":"Copeland Economic Group Inc",
    "wof:placetype":"venue"
},
  "geometry": {"coordinates":[-73.561627,41.066882],"type":"Point"}
}