{
  "type": "Feature",
  "properties": {
    "addr:full":"121 Ellington Ave Ellington CT 06029",
    "addr:housenumber":"121",
    "addr:postcode":"06029",
    "addr:street":"Ellington Ave Ellington Ct",
    "iso:country":"US",
    "sg:address":"121 Ellington Ave",
    "sg:city":"Ellington",
    "sg:classifiers":[
        {
            "category":"Farming",
            "subcategory":"Nursery",
            "type":"Manufacturing & Wholesale Goods"
        }
    ],
    "sg:phone":"+1 860 875 0425",
    "sg:postcode":"06029",
    "sg:province":"CT",
    "sg:tags":[
        "ornamental"
    ],
    "wof:name":"Earl Spielman",
    "wof:placetype":"venue"
},
  "geometry": {"coordinates":[-72.45018899999999,41.882598],"type":"Point"}
}