{
  "type": "Feature",
  "properties": {
    "addr:full":"15 Bayberry Ln Darien CT 06820",
    "addr:housenumber":"15",
    "addr:postcode":"06820",
    "addr:street":"Bayberry Ln Darien Ct",
    "iso:country":"US",
    "sg:address":"15 Bayberry Ln",
    "sg:city":"Darien",
    "sg:classifiers":[
        {
            "category":"Professional",
            "subcategory":"Business Services",
            "type":"Services"
        }
    ],
    "sg:phone":"+1   ",
    "sg:postcode":"06820",
    "sg:province":"CT",
    "wof:name":"Dargren Associates Inc",
    "wof:placetype":"venue"
},
  "geometry": {"coordinates":[-73.456706,41.083904],"type":"Point"}
}