{
  "type": "Feature",
  "properties": {
    "iso:country":"US",
    "sg:address":"168 Bridge St",
    "sg:city":"East Windsor",
    "sg:classifiers":[
        {
            "category":"Autos & Motor Vehicles",
            "subcategory":"Fuel & Gas Station",
            "type":"Retail Goods"
        }
    ],
    "sg:phone":"+1 860 623 2522",
    "sg:postcode":"06088",
    "sg:province":"CT",
    "sg:tags":[
        "grocery",
        "station",
        "gasoline"
    ],
    "wof:name":"Bridge Street Shell",
    "wof:placetype":"venue"
},
  "geometry": {"coordinates":[-72.609241,41.930242],"type":"Point"}
}