{
  "type": "Feature",
  "properties": {
    "iso:country":"US",
    "sg:address":"73 State Hwy 81",
    "sg:city":"Killingworth",
    "sg:classifiers":[
        {
            "category":"Building & Trades",
            "subcategory":"Construction",
            "type":"Services"
        }
    ],
    "sg:phone":"+1 860 663 2961",
    "sg:postcode":"06419",
    "sg:province":"CT",
    "sg:tags":[
        "excavation",
        "contractor"
    ],
    "wof:name":"Excavation Contractors LLC",
    "wof:placetype":"venue"
},
  "geometry": {"coordinates":[-72.549491,41.327374],"type":"Point"}
}