{
  "type": "Feature",
  "properties": {
    "iso:country":"US",
    "sg:address":"276 Silvermine Ave",
    "sg:city":"Norwalk",
    "sg:classifiers":[
        {
            "category":"Communications",
            "type":"Services"
        }
    ],
    "sg:phone":"+1 203 847 3507",
    "sg:postcode":"06850",
    "sg:province":"CT",
    "wof:name":"Hlf Communications",
    "wof:placetype":"venue"
},
  "geometry": {"coordinates":[-73.445554,41.147725],"type":"Point"}
}