{
  "type": "Feature",
  "properties": {
    "iso:country":"US",
    "sg:address":"4 Water St",
    "sg:city":"Chester",
    "sg:classifiers":[
        {
            "category":"Shopping",
            "subcategory":"Florist",
            "type":"Retail Goods"
        }
    ],
    "sg:phone":"+1 860 526 4343",
    "sg:postcode":"06412",
    "sg:province":"CT",
    "sg:website":"www.nancyellen.com",
    "wof:name":"Nancy Ellen's Florist",
    "wof:placetype":"venue"
},
  "geometry": {"coordinates":[-72.450401,41.403198],"type":"Point"}
}