{
  "type": "Feature",
  "properties": {
    "iso:country":"US",
    "sg:address":"1 Poor House Rd",
    "sg:city":"Newtown",
    "sg:classifiers":[
        {
            "category":"Health Services",
            "subcategory":"Doctor",
            "type":"Services"
        }
    ],
    "sg:phone":"+1   ",
    "sg:postcode":"06470",
    "sg:province":"CT",
    "sg:tags":[
        "medical"
    ],
    "wof:name":"Paul Herman Stephen",
    "wof:placetype":"venue"
},
  "geometry": {"coordinates":[-73.34898099999999,41.369606],"type":"Point"}
}