{
  "type": "Feature",
  "properties": {
    "addr:full":"10 Grant Rd Ellington CT 06029",
    "addr:housenumber":"10",
    "addr:postcode":"06029",
    "addr:street":"Grant Rd Ellington Ct",
    "iso:country":"US",
    "sg:address":"10 Grant Rd",
    "sg:city":"Ellington",
    "sg:classifiers":[
        {
            "category":"Professional",
            "subcategory":"Art Services",
            "type":"Services"
        },
        {
            "category":"Professional",
            "subcategory":"Business Services",
            "type":"Services"
        }
    ],
    "sg:phone":"+1 860 872 6045",
    "sg:postcode":"06029",
    "sg:province":"CT",
    "sg:tags":[
        "development",
        "product",
        "graphic",
        "designers-industrial",
        "marketing",
        "commercial",
        "designer",
        "design"
    ],
    "sg:website":"http://www.lmgraphicshome.com",
    "wof:name":"L & M Graphics",
    "wof:placetype":"venue"
},
  "geometry": {"coordinates":[-72.50196099999999,41.86055],"type":"Point"}
}