{
  "type": "Feature",
  "properties": {
    "addr:full":"1616 Corbin Ave New Britain CT 06053",
    "addr:housenumber":"1616",
    "addr:postcode":"06053",
    "addr:street":"Corbin Ave",
    "iso:country":"US",
    "sg:address":"1616 Corbin Ave",
    "sg:city":"New Britain",
    "sg:classifiers":[
        {
            "category":"Retail",
            "subcategory":"Self-service Laundry",
            "type":"Services"
        }
    ],
    "sg:phone":"+1   ",
    "sg:postcode":"06053",
    "sg:province":"CT",
    "sg:tags":[
        "machine",
        "coin",
        "lease"
    ],
    "wof:name":"Launderama LLC",
    "wof:placetype":"venue"
},
  "geometry": {"coordinates":[-72.804216,41.67723],"type":"Point"}
}