{
  "type": "Feature",
  "properties": {
    "iso:country":"US",
    "sg:address":"24 Old Wood Rd",
    "sg:city":"Avon",
    "sg:classifiers":[
        {
            "category":"Real Estate",
            "subcategory":"Developer",
            "type":"Services"
        }
    ],
    "sg:phone":"+1 860 675 1492",
    "sg:postcode":"06001",
    "sg:province":"CT",
    "wof:name":"Leone Brothers LLC",
    "wof:placetype":"venue"
},
  "geometry": {"coordinates":[-72.85193099999999,41.785138],"type":"Point"}
}