{
  "type": "Feature",
  "properties": {
    "addr:full":"221 Newfield St Middletown CT 06457",
    "addr:housenumber":"221",
    "addr:postcode":"06457",
    "addr:street":"Newfield St",
    "iso:country":"US",
    "sg:address":"221 Newfield St",
    "sg:city":"Middletown",
    "sg:classifiers":[
        {
            "category":"Food & Beverages",
            "subcategory":"Groceries & Convenience Stores",
            "type":"Retail Goods"
        }
    ],
    "sg:phone":"+1 860 347 1078",
    "sg:postcode":"06457",
    "sg:province":"CT",
    "wof:name":"Dairy Mart Convenience Store",
    "wof:placetype":"venue"
},
  "geometry": {"coordinates":[-72.66857299999999,41.562885],"type":"Point"}
}