{
  "type": "Feature",
  "properties": {
    "addr:full":"102 Greenwich Ave Greenwich CT 06830",
    "addr:housenumber":"102",
    "addr:postcode":"06830",
    "addr:street":"Greenwich Ave",
    "iso:country":"US",
    "sg:address":"102 Greenwich Ave",
    "sg:city":"Greenwich",
    "sg:classifiers":[
        {
            "category":"Professional",
            "type":"Services"
        }
    ],
    "sg:phone":"+1 203 622 8720",
    "sg:postcode":"06830",
    "sg:province":"CT",
    "sg:tags":[
        "establishment"
    ],
    "wof:name":"Execution LLC",
    "wof:placetype":"venue"
},
  "geometry": {"coordinates":[-73.62650600000001,41.029398],"type":"Point"}
}