{
  "type": "Feature",
  "properties": {
    "iso:country":"US",
    "sg:address":"566 New Park Ave",
    "sg:city":"Hartford",
    "sg:classifiers":[
        {
            "category":"Retail",
            "subcategory":"Auto Repair",
            "type":"Services"
        }
    ],
    "sg:phone":"+1   ",
    "sg:postcode":"06110",
    "sg:province":"CT",
    "sg:tags":[
        "general"
    ],
    "wof:name":"Advantage Automotive",
    "wof:placetype":"venue"
},
  "geometry": {"coordinates":[-72.721892,41.736114],"type":"Point"}
}