{
  "type": "Feature",
  "properties": {
    "iso:country":"US",
    "sg:address":"370 Center St",
    "sg:city":"Wallingford",
    "sg:classifiers":[
        {
            "category":"Home & Garden",
            "subcategory":"Home Furnishings",
            "type":"Retail Goods"
        },
        {
            "category":"Home & Garden",
            "subcategory":"Furniture",
            "type":"Retail Goods"
        },
        {
            "category":"Building & Trades",
            "subcategory":"Construction",
            "type":"Services"
        },
        {
            "category":"Wholesale",
            "subcategory":"Home Furnishings",
            "type":"Manufacturing & Wholesale Goods"
        }
    ],
    "sg:phone":"+1 203 294 9459",
    "sg:postcode":"06492",
    "sg:province":"CT",
    "sg:tags":[
        "bathroom",
        "equipment-wholesale",
        "kitchen",
        "cabinet",
        "refacing",
        "resurfacing",
        "planning",
        "equipment-household",
        "remodeling",
        "maker",
        "cabinets-refinishing",
        "manufacturer"
    ],
    "wof:name":"Custom Kitchen Designs",
    "wof:placetype":"venue"
},
  "geometry": {"coordinates":[-72.817002,41.453871],"type":"Point"}
}