{
  "type": "Feature",
  "properties": {
    "iso:country":"US",
    "sg:address":"30 Lindeman Dr",
    "sg:city":"Trumbull",
    "sg:classifiers":[
        {
            "category":"Building & Trades",
            "subcategory":"Electrical",
            "type":"Services"
        }
    ],
    "sg:phone":"+1 203 373 0004",
    "sg:postcode":"06611",
    "sg:province":"CT",
    "sg:tags":[
        "electric",
        "contractor"
    ],
    "wof:name":"New England Mechanical Svc Inc",
    "wof:placetype":"venue"
},
  "geometry": {"coordinates":[-73.197695,41.231827],"type":"Point"}
}