{
  "type": "Feature",
  "properties": {
    "iso:country":"US",
    "sg:address":"850 Boston Post Rd",
    "sg:city":"Guilford",
    "sg:classifiers":[
        {
            "category":"Food & Beverages",
            "subcategory":"Groceries & Convenience Stores",
            "type":"Retail Goods"
        }
    ],
    "sg:phone":"+1 203 453 3267",
    "sg:postcode":"06437",
    "sg:province":"CT",
    "sg:tags":[
        "grocer"
    ],
    "wof:name":"Big Y World Class Market",
    "wof:placetype":"venue"
},
  "geometry": {"coordinates":[-72.67714700000001,41.288635],"type":"Point"}
}