{
  "type": "Feature",
  "properties": {
    "iso:country":"US",
    "sg:address":"7 Batt Ln",
    "sg:city":"West Haven",
    "sg:classifiers":[
        {
            "category":"Restaurant",
            "type":"Food & Drink"
        }
    ],
    "sg:phone":"+1 203 933 3043",
    "sg:postcode":"06516",
    "sg:province":"CT",
    "sg:tags":[
        "eating"
    ],
    "wof:name":"Simply Catering LLC",
    "wof:placetype":"venue"
},
  "geometry": {"coordinates":[-72.98598800000001,41.241813],"type":"Point"}
}