{
  "type": "Feature",
  "properties": {
    "addr:full":"207 Lost District Dr New Canaan NY 06840",
    "addr:housenumber":"207",
    "addr:postcode":"06840",
    "addr:street":"Lost District Dr",
    "iso:country":"US",
    "sg:address":"207 Lost District Dr",
    "sg:city":"New Canaan",
    "sg:classifiers":[
        {
            "category":"Professional",
            "type":"Services"
        }
    ],
    "sg:phone":"+1 203 966 0557",
    "sg:postcode":"06840",
    "sg:province":"NY",
    "sg:tags":[
        "establishment"
    ],
    "wof:name":"Creative Branding Systems",
    "wof:placetype":"venue"
},
  "geometry": {"coordinates":[-73.54286399999999,41.177072],"type":"Point"}
}