{
  "type": "Feature",
  "properties": {
    "iso:country":"US",
    "sg:address":"840 Ruth St",
    "sg:city":"Bridgeport",
    "sg:classifiers":[
        {
            "category":"Professional",
            "type":"Services"
        }
    ],
    "sg:phone":"+1 203 374 3222",
    "sg:postcode":"06606",
    "sg:province":"CT",
    "sg:tags":[
        "establishment"
    ],
    "wof:name":"Advanced System Designs",
    "wof:placetype":"venue"
},
  "geometry": {"coordinates":[-73.225047,41.206416],"type":"Point"}
}