{
  "type": "Feature",
  "properties": {
    "addr:full":"11 Cheshire Rd Meriden CT 06451",
    "addr:housenumber":"11",
    "addr:postcode":"06451",
    "addr:street":"Cheshire Rd",
    "iso:country":"US",
    "sg:address":"11 Cheshire Rd",
    "sg:city":"Meriden",
    "sg:classifiers":[
        {
            "category":"Organizations",
            "subcategory":"Membership Organization",
            "type":"Services"
        }
    ],
    "sg:phone":"+1   ",
    "sg:postcode":"06451",
    "sg:province":"CT",
    "wof:name":"Alliance of Polish Womens",
    "wof:placetype":"venue"
},
  "geometry": {"coordinates":[-72.834423,41.518171],"type":"Point"}
}