{
  "type": "Feature",
  "properties": {
    "addr:full":"425 Windsor Ave Windsor CT 06095",
    "addr:housenumber":"425",
    "addr:postcode":"06095",
    "addr:street":"Windsor Ave",
    "iso:country":"US",
    "sg:address":"425 Windsor Ave",
    "sg:city":"Windsor",
    "sg:classifiers":[
        {
            "category":"Manufacturing",
            "subcategory":"Textiles",
            "type":"Manufacturing & Wholesale Goods"
        }
    ],
    "sg:phone":"+1 860 241 9030",
    "sg:postcode":"06095",
    "sg:province":"CT",
    "sg:tags":[
        "mfg"
    ],
    "wof:name":"Wire Rope Specialty Company",
    "wof:placetype":"venue"
},
  "geometry": {"coordinates":[-72.656964,41.816276],"type":"Point"}
}