{
  "type": "Feature",
  "properties": {
    "iso:country":"US",
    "sg:address":"11 Caldron Dr",
    "sg:city":"Trumbull",
    "sg:classifiers":[
        {
            "category":"Real Estate",
            "subcategory":"Real Estate Agent",
            "type":"Services"
        },
        {
            "category":"Professional",
            "subcategory":"Business Services",
            "type":"Services"
        }
    ],
    "sg:phone":"+1 203 268 7850",
    "sg:postcode":"06611",
    "sg:province":"CT",
    "sg:tags":[
        "inspection"
    ],
    "wof:name":"Inquiring Eye Home Inspections",
    "wof:placetype":"venue"
},
  "geometry": {"coordinates":[-73.225658,41.292687],"type":"Point"}
}