{
  "type": "Feature",
  "properties": {
    "addr:full":"12 Quail Run Dr Danbury CT 06811",
    "addr:housenumber":"12",
    "addr:postcode":"06811",
    "addr:street":"Quail Run Dr",
    "iso:country":"US",
    "sg:address":"12 Quail Run Dr",
    "sg:city":"Danbury",
    "sg:classifiers":[
        {
            "category":"Bakery",
            "type":"Food & Drink"
        }
    ],
    "sg:phone":"+1 203 730 2902",
    "sg:postcode":"06811",
    "sg:province":"CT",
    "wof:name":"Shannon's Bakery",
    "wof:placetype":"venue"
},
  "geometry": {"coordinates":[-73.50201300000001,41.395117],"type":"Point"}
}