{
  "type": "Feature",
  "properties": {
    "iso:country":"US",
    "sg:address":"99 Rowayton Ave",
    "sg:city":"Norwalk",
    "sg:classifiers":[
        {
            "category":"Autos & Motor Vehicles",
            "subcategory":"Boat Sales",
            "type":"Retail Goods"
        }
    ],
    "sg:phone":"+1 203 853 3811",
    "sg:postcode":"06853",
    "sg:province":"CT",
    "sg:tags":[
        "dealer",
        "sales"
    ],
    "wof:name":"Mako Boat Sales",
    "wof:placetype":"venue"
},
  "geometry": {"coordinates":[-73.444132,41.06511],"type":"Point"}
}