{
  "type": "Feature",
  "properties": {
    "addr:full":"11 Largo Dr Stamford CT 06907",
    "addr:housenumber":"11",
    "addr:postcode":"06907",
    "addr:street":"Largo Dr",
    "iso:country":"US",
    "sg:address":"11 Largo Dr",
    "sg:city":"Stamford",
    "sg:classifiers":[
        {
            "category":"Professional",
            "subcategory":"Advertising",
            "type":"Services"
        }
    ],
    "sg:phone":"+1 203 323 5161",
    "sg:postcode":"06907",
    "sg:province":"CT",
    "sg:tags":[
        "distributing",
        "sample",
        "business"
    ],
    "sg:website":"www.ctmbrochuredisplay.com",
    "wof:name":"C T M Brochure Display Inc",
    "wof:placetype":"venue"
},
  "geometry": {"coordinates":[-73.517816,41.089914],"type":"Point"}
}