{
  "type": "Feature",
  "properties": {
    "iso:country":"US",
    "sg:address":"11-C E Main",
    "sg:city":"Central Village",
    "sg:classifiers":[
        {
            "category":"Health Services",
            "subcategory":"Dentist",
            "type":"Services"
        }
    ],
    "sg:phone":"+1 860 564 7422",
    "sg:postcode":"06332",
    "sg:province":"CT",
    "wof:name":"Burbach Douglas DMD",
    "wof:placetype":"venue"
},
  "geometry": {"coordinates":[-71.902902,41.719504],"type":"Point"}
}