{
  "type": "Feature",
  "properties": {
    "iso:country":"US",
    "sg:address":"55 Hampton Close St",
    "sg:city":"Orange",
    "sg:classifiers":[
        {
            "category":"Wholesale",
            "subcategory":"Non-durable Goods",
            "type":"Manufacturing & Wholesale Goods"
        }
    ],
    "sg:phone":"+1 203 799 8060",
    "sg:postcode":"06477",
    "sg:province":"CT",
    "sg:tags":[
        "distributes",
        "advertising",
        "specialty"
    ],
    "wof:name":"Impact Associates Inc",
    "wof:placetype":"venue"
},
  "geometry": {"coordinates":[-73.009086,41.291189],"type":"Point"}
}