{
  "type": "Feature",
  "properties": {
    "iso:country":"US",
    "sg:address":"3 Gold St",
    "sg:city":"Norwalk",
    "sg:classifiers":[
        {
            "category":"Retail",
            "subcategory":"Auto Repair",
            "type":"Services"
        }
    ],
    "sg:phone":"+1   ",
    "sg:postcode":"06850",
    "sg:province":"CT",
    "sg:tags":[
        "body"
    ],
    "wof:name":"Esposito Auto Body",
    "wof:placetype":"venue"
},
  "geometry": {"coordinates":[-73.42834499999999,41.137133],"type":"Point"}
}