{
  "type": "Feature",
  "properties": {
    "iso:country":"US",
    "sg:address":"690 E Main St",
    "sg:city":"Meriden",
    "sg:classifiers":[
        {
            "category":"Shopping",
            "subcategory":"Computers & Home Electronics",
            "type":"Retail Goods"
        }
    ],
    "sg:phone":"+1 203 238 0012",
    "sg:postcode":"06450",
    "sg:province":"CT",
    "wof:name":"Take 1 Video Inc",
    "wof:placetype":"venue"
},
  "geometry": {"coordinates":[-72.780765,41.530345],"type":"Point"}
}