{
  "type": "Feature",
  "properties": {
    "addr:full":"7 Kenosia Ave Danbury CT 06810",
    "addr:housenumber":"7",
    "addr:postcode":"06810",
    "addr:street":"Kenosia Ave",
    "iso:country":"US",
    "sg:address":"7 Kenosia Ave",
    "sg:city":"Danbury",
    "sg:classifiers":[
        {
            "category":"Insurance",
            "subcategory":"Insurance Agent",
            "type":"Services"
        }
    ],
    "sg:phone":"+1 203 743 2150",
    "sg:postcode":"06810",
    "sg:province":"CT",
    "wof:name":"Bergman-KATZ Financial Svc",
    "wof:placetype":"venue"
},
  "geometry": {"coordinates":[-73.49726699999999,41.385243],"type":"Point"}
}