{
  "type": "Feature",
  "properties": {
    "addr:full":"28 Gorham Ave Hamden CT 06514",
    "addr:housenumber":"28",
    "addr:postcode":"06514",
    "addr:street":"Gorham Ave",
    "iso:country":"US",
    "sg:address":"28 Gorham Ave",
    "sg:city":"Hamden",
    "sg:classifiers":[
        {
            "category":"Retail",
            "subcategory":"Auto Repair",
            "type":"Services"
        }
    ],
    "sg:phone":"+1 203 281 1553",
    "sg:postcode":"06514",
    "sg:province":"CT",
    "sg:tags":[
        "repairing",
        "automobile",
        "general"
    ],
    "wof:name":"Tony Marone's Auto Repair",
    "wof:placetype":"venue"
},
  "geometry": {"coordinates":[-72.93943899999999,41.349109],"type":"Point"}
}