{
  "type": "Feature",
  "properties": {
    "addr:full":"20 Grasso Ter Bridgeport CT 06604",
    "addr:housenumber":"20",
    "addr:postcode":"06604",
    "addr:street":"Grasso Ter Bridgeport Ct",
    "iso:country":"US",
    "sg:address":"20 Grasso Ter",
    "sg:city":"Bridgeport",
    "sg:classifiers":[
        {
            "category":"Professional",
            "type":"Services"
        }
    ],
    "sg:phone":"+1 203 335 6420",
    "sg:postcode":"06604",
    "sg:province":"CT",
    "sg:tags":[
        "establishment"
    ],
    "wof:name":"R & T Creations",
    "wof:placetype":"venue"
},
  "geometry": {"coordinates":[-73.219762,41.188885],"type":"Point"}
}