{
  "type": "Feature",
  "properties": {
    "iso:country":"US",
    "sg:address":"757 Lake Ave",
    "sg:city":"Bristol",
    "sg:classifiers":[
        {
            "category":"Building & Trades",
            "subcategory":"Cleaning & Sanitation",
            "type":"Services"
        }
    ],
    "sg:phone":"+1   ",
    "sg:postcode":"06010",
    "sg:province":"CT",
    "sg:tags":[
        "maintenance"
    ],
    "wof:name":"Lemon Fresh Cleaning Service",
    "wof:placetype":"venue"
},
  "geometry": {"coordinates":[-72.92379699999999,41.645894],"type":"Point"}
}