{
  "type": "Feature",
  "properties": {
    "iso:country":"US",
    "sg:address":"34 Phillips Ln",
    "sg:city":"Darien",
    "sg:classifiers":[
        {
            "category":"Professional",
            "subcategory":"Accounting & Tax Preparation",
            "type":"Services"
        }
    ],
    "sg:phone":"+1   ",
    "sg:postcode":"06820",
    "sg:province":"CT",
    "wof:name":"Thomas L Foley CPA LLC",
    "wof:placetype":"venue"
},
  "geometry": {"coordinates":[-73.51505,41.078621],"type":"Point"}
}