{
  "type": "Feature",
  "properties": {
    "iso:country":"US",
    "sg:address":"90 Shelburne Rd",
    "sg:city":"Stamford",
    "sg:classifiers":[
        {
            "category":"Health Services",
            "subcategory":"Medical Lab",
            "type":"Services"
        }
    ],
    "sg:phone":"+1 203 325 7460",
    "sg:postcode":"06902",
    "sg:province":"CT",
    "sg:tags":[
        "laboratory"
    ],
    "wof:name":"Clinical Laboratory Svc",
    "wof:placetype":"venue"
},
  "geometry": {"coordinates":[-73.553466,41.055281],"type":"Point"}
}