{
  "type": "Feature",
  "properties": {
    "addr:full":"64 Stonybrook Rd Gales Ferry CT 06335",
    "addr:housenumber":"64",
    "addr:postcode":"06335",
    "addr:street":"Stonybrook Rd Gales Ferry Ct",
    "iso:country":"US",
    "sg:address":"64 Stonybrook Rd",
    "sg:city":"Gales Ferry",
    "sg:classifiers":[
        {
            "category":"Real Estate",
            "subcategory":"Real Estate Operator",
            "type":"Services"
        }
    ],
    "sg:phone":"+1 860 464 0009",
    "sg:postcode":"06335",
    "sg:province":"CT",
    "sg:tags":[
        "building",
        "nonresidential"
    ],
    "wof:name":"M&C Properties LLC",
    "wof:placetype":"venue"
},
  "geometry": {"coordinates":[-72.06109600000001,41.461992],"type":"Point"}
}