{
  "type": "Feature",
  "properties": {
    "addr:full":"25 Hickory Cir Middletown CT 06457",
    "addr:housenumber":"25",
    "addr:postcode":"06457",
    "addr:street":"Hickory Cir",
    "iso:country":"US",
    "sg:address":"25 Hickory Cir",
    "sg:city":"Middletown",
    "sg:classifiers":[
        {
            "category":"Building & Trades",
            "subcategory":"Construction",
            "type":"Services"
        }
    ],
    "sg:phone":"+1 860 704 0514",
    "sg:postcode":"06457",
    "sg:province":"CT",
    "sg:tags":[
        "heavy"
    ],
    "wof:name":"Fore Golf",
    "wof:placetype":"venue"
},
  "geometry": {"coordinates":[-72.686817,41.558779],"type":"Point"}
}