{
  "type": "Feature",
  "properties": {
    "iso:country":"US",
    "sg:address":"484 Wetherell St",
    "sg:city":"Manchester",
    "sg:classifiers":[
        {
            "category":"Organizations",
            "subcategory":"Membership Organization",
            "type":"Services"
        }
    ],
    "sg:phone":"+1   ",
    "sg:postcode":"06040",
    "sg:province":"CT",
    "wof:name":"Connectcut Pace Bptst Fllwship",
    "wof:placetype":"venue"
},
  "geometry": {"coordinates":[-72.562101,41.758965],"type":"Point"}
}