{
  "type": "Feature",
  "properties": {
    "addr:full":"23 S Main St Wallingford CT 06492",
    "addr:housenumber":"23",
    "addr:postcode":"06492",
    "addr:street":"S Main St",
    "iso:country":"US",
    "sg:address":"23 S Main St",
    "sg:city":"Wallingford",
    "sg:classifiers":[
        {
            "category":"Organizations",
            "subcategory":"Religious Organization",
            "type":"Services"
        }
    ],
    "sg:phone":"+1 203 265 1691",
    "sg:postcode":"06492",
    "sg:province":"CT",
    "sg:tags":[
        "church"
    ],
    "wof:name":"First Congregational Church",
    "wof:placetype":"venue"
},
  "geometry": {"coordinates":[-72.818764,41.453882],"type":"Point"}
}