{
  "type": "Feature",
  "properties": {
    "iso:country":"US",
    "sg:address":"39 Leroy Ave",
    "sg:city":"Darien",
    "sg:classifiers":[
        {
            "category":"Social Services",
            "type":"Services"
        }
    ],
    "sg:phone":"+1 203 655 2586",
    "sg:postcode":"06820",
    "sg:province":"CT",
    "sg:tags":[
        "organization",
        "welfare"
    ],
    "wof:name":"Red Cross-Darien Chapter",
    "wof:placetype":"venue"
},
  "geometry": {"coordinates":[-73.474339,41.074296],"type":"Point"}
}