{
  "type": "Feature",
  "properties": {
    "iso:country":"US",
    "sg:address":"370 Hunting Hill Ave",
    "sg:city":"Middletown",
    "sg:classifiers":[
        {
            "category":"Education",
            "subcategory":"School",
            "type":"Public Place"
        }
    ],
    "sg:phone":"+1 860 347 8571",
    "sg:postcode":"06457",
    "sg:province":"CT",
    "sg:tags":[
        "executive"
    ],
    "wof:name":"Middletown High School",
    "wof:placetype":"venue"
},
  "geometry": {"coordinates":[-72.647217,41.541462],"type":"Point"}
}