{
  "type": "Feature",
  "properties": {
    "iso:country":"US",
    "sg:address":"509 Wethersfield Ave",
    "sg:city":"Hartford",
    "sg:classifiers":[
        {
            "category":"Health Services",
            "subcategory":"Health Practitioner",
            "type":"Services"
        }
    ],
    "sg:phone":"+1   ",
    "sg:postcode":"06114",
    "sg:province":"CT",
    "wof:name":"Arzola & Dreyer Assoc LLC",
    "wof:placetype":"venue"
},
  "geometry": {"coordinates":[-72.672648,41.742418],"type":"Point"}
}