{
  "type": "Feature",
  "properties": {
    "addr:full":"12 Winthrop Rd Chester CT 06412",
    "addr:housenumber":"12",
    "addr:postcode":"06412",
    "addr:street":"Winthrop Rd",
    "iso:country":"US",
    "sg:address":"12 Winthrop Rd",
    "sg:city":"Chester",
    "sg:classifiers":[
        {
            "category":"Building & Trades",
            "subcategory":"Cleaning & Sanitation",
            "type":"Services"
        }
    ],
    "sg:phone":"+1   ",
    "sg:postcode":"06412",
    "sg:province":"CT",
    "sg:tags":[
        "coffee",
        "vending"
    ],
    "wof:name":"Commercial Clg Rfreshment Svcs",
    "wof:placetype":"venue"
},
  "geometry": {"coordinates":[-72.50366699999999,41.392077],"type":"Point"}
}