{
  "type": "Feature",
  "properties": {
    "iso:country":"US",
    "sg:address":"1260 New Britain Ave",
    "sg:city":"Hartford",
    "sg:classifiers":[
        {
            "category":"Professional",
            "subcategory":"Business Services",
            "type":"Services"
        }
    ],
    "sg:phone":"+1   ",
    "sg:postcode":"06110",
    "sg:province":"CT",
    "sg:tags":[
        "trade",
        "management",
        "event",
        "show"
    ],
    "wof:name":"Alice & Daniels Model MGT",
    "wof:placetype":"venue"
},
  "geometry": {"coordinates":[-72.744151,41.731687],"type":"Point"}
}