{
  "type": "Feature",
  "properties": {
    "iso:country":"US",
    "sg:address":"200 Boston Post Rd",
    "sg:city":"Madison",
    "sg:classifiers":[
        {
            "category":"Restaurant",
            "type":"Food & Drink"
        }
    ],
    "sg:menulink":"http://www.allmenus.com/ct/madison/44342-nicks-place/menu/",
    "sg:phone":"+1 203 245 0433",
    "sg:postcode":"06443",
    "sg:province":"CT",
    "sg:tags":[
        "american",
        "diner"
    ],
    "wof:name":"Nick's Place",
    "wof:placetype":"venue"
},
  "geometry": {"coordinates":[-72.63079999999999,41.281273],"type":"Point"}
}