{
  "type": "Feature",
  "properties": {
    "iso:country":"US",
    "sg:address":"838 Woodend Rd",
    "sg:city":"Stratford",
    "sg:classifiers":[
        {
            "category":"Building & Trades",
            "subcategory":"Landscaping Services",
            "type":"Services"
        }
    ],
    "sg:phone":"+1 203 375 7962",
    "sg:postcode":"06615",
    "sg:province":"CT",
    "sg:tags":[
        "tree"
    ],
    "wof:name":"Good Earth Tree Care Inc",
    "wof:placetype":"venue"
},
  "geometry": {"coordinates":[-73.13910799999999,41.170297],"type":"Point"}
}