{
  "type": "Feature",
  "properties": {
    "iso:country":"US",
    "sg:address":"71 Whitfield St",
    "sg:city":"Guilford",
    "sg:classifiers":[
        {
            "category":"Shopping",
            "subcategory":"Jewelry",
            "type":"Retail Goods"
        }
    ],
    "sg:phone":"+1 203 453 8868",
    "sg:postcode":"06437",
    "sg:province":"CT",
    "sg:tags":[
        "jeweler"
    ],
    "wof:name":"Tabar Designs",
    "wof:placetype":"venue"
},
  "geometry": {"coordinates":[-72.682861,41.283472],"type":"Point"}
}