{
  "type": "Feature",
  "properties": {
    "iso:country":"US",
    "sg:address":"10 Dale St",
    "sg:city":"Hartford",
    "sg:classifiers":[
        {
            "category":"Personal",
            "subcategory":"Beauty Salon",
            "type":"Services"
        }
    ],
    "sg:phone":"+1   ",
    "sg:postcode":"06107",
    "sg:province":"CT",
    "sg:tags":[
        "shop"
    ],
    "wof:name":"Renover Skincare",
    "wof:placetype":"venue"
},
  "geometry": {"coordinates":[-72.745554,41.762121],"type":"Point"}
}