{
  "type": "Feature",
  "properties": {
    "iso:country":"US",
    "sg:address":"15 Park Rd",
    "sg:city":"Ivoryton",
    "sg:classifiers":[
        {
            "category":"Autos & Motor Vehicles",
            "subcategory":"Automobile Sales",
            "type":"Retail Goods"
        },
        {
            "category":"Airline",
            "type":"Transportation"
        }
    ],
    "sg:phone":"+1 860 767 7004",
    "sg:postcode":"06442",
    "sg:province":"CT",
    "sg:tags":[
        "shuttle",
        "airport",
        "limo"
    ],
    "wof:name":"Corporate Connection Inc",
    "wof:placetype":"venue"
},
  "geometry": {"coordinates":[-72.446198,41.343498],"type":"Point"}
}