{
  "type": "Feature",
  "properties": {
    "addr:full":"525 Connecticut Ave Norwalk CT 06854",
    "addr:housenumber":"525",
    "addr:postcode":"06854",
    "addr:street":"Connecticut Ave",
    "iso:country":"US",
    "sg:address":"525 Connecticut Ave",
    "sg:city":"Norwalk",
    "sg:classifiers":[
        {
            "category":"Retail",
            "subcategory":"Veterinary Services",
            "type":"Services"
        }
    ],
    "sg:phone":"+1 203 866 2666",
    "sg:postcode":"06854",
    "sg:province":"CT",
    "sg:tags":[
        "veterinarian"
    ],
    "wof:name":"Banfield The Pet Hospital",
    "wof:placetype":"venue"
},
  "geometry": {"coordinates":[-73.442775,41.098948],"type":"Point"}
}