{
  "type": "Feature",
  "properties": {
    "iso:country":"US",
    "sg:address":"366 Federal Rd",
    "sg:city":"Brookfield",
    "sg:classifiers":[
        {
            "category":"Food & Beverages",
            "subcategory":"Specialty",
            "type":"Retail Goods"
        }
    ],
    "sg:phone":"+1 203 775 1819",
    "sg:postcode":"06804",
    "sg:province":"CT",
    "wof:name":"Healthy Weighs",
    "wof:placetype":"venue"
},
  "geometry": {"coordinates":[-73.402835,41.454174],"type":"Point"}
}