{
  "type": "Feature",
  "properties": {
    "addr:full":"168 State Hwy 66 E Columbia CT 06237",
    "addr:housenumber":"168",
    "addr:postcode":"06237",
    "addr:street":"State Hwy 66 E Columbia Ct",
    "iso:country":"US",
    "sg:address":"168 State Hwy 66 E",
    "sg:city":"Columbia",
    "sg:classifiers":[
        {
            "category":"Retail",
            "subcategory":"Auto Repair",
            "type":"Services"
        }
    ],
    "sg:phone":"+1   ",
    "sg:postcode":"06237",
    "sg:province":"CT",
    "sg:tags":[
        "recreational",
        "vehicle"
    ],
    "wof:name":"S & D Service Co",
    "wof:placetype":"venue"
},
  "geometry": {"coordinates":[-72.25228199999999,41.720059],"type":"Point"}
}