{
  "type": "Feature",
  "properties": {
    "iso:country":"US",
    "sg:address":"8 Paragon Ln",
    "sg:city":"Stamford",
    "sg:classifiers":[
        {
            "category":"Building & Trades",
            "subcategory":"Construction",
            "type":"Services"
        }
    ],
    "sg:phone":"+1 203 325 8160",
    "sg:postcode":"06905",
    "sg:province":"CT",
    "sg:tags":[
        "contractor"
    ],
    "wof:name":"Alvarados Contractor",
    "wof:placetype":"venue"
},
  "geometry": {"coordinates":[-73.551479,41.069244],"type":"Point"}
}