{
  "type": "Feature",
  "properties": {
    "iso:country":"US",
    "sg:address":"74 Boston Post Rd",
    "sg:city":"Madison",
    "sg:classifiers":[
        {
            "category":"Retail",
            "subcategory":"Funeral Services",
            "type":"Services"
        }
    ],
    "sg:phone":"+1 203 245 3660",
    "sg:postcode":"06443",
    "sg:province":"CT",
    "sg:tags":[
        "director"
    ],
    "wof:name":"Cooperative Funeral Fund Inc",
    "wof:placetype":"venue"
},
  "geometry": {"coordinates":[-72.641931,41.285585],"type":"Point"}
}