{
  "type": "Feature",
  "properties": {
    "addr:full":"168 Stanley St New Britain CT 06051",
    "addr:housenumber":"168",
    "addr:postcode":"06051",
    "addr:street":"Stanley St",
    "iso:country":"US",
    "sg:address":"168 Stanley St",
    "sg:city":"New Britain",
    "sg:classifiers":[
        {
            "category":"Manufacturing",
            "subcategory":"Signs",
            "type":"Manufacturing & Wholesale Goods"
        }
    ],
    "sg:phone":"+1 860 229 1812",
    "sg:postcode":"06051",
    "sg:province":"CT",
    "sg:tags":[
        "mfg"
    ],
    "wof:name":"Sign Pro Inc",
    "wof:placetype":"venue"
},
  "geometry": {"coordinates":[-72.76920800000001,41.653292],"type":"Point"}
}