{
  "type": "Feature",
  "properties": {
    "iso:country":"US",
    "sg:address":"721 Orange St",
    "sg:city":"New Haven",
    "sg:classifiers":[
        {
            "category":"Food & Beverages",
            "subcategory":"Groceries & Convenience Stores",
            "type":"Retail Goods"
        }
    ],
    "sg:phone":"+1 203 865 1147",
    "sg:postcode":"06511",
    "sg:province":"CT",
    "wof:name":"Orange Food Mart",
    "wof:placetype":"venue"
},
  "geometry": {"coordinates":[-72.912876,41.320446],"type":"Point"}
}