{
  "type": "Feature",
  "properties": {
    "addr:full":"42 State St North Haven CT 06473",
    "addr:housenumber":"42",
    "addr:postcode":"06473",
    "addr:street":"State St;Haven",
    "iso:country":"US",
    "sg:address":"42 State St",
    "sg:city":"North Haven",
    "sg:classifiers":[
        {
            "category":"Sports & Exercise",
            "subcategory":"Gym",
            "type":"Entertainment"
        }
    ],
    "sg:phone":"+1   ",
    "sg:postcode":"06473",
    "sg:province":"CT",
    "sg:tags":[
        "fitness",
        "physical",
        "facility"
    ],
    "wof:name":"Core Fitness LLC",
    "wof:placetype":"venue"
},
  "geometry": {"coordinates":[-72.876141,41.382409],"type":"Point"}
}