{
  "type": "Feature",
  "properties": {
    "iso:country":"US",
    "sg:address":"107 Danbury Rd",
    "sg:city":"New Milford",
    "sg:classifiers":[
        {
            "category":"Retail",
            "subcategory":"Car Wash",
            "type":"Services"
        }
    ],
    "sg:phone":"+1   ",
    "sg:postcode":"06776",
    "sg:province":"CT",
    "sg:tags":[
        "carwash"
    ],
    "wof:name":"New Milford Car Wash Inc",
    "wof:placetype":"venue"
},
  "geometry": {"coordinates":[-73.416962,41.557647],"type":"Point"}
}