{
  "type": "Feature",
  "properties": {
    "addr:full":"12 Main St Essex CT 06426",
    "addr:housenumber":"12",
    "addr:postcode":"06426",
    "addr:street":"Main St",
    "iso:country":"US",
    "sg:address":"12 Main St",
    "sg:city":"Essex",
    "sg:classifiers":[
        {
            "category":"Banks & Credit Unions",
            "subcategory":"Bank",
            "type":"Services"
        }
    ],
    "sg:phone":"+1 860 767 8292",
    "sg:postcode":"06426",
    "sg:province":"CT",
    "wof:name":"New Haven Savings Bank",
    "wof:placetype":"venue"
},
  "geometry": {"coordinates":[-72.390297,41.352798],"type":"Point"}
}