{
  "type": "Feature",
  "properties": {
    "addr:full":"65 Russell Ave Plainville CT 06062",
    "addr:housenumber":"65",
    "addr:postcode":"06062",
    "addr:street":"Russell Ave",
    "iso:country":"US",
    "sg:address":"65 Russell Ave",
    "sg:city":"Plainville",
    "sg:classifiers":[
        {
            "category":"Professional",
            "subcategory":"Business Services",
            "type":"Services"
        }
    ],
    "sg:phone":"+1   ",
    "sg:postcode":"06062",
    "sg:province":"CT",
    "sg:tags":[
        "machine",
        "tool",
        "mfg"
    ],
    "wof:name":"Jj Industries",
    "wof:placetype":"venue"
},
  "geometry": {"coordinates":[-72.869805,41.658696],"type":"Point"}
}