{
  "type": "Feature",
  "properties": {
    "addr:full":"145 Delay Rd Harwinton CT 06791",
    "addr:housenumber":"145",
    "addr:postcode":"06791",
    "addr:street":"Delay Rd Harwinton Ct",
    "iso:country":"US",
    "sg:address":"145 Delay Rd",
    "sg:city":"Harwinton",
    "sg:classifiers":[
        {
            "category":"Building & Trades",
            "subcategory":"Landscaping Services",
            "type":"Services"
        }
    ],
    "sg:phone":"+1 860 485 1121",
    "sg:postcode":"06791",
    "sg:province":"CT",
    "wof:name":"Glenn Bradley",
    "wof:placetype":"venue"
},
  "geometry": {"coordinates":[-73.084074,41.75336],"type":"Point"}
}