{
  "type": "Feature",
  "properties": {
    "iso:country":"US",
    "sg:address":"599 Matianuck Ave",
    "sg:city":"Windsor",
    "sg:classifiers":[
        {
            "category":"Utilities",
            "subcategory":"Cable",
            "type":"Services"
        }
    ],
    "sg:phone":"+1 860 688 2626",
    "sg:postcode":"06095",
    "sg:province":"CT",
    "sg:tags":[
        "access",
        "television",
        "station",
        "public"
    ],
    "wof:name":"Win TV",
    "wof:placetype":"venue"
},
  "geometry": {"coordinates":[-72.673074,41.823918],"type":"Point"}
}