{
  "type": "Feature",
  "properties": {
    "addr:full":"57 Country Hill Rd Naugatuck CT 06770",
    "addr:housenumber":"57",
    "addr:postcode":"06770",
    "addr:street":"Country Hill Rd Naugatuck Ct",
    "iso:country":"US",
    "sg:address":"57 Country Hill Rd",
    "sg:city":"Naugatuck",
    "sg:classifiers":[
        {
            "category":"Building & Trades",
            "subcategory":"Cleaning & Sanitation",
            "type":"Services"
        }
    ],
    "sg:phone":"+1 203 296 0153",
    "sg:postcode":"06770",
    "sg:province":"CT",
    "sg:tags":[
        "house"
    ],
    "wof:name":"R & R Crystal Cleaning Service",
    "wof:placetype":"venue"
},
  "geometry": {"coordinates":[-73.009777,41.470294],"type":"Point"}
}