{
  "type": "Feature",
  "properties": {
    "iso:country":"US",
    "sg:address":"8 Greenview Dr",
    "sg:city":"Portland",
    "sg:classifiers":[
        {
            "category":"Building & Trades",
            "subcategory":"Landscaping Services",
            "type":"Services"
        }
    ],
    "sg:phone":"+1 860 342 1675",
    "sg:postcode":"06480",
    "sg:province":"CT",
    "wof:name":"R A Spooner Lawn Mowing",
    "wof:placetype":"venue"
},
  "geometry": {"coordinates":[-72.595471,41.59278],"type":"Point"}
}