{
  "type": "Feature",
  "properties": {
    "iso:country":"US",
    "sg:address":"4 Broadway Ave",
    "sg:city":"Mystic",
    "sg:classifiers":[
        {
            "category":"Real Estate",
            "subcategory":"Real Estate Agent",
            "type":"Services"
        }
    ],
    "sg:phone":"+1 860 572 9131",
    "sg:postcode":"06355",
    "sg:province":"CT",
    "wof:name":"Cutler Street Ltd Partner",
    "wof:placetype":"venue"
},
  "geometry": {"coordinates":[-71.963987,41.354116],"type":"Point"}
}