{
  "type": "Feature",
  "properties": {
    "addr:full":"874 Main St Torrington CT 06790",
    "addr:housenumber":"874",
    "addr:postcode":"06790",
    "addr:street":"Main St",
    "iso:country":"US",
    "sg:address":"874 Main St",
    "sg:city":"Torrington",
    "sg:classifiers":[
        {
            "category":"Health Services",
            "subcategory":"Doctor",
            "type":"Services"
        }
    ],
    "sg:phone":"+1   ",
    "sg:postcode":"06790",
    "sg:province":"CT",
    "wof:name":"Jr Stanley E Moraski DMD",
    "wof:placetype":"venue"
},
  "geometry": {"coordinates":[-73.121876,41.81877],"type":"Point"}
}