{
  "type": "Feature",
  "properties": {
    "iso:country":"US",
    "sg:address":"20 Grand Ave",
    "sg:city":"New Haven",
    "sg:classifiers":[
        {
            "category":"Shopping",
            "type":"Retail Goods"
        }
    ],
    "sg:phone":"+1 203 562 0013",
    "sg:postcode":"06513",
    "sg:province":"CT",
    "sg:tags":[
        "cosmetic",
        "perfume"
    ],
    "wof:name":"In Style Fragrances",
    "wof:placetype":"venue"
},
  "geometry": {"coordinates":[-72.889612,41.309367],"type":"Point"}
}