{
  "type": "Feature",
  "properties": {
    "addr:full":"750 Post Rd Fairfield CT 06824",
    "addr:housenumber":"750",
    "addr:postcode":"06824",
    "addr:street":"Post Rd",
    "iso:country":"US",
    "sg:address":"750 Post Rd",
    "sg:city":"Fairfield",
    "sg:classifiers":[
        {
            "category":"Bars & Pubs",
            "type":"Food & Drink"
        }
    ],
    "sg:menulink":"http://www.allmenus.com/ct/fairfield/11963-american-joes-american-bar--grill/menu/",
    "sg:phone":"+1 203 319 1600",
    "sg:postcode":"06824",
    "sg:province":"CT",
    "sg:tags":[
        "american"
    ],
    "wof:name":"American Joe's American Bar & Grill",
    "wof:placetype":"venue"
},
  "geometry": {"coordinates":[-73.247981,41.147708],"type":"Point"}
}