{
  "type": "Feature",
  "properties": {
    "iso:country":"US",
    "sg:address":"279 Waterview Ave",
    "sg:city":"Bridgeport",
    "sg:classifiers":[
        {
            "category":"Building & Trades",
            "subcategory":"Construction",
            "type":"Services"
        }
    ],
    "sg:phone":"+1 203 367 5455",
    "sg:postcode":"06608",
    "sg:province":"CT",
    "sg:tags":[
        "contractor"
    ],
    "wof:name":"Pyramid Network Contracting",
    "wof:placetype":"venue"
},
  "geometry": {"coordinates":[-73.176114,41.180422],"type":"Point"}
}