{
  "type": "Feature",
  "properties": {
    "iso:country":"US",
    "sg:address":"500 Summer St",
    "sg:city":"Stamford",
    "sg:classifiers":[
        {
            "category":"Professional",
            "subcategory":"Computer Services",
            "type":"Services"
        }
    ],
    "sg:phone":"+1 203 921 1365",
    "sg:postcode":"06901",
    "sg:province":"CT",
    "sg:tags":[
        "website",
        "design",
        "system"
    ],
    "wof:name":"G C M Global Partnership",
    "wof:placetype":"venue"
},
  "geometry": {"coordinates":[-73.540575,41.055566],"type":"Point"}
}