{
  "type": "Feature",
  "properties": {
    "addr:full":"394 New Haven Ave Milford CT 06460",
    "addr:housenumber":"394",
    "addr:postcode":"06460",
    "addr:street":"New Haven Ave",
    "iso:country":"US",
    "sg:address":"394 New Haven Ave",
    "sg:city":"Milford",
    "sg:classifiers":[
        {
            "category":"Retail",
            "subcategory":"Repair Shop",
            "type":"Services"
        },
        {
            "category":"Shopping",
            "subcategory":"Bicycles & Sporting Goods",
            "type":"Retail Goods"
        }
    ],
    "sg:phone":"+1 203 877 8886",
    "sg:postcode":"06460",
    "sg:province":"CT",
    "sg:tags":[
        "gun",
        "gunsmith"
    ],
    "wof:name":"Milford Firearms & Fishing LLC",
    "wof:placetype":"venue"
},
  "geometry": {"coordinates":[-73.039411,41.223758],"type":"Point"}
}