{
  "type": "Feature",
  "properties": {
    "addr:full":"681 Wolcott Rd Wolcott CT 06716",
    "addr:housenumber":"681",
    "addr:postcode":"06716",
    "addr:street":"Wolcott Rd Wolcott Ct",
    "iso:country":"US",
    "sg:address":"681 Wolcott Rd",
    "sg:city":"Wolcott",
    "sg:classifiers":[
        {
            "category":"Manufacturing",
            "subcategory":"Signs",
            "type":"Manufacturing & Wholesale Goods"
        }
    ],
    "sg:phone":"+1 203 879 1911",
    "sg:postcode":"06716",
    "sg:province":"CT",
    "wof:name":"Sign Technologies",
    "wof:placetype":"venue"
},
  "geometry": {"coordinates":[-72.98574000000001,41.599824],"type":"Point"}
}