{
  "type": "Feature",
  "properties": {
    "addr:full":"33 Ledgebrook Dr Mansfield Center CT 06250",
    "addr:housenumber":"33",
    "addr:postcode":"06250",
    "addr:street":"Ledgebrook Dr",
    "iso:country":"US",
    "sg:address":"33 Ledgebrook Dr",
    "sg:city":"Mansfield Center",
    "sg:classifiers":[
        {
            "category":"Professional",
            "subcategory":"Management & Consulting",
            "type":"Services"
        }
    ],
    "sg:phone":"+1   ",
    "sg:postcode":"06250",
    "sg:province":"CT",
    "sg:tags":[
        "business"
    ],
    "wof:name":"Charter Oak Environmental Svcs",
    "wof:placetype":"venue"
},
  "geometry": {"coordinates":[-72.205698,41.733118],"type":"Point"}
}