{
  "type": "Feature",
  "properties": {
    "iso:country":"US",
    "sg:address":"525 Russell Rd",
    "sg:city":"Newington",
    "sg:classifiers":[
        {
            "category":"Health Services",
            "subcategory":"Hospital",
            "type":"Services"
        }
    ],
    "sg:phone":"+1 860 666 4613",
    "sg:postcode":"06111",
    "sg:province":"CT",
    "sg:tags":[
        "psychiatric",
        "general"
    ],
    "wof:name":"Cedar Crest Regional Hospital",
    "wof:placetype":"venue"
},
  "geometry": {"coordinates":[-72.706557,41.703935],"type":"Point"}
}