{
  "type": "Feature",
  "properties": {
    "iso:country":"US",
    "sg:address":"50 Weston St",
    "sg:city":"Hartford",
    "sg:classifiers":[
        {
            "category":"Professional",
            "subcategory":"Lawyer & Legal Services",
            "type":"Services"
        }
    ],
    "sg:phone":"+1   ",
    "sg:postcode":"06120",
    "sg:province":"CT",
    "sg:tags":[
        "attorney"
    ],
    "wof:name":"Beaudoin Gerald",
    "wof:placetype":"venue"
},
  "geometry": {"coordinates":[-72.664339,41.785106],"type":"Point"}
}