{
  "type": "Feature",
  "properties": {
    "iso:country":"US",
    "sg:address":"360 Fountain St",
    "sg:city":"New Haven",
    "sg:classifiers":[
        {
            "category":"Banks & Credit Unions",
            "subcategory":"Investment Brokerage",
            "type":"Services"
        }
    ],
    "sg:phone":"+1 203 397 2844",
    "sg:postcode":"06515",
    "sg:province":"CT",
    "wof:name":"P F Capital Inc",
    "wof:placetype":"venue"
},
  "geometry": {"coordinates":[-72.969735,41.327268],"type":"Point"}
}