{
  "type": "Feature",
  "properties": {
    "iso:country":"US",
    "sg:address":"163 Noroton Ave",
    "sg:city":"Darien",
    "sg:classifiers":[
        {
            "category":"Personal",
            "subcategory":"Beauty Salon",
            "type":"Services"
        }
    ],
    "sg:phone":"+1   ",
    "sg:postcode":"06820",
    "sg:province":"CT",
    "sg:tags":[
        "shop"
    ],
    "wof:name":"Sunny Nail Salon Inc",
    "wof:placetype":"venue"
},
  "geometry": {"coordinates":[-73.491502,41.069929],"type":"Point"}
}