{
  "type": "Feature",
  "properties": {
    "addr:full":"99 Winding Brook Ln Stamford CT 06902",
    "addr:housenumber":"99",
    "addr:postcode":"06902",
    "addr:street":"Winding Brook Ln",
    "iso:country":"US",
    "sg:address":"99 Winding Brook Ln",
    "sg:city":"Stamford",
    "sg:classifiers":[
        {
            "category":"Professional",
            "subcategory":"Management & Consulting",
            "type":"Services"
        }
    ],
    "sg:phone":"+1   ",
    "sg:postcode":"06902",
    "sg:province":"CT",
    "wof:name":"Joerg Schroeder",
    "wof:placetype":"venue"
},
  "geometry": {"coordinates":[-73.57695699999999,41.092312],"type":"Point"}
}