{
  "type": "Feature",
  "properties": {
    "iso:country":"US",
    "sg:address":"50 Spring Lake Rd",
    "sg:city":"Southington",
    "sg:classifiers":[
        {
            "category":"Education",
            "subcategory":"School",
            "type":"Public Place"
        }
    ],
    "sg:phone":"+1 860 628 3377",
    "sg:postcode":"06489",
    "sg:province":"CT",
    "sg:tags":[
        "executive"
    ],
    "wof:name":"Hatton William H Elemtry Schl",
    "wof:placetype":"venue"
},
  "geometry": {"coordinates":[-72.855919,41.601226],"type":"Point"}
}