{
  "type": "Feature",
  "properties": {
    "iso:country":"US",
    "sg:address":"174 Soundview Ave",
    "sg:city":"Stratford",
    "sg:classifiers":[
        {
            "category":"Arts & Performance",
            "subcategory":"Theater",
            "type":"Entertainment"
        }
    ],
    "sg:phone":"+1   ",
    "sg:postcode":"06615",
    "sg:province":"CT",
    "sg:tags":[
        "group"
    ],
    "wof:name":"Tidal Wave Entertainment Inc",
    "wof:placetype":"venue"
},
  "geometry": {"coordinates":[-73.14677399999999,41.189171],"type":"Point"}
}