{
  "type": "Feature",
  "properties": {
    "iso:country":"US",
    "sg:address":"707 Mix Ave",
    "sg:city":"Hamden",
    "sg:classifiers":[
        {
            "category":"Organizations",
            "subcategory":"Professional Association",
            "type":"Services"
        }
    ],
    "sg:phone":"+1 203 281 9196",
    "sg:postcode":"06514",
    "sg:province":"CT",
    "wof:name":"Clearview Association",
    "wof:placetype":"venue"
},
  "geometry": {"coordinates":[-72.92120799999999,41.374849],"type":"Point"}
}