{
  "type": "Feature",
  "properties": {
    "iso:country":"US",
    "sg:address":"58 Juniper Dr",
    "sg:city":"North Haven",
    "sg:classifiers":[
        {
            "category":"Professional",
            "subcategory":"Business Services",
            "type":"Services"
        }
    ],
    "sg:phone":"+1   ",
    "sg:postcode":"06473",
    "sg:province":"CT",
    "wof:name":"Family Solutions LLC",
    "wof:placetype":"venue"
},
  "geometry": {"coordinates":[-72.82799,41.36705],"type":"Point"}
}