{
  "type": "Feature",
  "properties": {
    "addr:full":"224 Park Rd Hartford CT 06119",
    "addr:housenumber":"224",
    "addr:postcode":"06119",
    "addr:street":"Park Rd",
    "iso:country":"US",
    "sg:address":"224 Park Rd",
    "sg:city":"Hartford",
    "sg:classifiers":[
        {
            "category":"Wholesale",
            "subcategory":"Medical Equipment & Supplies",
            "type":"Manufacturing & Wholesale Goods"
        }
    ],
    "sg:phone":"+1 860 232 1868",
    "sg:postcode":"06119",
    "sg:province":"CT",
    "wof:name":"Mt Medical LLC",
    "wof:placetype":"venue"
},
  "geometry": {"coordinates":[-72.72414499999999,41.757956],"type":"Point"}
}