{
  "type": "Feature",
  "properties": {
    "addr:full":"1299 Little Meadow Rd Guilford CT 06437",
    "addr:housenumber":"1299",
    "addr:postcode":"06437",
    "addr:street":"Little Meadow Rd",
    "iso:country":"US",
    "sg:address":"1299 Little Meadow Rd",
    "sg:city":"Guilford",
    "sg:classifiers":[
        {
            "category":"Professional",
            "subcategory":"Management & Consulting",
            "type":"Services"
        }
    ],
    "sg:phone":"+1   ",
    "sg:postcode":"06437",
    "sg:province":"CT",
    "sg:tags":[
        "business"
    ],
    "wof:name":"Arthur Haut",
    "wof:placetype":"venue"
},
  "geometry": {"coordinates":[-72.69761099999999,41.328668],"type":"Point"}
}