{
  "type": "Feature",
  "properties": {
    "iso:country":"US",
    "sg:address":"144 Beers Pl",
    "sg:city":"Stratford",
    "sg:classifiers":[
        {
            "category":"Building & Trades",
            "subcategory":"Landscaping Services",
            "type":"Services"
        }
    ],
    "sg:phone":"+1 203 375 0147",
    "sg:postcode":"06614",
    "sg:province":"CT",
    "sg:tags":[
        "landscape",
        "contractor"
    ],
    "wof:name":"Tony's Lawn Svc",
    "wof:placetype":"venue"
},
  "geometry": {"coordinates":[-73.13040700000001,41.204323],"type":"Point"}
}