{
  "type": "Feature",
  "properties": {
    "addr:full":"150 Watertown Rd Thomaston CT 06787",
    "addr:housenumber":"150",
    "addr:postcode":"06787",
    "addr:street":"Watertown Rd Thomaston Ct",
    "iso:country":"US",
    "sg:address":"150 Watertown Rd",
    "sg:city":"Thomaston",
    "sg:classifiers":[
        {
            "category":"Real Estate",
            "subcategory":"Architect",
            "type":"Services"
        }
    ],
    "sg:phone":"+1   ",
    "sg:postcode":"06787",
    "sg:province":"CT",
    "sg:tags":[
        "architectural"
    ],
    "wof:name":"Design Connection LLC",
    "wof:placetype":"venue"
},
  "geometry": {"coordinates":[-73.086118,41.658081],"type":"Point"}
}