{
  "type": "Feature",
  "properties": {
    "iso:country":"US",
    "sg:address":"500 Purdy Hill Rd",
    "sg:city":"Monroe",
    "sg:classifiers":[
        {
            "category":"Professional",
            "subcategory":"Employment Agencies",
            "type":"Services"
        }
    ],
    "sg:phone":"+1 203 268 8624",
    "sg:postcode":"06468",
    "sg:province":"CT",
    "sg:tags":[
        "opportunity"
    ],
    "sg:website":"www.themonroegroup.com",
    "wof:name":"Monroe Group",
    "wof:placetype":"venue"
},
  "geometry": {"coordinates":[-73.250883,41.305245],"type":"Point"}
}