{
  "type": "Feature",
  "properties": {
    "addr:full":"145 Dora Dr Middletown CT 06457",
    "addr:housenumber":"145",
    "addr:postcode":"06457",
    "addr:street":"Dora Dr",
    "iso:country":"US",
    "sg:address":"145 Dora Dr",
    "sg:city":"Middletown",
    "sg:classifiers":[
        {
            "category":"Communications",
            "subcategory":"Film & Video Production",
            "type":"Services"
        }
    ],
    "sg:phone":"+1   ",
    "sg:postcode":"06457",
    "sg:province":"CT",
    "sg:tags":[
        "motion"
    ],
    "wof:name":"Grandmas House Animation",
    "wof:placetype":"venue"
},
  "geometry": {"coordinates":[-72.656498,41.538161],"type":"Point"}
}