{
  "type": "Feature",
  "properties": {
    "addr:full":"21 Abendroth Ave Port Chester CT 10573",
    "addr:housenumber":"21",
    "addr:postcode":"10573",
    "addr:street":"Abendroth Ave;Chester",
    "iso:country":"US",
    "sg:address":"21 Abendroth Ave",
    "sg:city":"Port Chester",
    "sg:classifiers":[
        {
            "category":"Wholesale",
            "subcategory":"Machinery & Supplies",
            "type":"Manufacturing & Wholesale Goods"
        }
    ],
    "sg:phone":"+1 914 937 1771",
    "sg:postcode":"10573",
    "sg:province":"CT",
    "sg:tags":[
        "tool"
    ],
    "sg:website":"www.empiretools.com",
    "wof:name":"Empire Tools",
    "wof:placetype":"venue"
},
  "geometry": {"coordinates":[-73.66181,41.001159],"type":"Point"}
}