{
  "type": "Feature",
  "properties": {
    "iso:country":"US",
    "sg:address":"42 Paddy Hollow Rd",
    "sg:city":"Bethlehem",
    "sg:classifiers":[
        {
            "category":"Professional",
            "subcategory":"Business Services",
            "type":"Services"
        }
    ],
    "sg:phone":"+1   ",
    "sg:postcode":"06751",
    "sg:province":"CT",
    "wof:name":"New England Technology Service",
    "wof:placetype":"venue"
},
  "geometry": {"coordinates":[-73.232022,41.638829],"type":"Point"}
}