{
  "type": "Feature",
  "properties": {
    "iso:country":"US",
    "sg:address":"8 E Newberry Rd",
    "sg:city":"Bloomfield",
    "sg:classifiers":[
        {
            "category":"Utilities",
            "subcategory":"Refuse",
            "type":"Services"
        },
        {
            "category":"Utilities",
            "subcategory":"Recycling",
            "type":"Services"
        },
        {
            "category":"Building & Trades",
            "subcategory":"Construction",
            "type":"Services"
        }
    ],
    "sg:phone":"+1 860 243 2240",
    "sg:postcode":"06002",
    "sg:province":"CT",
    "sg:tags":[
        "container",
        "garbage",
        "collection",
        "removal",
        "rubbish",
        "contractor",
        "demolition"
    ],
    "wof:name":"Demolition Plus",
    "wof:placetype":"venue"
},
  "geometry": {"coordinates":[-72.69374999999999,41.861164],"type":"Point"}
}