{
  "type": "Feature",
  "properties": {
    "iso:country":"US",
    "sg:address":"927 High Ridge Rd",
    "sg:city":"Stamford",
    "sg:phone":"+1 203 329 7800",
    "sg:postcode":"06905",
    "sg:province":"CT",
    "sg:website":"http://www.kitsthaikitchen.com",
    "wof:name":"Kit's Thai Kitchen",
    "wof:placetype":"venue"
},
  "geometry": {"coordinates":[-73.54815499999999,41.10312],"type":"Point"}
}