{
  "type": "Feature",
  "properties": {
    "addr:full":"28 Bartlett Mnr Norwalk CT 06850",
    "addr:housenumber":"28",
    "addr:postcode":"06850",
    "addr:street":"Bartlett Mnr",
    "iso:country":"US",
    "sg:address":"28 Bartlett Mnr",
    "sg:city":"Norwalk",
    "sg:classifiers":[
        {
            "category":"Education",
            "subcategory":"Special Training",
            "type":"Public Place"
        }
    ],
    "sg:phone":"+1   ",
    "sg:postcode":"06850",
    "sg:province":"CT",
    "wof:name":"Country Crafts By Toni",
    "wof:placetype":"venue"
},
  "geometry": {"coordinates":[-73.433188,41.12415],"type":"Point"}
}