{
  "type": "Feature",
  "properties": {
    "addr:full":"2458 Whitney Ave Hamden CT 06518",
    "addr:housenumber":"2458",
    "addr:postcode":"06518",
    "addr:street":"Whitney Ave",
    "iso:country":"US",
    "sg:address":"2458 Whitney Ave",
    "sg:city":"Hamden",
    "sg:classifiers":[
        {
            "category":"Shopping",
            "subcategory":"Optical Goods",
            "type":"Retail Goods"
        }
    ],
    "sg:phone":"+1 203 281 4745",
    "sg:postcode":"06518",
    "sg:province":"CT",
    "wof:name":"Philips Optical LLC",
    "wof:placetype":"venue"
},
  "geometry": {"coordinates":[-72.900864,41.386503],"type":"Point"}
}