{
  "type": "Feature",
  "properties": {
    "addr:full":"16 Waterbury Rd Prospect CT 06712",
    "addr:housenumber":"16",
    "addr:postcode":"06712",
    "addr:street":"Waterbury Rd",
    "iso:country":"US",
    "sg:address":"16 Waterbury Rd",
    "sg:city":"Prospect",
    "sg:classifiers":[
        {
            "category":"Professional",
            "subcategory":"Employment Agencies",
            "type":"Services"
        }
    ],
    "sg:phone":"+1 203 758 7796",
    "sg:postcode":"06712",
    "sg:province":"CT",
    "sg:tags":[
        "consultant",
        "search",
        "executive"
    ],
    "wof:name":"Advance Synergy LLC",
    "wof:placetype":"venue"
},
  "geometry": {"coordinates":[-72.979682,41.504937],"type":"Point"}
}