{
  "type": "Feature",
  "properties": {
    "addr:full":"16 Stag Ln Trumbull CT 06611",
    "addr:housenumber":"16",
    "addr:postcode":"06611",
    "addr:street":"Stag Ln",
    "iso:country":"US",
    "sg:address":"16 Stag Ln",
    "sg:city":"Trumbull",
    "sg:classifiers":[
        {
            "category":"Organizations",
            "subcategory":"Religious Organization",
            "type":"Services"
        }
    ],
    "sg:phone":"+1 203 452 7043",
    "sg:postcode":"06611",
    "sg:province":"CT",
    "sg:tags":[
        "church"
    ],
    "wof:name":"Sharing Christ Minis",
    "wof:placetype":"venue"
},
  "geometry": {"coordinates":[-73.205839,41.298874],"type":"Point"}
}