{
  "type": "Feature",
  "properties": {
    "iso:country":"US",
    "sg:address":"1 Brook St",
    "sg:city":"Norwalk",
    "sg:classifiers":[
        {
            "category":"Arena",
            "subcategory":"Sports Club",
            "type":"Entertainment"
        }
    ],
    "sg:phone":"+1   ",
    "sg:postcode":"06851",
    "sg:province":"CT",
    "sg:tags":[
        "sporting",
        "event"
    ],
    "wof:name":"Sports Business International",
    "wof:placetype":"venue"
},
  "geometry": {"coordinates":[-73.410985,41.11932],"type":"Point"}
}