{
  "type": "Feature",
  "properties": {
    "iso:country":"US",
    "sg:address":"3 Seeley St",
    "sg:city":"Bethel",
    "sg:classifiers":[
        {
            "category":"Wholesale",
            "subcategory":"Hardware",
            "type":"Manufacturing & Wholesale Goods"
        },
        {
            "category":"Building & Trades",
            "subcategory":"Plumbing",
            "type":"Services"
        }
    ],
    "sg:phone":"+1 203 748 3790",
    "sg:postcode":"06801",
    "sg:province":"CT",
    "sg:tags":[
        "conditioning",
        "air",
        "system",
        "contractor"
    ],
    "wof:name":"Hobart W Thomas Co Inc",
    "wof:placetype":"venue"
},
  "geometry": {"coordinates":[-73.40957899999999,41.372433],"type":"Point"}
}