{
  "type": "Feature",
  "properties": {
    "iso:country":"US",
    "sg:address":"175 School St",
    "sg:city":"Hamden",
    "sg:classifiers":[
        {
            "category":"Recreation",
            "type":"Entertainment"
        }
    ],
    "sg:phone":"+1   ",
    "sg:postcode":"06518",
    "sg:province":"CT",
    "sg:tags":[
        "club",
        "membership"
    ],
    "wof:name":"Bpoe",
    "wof:placetype":"venue"
},
  "geometry": {"coordinates":[-72.903543,41.384782],"type":"Point"}
}