{
  "type": "Feature",
  "properties": {
    "addr:full":"650 Wolcott Rd Wolcott CT 06716",
    "addr:housenumber":"650",
    "addr:postcode":"06716",
    "addr:street":"Wolcott Rd Wolcott Ct",
    "iso:country":"US",
    "sg:address":"650 Wolcott Rd",
    "sg:city":"Wolcott",
    "sg:classifiers":[
        {
            "category":"Food & Beverages",
            "subcategory":"Groceries & Convenience Stores",
            "type":"Retail Goods"
        }
    ],
    "sg:phone":"+1 203 879 4015",
    "sg:postcode":"06716",
    "sg:province":"CT",
    "wof:name":"At Your Convenience",
    "wof:placetype":"venue"
},
  "geometry": {"coordinates":[-72.985349,41.598997],"type":"Point"}
}