{
  "type": "Feature",
  "properties": {
    "addr:full":"68 Le Grande Ave Greenwich CT 06830",
    "addr:housenumber":"68",
    "addr:postcode":"06830",
    "addr:street":"Le Grande Ave",
    "iso:country":"US",
    "sg:address":"68 Le Grande Ave",
    "sg:city":"Greenwich",
    "sg:classifiers":[
        {
            "category":"Building & Trades",
            "subcategory":"Construction",
            "type":"Services"
        }
    ],
    "sg:phone":"+1 203 622 8925",
    "sg:postcode":"06830",
    "sg:province":"CT",
    "sg:tags":[
        "repairing",
        "remodeling",
        "contractor"
    ],
    "wof:name":"Howe Custom Remodeling",
    "wof:placetype":"venue"
},
  "geometry": {"coordinates":[-73.61844000000001,41.027979],"type":"Point"}
}