{
  "type": "Feature",
  "properties": {
    "iso:country":"US",
    "sg:address":"388 Main St",
    "sg:city":"Monroe",
    "sg:classifiers":[
        {
            "category":"Professional",
            "subcategory":"Accounting & Tax Preparation",
            "type":"Services"
        }
    ],
    "sg:phone":"+1 203 261 6037",
    "sg:postcode":"06468",
    "sg:province":"CT",
    "sg:tags":[
        "accountant",
        "public",
        "certified"
    ],
    "wof:name":"Vincent F Russo CPA",
    "wof:placetype":"venue"
},
  "geometry": {"coordinates":[-73.26199,41.318831],"type":"Point"}
}