{
  "type": "Feature",
  "properties": {
    "iso:country":"US",
    "sg:address":"2785 Dixwell Ave",
    "sg:city":"Hamden",
    "sg:classifiers":[
        {
            "category":"Personal",
            "subcategory":"Beauty Salon",
            "type":"Services"
        }
    ],
    "sg:phone":"+1   ",
    "sg:postcode":"06518",
    "sg:province":"CT",
    "sg:tags":[
        "shop"
    ],
    "wof:name":"Color Nails",
    "wof:placetype":"venue"
},
  "geometry": {"coordinates":[-72.908647,41.382674],"type":"Point"}
}