{
  "type": "Feature",
  "properties": {
    "addr:full":"150 Sunnydale Rd Trumbull CT 06611",
    "addr:housenumber":"150",
    "addr:postcode":"06611",
    "addr:street":"Sunnydale Rd",
    "iso:country":"US",
    "sg:address":"150 Sunnydale Rd",
    "sg:city":"Trumbull",
    "sg:classifiers":[
        {
            "category":"Insurance",
            "subcategory":"Insurance Agent",
            "type":"Services"
        }
    ],
    "sg:phone":"+1 203 374 2417",
    "sg:postcode":"06611",
    "sg:province":"CT",
    "sg:tags":[
        "preparation",
        "tax",
        "return"
    ],
    "wof:name":"Surety Inc",
    "wof:placetype":"venue"
},
  "geometry": {"coordinates":[-73.224563,41.227578],"type":"Point"}
}