{
  "type": "Feature",
  "properties": {
    "addr:full":"70 N Water St East Windsor CT 06088",
    "addr:housenumber":"70",
    "addr:postcode":"06088",
    "addr:street":"N Water St East Windsor Ct",
    "iso:country":"US",
    "sg:address":"70 N Water St",
    "sg:city":"East Windsor",
    "sg:classifiers":[
        {
            "category":"Social Services",
            "type":"Services"
        }
    ],
    "sg:phone":"+1   ",
    "sg:postcode":"06088",
    "sg:province":"CT",
    "wof:name":"North Central Counseling Svrc",
    "wof:placetype":"venue"
},
  "geometry": {"coordinates":[-72.62136599999999,41.927191],"type":"Point"}
}