{
  "type": "Feature",
  "properties": {
    "iso:country":"US",
    "sg:address":"36 Brookside Blvd",
    "sg:city":"Hartford",
    "sg:classifiers":[
        {
            "category":"Banks & Credit Unions",
            "subcategory":"Financial Services",
            "type":"Services"
        }
    ],
    "sg:phone":"+1 860 232 8116",
    "sg:postcode":"06107",
    "sg:province":"CT",
    "sg:tags":[
        "trust",
        "management"
    ],
    "wof:name":"Fisher Foundation Inc",
    "wof:placetype":"venue"
},
  "geometry": {"coordinates":[-72.75000799999999,41.774757],"type":"Point"}
}