{
  "type": "Feature",
  "properties": {
    "addr:full":"680 Boston Post Rd Milford CT 06460",
    "addr:housenumber":"680",
    "addr:postcode":"06460",
    "addr:street":"Boston Post Rd",
    "iso:country":"US",
    "sg:address":"680 Boston Post Rd",
    "sg:city":"Milford",
    "sg:classifiers":[
        {
            "category":"Recreation",
            "type":"Entertainment"
        }
    ],
    "sg:phone":"+1 203 878 1247",
    "sg:postcode":"06460",
    "sg:province":"CT",
    "sg:tags":[
        "martial",
        "arts",
        "instruction"
    ],
    "wof:name":"Champion Karate Ctr",
    "wof:placetype":"venue"
},
  "geometry": {"coordinates":[-73.059834,41.23222],"type":"Point"}
}