{
  "type": "Feature",
  "properties": {
    "iso:country":"US",
    "sg:address":"19 Oak Dr",
    "sg:city":"Jewett City",
    "sg:classifiers":[
        {
            "category":"Building & Trades",
            "subcategory":"Construction",
            "type":"Services"
        }
    ],
    "sg:phone":"+1 860 376 9267",
    "sg:postcode":"06351",
    "sg:province":"CT",
    "sg:tags":[
        "house"
    ],
    "wof:name":"Lessard Home Improvement Co",
    "wof:placetype":"venue"
},
  "geometry": {"coordinates":[-71.998558,41.633228],"type":"Point"}
}