{
  "type": "Feature",
  "properties": {
    "addr:full":"596 Elm St Windsor Locks CT 06096",
    "addr:housenumber":"596",
    "addr:postcode":"06096",
    "addr:street":"Elm St Windsor Locks Ct",
    "iso:country":"US",
    "sg:address":"596 Elm St",
    "sg:city":"Windsor Locks",
    "sg:classifiers":[
        {
            "category":"Bakery",
            "type":"Food & Drink"
        },
        {
            "category":"Coffee & Tea",
            "type":"Food & Drink"
        },
        {
            "category":"Bagels",
            "type":"Food & Drink"
        },
        {
            "category":"Donuts",
            "type":"Food & Drink"
        }
    ],
    "sg:menulink":"http://www.allmenus.com/ct/windsor-locks/130241-dunkin-donuts/menu/",
    "sg:phone":"+1 860 623 2166",
    "sg:postcode":"06096",
    "sg:province":"CT",
    "sg:tags":[
        "american",
        "diner",
        "pastry"
    ],
    "wof:name":"Dunkin' Donuts",
    "wof:placetype":"venue"
},
  "geometry": {"coordinates":[-72.66966499999999,41.930031],"type":"Point"}
}