{
  "type": "Feature",
  "properties": {
    "iso:country":"US",
    "sg:address":"1041 New Haven Rd",
    "sg:city":"Durham",
    "sg:classifiers":[
        {
            "category":"Retail",
            "subcategory":"Auto Repair",
            "type":"Services"
        }
    ],
    "sg:phone":"+1   ",
    "sg:postcode":"06422",
    "sg:province":"CT",
    "sg:tags":[
        "automotive",
        "race",
        "general",
        "chassis",
        "mfg"
    ],
    "wof:name":"Aubreys Competition Driveline",
    "wof:placetype":"venue"
},
  "geometry": {"coordinates":[-72.73112399999999,41.430285],"type":"Point"}
}