{
  "type": "Feature",
  "properties": {
    "iso:country":"US",
    "sg:address":"952 White Plains Rd",
    "sg:city":"Trumbull",
    "sg:classifiers":[
        {
            "category":"Banks & Credit Unions",
            "subcategory":"Bank",
            "type":"Services"
        }
    ],
    "sg:phone":"+1 203 452 3025",
    "sg:postcode":"06611",
    "sg:province":"CT",
    "sg:tags":[
        "federal",
        "savings"
    ],
    "wof:name":"Webster Bank",
    "wof:placetype":"venue"
},
  "geometry": {"coordinates":[-73.196477,41.244793],"type":"Point"}
}