{
  "type": "Feature",
  "properties": {
    "iso:country":"US",
    "sg:address":"1167 Marion Rd",
    "sg:city":"Cheshire",
    "sg:classifiers":[
        {
            "category":"Professional",
            "subcategory":"Lawyer & Legal Services",
            "type":"Services"
        }
    ],
    "sg:phone":"+1   ",
    "sg:postcode":"06410",
    "sg:province":"CT",
    "wof:name":"Bradford Gentry",
    "wof:placetype":"venue"
},
  "geometry": {"coordinates":[-72.933088,41.534926],"type":"Point"}
}