{
  "type": "Feature",
  "properties": {
    "addr:full":"12 Campus Dr Madison CT 06443",
    "addr:housenumber":"12",
    "addr:postcode":"06443",
    "addr:street":"Campus Dr",
    "iso:country":"US",
    "sg:address":"12 Campus Dr",
    "sg:city":"Madison",
    "sg:classifiers":[
        {
            "category":"Government",
            "subcategory":"Office",
            "type":"Public Place"
        }
    ],
    "sg:phone":"+1 203 245 5677",
    "sg:postcode":"06443",
    "sg:province":"CT",
    "sg:tags":[
        "village"
    ],
    "wof:name":"Madison Cable TV",
    "wof:placetype":"venue"
},
  "geometry": {"coordinates":[-72.575028,41.29456],"type":"Point"}
}