{
  "type": "Feature",
  "properties": {
    "addr:full":"22 Johnson St Pawcatuck CT 06379",
    "addr:housenumber":"22",
    "addr:postcode":"06379",
    "addr:street":"Johnson St Pawcatuck Ct",
    "iso:country":"US",
    "sg:address":"22 Johnson St",
    "sg:city":"Pawcatuck",
    "sg:classifiers":[
        {
            "category":"Building & Trades",
            "subcategory":"Plumbing",
            "type":"Services"
        }
    ],
    "sg:phone":"+1 860 536 8679",
    "sg:postcode":"06379",
    "sg:province":"CT",
    "sg:tags":[
        "contractor"
    ],
    "wof:name":"Dave Bugbee Plumbing & Heating",
    "wof:placetype":"venue"
},
  "geometry": {"coordinates":[-71.842429,41.366169],"type":"Point"}
}