{
  "type": "Feature",
  "properties": {
    "iso:country":"US",
    "sg:address":"656 Blue Hills Ave",
    "sg:city":"Hartford",
    "sg:classifiers":[
        {
            "category":"Professional",
            "subcategory":"Accounting & Tax Preparation",
            "type":"Services"
        }
    ],
    "sg:phone":"+1   ",
    "sg:postcode":"06112",
    "sg:province":"CT",
    "sg:tags":[
        "return"
    ],
    "wof:name":"Ross Tax Service",
    "wof:placetype":"venue"
},
  "geometry": {"coordinates":[-72.695331,41.804759],"type":"Point"}
}