{
  "type": "Feature",
  "properties": {
    "iso:country":"US",
    "sg:address":"98 E Main St",
    "sg:city":"Bristol",
    "sg:classifiers":[
        {
            "category":"Retail",
            "subcategory":"Auto Repair",
            "type":"Services"
        }
    ],
    "sg:phone":"+1   ",
    "sg:postcode":"06010",
    "sg:province":"CT",
    "sg:tags":[
        "general"
    ],
    "wof:name":"Professional Automotive",
    "wof:placetype":"venue"
},
  "geometry": {"coordinates":[-72.889197,41.672837],"type":"Point"}
}