{
  "type": "Feature",
  "properties": {
    "iso:country":"US",
    "sg:address":"45 Thompson Hill Rd",
    "sg:city":"Milford",
    "sg:classifiers":[
        {
            "category":"Organizations",
            "subcategory":"Membership Organization",
            "type":"Services"
        }
    ],
    "sg:phone":"+1   ",
    "sg:postcode":"06460",
    "sg:province":"CT",
    "wof:name":"Milford Art League Inc",
    "wof:placetype":"venue"
},
  "geometry": {"coordinates":[-73.010133,41.211426],"type":"Point"}
}