{
  "type": "Feature",
  "properties": {
    "addr:full":"243 Main St Norwich CT 06360",
    "addr:housenumber":"243",
    "addr:postcode":"06360",
    "addr:street":"Main St",
    "iso:country":"US",
    "sg:address":"243 Main St",
    "sg:city":"Norwich",
    "sg:classifiers":[
        {
            "category":"Shopping",
            "subcategory":"Clothing, Apparel, & Fashions",
            "type":"Retail Goods"
        }
    ],
    "sg:phone":"+1 860 859 3943",
    "sg:postcode":"06360",
    "sg:province":"CT",
    "wof:name":"A D Fine Mens Wr & Import Shs",
    "wof:placetype":"venue"
},
  "geometry": {"coordinates":[-72.074602,41.524386],"type":"Point"}
}