{
  "type": "Feature",
  "properties": {
    "addr:full":"17 Whitfield St Guilford CT 06437",
    "addr:housenumber":"17",
    "addr:postcode":"06437",
    "addr:street":"Whitfield St",
    "iso:country":"US",
    "sg:address":"17 Whitfield St",
    "sg:city":"Guilford",
    "sg:classifiers":[
        {
            "category":"Organizations",
            "subcategory":"Religious Organization",
            "type":"Services"
        }
    ],
    "sg:phone":"+1 203 453 3627",
    "sg:postcode":"06437",
    "sg:province":"CT",
    "sg:tags":[
        "church"
    ],
    "wof:name":"First Church-Christ Scientist",
    "wof:placetype":"venue"
},
  "geometry": {"coordinates":[-72.68198099999999,41.281674],"type":"Point"}
}