{
  "type": "Feature",
  "properties": {
    "addr:full":"57 Charnes Dr New Haven CT 06513",
    "addr:housenumber":"57",
    "addr:postcode":"06513",
    "addr:street":"Charnes Dr",
    "iso:country":"US",
    "sg:address":"57 Charnes Dr",
    "sg:city":"New Haven",
    "sg:classifiers":[
        {
            "category":"Building & Trades",
            "subcategory":"Cleaning & Sanitation",
            "type":"Services"
        }
    ],
    "sg:phone":"+1   ",
    "sg:postcode":"06513",
    "sg:province":"CT",
    "sg:tags":[
        "maintenance"
    ],
    "wof:name":"Daves Cleaning Maintenance",
    "wof:placetype":"venue"
},
  "geometry": {"coordinates":[-72.849683,41.334247],"type":"Point"}
}