{
  "type": "Feature",
  "properties": {
    "iso:country":"US",
    "sg:address":"1660 Stafford Ave",
    "sg:city":"Bristol",
    "sg:classifiers":[
        {
            "category":"Food & Beverages",
            "subcategory":"Groceries & Convenience Stores",
            "type":"Retail Goods"
        }
    ],
    "sg:phone":"+1 860 675 7243",
    "sg:postcode":"06010",
    "sg:province":"CT",
    "wof:name":"Daily Mart",
    "wof:placetype":"venue"
},
  "geometry": {"coordinates":[-72.914496,41.72112],"type":"Point"}
}