{
  "type": "Feature",
  "properties": {
    "addr:full":"27 Grove St Sterling CT 06377",
    "addr:housenumber":"27",
    "addr:postcode":"06377",
    "addr:street":"Grove St",
    "iso:country":"US",
    "sg:address":"27 Grove St",
    "sg:city":"Sterling",
    "sg:classifiers":[
        {
            "category":"Professional",
            "type":"Services"
        }
    ],
    "sg:phone":"+1 860 230 0075",
    "sg:postcode":"06377",
    "sg:province":"CT",
    "wof:name":"Lazarus Baliente",
    "wof:placetype":"venue"
},
  "geometry": {"coordinates":[-71.83138099999999,41.709341],"type":"Point"}
}