{
  "type": "Feature",
  "properties": {
    "iso:country":"US",
    "sg:address":"250 Westport Ave",
    "sg:city":"Norwalk",
    "sg:classifiers":[
        {
            "category":"Food & Beverages",
            "subcategory":"Bakery",
            "type":"Retail Goods"
        }
    ],
    "sg:phone":"+1 203 846 2633",
    "sg:postcode":"06851",
    "sg:province":"CT",
    "sg:tags":[
        "bagel"
    ],
    "wof:name":"Bagel King",
    "wof:placetype":"venue"
},
  "geometry": {"coordinates":[-73.397531,41.124322],"type":"Point"}
}