{
  "type": "Feature",
  "properties": {
    "iso:country":"US",
    "sg:address":"21 N Plains Industrial Rd",
    "sg:city":"Wallingford",
    "sg:classifiers":[
        {
            "category":"Manufacturing",
            "subcategory":"Signs",
            "type":"Manufacturing & Wholesale Goods"
        }
    ],
    "sg:phone":"+1 203 949 0726",
    "sg:postcode":"06492",
    "sg:province":"CT",
    "sg:tags":[
        "mar",
        "specialty",
        "business",
        "mfg"
    ],
    "wof:name":"Nu Line Design",
    "wof:placetype":"venue"
},
  "geometry": {"coordinates":[-72.813097,41.486374],"type":"Point"}
}