{
  "type": "Feature",
  "properties": {
    "iso:country":"US",
    "sg:address":"26 Locust Ave ",
    "sg:city":"New Canaan",
    "sg:classifiers":[
        {
            "category":"Restaurant",
            "type":"Food & Drink"
        }
    ],
    "sg:menulink":"http://www.allmenus.com/ct/new-canaan/291512-fifty-coins/menu/",
    "sg:phone":"+1 203 972 3303",
    "sg:postcode":"06840",
    "sg:province":"CT",
    "sg:tags":[
        "american"
    ],
    "wof:name":"Fifty Coins",
    "wof:placetype":"venue"
},
  "geometry": {"coordinates":[-73.49266299999999,41.148922],"type":"Point"}
}