{
  "type": "Feature",
  "properties": {
    "addr:full":"79 Bridgeport Ave Milford CT 06460",
    "addr:housenumber":"79",
    "addr:postcode":"06460",
    "addr:street":"Bridgeport Ave",
    "iso:country":"US",
    "sg:address":"79 Bridgeport Ave",
    "sg:city":"Milford",
    "sg:classifiers":[
        {
            "category":"Retail",
            "subcategory":"Auto Repair",
            "type":"Services"
        }
    ],
    "sg:phone":"+1 203 877 8114",
    "sg:postcode":"06460",
    "sg:province":"CT",
    "sg:tags":[
        "automotive"
    ],
    "sg:website":"http://www.napaautocare.com/",
    "wof:name":"Dulin Automotive Inc",
    "wof:placetype":"venue"
},
  "geometry": {"coordinates":[-73.105558,41.200744],"type":"Point"}
}