{
  "type": "Feature",
  "properties": {
    "addr:full":"291 Farmington Ave Farmington CT 06032",
    "addr:housenumber":"291",
    "addr:postcode":"06032",
    "addr:street":"Farmington Ave",
    "iso:country":"US",
    "sg:address":"291 Farmington Ave",
    "sg:city":"Farmington",
    "sg:classifiers":[
        {
            "category":"Health Services",
            "subcategory":"Doctor",
            "type":"Services"
        }
    ],
    "sg:phone":"+1   ",
    "sg:postcode":"06032",
    "sg:province":"CT",
    "sg:tags":[
        "oral"
    ],
    "wof:name":"Connecticut Maxillofacial Surg",
    "wof:placetype":"venue"
},
  "geometry": {"coordinates":[-72.79742299999999,41.733114],"type":"Point"}
}