{
  "type": "Feature",
  "properties": {
    "iso:country":"US",
    "sg:address":"1 Lafayette Ave",
    "sg:city":"Ridgefield",
    "sg:classifiers":[
        {
            "category":"Professional",
            "type":"Services"
        }
    ],
    "sg:phone":"+1 203 431 0706",
    "sg:postcode":"06877",
    "sg:province":"CT",
    "sg:tags":[
        "establishment"
    ],
    "wof:name":"Ridgefield Community Pttnrshp",
    "wof:placetype":"venue"
},
  "geometry": {"coordinates":[-73.49758,41.295048],"type":"Point"}
}