{
  "type": "Feature",
  "properties": {
    "addr:full":"80 Pine Brook Ct Cheshire CT 06410",
    "addr:housenumber":"80",
    "addr:postcode":"06410",
    "addr:street":"Pine Brook Ct",
    "iso:country":"US",
    "sg:address":"80 Pine Brook Ct",
    "sg:city":"Cheshire",
    "sg:classifiers":[
        {
            "category":"Wholesale",
            "subcategory":"Non-durable Goods",
            "type":"Manufacturing & Wholesale Goods"
        }
    ],
    "sg:phone":"+1 203 272 9508",
    "sg:postcode":"06410",
    "sg:province":"CT",
    "sg:tags":[
        "premium"
    ],
    "wof:name":"J R Valen Co",
    "wof:placetype":"venue"
},
  "geometry": {"coordinates":[-72.882216,41.462982],"type":"Point"}
}