{
  "type": "Feature",
  "properties": {
    "addr:full":"99 Winsted Rd Torrington CT 06790",
    "addr:housenumber":"99",
    "addr:postcode":"06790",
    "addr:street":"Winsted Rd",
    "iso:country":"US",
    "sg:address":"99 Winsted Rd",
    "sg:city":"Torrington",
    "sg:classifiers":[
        {
            "category":"Retail",
            "subcategory":"Auto Repair",
            "type":"Services"
        }
    ],
    "sg:phone":"+1   ",
    "sg:postcode":"06790",
    "sg:province":"CT",
    "sg:tags":[
        "general"
    ],
    "wof:name":"Avis Lube",
    "wof:placetype":"venue"
},
  "geometry": {"coordinates":[-73.118612,41.822359],"type":"Point"}
}