{
  "type": "Feature",
  "properties": {
    "addr:full":"103 Holly Hill Ln Southbury CT 06488",
    "addr:housenumber":"103",
    "addr:postcode":"06488",
    "addr:street":"Holly Hill Ln",
    "iso:country":"US",
    "sg:address":"103 Holly Hill Ln",
    "sg:city":"Southbury",
    "sg:classifiers":[
        {
            "category":"Professional",
            "subcategory":"Business Services",
            "type":"Services"
        }
    ],
    "sg:phone":"+1   ",
    "sg:postcode":"06488",
    "sg:province":"CT",
    "wof:name":"Captiva Associates Ltd",
    "wof:placetype":"venue"
},
  "geometry": {"coordinates":[-73.2079,41.444749],"type":"Point"}
}