{
  "type": "Feature",
  "properties": {
    "iso:country":"US",
    "sg:address":"75 Holly Hill Ln",
    "sg:city":"Greenwich",
    "sg:classifiers":[
        {
            "category":"Professional",
            "subcategory":"Computer Services",
            "type":"Services"
        }
    ],
    "sg:phone":"+1 203 622 1503",
    "sg:postcode":"06830",
    "sg:province":"CT",
    "sg:tags":[
        "website",
        "design"
    ],
    "sg:website":"www.intraclub.com",
    "wof:name":"Intraclub.Com Inc",
    "wof:placetype":"venue"
},
  "geometry": {"coordinates":[-73.645478,41.017235],"type":"Point"}
}