{
  "type": "Feature",
  "properties": {
    "addr:full":"14 Research Pkwy Wallingford CT 06492",
    "addr:housenumber":"14",
    "addr:postcode":"06492",
    "addr:street":"Research Pkwy",
    "iso:country":"US",
    "sg:address":"14 Research Pkwy",
    "sg:city":"Wallingford",
    "sg:classifiers":[
        {
            "category":"Wholesale",
            "subcategory":"Stationery",
            "type":"Manufacturing & Wholesale Goods"
        }
    ],
    "sg:phone":"+1 203 294 1141",
    "sg:postcode":"06492",
    "sg:province":"CT",
    "sg:tags":[
        "product",
        "paper"
    ],
    "wof:name":"Lindenmeyr Munroe",
    "wof:placetype":"venue"
},
  "geometry": {"coordinates":[-72.765558,41.489484],"type":"Point"}
}