{
  "type": "Feature",
  "properties": {
    "iso:country":"US",
    "sg:address":"88 Old Stone Hwy",
    "sg:city":"East Hampton",
    "sg:classifiers":[
        {
            "category":"Real Estate",
            "subcategory":"Architect",
            "type":"Services"
        }
    ],
    "sg:phone":"+1 917 328 3905",
    "sg:postcode":"11937",
    "sg:province":"NY",
    "sg:website":"www.bergdesignarchitects.com",
    "wof:name":"BERG DESIGN ARCHITECTS",
    "wof:placetype":"venue"
},
  "geometry": {"coordinates":[-72.149958,41.818019],"type":"Point"}
}