{
  "type": "Feature",
  "properties": {
    "iso:country":"US",
    "sg:address":"20 Trinity St",
    "sg:city":"Hartford",
    "sg:classifiers":[
        {
            "category":"Government",
            "subcategory":"Office",
            "type":"Public Place"
        }
    ],
    "sg:phone":"+1 860 240 8330",
    "sg:postcode":"06106",
    "sg:province":"CT",
    "sg:tags":[
        "state",
        "agency"
    ],
    "wof:name":"Latino Prto Rican Affairs Comm",
    "wof:placetype":"venue"
},
  "geometry": {"coordinates":[-72.68061899999999,41.763724],"type":"Point"}
}