{
  "type": "Feature",
  "properties": {
    "iso:country":"US",
    "sg:address":"106 Pierremount Ave",
    "sg:city":"New Britain",
    "sg:classifiers":[
        {
            "category":"Professional",
            "subcategory":"Business Services",
            "type":"Services"
        }
    ],
    "sg:phone":"+1   ",
    "sg:postcode":"06053",
    "sg:province":"CT",
    "wof:name":"Driver Connection",
    "wof:placetype":"venue"
},
  "geometry": {"coordinates":[-72.79470000000001,41.686254],"type":"Point"}
}