{
  "type": "Feature",
  "properties": {
    "iso:country":"US",
    "sg:address":"707 Christian Ln",
    "sg:city":"Berlin",
    "sg:classifiers":[
        {
            "category":"Retail",
            "subcategory":"Auto Repair",
            "type":"Services"
        }
    ],
    "sg:phone":"+1   ",
    "sg:postcode":"06037",
    "sg:province":"CT",
    "sg:tags":[
        "general"
    ],
    "wof:name":"Grandy Motors Inc",
    "wof:placetype":"venue"
},
  "geometry": {"coordinates":[-72.750471,41.642102],"type":"Point"}
}