{
  "type": "Feature",
  "properties": {
    "iso:country":"US",
    "sg:address":"69 Fairy Dell Rd",
    "sg:city":"Clinton",
    "sg:classifiers":[
        {
            "category":"Education",
            "subcategory":"School",
            "type":"Public Place"
        }
    ],
    "sg:phone":"+1 860 664 6503",
    "sg:postcode":"06413",
    "sg:province":"CT",
    "sg:tags":[
        "high",
        "middle",
        "elementary"
    ],
    "wof:name":"Clinton Town of",
    "wof:placetype":"venue"
},
  "geometry": {"coordinates":[-72.519133,41.298],"type":"Point"}
}