{
  "type": "Feature",
  "properties": {
    "addr:full":"843 Hamilton Ave Waterbury CT 06706",
    "addr:housenumber":"843",
    "addr:postcode":"06706",
    "addr:street":"Hamilton Ave",
    "iso:country":"US",
    "sg:address":"843 Hamilton Ave",
    "sg:city":"Waterbury",
    "sg:classifiers":[
        {
            "category":"Wholesale",
            "subcategory":"Electrical",
            "type":"Manufacturing & Wholesale Goods"
        }
    ],
    "sg:phone":"+1 203 756 1950",
    "sg:postcode":"06706",
    "sg:province":"CT",
    "sg:tags":[
        "equipment",
        "electric",
        "supply"
    ],
    "wof:name":"CLS",
    "wof:placetype":"venue"
},
  "geometry": {"coordinates":[-73.020049,41.539253],"type":"Point"}
}