{
  "type": "Feature",
  "properties": {
    "iso:country":"US",
    "sg:address":"159 Maple Tree Hill Rd",
    "sg:city":"Oxford",
    "sg:classifiers":[
        {
            "category":"Building & Trades",
            "subcategory":"Construction",
            "type":"Services"
        }
    ],
    "sg:phone":"+1 203 264 1305",
    "sg:postcode":"06478",
    "sg:province":"CT",
    "sg:tags":[
        "painter"
    ],
    "wof:name":"Scattolini Painting LLC",
    "wof:placetype":"venue"
},
  "geometry": {"coordinates":[-73.18811599999999,41.427119],"type":"Point"}
}