{
  "type": "Feature",
  "properties": {
    "iso:country":"US",
    "sg:address":"85 Stage Harbor Rd",
    "sg:city":"Marlborough",
    "sg:classifiers":[
        {
            "category":"Health Services",
            "subcategory":"Nursing And Care Facility",
            "type":"Services"
        }
    ],
    "sg:phone":"+1   ",
    "sg:postcode":"06447",
    "sg:province":"CT",
    "sg:tags":[
        "skilled"
    ],
    "wof:name":"Marlborough Health Care Center",
    "wof:placetype":"venue"
},
  "geometry": {"coordinates":[-72.476955,41.652697],"type":"Point"}
}