{
  "type": "Feature",
  "properties": {
    "addr:full":"1683 Park Ave Bridgeport CT 06604",
    "addr:housenumber":"1683",
    "addr:postcode":"06604",
    "addr:street":"Park Ave",
    "iso:country":"US",
    "sg:address":"1683 Park Ave",
    "sg:city":"Bridgeport",
    "sg:classifiers":[
        {
            "category":"Wholesale",
            "subcategory":"Groceries",
            "type":"Manufacturing & Wholesale Goods"
        }
    ],
    "sg:phone":"+1 203 336 3663",
    "sg:postcode":"06604",
    "sg:province":"CT",
    "wof:name":"African Market",
    "wof:placetype":"venue"
},
  "geometry": {"coordinates":[-73.206688,41.183099],"type":"Point"}
}