{
  "type": "Feature",
  "properties": {
    "iso:country":"US",
    "sg:address":"294 Main St",
    "sg:city":"Winsted",
    "sg:classifiers":[
        {
            "category":"Health Services",
            "subcategory":"Health Practitioner",
            "type":"Services"
        }
    ],
    "sg:phone":"+1   ",
    "sg:postcode":"06098",
    "sg:province":"CT",
    "wof:name":"Charlotte Hungerford",
    "wof:placetype":"venue"
},
  "geometry": {"coordinates":[-72.961034,41.868898],"type":"Point"}
}