{
  "type": "Feature",
  "properties": {
    "addr:full":"36 Brewery St Waterbury CT 06708",
    "addr:housenumber":"36 brewery",
    "addr:postcode":"06708",
    "addr:street":"St Waterbury Ct",
    "iso:country":"US",
    "sg:address":"36 Brewery St",
    "sg:city":"Waterbury",
    "sg:classifiers":[
        {
            "category":"Wholesale",
            "subcategory":"Auto Parts",
            "type":"Manufacturing & Wholesale Goods"
        }
    ],
    "sg:phone":"+1 203 575 9642",
    "sg:postcode":"06708",
    "sg:province":"CT",
    "sg:tags":[
        "automobile",
        "rebuilt"
    ],
    "wof:name":"Conneticut Used Parts & Auto",
    "wof:placetype":"venue"
},
  "geometry": {"coordinates":[-73.03727000000001,41.53694],"type":"Point"}
}