{
  "type": "Feature",
  "properties": {
    "addr:full":"9 Indian Spring Trl Darien CT 06820",
    "addr:housenumber":"9",
    "addr:postcode":"06820",
    "addr:street":"Indian Spring Trl",
    "iso:country":"US",
    "sg:address":"9 Indian Spring Trl",
    "sg:city":"Darien",
    "sg:classifiers":[
        {
            "category":"Banks & Credit Unions",
            "subcategory":"Financial Services",
            "type":"Services"
        }
    ],
    "sg:phone":"+1 203 352 4000",
    "sg:postcode":"06820",
    "sg:province":"CT",
    "sg:tags":[
        "investment",
        "closed"
    ],
    "wof:name":"Chilton Investments",
    "wof:placetype":"venue"
},
  "geometry": {"coordinates":[-73.48732,41.111538],"type":"Point"}
}