{
  "type": "Feature",
  "properties": {
    "iso:country":"US",
    "sg:address":"262 Mixville Rd",
    "sg:city":"Cheshire",
    "sg:classifiers":[
        {
            "category":"Building & Trades",
            "subcategory":"Electrical",
            "type":"Services"
        }
    ],
    "sg:phone":"+1 203 272 7962",
    "sg:postcode":"06410",
    "sg:province":"CT",
    "sg:tags":[
        "electrical",
        "contractor"
    ],
    "wof:name":"William Spagnola",
    "wof:placetype":"venue"
},
  "geometry": {"coordinates":[-72.93680000000001,41.513511],"type":"Point"}
}