{
  "type": "Feature",
  "properties": {
    "iso:country":"US",
    "sg:address":"10 Suburban Dr",
    "sg:city":"Norwalk",
    "sg:classifiers":[
        {
            "category":"Building & Trades",
            "subcategory":"Plumbing",
            "type":"Services"
        }
    ],
    "sg:phone":"+1 203 847 9343",
    "sg:postcode":"06851",
    "sg:province":"CT",
    "sg:tags":[
        "conditioning",
        "air",
        "system",
        "contractor"
    ],
    "wof:name":"Air Care Specialists",
    "wof:placetype":"venue"
},
  "geometry": {"coordinates":[-73.416078,41.140564],"type":"Point"}
}