{
  "type": "Feature",
  "properties": {
    "addr:full":"12 Allen St Portland CT 06480",
    "addr:housenumber":"12",
    "addr:postcode":"06480",
    "addr:street":"Allen St",
    "iso:country":"US",
    "sg:address":"12 Allen St",
    "sg:city":"Portland",
    "sg:classifiers":[
        {
            "category":"Personal",
            "subcategory":"Beauty Salon",
            "type":"Services"
        }
    ],
    "sg:phone":"+1   ",
    "sg:postcode":"06480",
    "sg:province":"CT",
    "sg:tags":[
        "shop"
    ],
    "wof:name":"Lorraines Hair Salon",
    "wof:placetype":"venue"
},
  "geometry": {"coordinates":[-72.63735699999999,41.581521],"type":"Point"}
}