{
  "type": "Feature",
  "properties": {
    "addr:full":"49 Overlook Dr New Milford CT 06776",
    "addr:housenumber":"49",
    "addr:postcode":"06776",
    "addr:street":"Overlook Dr",
    "iso:country":"US",
    "sg:address":"49 Overlook Dr",
    "sg:city":"New Milford",
    "sg:classifiers":[
        {
            "category":"Manufacturing",
            "subcategory":"Tools & Machinery",
            "type":"Manufacturing & Wholesale Goods"
        }
    ],
    "sg:phone":"+1 860 355 3242",
    "sg:postcode":"06776",
    "sg:province":"CT",
    "sg:tags":[
        "mfg"
    ],
    "wof:name":"Bd Tool & Die",
    "wof:placetype":"venue"
},
  "geometry": {"coordinates":[-73.429436,41.503795],"type":"Point"}
}