{
  "type": "Feature",
  "properties": {
    "iso:country":"US",
    "sg:address":"227 Upton Rd",
    "sg:city":"Colchester",
    "sg:classifiers":[
        {
            "category":"Retail",
            "subcategory":"Animal Services",
            "type":"Services"
        }
    ],
    "sg:phone":"+1 860 537 3648",
    "sg:postcode":"06415",
    "sg:province":"CT",
    "sg:tags":[
        "grooming",
        "training",
        "care",
        "fe",
        "day"
    ],
    "wof:name":"Gagnon John Dog House LLC",
    "wof:placetype":"venue"
},
  "geometry": {"coordinates":[-72.354434,41.581316],"type":"Point"}
}