{
  "type": "Feature",
  "properties": {
    "iso:country":"US",
    "sg:address":"156 Main St",
    "sg:city":"Ansonia",
    "sg:classifiers":[
        {
            "category":"Professional",
            "subcategory":"Lawyer & Legal Services",
            "type":"Services"
        }
    ],
    "sg:phone":"+1 203 736 0400",
    "sg:postcode":"06401",
    "sg:province":"CT",
    "sg:tags":[
        "attorney"
    ],
    "wof:name":"Androski Androski Androski",
    "wof:placetype":"venue"
},
  "geometry": {"coordinates":[-73.079049,41.344081],"type":"Point"}
}