{
  "type": "Feature",
  "properties": {
    "addr:full":"23 Ridgewood Ave Stamford CT 06907",
    "addr:housenumber":"23",
    "addr:postcode":"06907",
    "addr:street":"Ridgewood Ave",
    "iso:country":"US",
    "sg:address":"23 Ridgewood Ave",
    "sg:city":"Stamford",
    "sg:classifiers":[
        {
            "category":"Shopping",
            "subcategory":"Computers & Home Electronics",
            "type":"Retail Goods"
        }
    ],
    "sg:phone":"+1 203 866 8420",
    "sg:postcode":"06907",
    "sg:province":"CT",
    "sg:tags":[
        "publishing"
    ],
    "wof:name":"Innovectral LLC",
    "wof:placetype":"venue"
},
  "geometry": {"coordinates":[-73.522886,41.080625],"type":"Point"}
}