{
  "type": "Feature",
  "properties": {
    "addr:full":"40 Laurel Lake E Weston CT 06883",
    "addr:housenumber":"40",
    "addr:postcode":"06883",
    "addr:street":"Laurel Lake E Weston Ct",
    "iso:country":"US",
    "sg:address":"40 Laurel Lake E",
    "sg:city":"Weston",
    "sg:classifiers":[
        {
            "category":"Professional",
            "subcategory":"Engineering",
            "type":"Services"
        }
    ],
    "sg:phone":"+1   ",
    "sg:postcode":"06883",
    "sg:province":"CT",
    "wof:name":"Seyer Frank Associates",
    "wof:placetype":"venue"
},
  "geometry": {"coordinates":[-73.370053,41.224283],"type":"Point"}
}