{
  "type": "Feature",
  "properties": {
    "iso:country":"US",
    "sg:address":"50 Hickory Ln",
    "sg:city":"Shelton",
    "sg:classifiers":[
        {
            "category":"Professional",
            "subcategory":"Accounting & Tax Preparation",
            "type":"Services"
        }
    ],
    "sg:phone":"+1 203 225 0247",
    "sg:postcode":"06484",
    "sg:province":"CT",
    "sg:tags":[
        "bookkeeping",
        "billing"
    ],
    "wof:name":"Cardio Phys Pc Billing",
    "wof:placetype":"venue"
},
  "geometry": {"coordinates":[-73.14099,41.347565],"type":"Point"}
}