{
  "type": "Feature",
  "properties": {
    "addr:full":"11 Hastings Ln Stamford CT 06905",
    "addr:housenumber":"11",
    "addr:postcode":"06905",
    "addr:street":"Hastings Ln",
    "iso:country":"US",
    "sg:address":"11 Hastings Ln",
    "sg:city":"Stamford",
    "sg:classifiers":[
        {
            "category":"Professional",
            "type":"Services"
        }
    ],
    "sg:phone":"+1 203 329 2442",
    "sg:postcode":"06905",
    "sg:province":"CT",
    "sg:tags":[
        "establishment"
    ],
    "wof:name":"Cruisefinders",
    "wof:placetype":"venue"
},
  "geometry": {"coordinates":[-73.53313799999999,41.085332],"type":"Point"}
}