{
  "type": "Feature",
  "properties": {
    "iso:country":"US",
    "sg:address":"74 Silo Rd",
    "sg:city":"Bristol",
    "sg:classifiers":[
        {
            "category":"Professional",
            "subcategory":"Computer Services",
            "type":"Services"
        }
    ],
    "sg:phone":"+1   ",
    "sg:postcode":"06010",
    "sg:province":"CT",
    "sg:tags":[
        "datum",
        "business",
        "association"
    ],
    "wof:name":"Bristolctnet",
    "wof:placetype":"venue"
},
  "geometry": {"coordinates":[-72.89333600000001,41.654444],"type":"Point"}
}