{
  "type": "Feature",
  "properties": {
    "addr:full":"610 Silas Deane Hwy Wethersfield CT 06109",
    "addr:housenumber":"610",
    "addr:postcode":"06109",
    "addr:street":"Silas Deane Hwy Wethersfield Ct",
    "iso:country":"US",
    "sg:address":"610 Silas Deane Hwy",
    "sg:city":"Wethersfield",
    "sg:classifiers":[
        {
            "category":"Retail",
            "subcategory":"Laundry & Dry Cleaning",
            "type":"Services"
        }
    ],
    "sg:phone":"+1   ",
    "sg:postcode":"06109",
    "sg:province":"CT",
    "sg:tags":[
        "drycleaning",
        "plant",
        "coin",
        "power"
    ],
    "wof:name":"Battistons of Wethersfield",
    "wof:placetype":"venue"
},
  "geometry": {"coordinates":[-72.66223599999999,41.708455],"type":"Point"}
}