{
  "type": "Feature",
  "properties": {
    "addr:full":"46 Hillside St Manchester CT 06042",
    "addr:housenumber":"46",
    "addr:postcode":"06042",
    "addr:street":"Hillside St",
    "iso:country":"US",
    "sg:address":"46 Hillside St",
    "sg:city":"Manchester",
    "sg:classifiers":[
        {
            "category":"Organizations",
            "subcategory":"Community Association",
            "type":"Services"
        }
    ],
    "sg:phone":"+1   ",
    "sg:postcode":"06042",
    "sg:province":"CT",
    "wof:name":"Washington 117",
    "wof:placetype":"venue"
},
  "geometry": {"coordinates":[-72.508004,41.784884],"type":"Point"}
}