{
  "type": "Feature",
  "properties": {
    "addr:full":"29 Flora Ln Fairfield CT 06478",
    "addr:housenumber":"29",
    "addr:postcode":"06478",
    "addr:street":"Flora Ln",
    "iso:country":"US",
    "sg:address":"29 Flora Ln",
    "sg:city":"Fairfield",
    "sg:classifiers":[
        {
            "category":"Retail",
            "subcategory":"Portrait Studio",
            "type":"Services"
        }
    ],
    "sg:phone":"+1 203 521 0870",
    "sg:postcode":"06478",
    "sg:province":"CT",
    "sg:tags":[
        "photographer"
    ],
    "wof:name":"Sacia Friedman Photography",
    "wof:placetype":"venue"
},
  "geometry": {"coordinates":[-73.166633,41.415665],"type":"Point"}
}