{
  "type": "Feature",
  "properties": {
    "addr:full":"7 Pershing Dr Derby CT 06418",
    "addr:housenumber":"7",
    "addr:postcode":"06418",
    "addr:street":"Pershing Dr Derby Ct",
    "iso:country":"US",
    "sg:address":"7 Pershing Dr",
    "sg:city":"Derby",
    "sg:classifiers":[
        {
            "category":"Restaurant",
            "type":"Food & Drink"
        }
    ],
    "sg:menulink":"http://www.allmenus.com/ct/derby/189498-kfc---kentucky-fried-chicken/menu/",
    "sg:phone":"+1 203 734 9881",
    "sg:postcode":"06418",
    "sg:province":"CT",
    "sg:tags":[
        "american",
        "chicken"
    ],
    "wof:name":"KFC - Kentucky Fried Chicken",
    "wof:placetype":"venue"
},
  "geometry": {"coordinates":[-73.08506800000001,41.330015],"type":"Point"}
}