{
  "type": "Feature",
  "properties": {
    "iso:country":"US",
    "sg:address":"499 Federal Rd",
    "sg:city":"Brookfield",
    "sg:classifiers":[
        {
            "category":"Professional",
            "subcategory":"Lawyer & Legal Services",
            "type":"Services"
        }
    ],
    "sg:phone":"+1 203 775 7008",
    "sg:postcode":"06804",
    "sg:province":"CT",
    "sg:tags":[
        "attorney"
    ],
    "wof:name":"Cynthia D Fox",
    "wof:placetype":"venue"
},
  "geometry": {"coordinates":[-73.40509299999999,41.458093],"type":"Point"}
}