{
  "type": "Feature",
  "properties": {
    "addr:full":"51 Smith St Niantic CT 06357",
    "addr:housenumber":"51",
    "addr:postcode":"06357",
    "addr:street":"Smith St Niantic Ct",
    "iso:country":"US",
    "sg:address":"51 Smith St",
    "sg:city":"Niantic",
    "sg:classifiers":[
        {
            "category":"Building & Trades",
            "subcategory":"Equipment Rental",
            "type":"Services"
        }
    ],
    "sg:phone":"+1   ",
    "sg:postcode":"06357",
    "sg:province":"CT",
    "wof:name":"S & H Inflatables",
    "wof:placetype":"venue"
},
  "geometry": {"coordinates":[-72.189055,41.328082],"type":"Point"}
}