{
  "type": "Feature",
  "properties": {
    "addr:full":"55 Old Farms Rd West Willington CT 06279",
    "addr:housenumber":"55",
    "addr:postcode":"06279",
    "addr:street":"Old Farms Rd West Willington Ct",
    "iso:country":"US",
    "sg:address":"55 Old Farms Rd",
    "sg:city":"West Willington",
    "sg:classifiers":[
        {
            "category":"Building & Trades",
            "subcategory":"Construction",
            "type":"Services"
        }
    ],
    "sg:phone":"+1 860 487 0009",
    "sg:postcode":"06279",
    "sg:province":"CT",
    "sg:tags":[
        "general",
        "remodeling",
        "contractor"
    ],
    "wof:name":"Barcon Home Improvments",
    "wof:placetype":"venue"
},
  "geometry": {"coordinates":[-72.258539,41.869692],"type":"Point"}
}