{
  "type": "Feature",
  "properties": {
    "iso:country":"US",
    "sg:address":"80 Main St",
    "sg:city":"New Canaan",
    "sg:classifiers":[
        {
            "category":"Home & Garden",
            "subcategory":"Home Furnishings",
            "type":"Retail Goods"
        }
    ],
    "sg:phone":"+1 203 972 1610",
    "sg:postcode":"06840",
    "sg:province":"NY",
    "sg:tags":[
        "pottery"
    ],
    "wof:name":"Art & Soul",
    "wof:placetype":"venue"
},
  "geometry": {"coordinates":[-73.493071,41.148268],"type":"Point"}
}