{
  "type": "Feature",
  "properties": {
    "addr:full":"6 Welch Rd North Haven CT 06473",
    "addr:housenumber":"6",
    "addr:postcode":"06473",
    "addr:street":"Welch Rd;Haven",
    "iso:country":"US",
    "sg:address":"6 Welch Rd",
    "sg:city":"North Haven",
    "sg:classifiers":[
        {
            "category":"Organizations",
            "subcategory":"Religious Organization",
            "type":"Services"
        }
    ],
    "sg:phone":"+1   ",
    "sg:postcode":"06473",
    "sg:province":"CT",
    "wof:name":"St Frances Cabrini Rectory",
    "wof:placetype":"venue"
},
  "geometry": {"coordinates":[-72.836983,41.383857],"type":"Point"}
}