{
  "type": "Feature",
  "properties": {
    "addr:full":"50 N Barnes St Waterbury CT 06704",
    "addr:housenumber":"50",
    "addr:postcode":"06704",
    "addr:street":"N Barnes St Waterbury Ct",
    "iso:country":"US",
    "sg:address":"50 N Barnes St",
    "sg:city":"Waterbury",
    "sg:classifiers":[
        {
            "category":"Sports & Exercise",
            "subcategory":"Gym",
            "type":"Entertainment"
        }
    ],
    "sg:phone":"+1   ",
    "sg:postcode":"06704",
    "sg:province":"CT",
    "sg:tags":[
        "fitness",
        "physical",
        "facility"
    ],
    "wof:name":"Aviglnese Athc CLB of Wterbury",
    "wof:placetype":"venue"
},
  "geometry": {"coordinates":[-73.035601,41.567252],"type":"Point"}
}