{
  "type": "Feature",
  "properties": {
    "iso:country":"US",
    "sg:address":"715 Colman St",
    "sg:city":"New London",
    "sg:classifiers":[
        {
            "category":"Food & Beverages",
            "subcategory":"Groceries & Convenience Stores",
            "type":"Retail Goods"
        }
    ],
    "sg:phone":"+1 860 444 2479",
    "sg:postcode":"06320",
    "sg:province":"CT",
    "wof:name":"Sunoco",
    "wof:placetype":"venue"
},
  "geometry": {"coordinates":[-72.114361,41.371119],"type":"Point"}
}