{
  "type": "Feature",
  "properties": {
    "addr:full":"12 Soundview Dr Pawcatuck CT 06379",
    "addr:housenumber":"12",
    "addr:postcode":"06379",
    "addr:street":"Soundview Dr Pawcatuck Ct",
    "iso:country":"US",
    "sg:address":"12 Soundview Dr",
    "sg:city":"Pawcatuck",
    "sg:classifiers":[
        {
            "category":"Health Services",
            "subcategory":"Clinic",
            "type":"Services"
        }
    ],
    "sg:phone":"+1   ",
    "sg:postcode":"06379",
    "sg:province":"CT",
    "sg:tags":[
        "program",
        "administrative",
        "social"
    ],
    "wof:name":"May Institute Inc",
    "wof:placetype":"venue"
},
  "geometry": {"coordinates":[-71.855569,41.404307],"type":"Point"}
}