{
  "type": "Feature",
  "properties": {
    "addr:full":"114 Bradley Rd Madison CT 06443",
    "addr:housenumber":"114",
    "addr:postcode":"06443",
    "addr:street":"Bradley Rd",
    "iso:country":"US",
    "sg:address":"114 Bradley Rd",
    "sg:city":"Madison",
    "sg:classifiers":[
        {
            "category":"Retail",
            "subcategory":"Self-service Laundry",
            "type":"Services"
        }
    ],
    "sg:phone":"+1 203 245 9934",
    "sg:postcode":"06443",
    "sg:province":"CT",
    "wof:name":"Tuxis Laundromat",
    "wof:placetype":"venue"
},
  "geometry": {"coordinates":[-72.59433799999999,41.283016],"type":"Point"}
}