{
  "type": "Feature",
  "properties": {
    "addr:full":"PO Box 147 Plainfield CT 06374",
    "addr:housenumber":"po",
    "addr:postcode":"06374",
    "addr:street":"Box 147",
    "iso:country":"US",
    "sg:address":"PO Box 147",
    "sg:city":"Plainfield",
    "sg:classifiers":[
        {
            "category":"Autos & Motor Vehicles",
            "subcategory":"Automobile Sales",
            "type":"Retail Goods"
        }
    ],
    "sg:phone":"+1 860 564 4014",
    "sg:postcode":"06374",
    "sg:province":"CT",
    "sg:tags":[
        "car"
    ],
    "wof:name":"Central Ford Mercury",
    "wof:placetype":"venue"
},
  "geometry": {"coordinates":[-71.91770200000001,41.676399],"type":"Point"}
}