{
  "type": "Feature",
  "properties": {
    "iso:country":"US",
    "sg:address":"1 State St",
    "sg:city":"Meriden",
    "sg:classifiers":[
        {
            "category":"Manufacturing",
            "subcategory":"Electronics",
            "type":"Manufacturing & Wholesale Goods"
        }
    ],
    "sg:phone":"+1 203 630 3311",
    "sg:postcode":"06450",
    "sg:province":"CT",
    "sg:tags":[
        "manufacture",
        "antenna",
        "mobile",
        "microwave",
        "ant",
        "sight",
        "line"
    ],
    "wof:name":"Cablewave Systems",
    "wof:placetype":"venue"
},
  "geometry": {"coordinates":[-72.80194299999999,41.537997],"type":"Point"}
}