{
  "type": "Feature",
  "properties": {
    "addr:full":"1171 Main St Branford CT 06405",
    "addr:housenumber":"1171",
    "addr:postcode":"06405",
    "addr:street":"Main St",
    "iso:country":"US",
    "sg:address":"1171 Main St",
    "sg:city":"Branford",
    "sg:classifiers":[
        {
            "category":"Professional",
            "type":"Services"
        }
    ],
    "sg:phone":"+1 203 315 0503",
    "sg:postcode":"06405",
    "sg:province":"CT",
    "sg:tags":[
        "establishment"
    ],
    "wof:name":"Twos Co Inc",
    "wof:placetype":"venue"
},
  "geometry": {"coordinates":[-72.809772,41.283817],"type":"Point"}
}