{
  "type": "Feature",
  "properties": {
    "addr:full":"401 Main St Torrington CT 06790",
    "addr:housenumber":"401",
    "addr:postcode":"06790",
    "addr:street":"Main St",
    "iso:country":"US",
    "sg:address":"401 Main St",
    "sg:city":"Torrington",
    "sg:classifiers":[
        {
            "category":"Banks & Credit Unions",
            "subcategory":"Bank",
            "type":"Services"
        }
    ],
    "sg:phone":"+1 860 489 2145",
    "sg:postcode":"06790",
    "sg:province":"CT",
    "sg:tags":[
        "national",
        "commercial"
    ],
    "wof:name":"Fleet",
    "wof:placetype":"venue"
},
  "geometry": {"coordinates":[-73.121352,41.807763],"type":"Point"}
}