{
  "type": "Feature",
  "properties": {
    "addr:full":"38 Harvester Rd Trumbull CT 06611",
    "addr:housenumber":"38",
    "addr:postcode":"06611",
    "addr:street":"Harvester Rd",
    "iso:country":"US",
    "sg:address":"38 Harvester Rd",
    "sg:city":"Trumbull",
    "sg:classifiers":[
        {
            "category":"Building & Trades",
            "subcategory":"Construction",
            "type":"Services"
        }
    ],
    "sg:phone":"+1 203 261 8889",
    "sg:postcode":"06611",
    "sg:province":"CT",
    "sg:tags":[
        "tile",
        "dealer"
    ],
    "wof:name":"Masters Tile Co",
    "wof:placetype":"venue"
},
  "geometry": {"coordinates":[-73.239611,41.243526],"type":"Point"}
}