{
  "type": "Feature",
  "properties": {
    "addr:full":"120 Commercial Pkwy Branford CT 06405",
    "addr:housenumber":"120",
    "addr:postcode":"06405",
    "addr:street":"Commercial Pkwy;Ct",
    "iso:country":"US",
    "sg:address":"120 Commercial Pkwy",
    "sg:city":"Branford",
    "sg:classifiers":[
        {
            "category":"Retail",
            "subcategory":"Portrait Studio",
            "type":"Services"
        }
    ],
    "sg:phone":"+1   ",
    "sg:postcode":"06405",
    "sg:province":"CT",
    "sg:tags":[
        "photo"
    ],
    "wof:name":"Wal-Mart Prtrait Studio 02232",
    "wof:placetype":"venue"
},
  "geometry": {"coordinates":[-72.829255,41.277357],"type":"Point"}
}