{
  "type": "Feature",
  "properties": {
    "iso:country":"US",
    "sg:address":"2 Hearthstone Dr",
    "sg:city":"Sandy Hook",
    "sg:classifiers":[
        {
            "category":"Shopping",
            "subcategory":"Computers & Home Electronics",
            "type":"Retail Goods"
        }
    ],
    "sg:phone":"+1 203 426 5838",
    "sg:postcode":"06484",
    "sg:province":"CT",
    "sg:tags":[
        "software"
    ],
    "wof:name":"P C Help",
    "wof:placetype":"venue"
},
  "geometry": {"coordinates":[-73.186643,41.297366],"type":"Point"}
}