{
  "type": "Feature",
  "properties": {
    "addr:full":"39 Nutmeg Dr Greenwich NY 06831",
    "addr:housenumber":"39",
    "addr:postcode":"06831",
    "addr:street":"Nutmeg Dr",
    "iso:country":"US",
    "sg:address":"39 Nutmeg Dr",
    "sg:city":"Greenwich",
    "sg:classifiers":[
        {
            "category":"Social Services",
            "type":"Services"
        }
    ],
    "sg:phone":"+1 203 531 5090",
    "sg:postcode":"06831",
    "sg:province":"NY",
    "sg:tags":[
        "organization",
        "welfare"
    ],
    "wof:name":"Greenwich Lyme Disease Task",
    "wof:placetype":"venue"
},
  "geometry": {"coordinates":[-73.681826,41.056634],"type":"Point"}
}