{
  "type": "Feature",
  "properties": {
    "iso:country":"US",
    "sg:address":"112 Merrimac Dr",
    "sg:city":"Trumbull",
    "sg:classifiers":[
        {
            "category":"Professional",
            "type":"Services"
        }
    ],
    "sg:phone":"+1 203 261 8246",
    "sg:postcode":"06611",
    "sg:province":"CT",
    "wof:name":"Mahmaud Hessemmi",
    "wof:placetype":"venue"
},
  "geometry": {"coordinates":[-73.249832,41.260866],"type":"Point"}
}