{
  "type": "Feature",
  "properties": {
    "iso:country":"US",
    "sg:address":"55 Gibson Ave",
    "sg:city":"Trumbull",
    "sg:classifiers":[
        {
            "category":"Real Estate",
            "subcategory":"Real Estate Operator",
            "type":"Services"
        }
    ],
    "sg:phone":"+1 203 261 8184",
    "sg:postcode":"06611",
    "sg:province":"CT",
    "sg:tags":[
        "building",
        "nonresidential"
    ],
    "wof:name":"Ganino Properties LLC",
    "wof:placetype":"venue"
},
  "geometry": {"coordinates":[-73.212005,41.244366],"type":"Point"}
}