{
  "type": "Feature",
  "properties": {
    "iso:country":"US",
    "sg:address":"162 Bouton St",
    "sg:city":"Norwalk",
    "sg:classifiers":[
        {
            "category":"Freight",
            "type":"Transportation"
        }
    ],
    "sg:phone":"+1 203 855 9222",
    "sg:postcode":"06854",
    "sg:province":"CT",
    "sg:tags":[
        "general"
    ],
    "wof:name":"Affordable Self Storage",
    "wof:placetype":"venue"
},
  "geometry": {"coordinates":[-73.430823,41.083706],"type":"Point"}
}