{
  "type": "Feature",
  "properties": {
    "addr:full":"164 Fellows Rd Oakdale CT 06370",
    "addr:housenumber":"164",
    "addr:postcode":"06370",
    "addr:street":"Fellows Rd Oakdale Ct",
    "iso:country":"US",
    "sg:address":"164 Fellows Rd",
    "sg:city":"Oakdale",
    "sg:classifiers":[
        {
            "category":"Building & Trades",
            "subcategory":"Landscaping Services",
            "type":"Services"
        }
    ],
    "sg:phone":"+1 860 848 0001",
    "sg:postcode":"06370",
    "sg:province":"CT",
    "wof:name":"Dj Landscaping Plus",
    "wof:placetype":"venue"
},
  "geometry": {"coordinates":[-72.165272,41.471036],"type":"Point"}
}