{
  "type": "Feature",
  "properties": {
    "addr:full":"227 Church St Wallingford CT 06492",
    "addr:housenumber":"227",
    "addr:postcode":"06492",
    "addr:street":"Church St",
    "iso:country":"US",
    "sg:address":"227 Church St",
    "sg:city":"Wallingford",
    "sg:classifiers":[
        {
            "category":"Building & Trades",
            "subcategory":"Plumbing",
            "type":"Services"
        }
    ],
    "sg:phone":"+1 203 269 8937",
    "sg:postcode":"06492",
    "sg:province":"CT",
    "sg:tags":[
        "installation",
        "tank",
        "cleaning",
        "septic"
    ],
    "wof:name":"Yalesville Sanitation Service",
    "wof:placetype":"venue"
},
  "geometry": {"coordinates":[-72.814426,41.490308],"type":"Point"}
}