{
  "type": "Feature",
  "properties": {
    "addr:full":"31 Ensign Dr Avon CT 06001",
    "addr:housenumber":"31",
    "addr:postcode":"06001",
    "addr:street":"Ensign Dr",
    "iso:country":"US",
    "sg:address":"31 Ensign Dr",
    "sg:city":"Avon",
    "sg:classifiers":[
        {
            "category":"Sports & Exercise",
            "subcategory":"Gym",
            "type":"Entertainment"
        }
    ],
    "sg:phone":"+1 860 409 9125",
    "sg:postcode":"06001",
    "sg:province":"CT",
    "sg:tags":[
        "trainer"
    ],
    "sg:website":"www.theperfectworkout.org",
    "wof:name":"Perfect Workout the",
    "wof:placetype":"venue"
},
  "geometry": {"coordinates":[-72.83444799999999,41.814687],"type":"Point"}
}