{
  "type": "Feature",
  "properties": {
    "addr:full":"46 Long Hill Rd Guilford CT 06437",
    "addr:housenumber":"46",
    "addr:postcode":"06437",
    "addr:street":"Long Hill Rd",
    "iso:country":"US",
    "sg:address":"46 Long Hill Rd",
    "sg:city":"Guilford",
    "sg:classifiers":[
        {
            "category":"Manufacturing",
            "subcategory":"Electronics",
            "type":"Manufacturing & Wholesale Goods"
        }
    ],
    "sg:phone":"+1   ",
    "sg:postcode":"06437",
    "sg:province":"CT",
    "sg:tags":[
        "prerecorded",
        "consulting",
        "management",
        "mfg"
    ],
    "wof:name":"Time Warner",
    "wof:placetype":"venue"
},
  "geometry": {"coordinates":[-72.69301400000001,41.289033],"type":"Point"}
}