{
  "type": "Feature",
  "properties": {
    "addr:full":"116 W Ridge Dr Hartford CT 06117",
    "addr:housenumber":"116",
    "addr:postcode":"06117",
    "addr:street":"W Ridge Dr",
    "iso:country":"US",
    "sg:address":"116 W Ridge Dr",
    "sg:city":"Hartford",
    "sg:classifiers":[
        {
            "category":"Professional",
            "subcategory":"Business Services",
            "type":"Services"
        }
    ],
    "sg:phone":"+1   ",
    "sg:postcode":"06117",
    "sg:province":"CT",
    "wof:name":"Spirited Design",
    "wof:placetype":"venue"
},
  "geometry": {"coordinates":[-72.756781,41.791116],"type":"Point"}
}