{
  "type": "Feature",
  "properties": {
    "addr:full":"16 Old Plainfield Rd Canterbury CT 06331",
    "addr:housenumber":"16",
    "addr:postcode":"06331",
    "addr:street":"Old Plainfield Rd",
    "iso:country":"US",
    "sg:address":"16 Old Plainfield Rd",
    "sg:city":"Canterbury",
    "sg:classifiers":[
        {
            "category":"Retail",
            "subcategory":"Auto Repair",
            "type":"Services"
        }
    ],
    "sg:phone":"+1   ",
    "sg:postcode":"06331",
    "sg:province":"CT",
    "sg:tags":[
        "body",
        "automotive",
        "collision",
        "general"
    ],
    "wof:name":"R&R Generalk Repair",
    "wof:placetype":"venue"
},
  "geometry": {"coordinates":[-71.96831299999999,41.700975],"type":"Point"}
}