{
  "type": "Feature",
  "properties": {
    "iso:country":"US",
    "sg:address":"881 Washington Blvd",
    "sg:city":"Stamford",
    "sg:classifiers":[
        {
            "category":"Wholesale",
            "subcategory":"Electrical",
            "type":"Manufacturing & Wholesale Goods"
        }
    ],
    "sg:phone":"+1 203 324 6779",
    "sg:postcode":"06901",
    "sg:province":"CT",
    "sg:tags":[
        "radio"
    ],
    "wof:name":"World Paging Wireless",
    "wof:placetype":"venue"
},
  "geometry": {"coordinates":[-73.542068,41.051769],"type":"Point"}
}