{
  "type": "Feature",
  "properties": {
    "addr:full":"287 Scofield Ave Bridgeport CT 06605",
    "addr:housenumber":"287",
    "addr:postcode":"06605",
    "addr:street":"Scofield Ave",
    "iso:country":"US",
    "sg:address":"287 Scofield Ave",
    "sg:city":"Bridgeport",
    "sg:classifiers":[
        {
            "category":"Autos & Motor Vehicles",
            "subcategory":"Automobile Sales",
            "type":"Retail Goods"
        },
        {
            "category":"Retail",
            "subcategory":"Auto Repair",
            "type":"Services"
        }
    ],
    "sg:phone":"+1 203 334 0691",
    "sg:postcode":"06605",
    "sg:province":"CT",
    "sg:tags":[
        "body",
        "shop",
        "classic"
    ],
    "wof:name":"Monroe Restoration Inc",
    "wof:placetype":"venue"
},
  "geometry": {"coordinates":[-73.22694,41.164089],"type":"Point"}
}