{
  "type": "Feature",
  "properties": {
    "iso:country":"US",
    "sg:address":"27 State St",
    "sg:city":"Waterbury",
    "sg:classifiers":[
        {
            "category":"Professional",
            "subcategory":"Lawyer & Legal Services",
            "type":"Services"
        }
    ],
    "sg:phone":"+1   ",
    "sg:postcode":"06702",
    "sg:province":"CT",
    "wof:name":"Laurie Singer",
    "wof:placetype":"venue"
},
  "geometry": {"coordinates":[-73.04530099999999,41.555947],"type":"Point"}
}