{
  "type": "Feature",
  "properties": {
    "iso:country":"US",
    "sg:address":"139 W Main St",
    "sg:city":"Waterbury",
    "sg:classifiers":[
        {
            "category":"Shopping",
            "subcategory":"Clothing, Apparel, & Fashions",
            "type":"Retail Goods"
        }
    ],
    "sg:phone":"+1 203 596 3449",
    "sg:postcode":"06702",
    "sg:province":"CT",
    "wof:name":"J G I L Apparel",
    "wof:placetype":"venue"
},
  "geometry": {"coordinates":[-73.042728,41.556233],"type":"Point"}
}