{
  "type": "Feature",
  "properties": {
    "addr:full":"42 E High St East Hampton CT 06424",
    "addr:housenumber":"42",
    "addr:postcode":"06424",
    "addr:street":"E High St East Hampton Ct",
    "iso:country":"US",
    "sg:address":"42 E High St",
    "sg:city":"East Hampton",
    "sg:classifiers":[
        {
            "category":"Education",
            "subcategory":"Vocational School",
            "type":"Public Place"
        }
    ],
    "sg:phone":"+1   ",
    "sg:postcode":"06424",
    "sg:province":"CT",
    "wof:name":"Family Practice Group",
    "wof:placetype":"venue"
},
  "geometry": {"coordinates":[-72.502982,41.583562],"type":"Point"}
}