{
  "type": "Feature",
  "properties": {
    "addr:full":"239 Squaw Rock Rd Moosup CT 06354",
    "addr:housenumber":"239",
    "addr:postcode":"06354",
    "addr:street":"Squaw Rock Rd Moosup Ct",
    "iso:country":"US",
    "sg:address":"239 Squaw Rock Rd",
    "sg:city":"Moosup",
    "sg:classifiers":[
        {
            "category":"Building & Trades",
            "subcategory":"Plumbing",
            "type":"Services"
        }
    ],
    "sg:phone":"+1 860 564 4143",
    "sg:postcode":"06354",
    "sg:province":"CT",
    "wof:name":"D Mac & Son Plumbing & Heating",
    "wof:placetype":"venue"
},
  "geometry": {"coordinates":[-71.881989,41.731042],"type":"Point"}
}