{
  "type": "Feature",
  "properties": {
    "iso:country":"US",
    "sg:address":"75 Arrow Head Trl",
    "sg:city":"New Canaan",
    "sg:classifiers":[
        {
            "category":"Real Estate",
            "subcategory":"Real Estate Operator",
            "type":"Services"
        }
    ],
    "sg:phone":"+1 203 972 5705",
    "sg:postcode":"06840",
    "sg:province":"NY",
    "sg:tags":[
        "building",
        "nonresidential"
    ],
    "wof:name":"Arrowhead Properties LLC",
    "wof:placetype":"venue"
},
  "geometry": {"coordinates":[-73.526472,41.143116],"type":"Point"}
}