{
  "type": "Feature",
  "properties": {
    "addr:full":"90 Highland Ave New Haven CT 06513",
    "addr:housenumber":"90",
    "addr:postcode":"06513",
    "addr:street":"Highland Ave",
    "iso:country":"US",
    "sg:address":"90 Highland Ave",
    "sg:city":"New Haven",
    "sg:classifiers":[
        {
            "category":"Retail",
            "subcategory":"Repair Shop",
            "type":"Services"
        }
    ],
    "sg:phone":"+1   ",
    "sg:postcode":"06513",
    "sg:province":"CT",
    "sg:tags":[
        "electrical"
    ],
    "wof:name":"Affordable Appliance Repair",
    "wof:placetype":"venue"
},
  "geometry": {"coordinates":[-72.860784,41.323718],"type":"Point"}
}