{
  "type": "Feature",
  "properties": {
    "addr:full":"63 Prescott St Bridgeport CT 06605",
    "addr:housenumber":"63",
    "addr:postcode":"06605",
    "addr:street":"Prescott St",
    "iso:country":"US",
    "sg:address":"63 Prescott St",
    "sg:city":"Bridgeport",
    "sg:classifiers":[
        {
            "category":"Professional",
            "type":"Services"
        }
    ],
    "sg:phone":"+1 203 333 3071",
    "sg:postcode":"06605",
    "sg:province":"CT",
    "wof:name":"Magnolia LLC",
    "wof:placetype":"venue"
},
  "geometry": {"coordinates":[-73.221279,41.158164],"type":"Point"}
}