{
  "type": "Feature",
  "properties": {
    "addr:full":"89 Dodgingtown Rd Bethel CT 06801",
    "addr:housenumber":"89",
    "addr:postcode":"06801",
    "addr:street":"Dodgingtown Rd",
    "iso:country":"US",
    "sg:address":"89 Dodgingtown Rd",
    "sg:city":"Bethel",
    "sg:classifiers":[
        {
            "category":"Social Services",
            "subcategory":"Job Training",
            "type":"Services"
        }
    ],
    "sg:phone":"+1 203 792 6906",
    "sg:postcode":"06801",
    "sg:province":"CT",
    "sg:tags":[
        "rehabilitation"
    ],
    "wof:name":"Ability Beyond Disability",
    "wof:placetype":"venue"
},
  "geometry": {"coordinates":[-73.37437300000001,41.381219],"type":"Point"}
}