{
  "type": "Feature",
  "properties": {
    "iso:country":"US",
    "sg:address":"128 Cipolla Dr",
    "sg:city":"East Hartford",
    "sg:classifiers":[
        {
            "category":"Building & Trades",
            "subcategory":"Construction",
            "type":"Services"
        }
    ],
    "sg:phone":"+1 860 569 8937",
    "sg:postcode":"06118",
    "sg:province":"CT",
    "sg:tags":[
        "hanging",
        "contractor"
    ],
    "wof:name":"Ace Maintenance",
    "wof:placetype":"venue"
},
  "geometry": {"coordinates":[-72.587898,41.769111],"type":"Point"}
}