{
  "type": "Feature",
  "properties": {
    "iso:country":"US",
    "sg:address":"188 S Main St",
    "sg:city":"Cheshire",
    "sg:classifiers":[
        {
            "category":"Retail",
            "subcategory":"Laundry & Dry Cleaning",
            "type":"Services"
        }
    ],
    "sg:phone":"+1   ",
    "sg:postcode":"06410",
    "sg:province":"CT",
    "sg:tags":[
        "drycleaning",
        "plant"
    ],
    "wof:name":"Burdette Cleaners Inc",
    "wof:placetype":"venue"
},
  "geometry": {"coordinates":[-72.902586,41.496351],"type":"Point"}
}