{
  "type": "Feature",
  "properties": {
    "iso:country":"US",
    "sg:address":"54 Abbe Rd",
    "sg:city":"Enfield",
    "sg:classifiers":[
        {
            "category":"Farming",
            "subcategory":"Livestock Farm",
            "type":"Manufacturing & Wholesale Goods"
        }
    ],
    "sg:phone":"+1 860 749 4866",
    "sg:postcode":"06082",
    "sg:province":"CT",
    "sg:tags":[
        "beef",
        "feedlot",
        "cattle"
    ],
    "wof:name":"Stocker Farm",
    "wof:placetype":"venue"
},
  "geometry": {"coordinates":[-72.523612,41.975827],"type":"Point"}
}