{
  "type": "Feature",
  "properties": {
    "addr:full":"836 Baldwin St Waterbury CT 06706",
    "addr:housenumber":"836",
    "addr:postcode":"06706",
    "addr:street":"Baldwin St Waterbury Ct",
    "iso:country":"US",
    "sg:address":"836 Baldwin St",
    "sg:city":"Waterbury",
    "sg:classifiers":[
        {
            "category":"Recreation",
            "type":"Entertainment"
        }
    ],
    "sg:phone":"+1   ",
    "sg:postcode":"06706",
    "sg:province":"CT",
    "sg:tags":[
        "club",
        "membership"
    ],
    "wof:name":"Washington Hill Athletic Club",
    "wof:placetype":"venue"
},
  "geometry": {"coordinates":[-73.033546,41.540933],"type":"Point"}
}