{
  "type": "Feature",
  "properties": {
    "iso:country":"US",
    "sg:address":"378 Middle Tpke W",
    "sg:city":"Manchester",
    "sg:classifiers":[
        {
            "category":"Personal",
            "subcategory":"Barber",
            "type":"Services"
        }
    ],
    "sg:phone":"+1   ",
    "sg:postcode":"06040",
    "sg:province":"CT",
    "sg:tags":[
        "shop"
    ],
    "wof:name":"Parkway Barber Shop",
    "wof:placetype":"venue"
},
  "geometry": {"coordinates":[-72.541815,41.780573],"type":"Point"}
}