{
  "type": "Feature",
  "properties": {
    "iso:country":"US",
    "sg:address":"1030 Baldwin St",
    "sg:city":"Waterbury",
    "sg:classifiers":[
        {
            "category":"Personal",
            "subcategory":"Barber",
            "type":"Services"
        }
    ],
    "sg:phone":"+1 203 756 3533",
    "sg:postcode":"06706",
    "sg:province":"CT",
    "wof:name":"John's Hair Styling & Brbrng",
    "wof:placetype":"venue"
},
  "geometry": {"coordinates":[-73.033731,41.538276],"type":"Point"}
}