{
  "type": "Feature",
  "properties": {
    "addr:full":"425 Platt St Bridgeport CT 06606",
    "addr:housenumber":"425",
    "addr:postcode":"06606",
    "addr:street":"Platt St",
    "iso:country":"US",
    "sg:address":"425 Platt St",
    "sg:city":"Bridgeport",
    "sg:classifiers":[
        {
            "category":"Building & Trades",
            "subcategory":"Construction",
            "type":"Services"
        }
    ],
    "sg:phone":"+1 203 371 1959",
    "sg:postcode":"06606",
    "sg:province":"CT",
    "sg:tags":[
        "resurfacing",
        "refinishing",
        "floor"
    ],
    "wof:name":"Bridgeport Hardwood Floors",
    "wof:placetype":"venue"
},
  "geometry": {"coordinates":[-73.199302,41.215642],"type":"Point"}
}