{
  "type": "Feature",
  "properties": {
    "iso:country":"US",
    "sg:address":"233 Research Dr",
    "sg:city":"Milford",
    "sg:classifiers":[
        {
            "category":"Health Services",
            "subcategory":"Clinic",
            "type":"Services"
        }
    ],
    "sg:phone":"+1 203 874 3235",
    "sg:postcode":"06460",
    "sg:province":"CT",
    "sg:tags":[
        "home"
    ],
    "wof:name":"Professional Homecare Svc",
    "wof:placetype":"venue"
},
  "geometry": {"coordinates":[-73.011611,41.241848],"type":"Point"}
}