{
  "type": "Feature",
  "properties": {
    "iso:country":"US",
    "sg:address":"219 Ashley Rd",
    "sg:city":"Bristol",
    "sg:classifiers":[
        {
            "category":"Wholesale",
            "subcategory":"Machinery & Supplies",
            "type":"Manufacturing & Wholesale Goods"
        }
    ],
    "sg:phone":"+1 860 583 2670",
    "sg:postcode":"06010",
    "sg:province":"CT",
    "sg:tags":[
        "industrial"
    ],
    "wof:name":"M&G Backflow Testing LLC",
    "wof:placetype":"venue"
},
  "geometry": {"coordinates":[-72.947473,41.705646],"type":"Point"}
}