{
  "type": "Feature",
  "properties": {
    "iso:country":"US",
    "sg:address":"90 Reservoir Rd",
    "sg:city":"Broad Brook",
    "sg:classifiers":[
        {
            "category":"Building & Trades",
            "subcategory":"Plumbing",
            "type":"Services"
        }
    ],
    "sg:phone":"+1 860 627 8380",
    "sg:postcode":"06016",
    "sg:province":"CT",
    "sg:tags":[
        "heating",
        "contractor"
    ],
    "wof:name":"Donald J Sawyer",
    "wof:placetype":"venue"
},
  "geometry": {"coordinates":[-72.52692,41.912097],"type":"Point"}
}