{
  "type": "Feature",
  "properties": {
    "addr:full":"32 Canterbury Rd Bridgeport CT 06606",
    "addr:housenumber":"32",
    "addr:postcode":"06606",
    "addr:street":"Canterbury Rd",
    "iso:country":"US",
    "sg:address":"32 Canterbury Rd",
    "sg:city":"Bridgeport",
    "sg:classifiers":[
        {
            "category":"Professional",
            "type":"Services"
        }
    ],
    "sg:phone":"+1 203 330 1303",
    "sg:postcode":"06606",
    "sg:province":"CT",
    "sg:tags":[
        "establishment"
    ],
    "wof:name":"Creative Web Designs",
    "wof:placetype":"venue"
},
  "geometry": {"coordinates":[-73.22468499999999,41.212116],"type":"Point"}
}