{
  "type": "Feature",
  "properties": {
    "addr:full":"42 Lakeside Ave Middletown CT 06457",
    "addr:housenumber":"42",
    "addr:postcode":"06457",
    "addr:street":"Lakeside Ave",
    "iso:country":"US",
    "sg:address":"42 Lakeside Ave",
    "sg:city":"Middletown",
    "sg:classifiers":[
        {
            "category":"Real Estate",
            "subcategory":"Surveying",
            "type":"Services"
        }
    ],
    "sg:phone":"+1   ",
    "sg:postcode":"06457",
    "sg:province":"CT",
    "wof:name":"Jackowiak Land Surveying",
    "wof:placetype":"venue"
},
  "geometry": {"coordinates":[-72.654498,41.543255],"type":"Point"}
}