{
  "type": "Feature",
  "properties": {
    "addr:full":"34 Wilford Rd Branford CT 06405",
    "addr:housenumber":"34",
    "addr:postcode":"06405",
    "addr:street":"Wilford Rd",
    "iso:country":"US",
    "sg:address":"34 Wilford Rd",
    "sg:city":"Branford",
    "sg:classifiers":[
        {
            "category":"Building & Trades",
            "subcategory":"Construction",
            "type":"Services"
        }
    ],
    "sg:phone":"+1 203 483 1960",
    "sg:postcode":"06405",
    "sg:province":"CT",
    "sg:tags":[
        "general",
        "contractor"
    ],
    "wof:name":"Tradewinds Construction Inc",
    "wof:placetype":"venue"
},
  "geometry": {"coordinates":[-72.79898799999999,41.26101],"type":"Point"}
}