{
  "type": "Feature",
  "properties": {
    "iso:country":"US",
    "sg:address":"60 Stanley Rd",
    "sg:city":"Monroe",
    "sg:classifiers":[
        {
            "category":"Building & Trades",
            "subcategory":"Construction",
            "type":"Services"
        }
    ],
    "sg:phone":"+1 203 268 0450",
    "sg:postcode":"06468",
    "sg:province":"CT",
    "sg:tags":[
        "general",
        "contractor"
    ],
    "wof:name":"Pine Tree Construction",
    "wof:placetype":"venue"
},
  "geometry": {"coordinates":[-73.26783399999999,41.307085],"type":"Point"}
}