{
  "type": "Feature",
  "properties": {
    "iso:country":"US",
    "sg:address":"12 Windsor Ave",
    "sg:city":"Windsor",
    "sg:classifiers":[
        {
            "category":"Organizations",
            "subcategory":"Religious Organization",
            "type":"Services"
        }
    ],
    "sg:phone":"+1   ",
    "sg:postcode":"06095",
    "sg:province":"CT",
    "wof:name":"Greater St Paul Baptist Church",
    "wof:placetype":"venue"
},
  "geometry": {"coordinates":[-72.660607,41.801477],"type":"Point"}
}