{
  "type": "Feature",
  "properties": {
    "iso:country":"US",
    "sg:address":"20 Cold Spring Cir",
    "sg:city":"Naugatuck",
    "sg:classifiers":[
        {
            "category":"Building & Trades",
            "subcategory":"Construction",
            "type":"Services"
        }
    ],
    "sg:phone":"+1 203 723 2032",
    "sg:postcode":"06770",
    "sg:province":"CT",
    "sg:tags":[
        "painter"
    ],
    "wof:name":"Quality Colors Painting",
    "wof:placetype":"venue"
},
  "geometry": {"coordinates":[-73.03626199999999,41.49806],"type":"Point"}
}