{
  "type": "Feature",
  "properties": {
    "addr:full":"1 Sawmill Rd New Fairfield CT 06812",
    "addr:housenumber":"1",
    "addr:postcode":"06812",
    "addr:street":"Sawmill Rd;Fairfield Ct",
    "iso:country":"US",
    "sg:address":"1 Sawmill Rd",
    "sg:city":"New Fairfield",
    "sg:classifiers":[
        {
            "category":"Professional",
            "subcategory":"Lawyer & Legal Services",
            "type":"Services"
        }
    ],
    "sg:phone":"+1 203 746 7411",
    "sg:postcode":"06812",
    "sg:province":"CT",
    "sg:tags":[
        "attorney"
    ],
    "wof:name":"Peter S Vannucci",
    "wof:placetype":"venue"
},
  "geometry": {"coordinates":[-73.48079,41.464904],"type":"Point"}
}