{
  "type": "Feature",
  "properties": {
    "addr:full":"20 Westbrook St East Hartford CT 06108",
    "addr:housenumber":"20",
    "addr:postcode":"06108",
    "addr:street":"Westbrook St East;Ct",
    "iso:country":"US",
    "sg:address":"20 Westbrook St",
    "sg:city":"East Hartford",
    "sg:classifiers":[
        {
            "category":"Professional",
            "subcategory":"Computer Services",
            "type":"Services"
        }
    ],
    "sg:phone":"+1   ",
    "sg:postcode":"06108",
    "sg:province":"CT",
    "sg:tags":[
        "development",
        "system",
        "software"
    ],
    "wof:name":"K T International Inc",
    "wof:placetype":"venue"
},
  "geometry": {"coordinates":[-72.626006,41.776655],"type":"Point"}
}