{
  "type": "Feature",
  "properties": {
    "addr:full":"63 Buttles Rd Granby CT 06035",
    "addr:housenumber":"63",
    "addr:postcode":"06035",
    "addr:street":"Buttles Rd",
    "iso:country":"US",
    "sg:address":"63 Buttles Rd",
    "sg:city":"Granby",
    "sg:classifiers":[
        {
            "category":"Professional",
            "subcategory":"Accounting & Tax Preparation",
            "type":"Services"
        }
    ],
    "sg:phone":"+1   ",
    "sg:postcode":"06035",
    "sg:province":"CT",
    "wof:name":"Child William C W",
    "wof:placetype":"venue"
},
  "geometry": {"coordinates":[-72.808325,41.922592],"type":"Point"}
}