{
  "type": "Feature",
  "properties": {
    "iso:country":"US",
    "sg:address":"201 Clapboard Ridge Rd",
    "sg:city":"Greenwich",
    "sg:classifiers":[
        {
            "category":"Building & Trades",
            "subcategory":"Landscaping Services",
            "type":"Services"
        },
        {
            "category":"Farming",
            "subcategory":"Nursery",
            "type":"Manufacturing & Wholesale Goods"
        }
    ],
    "sg:phone":"+1 203 869 3152",
    "sg:postcode":"06831",
    "sg:province":"CT",
    "sg:tags":[
        "designer",
        "consultant",
        "nursery-wholesale",
        "contractor",
        "grower",
        "landscape"
    ],
    "wof:name":"Kennedy Nursery Inc",
    "wof:placetype":"venue"
},
  "geometry": {"coordinates":[-73.64909299999999,41.07161],"type":"Point"}
}