{
  "type": "Feature",
  "properties": {
    "addr:full":"20 Washington Ave North Haven CT 06473",
    "addr:housenumber":"20",
    "addr:postcode":"06473",
    "addr:street":"Washington Ave;Haven",
    "iso:country":"US",
    "sg:address":"20 Washington Ave",
    "sg:city":"North Haven",
    "sg:classifiers":[
        {
            "category":"Professional",
            "subcategory":"Management & Consulting",
            "type":"Services"
        }
    ],
    "sg:phone":"+1 203 234 7401",
    "sg:postcode":"06473",
    "sg:province":"CT",
    "sg:tags":[
        "consultant",
        "educational"
    ],
    "wof:name":"Idea Inc Educational Ctr",
    "wof:placetype":"venue"
},
  "geometry": {"coordinates":[-72.860564,41.389064],"type":"Point"}
}