{
  "type": "Feature",
  "properties": {
    "iso:country":"US",
    "sg:address":"15 Lyon Rd",
    "sg:city":"Burlington",
    "sg:classifiers":[
        {
            "category":"Professional",
            "type":"Services"
        }
    ],
    "sg:phone":"+1 860 673 3985",
    "sg:postcode":"06013",
    "sg:province":"CT",
    "wof:name":"Bruce Butler LLC",
    "wof:placetype":"venue"
},
  "geometry": {"coordinates":[-72.991198,41.779401],"type":"Point"}
}