{
  "type": "Feature",
  "properties": {
    "addr:full":"484 Main St Middletown CT 06457",
    "addr:housenumber":"484",
    "addr:postcode":"06457",
    "addr:street":"Main St",
    "iso:country":"US",
    "sg:address":"484 Main St",
    "sg:city":"Middletown",
    "sg:classifiers":[
        {
            "category":"Shopping",
            "subcategory":"Clothing, Apparel, & Fashions",
            "type":"Retail Goods"
        }
    ],
    "sg:phone":"+1 860 344 3095",
    "sg:postcode":"06457",
    "sg:province":"CT",
    "sg:tags":[
        "bridal"
    ],
    "wof:name":"Page Boutique",
    "wof:placetype":"venue"
},
  "geometry": {"coordinates":[-72.65034,41.561701],"type":"Point"}
}