{
  "type": "Feature",
  "properties": {
    "addr:full":"135 Hunting Hill Ave Middletown CT 06457",
    "addr:housenumber":"135",
    "addr:postcode":"06457",
    "addr:street":"Hunting Hill Ave",
    "iso:country":"US",
    "sg:address":"135 Hunting Hill Ave",
    "sg:city":"Middletown",
    "sg:classifiers":[
        {
            "category":"Building & Trades",
            "subcategory":"Construction",
            "type":"Services"
        }
    ],
    "sg:phone":"+1 860 346 3226",
    "sg:postcode":"06457",
    "sg:province":"CT",
    "sg:tags":[
        "contractor"
    ],
    "wof:name":"Monarca Construction Company",
    "wof:placetype":"venue"
},
  "geometry": {"coordinates":[-72.64832,41.546133],"type":"Point"}
}