{
  "type": "Feature",
  "properties": {
    "addr:full":"16 Ledger St Hartford CT 06106",
    "addr:housenumber":"16",
    "addr:postcode":"06106",
    "addr:street":"Ledger St",
    "iso:country":"US",
    "sg:address":"16 Ledger St",
    "sg:city":"Hartford",
    "sg:classifiers":[
        {
            "category":"Social Services",
            "subcategory":"Child Care",
            "type":"Services"
        }
    ],
    "sg:phone":"+1   ",
    "sg:postcode":"06106",
    "sg:province":"CT",
    "sg:tags":[
        "day"
    ],
    "wof:name":"Josies Child Care",
    "wof:placetype":"venue"
},
  "geometry": {"coordinates":[-72.700312,41.747819],"type":"Point"}
}