{
  "type": "Feature",
  "properties": {
    "iso:country":"US",
    "sg:address":"210 Lyons Plain Rd",
    "sg:city":"Weston",
    "sg:classifiers":[
        {
            "category":"Organizations",
            "subcategory":"Religious Organization",
            "type":"Services"
        }
    ],
    "sg:phone":"+1   ",
    "sg:postcode":"06883",
    "sg:province":"CT",
    "wof:name":"R A Hoffman Rev",
    "wof:placetype":"venue"
},
  "geometry": {"coordinates":[-73.34943800000001,41.218581],"type":"Point"}
}