{
  "type": "Feature",
  "properties": {
    "iso:country":"US",
    "sg:address":"111 River Rd",
    "sg:city":"Willington",
    "sg:classifiers":[
        {
            "category":"Education",
            "subcategory":"Preschool",
            "type":"Public Place"
        },
        {
            "category":"Education",
            "subcategory":"School",
            "type":"Public Place"
        }
    ],
    "sg:phone":"+1 860 429 0215",
    "sg:postcode":"06279",
    "sg:province":"CT",
    "sg:tags":[
        "kindergarten"
    ],
    "wof:name":"The School Age Children Programs of Northeast Connecticut Inc.",
    "wof:placetype":"venue"
},
  "geometry": {"coordinates":[-72.301857,41.85121],"type":"Point"}
}