{
  "type": "Feature",
  "properties": {
    "addr:full":"96 Oak St Hartford CT 06106",
    "addr:housenumber":"96",
    "addr:postcode":"06106",
    "addr:street":"Oak St",
    "iso:country":"US",
    "sg:address":"96 Oak St",
    "sg:city":"Hartford",
    "sg:classifiers":[
        {
            "category":"Social Services",
            "type":"Services"
        }
    ],
    "sg:phone":"+1   ",
    "sg:postcode":"06106",
    "sg:province":"CT",
    "wof:name":"Alzheimers Association",
    "wof:placetype":"venue"
},
  "geometry": {"coordinates":[-72.684392,41.760236],"type":"Point"}
}