{
  "type": "Feature",
  "properties": {
    "iso:country":"US",
    "sg:address":"4 Forest Park Dr",
    "sg:city":"Farmington",
    "sg:classifiers":[
        {
            "category":"Professional",
            "subcategory":"Employment Agencies",
            "type":"Services"
        }
    ],
    "sg:phone":"+1   ",
    "sg:postcode":"06032",
    "sg:province":"CT",
    "wof:name":"Cph Staffing & Consulting LLC",
    "wof:placetype":"venue"
},
  "geometry": {"coordinates":[-72.83773600000001,41.736691],"type":"Point"}
}