{
  "type": "Feature",
  "properties": {
    "addr:full":"7 Bus Park Dr Branford CT 06405",
    "addr:housenumber":"7",
    "addr:postcode":"06405",
    "addr:street":"Bus Park Dr",
    "iso:country":"US",
    "sg:address":"7 Bus Park Dr",
    "sg:city":"Branford",
    "sg:classifiers":[
        {
            "category":"Professional",
            "subcategory":"Management & Consulting",
            "type":"Services"
        }
    ],
    "sg:phone":"+1   ",
    "sg:postcode":"06405",
    "sg:province":"CT",
    "sg:tags":[
        "financial"
    ],
    "wof:name":"Anchor Business Capital LLC",
    "wof:placetype":"venue"
},
  "geometry": {"coordinates":[-72.764928,41.296708],"type":"Point"}
}