{
  "type": "Feature",
  "properties": {
    "iso:country":"US",
    "sg:address":"54 Post Rd E",
    "sg:city":"Westport",
    "sg:classifiers":[
        {
            "category":"Shopping",
            "subcategory":"Shoes",
            "type":"Retail Goods"
        }
    ],
    "sg:phone":"+1 203 222 3957",
    "sg:postcode":"06880",
    "sg:province":"CT",
    "wof:name":"Preschoolians",
    "wof:placetype":"venue"
},
  "geometry": {"coordinates":[-73.361361,41.141327],"type":"Point"}
}