{
  "type": "Feature",
  "properties": {
    "addr:full":"160 State Hwy 165 Preston CT 06365",
    "addr:housenumber":"160",
    "addr:postcode":"06365",
    "addr:street":"State Hwy 165 Preston Ct",
    "iso:country":"US",
    "sg:address":"160 State Hwy 165",
    "sg:city":"Preston",
    "sg:classifiers":[
        {
            "category":"Manufacturing",
            "subcategory":"Lumber",
            "type":"Manufacturing & Wholesale Goods"
        }
    ],
    "sg:phone":"+1 860 887 0604",
    "sg:postcode":"06365",
    "sg:province":"CT",
    "sg:tags":[
        "operation",
        "timber",
        "tract"
    ],
    "wof:name":"Murray Tree Farm",
    "wof:placetype":"venue"
},
  "geometry": {"coordinates":[-72.012508,41.533298],"type":"Point"}
}