{
  "type": "Feature",
  "properties": {
    "addr:full":"31 Viaduct Rd Stamford CT 06907",
    "addr:housenumber":"31",
    "addr:postcode":"06907",
    "addr:street":"Viaduct Rd",
    "iso:country":"US",
    "sg:address":"31 Viaduct Rd",
    "sg:city":"Stamford",
    "sg:classifiers":[
        {
            "category":"Building & Trades",
            "subcategory":"Plumbing",
            "type":"Services"
        }
    ],
    "sg:phone":"+1 203 324 5763",
    "sg:postcode":"06907",
    "sg:province":"CT",
    "sg:tags":[
        "conditioning",
        "air",
        "system",
        "contractor"
    ],
    "wof:name":"Pelham Heating & Air Cond",
    "wof:placetype":"venue"
},
  "geometry": {"coordinates":[-73.520934,41.079897],"type":"Point"}
}