{
  "type": "Feature",
  "properties": {
    "addr:full":"4 S Barn Hill Rd Bloomfield CT 06002",
    "addr:housenumber":"4",
    "addr:postcode":"06002",
    "addr:street":"S Barn Hill Rd Bloomfield Ct",
    "iso:country":"US",
    "sg:address":"4 S Barn Hill Rd",
    "sg:city":"Bloomfield",
    "sg:classifiers":[
        {
            "category":"Building & Trades",
            "subcategory":"Plumbing",
            "type":"Services"
        }
    ],
    "sg:phone":"+1 860 243 5301",
    "sg:postcode":"06002",
    "sg:province":"CT",
    "sg:tags":[
        "contractor"
    ],
    "wof:name":"Anopolsky Plumbing & Heating L",
    "wof:placetype":"venue"
},
  "geometry": {"coordinates":[-72.75987000000001,41.850853],"type":"Point"}
}