{
  "type": "Feature",
  "properties": {
    "addr:full":"80 Kenyon St Hartford CT 06105",
    "addr:housenumber":"80",
    "addr:postcode":"06105",
    "addr:street":"Kenyon St",
    "iso:country":"US",
    "sg:address":"80 Kenyon St",
    "sg:city":"Hartford",
    "sg:classifiers":[
        {
            "category":"Professional",
            "subcategory":"Business Services",
            "type":"Services"
        }
    ],
    "sg:phone":"+1   ",
    "sg:postcode":"06105",
    "sg:province":"CT",
    "wof:name":"Modifica Interiors LLC",
    "wof:placetype":"venue"
},
  "geometry": {"coordinates":[-72.710116,41.767807],"type":"Point"}
}