{
  "type": "Feature",
  "properties": {
    "addr:full":"233 Main St Terryville CT 06786",
    "addr:housenumber":"233",
    "addr:postcode":"06786",
    "addr:street":"Main St",
    "iso:country":"US",
    "sg:address":"233 Main St",
    "sg:city":"Terryville",
    "sg:classifiers":[
        {
            "category":"Place Of Worship",
            "subcategory":"Church",
            "type":"Public Place"
        },
        {
            "category":"Place Of Worship",
            "type":"Public Place"
        }
    ],
    "sg:phone":"+1 860 589 0182",
    "sg:postcode":"06786",
    "sg:province":"CT",
    "sg:tags":[
        "churches-congregational"
    ],
    "wof:name":"Terryville Congregational Church",
    "wof:placetype":"venue"
},
  "geometry": {"coordinates":[-73.012198,41.6788],"type":"Point"}
}