{
  "type": "Feature",
  "properties": {
    "iso:country":"US",
    "sg:address":"493 Connecticut Ave",
    "sg:city":"Norwalk",
    "sg:classifiers":[
        {
            "category":"Restaurant",
            "type":"Food & Drink"
        }
    ],
    "sg:phone":"+1 203 838 8598",
    "sg:postcode":"06854",
    "sg:province":"CT",
    "sg:tags":[
        "caterer"
    ],
    "wof:name":"Chatham Manor",
    "wof:placetype":"venue"
},
  "geometry": {"coordinates":[-73.443944,41.09823],"type":"Point"}
}