{
  "type": "Feature",
  "properties": {
    "addr:full":"462 East St Plainville CT 06062",
    "addr:housenumber":"462",
    "addr:postcode":"06062",
    "addr:street":"East St",
    "iso:country":"US",
    "sg:address":"462 East St",
    "sg:city":"Plainville",
    "sg:classifiers":[
        {
            "category":"Retail",
            "subcategory":"Auto Repair",
            "type":"Services"
        }
    ],
    "sg:phone":"+1   ",
    "sg:postcode":"06062",
    "sg:province":"CT",
    "sg:tags":[
        "general"
    ],
    "wof:name":"Russells Garage",
    "wof:placetype":"venue"
},
  "geometry": {"coordinates":[-72.870062,41.651712],"type":"Point"}
}