{
  "type": "Feature",
  "properties": {
    "iso:country":"US",
    "sg:address":"30 E River Rd",
    "sg:city":"Guilford",
    "sg:classifiers":[
        {
            "category":"Professional",
            "type":"Services"
        }
    ],
    "sg:phone":"+1   ",
    "sg:postcode":"06437",
    "sg:province":"CT",
    "wof:name":"Gardner Services LLC",
    "wof:placetype":"venue"
},
  "geometry": {"coordinates":[-72.64801900000001,41.287604],"type":"Point"}
}