{
  "type": "Feature",
  "properties": {
    "iso:country":"US",
    "sg:address":"59 Bridge St",
    "sg:city":"Willimantic",
    "sg:classifiers":[
        {
            "category":"Retail",
            "subcategory":"Self-service Laundry",
            "type":"Services"
        }
    ],
    "sg:phone":"+1   ",
    "sg:postcode":"06226",
    "sg:province":"CT",
    "sg:tags":[
        "coin"
    ],
    "wof:name":"Fluff N Fold Laundromat",
    "wof:placetype":"venue"
},
  "geometry": {"coordinates":[-72.22010400000001,41.71163],"type":"Point"}
}