{
  "type": "Feature",
  "properties": {
    "iso:country":"US",
    "sg:address":"464 Pratt St",
    "sg:city":"Meriden",
    "sg:classifiers":[
        {
            "category":"Wholesale",
            "subcategory":"Chemicals & Plastics",
            "type":"Manufacturing & Wholesale Goods"
        }
    ],
    "sg:phone":"+1 203 634 1264",
    "sg:postcode":"06450",
    "sg:province":"CT",
    "sg:tags":[
        "oxygen"
    ],
    "wof:name":"Lincare",
    "wof:placetype":"venue"
},
  "geometry": {"coordinates":[-72.78563200000001,41.543764],"type":"Point"}
}