{
  "type": "Feature",
  "properties": {
    "iso:country":"US",
    "sg:address":"123 Dartmouth St",
    "sg:city":"Torrington",
    "sg:classifiers":[
        {
            "category":"Professional",
            "subcategory":"Business Services",
            "type":"Services"
        }
    ],
    "sg:phone":"+1   ",
    "sg:postcode":"06790",
    "sg:province":"CT",
    "wof:name":"Ngc Associates Inc",
    "wof:placetype":"venue"
},
  "geometry": {"coordinates":[-73.109319,41.810896],"type":"Point"}
}