{
  "type": "Feature",
  "properties": {
    "addr:full":"114 Branford Rd North Branford CT 06471",
    "addr:housenumber":"114",
    "addr:postcode":"06471",
    "addr:street":"Branford Rd North Branford Ct",
    "iso:country":"US",
    "sg:address":"114 Branford Rd",
    "sg:city":"North Branford",
    "sg:classifiers":[
        {
            "category":"Building & Trades",
            "subcategory":"Equipment Rental",
            "type":"Services"
        }
    ],
    "sg:phone":"+1 203 484 4558",
    "sg:postcode":"06471",
    "sg:province":"CT",
    "sg:tags":[
        "toilet"
    ],
    "sg:website":"www.scottyspottys.net",
    "wof:name":"Scotty's Pottys",
    "wof:placetype":"venue"
},
  "geometry": {"coordinates":[-72.770482,41.316131],"type":"Point"}
}