{
  "type": "Feature",
  "properties": {
    "iso:country":"US",
    "sg:address":"990 Hope St",
    "sg:city":"Stamford",
    "sg:classifiers":[
        {
            "category":"Wholesale",
            "subcategory":"Medical Equipment & Supplies",
            "type":"Manufacturing & Wholesale Goods"
        },
        {
            "category":"Shopping",
            "type":"Retail Goods"
        }
    ],
    "sg:phone":"+1 203 316 0332",
    "sg:postcode":"06907",
    "sg:province":"CT",
    "sg:tags":[
        "durable",
        "hospital"
    ],
    "wof:name":"ABC Medical Surgical Sups Inc",
    "wof:placetype":"venue"
},
  "geometry": {"coordinates":[-73.51816700000001,41.091599],"type":"Point"}
}