{
  "type": "Feature",
  "properties": {
    "addr:full":"1390 East St New Britain CT 06053",
    "addr:housenumber":"1390",
    "addr:postcode":"06053",
    "addr:street":"East St",
    "iso:country":"US",
    "sg:address":"1390 East St",
    "sg:city":"New Britain",
    "sg:classifiers":[
        {
            "category":"Professional",
            "subcategory":"Computer Services",
            "type":"Services"
        }
    ],
    "sg:phone":"+1   ",
    "sg:postcode":"06053",
    "sg:province":"CT",
    "sg:tags":[
        "related"
    ],
    "wof:name":"Kevindragon Co",
    "wof:placetype":"venue"
},
  "geometry": {"coordinates":[-72.75989300000001,41.690489],"type":"Point"}
}