{
  "type": "Feature",
  "properties": {
    "addr:full":"17 W Vine St Pawcatuck CT 06379",
    "addr:housenumber":"17",
    "addr:postcode":"06379",
    "addr:street":"W Vine St Pawcatuck Ct",
    "iso:country":"US",
    "sg:address":"17 W Vine St",
    "sg:city":"Pawcatuck",
    "sg:classifiers":[
        {
            "category":"Education",
            "subcategory":"School",
            "type":"Public Place"
        }
    ],
    "sg:phone":"+1   ",
    "sg:postcode":"06379",
    "sg:province":"CT",
    "wof:name":"West Vine St Elementary School",
    "wof:placetype":"venue"
},
  "geometry": {"coordinates":[-71.842399,41.385441],"type":"Point"}
}