{
  "type": "Feature",
  "properties": {
    "iso:country":"US",
    "sg:address":"101 W Town St",
    "sg:city":"Norwich",
    "sg:classifiers":[
        {
            "category":"Social Services",
            "type":"Services"
        }
    ],
    "sg:phone":"+1   ",
    "sg:postcode":"06360",
    "sg:province":"CT",
    "wof:name":"Carenet Pregnancy Resource Cen",
    "wof:placetype":"venue"
},
  "geometry": {"coordinates":[-72.10459400000001,41.552754],"type":"Point"}
}