{
  "type": "Feature",
  "properties": {
    "iso:country":"US",
    "sg:address":"4 Scott Dr",
    "sg:city":"Prospect",
    "sg:classifiers":[
        {
            "category":"Wholesale",
            "subcategory":"Fruits & Vegetables",
            "type":"Manufacturing & Wholesale Goods"
        }
    ],
    "sg:phone":"+1 203 758 6143",
    "sg:postcode":"06712",
    "sg:province":"CT",
    "wof:name":"Produce Plus Inc",
    "wof:placetype":"venue"
},
  "geometry": {"coordinates":[-72.993427,41.525684],"type":"Point"}
}