{
  "type": "Feature",
  "properties": {
    "iso:country":"US",
    "sg:address":"18 Hale Dr",
    "sg:city":"Windsor",
    "sg:classifiers":[
        {
            "category":"Shopping",
            "subcategory":"Computers & Home Electronics",
            "type":"Retail Goods"
        }
    ],
    "sg:phone":"+1 860 683 2730",
    "sg:postcode":"06095",
    "sg:province":"CT",
    "wof:name":"Parker Computer Assoc LLC",
    "wof:placetype":"venue"
},
  "geometry": {"coordinates":[-72.668982,41.839157],"type":"Point"}
}