{
  "type": "Feature",
  "properties": {
    "addr:full":"545 Garfield Ave Bridgeport CT 06606",
    "addr:housenumber":"545",
    "addr:postcode":"06606",
    "addr:street":"Garfield Ave",
    "iso:country":"US",
    "sg:address":"545 Garfield Ave",
    "sg:city":"Bridgeport",
    "sg:classifiers":[
        {
            "category":"Building & Trades",
            "subcategory":"Construction",
            "type":"Services"
        }
    ],
    "sg:phone":"+1 203 367 4287",
    "sg:postcode":"06606",
    "sg:province":"CT",
    "sg:tags":[
        "tile",
        "dealer"
    ],
    "wof:name":"Town & Country Tile",
    "wof:placetype":"venue"
},
  "geometry": {"coordinates":[-73.207669,41.194083],"type":"Point"}
}