{
  "type": "Feature",
  "properties": {
    "addr:full":"567 Campbell Ave West Haven CT 06516",
    "addr:housenumber":"567",
    "addr:postcode":"06516",
    "addr:street":"Campbell Ave",
    "iso:country":"US",
    "sg:address":"567 Campbell Ave",
    "sg:city":"West Haven",
    "sg:classifiers":[
        {
            "category":"Retail",
            "subcategory":"Photofinishing",
            "type":"Services"
        }
    ],
    "sg:phone":"+1 203 931 9956",
    "sg:postcode":"06516",
    "sg:province":"CT",
    "sg:tags":[
        "photo",
        "finishing"
    ],
    "wof:name":"Brooks Pharmacy",
    "wof:placetype":"venue"
},
  "geometry": {"coordinates":[-72.949747,41.272096],"type":"Point"}
}