{
  "type": "Feature",
  "properties": {
    "addr:full":"15 Hartford Ave Granby CT 06035",
    "addr:housenumber":"15",
    "addr:postcode":"06035",
    "addr:street":"Hartford Ave",
    "iso:country":"US",
    "sg:address":"15 Hartford Ave",
    "sg:city":"Granby",
    "sg:classifiers":[
        {
            "category":"Personal",
            "subcategory":"Beauty Salon",
            "type":"Services"
        }
    ],
    "sg:phone":"+1   ",
    "sg:postcode":"06035",
    "sg:province":"CT",
    "sg:tags":[
        "shop"
    ],
    "wof:name":"Creative Cut",
    "wof:placetype":"venue"
},
  "geometry": {"coordinates":[-72.789062,41.9528],"type":"Point"}
}