{
  "type": "Feature",
  "properties": {
    "iso:country":"US",
    "sg:address":"263 Tresser Blvd",
    "sg:city":"Stamford",
    "sg:classifiers":[
        {
            "category":"Professional",
            "subcategory":"Employment Agencies",
            "type":"Services"
        }
    ],
    "sg:phone":"+1   ",
    "sg:postcode":"06901",
    "sg:province":"CT",
    "sg:tags":[
        "operator",
        "suite",
        "business"
    ],
    "wof:name":"Regus Business Centre Corp",
    "wof:placetype":"venue"
},
  "geometry": {"coordinates":[-73.53298700000001,41.052912],"type":"Point"}
}