{
  "type": "Feature",
  "properties": {
    "iso:country":"US",
    "sg:address":"246 Segar Mountain Rd",
    "sg:city":"Kent",
    "sg:classifiers":[
        {
            "category":"Professional",
            "subcategory":"Detective & Security Services",
            "type":"Services"
        }
    ],
    "sg:phone":"+1 860 927 3005",
    "sg:postcode":"06757",
    "sg:province":"CT",
    "sg:tags":[
        "information",
        "bureau"
    ],
    "wof:name":"Casey Estate Services",
    "wof:placetype":"venue"
},
  "geometry": {"coordinates":[-73.47242,41.716549],"type":"Point"}
}