{
  "type": "Feature",
  "properties": {
    "addr:full":"591 Arctic St Bridgeport CT 06608",
    "addr:housenumber":"591",
    "addr:postcode":"06608",
    "addr:street":"Arctic St",
    "iso:country":"US",
    "sg:address":"591 Arctic St",
    "sg:city":"Bridgeport",
    "sg:classifiers":[
        {
            "category":"Organizations",
            "subcategory":"Religious Organization",
            "type":"Services"
        }
    ],
    "sg:phone":"+1 203 368 2124",
    "sg:postcode":"06608",
    "sg:province":"CT",
    "sg:tags":[
        "church"
    ],
    "wof:name":"Congregation Mita",
    "wof:placetype":"venue"
},
  "geometry": {"coordinates":[-73.178774,41.189246],"type":"Point"}
}