{
  "type": "Feature",
  "properties": {
    "addr:full":"11 Roby Ct Branford CT 06405",
    "addr:housenumber":"11",
    "addr:postcode":"06405",
    "addr:street":"Roby Ct;Ct",
    "iso:country":"US",
    "sg:address":"11 Roby Ct",
    "sg:city":"Branford",
    "sg:classifiers":[
        {
            "category":"Personal",
            "subcategory":"Beauty Salon",
            "type":"Services"
        }
    ],
    "sg:phone":"+1   ",
    "sg:postcode":"06405",
    "sg:province":"CT",
    "sg:tags":[
        "shop"
    ],
    "wof:name":"Elaine Castiglione",
    "wof:placetype":"venue"
},
  "geometry": {"coordinates":[-72.839539,41.268221],"type":"Point"}
}