{
  "type": "Feature",
  "properties": {
    "iso:country":"US",
    "sg:address":"95 Songbird Ln",
    "sg:city":"Farmington",
    "sg:classifiers":[
        {
            "category":"Professional",
            "subcategory":"Employment Agencies",
            "type":"Services"
        }
    ],
    "sg:phone":"+1   ",
    "sg:postcode":"06032",
    "sg:province":"CT",
    "wof:name":"Executive Solution Inc",
    "wof:placetype":"venue"
},
  "geometry": {"coordinates":[-72.891119,41.698689],"type":"Point"}
}