{
  "type": "Feature",
  "properties": {
    "addr:full":"1551 Paradise Ave Hamden CT 06514",
    "addr:housenumber":"1551",
    "addr:postcode":"06514",
    "addr:street":"Paradise Ave",
    "iso:country":"US",
    "sg:address":"1551 Paradise Ave",
    "sg:city":"Hamden",
    "sg:classifiers":[
        {
            "category":"Building & Trades",
            "subcategory":"Construction",
            "type":"Services"
        }
    ],
    "sg:phone":"+1 203 248 5350",
    "sg:postcode":"06514",
    "sg:province":"CT",
    "sg:tags":[
        "maker",
        "cabinet"
    ],
    "wof:name":"A M Errichetti",
    "wof:placetype":"venue"
},
  "geometry": {"coordinates":[-72.931168,41.403896],"type":"Point"}
}