{
  "type": "Feature",
  "properties": {
    "iso:country":"US",
    "sg:address":"140 Christian Hill Rd",
    "sg:city":"Higganum",
    "sg:classifiers":[
        {
            "category":"Building & Trades",
            "subcategory":"Construction",
            "type":"Services"
        }
    ],
    "sg:phone":"+1 860 985 8601",
    "sg:postcode":"06441",
    "sg:province":"CT",
    "sg:tags":[
        "contractor"
    ],
    "wof:name":"Alt Builders",
    "wof:placetype":"venue"
},
  "geometry": {"coordinates":[-72.573888,41.495235],"type":"Point"}
}