{
  "type": "Feature",
  "properties": {
    "iso:country":"US",
    "sg:address":"353 Main St",
    "sg:city":"Ridgefield",
    "sg:classifiers":[
        {
            "category":"Social Services",
            "subcategory":"Child Care",
            "type":"Services"
        }
    ],
    "sg:phone":"+1   ",
    "sg:postcode":"06877",
    "sg:province":"CT",
    "sg:tags":[
        "day"
    ],
    "wof:name":"St Stephens Nursery School",
    "wof:placetype":"venue"
},
  "geometry": {"coordinates":[-73.49835,41.280324],"type":"Point"}
}