{
  "type": "Feature",
  "properties": {
    "iso:country":"US",
    "sg:address":"34 Simsbury Rd",
    "sg:city":"Avon",
    "sg:classifiers":[
        {
            "category":"Education",
            "subcategory":"School",
            "type":"Public Place"
        }
    ],
    "sg:phone":"+1 860 678 0815",
    "sg:postcode":"06001",
    "sg:province":"CT",
    "sg:tags":[
        "executive"
    ],
    "wof:name":"Avon Public Schools",
    "wof:placetype":"venue"
},
  "geometry": {"coordinates":[-72.829926,41.814947],"type":"Point"}
}