{
  "type": "Feature",
  "properties": {
    "iso:country":"US",
    "sg:address":"586 Clinton Ave",
    "sg:city":"Bridgeport",
    "sg:classifiers":[
        {
            "category":"Professional",
            "type":"Services"
        }
    ],
    "sg:phone":"+1 203 336 5716",
    "sg:postcode":"06605",
    "sg:province":"CT",
    "wof:name":"You Got Web",
    "wof:placetype":"venue"
},
  "geometry": {"coordinates":[-73.211224,41.175853],"type":"Point"}
}