{
  "type": "Feature",
  "properties": {
    "iso:country":"US",
    "sg:address":"2511 Main St",
    "sg:city":"Bridgeport",
    "sg:classifiers":[
        {
            "category":"Health Services",
            "subcategory":"Clinic",
            "type":"Services"
        }
    ],
    "sg:phone":"+1   ",
    "sg:postcode":"06606",
    "sg:province":"CT",
    "wof:name":"Tc Health Products LLC",
    "wof:placetype":"venue"
},
  "geometry": {"coordinates":[-73.20077499999999,41.197193],"type":"Point"}
}