{
  "type": "Feature",
  "properties": {
    "addr:full":"963 Hopmeadow St Simsbury CT 06070",
    "addr:housenumber":"963",
    "addr:postcode":"06070",
    "addr:street":"Hopmeadow St Simsbury Ct",
    "iso:country":"US",
    "sg:address":"963 Hopmeadow St",
    "sg:city":"Simsbury",
    "sg:classifiers":[
        {
            "category":"Real Estate",
            "subcategory":"Real Estate Operator",
            "type":"Services"
        }
    ],
    "sg:phone":"+1 860 653 4511",
    "sg:postcode":"06070",
    "sg:province":"CT",
    "sg:tags":[
        "building",
        "nonresidential"
    ],
    "wof:name":"Ledgehill Associates",
    "wof:placetype":"venue"
},
  "geometry": {"coordinates":[-72.799674,41.883342],"type":"Point"}
}