{
  "type": "Feature",
  "properties": {
    "iso:country":"US",
    "sg:address":"659 Hope St",
    "sg:city":"Stamford",
    "sg:classifiers":[
        {
            "category":"Building & Trades",
            "subcategory":"Construction",
            "type":"Services"
        }
    ],
    "sg:phone":"+1 203 358 9713",
    "sg:postcode":"06907",
    "sg:province":"CT",
    "sg:tags":[
        "repairing",
        "remodeling",
        "contractor"
    ],
    "wof:name":"Gesualdi Construction Inc",
    "wof:placetype":"venue"
},
  "geometry": {"coordinates":[-73.520213,41.082677],"type":"Point"}
}