{
  "type": "Feature",
  "properties": {
    "iso:country":"US",
    "sg:address":"1189 Georges Hill Rd",
    "sg:city":"Southbury",
    "sg:classifiers":[
        {
            "category":"Building & Trades",
            "subcategory":"Construction",
            "type":"Services"
        }
    ],
    "sg:phone":"+1 203 264 9009",
    "sg:postcode":"06488",
    "sg:province":"CT",
    "sg:tags":[
        "repairing",
        "remodeling",
        "contractor"
    ],
    "wof:name":"Fine Carpentry LLC",
    "wof:placetype":"venue"
},
  "geometry": {"coordinates":[-73.212304,41.436809],"type":"Point"}
}