{
  "type": "Feature",
  "properties": {
    "iso:country":"US",
    "sg:address":"48 Separatist Rd",
    "sg:city":"Storrs Mansfield",
    "sg:classifiers":[
        {
            "category":"Professional",
            "subcategory":"Management & Consulting",
            "type":"Services"
        }
    ],
    "sg:phone":"+1   ",
    "sg:postcode":"06268",
    "sg:province":"CT",
    "wof:name":"Optimal Enterprises",
    "wof:placetype":"venue"
},
  "geometry": {"coordinates":[-72.258876,41.796497],"type":"Point"}
}