{
  "type": "Feature",
  "properties": {
    "addr:full":"50 Putnam Ln Enfield CT 06082",
    "addr:housenumber":"50",
    "addr:postcode":"06082",
    "addr:street":"Putnam Ln",
    "iso:country":"US",
    "sg:address":"50 Putnam Ln",
    "sg:city":"Enfield",
    "sg:classifiers":[
        {
            "category":"Building & Trades",
            "subcategory":"Electrical",
            "type":"Services"
        }
    ],
    "sg:phone":"+1 860 749 9187",
    "sg:postcode":"06082",
    "sg:province":"CT",
    "sg:tags":[
        "electrical",
        "contractor"
    ],
    "wof:name":"Willett Electrical Inc",
    "wof:placetype":"venue"
},
  "geometry": {"coordinates":[-72.50893600000001,41.996443],"type":"Point"}
}