{
  "type": "Feature",
  "properties": {
    "iso:country":"US",
    "sg:address":"3 Getner Trl",
    "sg:city":"Norwalk",
    "sg:classifiers":[
        {
            "category":"Banks & Credit Unions",
            "subcategory":"Bank",
            "type":"Services"
        }
    ],
    "sg:phone":"+1 203 838 9158",
    "sg:postcode":"06854",
    "sg:province":"CT",
    "sg:tags":[
        "institution",
        "business"
    ],
    "wof:name":"Ionian Strategic Fund Ltd",
    "wof:placetype":"venue"
},
  "geometry": {"coordinates":[-73.44487700000001,41.091381],"type":"Point"}
}