{
  "type": "Feature",
  "properties": {
    "iso:country":"US",
    "sg:address":"6 Valley Rd",
    "sg:city":"Danbury",
    "sg:classifiers":[
        {
            "category":"Building & Trades",
            "subcategory":"Construction",
            "type":"Services"
        }
    ],
    "sg:phone":"+1 203 798 0667",
    "sg:postcode":"06811",
    "sg:province":"CT",
    "sg:tags":[
        "asphalt",
        "contractor",
        "sealcoating",
        "driveway",
        "road",
        "paving"
    ],
    "wof:name":"Garron & Pinet Asphalt Paving Co.",
    "wof:placetype":"venue"
},
  "geometry": {"coordinates":[-73.428588,41.443551],"type":"Point"}
}