{
  "type": "Feature",
  "properties": {
    "addr:full":"20 Middlesex Tpke Essex CT 06426",
    "addr:housenumber":"20",
    "addr:postcode":"06426",
    "addr:street":"Middlesex Tpke",
    "iso:country":"US",
    "sg:address":"20 Middlesex Tpke",
    "sg:city":"Essex",
    "sg:classifiers":[
        {
            "category":"Health Services",
            "subcategory":"Doctor",
            "type":"Services"
        }
    ],
    "sg:phone":"+1 860 767 4990",
    "sg:postcode":"06426",
    "sg:province":"CT",
    "sg:tags":[
        "dermatologist"
    ],
    "wof:name":"Essex Dermatology Center Llc",
    "wof:placetype":"venue"
},
  "geometry": {"coordinates":[-72.4002,41.349899],"type":"Point"}
}