{
  "type": "Feature",
  "properties": {
    "iso:country":"US",
    "sg:address":"55 Willow St",
    "sg:city":"Mystic",
    "sg:classifiers":[
        {
            "category":"Health Services",
            "subcategory":"Doctor",
            "type":"Services"
        }
    ],
    "sg:phone":"+1   ",
    "sg:postcode":"06355",
    "sg:province":"CT",
    "sg:tags":[
        "dermatologist"
    ],
    "wof:name":"Coastal Dermatology PC",
    "wof:placetype":"venue"
},
  "geometry": {"coordinates":[-71.968886,41.351811],"type":"Point"}
}