{
  "type": "Feature",
  "properties": {
    "iso:country":"US",
    "sg:address":"17 Cedar Crest Pl",
    "sg:city":"Norwalk",
    "sg:classifiers":[
        {
            "category":"Professional",
            "subcategory":"Management & Consulting",
            "type":"Services"
        }
    ],
    "sg:phone":"+1 203 866 9218",
    "sg:postcode":"06854",
    "sg:province":"CT",
    "sg:tags":[
        "marketing",
        "program",
        "direct",
        "business"
    ],
    "wof:name":"Game Plan Marketing LLC",
    "wof:placetype":"venue"
},
  "geometry": {"coordinates":[-73.436767,41.108139],"type":"Point"}
}