{
  "type": "Feature",
  "properties": {
    "iso:country":"US",
    "sg:address":"450 Capitol Ave",
    "sg:city":"Hartford",
    "sg:classifiers":[
        {
            "category":"Government",
            "subcategory":"Office",
            "type":"Public Place"
        }
    ],
    "sg:phone":"+1 860 418 6200",
    "sg:postcode":"06106",
    "sg:province":"CT",
    "sg:tags":[
        "administration",
        "general"
    ],
    "wof:name":"O P M",
    "wof:placetype":"venue"
},
  "geometry": {"coordinates":[-72.69119499999999,41.763685],"type":"Point"}
}