{
  "type": "Feature",
  "properties": {
    "addr:full":"775 Shuttle Meadow Rd Southington CT 06489",
    "addr:housenumber":"775",
    "addr:postcode":"06489",
    "addr:street":"Shuttle Meadow Rd",
    "iso:country":"US",
    "sg:address":"775 Shuttle Meadow Rd",
    "sg:city":"Southington",
    "sg:classifiers":[
        {
            "category":"Building & Trades",
            "subcategory":"Construction",
            "type":"Services"
        }
    ],
    "sg:phone":"+1 860 747 5675",
    "sg:postcode":"06489",
    "sg:province":"CT",
    "sg:tags":[
        "residential",
        "commercial",
        "contractor"
    ],
    "wof:name":"Buti Construction Inc",
    "wof:placetype":"venue"
},
  "geometry": {"coordinates":[-72.853723,41.649977],"type":"Point"}
}