{
  "type": "Feature",
  "properties": {
    "addr:full":"31 Dow Rd Plainfield CT 06374",
    "addr:housenumber":"31",
    "addr:postcode":"06374",
    "addr:street":"Dow Rd",
    "iso:country":"US",
    "sg:address":"31 Dow Rd",
    "sg:city":"Plainfield",
    "sg:classifiers":[
        {
            "category":"Health Services",
            "subcategory":"Doctor",
            "type":"Services"
        }
    ],
    "sg:phone":"+1   ",
    "sg:postcode":"06374",
    "sg:province":"CT",
    "sg:tags":[
        "medical"
    ],
    "wof:name":"North Estrn CT Cardiology Asso",
    "wof:placetype":"venue"
},
  "geometry": {"coordinates":[-71.91078899999999,41.669326],"type":"Point"}
}