{
  "type": "Feature",
  "properties": {
    "iso:country":"US",
    "sg:address":"24 Norwich Ave",
    "sg:city":"Norwich",
    "sg:classifiers":[
        {
            "category":"Food & Beverages",
            "subcategory":"Liquor & Beverages",
            "type":"Retail Goods"
        }
    ],
    "sg:phone":"+1 860 823 1266",
    "sg:postcode":"06360",
    "sg:province":"CT",
    "sg:tags":[
        "alcoholic"
    ],
    "wof:name":"Garys Wine & Spirit",
    "wof:placetype":"venue"
},
  "geometry": {"coordinates":[-72.051501,41.554446],"type":"Point"}
}