{
  "type": "Feature",
  "properties": {
    "addr:full":"789 Federal Rd Brookfield CT 06804",
    "addr:housenumber":"789",
    "addr:postcode":"06804",
    "addr:street":"Federal Rd",
    "iso:country":"US",
    "sg:address":"789 Federal Rd",
    "sg:city":"Brookfield",
    "sg:classifiers":[
        {
            "category":"Banks & Credit Unions",
            "subcategory":"Bank",
            "type":"Services"
        }
    ],
    "sg:phone":"+1 203 775 2506",
    "sg:postcode":"06804",
    "sg:province":"CT",
    "wof:name":"New Mil Bank",
    "wof:placetype":"venue"
},
  "geometry": {"coordinates":[-73.40876299999999,41.479418],"type":"Point"}
}