{
  "type": "Feature",
  "properties": {
    "iso:country":"US",
    "sg:address":"200 Merrow Rd",
    "sg:city":"Tolland",
    "sg:classifiers":[
        {
            "category":"Bars & Pubs",
            "type":"Food & Drink"
        },
        {
            "category":"Bars & Pubs",
            "subcategory":"Lounge",
            "type":"Food & Drink"
        },
        {
            "category":"Restaurant",
            "type":"Food & Drink"
        },
        {
            "category":"Bars & Pubs",
            "subcategory":"Sports Bar",
            "type":"Food & Drink"
        }
    ],
    "sg:phone":"+1 860 872 0332",
    "sg:postcode":"06084",
    "sg:province":"CT",
    "sg:tags":[
        "tavern",
        "grill",
        "cafeteria",
        "karaoke"
    ],
    "sg:website":"http://www.tavernhousegrill.com",
    "wof:name":"Tavern House Grill",
    "wof:placetype":"venue"
},
  "geometry": {"coordinates":[-72.352768,41.859989],"type":"Point"}
}