{
  "type": "Feature",
  "properties": {
    "addr:full":"93 W Main St Plainville CT 06062",
    "addr:housenumber":"93",
    "addr:postcode":"06062",
    "addr:street":"W Main St",
    "iso:country":"US",
    "sg:address":"93 W Main St",
    "sg:city":"Plainville",
    "sg:classifiers":[
        {
            "category":"Wholesale",
            "subcategory":"Wine & Distilled Alcoholic Beverages",
            "type":"Manufacturing & Wholesale Goods"
        }
    ],
    "sg:phone":"+1 860 793 1400",
    "sg:postcode":"06062",
    "sg:province":"CT",
    "wof:name":"Ace Distributing LLC",
    "wof:placetype":"venue"
},
  "geometry": {"coordinates":[-72.87127599999999,41.670272],"type":"Point"}
}