{
  "type": "Feature",
  "properties": {
    "iso:country":"US",
    "sg:address":"472 Wauregan Rd",
    "sg:city":"Danielson",
    "sg:classifiers":[
        {
            "category":"Professional",
            "type":"Services"
        }
    ],
    "sg:phone":"+1 860 774 5514",
    "sg:postcode":"06239",
    "sg:province":"CT",
    "wof:name":"Nemmco  LLC",
    "wof:placetype":"venue"
},
  "geometry": {"coordinates":[-71.897527,41.771357],"type":"Point"}
}