{
  "type": "Feature",
  "properties": {
    "iso:country":"US",
    "sg:address":"1055 Washington Boulevard Suite 400",
    "sg:city":"Stamford",
    "sg:classifiers":[
        {
            "category":"Professional",
            "subcategory":"Computer Services",
            "type":"Services"
        }
    ],
    "sg:phone":"+1 203 595 3200",
    "sg:postcode":"06901",
    "sg:province":"CT",
    "sg:website":"http://www.assetinternational.com",
    "wof:name":"Asset International",
    "wof:placetype":"venue"
},
  "geometry": {"coordinates":[-73.54273499999999,41.053547],"type":"Point"}
}