{
  "type": "Feature",
  "properties": {
    "iso:country":"US",
    "sg:address":"15 Cornerstone Ct",
    "sg:city":"Plantsville",
    "sg:classifiers":[
        {
            "category":"Health Services",
            "subcategory":"Doctor",
            "type":"Services"
        }
    ],
    "sg:phone":"+1   ",
    "sg:postcode":"06479",
    "sg:province":"CT",
    "wof:name":"Michael Reisman DDS",
    "wof:placetype":"venue"
},
  "geometry": {"coordinates":[-72.888406,41.588969],"type":"Point"}
}