{
  "type": "Feature",
  "properties": {
    "addr:full":"279 Main St Portland CT 06480",
    "addr:housenumber":"279",
    "addr:postcode":"06480",
    "addr:street":"Main St",
    "iso:country":"US",
    "sg:address":"279 Main St",
    "sg:city":"Portland",
    "sg:classifiers":[
        {
            "category":"Restaurant",
            "type":"Food & Drink"
        }
    ],
    "sg:phone":"+1 860 342 1516",
    "sg:postcode":"06480",
    "sg:province":"CT",
    "sg:tags":[
        "eating"
    ],
    "wof:name":"Athens Pizza",
    "wof:placetype":"venue"
},
  "geometry": {"coordinates":[-72.63753199999999,41.576929],"type":"Point"}
}