{
  "type": "Feature",
  "properties": {
    "addr:full":"80 Rimmon Rd Woodbridge CT 06525",
    "addr:housenumber":"80",
    "addr:postcode":"06525",
    "addr:street":"Rimmon Rd",
    "iso:country":"US",
    "sg:address":"80 Rimmon Rd",
    "sg:city":"Woodbridge",
    "sg:classifiers":[
        {
            "category":"Professional",
            "type":"Services"
        }
    ],
    "sg:phone":"+1 203 397 3566",
    "sg:postcode":"06525",
    "sg:province":"CT",
    "wof:name":"Robert Stepto",
    "wof:placetype":"venue"
},
  "geometry": {"coordinates":[-73.00408299999999,41.336887],"type":"Point"}
}