{
  "type": "Feature",
  "properties": {
    "addr:full":"23 Riverbank Rd Weston CT 06883",
    "addr:housenumber":"23",
    "addr:postcode":"06883",
    "addr:street":"Riverbank Rd",
    "iso:country":"US",
    "sg:address":"23 Riverbank Rd",
    "sg:city":"Weston",
    "sg:classifiers":[
        {
            "category":"Professional",
            "subcategory":"Management & Consulting",
            "type":"Services"
        }
    ],
    "sg:phone":"+1   ",
    "sg:postcode":"06883",
    "sg:province":"CT",
    "wof:name":"New World Consulting Inc",
    "wof:placetype":"venue"
},
  "geometry": {"coordinates":[-73.35138999999999,41.210004],"type":"Point"}
}