{
  "type": "Feature",
  "properties": {
    "iso:country":"US",
    "sg:address":"201 Talcottville Rd",
    "sg:city":"Vernon Rockville",
    "sg:classifiers":[
        {
            "category":"Health Services",
            "subcategory":"Chiropractor",
            "type":"Services"
        }
    ],
    "sg:phone":"+1   ",
    "sg:postcode":"06066",
    "sg:province":"CT",
    "wof:name":"Giacalone Dr David M DC",
    "wof:placetype":"venue"
},
  "geometry": {"coordinates":[-72.49120600000001,41.837569],"type":"Point"}
}