{
  "type": "Feature",
  "properties": {
    "iso:country":"US",
    "sg:address":"136 Main St",
    "sg:city":"Westport",
    "sg:classifiers":[
        {
            "category":"Professional",
            "subcategory":"Research",
            "type":"Services"
        }
    ],
    "sg:phone":"+1 203 454 0877",
    "sg:postcode":"06880",
    "sg:province":"CT",
    "sg:tags":[
        "radio",
        "program",
        "survey"
    ],
    "wof:name":"Emmis Communications Inc",
    "wof:placetype":"venue"
},
  "geometry": {"coordinates":[-73.36134300000001,41.141489],"type":"Point"}
}