{
  "type": "Feature",
  "properties": {
    "iso:country":"US",
    "sg:address":"34 Twixt Hills Rd",
    "sg:city":"Ridgefield",
    "sg:classifiers":[
        {
            "category":"Banks & Credit Unions",
            "subcategory":"Investment Brokerage",
            "type":"Services"
        }
    ],
    "sg:phone":"+1 203 431 3666",
    "sg:postcode":"06877",
    "sg:province":"CT",
    "sg:tags":[
        "security",
        "banker"
    ],
    "sg:website":"www.memhard.com",
    "wof:name":"Memhard Investment Banker Inc",
    "wof:placetype":"venue"
},
  "geometry": {"coordinates":[-73.50567599999999,41.329385],"type":"Point"}
}