{
  "type": "Feature",
  "properties": {
    "addr:full":"95 State St North Haven CT 06473",
    "addr:housenumber":"95",
    "addr:postcode":"06473",
    "addr:street":"State St;Haven",
    "iso:country":"US",
    "sg:address":"95 State St",
    "sg:city":"North Haven",
    "sg:classifiers":[
        {
            "category":"Manufacturing",
            "subcategory":"Printing",
            "type":"Manufacturing & Wholesale Goods"
        }
    ],
    "sg:phone":"+1 203 234 1472",
    "sg:postcode":"06473",
    "sg:province":"CT",
    "sg:tags":[
        "screen"
    ],
    "wof:name":"Creative Sportswear",
    "wof:placetype":"venue"
},
  "geometry": {"coordinates":[-72.874256,41.385963],"type":"Point"}
}