{
  "type": "Feature",
  "properties": {
    "addr:full":"2906 Main St Hartford CT 06120",
    "addr:housenumber":"2906",
    "addr:postcode":"06120",
    "addr:street":"Main St",
    "iso:country":"US",
    "sg:address":"2906 Main St",
    "sg:city":"Hartford",
    "sg:classifiers":[
        {
            "category":"Social Services",
            "type":"Services"
        }
    ],
    "sg:phone":"+1   ",
    "sg:postcode":"06120",
    "sg:province":"CT",
    "sg:tags":[
        "health"
    ],
    "wof:name":"Main St Psychological Assoc",
    "wof:placetype":"venue"
},
  "geometry": {"coordinates":[-72.667062,41.792795],"type":"Point"}
}