{
  "type": "Feature",
  "properties": {
    "addr:full":"5 Wigwam Ave Waterbury CT 06704",
    "addr:housenumber":"5",
    "addr:postcode":"06704",
    "addr:street":"Wigwam Ave",
    "iso:country":"US",
    "sg:address":"5 Wigwam Ave",
    "sg:city":"Waterbury",
    "sg:classifiers":[
        {
            "category":"Banks & Credit Unions",
            "subcategory":"Bank",
            "type":"Services"
        }
    ],
    "sg:phone":"+1 203 573 7914",
    "sg:postcode":"06704",
    "sg:province":"CT",
    "sg:website":"www.websterbank.com",
    "wof:name":"Webster Bank",
    "wof:placetype":"venue"
},
  "geometry": {"coordinates":[-73.035252,41.58358],"type":"Point"}
}