{
  "type": "Feature",
  "properties": {
    "addr:full":"2 Batterson Park Rd Farmington CT 06032",
    "addr:housenumber":"2",
    "addr:postcode":"06032",
    "addr:street":"Batterson Park Rd",
    "iso:country":"US",
    "sg:address":"2 Batterson Park Rd",
    "sg:city":"Farmington",
    "sg:classifiers":[
        {
            "category":"Professional",
            "subcategory":"Management & Consulting",
            "type":"Services"
        }
    ],
    "sg:phone":"+1   ",
    "sg:postcode":"06032",
    "sg:province":"CT",
    "sg:tags":[
        "consultant",
        "telecommunication"
    ],
    "wof:name":"Rand Associates Ltd",
    "wof:placetype":"venue"
},
  "geometry": {"coordinates":[-72.79433899999999,41.712514],"type":"Point"}
}