{
  "type": "Feature",
  "properties": {
    "addr:full":"69 Prange Rd Brookfield CT 06804",
    "addr:housenumber":"69",
    "addr:postcode":"06804",
    "addr:street":"Prange Rd",
    "iso:country":"US",
    "sg:address":"69 Prange Rd",
    "sg:city":"Brookfield",
    "sg:classifiers":[
        {
            "category":"Utilities",
            "subcategory":"Electric",
            "type":"Services"
        }
    ],
    "sg:phone":"+1 203 798 9787",
    "sg:postcode":"06804",
    "sg:province":"CT",
    "sg:tags":[
        "company"
    ],
    "wof:name":"P R Electrical Corp",
    "wof:placetype":"venue"
},
  "geometry": {"coordinates":[-73.431929,41.481844],"type":"Point"}
}