{
  "type": "Feature",
  "properties": {
    "iso:country":"US",
    "sg:address":"21 Robinswood Dr",
    "sg:city":"Wethersfield",
    "sg:classifiers":[
        {
            "category":"Professional",
            "subcategory":"Computer Services",
            "type":"Services"
        }
    ],
    "sg:phone":"+1   ",
    "sg:postcode":"06109",
    "sg:province":"CT",
    "sg:tags":[
        "related"
    ],
    "wof:name":"Maven Consultin",
    "wof:placetype":"venue"
},
  "geometry": {"coordinates":[-72.65051699999999,41.711284],"type":"Point"}
}