{
  "type": "Feature",
  "properties": {
    "iso:country":"US",
    "sg:address":"487 Burnside Ave",
    "sg:city":"East Hartford",
    "sg:classifiers":[
        {
            "category":"Food & Beverages",
            "subcategory":"Groceries & Convenience Stores",
            "type":"Retail Goods"
        }
    ],
    "sg:phone":"+1 860 528 8886",
    "sg:postcode":"06108",
    "sg:province":"CT",
    "wof:name":"Accra Market",
    "wof:placetype":"venue"
},
  "geometry": {"coordinates":[-72.620244,41.778119],"type":"Point"}
}