{
  "type": "Feature",
  "properties": {
    "addr:full":"357 Main St Old Saybrook CT 06475",
    "addr:housenumber":"357",
    "addr:postcode":"06475",
    "addr:street":"Main St",
    "iso:country":"US",
    "sg:address":"357 Main St",
    "sg:city":"Old Saybrook",
    "sg:classifiers":[
        {
            "category":"Professional",
            "subcategory":"Business Services",
            "type":"Services"
        }
    ],
    "sg:phone":"+1   ",
    "sg:postcode":"06475",
    "sg:province":"CT",
    "wof:name":"Kennedy Leonard Design",
    "wof:placetype":"venue"
},
  "geometry": {"coordinates":[-72.37449599999999,41.284642],"type":"Point"}
}