{
  "type": "Feature",
  "properties": {
    "addr:full":"340 Main St Norwich CT 06360",
    "addr:housenumber":"340",
    "addr:postcode":"06360",
    "addr:street":"Main St",
    "iso:country":"US",
    "sg:address":"340 Main St",
    "sg:city":"Norwich",
    "sg:classifiers":[
        {
            "category":"Government",
            "subcategory":"Post Office",
            "type":"Public Place"
        }
    ],
    "sg:phone":"+1 860 887 3559",
    "sg:postcode":"06360",
    "sg:province":"CT",
    "sg:tags":[
        "postal",
        "us"
    ],
    "wof:name":"US Post Office",
    "wof:placetype":"venue"
},
  "geometry": {"coordinates":[-72.07135599999999,41.52426],"type":"Point"}
}