{
  "type": "Feature",
  "properties": {
    "addr:full":"717 Wheelers Farm Rd Orange CT 06477",
    "addr:housenumber":"717",
    "addr:postcode":"06477",
    "addr:street":"Wheelers Farm Rd",
    "iso:country":"US",
    "sg:address":"717 Wheelers Farm Rd",
    "sg:city":"Orange",
    "sg:classifiers":[
        {
            "category":"Professional",
            "type":"Services"
        },
        {
            "category":"Retail",
            "subcategory":"Portrait Studio",
            "type":"Services"
        }
    ],
    "sg:phone":"+1 203 795 8651",
    "sg:postcode":"06477",
    "sg:province":"CT",
    "sg:tags":[
        "photo",
        "establishment"
    ],
    "wof:name":"Gregeiger Co Unlimited",
    "wof:placetype":"venue"
},
  "geometry": {"coordinates":[-73.056146,41.290576],"type":"Point"}
}