{
  "type": "Feature",
  "properties": {
    "iso:country":"US",
    "sg:address":"1960 Whitney Ave",
    "sg:city":"Hamden",
    "sg:classifiers":[
        {
            "category":"Professional",
            "subcategory":"Lawyer & Legal Services",
            "type":"Services"
        }
    ],
    "sg:phone":"+1   ",
    "sg:postcode":"06517",
    "sg:province":"CT",
    "wof:name":"Loughlin Fitzgerald Kamp Henri",
    "wof:placetype":"venue"
},
  "geometry": {"coordinates":[-72.906448,41.37082],"type":"Point"}
}