{
  "type": "Feature",
  "properties": {
    "addr:full":"82 Gorham St Oakville CT 06779",
    "addr:housenumber":"82",
    "addr:postcode":"06779",
    "addr:street":"Gorham St",
    "iso:country":"US",
    "sg:address":"82 Gorham St",
    "sg:city":"Oakville",
    "sg:classifiers":[
        {
            "category":"Health Services",
            "subcategory":"Health Practitioner",
            "type":"Services"
        }
    ],
    "sg:phone":"+1   ",
    "sg:postcode":"06779",
    "sg:province":"CT",
    "wof:name":"Margaret A Walker Rn",
    "wof:placetype":"venue"
},
  "geometry": {"coordinates":[-73.093141,41.60413],"type":"Point"}
}