{
  "type": "Feature",
  "properties": {
    "addr:full":"25 Admiral St Bridgeport CT 06605",
    "addr:housenumber":"25",
    "addr:postcode":"06605",
    "addr:street":"Admiral St",
    "iso:country":"US",
    "sg:address":"25 Admiral St",
    "sg:city":"Bridgeport",
    "sg:classifiers":[
        {
            "category":"Wholesale",
            "subcategory":"Machinery & Supplies",
            "type":"Manufacturing & Wholesale Goods"
        }
    ],
    "sg:phone":"+1 203 367 1211",
    "sg:postcode":"06605",
    "sg:province":"CT",
    "sg:tags":[
        "box",
        "packing",
        "crating"
    ],
    "wof:name":"J J Box Co",
    "wof:placetype":"venue"
},
  "geometry": {"coordinates":[-73.20081399999999,41.167451],"type":"Point"}
}