{
  "type": "Feature",
  "properties": {
    "iso:country":"US",
    "sg:address":"125 Crown St",
    "sg:city":"Fairfield",
    "sg:classifiers":[
        {
            "category":"Professional",
            "type":"Services"
        }
    ],
    "sg:phone":"+1 203 334 8280",
    "sg:postcode":"06450",
    "sg:province":"CT",
    "sg:tags":[
        "establishment"
    ],
    "wof:name":"Tidewater Group",
    "wof:placetype":"venue"
},
  "geometry": {"coordinates":[-72.80230299999999,41.535398],"type":"Point"}
}