{
  "type": "Feature",
  "properties": {
    "addr:full":"358 Scott Swamp Rd Farmington CT 06032",
    "addr:housenumber":"358",
    "addr:postcode":"06032",
    "addr:street":"Scott Swamp Rd",
    "iso:country":"US",
    "sg:address":"358 Scott Swamp Rd",
    "sg:city":"Farmington",
    "sg:classifiers":[
        {
            "category":"Ice Cream",
            "type":"Food & Drink"
        }
    ],
    "sg:phone":"+1 860 677 0880",
    "sg:postcode":"06032",
    "sg:province":"CT",
    "sg:tags":[
        "frozen",
        "yogurt"
    ],
    "sg:website":"www.ritasice.com",
    "wof:name":"Rita's",
    "wof:placetype":"venue"
},
  "geometry": {"coordinates":[-72.887873,41.702317],"type":"Point"}
}