{
  "type": "Feature",
  "properties": {
    "iso:country":"US",
    "sg:address":"109 Church St",
    "sg:city":"New Haven",
    "sg:classifiers":[
        {
            "category":"Government",
            "subcategory":"Police Station",
            "type":"Public Place"
        }
    ],
    "sg:phone":"+1 203 624 0700",
    "sg:postcode":"06510",
    "sg:province":"CT",
    "sg:tags":[
        "sheriff"
    ],
    "wof:name":"Norris H Horton",
    "wof:placetype":"venue"
},
  "geometry": {"coordinates":[-72.92601999999999,41.305452],"type":"Point"}
}