{
  "type": "Feature",
  "properties": {
    "iso:country":"US",
    "sg:address":"385 Orange St",
    "sg:city":"New Haven",
    "sg:classifiers":[
        {
            "category":"Professional",
            "subcategory":"Business Services",
            "type":"Services"
        }
    ],
    "sg:phone":"+1   ",
    "sg:postcode":"06511",
    "sg:province":"CT",
    "wof:name":"385 Orange Street Associates",
    "wof:placetype":"venue"
},
  "geometry": {"coordinates":[-72.919392,41.311777],"type":"Point"}
}