{
  "type": "Feature",
  "properties": {
    "addr:full":"440 Sackett Point Rd North Haven CT 06473",
    "addr:housenumber":"440",
    "addr:postcode":"06473",
    "addr:street":"Sackett Point Rd;Haven",
    "iso:country":"US",
    "sg:address":"440 Sackett Point Rd",
    "sg:city":"North Haven",
    "sg:classifiers":[
        {
            "category":"Retail",
            "subcategory":"Auto Repair",
            "type":"Services"
        }
    ],
    "sg:phone":"+1   ",
    "sg:postcode":"06473",
    "sg:province":"CT",
    "sg:tags":[
        "automotive"
    ],
    "wof:name":"Icon Equipment Distributors",
    "wof:placetype":"venue"
},
  "geometry": {"coordinates":[-72.881968,41.368216],"type":"Point"}
}