{
  "type": "Feature",
  "properties": {
    "addr:full":"82 Paper Mill Rd Fairfield CT 06419",
    "addr:housenumber":"82",
    "addr:postcode":"06419",
    "addr:street":"Paper Mill Rd",
    "iso:country":"US",
    "sg:address":"82 Paper Mill Rd",
    "sg:city":"Fairfield",
    "sg:classifiers":[
        {
            "category":"Building & Trades",
            "subcategory":"Construction",
            "type":"Services"
        }
    ],
    "sg:phone":"+1 203 319 9797",
    "sg:postcode":"06419",
    "sg:province":"CT",
    "sg:tags":[
        "excavation",
        "contractor"
    ],
    "wof:name":"Veno Excavating",
    "wof:placetype":"venue"
},
  "geometry": {"coordinates":[-72.592045,41.335567],"type":"Point"}
}