{
  "type": "Feature",
  "properties": {
    "iso:country":"US",
    "sg:address":"229 Grand Ave",
    "sg:city":"New Haven",
    "sg:classifiers":[
        {
            "category":"Organizations",
            "subcategory":"Community Association",
            "type":"Services"
        }
    ],
    "sg:phone":"+1 203 624 8669",
    "sg:postcode":"06513",
    "sg:province":"CT",
    "sg:tags":[
        "club"
    ],
    "wof:name":"Coamo Social Club",
    "wof:placetype":"venue"
},
  "geometry": {"coordinates":[-72.896388,41.309],"type":"Point"}
}