{
  "type": "Feature",
  "properties": {
    "addr:full":"1486 Albany Ave Hartford CT 06112",
    "addr:housenumber":"1486",
    "addr:postcode":"06112",
    "addr:street":"Albany Ave;Ct",
    "iso:country":"US",
    "sg:address":"1486 Albany Ave",
    "sg:city":"Hartford",
    "sg:classifiers":[
        {
            "category":"Bars & Pubs",
            "type":"Food & Drink"
        }
    ],
    "sg:phone":"+1 860 548 1221",
    "sg:postcode":"06112",
    "sg:province":"CT",
    "sg:tags":[
        "drinking"
    ],
    "wof:name":"V & TS Lounge",
    "wof:placetype":"venue"
},
  "geometry": {"coordinates":[-72.702713,41.784241],"type":"Point"}
}