{
  "type": "Feature",
  "properties": {
    "addr:full":"59 Clovelly Rd Stamford CT 06902",
    "addr:housenumber":"59",
    "addr:postcode":"06902",
    "addr:street":"Clovelly Rd",
    "iso:country":"US",
    "sg:address":"59 Clovelly Rd",
    "sg:city":"Stamford",
    "sg:classifiers":[
        {
            "category":"Building & Trades",
            "subcategory":"Construction",
            "type":"Services"
        }
    ],
    "sg:phone":"+1 203 325 3406",
    "sg:postcode":"06902",
    "sg:province":"CT",
    "sg:tags":[
        "house"
    ],
    "wof:name":"Lamberty Construction",
    "wof:placetype":"venue"
},
  "geometry": {"coordinates":[-73.523797,41.061044],"type":"Point"}
}