{
  "type": "Feature",
  "properties": {
    "iso:country":"US",
    "sg:address":"239 Main St",
    "sg:city":"Danielson",
    "sg:classifiers":[
        {
            "category":"Insurance",
            "subcategory":"Insurance Agent",
            "type":"Services"
        }
    ],
    "sg:phone":"+1 860 774 1389",
    "sg:postcode":"06239",
    "sg:province":"CT",
    "sg:tags":[
        "agency"
    ],
    "wof:name":"G A Macdonald Insurance Agency",
    "wof:placetype":"venue"
},
  "geometry": {"coordinates":[-71.88039000000001,41.808018],"type":"Point"}
}