{
  "type": "Feature",
  "properties": {
    "iso:country":"US",
    "sg:address":"48 N Main St",
    "sg:city":"Norwalk",
    "sg:classifiers":[
        {
            "category":"Restaurant",
            "type":"Food & Drink"
        }
    ],
    "sg:menulink":"http://www.allmenus.com/ct/norwalk/235034-roly-poly-sandwiches/menu/",
    "sg:phone":"+1 203 831 9981",
    "sg:postcode":"06854",
    "sg:province":"CT",
    "sg:tags":[
        "wrap",
        "american",
        "sandwich"
    ],
    "wof:name":"Roly Poly Sandwiches",
    "wof:placetype":"venue"
},
  "geometry": {"coordinates":[-73.419043,41.100217],"type":"Point"}
}