{
  "type": "Feature",
  "properties": {
    "addr:full":"1 Independence Way Danbury CT 06810",
    "addr:housenumber":"1",
    "addr:postcode":"06810",
    "addr:street":"Independence Way",
    "iso:country":"US",
    "sg:address":"1 Independence Way",
    "sg:city":"Danbury",
    "sg:classifiers":[
        {
            "category":"Sports & Exercise",
            "subcategory":"Ice Rink",
            "type":"Entertainment"
        }
    ],
    "sg:phone":"+1 203 794 1704",
    "sg:postcode":"06810",
    "sg:province":"CT",
    "sg:tags":[
        "skating",
        "rinks-ice"
    ],
    "sg:website":"http://www.danburyice.com",
    "wof:name":"Danbury Ice Arena",
    "wof:placetype":"venue"
},
  "geometry": {"coordinates":[-73.450401,41.395809],"type":"Point"}
}