{
  "type": "Feature",
  "properties": {
    "addr:full":"230 Mill St Greenwich CT 06830",
    "addr:housenumber":"230",
    "addr:postcode":"06830",
    "addr:street":"Mill St Greenwich Ct",
    "iso:country":"US",
    "sg:address":"230 Mill St",
    "sg:city":"Greenwich",
    "sg:classifiers":[
        {
            "category":"Professional",
            "subcategory":"Management & Consulting",
            "type":"Services"
        },
        {
            "category":"Professional",
            "subcategory":"Advertising",
            "type":"Services"
        }
    ],
    "sg:phone":"+1 203 531 6600",
    "sg:postcode":"06830",
    "sg:province":"CT",
    "sg:tags":[
        "marketing",
        "program",
        "planning",
        "medium",
        "buying"
    ],
    "wof:name":"Media Dynamics",
    "wof:placetype":"venue"
},
  "geometry": {"coordinates":[-73.657556,41.00362],"type":"Point"}
}