{
  "type": "Feature",
  "properties": {
    "addr:full":"730 Elm St Rocky Hill CT 06067",
    "addr:housenumber":"730",
    "addr:postcode":"06067",
    "addr:street":"Elm St",
    "iso:country":"US",
    "sg:address":"730 Elm St",
    "sg:city":"Rocky Hill",
    "sg:classifiers":[
        {
            "category":"Farming",
            "subcategory":"Farm",
            "type":"Manufacturing & Wholesale Goods"
        }
    ],
    "sg:phone":"+1 860 571 0373",
    "sg:postcode":"06067",
    "sg:province":"CT",
    "sg:tags":[
        "crop",
        "general"
    ],
    "wof:name":"Gilbert Farm",
    "wof:placetype":"venue"
},
  "geometry": {"coordinates":[-72.663498,41.659976],"type":"Point"}
}