{
  "type": "Feature",
  "properties": {
    "iso:country":"US",
    "sg:address":"36 Mulberry St",
    "sg:city":"Ridgefield",
    "sg:classifiers":[
        {
            "category":"Shopping",
            "subcategory":"Gifts & Souvenirs",
            "type":"Retail Goods"
        }
    ],
    "sg:phone":"+1   ",
    "sg:postcode":"06877",
    "sg:province":"CT",
    "sg:tags":[
        "product",
        "wood",
        "mfg"
    ],
    "wof:name":"Kari Lonning Designer",
    "wof:placetype":"venue"
},
  "geometry": {"coordinates":[-73.513982,41.291837],"type":"Point"}
}