{
  "type": "Feature",
  "properties": {
    "addr:full":"18 Orehill Rd New Fairfield CT 06812",
    "addr:housenumber":"18",
    "addr:postcode":"06812",
    "addr:street":"Orehill Rd;Fairfield Ct",
    "iso:country":"US",
    "sg:address":"18 Orehill Rd",
    "sg:city":"New Fairfield",
    "sg:classifiers":[
        {
            "category":"Building & Trades",
            "subcategory":"Cleaning & Sanitation",
            "type":"Services"
        }
    ],
    "sg:phone":"+1 203 746 8559",
    "sg:postcode":"06812",
    "sg:province":"CT",
    "sg:tags":[
        "window"
    ],
    "wof:name":"Brite-Way Window Cleaning",
    "wof:placetype":"venue"
},
  "geometry": {"coordinates":[-73.531983,41.46013],"type":"Point"}
}