{
  "type": "Feature",
  "properties": {
    "addr:full":"141 West St Simsbury CT 06070",
    "addr:housenumber":"141",
    "addr:postcode":"06070",
    "addr:street":"West St Simsbury Ct",
    "iso:country":"US",
    "sg:address":"141 West St",
    "sg:city":"Simsbury",
    "sg:classifiers":[
        {
            "category":"Shopping",
            "type":"Retail Goods"
        }
    ],
    "sg:phone":"+1 860 658 0338",
    "sg:postcode":"06070",
    "sg:province":"CT",
    "sg:tags":[
        "merchandise"
    ],
    "wof:name":"Corner Cupboard Country Store",
    "wof:placetype":"venue"
},
  "geometry": {"coordinates":[-72.817998,41.869795],"type":"Point"}
}