{
  "type": "Feature",
  "properties": {
    "addr:full":"163 Tall Timbers Rd Glastonbury CT 06033",
    "addr:housenumber":"163",
    "addr:postcode":"06033",
    "addr:street":"Tall Timbers Rd",
    "iso:country":"US",
    "sg:address":"163 Tall Timbers Rd",
    "sg:city":"Glastonbury",
    "sg:classifiers":[
        {
            "category":"Professional",
            "subcategory":"Employment Agencies",
            "type":"Services"
        }
    ],
    "sg:phone":"+1   ",
    "sg:postcode":"06033",
    "sg:province":"CT",
    "wof:name":"East Coast Search LLC",
    "wof:placetype":"venue"
},
  "geometry": {"coordinates":[-72.581227,41.68983],"type":"Point"}
}