{
  "type": "Feature",
  "properties": {
    "iso:country":"US",
    "sg:address":"199 Sound Beach Ave",
    "sg:city":"Old Greenwich",
    "sg:classifiers":[
        {
            "category":"Building & Trades",
            "subcategory":"Landscaping Services",
            "type":"Services"
        }
    ],
    "sg:phone":"+1 203 637 2718",
    "sg:postcode":"06870",
    "sg:province":"CT",
    "sg:tags":[
        "designer",
        "landscape"
    ],
    "wof:name":"Rutherford Associates PC",
    "wof:placetype":"venue"
},
  "geometry": {"coordinates":[-73.56806899999999,41.031894],"type":"Point"}
}