{
  "type": "Feature",
  "properties": {
    "iso:country":"US",
    "sg:address":"89 Bassick Rd",
    "sg:city":"Trumbull",
    "sg:classifiers":[
        {
            "category":"Real Estate",
            "subcategory":"Surveying",
            "type":"Services"
        }
    ],
    "sg:phone":"+1   ",
    "sg:postcode":"06611",
    "sg:province":"CT",
    "wof:name":"Ted Kozlowski LLC",
    "wof:placetype":"venue"
},
  "geometry": {"coordinates":[-73.226392,41.243634],"type":"Point"}
}