{
  "type": "Feature",
  "properties": {
    "iso:country":"US",
    "sg:address":"63 Ralsey Rd",
    "sg:city":"Stamford",
    "sg:classifiers":[
        {
            "category":"Professional",
            "subcategory":"Business Services",
            "type":"Services"
        }
    ],
    "sg:phone":"+1   ",
    "sg:postcode":"06902",
    "sg:province":"CT",
    "sg:tags":[
        "estimator",
        "purchasing"
    ],
    "wof:name":"Baker Residential Ltd Partnr",
    "wof:placetype":"venue"
},
  "geometry": {"coordinates":[-73.53127499999999,41.032031],"type":"Point"}
}