{
  "type": "Feature",
  "properties": {
    "addr:full":"1 Bailey Dr Guilford CT 06437",
    "addr:housenumber":"1",
    "addr:postcode":"06437",
    "addr:street":"Bailey Dr",
    "iso:country":"US",
    "sg:address":"1 Bailey Dr",
    "sg:city":"Guilford",
    "sg:classifiers":[
        {
            "category":"Manufacturing",
            "subcategory":"Electronics",
            "type":"Manufacturing & Wholesale Goods"
        }
    ],
    "sg:phone":"+1 203 458 2646",
    "sg:postcode":"06437",
    "sg:province":"CT",
    "sg:tags":[
        "equipment",
        "mfg",
        "home"
    ],
    "wof:name":"Alarmco",
    "wof:placetype":"venue"
},
  "geometry": {"coordinates":[-72.713054,41.307671],"type":"Point"}
}