{
  "type": "Feature",
  "properties": {
    "addr:full":"224 New London Tpke Glastonbury CT 06033",
    "addr:housenumber":"224",
    "addr:postcode":"06033",
    "addr:street":"New London Tpke",
    "iso:country":"US",
    "sg:address":"224 New London Tpke",
    "sg:city":"Glastonbury",
    "sg:classifiers":[
        {
            "category":"Professional",
            "subcategory":"Management & Consulting",
            "type":"Services"
        }
    ],
    "sg:phone":"+1 860 652 9227",
    "sg:postcode":"06033",
    "sg:province":"CT",
    "sg:tags":[
        "advisory",
        "investment"
    ],
    "wof:name":"American Express",
    "wof:placetype":"venue"
},
  "geometry": {"coordinates":[-72.602632,41.70915],"type":"Point"}
}