{
  "type": "Feature",
  "properties": {
    "addr:full":"868 Clintonville Rd Wallingford CT 06492",
    "addr:housenumber":"868",
    "addr:postcode":"06492",
    "addr:street":"Clintonville Rd",
    "iso:country":"US",
    "sg:address":"868 Clintonville Rd",
    "sg:city":"Wallingford",
    "sg:classifiers":[
        {
            "category":"Building & Trades",
            "subcategory":"Construction",
            "type":"Services"
        }
    ],
    "sg:phone":"+1 203 265 7690",
    "sg:postcode":"06492",
    "sg:province":"CT",
    "sg:tags":[
        "new",
        "general",
        "ho",
        "contractor"
    ],
    "wof:name":"Artistic Construction L L C",
    "wof:placetype":"venue"
},
  "geometry": {"coordinates":[-72.824399,41.41566],"type":"Point"}
}