{
  "type": "Feature",
  "properties": {
    "iso:country":"US",
    "sg:address":"3015 High Ridge Rd",
    "sg:city":"Stamford",
    "sg:classifiers":[
        {
            "category":"Professional",
            "type":"Services"
        }
    ],
    "sg:phone":"+1   ",
    "sg:postcode":"06903",
    "sg:province":"CT",
    "wof:name":"James Knowles & Co",
    "wof:placetype":"venue"
},
  "geometry": {"coordinates":[-73.563208,41.170846],"type":"Point"}
}