{
  "type": "Feature",
  "properties": {
    "addr:full":"185 Research Dr Milford CT 06460",
    "addr:housenumber":"185",
    "addr:postcode":"06460",
    "addr:street":"Research Dr",
    "iso:country":"US",
    "sg:address":"185 Research Dr",
    "sg:city":"Milford",
    "sg:classifiers":[
        {
            "category":"Professional",
            "subcategory":"Research",
            "type":"Services"
        }
    ],
    "sg:phone":"+1 203 878 7411",
    "sg:postcode":"06460",
    "sg:province":"CT",
    "sg:tags":[
        "development",
        "product",
        "scientific",
        "g",
        "mfg",
        "marketing",
        "electrophoresis",
        "biotechnology"
    ],
    "wof:name":"Jule Biotechnologies Inc",
    "wof:placetype":"venue"
},
  "geometry": {"coordinates":[-73.010468,41.242175],"type":"Point"}
}