{
  "type": "Feature",
  "properties": {
    "addr:full":"1 Shaws Cove New London CT 06320",
    "addr:housenumber":"1",
    "addr:postcode":"06320",
    "addr:street":"Shaws Cove New London Ct",
    "iso:country":"US",
    "sg:address":"1 Shaws Cove",
    "sg:city":"New London",
    "sg:classifiers":[
        {
            "category":"Health Services",
            "subcategory":"Clinic",
            "type":"Services"
        }
    ],
    "sg:phone":"+1   ",
    "sg:postcode":"06320",
    "sg:province":"CT",
    "sg:tags":[
        "out",
        "care",
        "patient",
        "primary",
        "facility"
    ],
    "wof:name":"Community Hlth Ctr New London",
    "wof:placetype":"venue"
},
  "geometry": {"coordinates":[-72.100736,41.347256],"type":"Point"}
}