{
  "type": "Feature",
  "properties": {
    "iso:country":"US",
    "sg:address":"3265 Whitney Ave",
    "sg:city":"Hamden",
    "sg:classifiers":[
        {
            "category":"Banks & Credit Unions",
            "subcategory":"Bank",
            "type":"Services"
        }
    ],
    "sg:phone":"+1 203 288 2515",
    "sg:postcode":"06518",
    "sg:province":"CT",
    "sg:tags":[
        "loan",
        "real estate"
    ],
    "wof:name":"Mortgage Executives",
    "wof:placetype":"venue"
},
  "geometry": {"coordinates":[-72.901096,41.411371],"type":"Point"}
}