{
  "type": "Feature",
  "properties": {
    "addr:full":"89 Rivergate Dr Wilton CT 06897",
    "addr:housenumber":"89",
    "addr:postcode":"06897",
    "addr:street":"Rivergate Dr",
    "iso:country":"US",
    "sg:address":"89 Rivergate Dr",
    "sg:city":"Wilton",
    "sg:classifiers":[
        {
            "category":"Organizations",
            "subcategory":"Community Association",
            "type":"Services"
        }
    ],
    "sg:phone":"+1   ",
    "sg:postcode":"06897",
    "sg:province":"CT",
    "wof:name":"Kiwanis International",
    "wof:placetype":"venue"
},
  "geometry": {"coordinates":[-73.39015499999999,41.183384],"type":"Point"}
}