{
  "type": "Feature",
  "properties": {
    "iso:country":"US",
    "sg:address":"112 Canton Rd",
    "sg:city":"Granby",
    "sg:classifiers":[
        {
            "category":"Professional",
            "subcategory":"Business Services",
            "type":"Services"
        }
    ],
    "sg:phone":"+1   ",
    "sg:postcode":"06035",
    "sg:province":"CT",
    "wof:name":"Aircraft Engravers",
    "wof:placetype":"venue"
},
  "geometry": {"coordinates":[-72.80379499999999,41.928602],"type":"Point"}
}