{
  "type": "Feature",
  "properties": {
    "iso:country":"US",
    "sg:address":"1250 Summer St",
    "sg:city":"Stamford",
    "sg:classifiers":[
        {
            "category":"Shopping",
            "subcategory":"Computers & Home Electronics",
            "type":"Retail Goods"
        }
    ],
    "sg:phone":"+1 203 323 0042",
    "sg:postcode":"06905",
    "sg:province":"CT",
    "sg:tags":[
        "equipment",
        "satellite",
        "system"
    ],
    "sg:website":"www.newtecamerica.com",
    "wof:name":"Newtec America Inc",
    "wof:placetype":"venue"
},
  "geometry": {"coordinates":[-73.541031,41.060705],"type":"Point"}
}