{
  "type": "Feature",
  "properties": {
    "addr:full":"358 Springside Ave New Haven CT 06515",
    "addr:housenumber":"358",
    "addr:postcode":"06515",
    "addr:street":"Springside Ave",
    "iso:country":"US",
    "sg:address":"358 Springside Ave",
    "sg:city":"New Haven",
    "sg:classifiers":[
        {
            "category":"Government",
            "subcategory":"Office",
            "type":"Public Place"
        }
    ],
    "sg:phone":"+1 203 389 4333",
    "sg:postcode":"06515",
    "sg:province":"CT",
    "sg:tags":[
        "foundation",
        "education"
    ],
    "wof:name":"New Haven Ecology Project Inc",
    "wof:placetype":"venue"
},
  "geometry": {"coordinates":[-72.95854799999999,41.336236],"type":"Point"}
}