{
  "type": "Feature",
  "properties": {
    "addr:full":"125 Elm St New Canaan NY 06840",
    "addr:housenumber":"125",
    "addr:postcode":"06840",
    "addr:street":"Elm St",
    "iso:country":"US",
    "sg:address":"125 Elm St",
    "sg:city":"New Canaan",
    "sg:classifiers":[
        {
            "category":"Banks & Credit Unions",
            "subcategory":"Investment Brokerage",
            "type":"Services"
        }
    ],
    "sg:phone":"+1 203 972 8605",
    "sg:postcode":"06840",
    "sg:province":"NY",
    "sg:tags":[
        "consultant",
        "planning",
        "financial"
    ],
    "wof:name":"Westbrook Financial Advisers",
    "wof:placetype":"venue"
},
  "geometry": {"coordinates":[-73.494111,41.146877],"type":"Point"}
}