{
  "type": "Feature",
  "properties": {
    "iso:country":"US",
    "sg:address":"73 High St",
    "sg:city":"Derby",
    "sg:classifiers":[
        {
            "category":"Organizations",
            "subcategory":"Community Association",
            "type":"Services"
        }
    ],
    "sg:phone":"+1 203 734 9829",
    "sg:postcode":"06418",
    "sg:province":"CT",
    "sg:tags":[
        "fraternal"
    ],
    "wof:name":"Sons Of Italy",
    "wof:placetype":"venue"
},
  "geometry": {"coordinates":[-73.07673200000001,41.31489],"type":"Point"}
}