{
  "type": "Feature",
  "properties": {
    "iso:country":"US",
    "sg:address":"108 Liberty St",
    "sg:city":"Newington",
    "sg:classifiers":[
        {
            "category":"Retail",
            "subcategory":"Repair Shop",
            "type":"Services"
        }
    ],
    "sg:phone":"+1   ",
    "sg:postcode":"06111",
    "sg:province":"CT",
    "sg:tags":[
        "electrical"
    ],
    "wof:name":"Guilmartin Electric Motor LLC",
    "wof:placetype":"venue"
},
  "geometry": {"coordinates":[-72.74793699999999,41.684321],"type":"Point"}
}