{
  "type": "Feature",
  "properties": {
    "iso:country":"US",
    "sg:address":"4 Brookdale St",
    "sg:city":"Wolcott",
    "sg:classifiers":[
        {
            "category":"Education",
            "subcategory":"Dance Studio",
            "type":"Public Place"
        }
    ],
    "sg:phone":"+1 203 879 0312",
    "sg:postcode":"06716",
    "sg:province":"CT",
    "sg:tags":[
        "instruction",
        "dancing"
    ],
    "wof:name":"Studio 1 Dance Center",
    "wof:placetype":"venue"
},
  "geometry": {"coordinates":[-72.989886,41.604086],"type":"Point"}
}