{
  "type": "Feature",
  "properties": {
    "iso:country":"US",
    "sg:address":"6 Highfield Dr",
    "sg:city":"Trumbull",
    "sg:classifiers":[
        {
            "category":"Professional",
            "subcategory":"Business Services",
            "type":"Services"
        }
    ],
    "sg:phone":"+1   ",
    "sg:postcode":"06611",
    "sg:province":"CT",
    "wof:name":"Wolfe Group LLC",
    "wof:placetype":"venue"
},
  "geometry": {"coordinates":[-73.243285,41.256911],"type":"Point"}
}