{
  "type": "Feature",
  "properties": {
    "addr:full":"1 Ethan Allen Hwy Ridgefield CT 06877",
    "addr:housenumber":"1",
    "addr:postcode":"06877",
    "addr:street":"Ethan Allen Hwy Ridgefield Ct",
    "iso:country":"US",
    "sg:address":"1 Ethan Allen Hwy",
    "sg:city":"Ridgefield",
    "sg:classifiers":[
        {
            "category":"Health Services",
            "subcategory":"Medical Lab",
            "type":"Services"
        }
    ],
    "sg:phone":"+1 203 544 9535",
    "sg:postcode":"06877",
    "sg:province":"CT",
    "sg:tags":[
        "laboratory"
    ],
    "wof:name":"Mandell Dental Laboratory",
    "wof:placetype":"venue"
},
  "geometry": {"coordinates":[-73.440642,41.265045],"type":"Point"}
}