{
  "type": "Feature",
  "properties": {
    "addr:full":"171 E Mountain Rd Waterbury CT 06706",
    "addr:housenumber":"171",
    "addr:postcode":"06706",
    "addr:street":"E Mountain Rd",
    "iso:country":"US",
    "sg:address":"171 E Mountain Rd",
    "sg:city":"Waterbury",
    "sg:classifiers":[
        {
            "category":"Restaurant",
            "type":"Food & Drink"
        }
    ],
    "sg:phone":"+1 203 754 0277",
    "sg:postcode":"06706",
    "sg:province":"CT",
    "wof:name":"19th Hole Cafe",
    "wof:placetype":"venue"
},
  "geometry": {"coordinates":[-73.013679,41.5275],"type":"Point"}
}