{
  "type": "Feature",
  "properties": {
    "iso:country":"US",
    "sg:address":"500 Monroe Tpke",
    "sg:city":"Monroe",
    "sg:classifiers":[
        {
            "category":"Local Transit",
            "type":"Transportation"
        }
    ],
    "sg:phone":"+1 203 261 8880",
    "sg:postcode":"06468",
    "sg:province":"CT",
    "sg:tags":[
        "limousine"
    ],
    "wof:name":"Joseph's Five Star Limousine",
    "wof:placetype":"venue"
},
  "geometry": {"coordinates":[-73.21850499999999,41.314209],"type":"Point"}
}