{
  "type": "Feature",
  "properties": {
    "addr:full":"20 Founders Ln Monroe CT 06468",
    "addr:housenumber":"20",
    "addr:postcode":"06468",
    "addr:street":"Founders Ln",
    "iso:country":"US",
    "sg:address":"20 Founders Ln",
    "sg:city":"Monroe",
    "sg:classifiers":[
        {
            "category":"Building & Trades",
            "subcategory":"Construction",
            "type":"Services"
        }
    ],
    "sg:phone":"+1 203 261 3345",
    "sg:postcode":"06468",
    "sg:province":"CT",
    "sg:tags":[
        "company"
    ],
    "wof:name":"Bienashski Construction Co",
    "wof:placetype":"venue"
},
  "geometry": {"coordinates":[-73.21327100000001,41.330603],"type":"Point"}
}