{
  "type": "Feature",
  "properties": {
    "addr:full":"406 Lowell Davis Rd North Grosvenordale CT 06255",
    "addr:housenumber":"406",
    "addr:postcode":"06255",
    "addr:street":"Lowell Davis Rd;Grosvenordale",
    "iso:country":"US",
    "sg:address":"406 Lowell Davis Rd",
    "sg:city":"North Grosvenordale",
    "sg:classifiers":[
        {
            "category":"Food & Beverages",
            "subcategory":"Liquor & Beverages",
            "type":"Retail Goods"
        }
    ],
    "sg:phone":"+1 860 923 6987",
    "sg:postcode":"06255",
    "sg:province":"CT",
    "sg:tags":[
        "alcoholic"
    ],
    "wof:name":"Hidden Wine LLC",
    "wof:placetype":"venue"
},
  "geometry": {"coordinates":[-71.861791,42.008486],"type":"Point"}
}