{
  "type": "Feature",
  "properties": {
    "iso:country":"US",
    "sg:address":"41 Sportsman Hill Rd",
    "sg:city":"Madison",
    "sg:classifiers":[
        {
            "category":"Professional",
            "subcategory":"Accounting & Tax Preparation",
            "type":"Services"
        }
    ],
    "sg:phone":"+1 203 245 3004",
    "sg:postcode":"06443",
    "sg:province":"CT",
    "sg:tags":[
        "accountant"
    ],
    "wof:name":"E K Williams & Company",
    "wof:placetype":"venue"
},
  "geometry": {"coordinates":[-72.596484,41.292823],"type":"Point"}
}