{
  "type": "Feature",
  "properties": {
    "addr:full":"1412 Park Ave Bridgeport CT 06604",
    "addr:housenumber":"1412",
    "addr:postcode":"06604",
    "addr:street":"Park Ave",
    "iso:country":"US",
    "sg:address":"1412 Park Ave",
    "sg:city":"Bridgeport",
    "sg:classifiers":[
        {
            "category":"Retail",
            "subcategory":"Auto Repair",
            "type":"Services"
        }
    ],
    "sg:phone":"+1 203 333 0355",
    "sg:postcode":"06604",
    "sg:province":"CT",
    "sg:tags":[
        "repairing",
        "exhaust",
        "general",
        "automobile"
    ],
    "wof:name":"A American Muffler & Brake Sho",
    "wof:placetype":"venue"
},
  "geometry": {"coordinates":[-73.202648,41.179203],"type":"Point"}
}