{
  "type": "Feature",
  "properties": {
    "addr:full":"888 Summer Hill Rd Madison CT 06443",
    "addr:housenumber":"888",
    "addr:postcode":"06443",
    "addr:street":"Summer Hill Rd",
    "iso:country":"US",
    "sg:address":"888 Summer Hill Rd",
    "sg:city":"Madison",
    "sg:classifiers":[
        {
            "category":"Wholesale",
            "subcategory":"Plants",
            "type":"Manufacturing & Wholesale Goods"
        }
    ],
    "sg:phone":"+1 203 421 3055",
    "sg:postcode":"06443",
    "sg:province":"CT",
    "sg:tags":[
        "nursery",
        "tree"
    ],
    "sg:website":"www.summerhillnursery.com",
    "wof:name":"Summer Hill Nursery Inc",
    "wof:placetype":"venue"
},
  "geometry": {"coordinates":[-72.624152,41.374888],"type":"Point"}
}