{
  "type": "Feature",
  "properties": {
    "iso:country":"US",
    "sg:address":"1 Grist Mill Rd",
    "sg:city":"Simsbury",
    "sg:classifiers":[
        {
            "category":"Insurance",
            "subcategory":"Insurance Agent",
            "type":"Services"
        }
    ],
    "sg:phone":"+1 860 651 6256",
    "sg:postcode":"06070",
    "sg:province":"CT",
    "wof:name":"Ebenefits Group",
    "wof:placetype":"venue"
},
  "geometry": {"coordinates":[-72.812962,41.869375],"type":"Point"}
}