{
  "type": "Feature",
  "properties": {
    "iso:country":"US",
    "sg:address":"425 Main St",
    "sg:city":"Durham",
    "sg:classifiers":[
        {
            "category":"Personal",
            "subcategory":"Barber",
            "type":"Services"
        }
    ],
    "sg:phone":"+1   ",
    "sg:postcode":"06422",
    "sg:province":"CT",
    "sg:tags":[
        "shop"
    ],
    "wof:name":"Thee Razors Edge",
    "wof:placetype":"venue"
},
  "geometry": {"coordinates":[-72.68096799999999,41.48952],"type":"Point"}
}