{
  "type": "Feature",
  "properties": {
    "addr:full":"264 W Putnam Ave Greenwich CT 06830",
    "addr:housenumber":"264",
    "addr:postcode":"06830",
    "addr:street":"W Putnam Ave",
    "iso:country":"US",
    "sg:address":"264 W Putnam Ave",
    "sg:city":"Greenwich",
    "sg:classifiers":[
        {
            "category":"Shopping",
            "subcategory":"Computers & Home Electronics",
            "type":"Retail Goods"
        }
    ],
    "sg:phone":"+1 203 661 0234",
    "sg:postcode":"06830",
    "sg:province":"CT",
    "sg:tags":[
        "stereo",
        "for",
        "car",
        "player",
        "tape",
        "recorder"
    ],
    "wof:name":"Auto Sound LTD",
    "wof:placetype":"venue"
},
  "geometry": {"coordinates":[-73.635639,41.024268],"type":"Point"}
}