{
  "type": "Feature",
  "properties": {
    "iso:country":"US",
    "sg:address":"1060 Bridgeport Ave",
    "sg:city":"Milford",
    "sg:classifiers":[
        {
            "category":"Retail",
            "subcategory":"Auto Rental",
            "type":"Services"
        }
    ],
    "sg:phone":"+1   ",
    "sg:postcode":"06460",
    "sg:province":"CT",
    "sg:tags":[
        "passenger",
        "car"
    ],
    "wof:name":"Rent-A-Wreck",
    "wof:placetype":"venue"
},
  "geometry": {"coordinates":[-73.068455,41.216927],"type":"Point"}
}