{
  "type": "Feature",
  "properties": {
    "addr:full":"10 Eagle Rock Hill Bethel CT 06801",
    "addr:housenumber":"10",
    "addr:postcode":"06801",
    "addr:street":"Eagle Rock Hill Bethel Ct",
    "iso:country":"US",
    "sg:address":"10 Eagle Rock Hill",
    "sg:city":"Bethel",
    "sg:classifiers":[
        {
            "category":"Professional",
            "subcategory":"Business Services",
            "type":"Services"
        }
    ],
    "sg:phone":"+1   ",
    "sg:postcode":"06801",
    "sg:province":"CT",
    "sg:tags":[
        "computer",
        "broker"
    ],
    "wof:name":"Gbrl Corporation",
    "wof:placetype":"venue"
},
  "geometry": {"coordinates":[-73.408399,41.381608],"type":"Point"}
}