{
  "type": "Feature",
  "properties": {
    "addr:full":"190 Weston Rd Weston CT 06883",
    "addr:housenumber":"190",
    "addr:postcode":"06883",
    "addr:street":"Weston Rd",
    "iso:country":"US",
    "sg:address":"190 Weston Rd",
    "sg:city":"Weston",
    "sg:classifiers":[
        {
            "category":"Government",
            "subcategory":"Post Office",
            "type":"Public Place"
        }
    ],
    "sg:phone":"+1 203 227 1605",
    "sg:postcode":"06883",
    "sg:province":"CT",
    "sg:website":"www.usps.com",
    "wof:name":"US Post Office",
    "wof:placetype":"venue"
},
  "geometry": {"coordinates":[-73.382012,41.202628],"type":"Point"}
}