{
  "type": "Feature",
  "properties": {
    "addr:full":"30 Fabyan Rd North Grosvenordale CT 06255",
    "addr:housenumber":"30",
    "addr:postcode":"06255",
    "addr:street":"Fabyan Rd;Grosvenordale",
    "iso:country":"US",
    "sg:address":"30 Fabyan Rd",
    "sg:city":"North Grosvenordale",
    "sg:classifiers":[
        {
            "category":"Retail",
            "subcategory":"Car Wash",
            "type":"Services"
        }
    ],
    "sg:phone":"+1   ",
    "sg:postcode":"06255",
    "sg:province":"CT",
    "sg:tags":[
        "carwash"
    ],
    "wof:name":"D&L Car Wash & Laundromat",
    "wof:placetype":"venue"
},
  "geometry": {"coordinates":[-71.922391,41.985296],"type":"Point"}
}