{
  "type": "Feature",
  "properties": {
    "addr:full":"27 Bonnie Dr Farmington CT 06032",
    "addr:housenumber":"27",
    "addr:postcode":"06032",
    "addr:street":"Bonnie Dr",
    "iso:country":"US",
    "sg:address":"27 Bonnie Dr",
    "sg:city":"Farmington",
    "sg:classifiers":[
        {
            "category":"Real Estate",
            "subcategory":"Real Estate Agent",
            "type":"Services"
        }
    ],
    "sg:phone":"+1 860 677 9415",
    "sg:postcode":"06032",
    "sg:province":"CT",
    "wof:name":"Farm-West Building Management",
    "wof:placetype":"venue"
},
  "geometry": {"coordinates":[-72.811027,41.704775],"type":"Point"}
}