{
  "type": "Feature",
  "properties": {
    "iso:country":"US",
    "sg:address":"71 New St",
    "sg:city":"Naugatuck",
    "sg:classifiers":[
        {
            "category":"Professional",
            "subcategory":"Management & Consulting",
            "type":"Services"
        }
    ],
    "sg:phone":"+1   ",
    "sg:postcode":"06770",
    "sg:province":"CT",
    "sg:tags":[
        "nutrition"
    ],
    "wof:name":"Mna Nutrition LLC",
    "wof:placetype":"venue"
},
  "geometry": {"coordinates":[-73.05949099999999,41.498509],"type":"Point"}
}