{
  "type": "Feature",
  "properties": {
    "iso:country":"US",
    "sg:address":"567 Vauxhall St Exd",
    "sg:city":"Waterford",
    "sg:classifiers":[
        {
            "category":"Social Services",
            "type":"Services"
        }
    ],
    "sg:phone":"+1   ",
    "sg:postcode":"06385",
    "sg:province":"CT",
    "wof:name":"Ellen Calkins Lcsw",
    "wof:placetype":"venue"
},
  "geometry": {"coordinates":[-72.123806,41.370824],"type":"Point"}
}