{
  "type": "Feature",
  "properties": {
    "addr:full":"2113 Summer St Stamford CT 06905",
    "addr:housenumber":"2113",
    "addr:postcode":"06905",
    "addr:street":"Summer St",
    "iso:country":"US",
    "sg:address":"2113 Summer St",
    "sg:city":"Stamford",
    "sg:classifiers":[
        {
            "category":"Shopping",
            "subcategory":"Discount & Variety Stores",
            "type":"Retail Goods"
        }
    ],
    "sg:phone":"+1 203 602 4424",
    "sg:postcode":"06905",
    "sg:province":"CT",
    "wof:name":"Amazing Savings",
    "wof:placetype":"venue"
},
  "geometry": {"coordinates":[-73.545721,41.06698],"type":"Point"}
}