{
  "type": "Feature",
  "properties": {
    "addr:full":"166 Amity Rd New Haven CT 06515",
    "addr:housenumber":"166",
    "addr:postcode":"06515",
    "addr:street":"Amity Rd",
    "iso:country":"US",
    "sg:address":"166 Amity Rd",
    "sg:city":"New Haven",
    "sg:classifiers":[
        {
            "category":"Shopping",
            "subcategory":"Clothing, Apparel, & Fashions",
            "type":"Retail Goods"
        }
    ],
    "sg:phone":"+1 203 389 5438",
    "sg:postcode":"06515",
    "sg:province":"CT",
    "sg:tags":[
        "dressmaker"
    ],
    "wof:name":"Vicky's Custom Design",
    "wof:placetype":"venue"
},
  "geometry": {"coordinates":[-72.98033100000001,41.338455],"type":"Point"}
}