{
  "type": "Feature",
  "properties": {
    "addr:full":"610 Quinnipiac Ave New Haven CT 06513",
    "addr:housenumber":"610",
    "addr:postcode":"06513",
    "addr:street":"Quinnipiac Ave",
    "iso:country":"US",
    "sg:address":"610 Quinnipiac Ave",
    "sg:city":"New Haven",
    "sg:classifiers":[
        {
            "category":"Professional",
            "subcategory":"Management & Consulting",
            "type":"Services"
        }
    ],
    "sg:phone":"+1   ",
    "sg:postcode":"06513",
    "sg:province":"CT",
    "sg:tags":[
        "marketing",
        "consultant"
    ],
    "wof:name":"Tallmadge Brothers Marketing",
    "wof:placetype":"venue"
},
  "geometry": {"coordinates":[-72.887771,41.30577],"type":"Point"}
}