{
  "type": "Feature",
  "properties": {
    "addr:full":"547 Shuttle Meadow Rd Southington CT 06489",
    "addr:housenumber":"547",
    "addr:postcode":"06489",
    "addr:street":"Shuttle Meadow Rd",
    "iso:country":"US",
    "sg:address":"547 Shuttle Meadow Rd",
    "sg:city":"Southington",
    "sg:classifiers":[
        {
            "category":"Professional",
            "subcategory":"Engineering",
            "type":"Services"
        }
    ],
    "sg:phone":"+1   ",
    "sg:postcode":"06489",
    "sg:province":"CT",
    "wof:name":"Hydro Dynamic Engineering",
    "wof:placetype":"venue"
},
  "geometry": {"coordinates":[-72.84316800000001,41.648366],"type":"Point"}
}