{
  "type": "Feature",
  "properties": {
    "iso:country":"US",
    "sg:address":"511 Chapel St",
    "sg:city":"New Haven",
    "sg:classifiers":[
        {
            "category":"Education",
            "subcategory":"School",
            "type":"Public Place"
        }
    ],
    "sg:phone":"+1 203 946 8613",
    "sg:postcode":"06511",
    "sg:province":"CT",
    "wof:name":"West Hills School",
    "wof:placetype":"venue"
},
  "geometry": {"coordinates":[-72.91432,41.303743],"type":"Point"}
}