{
  "type": "Feature",
  "properties": {
    "addr:full":"455 East St Middletown CT 06457",
    "addr:housenumber":"455",
    "addr:postcode":"06457",
    "addr:street":"East St",
    "iso:country":"US",
    "sg:address":"455 East St",
    "sg:city":"Middletown",
    "sg:classifiers":[
        {
            "category":"Professional",
            "subcategory":"Business Services",
            "type":"Services"
        }
    ],
    "sg:phone":"+1   ",
    "sg:postcode":"06457",
    "sg:province":"CT",
    "wof:name":"Brainard Agency Inc",
    "wof:placetype":"venue"
},
  "geometry": {"coordinates":[-72.70187199999999,41.577694],"type":"Point"}
}