{
  "type": "Feature",
  "properties": {
    "iso:country":"US",
    "sg:address":"77 Clarence St",
    "sg:city":"Bridgeport",
    "sg:classifiers":[
        {
            "category":"Building & Trades",
            "subcategory":"Construction",
            "type":"Services"
        }
    ],
    "sg:phone":"+1 203 866 8883",
    "sg:postcode":"06608",
    "sg:province":"CT",
    "sg:tags":[
        "paving",
        "contractor"
    ],
    "sg:website":"www.piroinc.com",
    "wof:name":"Piro Paving Inc",
    "wof:placetype":"venue"
},
  "geometry": {"coordinates":[-73.18358000000001,41.184797],"type":"Point"}
}