{
  "type": "Feature",
  "properties": {
    "iso:country":"US",
    "sg:address":"35 Tamarack Ave",
    "sg:city":"Danbury",
    "sg:classifiers":[
        {
            "category":"Health Services",
            "subcategory":"Doctor",
            "type":"Services"
        }
    ],
    "sg:phone":"+1 203 792 4263",
    "sg:postcode":"06811",
    "sg:province":"CT",
    "sg:tags":[
        "physician",
        "surgeons",
        "hand",
        "orthopedics",
        "surgery",
        "surgeon"
    ],
    "sg:website":"http://www.hand-center.com",
    "wof:name":"Hand Center Of Western Connecticut",
    "wof:placetype":"venue"
},
  "geometry": {"coordinates":[-73.450819,41.414567],"type":"Point"}
}