{
  "type": "Feature",
  "properties": {
    "addr:full":"15 Elliott St Fairfield CT 06451",
    "addr:housenumber":"15",
    "addr:postcode":"06451",
    "addr:street":"Elliott St",
    "iso:country":"US",
    "sg:address":"15 Elliott St",
    "sg:city":"Fairfield",
    "sg:classifiers":[
        {
            "category":"Building & Trades",
            "subcategory":"Landscaping Services",
            "type":"Services"
        }
    ],
    "sg:phone":"+1 203 259 2739",
    "sg:postcode":"06451",
    "sg:province":"CT",
    "sg:tags":[
        "landscape",
        "contractor"
    ],
    "wof:name":"Ground Crew",
    "wof:placetype":"venue"
},
  "geometry": {"coordinates":[-72.80988000000001,41.529181],"type":"Point"}
}