{
  "type": "Feature",
  "properties": {
    "iso:country":"US",
    "sg:address":"2519 Whitney Ave",
    "sg:city":"Hamden",
    "sg:classifiers":[
        {
            "category":"Real Estate",
            "subcategory":"Real Estate Agent",
            "type":"Services"
        }
    ],
    "sg:phone":"+1 203 281 4225",
    "sg:postcode":"06518",
    "sg:province":"CT",
    "wof:name":"Ned M Leginsky",
    "wof:placetype":"venue"
},
  "geometry": {"coordinates":[-72.898399,41.39075],"type":"Point"}
}