{
  "type": "Feature",
  "properties": {
    "iso:country":"US",
    "sg:address":"1370 New Haven Ave",
    "sg:city":"Milford",
    "sg:classifiers":[
        {
            "category":"Shopping",
            "subcategory":"News",
            "type":"Retail Goods"
        }
    ],
    "sg:phone":"+1 203 874 7752",
    "sg:postcode":"06460",
    "sg:province":"CT",
    "sg:tags":[
        "dealer"
    ],
    "wof:name":"News Den",
    "wof:placetype":"venue"
},
  "geometry": {"coordinates":[-72.996095,41.228791],"type":"Point"}
}