{
  "type": "Feature",
  "properties": {
    "iso:country":"US",
    "sg:address":"2 Orange Ave",
    "sg:city":"New Haven",
    "sg:classifiers":[
        {
            "category":"Retail",
            "subcategory":"Car Wash",
            "type":"Services"
        }
    ],
    "sg:phone":"+1 203 933 3005",
    "sg:postcode":"06519",
    "sg:province":"CT",
    "sg:tags":[
        "polishing",
        "washing"
    ],
    "wof:name":"Super Sonic Carwash & Oil",
    "wof:placetype":"venue"
},
  "geometry": {"coordinates":[-72.95108399999999,41.297262],"type":"Point"}
}