{
  "type": "Feature",
  "properties": {
    "iso:country":"US",
    "sg:address":"45 Center St",
    "sg:city":"Winsted",
    "sg:classifiers":[
        {
            "category":"Professional",
            "subcategory":"Lawyer & Legal Services",
            "type":"Services"
        }
    ],
    "sg:phone":"+1   ",
    "sg:postcode":"06098",
    "sg:province":"CT",
    "wof:name":"Dixon & Brooks PC",
    "wof:placetype":"venue"
},
  "geometry": {"coordinates":[-73.06795099999999,41.922095],"type":"Point"}
}