{
  "type": "Feature",
  "properties": {
    "addr:full":"1240 Stratford Ave Stratford CT 06615",
    "addr:housenumber":"1240",
    "addr:postcode":"06615",
    "addr:street":"Stratford Ave",
    "iso:country":"US",
    "sg:address":"1240 Stratford Ave",
    "sg:city":"Stratford",
    "sg:classifiers":[
        {
            "category":"Restaurant",
            "type":"Food & Drink"
        }
    ],
    "sg:menulink":"http://www.allmenus.com/ct/stratford/144050-subway/menu/",
    "sg:phone":"+1 203 385 0882",
    "sg:postcode":"06615",
    "sg:province":"CT",
    "sg:tags":[
        "american",
        "sandwich"
    ],
    "wof:name":"Subway",
    "wof:placetype":"venue"
},
  "geometry": {"coordinates":[-73.13469000000001,41.187018],"type":"Point"}
}