{
  "type": "Feature",
  "properties": {
    "iso:country":"US",
    "sg:address":"63 Prospect St",
    "sg:city":"Waterbury",
    "sg:classifiers":[
        {
            "category":"Social Services",
            "subcategory":"Child Care",
            "type":"Services"
        }
    ],
    "sg:phone":"+1   ",
    "sg:postcode":"06702",
    "sg:province":"CT",
    "sg:tags":[
        "day"
    ],
    "wof:name":"Stepping Stones",
    "wof:placetype":"venue"
},
  "geometry": {"coordinates":[-73.04128799999999,41.557059],"type":"Point"}
}