{
  "type": "Feature",
  "properties": {
    "iso:country":"US",
    "sg:address":"93 Kasson Rd",
    "sg:city":"Bethlehem",
    "sg:classifiers":[
        {
            "category":"Building & Trades",
            "subcategory":"Landscaping Services",
            "type":"Services"
        }
    ],
    "sg:phone":"+1 203 266 5898",
    "sg:postcode":"06751",
    "sg:province":"CT",
    "wof:name":"Quality Landscaping",
    "wof:placetype":"venue"
},
  "geometry": {"coordinates":[-73.191558,41.649441],"type":"Point"}
}