{
  "type": "Feature",
  "properties": {
    "iso:country":"US",
    "sg:address":"65 S Turnpike Rd",
    "sg:city":"Wallingford",
    "sg:classifiers":[
        {
            "category":"Wholesale",
            "subcategory":"Electrical",
            "type":"Manufacturing & Wholesale Goods"
        }
    ],
    "sg:phone":"+1 203 269 1354",
    "sg:postcode":"06492",
    "sg:province":"CT",
    "sg:tags":[
        "electric",
        "motor"
    ],
    "sg:website":"www.baldor.com",
    "wof:name":"Ems Baldor Electric Co",
    "wof:placetype":"venue"
},
  "geometry": {"coordinates":[-72.84048900000001,41.455281],"type":"Point"}
}