{
  "type": "Feature",
  "properties": {
    "iso:country":"US",
    "sg:address":"251 Dwight St",
    "sg:city":"New Haven",
    "sg:classifiers":[
        {
            "category":"Professional",
            "subcategory":"Management & Consulting",
            "type":"Services"
        }
    ],
    "sg:phone":"+1 203 624 8619",
    "sg:postcode":"06511",
    "sg:province":"CT",
    "sg:tags":[
        "consultant",
        "educational"
    ],
    "sg:website":"www.eastrockinstitute.org",
    "wof:name":"East Rock Institute",
    "wof:placetype":"venue"
},
  "geometry": {"coordinates":[-72.93567400000001,41.311227],"type":"Point"}
}