{
  "type": "Feature",
  "properties": {
    "iso:country":"US",
    "sg:address":"728 Hampton Rd",
    "sg:city":"Abington",
    "sg:classifiers":[
        {
            "category":"Restaurant",
            "type":"Food & Drink"
        }
    ],
    "sg:phone":"+1 860 974 1095",
    "sg:postcode":"06230",
    "sg:province":"CT",
    "sg:tags":[
        "eating"
    ],
    "wof:name":"We-Li-Kit Ice Cream",
    "wof:placetype":"venue"
},
  "geometry": {"coordinates":[-72.00706599999999,41.860113],"type":"Point"}
}