{
  "type": "Feature",
  "properties": {
    "iso:country":"US",
    "sg:address":"35 Skyview Dr",
    "sg:city":"Stamford",
    "sg:classifiers":[
        {
            "category":"Building & Trades",
            "subcategory":"Construction",
            "type":"Services"
        }
    ],
    "sg:phone":"+1 203 975 8811",
    "sg:postcode":"06902",
    "sg:province":"CT",
    "sg:tags":[
        "painter"
    ],
    "wof:name":"Kings Painting",
    "wof:placetype":"venue"
},
  "geometry": {"coordinates":[-73.565641,41.077237],"type":"Point"}
}