{
  "type": "Feature",
  "properties": {
    "iso:country":"US",
    "sg:address":"102 Butternut Rd",
    "sg:city":"Manchester",
    "sg:classifiers":[
        {
            "category":"Real Estate",
            "subcategory":"Real Estate Agent",
            "type":"Services"
        }
    ],
    "sg:phone":"+1 860 643 2688",
    "sg:postcode":"06040",
    "sg:province":"CT",
    "wof:name":"Sheila B Flanagan Real Estate",
    "wof:placetype":"venue"
},
  "geometry": {"coordinates":[-72.48744000000001,41.772005],"type":"Point"}
}