{
  "type": "Feature",
  "properties": {
    "addr:full":"414 State Hwy 165 Preston CT 06365",
    "addr:housenumber":"414",
    "addr:postcode":"06365",
    "addr:street":"State Hwy 165 Preston Ct",
    "iso:country":"US",
    "sg:address":"414 State Hwy 165",
    "sg:city":"Preston",
    "sg:classifiers":[
        {
            "category":"Farming",
            "subcategory":"Farm",
            "type":"Manufacturing & Wholesale Goods"
        }
    ],
    "sg:phone":"+1 860 204 0331",
    "sg:postcode":"06365",
    "sg:province":"CT",
    "sg:tags":[
        "crop",
        "general"
    ],
    "wof:name":"Stone Silo Farm",
    "wof:placetype":"venue"
},
  "geometry": {"coordinates":[-71.97194399999999,41.530999],"type":"Point"}
}