{
  "type": "Feature",
  "properties": {
    "iso:country":"US",
    "sg:address":"23 N Plains Industrial Rd",
    "sg:city":"Wallingford",
    "sg:classifiers":[
        {
            "category":"Manufacturing",
            "subcategory":"Metals",
            "type":"Manufacturing & Wholesale Goods"
        }
    ],
    "sg:phone":"+1 203 284 9764",
    "sg:postcode":"06492",
    "sg:province":"CT",
    "sg:website":"www.bhs-ltd.com",
    "wof:name":"Bhs Industries LTD",
    "wof:placetype":"venue"
},
  "geometry": {"coordinates":[-72.812945,41.486574],"type":"Point"}
}