{
  "type": "Feature",
  "properties": {
    "addr:full":"401 Shippan Ave Ste 2 Stamford CT 06902",
    "addr:housenumber":"401",
    "addr:postcode":"06902",
    "addr:street":"Shippan Ave Ste 2",
    "iso:country":"US",
    "sg:address":"401 Shippan Ave Ste 2",
    "sg:city":"Stamford",
    "sg:classifiers":[
        {
            "category":"Government",
            "subcategory":"Office",
            "type":"Public Place"
        }
    ],
    "sg:phone":"+1 203 348 4294",
    "sg:postcode":"06902",
    "sg:province":"CT",
    "sg:tags":[
        "government-united",
        "state"
    ],
    "wof:name":"Stamford Sub-Office",
    "wof:placetype":"venue"
},
  "geometry": {"coordinates":[-73.52384600000001,41.045546],"type":"Point"}
}