{
  "type": "Feature",
  "properties": {
    "iso:country":"US",
    "sg:address":"129 Mill St",
    "sg:city":"Berlin",
    "sg:classifiers":[
        {
            "category":"Professional",
            "subcategory":"Management & Consulting",
            "type":"Services"
        }
    ],
    "sg:phone":"+1   ",
    "sg:postcode":"06037",
    "sg:province":"CT",
    "sg:tags":[
        "public",
        "relations"
    ],
    "wof:name":"London Michael J & Associates",
    "wof:placetype":"venue"
},
  "geometry": {"coordinates":[-72.74589400000001,41.625604],"type":"Point"}
}