{
  "type": "Feature",
  "properties": {
    "addr:full":"242 Weatherly Trl Guilford CT 06437",
    "addr:housenumber":"242",
    "addr:postcode":"06437",
    "addr:street":"Weatherly Trl",
    "iso:country":"US",
    "sg:address":"242 Weatherly Trl",
    "sg:city":"Guilford",
    "sg:classifiers":[
        {
            "category":"Building & Trades",
            "subcategory":"Cleaning & Sanitation",
            "type":"Services"
        }
    ],
    "sg:phone":"+1   ",
    "sg:postcode":"06437",
    "sg:province":"CT",
    "sg:tags":[
        "maintenance"
    ],
    "wof:name":"Berts Cleaning",
    "wof:placetype":"venue"
},
  "geometry": {"coordinates":[-72.70598200000001,41.366741],"type":"Point"}
}