{
  "type": "Feature",
  "properties": {
    "addr:full":"8 Lolly Ln Oxford CT 06478",
    "addr:housenumber":"8",
    "addr:postcode":"06478",
    "addr:street":"Lolly Ln",
    "iso:country":"US",
    "sg:address":"8 Lolly Ln",
    "sg:city":"Oxford",
    "sg:classifiers":[
        {
            "category":"Professional",
            "type":"Services"
        },
        {
            "category":"Professional",
            "subcategory":"Management & Consulting",
            "type":"Services"
        }
    ],
    "sg:phone":"+1 203 888 8637",
    "sg:postcode":"06478",
    "sg:province":"CT",
    "sg:tags":[
        "establishment"
    ],
    "wof:name":"Miko Enterprises LLC",
    "wof:placetype":"venue"
},
  "geometry": {"coordinates":[-73.173661,41.435264],"type":"Point"}
}