{
  "type": "Feature",
  "properties": {
    "addr:full":"79 Munson Rd Beacon Falls CT 06403",
    "addr:housenumber":"79",
    "addr:postcode":"06403",
    "addr:street":"Munson Rd Beacon Falls Ct",
    "iso:country":"US",
    "sg:address":"79 Munson Rd",
    "sg:city":"Beacon Falls",
    "sg:classifiers":[
        {
            "category":"Shopping",
            "subcategory":"Florist",
            "type":"Retail Goods"
        }
    ],
    "sg:phone":"+1 203 723 7773",
    "sg:postcode":"06403",
    "sg:province":"CT",
    "wof:name":"Classey Craft House",
    "wof:placetype":"venue"
},
  "geometry": {"coordinates":[-73.03744500000001,41.442456],"type":"Point"}
}