{
  "type": "Feature",
  "properties": {
    "iso:country":"US",
    "sg:address":"401 Monroe Tpke",
    "sg:city":"Monroe",
    "sg:classifiers":[
        {
            "category":"Personal",
            "type":"Services"
        }
    ],
    "sg:phone":"+1   ",
    "sg:postcode":"06468",
    "sg:province":"CT",
    "wof:name":"Personal Weight Loss Center",
    "wof:placetype":"venue"
},
  "geometry": {"coordinates":[-73.22148,41.310295],"type":"Point"}
}