{
  "type": "Feature",
  "properties": {
    "addr:full":"2 Pennywise Lane Old Saybrook CT 06475",
    "addr:housenumber":"2",
    "addr:postcode":"06475",
    "addr:street":"Pennywise Lane Old Saybrook Ct",
    "iso:country":"US",
    "sg:address":"2 Pennywise Lane",
    "sg:city":"Old Saybrook",
    "sg:classifiers":[
        {
            "category":"Ice Cream",
            "type":"Food & Drink"
        }
    ],
    "sg:phone":"+1 860 395 1406",
    "sg:postcode":"06475",
    "sg:province":"CT",
    "sg:tags":[
        "frozen",
        "yogurt"
    ],
    "sg:website":"www.pratthouse.net/jamesgallery.htm",
    "wof:name":"The James Gallery & Soda Fountain",
    "wof:placetype":"venue"
},
  "geometry": {"coordinates":[-72.375638,41.286207],"type":"Point"}
}