{
  "type": "Feature",
  "properties": {
    "addr:full":"125 N Regent St Port Chester CT 10573",
    "addr:housenumber":"125",
    "addr:postcode":"10573",
    "addr:street":"N Regent St Port Chester Ct",
    "iso:country":"US",
    "sg:address":"125 N Regent St",
    "sg:city":"Port Chester",
    "sg:classifiers":[
        {
            "category":"Food & Beverages",
            "subcategory":"Bakery",
            "type":"Retail Goods"
        }
    ],
    "sg:phone":"+1 914 939 5963",
    "sg:postcode":"10573",
    "sg:province":"CT",
    "sg:tags":[
        "baker"
    ],
    "wof:name":"JMJ Bakery Svc Inc",
    "wof:placetype":"venue"
},
  "geometry": {"coordinates":[-73.672251,41.009303],"type":"Point"}
}