{
  "type": "Feature",
  "properties": {
    "iso:country":"US",
    "sg:address":"540 Grant St",
    "sg:city":"Bridgeport",
    "sg:classifiers":[
        {
            "category":"Professional",
            "type":"Services"
        }
    ],
    "sg:phone":"+1 203 334 3154",
    "sg:postcode":"06610",
    "sg:province":"CT",
    "sg:tags":[
        "establishment"
    ],
    "wof:name":"Checkmate",
    "wof:placetype":"venue"
},
  "geometry": {"coordinates":[-73.16140799999999,41.188466],"type":"Point"}
}