{
  "type": "Feature",
  "properties": {
    "addr:full":"91 Commerce Dr Brookfield CT 06804",
    "addr:housenumber":"91",
    "addr:postcode":"06804",
    "addr:street":"Commerce Dr",
    "iso:country":"US",
    "sg:address":"91 Commerce Dr",
    "sg:city":"Brookfield",
    "sg:classifiers":[
        {
            "category":"Wholesale",
            "subcategory":"Electrical",
            "type":"Manufacturing & Wholesale Goods"
        }
    ],
    "sg:phone":"+1 203 740 2700",
    "sg:postcode":"06804",
    "sg:province":"CT",
    "sg:tags":[
        "equipment",
        "electronic",
        "supply"
    ],
    "wof:name":"Pilgrim Electronics Inc",
    "wof:placetype":"venue"
},
  "geometry": {"coordinates":[-73.394001,41.452231],"type":"Point"}
}