{
  "type": "Feature",
  "properties": {
    "addr:full":"48 Van Zant St Norwalk CT 06855",
    "addr:housenumber":"48",
    "addr:postcode":"06855",
    "addr:street":"Van Zant St",
    "iso:country":"US",
    "sg:address":"48 Van Zant St",
    "sg:city":"Norwalk",
    "sg:classifiers":[
        {
            "category":"Retail",
            "subcategory":"Auto Repair",
            "type":"Services"
        }
    ],
    "sg:phone":"+1   ",
    "sg:postcode":"06855",
    "sg:province":"CT",
    "sg:tags":[
        "body",
        "general"
    ],
    "wof:name":"Norwalk Collision Inc",
    "wof:placetype":"venue"
},
  "geometry": {"coordinates":[-73.403863,41.101995],"type":"Point"}
}