{
  "type": "Feature",
  "properties": {
    "iso:country":"US",
    "sg:address":"1351 N Main St",
    "sg:city":"Waterbury",
    "sg:classifiers":[
        {
            "category":"Personal",
            "subcategory":"Beauty Salon",
            "type":"Services"
        }
    ],
    "sg:phone":"+1 203 596 9697",
    "sg:postcode":"06704",
    "sg:province":"CT",
    "wof:name":"Felisha's Hair Salon",
    "wof:placetype":"venue"
},
  "geometry": {"coordinates":[-73.026031,41.568591],"type":"Point"}
}