{
  "type": "Feature",
  "properties": {
    "iso:country":"US",
    "sg:address":"334 Main St",
    "sg:city":"West Haven",
    "sg:classifiers":[
        {
            "category":"Organizations",
            "subcategory":"Professional Association",
            "type":"Services"
        }
    ],
    "sg:phone":"+1   ",
    "sg:postcode":"06516",
    "sg:province":"CT",
    "sg:tags":[
        "business"
    ],
    "wof:name":"West Haven Chamber of Commerce",
    "wof:placetype":"venue"
},
  "geometry": {"coordinates":[-72.94871999999999,41.272798],"type":"Point"}
}