{
  "type": "Feature",
  "properties": {
    "iso:country":"US",
    "sg:address":"452 Jackson St",
    "sg:city":"Willimantic",
    "sg:classifiers":[
        {
            "category":"Professional",
            "subcategory":"Lawyer & Legal Services",
            "type":"Services"
        }
    ],
    "sg:phone":"+1   ",
    "sg:postcode":"06226",
    "sg:province":"CT",
    "wof:name":"Mark James R Esq",
    "wof:placetype":"venue"
},
  "geometry": {"coordinates":[-72.202023,41.725276],"type":"Point"}
}