{
  "type": "Feature",
  "properties": {
    "addr:full":"25 Bernadine Rd Milford CT 06461",
    "addr:housenumber":"25",
    "addr:postcode":"06461",
    "addr:street":"Bernadine Rd",
    "iso:country":"US",
    "sg:address":"25 Bernadine Rd",
    "sg:city":"Milford",
    "sg:classifiers":[
        {
            "category":"Organizations",
            "subcategory":"Membership Organization",
            "type":"Services"
        }
    ],
    "sg:phone":"+1   ",
    "sg:postcode":"06461",
    "sg:province":"CT",
    "wof:name":"Darkbliss Demonstrations Inc",
    "wof:placetype":"venue"
},
  "geometry": {"coordinates":[-73.09143899999999,41.222931],"type":"Point"}
}