{
  "type": "Feature",
  "properties": {
    "addr:full":"221 James St Bridgeport CT 06604",
    "addr:housenumber":"221",
    "addr:postcode":"06604",
    "addr:street":"James St",
    "iso:country":"US",
    "sg:address":"221 James St",
    "sg:city":"Bridgeport",
    "sg:classifiers":[
        {
            "category":"Organizations",
            "subcategory":"Religious Organization",
            "type":"Services"
        }
    ],
    "sg:phone":"+1 203 333 3308",
    "sg:postcode":"06604",
    "sg:province":"CT",
    "sg:tags":[
        "church"
    ],
    "wof:name":"Gospel Temple Church",
    "wof:placetype":"venue"
},
  "geometry": {"coordinates":[-73.198487,41.182232],"type":"Point"}
}