{
  "type": "Feature",
  "properties": {
    "addr:full":"29 Cross Hwy Westport CT 06880",
    "addr:housenumber":"29",
    "addr:postcode":"06880",
    "addr:street":"Cross Hwy Westport Ct",
    "iso:country":"US",
    "sg:address":"29 Cross Hwy",
    "sg:city":"Westport",
    "sg:classifiers":[
        {
            "category":"Professional",
            "subcategory":"Management & Consulting",
            "type":"Services"
        }
    ],
    "sg:phone":"+1   ",
    "sg:postcode":"06880",
    "sg:province":"CT",
    "sg:tags":[
        "public",
        "relations"
    ],
    "wof:name":"BCC Public Relations",
    "wof:placetype":"venue"
},
  "geometry": {"coordinates":[-73.355228,41.157574],"type":"Point"}
}