{
  "type": "Feature",
  "properties": {
    "addr:full":"21 Pearl St Guilford CT 06437",
    "addr:housenumber":"21",
    "addr:postcode":"06437",
    "addr:street":"Pearl St",
    "iso:country":"US",
    "sg:address":"21 Pearl St",
    "sg:city":"Guilford",
    "sg:classifiers":[
        {
            "category":"Building & Trades",
            "subcategory":"Construction",
            "type":"Services"
        }
    ],
    "sg:phone":"+1 203 453 5857",
    "sg:postcode":"06437",
    "sg:province":"CT",
    "sg:tags":[
        "woodworker"
    ],
    "wof:name":"S R Woodworks",
    "wof:placetype":"venue"
},
  "geometry": {"coordinates":[-72.67673000000001,41.285337],"type":"Point"}
}