{
  "type": "Feature",
  "properties": {
    "iso:country":"US",
    "sg:address":"241 Main St",
    "sg:city":"Danbury",
    "sg:classifiers":[
        {
            "category":"Retail",
            "subcategory":"Portrait Studio",
            "type":"Services"
        }
    ],
    "sg:phone":"+1 203 748 3958",
    "sg:postcode":"06810",
    "sg:province":"CT",
    "sg:tags":[
        "photographer"
    ],
    "wof:name":"Daniel Kemp Photography",
    "wof:placetype":"venue"
},
  "geometry": {"coordinates":[-73.452685,41.394853],"type":"Point"}
}