{
  "type": "Feature",
  "properties": {
    "addr:full":"59 Howe Ave Shelton CT 06484",
    "addr:housenumber":"59",
    "addr:postcode":"06484",
    "addr:street":"Howe Ave",
    "iso:country":"US",
    "sg:address":"59 Howe Ave",
    "sg:city":"Shelton",
    "sg:classifiers":[
        {
            "category":"Retail",
            "subcategory":"Animal Services",
            "type":"Services"
        }
    ],
    "sg:phone":"+1 203 924 8431",
    "sg:postcode":"06484",
    "sg:province":"CT",
    "sg:tags":[
        "pet",
        "grooming",
        "washing"
    ],
    "wof:name":"Canine Castle Grooming Salon",
    "wof:placetype":"venue"
},
  "geometry": {"coordinates":[-73.08320399999999,41.308913],"type":"Point"}
}