{
  "type": "Feature",
  "properties": {
    "addr:full":"5 S Main St Terryville CT 06786",
    "addr:housenumber":"5",
    "addr:postcode":"06786",
    "addr:street":"S Main St Terryville Ct",
    "iso:country":"US",
    "sg:address":"5 S Main St",
    "sg:city":"Terryville",
    "sg:classifiers":[
        {
            "category":"Shopping",
            "subcategory":"Florist",
            "type":"Retail Goods"
        }
    ],
    "sg:phone":"+1 860 589 2746",
    "sg:postcode":"06786",
    "sg:province":"CT",
    "wof:name":"Village Florist",
    "wof:placetype":"venue"
},
  "geometry": {"coordinates":[-73.011336,41.677641],"type":"Point"}
}