{
  "type": "Feature",
  "properties": {
    "iso:country":"US",
    "sg:address":"195 Greenwich Ave",
    "sg:city":"Greenwich",
    "sg:classifiers":[
        {
            "category":"Wholesale",
            "subcategory":"Painting Supplies",
            "type":"Manufacturing & Wholesale Goods"
        },
        {
            "category":"Home & Garden",
            "subcategory":"Garden Supply",
            "type":"Retail Goods"
        },
        {
            "category":"Wholesale",
            "subcategory":"Construction Materials",
            "type":"Manufacturing & Wholesale Goods"
        },
        {
            "category":"Home & Garden",
            "subcategory":"Hardware",
            "type":"Retail Goods"
        }
    ],
    "sg:phone":"+1 203 869 6750",
    "sg:postcode":"06830",
    "sg:province":"CT",
    "sg:tags":[
        "lawn",
        "paint",
        "equipment",
        "part",
        "plumbing",
        "fixtures",
        "store"
    ],
    "sg:website":"http://www.truevalue.com/greenwichtv",
    "wof:name":"Greenwich True Value Hardware",
    "wof:placetype":"venue"
},
  "geometry": {"coordinates":[-73.626057,41.027303],"type":"Point"}
}