{
  "type": "Feature",
  "properties": {
    "addr:full":"1575 Boston Ave Bridgeport CT 06610",
    "addr:housenumber":"1575",
    "addr:postcode":"06610",
    "addr:street":"Boston Ave",
    "iso:country":"US",
    "sg:address":"1575 Boston Ave",
    "sg:city":"Bridgeport",
    "sg:classifiers":[
        {
            "category":"Building & Trades",
            "subcategory":"Construction",
            "type":"Services"
        }
    ],
    "sg:phone":"+1 203 334 5557",
    "sg:postcode":"06610",
    "sg:province":"CT",
    "sg:tags":[
        "painter"
    ],
    "wof:name":"Swanson Painting",
    "wof:placetype":"venue"
},
  "geometry": {"coordinates":[-73.16403,41.193578],"type":"Point"}
}