{
  "type": "Feature",
  "properties": {
    "addr:full":"16 Savarese Ln Burlington CT 06013",
    "addr:housenumber":"16",
    "addr:postcode":"06013",
    "addr:street":"Savarese Ln",
    "iso:country":"US",
    "sg:address":"16 Savarese Ln",
    "sg:city":"Burlington",
    "sg:classifiers":[
        {
            "category":"Farming",
            "subcategory":"Farm & Veterinary Services",
            "type":"Manufacturing & Wholesale Goods"
        }
    ],
    "sg:phone":"+1 860 675 8828",
    "sg:postcode":"06013",
    "sg:province":"CT",
    "sg:tags":[
        "labor",
        "contractor",
        "hanging"
    ],
    "wof:name":"Gresh Construction",
    "wof:placetype":"venue"
},
  "geometry": {"coordinates":[-72.966279,41.768975],"type":"Point"}
}