{
  "type": "Feature",
  "properties": {
    "addr:full":"15 Sycamore Ct Bethel CT 06801",
    "addr:housenumber":"15",
    "addr:postcode":"06801",
    "addr:street":"Sycamore Ct Bethel Ct",
    "iso:country":"US",
    "sg:address":"15 Sycamore Ct",
    "sg:city":"Bethel",
    "sg:classifiers":[
        {
            "category":"Building & Trades",
            "subcategory":"Landscaping Services",
            "type":"Services"
        }
    ],
    "sg:phone":"+1 203 798 2415",
    "sg:postcode":"06801",
    "sg:province":"CT",
    "sg:tags":[
        "landscape",
        "contractor"
    ],
    "wof:name":"T & M Lawn & Landscape",
    "wof:placetype":"venue"
},
  "geometry": {"coordinates":[-73.426695,41.370752],"type":"Point"}
}