{
  "type": "Feature",
  "properties": {
    "iso:country":"US",
    "sg:address":"280 Collins St",
    "sg:city":"Hartford",
    "sg:classifiers":[
        {
            "category":"Real Estate",
            "subcategory":"Real Estate Operator",
            "type":"Services"
        }
    ],
    "sg:phone":"+1 860 249 7743",
    "sg:postcode":"06105",
    "sg:province":"CT",
    "sg:tags":[
        "building",
        "apartment"
    ],
    "wof:name":"Wingate",
    "wof:placetype":"venue"
},
  "geometry": {"coordinates":[-72.696212,41.77383],"type":"Point"}
}