{
  "type": "Feature",
  "properties": {
    "iso:country":"US",
    "sg:address":"240 E Main St",
    "sg:city":"Clinton",
    "sg:classifiers":[
        {
            "category":"Autos & Motor Vehicles",
            "subcategory":"Auto Supplies",
            "type":"Retail Goods"
        },
        {
            "category":"Retail",
            "subcategory":"Auto Repair",
            "type":"Services"
        }
    ],
    "sg:phone":"+1 860 669 1975",
    "sg:postcode":"06413",
    "sg:province":"CT",
    "sg:tags":[
        "exhaust",
        "oil",
        "tire",
        "automobile",
        "system",
        "lube",
        "part",
        "brake",
        "muffler"
    ],
    "sg:website":"http://www.monro.com",
    "wof:name":"Monro Muffler Brake & Service",
    "wof:placetype":"venue"
},
  "geometry": {"coordinates":[-72.50368899999999,41.271429],"type":"Point"}
}