{
  "type": "Feature",
  "properties": {
    "iso:country":"US",
    "sg:address":"1052 Main St",
    "sg:city":"Branford",
    "sg:classifiers":[
        {
            "category":"Professional",
            "subcategory":"Lawyer & Legal Services",
            "type":"Services"
        }
    ],
    "sg:phone":"+1 203 488 9663",
    "sg:postcode":"06405",
    "sg:province":"CT",
    "sg:tags":[
        "attorney"
    ],
    "wof:name":"Vincent Federico Jr Law Office",
    "wof:placetype":"venue"
},
  "geometry": {"coordinates":[-72.81093199999999,41.282161],"type":"Point"}
}