{
  "type": "Feature",
  "properties": {
    "addr:full":"722 Main St Winsted CT 06098",
    "addr:housenumber":"722",
    "addr:postcode":"06098",
    "addr:street":"Main St",
    "iso:country":"US",
    "sg:address":"722 Main St",
    "sg:city":"Winsted",
    "sg:classifiers":[
        {
            "category":"Retail",
            "subcategory":"Self-service Laundry",
            "type":"Services"
        }
    ],
    "sg:phone":"+1   ",
    "sg:postcode":"06098",
    "sg:province":"CT",
    "sg:tags":[
        "coin"
    ],
    "wof:name":"Pags Coin Op Ldry & Valet Svc",
    "wof:placetype":"venue"
},
  "geometry": {"coordinates":[-73.07560599999999,41.923045],"type":"Point"}
}