{
  "type": "Feature",
  "properties": {
    "addr:full":"80 Park Lane Rd New Milford CT 06776",
    "addr:housenumber":"80",
    "addr:postcode":"06776",
    "addr:street":"Park Lane Rd",
    "iso:country":"US",
    "sg:address":"80 Park Lane Rd",
    "sg:city":"New Milford",
    "sg:classifiers":[
        {
            "category":"Restaurant",
            "type":"Food & Drink"
        }
    ],
    "sg:menulink":"http://www.allmenus.com/ct/new-milford/144265-subway/menu/",
    "sg:phone":"+1 860 915 1032",
    "sg:postcode":"06776",
    "sg:province":"CT",
    "sg:tags":[
        "american",
        "sandwich"
    ],
    "wof:name":"Subway",
    "wof:placetype":"venue"
},
  "geometry": {"coordinates":[-73.406263,41.601731],"type":"Point"}
}