{
  "type": "Feature",
  "properties": {
    "iso:country":"US",
    "sg:address":"1210 New Haven Rd",
    "sg:city":"Naugatuck",
    "sg:classifiers":[
        {
            "category":"Education",
            "subcategory":"Preschool",
            "type":"Public Place"
        }
    ],
    "sg:phone":"+1 203 729 0013",
    "sg:postcode":"06770",
    "sg:province":"CT",
    "sg:tags":[
        "school",
        "nursery"
    ],
    "wof:name":"Rainbowland Nursery School Ctr",
    "wof:placetype":"venue"
},
  "geometry": {"coordinates":[-73.021083,41.467882],"type":"Point"}
}