{
  "type": "Feature",
  "properties": {
    "addr:full":"12 Palestine Rd Newtown CT 06470",
    "addr:housenumber":"12",
    "addr:postcode":"06470",
    "addr:street":"Palestine Rd",
    "iso:country":"US",
    "sg:address":"12 Palestine Rd",
    "sg:city":"Newtown",
    "sg:classifiers":[
        {
            "category":"Professional",
            "subcategory":"Employment Agencies",
            "type":"Services"
        }
    ],
    "sg:phone":"+1   ",
    "sg:postcode":"06470",
    "sg:province":"CT",
    "wof:name":"Russo Staffing",
    "wof:placetype":"venue"
},
  "geometry": {"coordinates":[-73.313446,41.370648],"type":"Point"}
}