{
  "type": "Feature",
  "properties": {
    "addr:full":"161 Whalley Ave New Haven CT 06511",
    "addr:housenumber":"161",
    "addr:postcode":"06511",
    "addr:street":"Whalley Ave",
    "iso:country":"US",
    "sg:address":"161 Whalley Ave",
    "sg:city":"New Haven",
    "sg:classifiers":[
        {
            "category":"Building & Trades",
            "subcategory":"Equipment Rental",
            "type":"Services"
        }
    ],
    "sg:phone":"+1 203 776 1300",
    "sg:postcode":"06511",
    "sg:province":"CT",
    "sg:tags":[
        "yard"
    ],
    "wof:name":"Rent-A-Center",
    "wof:placetype":"venue"
},
  "geometry": {"coordinates":[-72.937478,41.314885],"type":"Point"}
}