{
  "type": "Feature",
  "properties": {
    "addr:full":"310 Albany Tpke Canton CT 06019",
    "addr:housenumber":"310",
    "addr:postcode":"06019",
    "addr:street":"Albany Tpke Canton Ct",
    "iso:country":"US",
    "sg:address":"310 Albany Tpke",
    "sg:city":"Canton",
    "sg:classifiers":[
        {
            "category":"Sports & Exercise",
            "subcategory":"Tennis Court",
            "type":"Entertainment"
        }
    ],
    "sg:phone":"+1 860 693 4814",
    "sg:postcode":"06019",
    "sg:province":"CT",
    "sg:website":"www.cantonracquet.com",
    "wof:name":"Canton Racquet Club",
    "wof:placetype":"venue"
},
  "geometry": {"coordinates":[-72.90100099999999,41.828999],"type":"Point"}
}