{
  "type": "Feature",
  "properties": {
    "addr:full":"3 Simm Ln Newtown CT 06470",
    "addr:housenumber":"3",
    "addr:postcode":"06470",
    "addr:street":"Simm Ln",
    "iso:country":"US",
    "sg:address":"3 Simm Ln",
    "sg:city":"Newtown",
    "sg:classifiers":[
        {
            "category":"Building & Trades",
            "subcategory":"Construction",
            "type":"Services"
        }
    ],
    "sg:phone":"+1 203 270 9829",
    "sg:postcode":"06470",
    "sg:province":"CT",
    "sg:tags":[
        "repairing",
        "remodeling",
        "contractor"
    ],
    "sg:website":"www.windowland.net",
    "wof:name":"Windowland",
    "wof:placetype":"venue"
},
  "geometry": {"coordinates":[-73.287119,41.391881],"type":"Point"}
}