{
  "type": "Feature",
  "properties": {
    "iso:country":"US",
    "sg:address":"20 Highview Dr",
    "sg:city":"Rocky Hill",
    "sg:classifiers":[
        {
            "category":"Shopping",
            "subcategory":"Crafts & Fabrics",
            "type":"Retail Goods"
        }
    ],
    "sg:phone":"+1 860 529 3630",
    "sg:postcode":"06067",
    "sg:province":"CT",
    "sg:tags":[
        "sewing"
    ],
    "wof:name":"Romar Fabrics Inc",
    "wof:placetype":"venue"
},
  "geometry": {"coordinates":[-72.65014600000001,41.64346],"type":"Point"}
}