{
  "type": "Feature",
  "properties": {
    "addr:full":"2001 W Main St Stamford CT 06902",
    "addr:housenumber":"2001",
    "addr:postcode":"06902",
    "addr:street":"W Main St",
    "iso:country":"US",
    "sg:address":"2001 W Main St",
    "sg:city":"Stamford",
    "sg:classifiers":[
        {
            "category":"Autos & Motor Vehicles",
            "subcategory":"Fuel & Gas Station",
            "type":"Retail Goods"
        }
    ],
    "sg:phone":"+1 203 327 4773",
    "sg:postcode":"06902",
    "sg:province":"CT",
    "sg:tags":[
        "oil"
    ],
    "sg:website":"www.gasda.org",
    "wof:name":"Gasoline & Automotive Svc",
    "wof:placetype":"venue"
},
  "geometry": {"coordinates":[-73.563479,41.048911],"type":"Point"}
}