{
  "type": "Feature",
  "properties": {
    "iso:country":"US",
    "sg:address":"1248 Boston Post Rd",
    "sg:city":"Westbrook",
    "sg:classifiers":[
        {
            "category":"Professional",
            "subcategory":"Lawyer & Legal Services",
            "type":"Services"
        }
    ],
    "sg:phone":"+1   ",
    "sg:postcode":"06498",
    "sg:province":"CT",
    "wof:name":"James A McGee Jr",
    "wof:placetype":"venue"
},
  "geometry": {"coordinates":[-72.44558000000001,41.284628],"type":"Point"}
}