{
  "type": "Feature",
  "properties": {
    "iso:country":"US",
    "sg:address":"440 Freeman Ave",
    "sg:city":"Stratford",
    "sg:classifiers":[
        {
            "category":"Food & Beverages",
            "subcategory":"Bakery",
            "type":"Retail Goods"
        },
        {
            "category":"Bakery",
            "type":"Food & Drink"
        }
    ],
    "sg:phone":"+1 347 728 3978",
    "sg:postcode":"06614",
    "sg:province":"CT",
    "sg:tags":[
        "bakers-wholesale"
    ],
    "wof:name":"Antonio Fernandes",
    "wof:placetype":"venue"
},
  "geometry": {"coordinates":[-73.13864700000001,41.208795],"type":"Point"}
}