{
  "type": "Feature",
  "properties": {
    "addr:full":"1 Wildwood Ter Essex CT 06401",
    "addr:housenumber":"1",
    "addr:postcode":"06401",
    "addr:street":"Wildwood Ter Essex Ct",
    "iso:country":"US",
    "sg:address":"1 Wildwood Ter",
    "sg:city":"Essex",
    "sg:classifiers":[
        {
            "category":"Health Services",
            "subcategory":"Doctor",
            "type":"Services"
        }
    ],
    "sg:phone":"+1   ",
    "sg:postcode":"06401",
    "sg:province":"CT",
    "sg:tags":[
        "medical"
    ],
    "wof:name":"Burke Kenneth MD",
    "wof:placetype":"venue"
},
  "geometry": {"coordinates":[-73.04628,41.32756],"type":"Point"}
}