{
  "type": "Feature",
  "properties": {
    "addr:full":"18 Dog Ln Storrs Mansfield CT 06268",
    "addr:housenumber":"18",
    "addr:postcode":"06268",
    "addr:street":"Dog Ln;Mansfield Ct",
    "iso:country":"US",
    "sg:address":"18 Dog Ln",
    "sg:city":"Storrs Mansfield",
    "sg:classifiers":[
        {
            "category":"Professional",
            "subcategory":"Management & Consulting",
            "type":"Services"
        }
    ],
    "sg:phone":"+1   ",
    "sg:postcode":"06268",
    "sg:province":"CT",
    "wof:name":"Academic Keys LLC",
    "wof:placetype":"venue"
},
  "geometry": {"coordinates":[-72.243843,41.804504],"type":"Point"}
}