{
  "type": "Feature",
  "properties": {
    "addr:full":"163 Cherry St Milford CT 06460",
    "addr:housenumber":"163",
    "addr:postcode":"06460",
    "addr:street":"Cherry St",
    "iso:country":"US",
    "sg:address":"163 Cherry St",
    "sg:city":"Milford",
    "sg:classifiers":[
        {
            "category":"Recreation",
            "type":"Entertainment"
        }
    ],
    "sg:phone":"+1   ",
    "sg:postcode":"06460",
    "sg:province":"CT",
    "wof:name":"World Champion Tae KWON Do",
    "wof:placetype":"venue"
},
  "geometry": {"coordinates":[-73.0491,41.228971],"type":"Point"}
}