{
  "type": "Feature",
  "properties": {
    "addr:full":"21 Overlook Dr Hamden CT 06514",
    "addr:housenumber":"21",
    "addr:postcode":"06514",
    "addr:street":"Overlook Dr",
    "iso:country":"US",
    "sg:address":"21 Overlook Dr",
    "sg:city":"Hamden",
    "sg:classifiers":[
        {
            "category":"Building & Trades",
            "subcategory":"Construction",
            "type":"Services"
        }
    ],
    "sg:phone":"+1 203 848 1290",
    "sg:postcode":"06514",
    "sg:province":"CT",
    "sg:tags":[
        "bathroom",
        "remodeling"
    ],
    "sg:website":"www.rebath.com",
    "wof:name":"Rebath Of Connecticut",
    "wof:placetype":"venue"
},
  "geometry": {"coordinates":[-72.920306,41.402159],"type":"Point"}
}