{
  "type": "Feature",
  "properties": {
    "iso:country":"US",
    "sg:address":"15 Water St",
    "sg:city":"Torrington",
    "sg:classifiers":[
        {
            "category":"Shopping",
            "subcategory":"Hobbies, Toys, & Games",
            "type":"Retail Goods"
        }
    ],
    "sg:phone":"+1 860 626 7118",
    "sg:postcode":"06790",
    "sg:province":"CT",
    "wof:name":"Greene Fox Gallery LLC",
    "wof:placetype":"venue"
},
  "geometry": {"coordinates":[-73.12268299999999,41.801316],"type":"Point"}
}