{
  "type": "Feature",
  "properties": {
    "addr:full":"41 Holmes Ave Waterbury CT 06710",
    "addr:housenumber":"41",
    "addr:postcode":"06710",
    "addr:street":"Holmes Ave",
    "iso:country":"US",
    "sg:address":"41 Holmes Ave",
    "sg:city":"Waterbury",
    "sg:classifiers":[
        {
            "category":"Professional",
            "subcategory":"Lawyer & Legal Services",
            "type":"Services"
        }
    ],
    "sg:phone":"+1 203 754 8645",
    "sg:postcode":"06710",
    "sg:province":"CT",
    "sg:tags":[
        "attorney"
    ],
    "wof:name":"Thomas R Frizzell",
    "wof:placetype":"venue"
},
  "geometry": {"coordinates":[-73.04451899999999,41.559323],"type":"Point"}
}