{
  "type": "Feature",
  "properties": {
    "iso:country":"US",
    "sg:address":"2052 Shippan Ave",
    "sg:city":"Stamford",
    "sg:classifiers":[
        {
            "category":"Manufacturing",
            "subcategory":"Printing",
            "type":"Manufacturing & Wholesale Goods"
        }
    ],
    "sg:phone":"+1 203 964 1888",
    "sg:postcode":"06902",
    "sg:province":"CT",
    "sg:tags":[
        "book"
    ],
    "wof:name":"Weddles",
    "wof:placetype":"venue"
},
  "geometry": {"coordinates":[-73.523117,41.02572],"type":"Point"}
}