{
  "type": "Feature",
  "properties": {
    "iso:country":"US",
    "sg:address":"58 Rings End Rd",
    "sg:city":"Darien",
    "sg:classifiers":[
        {
            "category":"Insurance",
            "subcategory":"Insurance Agent",
            "type":"Services"
        }
    ],
    "sg:phone":"+1 203 964 6100",
    "sg:postcode":"06820",
    "sg:province":"CT",
    "sg:tags":[
        "advisory",
        "life"
    ],
    "wof:name":"Evergreen Group Incorporated",
    "wof:placetype":"venue"
},
  "geometry": {"coordinates":[-73.48182799999999,41.057406],"type":"Point"}
}