{
  "type": "Feature",
  "properties": {
    "iso:country":"US",
    "sg:address":"23 Danbury Rd",
    "sg:city":"Ridgefield",
    "sg:classifiers":[
        {
            "category":"Insurance",
            "subcategory":"Insurance Agent",
            "type":"Services"
        }
    ],
    "sg:phone":"+1 203 438 1466",
    "sg:postcode":"06877",
    "sg:province":"CT",
    "wof:name":"Prudential",
    "wof:placetype":"venue"
},
  "geometry": {"coordinates":[-73.49866,41.289615],"type":"Point"}
}