{
  "type": "Feature",
  "properties": {
    "iso:country":"US",
    "sg:address":"25 Danbury Rd",
    "sg:city":"Ridgefield",
    "sg:classifiers":[
        {
            "category":"Personal",
            "subcategory":"Beauty Salon",
            "type":"Services"
        }
    ],
    "sg:phone":"+1 203 438 2859",
    "sg:postcode":"06877",
    "sg:province":"CT",
    "wof:name":"Supercuts",
    "wof:placetype":"venue"
},
  "geometry": {"coordinates":[-73.498465,41.289646],"type":"Point"}
}