{
  "type": "Feature",
  "properties": {
    "iso:country":"US",
    "sg:address":"200 Goffe St",
    "sg:city":"New Haven",
    "sg:classifiers":[
        {
            "category":"Real Estate",
            "subcategory":"Real Estate Operator",
            "type":"Services"
        }
    ],
    "sg:phone":"+1 203 787 4063",
    "sg:postcode":"06511",
    "sg:province":"CT",
    "sg:tags":[
        "apartment"
    ],
    "wof:name":"St Martin's Townehouses",
    "wof:placetype":"venue"
},
  "geometry": {"coordinates":[-72.93862799999999,41.318498],"type":"Point"}
}