{
  "type": "Feature",
  "properties": {
    "iso:country":"US",
    "sg:address":"99 Bank St",
    "sg:city":"Waterbury",
    "sg:classifiers":[
        {
            "category":"Arts & Performance",
            "subcategory":"Art Gallery",
            "type":"Entertainment"
        },
        {
            "category":"Farming",
            "subcategory":"Fish & Marine Products",
            "type":"Manufacturing & Wholesale Goods"
        },
        {
            "category":"Professional",
            "subcategory":"Art Services",
            "type":"Services"
        },
        {
            "category":"Shopping",
            "subcategory":"Crafts & Fabrics",
            "type":"Retail Goods"
        }
    ],
    "sg:phone":"+1 203 757 0356",
    "sg:postcode":"06702",
    "sg:province":"CT",
    "sg:tags":[
        "picture",
        "supply",
        "consultant",
        "frame",
        "galleries",
        "framing"
    ],
    "sg:website":"http://www.goldsmithsartandframegallery.com",
    "wof:name":"Goldsmiths Art & Frame Gallery",
    "wof:placetype":"venue"
},
  "geometry": {"coordinates":[-73.041003,41.554247],"type":"Point"}
}