{
  "type": "Feature",
  "properties": {
    "iso:country":"US",
    "sg:address":"744 Main St",
    "sg:city":"Somers",
    "sg:classifiers":[
        {
            "category":"Retail",
            "subcategory":"Animal Services",
            "type":"Services"
        }
    ],
    "sg:phone":"+1 860 749 4531",
    "sg:postcode":"06071",
    "sg:province":"CT",
    "wof:name":"Red House Kennels",
    "wof:placetype":"venue"
},
  "geometry": {"coordinates":[-72.434303,41.984626],"type":"Point"}
}