{
  "type": "Feature",
  "properties": {
    "iso:country":"US",
    "sg:address":"53 Larkin St",
    "sg:city":"Stamford",
    "sg:classifiers":[
        {
            "category":"Building & Trades",
            "subcategory":"Landscaping Services",
            "type":"Services"
        }
    ],
    "sg:phone":"+1 203 967 3186",
    "sg:postcode":"06907",
    "sg:province":"CT",
    "sg:tags":[
        "landscape",
        "contractor"
    ],
    "sg:website":"www.landserv.com",
    "wof:name":"Landserv Inc",
    "wof:placetype":"venue"
},
  "geometry": {"coordinates":[-73.51903900000001,41.078032],"type":"Point"}
}