{
  "type": "Feature",
  "properties": {
    "addr:full":"365 Main St Watertown CT 06795",
    "addr:housenumber":"365",
    "addr:postcode":"06795",
    "addr:street":"Main St",
    "iso:country":"US",
    "sg:address":"365 Main St",
    "sg:city":"Watertown",
    "sg:classifiers":[
        {
            "category":"Real Estate",
            "subcategory":"Real Estate Services",
            "type":"Services"
        },
        {
            "category":"Professional",
            "subcategory":"Lawyer & Legal Services",
            "type":"Services"
        }
    ],
    "sg:phone":"+1 860 274 0018",
    "sg:postcode":"06795",
    "sg:province":"CT",
    "sg:tags":[
        "attorney",
        "title"
    ],
    "sg:website":"http://www.pilicy.com",
    "wof:name":"Pilicy Franklin G",
    "wof:placetype":"venue"
},
  "geometry": {"coordinates":[-73.117857,41.605323],"type":"Point"}
}