{
  "type": "Feature",
  "properties": {
    "iso:country":"US",
    "sg:address":"3 Old County Way",
    "sg:city":"Portland",
    "sg:classifiers":[
        {
            "category":"Professional",
            "subcategory":"Business Services",
            "type":"Services"
        }
    ],
    "sg:phone":"+1   ",
    "sg:postcode":"06480",
    "sg:province":"CT",
    "wof:name":"Weisser Solutions LLC",
    "wof:placetype":"venue"
},
  "geometry": {"coordinates":[-72.604966,41.63522],"type":"Point"}
}