{
  "type": "Feature",
  "properties": {
    "iso:country":"US",
    "sg:address":"165 Center St",
    "sg:city":"Shelton",
    "sg:classifiers":[
        {
            "category":"Shopping",
            "subcategory":"Hobbies, Toys, & Games",
            "type":"Retail Goods"
        }
    ],
    "sg:phone":"+1 203 924 8697",
    "sg:postcode":"06484",
    "sg:province":"CT",
    "wof:name":"Lizotte's Magic & Toy Shop",
    "wof:placetype":"venue"
},
  "geometry": {"coordinates":[-73.09587399999999,41.314686],"type":"Point"}
}