{
  "type": "Feature",
  "properties": {
    "iso:country":"US",
    "sg:address":"39 Saxon Woods",
    "sg:city":"Avon",
    "sg:classifiers":[
        {
            "category":"Arts & Performance",
            "subcategory":"Art Gallery",
            "type":"Entertainment"
        }
    ],
    "sg:phone":"+1 860 675 1609",
    "sg:postcode":"06001",
    "sg:province":"CT",
    "wof:name":"Berg Associates Inc",
    "wof:placetype":"venue"
},
  "geometry": {"coordinates":[-72.884804,41.799099],"type":"Point"}
}