{
  "type": "Feature",
  "properties": {
    "addr:full":"363 Spindle Hill Rd Wolcott CT 06716",
    "addr:housenumber":"363",
    "addr:postcode":"06716",
    "addr:street":"Spindle Hill Rd Wolcott Ct",
    "iso:country":"US",
    "sg:address":"363 Spindle Hill Rd",
    "sg:city":"Wolcott",
    "sg:classifiers":[
        {
            "category":"Social Services",
            "subcategory":"Child Care",
            "type":"Services"
        }
    ],
    "sg:phone":"+1 203 879 9777",
    "sg:postcode":"06716",
    "sg:province":"CT",
    "wof:name":"Care-A-Lot Day Care",
    "wof:placetype":"venue"
},
  "geometry": {"coordinates":[-73.005639,41.612138],"type":"Point"}
}