{
  "type": "Feature",
  "properties": {
    "iso:country":"US",
    "sg:address":"104 S Turnpike Rd",
    "sg:city":"Wallingford",
    "sg:classifiers":[
        {
            "category":"Government",
            "subcategory":"Office",
            "type":"Public Place"
        }
    ],
    "sg:phone":"+1 203 294 5049",
    "sg:postcode":"06492",
    "sg:province":"CT",
    "sg:tags":[
        "state",
        "program",
        "health"
    ],
    "wof:name":"Mental Health Dept",
    "wof:placetype":"venue"
},
  "geometry": {"coordinates":[-72.84780600000001,41.441769],"type":"Point"}
}