{
  "type": "Feature",
  "properties": {
    "addr:full":"574 Monroe Tpke Monroe CT 06468",
    "addr:housenumber":"574",
    "addr:postcode":"06468",
    "addr:street":"Monroe Tpke Monroe Ct",
    "iso:country":"US",
    "sg:address":"574 Monroe Tpke",
    "sg:city":"Monroe",
    "sg:classifiers":[
        {
            "category":"Shopping",
            "subcategory":"Used Merchandise",
            "type":"Retail Goods"
        }
    ],
    "sg:phone":"+1 203 445 0884",
    "sg:postcode":"06468",
    "sg:province":"CT",
    "sg:tags":[
        "shop",
        "thrift"
    ],
    "wof:name":"Goodwill Industries",
    "wof:placetype":"venue"
},
  "geometry": {"coordinates":[-73.21216099999999,41.320752],"type":"Point"}
}