{
  "type": "Feature",
  "properties": {
    "addr:full":"530 Enfield St Enfield CT 06082",
    "addr:housenumber":"530",
    "addr:postcode":"06082",
    "addr:street":"Enfield St Enfield Ct",
    "iso:country":"US",
    "sg:address":"530 Enfield St",
    "sg:city":"Enfield",
    "sg:classifiers":[
        {
            "category":"Building & Trades",
            "subcategory":"Construction",
            "type":"Services"
        }
    ],
    "sg:phone":"+1 860 741 8845",
    "sg:postcode":"06082",
    "sg:province":"CT",
    "sg:tags":[
        "real estate",
        "contractor"
    ],
    "wof:name":"First Choice Real Estate",
    "wof:placetype":"venue"
},
  "geometry": {"coordinates":[-72.593414,42.009191],"type":"Point"}
}