{
  "type": "Feature",
  "properties": {
    "iso:country":"US",
    "sg:address":"1 Carriage Pl",
    "sg:city":"Waterbury",
    "sg:classifiers":[
        {
            "category":"Professional",
            "subcategory":"Lawyer & Legal Services",
            "type":"Services"
        }
    ],
    "sg:phone":"+1 203 755 4465",
    "sg:postcode":"06702",
    "sg:province":"CT",
    "sg:tags":[
        "attorney"
    ],
    "wof:name":"Danielle S Rado Law Offices",
    "wof:placetype":"venue"
},
  "geometry": {"coordinates":[-73.041465,41.555355],"type":"Point"}
}