{
  "type": "Feature",
  "properties": {
    "iso:country":"US",
    "sg:address":"456 N Main St",
    "sg:city":"Southington",
    "sg:classifiers":[
        {
            "category":"Shopping",
            "subcategory":"Florist",
            "type":"Retail Goods"
        }
    ],
    "sg:phone":"+1 860 628 6636",
    "sg:postcode":"06489",
    "sg:province":"CT",
    "wof:name":"Nyren's Of New England Florist",
    "wof:placetype":"venue"
},
  "geometry": {"coordinates":[-72.87512099999999,41.612695],"type":"Point"}
}