{
  "type": "Feature",
  "properties": {
    "iso:country":"US",
    "sg:address":"17 Gifford Rd",
    "sg:city":"Hartford",
    "sg:classifiers":[
        {
            "category":"Professional",
            "subcategory":"Engineering",
            "type":"Services"
        }
    ],
    "sg:phone":"+1   ",
    "sg:postcode":"06119",
    "sg:province":"CT",
    "wof:name":"Electronic Pencil",
    "wof:placetype":"venue"
},
  "geometry": {"coordinates":[-72.733124,41.754554],"type":"Point"}
}