{
  "type": "Feature",
  "properties": {
    "iso:country":"US",
    "sg:address":"648 Pacific St",
    "sg:city":"Stamford",
    "sg:classifiers":[
        {
            "category":"Organizations",
            "subcategory":"Religious Organization",
            "type":"Services"
        }
    ],
    "sg:phone":"+1 203 327 5536",
    "sg:postcode":"06902",
    "sg:province":"CT",
    "sg:tags":[
        "church"
    ],
    "wof:name":"Pentecostal Mission John 3 16",
    "wof:placetype":"venue"
},
  "geometry": {"coordinates":[-73.537513,41.04357],"type":"Point"}
}