{
  "type": "Feature",
  "properties": {
    "addr:full":"203 Boston Hill Rd Andover CT 06232",
    "addr:housenumber":"203",
    "addr:postcode":"06232",
    "addr:street":"Boston Hill Rd",
    "iso:country":"US",
    "sg:address":"203 Boston Hill Rd",
    "sg:city":"Andover",
    "sg:classifiers":[
        {
            "category":"Professional",
            "subcategory":"Engineering",
            "type":"Services"
        }
    ],
    "sg:phone":"+1   ",
    "sg:postcode":"06232",
    "sg:province":"CT",
    "wof:name":"Ces Engineering",
    "wof:placetype":"venue"
},
  "geometry": {"coordinates":[-72.396365,41.72474],"type":"Point"}
}