{
  "type": "Feature",
  "properties": {
    "addr:full":"88 Woodhouse Ave Wallingford CT 06492",
    "addr:housenumber":"88",
    "addr:postcode":"06492",
    "addr:street":"Woodhouse Ave",
    "iso:country":"US",
    "sg:address":"88 Woodhouse Ave",
    "sg:city":"Wallingford",
    "sg:classifiers":[
        {
            "category":"Building & Trades",
            "subcategory":"Construction",
            "type":"Services"
        }
    ],
    "sg:phone":"+1 203 269 5703",
    "sg:postcode":"06492",
    "sg:province":"CT",
    "sg:tags":[
        "house",
        "apartment",
        "ope",
        "contractor"
    ],
    "wof:name":"Ahearn Builders LLC",
    "wof:placetype":"venue"
},
  "geometry": {"coordinates":[-72.804299,41.444913],"type":"Point"}
}