{
  "type": "Feature",
  "properties": {
    "addr:full":"24 Olde Meadow Rd Woodstock CT 06281",
    "addr:housenumber":"24",
    "addr:postcode":"06281",
    "addr:street":"Olde Meadow Rd",
    "iso:country":"US",
    "sg:address":"24 Olde Meadow Rd",
    "sg:city":"Woodstock",
    "sg:classifiers":[
        {
            "category":"Personal",
            "subcategory":"Beauty Salon",
            "type":"Services"
        }
    ],
    "sg:phone":"+1 860 315 5055",
    "sg:postcode":"06281",
    "sg:province":"CT",
    "wof:name":"The Perfect Look-Make-Up Artistry",
    "wof:placetype":"venue"
},
  "geometry": {"coordinates":[-71.981238,41.999383],"type":"Point"}
}