{
  "type": "Feature",
  "properties": {
    "iso:country":"US",
    "sg:address":"165 Pratt St",
    "sg:city":"Meriden",
    "sg:classifiers":[
        {
            "category":"Professional",
            "subcategory":"Employment Agencies",
            "type":"Services"
        }
    ],
    "sg:phone":"+1 203 235 2583",
    "sg:postcode":"06450",
    "sg:province":"CT",
    "sg:tags":[
        "help",
        "contractor"
    ],
    "wof:name":"Kuhn Employment Opportunities",
    "wof:placetype":"venue"
},
  "geometry": {"coordinates":[-72.793808,41.54025],"type":"Point"}
}