{
  "type": "Feature",
  "properties": {
    "iso:country":"US",
    "sg:address":"2336 Fairfield Ave",
    "sg:city":"Bridgeport",
    "sg:classifiers":[
        {
            "category":"Shopping",
            "subcategory":"Used Merchandise",
            "type":"Retail Goods"
        }
    ],
    "sg:phone":"+1 203 333 5311",
    "sg:postcode":"06605",
    "sg:province":"CT",
    "sg:tags":[
        "pawnbroker"
    ],
    "sg:website":"www.thepawnbroker.com",
    "wof:name":"Joe Davis Pawnbroker",
    "wof:placetype":"venue"
},
  "geometry": {"coordinates":[-73.220975,41.163283],"type":"Point"}
}