{
  "type": "Feature",
  "properties": {
    "addr:full":"932 Quinnipiac Ave New Haven CT 06513",
    "addr:housenumber":"932",
    "addr:postcode":"06513",
    "addr:street":"Quinnipiac Ave",
    "iso:country":"US",
    "sg:address":"932 Quinnipiac Ave",
    "sg:city":"New Haven",
    "sg:classifiers":[
        {
            "category":"Retail",
            "subcategory":"Repair Shop",
            "type":"Services"
        }
    ],
    "sg:phone":"+1   ",
    "sg:postcode":"06513",
    "sg:province":"CT",
    "wof:name":"Cooking On TV LLC",
    "wof:placetype":"venue"
},
  "geometry": {"coordinates":[-72.88155,41.311582],"type":"Point"}
}