{
  "type": "Feature",
  "properties": {
    "iso:country":"US",
    "sg:address":"135 Church St",
    "sg:city":"Guilford",
    "sg:classifiers":[
        {
            "category":"Education",
            "subcategory":"Special Training",
            "type":"Public Place"
        }
    ],
    "sg:phone":"+1 203 453 5067",
    "sg:postcode":"06437",
    "sg:province":"CT",
    "sg:tags":[
        "tutoring"
    ],
    "sg:website":"www.handleassociates.com",
    "wof:name":"Handle Associates/Kumon Math",
    "wof:placetype":"venue"
},
  "geometry": {"coordinates":[-72.684445,41.289381],"type":"Point"}
}