{
  "type": "Feature",
  "properties": {
    "iso:country":"US",
    "sg:address":"29 Grove St",
    "sg:city":"Stamford",
    "sg:classifiers":[
        {
            "category":"Organizations",
            "subcategory":"Religious Organization",
            "type":"Services"
        }
    ],
    "sg:phone":"+1   ",
    "sg:postcode":"06901",
    "sg:province":"CT",
    "wof:name":"Mark Of Excellence Pre-School",
    "wof:placetype":"venue"
},
  "geometry": {"coordinates":[-73.53324499999999,41.054011],"type":"Point"}
}