{
  "type": "Feature",
  "properties": {
    "addr:full":"101 Barr Rd Meriden CT 06450",
    "addr:housenumber":"101",
    "addr:postcode":"06450",
    "addr:street":"Barr Rd",
    "iso:country":"US",
    "sg:address":"101 Barr Rd",
    "sg:city":"Meriden",
    "sg:classifiers":[
        {
            "category":"Retail",
            "subcategory":"Repair Shop",
            "type":"Services"
        }
    ],
    "sg:phone":"+1 203 634 7600",
    "sg:postcode":"06450",
    "sg:province":"CT",
    "sg:tags":[
        "lock",
        "locksmith"
    ],
    "wof:name":"Absolute Security Inc",
    "wof:placetype":"venue"
},
  "geometry": {"coordinates":[-72.774925,41.515336],"type":"Point"}
}