{
  "type": "Feature",
  "properties": {
    "addr:full":"35 Shamrock Dr Brookfield CT 06804",
    "addr:housenumber":"35",
    "addr:postcode":"06804",
    "addr:street":"Shamrock Dr",
    "iso:country":"US",
    "sg:address":"35 Shamrock Dr",
    "sg:city":"Brookfield",
    "sg:classifiers":[
        {
            "category":"Recreation",
            "type":"Entertainment"
        }
    ],
    "sg:phone":"+1 203 775 9094",
    "sg:postcode":"06804",
    "sg:province":"CT",
    "sg:tags":[
        "instruction",
        "yoga"
    ],
    "wof:name":"Still River Yoga Center LLC",
    "wof:placetype":"venue"
},
  "geometry": {"coordinates":[-73.398652,41.485342],"type":"Point"}
}