{
  "type": "Feature",
  "properties": {
    "addr:full":"327 Willetts Ave Waterford CT 06385",
    "addr:housenumber":"327",
    "addr:postcode":"06385",
    "addr:street":"Willetts Ave",
    "iso:country":"US",
    "sg:address":"327 Willetts Ave",
    "sg:city":"Waterford",
    "sg:classifiers":[
        {
            "category":"Professional",
            "subcategory":"Accounting & Tax Preparation",
            "type":"Services"
        }
    ],
    "sg:phone":"+1   ",
    "sg:postcode":"06385",
    "sg:province":"CT",
    "wof:name":"Demarco R Rssell Pub Accuntant",
    "wof:placetype":"venue"
},
  "geometry": {"coordinates":[-72.119968,41.341566],"type":"Point"}
}