{
  "type": "Feature",
  "properties": {
    "iso:country":"US",
    "sg:address":"1 Lafayette Ct",
    "sg:city":"Greenwich",
    "sg:classifiers":[
        {
            "category":"Organizations",
            "subcategory":"Non-profit Organization",
            "type":"Services"
        }
    ],
    "sg:phone":"+1   ",
    "sg:postcode":"06830",
    "sg:province":"CT",
    "sg:tags":[
        "consulting",
        "management",
        "social"
    ],
    "wof:name":"United Way of Greenwich Inc",
    "wof:placetype":"venue"
},
  "geometry": {"coordinates":[-73.629009,41.031915],"type":"Point"}
}