{
  "type": "Feature",
  "properties": {
    "iso:country":"US",
    "sg:address":"25 Northwest Dr",
    "sg:city":"Watertown",
    "sg:classifiers":[
        {
            "category":"Landmark",
            "subcategory":"Tourist Information",
            "type":"Public Place"
        }
    ],
    "sg:phone":"+1 860 945 6784",
    "sg:postcode":"06795",
    "sg:province":"CT",
    "sg:tags":[
        "promoter",
        "tours-operators"
    ],
    "wof:name":"American Motorcycle Tour",
    "wof:placetype":"venue"
},
  "geometry": {"coordinates":[-73.11008,41.608223],"type":"Point"}
}