{
  "type": "Feature",
  "properties": {
    "addr:full":"10 Parallel St Norwalk CT 06850",
    "addr:housenumber":"10",
    "addr:postcode":"06850",
    "addr:street":"Parallel St",
    "iso:country":"US",
    "sg:address":"10 Parallel St",
    "sg:city":"Norwalk",
    "sg:classifiers":[
        {
            "category":"Professional",
            "subcategory":"Computer Services",
            "type":"Services"
        }
    ],
    "sg:phone":"+1   ",
    "sg:postcode":"06850",
    "sg:province":"CT",
    "sg:tags":[
        "programing",
        "custom"
    ],
    "wof:name":"Spearhead Enterprises Inc",
    "wof:placetype":"venue"
},
  "geometry": {"coordinates":[-73.43187399999999,41.124481],"type":"Point"}
}