{
  "type": "Feature",
  "properties": {
    "iso:country":"US",
    "sg:address":"2171 Black Rock Tpke",
    "sg:city":"Fairfield",
    "sg:classifiers":[
        {
            "category":"Coffee & Tea",
            "type":"Food & Drink"
        }
    ],
    "sg:menulink":"http://www.allmenus.com/ct/fairfield/108461-starbucks-coffee/menu/",
    "sg:phone":"+1 203 362 0347",
    "sg:postcode":"06825",
    "sg:province":"CT",
    "sg:tags":[
        "american"
    ],
    "wof:name":"Starbucks Coffee",
    "wof:placetype":"venue"
},
  "geometry": {"coordinates":[-73.252523,41.181942],"type":"Point"}
}