{
  "type": "Feature",
  "properties": {
    "iso:country":"US",
    "sg:address":"37 Huckleberry Hill Rd",
    "sg:city":"Brookfield",
    "sg:classifiers":[
        {
            "category":"Building & Trades",
            "subcategory":"Construction",
            "type":"Services"
        }
    ],
    "sg:phone":"+1 203 775 8713",
    "sg:postcode":"06804",
    "sg:province":"CT",
    "sg:tags":[
        "carpenter"
    ],
    "wof:name":"SMB Carpentry & Remodeling",
    "wof:placetype":"venue"
},
  "geometry": {"coordinates":[-73.415685,41.454525],"type":"Point"}
}