{
  "type": "Feature",
  "properties": {
    "addr:full":"888 Washington Blvd Stamford CT 06901",
    "addr:housenumber":"888",
    "addr:postcode":"06901",
    "addr:street":"Washington Blvd",
    "iso:country":"US",
    "sg:address":"888 Washington Blvd",
    "sg:city":"Stamford",
    "sg:classifiers":[
        {
            "category":"Professional",
            "type":"Services"
        }
    ],
    "sg:phone":"+1 203 977 4050",
    "sg:postcode":"06901",
    "sg:province":"CT",
    "sg:tags":[
        "establishment"
    ],
    "wof:name":"Commission On Aging",
    "wof:placetype":"venue"
},
  "geometry": {"coordinates":[-73.54232500000001,41.052571],"type":"Point"}
}