{
  "type": "Feature",
  "properties": {
    "iso:country":"US",
    "sg:address":"30 Conifer Dr",
    "sg:city":"Northford",
    "sg:classifiers":[
        {
            "category":"Building & Trades",
            "subcategory":"Construction",
            "type":"Services"
        }
    ],
    "sg:phone":"+1 203 484 6706",
    "sg:postcode":"06472",
    "sg:province":"CT",
    "sg:tags":[
        "downspouts",
        "gutter"
    ],
    "wof:name":"C R Gutters",
    "wof:placetype":"venue"
},
  "geometry": {"coordinates":[-72.79937,41.40261],"type":"Point"}
}