{
  "type": "Feature",
  "properties": {
    "iso:country":"US",
    "sg:address":"411 North Rd",
    "sg:city":"Ashford",
    "sg:classifiers":[
        {
            "category":"Professional",
            "subcategory":"Business Services",
            "type":"Services"
        }
    ],
    "sg:phone":"+1   ",
    "sg:postcode":"06278",
    "sg:province":"CT",
    "wof:name":"Ashford Enterprises LLC",
    "wof:placetype":"venue"
},
  "geometry": {"coordinates":[-72.135728,41.901681],"type":"Point"}
}