{
  "type": "Feature",
  "properties": {
    "addr:full":"420 Westport Ave Norwalk CT 06851",
    "addr:housenumber":"420",
    "addr:postcode":"06851",
    "addr:street":"Westport Ave",
    "iso:country":"US",
    "sg:address":"420 Westport Ave",
    "sg:city":"Norwalk",
    "sg:classifiers":[
        {
            "category":"Cinema",
            "subcategory":"Movie Rental",
            "type":"Entertainment"
        }
    ],
    "sg:phone":"+1 203 846 4220",
    "sg:postcode":"06851",
    "sg:province":"CT",
    "sg:tags":[
        "leasing",
        "video",
        "disc",
        "tape"
    ],
    "sg:website":"www.blockbuster.com",
    "wof:name":"Blockbuster Video",
    "wof:placetype":"venue"
},
  "geometry": {"coordinates":[-73.38817400000001,41.126623],"type":"Point"}
}