{
  "type": "Feature",
  "properties": {
    "iso:country":"US",
    "sg:address":"116 Cook Ave",
    "sg:city":"Meriden",
    "sg:classifiers":[
        {
            "category":"Real Estate",
            "subcategory":"Real Estate Agent",
            "type":"Services"
        }
    ],
    "sg:phone":"+1 203 630 9260",
    "sg:postcode":"06451",
    "sg:province":"CT",
    "wof:name":"120 Cook Avenue Realty Inc",
    "wof:placetype":"venue"
},
  "geometry": {"coordinates":[-72.807936,41.534207],"type":"Point"}
}