{
  "type": "Feature",
  "properties": {
    "iso:country":"US",
    "sg:address":"167 Neck Rd",
    "sg:city":"Madison",
    "sg:classifiers":[
        {
            "category":"Professional",
            "subcategory":"Business Services",
            "type":"Services"
        }
    ],
    "sg:phone":"+1 203 245 0401",
    "sg:postcode":"06443",
    "sg:province":"CT",
    "sg:tags":[
        "conference",
        "center"
    ],
    "sg:website":"www.mercyctrmadison.com",
    "wof:name":"Mercy Center At Madison",
    "wof:placetype":"venue"
},
  "geometry": {"coordinates":[-72.634638,41.273198],"type":"Point"}
}