{
  "type": "Feature",
  "properties": {
    "addr:full":"253 E Main St Branford CT 06405",
    "addr:housenumber":"253",
    "addr:postcode":"06405",
    "addr:street":"E Main St",
    "iso:country":"US",
    "sg:address":"253 E Main St",
    "sg:city":"Branford",
    "sg:classifiers":[
        {
            "category":"Retail",
            "subcategory":"Auto Repair",
            "type":"Services"
        }
    ],
    "sg:phone":"+1   ",
    "sg:postcode":"06405",
    "sg:province":"CT",
    "sg:tags":[
        "general"
    ],
    "wof:name":"Petes Service",
    "wof:placetype":"venue"
},
  "geometry": {"coordinates":[-72.79564999999999,41.291078],"type":"Point"}
}