{
  "type": "Feature",
  "properties": {
    "addr:full":"83 Berwyn St Milford CT 06461",
    "addr:housenumber":"83",
    "addr:postcode":"06461",
    "addr:street":"Berwyn St",
    "iso:country":"US",
    "sg:address":"83 Berwyn St",
    "sg:city":"Milford",
    "sg:classifiers":[
        {
            "category":"Building & Trades",
            "subcategory":"Construction",
            "type":"Services"
        }
    ],
    "sg:phone":"+1 203 783 9655",
    "sg:postcode":"06461",
    "sg:province":"CT",
    "sg:tags":[
        "company"
    ],
    "wof:name":"MJS Construction",
    "wof:placetype":"venue"
},
  "geometry": {"coordinates":[-73.101305,41.205534],"type":"Point"}
}