{
  "type": "Feature",
  "properties": {
    "iso:country":"US",
    "sg:address":"25 Knowles Rd",
    "sg:city":"Middle Haddam",
    "sg:classifiers":[
        {
            "category":"Professional",
            "subcategory":"Business Services",
            "type":"Services"
        }
    ],
    "sg:phone":"+1   ",
    "sg:postcode":"06456",
    "sg:province":"CT",
    "sg:tags":[
        "public",
        "relations",
        "advertising"
    ],
    "wof:name":"Weintraub & Company",
    "wof:placetype":"venue"
},
  "geometry": {"coordinates":[-72.551996,41.550993],"type":"Point"}
}