{
  "type": "Feature",
  "properties": {
    "iso:country":"US",
    "sg:address":"1152 E Putnam Ave",
    "sg:city":"Riverside",
    "sg:classifiers":[
        {
            "category":"Insurance",
            "subcategory":"Insurance Agent",
            "type":"Services"
        }
    ],
    "sg:phone":"+1 203 661 8998",
    "sg:postcode":"06878",
    "sg:province":"CT",
    "wof:name":"State Farm Insurance",
    "wof:placetype":"venue"
},
  "geometry": {"coordinates":[-73.581936,41.04116],"type":"Point"}
}