{
  "type": "Feature",
  "properties": {
    "addr:full":"98 Cold Spring Rd Rocky Hill CT 06067",
    "addr:housenumber":"98",
    "addr:postcode":"06067",
    "addr:street":"Cold Spring Rd",
    "iso:country":"US",
    "sg:address":"98 Cold Spring Rd",
    "sg:city":"Rocky Hill",
    "sg:classifiers":[
        {
            "category":"Real Estate",
            "subcategory":"Real Estate Operator",
            "type":"Services"
        }
    ],
    "sg:phone":"+1 860 563 5300",
    "sg:postcode":"06067",
    "sg:province":"CT",
    "sg:tags":[
        "property",
        "management"
    ],
    "wof:name":"Century Hills Apartments",
    "wof:placetype":"venue"
},
  "geometry": {"coordinates":[-72.677638,41.64467],"type":"Point"}
}