{
  "type": "Feature",
  "properties": {
    "iso:country":"US",
    "sg:address":"25 West Ct",
    "sg:city":"Fairfield",
    "sg:classifiers":[
        {
            "category":"Food & Beverages",
            "subcategory":"Groceries & Convenience Stores",
            "type":"Retail Goods"
        }
    ],
    "sg:phone":"+1 203 319 9685",
    "sg:postcode":"06418",
    "sg:province":"CT",
    "wof:name":"Innovative Management & Market",
    "wof:placetype":"venue"
},
  "geometry": {"coordinates":[-73.049447,41.312787],"type":"Point"}
}