{
  "type": "Feature",
  "properties": {
    "addr:full":"5 Salem Straits Darien CT 06820",
    "addr:housenumber":"5",
    "addr:postcode":"06820",
    "addr:street":"Salem;Darien",
    "iso:country":"US",
    "sg:address":"5 Salem Straits",
    "sg:city":"Darien",
    "sg:classifiers":[
        {
            "category":"Professional",
            "subcategory":"Management & Consulting",
            "type":"Services"
        }
    ],
    "sg:phone":"+1   ",
    "sg:postcode":"06820",
    "sg:province":"CT",
    "sg:tags":[
        "business"
    ],
    "wof:name":"Granville Toogood Associates",
    "wof:placetype":"venue"
},
  "geometry": {"coordinates":[-73.47740400000001,41.057926],"type":"Point"}
}