{
  "type": "Feature",
  "properties": {
    "addr:full":"1212 E Putnam Ave Riverside CT 06878",
    "addr:housenumber":"1212",
    "addr:postcode":"06878",
    "addr:street":"E Putnam Ave Riverside Ct",
    "iso:country":"US",
    "sg:address":"1212 E Putnam Ave",
    "sg:city":"Riverside",
    "sg:classifiers":[
        {
            "category":"Personal",
            "subcategory":"Beauty Salon",
            "type":"Services"
        }
    ],
    "sg:phone":"+1   ",
    "sg:postcode":"06878",
    "sg:province":"CT",
    "sg:tags":[
        "shop"
    ],
    "wof:name":"Rose Nail Store",
    "wof:placetype":"venue"
},
  "geometry": {"coordinates":[-73.579904,41.041461],"type":"Point"}
}