{
  "type": "Feature",
  "properties": {
    "addr:full":"40 Heights Rd Darien CT 06820",
    "addr:housenumber":"40",
    "addr:postcode":"06820",
    "addr:street":"Heights Rd",
    "iso:country":"US",
    "sg:address":"40 Heights Rd",
    "sg:city":"Darien",
    "sg:classifiers":[
        {
            "category":"Insurance",
            "subcategory":"Insurance Agent",
            "type":"Services"
        }
    ],
    "sg:phone":"+1 203 655 9716",
    "sg:postcode":"06820",
    "sg:province":"CT",
    "wof:name":"Wj Deveral Insurance",
    "wof:placetype":"venue"
},
  "geometry": {"coordinates":[-73.493424,41.06913],"type":"Point"}
}