{
  "type": "Feature",
  "properties": {
    "addr:full":"14 Greenview Ter Middletown CT 06457",
    "addr:housenumber":"14",
    "addr:postcode":"06457",
    "addr:street":"Greenview Ter Middletown Ct",
    "iso:country":"US",
    "sg:address":"14 Greenview Ter",
    "sg:city":"Middletown",
    "sg:classifiers":[
        {
            "category":"Professional",
            "subcategory":"Management & Consulting",
            "type":"Services"
        }
    ],
    "sg:phone":"+1   ",
    "sg:postcode":"06457",
    "sg:province":"CT",
    "wof:name":"Research Triangle LLC",
    "wof:placetype":"venue"
},
  "geometry": {"coordinates":[-72.68405799999999,41.596878],"type":"Point"}
}