{
  "type": "Feature",
  "properties": {
    "addr:full":"31 Kaechele St Trumbull CT 06611",
    "addr:housenumber":"31",
    "addr:postcode":"06611",
    "addr:street":"Kaechele St",
    "iso:country":"US",
    "sg:address":"31 Kaechele St",
    "sg:city":"Trumbull",
    "sg:classifiers":[
        {
            "category":"Banks & Credit Unions",
            "subcategory":"Bank",
            "type":"Services"
        }
    ],
    "sg:phone":"+1 203 373 1738",
    "sg:postcode":"06611",
    "sg:province":"CT",
    "sg:tags":[
        "broker",
        "mortgage"
    ],
    "wof:name":"CJ Mortgage LLC",
    "wof:placetype":"venue"
},
  "geometry": {"coordinates":[-73.252616,41.253958],"type":"Point"}
}