{
  "type": "Feature",
  "properties": {
    "addr:full":"235 Main St Norwalk CT 06851",
    "addr:housenumber":"235",
    "addr:postcode":"06851",
    "addr:street":"Main St",
    "iso:country":"US",
    "sg:address":"235 Main St",
    "sg:city":"Norwalk",
    "sg:classifiers":[
        {
            "category":"Travel",
            "subcategory":"Travel Agent",
            "type":"Entertainment"
        }
    ],
    "sg:phone":"+1 203 846 3411",
    "sg:postcode":"06851",
    "sg:province":"CT",
    "sg:tags":[
        "agency",
        "bureau"
    ],
    "wof:name":"Happy Holidays Inc",
    "wof:placetype":"venue"
},
  "geometry": {"coordinates":[-73.42349900000001,41.130917],"type":"Point"}
}