{
  "type": "Feature",
  "properties": {
    "addr:full":"2 Greenwich Hills Dr Greenwich CT 06831",
    "addr:housenumber":"2",
    "addr:postcode":"06831",
    "addr:street":"Greenwich Hills Dr",
    "iso:country":"US",
    "sg:address":"2 Greenwich Hills Dr",
    "sg:city":"Greenwich",
    "sg:classifiers":[
        {
            "category":"Banks & Credit Unions",
            "subcategory":"Investment Brokerage",
            "type":"Services"
        }
    ],
    "sg:phone":"+1 203 661 8350",
    "sg:postcode":"06831",
    "sg:province":"CT",
    "sg:tags":[
        "advisory",
        "security"
    ],
    "wof:name":"Ardshiel Inc Delaware",
    "wof:placetype":"venue"
},
  "geometry": {"coordinates":[-73.665171,41.025933],"type":"Point"}
}