{
  "type": "Feature",
  "properties": {
    "iso:country":"US",
    "sg:address":"157 Shelter Rock Rd",
    "sg:city":"Danbury",
    "sg:classifiers":[
        {
            "category":"Building & Trades",
            "subcategory":"Landscaping Services",
            "type":"Services"
        }
    ],
    "sg:phone":"+1 203 746 0841",
    "sg:postcode":"06810",
    "sg:province":"CT",
    "sg:tags":[
        "lawn",
        "maintenance",
        "grounds"
    ],
    "wof:name":"D G's Lawn Maintenance",
    "wof:placetype":"venue"
},
  "geometry": {"coordinates":[-73.419112,41.395075],"type":"Point"}
}