{
  "type": "Feature",
  "properties": {
    "addr:full":"40 Nida Dr Northford CT 06472",
    "addr:housenumber":"40",
    "addr:postcode":"06472",
    "addr:street":"Nida Dr Northford Ct",
    "iso:country":"US",
    "sg:address":"40 Nida Dr",
    "sg:city":"Northford",
    "sg:classifiers":[
        {
            "category":"Professional",
            "subcategory":"Business Services",
            "type":"Services"
        },
        {
            "category":"Professional",
            "subcategory":"Employment Agencies",
            "type":"Services"
        }
    ],
    "sg:phone":"+1 203 484 0073",
    "sg:postcode":"06472",
    "sg:province":"CT",
    "sg:tags":[
        "opportunity"
    ],
    "wof:name":"Seek Technologies Inc",
    "wof:placetype":"venue"
},
  "geometry": {"coordinates":[-72.81187300000001,41.385672],"type":"Point"}
}