{
  "type": "Feature",
  "properties": {
    "addr:full":"28 N Main St Kent CT 06757",
    "addr:housenumber":"28",
    "addr:postcode":"06757",
    "addr:street":"N Main St",
    "iso:country":"US",
    "sg:address":"28 N Main St",
    "sg:city":"Kent",
    "sg:classifiers":[
        {
            "category":"Restaurant",
            "type":"Food & Drink"
        }
    ],
    "sg:phone":"+1 860 927 1555",
    "sg:postcode":"06757",
    "sg:province":"CT",
    "sg:website":"http://www.villagerkent.com",
    "wof:name":"Villager Restaurant & Catering",
    "wof:placetype":"venue"
},
  "geometry": {"coordinates":[-73.47628899999999,41.725768],"type":"Point"}
}