{
  "type": "Feature",
  "properties": {
    "addr:full":"701 Cottage Grove Rd A Bloomfield CT 06002",
    "addr:housenumber":"701",
    "addr:postcode":"06002",
    "addr:street":"Cottage Grove Rd;Bloomfield",
    "iso:country":"US",
    "sg:address":"701 Cottage Grove Rd A",
    "sg:city":"Bloomfield",
    "sg:classifiers":[
        {
            "category":"Health Services",
            "subcategory":"Doctor",
            "type":"Services"
        }
    ],
    "sg:phone":"+1 860 242 5274",
    "sg:postcode":"06002",
    "sg:province":"CT",
    "sg:tags":[
        "physician",
        "pediatrics-otorhinolaryngology",
        "surgeons",
        "otorhinolaryngology",
        "nose",
        "throat",
        "surgeon",
        "ear"
    ],
    "wof:name":"Snyder, G Gordon Iii Md",
    "wof:placetype":"venue"
},
  "geometry": {"coordinates":[-72.73358500000001,41.816943],"type":"Point"}
}