{
  "type": "Feature",
  "properties": {
    "addr:full":"1 Willow Point Essex CT 06426",
    "addr:housenumber":"1",
    "addr:postcode":"06426",
    "addr:street":"Willow Point Essex Ct",
    "iso:country":"US",
    "sg:address":"1 Willow Point",
    "sg:city":"Essex",
    "sg:classifiers":[
        {
            "category":"Building & Trades",
            "subcategory":"Construction",
            "type":"Services"
        }
    ],
    "sg:phone":"+1 860 304 8383",
    "sg:postcode":"06426",
    "sg:province":"CT",
    "sg:tags":[
        "contractor"
    ],
    "sg:website":"www.sapiacorp.com",
    "wof:name":"The Sapia Corporation",
    "wof:placetype":"venue"
},
  "geometry": {"coordinates":[-72.391203,41.359774],"type":"Point"}
}