{
  "type": "Feature",
  "properties": {
    "addr:full":"111 Hillside Ave Hartford CT 06106",
    "addr:housenumber":"111",
    "addr:postcode":"06106",
    "addr:street":"Hillside Ave;Ct",
    "iso:country":"US",
    "sg:address":"111 Hillside Ave",
    "sg:city":"Hartford",
    "sg:classifiers":[
        {
            "category":"Education",
            "subcategory":"School",
            "type":"Public Place"
        }
    ],
    "sg:phone":"+1   ",
    "sg:postcode":"06106",
    "sg:province":"CT",
    "wof:name":"McDonough Elementary School",
    "wof:placetype":"venue"
},
  "geometry": {"coordinates":[-72.698177,41.748371],"type":"Point"}
}