{
  "type": "Feature",
  "properties": {
    "addr:full":"200 Great Pond Dr Windsor CT 06095",
    "addr:housenumber":"200",
    "addr:postcode":"06095",
    "addr:street":"Great Pond Dr",
    "iso:country":"US",
    "sg:address":"200 Great Pond Dr",
    "sg:city":"Windsor",
    "sg:classifiers":[
        {
            "category":"Insurance",
            "subcategory":"Insurance Agent",
            "type":"Services"
        }
    ],
    "sg:phone":"+1 860 843 6820",
    "sg:postcode":"06095",
    "sg:province":"CT",
    "wof:name":"Hartford",
    "wof:placetype":"venue"
},
  "geometry": {"coordinates":[-72.71584799999999,41.875992],"type":"Point"}
}