{
  "type": "Feature",
  "properties": {
    "iso:country":"US",
    "sg:address":"48 Putter Dr",
    "sg:city":"Stamford",
    "sg:classifiers":[
        {
            "category":"Manufacturing",
            "subcategory":"Signs",
            "type":"Manufacturing & Wholesale Goods"
        }
    ],
    "sg:phone":"+1 203 322 3519",
    "sg:postcode":"06907",
    "sg:province":"CT",
    "sg:tags":[
        "specialty",
        "mfg"
    ],
    "wof:name":"Simply Signs",
    "wof:placetype":"venue"
},
  "geometry": {"coordinates":[-73.51628599999999,41.106073],"type":"Point"}
}