{
  "type": "Feature",
  "properties": {
    "iso:country":"US",
    "sg:address":"277 Albany Tpke",
    "sg:city":"Canton",
    "sg:classifiers":[
        {
            "category":"Real Estate",
            "subcategory":"Surveying",
            "type":"Services"
        }
    ],
    "sg:phone":"+1   ",
    "sg:postcode":"06019",
    "sg:province":"CT",
    "wof:name":"Hoffmann Arthur Land Surveyor",
    "wof:placetype":"venue"
},
  "geometry": {"coordinates":[-72.90593200000001,41.830921],"type":"Point"}
}