{
  "type": "Feature",
  "properties": {
    "iso:country":"US",
    "sg:address":"501 Wolcott Rd",
    "sg:city":"Bristol",
    "sg:classifiers":[
        {
            "category":"Travel",
            "subcategory":"Campground",
            "type":"Entertainment"
        }
    ],
    "sg:phone":"+1 860 583 1234",
    "sg:postcode":"06010",
    "sg:province":"CT",
    "sg:tags":[
        "camp"
    ],
    "wof:name":"Indian Rock Nature Preserve",
    "wof:placetype":"venue"
},
  "geometry": {"coordinates":[-72.964043,41.649091],"type":"Point"}
}