{
  "type": "Feature",
  "properties": {
    "addr:full":"346 Quinnipiac St Wallingford CT 06492",
    "addr:housenumber":"346",
    "addr:postcode":"06492",
    "addr:street":"Quinnipiac St",
    "iso:country":"US",
    "sg:address":"346 Quinnipiac St",
    "sg:city":"Wallingford",
    "sg:classifiers":[
        {
            "category":"Manufacturing",
            "subcategory":"Tools & Machinery",
            "type":"Manufacturing & Wholesale Goods"
        }
    ],
    "sg:phone":"+1 203 269 1545",
    "sg:postcode":"06492",
    "sg:province":"CT",
    "sg:tags":[
        "control",
        "electronic"
    ],
    "wof:name":"Samarius Precision Instruments",
    "wof:placetype":"venue"
},
  "geometry": {"coordinates":[-72.835399,41.457681],"type":"Point"}
}