{
  "type": "Feature",
  "properties": {
    "addr:full":"36 Jordan Ln Stamford CT 06903",
    "addr:housenumber":"36",
    "addr:postcode":"06903",
    "addr:street":"Jordan Ln",
    "iso:country":"US",
    "sg:address":"36 Jordan Ln",
    "sg:city":"Stamford",
    "sg:classifiers":[
        {
            "category":"Building & Trades",
            "subcategory":"Construction",
            "type":"Services"
        }
    ],
    "sg:phone":"+1 203 595 0589",
    "sg:postcode":"06903",
    "sg:province":"CT",
    "sg:tags":[
        "driveway"
    ],
    "wof:name":"Evans Paving & Excavating Inc",
    "wof:placetype":"venue"
},
  "geometry": {"coordinates":[-73.56603200000001,41.124785],"type":"Point"}
}