{
  "type": "Feature",
  "properties": {
    "addr:full":"58 Sage Rd Woodbury CT 06798",
    "addr:housenumber":"58",
    "addr:postcode":"06798",
    "addr:street":"Sage Rd",
    "iso:country":"US",
    "sg:address":"58 Sage Rd",
    "sg:city":"Woodbury",
    "sg:classifiers":[
        {
            "category":"Professional",
            "subcategory":"Management & Consulting",
            "type":"Services"
        }
    ],
    "sg:phone":"+1   ",
    "sg:postcode":"06798",
    "sg:province":"CT",
    "sg:tags":[
        "business"
    ],
    "wof:name":"Doctor Broadband LLC",
    "wof:placetype":"venue"
},
  "geometry": {"coordinates":[-73.186853,41.529732],"type":"Point"}
}