{
  "type": "Feature",
  "properties": {
    "addr:full":"44 State Hwy 32 Quaker Hill CT 06375",
    "addr:housenumber":"44",
    "addr:postcode":"06375",
    "addr:street":"State Hwy 32 Quaker Hill Ct",
    "iso:country":"US",
    "sg:address":"44 State Hwy 32",
    "sg:city":"Quaker Hill",
    "sg:classifiers":[
        {
            "category":"Building & Trades",
            "subcategory":"Construction",
            "type":"Services"
        }
    ],
    "sg:phone":"+1 860 444 7144",
    "sg:postcode":"06375",
    "sg:province":"CT",
    "sg:tags":[
        "specializing",
        "residential",
        "ki",
        "remodeling",
        "contractor"
    ],
    "wof:name":"Scribners Kit & Bath Design",
    "wof:placetype":"venue"
},
  "geometry": {"coordinates":[-72.10996299999999,41.421814],"type":"Point"}
}