{
  "type": "Feature",
  "properties": {
    "addr:full":"246 Federal Rd Brookfield CT 06804",
    "addr:housenumber":"246",
    "addr:postcode":"06804",
    "addr:street":"Federal Rd",
    "iso:country":"US",
    "sg:address":"246 Federal Rd",
    "sg:city":"Brookfield",
    "sg:classifiers":[
        {
            "category":"Recreation",
            "type":"Entertainment"
        }
    ],
    "sg:phone":"+1 203 775 8350",
    "sg:postcode":"06804",
    "sg:province":"CT",
    "sg:tags":[
        "center"
    ],
    "wof:name":"Regional YMCA Of Western Ct",
    "wof:placetype":"venue"
},
  "geometry": {"coordinates":[-73.40419799999999,41.445524],"type":"Point"}
}