{
  "type": "Feature",
  "properties": {
    "iso:country":"US",
    "sg:address":"89 Old Ridgefield Rd",
    "sg:city":"Wilton",
    "sg:classifiers":[
        {
            "category":"Shopping",
            "subcategory":"Department Store",
            "type":"Retail Goods"
        }
    ],
    "sg:phone":"+1 203 762 3341",
    "sg:postcode":"06897",
    "sg:province":"CT",
    "wof:name":"Tallmadge's Wilton Dept Store",
    "wof:placetype":"venue"
},
  "geometry": {"coordinates":[-73.433154,41.194246],"type":"Point"}
}