{
  "type": "Feature",
  "properties": {
    "iso:country":"US",
    "sg:address":"9 Glover Ave",
    "sg:city":"Newtown",
    "sg:classifiers":[
        {
            "category":"Building & Trades",
            "subcategory":"Construction",
            "type":"Services"
        }
    ],
    "sg:phone":"+1 203 426 7775",
    "sg:postcode":"06470",
    "sg:province":"CT",
    "sg:tags":[
        "repair",
        "designer",
        "concrete",
        "maintenance",
        "dealer",
        "pool",
        "swimming"
    ],
    "wof:name":"J & J Pool & Concrete Svc",
    "wof:placetype":"venue"
},
  "geometry": {"coordinates":[-73.304498,41.40914],"type":"Point"}
}