{
  "type": "Feature",
  "properties": {
    "addr:full":"3 South St Roxbury CT 06783",
    "addr:housenumber":"3",
    "addr:postcode":"06783",
    "addr:street":"South St",
    "iso:country":"US",
    "sg:address":"3 South St",
    "sg:city":"Roxbury",
    "sg:classifiers":[
        {
            "category":"Communications",
            "subcategory":"Film & Video Production",
            "type":"Services"
        }
    ],
    "sg:phone":"+1   ",
    "sg:postcode":"06783",
    "sg:province":"CT",
    "sg:tags":[
        "motion"
    ],
    "wof:name":"Chris Brigham Production",
    "wof:placetype":"venue"
},
  "geometry": {"coordinates":[-73.30505700000001,41.549628],"type":"Point"}
}