{
  "type": "Feature",
  "properties": {
    "iso:country":"US",
    "sg:address":"506 Windsor Ave",
    "sg:city":"Windsor",
    "sg:classifiers":[
        {
            "category":"Shopping",
            "subcategory":"Discount & Variety Stores",
            "type":"Retail Goods"
        }
    ],
    "sg:phone":"+1 860 683 0730",
    "sg:postcode":"06095",
    "sg:province":"CT",
    "wof:name":"All For A Buck",
    "wof:placetype":"venue"
},
  "geometry": {"coordinates":[-72.656622,41.819116],"type":"Point"}
}