{
  "type": "Feature",
  "properties": {
    "addr:full":"55 Quaker Ridge Rd Bethel CT 06801",
    "addr:housenumber":"55",
    "addr:postcode":"06801",
    "addr:street":"Quaker Ridge Rd",
    "iso:country":"US",
    "sg:address":"55 Quaker Ridge Rd",
    "sg:city":"Bethel",
    "sg:classifiers":[
        {
            "category":"Communications",
            "subcategory":"Film & Video Production",
            "type":"Services"
        }
    ],
    "sg:phone":"+1   ",
    "sg:postcode":"06801",
    "sg:province":"CT",
    "sg:tags":[
        "consulting",
        "taping"
    ],
    "wof:name":"Creative Video Productions",
    "wof:placetype":"venue"
},
  "geometry": {"coordinates":[-73.398752,41.398523],"type":"Point"}
}