{
  "type": "Feature",
  "properties": {
    "iso:country":"US",
    "sg:address":"39 Lewis St",
    "sg:city":"Greenwich",
    "sg:classifiers":[
        {
            "category":"Professional",
            "subcategory":"Advertising",
            "type":"Services"
        }
    ],
    "sg:phone":"+1 203 661 0300",
    "sg:postcode":"06830",
    "sg:province":"CT",
    "sg:tags":[
        "counselor"
    ],
    "wof:name":"Ted Chin & Co",
    "wof:placetype":"venue"
},
  "geometry": {"coordinates":[-73.62446199999999,41.02904],"type":"Point"}
}