{
  "type": "Feature",
  "properties": {
    "iso:country":"US",
    "sg:address":"1 Elizabeth St",
    "sg:city":"Norwalk",
    "sg:classifiers":[
        {
            "category":"Organizations",
            "subcategory":"Religious Organization",
            "type":"Services"
        }
    ],
    "sg:phone":"+1   ",
    "sg:postcode":"06854",
    "sg:province":"CT",
    "wof:name":"Antioch Temple Church",
    "wof:placetype":"venue"
},
  "geometry": {"coordinates":[-73.417062,41.097325],"type":"Point"}
}