{
  "type": "Feature",
  "properties": {
    "iso:country":"US",
    "sg:address":"141 Franklin St",
    "sg:city":"Stamford",
    "sg:classifiers":[
        {
            "category":"Education",
            "subcategory":"Special Training",
            "type":"Public Place"
        }
    ],
    "sg:phone":"+1 203 324 5214",
    "sg:postcode":"06901",
    "sg:province":"CT",
    "sg:tags":[
        "reading",
        "instruction",
        "improvement"
    ],
    "wof:name":"Literacy Volunteers Of America",
    "wof:placetype":"venue"
},
  "geometry": {"coordinates":[-73.54207700000001,41.059351],"type":"Point"}
}