{
  "type": "Feature",
  "properties": {
    "iso:country":"US",
    "sg:address":"8 Queen St",
    "sg:city":"Newtown",
    "sg:classifiers":[
        {
            "category":"Restaurant",
            "type":"Food & Drink"
        }
    ],
    "sg:phone":"+1 203 270 7061",
    "sg:postcode":"06470",
    "sg:province":"CT",
    "sg:website":"www.myplacepizza.com",
    "wof:name":"My Place Restaurant",
    "wof:placetype":"venue"
},
  "geometry": {"coordinates":[-73.303303,41.413261],"type":"Point"}
}