{
  "type": "Feature",
  "properties": {
    "iso:country":"US",
    "sg:address":"231 Judd Rd",
    "sg:city":"Easton",
    "sg:classifiers":[
        {
            "category":"Professional",
            "subcategory":"Art Services",
            "type":"Services"
        }
    ],
    "sg:phone":"+1 203 445 1511",
    "sg:postcode":"06612",
    "sg:province":"CT",
    "sg:tags":[
        "artist"
    ],
    "sg:website":"www.publishersgraphics.com",
    "wof:name":"Publishers Graphics Inc",
    "wof:placetype":"venue"
},
  "geometry": {"coordinates":[-73.289738,41.305254],"type":"Point"}
}