{
  "type": "Feature",
  "properties": {
    "iso:country":"US",
    "sg:address":"93 Triangle St",
    "sg:city":"Danbury",
    "sg:classifiers":[
        {
            "category":"Professional",
            "type":"Services"
        }
    ],
    "sg:phone":"+1 203 792 7400",
    "sg:postcode":"06810",
    "sg:province":"CT",
    "wof:name":"Triangle Aviation LLC",
    "wof:placetype":"venue"
},
  "geometry": {"coordinates":[-73.435647,41.393082],"type":"Point"}
}