{
  "type": "Feature",
  "properties": {
    "addr:full":"391 Broad St Meriden CT 06450",
    "addr:housenumber":"391",
    "addr:postcode":"06450",
    "addr:street":"Broad St",
    "iso:country":"US",
    "sg:address":"391 Broad St",
    "sg:city":"Meriden",
    "sg:classifiers":[
        {
            "category":"Health Services",
            "subcategory":"Health Practitioner",
            "type":"Services"
        },
        {
            "category":"Professional",
            "subcategory":"Employment Agencies",
            "type":"Services"
        }
    ],
    "sg:phone":"+1 203 238 3336",
    "sg:postcode":"06450",
    "sg:province":"CT",
    "sg:tags":[
        "nurse",
        "registry"
    ],
    "sg:website":"www.nursefinders.com",
    "wof:name":"Nursefinders",
    "wof:placetype":"venue"
},
  "geometry": {"coordinates":[-72.794222,41.531418],"type":"Point"}
}