{
  "type": "Feature",
  "properties": {
    "iso:country":"US",
    "sg:address":"241 Kennedy Dr",
    "sg:city":"Putnam",
    "sg:classifiers":[
        {
            "category":"Shopping",
            "subcategory":"Computers & Home Electronics",
            "type":"Retail Goods"
        }
    ],
    "sg:phone":"+1 860 928 3422",
    "sg:postcode":"06260",
    "sg:province":"CT",
    "wof:name":"Savage Systems LLC",
    "wof:placetype":"venue"
},
  "geometry": {"coordinates":[-71.907729,41.919788],"type":"Point"}
}