{
  "type": "Feature",
  "properties": {
    "addr:full":"49 Regent St Manchester CT 06042",
    "addr:housenumber":"49",
    "addr:postcode":"06042",
    "addr:street":"Regent St",
    "iso:country":"US",
    "sg:address":"49 Regent St",
    "sg:city":"Manchester",
    "sg:classifiers":[
        {
            "category":"Manufacturing",
            "subcategory":"Furniture",
            "type":"Manufacturing & Wholesale Goods"
        }
    ],
    "sg:phone":"+1   ",
    "sg:postcode":"06042",
    "sg:province":"CT",
    "sg:tags":[
        "rep",
        "mfg"
    ],
    "wof:name":"Prevo Office Solutions",
    "wof:placetype":"venue"
},
  "geometry": {"coordinates":[-72.529381,41.790202],"type":"Point"}
}