{
  "type": "Feature",
  "properties": {
    "addr:full":"149 Grassy Plain St Bethel CT 06801",
    "addr:housenumber":"149",
    "addr:postcode":"06801",
    "addr:street":"Grassy Plain St Bethel Ct",
    "iso:country":"US",
    "sg:address":"149 Grassy Plain St",
    "sg:city":"Bethel",
    "sg:classifiers":[
        {
            "category":"Wholesale",
            "subcategory":"Non-durable Goods",
            "type":"Manufacturing & Wholesale Goods"
        }
    ],
    "sg:phone":"+1 203 743 3930",
    "sg:postcode":"06801",
    "sg:province":"CT",
    "wof:name":"Wholesale Nozzle & Supply Co",
    "wof:placetype":"venue"
},
  "geometry": {"coordinates":[-73.421098,41.362715],"type":"Point"}
}