{
  "type": "Feature",
  "properties": {
    "iso:country":"US",
    "sg:address":"449 Silas Deane Hwy",
    "sg:city":"Wethersfield",
    "sg:classifiers":[
        {
            "category":"Banks & Credit Unions",
            "subcategory":"Bank",
            "type":"Services"
        }
    ],
    "sg:phone":"+1 860 257 6925",
    "sg:postcode":"06109",
    "sg:province":"CT",
    "sg:tags":[
        "mortgage"
    ],
    "wof:name":"Wells Fargo",
    "wof:placetype":"venue"
},
  "geometry": {"coordinates":[-72.66387400000001,41.713034],"type":"Point"}
}