{
  "type": "Feature",
  "properties": {
    "iso:country":"US",
    "sg:address":"5 Hart St",
    "sg:city":"New Britain",
    "sg:classifiers":[
        {
            "category":"Health Services",
            "subcategory":"Clinic",
            "type":"Services"
        }
    ],
    "sg:phone":"+1   ",
    "sg:postcode":"06052",
    "sg:province":"CT",
    "sg:tags":[
        "specialty",
        "outpatient"
    ],
    "wof:name":"Harvest House",
    "wof:placetype":"venue"
},
  "geometry": {"coordinates":[-72.78452799999999,41.660058],"type":"Point"}
}