{
  "type": "Feature",
  "properties": {
    "iso:country":"US",
    "sg:address":"348 Huntingdon Ave",
    "sg:city":"Waterbury",
    "sg:classifiers":[
        {
            "category":"Building & Trades",
            "subcategory":"Construction",
            "type":"Services"
        }
    ],
    "sg:phone":"+1 203 755 2101",
    "sg:postcode":"06708",
    "sg:province":"CT",
    "sg:tags":[
        "roofing",
        "contractor"
    ],
    "wof:name":"Heritage Systems Inc",
    "wof:placetype":"venue"
},
  "geometry": {"coordinates":[-73.064083,41.576133],"type":"Point"}
}