{
  "type": "Feature",
  "properties": {
    "addr:full":"15 Kenyon Rd Jewett City CT 06351",
    "addr:housenumber":"15",
    "addr:postcode":"06351",
    "addr:street":"Kenyon Rd Jewett City Ct",
    "iso:country":"US",
    "sg:address":"15 Kenyon Rd",
    "sg:city":"Jewett City",
    "sg:classifiers":[
        {
            "category":"Travel",
            "subcategory":"Campground",
            "type":"Entertainment"
        }
    ],
    "sg:phone":"+1   ",
    "sg:postcode":"06351",
    "sg:province":"CT",
    "sg:tags":[
        "trailer"
    ],
    "wof:name":"Deer Haven Campground LLC",
    "wof:placetype":"venue"
},
  "geometry": {"coordinates":[-72.02430099999999,41.594544],"type":"Point"}
}