{
  "type": "Feature",
  "properties": {
    "iso:country":"US",
    "sg:address":"197 Huntingtown Rd",
    "sg:city":"Newtown",
    "sg:classifiers":[
        {
            "category":"Wholesale",
            "subcategory":"Construction Materials",
            "type":"Manufacturing & Wholesale Goods"
        }
    ],
    "sg:phone":"+1 203 270 8820",
    "sg:postcode":"06470",
    "sg:province":"CT",
    "wof:name":"Sticks & Stones Farm",
    "wof:placetype":"venue"
},
  "geometry": {"coordinates":[-73.29237500000001,41.33969],"type":"Point"}
}