{
  "type": "Feature",
  "properties": {
    "addr:full":"52 Larkin St Stamford CT 06907",
    "addr:housenumber":"52",
    "addr:postcode":"06907",
    "addr:street":"Larkin St",
    "iso:country":"US",
    "sg:address":"52 Larkin St",
    "sg:city":"Stamford",
    "sg:classifiers":[
        {
            "category":"Building & Trades",
            "subcategory":"Construction",
            "type":"Services"
        }
    ],
    "sg:phone":"+1 203 965 0660",
    "sg:postcode":"06907",
    "sg:province":"CT",
    "sg:tags":[
        "repairing",
        "remodeling",
        "contractor"
    ],
    "wof:name":"E R Salvatore Associate Inc",
    "wof:placetype":"venue"
},
  "geometry": {"coordinates":[-73.519014,41.078181],"type":"Point"}
}