{
  "type": "Feature",
  "properties": {
    "iso:country":"US",
    "sg:address":"80 Main St",
    "sg:city":"Danbury",
    "sg:classifiers":[
        {
            "category":"Health Services",
            "subcategory":"Clinic",
            "type":"Services"
        }
    ],
    "sg:phone":"+1 203 748 0598",
    "sg:postcode":"06810",
    "sg:province":"CT",
    "sg:tags":[
        "home",
        "care"
    ],
    "wof:name":"Connecticut Community Care Inc",
    "wof:placetype":"venue"
},
  "geometry": {"coordinates":[-73.447912,41.389865],"type":"Point"}
}