{
  "type": "Feature",
  "properties": {
    "iso:country":"US",
    "sg:address":"59 Lynam Rd",
    "sg:city":"Stamford",
    "sg:classifiers":[
        {
            "category":"Building & Trades",
            "subcategory":"Construction",
            "type":"Services"
        }
    ],
    "sg:phone":"+1 203 595 0537",
    "sg:postcode":"06903",
    "sg:province":"CT",
    "sg:tags":[
        "painter"
    ],
    "wof:name":"European Painters",
    "wof:placetype":"venue"
},
  "geometry": {"coordinates":[-73.568917,41.116025],"type":"Point"}
}