{
  "type": "Feature",
  "properties": {
    "iso:country":"US",
    "sg:address":"1152 Russell Ave",
    "sg:city":"Suffield",
    "sg:classifiers":[
        {
            "category":"Building & Trades",
            "subcategory":"Construction",
            "type":"Services"
        }
    ],
    "sg:phone":"+1 860 668 9099",
    "sg:postcode":"06078",
    "sg:province":"CT",
    "sg:tags":[
        "contractor"
    ],
    "wof:name":"Exterior Design Specialist",
    "wof:placetype":"venue"
},
  "geometry": {"coordinates":[-72.676683,42.01334],"type":"Point"}
}