{
  "type": "Feature",
  "properties": {
    "addr:full":"25 Joann Cir Westport CT 06880",
    "addr:housenumber":"25",
    "addr:postcode":"06880",
    "addr:street":"Joann Cir",
    "iso:country":"US",
    "sg:address":"25 Joann Cir",
    "sg:city":"Westport",
    "sg:classifiers":[
        {
            "category":"Social Services",
            "subcategory":"Child Care",
            "type":"Services"
        }
    ],
    "sg:phone":"+1   ",
    "sg:postcode":"06880",
    "sg:province":"CT",
    "sg:tags":[
        "day"
    ],
    "wof:name":"Chldrens Athletic Training",
    "wof:placetype":"venue"
},
  "geometry": {"coordinates":[-73.34362400000001,41.154452],"type":"Point"}
}