{
  "type": "Feature",
  "properties": {
    "iso:country":"US",
    "sg:address":"1 Sound Ave",
    "sg:city":"Stamford",
    "sg:classifiers":[
        {
            "category":"Organizations",
            "subcategory":"Religious Organization",
            "type":"Services"
        }
    ],
    "sg:phone":"+1 203 327 7250",
    "sg:postcode":"06902",
    "sg:province":"CT",
    "sg:tags":[
        "church"
    ],
    "wof:name":"St Benedict's Church",
    "wof:placetype":"venue"
},
  "geometry": {"coordinates":[-73.525316,41.02737],"type":"Point"}
}