{
  "type": "Feature",
  "properties": {
    "iso:country":"US",
    "sg:address":"5 Heritage Hill Rd",
    "sg:city":"Norwalk",
    "sg:classifiers":[
        {
            "category":"Professional",
            "subcategory":"Advertising",
            "type":"Services"
        }
    ],
    "sg:phone":"+1   ",
    "sg:postcode":"06851",
    "sg:province":"CT",
    "sg:tags":[
        "mail",
        "direct"
    ],
    "wof:name":"Big Wave Inc",
    "wof:placetype":"venue"
},
  "geometry": {"coordinates":[-73.40354499999999,41.143502],"type":"Point"}
}