{
  "type": "Feature",
  "properties": {
    "addr:full":"415 Riverside Dr North Grosvenordale CT 06255",
    "addr:housenumber":"415",
    "addr:postcode":"06255",
    "addr:street":"Riverside Dr North Grosvenordale Ct",
    "iso:country":"US",
    "sg:address":"415 Riverside Dr",
    "sg:city":"North Grosvenordale",
    "sg:classifiers":[
        {
            "category":"Shopping",
            "subcategory":"Pharmacy",
            "type":"Retail Goods"
        }
    ],
    "sg:phone":"+1 860 923 9545",
    "sg:postcode":"06255",
    "sg:province":"CT",
    "wof:name":"Franklin Pharmacy Inc",
    "wof:placetype":"venue"
},
  "geometry": {"coordinates":[-71.88187499999999,41.956485],"type":"Point"}
}