{
  "type": "Feature",
  "properties": {
    "addr:full":"422 Main St East Haven CT 06512",
    "addr:housenumber":"422",
    "addr:postcode":"06512",
    "addr:street":"Main St",
    "iso:country":"US",
    "sg:address":"422 Main St",
    "sg:city":"East Haven",
    "sg:classifiers":[
        {
            "category":"Education",
            "subcategory":"Special Training",
            "type":"Public Place"
        }
    ],
    "sg:phone":"+1 203 468 8718",
    "sg:postcode":"06512",
    "sg:province":"CT",
    "sg:tags":[
        "instruction",
        "music"
    ],
    "wof:name":"Alliance Music",
    "wof:placetype":"venue"
},
  "geometry": {"coordinates":[-72.877439,41.282135],"type":"Point"}
}