{
  "type": "Feature",
  "properties": {
    "iso:country":"US",
    "sg:address":"83 Halls Rd",
    "sg:city":"Old Lyme",
    "sg:classifiers":[
        {
            "category":"Health Services",
            "subcategory":"Optometrist",
            "type":"Services"
        }
    ],
    "sg:phone":"+1 860 434 2020",
    "sg:postcode":"06371",
    "sg:province":"CT",
    "sg:tags":[
        "ophthalmologist"
    ],
    "wof:name":"Brooks Jeanne Q MD",
    "wof:placetype":"venue"
},
  "geometry": {"coordinates":[-72.334999,41.323898],"type":"Point"}
}