{
  "type": "Feature",
  "properties": {
    "iso:country":"US",
    "sg:address":"608 Wolcott Rd",
    "sg:city":"Wolcott",
    "sg:classifiers":[
        {
            "category":"Insurance",
            "subcategory":"Insurance Agent",
            "type":"Services"
        }
    ],
    "sg:phone":"+1 203 879 2505",
    "sg:postcode":"06716",
    "sg:province":"CT",
    "wof:name":"Ira J Kaplan Insurance",
    "wof:placetype":"venue"
},
  "geometry": {"coordinates":[-72.986076,41.596592],"type":"Point"}
}