{
  "type": "Feature",
  "properties": {
    "addr:full":"2525 E Main St Bridgeport CT 06610",
    "addr:housenumber":"2525",
    "addr:postcode":"06610",
    "addr:street":"E Main St",
    "iso:country":"US",
    "sg:address":"2525 E Main St",
    "sg:city":"Bridgeport",
    "sg:classifiers":[
        {
            "category":"Autos & Motor Vehicles",
            "subcategory":"Fuel & Gas Station",
            "type":"Retail Goods"
        }
    ],
    "sg:phone":"+1 203 366 2360",
    "sg:postcode":"06610",
    "sg:province":"CT",
    "sg:tags":[
        "oil"
    ],
    "wof:name":"Gulf Oil Co",
    "wof:placetype":"venue"
},
  "geometry": {"coordinates":[-73.179013,41.21011],"type":"Point"}
}