{
  "type": "Feature",
  "properties": {
    "addr:full":"80 Jacqueline Dr Southbury CT 06488",
    "addr:housenumber":"80",
    "addr:postcode":"06488",
    "addr:street":"Jacqueline Dr",
    "iso:country":"US",
    "sg:address":"80 Jacqueline Dr",
    "sg:city":"Southbury",
    "sg:classifiers":[
        {
            "category":"Wholesale",
            "subcategory":"Jewelry",
            "type":"Manufacturing & Wholesale Goods"
        }
    ],
    "sg:phone":"+1 203 264 9124",
    "sg:postcode":"06488",
    "sg:province":"CT",
    "sg:tags":[
        "stone"
    ],
    "wof:name":"Watch Faces USA Inc",
    "wof:placetype":"venue"
},
  "geometry": {"coordinates":[-73.18408100000001,41.468129],"type":"Point"}
}