{
  "type": "Feature",
  "properties": {
    "addr:full":"690 Main St East Haven CT 06512",
    "addr:housenumber":"690",
    "addr:postcode":"06512",
    "addr:street":"Main St",
    "iso:country":"US",
    "sg:address":"690 Main St",
    "sg:city":"East Haven",
    "sg:classifiers":[
        {
            "category":"Wholesale",
            "subcategory":"Machinery & Supplies",
            "type":"Manufacturing & Wholesale Goods"
        }
    ],
    "sg:phone":"+1 203 467 0077",
    "sg:postcode":"06512",
    "sg:province":"CT",
    "sg:tags":[
        "janitor"
    ],
    "sg:website":"www.verton.com",
    "wof:name":"Verton Inc",
    "wof:placetype":"venue"
},
  "geometry": {"coordinates":[-72.88647,41.284981],"type":"Point"}
}