{
  "type": "Feature",
  "properties": {
    "iso:country":"US",
    "sg:address":"48 High St",
    "sg:city":"Bristol",
    "sg:classifiers":[
        {
            "category":"Building & Trades",
            "subcategory":"Construction",
            "type":"Services"
        }
    ],
    "sg:phone":"+1 860 589 6732",
    "sg:postcode":"06010",
    "sg:province":"CT",
    "sg:tags":[
        "contractor"
    ],
    "wof:name":"Mels Contracting LLC",
    "wof:placetype":"venue"
},
  "geometry": {"coordinates":[-72.94185899999999,41.673333],"type":"Point"}
}