{
  "type": "Feature",
  "properties": {
    "addr:full":"2 Northgate Rd Windsor Locks CT 06096",
    "addr:housenumber":"2",
    "addr:postcode":"06096",
    "addr:street":"Northgate Rd Windsor Locks Ct",
    "iso:country":"US",
    "sg:address":"2 Northgate Rd",
    "sg:city":"Windsor Locks",
    "sg:classifiers":[
        {
            "category":"Building & Trades",
            "subcategory":"Electrical",
            "type":"Services"
        }
    ],
    "sg:phone":"+1 860 292 6864",
    "sg:postcode":"06096",
    "sg:province":"CT",
    "sg:tags":[
        "electrical",
        "contractor"
    ],
    "wof:name":"Tomasko Electric",
    "wof:placetype":"venue"
},
  "geometry": {"coordinates":[-72.655928,41.941162],"type":"Point"}
}