{
  "type": "Feature",
  "properties": {
    "addr:full":"386 Still Hill Rd Hamden CT 06518",
    "addr:housenumber":"386",
    "addr:postcode":"06518",
    "addr:street":"Still Hill Rd",
    "iso:country":"US",
    "sg:address":"386 Still Hill Rd",
    "sg:city":"Hamden",
    "sg:classifiers":[
        {
            "category":"Building & Trades",
            "subcategory":"Construction",
            "type":"Services"
        }
    ],
    "sg:phone":"+1 203 288 5744",
    "sg:postcode":"06518",
    "sg:province":"CT",
    "sg:tags":[
        "excavation",
        "work"
    ],
    "wof:name":"F J Miller Construction Co",
    "wof:placetype":"venue"
},
  "geometry": {"coordinates":[-72.930286,41.42804],"type":"Point"}
}