{
  "type": "Feature",
  "properties": {
    "iso:country":"US",
    "sg:address":"113 Tall Timbers Rd",
    "sg:city":"Glastonbury",
    "sg:classifiers":[
        {
            "category":"Home & Garden",
            "subcategory":"Carpets & Floor Coverings",
            "type":"Retail Goods"
        }
    ],
    "sg:phone":"+1 860 633 1992",
    "sg:postcode":"06033",
    "sg:province":"CT",
    "sg:tags":[
        "oriental",
        "rug"
    ],
    "wof:name":"Hickey Enterprises",
    "wof:placetype":"venue"
},
  "geometry": {"coordinates":[-72.58681199999999,41.688347],"type":"Point"}
}