{
  "type": "Feature",
  "properties": {
    "iso:country":"US",
    "sg:address":"221 Governor St",
    "sg:city":"East Hartford",
    "sg:classifiers":[
        {
            "category":"Autos & Motor Vehicles",
            "subcategory":"Motorcycle Sales",
            "type":"Retail Goods"
        }
    ],
    "sg:phone":"+1   ",
    "sg:postcode":"06108",
    "sg:province":"CT",
    "sg:tags":[
        "repair"
    ],
    "wof:name":"Gengras Harley-Davidson Inc",
    "wof:placetype":"venue"
},
  "geometry": {"coordinates":[-72.65255000000001,41.770873],"type":"Point"}
}