{
  "type": "Feature",
  "properties": {
    "addr:full":"4 Wolf Den Rd Brooklyn CT 06234",
    "addr:housenumber":"4",
    "addr:postcode":"06234",
    "addr:street":"Wolf Den Rd",
    "iso:country":"US",
    "sg:address":"4 Wolf Den Rd",
    "sg:city":"Brooklyn",
    "sg:classifiers":[
        {
            "category":"Government",
            "subcategory":"Office",
            "type":"Public Place"
        }
    ],
    "sg:phone":"+1 860 774 9543",
    "sg:postcode":"06234",
    "sg:province":"CT",
    "sg:tags":[
        "town"
    ],
    "wof:name":"Brooklyn Town Clerk",
    "wof:placetype":"venue"
},
  "geometry": {"coordinates":[-71.95070800000001,41.787942],"type":"Point"}
}