{
  "type": "Feature",
  "properties": {
    "addr:full":"1 Bestor Ln Bloomfield CT 06002",
    "addr:housenumber":"1",
    "addr:postcode":"06002",
    "addr:street":"Bestor Ln Bloomfield Ct",
    "iso:country":"US",
    "sg:address":"1 Bestor Ln",
    "sg:city":"Bloomfield",
    "sg:classifiers":[
        {
            "category":"Insurance",
            "subcategory":"Insurance Agent",
            "type":"Services"
        },
        {
            "category":"Insurance",
            "subcategory":"Hazard Insurance",
            "type":"Services"
        },
        {
            "category":"Insurance",
            "subcategory":"Title Insurance",
            "type":"Services"
        },
        {
            "category":"Insurance",
            "subcategory":"Life Insurance",
            "type":"Services"
        }
    ],
    "sg:phone":"+1 860 243 2585",
    "sg:postcode":"06002",
    "sg:province":"CT",
    "sg:tags":[
        "business",
        "auto",
        "commercial",
        "homeowner",
        "motorcycle",
        "renter"
    ],
    "sg:website":"http://www.allstateagencies.com/NathanGridley/Welcome",
    "wof:name":"Allstate Insurance Company - John Costales",
    "wof:placetype":"venue"
},
  "geometry": {"coordinates":[-72.73223900000001,41.828499],"type":"Point"}
}