{
  "type": "Feature",
  "properties": {
    "addr:full":"331 Poquonnock Rd Groton CT 06340",
    "addr:housenumber":"331",
    "addr:postcode":"06340",
    "addr:street":"Poquonnock Rd Groton Ct",
    "iso:country":"US",
    "sg:address":"331 Poquonnock Rd",
    "sg:city":"Groton",
    "sg:classifiers":[
        {
            "category":"Personal",
            "subcategory":"Barber",
            "type":"Services"
        }
    ],
    "sg:phone":"+1   ",
    "sg:postcode":"06340",
    "sg:province":"CT",
    "sg:tags":[
        "shop"
    ],
    "wof:name":"Supreme Blenz",
    "wof:placetype":"venue"
},
  "geometry": {"coordinates":[-72.070566,41.345722],"type":"Point"}
}