{
  "type": "Feature",
  "properties": {
    "addr:full":"88 Wall St Norwalk CT 06850",
    "addr:housenumber":"88",
    "addr:postcode":"06850",
    "addr:street":"Wall St",
    "iso:country":"US",
    "sg:address":"88 Wall St",
    "sg:city":"Norwalk",
    "sg:classifiers":[
        {
            "category":"Shopping",
            "subcategory":"Books",
            "type":"Retail Goods"
        }
    ],
    "sg:phone":"+1 203 854 5534",
    "sg:postcode":"06850",
    "sg:province":"CT",
    "wof:name":"Afro Heart",
    "wof:placetype":"venue"
},
  "geometry": {"coordinates":[-73.413335,41.11791],"type":"Point"}
}