{
  "type": "Feature",
  "properties": {
    "addr:full":"3 Old Tavern Rd Orange CT 06477",
    "addr:housenumber":"3",
    "addr:postcode":"06477",
    "addr:street":"Old Tavern Rd",
    "iso:country":"US",
    "sg:address":"3 Old Tavern Rd",
    "sg:city":"Orange",
    "sg:classifiers":[
        {
            "category":"Shopping",
            "subcategory":"Clothing, Apparel, & Fashions",
            "type":"Retail Goods"
        }
    ],
    "sg:phone":"+1 203 795 1050",
    "sg:postcode":"06477",
    "sg:province":"CT",
    "sg:tags":[
        "shop",
        "s",
        "accessory"
    ],
    "wof:name":"Hearts Content Bridal Inc",
    "wof:placetype":"venue"
},
  "geometry": {"coordinates":[-73.00347499999999,41.267602],"type":"Point"}
}