{
  "type": "Feature",
  "properties": {
    "iso:country":"US",
    "sg:address":"1011 Hope St",
    "sg:city":"Stamford",
    "sg:classifiers":[
        {
            "category":"Local Transit",
            "type":"Transportation"
        }
    ],
    "sg:phone":"+1 203 964 1100",
    "sg:postcode":"06907",
    "sg:province":"CT",
    "sg:tags":[
        "airport"
    ],
    "sg:website":"www.alliancelimo.com",
    "wof:name":"Alliance Limousine",
    "wof:placetype":"venue"
},
  "geometry": {"coordinates":[-73.518102,41.094396],"type":"Point"}
}