{
  "type": "Feature",
  "properties": {
    "addr:full":"55 Pearl St New Britain CT 06051",
    "addr:housenumber":"55",
    "addr:postcode":"06051",
    "addr:street":"Pearl St",
    "iso:country":"US",
    "sg:address":"55 Pearl St",
    "sg:city":"New Britain",
    "sg:classifiers":[
        {
            "category":"Social Services",
            "type":"Services"
        }
    ],
    "sg:phone":"+1   ",
    "sg:postcode":"06051",
    "sg:province":"CT",
    "sg:tags":[
        "senior",
        "citizen"
    ],
    "wof:name":"Dial A Ride",
    "wof:placetype":"venue"
},
  "geometry": {"coordinates":[-72.77553,41.663201],"type":"Point"}
}