{
  "type": "Feature",
  "properties": {
    "addr:full":"233 Main St Terryville CT 06786",
    "addr:housenumber":"233",
    "addr:postcode":"06786",
    "addr:street":"Main St",
    "iso:country":"US",
    "sg:address":"233 Main St",
    "sg:city":"Terryville",
    "sg:classifiers":[
        {
            "category":"Organizations",
            "subcategory":"Religious Organization",
            "type":"Services"
        }
    ],
    "sg:phone":"+1   ",
    "sg:postcode":"06786",
    "sg:province":"CT",
    "wof:name":"Terryvlle Cngregational Church",
    "wof:placetype":"venue"
},
  "geometry": {"coordinates":[-73.008824,41.678322],"type":"Point"}
}