{
  "type": "Feature",
  "properties": {
    "iso:country":"US",
    "sg:address":"8 Kevin Dr",
    "sg:city":"Danbury",
    "sg:classifiers":[
        {
            "category":"Local Transit",
            "type":"Transportation"
        }
    ],
    "sg:phone":"+1 203 746 8532",
    "sg:postcode":"06811",
    "sg:province":"CT",
    "sg:tags":[
        "limousine"
    ],
    "sg:website":"www.aandmtransportation.com",
    "wof:name":"A & M Transportation",
    "wof:placetype":"venue"
},
  "geometry": {"coordinates":[-73.471137,41.441911],"type":"Point"}
}