{
  "type": "Feature",
  "properties": {
    "addr:full":"1100 Rock Rimmon Rd Stamford CT 06903",
    "addr:housenumber":"1100",
    "addr:postcode":"06903",
    "addr:street":"Rock Rimmon Rd",
    "iso:country":"US",
    "sg:address":"1100 Rock Rimmon Rd",
    "sg:city":"Stamford",
    "sg:classifiers":[
        {
            "category":"Real Estate",
            "subcategory":"Architect",
            "type":"Services"
        }
    ],
    "sg:phone":"+1   ",
    "sg:postcode":"06903",
    "sg:province":"CT",
    "sg:tags":[
        "architectural"
    ],
    "wof:name":"Carl Mezedoff Architect",
    "wof:placetype":"venue"
},
  "geometry": {"coordinates":[-73.583294,41.161714],"type":"Point"}
}