{
  "type": "Feature",
  "properties": {
    "addr:full":"98 Knight St Watertown CT 06795",
    "addr:housenumber":"98",
    "addr:postcode":"06795",
    "addr:street":"Knight St",
    "iso:country":"US",
    "sg:address":"98 Knight St",
    "sg:city":"Watertown",
    "sg:classifiers":[
        {
            "category":"Arts & Performance",
            "subcategory":"Theater",
            "type":"Entertainment"
        }
    ],
    "sg:phone":"+1   ",
    "sg:postcode":"06795",
    "sg:province":"CT",
    "sg:tags":[
        "theatrical",
        "lighting"
    ],
    "wof:name":"Tech Services of Connecticut",
    "wof:placetype":"venue"
},
  "geometry": {"coordinates":[-73.108069,41.592426],"type":"Point"}
}