{
  "type": "Feature",
  "properties": {
    "addr:full":"52 Shearer Rd Washington CT 06793",
    "addr:housenumber":"52",
    "addr:postcode":"06793",
    "addr:street":"Shearer Rd",
    "iso:country":"US",
    "sg:address":"52 Shearer Rd",
    "sg:city":"Washington",
    "sg:classifiers":[
        {
            "category":"Professional",
            "subcategory":"Management & Consulting",
            "type":"Services"
        }
    ],
    "sg:phone":"+1   ",
    "sg:postcode":"06793",
    "sg:province":"CT",
    "sg:tags":[
        "business"
    ],
    "wof:name":"Structural Consulting Services",
    "wof:placetype":"venue"
},
  "geometry": {"coordinates":[-73.269901,41.66879],"type":"Point"}
}