{
  "type": "Feature",
  "properties": {
    "addr:full":"44 Fenn Rd Newington CT 06111",
    "addr:housenumber":"44",
    "addr:postcode":"06111",
    "addr:street":"Fenn Rd",
    "iso:country":"US",
    "sg:address":"44 Fenn Rd",
    "sg:city":"Newington",
    "sg:classifiers":[
        {
            "category":"Shopping",
            "subcategory":"Pharmacy",
            "type":"Retail Goods"
        }
    ],
    "sg:phone":"+1 860 667 9292",
    "sg:postcode":"06111",
    "sg:province":"CT",
    "wof:name":"Stop & Shop Pharmacy",
    "wof:placetype":"venue"
},
  "geometry": {"coordinates":[-72.75709500000001,41.694878],"type":"Point"}
}