{
  "type": "Feature",
  "properties": {
    "addr:full":"31 Mudge Pond Rd Sharon CT 06069",
    "addr:housenumber":"31",
    "addr:postcode":"06069",
    "addr:street":"Mudge Pond Rd Sharon Ct",
    "iso:country":"US",
    "sg:address":"31 Mudge Pond Rd",
    "sg:city":"Sharon",
    "sg:classifiers":[
        {
            "category":"Personal",
            "subcategory":"Barber",
            "type":"Services"
        }
    ],
    "sg:phone":"+1   ",
    "sg:postcode":"06069",
    "sg:province":"CT",
    "sg:tags":[
        "shop"
    ],
    "wof:name":"Skip Barber Personally",
    "wof:placetype":"venue"
},
  "geometry": {"coordinates":[-73.481853,41.892056],"type":"Point"}
}