{
  "type": "Feature",
  "properties": {
    "iso:country":"US",
    "sg:address":"27 Maple Ave",
    "sg:city":"Bethel",
    "sg:classifiers":[
        {
            "category":"Social Services",
            "subcategory":"Job Training",
            "type":"Services"
        }
    ],
    "sg:phone":"+1 203 731 3045",
    "sg:postcode":"06801",
    "sg:province":"CT",
    "sg:tags":[
        "rehabilitation"
    ],
    "wof:name":"Datahr Rehabilitation Inst",
    "wof:placetype":"venue"
},
  "geometry": {"coordinates":[-73.405323,41.377697],"type":"Point"}
}