{
  "type": "Feature",
  "properties": {
    "addr:full":"963 Main St Watertown CT 06795",
    "addr:housenumber":"963",
    "addr:postcode":"06795",
    "addr:street":"Main St",
    "iso:country":"US",
    "sg:address":"963 Main St",
    "sg:city":"Watertown",
    "sg:classifiers":[
        {
            "category":"Food & Beverages",
            "subcategory":"Liquor & Beverages",
            "type":"Retail Goods"
        }
    ],
    "sg:phone":"+1 860 274 6766",
    "sg:postcode":"06795",
    "sg:province":"CT",
    "sg:tags":[
        "alcoholic"
    ],
    "wof:name":"Highgate Liquor Shop",
    "wof:placetype":"venue"
},
  "geometry": {"coordinates":[-73.113032,41.596677],"type":"Point"}
}