{
  "type": "Feature",
  "properties": {
    "addr:full":"441 W Avon Rd Avon CT 06001",
    "addr:housenumber":"441",
    "addr:postcode":"06001",
    "addr:street":"W Avon Rd",
    "iso:country":"US",
    "sg:address":"441 W Avon Rd",
    "sg:city":"Avon",
    "sg:classifiers":[
        {
            "category":"Food & Beverages",
            "subcategory":"Groceries & Convenience Stores",
            "type":"Retail Goods"
        }
    ],
    "sg:phone":"+1 860 673 7111",
    "sg:postcode":"06001",
    "sg:province":"CT",
    "wof:name":"Mrs G's Petro Mart",
    "wof:placetype":"venue"
},
  "geometry": {"coordinates":[-72.86406100000001,41.785975],"type":"Point"}
}