{
  "type": "Feature",
  "properties": {
    "addr:full":"1242 Shippan Ave Stamford CT 06902",
    "addr:housenumber":"1242",
    "addr:postcode":"06902",
    "addr:street":"Shippan Ave",
    "iso:country":"US",
    "sg:address":"1242 Shippan Ave",
    "sg:city":"Stamford",
    "sg:classifiers":[
        {
            "category":"Building & Trades",
            "subcategory":"Landscaping Services",
            "type":"Services"
        }
    ],
    "sg:phone":"+1 203 327 2445",
    "sg:postcode":"06902",
    "sg:province":"CT",
    "wof:name":"Pj Glynn Landscaping",
    "wof:placetype":"venue"
},
  "geometry": {"coordinates":[-73.527074,41.035053],"type":"Point"}
}