{
  "type": "Feature",
  "properties": {
    "addr:full":"93 Wheeler Dr Southbury CT 06488",
    "addr:housenumber":"93",
    "addr:postcode":"06488",
    "addr:street":"Wheeler Dr",
    "iso:country":"US",
    "sg:address":"93 Wheeler Dr",
    "sg:city":"Southbury",
    "sg:classifiers":[
        {
            "category":"Building & Trades",
            "subcategory":"Construction",
            "type":"Services"
        }
    ],
    "sg:phone":"+1 203 267 5746",
    "sg:postcode":"06488",
    "sg:province":"CT",
    "sg:tags":[
        "hanging",
        "contractor"
    ],
    "wof:name":"A C O Paint & Wallpaper",
    "wof:placetype":"venue"
},
  "geometry": {"coordinates":[-73.220832,41.476186],"type":"Point"}
}