{
  "type": "Feature",
  "properties": {
    "iso:country":"US",
    "sg:address":"1215 Thomaston Ave",
    "sg:city":"Waterbury",
    "sg:classifiers":[
        {
            "category":"Manufacturing",
            "subcategory":"Metals",
            "type":"Manufacturing & Wholesale Goods"
        }
    ],
    "sg:phone":"+1 203 755 2687",
    "sg:postcode":"06704",
    "sg:province":"CT",
    "sg:website":"www.powercover.com",
    "wof:name":"Power Cover",
    "wof:placetype":"venue"
},
  "geometry": {"coordinates":[-73.054321,41.568849],"type":"Point"}
}