{
  "type": "Feature",
  "properties": {
    "addr:full":"28 E Main St Waterbury CT 06702",
    "addr:housenumber":"28",
    "addr:postcode":"06702",
    "addr:street":"E Main St",
    "iso:country":"US",
    "sg:address":"28 E Main St",
    "sg:city":"Waterbury",
    "sg:classifiers":[
        {
            "category":"Personal",
            "subcategory":"Beauty Salon",
            "type":"Services"
        }
    ],
    "sg:phone":"+1   ",
    "sg:postcode":"06702",
    "sg:province":"CT",
    "sg:tags":[
        "shop"
    ],
    "wof:name":"Chez Dior",
    "wof:placetype":"venue"
},
  "geometry": {"coordinates":[-73.04015099999999,41.55562],"type":"Point"}
}