{
  "type": "Feature",
  "properties": {
    "addr:full":"228 Fillow St Norwalk CT 06850",
    "addr:housenumber":"228",
    "addr:postcode":"06850",
    "addr:street":"Fillow St",
    "iso:country":"US",
    "sg:address":"228 Fillow St",
    "sg:city":"Norwalk",
    "sg:classifiers":[
        {
            "category":"Education",
            "subcategory":"School",
            "type":"Public Place"
        }
    ],
    "sg:phone":"+1 203 899 2860",
    "sg:postcode":"06850",
    "sg:province":"CT",
    "wof:name":"Fox Run Elementary School",
    "wof:placetype":"venue"
},
  "geometry": {"coordinates":[-73.45289699999999,41.115687],"type":"Point"}
}