{
  "type": "Feature",
  "properties": {
    "addr:full":"98 Spithead Rd Waterford CT 06385",
    "addr:housenumber":"98",
    "addr:postcode":"06385",
    "addr:street":"Spithead Rd",
    "iso:country":"US",
    "sg:address":"98 Spithead Rd",
    "sg:city":"Waterford",
    "sg:classifiers":[
        {
            "category":"Professional",
            "subcategory":"Business Services",
            "type":"Services"
        }
    ],
    "sg:phone":"+1   ",
    "sg:postcode":"06385",
    "sg:province":"CT",
    "wof:name":"Buckingham Assoc of Waterford",
    "wof:placetype":"venue"
},
  "geometry": {"coordinates":[-72.164288,41.342642],"type":"Point"}
}