{
  "type": "Feature",
  "properties": {
    "iso:country":"US",
    "sg:address":"45 E Putnam Ave",
    "sg:city":"Greenwich",
    "sg:classifiers":[
        {
            "category":"Real Estate",
            "subcategory":"Real Estate Agent",
            "type":"Services"
        }
    ],
    "sg:phone":"+1 203 661 8700",
    "sg:postcode":"06830",
    "sg:province":"CT",
    "wof:name":"Hyland Associates",
    "wof:placetype":"venue"
},
  "geometry": {"coordinates":[-73.62682,41.031408],"type":"Point"}
}