{
  "type": "Feature",
  "properties": {
    "iso:country":"US",
    "sg:address":"91 Main St",
    "sg:city":"Deep River",
    "sg:classifiers":[
        {
            "category":"Retail",
            "subcategory":"Repair Shop",
            "type":"Services"
        }
    ],
    "sg:phone":"+1   ",
    "sg:postcode":"06412",
    "sg:province":"CT",
    "sg:tags":[
        "jewelry"
    ],
    "wof:name":"Strempels Clocks",
    "wof:placetype":"venue"
},
  "geometry": {"coordinates":[-72.43825699999999,41.391231],"type":"Point"}
}