{
  "type": "Feature",
  "properties": {
    "iso:country":"US",
    "sg:address":"157 Pearl Lake Rd",
    "sg:city":"Waterbury",
    "sg:classifiers":[
        {
            "category":"Local Transit",
            "type":"Transportation"
        }
    ],
    "sg:phone":"+1 203 755 9117",
    "sg:postcode":"06706",
    "sg:province":"CT",
    "sg:tags":[
        "limousine"
    ],
    "wof:name":"East Coast Limousine LLC",
    "wof:placetype":"venue"
},
  "geometry": {"coordinates":[-73.035743,41.525564],"type":"Point"}
}