{
  "type": "Feature",
  "properties": {
    "iso:country":"US",
    "sg:address":"64 Springbrook Dr",
    "sg:city":"Glastonbury",
    "sg:classifiers":[
        {
            "category":"Shopping",
            "subcategory":"Bicycles & Sporting Goods",
            "type":"Retail Goods"
        }
    ],
    "sg:phone":"+1 860 633 8987",
    "sg:postcode":"06033",
    "sg:province":"CT",
    "wof:name":"Dwps Sport Center",
    "wof:placetype":"venue"
},
  "geometry": {"coordinates":[-72.60735,41.719428],"type":"Point"}
}