{
  "type": "Feature",
  "properties": {
    "iso:country":"US",
    "sg:address":"155 Hazard Ave",
    "sg:city":"Enfield",
    "sg:classifiers":[
        {
            "category":"Building & Trades",
            "subcategory":"Cleaning & Sanitation",
            "type":"Services"
        }
    ],
    "sg:phone":"+1   ",
    "sg:postcode":"06082",
    "sg:province":"CT",
    "sg:tags":[
        "maintenance"
    ],
    "wof:name":"Victory Dry Cleaners & Tailors",
    "wof:placetype":"venue"
},
  "geometry": {"coordinates":[-72.570944,41.989691],"type":"Point"}
}