{
  "type": "Feature",
  "properties": {
    "addr:full":"2100 Dixwell Ave Hamden CT 06514",
    "addr:housenumber":"2100",
    "addr:postcode":"06514",
    "addr:street":"Dixwell Ave",
    "iso:country":"US",
    "sg:address":"2100 Dixwell Ave",
    "sg:city":"Hamden",
    "sg:classifiers":[
        {
            "category":"Shopping",
            "type":"Retail Goods"
        }
    ],
    "sg:phone":"+1 203 230 1888",
    "sg:postcode":"06514",
    "sg:province":"CT",
    "sg:tags":[
        "pet",
        "shop"
    ],
    "wof:name":"PETCO",
    "wof:placetype":"venue"
},
  "geometry": {"coordinates":[-72.91930000000001,41.369238],"type":"Point"}
}