{
  "type": "Feature",
  "properties": {
    "addr:full":"200 New Hartford Rd Winsted CT 06098",
    "addr:housenumber":"200",
    "addr:postcode":"06098",
    "addr:street":"New Hartford Rd Winsted Ct",
    "iso:country":"US",
    "sg:address":"200 New Hartford Rd",
    "sg:city":"Winsted",
    "sg:classifiers":[
        {
            "category":"Banks & Credit Unions",
            "subcategory":"Bank",
            "type":"Services"
        }
    ],
    "sg:phone":"+1 860 379 5198",
    "sg:postcode":"06098",
    "sg:province":"CT",
    "sg:tags":[
        "state",
        "savings"
    ],
    "wof:name":"Peoples Bank",
    "wof:placetype":"venue"
},
  "geometry": {"coordinates":[-73.05107,41.911744],"type":"Point"}
}