{
  "type": "Feature",
  "properties": {
    "addr:full":"150 White Hollow Rd Sharon CT 06069",
    "addr:housenumber":"150",
    "addr:postcode":"06069",
    "addr:street":"White Hollow Rd Sharon Ct",
    "iso:country":"US",
    "sg:address":"150 White Hollow Rd",
    "sg:city":"Sharon",
    "sg:classifiers":[
        {
            "category":"Building & Trades",
            "subcategory":"Construction",
            "type":"Services"
        }
    ],
    "sg:phone":"+1 860 364 5685",
    "sg:postcode":"06069",
    "sg:province":"CT",
    "sg:tags":[
        "concrete",
        "contractor"
    ],
    "wof:name":"Short Load Specialties",
    "wof:placetype":"venue"
},
  "geometry": {"coordinates":[-73.406423,41.914698],"type":"Point"}
}