{
  "type": "Feature",
  "properties": {
    "addr:full":"2477 Boston Post Rd Guilford CT 06437",
    "addr:housenumber":"2477",
    "addr:postcode":"06437",
    "addr:street":"Boston Post Rd",
    "iso:country":"US",
    "sg:address":"2477 Boston Post Rd",
    "sg:city":"Guilford",
    "sg:classifiers":[
        {
            "category":"Retail",
            "subcategory":"Animal Services",
            "type":"Services"
        }
    ],
    "sg:phone":"+1 203 453 6433",
    "sg:postcode":"06437",
    "sg:province":"CT",
    "sg:tags":[
        "pet",
        "grooming"
    ],
    "wof:name":"Guilford Groomer",
    "wof:placetype":"venue"
},
  "geometry": {"coordinates":[-72.723197,41.308456],"type":"Point"}
}