{
  "type": "Feature",
  "properties": {
    "iso:country":"US",
    "sg:address":"145 Lang Rd",
    "sg:city":"Windsor",
    "sg:classifiers":[
        {
            "category":"Government",
            "subcategory":"Office",
            "type":"Public Place"
        }
    ],
    "sg:phone":"+1 860 285 1886",
    "sg:postcode":"06095",
    "sg:province":"CT",
    "sg:tags":[
        "conservation"
    ],
    "wof:name":"Northwest Park Nature Center",
    "wof:placetype":"venue"
},
  "geometry": {"coordinates":[-72.70329700000001,41.899943],"type":"Point"}
}