{
  "type": "Feature",
  "properties": {
    "addr:full":"25 Tabor Dr Branford CT 06405",
    "addr:housenumber":"25",
    "addr:postcode":"06405",
    "addr:street":"Tabor Dr",
    "iso:country":"US",
    "sg:address":"25 Tabor Dr",
    "sg:city":"Branford",
    "sg:classifiers":[
        {
            "category":"Organizations",
            "subcategory":"Religious Organization",
            "type":"Services"
        }
    ],
    "sg:phone":"+1   ",
    "sg:postcode":"06405",
    "sg:province":"CT",
    "wof:name":"Bryan Myers Rev",
    "wof:placetype":"venue"
},
  "geometry": {"coordinates":[-72.803105,41.272896],"type":"Point"}
}