{
  "type": "Feature",
  "properties": {
    "addr:full":"23 Burnham Hill Westport CT 06880",
    "addr:housenumber":"23",
    "addr:postcode":"06880",
    "addr:street":"Burnham Hill",
    "iso:country":"US",
    "sg:address":"23 Burnham Hill",
    "sg:city":"Westport",
    "sg:classifiers":[
        {
            "category":"Professional",
            "subcategory":"Management & Consulting",
            "type":"Services"
        }
    ],
    "sg:phone":"+1   ",
    "sg:postcode":"06880",
    "sg:province":"CT",
    "wof:name":"Gerson Marketing Services LLC",
    "wof:placetype":"venue"
},
  "geometry": {"coordinates":[-73.350433,41.115937],"type":"Point"}
}