{
  "type": "Feature",
  "properties": {
    "iso:country":"US",
    "sg:address":"864 Cove Rd",
    "sg:city":"Stamford",
    "sg:classifiers":[
        {
            "category":"Restaurant",
            "type":"Food & Drink"
        }
    ],
    "sg:phone":"+1 203 323 1059",
    "sg:postcode":"06902",
    "sg:province":"CT",
    "sg:tags":[
        "eating"
    ],
    "wof:name":"Cove Pizza Restaurant",
    "wof:placetype":"venue"
},
  "geometry": {"coordinates":[-73.50956600000001,41.048943],"type":"Point"}
}