{
  "type": "Feature",
  "properties": {
    "addr:full":"1492 High Ridge Rd Stamford CT 06903",
    "addr:housenumber":"1492",
    "addr:postcode":"06903",
    "addr:street":"High Ridge Rd",
    "iso:country":"US",
    "sg:address":"1492 High Ridge Rd",
    "sg:city":"Stamford",
    "sg:classifiers":[
        {
            "category":"Autos & Motor Vehicles",
            "subcategory":"Fuel & Gas Station",
            "type":"Retail Goods"
        }
    ],
    "sg:phone":"+1 203 322 2141",
    "sg:postcode":"06903",
    "sg:province":"CT",
    "sg:tags":[
        "station",
        "gasoline",
        "oil"
    ],
    "wof:name":"Avon Automotive Services Inc",
    "wof:placetype":"venue"
},
  "geometry": {"coordinates":[-73.54387699999999,41.120979],"type":"Point"}
}