{
  "type": "Feature",
  "properties": {
    "iso:country":"US",
    "sg:address":"19 Thompson Ave",
    "sg:city":"East Haven",
    "sg:classifiers":[
        {
            "category":"Building & Trades",
            "subcategory":"Construction",
            "type":"Services"
        }
    ],
    "sg:phone":"+1 203 467 2557",
    "sg:postcode":"06512",
    "sg:province":"CT",
    "sg:tags":[
        "roofing",
        "contractor"
    ],
    "wof:name":"AA-Msa Roof Maintenance",
    "wof:placetype":"venue"
},
  "geometry": {"coordinates":[-72.882868,41.265364],"type":"Point"}
}