{
  "type": "Feature",
  "properties": {
    "iso:country":"US",
    "sg:address":"33 Silver St",
    "sg:city":"Branford",
    "sg:classifiers":[
        {
            "category":"Building & Trades",
            "subcategory":"Construction",
            "type":"Services"
        }
    ],
    "sg:phone":"+1 203 315 0096",
    "sg:postcode":"06405",
    "sg:province":"CT",
    "sg:tags":[
        "contractor"
    ],
    "wof:name":"Kellrann Masonry",
    "wof:placetype":"venue"
},
  "geometry": {"coordinates":[-72.81074599999999,41.285731],"type":"Point"}
}