{
  "type": "Feature",
  "properties": {
    "iso:country":"US",
    "sg:address":"800 Federal Rd",
    "sg:city":"Brookfield",
    "sg:classifiers":[
        {
            "category":"Insurance",
            "subcategory":"Insurance Agent",
            "type":"Services"
        }
    ],
    "sg:phone":"+1 203 775 5400",
    "sg:postcode":"06804",
    "sg:province":"CT",
    "wof:name":"Summers Insurance",
    "wof:placetype":"venue"
},
  "geometry": {"coordinates":[-73.408715,41.478702],"type":"Point"}
}