{
  "type": "Feature",
  "properties": {
    "addr:full":"16 Fox Ridge Guilford CT 06437",
    "addr:housenumber":"16",
    "addr:postcode":"06437",
    "addr:street":"Fox",
    "iso:country":"US",
    "sg:address":"16 Fox Ridge",
    "sg:city":"Guilford",
    "sg:classifiers":[
        {
            "category":"Building & Trades",
            "subcategory":"Equipment Rental",
            "type":"Services"
        }
    ],
    "sg:phone":"+1   ",
    "sg:postcode":"06437",
    "sg:province":"CT",
    "wof:name":"Trac Leasing Company Inc",
    "wof:placetype":"venue"
},
  "geometry": {"coordinates":[-72.724682,41.303391],"type":"Point"}
}