{
  "type": "Feature",
  "properties": {
    "addr:full":"16 Forestville Ave Plainville CT 06062",
    "addr:housenumber":"16",
    "addr:postcode":"06062",
    "addr:street":"Forestville Ave",
    "iso:country":"US",
    "sg:address":"16 Forestville Ave",
    "sg:city":"Plainville",
    "sg:classifiers":[
        {
            "category":"Retail",
            "subcategory":"Auto Repair",
            "type":"Services"
        }
    ],
    "sg:phone":"+1   ",
    "sg:postcode":"06062",
    "sg:province":"CT",
    "sg:tags":[
        "automotive"
    ],
    "wof:name":"Chriss Car Clinic & U Auto Sls",
    "wof:placetype":"venue"
},
  "geometry": {"coordinates":[-72.883892,41.671551],"type":"Point"}
}