{
  "type": "Feature",
  "properties": {
    "iso:country":"US",
    "sg:address":"531 Danbury Rd",
    "sg:city":"Wilton",
    "sg:classifiers":[
        {
            "category":"Education",
            "subcategory":"School",
            "type":"Public Place"
        }
    ],
    "sg:phone":"+1 203 834 1195",
    "sg:postcode":"06897",
    "sg:province":"CT",
    "wof:name":"Montessori-Town & Country Schl",
    "wof:placetype":"venue"
},
  "geometry": {"coordinates":[-73.425082,41.227168],"type":"Point"}
}