{
  "type": "Feature",
  "properties": {
    "iso:country":"US",
    "sg:address":"525 Orange Center Rd",
    "sg:city":"Orange",
    "sg:classifiers":[
        {
            "category":"Government",
            "subcategory":"Office",
            "type":"Public Place"
        }
    ],
    "sg:phone":"+1 203 891 2122",
    "sg:postcode":"06477",
    "sg:province":"CT",
    "sg:tags":[
        "city",
        "program",
        "health"
    ],
    "wof:name":"Orange Health Dept",
    "wof:placetype":"venue"
},
  "geometry": {"coordinates":[-73.02328199999999,41.274456],"type":"Point"}
}