{
  "type": "Feature",
  "properties": {
    "addr:full":"527 Knotter Dr Cheshire CT 06410",
    "addr:housenumber":"527",
    "addr:postcode":"06410",
    "addr:street":"Knotter Dr",
    "iso:country":"US",
    "sg:address":"527 Knotter Dr",
    "sg:city":"Cheshire",
    "sg:classifiers":[
        {
            "category":"Wholesale",
            "subcategory":"Electrical",
            "type":"Manufacturing & Wholesale Goods"
        }
    ],
    "sg:phone":"+1 203 271 3600",
    "sg:postcode":"06410",
    "sg:province":"CT",
    "sg:tags":[
        "wire",
        "cable"
    ],
    "sg:website":"www.anixter.com",
    "wof:name":"Anixter",
    "wof:placetype":"venue"
},
  "geometry": {"coordinates":[-72.92212499999999,41.549601],"type":"Point"}
}