{
  "type": "Feature",
  "properties": {
    "addr:full":"10 N Water St Norwalk CT 06854",
    "addr:housenumber":"10",
    "addr:postcode":"06854",
    "addr:street":"N Water St",
    "iso:country":"US",
    "sg:address":"10 N Water St",
    "sg:city":"Norwalk",
    "sg:classifiers":[
        {
            "category":"Museum",
            "subcategory":"Botanical Garden",
            "type":"Entertainment"
        }
    ],
    "sg:phone":"+1 203 852 0700",
    "sg:postcode":"06854",
    "sg:province":"CT",
    "sg:tags":[
        "party",
        "aquarium",
        "planning",
        "event",
        "public"
    ],
    "sg:website":"www.maritimeaquarium.org",
    "wof:name":"Maritime Aquarium",
    "wof:placetype":"venue"
},
  "geometry": {"coordinates":[-73.416397,41.100239],"type":"Point"}
}