{
  "type": "Feature",
  "properties": {
    "iso:country":"US",
    "sg:address":"358 Scott Swamp Rd",
    "sg:city":"Farmington",
    "sg:classifiers":[
        {
            "category":"Recreation",
            "type":"Entertainment"
        }
    ],
    "sg:phone":"+1   ",
    "sg:postcode":"06032",
    "sg:province":"CT",
    "wof:name":"Kevin Sullivans Blk Belt Krte",
    "wof:placetype":"venue"
},
  "geometry": {"coordinates":[-72.88918,41.701438],"type":"Point"}
}