{
  "type": "Feature",
  "properties": {
    "addr:full":"15 Schuyler Ave Stamford CT 06902",
    "addr:housenumber":"15",
    "addr:postcode":"06902",
    "addr:street":"Schuyler Ave",
    "iso:country":"US",
    "sg:address":"15 Schuyler Ave",
    "sg:city":"Stamford",
    "sg:classifiers":[
        {
            "category":"Health Services",
            "subcategory":"Doctor",
            "type":"Services"
        }
    ],
    "sg:phone":"+1   ",
    "sg:postcode":"06902",
    "sg:province":"CT",
    "sg:tags":[
        "medical"
    ],
    "wof:name":"Dryer Neil P MD",
    "wof:placetype":"venue"
},
  "geometry": {"coordinates":[-73.547467,41.054301],"type":"Point"}
}