{
  "type": "Feature",
  "properties": {
    "addr:full":"78 Hickory Hill Rd Simsbury CT 06070",
    "addr:housenumber":"78",
    "addr:postcode":"06070",
    "addr:street":"Hickory Hill Rd Simsbury Ct",
    "iso:country":"US",
    "sg:address":"78 Hickory Hill Rd",
    "sg:city":"Simsbury",
    "sg:classifiers":[
        {
            "category":"Professional",
            "subcategory":"Management & Consulting",
            "type":"Services"
        }
    ],
    "sg:phone":"+1   ",
    "sg:postcode":"06070",
    "sg:province":"CT",
    "wof:name":"RE Sources Inc",
    "wof:placetype":"venue"
},
  "geometry": {"coordinates":[-72.844132,41.829612],"type":"Point"}
}