{
  "type": "Feature",
  "properties": {
    "iso:country":"US",
    "sg:address":"558 Newfield St",
    "sg:city":"Middletown",
    "sg:classifiers":[
        {
            "category":"Home & Garden",
            "subcategory":"Carpets & Floor Coverings",
            "type":"Retail Goods"
        }
    ],
    "sg:phone":"+1 860 347 9044",
    "sg:postcode":"06457",
    "sg:province":"CT",
    "wof:name":"R & M Carpet Sales",
    "wof:placetype":"venue"
},
  "geometry": {"coordinates":[-72.671875,41.574135],"type":"Point"}
}