{
  "type": "Feature",
  "properties": {
    "iso:country":"US",
    "sg:address":"46 John St",
    "sg:city":"Windsor Locks",
    "sg:classifiers":[
        {
            "category":"Building & Trades",
            "subcategory":"Plumbing",
            "type":"Services"
        }
    ],
    "sg:phone":"+1 860 291 8797",
    "sg:postcode":"06096",
    "sg:province":"CT",
    "sg:tags":[
        "contractor"
    ],
    "wof:name":"Blue Ribbon Plumbing",
    "wof:placetype":"venue"
},
  "geometry": {"coordinates":[-72.652052,41.922895],"type":"Point"}
}