{
  "type": "Feature",
  "properties": {
    "iso:country":"US",
    "sg:address":"2 Bank St",
    "sg:city":"New London",
    "sg:classifiers":[
        {
            "category":"Restaurant",
            "type":"Food & Drink"
        }
    ],
    "sg:menulink":"http://www.allmenus.com/ct/new-london/144101-subway/menu/",
    "sg:phone":"+1 860 443 0400",
    "sg:postcode":"06320",
    "sg:province":"CT",
    "sg:tags":[
        "american",
        "sandwich"
    ],
    "wof:name":"Subway",
    "wof:placetype":"venue"
},
  "geometry": {"coordinates":[-72.09383699999999,41.354042],"type":"Point"}
}