{
  "type": "Feature",
  "properties": {
    "addr:full":"42 Rockwell St Norwich CT 06360",
    "addr:housenumber":"42",
    "addr:postcode":"06360",
    "addr:street":"Rockwell St Norwich Ct",
    "iso:country":"US",
    "sg:address":"42 Rockwell St",
    "sg:city":"Norwich",
    "sg:classifiers":[
        {
            "category":"Organizations",
            "subcategory":"Professional Association",
            "type":"Services"
        }
    ],
    "sg:phone":"+1   ",
    "sg:postcode":"06360",
    "sg:province":"CT",
    "sg:tags":[
        "business"
    ],
    "wof:name":"Dar Faith Trumbull Incchapter",
    "wof:placetype":"venue"
},
  "geometry": {"coordinates":[-72.079532,41.534449],"type":"Point"}
}