{
  "type": "Feature",
  "properties": {
    "addr:full":"2377 Main St Glastonbury CT 06033",
    "addr:housenumber":"2377",
    "addr:postcode":"06033",
    "addr:street":"Main St",
    "iso:country":"US",
    "sg:address":"2377 Main St",
    "sg:city":"Glastonbury",
    "sg:classifiers":[
        {
            "category":"Personal",
            "subcategory":"Shoe Repair & Shine",
            "type":"Services"
        }
    ],
    "sg:phone":"+1   ",
    "sg:postcode":"06033",
    "sg:province":"CT",
    "sg:tags":[
        "parlor"
    ],
    "wof:name":"Nino Shoe Repair",
    "wof:placetype":"venue"
},
  "geometry": {"coordinates":[-72.60933900000001,41.713319],"type":"Point"}
}