{
  "type": "Feature",
  "properties": {
    "iso:country":"US",
    "sg:address":"880 Boston Post Rd",
    "sg:city":"Guilford",
    "sg:classifiers":[
        {
            "category":"Shopping",
            "subcategory":"Pharmacy",
            "type":"Retail Goods"
        }
    ],
    "sg:phone":"+1 203 453 4310",
    "sg:postcode":"06437",
    "sg:province":"CT",
    "wof:name":"Eckerd",
    "wof:placetype":"venue"
},
  "geometry": {"coordinates":[-72.676332,41.288695],"type":"Point"}
}