{
  "type": "Feature",
  "properties": {
    "iso:country":"US",
    "sg:address":"503 Bucks Hill Rd",
    "sg:city":"Waterbury",
    "sg:classifiers":[
        {
            "category":"Education",
            "subcategory":"School",
            "type":"Public Place"
        }
    ],
    "sg:phone":"+1 203 756 4348",
    "sg:postcode":"06704",
    "sg:province":"CT",
    "wof:name":"Connecticut Institute-Blind",
    "wof:placetype":"venue"
},
  "geometry": {"coordinates":[-73.03099400000001,41.604021],"type":"Point"}
}