{
  "type": "Feature",
  "properties": {
    "addr:full":"3 Sterling Dr Wallingford CT 06492",
    "addr:housenumber":"3",
    "addr:postcode":"06492",
    "addr:street":"Sterling Dr",
    "iso:country":"US",
    "sg:address":"3 Sterling Dr",
    "sg:city":"Wallingford",
    "sg:classifiers":[
        {
            "category":"Health Services",
            "subcategory":"Medical Lab",
            "type":"Services"
        }
    ],
    "sg:phone":"+1 203 949 5500",
    "sg:postcode":"06492",
    "sg:province":"CT",
    "sg:tags":[
        "laboratory"
    ],
    "sg:website":"www.questdiagnostics.com",
    "wof:name":"Quest Diagnostics Inc",
    "wof:placetype":"venue"
},
  "geometry": {"coordinates":[-72.794208,41.488376],"type":"Point"}
}