{
  "type": "Feature",
  "properties": {
    "iso:country":"US",
    "sg:address":"155 Main St",
    "sg:city":"Terryville",
    "sg:phone":"+1 860 582 9368",
    "sg:postcode":"06786",
    "sg:province":"CT",
    "sg:tags":[
        "farm",
        "corn"
    ],
    "wof:name":"W P Siemiatkoski",
    "wof:placetype":"venue"
},
  "geometry": {"coordinates":[-73.003987,41.678501],"type":"Point"}
}