{
  "type": "Feature",
  "properties": {
    "addr:full":"685 Baldwin St Waterbury CT 06706",
    "addr:housenumber":"685",
    "addr:postcode":"06706",
    "addr:street":"Baldwin St Waterbury Ct",
    "iso:country":"US",
    "sg:address":"685 Baldwin St",
    "sg:city":"Waterbury",
    "sg:classifiers":[
        {
            "category":"Education",
            "subcategory":"School",
            "type":"Public Place"
        }
    ],
    "sg:phone":"+1   ",
    "sg:postcode":"06706",
    "sg:province":"CT",
    "wof:name":"Washington Elementary School",
    "wof:placetype":"venue"
},
  "geometry": {"coordinates":[-73.03372,41.54255],"type":"Point"}
}