{
  "type": "Feature",
  "properties": {
    "iso:country":"US",
    "sg:address":"290 N Star Dr",
    "sg:city":"Southington",
    "sg:classifiers":[
        {
            "category":"Professional",
            "type":"Services"
        }
    ],
    "sg:phone":"+1 860 628 2994",
    "sg:postcode":"06489",
    "sg:province":"CT",
    "wof:name":"Double Nine LLC",
    "wof:placetype":"venue"
},
  "geometry": {"coordinates":[-72.838931,41.598994],"type":"Point"}
}