{
  "type": "Feature",
  "properties": {
    "iso:country":"US",
    "sg:address":"13 Woodland Park",
    "sg:city":"Windsor",
    "sg:classifiers":[
        {
            "category":"Professional",
            "type":"Services"
        }
    ],
    "sg:phone":"+1 860 688 6659",
    "sg:postcode":"06095",
    "sg:province":"CT",
    "wof:name":"Godwin C Okeke",
    "wof:placetype":"venue"
},
  "geometry": {"coordinates":[-72.647464,41.821693],"type":"Point"}
}