{
  "type": "Feature",
  "properties": {
    "iso:country":"US",
    "sg:address":"1455 Long Hill Rd",
    "sg:city":"Guilford",
    "sg:classifiers":[
        {
            "category":"Professional",
            "subcategory":"Business Services",
            "type":"Services"
        }
    ],
    "sg:phone":"+1   ",
    "sg:postcode":"06437",
    "sg:province":"CT",
    "wof:name":"Assoc For Systems Managem",
    "wof:placetype":"venue"
},
  "geometry": {"coordinates":[-72.71359099999999,41.324559],"type":"Point"}
}