{
  "type": "Feature",
  "properties": {
    "addr:full":"104 Lincoln Ave Stamford CT 06902",
    "addr:housenumber":"104",
    "addr:postcode":"06902",
    "addr:street":"Lincoln Ave",
    "iso:country":"US",
    "sg:address":"104 Lincoln Ave",
    "sg:city":"Stamford",
    "sg:classifiers":[
        {
            "category":"Professional",
            "subcategory":"Business Services",
            "type":"Services"
        }
    ],
    "sg:phone":"+1   ",
    "sg:postcode":"06902",
    "sg:province":"CT",
    "wof:name":"Digital Warehouse",
    "wof:placetype":"venue"
},
  "geometry": {"coordinates":[-73.52111600000001,41.059927],"type":"Point"}
}