{
  "type": "Feature",
  "properties": {
    "addr:full":"193 Woodmont Dr Coventry CT 06238",
    "addr:housenumber":"193",
    "addr:postcode":"06238",
    "addr:street":"Woodmont Dr",
    "iso:country":"US",
    "sg:address":"193 Woodmont Dr",
    "sg:city":"Coventry",
    "sg:classifiers":[
        {
            "category":"Cinema",
            "subcategory":"Movie Rental",
            "type":"Entertainment"
        }
    ],
    "sg:phone":"+1   ",
    "sg:postcode":"06238",
    "sg:province":"CT",
    "sg:tags":[
        "video",
        "tape"
    ],
    "wof:name":"D&D Audio/Video LLC",
    "wof:placetype":"venue"
},
  "geometry": {"coordinates":[-72.341745,41.816687],"type":"Point"}
}