{
  "type": "Feature",
  "properties": {
    "iso:country":"US",
    "sg:address":"150 Oronoque Ln",
    "sg:city":"Stratford",
    "sg:classifiers":[
        {
            "category":"Professional",
            "subcategory":"Art Services",
            "type":"Services"
        }
    ],
    "sg:phone":"+1 203 377 8822",
    "sg:postcode":"06614",
    "sg:province":"CT",
    "sg:tags":[
        "graphic",
        "design",
        "designer"
    ],
    "wof:name":"Emilio Ruiz & Associates Inc",
    "wof:placetype":"venue"
},
  "geometry": {"coordinates":[-73.11375099999999,41.250995],"type":"Point"}
}