{
  "type": "Feature",
  "properties": {
    "addr:full":"138 Spring Rd North Haven CT 06473",
    "addr:housenumber":"138",
    "addr:postcode":"06473",
    "addr:street":"Spring Rd;Haven",
    "iso:country":"US",
    "sg:address":"138 Spring Rd",
    "sg:city":"North Haven",
    "sg:classifiers":[
        {
            "category":"Recreation",
            "type":"Entertainment"
        }
    ],
    "sg:phone":"+1 203 234 2547",
    "sg:postcode":"06473",
    "sg:province":"CT",
    "sg:tags":[
        "stable"
    ],
    "wof:name":"Rambling River Ranch",
    "wof:placetype":"venue"
},
  "geometry": {"coordinates":[-72.846495,41.366678],"type":"Point"}
}