{
  "type": "Feature",
  "properties": {
    "addr:full":"10 Waterchase Dr Rocky Hill CT 06067",
    "addr:housenumber":"10",
    "addr:postcode":"06067",
    "addr:street":"Waterchase Dr;Hill Ct",
    "iso:country":"US",
    "sg:address":"10 Waterchase Dr",
    "sg:city":"Rocky Hill",
    "sg:classifiers":[
        {
            "category":"Real Estate",
            "subcategory":"Real Estate Agent",
            "type":"Services"
        }
    ],
    "sg:phone":"+1 860 257 4600",
    "sg:postcode":"06067",
    "sg:province":"CT",
    "wof:name":"Advenir LLC",
    "wof:placetype":"venue"
},
  "geometry": {"coordinates":[-72.65246,41.678011],"type":"Point"}
}