{
  "type": "Feature",
  "properties": {
    "addr:full":"858 W Main St Branford CT 06405",
    "addr:housenumber":"858",
    "addr:postcode":"06405",
    "addr:street":"W Main St",
    "iso:country":"US",
    "sg:address":"858 W Main St",
    "sg:city":"Branford",
    "sg:classifiers":[
        {
            "category":"Bakery",
            "type":"Food & Drink"
        },
        {
            "category":"Coffee & Tea",
            "type":"Food & Drink"
        },
        {
            "category":"Bagels",
            "type":"Food & Drink"
        },
        {
            "category":"Donuts",
            "type":"Food & Drink"
        }
    ],
    "sg:menulink":"http://www.allmenus.com/ct/branford/129779-dunkin-donuts/menu/",
    "sg:phone":"+1 203 488 7402",
    "sg:postcode":"06405",
    "sg:province":"CT",
    "sg:tags":[
        "american",
        "diner",
        "pastry"
    ],
    "wof:name":"Dunkin' Donuts",
    "wof:placetype":"venue"
},
  "geometry": {"coordinates":[-72.836589,41.276214],"type":"Point"}
}