{
  "type": "Feature",
  "properties": {
    "addr:full":"23 Strickland Rd Cos Cob CT 06807",
    "addr:housenumber":"23",
    "addr:postcode":"06807",
    "addr:street":"Strickland Rd;Cob Ct",
    "iso:country":"US",
    "sg:address":"23 Strickland Rd",
    "sg:city":"Cos Cob",
    "sg:classifiers":[
        {
            "category":"Professional",
            "subcategory":"Management & Consulting",
            "type":"Services"
        }
    ],
    "sg:phone":"+1   ",
    "sg:postcode":"06807",
    "sg:province":"CT",
    "wof:name":"Atlas Capital Management Inc",
    "wof:placetype":"venue"
},
  "geometry": {"coordinates":[-73.599986,41.036156],"type":"Point"}
}