{
  "type": "Feature",
  "properties": {
    "iso:country":"US",
    "sg:address":"195 Old Branchville Rd",
    "sg:city":"Ridgefield",
    "sg:classifiers":[
        {
            "category":"Professional",
            "subcategory":"Lawyer & Legal Services",
            "type":"Services"
        }
    ],
    "sg:phone":"+1 203 438 1570",
    "sg:postcode":"06877",
    "sg:province":"CT",
    "sg:tags":[
        "attorney"
    ],
    "wof:name":"A J Di Mattia",
    "wof:placetype":"venue"
},
  "geometry": {"coordinates":[-73.45935,41.265252],"type":"Point"}
}