{
  "type": "Feature",
  "properties": {
    "iso:country":"US",
    "sg:address":"487 Berkshire Rd",
    "sg:city":"Southbury",
    "sg:classifiers":[
        {
            "category":"Professional",
            "subcategory":"Computer Services",
            "type":"Services"
        }
    ],
    "sg:phone":"+1   ",
    "sg:postcode":"06488",
    "sg:province":"CT",
    "sg:tags":[
        "related"
    ],
    "wof:name":"All American Enterprises",
    "wof:placetype":"venue"
},
  "geometry": {"coordinates":[-73.25933499999999,41.443881],"type":"Point"}
}