{
  "type": "Feature",
  "properties": {
    "iso:country":"US",
    "sg:address":"2333 Congress St",
    "sg:city":"Fairfield",
    "sg:classifiers":[
        {
            "category":"Arena",
            "subcategory":"Sports Club",
            "type":"Entertainment"
        }
    ],
    "sg:phone":"+1 203 259 0621",
    "sg:postcode":"06824",
    "sg:province":"CT",
    "sg:tags":[
        "park",
        "baseball"
    ],
    "wof:name":"Baseball Gurn Com",
    "wof:placetype":"venue"
},
  "geometry": {"coordinates":[-73.276619,41.196041],"type":"Point"}
}