{
  "type": "Feature",
  "properties": {
    "addr:full":"149 Weaver St Greenwich NY 06831",
    "addr:housenumber":"149",
    "addr:postcode":"06831",
    "addr:street":"Weaver St",
    "iso:country":"US",
    "sg:address":"149 Weaver St",
    "sg:city":"Greenwich",
    "sg:classifiers":[
        {
            "category":"Manufacturing",
            "subcategory":"Printing",
            "type":"Manufacturing & Wholesale Goods"
        }
    ],
    "sg:phone":"+1 203 531 6877",
    "sg:postcode":"06831",
    "sg:province":"NY",
    "sg:tags":[
        "publisher",
        "book"
    ],
    "wof:name":"Triune Books",
    "wof:placetype":"venue"
},
  "geometry": {"coordinates":[-73.65216599999999,41.027777],"type":"Point"}
}