{
  "type": "Feature",
  "properties": {
    "iso:country":"US",
    "sg:address":"205 Barbour St",
    "sg:city":"Hartford",
    "sg:classifiers":[
        {
            "category":"Food & Beverages",
            "subcategory":"Groceries & Convenience Stores",
            "type":"Retail Goods"
        }
    ],
    "sg:phone":"+1 860 728 1378",
    "sg:postcode":"06120",
    "sg:province":"CT",
    "wof:name":"Lafayette Grocery",
    "wof:placetype":"venue"
},
  "geometry": {"coordinates":[-72.677921,41.791196],"type":"Point"}
}