{
  "type": "Feature",
  "properties": {
    "addr:full":"156 Fresh Meadow Dr Trumbull CT 06611",
    "addr:housenumber":"156",
    "addr:postcode":"06611",
    "addr:street":"Fresh Meadow Dr",
    "iso:country":"US",
    "sg:address":"156 Fresh Meadow Dr",
    "sg:city":"Trumbull",
    "sg:classifiers":[
        {
            "category":"Banks & Credit Unions",
            "subcategory":"Investment Brokerage",
            "type":"Services"
        }
    ],
    "sg:phone":"+1 203 268 2772",
    "sg:postcode":"06611",
    "sg:province":"CT",
    "sg:tags":[
        "advisory"
    ],
    "wof:name":"Smith Financial Concepts Inc",
    "wof:placetype":"venue"
},
  "geometry": {"coordinates":[-73.262601,41.282718],"type":"Point"}
}