{
  "type": "Feature",
  "properties": {
    "addr:full":"240 Post Rd E Westport CT 06880",
    "addr:housenumber":"240",
    "addr:postcode":"06880",
    "addr:street":"Post Rd E Westport Ct",
    "iso:country":"US",
    "sg:address":"240 Post Rd E",
    "sg:city":"Westport",
    "sg:classifiers":[
        {
            "category":"Professional",
            "subcategory":"Business Services",
            "type":"Services"
        }
    ],
    "sg:phone":"+1 203 341 6622",
    "sg:postcode":"06880",
    "sg:province":"CT",
    "sg:tags":[
        "interior",
        "consultant",
        "design",
        "decorator"
    ],
    "wof:name":"Jacobs Fenn Home",
    "wof:placetype":"venue"
},
  "geometry": {"coordinates":[-73.355873,41.140978],"type":"Point"}
}