{
  "type": "Feature",
  "properties": {
    "addr:full":"168 Irving Ave Port Chester CT 10573",
    "addr:housenumber":"168",
    "addr:postcode":"10573",
    "addr:street":"Irving Ave;Chester",
    "iso:country":"US",
    "sg:address":"168 Irving Ave",
    "sg:city":"Port Chester",
    "sg:classifiers":[
        {
            "category":"Professional",
            "type":"Services"
        }
    ],
    "sg:phone":"+1 914 934 2348",
    "sg:postcode":"10573",
    "sg:province":"CT",
    "sg:tags":[
        "establishment"
    ],
    "wof:name":"Digizip Inc",
    "wof:placetype":"venue"
},
  "geometry": {"coordinates":[-73.66579400000001,41.002563],"type":"Point"}
}