{
  "type": "Feature",
  "properties": {
    "iso:country":"US",
    "sg:address":"40 Kirkham St",
    "sg:city":"Branford",
    "sg:classifiers":[
        {
            "category":"Communications",
            "subcategory":"Television Station",
            "type":"Services"
        }
    ],
    "sg:phone":"+1 203 481 3232",
    "sg:postcode":"06405",
    "sg:province":"CT",
    "sg:tags":[
        "executive"
    ],
    "wof:name":"Channel 18",
    "wof:placetype":"venue"
},
  "geometry": {"coordinates":[-72.816445,41.275286],"type":"Point"}
}