{
  "type": "Feature",
  "properties": {
    "iso:country":"US",
    "sg:address":"1440 North St",
    "sg:city":"Suffield",
    "sg:classifiers":[
        {
            "category":"Professional",
            "subcategory":"Management & Consulting",
            "type":"Services"
        }
    ],
    "sg:phone":"+1 860 558 7066",
    "sg:postcode":"06078",
    "sg:province":"CT",
    "sg:tags":[
        "consultant",
        "coach",
        "business"
    ],
    "sg:website":"http://www.littlehandsmusic.com",
    "wof:name":"Litte Hands Music",
    "wof:placetype":"venue"
},
  "geometry": {"coordinates":[-72.63963800000001,42.020739],"type":"Point"}
}