{
  "type": "Feature",
  "properties": {
    "addr:full":"8 Dillon Pass Weston CT 06883",
    "addr:housenumber":"8",
    "addr:postcode":"06883",
    "addr:street":"Dillon Pass",
    "iso:country":"US",
    "sg:address":"8 Dillon Pass",
    "sg:city":"Weston",
    "sg:classifiers":[
        {
            "category":"Banks & Credit Unions",
            "subcategory":"Financial Services",
            "type":"Services"
        }
    ],
    "sg:phone":"+1 203 227 7715",
    "sg:postcode":"06883",
    "sg:province":"CT",
    "sg:tags":[
        "investment",
        "closed"
    ],
    "wof:name":"Tad Family LLC",
    "wof:placetype":"venue"
},
  "geometry": {"coordinates":[-73.383167,41.230902],"type":"Point"}
}