{
  "type": "Feature",
  "properties": {
    "iso:country":"US",
    "sg:address":"37 Brookview Ter",
    "sg:city":"Madison",
    "sg:classifiers":[
        {
            "category":"Banks & Credit Unions",
            "subcategory":"Investment Brokerage",
            "type":"Services"
        }
    ],
    "sg:phone":"+1 203 318 0528",
    "sg:postcode":"06443",
    "sg:province":"CT",
    "sg:tags":[
        "consultant",
        "planning",
        "financial"
    ],
    "wof:name":"Roberts & Assoc",
    "wof:placetype":"venue"
},
  "geometry": {"coordinates":[-72.617783,41.304042],"type":"Point"}
}