{
  "type": "Feature",
  "properties": {
    "iso:country":"US",
    "sg:address":"40 Brewster St",
    "sg:city":"Bridgeport",
    "sg:classifiers":[
        {
            "category":"Building & Trades",
            "subcategory":"Landscaping Services",
            "type":"Services"
        }
    ],
    "sg:phone":"+1 203 334 8001",
    "sg:postcode":"06605",
    "sg:province":"CT",
    "sg:tags":[
        "landscape",
        "contractor"
    ],
    "wof:name":"CCG Landscaping & Excvtng",
    "wof:placetype":"venue"
},
  "geometry": {"coordinates":[-73.219004,41.153984],"type":"Point"}
}