{
  "type": "Feature",
  "properties": {
    "iso:country":"US",
    "sg:address":"97 Fayerweather Ter",
    "sg:city":"Bridgeport",
    "sg:classifiers":[
        {
            "category":"Personal",
            "subcategory":"Beauty Salon",
            "type":"Services"
        }
    ],
    "sg:phone":"+1   ",
    "sg:postcode":"06605",
    "sg:province":"CT",
    "sg:tags":[
        "shop"
    ],
    "wof:name":"Ne Generation Event Consulting",
    "wof:placetype":"venue"
},
  "geometry": {"coordinates":[-73.225517,41.15226],"type":"Point"}
}