{
  "type": "Feature",
  "properties": {
    "addr:full":"34 Hazard Ave Enfield CT 06082",
    "addr:housenumber":"34",
    "addr:postcode":"06082",
    "addr:street":"Hazard Ave",
    "iso:country":"US",
    "sg:address":"34 Hazard Ave",
    "sg:city":"Enfield",
    "sg:classifiers":[
        {
            "category":"Utilities",
            "subcategory":"Mobile Phone",
            "type":"Services"
        },
        {
            "category":"Shopping",
            "subcategory":"Mobile Phones",
            "type":"Retail Goods"
        },
        {
            "category":"Communications",
            "type":"Services"
        },
        {
            "category":"Internet Cafe",
            "subcategory":"None",
            "type":"Food & Drink"
        }
    ],
    "sg:phone":"+1 860 745 7778",
    "sg:postcode":"06082",
    "sg:province":"CT",
    "sg:tags":[
        "supply",
        "telephone",
        "wireless",
        "equipment",
        "paging",
        "signaling",
        "cellular",
        "provider"
    ],
    "sg:website":"http://www.att.com",
    "wof:name":"AT&T",
    "wof:placetype":"venue"
},
  "geometry": {"coordinates":[-72.578406,41.989759],"type":"Point"}
}