{
  "type": "Feature",
  "properties": {
    "addr:full":"365 John Downey Dr New Britain CT 06051",
    "addr:housenumber":"365",
    "addr:postcode":"06051",
    "addr:street":"John Downey Dr",
    "iso:country":"US",
    "sg:address":"365 John Downey Dr",
    "sg:city":"New Britain",
    "sg:classifiers":[
        {
            "category":"Wholesale",
            "subcategory":"Machinery & Supplies",
            "type":"Manufacturing & Wholesale Goods"
        }
    ],
    "sg:phone":"+1 860 225 7777",
    "sg:postcode":"06051",
    "sg:province":"CT",
    "sg:tags":[
        "industrial"
    ],
    "wof:name":"Allied Industrial Products",
    "wof:placetype":"venue"
},
  "geometry": {"coordinates":[-72.75439,41.660868],"type":"Point"}
}