{
  "type": "Feature",
  "properties": {
    "iso:country":"US",
    "sg:address":"3333 Main St",
    "sg:city":"Stratford",
    "sg:classifiers":[
        {
            "category":"Professional",
            "subcategory":"Management & Consulting",
            "type":"Services"
        }
    ],
    "sg:phone":"+1 203 378 9134",
    "sg:postcode":"06614",
    "sg:province":"CT",
    "sg:tags":[
        "fuel"
    ],
    "wof:name":"Millennium Group Mgmt LLC",
    "wof:placetype":"venue"
},
  "geometry": {"coordinates":[-73.132041,41.205838],"type":"Point"}
}