{
  "type": "Feature",
  "properties": {
    "addr:full":"720 Wolcott Rd Wolcott CT 06716",
    "addr:housenumber":"720",
    "addr:postcode":"06716",
    "addr:street":"Wolcott Rd Wolcott Ct",
    "iso:country":"US",
    "sg:address":"720 Wolcott Rd",
    "sg:city":"Wolcott",
    "sg:classifiers":[
        {
            "category":"Recreation",
            "type":"Entertainment"
        }
    ],
    "sg:phone":"+1   ",
    "sg:postcode":"06716",
    "sg:province":"CT",
    "wof:name":"Family Recreation Center",
    "wof:placetype":"venue"
},
  "geometry": {"coordinates":[-72.98653400000001,41.602085],"type":"Point"}
}