{
  "type": "Feature",
  "properties": {
    "iso:country":"US",
    "sg:address":"1845 Silas Deane Hwy",
    "sg:city":"Rocky Hill",
    "sg:classifiers":[
        {
            "category":"Health Services",
            "subcategory":"Health Practitioner",
            "type":"Services"
        }
    ],
    "sg:phone":"+1   ",
    "sg:postcode":"06067",
    "sg:province":"CT",
    "wof:name":"Leigh N McClelland",
    "wof:placetype":"venue"
},
  "geometry": {"coordinates":[-72.65145099999999,41.6777],"type":"Point"}
}