{
  "type": "Feature",
  "properties": {
    "iso:country":"US",
    "sg:address":"42 Perry Merrill Dr",
    "sg:city":"West Haven",
    "sg:classifiers":[
        {
            "category":"Real Estate",
            "subcategory":"Real Estate Agent",
            "type":"Services"
        }
    ],
    "sg:phone":"+1 203 931 9633",
    "sg:postcode":"06516",
    "sg:province":"CT",
    "wof:name":"Rufrano Realty LLC",
    "wof:placetype":"venue"
},
  "geometry": {"coordinates":[-72.987094,41.251072],"type":"Point"}
}