{
  "type": "Feature",
  "properties": {
    "addr:full":"8 Rockwood Ln Danbury CT 06811",
    "addr:housenumber":"8",
    "addr:postcode":"06811",
    "addr:street":"Rockwood Ln",
    "iso:country":"US",
    "sg:address":"8 Rockwood Ln",
    "sg:city":"Danbury",
    "sg:classifiers":[
        {
            "category":"Building & Trades",
            "subcategory":"Landscaping Services",
            "type":"Services"
        }
    ],
    "sg:phone":"+1 203 743 5296",
    "sg:postcode":"06811",
    "sg:province":"CT",
    "sg:tags":[
        "landscape"
    ],
    "wof:name":"Acorn Landscaping & Excavating",
    "wof:placetype":"venue"
},
  "geometry": {"coordinates":[-73.530294,41.422467],"type":"Point"}
}