{
  "type": "Feature",
  "properties": {
    "iso:country":"US",
    "sg:address":"433 S Main St",
    "sg:city":"Hartford",
    "sg:classifiers":[
        {
            "category":"Real Estate",
            "subcategory":"Developer",
            "type":"Services"
        }
    ],
    "sg:phone":"+1 860 561 6764",
    "sg:postcode":"06110",
    "sg:province":"CT",
    "sg:tags":[
        "development",
        "management"
    ],
    "wof:name":"Samuels & Associates Inc",
    "wof:placetype":"venue"
},
  "geometry": {"coordinates":[-72.743202,41.734041],"type":"Point"}
}