{
  "type": "Feature",
  "properties": {
    "addr:full":"205 Research Dr Milford CT 06460",
    "addr:housenumber":"205",
    "addr:postcode":"06460",
    "addr:street":"Research Dr",
    "iso:country":"US",
    "sg:address":"205 Research Dr",
    "sg:city":"Milford",
    "sg:classifiers":[
        {
            "category":"Professional",
            "subcategory":"Art Services",
            "type":"Services"
        }
    ],
    "sg:phone":"+1   ",
    "sg:postcode":"06460",
    "sg:province":"CT",
    "sg:tags":[
        "photography",
        "commercial"
    ],
    "wof:name":"S M Cooper Photography",
    "wof:placetype":"venue"
},
  "geometry": {"coordinates":[-73.01094500000001,41.242039],"type":"Point"}
}