{
  "type": "Feature",
  "properties": {
    "iso:country":"US",
    "sg:address":"27 Church Hill Rd",
    "sg:city":"Glastonbury",
    "sg:classifiers":[
        {
            "category":"Communications",
            "subcategory":"Film & Video Production",
            "type":"Services"
        }
    ],
    "sg:phone":"+1   ",
    "sg:postcode":"06033",
    "sg:province":"CT",
    "sg:tags":[
        "motion"
    ],
    "wof:name":"Speed Twin Films LLC",
    "wof:placetype":"venue"
},
  "geometry": {"coordinates":[-72.51917299999999,41.714448],"type":"Point"}
}