{
  "type": "Feature",
  "properties": {
    "addr:full":"1089 Woodtick Rd Wolcott CT 06716",
    "addr:housenumber":"1089",
    "addr:postcode":"06716",
    "addr:street":"Woodtick Rd Wolcott Ct",
    "iso:country":"US",
    "sg:address":"1089 Woodtick Rd",
    "sg:city":"Wolcott",
    "sg:classifiers":[
        {
            "category":"Manufacturing",
            "subcategory":"Lumber",
            "type":"Manufacturing & Wholesale Goods"
        }
    ],
    "sg:phone":"+1 203 879 9485",
    "sg:postcode":"06716",
    "sg:province":"CT",
    "sg:tags":[
        "operation",
        "timber",
        "tract"
    ],
    "wof:name":"Pillwillup Farm",
    "wof:placetype":"venue"
},
  "geometry": {"coordinates":[-72.961563,41.604924],"type":"Point"}
}