{
  "type": "Feature",
  "properties": {
    "addr:full":"66 Quirk Rd Milford CT 06460",
    "addr:housenumber":"66",
    "addr:postcode":"06460",
    "addr:street":"Quirk Rd",
    "iso:country":"US",
    "sg:address":"66 Quirk Rd",
    "sg:city":"Milford",
    "sg:classifiers":[
        {
            "category":"Professional",
            "subcategory":"Business Services",
            "type":"Services"
        },
        {
            "category":"Building & Trades",
            "subcategory":"Construction",
            "type":"Services"
        }
    ],
    "sg:phone":"+1 203 878 3392",
    "sg:postcode":"06460",
    "sg:province":"CT",
    "sg:tags":[
        "trad",
        "dry wall",
        "contractor",
        "special"
    ],
    "wof:name":"A & A Drywall and Acoustics",
    "wof:placetype":"venue"
},
  "geometry": {"coordinates":[-73.008133,41.238753],"type":"Point"}
}