{
  "type": "Feature",
  "properties": {
    "addr:full":"13 Longview Dr Bloomfield CT 06002",
    "addr:housenumber":"13",
    "addr:postcode":"06002",
    "addr:street":"Longview Dr Bloomfield Ct",
    "iso:country":"US",
    "sg:address":"13 Longview Dr",
    "sg:city":"Bloomfield",
    "sg:classifiers":[
        {
            "category":"Shopping",
            "subcategory":"Hobbies, Toys, & Games",
            "type":"Retail Goods"
        },
        {
            "category":"Shopping",
            "subcategory":"Crafts & Fabrics",
            "type":"Retail Goods"
        }
    ],
    "sg:phone":"+1 860 206 0111",
    "sg:postcode":"06002",
    "sg:province":"CT",
    "sg:tags":[
        "shop",
        "hobby",
        "model",
        "supply"
    ],
    "wof:name":"Wood Crafts By Newman",
    "wof:placetype":"venue"
},
  "geometry": {"coordinates":[-72.726912,41.838036],"type":"Point"}
}