{
  "type": "Feature",
  "properties": {
    "addr:full":"104 Folly Ln Coventry CT 06238",
    "addr:housenumber":"104",
    "addr:postcode":"06238",
    "addr:street":"Folly Ln",
    "iso:country":"US",
    "sg:address":"104 Folly Ln",
    "sg:city":"Coventry",
    "sg:classifiers":[
        {
            "category":"Recreation",
            "type":"Entertainment"
        }
    ],
    "sg:phone":"+1   ",
    "sg:postcode":"06238",
    "sg:province":"CT",
    "sg:tags":[
        "club",
        "liquor",
        "serving",
        "golf"
    ],
    "wof:name":"Skungamaug Golf Club",
    "wof:placetype":"venue"
},
  "geometry": {"coordinates":[-72.347628,41.825639],"type":"Point"}
}