{
  "type": "Feature",
  "properties": {
    "addr:full":"51 Shunpike Rd Cromwell CT 06416",
    "addr:housenumber":"51",
    "addr:postcode":"06416",
    "addr:street":"Shunpike Rd Cromwell Ct",
    "iso:country":"US",
    "sg:address":"51 Shunpike Rd",
    "sg:city":"Cromwell",
    "sg:classifiers":[
        {
            "category":"Personal",
            "subcategory":"Beauty Salon",
            "type":"Services"
        }
    ],
    "sg:phone":"+1   ",
    "sg:postcode":"06416",
    "sg:province":"CT",
    "sg:tags":[
        "shop"
    ],
    "wof:name":"Bellas Hair Design",
    "wof:placetype":"venue"
},
  "geometry": {"coordinates":[-72.676714,41.60637],"type":"Point"}
}