{
  "type": "Feature",
  "properties": {
    "addr:full":"55 Old Lantern Rd Danbury CT 06810",
    "addr:housenumber":"55",
    "addr:postcode":"06810",
    "addr:street":"Old Lantern Rd",
    "iso:country":"US",
    "sg:address":"55 Old Lantern Rd",
    "sg:city":"Danbury",
    "sg:classifiers":[
        {
            "category":"Building & Trades",
            "subcategory":"Landscaping Services",
            "type":"Services"
        }
    ],
    "sg:phone":"+1 203 948 5090",
    "sg:postcode":"06810",
    "sg:province":"CT",
    "sg:tags":[
        "baling",
        "mulch",
        "wood",
        "for",
        "shaving"
    ],
    "wof:name":"Pauls Mulch LLC",
    "wof:placetype":"venue"
},
  "geometry": {"coordinates":[-73.431904,41.337042],"type":"Point"}
}