{
  "type": "Feature",
  "properties": {
    "addr:full":"147 Garnet Ln South Windsor CT 06074",
    "addr:housenumber":"147",
    "addr:postcode":"06074",
    "addr:street":"Garnet Ln South Windsor Ct",
    "iso:country":"US",
    "sg:address":"147 Garnet Ln",
    "sg:city":"South Windsor",
    "sg:classifiers":[
        {
            "category":"Insurance",
            "subcategory":"Insurance Agent",
            "type":"Services"
        }
    ],
    "sg:phone":"+1 860 648 4478",
    "sg:postcode":"06074",
    "sg:province":"CT",
    "wof:name":"C N A Commercial Insurance Co",
    "wof:placetype":"venue"
},
  "geometry": {"coordinates":[-72.54204300000001,41.863466],"type":"Point"}
}