{
  "type": "Feature",
  "properties": {
    "iso:country":"US",
    "sg:address":"1147 East St N",
    "sg:city":"Suffield",
    "sg:classifiers":[
        {
            "category":"Professional",
            "type":"Services"
        }
    ],
    "sg:phone":"+1 860 668 9677",
    "sg:postcode":"06078",
    "sg:province":"CT",
    "wof:name":"Andrew Fleck LLC",
    "wof:placetype":"venue"
},
  "geometry": {"coordinates":[-72.615319,42.006053],"type":"Point"}
}