{
  "type": "Feature",
  "properties": {
    "iso:country":"US",
    "sg:address":"464 Ocean Ave",
    "sg:city":"New London",
    "sg:classifiers":[
        {
            "category":"Shopping",
            "subcategory":"Pharmacy",
            "type":"Retail Goods"
        }
    ],
    "sg:phone":"+1 860 443 5331",
    "sg:postcode":"06320",
    "sg:province":"CT",
    "wof:name":"N C S Healthcare Inc",
    "wof:placetype":"venue"
},
  "geometry": {"coordinates":[-72.10423299999999,41.333461],"type":"Point"}
}