{
  "type": "Feature",
  "properties": {
    "addr:full":"195 Alvord Park Rd Torrington CT 06790",
    "addr:housenumber":"195",
    "addr:postcode":"06790",
    "addr:street":"Alvord Park Rd",
    "iso:country":"US",
    "sg:address":"195 Alvord Park Rd",
    "sg:city":"Torrington",
    "sg:classifiers":[
        {
            "category":"Government",
            "subcategory":"Office",
            "type":"Public Place"
        }
    ],
    "sg:phone":"+1 860 496 3086",
    "sg:postcode":"06790",
    "sg:province":"CT",
    "sg:tags":[
        "executive"
    ],
    "wof:name":"Dmr Northwest Regiondmr N",
    "wof:placetype":"venue"
},
  "geometry": {"coordinates":[-73.10159899999999,41.823789],"type":"Point"}
}