{
  "type": "Feature",
  "properties": {
    "addr:full":"19 Wild Rose Rd Westport CT 06880",
    "addr:housenumber":"19",
    "addr:postcode":"06880",
    "addr:street":"Wild Rose Rd",
    "iso:country":"US",
    "sg:address":"19 Wild Rose Rd",
    "sg:city":"Westport",
    "sg:classifiers":[
        {
            "category":"Communications",
            "subcategory":"Film & Video Production",
            "type":"Services"
        }
    ],
    "sg:phone":"+1   ",
    "sg:postcode":"06880",
    "sg:province":"CT",
    "sg:tags":[
        "motion"
    ],
    "wof:name":"Cinnamon Productions Inc",
    "wof:placetype":"venue"
},
  "geometry": {"coordinates":[-73.360153,41.150371],"type":"Point"}
}