{
  "type": "Feature",
  "properties": {
    "iso:country":"US",
    "sg:address":"68 Weaver St",
    "sg:city":"Greenwich",
    "sg:classifiers":[
        {
            "category":"Freight",
            "type":"Transportation"
        }
    ],
    "sg:phone":"+1 203 531 7075",
    "sg:postcode":"06831",
    "sg:province":"CT",
    "sg:tags":[
        "trucking"
    ],
    "wof:name":"Jeff Benvenuto Truckin",
    "wof:placetype":"venue"
},
  "geometry": {"coordinates":[-73.650114,41.020483],"type":"Point"}
}