{
  "type": "Feature",
  "properties": {
    "addr:full":"280 N Colony St Wallingford CT 06492",
    "addr:housenumber":"280",
    "addr:postcode":"06492",
    "addr:street":"N Colony St",
    "iso:country":"US",
    "sg:address":"280 N Colony St",
    "sg:city":"Wallingford",
    "sg:classifiers":[
        {
            "category":"Retail",
            "subcategory":"Auto Repair",
            "type":"Services"
        }
    ],
    "sg:phone":"+1 203 265 1324",
    "sg:postcode":"06492",
    "sg:province":"CT",
    "sg:tags":[
        "body",
        "automobile",
        "painting"
    ],
    "wof:name":"Super Sales Auto Body Inc",
    "wof:placetype":"venue"
},
  "geometry": {"coordinates":[-72.82111399999999,41.461932],"type":"Point"}
}