{
  "type": "Feature",
  "properties": {
    "addr:full":"1905 State St Hamden CT 06517",
    "addr:housenumber":"1905",
    "addr:postcode":"06517",
    "addr:street":"State St",
    "iso:country":"US",
    "sg:address":"1905 State St",
    "sg:city":"Hamden",
    "sg:classifiers":[
        {
            "category":"Professional",
            "subcategory":"Lawyer & Legal Services",
            "type":"Services"
        }
    ],
    "sg:phone":"+1   ",
    "sg:postcode":"06517",
    "sg:province":"CT",
    "wof:name":"Tony Karajanis Attorney",
    "wof:placetype":"venue"
},
  "geometry": {"coordinates":[-72.90054499999999,41.333205],"type":"Point"}
}