{
  "type": "Feature",
  "properties": {
    "addr:full":"89 Beverly Rd New Haven CT 06515",
    "addr:housenumber":"89",
    "addr:postcode":"06515",
    "addr:street":"Beverly Rd",
    "iso:country":"US",
    "sg:address":"89 Beverly Rd",
    "sg:city":"New Haven",
    "sg:classifiers":[
        {
            "category":"Professional",
            "subcategory":"Business Services",
            "type":"Services"
        }
    ],
    "sg:phone":"+1   ",
    "sg:postcode":"06515",
    "sg:province":"CT",
    "sg:tags":[
        "record",
        "company",
        "entertainment"
    ],
    "wof:name":"Crumbs 2 Bricks Entrmt LLC",
    "wof:placetype":"venue"
},
  "geometry": {"coordinates":[-72.977718,41.33245],"type":"Point"}
}