{
  "type": "Feature",
  "properties": {
    "addr:full":"2 Highland Pl Greenwich NY 06831",
    "addr:housenumber":"2",
    "addr:postcode":"06831",
    "addr:street":"Highland Pl",
    "iso:country":"US",
    "sg:address":"2 Highland Pl",
    "sg:city":"Greenwich",
    "sg:classifiers":[
        {
            "category":"Building & Trades",
            "subcategory":"Electrical",
            "type":"Services"
        }
    ],
    "sg:phone":"+1 203 531 2895",
    "sg:postcode":"06831",
    "sg:province":"NY",
    "sg:tags":[
        "electrical",
        "contractor"
    ],
    "wof:name":"Randall Enterprises",
    "wof:placetype":"venue"
},
  "geometry": {"coordinates":[-73.65348299999999,41.020137],"type":"Point"}
}