{
  "type": "Feature",
  "properties": {
    "iso:country":"US",
    "sg:address":"27 Pond Rd",
    "sg:city":"Litchfield",
    "sg:classifiers":[
        {
            "category":"Wholesale",
            "subcategory":"Construction Materials",
            "type":"Manufacturing & Wholesale Goods"
        }
    ],
    "sg:phone":"+1 860 489 8012",
    "sg:postcode":"06754",
    "sg:province":"CT",
    "wof:name":"J Riga",
    "wof:placetype":"venue"
},
  "geometry": {"coordinates":[-73.362758,41.798604],"type":"Point"}
}