{
  "type": "Feature",
  "properties": {
    "iso:country":"US",
    "sg:address":"254 Hyland Ter",
    "sg:city":"Orange",
    "sg:classifiers":[
        {
            "category":"Freight",
            "type":"Transportation"
        }
    ],
    "sg:phone":"+1 203 795 4475",
    "sg:postcode":"06477",
    "sg:province":"CT",
    "wof:name":"Back In Black Transport LLC",
    "wof:placetype":"venue"
},
  "geometry": {"coordinates":[-73.043086,41.304779],"type":"Point"}
}