{
  "type": "Feature",
  "properties": {
    "addr:full":"70 Shelter Rock Rd Stamford CT 06903",
    "addr:housenumber":"70",
    "addr:postcode":"06903",
    "addr:street":"Shelter Rock Rd",
    "iso:country":"US",
    "sg:address":"70 Shelter Rock Rd",
    "sg:city":"Stamford",
    "sg:classifiers":[
        {
            "category":"Communications",
            "subcategory":"Film & Video Production",
            "type":"Services"
        }
    ],
    "sg:phone":"+1   ",
    "sg:postcode":"06903",
    "sg:province":"CT",
    "sg:tags":[
        "motion"
    ],
    "wof:name":"Brent Ramsey Productions",
    "wof:placetype":"venue"
},
  "geometry": {"coordinates":[-73.591492,41.127091],"type":"Point"}
}