{
  "type": "Feature",
  "properties": {
    "iso:country":"US",
    "sg:address":"40 Judson Ct",
    "sg:city":"Cheshire",
    "sg:classifiers":[
        {
            "category":"Health Services",
            "subcategory":"Doctor",
            "type":"Services"
        }
    ],
    "sg:phone":"+1   ",
    "sg:postcode":"06410",
    "sg:province":"CT",
    "sg:tags":[
        "medical"
    ],
    "wof:name":"Jay Kaplan MD",
    "wof:placetype":"venue"
},
  "geometry": {"coordinates":[-72.884996,41.499896],"type":"Point"}
}