{
  "type": "Feature",
  "properties": {
    "addr:full":"562 Milford Point Rd Milford CT 06460",
    "addr:housenumber":"562",
    "addr:postcode":"06460",
    "addr:street":"Milford Point Rd",
    "iso:country":"US",
    "sg:address":"562 Milford Point Rd",
    "sg:city":"Milford",
    "sg:classifiers":[
        {
            "category":"Building & Trades",
            "subcategory":"Construction",
            "type":"Services"
        }
    ],
    "sg:phone":"+1 203 876 1407",
    "sg:postcode":"06460",
    "sg:province":"CT",
    "sg:tags":[
        "dry wall",
        "contractor"
    ],
    "wof:name":"Dry Wall By Bellegarde",
    "wof:placetype":"venue"
},
  "geometry": {"coordinates":[-73.09584700000001,41.192879],"type":"Point"}
}