{
  "type": "Feature",
  "properties": {
    "iso:country":"US",
    "sg:address":"36 Tanglewood Dr",
    "sg:city":"Danbury",
    "sg:classifiers":[
        {
            "category":"Professional",
            "type":"Services"
        }
    ],
    "sg:phone":"+1 203 778 6011",
    "sg:postcode":"06811",
    "sg:province":"CT",
    "wof:name":"Pirtek-Fairfield",
    "wof:placetype":"venue"
},
  "geometry": {"coordinates":[-73.524784,41.405023],"type":"Point"}
}