{
  "type": "Feature",
  "properties": {
    "iso:country":"US",
    "sg:address":"153 White St",
    "sg:city":"Danbury",
    "sg:classifiers":[
        {
            "category":"Professional",
            "subcategory":"Lawyer & Legal Services",
            "type":"Services"
        }
    ],
    "sg:phone":"+1   ",
    "sg:postcode":"06810",
    "sg:province":"CT",
    "sg:tags":[
        "law"
    ],
    "wof:name":"McGetrick Michael S",
    "wof:placetype":"venue"
},
  "geometry": {"coordinates":[-73.447332,41.399377],"type":"Point"}
}