{
  "type": "Feature",
  "properties": {
    "addr:full":"1230 Old Town Rd Trumbull CT 06611",
    "addr:housenumber":"1230",
    "addr:postcode":"06611",
    "addr:street":"Old Town Rd",
    "iso:country":"US",
    "sg:address":"1230 Old Town Rd",
    "sg:city":"Trumbull",
    "sg:classifiers":[
        {
            "category":"Retail",
            "subcategory":"Repair Shop",
            "type":"Services"
        }
    ],
    "sg:phone":"+1   ",
    "sg:postcode":"06611",
    "sg:province":"CT",
    "wof:name":"Truball Piano Services",
    "wof:placetype":"venue"
},
  "geometry": {"coordinates":[-73.195381,41.227393],"type":"Point"}
}