{
  "type": "Feature",
  "properties": {
    "iso:country":"US",
    "sg:address":"17 Mountain Ave",
    "sg:city":"Bloomfield",
    "sg:classifiers":[
        {
            "category":"Social Services",
            "type":"Services"
        }
    ],
    "sg:phone":"+1 860 242 1895",
    "sg:postcode":"06002",
    "sg:province":"CT",
    "sg:tags":[
        "executive"
    ],
    "wof:name":"Bloomfield Social & Youth Svcs",
    "wof:placetype":"venue"
},
  "geometry": {"coordinates":[-72.73922399999999,41.830849],"type":"Point"}
}