{
  "type": "Feature",
  "properties": {
    "addr:full":"89 Ball Pond Rd New Fairfield CT 06812",
    "addr:housenumber":"89",
    "addr:postcode":"06812",
    "addr:street":"Ball Pond Rd New Fairfield Ct",
    "iso:country":"US",
    "sg:address":"89 Ball Pond Rd",
    "sg:city":"New Fairfield",
    "sg:classifiers":[
        {
            "category":"Shopping",
            "subcategory":"Computers & Home Electronics",
            "type":"Retail Goods"
        }
    ],
    "sg:phone":"+1 203 312 0859",
    "sg:postcode":"06812",
    "sg:province":"CT",
    "sg:tags":[
        "software"
    ],
    "sg:website":"www.filemaxx.com",
    "wof:name":"Receptor Software LLC",
    "wof:placetype":"venue"
},
  "geometry": {"coordinates":[-73.52558399999999,41.460779],"type":"Point"}
}