{
  "type": "Feature",
  "properties": {
    "addr:full":"87 Skyview Dr Trumbull CT 06611",
    "addr:housenumber":"87",
    "addr:postcode":"06611",
    "addr:street":"Skyview Dr",
    "iso:country":"US",
    "sg:address":"87 Skyview Dr",
    "sg:city":"Trumbull",
    "sg:classifiers":[
        {
            "category":"Banks & Credit Unions",
            "subcategory":"Investment Brokerage",
            "type":"Services"
        }
    ],
    "sg:phone":"+1 203 377 2889",
    "sg:postcode":"06611",
    "sg:province":"CT",
    "sg:tags":[
        "advisory"
    ],
    "wof:name":"Lifetime Financial Strategies",
    "wof:placetype":"venue"
},
  "geometry": {"coordinates":[-73.17231200000001,41.256912],"type":"Point"}
}