{
  "type": "Feature",
  "properties": {
    "iso:country":"US",
    "sg:address":"30 Inwood Rd",
    "sg:city":"Rocky Hill",
    "sg:classifiers":[
        {
            "category":"Manufacturing",
            "subcategory":"Chemicals & Compounds",
            "type":"Manufacturing & Wholesale Goods"
        }
    ],
    "sg:phone":"+1 860 571 5100",
    "sg:postcode":"06067",
    "sg:province":"CT",
    "sg:tags":[
        "adhesive",
        "sealing",
        "mfg"
    ],
    "wof:name":"Rapid Response Center",
    "wof:placetype":"venue"
},
  "geometry": {"coordinates":[-72.679778,41.637582],"type":"Point"}
}