{
  "type": "Feature",
  "properties": {
    "addr:full":"920 Hopmeadow St Simsbury CT 06070",
    "addr:housenumber":"920",
    "addr:postcode":"06070",
    "addr:street":"Hopmeadow St Simsbury Ct",
    "iso:country":"US",
    "sg:address":"920 Hopmeadow St",
    "sg:city":"Simsbury",
    "sg:classifiers":[
        {
            "category":"Banks & Credit Unions",
            "subcategory":"Financial Services",
            "type":"Services"
        }
    ],
    "sg:phone":"+1 860 658 1981",
    "sg:postcode":"06070",
    "sg:province":"CT",
    "sg:tags":[
        "broker",
        "real estate"
    ],
    "wof:name":"P C R E LLC",
    "wof:placetype":"venue"
},
  "geometry": {"coordinates":[-72.799825,41.881008],"type":"Point"}
}