{
  "type": "Feature",
  "properties": {
    "iso:country":"US",
    "sg:address":"8 Hillside Ct",
    "sg:city":"Brookfield",
    "sg:classifiers":[
        {
            "category":"Building & Trades",
            "subcategory":"Plumbing",
            "type":"Services"
        }
    ],
    "sg:phone":"+1 203 740 1709",
    "sg:postcode":"06804",
    "sg:province":"CT",
    "sg:tags":[
        "conditioning",
        "air",
        "system",
        "contractor"
    ],
    "wof:name":"Corna Heating & Cooling",
    "wof:placetype":"venue"
},
  "geometry": {"coordinates":[-73.415486,41.473466],"type":"Point"}
}