{
  "type": "Feature",
  "properties": {
    "iso:country":"US",
    "sg:address":"134 State Hwy 12",
    "sg:city":"Preston",
    "sg:classifiers":[
        {
            "category":"Bars & Pubs",
            "type":"Food & Drink"
        }
    ],
    "sg:phone":"+1 860 889 5659",
    "sg:postcode":"06365",
    "sg:province":"CT",
    "sg:tags":[
        "lounge"
    ],
    "wof:name":"Davids Cafe",
    "wof:placetype":"venue"
},
  "geometry": {"coordinates":[-72.064679,41.47526],"type":"Point"}
}