{
  "type": "Feature",
  "properties": {
    "addr:full":"85 Mill Plain Rd Danbury CT 06811",
    "addr:housenumber":"85",
    "addr:postcode":"06811",
    "addr:street":"Mill Plain Rd",
    "iso:country":"US",
    "sg:address":"85 Mill Plain Rd",
    "sg:city":"Danbury",
    "sg:classifiers":[
        {
            "category":"Retail",
            "subcategory":"Auto Repair",
            "type":"Services"
        }
    ],
    "sg:phone":"+1   ",
    "sg:postcode":"06811",
    "sg:province":"CT",
    "sg:tags":[
        "body"
    ],
    "wof:name":"State Line Auto Body",
    "wof:placetype":"venue"
},
  "geometry": {"coordinates":[-73.512934,41.394373],"type":"Point"}
}