{
  "type": "Feature",
  "properties": {
    "iso:country":"US",
    "sg:address":"215 Daniels Ave",
    "sg:city":"Bridgeport",
    "sg:classifiers":[
        {
            "category":"Retail",
            "subcategory":"Animal Services",
            "type":"Services"
        }
    ],
    "sg:phone":"+1 203 371 5780",
    "sg:postcode":"06606",
    "sg:province":"CT",
    "sg:tags":[
        "pet",
        "grooming",
        "washing"
    ],
    "wof:name":"You Dirty Dog",
    "wof:placetype":"venue"
},
  "geometry": {"coordinates":[-73.189455,41.221661],"type":"Point"}
}