{
  "type": "Feature",
  "properties": {
    "addr:full":"39 Water St Torrington CT 06790",
    "addr:housenumber":"39",
    "addr:postcode":"06790",
    "addr:street":"Water St",
    "iso:country":"US",
    "sg:address":"39 Water St",
    "sg:city":"Torrington",
    "sg:classifiers":[
        {
            "category":"Shopping",
            "subcategory":"Jewelry",
            "type":"Retail Goods"
        },
        {
            "category":"Retail",
            "subcategory":"Repair Shop",
            "type":"Services"
        },
        {
            "category":"Manufacturing",
            "subcategory":"Jewelry",
            "type":"Manufacturing & Wholesale Goods"
        }
    ],
    "sg:phone":"+1 860 482 5810",
    "sg:postcode":"06790",
    "sg:province":"CT",
    "sg:tags":[
        "stone",
        "designer",
        "jewelers-wholesale",
        "clock",
        "watch",
        "jeweler",
        "precious",
        "semi-precious",
        "manufacturer"
    ],
    "wof:name":"O'sullivan's Jewelers",
    "wof:placetype":"venue"
},
  "geometry": {"coordinates":[-73.121944,41.801259],"type":"Point"}
}