{
  "type": "Feature",
  "properties": {
    "iso:country":"US",
    "sg:address":"3005 Main St",
    "sg:city":"Stratford",
    "sg:classifiers":[
        {
            "category":"Professional",
            "subcategory":"Lawyer & Legal Services",
            "type":"Services"
        }
    ],
    "sg:phone":"+1   ",
    "sg:postcode":"06614",
    "sg:province":"CT",
    "wof:name":"Richard Bortolot LLC",
    "wof:placetype":"venue"
},
  "geometry": {"coordinates":[-73.131252,41.201737],"type":"Point"}
}