{
  "type": "Feature",
  "properties": {
    "iso:country":"US",
    "sg:address":"6 Sycamore Way",
    "sg:city":"Branford",
    "sg:classifiers":[
        {
            "category":"Building & Trades",
            "subcategory":"Construction",
            "type":"Services"
        }
    ],
    "sg:phone":"+1 203 315 0093",
    "sg:postcode":"06405",
    "sg:province":"CT",
    "sg:tags":[
        "concrete",
        "contractor"
    ],
    "wof:name":"A L Franklyn Foundations",
    "wof:placetype":"venue"
},
  "geometry": {"coordinates":[-72.762277,41.29891],"type":"Point"}
}