{
  "type": "Feature",
  "properties": {
    "iso:country":"US",
    "sg:address":"24 Thorpe St",
    "sg:city":"Fairfield",
    "sg:classifiers":[
        {
            "category":"Professional",
            "subcategory":"Management & Consulting",
            "type":"Services"
        }
    ],
    "sg:phone":"+1 203 259 4004",
    "sg:postcode":"06473",
    "sg:province":"CT",
    "sg:tags":[
        "fuel"
    ],
    "wof:name":"Charter Research & Investment",
    "wof:placetype":"venue"
},
  "geometry": {"coordinates":[-72.85631600000001,41.392381],"type":"Point"}
}