{
  "type": "Feature",
  "properties": {
    "iso:country":"US",
    "sg:address":"84 Branford Rd",
    "sg:city":"North Branford",
    "sg:classifiers":[
        {
            "category":"Building & Trades",
            "subcategory":"Plumbing",
            "type":"Services"
        }
    ],
    "sg:phone":"+1 203 481 9558",
    "sg:postcode":"06471",
    "sg:province":"CT",
    "sg:tags":[
        "plumbing",
        "contractor"
    ],
    "wof:name":"Ronald Mattson & Son",
    "wof:placetype":"venue"
},
  "geometry": {"coordinates":[-72.77149300000001,41.310457],"type":"Point"}
}