{
  "type": "Feature",
  "properties": {
    "iso:country":"US",
    "sg:address":"30 W Mountain Rd",
    "sg:city":"Washington",
    "sg:classifiers":[
        {
            "category":"Building & Trades",
            "subcategory":"Construction",
            "type":"Services"
        }
    ],
    "sg:phone":"+1 860 868 7528",
    "sg:postcode":"06793",
    "sg:province":"CT",
    "sg:tags":[
        "family",
        "construct",
        "general",
        "new",
        "home",
        "contractor"
    ],
    "wof:name":"Walter Johnson Builders Inc",
    "wof:placetype":"venue"
},
  "geometry": {"coordinates":[-73.28051600000001,41.611535],"type":"Point"}
}