{
  "type": "Feature",
  "properties": {
    "addr:full":"136 Jefferson Ave New London CT 06320",
    "addr:housenumber":"136",
    "addr:postcode":"06320",
    "addr:street":"Jefferson Ave New London Ct",
    "iso:country":"US",
    "sg:address":"136 Jefferson Ave",
    "sg:city":"New London",
    "sg:classifiers":[
        {
            "category":"Utilities",
            "subcategory":"Fuel Oil & Lpg",
            "type":"Services"
        }
    ],
    "sg:phone":"+1   ",
    "sg:postcode":"06320",
    "sg:province":"CT",
    "sg:tags":[
        "car",
        "used",
        "truck",
        "motorcycle"
    ],
    "wof:name":"Bernies Fuel Oil",
    "wof:placetype":"venue"
},
  "geometry": {"coordinates":[-72.10926600000001,41.352176],"type":"Point"}
}