{
  "type": "Feature",
  "properties": {
    "addr:full":"120 Carew Rd Hamden CT 06517",
    "addr:housenumber":"120",
    "addr:postcode":"06517",
    "addr:street":"Carew Rd",
    "iso:country":"US",
    "sg:address":"120 Carew Rd",
    "sg:city":"Hamden",
    "sg:classifiers":[
        {
            "category":"Organizations",
            "subcategory":"Community Association",
            "type":"Services"
        }
    ],
    "sg:phone":"+1 203 407 2035",
    "sg:postcode":"06517",
    "sg:province":"CT",
    "sg:tags":[
        "executive"
    ],
    "wof:name":"Ridge Hill School",
    "wof:placetype":"venue"
},
  "geometry": {"coordinates":[-72.89797,41.346607],"type":"Point"}
}