{
  "type": "Feature",
  "properties": {
    "addr:full":"171 Brownstone Ave Portland CT 06480",
    "addr:housenumber":"171",
    "addr:postcode":"06480",
    "addr:street":"Brownstone Ave",
    "iso:country":"US",
    "sg:address":"171 Brownstone Ave",
    "sg:city":"Portland",
    "sg:classifiers":[
        {
            "category":"Wholesale",
            "subcategory":"Construction Materials",
            "type":"Manufacturing & Wholesale Goods"
        }
    ],
    "sg:phone":"+1 860 342 2227",
    "sg:postcode":"06480",
    "sg:province":"CT",
    "sg:tags":[
        "asphalt"
    ],
    "wof:name":"Portland Asphalt LLC",
    "wof:placetype":"venue"
},
  "geometry": {"coordinates":[-72.645081,41.576029],"type":"Point"}
}