{
  "type": "Feature",
  "properties": {
    "addr:full":"365 E Washington Ave Bridgeport CT 06608",
    "addr:housenumber":"365",
    "addr:postcode":"06608",
    "addr:street":"E Washington Ave",
    "iso:country":"US",
    "sg:address":"365 E Washington Ave",
    "sg:city":"Bridgeport",
    "sg:classifiers":[
        {
            "category":"Organizations",
            "subcategory":"Religious Organization",
            "type":"Services"
        }
    ],
    "sg:phone":"+1   ",
    "sg:postcode":"06608",
    "sg:province":"CT",
    "wof:name":"Holy Rosary Catholic Church",
    "wof:placetype":"venue"
},
  "geometry": {"coordinates":[-73.185626,41.185981],"type":"Point"}
}