{
  "type": "Feature",
  "properties": {
    "addr:full":"1 Heritage Dr Windsor CT 06095",
    "addr:housenumber":"1",
    "addr:postcode":"06095",
    "addr:street":"Heritage Dr",
    "iso:country":"US",
    "sg:address":"1 Heritage Dr",
    "sg:city":"Windsor",
    "sg:classifiers":[
        {
            "category":"Professional",
            "type":"Services"
        }
    ],
    "sg:phone":"+1 860 687 9953",
    "sg:postcode":"06095",
    "sg:province":"CT",
    "wof:name":"Abcd Rom Incorporated",
    "wof:placetype":"venue"
},
  "geometry": {"coordinates":[-72.65503699999999,41.852795],"type":"Point"}
}