{
  "type": "Feature",
  "properties": {
    "iso:country":"US",
    "sg:address":"281 State St",
    "sg:city":"New London",
    "sg:classifiers":[
        {
            "category":"Real Estate",
            "subcategory":"Real Estate Operator",
            "type":"Services"
        }
    ],
    "sg:phone":"+1 860 442 9590",
    "sg:postcode":"06320",
    "sg:province":"CT",
    "sg:tags":[
        "apartment",
        "complex"
    ],
    "wof:name":"Mohican Senior Apartments",
    "wof:placetype":"venue"
},
  "geometry": {"coordinates":[-72.098403,41.355074],"type":"Point"}
}