{
  "type": "Feature",
  "properties": {
    "addr:full":"758 Colonel Ledyard Hwy Ledyard CT 06339",
    "addr:housenumber":"758",
    "addr:postcode":"06339",
    "addr:street":"Colonel Ledyard Hwy Ledyard Ct",
    "iso:country":"US",
    "sg:address":"758 Colonel Ledyard Hwy",
    "sg:city":"Ledyard",
    "sg:classifiers":[
        {
            "category":"Communications",
            "subcategory":"Radio Station",
            "type":"Services"
        }
    ],
    "sg:phone":"+1 860 464 1077",
    "sg:postcode":"06339",
    "sg:province":"CT",
    "sg:tags":[
        "broadcast"
    ],
    "wof:name":"Jammin 107.7 Wwrx Request",
    "wof:placetype":"venue"
},
  "geometry": {"coordinates":[-72.018123,41.445086],"type":"Point"}
}