{
  "type": "Feature",
  "properties": {
    "addr:full":"57 William Shorty Campbell St Hartford CT 06106",
    "addr:housenumber":"57",
    "addr:postcode":"06106",
    "addr:street":"William Shorty;St",
    "iso:country":"US",
    "sg:address":"57 William Shorty Campbell St",
    "sg:city":"Hartford",
    "sg:classifiers":[
        {
            "category":"Bakery",
            "type":"Food & Drink"
        },
        {
            "category":"Coffee & Tea",
            "type":"Food & Drink"
        },
        {
            "category":"Bagels",
            "type":"Food & Drink"
        },
        {
            "category":"Donuts",
            "type":"Food & Drink"
        }
    ],
    "sg:menulink":"http://www.allmenus.com/ct/hartford/129897-dunkin-donuts/menu/",
    "sg:phone":"+1 860 953 5590",
    "sg:postcode":"06106",
    "sg:province":"CT",
    "sg:tags":[
        "american",
        "diner",
        "pastry"
    ],
    "wof:name":"Dunkin' Donuts",
    "wof:placetype":"venue"
},
  "geometry": {"coordinates":[-72.709682,41.740998],"type":"Point"}
}