{
  "type": "Feature",
  "properties": {
    "addr:full":"18 Lafayette Pl Greenwich CT 06830",
    "addr:housenumber":"18",
    "addr:postcode":"06830",
    "addr:street":"Lafayette Pl",
    "iso:country":"US",
    "sg:address":"18 Lafayette Pl",
    "sg:city":"Greenwich",
    "sg:classifiers":[
        {
            "category":"Social Services",
            "type":"Services"
        }
    ],
    "sg:phone":"+1 203 869 5221",
    "sg:postcode":"06830",
    "sg:province":"CT",
    "sg:tags":[
        "organization",
        "welfare"
    ],
    "wof:name":"Alcoholics Anonymous",
    "wof:placetype":"venue"
},
  "geometry": {"coordinates":[-73.627718,41.032131],"type":"Point"}
}