{
  "type": "Feature",
  "properties": {
    "iso:country":"US",
    "sg:address":"39 Highwood Rd",
    "sg:city":"Farmington",
    "sg:classifiers":[
        {
            "category":"Health Services",
            "subcategory":"Medical Lab",
            "type":"Services"
        }
    ],
    "sg:phone":"+1   ",
    "sg:postcode":"06032",
    "sg:province":"CT",
    "sg:tags":[
        "laboratory",
        "dental"
    ],
    "wof:name":"Farmington Dental Studio",
    "wof:placetype":"venue"
},
  "geometry": {"coordinates":[-72.86841,41.755915],"type":"Point"}
}