{
  "type": "Feature",
  "properties": {
    "addr:full":"263 Tresser Blvd Stamford CT 06901",
    "addr:housenumber":"263",
    "addr:postcode":"06901",
    "addr:street":"Tresser Blvd",
    "iso:country":"US",
    "sg:address":"263 Tresser Blvd",
    "sg:city":"Stamford",
    "sg:classifiers":[
        {
            "category":"Banks & Credit Unions",
            "subcategory":"Investment Brokerage",
            "type":"Services"
        }
    ],
    "sg:phone":"+1 203 425 1420",
    "sg:postcode":"06901",
    "sg:province":"CT",
    "sg:tags":[
        "consultant",
        "planning",
        "financial"
    ],
    "sg:website":"www.sebank.se",
    "wof:name":"SEB Asset Management",
    "wof:placetype":"venue"
},
  "geometry": {"coordinates":[-73.53298700000001,41.052912],"type":"Point"}
}