{
  "type": "Feature",
  "properties": {
    "addr:full":"731 Main St Monroe CT 06468",
    "addr:housenumber":"731",
    "addr:postcode":"06468",
    "addr:street":"Main St",
    "iso:country":"US",
    "sg:address":"731 Main St",
    "sg:city":"Monroe",
    "sg:classifiers":[
        {
            "category":"Insurance",
            "subcategory":"Health Insurance",
            "type":"Services"
        }
    ],
    "sg:phone":"+1 203 445 9095",
    "sg:postcode":"06468",
    "sg:province":"CT",
    "sg:tags":[
        "carrier"
    ],
    "wof:name":"John P Woods Co Inc",
    "wof:placetype":"venue"
},
  "geometry": {"coordinates":[-73.26248,41.339656],"type":"Point"}
}