{
  "type": "Feature",
  "properties": {
    "addr:full":"55 Church St New Haven CT 06510",
    "addr:housenumber":"55",
    "addr:postcode":"06510",
    "addr:street":"Church St",
    "iso:country":"US",
    "sg:address":"55 Church St",
    "sg:city":"New Haven",
    "sg:classifiers":[
        {
            "category":"Local Transit",
            "type":"Transportation"
        }
    ],
    "sg:phone":"+1 203 562 4104",
    "sg:postcode":"06510",
    "sg:province":"CT",
    "sg:tags":[
        "ambulance"
    ],
    "wof:name":"American Medical Response",
    "wof:placetype":"venue"
},
  "geometry": {"coordinates":[-72.926349,41.305084],"type":"Point"}
}