{
  "type": "Feature",
  "properties": {
    "addr:full":"33 W Main St Clinton CT 06413",
    "addr:housenumber":"33",
    "addr:postcode":"06413",
    "addr:street":"W Main St",
    "iso:country":"US",
    "sg:address":"33 W Main St",
    "sg:city":"Clinton",
    "sg:classifiers":[
        {
            "category":"Autos & Motor Vehicles",
            "subcategory":"Fuel & Gas Station",
            "type":"Retail Goods"
        }
    ],
    "sg:phone":"+1 860 669 7317",
    "sg:postcode":"06413",
    "sg:province":"CT",
    "sg:tags":[
        "station",
        "gasoline"
    ],
    "wof:name":"Clinton Automotive LLC",
    "wof:placetype":"venue"
},
  "geometry": {"coordinates":[-72.53161,41.279462],"type":"Point"}
}