{
  "type": "Feature",
  "properties": {
    "iso:country":"US",
    "sg:address":"77 Skyline Dr",
    "sg:city":"Salem",
    "sg:classifiers":[
        {
            "category":"Retail",
            "subcategory":"Auto Repair",
            "type":"Services"
        }
    ],
    "sg:phone":"+1   ",
    "sg:postcode":"06420",
    "sg:province":"CT",
    "sg:tags":[
        "body"
    ],
    "wof:name":"Body Works II Unlimited LLC",
    "wof:placetype":"venue"
},
  "geometry": {"coordinates":[-72.238089,41.448527],"type":"Point"}
}