{
  "type": "Feature",
  "properties": {
    "addr:full":"800 Marshall Phelps Rd Windsor CT 06095",
    "addr:housenumber":"800",
    "addr:postcode":"06095",
    "addr:street":"Marshall Phelps Rd",
    "iso:country":"US",
    "sg:address":"800 Marshall Phelps Rd",
    "sg:city":"Windsor",
    "sg:classifiers":[
        {
            "category":"Home & Garden",
            "subcategory":"Building Materials",
            "type":"Retail Goods"
        },
        {
            "category":"Professional",
            "subcategory":"Business Services",
            "type":"Services"
        }
    ],
    "sg:phone":"+1 860 298 0368",
    "sg:postcode":"06095",
    "sg:province":"CT",
    "sg:tags":[
        "marble-natural-wholesale",
        "marble-natural",
        "manufacturer"
    ],
    "sg:website":"http://www.igmcorp.com",
    "wof:name":"I G M",
    "wof:placetype":"venue"
},
  "geometry": {"coordinates":[-72.687494,41.869222],"type":"Point"}
}