{
  "type": "Feature",
  "properties": {
    "addr:full":"180 Connecticut Ave Norwalk CT 06854",
    "addr:housenumber":"180",
    "addr:postcode":"06854",
    "addr:street":"Connecticut Ave",
    "iso:country":"US",
    "sg:address":"180 Connecticut Ave",
    "sg:city":"Norwalk",
    "sg:classifiers":[
        {
            "category":"Retail",
            "subcategory":"Auto Repair",
            "type":"Services"
        }
    ],
    "sg:phone":"+1 203 855 1175",
    "sg:postcode":"06854",
    "sg:province":"CT",
    "sg:tags":[
        "transmission"
    ],
    "wof:name":"A-1 Transmissions",
    "wof:placetype":"venue"
},
  "geometry": {"coordinates":[-73.435062,41.102873],"type":"Point"}
}