{
  "type": "Feature",
  "properties": {
    "iso:country":"US",
    "sg:address":"6 Candlewood Knolls Rd",
    "sg:city":"New Fairfield",
    "sg:classifiers":[
        {
            "category":"Recreation",
            "subcategory":"Marina",
            "type":"Entertainment"
        }
    ],
    "sg:phone":"+1 203 746 1146",
    "sg:postcode":"06812",
    "sg:province":"CT",
    "wof:name":"Marina",
    "wof:placetype":"venue"
},
  "geometry": {"coordinates":[-73.46416499999999,41.481016],"type":"Point"}
}