{
  "type": "Feature",
  "properties": {
    "iso:country":"US",
    "sg:address":"10 Griswold Hills Dr",
    "sg:city":"Newington",
    "sg:classifiers":[
        {
            "category":"Real Estate",
            "subcategory":"Real Estate Operator",
            "type":"Services"
        }
    ],
    "sg:phone":"+1 860 666 4567",
    "sg:postcode":"06111",
    "sg:province":"CT",
    "sg:tags":[
        "building",
        "apartment"
    ],
    "wof:name":"Griswold Hills Newington LP",
    "wof:placetype":"venue"
},
  "geometry": {"coordinates":[-72.70895400000001,41.673454],"type":"Point"}
}