{
  "type": "Feature",
  "properties": {
    "iso:country":"US",
    "sg:address":"110 Brainard Rd",
    "sg:city":"Hartford",
    "sg:classifiers":[
        {
            "category":"Bakery",
            "type":"Food & Drink"
        },
        {
            "category":"Coffee & Tea",
            "type":"Food & Drink"
        },
        {
            "category":"Bagels",
            "type":"Food & Drink"
        },
        {
            "category":"Donuts",
            "type":"Food & Drink"
        }
    ],
    "sg:menulink":"http://www.allmenus.com/ct/hartford/129884-dunkin-donuts/menu/",
    "sg:phone":"+1 860 293 2114",
    "sg:postcode":"06114",
    "sg:province":"CT",
    "sg:tags":[
        "american",
        "diner",
        "pastry"
    ],
    "wof:name":"Dunkin' Donuts",
    "wof:placetype":"venue"
},
  "geometry": {"coordinates":[-72.65961,41.737295],"type":"Point"}
}