{
  "type": "Feature",
  "properties": {
    "iso:country":"US",
    "sg:address":"215 Roxbury Rd",
    "sg:city":"New Britain",
    "sg:classifiers":[
        {
            "category":"Real Estate",
            "subcategory":"Real Estate Operator",
            "type":"Services"
        }
    ],
    "sg:phone":"+1 860 827 9999",
    "sg:postcode":"06053",
    "sg:province":"CT",
    "sg:tags":[
        "building",
        "nonresidential"
    ],
    "wof:name":"Roomie Properties LLC",
    "wof:placetype":"venue"
},
  "geometry": {"coordinates":[-72.77585999999999,41.685162],"type":"Point"}
}