{
  "type": "Feature",
  "properties": {
    "addr:full":"1066 Hope St Stamford CT 06907",
    "addr:housenumber":"1066",
    "addr:postcode":"06907",
    "addr:street":"Hope St",
    "iso:country":"US",
    "sg:address":"1066 Hope St",
    "sg:city":"Stamford",
    "sg:classifiers":[
        {
            "category":"Home & Garden",
            "subcategory":"Building Materials",
            "type":"Retail Goods"
        }
    ],
    "sg:phone":"+1 203 968 0500",
    "sg:postcode":"06907",
    "sg:province":"CT",
    "sg:tags":[
        "shower",
        "door",
        "enclosure"
    ],
    "wof:name":"Coastal Shower Doors",
    "wof:placetype":"venue"
},
  "geometry": {"coordinates":[-73.518693,41.094698],"type":"Point"}
}