{
  "type": "Feature",
  "properties": {
    "addr:full":"31 Staple St Danbury CT 06810",
    "addr:housenumber":"31",
    "addr:postcode":"06810",
    "addr:street":"Staple St",
    "iso:country":"US",
    "sg:address":"31 Staple St",
    "sg:city":"Danbury",
    "sg:classifiers":[
        {
            "category":"Health Services",
            "subcategory":"Nursing And Care Facility",
            "type":"Services"
        }
    ],
    "sg:phone":"+1   ",
    "sg:postcode":"06810",
    "sg:province":"CT",
    "sg:tags":[
        "home",
        "convalescent"
    ],
    "wof:name":"Hancock Hall",
    "wof:placetype":"venue"
},
  "geometry": {"coordinates":[-73.472109,41.39507],"type":"Point"}
}