{
  "type": "Feature",
  "properties": {
    "addr:full":"99 High Wood Rd Hartford CT 06117",
    "addr:housenumber":"99",
    "addr:postcode":"06117",
    "addr:street":"High Wood Rd",
    "iso:country":"US",
    "sg:address":"99 High Wood Rd",
    "sg:city":"Hartford",
    "sg:classifiers":[
        {
            "category":"Health Services",
            "subcategory":"Clinic",
            "type":"Services"
        }
    ],
    "sg:phone":"+1   ",
    "sg:postcode":"06117",
    "sg:province":"CT",
    "wof:name":"Leisure Medical Media Inc",
    "wof:placetype":"venue"
},
  "geometry": {"coordinates":[-72.77179700000001,41.800417],"type":"Point"}
}