{
  "type": "Feature",
  "properties": {
    "iso:country":"US",
    "sg:address":"39 Glenbrook Rd",
    "sg:city":"Stamford",
    "sg:classifiers":[
        {
            "category":"Real Estate",
            "subcategory":"Real Estate Operator",
            "type":"Services"
        }
    ],
    "sg:phone":"+1 203 359 2867",
    "sg:postcode":"06902",
    "sg:province":"CT",
    "sg:tags":[
        "condominium"
    ],
    "wof:name":"Redstone Manor Condominiums",
    "wof:placetype":"venue"
},
  "geometry": {"coordinates":[-73.52864099999999,41.058015],"type":"Point"}
}