{
  "type": "Feature",
  "properties": {
    "iso:country":"US",
    "sg:address":"7 Liberty Pl",
    "sg:city":"Clinton",
    "sg:classifiers":[
        {
            "category":"Building & Trades",
            "subcategory":"Electrical",
            "type":"Services"
        }
    ],
    "sg:phone":"+1 860 669 0112",
    "sg:postcode":"06413",
    "sg:province":"CT",
    "sg:tags":[
        "electrical",
        "contractor"
    ],
    "wof:name":"Bruce Johnston",
    "wof:placetype":"venue"
},
  "geometry": {"coordinates":[-72.52167799999999,41.289542],"type":"Point"}
}