{
  "type": "Feature",
  "properties": {
    "iso:country":"US",
    "sg:address":"838 Farmington Ave",
    "sg:city":"Farmington",
    "sg:classifiers":[
        {
            "category":"Shopping",
            "subcategory":"Hobbies, Toys, & Games",
            "type":"Retail Goods"
        }
    ],
    "sg:phone":"+1 860 677 6641",
    "sg:postcode":"06032",
    "sg:province":"CT",
    "wof:name":"Creative Toymaker",
    "wof:placetype":"venue"
},
  "geometry": {"coordinates":[-72.82811100000001,41.728594],"type":"Point"}
}