{
  "type": "Feature",
  "properties": {
    "iso:country":"US",
    "sg:address":"530 Edgewood Rd",
    "sg:city":"Berlin",
    "sg:classifiers":[
        {
            "category":"Organizations",
            "subcategory":"Community Association",
            "type":"Services"
        }
    ],
    "sg:phone":"+1   ",
    "sg:postcode":"06037",
    "sg:province":"CT",
    "wof:name":"Interstate Police Assn",
    "wof:placetype":"venue"
},
  "geometry": {"coordinates":[-72.81759,41.586766],"type":"Point"}
}