{
  "type": "Feature",
  "properties": {
    "iso:country":"US",
    "sg:address":"146 Hopmeadow St",
    "sg:city":"Weatogue",
    "sg:classifiers":[
        {
            "category":"Professional",
            "subcategory":"Lawyer & Legal Services",
            "type":"Services"
        }
    ],
    "sg:phone":"+1 860 651 3200",
    "sg:postcode":"06089",
    "sg:province":"CT",
    "sg:tags":[
        "personal",
        "injury"
    ],
    "wof:name":"Ritson John D Atty",
    "wof:placetype":"venue"
},
  "geometry": {"coordinates":[-72.8181,41.833302],"type":"Point"}
}