{
  "type": "Feature",
  "properties": {
    "iso:country":"US",
    "sg:address":"488 N Main St",
    "sg:city":"Waterbury",
    "sg:classifiers":[
        {
            "category":"Food & Beverages",
            "subcategory":"Groceries & Convenience Stores",
            "type":"Retail Goods"
        }
    ],
    "sg:phone":"+1 203 596 1410",
    "sg:postcode":"06704",
    "sg:province":"CT",
    "wof:name":"Paola Market",
    "wof:placetype":"venue"
},
  "geometry": {"coordinates":[-73.034961,41.559867],"type":"Point"}
}