{
  "type": "Feature",
  "properties": {
    "iso:country":"US",
    "sg:address":"17 Meadowlark Rd",
    "sg:city":"Port Chester",
    "sg:classifiers":[
        {
            "category":"Professional",
            "type":"Services"
        }
    ],
    "sg:phone":"+1   ",
    "sg:postcode":"10573",
    "sg:province":"CT",
    "wof:name":"Rosemary S Haraguchi",
    "wof:placetype":"venue"
},
  "geometry": {"coordinates":[-73.679937,41.025711],"type":"Point"}
}