{
  "type": "Feature",
  "properties": {
    "addr:full":"60 Crouch Ave Norwich CT 06360",
    "addr:housenumber":"60",
    "addr:postcode":"06360",
    "addr:street":"Crouch Ave",
    "iso:country":"US",
    "sg:address":"60 Crouch Ave",
    "sg:city":"Norwich",
    "sg:classifiers":[
        {
            "category":"Health Services",
            "subcategory":"Nursing And Care Facility",
            "type":"Services"
        }
    ],
    "sg:phone":"+1   ",
    "sg:postcode":"06360",
    "sg:province":"CT",
    "sg:tags":[
        "skilled"
    ],
    "wof:name":"Saint Christopers Health Ctr",
    "wof:placetype":"venue"
},
  "geometry": {"coordinates":[-72.07196500000001,41.504349],"type":"Point"}
}