{
  "type": "Feature",
  "properties": {
    "addr:full":"734 Clinton Ave Bridgeport CT 06604",
    "addr:housenumber":"734",
    "addr:postcode":"06604",
    "addr:street":"Clinton Ave",
    "iso:country":"US",
    "sg:address":"734 Clinton Ave",
    "sg:city":"Bridgeport",
    "sg:classifiers":[
        {
            "category":"Health Services",
            "subcategory":"Chiropractor",
            "type":"Services"
        }
    ],
    "sg:phone":"+1   ",
    "sg:postcode":"06604",
    "sg:province":"CT",
    "wof:name":"Best Health Chiropractic",
    "wof:placetype":"venue"
},
  "geometry": {"coordinates":[-73.21262,41.177086],"type":"Point"}
}