{
  "type": "Feature",
  "properties": {
    "iso:country":"US",
    "sg:address":"80 Atlantic St",
    "sg:city":"Stamford",
    "sg:classifiers":[
        {
            "category":"Food & Beverages",
            "subcategory":"Bakery",
            "type":"Retail Goods"
        }
    ],
    "sg:phone":"+1 203 967 2537",
    "sg:postcode":"06901",
    "sg:province":"CT",
    "wof:name":"Cafe Julia Acquisition Corp",
    "wof:placetype":"venue"
},
  "geometry": {"coordinates":[-73.539053,41.053192],"type":"Point"}
}