{
  "type": "Feature",
  "properties": {
    "addr:full":"227 Bayberry Ln Westport CT 06880",
    "addr:housenumber":"227",
    "addr:postcode":"06880",
    "addr:street":"Bayberry Ln",
    "iso:country":"US",
    "sg:address":"227 Bayberry Ln",
    "sg:city":"Westport",
    "sg:classifiers":[
        {
            "category":"Wholesale",
            "subcategory":"Apparel",
            "type":"Manufacturing & Wholesale Goods"
        }
    ],
    "sg:phone":"+1 212 239 1366",
    "sg:postcode":"06880",
    "sg:province":"CT",
    "sg:tags":[
        "synthetic",
        "textile",
        "converter",
        "knitted",
        "woven",
        "fabric"
    ],
    "wof:name":"Komco Textiles Inc",
    "wof:placetype":"venue"
},
  "geometry": {"coordinates":[-73.33556900000001,41.177716],"type":"Point"}
}