{
  "type": "Feature",
  "properties": {
    "iso:country":"US",
    "sg:address":"319 Hazard Ave",
    "sg:city":"Enfield",
    "sg:classifiers":[
        {
            "category":"Personal",
            "subcategory":"Beauty Salon",
            "type":"Services"
        }
    ],
    "sg:phone":"+1   ",
    "sg:postcode":"06082",
    "sg:province":"CT",
    "sg:tags":[
        "shop",
        "barber"
    ],
    "wof:name":"First Impressions",
    "wof:placetype":"venue"
},
  "geometry": {"coordinates":[-72.538184,41.986335],"type":"Point"}
}