{
  "type": "Feature",
  "properties": {
    "addr:full":"16 High St Moosup CT 06354",
    "addr:housenumber":"16",
    "addr:postcode":"06354",
    "addr:street":"High St Moosup Ct",
    "iso:country":"US",
    "sg:address":"16 High St",
    "sg:city":"Moosup",
    "sg:classifiers":[
        {
            "category":"Wholesale",
            "subcategory":"Machinery & Supplies",
            "type":"Manufacturing & Wholesale Goods"
        }
    ],
    "sg:phone":"+1 860 230 0581",
    "sg:postcode":"06354",
    "sg:province":"CT",
    "sg:tags":[
        "equipment",
        "industrial"
    ],
    "wof:name":"Crellin Handling Equipment",
    "wof:placetype":"venue"
},
  "geometry": {"coordinates":[-71.87513199999999,41.719773],"type":"Point"}
}