{
  "type": "Feature",
  "properties": {
    "addr:full":"7 Park St Stafford Springs CT 06076",
    "addr:housenumber":"7",
    "addr:postcode":"06076",
    "addr:street":"Park St",
    "iso:country":"US",
    "sg:address":"7 Park St",
    "sg:city":"Stafford Springs",
    "sg:classifiers":[
        {
            "category":"Social Services",
            "subcategory":"Child Care",
            "type":"Services"
        }
    ],
    "sg:phone":"+1   ",
    "sg:postcode":"06076",
    "sg:province":"CT",
    "sg:tags":[
        "day"
    ],
    "wof:name":"Red Balloon Too",
    "wof:placetype":"venue"
},
  "geometry": {"coordinates":[-72.313132,41.951772],"type":"Point"}
}