{
  "type": "Feature",
  "properties": {
    "addr:full":"368 Winsted Rd Torrington CT 06790",
    "addr:housenumber":"368",
    "addr:postcode":"06790",
    "addr:street":"Winsted Rd",
    "iso:country":"US",
    "sg:address":"368 Winsted Rd",
    "sg:city":"Torrington",
    "sg:classifiers":[
        {
            "category":"Home & Garden",
            "subcategory":"Building Materials",
            "type":"Retail Goods"
        }
    ],
    "sg:phone":"+1 860 482 5086",
    "sg:postcode":"06790",
    "sg:province":"CT",
    "sg:tags":[
        "covering"
    ],
    "wof:name":"Sherwin-Williams",
    "wof:placetype":"venue"
},
  "geometry": {"coordinates":[-73.115354,41.824212],"type":"Point"}
}