{
  "type": "Feature",
  "properties": {
    "addr:full":"670 Boston Post Rd Madison CT 06443",
    "addr:housenumber":"670",
    "addr:postcode":"06443",
    "addr:street":"Boston Post Rd",
    "iso:country":"US",
    "sg:address":"670 Boston Post Rd",
    "sg:city":"Madison",
    "sg:classifiers":[
        {
            "category":"Restaurant",
            "type":"Food & Drink"
        }
    ],
    "sg:menulink":"http://www.allmenus.com/ct/madison/47547-allegre-gourmet-express/menu/",
    "sg:phone":"+1 203 245 0744",
    "sg:postcode":"06443",
    "sg:province":"CT",
    "sg:tags":[
        "soup",
        "seafood",
        "american",
        "salad"
    ],
    "wof:name":"Allegre Gourmet Express",
    "wof:placetype":"venue"
},
  "geometry": {"coordinates":[-72.596913,41.279394],"type":"Point"}
}