{
  "type": "Feature",
  "properties": {
    "addr:full":"65 Halliwell Dr Stamford CT 06902",
    "addr:housenumber":"65",
    "addr:postcode":"06902",
    "addr:street":"Halliwell Dr",
    "iso:country":"US",
    "sg:address":"65 Halliwell Dr",
    "sg:city":"Stamford",
    "sg:classifiers":[
        {
            "category":"Professional",
            "type":"Services"
        }
    ],
    "sg:phone":"+1 203 324 1189",
    "sg:postcode":"06902",
    "sg:province":"CT",
    "wof:name":"Through Eternity",
    "wof:placetype":"venue"
},
  "geometry": {"coordinates":[-73.55938399999999,41.06344],"type":"Point"}
}