{
  "type": "Feature",
  "properties": {
    "iso:country":"US",
    "sg:address":"1344 Silas Deane Hwy",
    "sg:city":"Rocky Hill",
    "sg:classifiers":[
        {
            "category":"Banks & Credit Unions",
            "subcategory":"Bank",
            "type":"Services"
        }
    ],
    "sg:phone":"+1 860 529 6444",
    "sg:postcode":"06067",
    "sg:province":"CT",
    "sg:tags":[
        "mortgage"
    ],
    "wof:name":"Bates Financial Corp",
    "wof:placetype":"venue"
},
  "geometry": {"coordinates":[-72.654223,41.682969],"type":"Point"}
}