{
  "type": "Feature",
  "properties": {
    "addr:full":"768 Quinebaug Rd Quinebaug CT 06262",
    "addr:housenumber":"768",
    "addr:postcode":"06262",
    "addr:street":"Quinebaug Rd Quinebaug Ct",
    "iso:country":"US",
    "sg:address":"768 Quinebaug Rd",
    "sg:city":"Quinebaug",
    "sg:classifiers":[
        {
            "category":"Place Of Worship",
            "subcategory":"Church",
            "type":"Public Place"
        },
        {
            "category":"Place Of Worship",
            "type":"Public Place"
        }
    ],
    "sg:phone":"+1 860 935 5412",
    "sg:postcode":"06262",
    "sg:province":"CT",
    "sg:tags":[
        "churches-seventh-day",
        "adventist",
        "christian",
        "churches-advent"
    ],
    "sg:website":"http://www.adventist.org",
    "wof:name":"Seventh Day Adventist Church",
    "wof:placetype":"venue"
},
  "geometry": {"coordinates":[-71.951716,42.024737],"type":"Point"}
}