{
  "type": "Feature",
  "properties": {
    "addr:full":"15 Whitfield St Guilford CT 06437",
    "addr:housenumber":"15",
    "addr:postcode":"06437",
    "addr:street":"Whitfield St",
    "iso:country":"US",
    "sg:address":"15 Whitfield St",
    "sg:city":"Guilford",
    "sg:classifiers":[
        {
            "category":"Professional",
            "subcategory":"Art Services",
            "type":"Services"
        }
    ],
    "sg:phone":"+1   ",
    "sg:postcode":"06437",
    "sg:province":"CT",
    "sg:tags":[
        "commercial",
        "design"
    ],
    "wof:name":"Erica Udoff & Co",
    "wof:placetype":"venue"
},
  "geometry": {"coordinates":[-72.68194699999999,41.281612],"type":"Point"}
}