{
  "type": "Feature",
  "properties": {
    "addr:full":"78 Grumman Ave Norwalk CT 06851",
    "addr:housenumber":"78",
    "addr:postcode":"06851",
    "addr:street":"Grumman Ave",
    "iso:country":"US",
    "sg:address":"78 Grumman Ave",
    "sg:city":"Norwalk",
    "sg:classifiers":[
        {
            "category":"Professional",
            "subcategory":"Management & Consulting",
            "type":"Services"
        }
    ],
    "sg:phone":"+1   ",
    "sg:postcode":"06851",
    "sg:province":"CT",
    "sg:tags":[
        "clinical",
        "datum"
    ],
    "wof:name":"Clinfo Systems LLC",
    "wof:placetype":"venue"
},
  "geometry": {"coordinates":[-73.399497,41.147093],"type":"Point"}
}