{
  "type": "Feature",
  "properties": {
    "iso:country":"US",
    "sg:address":"132 Federal Rd",
    "sg:city":"Danbury",
    "sg:classifiers":[
        {
            "category":"Restaurant",
            "type":"Food & Drink"
        }
    ],
    "sg:menulink":"http://www.allmenus.com/ct/danbury/144057-subway/menu/",
    "sg:phone":"+1 203 748 8231",
    "sg:postcode":"06811",
    "sg:province":"CT",
    "sg:tags":[
        "american",
        "sandwich"
    ],
    "wof:name":"Subway",
    "wof:placetype":"venue"
},
  "geometry": {"coordinates":[-73.417962,41.427416],"type":"Point"}
}