{
  "type": "Feature",
  "properties": {
    "addr:full":"16 Cannon Rd East Hartford CT 06108",
    "addr:housenumber":"16",
    "addr:postcode":"06108",
    "addr:street":"Cannon Rd East;Ct",
    "iso:country":"US",
    "sg:address":"16 Cannon Rd",
    "sg:city":"East Hartford",
    "sg:classifiers":[
        {
            "category":"Professional",
            "subcategory":"Engineering",
            "type":"Services"
        }
    ],
    "sg:phone":"+1   ",
    "sg:postcode":"06108",
    "sg:province":"CT",
    "sg:tags":[
        "consulting"
    ],
    "wof:name":"Roser Engineering & Consulting",
    "wof:placetype":"venue"
},
  "geometry": {"coordinates":[-72.59201299999999,41.780396],"type":"Point"}
}