{
  "type": "Feature",
  "properties": {
    "iso:country":"US",
    "sg:address":"320 Boston Post Rd",
    "sg:city":"Orange",
    "sg:classifiers":[
        {
            "category":"Shopping",
            "subcategory":"Used Merchandise",
            "type":"Retail Goods"
        }
    ],
    "sg:phone":"+1 203 799 8075",
    "sg:postcode":"06477",
    "sg:province":"CT",
    "sg:tags":[
        "shop",
        "consignment"
    ],
    "wof:name":"Consignment Originals",
    "wof:placetype":"venue"
},
  "geometry": {"coordinates":[-73.000148,41.267697],"type":"Point"}
}