{
  "type": "Feature",
  "properties": {
    "iso:country":"US",
    "sg:address":"137 Scoville Hill Rd",
    "sg:city":"Harwinton",
    "sg:classifiers":[
        {
            "category":"Farming",
            "subcategory":"Farm",
            "type":"Manufacturing & Wholesale Goods"
        }
    ],
    "sg:phone":"+1 860 485 9207",
    "sg:postcode":"06791",
    "sg:province":"CT",
    "sg:tags":[
        "crop",
        "general"
    ],
    "wof:name":"John Robert Seelye",
    "wof:placetype":"venue"
},
  "geometry": {"coordinates":[-73.102632,41.773486],"type":"Point"}
}