{
  "type": "Feature",
  "properties": {
    "addr:full":"4 Florian Ct Westport CT 06880",
    "addr:housenumber":"4",
    "addr:postcode":"06880",
    "addr:street":"Florian Ct",
    "iso:country":"US",
    "sg:address":"4 Florian Ct",
    "sg:city":"Westport",
    "sg:classifiers":[
        {
            "category":"Health Services",
            "subcategory":"Health Practitioner",
            "type":"Services"
        }
    ],
    "sg:phone":"+1   ",
    "sg:postcode":"06880",
    "sg:province":"CT",
    "wof:name":"Barbara Frumkin PHD",
    "wof:placetype":"venue"
},
  "geometry": {"coordinates":[-73.335252,41.180077],"type":"Point"}
}