{
  "type": "Feature",
  "properties": {
    "iso:country":"US",
    "sg:address":"996 Farmington Ave",
    "sg:city":"Berlin",
    "sg:classifiers":[
        {
            "category":"Real Estate",
            "subcategory":"Real Estate Agent",
            "type":"Services"
        }
    ],
    "sg:phone":"+1 860 828 8557",
    "sg:postcode":"06037",
    "sg:province":"CT",
    "wof:name":"Re/Max",
    "wof:placetype":"venue"
},
  "geometry": {"coordinates":[-72.76581,41.634213],"type":"Point"}
}