{
  "type": "Feature",
  "properties": {
    "addr:full":"495 Union St Waterbury CT 06706",
    "addr:housenumber":"495",
    "addr:postcode":"06706",
    "addr:street":"Union St Waterbury Ct",
    "iso:country":"US",
    "sg:address":"495 Union St",
    "sg:city":"Waterbury",
    "sg:classifiers":[
        {
            "category":"Fast Food",
            "type":"Food & Drink"
        },
        {
            "category":"Restaurant",
            "type":"Food & Drink"
        }
    ],
    "sg:phone":"+1 203 597 0775",
    "sg:postcode":"06706",
    "sg:province":"CT",
    "sg:tags":[
        "style",
        "family",
        "american",
        "take",
        "pasta",
        "italian"
    ],
    "sg:website":"http://www.olivegarden.com",
    "wof:name":"Olive Garden",
    "wof:placetype":"venue"
},
  "geometry": {"coordinates":[-73.02685099999999,41.547819],"type":"Point"}
}