{
  "type": "Feature",
  "properties": {
    "addr:full":"551 N Stone St West Suffield CT 06093",
    "addr:housenumber":"551",
    "addr:postcode":"06093",
    "addr:street":"N Stone St West Suffield Ct",
    "iso:country":"US",
    "sg:address":"551 N Stone St",
    "sg:city":"West Suffield",
    "sg:classifiers":[
        {
            "category":"Banks & Credit Unions",
            "subcategory":"Financial Services",
            "type":"Services"
        }
    ],
    "sg:phone":"+1 860 635 2722",
    "sg:postcode":"06093",
    "sg:province":"CT",
    "sg:tags":[
        "company",
        "holding"
    ],
    "wof:name":"551 North Stone Street LLC",
    "wof:placetype":"venue"
},
  "geometry": {"coordinates":[-72.713959,42.002814],"type":"Point"}
}