{
  "type": "Feature",
  "properties": {
    "iso:country":"US",
    "sg:address":"5 Old County Way",
    "sg:city":"Portland",
    "sg:classifiers":[
        {
            "category":"Building & Trades",
            "subcategory":"Electrical",
            "type":"Services"
        }
    ],
    "sg:phone":"+1 860 342 5140",
    "sg:postcode":"06480",
    "sg:province":"CT",
    "sg:tags":[
        "electrical",
        "contractor"
    ],
    "wof:name":"Billy Z Electric",
    "wof:placetype":"venue"
},
  "geometry": {"coordinates":[-72.60504299999999,41.635215],"type":"Point"}
}