{
  "type": "Feature",
  "properties": {
    "iso:country":"US",
    "sg:address":"45 Old Colony Rd",
    "sg:city":"Monroe",
    "sg:classifiers":[
        {
            "category":"Professional",
            "type":"Services"
        }
    ],
    "sg:phone":"+1 203 268 4544",
    "sg:postcode":"06468",
    "sg:province":"CT",
    "wof:name":"Bsf Global Outsourcing Svc",
    "wof:placetype":"venue"
},
  "geometry": {"coordinates":[-73.249848,41.31798],"type":"Point"}
}