{
  "type": "Feature",
  "properties": {
    "iso:country":"US",
    "sg:address":"12 Good Hill Estates Rd",
    "sg:city":"Kent",
    "sg:classifiers":[
        {
            "category":"Utilities",
            "subcategory":"Refuse",
            "type":"Services"
        }
    ],
    "sg:phone":"+1 860 927 1935",
    "sg:postcode":"06757",
    "sg:province":"CT",
    "sg:tags":[
        "collection",
        "garbage"
    ],
    "wof:name":"Five Star Carting",
    "wof:placetype":"venue"
},
  "geometry": {"coordinates":[-73.44165599999999,41.746855],"type":"Point"}
}