{
  "type": "Feature",
  "properties": {
    "addr:full":"50 Church St Windsor Locks CT 06096",
    "addr:housenumber":"50",
    "addr:postcode":"06096",
    "addr:street":"Church St;Locks Ct",
    "iso:country":"US",
    "sg:address":"50 Church St",
    "sg:city":"Windsor Locks",
    "sg:classifiers":[
        {
            "category":"Government",
            "subcategory":"Office",
            "type":"Public Place"
        }
    ],
    "sg:phone":"+1 860 627 1447",
    "sg:postcode":"06096",
    "sg:province":"CT",
    "sg:tags":[
        "general"
    ],
    "wof:name":"Building Department",
    "wof:placetype":"venue"
},
  "geometry": {"coordinates":[-72.63237700000001,41.929626],"type":"Point"}
}