{
  "type": "Feature",
  "properties": {
    "addr:full":"158 Falls Ave Oakville CT 06779",
    "addr:housenumber":"158",
    "addr:postcode":"06779",
    "addr:street":"Falls Ave",
    "iso:country":"US",
    "sg:address":"158 Falls Ave",
    "sg:city":"Oakville",
    "sg:classifiers":[
        {
            "category":"Retail",
            "subcategory":"Auto Repair",
            "type":"Services"
        }
    ],
    "sg:phone":"+1   ",
    "sg:postcode":"06779",
    "sg:province":"CT",
    "sg:tags":[
        "automotive"
    ],
    "wof:name":"J B Motor Repair",
    "wof:placetype":"venue"
},
  "geometry": {"coordinates":[-73.077957,41.59106],"type":"Point"}
}