{
  "type": "Feature",
  "properties": {
    "addr:full":"165 Bedford St Stamford CT 06901",
    "addr:housenumber":"165",
    "addr:postcode":"06901",
    "addr:street":"Bedford St",
    "iso:country":"US",
    "sg:address":"165 Bedford St",
    "sg:city":"Stamford",
    "sg:classifiers":[
        {
            "category":"Professional",
            "subcategory":"Art Services",
            "type":"Services"
        }
    ],
    "sg:phone":"+1   ",
    "sg:postcode":"06901",
    "sg:province":"CT",
    "sg:tags":[
        "commercial",
        "design"
    ],
    "wof:name":"Seaside Design LLC",
    "wof:placetype":"venue"
},
  "geometry": {"coordinates":[-73.537947,41.054947],"type":"Point"}
}