{
  "type": "Feature",
  "properties": {
    "addr:full":"351 New Whitfield St Guilford CT 06437",
    "addr:housenumber":"351",
    "addr:postcode":"06437",
    "addr:street":"New Whitfield St",
    "iso:country":"US",
    "sg:address":"351 New Whitfield St",
    "sg:city":"Guilford",
    "sg:classifiers":[
        {
            "category":"Manufacturing",
            "subcategory":"Watercraft",
            "type":"Manufacturing & Wholesale Goods"
        }
    ],
    "sg:phone":"+1 203 458 4903",
    "sg:postcode":"06437",
    "sg:province":"CT",
    "sg:tags":[
        "boat"
    ],
    "sg:website":"www.navtec.net",
    "wof:name":"Navtec",
    "wof:placetype":"venue"
},
  "geometry": {"coordinates":[-72.674092,41.274471],"type":"Point"}
}