{
  "type": "Feature",
  "properties": {
    "addr:full":"1439 Madison Ave Bridgeport CT 06606",
    "addr:housenumber":"1439",
    "addr:postcode":"06606",
    "addr:street":"Madison Ave",
    "iso:country":"US",
    "sg:address":"1439 Madison Ave",
    "sg:city":"Bridgeport",
    "sg:classifiers":[
        {
            "category":"Restaurant",
            "type":"Food & Drink"
        }
    ],
    "sg:phone":"+1 203 576 1281",
    "sg:postcode":"06606",
    "sg:province":"CT",
    "wof:name":"Tartaglia's Restaurant",
    "wof:placetype":"venue"
},
  "geometry": {"coordinates":[-73.210792,41.198743],"type":"Point"}
}