{
  "type": "Feature",
  "properties": {
    "addr:full":"165 Cardinal Dr Fairfield CT 06450",
    "addr:housenumber":"165",
    "addr:postcode":"06450",
    "addr:street":"Cardinal Dr",
    "iso:country":"US",
    "sg:address":"165 Cardinal Dr",
    "sg:city":"Fairfield",
    "sg:classifiers":[
        {
            "category":"Shopping",
            "type":"Retail Goods"
        },
        {
            "category":"Retail",
            "subcategory":"Animal Services",
            "type":"Services"
        }
    ],
    "sg:phone":"+1 203 336 9008",
    "sg:postcode":"06450",
    "sg:province":"CT",
    "sg:tags":[
        "pet",
        "boarding",
        "merchandise",
        "sitting"
    ],
    "wof:name":"Animal Companion Pet Care LLC",
    "wof:placetype":"venue"
},
  "geometry": {"coordinates":[-72.783247,41.504652],"type":"Point"}
}