{
  "type": "Feature",
  "properties": {
    "addr:full":"130 Meadow Brook Dr Waterbury CT 06706",
    "addr:housenumber":"130",
    "addr:postcode":"06706",
    "addr:street":"Meadow Brook Dr",
    "iso:country":"US",
    "sg:address":"130 Meadow Brook Dr",
    "sg:city":"Waterbury",
    "sg:classifiers":[
        {
            "category":"Retail",
            "subcategory":"Laundry & Dry Cleaning",
            "type":"Services"
        }
    ],
    "sg:phone":"+1   ",
    "sg:postcode":"06706",
    "sg:province":"CT",
    "sg:tags":[
        "upholstery",
        "carpet"
    ],
    "wof:name":"A1 Carpet Care",
    "wof:placetype":"venue"
},
  "geometry": {"coordinates":[-73.027693,41.523038],"type":"Point"}
}