{
  "type": "Feature",
  "properties": {
    "iso:country":"US",
    "sg:address":"130 New Haven Rd",
    "sg:city":"Seymour",
    "sg:classifiers":[
        {
            "category":"Freight",
            "type":"Transportation"
        }
    ],
    "sg:phone":"+1 203 881 3245",
    "sg:postcode":"06483",
    "sg:province":"CT",
    "sg:tags":[
        "operator",
        "mover",
        "trucking"
    ],
    "wof:name":"Action Moving & Storage",
    "wof:placetype":"venue"
},
  "geometry": {"coordinates":[-73.048125,41.396316],"type":"Point"}
}