{
  "type": "Feature",
  "properties": {
    "addr:full":"58 Middletown Ave New Haven CT 06513",
    "addr:housenumber":"58",
    "addr:postcode":"06513",
    "addr:street":"Middletown Ave",
    "iso:country":"US",
    "sg:address":"58 Middletown Ave",
    "sg:city":"New Haven",
    "sg:classifiers":[
        {
            "category":"Local Transit",
            "type":"Transportation"
        }
    ],
    "sg:phone":"+1 203 562 4104",
    "sg:postcode":"06513",
    "sg:province":"CT",
    "sg:tags":[
        "handicapped"
    ],
    "wof:name":"American Medical Response",
    "wof:placetype":"venue"
},
  "geometry": {"coordinates":[-72.895999,41.319364],"type":"Point"}
}