{
  "type": "Feature",
  "properties": {
    "iso:country":"US",
    "sg:address":"1274 Thomaston Ave",
    "sg:city":"Waterbury",
    "sg:classifiers":[
        {
            "category":"Shopping",
            "subcategory":"Used Merchandise",
            "type":"Retail Goods"
        }
    ],
    "sg:phone":"+1 203 573 8650",
    "sg:postcode":"06704",
    "sg:province":"CT",
    "sg:tags":[
        "pawnbroker"
    ],
    "wof:name":"Brass City Pawn",
    "wof:placetype":"venue"
},
  "geometry": {"coordinates":[-73.054479,41.567594],"type":"Point"}
}