{
  "type": "Feature",
  "properties": {
    "addr:full":"51 Taff Ave Stamford CT 06902",
    "addr:housenumber":"51",
    "addr:postcode":"06902",
    "addr:street":"Taff Ave",
    "iso:country":"US",
    "sg:address":"51 Taff Ave",
    "sg:city":"Stamford",
    "sg:classifiers":[
        {
            "category":"Retail",
            "subcategory":"Auto Repair",
            "type":"Services"
        }
    ],
    "sg:phone":"+1 203 353 0087",
    "sg:postcode":"06902",
    "sg:province":"CT",
    "sg:tags":[
        "truck",
        "general"
    ],
    "wof:name":"Southpark Garage LLC",
    "wof:placetype":"venue"
},
  "geometry": {"coordinates":[-73.549932,41.038594],"type":"Point"}
}