{
  "type": "Feature",
  "properties": {
    "iso:country":"US",
    "sg:address":"49 Johnson Ln",
    "sg:city":"Madison",
    "sg:classifiers":[
        {
            "category":"Professional",
            "subcategory":"Business Services",
            "type":"Services"
        }
    ],
    "sg:phone":"+1 203 245 4868",
    "sg:postcode":"06443",
    "sg:province":"CT",
    "sg:tags":[
        "drafting"
    ],
    "wof:name":"Quality Draft Svc",
    "wof:placetype":"venue"
},
  "geometry": {"coordinates":[-72.626024,41.284671],"type":"Point"}
}