{
  "type": "Feature",
  "properties": {
    "addr:full":"807 Middlesex Tpke Old Saybrook CT 06475",
    "addr:housenumber":"807",
    "addr:postcode":"06475",
    "addr:street":"Middlesex Tpke Old Saybrook Ct",
    "iso:country":"US",
    "sg:address":"807 Middlesex Tpke",
    "sg:city":"Old Saybrook",
    "sg:classifiers":[
        {
            "category":"Retail",
            "subcategory":"Veterinary Services",
            "type":"Services"
        }
    ],
    "sg:phone":"+1 860 388 9681",
    "sg:postcode":"06475",
    "sg:province":"CT",
    "sg:tags":[
        "veterinarian"
    ],
    "wof:name":"Thouin Andre DVM",
    "wof:placetype":"venue"
},
  "geometry": {"coordinates":[-72.378197,41.326599],"type":"Point"}
}