{
  "type": "Feature",
  "properties": {
    "addr:full":"26 Commerce Dr Danbury CT 06810",
    "addr:housenumber":"26",
    "addr:postcode":"06810",
    "addr:street":"Commerce Dr",
    "iso:country":"US",
    "sg:address":"26 Commerce Dr",
    "sg:city":"Danbury",
    "sg:phone":"+1 203 790 4774",
    "sg:postcode":"06810",
    "sg:province":"CT",
    "sg:tags":[
        "scale"
    ],
    "wof:name":"Adam Equipment",
    "wof:placetype":"venue"
},
  "geometry": {"coordinates":[-73.418254,41.409459],"type":"Point"}
}