{
  "type": "Feature",
  "properties": {
    "addr:full":"1396 Wilbur Cross Hwy Berlin CT 06037",
    "addr:housenumber":"1396",
    "addr:postcode":"06037",
    "addr:street":"Wilbur Cross Hwy",
    "iso:country":"US",
    "sg:address":"1396 Wilbur Cross Hwy",
    "sg:city":"Berlin",
    "sg:classifiers":[
        {
            "category":"Real Estate",
            "subcategory":"Real Estate Agent",
            "type":"Services"
        }
    ],
    "sg:phone":"+1 860 828 7699",
    "sg:postcode":"06037",
    "sg:province":"CT",
    "wof:name":"Complete Appraisal Insptn Svc",
    "wof:placetype":"venue"
},
  "geometry": {"coordinates":[-72.74482500000001,41.614119],"type":"Point"}
}