{
  "type": "Feature",
  "properties": {
    "iso:country":"US",
    "sg:address":"96 Old Post Rd",
    "sg:city":"Southport",
    "sg:classifiers":[
        {
            "category":"Real Estate",
            "subcategory":"Architect",
            "type":"Services"
        }
    ],
    "sg:phone":"+1 203 254 2388",
    "sg:postcode":"06475",
    "sg:province":"CT",
    "sg:website":"www.markfinlay.com",
    "wof:name":"Mark P Finlay Architects",
    "wof:placetype":"venue"
},
  "geometry": {"coordinates":[-72.398752,41.285215],"type":"Point"}
}