{
  "type": "Feature",
  "properties": {
    "addr:full":"86 Garden Grove Rd Manchester CT 06040",
    "addr:housenumber":"86",
    "addr:postcode":"06040",
    "addr:street":"Garden Grove Rd",
    "iso:country":"US",
    "sg:address":"86 Garden Grove Rd",
    "sg:city":"Manchester",
    "sg:classifiers":[
        {
            "category":"Professional",
            "subcategory":"Business Services",
            "type":"Services"
        }
    ],
    "sg:phone":"+1   ",
    "sg:postcode":"06040",
    "sg:province":"CT",
    "wof:name":"Core Assoc LLC",
    "wof:placetype":"venue"
},
  "geometry": {"coordinates":[-72.537914,41.751193],"type":"Point"}
}