{
  "type": "Feature",
  "properties": {
    "addr:full":"250 Skeet Club Rd Durham CT 06422",
    "addr:housenumber":"250",
    "addr:postcode":"06422",
    "addr:street":"Skeet Club Rd",
    "iso:country":"US",
    "sg:address":"250 Skeet Club Rd",
    "sg:city":"Durham",
    "sg:classifiers":[
        {
            "category":"Building & Trades",
            "subcategory":"Construction",
            "type":"Services"
        }
    ],
    "sg:phone":"+1 860 349 0319",
    "sg:postcode":"06422",
    "sg:province":"CT",
    "sg:tags":[
        "house"
    ],
    "wof:name":"Korzon Building Co",
    "wof:placetype":"venue"
},
  "geometry": {"coordinates":[-72.72284999999999,41.487467],"type":"Point"}
}