{
  "type": "Feature",
  "properties": {
    "addr:full":"819 Federal Rd Brookfield CT 06804",
    "addr:housenumber":"819",
    "addr:postcode":"06804",
    "addr:street":"Federal Rd",
    "iso:country":"US",
    "sg:address":"819 Federal Rd",
    "sg:city":"Brookfield",
    "sg:classifiers":[
        {
            "category":"Autos & Motor Vehicles",
            "subcategory":"Fuel & Gas Station",
            "type":"Retail Goods"
        }
    ],
    "sg:phone":"+1 203 775 0622",
    "sg:postcode":"06804",
    "sg:province":"CT",
    "sg:tags":[
        "oil"
    ],
    "wof:name":"Sameer's Brookfield Texaco",
    "wof:placetype":"venue"
},
  "geometry": {"coordinates":[-73.415424,41.491911],"type":"Point"}
}