{
  "type": "Feature",
  "properties": {
    "iso:country":"US",
    "sg:address":"285 Thimble Islands Rd",
    "sg:city":"Branford",
    "sg:classifiers":[
        {
            "category":"Real Estate",
            "subcategory":"Architect",
            "type":"Services"
        }
    ],
    "sg:phone":"+1   ",
    "sg:postcode":"06405",
    "sg:province":"CT",
    "sg:tags":[
        "architectural"
    ],
    "wof:name":"Peter A Hentschel",
    "wof:placetype":"venue"
},
  "geometry": {"coordinates":[-72.74938299999999,41.263141],"type":"Point"}
}