{
  "type": "Feature",
  "properties": {
    "iso:country":"US",
    "sg:address":"1966 Baldwin St",
    "sg:city":"Waterbury",
    "sg:classifiers":[
        {
            "category":"Recreation",
            "type":"Entertainment"
        },
        {
            "category":"Organizations",
            "subcategory":"Community Association",
            "type":"Services"
        }
    ],
    "sg:phone":"+1 203 574 9045",
    "sg:postcode":"06706",
    "sg:province":"CT",
    "sg:tags":[
        "club",
        "membership",
        "sporting"
    ],
    "wof:name":"Portuguese Sport Club Inc",
    "wof:placetype":"venue"
},
  "geometry": {"coordinates":[-73.040696,41.522546],"type":"Point"}
}