{
  "type": "Feature",
  "properties": {
    "addr:full":"3 Tanglewood Trl Darien CT 06820",
    "addr:housenumber":"3",
    "addr:postcode":"06820",
    "addr:street":"Tanglewood Trl",
    "iso:country":"US",
    "sg:address":"3 Tanglewood Trl",
    "sg:city":"Darien",
    "sg:classifiers":[
        {
            "category":"Professional",
            "type":"Services"
        }
    ],
    "sg:phone":"+1   ",
    "sg:postcode":"06820",
    "sg:province":"CT",
    "wof:name":"Afrex Intl Corp",
    "wof:placetype":"venue"
},
  "geometry": {"coordinates":[-73.480216,41.080469],"type":"Point"}
}