{
  "type": "Feature",
  "properties": {
    "addr:full":"95 Elm St Enfield CT 06082",
    "addr:housenumber":"95",
    "addr:postcode":"06082",
    "addr:street":"Elm St Enfield Ct",
    "iso:country":"US",
    "sg:address":"95 Elm St",
    "sg:city":"Enfield",
    "sg:classifiers":[
        {
            "category":"Shopping",
            "subcategory":"Department Store",
            "type":"Retail Goods"
        }
    ],
    "sg:phone":"+1 860 741 6100",
    "sg:postcode":"06082",
    "sg:province":"CT",
    "sg:website":"http://www.kohls.com",
    "wof:name":"Kohl's",
    "wof:placetype":"venue"
},
  "geometry": {"coordinates":[-72.58384700000001,41.997879],"type":"Point"}
}