{
  "type": "Feature",
  "properties": {
    "iso:country":"US",
    "sg:address":"722 E Main St",
    "sg:city":"Waterbury",
    "sg:classifiers":[
        {
            "category":"Professional",
            "type":"Services"
        }
    ],
    "sg:phone":"+1 203 597 1086",
    "sg:postcode":"06702",
    "sg:province":"CT",
    "wof:name":"Amber Valentine",
    "wof:placetype":"venue"
},
  "geometry": {"coordinates":[-73.028131,41.553619],"type":"Point"}
}