{
  "type": "Feature",
  "properties": {
    "iso:country":"US",
    "sg:address":"125 Club Rd",
    "sg:city":"Stamford",
    "sg:classifiers":[
        {
            "category":"Professional",
            "subcategory":"Management & Consulting",
            "type":"Services"
        }
    ],
    "sg:phone":"+1 203 329 0199",
    "sg:postcode":"06905",
    "sg:province":"CT",
    "sg:tags":[
        "consultant",
        "business"
    ],
    "wof:name":"John Vaccaro Productions",
    "wof:placetype":"venue"
},
  "geometry": {"coordinates":[-73.53473,41.100569],"type":"Point"}
}