{
  "type": "Feature",
  "properties": {
    "iso:country":"US",
    "sg:address":"27 Woodtick Rd",
    "sg:city":"Waterbury",
    "sg:classifiers":[
        {
            "category":"Insurance",
            "subcategory":"Insurance Agent",
            "type":"Services"
        }
    ],
    "sg:phone":"+1 203 753 4465",
    "sg:postcode":"06705",
    "sg:province":"CT",
    "wof:name":"American Auto Insurance",
    "wof:placetype":"venue"
},
  "geometry": {"coordinates":[-73.007516,41.551749],"type":"Point"}
}