{
  "type": "Feature",
  "properties": {
    "iso:country":"US",
    "sg:address":"12 Hempel Dr",
    "sg:city":"Wolcott",
    "sg:classifiers":[
        {
            "category":"Education",
            "subcategory":"School",
            "type":"Public Place"
        }
    ],
    "sg:phone":"+1 203 879 8154",
    "sg:postcode":"06716",
    "sg:province":"CT",
    "wof:name":"Wakelee School",
    "wof:placetype":"venue"
},
  "geometry": {"coordinates":[-73.01239700000001,41.609746],"type":"Point"}
}