{
  "type": "Feature",
  "properties": {
    "iso:country":"US",
    "sg:address":"928 Farmington Ave",
    "sg:city":"Hartford",
    "sg:classifiers":[
        {
            "category":"Health Services",
            "subcategory":"Doctor",
            "type":"Services"
        }
    ],
    "sg:phone":"+1   ",
    "sg:postcode":"06107",
    "sg:province":"CT",
    "wof:name":"Bruce M Abel DDS",
    "wof:placetype":"venue"
},
  "geometry": {"coordinates":[-72.73869500000001,41.762814],"type":"Point"}
}