{
  "type": "Feature",
  "properties": {
    "iso:country":"US",
    "sg:address":"162 Wahackme Rd",
    "sg:city":"New Canaan",
    "sg:classifiers":[
        {
            "category":"Manufacturing",
            "subcategory":"Printing",
            "type":"Manufacturing & Wholesale Goods"
        }
    ],
    "sg:phone":"+1 203 972 6305",
    "sg:postcode":"06840",
    "sg:province":"NY",
    "sg:tags":[
        "miscellaneous",
        "publishing"
    ],
    "wof:name":"Total-Content LLC",
    "wof:placetype":"venue"
},
  "geometry": {"coordinates":[-73.512401,41.149233],"type":"Point"}
}