{
  "type": "Feature",
  "properties": {
    "iso:country":"US",
    "sg:address":"1863 Long Ridge Rd",
    "sg:city":"Stamford",
    "sg:classifiers":[
        {
            "category":"Professional",
            "subcategory":"Management & Consulting",
            "type":"Services"
        }
    ],
    "sg:phone":"+1 203 461 8263",
    "sg:postcode":"06903",
    "sg:province":"CT",
    "sg:tags":[
        "consultant",
        "business"
    ],
    "sg:website":"www.businessu.com",
    "wof:name":"Executives On The Cutting Edge",
    "wof:placetype":"venue"
},
  "geometry": {"coordinates":[-73.584216,41.132023],"type":"Point"}
}