{
  "type": "Feature",
  "properties": {
    "addr:full":"37 Marne St Hamden CT 06514",
    "addr:housenumber":"37",
    "addr:postcode":"06514",
    "addr:street":"Marne St",
    "iso:country":"US",
    "sg:address":"37 Marne St",
    "sg:city":"Hamden",
    "sg:classifiers":[
        {
            "category":"Professional",
            "subcategory":"Detective & Security Services",
            "type":"Services"
        }
    ],
    "sg:phone":"+1 203 288 5470",
    "sg:postcode":"06514",
    "sg:province":"CT",
    "sg:tags":[
        "system"
    ],
    "wof:name":"ADT Security Svc",
    "wof:placetype":"venue"
},
  "geometry": {"coordinates":[-72.92699500000001,41.355285],"type":"Point"}
}