{
  "type": "Feature",
  "properties": {
    "iso:country":"US",
    "sg:address":"240 Greenwich Avenue",
    "sg:city":"Greenwich",
    "sg:classifiers":[
        {
            "category":"Professional",
            "subcategory":"Business Services",
            "type":"Services"
        }
    ],
    "sg:phone":"+1 203 861 0900",
    "sg:province":"CT",
    "sg:tags":[
        "media",
        "acquisition",
        "development",
        "operation",
        "radio",
        "digital-properties",
        "mid-sized-markets"
    ],
    "sg:website":"http://townsquaremedia.com/",
    "wof:name":"Townsquare Media",
    "wof:placetype":"venue"
},
  "geometry": {"coordinates":[-73.62585300000001,41.026099],"type":"Point"}
}