{
  "type": "Feature",
  "properties": {
    "iso:country":"US",
    "sg:address":"156 Spencer St",
    "sg:city":"Manchester",
    "sg:classifiers":[
        {
            "category":"Retail",
            "subcategory":"Veterinary Services",
            "type":"Services"
        }
    ],
    "sg:phone":"+1 860 646 5170",
    "sg:postcode":"06040",
    "sg:province":"CT",
    "sg:tags":[
        "veterinarian",
        "specialty"
    ],
    "wof:name":"Soutter Alexis DVM",
    "wof:placetype":"venue"
},
  "geometry": {"coordinates":[-72.567696,41.767193],"type":"Point"}
}