{
  "type": "Feature",
  "properties": {
    "iso:country":"US",
    "sg:address":"17 State Hwy 39",
    "sg:city":"New Fairfield",
    "sg:classifiers":[
        {
            "category":"Food & Beverages",
            "subcategory":"Liquor & Beverages",
            "type":"Retail Goods"
        }
    ],
    "sg:phone":"+1 203 746 5024",
    "sg:postcode":"06812",
    "sg:province":"CT",
    "wof:name":"Fairwood Wines & Liquors",
    "wof:placetype":"venue"
},
  "geometry": {"coordinates":[-73.523805,41.44554],"type":"Point"}
}