{
  "type": "Feature",
  "properties": {
    "iso:country":"US",
    "sg:address":"5 Town",
    "sg:city":"Hadlyme",
    "sg:classifiers":[
        {
            "category":"Shopping",
            "subcategory":"Antiques",
            "type":"Retail Goods"
        }
    ],
    "sg:phone":"+1 860 526 5073",
    "sg:postcode":"06439",
    "sg:province":"CT",
    "wof:name":"Rattleberry Farm",
    "wof:placetype":"venue"
},
  "geometry": {"coordinates":[-72.400902,41.423698],"type":"Point"}
}