{
  "type": "Feature",
  "properties": {
    "iso:country":"US",
    "sg:address":"134 Wells Rd",
    "sg:city":"Granby",
    "sg:classifiers":[
        {
            "category":"Education",
            "subcategory":"School",
            "type":"Public Place"
        }
    ],
    "sg:phone":"+1 860 844 3048",
    "sg:postcode":"06035",
    "sg:province":"CT",
    "wof:name":"Wells Road Intermediate School",
    "wof:placetype":"venue"
},
  "geometry": {"coordinates":[-72.808832,41.992373],"type":"Point"}
}