{
  "type": "Feature",
  "properties": {
    "iso:country":"US",
    "sg:address":"30 Gilbert Dr",
    "sg:city":"Trumbull",
    "sg:classifiers":[
        {
            "category":"Professional",
            "subcategory":"Business Services",
            "type":"Services"
        }
    ],
    "sg:phone":"+1   ",
    "sg:postcode":"06611",
    "sg:province":"CT",
    "sg:tags":[
        "production",
        "video"
    ],
    "wof:name":"Innovative Media Inc",
    "wof:placetype":"venue"
},
  "geometry": {"coordinates":[-73.23935400000001,41.245827],"type":"Point"}
}