{
  "type": "Feature",
  "properties": {
    "iso:country":"US",
    "sg:address":"377 Christian Hill Rd",
    "sg:city":"Brooklyn",
    "sg:classifiers":[
        {
            "category":"Building & Trades",
            "subcategory":"Cleaning & Sanitation",
            "type":"Services"
        }
    ],
    "sg:phone":"+1   ",
    "sg:postcode":"06234",
    "sg:province":"CT",
    "sg:tags":[
        "maintenance"
    ],
    "wof:name":"D & R Chimney",
    "wof:placetype":"venue"
},
  "geometry": {"coordinates":[-71.918879,41.748781],"type":"Point"}
}