{
  "type": "Feature",
  "properties": {
    "addr:full":"760 Stepney Rd Easton CT 06612",
    "addr:housenumber":"760",
    "addr:postcode":"06612",
    "addr:street":"Stepney Rd",
    "iso:country":"US",
    "sg:address":"760 Stepney Rd",
    "sg:city":"Easton",
    "sg:classifiers":[
        {
            "category":"Professional",
            "subcategory":"Computer Services",
            "type":"Services"
        }
    ],
    "sg:phone":"+1   ",
    "sg:postcode":"06612",
    "sg:province":"CT",
    "sg:tags":[
        "programing",
        "custom"
    ],
    "wof:name":"Pats Foundation",
    "wof:placetype":"venue"
},
  "geometry": {"coordinates":[-73.274441,41.317755],"type":"Point"}
}