{
  "type": "Feature",
  "properties": {
    "iso:country":"US",
    "sg:address":"398 Franklin Ave",
    "sg:city":"Hartford",
    "sg:classifiers":[
        {
            "category":"Professional",
            "type":"Services"
        }
    ],
    "sg:phone":"+1 860 296 8630",
    "sg:postcode":"06114",
    "sg:province":"CT",
    "wof:name":"Greater Hartford All American",
    "wof:placetype":"venue"
},
  "geometry": {"coordinates":[-72.675659,41.739592],"type":"Point"}
}