{
  "type": "Feature",
  "properties": {
    "iso:country":"US",
    "sg:address":"22 Poverty Hollow Rd",
    "sg:city":"Newtown",
    "sg:classifiers":[
        {
            "category":"Building & Trades",
            "subcategory":"Construction",
            "type":"Services"
        }
    ],
    "sg:phone":"+1 203 426 3048",
    "sg:postcode":"06470",
    "sg:province":"CT",
    "sg:tags":[
        "repairing",
        "remodeling",
        "contractor"
    ],
    "wof:name":"Rock Ridge Builders Inc",
    "wof:placetype":"venue"
},
  "geometry": {"coordinates":[-73.33713299999999,41.360244],"type":"Point"}
}