{
  "type": "Feature",
  "properties": {
    "addr:full":"25 Hecker Ave Darien CT 06820",
    "addr:housenumber":"25",
    "addr:postcode":"06820",
    "addr:street":"Hecker Ave Darien Ct",
    "iso:country":"US",
    "sg:address":"25 Hecker Ave",
    "sg:city":"Darien",
    "sg:classifiers":[
        {
            "category":"Government",
            "subcategory":"Police Station",
            "type":"Public Place"
        }
    ],
    "sg:phone":"+1 203 662 5330",
    "sg:postcode":"06820",
    "sg:province":"CT",
    "sg:tags":[
        "department"
    ],
    "wof:name":"Darien Police Detective Bureau",
    "wof:placetype":"venue"
},
  "geometry": {"coordinates":[-73.479373,41.069027],"type":"Point"}
}