{
  "type": "Feature",
  "properties": {
    "addr:full":"791 W Main St New Britain CT 06053",
    "addr:housenumber":"791",
    "addr:postcode":"06053",
    "addr:street":"W Main St",
    "iso:country":"US",
    "sg:address":"791 W Main St",
    "sg:city":"New Britain",
    "sg:classifiers":[
        {
            "category":"Professional",
            "subcategory":"Management & Consulting",
            "type":"Services"
        }
    ],
    "sg:phone":"+1   ",
    "sg:postcode":"06053",
    "sg:province":"CT",
    "sg:tags":[
        "business"
    ],
    "wof:name":"Emma Here",
    "wof:placetype":"venue"
},
  "geometry": {"coordinates":[-72.81074700000001,41.667201],"type":"Point"}
}