{
  "type": "Feature",
  "properties": {
    "addr:full":"291 Newtown Tpke Weston CT 06883",
    "addr:housenumber":"291",
    "addr:postcode":"06883",
    "addr:street":"Newtown Tpke",
    "iso:country":"US",
    "sg:address":"291 Newtown Tpke",
    "sg:city":"Weston",
    "sg:classifiers":[
        {
            "category":"Banks & Credit Unions",
            "subcategory":"Financial Services",
            "type":"Services"
        }
    ],
    "sg:phone":"+1 203 912 6376",
    "sg:postcode":"06883",
    "sg:province":"CT",
    "sg:tags":[
        "investor"
    ],
    "wof:name":"Sun Tzu Capital",
    "wof:placetype":"venue"
},
  "geometry": {"coordinates":[-73.383596,41.232814],"type":"Point"}
}