{
  "type": "Feature",
  "properties": {
    "iso:country":"US",
    "sg:address":"336 Federal Rd",
    "sg:city":"Brookfield",
    "sg:classifiers":[
        {
            "category":"Education",
            "subcategory":"Dance Studio",
            "type":"Public Place"
        }
    ],
    "sg:phone":"+1   ",
    "sg:postcode":"06804",
    "sg:province":"CT",
    "wof:name":"Academy Of Dance Arts",
    "wof:placetype":"venue"
},
  "geometry": {"coordinates":[-73.402,41.450891],"type":"Point"}
}