{
  "type": "Feature",
  "properties": {
    "addr:full":"110 Mountain Rd Suffield CT 06078",
    "addr:housenumber":"110",
    "addr:postcode":"06078",
    "addr:street":"Mountain Rd",
    "iso:country":"US",
    "sg:address":"110 Mountain Rd",
    "sg:city":"Suffield",
    "sg:classifiers":[
        {
            "category":"Organizations",
            "subcategory":"Community Association",
            "type":"Services"
        }
    ],
    "sg:phone":"+1   ",
    "sg:postcode":"06078",
    "sg:province":"CT",
    "sg:tags":[
        "condominium"
    ],
    "wof:name":"C/O Residential Management Co",
    "wof:placetype":"venue"
},
  "geometry": {"coordinates":[-72.65211600000001,41.982329],"type":"Point"}
}