{
  "type": "Feature",
  "properties": {
    "iso:country":"US",
    "sg:address":"115 Beths Ave",
    "sg:city":"Bristol",
    "sg:classifiers":[
        {
            "category":"Building & Trades",
            "subcategory":"Cleaning & Sanitation",
            "type":"Services"
        }
    ],
    "sg:phone":"+1   ",
    "sg:postcode":"06010",
    "sg:province":"CT",
    "sg:tags":[
        "maintenance"
    ],
    "wof:name":"Connecticlean",
    "wof:placetype":"venue"
},
  "geometry": {"coordinates":[-72.90347199999999,41.694396],"type":"Point"}
}