{
  "type": "Feature",
  "properties": {
    "addr:full":"58 Progress Dr Stamford CT 06902",
    "addr:housenumber":"58",
    "addr:postcode":"06902",
    "addr:street":"Progress Dr",
    "iso:country":"US",
    "sg:address":"58 Progress Dr",
    "sg:city":"Stamford",
    "sg:classifiers":[
        {
            "category":"Health Services",
            "subcategory":"Hospital",
            "type":"Services"
        }
    ],
    "sg:phone":"+1   ",
    "sg:postcode":"06902",
    "sg:province":"CT",
    "sg:tags":[
        "general"
    ],
    "wof:name":"Stamford Hospital",
    "wof:placetype":"venue"
},
  "geometry": {"coordinates":[-73.56096599999999,41.05425],"type":"Point"}
}