{
  "type": "Feature",
  "properties": {
    "addr:full":"874 Lakewood Rd Waterbury CT 06704",
    "addr:housenumber":"874",
    "addr:postcode":"06704",
    "addr:street":"Lakewood Rd",
    "iso:country":"US",
    "sg:address":"874 Lakewood Rd",
    "sg:city":"Waterbury",
    "sg:classifiers":[
        {
            "category":"Restaurant",
            "type":"Food & Drink"
        }
    ],
    "sg:phone":"+1 203 754 5100",
    "sg:postcode":"06704",
    "sg:province":"CT",
    "sg:website":"www.clearyspub.net",
    "wof:name":"Cleary's Restaurant & Pub",
    "wof:placetype":"venue"
},
  "geometry": {"coordinates":[-73.00743199999999,41.56997],"type":"Point"}
}