{
  "type": "Feature",
  "properties": {
    "addr:full":"245 Blake Rd Hamden CT 06517",
    "addr:housenumber":"245",
    "addr:postcode":"06517",
    "addr:street":"Blake Rd",
    "iso:country":"US",
    "sg:address":"245 Blake Rd",
    "sg:city":"Hamden",
    "sg:classifiers":[
        {
            "category":"Social Services",
            "subcategory":"Job Training",
            "type":"Services"
        }
    ],
    "sg:phone":"+1 203 498 7588",
    "sg:postcode":"06517",
    "sg:province":"CT",
    "sg:tags":[
        "career",
        "counseling",
        "vocational"
    ],
    "wof:name":"E S Hallo",
    "wof:placetype":"venue"
},
  "geometry": {"coordinates":[-72.92212600000001,41.340455],"type":"Point"}
}