{
  "type": "Feature",
  "properties": {
    "addr:full":"460 Prayer Spring Rd Stratford CT 06614",
    "addr:housenumber":"460",
    "addr:postcode":"06614",
    "addr:street":"Prayer Spring Rd",
    "iso:country":"US",
    "sg:address":"460 Prayer Spring Rd",
    "sg:city":"Stratford",
    "sg:classifiers":[
        {
            "category":"Professional",
            "subcategory":"Engineering",
            "type":"Services"
        }
    ],
    "sg:phone":"+1   ",
    "sg:postcode":"06614",
    "sg:province":"CT",
    "wof:name":"Brooklands Engineering Works",
    "wof:placetype":"venue"
},
  "geometry": {"coordinates":[-73.102677,41.255553],"type":"Point"}
}