{
  "type": "Feature",
  "properties": {
    "iso:country":"US",
    "sg:address":"15 Woodland Dr",
    "sg:city":"Rye Brook",
    "sg:classifiers":[
        {
            "category":"Health Services",
            "subcategory":"Health Practitioner",
            "type":"Services"
        }
    ],
    "sg:phone":"+1 914 937 4234",
    "sg:postcode":"10573",
    "sg:province":"CT",
    "sg:tags":[
        "psychologist"
    ],
    "wof:name":"Robert Page PHD",
    "wof:placetype":"venue"
},
  "geometry": {"coordinates":[-73.675588,41.022497],"type":"Point"}
}