{
  "type": "Feature",
  "properties": {
    "iso:country":"US",
    "sg:address":"1217 Whitney Ave",
    "sg:city":"Hamden",
    "sg:classifiers":[
        {
            "category":"Banks & Credit Unions",
            "subcategory":"Investment Brokerage",
            "type":"Services"
        }
    ],
    "sg:phone":"+1 203 407 1046",
    "sg:postcode":"06517",
    "sg:province":"CT",
    "wof:name":"Whitney Investment Assoc",
    "wof:placetype":"venue"
},
  "geometry": {"coordinates":[-72.91221899999999,41.344813],"type":"Point"}
}