{
  "type": "Feature",
  "properties": {
    "iso:country":"US",
    "sg:address":"40 Lindeman Dr",
    "sg:city":"Trumbull",
    "sg:classifiers":[
        {
            "category":"Professional",
            "type":"Services"
        }
    ],
    "sg:phone":"+1 203 330 5404",
    "sg:postcode":"06611",
    "sg:province":"CT",
    "wof:name":"United V Nurse Associatio",
    "wof:placetype":"venue"
},
  "geometry": {"coordinates":[-73.19855699999999,41.231812],"type":"Point"}
}