{
  "type": "Feature",
  "properties": {
    "iso:country":"US",
    "sg:address":"50 Applewood Dr",
    "sg:city":"Woodstock",
    "sg:classifiers":[
        {
            "category":"Organizations",
            "subcategory":"Professional Association",
            "type":"Services"
        }
    ],
    "sg:phone":"+1   ",
    "sg:postcode":"06281",
    "sg:province":"CT",
    "wof:name":"Integral Health Services",
    "wof:placetype":"venue"
},
  "geometry": {"coordinates":[-71.97381300000001,41.959031],"type":"Point"}
}