{
  "type": "Feature",
  "properties": {
    "iso:country":"US",
    "sg:address":"757 Bunker Hill Rd",
    "sg:city":"Watertown",
    "sg:classifiers":[
        {
            "category":"Building & Trades",
            "subcategory":"Construction",
            "type":"Services"
        }
    ],
    "sg:phone":"+1 860 274 7898",
    "sg:postcode":"06795",
    "sg:province":"CT",
    "sg:tags":[
        "general",
        "contractor"
    ],
    "wof:name":"Michael R Hostetler",
    "wof:placetype":"venue"
},
  "geometry": {"coordinates":[-73.113652,41.576389],"type":"Point"}
}