{
  "type": "Feature",
  "properties": {
    "addr:full":"273 W Putnam Ave Greenwich CT 06830",
    "addr:housenumber":"273",
    "addr:postcode":"06830",
    "addr:street":"W Putnam Ave",
    "iso:country":"US",
    "sg:address":"273 W Putnam Ave",
    "sg:city":"Greenwich",
    "sg:classifiers":[
        {
            "category":"Autos & Motor Vehicles",
            "subcategory":"Automobile Sales",
            "type":"Retail Goods"
        }
    ],
    "sg:phone":"+1 203 622 9623",
    "sg:postcode":"06830",
    "sg:province":"CT",
    "sg:tags":[
        "new",
        "car"
    ],
    "sg:website":"http://www.nissanusa.com",
    "wof:name":"Nissan",
    "wof:placetype":"venue"
},
  "geometry": {"coordinates":[-73.63612000000001,41.024042],"type":"Point"}
}