{
  "type": "Feature",
  "properties": {
    "addr:full":"776 Lakeside Dr Bridgeport CT 06606",
    "addr:housenumber":"776",
    "addr:postcode":"06606",
    "addr:street":"Lakeside Dr",
    "iso:country":"US",
    "sg:address":"776 Lakeside Dr",
    "sg:city":"Bridgeport",
    "sg:classifiers":[
        {
            "category":"Personal",
            "subcategory":"Shoe Repair & Shine",
            "type":"Services"
        }
    ],
    "sg:phone":"+1   ",
    "sg:postcode":"06606",
    "sg:province":"CT",
    "sg:tags":[
        "parlor"
    ],
    "wof:name":"Larrys Shoe Repair",
    "wof:placetype":"venue"
},
  "geometry": {"coordinates":[-73.20961800000001,41.221149],"type":"Point"}
}