{
  "type": "Feature",
  "properties": {
    "addr:full":"308 Farmington Ave Farmington CT 06032",
    "addr:housenumber":"308",
    "addr:postcode":"06032",
    "addr:street":"Farmington Ave",
    "iso:country":"US",
    "sg:address":"308 Farmington Ave",
    "sg:city":"Farmington",
    "sg:classifiers":[
        {
            "category":"Professional",
            "subcategory":"Accounting & Tax Preparation",
            "type":"Services"
        }
    ],
    "sg:phone":"+1   ",
    "sg:postcode":"06032",
    "sg:province":"CT",
    "wof:name":"Hartford",
    "wof:placetype":"venue"
},
  "geometry": {"coordinates":[-72.799764,41.73065],"type":"Point"}
}