{
  "type": "Feature",
  "properties": {
    "addr:full":"230 W Hill Rd Newington CT 06111",
    "addr:housenumber":"230",
    "addr:postcode":"06111",
    "addr:street":"W Hill Rd",
    "iso:country":"US",
    "sg:address":"230 W Hill Rd",
    "sg:city":"Newington",
    "sg:classifiers":[
        {
            "category":"Food & Beverages",
            "subcategory":"Groceries & Convenience Stores",
            "type":"Retail Goods"
        }
    ],
    "sg:phone":"+1 860 570 1112",
    "sg:postcode":"06111",
    "sg:province":"CT",
    "wof:name":"Asia Grocers",
    "wof:placetype":"venue"
},
  "geometry": {"coordinates":[-72.737308,41.7164],"type":"Point"}
}