{
  "type": "Feature",
  "properties": {
    "iso:country":"US",
    "sg:address":"8 Park Pl",
    "sg:city":"Darien",
    "sg:classifiers":[
        {
            "category":"Real Estate",
            "subcategory":"Architect",
            "type":"Services"
        }
    ],
    "sg:phone":"+1   ",
    "sg:postcode":"06820",
    "sg:province":"CT",
    "sg:tags":[
        "architectural"
    ],
    "wof:name":"Richard G Nemeth Architect",
    "wof:placetype":"venue"
},
  "geometry": {"coordinates":[-73.486034,41.064987],"type":"Point"}
}