{
  "type": "Feature",
  "properties": {
    "addr:full":"515 Bridgeport Ave Shelton CT 06484",
    "addr:housenumber":"515",
    "addr:postcode":"06484",
    "addr:street":"Bridgeport Ave",
    "iso:country":"US",
    "sg:address":"515 Bridgeport Ave",
    "sg:city":"Shelton",
    "sg:classifiers":[
        {
            "category":"Sports & Exercise",
            "subcategory":"Gym",
            "type":"Entertainment"
        }
    ],
    "sg:phone":"+1   ",
    "sg:postcode":"06484",
    "sg:province":"CT",
    "sg:tags":[
        "fitness",
        "physical",
        "facility"
    ],
    "wof:name":"Simply Body Llc",
    "wof:placetype":"venue"
},
  "geometry": {"coordinates":[-73.11246300000001,41.289589],"type":"Point"}
}