{
  "type": "Feature",
  "properties": {
    "iso:country":"US",
    "sg:address":"382 Main St",
    "sg:city":"Ansonia",
    "sg:classifiers":[
        {
            "category":"Banks & Credit Unions",
            "subcategory":"Bank",
            "type":"Services"
        }
    ],
    "sg:phone":"+1 203 000 1111",
    "sg:postcode":"06401",
    "sg:province":"CT",
    "wof:name":"Bank Of America",
    "wof:placetype":"venue"
},
  "geometry": {"coordinates":[-73.077828,41.340987],"type":"Point"}
}