{
  "type": "Feature",
  "properties": {
    "addr:full":"53 Putnam Park Rd Bethel CT 06801",
    "addr:housenumber":"53",
    "addr:postcode":"06801",
    "addr:street":"Putnam Park Rd",
    "iso:country":"US",
    "sg:address":"53 Putnam Park Rd",
    "sg:city":"Bethel",
    "sg:classifiers":[
        {
            "category":"Building & Trades",
            "subcategory":"Construction",
            "type":"Services"
        }
    ],
    "sg:phone":"+1 203 790 1348",
    "sg:postcode":"06801",
    "sg:province":"CT",
    "sg:tags":[
        "painter"
    ],
    "wof:name":"Mc Guire Brother's Painting",
    "wof:placetype":"venue"
},
  "geometry": {"coordinates":[-73.393044,41.3738],"type":"Point"}
}