{
  "type": "Feature",
  "properties": {
    "addr:full":"375 Bridgeport Ave Shelton CT 06484",
    "addr:housenumber":"375",
    "addr:postcode":"06484",
    "addr:street":"Bridgeport Ave",
    "iso:country":"US",
    "sg:address":"375 Bridgeport Ave",
    "sg:city":"Shelton",
    "sg:classifiers":[
        {
            "category":"Professional",
            "subcategory":"Lawyer & Legal Services",
            "type":"Services"
        }
    ],
    "sg:phone":"+1 203 929 8283",
    "sg:postcode":"06484",
    "sg:province":"CT",
    "sg:tags":[
        "attorney"
    ],
    "wof:name":"Sousa Stone & D'Agosto",
    "wof:placetype":"venue"
},
  "geometry": {"coordinates":[-73.10562,41.299366],"type":"Point"}
}