{
  "type": "Feature",
  "properties": {
    "addr:full":"846 Southford Rd Southbury CT 06488",
    "addr:housenumber":"846",
    "addr:postcode":"06488",
    "addr:street":"Southford Rd",
    "iso:country":"US",
    "sg:address":"846 Southford Rd",
    "sg:city":"Southbury",
    "sg:classifiers":[
        {
            "category":"Communications",
            "subcategory":"Film & Video Production",
            "type":"Services"
        }
    ],
    "sg:phone":"+1 203 405 1197",
    "sg:postcode":"06488",
    "sg:province":"CT",
    "sg:tags":[
        "tv",
        "radio",
        "services-commercial",
        "companies-film"
    ],
    "wof:name":"Binge Productions",
    "wof:placetype":"venue"
},
  "geometry": {"coordinates":[-73.18074300000001,41.470905],"type":"Point"}
}