{
  "type": "Feature",
  "properties": {
    "iso:country":"US",
    "sg:address":"24 Keirstead Cir",
    "sg:city":"Marlborough",
    "sg:classifiers":[
        {
            "category":"Travel",
            "subcategory":"Travel Agent",
            "type":"Entertainment"
        }
    ],
    "sg:phone":"+1 860 295 8662",
    "sg:postcode":"06447",
    "sg:province":"CT",
    "sg:tags":[
        "agency"
    ],
    "wof:name":"Middlesex Tickets & Travel LLC",
    "wof:placetype":"venue"
},
  "geometry": {"coordinates":[-72.467798,41.632055],"type":"Point"}
}