{
  "type": "Feature",
  "properties": {
    "iso:country":"US",
    "sg:address":"50 Great Oak Ln",
    "sg:city":"Redding",
    "sg:classifiers":[
        {
            "category":"Professional",
            "subcategory":"Computer Services",
            "type":"Services"
        }
    ],
    "sg:phone":"+1   ",
    "sg:postcode":"06896",
    "sg:province":"CT",
    "sg:tags":[
        "programing",
        "custom"
    ],
    "wof:name":"Winterhalder Systems Inc",
    "wof:placetype":"venue"
},
  "geometry": {"coordinates":[-73.389027,41.307418],"type":"Point"}
}