{
  "type": "Feature",
  "properties": {
    "addr:full":"4 Broadway Ave Exd Mystic CT 06355",
    "addr:housenumber":"4",
    "addr:postcode":"06355",
    "addr:street":"Broadway Ave Exd Mystic Ct",
    "iso:country":"US",
    "sg:address":"4 Broadway Ave Exd",
    "sg:city":"Mystic",
    "sg:classifiers":[
        {
            "category":"Professional",
            "subcategory":"Computer Services",
            "type":"Services"
        }
    ],
    "sg:phone":"+1   ",
    "sg:postcode":"06355",
    "sg:province":"CT",
    "sg:tags":[
        "process",
        "integrator",
        "control",
        "building",
        "system"
    ],
    "wof:name":"Systems Performance Engrg Corp",
    "wof:placetype":"venue"
},
  "geometry": {"coordinates":[-71.96406899999999,41.348364],"type":"Point"}
}