{
  "type": "Feature",
  "properties": {
    "addr:full":"99 Ash St East Hartford CT 06108",
    "addr:housenumber":"99",
    "addr:postcode":"06108",
    "addr:street":"Ash St East;Ct",
    "iso:country":"US",
    "sg:address":"99 Ash St",
    "sg:city":"East Hartford",
    "sg:classifiers":[
        {
            "category":"Health Services",
            "subcategory":"Doctor",
            "type":"Services"
        }
    ],
    "sg:phone":"+1   ",
    "sg:postcode":"06108",
    "sg:province":"CT",
    "sg:tags":[
        "medical"
    ],
    "wof:name":"Eugene Fanti MD",
    "wof:placetype":"venue"
},
  "geometry": {"coordinates":[-72.65495199999999,41.768386],"type":"Point"}
}