{
  "type": "Feature",
  "properties": {
    "addr:full":"54 Hoyclo Rd Stamford CT 06903",
    "addr:housenumber":"54",
    "addr:postcode":"06903",
    "addr:street":"Hoyclo Rd",
    "iso:country":"US",
    "sg:address":"54 Hoyclo Rd",
    "sg:city":"Stamford",
    "sg:classifiers":[
        {
            "category":"Insurance",
            "subcategory":"Hazard Insurance",
            "type":"Services"
        }
    ],
    "sg:phone":"+1 203 322 7954",
    "sg:postcode":"06903",
    "sg:province":"CT",
    "sg:tags":[
        "profit",
        "sharing",
        "pension",
        "plan"
    ],
    "sg:website":"www.suretytrustee.com",
    "wof:name":"Surety Trustee Svc",
    "wof:placetype":"venue"
},
  "geometry": {"coordinates":[-73.551238,41.147843],"type":"Point"}
}