{
  "type": "Feature",
  "properties": {
    "iso:country":"US",
    "sg:address":"123 Rectory St",
    "sg:city":"Port Chester",
    "sg:classifiers":[
        {
            "category":"Retail",
            "subcategory":"Auto Repair",
            "type":"Services"
        }
    ],
    "sg:phone":"+1 914 937 4152",
    "sg:postcode":"10573",
    "sg:province":"CT",
    "sg:tags":[
        "wrecker"
    ],
    "wof:name":"Ace Towing",
    "wof:placetype":"venue"
},
  "geometry": {"coordinates":[-73.65761500000001,41.007695],"type":"Point"}
}