{
  "type": "Feature",
  "properties": {
    "iso:country":"US",
    "sg:address":"35 Edgemere Rd",
    "sg:city":"East Haven",
    "sg:classifiers":[
        {
            "category":"Education",
            "subcategory":"Special Training",
            "type":"Public Place"
        }
    ],
    "sg:phone":"+1   ",
    "sg:postcode":"06512",
    "sg:province":"CT",
    "wof:name":"Connecticut Comm Driver",
    "wof:placetype":"venue"
},
  "geometry": {"coordinates":[-72.869681,41.26218],"type":"Point"}
}