{
  "type": "Feature",
  "properties": {
    "iso:country":"US",
    "sg:address":"522 Cottage Grove Rd",
    "sg:city":"Bloomfield",
    "sg:classifiers":[
        {
            "category":"Wholesale",
            "subcategory":"Machinery & Supplies",
            "type":"Manufacturing & Wholesale Goods"
        }
    ],
    "sg:phone":"+1 860 243 0337",
    "sg:postcode":"06002",
    "sg:province":"CT",
    "sg:tags":[
        "equipment"
    ],
    "wof:name":"New England Scaffolding",
    "wof:placetype":"venue"
},
  "geometry": {"coordinates":[-72.72269799999999,41.817396],"type":"Point"}
}