{
  "type": "Feature",
  "properties": {
    "addr:full":"216 Chase Ave Waterbury CT 06704",
    "addr:housenumber":"216",
    "addr:postcode":"06704",
    "addr:street":"Chase Ave",
    "iso:country":"US",
    "sg:address":"216 Chase Ave",
    "sg:city":"Waterbury",
    "sg:classifiers":[
        {
            "category":"Professional",
            "subcategory":"Accounting & Tax Preparation",
            "type":"Services"
        }
    ],
    "sg:phone":"+1 203 754 6488",
    "sg:postcode":"06704",
    "sg:province":"CT",
    "sg:tags":[
        "return",
        "filing"
    ],
    "wof:name":"H & R Block Tax Svc",
    "wof:placetype":"venue"
},
  "geometry": {"coordinates":[-73.033305,41.580869],"type":"Point"}
}