{
  "type": "Feature",
  "properties": {
    "addr:full":"1625 Middlebury Rd Middlebury CT 06762",
    "addr:housenumber":"1625",
    "addr:postcode":"06762",
    "addr:street":"Middlebury Rd",
    "iso:country":"US",
    "sg:address":"1625 Middlebury Rd",
    "sg:city":"Middlebury",
    "sg:classifiers":[
        {
            "category":"Health Services",
            "subcategory":"Doctor",
            "type":"Services"
        }
    ],
    "sg:phone":"+1 203 759 0666",
    "sg:postcode":"06762",
    "sg:province":"CT",
    "sg:tags":[
        "physician",
        "surgeon"
    ],
    "wof:name":"Alliance Medical Group",
    "wof:placetype":"venue"
},
  "geometry": {"coordinates":[-73.132988,41.524383],"type":"Point"}
}