{
  "type": "Feature",
  "properties": {
    "addr:full":"5 Lancaster Dr Norwalk CT 06850",
    "addr:housenumber":"5",
    "addr:postcode":"06850",
    "addr:street":"Lancaster Dr",
    "iso:country":"US",
    "sg:address":"5 Lancaster Dr",
    "sg:city":"Norwalk",
    "sg:classifiers":[
        {
            "category":"Professional",
            "subcategory":"Management & Consulting",
            "type":"Services"
        }
    ],
    "sg:phone":"+1   ",
    "sg:postcode":"06850",
    "sg:province":"CT",
    "sg:tags":[
        "business"
    ],
    "wof:name":"IDEAS",
    "wof:placetype":"venue"
},
  "geometry": {"coordinates":[-73.446254,41.12405],"type":"Point"}
}