{
  "type": "Feature",
  "properties": {
    "iso:country":"US",
    "sg:address":"734 Pacific St",
    "sg:city":"Stamford",
    "sg:classifiers":[
        {
            "category":"Food & Beverages",
            "subcategory":"Liquor & Beverages",
            "type":"Retail Goods"
        }
    ],
    "sg:phone":"+1 203 323 3241",
    "sg:postcode":"06902",
    "sg:province":"CT",
    "wof:name":"Polonia's Liquor Store",
    "wof:placetype":"venue"
},
  "geometry": {"coordinates":[-73.53813100000001,41.042229],"type":"Point"}
}