{
  "type": "Feature",
  "properties": {
    "iso:country":"US",
    "sg:address":"1297 Long Ridge Rd",
    "sg:city":"Stamford",
    "sg:classifiers":[
        {
            "category":"Real Estate",
            "subcategory":"Real Estate Operator",
            "type":"Services"
        },
        {
            "category":"Restaurant",
            "type":"Food & Drink"
        }
    ],
    "sg:phone":"+1 203 322 8870",
    "sg:postcode":"06903",
    "sg:province":"CT",
    "sg:tags":[
        "owner",
        "property",
        "commercial"
    ],
    "sg:website":"www.giovanni.com",
    "wof:name":"Giovanni's Steakhouse",
    "wof:placetype":"venue"
},
  "geometry": {"coordinates":[-73.570425,41.109826],"type":"Point"}
}