{
  "type": "Feature",
  "properties": {
    "iso:country":"US",
    "sg:address":"286 Maple Ave",
    "sg:city":"Cheshire",
    "sg:classifiers":[
        {
            "category":"Restaurant",
            "type":"Food & Drink"
        }
    ],
    "sg:phone":"+1 203 272 5998",
    "sg:postcode":"06410",
    "sg:province":"CT",
    "wof:name":"Waverly Tavern Restaurant",
    "wof:placetype":"venue"
},
  "geometry": {"coordinates":[-72.90322500000001,41.506708],"type":"Point"}
}