{
  "type": "Feature",
  "properties": {
    "addr:full":"110 Myrtle Ave Westport CT 06880",
    "addr:housenumber":"110",
    "addr:postcode":"06880",
    "addr:street":"Myrtle Ave",
    "iso:country":"US",
    "sg:address":"110 Myrtle Ave",
    "sg:city":"Westport",
    "sg:classifiers":[
        {
            "category":"Education",
            "subcategory":"School",
            "type":"Public Place"
        }
    ],
    "sg:phone":"+1 203 341 1025",
    "sg:postcode":"06880",
    "sg:province":"CT",
    "sg:website":"www.westport.k12.ct.us",
    "wof:name":"Westport Superintendent-Schl",
    "wof:placetype":"venue"
},
  "geometry": {"coordinates":[-73.36062099999999,41.145111],"type":"Point"}
}