{
  "type": "Feature",
  "properties": {
    "addr:full":"96 S Turnpike Rd Wallingford CT 06492",
    "addr:housenumber":"96",
    "addr:postcode":"06492",
    "addr:street":"S Turnpike Rd",
    "iso:country":"US",
    "sg:address":"96 S Turnpike Rd",
    "sg:city":"Wallingford",
    "sg:classifiers":[
        {
            "category":"Real Estate",
            "subcategory":"Real Estate Agent",
            "type":"Services"
        }
    ],
    "sg:phone":"+1 203 269 6481",
    "sg:postcode":"06492",
    "sg:province":"CT",
    "sg:tags":[
        "management"
    ],
    "wof:name":"Halcyon Office Park",
    "wof:placetype":"venue"
},
  "geometry": {"coordinates":[-72.843863,41.448705],"type":"Point"}
}