{
  "type": "Feature",
  "properties": {
    "addr:full":"219 Main St Norwalk CT 06851",
    "addr:housenumber":"219",
    "addr:postcode":"06851",
    "addr:street":"Main St",
    "iso:country":"US",
    "sg:address":"219 Main St",
    "sg:city":"Norwalk",
    "sg:classifiers":[
        {
            "category":"Retail",
            "subcategory":"Auto Repair",
            "type":"Services"
        }
    ],
    "sg:phone":"+1 203 845 8828",
    "sg:postcode":"06851",
    "sg:province":"CT",
    "wof:name":"Safe Line Tire & Auto Repair",
    "wof:placetype":"venue"
},
  "geometry": {"coordinates":[-73.422642,41.129284],"type":"Point"}
}