{
  "type": "Feature",
  "properties": {
    "iso:country":"US",
    "sg:address":"804 Stanley St",
    "sg:city":"New Britain",
    "sg:classifiers":[
        {
            "category":"Retail",
            "subcategory":"Auto Repair",
            "type":"Services"
        }
    ],
    "sg:phone":"+1   ",
    "sg:postcode":"06051",
    "sg:province":"CT",
    "sg:tags":[
        "body",
        "automotive",
        "work",
        "including",
        "general"
    ],
    "wof:name":"Pauls Automotive",
    "wof:placetype":"venue"
},
  "geometry": {"coordinates":[-72.772351,41.668844],"type":"Point"}
}