{
  "type": "Feature",
  "properties": {
    "addr:full":"340 Heights Rd Darien CT 06820",
    "addr:housenumber":"340",
    "addr:postcode":"06820",
    "addr:street":"Heights Rd",
    "iso:country":"US",
    "sg:address":"340 Heights Rd",
    "sg:city":"Darien",
    "sg:classifiers":[
        {
            "category":"Cinema",
            "subcategory":"Movie Rental",
            "type":"Entertainment"
        }
    ],
    "sg:phone":"+1   ",
    "sg:postcode":"06820",
    "sg:province":"CT",
    "sg:tags":[
        "video",
        "production",
        "tape"
    ],
    "wof:name":"Roxy Video",
    "wof:placetype":"venue"
},
  "geometry": {"coordinates":[-73.495966,41.069211],"type":"Point"}
}