{
  "type": "Feature",
  "properties": {
    "iso:country":"US",
    "sg:address":"43 Rosedale Rd",
    "sg:city":"Hartford",
    "sg:classifiers":[
        {
            "category":"Retail",
            "subcategory":"Self-service Laundry",
            "type":"Services"
        }
    ],
    "sg:phone":"+1   ",
    "sg:postcode":"06107",
    "sg:province":"CT",
    "sg:tags":[
        "coin"
    ],
    "wof:name":"Super Suds",
    "wof:placetype":"venue"
},
  "geometry": {"coordinates":[-72.76227299999999,41.748005],"type":"Point"}
}