{
  "type": "Feature",
  "properties": {
    "addr:full":"216 Scribner Ave Norwalk CT 06854",
    "addr:housenumber":"216",
    "addr:postcode":"06854",
    "addr:street":"Scribner Ave",
    "iso:country":"US",
    "sg:address":"216 Scribner Ave",
    "sg:city":"Norwalk",
    "sg:classifiers":[
        {
            "category":"Organizations",
            "subcategory":"Religious Organization",
            "type":"Services"
        }
    ],
    "sg:phone":"+1   ",
    "sg:postcode":"06854",
    "sg:province":"CT",
    "wof:name":"Saint Matthew Church",
    "wof:placetype":"venue"
},
  "geometry": {"coordinates":[-73.450219,41.110002],"type":"Point"}
}