{
  "type": "Feature",
  "properties": {
    "iso:country":"US",
    "sg:address":"20 Dogwood Dr",
    "sg:city":"Danbury",
    "sg:classifiers":[
        {
            "category":"Personal",
            "type":"Services"
        }
    ],
    "sg:phone":"+1 203 797 0077",
    "sg:postcode":"06811",
    "sg:province":"CT",
    "sg:tags":[
        "therapist",
        "massage"
    ],
    "wof:name":"Nancy Lavers",
    "wof:placetype":"venue"
},
  "geometry": {"coordinates":[-73.477228,41.415026],"type":"Point"}
}