{
  "type": "Feature",
  "properties": {
    "addr:full":"246 Dodge Ave East Haven CT 06512",
    "addr:housenumber":"246",
    "addr:postcode":"06512",
    "addr:street":"Dodge Ave",
    "iso:country":"US",
    "sg:address":"246 Dodge Ave",
    "sg:city":"East Haven",
    "sg:classifiers":[
        {
            "category":"Professional",
            "subcategory":"Engineering",
            "type":"Services"
        }
    ],
    "sg:phone":"+1   ",
    "sg:postcode":"06512",
    "sg:province":"CT",
    "wof:name":"Advanced Control Systems Inc",
    "wof:placetype":"venue"
},
  "geometry": {"coordinates":[-72.88336700000001,41.271598],"type":"Point"}
}