{
  "type": "Feature",
  "properties": {
    "iso:country":"US",
    "sg:address":"843 Boston Post Rd",
    "sg:city":"Old Saybrook",
    "sg:classifiers":[
        {
            "category":"Food & Beverages",
            "subcategory":"Specialty",
            "type":"Retail Goods"
        }
    ],
    "sg:phone":"+1 860 388 5616",
    "sg:postcode":"06475",
    "sg:province":"CT",
    "wof:name":"GNC",
    "wof:placetype":"venue"
},
  "geometry": {"coordinates":[-72.382661,41.292439],"type":"Point"}
}