{
  "type": "Feature",
  "properties": {
    "iso:country":"US",
    "sg:address":"53 Hotchkiss Grove Rd",
    "sg:city":"Branford",
    "sg:classifiers":[
        {
            "category":"Professional",
            "type":"Services"
        }
    ],
    "sg:phone":"+1 203 481 4063",
    "sg:postcode":"06405",
    "sg:province":"CT",
    "sg:tags":[
        "establishment"
    ],
    "wof:name":"Peter C Young LLC",
    "wof:placetype":"venue"
},
  "geometry": {"coordinates":[-72.786737,41.270961],"type":"Point"}
}