{
  "type": "Feature",
  "properties": {
    "iso:country":"US",
    "sg:address":"64 Maple Ave",
    "sg:city":"Canton",
    "sg:classifiers":[
        {
            "category":"Professional",
            "subcategory":"Business Services",
            "type":"Services"
        }
    ],
    "sg:phone":"+1   ",
    "sg:postcode":"06022",
    "sg:province":"CT",
    "sg:tags":[
        "consulting",
        "industrial",
        "design",
        "machinery",
        "for"
    ],
    "wof:name":"Deco",
    "wof:placetype":"venue"
},
  "geometry": {"coordinates":[-72.913247,41.82126],"type":"Point"}
}