{
  "type": "Feature",
  "properties": {
    "iso:country":"US",
    "sg:address":"400 King St",
    "sg:city":"Port Chester",
    "sg:classifiers":[
        {
            "category":"Organizations",
            "subcategory":"Community Association",
            "type":"Services"
        }
    ],
    "sg:phone":"+1 914 939 2867",
    "sg:postcode":"10573",
    "sg:province":"CT",
    "wof:name":"Rotary CLB Fort Chster Rybrook",
    "wof:placetype":"venue"
},
  "geometry": {"coordinates":[-73.666112,41.01086],"type":"Point"}
}