{
  "type": "Feature",
  "properties": {
    "iso:country":"US",
    "sg:address":"235 Main St",
    "sg:city":"Danbury",
    "sg:classifiers":[
        {
            "category":"Education",
            "subcategory":"School",
            "type":"Public Place"
        }
    ],
    "sg:phone":"+1   ",
    "sg:postcode":"06810",
    "sg:province":"CT",
    "wof:name":"Project Succeed",
    "wof:placetype":"venue"
},
  "geometry": {"coordinates":[-73.45288600000001,41.394979],"type":"Point"}
}