{
  "type": "Feature",
  "properties": {
    "iso:country":"US",
    "sg:address":"45 Brown Pl",
    "sg:city":"Waterbury",
    "sg:classifiers":[
        {
            "category":"Building & Trades",
            "subcategory":"Cleaning & Sanitation",
            "type":"Services"
        }
    ],
    "sg:phone":"+1   ",
    "sg:postcode":"06702",
    "sg:province":"CT",
    "sg:tags":[
        "maintenance"
    ],
    "wof:name":"Premier Maintenance",
    "wof:placetype":"venue"
},
  "geometry": {"coordinates":[-73.047527,41.556919],"type":"Point"}
}