{
  "type": "Feature",
  "properties": {
    "addr:full":"58 Fair St Guilford CT 06437",
    "addr:housenumber":"58",
    "addr:postcode":"06437",
    "addr:street":"Fair St",
    "iso:country":"US",
    "sg:address":"58 Fair St",
    "sg:city":"Guilford",
    "sg:classifiers":[
        {
            "category":"Travel",
            "subcategory":"Travel Agent",
            "type":"Entertainment"
        }
    ],
    "sg:phone":"+1 203 481 2318",
    "sg:postcode":"06437",
    "sg:province":"CT",
    "sg:tags":[
        "agency",
        "bureau"
    ],
    "sg:website":"www.carrtravel.com",
    "wof:name":"Carr Travel LTD",
    "wof:placetype":"venue"
},
  "geometry": {"coordinates":[-72.68502700000001,41.28575],"type":"Point"}
}