{
  "type": "Feature",
  "properties": {
    "iso:country":"US",
    "sg:address":"911 Hartford Tpke",
    "sg:city":"Vernon Rockville",
    "sg:classifiers":[
        {
            "category":"Restaurant",
            "type":"Food & Drink"
        }
    ],
    "sg:phone":"+1 860 871 9300",
    "sg:postcode":"06066",
    "sg:province":"CT",
    "sg:tags":[
        "eating"
    ],
    "wof:name":"New England Pizza & Restaurant",
    "wof:placetype":"venue"
},
  "geometry": {"coordinates":[-72.453869,41.846289],"type":"Point"}
}