{
  "type": "Feature",
  "properties": {
    "iso:country":"US",
    "sg:address":"59 Wooddale Dr",
    "sg:city":"Unionville",
    "sg:classifiers":[
        {
            "category":"Professional",
            "subcategory":"Management & Consulting",
            "type":"Services"
        }
    ],
    "sg:phone":"+1   ",
    "sg:postcode":"06085",
    "sg:province":"CT",
    "wof:name":"Lorbert Assoc",
    "wof:placetype":"venue"
},
  "geometry": {"coordinates":[-72.89401700000001,41.742723],"type":"Point"}
}