{
  "type": "Feature",
  "properties": {
    "iso:country":"US",
    "sg:address":"29 Heritage Rd",
    "sg:city":"Southbury",
    "sg:classifiers":[
        {
            "category":"Real Estate",
            "subcategory":"Real Estate Operator",
            "type":"Services"
        }
    ],
    "sg:phone":"+1 203 264 0940",
    "sg:postcode":"06488",
    "sg:province":"CT",
    "sg:tags":[
        "condominium"
    ],
    "wof:name":"Heritage Crest Condo",
    "wof:placetype":"venue"
},
  "geometry": {"coordinates":[-73.224874,41.488439],"type":"Point"}
}