{
  "type": "Feature",
  "properties": {
    "iso:country":"US",
    "sg:address":"3070 Main St",
    "sg:city":"Bridgeport",
    "sg:classifiers":[
        {
            "category":"Health Services",
            "subcategory":"Doctor",
            "type":"Services"
        }
    ],
    "sg:phone":"+1 203 374 0082",
    "sg:postcode":"06606",
    "sg:province":"CT",
    "sg:tags":[
        "dentist"
    ],
    "wof:name":"Carl F De Lucia DDS",
    "wof:placetype":"venue"
},
  "geometry": {"coordinates":[-73.20448,41.203266],"type":"Point"}
}