{
  "type": "Feature",
  "properties": {
    "iso:country":"US",
    "sg:address":"2941 Main St",
    "sg:city":"Glastonbury",
    "sg:classifiers":[
        {
            "category":"Personal",
            "type":"Services"
        }
    ],
    "sg:phone":"+1   ",
    "sg:postcode":"06033",
    "sg:province":"CT",
    "sg:tags":[
        "banquet",
        "hall",
        "facility"
    ],
    "wof:name":"Buckbard Bnquet Conference Ctr",
    "wof:placetype":"venue"
},
  "geometry": {"coordinates":[-72.61533799999999,41.725108],"type":"Point"}
}