{
  "type": "Feature",
  "properties": {
    "iso:country":"US",
    "sg:address":"411 Barnum Ave",
    "sg:city":"Stratford",
    "sg:classifiers":[
        {
            "category":"Shopping",
            "subcategory":"Department Store",
            "type":"Retail Goods"
        }
    ],
    "sg:phone":"+1 203 377 4742",
    "sg:postcode":"06614",
    "sg:province":"CT",
    "wof:name":"Marshalls",
    "wof:placetype":"venue"
},
  "geometry": {"coordinates":[-73.120333,41.1988],"type":"Point"}
}