{
  "type": "Feature",
  "properties": {
    "addr:full":"300 3rd Ave Milford CT 06460",
    "addr:housenumber":"300",
    "addr:postcode":"06460",
    "addr:street":"3Rd Ave",
    "iso:country":"US",
    "sg:address":"300 3rd Ave",
    "sg:city":"Milford",
    "sg:classifiers":[
        {
            "category":"Social Services",
            "subcategory":"Adult Care",
            "type":"Services"
        }
    ],
    "sg:phone":"+1   ",
    "sg:postcode":"06460",
    "sg:province":"CT",
    "sg:tags":[
        "residential"
    ],
    "wof:name":"Third Ave Group Home",
    "wof:placetype":"venue"
},
  "geometry": {"coordinates":[-73.099058,41.185368],"type":"Point"}
}