{
  "type": "Feature",
  "properties": {
    "iso:country":"US",
    "sg:address":"29 Barmore Dr E",
    "sg:city":"Stamford",
    "sg:classifiers":[
        {
            "category":"Building & Trades",
            "subcategory":"Construction",
            "type":"Services"
        }
    ],
    "sg:phone":"+1 203 325 4760",
    "sg:postcode":"06905",
    "sg:province":"CT",
    "sg:tags":[
        "house",
        "nonresidential"
    ],
    "wof:name":"Ray Interlandi & Son",
    "wof:placetype":"venue"
},
  "geometry": {"coordinates":[-73.542354,41.102042],"type":"Point"}
}