{
  "type": "Feature",
  "properties": {
    "iso:country":"US",
    "sg:address":"19 Smoke Ridge Rd",
    "sg:city":"Sherman",
    "sg:classifiers":[
        {
            "category":"Building & Trades",
            "subcategory":"Plumbing",
            "type":"Services"
        }
    ],
    "sg:phone":"+1 860 210 1255",
    "sg:postcode":"06784",
    "sg:province":"CT",
    "sg:tags":[
        "tank",
        "septic"
    ],
    "wof:name":"A 1 Septic Co Inc",
    "wof:placetype":"venue"
},
  "geometry": {"coordinates":[-73.50861500000001,41.637512],"type":"Point"}
}