{
  "type": "Feature",
  "properties": {
    "iso:country":"US",
    "sg:address":"30 Hazel Ter",
    "sg:city":"Woodbridge",
    "sg:classifiers":[
        {
            "category":"Building & Trades",
            "subcategory":"Construction",
            "type":"Services"
        }
    ],
    "sg:phone":"+1 203 397 1680",
    "sg:postcode":"06525",
    "sg:province":"CT",
    "sg:tags":[
        "general",
        "contractor"
    ],
    "wof:name":"Crystal Homes Lllc",
    "wof:placetype":"venue"
},
  "geometry": {"coordinates":[-72.98346100000001,41.339608],"type":"Point"}
}