{
  "type": "Feature",
  "properties": {
    "addr:full":"208 Flax Hill Rd Norwalk CT 06854",
    "addr:housenumber":"208",
    "addr:postcode":"06854",
    "addr:street":"Flax Hill Rd",
    "iso:country":"US",
    "sg:address":"208 Flax Hill Rd",
    "sg:city":"Norwalk",
    "sg:classifiers":[
        {
            "category":"Real Estate",
            "subcategory":"Real Estate Operator",
            "type":"Services"
        }
    ],
    "sg:phone":"+1 203 838 2728",
    "sg:postcode":"06854",
    "sg:province":"CT",
    "sg:tags":[
        "apartment"
    ],
    "wof:name":"Flax Hill Apartments",
    "wof:placetype":"venue"
},
  "geometry": {"coordinates":[-73.42592399999999,41.09624],"type":"Point"}
}