{
  "type": "Feature",
  "properties": {
    "addr:full":"1767 Summer St Stamford CT 06905",
    "addr:housenumber":"1767",
    "addr:postcode":"06905",
    "addr:street":"Summer St",
    "iso:country":"US",
    "sg:address":"1767 Summer St",
    "sg:city":"Stamford",
    "sg:classifiers":[
        {
            "category":"Social Services",
            "type":"Services"
        }
    ],
    "sg:phone":"+1   ",
    "sg:postcode":"06905",
    "sg:province":"CT",
    "wof:name":"James E Sherry Lcsw",
    "wof:placetype":"venue"
},
  "geometry": {"coordinates":[-73.54342200000001,41.06452],"type":"Point"}
}