{
  "type": "Feature",
  "properties": {
    "iso:country":"US",
    "sg:address":"13 Barnett St",
    "sg:city":"New Haven",
    "sg:classifiers":[
        {
            "category":"Building & Trades",
            "subcategory":"Landscaping Services",
            "type":"Services"
        }
    ],
    "sg:phone":"+1 203 387 4262",
    "sg:postcode":"06515",
    "sg:province":"CT",
    "wof:name":"Grass Roots Landscaping",
    "wof:placetype":"venue"
},
  "geometry": {"coordinates":[-72.96584900000001,41.324773],"type":"Point"}
}