{
  "type": "Feature",
  "properties": {
    "addr:full":"529 Broad St Meriden CT 06450",
    "addr:housenumber":"529",
    "addr:postcode":"06450",
    "addr:street":"Broad St",
    "iso:country":"US",
    "sg:address":"529 Broad St",
    "sg:city":"Meriden",
    "sg:classifiers":[
        {
            "category":"Real Estate",
            "subcategory":"Real Estate Agent",
            "type":"Services"
        }
    ],
    "sg:phone":"+1 203 630 2847",
    "sg:postcode":"06450",
    "sg:province":"CT",
    "wof:name":"Sutherland Realty",
    "wof:placetype":"venue"
},
  "geometry": {"coordinates":[-72.790548,41.535221],"type":"Point"}
}