{
  "type": "Feature",
  "properties": {
    "addr:full":"1 Cards Mills Rd Columbia CT 06237",
    "addr:postcode":"06237",
    "addr:street":"Mills Rd",
    "iso:country":"US",
    "sg:address":"1 Cards Mills Rd",
    "sg:city":"Columbia",
    "sg:classifiers":[
        {
            "category":"Professional",
            "subcategory":"Accounting & Tax Preparation",
            "type":"Services"
        }
    ],
    "sg:phone":"+1   ",
    "sg:postcode":"06237",
    "sg:province":"CT",
    "sg:tags":[
        "return"
    ],
    "wof:name":"Sipple Enterprises",
    "wof:placetype":"venue"
},
  "geometry": {"coordinates":[-72.24694100000001,41.717366],"type":"Point"}
}