{
  "type": "Feature",
  "properties": {
    "addr:full":"199 Ethan Allen Hwy Ridgefield CT 06877",
    "addr:housenumber":"199",
    "addr:postcode":"06877",
    "addr:street":"Ethan Allen Hwy Ridgefield Ct",
    "iso:country":"US",
    "sg:address":"199 Ethan Allen Hwy",
    "sg:city":"Ridgefield",
    "sg:classifiers":[
        {
            "category":"Manufacturing",
            "subcategory":"Printing",
            "type":"Manufacturing & Wholesale Goods"
        }
    ],
    "sg:phone":"+1 203 431 0421",
    "sg:postcode":"06877",
    "sg:province":"CT",
    "sg:tags":[
        "printer"
    ],
    "wof:name":"Ridgefield Printing Inc",
    "wof:placetype":"venue"
},
  "geometry": {"coordinates":[-73.445756,41.281139],"type":"Point"}
}