{
  "type": "Feature",
  "properties": {
    "addr:full":"1125 Hartford Tpke Vernon Rockville CT 06066",
    "addr:housenumber":"1125",
    "addr:postcode":"06066",
    "addr:street":"Hartford Tpke",
    "iso:country":"US",
    "sg:address":"1125 Hartford Tpke",
    "sg:city":"Vernon Rockville",
    "sg:classifiers":[
        {
            "category":"Real Estate",
            "subcategory":"Real Estate Operator",
            "type":"Services"
        }
    ],
    "sg:phone":"+1 860 872 7384",
    "sg:postcode":"06066",
    "sg:province":"CT",
    "sg:tags":[
        "building",
        "apartment"
    ],
    "wof:name":"Santini Homes",
    "wof:placetype":"venue"
},
  "geometry": {"coordinates":[-72.448887,41.850229],"type":"Point"}
}