{
  "type": "Feature",
  "properties": {
    "addr:full":"12 Pleasant St Norwalk CT 06855",
    "addr:housenumber":"12",
    "addr:postcode":"06855",
    "addr:street":"Pleasant St",
    "iso:country":"US",
    "sg:address":"12 Pleasant St",
    "sg:city":"Norwalk",
    "sg:classifiers":[
        {
            "category":"Manufacturing",
            "subcategory":"Metals",
            "type":"Manufacturing & Wholesale Goods"
        }
    ],
    "sg:phone":"+1 203 853 7276",
    "sg:postcode":"06855",
    "sg:province":"CT",
    "sg:tags":[
        "machine",
        "screw",
        "product"
    ],
    "wof:name":"Hannes Precision Industries",
    "wof:placetype":"venue"
},
  "geometry": {"coordinates":[-73.409931,41.103676],"type":"Point"}
}