{
  "type": "Feature",
  "properties": {
    "iso:country":"US",
    "sg:address":"390 East St",
    "sg:city":"New Haven",
    "sg:classifiers":[
        {
            "category":"Home & Garden",
            "subcategory":"Building Materials",
            "type":"Retail Goods"
        }
    ],
    "sg:phone":"+1 203 562 5173",
    "sg:postcode":"06511",
    "sg:province":"CT",
    "sg:tags":[
        "paint"
    ],
    "wof:name":"Brandman's Paint Warehouse",
    "wof:placetype":"venue"
},
  "geometry": {"coordinates":[-72.909864,41.309022],"type":"Point"}
}