{
  "type": "Feature",
  "properties": {
    "addr:full":"232 Housatonic Ave Stratford CT 06615",
    "addr:housenumber":"232",
    "addr:postcode":"06615",
    "addr:street":"Housatonic Ave",
    "iso:country":"US",
    "sg:address":"232 Housatonic Ave",
    "sg:city":"Stratford",
    "sg:classifiers":[
        {
            "category":"Insurance",
            "subcategory":"Insurance Agent",
            "type":"Services"
        }
    ],
    "sg:phone":"+1 203 375 7275",
    "sg:postcode":"06615",
    "sg:province":"CT",
    "wof:name":"Roxanne Pruzinsky & Assoc",
    "wof:placetype":"venue"
},
  "geometry": {"coordinates":[-73.121945,41.190701],"type":"Point"}
}