{
  "type": "Feature",
  "properties": {
    "addr:full":"203 Foxon Rd North Branford CT 06471",
    "addr:housenumber":"203",
    "addr:postcode":"06471",
    "addr:street":"Foxon Rd North Branford Ct",
    "iso:country":"US",
    "sg:address":"203 Foxon Rd",
    "sg:city":"North Branford",
    "sg:classifiers":[
        {
            "category":"Bars & Pubs",
            "type":"Food & Drink"
        }
    ],
    "sg:phone":"+1 203 484 5183",
    "sg:postcode":"06471",
    "sg:province":"CT",
    "wof:name":"Lage Lounge",
    "wof:placetype":"venue"
},
  "geometry": {"coordinates":[-72.815744,41.328027],"type":"Point"}
}