{
  "type": "Feature",
  "properties": {
    "iso:country":"US",
    "sg:address":"35 Greenmanville Ave",
    "sg:city":"Mystic",
    "sg:classifiers":[
        {
            "category":"Retail",
            "subcategory":"Repair Shop",
            "type":"Services"
        }
    ],
    "sg:phone":"+1   ",
    "sg:postcode":"06355",
    "sg:province":"CT",
    "sg:tags":[
        "building",
        "restoration"
    ],
    "wof:name":"Robert F Tatro",
    "wof:placetype":"venue"
},
  "geometry": {"coordinates":[-71.96358499999999,41.360881],"type":"Point"}
}