{
  "type": "Feature",
  "properties": {
    "iso:country":"US",
    "sg:address":"150 Connecticut Ave",
    "sg:city":"Norwalk",
    "sg:classifiers":[
        {
            "category":"Building & Trades",
            "subcategory":"Plumbing",
            "type":"Services"
        }
    ],
    "sg:phone":"+1 203 838 7633",
    "sg:postcode":"06854",
    "sg:province":"CT",
    "sg:tags":[
        "heating",
        "contractor"
    ],
    "wof:name":"Caruso's Plumbing & Heating",
    "wof:placetype":"venue"
},
  "geometry": {"coordinates":[-73.432964,41.103795],"type":"Point"}
}