{
  "type": "Feature",
  "properties": {
    "iso:country":"US",
    "sg:address":"30 Fountain St",
    "sg:city":"New Haven",
    "sg:classifiers":[
        {
            "category":"Shopping",
            "subcategory":"Used Merchandise",
            "type":"Retail Goods"
        }
    ],
    "sg:phone":"+1 203 389 5440",
    "sg:postcode":"06515",
    "sg:province":"CT",
    "sg:tags":[
        "antique"
    ],
    "wof:name":"Antiques Market",
    "wof:placetype":"venue"
},
  "geometry": {"coordinates":[-72.959146,41.326028],"type":"Point"}
}