{
  "type": "Feature",
  "properties": {
    "iso:country":"US",
    "sg:address":"553 Jeremy Swamp Rd",
    "sg:city":"Southbury",
    "sg:classifiers":[
        {
            "category":"Farming",
            "subcategory":"Farm",
            "type":"Manufacturing & Wholesale Goods"
        }
    ],
    "sg:phone":"+1 203 264 8124",
    "sg:postcode":"06488",
    "sg:province":"CT",
    "sg:tags":[
        "crop",
        "general"
    ],
    "wof:name":"Bline Farm LLC",
    "wof:placetype":"venue"
},
  "geometry": {"coordinates":[-73.188356,41.46601],"type":"Point"}
}