{
  "type": "Feature",
  "properties": {
    "iso:country":"US",
    "sg:address":"338 Main St",
    "sg:city":"Winsted",
    "sg:classifiers":[
        {
            "category":"Government",
            "subcategory":"Office",
            "type":"Public Place"
        }
    ],
    "sg:phone":"+1 860 379 5461",
    "sg:postcode":"06098",
    "sg:province":"CT",
    "sg:tags":[
        "policy"
    ],
    "wof:name":"Tax Assessor",
    "wof:placetype":"venue"
},
  "geometry": {"coordinates":[-72.963965,41.870487],"type":"Point"}
}