{
  "type": "Feature",
  "properties": {
    "iso:country":"US",
    "sg:address":"20 N Whittlesey Ave",
    "sg:city":"Wallingford",
    "sg:classifiers":[
        {
            "category":"Social Services",
            "subcategory":"Child Care",
            "type":"Services"
        }
    ],
    "sg:phone":"+1   ",
    "sg:postcode":"06492",
    "sg:province":"CT",
    "sg:tags":[
        "day"
    ],
    "wof:name":"Good Shepherd Pre-School",
    "wof:placetype":"venue"
},
  "geometry": {"coordinates":[-72.819278,41.456119],"type":"Point"}
}