{
  "type": "Feature",
  "properties": {
    "iso:country":"US",
    "sg:address":"164 Newtown Tpke",
    "sg:city":"Westport",
    "sg:classifiers":[
        {
            "category":"Professional",
            "type":"Services"
        }
    ],
    "sg:phone":"+1   ",
    "sg:postcode":"06880",
    "sg:province":"CT",
    "wof:name":"Tobra Productions Ltd",
    "wof:placetype":"venue"
},
  "geometry": {"coordinates":[-73.37986600000001,41.177557],"type":"Point"}
}