{
  "type": "Feature",
  "properties": {
    "iso:country":"US",
    "sg:address":"1 Old Field Ln",
    "sg:city":"Weston",
    "sg:classifiers":[
        {
            "category":"Building & Trades",
            "subcategory":"Construction",
            "type":"Services"
        }
    ],
    "sg:phone":"+1 203 222 1319",
    "sg:postcode":"06883",
    "sg:province":"CT",
    "sg:tags":[
        "house"
    ],
    "wof:name":"Innovative Concepts In Design",
    "wof:placetype":"venue"
},
  "geometry": {"coordinates":[-73.386428,41.233678],"type":"Point"}
}