{
  "type": "Feature",
  "properties": {
    "iso:country":"US",
    "sg:address":"99 New Canaan Ave",
    "sg:city":"Norwalk",
    "sg:classifiers":[
        {
            "category":"Retail",
            "subcategory":"Laundry & Dry Cleaning",
            "type":"Services"
        }
    ],
    "sg:phone":"+1   ",
    "sg:postcode":"06850",
    "sg:province":"CT",
    "sg:tags":[
        "garment",
        "plant",
        "agent",
        "drycleaning"
    ],
    "wof:name":"Broad River Cleaners",
    "wof:placetype":"venue"
},
  "geometry": {"coordinates":[-73.434398,41.127655],"type":"Point"}
}