{
  "type": "Feature",
  "properties": {
    "addr:full":"31 Copplestone Rd Avon CT 06001",
    "addr:housenumber":"31",
    "addr:postcode":"06001",
    "addr:street":"Copplestone Rd",
    "iso:country":"US",
    "sg:address":"31 Copplestone Rd",
    "sg:city":"Avon",
    "sg:classifiers":[
        {
            "category":"Shopping",
            "subcategory":"Jewelry",
            "type":"Retail Goods"
        }
    ],
    "sg:phone":"+1 860 673 0039",
    "sg:postcode":"06001",
    "sg:province":"CT",
    "wof:name":"Acc Jewelers",
    "wof:placetype":"venue"
},
  "geometry": {"coordinates":[-72.86944099999999,41.77623],"type":"Point"}
}