{
  "type": "Feature",
  "properties": {
    "iso:country":"US",
    "sg:address":"41 Mayflower Dr",
    "sg:city":"Wilton",
    "sg:classifiers":[
        {
            "category":"Professional",
            "subcategory":"Computer Services",
            "type":"Services"
        }
    ],
    "sg:phone":"+1   ",
    "sg:postcode":"06897",
    "sg:province":"CT",
    "sg:tags":[
        "programing",
        "custom"
    ],
    "wof:name":"Computercare LLC",
    "wof:placetype":"venue"
},
  "geometry": {"coordinates":[-73.493908,41.234376],"type":"Point"}
}