{
  "type": "Feature",
  "properties": {
    "addr:full":"248 Palisado Ave Windsor CT 06095",
    "addr:housenumber":"248",
    "addr:postcode":"06095",
    "addr:street":"Palisado Ave",
    "iso:country":"US",
    "sg:address":"248 Palisado Ave",
    "sg:city":"Windsor",
    "sg:classifiers":[
        {
            "category":"Manufacturing",
            "subcategory":"Jewelry",
            "type":"Manufacturing & Wholesale Goods"
        }
    ],
    "sg:phone":"+1 860 285 0459",
    "sg:postcode":"06095",
    "sg:province":"CT",
    "sg:tags":[
        "pottery",
        "product",
        "ware",
        "mfg"
    ],
    "wof:name":"Alexander International LLC",
    "wof:placetype":"venue"
},
  "geometry": {"coordinates":[-72.63182999999999,41.8629],"type":"Point"}
}