{
  "type": "Feature",
  "properties": {
    "iso:country":"US",
    "sg:address":"156 Chatterton Way",
    "sg:city":"Hamden",
    "sg:classifiers":[
        {
            "category":"Building & Trades",
            "subcategory":"Construction",
            "type":"Services"
        }
    ],
    "sg:phone":"+1 203 641 0841",
    "sg:postcode":"06518",
    "sg:province":"CT",
    "sg:tags":[
        "repair",
        "handyman",
        "maintenance",
        "home"
    ],
    "wof:name":"Stan's Handyman Services",
    "wof:placetype":"venue"
},
  "geometry": {"coordinates":[-72.919177,41.434512],"type":"Point"}
}