{
  "type": "Feature",
  "properties": {
    "iso:country":"US",
    "sg:address":"117 Commerce St",
    "sg:city":"Glastonbury",
    "sg:classifiers":[
        {
            "category":"Retail",
            "subcategory":"Auto Repair",
            "type":"Services"
        }
    ],
    "sg:phone":"+1   ",
    "sg:postcode":"06033",
    "sg:province":"CT",
    "sg:tags":[
        "body",
        "shop"
    ],
    "wof:name":"Heritage Auto Body Inc",
    "wof:placetype":"venue"
},
  "geometry": {"coordinates":[-72.58957100000001,41.709479],"type":"Point"}
}