{
  "type": "Feature",
  "properties": {
    "iso:country":"US",
    "sg:address":"122 Prospect Hill Rd",
    "sg:city":"East Windsor",
    "sg:classifiers":[
        {
            "category":"Ice Cream",
            "type":"Food & Drink"
        }
    ],
    "sg:menulink":"http://www.allmenus.com/ct/east-windsor/99018-friendlys/menu/",
    "sg:phone":"+1 860 623 4450",
    "sg:postcode":"06088",
    "sg:province":"CT",
    "sg:tags":[
        "burger",
        "american"
    ],
    "wof:name":"Friendly's",
    "wof:placetype":"venue"
},
  "geometry": {"coordinates":[-72.605188,41.930737],"type":"Point"}
}