{
  "type": "Feature",
  "properties": {
    "addr:full":"21 Ridgewood Dr Redding CT 06896",
    "addr:housenumber":"21",
    "addr:postcode":"06896",
    "addr:street":"Ridgewood Dr",
    "iso:country":"US",
    "sg:address":"21 Ridgewood Dr",
    "sg:city":"Redding",
    "sg:classifiers":[
        {
            "category":"Professional",
            "subcategory":"Business Services",
            "type":"Services"
        }
    ],
    "sg:phone":"+1   ",
    "sg:postcode":"06896",
    "sg:province":"CT",
    "wof:name":"In Stitches",
    "wof:placetype":"venue"
},
  "geometry": {"coordinates":[-73.394766,41.327698],"type":"Point"}
}