{
  "type": "Feature",
  "properties": {
    "iso:country":"US",
    "sg:address":"12 Chapel Pl",
    "sg:city":"Danbury",
    "sg:classifiers":[
        {
            "category":"Health Services",
            "subcategory":"Doctor",
            "type":"Services"
        }
    ],
    "sg:phone":"+1 203 794 0464",
    "sg:postcode":"06810",
    "sg:province":"CT",
    "sg:tags":[
        "dentist"
    ],
    "wof:name":"Suzanne A Knox DDS",
    "wof:placetype":"venue"
},
  "geometry": {"coordinates":[-73.45322400000001,41.393991],"type":"Point"}
}