{
  "type": "Feature",
  "properties": {
    "addr:full":"14 Coolidge Rd Hartford CT 06117",
    "addr:housenumber":"14",
    "addr:postcode":"06117",
    "addr:street":"Coolidge Rd",
    "iso:country":"US",
    "sg:address":"14 Coolidge Rd",
    "sg:city":"Hartford",
    "sg:classifiers":[
        {
            "category":"Professional",
            "subcategory":"Lawyer & Legal Services",
            "type":"Services"
        }
    ],
    "sg:phone":"+1   ",
    "sg:postcode":"06117",
    "sg:province":"CT",
    "wof:name":"Rosenblit Mark S",
    "wof:placetype":"venue"
},
  "geometry": {"coordinates":[-72.757594,41.786224],"type":"Point"}
}