{
  "type": "Feature",
  "properties": {
    "addr:full":"6 Price Ave Norwalk CT 06854",
    "addr:housenumber":"6",
    "addr:postcode":"06854",
    "addr:street":"Price Ave",
    "iso:country":"US",
    "sg:address":"6 Price Ave",
    "sg:city":"Norwalk",
    "sg:classifiers":[
        {
            "category":"Building & Trades",
            "subcategory":"Landscaping Services",
            "type":"Services"
        }
    ],
    "sg:phone":"+1 203 852 6806",
    "sg:postcode":"06854",
    "sg:province":"CT",
    "sg:tags":[
        "garden"
    ],
    "wof:name":"Bruce S Pauley Tree Care Inc",
    "wof:placetype":"venue"
},
  "geometry": {"coordinates":[-73.435275,41.103685],"type":"Point"}
}