{
  "type": "Feature",
  "properties": {
    "addr:full":"641 Buckingham St Oakville CT 06779",
    "addr:housenumber":"641",
    "addr:postcode":"06779",
    "addr:street":"Buckingham St",
    "iso:country":"US",
    "sg:address":"641 Buckingham St",
    "sg:city":"Oakville",
    "sg:classifiers":[
        {
            "category":"Professional",
            "type":"Services"
        }
    ],
    "sg:phone":"+1 860 274 5751",
    "sg:postcode":"06779",
    "sg:province":"CT",
    "wof:name":"Westbury Drum Corps Inc",
    "wof:placetype":"venue"
},
  "geometry": {"coordinates":[-73.088525,41.603671],"type":"Point"}
}