{
  "type": "Feature",
  "properties": {
    "iso:country":"US",
    "sg:address":"266 Broad St",
    "sg:city":"Milford",
    "sg:classifiers":[
        {
            "category":"Professional",
            "subcategory":"Accounting & Tax Preparation",
            "type":"Services"
        }
    ],
    "sg:phone":"+1 203 874 1675",
    "sg:postcode":"06460",
    "sg:province":"CT",
    "sg:tags":[
        "accountant"
    ],
    "wof:name":"James A Scholfield & Co",
    "wof:placetype":"venue"
},
  "geometry": {"coordinates":[-73.063975,41.218149],"type":"Point"}
}