{
  "type": "Feature",
  "properties": {
    "iso:country":"US",
    "sg:address":"388 High St",
    "sg:city":"Naugatuck",
    "sg:classifiers":[
        {
            "category":"Organizations",
            "subcategory":"Community Association",
            "type":"Services"
        }
    ],
    "sg:phone":"+1   ",
    "sg:postcode":"06770",
    "sg:province":"CT",
    "wof:name":"Foe 640",
    "wof:placetype":"venue"
},
  "geometry": {"coordinates":[-73.049209,41.493631],"type":"Point"}
}