{
  "type": "Feature",
  "properties": {
    "iso:country":"US",
    "sg:address":"1855 Peck Ln",
    "sg:city":"Cheshire",
    "sg:classifiers":[
        {
            "category":"Manufacturing",
            "subcategory":"Retail Goods",
            "type":"Manufacturing & Wholesale Goods"
        }
    ],
    "sg:phone":"+1 203 271 9055",
    "sg:postcode":"06410",
    "sg:province":"CT",
    "sg:tags":[
        "equipment",
        "button"
    ],
    "sg:website":"www.waterburybutton.com",
    "wof:name":"Waterbury Button",
    "wof:placetype":"venue"
},
  "geometry": {"coordinates":[-72.903094,41.557931],"type":"Point"}
}