{
  "type": "Feature",
  "properties": {
    "addr:full":"38 Marshall Phelps Rd Windsor CT 06095",
    "addr:housenumber":"38",
    "addr:postcode":"06095",
    "addr:street":"Marshall Phelps Rd",
    "iso:country":"US",
    "sg:address":"38 Marshall Phelps Rd",
    "sg:city":"Windsor",
    "sg:classifiers":[
        {
            "category":"Wholesale",
            "subcategory":"Non-durable Goods",
            "type":"Manufacturing & Wholesale Goods"
        }
    ],
    "sg:phone":"+1 860 298 9681",
    "sg:postcode":"06095",
    "sg:province":"CT",
    "wof:name":"Designs Etc",
    "wof:placetype":"venue"
},
  "geometry": {"coordinates":[-72.68006,41.887353],"type":"Point"}
}