{
  "type": "Feature",
  "properties": {
    "addr:full":"129 Kreiger Ln Glastonbury CT 06033",
    "addr:housenumber":"129",
    "addr:postcode":"06033",
    "addr:street":"Kreiger Ln",
    "iso:country":"US",
    "sg:address":"129 Kreiger Ln",
    "sg:city":"Glastonbury",
    "sg:classifiers":[
        {
            "category":"Mining & Drilling",
            "type":"Manufacturing & Wholesale Goods"
        }
    ],
    "sg:phone":"+1 860 633 4649",
    "sg:postcode":"06033",
    "sg:province":"CT",
    "sg:tags":[
        "test",
        "boring"
    ],
    "wof:name":"New England Bring Contrs of CT",
    "wof:placetype":"venue"
},
  "geometry": {"coordinates":[-72.590615,41.706495],"type":"Point"}
}