{
  "type": "Feature",
  "properties": {
    "iso:country":"US",
    "sg:address":"51 Taylor Rd",
    "sg:city":"Hartford",
    "sg:classifiers":[
        {
            "category":"Recreation",
            "type":"Entertainment"
        }
    ],
    "sg:phone":"+1   ",
    "sg:postcode":"06110",
    "sg:province":"CT",
    "wof:name":"Able Body Conditioning LLC",
    "wof:placetype":"venue"
},
  "geometry": {"coordinates":[-72.730788,41.745774],"type":"Point"}
}