{
  "type": "Feature",
  "properties": {
    "addr:full":"71 Sweetbrier Trl Easton CT 06612",
    "addr:housenumber":"71",
    "addr:postcode":"06612",
    "addr:street":"Sweetbrier Trl",
    "iso:country":"US",
    "sg:address":"71 Sweetbrier Trl",
    "sg:city":"Easton",
    "sg:classifiers":[
        {
            "category":"Professional",
            "subcategory":"Lawyer & Legal Services",
            "type":"Services"
        }
    ],
    "sg:phone":"+1   ",
    "sg:postcode":"06612",
    "sg:province":"CT",
    "wof:name":"Mark A Smith",
    "wof:placetype":"venue"
},
  "geometry": {"coordinates":[-73.31009400000001,41.279765],"type":"Point"}
}