{
  "type": "Feature",
  "properties": {
    "addr:full":"9 Trowbridge Dr Bethel CT 06801",
    "addr:housenumber":"9",
    "addr:postcode":"06801",
    "addr:street":"Trowbridge Dr Bethel Ct",
    "iso:country":"US",
    "sg:address":"9 Trowbridge Dr",
    "sg:city":"Bethel",
    "sg:classifiers":[
        {
            "category":"Manufacturing",
            "subcategory":"Tools & Machinery",
            "type":"Manufacturing & Wholesale Goods"
        }
    ],
    "sg:phone":"+1 203 748 5122",
    "sg:postcode":"06801",
    "sg:province":"CT",
    "sg:tags":[
        "machine",
        "shop"
    ],
    "wof:name":"E & M Co",
    "wof:placetype":"venue"
},
  "geometry": {"coordinates":[-73.42071300000001,41.347698],"type":"Point"}
}