{
  "type": "Feature",
  "properties": {
    "addr:full":"100 Great Meadow Rd Wethersfield CT 06109",
    "addr:housenumber":"100",
    "addr:postcode":"06109",
    "addr:street":"Great Meadow Rd",
    "iso:country":"US",
    "sg:address":"100 Great Meadow Rd",
    "sg:city":"Wethersfield",
    "sg:classifiers":[
        {
            "category":"Banks & Credit Unions",
            "subcategory":"Bank",
            "type":"Services"
        }
    ],
    "sg:phone":"+1 860 721 7600",
    "sg:postcode":"06109",
    "sg:province":"CT",
    "sg:tags":[
        "mortgage"
    ],
    "wof:name":"GMAC",
    "wof:placetype":"venue"
},
  "geometry": {"coordinates":[-72.63992,41.708804],"type":"Point"}
}