{
  "type": "Feature",
  "properties": {
    "iso:country":"US",
    "sg:address":"44 Duffy St",
    "sg:city":"Stamford",
    "sg:classifiers":[
        {
            "category":"Building & Trades",
            "subcategory":"Cleaning & Sanitation",
            "type":"Services"
        }
    ],
    "sg:phone":"+1   ",
    "sg:postcode":"06902",
    "sg:province":"CT",
    "sg:tags":[
        "maintenance"
    ],
    "wof:name":"Gladys Nice Cleaning Service",
    "wof:placetype":"venue"
},
  "geometry": {"coordinates":[-73.51415799999999,41.050946],"type":"Point"}
}