{
  "type": "Feature",
  "properties": {
    "addr:full":"17 Connecticut Ave Danbury CT 06810",
    "addr:housenumber":"17",
    "addr:postcode":"06810",
    "addr:street":"Connecticut Ave",
    "iso:country":"US",
    "sg:address":"17 Connecticut Ave",
    "sg:city":"Danbury",
    "sg:classifiers":[
        {
            "category":"Real Estate",
            "subcategory":"Architect",
            "type":"Services"
        }
    ],
    "sg:phone":"+1   ",
    "sg:postcode":"06810",
    "sg:province":"CT",
    "sg:tags":[
        "architectural"
    ],
    "wof:name":"Ime Building Design Service",
    "wof:placetype":"venue"
},
  "geometry": {"coordinates":[-73.46283200000001,41.382807],"type":"Point"}
}