{
  "type": "Feature",
  "properties": {
    "addr:full":"79 Cedar St Branford CT 06405",
    "addr:housenumber":"79",
    "addr:postcode":"06405",
    "addr:street":"Cedar St",
    "iso:country":"US",
    "sg:address":"79 Cedar St",
    "sg:city":"Branford",
    "sg:classifiers":[
        {
            "category":"Health Services",
            "subcategory":"Clinic",
            "type":"Services"
        }
    ],
    "sg:phone":"+1   ",
    "sg:postcode":"06405",
    "sg:province":"CT",
    "sg:tags":[
        "mental"
    ],
    "wof:name":"Harbor House",
    "wof:placetype":"venue"
},
  "geometry": {"coordinates":[-72.815437,41.282871],"type":"Point"}
}