{
  "type": "Feature",
  "properties": {
    "iso:country":"US",
    "sg:address":"518 Boston Post Rd",
    "sg:city":"Orange",
    "sg:classifiers":[
        {
            "category":"Retail",
            "subcategory":"Photofinishing",
            "type":"Services"
        }
    ],
    "sg:phone":"+1   ",
    "sg:postcode":"06477",
    "sg:province":"CT",
    "sg:tags":[
        "development",
        "hour",
        "photo",
        "processing",
        "lab",
        "one"
    ],
    "wof:name":"Photoland",
    "wof:placetype":"venue"
},
  "geometry": {"coordinates":[-73.014706,41.256424],"type":"Point"}
}