{
  "type": "Feature",
  "properties": {
    "addr:full":"807 Boston Post Rd Milford CT 06460",
    "addr:housenumber":"807",
    "addr:postcode":"06460",
    "addr:street":"Boston Post Rd",
    "iso:country":"US",
    "sg:address":"807 Boston Post Rd",
    "sg:city":"Milford",
    "sg:classifiers":[
        {
            "category":"Building & Trades",
            "subcategory":"Construction",
            "type":"Services"
        }
    ],
    "sg:phone":"+1 203 877 5685",
    "sg:postcode":"06460",
    "sg:province":"CT",
    "sg:tags":[
        "glazing",
        "contractor"
    ],
    "wof:name":"Custom Glass & Mirror",
    "wof:placetype":"venue"
},
  "geometry": {"coordinates":[-73.055063,41.232307],"type":"Point"}
}