{
  "type": "Feature",
  "properties": {
    "addr:full":"375 State Hwy 12 Groton CT 06340",
    "addr:housenumber":"375",
    "addr:postcode":"06340",
    "addr:street":"State Hwy 12 Groton Ct",
    "iso:country":"US",
    "sg:address":"375 State Hwy 12",
    "sg:city":"Groton",
    "sg:classifiers":[
        {
            "category":"Building & Trades",
            "subcategory":"Equipment Rental",
            "type":"Services"
        }
    ],
    "sg:phone":"+1   ",
    "sg:postcode":"06340",
    "sg:province":"CT",
    "wof:name":"Ryder Consumer Truck Rental",
    "wof:placetype":"venue"
},
  "geometry": {"coordinates":[-72.07135700000001,41.370087],"type":"Point"}
}