{
  "type": "Feature",
  "properties": {
    "addr:full":"7 Tods Driftway Old Greenwich CT 06870",
    "addr:housenumber":"7",
    "addr:postcode":"06870",
    "addr:street":"Tods Driftway",
    "iso:country":"US",
    "sg:address":"7 Tods Driftway",
    "sg:city":"Old Greenwich",
    "sg:classifiers":[
        {
            "category":"Professional",
            "subcategory":"Management & Consulting",
            "type":"Services"
        }
    ],
    "sg:phone":"+1   ",
    "sg:postcode":"06870",
    "sg:province":"CT",
    "wof:name":"Cove Capital Corp",
    "wof:placetype":"venue"
},
  "geometry": {"coordinates":[-73.582438,41.003815],"type":"Point"}
}