{
  "type": "Feature",
  "properties": {
    "addr:full":"804 Neipsic Rd Glastonbury CT 06033",
    "addr:housenumber":"804",
    "addr:postcode":"06033",
    "addr:street":"Neipsic Rd",
    "iso:country":"US",
    "sg:address":"804 Neipsic Rd",
    "sg:city":"Glastonbury",
    "sg:classifiers":[
        {
            "category":"Professional",
            "subcategory":"Management & Consulting",
            "type":"Services"
        }
    ],
    "sg:phone":"+1   ",
    "sg:postcode":"06033",
    "sg:province":"CT",
    "sg:tags":[
        "business"
    ],
    "wof:name":"Counterbalance Consulting LLC",
    "wof:placetype":"venue"
},
  "geometry": {"coordinates":[-72.55448699999999,41.698518],"type":"Point"}
}