{
  "type": "Feature",
  "properties": {
    "addr:full":"14 Crawford Rd Westport CT 06880",
    "addr:housenumber":"14",
    "addr:postcode":"06880",
    "addr:street":"Crawford Rd",
    "iso:country":"US",
    "sg:address":"14 Crawford Rd",
    "sg:city":"Westport",
    "sg:classifiers":[
        {
            "category":"Professional",
            "type":"Services"
        }
    ],
    "sg:phone":"+1   ",
    "sg:postcode":"06880",
    "sg:province":"CT",
    "wof:name":"Kellerman Communications",
    "wof:placetype":"venue"
},
  "geometry": {"coordinates":[-73.38436299999999,41.155272],"type":"Point"}
}