{
  "type": "Feature",
  "properties": {
    "addr:full":"544 Reidville Dr Waterbury CT 06705",
    "addr:housenumber":"544",
    "addr:postcode":"06705",
    "addr:street":"Reidville Dr",
    "iso:country":"US",
    "sg:address":"544 Reidville Dr",
    "sg:city":"Waterbury",
    "sg:classifiers":[
        {
            "category":"Ice Cream",
            "type":"Food & Drink"
        }
    ],
    "sg:menulink":"http://www.allmenus.com/ct/waterbury/99031-friendlys/menu/",
    "sg:phone":"+1 203 574 1244",
    "sg:postcode":"06705",
    "sg:province":"CT",
    "sg:tags":[
        "burger",
        "american"
    ],
    "wof:name":"Friendly's",
    "wof:placetype":"venue"
},
  "geometry": {"coordinates":[-72.996337,41.539823],"type":"Point"}
}