{
  "type": "Feature",
  "properties": {
    "iso:country":"US",
    "sg:address":"50 Gillies Ln",
    "sg:city":"Norwalk",
    "sg:classifiers":[
        {
            "category":"Professional",
            "type":"Services"
        }
    ],
    "sg:phone":"+1 203 838 3695",
    "sg:postcode":"06854",
    "sg:province":"CT",
    "wof:name":"Holman LLC",
    "wof:placetype":"venue"
},
  "geometry": {"coordinates":[-73.44083999999999,41.106962],"type":"Point"}
}