{
  "type": "Feature",
  "properties": {
    "iso:country":"US",
    "sg:address":"27 Woodlawn Dr",
    "sg:city":"Trumbull",
    "sg:classifiers":[
        {
            "category":"Wholesale",
            "subcategory":"Stationery",
            "type":"Manufacturing & Wholesale Goods"
        }
    ],
    "sg:phone":"+1 203 268 1333",
    "sg:postcode":"06611",
    "sg:province":"CT",
    "sg:tags":[
        "printing",
        "representative",
        "graphics"
    ],
    "wof:name":"Bill Wagner & Co",
    "wof:placetype":"venue"
},
  "geometry": {"coordinates":[-73.21045100000001,41.251663],"type":"Point"}
}