{
  "type": "Feature",
  "properties": {
    "addr:full":"275 Union Ave Bridgeport CT 06607",
    "addr:housenumber":"275",
    "addr:postcode":"06607",
    "addr:street":"Union Ave",
    "iso:country":"US",
    "sg:address":"275 Union Ave",
    "sg:city":"Bridgeport",
    "sg:classifiers":[
        {
            "category":"Organizations",
            "subcategory":"Religious Organization",
            "type":"Services"
        }
    ],
    "sg:phone":"+1 203 333 1202",
    "sg:postcode":"06607",
    "sg:province":"CT",
    "sg:tags":[
        "church"
    ],
    "wof:name":"Blessed Sacrament RC Church",
    "wof:placetype":"venue"
},
  "geometry": {"coordinates":[-73.16418,41.176931],"type":"Point"}
}