{
  "type": "Feature",
  "properties": {
    "iso:country":"US",
    "sg:address":"204 W Newberry Rd",
    "sg:city":"Bloomfield",
    "sg:classifiers":[
        {
            "category":"Government",
            "subcategory":"Office",
            "type":"Public Place"
        }
    ],
    "sg:phone":"+1 860 243 0148",
    "sg:postcode":"06002",
    "sg:province":"CT",
    "sg:tags":[
        "station",
        "inspection",
        "vehicle"
    ],
    "wof:name":"Connecticut Emissions Station",
    "wof:placetype":"venue"
},
  "geometry": {"coordinates":[-72.73595,41.868852],"type":"Point"}
}