{
  "type": "Feature",
  "properties": {
    "addr:full":"511 Kitemaug Rd Uncasville CT 06382",
    "addr:housenumber":"511",
    "addr:postcode":"06382",
    "addr:street":"Kitemaug Rd Uncasville Ct",
    "iso:country":"US",
    "sg:address":"511 Kitemaug Rd",
    "sg:city":"Uncasville",
    "sg:classifiers":[
        {
            "category":"Personal",
            "subcategory":"Beauty Salon",
            "type":"Services"
        }
    ],
    "sg:phone":"+1   ",
    "sg:postcode":"06382",
    "sg:province":"CT",
    "sg:tags":[
        "shop"
    ],
    "wof:name":"Hair Affair",
    "wof:placetype":"venue"
},
  "geometry": {"coordinates":[-72.08866500000001,41.449797],"type":"Point"}
}