{
  "type": "Feature",
  "properties": {
    "iso:country":"US",
    "sg:address":"297 Thomaston Ave",
    "sg:city":"Waterbury",
    "sg:classifiers":[
        {
            "category":"Retail",
            "subcategory":"Auto Repair",
            "type":"Services"
        }
    ],
    "sg:phone":"+1   ",
    "sg:postcode":"06702",
    "sg:province":"CT",
    "sg:tags":[
        "body"
    ],
    "wof:name":"West End Auto Body Shop",
    "wof:placetype":"venue"
},
  "geometry": {"coordinates":[-73.05335599999999,41.5607],"type":"Point"}
}