{
  "type": "Feature",
  "properties": {
    "addr:full":"500 Waterfront St New Haven CT 06512",
    "addr:housenumber":"500",
    "addr:postcode":"06512",
    "addr:street":"Waterfront St",
    "iso:country":"US",
    "sg:address":"500 Waterfront St",
    "sg:city":"New Haven",
    "sg:classifiers":[
        {
            "category":"Travel",
            "subcategory":"Travel Agent",
            "type":"Entertainment"
        }
    ],
    "sg:phone":"+1 203 466 8063",
    "sg:postcode":"06512",
    "sg:province":"CT",
    "sg:tags":[
        "agency",
        "steamship"
    ],
    "wof:name":"Northern Star Shipping Agency",
    "wof:placetype":"venue"
},
  "geometry": {"coordinates":[-72.902727,41.29108],"type":"Point"}
}