{
  "type": "Feature",
  "properties": {
    "iso:country":"US",
    "sg:address":"325 White Birch Dr",
    "sg:city":"Guilford",
    "sg:classifiers":[
        {
            "category":"Professional",
            "subcategory":"Management & Consulting",
            "type":"Services"
        }
    ],
    "sg:phone":"+1   ",
    "sg:postcode":"06437",
    "sg:province":"CT",
    "sg:tags":[
        "business"
    ],
    "wof:name":"Stephen Joyce",
    "wof:placetype":"venue"
},
  "geometry": {"coordinates":[-72.680359,41.324894],"type":"Point"}
}