{
  "type": "Feature",
  "properties": {
    "addr:full":"324 Elm St Monroe CT 06468",
    "addr:housenumber":"324",
    "addr:postcode":"06468",
    "addr:street":"Elm St",
    "iso:country":"US",
    "sg:address":"324 Elm St",
    "sg:city":"Monroe",
    "sg:classifiers":[
        {
            "category":"Wholesale",
            "subcategory":"Durable Goods & Equipment",
            "type":"Manufacturing & Wholesale Goods"
        }
    ],
    "sg:phone":"+1 203 452 9570",
    "sg:postcode":"06468",
    "sg:province":"CT",
    "sg:tags":[
        "representative",
        "manufacturer"
    ],
    "wof:name":"Santa's Best Craft LTD",
    "wof:placetype":"venue"
},
  "geometry": {"coordinates":[-73.218521,41.314356],"type":"Point"}
}