{
  "type": "Feature",
  "properties": {
    "addr:full":"1 Washington Hill Newtown CT 06470",
    "addr:housenumber":"1",
    "addr:postcode":"06470",
    "addr:street":"Washington",
    "iso:country":"US",
    "sg:address":"1 Washington Hill",
    "sg:city":"Newtown",
    "sg:classifiers":[
        {
            "category":"Professional",
            "subcategory":"Lawyer & Legal Services",
            "type":"Services"
        }
    ],
    "sg:phone":"+1 203 270 9272",
    "sg:postcode":"06470",
    "sg:province":"CT",
    "sg:tags":[
        "attorney"
    ],
    "wof:name":"Emmett & Glander",
    "wof:placetype":"venue"
},
  "geometry": {"coordinates":[-73.321939,41.417667],"type":"Point"}
}