{
  "type": "Feature",
  "properties": {
    "iso:country":"US",
    "sg:address":"9 Linden Ln",
    "sg:city":"Madison",
    "sg:classifiers":[
        {
            "category":"Manufacturing",
            "subcategory":"Printing",
            "type":"Manufacturing & Wholesale Goods"
        }
    ],
    "sg:phone":"+1 203 245 5174",
    "sg:postcode":"06443",
    "sg:province":"CT",
    "sg:tags":[
        "publisher"
    ],
    "wof:name":"Fence Creek Publishing",
    "wof:placetype":"venue"
},
  "geometry": {"coordinates":[-72.589916,41.271458],"type":"Point"}
}