{
  "type": "Feature",
  "properties": {
    "addr:full":"33 Great Neck Rd Waterford CT 06385",
    "addr:housenumber":"33",
    "addr:postcode":"06385",
    "addr:street":"Great Neck Rd",
    "iso:country":"US",
    "sg:address":"33 Great Neck Rd",
    "sg:city":"Waterford",
    "sg:classifiers":[
        {
            "category":"Professional",
            "subcategory":"Accounting & Tax Preparation",
            "type":"Services"
        }
    ],
    "sg:phone":"+1   ",
    "sg:postcode":"06385",
    "sg:province":"CT",
    "sg:tags":[
        "return"
    ],
    "wof:name":"Perfect Papers",
    "wof:placetype":"venue"
},
  "geometry": {"coordinates":[-72.135943,41.334645],"type":"Point"}
}