{
  "type": "Feature",
  "properties": {
    "addr:full":"7 Crown St Naugatuck CT 06770",
    "addr:housenumber":"7",
    "addr:postcode":"06770",
    "addr:street":"Crown St Naugatuck Ct",
    "iso:country":"US",
    "sg:address":"7 Crown St",
    "sg:city":"Naugatuck",
    "sg:classifiers":[
        {
            "category":"Building & Trades",
            "subcategory":"Landscaping Services",
            "type":"Services"
        }
    ],
    "sg:phone":"+1 203 509 5248",
    "sg:postcode":"06770",
    "sg:province":"CT",
    "sg:tags":[
        "tree"
    ],
    "wof:name":"Bellemare Stump Grinding",
    "wof:placetype":"venue"
},
  "geometry": {"coordinates":[-73.054317,41.501498],"type":"Point"}
}