{
  "type": "Feature",
  "properties": {
    "addr:full":"85 Scoville Ore Mine Rd Salisbury CT 06068",
    "addr:housenumber":"85",
    "addr:postcode":"06068",
    "addr:street":"Scoville Ore Mine Rd",
    "iso:country":"US",
    "sg:address":"85 Scoville Ore Mine Rd",
    "sg:city":"Salisbury",
    "sg:classifiers":[
        {
            "category":"Banks & Credit Unions",
            "subcategory":"Investment Brokerage",
            "type":"Services"
        }
    ],
    "sg:phone":"+1 860 435 1058",
    "sg:postcode":"06068",
    "sg:province":"CT",
    "sg:tags":[
        "security"
    ],
    "wof:name":"Bruce D Janelli",
    "wof:placetype":"venue"
},
  "geometry": {"coordinates":[-73.443102,42.013765],"type":"Point"}
}