{
  "type": "Feature",
  "properties": {
    "iso:country":"US",
    "sg:address":"430 Main Ave",
    "sg:city":"Norwalk",
    "sg:classifiers":[
        {
            "category":"Restaurant",
            "type":"Food & Drink"
        }
    ],
    "sg:phone":"+1 203 847 1003",
    "sg:postcode":"06851",
    "sg:province":"CT",
    "sg:tags":[
        "delicatessen"
    ],
    "wof:name":"M & M Deli & Grille",
    "wof:placetype":"venue"
},
  "geometry": {"coordinates":[-73.426334,41.146507],"type":"Point"}
}