{
  "type": "Feature",
  "properties": {
    "addr:full":"82 Harold Dr Newington CT 06111",
    "addr:housenumber":"82",
    "addr:postcode":"06111",
    "addr:street":"Harold Dr",
    "iso:country":"US",
    "sg:address":"82 Harold Dr",
    "sg:city":"Newington",
    "sg:classifiers":[
        {
            "category":"Real Estate",
            "subcategory":"Real Estate Agent",
            "type":"Services"
        }
    ],
    "sg:phone":"+1 860 666 2318",
    "sg:postcode":"06111",
    "sg:province":"CT",
    "wof:name":"Raiche Associates",
    "wof:placetype":"venue"
},
  "geometry": {"coordinates":[-72.705946,41.684606],"type":"Point"}
}