{
  "type": "Feature",
  "properties": {
    "addr:full":"509 Boston St Guilford CT 06437",
    "addr:housenumber":"509",
    "addr:postcode":"06437",
    "addr:street":"Boston St",
    "iso:country":"US",
    "sg:address":"509 Boston St",
    "sg:city":"Guilford",
    "sg:classifiers":[
        {
            "category":"Building & Trades",
            "subcategory":"Construction",
            "type":"Services"
        }
    ],
    "sg:phone":"+1 203 458 9985",
    "sg:postcode":"06437",
    "sg:province":"CT",
    "sg:tags":[
        "general",
        "contractor"
    ],
    "wof:name":"Fogarty Brother Remodel/Constr",
    "wof:placetype":"venue"
},
  "geometry": {"coordinates":[-72.66977799999999,41.286715],"type":"Point"}
}