{
  "type": "Feature",
  "properties": {
    "addr:full":"90 Grove St Ridgefield CT 06877",
    "addr:housenumber":"90",
    "addr:postcode":"06877",
    "addr:street":"Grove St",
    "iso:country":"US",
    "sg:address":"90 Grove St",
    "sg:city":"Ridgefield",
    "sg:classifiers":[
        {
            "category":"Professional",
            "type":"Services"
        }
    ],
    "sg:phone":"+1 203 438 6483",
    "sg:postcode":"06877",
    "sg:province":"CT",
    "sg:tags":[
        "establishment"
    ],
    "wof:name":"CMG LLC",
    "wof:placetype":"venue"
},
  "geometry": {"coordinates":[-73.496943,41.289618],"type":"Point"}
}