{
  "type": "Feature",
  "properties": {
    "iso:country":"US",
    "sg:address":"45 Field Point Rd",
    "sg:city":"Greenwich",
    "sg:classifiers":[
        {
            "category":"Real Estate",
            "subcategory":"Real Estate Agent",
            "type":"Services"
        }
    ],
    "sg:phone":"+1 203 869 9797",
    "sg:postcode":"06830",
    "sg:province":"CT",
    "wof:name":"Joseph Barbieri",
    "wof:placetype":"venue"
},
  "geometry": {"coordinates":[-73.62911200000001,41.028119],"type":"Point"}
}