{
  "type": "Feature",
  "properties": {
    "iso:country":"US",
    "sg:address":"327 N Colony St",
    "sg:city":"Wallingford",
    "sg:classifiers":[
        {
            "category":"Wholesale",
            "subcategory":"Non-durable Goods",
            "type":"Manufacturing & Wholesale Goods"
        },
        {
            "category":"Shopping",
            "subcategory":"Crafts & Fabrics",
            "type":"Retail Goods"
        }
    ],
    "sg:phone":"+1 203 269 6662",
    "sg:postcode":"06492",
    "sg:province":"CT",
    "sg:tags":[
        "sewing",
        "yarn"
    ],
    "wof:name":"Country Yarns",
    "wof:placetype":"venue"
},
  "geometry": {"coordinates":[-72.820932,41.462057],"type":"Point"}
}