{
  "type": "Feature",
  "properties": {
    "addr:full":"239 Glenville Rd Greenwich NY 06831",
    "addr:housenumber":"239",
    "addr:postcode":"06831",
    "addr:street":"Glenville Rd",
    "iso:country":"US",
    "sg:address":"239 Glenville Rd",
    "sg:city":"Greenwich",
    "sg:classifiers":[
        {
            "category":"Health Services",
            "subcategory":"Doctor",
            "type":"Services"
        }
    ],
    "sg:phone":"+1 203 532 0600",
    "sg:postcode":"06831",
    "sg:province":"NY",
    "sg:tags":[
        "specializing",
        "physician",
        "surgeon",
        "oncology"
    ],
    "wof:name":"Integrative Oncology LLC",
    "wof:placetype":"venue"
},
  "geometry": {"coordinates":[-73.662431,41.037765],"type":"Point"}
}