{
  "type": "Feature",
  "properties": {
    "addr:full":"16 Windsor Rd E North Haven CT 06473",
    "addr:housenumber":"16",
    "addr:postcode":"06473",
    "addr:street":"Windsor Rd E North Haven Ct",
    "iso:country":"US",
    "sg:address":"16 Windsor Rd E",
    "sg:city":"North Haven",
    "sg:classifiers":[
        {
            "category":"Manufacturing",
            "subcategory":"Printing",
            "type":"Manufacturing & Wholesale Goods"
        }
    ],
    "sg:phone":"+1 203 230 2391",
    "sg:postcode":"06473",
    "sg:province":"CT",
    "sg:tags":[
        "publisher"
    ],
    "wof:name":"Catbird Press",
    "wof:placetype":"venue"
},
  "geometry": {"coordinates":[-72.889174,41.374045],"type":"Point"}
}