{
  "type": "Feature",
  "properties": {
    "iso:country":"US",
    "sg:address":"30 Barry Dr",
    "sg:city":"Gales Ferry",
    "sg:classifiers":[
        {
            "category":"Professional",
            "subcategory":"Management & Consulting",
            "type":"Services"
        }
    ],
    "sg:phone":"+1   ",
    "sg:postcode":"06335",
    "sg:province":"CT",
    "sg:tags":[
        "test",
        "computer",
        "evaluation"
    ],
    "wof:name":"Responsive Technical Services",
    "wof:placetype":"venue"
},
  "geometry": {"coordinates":[-72.08113299999999,41.418995],"type":"Point"}
}