{
  "type": "Feature",
  "properties": {
    "iso:country":"US",
    "sg:address":"3320 Dixwell Ave",
    "sg:city":"North Haven",
    "sg:classifiers":[
        {
            "category":"Banks & Credit Unions",
            "subcategory":"Investment Brokerage",
            "type":"Services"
        }
    ],
    "sg:phone":"+1 203 288 4039",
    "sg:postcode":"06473",
    "sg:province":"CT",
    "sg:tags":[
        "consultant",
        "planning",
        "financial"
    ],
    "wof:name":"Benefit Plans Inc",
    "wof:placetype":"venue"
},
  "geometry": {"coordinates":[-72.89140399999999,41.382398],"type":"Point"}
}