{
  "type": "Feature",
  "properties": {
    "addr:full":"15 Cowles St Milford CT 06461",
    "addr:housenumber":"15",
    "addr:postcode":"06461",
    "addr:street":"Cowles St",
    "iso:country":"US",
    "sg:address":"15 Cowles St",
    "sg:city":"Milford",
    "sg:classifiers":[
        {
            "category":"Wholesale",
            "subcategory":"Auto Parts",
            "type":"Manufacturing & Wholesale Goods"
        }
    ],
    "sg:phone":"+1 203 876 9464",
    "sg:postcode":"06461",
    "sg:province":"CT",
    "wof:name":"Dons Precision Manufacturing",
    "wof:placetype":"venue"
},
  "geometry": {"coordinates":[-73.09683699999999,41.204586],"type":"Point"}
}