{
  "type": "Feature",
  "properties": {
    "addr:full":"134 Round Hill Rd Fairfield CT 06473",
    "addr:housenumber":"134",
    "addr:postcode":"06473",
    "addr:street":"Round Hill Rd",
    "iso:country":"US",
    "sg:address":"134 Round Hill Rd",
    "sg:city":"Fairfield",
    "sg:classifiers":[
        {
            "category":"Health Services",
            "subcategory":"Doctor",
            "type":"Services"
        }
    ],
    "sg:phone":"+1   ",
    "sg:postcode":"06473",
    "sg:province":"CT",
    "sg:tags":[
        "medical"
    ],
    "wof:name":"Molloy Dafcik & Kryspin",
    "wof:placetype":"venue"
},
  "geometry": {"coordinates":[-72.895347,41.377095],"type":"Point"}
}