{
  "type": "Feature",
  "properties": {
    "addr:full":"6 Morris St West Haven CT 06516",
    "addr:housenumber":"6",
    "addr:postcode":"06516",
    "addr:street":"Morris St;Haven",
    "iso:country":"US",
    "sg:address":"6 Morris St",
    "sg:city":"West Haven",
    "sg:classifiers":[
        {
            "category":"Government",
            "subcategory":"Office",
            "type":"Public Place"
        }
    ],
    "sg:phone":"+1 203 933 2428",
    "sg:postcode":"06516",
    "sg:province":"CT",
    "wof:name":"Representative RV Collins",
    "wof:placetype":"venue"
},
  "geometry": {"coordinates":[-72.936773,41.261402],"type":"Point"}
}