{
  "type": "Feature",
  "properties": {
    "addr:full":"25 Golden Rd Mystic CT 06355",
    "addr:housenumber":"25",
    "addr:postcode":"06355",
    "addr:street":"Golden Rd",
    "iso:country":"US",
    "sg:address":"25 Golden Rd",
    "sg:city":"Mystic",
    "sg:classifiers":[
        {
            "category":"Professional",
            "type":"Services"
        }
    ],
    "sg:phone":"+1 860 572 9872",
    "sg:postcode":"06355",
    "sg:province":"CT",
    "wof:name":"Daughters of Isabella",
    "wof:placetype":"venue"
},
  "geometry": {"coordinates":[-71.950613,41.356082],"type":"Point"}
}