{
  "type": "Feature",
  "properties": {
    "iso:country":"US",
    "sg:address":"8 Burr Ave",
    "sg:city":"Middletown",
    "sg:classifiers":[
        {
            "category":"Personal",
            "subcategory":"Barber",
            "type":"Services"
        }
    ],
    "sg:phone":"+1   ",
    "sg:postcode":"06457",
    "sg:province":"CT",
    "sg:tags":[
        "shop",
        "beauty"
    ],
    "wof:name":"A1 Hair Styles",
    "wof:placetype":"venue"
},
  "geometry": {"coordinates":[-72.64834500000001,41.551498],"type":"Point"}
}