{
  "type": "Feature",
  "properties": {
    "addr:full":"30 Friendlee Ln Wilton CT 06897",
    "addr:housenumber":"30",
    "addr:postcode":"06897",
    "addr:street":"Friendlee Ln",
    "iso:country":"US",
    "sg:address":"30 Friendlee Ln",
    "sg:city":"Wilton",
    "sg:classifiers":[
        {
            "category":"Travel",
            "subcategory":"Hotels & Motels",
            "type":"Entertainment"
        }
    ],
    "sg:phone":"+1   ",
    "sg:postcode":"06897",
    "sg:province":"CT",
    "sg:tags":[
        "operation"
    ],
    "wof:name":"Sixpence",
    "wof:placetype":"venue"
},
  "geometry": {"coordinates":[-73.413978,41.202158],"type":"Point"}
}