{
  "type": "Feature",
  "properties": {
    "iso:country":"US",
    "sg:address":"14 Park St",
    "sg:city":"Thomaston",
    "sg:classifiers":[
        {
            "category":"Social Services",
            "subcategory":"Child Care",
            "type":"Services"
        }
    ],
    "sg:phone":"+1   ",
    "sg:postcode":"06787",
    "sg:province":"CT",
    "sg:tags":[
        "day"
    ],
    "wof:name":"Angels 4 Kidz Learning Center",
    "wof:placetype":"venue"
},
  "geometry": {"coordinates":[-73.07159299999999,41.67285],"type":"Point"}
}