{
  "type": "Feature",
  "properties": {
    "iso:country":"US",
    "sg:address":"1943 Broad St",
    "sg:city":"Hartford",
    "sg:classifiers":[
        {
            "category":"Restaurant",
            "type":"Food & Drink"
        }
    ],
    "sg:phone":"+1 860 956 9260",
    "sg:postcode":"06114",
    "sg:province":"CT",
    "sg:tags":[
        "eating"
    ],
    "wof:name":"Albaniam Brothers Cafe",
    "wof:placetype":"venue"
},
  "geometry": {"coordinates":[-72.687285,41.739664],"type":"Point"}
}