{
  "type": "Feature",
  "properties": {
    "addr:full":"60 Charter Oak Ave Hartford CT 06106",
    "addr:housenumber":"60",
    "addr:postcode":"06106",
    "addr:street":"Charter Oak Ave;Ct",
    "iso:country":"US",
    "sg:address":"60 Charter Oak Ave",
    "sg:city":"Hartford",
    "sg:classifiers":[
        {
            "category":"Organizations",
            "subcategory":"Community Association",
            "type":"Services"
        }
    ],
    "sg:phone":"+1   ",
    "sg:postcode":"06106",
    "sg:province":"CT",
    "sg:tags":[
        "club",
        "ethnic"
    ],
    "wof:name":"Polish National Hm of Hartford",
    "wof:placetype":"venue"
},
  "geometry": {"coordinates":[-72.673404,41.759445],"type":"Point"}
}