{
  "type": "Feature",
  "properties": {
    "addr:full":"212 New London Tpke Glastonbury CT 06033",
    "addr:housenumber":"212",
    "addr:postcode":"06033",
    "addr:street":"New London Tpke",
    "iso:country":"US",
    "sg:address":"212 New London Tpke",
    "sg:city":"Glastonbury",
    "sg:classifiers":[
        {
            "category":"Health Services",
            "subcategory":"Optometrist",
            "type":"Services"
        }
    ],
    "sg:phone":"+1   ",
    "sg:postcode":"06033",
    "sg:province":"CT",
    "wof:name":"Susan C Danberg Od PC",
    "wof:placetype":"venue"
},
  "geometry": {"coordinates":[-72.602464,41.709075],"type":"Point"}
}