{
  "type": "Feature",
  "properties": {
    "addr:full":"158 4th Ave Milford CT 06460",
    "addr:housenumber":"158",
    "addr:postcode":"06460",
    "addr:street":"4Th Ave",
    "iso:country":"US",
    "sg:address":"158 4th Ave",
    "sg:city":"Milford",
    "sg:classifiers":[
        {
            "category":"Professional",
            "subcategory":"Accounting & Tax Preparation",
            "type":"Services"
        }
    ],
    "sg:phone":"+1 203 878 5505",
    "sg:postcode":"06460",
    "sg:province":"CT",
    "sg:tags":[
        "accountant",
        "return"
    ],
    "wof:name":"Accounting & Tax Services Inc",
    "wof:placetype":"venue"
},
  "geometry": {"coordinates":[-73.094174,41.182192],"type":"Point"}
}