{
  "type": "Feature",
  "properties": {
    "addr:full":"8 Obtuse Hill Rd Brookfield CT 06804",
    "addr:housenumber":"8",
    "addr:postcode":"06804",
    "addr:street":"Obtuse Hill Rd",
    "iso:country":"US",
    "sg:address":"8 Obtuse Hill Rd",
    "sg:city":"Brookfield",
    "sg:classifiers":[
        {
            "category":"Education",
            "subcategory":"School",
            "type":"Public Place"
        }
    ],
    "sg:phone":"+1 203 775 7650",
    "sg:postcode":"06804",
    "sg:province":"CT",
    "wof:name":"Center Elementary School",
    "wof:placetype":"venue"
},
  "geometry": {"coordinates":[-73.382547,41.468357],"type":"Point"}
}