{
  "type": "Feature",
  "properties": {
    "addr:full":"245 West St Seymour CT 06483",
    "addr:housenumber":"245",
    "addr:postcode":"06483",
    "addr:street":"West St",
    "iso:country":"US",
    "sg:address":"245 West St",
    "sg:city":"Seymour",
    "sg:classifiers":[
        {
            "category":"Health Services",
            "subcategory":"Doctor",
            "type":"Services"
        }
    ],
    "sg:phone":"+1   ",
    "sg:postcode":"06483",
    "sg:province":"CT",
    "wof:name":"Frederick W Rohwedder DMD",
    "wof:placetype":"venue"
},
  "geometry": {"coordinates":[-73.08429,41.395748],"type":"Point"}
}