{
  "type": "Feature",
  "properties": {
    "addr:full":"278 Oxford Rd Oxford CT 06478",
    "addr:housenumber":"278",
    "addr:postcode":"06478",
    "addr:street":"Oxford Rd",
    "iso:country":"US",
    "sg:address":"278 Oxford Rd",
    "sg:city":"Oxford",
    "sg:classifiers":[
        {
            "category":"Home & Garden",
            "subcategory":"Building Materials",
            "type":"Retail Goods"
        }
    ],
    "sg:phone":"+1 203 881 9325",
    "sg:postcode":"06478",
    "sg:province":"CT",
    "sg:tags":[
        "mixed",
        "concrete"
    ],
    "sg:website":"www.haynesconstruction.com",
    "wof:name":"Haynes Aggregate",
    "wof:placetype":"venue"
},
  "geometry": {"coordinates":[-73.108779,41.422886],"type":"Point"}
}