{
  "type": "Feature",
  "properties": {
    "addr:full":"781 Whalley Ave New Haven CT 06515",
    "addr:housenumber":"781",
    "addr:postcode":"06515",
    "addr:street":"Whalley Ave",
    "iso:country":"US",
    "sg:address":"781 Whalley Ave",
    "sg:city":"New Haven",
    "sg:classifiers":[
        {
            "category":"Social Services",
            "type":"Services"
        }
    ],
    "sg:phone":"+1 203 387 5026",
    "sg:postcode":"06515",
    "sg:province":"CT",
    "sg:tags":[
        "organization",
        "welfare"
    ],
    "wof:name":"Meals On Wheels",
    "wof:placetype":"venue"
},
  "geometry": {"coordinates":[-72.957476,41.325241],"type":"Point"}
}