{
  "type": "Feature",
  "properties": {
    "iso:country":"US",
    "sg:address":"344 Prospect St",
    "sg:city":"Moosup",
    "sg:classifiers":[
        {
            "category":"Banks & Credit Unions",
            "subcategory":"Bank",
            "type":"Services"
        },
        {
            "category":"Banks & Credit Unions",
            "subcategory":"Financial Services",
            "type":"Services"
        }
    ],
    "sg:phone":"+1 860 564 3328",
    "sg:postcode":"06354",
    "sg:province":"CT",
    "sg:tags":[
        "broker",
        "mortgage"
    ],
    "wof:name":"Savings Institute",
    "wof:placetype":"venue"
},
  "geometry": {"coordinates":[-71.883003,41.712898],"type":"Point"}
}