{
  "type": "Feature",
  "properties": {
    "iso:country":"US",
    "sg:address":"377 Ardsley Rd",
    "sg:city":"Waterbury",
    "sg:classifiers":[
        {
            "category":"Professional",
            "type":"Services"
        }
    ],
    "sg:phone":"+1 203 755 6794",
    "sg:postcode":"06708",
    "sg:province":"CT",
    "wof:name":"In Backup Generators",
    "wof:placetype":"venue"
},
  "geometry": {"coordinates":[-73.078987,41.563818],"type":"Point"}
}