{
  "type": "Feature",
  "properties": {
    "addr:full":"600 Main St Monroe CT 06468",
    "addr:housenumber":"600",
    "addr:postcode":"06468",
    "addr:street":"Main St",
    "iso:country":"US",
    "sg:address":"600 Main St",
    "sg:city":"Monroe",
    "sg:classifiers":[
        {
            "category":"Professional",
            "subcategory":"Detective & Security Services",
            "type":"Services"
        }
    ],
    "sg:phone":"+1 203 452 8366",
    "sg:postcode":"06468",
    "sg:province":"CT",
    "sg:tags":[
        "investigator"
    ],
    "wof:name":"C T Tax FRAUD Bureau LLC",
    "wof:placetype":"venue"
},
  "geometry": {"coordinates":[-73.265255,41.33086],"type":"Point"}
}