{
  "type": "Feature",
  "properties": {
    "iso:country":"US",
    "sg:address":"52 Field Rd",
    "sg:city":"Somers",
    "sg:classifiers":[
        {
            "category":"Building & Trades",
            "subcategory":"Plumbing",
            "type":"Services"
        }
    ],
    "sg:phone":"+1 860 749 7253",
    "sg:postcode":"06071",
    "sg:province":"CT",
    "sg:tags":[
        "plumber",
        "industrial",
        "contractors-commercial"
    ],
    "wof:name":"Conway Plumbing & Heating",
    "wof:placetype":"venue"
},
  "geometry": {"coordinates":[-72.450304,41.979112],"type":"Point"}
}