{
  "type": "Feature",
  "properties": {
    "addr:full":"327 Shelton Ave Shelton CT 06484",
    "addr:housenumber":"327",
    "addr:postcode":"06484",
    "addr:street":"Shelton Ave",
    "iso:country":"US",
    "sg:address":"327 Shelton Ave",
    "sg:city":"Shelton",
    "sg:classifiers":[
        {
            "category":"Professional",
            "subcategory":"Business Services",
            "type":"Services"
        }
    ],
    "sg:phone":"+1   ",
    "sg:postcode":"06484",
    "sg:province":"CT",
    "wof:name":"Top Cat Enterprises",
    "wof:placetype":"venue"
},
  "geometry": {"coordinates":[-73.128923,41.30557],"type":"Point"}
}