{
  "type": "Feature",
  "properties": {
    "iso:country":"US",
    "sg:address":"556 Washington Ave",
    "sg:city":"North Haven",
    "sg:classifiers":[
        {
            "category":"Professional",
            "subcategory":"Engineering",
            "type":"Services"
        }
    ],
    "sg:phone":"+1 203 239 4200",
    "sg:postcode":"06473",
    "sg:province":"CT",
    "sg:tags":[
        "engineer"
    ],
    "sg:website":"www.teamdtc.com",
    "wof:name":"Diversified Technology Conslnt",
    "wof:placetype":"venue"
},
  "geometry": {"coordinates":[-72.840524,41.417177],"type":"Point"}
}