{
  "type": "Feature",
  "properties": {
    "addr:full":"366 E Hartland Rd Pleasant Valley CT 06063",
    "addr:housenumber":"366",
    "addr:postcode":"06063",
    "addr:street":"E Hartland Rd Pleasant Valley Ct",
    "iso:country":"US",
    "sg:address":"366 E Hartland Rd",
    "sg:city":"Pleasant Valley",
    "sg:phone":"+1 860 379 9088",
    "sg:postcode":"06063",
    "sg:province":"CT",
    "sg:tags":[
        "farm",
        "field",
        "crop"
    ],
    "wof:name":"Highledge Farm",
    "wof:placetype":"venue"
},
  "geometry": {"coordinates":[-72.91691400000001,41.947222],"type":"Point"}
}