{
  "type": "Feature",
  "properties": {
    "iso:country":"US",
    "sg:address":"37 Warehouse Point Rd",
    "sg:city":"Wallingford",
    "sg:classifiers":[
        {
            "category":"Autos & Motor Vehicles",
            "subcategory":"Automobile Sales",
            "type":"Retail Goods"
        }
    ],
    "sg:phone":"+1 203 284 3863",
    "sg:postcode":"06492",
    "sg:province":"CT",
    "sg:tags":[
        "classic"
    ],
    "sg:website":"www.cobraautomotive.com",
    "wof:name":"Cobra Automotive",
    "wof:placetype":"venue"
},
  "geometry": {"coordinates":[-72.814061,41.488738],"type":"Point"}
}