{
  "type": "Feature",
  "properties": {
    "iso:country":"US",
    "sg:address":"7 Charterhouse Rd",
    "sg:city":"New Milford",
    "sg:classifiers":[
        {
            "category":"Home & Garden",
            "subcategory":"Building Materials",
            "type":"Retail Goods"
        }
    ],
    "sg:phone":"+1 860 350 0253",
    "sg:postcode":"06776",
    "sg:province":"CT",
    "wof:name":"Dragonfly Studios",
    "wof:placetype":"venue"
},
  "geometry": {"coordinates":[-73.383661,41.610984],"type":"Point"}
}