{
  "type": "Feature",
  "properties": {
    "addr:full":"80 Beaverbrook Rd Weston CT 06883",
    "addr:housenumber":"80",
    "addr:postcode":"06883",
    "addr:street":"Beaverbrook Rd",
    "iso:country":"US",
    "sg:address":"80 Beaverbrook Rd",
    "sg:city":"Weston",
    "sg:classifiers":[
        {
            "category":"Professional",
            "subcategory":"Lawyer & Legal Services",
            "type":"Services"
        }
    ],
    "sg:phone":"+1   ",
    "sg:postcode":"06883",
    "sg:province":"CT",
    "wof:name":"Philip Brent Hover Esquire",
    "wof:placetype":"venue"
},
  "geometry": {"coordinates":[-73.367645,41.213981],"type":"Point"}
}