{
  "type": "Feature",
  "properties": {
    "addr:full":"26 Union St Vernon Rockville CT 06066",
    "addr:housenumber":"26",
    "addr:postcode":"06066",
    "addr:street":"Union St",
    "iso:country":"US",
    "sg:address":"26 Union St",
    "sg:city":"Vernon Rockville",
    "sg:classifiers":[
        {
            "category":"Professional",
            "subcategory":"Accounting & Tax Preparation",
            "type":"Services"
        }
    ],
    "sg:phone":"+1   ",
    "sg:postcode":"06066",
    "sg:province":"CT",
    "wof:name":"Bob Murzyn",
    "wof:placetype":"venue"
},
  "geometry": {"coordinates":[-72.451189,41.867017],"type":"Point"}
}