{
  "type": "Feature",
  "properties": {
    "iso:country":"US",
    "sg:address":"5 Myrica Way",
    "sg:city":"Old Lyme",
    "sg:classifiers":[
        {
            "category":"Professional",
            "subcategory":"Computer Services",
            "type":"Services"
        }
    ],
    "sg:phone":"+1   ",
    "sg:postcode":"06371",
    "sg:province":"CT",
    "sg:tags":[
        "hardware",
        "consulting",
        "design",
        "specialty",
        "for"
    ],
    "wof:name":"Don Leroi",
    "wof:placetype":"venue"
},
  "geometry": {"coordinates":[-72.276353,41.307141],"type":"Point"}
}