{
  "type": "Feature",
  "properties": {
    "addr:full":"56 Cornell Cir East Hartford CT 06108",
    "addr:housenumber":"56",
    "addr:postcode":"06108",
    "addr:street":"Cornell Cir East Hartford Ct",
    "iso:country":"US",
    "sg:address":"56 Cornell Cir",
    "sg:city":"East Hartford",
    "sg:classifiers":[
        {
            "category":"Professional",
            "subcategory":"Business Services",
            "type":"Services"
        }
    ],
    "sg:phone":"+1   ",
    "sg:postcode":"06108",
    "sg:province":"CT",
    "wof:name":"HI Tech Wrless Cmmncations LLC",
    "wof:placetype":"venue"
},
  "geometry": {"coordinates":[-72.60372700000001,41.795516],"type":"Point"}
}