{
  "type": "Feature",
  "properties": {
    "addr:full":"419 N High St East Haven CT 06512",
    "addr:housenumber":"419",
    "addr:postcode":"06512",
    "addr:street":"N High St",
    "iso:country":"US",
    "sg:address":"419 N High St",
    "sg:city":"East Haven",
    "sg:classifiers":[
        {
            "category":"Wholesale",
            "subcategory":"Seafood",
            "type":"Manufacturing & Wholesale Goods"
        }
    ],
    "sg:phone":"+1 203 467 2800",
    "sg:postcode":"06512",
    "sg:province":"CT",
    "sg:tags":[
        "fresh",
        "fish"
    ],
    "wof:name":"Gambardellas Whl Fish Dlr",
    "wof:placetype":"venue"
},
  "geometry": {"coordinates":[-72.867063,41.291898],"type":"Point"}
}