{
  "type": "Feature",
  "properties": {
    "iso:country":"US",
    "sg:address":"244 Kent Rd",
    "sg:city":"New Milford",
    "sg:classifiers":[
        {
            "category":"Travel",
            "subcategory":"Hotels & Motels",
            "type":"Entertainment"
        }
    ],
    "sg:phone":"+1   ",
    "sg:postcode":"06776",
    "sg:province":"CT",
    "sg:tags":[
        "operation"
    ],
    "wof:name":"Green Valley Motel",
    "wof:placetype":"venue"
},
  "geometry": {"coordinates":[-73.44239899999999,41.583585],"type":"Point"}
}