{
  "type": "Feature",
  "properties": {
    "addr:full":"114 Pearl St Port Chester CT 10573",
    "addr:housenumber":"114",
    "addr:postcode":"10573",
    "addr:street":"Pearl St Port Chester Ct",
    "iso:country":"US",
    "sg:address":"114 Pearl St",
    "sg:city":"Port Chester",
    "sg:classifiers":[
        {
            "category":"Manufacturing",
            "subcategory":"Wood Products",
            "type":"Manufacturing & Wholesale Goods"
        }
    ],
    "sg:phone":"+1   ",
    "sg:postcode":"10573",
    "sg:province":"CT",
    "sg:tags":[
        "mfg"
    ],
    "wof:name":"Medi Wood Work Inc",
    "wof:placetype":"venue"
},
  "geometry": {"coordinates":[-73.66817500000001,40.998425],"type":"Point"}
}