{
  "type": "Feature",
  "properties": {
    "iso:country":"US",
    "sg:address":"8 Farmington Ave",
    "sg:city":"New Britain",
    "sg:classifiers":[
        {
            "category":"Professional",
            "subcategory":"Business Services",
            "type":"Services"
        }
    ],
    "sg:phone":"+1   ",
    "sg:postcode":"06053",
    "sg:province":"CT",
    "wof:name":"Ameri Gas Enterprises LLC",
    "wof:placetype":"venue"
},
  "geometry": {"coordinates":[-72.786067,41.678422],"type":"Point"}
}