{
  "type": "Feature",
  "properties": {
    "iso:country":"US",
    "sg:address":"208 Post Rd W",
    "sg:city":"Westport",
    "sg:classifiers":[
        {
            "category":"Health Services",
            "subcategory":"Doctor",
            "type":"Services"
        }
    ],
    "sg:phone":"+1   ",
    "sg:postcode":"06880",
    "sg:province":"CT",
    "sg:tags":[
        "medical"
    ],
    "wof:name":"Westport Pain Assoc",
    "wof:placetype":"venue"
},
  "geometry": {"coordinates":[-73.37222300000001,41.135164],"type":"Point"}
}