{
  "type": "Feature",
  "properties": {
    "iso:country":"US",
    "sg:address":"259 Ellsworth St",
    "sg:city":"Bridgeport",
    "sg:classifiers":[
        {
            "category":"Professional",
            "type":"Services"
        }
    ],
    "sg:phone":"+1 203 368 0533",
    "sg:postcode":"06605",
    "sg:province":"CT",
    "sg:tags":[
        "establishment"
    ],
    "wof:name":"Holleran Brothers",
    "wof:placetype":"venue"
},
  "geometry": {"coordinates":[-73.221858,41.156524],"type":"Point"}
}