{
  "type": "Feature",
  "properties": {
    "addr:full":"425 New Britain Ave Newington CT 06111",
    "addr:housenumber":"425",
    "addr:postcode":"06111",
    "addr:street":"New Britain Ave",
    "iso:country":"US",
    "sg:address":"425 New Britain Ave",
    "sg:city":"Newington",
    "sg:classifiers":[
        {
            "category":"Personal",
            "subcategory":"Beauty Salon",
            "type":"Services"
        }
    ],
    "sg:phone":"+1   ",
    "sg:postcode":"06111",
    "sg:province":"CT",
    "sg:tags":[
        "shop"
    ],
    "wof:name":"Aqua Eita",
    "wof:placetype":"venue"
},
  "geometry": {"coordinates":[-72.739104,41.673927],"type":"Point"}
}