{
  "type": "Feature",
  "properties": {
    "iso:country":"US",
    "sg:address":"585 Enfield St",
    "sg:city":"Enfield",
    "sg:classifiers":[
        {
            "category":"Manufacturing",
            "subcategory":"Retail Goods",
            "type":"Manufacturing & Wholesale Goods"
        }
    ],
    "sg:phone":"+1 860 741 8261",
    "sg:postcode":"06082",
    "sg:province":"CT",
    "sg:tags":[
        "product",
        "mfg"
    ],
    "wof:name":"Cityline Nails",
    "wof:placetype":"venue"
},
  "geometry": {"coordinates":[-72.59302,42.008583],"type":"Point"}
}