{
  "type": "Feature",
  "properties": {
    "iso:country":"US",
    "sg:address":"609 Bridgeport Ave",
    "sg:city":"Milford",
    "sg:classifiers":[
        {
            "category":"Restaurant",
            "type":"Food & Drink"
        }
    ],
    "sg:menulink":"http://www.allmenus.com/ct/milford/144222-subway/menu/",
    "sg:phone":"+1 203 877 4082",
    "sg:postcode":"06460",
    "sg:province":"CT",
    "sg:tags":[
        "american",
        "sandwich"
    ],
    "wof:name":"Subway",
    "wof:placetype":"venue"
},
  "geometry": {"coordinates":[-73.086021,41.20797],"type":"Point"}
}