{
  "type": "Feature",
  "properties": {
    "iso:country":"US",
    "sg:address":"447 1st Ave",
    "sg:city":"West Haven",
    "sg:classifiers":[
        {
            "category":"Social Services",
            "type":"Services"
        }
    ],
    "sg:phone":"+1 203 937 7885",
    "sg:postcode":"06516",
    "sg:province":"CT",
    "sg:tags":[
        "youth",
        "organization",
        "center"
    ],
    "wof:name":"For Youth Inc",
    "wof:placetype":"venue"
},
  "geometry": {"coordinates":[-72.943023,41.279629],"type":"Point"}
}