{
  "type": "Feature",
  "properties": {
    "addr:full":"266 Boston Post Rd Madison CT 06443",
    "addr:housenumber":"266",
    "addr:postcode":"06443",
    "addr:street":"Boston Post Rd",
    "iso:country":"US",
    "sg:address":"266 Boston Post Rd",
    "sg:city":"Madison",
    "sg:classifiers":[
        {
            "category":"Wholesale",
            "subcategory":"Machinery & Supplies",
            "type":"Manufacturing & Wholesale Goods"
        },
        {
            "category":"Home & Garden",
            "subcategory":"Household Appliances",
            "type":"Retail Goods"
        }
    ],
    "sg:phone":"+1 203 245 1697",
    "sg:postcode":"06443",
    "sg:province":"CT",
    "sg:tags":[
        "repair",
        "cleaners",
        "sewing",
        "system",
        "cleaning",
        "vacuum"
    ],
    "wof:name":"Howard Service Co Inc",
    "wof:placetype":"venue"
},
  "geometry": {"coordinates":[-72.627295,41.278234],"type":"Point"}
}