{
  "type": "Feature",
  "properties": {
    "addr:full":"87 E Liberty St Danbury CT 06810",
    "addr:housenumber":"87",
    "addr:postcode":"06810",
    "addr:street":"E Liberty St",
    "iso:country":"US",
    "sg:address":"87 E Liberty St",
    "sg:city":"Danbury",
    "sg:classifiers":[
        {
            "category":"Food & Beverages",
            "subcategory":"Bakery",
            "type":"Retail Goods"
        }
    ],
    "sg:phone":"+1 203 798 6290",
    "sg:postcode":"06810",
    "sg:province":"CT",
    "sg:tags":[
        "baker"
    ],
    "wof:name":"International Bakery",
    "wof:placetype":"venue"
},
  "geometry": {"coordinates":[-73.44580499999999,41.394472],"type":"Point"}
}