{
  "type": "Feature",
  "properties": {
    "addr:full":"469 Orange St New Haven CT 06511",
    "addr:housenumber":"469",
    "addr:postcode":"06511",
    "addr:street":"Orange St",
    "iso:country":"US",
    "sg:address":"469 Orange St",
    "sg:city":"New Haven",
    "sg:classifiers":[
        {
            "category":"Health Services",
            "subcategory":"Doctor",
            "type":"Services"
        }
    ],
    "sg:phone":"+1   ",
    "sg:postcode":"06511",
    "sg:province":"CT",
    "sg:tags":[
        "medical"
    ],
    "wof:name":"Allen Alton Dr",
    "wof:placetype":"venue"
},
  "geometry": {"coordinates":[-72.917923,41.31375],"type":"Point"}
}