{
  "type": "Feature",
  "properties": {
    "addr:full":"31 Ox Ridge Ln Darien CT 06820",
    "addr:housenumber":"31",
    "addr:postcode":"06820",
    "addr:street":"Ox Ridge Ln Darien Ct",
    "iso:country":"US",
    "sg:address":"31 Ox Ridge Ln",
    "sg:city":"Darien",
    "sg:classifiers":[
        {
            "category":"Professional",
            "subcategory":"Business Services",
            "type":"Services"
        }
    ],
    "sg:phone":"+1   ",
    "sg:postcode":"06820",
    "sg:province":"CT",
    "wof:name":"Kmj Manor Partners Ltd Partnr",
    "wof:placetype":"venue"
},
  "geometry": {"coordinates":[-73.48949500000001,41.10064],"type":"Point"}
}