{
  "type": "Feature",
  "properties": {
    "addr:full":"111 Forty Acre Mountain Rd Danbury CT 06811",
    "addr:housenumber":"111",
    "addr:postcode":"06811",
    "addr:street":"Forty Acre Mountain Rd",
    "iso:country":"US",
    "sg:address":"111 Forty Acre Mountain Rd",
    "sg:city":"Danbury",
    "sg:classifiers":[
        {
            "category":"Banks & Credit Unions",
            "subcategory":"Investment Brokerage",
            "type":"Services"
        }
    ],
    "sg:phone":"+1 203 778 1096",
    "sg:postcode":"06811",
    "sg:province":"CT",
    "sg:tags":[
        "advisory"
    ],
    "wof:name":"Mimoso Investments",
    "wof:placetype":"venue"
},
  "geometry": {"coordinates":[-73.432901,41.456024],"type":"Point"}
}