{
  "type": "Feature",
  "properties": {
    "iso:country":"US",
    "sg:address":"25 Butler St",
    "sg:city":"Norwalk",
    "sg:classifiers":[
        {
            "category":"Organizations",
            "subcategory":"Non-profit Organization",
            "type":"Services"
        }
    ],
    "sg:phone":"+1 203 866 6166",
    "sg:postcode":"06850",
    "sg:province":"CT",
    "sg:tags":[
        "handicapped"
    ],
    "wof:name":"Butler Street Program",
    "wof:placetype":"venue"
},
  "geometry": {"coordinates":[-73.413228,41.110427],"type":"Point"}
}