{
  "type": "Feature",
  "properties": {
    "iso:country":"US",
    "sg:address":"138 Waterbury Rd",
    "sg:city":"Prospect",
    "sg:classifiers":[
        {
            "category":"Retail",
            "subcategory":"Animal Services",
            "type":"Services"
        }
    ],
    "sg:phone":"+1 203 758 6846",
    "sg:postcode":"06712",
    "sg:province":"CT",
    "sg:tags":[
        "butterfly",
        "releasing",
        "dove",
        "wedding"
    ],
    "wof:name":"Love Birds",
    "wof:placetype":"venue"
},
  "geometry": {"coordinates":[-72.995862,41.524428],"type":"Point"}
}