{
  "type": "Feature",
  "properties": {
    "addr:full":"1506 Stratford Ave Bridgeport CT 06607",
    "addr:housenumber":"1506",
    "addr:postcode":"06607",
    "addr:street":"Stratford Ave",
    "iso:country":"US",
    "sg:address":"1506 Stratford Ave",
    "sg:city":"Bridgeport",
    "sg:classifiers":[
        {
            "category":"Food & Beverages",
            "subcategory":"Liquor & Beverages",
            "type":"Retail Goods"
        }
    ],
    "sg:phone":"+1 203 333 7299",
    "sg:postcode":"06607",
    "sg:province":"CT",
    "sg:tags":[
        "store"
    ],
    "wof:name":"Jacksons Liquor Store",
    "wof:placetype":"venue"
},
  "geometry": {"coordinates":[-73.162539,41.179314],"type":"Point"}
}