{
  "type": "Feature",
  "properties": {
    "iso:country":"US",
    "sg:address":"2049 Silas Deane Hwy",
    "sg:city":"Rocky Hill",
    "sg:classifiers":[
        {
            "category":"Banks & Credit Unions",
            "subcategory":"Bank",
            "type":"Services"
        }
    ],
    "sg:phone":"+1 860 920 1485",
    "sg:postcode":"06067",
    "sg:province":"CT",
    "sg:tags":[
        "lender",
        "broker",
        "mortgage"
    ],
    "wof:name":"Travis Mortgage LLC",
    "wof:placetype":"venue"
},
  "geometry": {"coordinates":[-72.645304,41.672488],"type":"Point"}
}