{
  "type": "Feature",
  "properties": {
    "addr:full":"7 Blackberry Ln Norwalk CT 06850",
    "addr:housenumber":"7",
    "addr:postcode":"06850",
    "addr:street":"Blackberry Ln",
    "iso:country":"US",
    "sg:address":"7 Blackberry Ln",
    "sg:city":"Norwalk",
    "sg:classifiers":[
        {
            "category":"Professional",
            "type":"Services"
        }
    ],
    "sg:phone":"+1   ",
    "sg:postcode":"06850",
    "sg:province":"CT",
    "wof:name":"Joseph Sgammato Co",
    "wof:placetype":"venue"
},
  "geometry": {"coordinates":[-73.44247900000001,41.137089],"type":"Point"}
}