{
  "type": "Feature",
  "properties": {
    "addr:full":"40 Wiebe Ave Stratford CT 06614",
    "addr:housenumber":"40",
    "addr:postcode":"06614",
    "addr:street":"Wiebe Ave",
    "iso:country":"US",
    "sg:address":"40 Wiebe Ave",
    "sg:city":"Stratford",
    "sg:classifiers":[
        {
            "category":"Building & Trades",
            "subcategory":"Construction",
            "type":"Services"
        }
    ],
    "sg:phone":"+1 203 386 8916",
    "sg:postcode":"06614",
    "sg:province":"CT",
    "sg:tags":[
        "remodeling",
        "contractor"
    ],
    "wof:name":"Borodack Contractors",
    "wof:placetype":"venue"
},
  "geometry": {"coordinates":[-73.144203,41.201529],"type":"Point"}
}