{
  "type": "Feature",
  "properties": {
    "addr:full":"273 Canal St E Shelton CT 06484",
    "addr:housenumber":"273",
    "addr:postcode":"06484",
    "addr:street":"Canal St E Shelton Ct",
    "iso:country":"US",
    "sg:address":"273 Canal St E",
    "sg:city":"Shelton",
    "sg:classifiers":[
        {
            "category":"Manufacturing",
            "subcategory":"Printing",
            "type":"Manufacturing & Wholesale Goods"
        }
    ],
    "sg:phone":"+1 203 924 1172",
    "sg:postcode":"06484",
    "sg:province":"CT",
    "sg:tags":[
        "typesetting"
    ],
    "wof:name":"All Caps Designer Typography",
    "wof:placetype":"venue"
},
  "geometry": {"coordinates":[-73.09616800000001,41.321103],"type":"Point"}
}