{
  "type": "Feature",
  "properties": {
    "iso:country":"US",
    "sg:address":"333 Cedar St",
    "sg:city":"New Haven",
    "sg:classifiers":[
        {
            "category":"Health Services",
            "subcategory":"Doctor",
            "type":"Services"
        }
    ],
    "sg:phone":"+1 203 785 2809",
    "sg:postcode":"06510",
    "sg:province":"CT",
    "sg:tags":[
        "physician",
        "surgeon"
    ],
    "wof:name":"Yale University School Of Mdcn",
    "wof:placetype":"venue"
},
  "geometry": {"coordinates":[-72.93456999999999,41.303762],"type":"Point"}
}