{
  "type": "Feature",
  "properties": {
    "iso:country":"US",
    "sg:address":"33 E Brown St",
    "sg:city":"West Haven",
    "sg:classifiers":[
        {
            "category":"Utilities",
            "subcategory":"Telephone",
            "type":"Services"
        }
    ],
    "sg:phone":"+1   ",
    "sg:postcode":"06516",
    "sg:province":"CT",
    "sg:tags":[
        "communications",
        "consulting",
        "management"
    ],
    "wof:name":"John Dechello Intern",
    "wof:placetype":"venue"
},
  "geometry": {"coordinates":[-72.939712,41.272095],"type":"Point"}
}