{
  "type": "Feature",
  "properties": {
    "iso:country":"US",
    "sg:address":"30 Milbank Ave",
    "sg:city":"Greenwich",
    "sg:classifiers":[
        {
            "category":"Real Estate",
            "subcategory":"Real Estate Agent",
            "type":"Services"
        }
    ],
    "sg:phone":"+1 203 869 7800",
    "sg:postcode":"06830",
    "sg:province":"CT",
    "sg:website":"www.raveis.com",
    "wof:name":"William Raveis Intl",
    "wof:placetype":"venue"
},
  "geometry": {"coordinates":[-73.622877,41.03398],"type":"Point"}
}