{
  "type": "Feature",
  "properties": {
    "addr:full":"31 Woodbridge Dr Suffield CT 06078",
    "addr:housenumber":"31",
    "addr:postcode":"06078",
    "addr:street":"Woodbridge Dr Suffield Ct",
    "iso:country":"US",
    "sg:address":"31 Woodbridge Dr",
    "sg:city":"Suffield",
    "sg:classifiers":[
        {
            "category":"Professional",
            "subcategory":"Business Services",
            "type":"Services"
        }
    ],
    "sg:phone":"+1   ",
    "sg:postcode":"06078",
    "sg:province":"CT",
    "wof:name":"Hartford Tech Partners LLC",
    "wof:placetype":"venue"
},
  "geometry": {"coordinates":[-72.624816,42.015472],"type":"Point"}
}