{
  "type": "Feature",
  "properties": {
    "iso:country":"US",
    "sg:address":"74 Newtown Rd",
    "sg:city":"Danbury",
    "sg:classifiers":[
        {
            "category":"Autos & Motor Vehicles",
            "subcategory":"Automobile Sales",
            "type":"Retail Goods"
        }
    ],
    "sg:phone":"+1 203 792 9501",
    "sg:postcode":"06810",
    "sg:province":"CT",
    "sg:tags":[
        "car",
        "dealer"
    ],
    "wof:name":"Action Motors Corp",
    "wof:placetype":"venue"
},
  "geometry": {"coordinates":[-73.412048,41.411339],"type":"Point"}
}