{
  "type": "Feature",
  "properties": {
    "iso:country":"US",
    "sg:address":"15 Hearthstone Dr",
    "sg:city":"Brookfield",
    "sg:classifiers":[
        {
            "category":"Retail",
            "subcategory":"Repair Shop",
            "type":"Services"
        }
    ],
    "sg:phone":"+1   ",
    "sg:postcode":"06804",
    "sg:province":"CT",
    "wof:name":"Cullen Timothy & Brandon",
    "wof:placetype":"venue"
},
  "geometry": {"coordinates":[-73.37684299999999,41.486183],"type":"Point"}
}