{
  "type": "Feature",
  "properties": {
    "addr:full":"61 Pickett Rd Plainfield CT 06374",
    "addr:housenumber":"61",
    "addr:postcode":"06374",
    "addr:street":"Pickett Rd",
    "iso:country":"US",
    "sg:address":"61 Pickett Rd",
    "sg:city":"Plainfield",
    "sg:classifiers":[
        {
            "category":"Building & Trades",
            "subcategory":"Plumbing",
            "type":"Services"
        }
    ],
    "sg:phone":"+1 860 564 2535",
    "sg:postcode":"06374",
    "sg:province":"CT",
    "sg:tags":[
        "contractor"
    ],
    "wof:name":"Georges Plumbing & Heating",
    "wof:placetype":"venue"
},
  "geometry": {"coordinates":[-71.91513999999999,41.715879],"type":"Point"}
}