{
  "type": "Feature",
  "properties": {
    "iso:country":"US",
    "sg:address":"8 Clement St",
    "sg:city":"Waterford",
    "sg:classifiers":[
        {
            "category":"Shopping",
            "subcategory":"Clothing, Apparel, & Fashions",
            "type":"Retail Goods"
        }
    ],
    "sg:phone":"+1 860 442 8298",
    "sg:postcode":"06385",
    "sg:province":"CT",
    "wof:name":"Stitch & Squiggles LLC",
    "wof:placetype":"venue"
},
  "geometry": {"coordinates":[-72.112477,41.33982],"type":"Point"}
}