{
  "type": "Feature",
  "properties": {
    "addr:full":"328 County Rd Torrington CT 06790",
    "addr:housenumber":"328",
    "addr:postcode":"06790",
    "addr:street":"County Rd",
    "iso:country":"US",
    "sg:address":"328 County Rd",
    "sg:city":"Torrington",
    "sg:classifiers":[
        {
            "category":"Building & Trades",
            "subcategory":"Landscaping Services",
            "type":"Services"
        }
    ],
    "sg:phone":"+1 860 482 1841",
    "sg:postcode":"06790",
    "sg:province":"CT",
    "wof:name":"Classic Landscape Management",
    "wof:placetype":"venue"
},
  "geometry": {"coordinates":[-73.082358,41.804074],"type":"Point"}
}