{
  "type": "Feature",
  "properties": {
    "addr:full":"864 Wethersfield Ave Hartford CT 06114",
    "addr:housenumber":"864",
    "addr:postcode":"06114",
    "addr:street":"Wethersfield Ave;Ct",
    "iso:country":"US",
    "sg:address":"864 Wethersfield Ave",
    "sg:city":"Hartford",
    "sg:classifiers":[
        {
            "category":"Health Services",
            "subcategory":"Chiropractor",
            "type":"Services"
        }
    ],
    "sg:phone":"+1   ",
    "sg:postcode":"06114",
    "sg:province":"CT",
    "wof:name":"Carbone Chiropractic Center",
    "wof:placetype":"venue"
},
  "geometry": {"coordinates":[-72.669724,41.731891],"type":"Point"}
}