{
  "type": "Feature",
  "properties": {
    "iso:country":"US",
    "sg:address":"84 Zeya Dr",
    "sg:city":"Coventry",
    "sg:classifiers":[
        {
            "category":"Retail",
            "subcategory":"Repair Shop",
            "type":"Services"
        }
    ],
    "sg:phone":"+1   ",
    "sg:postcode":"06238",
    "sg:province":"CT",
    "sg:tags":[
        "elevator"
    ],
    "wof:name":"Michael Barselau",
    "wof:placetype":"venue"
},
  "geometry": {"coordinates":[-72.400097,41.820228],"type":"Point"}
}