{
  "type": "Feature",
  "properties": {
    "addr:full":"88 Sylvan Crest Dr Southbury CT 06488",
    "addr:housenumber":"88",
    "addr:postcode":"06488",
    "addr:street":"Sylvan Crest Dr",
    "iso:country":"US",
    "sg:address":"88 Sylvan Crest Dr",
    "sg:city":"Southbury",
    "sg:classifiers":[
        {
            "category":"Recreation",
            "type":"Entertainment"
        }
    ],
    "sg:phone":"+1   ",
    "sg:postcode":"06488",
    "sg:province":"CT",
    "wof:name":"Gone Ballooning",
    "wof:placetype":"venue"
},
  "geometry": {"coordinates":[-73.23730500000001,41.47262],"type":"Point"}
}