{
  "type": "Feature",
  "properties": {
    "addr:full":"83 Windy Hill Rd Hampton CT 06247",
    "addr:housenumber":"83",
    "addr:postcode":"06247",
    "addr:street":"Windy Hill Rd",
    "iso:country":"US",
    "sg:address":"83 Windy Hill Rd",
    "sg:city":"Hampton",
    "sg:classifiers":[
        {
            "category":"Building & Trades",
            "subcategory":"Landscaping Services",
            "type":"Services"
        }
    ],
    "sg:phone":"+1 860 455 0437",
    "sg:postcode":"06247",
    "sg:province":"CT",
    "wof:name":"Weeds R US Landscape",
    "wof:placetype":"venue"
},
  "geometry": {"coordinates":[-72.03999,41.800692],"type":"Point"}
}