{
  "type": "Feature",
  "properties": {
    "addr:full":"331 Federal Rd Brookfield CT 06804",
    "addr:housenumber":"331",
    "addr:postcode":"06804",
    "addr:street":"Federal Rd",
    "iso:country":"US",
    "sg:address":"331 Federal Rd",
    "sg:city":"Brookfield",
    "sg:classifiers":[
        {
            "category":"Retail",
            "subcategory":"Car Wash",
            "type":"Services"
        }
    ],
    "sg:phone":"+1 203 775 5694",
    "sg:postcode":"06804",
    "sg:province":"CT",
    "sg:tags":[
        "automobile",
        "detail",
        "clean"
    ],
    "wof:name":"Ultimate Touch",
    "wof:placetype":"venue"
},
  "geometry": {"coordinates":[-73.40183500000001,41.451038],"type":"Point"}
}