{
  "type": "Feature",
  "properties": {
    "addr:full":"5 Capitol Dr Wallingford CT 06492",
    "addr:housenumber":"5",
    "addr:postcode":"06492",
    "addr:street":"Capitol Dr",
    "iso:country":"US",
    "sg:address":"5 Capitol Dr",
    "sg:city":"Wallingford",
    "sg:classifiers":[
        {
            "category":"Professional",
            "subcategory":"Business Services",
            "type":"Services"
        }
    ],
    "sg:phone":"+1   ",
    "sg:postcode":"06492",
    "sg:province":"CT",
    "sg:tags":[
        "engineering",
        "testing",
        "electrical"
    ],
    "wof:name":"High Voltage Maintenance Corp",
    "wof:placetype":"venue"
},
  "geometry": {"coordinates":[-72.818489,41.47947],"type":"Point"}
}