{
  "type": "Feature",
  "properties": {
    "addr:full":"65 Frontage Rd East Haven CT 06512",
    "addr:postcode":"06512",
    "addr:street":"65 Frontage Rd;Haven",
    "iso:country":"US",
    "sg:address":"65 Frontage Rd",
    "sg:city":"East Haven",
    "sg:classifiers":[
        {
            "category":"Restaurant",
            "type":"Food & Drink"
        }
    ],
    "sg:menulink":"http://www.allmenus.com/ct/east-haven/169442-wendys/menu/",
    "sg:phone":"+1 203 469 9459",
    "sg:postcode":"06512",
    "sg:province":"CT",
    "sg:tags":[
        "burger",
        "american",
        "soup"
    ],
    "wof:name":"Wendy's",
    "wof:placetype":"venue"
},
  "geometry": {"coordinates":[-72.88015900000001,41.286678],"type":"Point"}
}