{
  "type": "Feature",
  "properties": {
    "addr:full":"121 Deepwood Dr Waterbury CT 06708",
    "addr:housenumber":"121",
    "addr:postcode":"06708",
    "addr:street":"Deepwood Dr",
    "iso:country":"US",
    "sg:address":"121 Deepwood Dr",
    "sg:city":"Waterbury",
    "sg:classifiers":[
        {
            "category":"Professional",
            "type":"Services"
        }
    ],
    "sg:phone":"+1 203 597 0628",
    "sg:postcode":"06708",
    "sg:province":"CT",
    "sg:tags":[
        "establishment"
    ],
    "wof:name":"Smedley Comp",
    "wof:placetype":"venue"
},
  "geometry": {"coordinates":[-73.077844,41.548144],"type":"Point"}
}