{
  "type": "Feature",
  "properties": {
    "iso:country":"US",
    "sg:address":"934 Merritt St",
    "sg:city":"Bridgeport",
    "sg:classifiers":[
        {
            "category":"Travel",
            "subcategory":"Hotels & Motels",
            "type":"Entertainment"
        }
    ],
    "sg:phone":"+1   ",
    "sg:postcode":"06606",
    "sg:province":"CT",
    "sg:tags":[
        "operation"
    ],
    "wof:name":"Helga Travel Inc",
    "wof:placetype":"venue"
},
  "geometry": {"coordinates":[-73.22414000000001,41.204287],"type":"Point"}
}