{
  "type": "Feature",
  "properties": {
    "addr:full":"530 Farmington Ave Hartford CT 06105",
    "addr:housenumber":"530",
    "addr:postcode":"06105",
    "addr:street":"Farmington Ave;Ct",
    "iso:country":"US",
    "sg:address":"530 Farmington Ave",
    "sg:city":"Hartford",
    "sg:classifiers":[
        {
            "category":"Restaurant",
            "type":"Food & Drink"
        }
    ],
    "sg:menulink":"http://www.allmenus.com/ct/hartford/270496-ichiban/menu/",
    "sg:phone":"+1 860 236 5599",
    "sg:postcode":"06105",
    "sg:province":"CT",
    "sg:tags":[
        "korean",
        "japanese",
        "asian"
    ],
    "wof:name":"Ichiban",
    "wof:placetype":"venue"
},
  "geometry": {"coordinates":[-72.709761,41.766528],"type":"Point"}
}