{
  "type": "Feature",
  "properties": {
    "addr:full":"111 New Haven Ave Derby CT 06418",
    "addr:housenumber":"111",
    "addr:postcode":"06418",
    "addr:street":"New Haven Ave",
    "iso:country":"US",
    "sg:address":"111 New Haven Ave",
    "sg:city":"Derby",
    "sg:classifiers":[
        {
            "category":"Building & Trades",
            "subcategory":"Cleaning & Sanitation",
            "type":"Services"
        }
    ],
    "sg:phone":"+1 203 735 9988",
    "sg:postcode":"06418",
    "sg:province":"CT",
    "sg:tags":[
        "house"
    ],
    "wof:name":"Maid Brigade",
    "wof:placetype":"venue"
},
  "geometry": {"coordinates":[-73.076126,41.311046],"type":"Point"}
}