{
  "type": "Feature",
  "properties": {
    "addr:full":"7 Hickory Hill Rd Simsbury CT 06070",
    "addr:housenumber":"7",
    "addr:postcode":"06070",
    "addr:street":"Hickory Hill Rd Simsbury Ct",
    "iso:country":"US",
    "sg:address":"7 Hickory Hill Rd",
    "sg:city":"Simsbury",
    "sg:classifiers":[
        {
            "category":"Real Estate",
            "subcategory":"Surveying",
            "type":"Services"
        }
    ],
    "sg:phone":"+1   ",
    "sg:postcode":"06070",
    "sg:province":"CT",
    "wof:name":"Nascimbeni Benedito",
    "wof:placetype":"venue"
},
  "geometry": {"coordinates":[-72.84860399999999,41.831537],"type":"Point"}
}