{
  "type": "Feature",
  "properties": {
    "iso:country":"US",
    "sg:address":"7 Backus Ave",
    "sg:city":"Danbury",
    "sg:classifiers":[
        {
            "category":"Shopping",
            "type":"Retail Goods"
        }
    ],
    "sg:phone":"+1 203 798 1006",
    "sg:postcode":"06810",
    "sg:province":"CT",
    "sg:tags":[
        "cosmetic",
        "perfume"
    ],
    "wof:name":"L'Occitane",
    "wof:placetype":"venue"
},
  "geometry": {"coordinates":[-73.47560799999999,41.380075],"type":"Point"}
}