{
  "type": "Feature",
  "properties": {
    "iso:country":"US",
    "sg:address":"460 Smith St",
    "sg:city":"Middletown",
    "sg:classifiers":[
        {
            "category":"Manufacturing",
            "subcategory":"Tools & Machinery",
            "type":"Manufacturing & Wholesale Goods"
        }
    ],
    "sg:phone":"+1 860 632 9736",
    "sg:postcode":"06457",
    "sg:province":"CT",
    "sg:tags":[
        "mfg"
    ],
    "wof:name":"Magnetek",
    "wof:placetype":"venue"
},
  "geometry": {"coordinates":[-72.72011500000001,41.584272],"type":"Point"}
}