{
  "type": "Feature",
  "properties": {
    "addr:full":"64 Gould Ln Branford CT 06405",
    "addr:housenumber":"64",
    "addr:postcode":"06405",
    "addr:street":"Gould Ln;Ct",
    "iso:country":"US",
    "sg:address":"64 Gould Ln",
    "sg:city":"Branford",
    "sg:classifiers":[
        {
            "category":"Personal",
            "subcategory":"Beauty Salon",
            "type":"Services"
        }
    ],
    "sg:phone":"+1 203 488 3659",
    "sg:postcode":"06405",
    "sg:province":"CT",
    "wof:name":"Bernie's Hair Cutting",
    "wof:placetype":"venue"
},
  "geometry": {"coordinates":[-72.771732,41.292916],"type":"Point"}
}