{
  "type": "Feature",
  "properties": {
    "addr:full":"53 High Ridge Rd Trumbull CT 06611",
    "addr:housenumber":"53",
    "addr:postcode":"06611",
    "addr:street":"High Ridge Rd",
    "iso:country":"US",
    "sg:address":"53 High Ridge Rd",
    "sg:city":"Trumbull",
    "sg:classifiers":[
        {
            "category":"Professional",
            "type":"Services"
        }
    ],
    "sg:phone":"+1 203 459 9134",
    "sg:postcode":"06611",
    "sg:province":"CT",
    "sg:tags":[
        "establishment"
    ],
    "wof:name":"Reddy Mahesh",
    "wof:placetype":"venue"
},
  "geometry": {"coordinates":[-73.26763800000001,41.286997],"type":"Point"}
}