{
  "type": "Feature",
  "properties": {
    "iso:country":"US",
    "sg:address":"9 John St",
    "sg:city":"Clinton",
    "sg:classifiers":[
        {
            "category":"Professional",
            "subcategory":"Employment Agencies",
            "type":"Services"
        }
    ],
    "sg:phone":"+1   ",
    "sg:postcode":"06413",
    "sg:province":"CT",
    "wof:name":"Monroe Personel Services LLC",
    "wof:placetype":"venue"
},
  "geometry": {"coordinates":[-72.529094,41.280219],"type":"Point"}
}