{
  "type": "Feature",
  "properties": {
    "addr:full":"20 E Main St Waterbury CT 06702",
    "addr:housenumber":"20",
    "addr:postcode":"06702",
    "addr:street":"E Main St",
    "iso:country":"US",
    "sg:address":"20 E Main St",
    "sg:city":"Waterbury",
    "sg:classifiers":[
        {
            "category":"Government",
            "subcategory":"Office",
            "type":"Public Place"
        }
    ],
    "sg:phone":"+1 203 573 1418",
    "sg:postcode":"06702",
    "sg:province":"CT",
    "sg:tags":[
        "congressman"
    ],
    "wof:name":"Congressman James H Maloney",
    "wof:placetype":"venue"
},
  "geometry": {"coordinates":[-73.03993800000001,41.555576],"type":"Point"}
}