{
  "type": "Feature",
  "properties": {
    "addr:full":"17 Commons Dr Litchfield CT 06759",
    "addr:housenumber":"17",
    "addr:postcode":"06759",
    "addr:street":"Commons Dr",
    "iso:country":"US",
    "sg:address":"17 Commons Dr",
    "sg:city":"Litchfield",
    "sg:classifiers":[
        {
            "category":"Shopping",
            "subcategory":"Clothing, Apparel, & Fashions",
            "type":"Retail Goods"
        }
    ],
    "sg:phone":"+1 860 567 1909",
    "sg:postcode":"06759",
    "sg:province":"CT",
    "sg:tags":[
        "family"
    ],
    "wof:name":"Threads",
    "wof:placetype":"venue"
},
  "geometry": {"coordinates":[-73.202077,41.744119],"type":"Point"}
}