{
  "type": "Feature",
  "properties": {
    "addr:full":"249 Winsted Rd Torrington CT 06790",
    "addr:housenumber":"249",
    "addr:postcode":"06790",
    "addr:street":"Winsted Rd",
    "iso:country":"US",
    "sg:address":"249 Winsted Rd",
    "sg:city":"Torrington",
    "sg:classifiers":[
        {
            "category":"Banks & Credit Unions",
            "subcategory":"Bank",
            "type":"Services"
        }
    ],
    "sg:phone":"+1 860 482 3423",
    "sg:postcode":"06790",
    "sg:province":"CT",
    "sg:tags":[
        "mortgage"
    ],
    "wof:name":"Northwest Community Bank",
    "wof:placetype":"venue"
},
  "geometry": {"coordinates":[-73.116265,41.823848],"type":"Point"}
}