{
  "type": "Feature",
  "properties": {
    "iso:country":"US",
    "sg:address":"136 Dudley Ave",
    "sg:city":"Wallingford",
    "sg:classifiers":[
        {
            "category":"Retail",
            "subcategory":"Auto Repair",
            "type":"Services"
        },
        {
            "category":"Autos & Motor Vehicles",
            "subcategory":"Auto Supplies",
            "type":"Retail Goods"
        }
    ],
    "sg:phone":"+1 203 265 2027",
    "sg:postcode":"06492",
    "sg:province":"CT",
    "sg:tags":[
        "shop",
        "a",
        "retreading",
        "tire",
        "truck",
        "t"
    ],
    "wof:name":"Tri-State Tire Co Inc",
    "wof:placetype":"venue"
},
  "geometry": {"coordinates":[-72.831377,41.443718],"type":"Point"}
}