{
  "type": "Feature",
  "properties": {
    "addr:full":"1 Burning Tree Rd Greenwich CT 06830",
    "addr:housenumber":"1",
    "addr:postcode":"06830",
    "addr:street":"Burning Tree Rd",
    "iso:country":"US",
    "sg:address":"1 Burning Tree Rd",
    "sg:city":"Greenwich",
    "sg:classifiers":[
        {
            "category":"Banks & Credit Unions",
            "subcategory":"Investment Brokerage",
            "type":"Services"
        }
    ],
    "sg:phone":"+1 203 629 5604",
    "sg:postcode":"06830",
    "sg:province":"CT",
    "sg:tags":[
        "advisory"
    ],
    "wof:name":"Raffles Capital Group Inc",
    "wof:placetype":"venue"
},
  "geometry": {"coordinates":[-73.604444,41.09372],"type":"Point"}
}