{
  "type": "Feature",
  "properties": {
    "addr:full":"205 Boston Post Rd Orange CT 06477",
    "addr:housenumber":"205",
    "addr:postcode":"06477",
    "addr:street":"Boston Post Rd",
    "iso:country":"US",
    "sg:address":"205 Boston Post Rd",
    "sg:city":"Orange",
    "sg:classifiers":[
        {
            "category":"Manufacturing",
            "subcategory":"Metals",
            "type":"Manufacturing & Wholesale Goods"
        }
    ],
    "sg:phone":"+1 203 799 2437",
    "sg:postcode":"06477",
    "sg:province":"CT",
    "sg:tags":[
        "link",
        "chain",
        "fence"
    ],
    "sg:website":"www.orangefence.com",
    "wof:name":"Orange Fence & Supply Co",
    "wof:placetype":"venue"
},
  "geometry": {"coordinates":[-72.996287,41.271262],"type":"Point"}
}