{
  "type": "Feature",
  "properties": {
    "addr:full":"141 Daniel Rd Hamden CT 06517",
    "addr:housenumber":"141",
    "addr:postcode":"06517",
    "addr:street":"Daniel Rd",
    "iso:country":"US",
    "sg:address":"141 Daniel Rd",
    "sg:city":"Hamden",
    "sg:classifiers":[
        {
            "category":"Professional",
            "type":"Services"
        }
    ],
    "sg:phone":"+1 203 281 4894",
    "sg:postcode":"06517",
    "sg:province":"CT",
    "wof:name":"Bertazzo Inc",
    "wof:placetype":"venue"
},
  "geometry": {"coordinates":[-72.89464,41.355089],"type":"Point"}
}