{
  "type": "Feature",
  "properties": {
    "addr:full":"130 Washington Ave Waterbury CT 06708",
    "addr:housenumber":"130",
    "addr:postcode":"06708",
    "addr:street":"Washington Ave",
    "iso:country":"US",
    "sg:address":"130 Washington Ave",
    "sg:city":"Waterbury",
    "sg:classifiers":[
        {
            "category":"Wholesale",
            "subcategory":"Electrical",
            "type":"Manufacturing & Wholesale Goods"
        }
    ],
    "sg:phone":"+1 203 597 8662",
    "sg:postcode":"06708",
    "sg:province":"CT",
    "sg:tags":[
        "equipment"
    ],
    "wof:name":"Distinctive Landscape Lighting",
    "wof:placetype":"venue"
},
  "geometry": {"coordinates":[-73.040474,41.544075],"type":"Point"}
}