{
  "type": "Feature",
  "properties": {
    "addr:full":"1003 W Main St Branford CT 06405",
    "addr:housenumber":"1003",
    "addr:postcode":"06405",
    "addr:street":"W Main St",
    "iso:country":"US",
    "sg:address":"1003 W Main St",
    "sg:city":"Branford",
    "sg:classifiers":[
        {
            "category":"Autos & Motor Vehicles",
            "subcategory":"Automobile Sales",
            "type":"Retail Goods"
        }
    ],
    "sg:phone":"+1 203 483 3838",
    "sg:postcode":"06405",
    "sg:province":"CT",
    "sg:tags":[
        "car",
        "dealer"
    ],
    "sg:website":"www.saturnofbranford.com",
    "wof:name":"Saturn Of Branford",
    "wof:placetype":"venue"
},
  "geometry": {"coordinates":[-72.833895,41.275711],"type":"Point"}
}