{
  "type": "Feature",
  "properties": {
    "addr:full":"93 Joy Rd Woodstock CT 06281",
    "addr:housenumber":"93",
    "addr:postcode":"06281",
    "addr:street":"Joy Rd",
    "iso:country":"US",
    "sg:address":"93 Joy Rd",
    "sg:city":"Woodstock",
    "sg:classifiers":[
        {
            "category":"Professional",
            "subcategory":"Business Services",
            "type":"Services"
        }
    ],
    "sg:phone":"+1   ",
    "sg:postcode":"06281",
    "sg:province":"CT",
    "sg:tags":[
        "electronic",
        "automation",
        "design",
        "software"
    ],
    "wof:name":"Silicon Dimensions Inc",
    "wof:placetype":"venue"
},
  "geometry": {"coordinates":[-71.99230900000001,41.961338],"type":"Point"}
}