{
  "type": "Feature",
  "properties": {
    "addr:full":"1540 Pleasant Valley Rd Ste A Manchester CT 06042",
    "addr:housenumber":"1540",
    "addr:postcode":"06042",
    "addr:street":"Pleasant Valley Rd Ste A Manchester Ct",
    "iso:country":"US",
    "sg:address":"1540 Pleasant Valley Rd Ste A",
    "sg:city":"Manchester",
    "sg:classifiers":[
        {
            "category":"Professional",
            "type":"Services"
        },
        {
            "category":"Restaurant",
            "type":"Food & Drink"
        },
        {
            "category":"Bagels",
            "subcategory":"None",
            "type":"Food & Drink"
        },
        {
            "category":"Fast Food",
            "type":"Food & Drink"
        }
    ],
    "sg:phone":"+1 860 644 9025",
    "sg:postcode":"06042",
    "sg:province":"CT",
    "sg:tags":[
        "delivery",
        "take",
        "caterer"
    ],
    "wof:name":"Between Rounds Bakery Sandwich Cafe",
    "wof:placetype":"venue"
},
  "geometry": {"coordinates":[-72.558628,41.805127],"type":"Point"}
}