{
  "type": "Feature",
  "properties": {
    "iso:country":"US",
    "sg:address":"15 School St",
    "sg:city":"East Granby",
    "sg:classifiers":[
        {
            "category":"Health Services",
            "subcategory":"Doctor",
            "type":"Services"
        }
    ],
    "sg:phone":"+1   ",
    "sg:postcode":"06026",
    "sg:province":"CT",
    "wof:name":"Richard H Sikes DMD",
    "wof:placetype":"venue"
},
  "geometry": {"coordinates":[-72.72248,41.939765],"type":"Point"}
}