{
  "type": "Feature",
  "properties": {
    "addr:full":"2914 Fairfield Ave Bridgeport CT 06605",
    "addr:housenumber":"2914",
    "addr:postcode":"06605",
    "addr:street":"Fairfield Ave",
    "iso:country":"US",
    "sg:address":"2914 Fairfield Ave",
    "sg:city":"Bridgeport",
    "sg:classifiers":[
        {
            "category":"Personal",
            "subcategory":"Beauty Salon",
            "type":"Services"
        }
    ],
    "sg:phone":"+1 203 362 2570",
    "sg:postcode":"06605",
    "sg:province":"CT",
    "wof:name":"H & A Beauty Salon",
    "wof:placetype":"venue"
},
  "geometry": {"coordinates":[-73.22830500000001,41.156293],"type":"Point"}
}