{
  "type": "Feature",
  "properties": {
    "addr:full":"69 E Shore Dr Clinton CT 06413",
    "addr:housenumber":"69",
    "addr:postcode":"06413",
    "addr:street":"E Shore Dr",
    "iso:country":"US",
    "sg:address":"69 E Shore Dr",
    "sg:city":"Clinton",
    "sg:classifiers":[
        {
            "category":"Professional",
            "subcategory":"Management & Consulting",
            "type":"Services"
        }
    ],
    "sg:phone":"+1   ",
    "sg:postcode":"06413",
    "sg:province":"CT",
    "sg:tags":[
        "business"
    ],
    "wof:name":"Inspire Web Consulting LLC",
    "wof:placetype":"venue"
},
  "geometry": {"coordinates":[-72.55711700000001,41.295405],"type":"Point"}
}