{
  "type": "Feature",
  "properties": {
    "addr:full":"1938 State St Hamden CT 06517",
    "addr:housenumber":"1938",
    "addr:postcode":"06517",
    "addr:street":"State St",
    "iso:country":"US",
    "sg:address":"1938 State St",
    "sg:city":"Hamden",
    "sg:classifiers":[
        {
            "category":"Education",
            "subcategory":"Dance Studio",
            "type":"Public Place"
        }
    ],
    "sg:phone":"+1 203 782 6681",
    "sg:postcode":"06517",
    "sg:province":"CT",
    "sg:tags":[
        "instruction",
        "dancing"
    ],
    "wof:name":"O'Keefe Irish Dance Studio",
    "wof:placetype":"venue"
},
  "geometry": {"coordinates":[-72.900204,41.335515],"type":"Point"}
}