{
  "type": "Feature",
  "properties": {
    "addr:full":"98 Southfield Ave Stamford CT 06902",
    "addr:housenumber":"98",
    "addr:postcode":"06902",
    "addr:street":"Southfield Ave",
    "iso:country":"US",
    "sg:address":"98 Southfield Ave",
    "sg:city":"Stamford",
    "sg:classifiers":[
        {
            "category":"Recreation",
            "type":"Entertainment"
        },
        {
            "category":"Education",
            "subcategory":"Special Training",
            "type":"Public Place"
        }
    ],
    "sg:phone":"+1 203 353 9976",
    "sg:postcode":"06902",
    "sg:province":"CT",
    "sg:tags":[
        "charter",
        "safe",
        "instruction",
        "consulting",
        "boating",
        "marine",
        "boat"
    ],
    "wof:name":"Sound Environment Associates",
    "wof:placetype":"venue"
},
  "geometry": {"coordinates":[-73.54762599999999,41.036235],"type":"Point"}
}