{
  "type": "Feature",
  "properties": {
    "iso:country":"US",
    "sg:address":"115 Pocono Rd",
    "sg:city":"Brookfield",
    "sg:classifiers":[
        {
            "category":"Government",
            "subcategory":"Post Office",
            "type":"Public Place"
        }
    ],
    "sg:phone":"+1 203 775 2717",
    "sg:postcode":"06804",
    "sg:province":"CT",
    "wof:name":"US Post Office",
    "wof:placetype":"venue"
},
  "geometry": {"coordinates":[-73.393838,41.456369],"type":"Point"}
}