{
  "type": "Feature",
  "properties": {
    "addr:full":"39 Edmonds Rd Sherman CT 06784",
    "addr:housenumber":"39",
    "addr:postcode":"06784",
    "addr:street":"Edmonds Rd",
    "iso:country":"US",
    "sg:address":"39 Edmonds Rd",
    "sg:city":"Sherman",
    "sg:classifiers":[
        {
            "category":"Freight",
            "type":"Transportation"
        }
    ],
    "sg:phone":"+1 860 354 2608",
    "sg:postcode":"06784",
    "sg:province":"CT",
    "sg:tags":[
        "a",
        "business",
        "operates"
    ],
    "wof:name":"N I S C O",
    "wof:placetype":"venue"
},
  "geometry": {"coordinates":[-73.495062,41.620658],"type":"Point"}
}