{
  "type": "Feature",
  "properties": {
    "addr:full":"345 Whitney Ave New Haven CT 06511",
    "addr:housenumber":"345",
    "addr:postcode":"06511",
    "addr:street":"Whitney Ave",
    "iso:country":"US",
    "sg:address":"345 Whitney Ave",
    "sg:city":"New Haven",
    "sg:classifiers":[
        {
            "category":"Health Services",
            "subcategory":"Doctor",
            "type":"Services"
        }
    ],
    "sg:phone":"+1   ",
    "sg:postcode":"06511",
    "sg:province":"CT",
    "sg:tags":[
        "medical"
    ],
    "wof:name":"Boris Meandzija",
    "wof:placetype":"venue"
},
  "geometry": {"coordinates":[-72.918626,41.319935],"type":"Point"}
}