{
  "type": "Feature",
  "properties": {
    "iso:country":"US",
    "sg:address":"44 Cross Ln",
    "sg:city":"Cos Cob",
    "sg:classifiers":[
        {
            "category":"Professional",
            "subcategory":"Research",
            "type":"Services"
        }
    ],
    "sg:phone":"+1   ",
    "sg:postcode":"06807",
    "sg:province":"CT",
    "sg:tags":[
        "company"
    ],
    "wof:name":"David Glennn",
    "wof:placetype":"venue"
},
  "geometry": {"coordinates":[-73.601848,41.035917],"type":"Point"}
}