{
  "type": "Feature",
  "properties": {
    "addr:full":"250 Hudson St Hartford CT 06106",
    "addr:housenumber":"250",
    "addr:postcode":"06106",
    "addr:street":"Hudson St",
    "iso:country":"US",
    "sg:address":"250 Hudson St",
    "sg:city":"Hartford",
    "sg:classifiers":[
        {
            "category":"Social Services",
            "type":"Services"
        }
    ],
    "sg:phone":"+1   ",
    "sg:postcode":"06106",
    "sg:province":"CT",
    "wof:name":"Connectcut Jnior Rpub Assn Inc",
    "wof:placetype":"venue"
},
  "geometry": {"coordinates":[-72.678456,41.757746],"type":"Point"}
}