{
  "type": "Feature",
  "properties": {
    "iso:country":"US",
    "sg:address":"293 Audubon Ave",
    "sg:city":"Newington",
    "sg:classifiers":[
        {
            "category":"Wholesale",
            "subcategory":"Durable Goods & Equipment",
            "type":"Manufacturing & Wholesale Goods"
        }
    ],
    "sg:phone":"+1 860 666 2212",
    "sg:postcode":"06111",
    "sg:province":"CT",
    "wof:name":"Ould Brogue",
    "wof:placetype":"venue"
},
  "geometry": {"coordinates":[-72.72582,41.686853],"type":"Point"}
}