{
  "type": "Feature",
  "properties": {
    "addr:full":"2764 Whitney Ave Hamden CT 06518",
    "addr:housenumber":"2764",
    "addr:postcode":"06518",
    "addr:street":"Whitney Ave",
    "iso:country":"US",
    "sg:address":"2764 Whitney Ave",
    "sg:city":"Hamden",
    "sg:classifiers":[
        {
            "category":"Real Estate",
            "subcategory":"Real Estate Services",
            "type":"Services"
        },
        {
            "category":"Professional",
            "subcategory":"Lawyer & Legal Services",
            "type":"Services"
        },
        {
            "category":"Insurance",
            "subcategory":"Title Insurance",
            "type":"Services"
        }
    ],
    "sg:phone":"+1 203 230 8739",
    "sg:postcode":"06518",
    "sg:province":"CT",
    "sg:tags":[
        "attorney",
        "law",
        "business"
    ],
    "sg:website":"http://www.attybegemann.com",
    "wof:name":"Attny Paul H Begemann",
    "wof:placetype":"venue"
},
  "geometry": {"coordinates":[-72.89688,41.39606],"type":"Point"}
}