{
  "type": "Feature",
  "properties": {
    "iso:country":"US",
    "sg:address":"6 Anchor Ln",
    "sg:city":"Westport",
    "sg:classifiers":[
        {
            "category":"Arena",
            "subcategory":"Sports Club",
            "type":"Entertainment"
        }
    ],
    "sg:phone":"+1   ",
    "sg:postcode":"06880",
    "sg:province":"CT",
    "wof:name":"Shotgun Report LLC",
    "wof:placetype":"venue"
},
  "geometry": {"coordinates":[-73.350801,41.144245],"type":"Point"}
}