{
  "type": "Feature",
  "properties": {
    "iso:country":"US",
    "sg:address":"61 Paper Mill Rd",
    "sg:city":"New Milford",
    "sg:classifiers":[
        {
            "category":"Retail",
            "subcategory":"Repair Shop",
            "type":"Services"
        }
    ],
    "sg:phone":"+1   ",
    "sg:postcode":"06776",
    "sg:province":"CT",
    "wof:name":"Upholstery Shed",
    "wof:placetype":"venue"
},
  "geometry": {"coordinates":[-73.412266,41.608501],"type":"Point"}
}