{
  "type": "Feature",
  "properties": {
    "iso:country":"US",
    "sg:address":"138 Old Turnpike Rd",
    "sg:city":"Bristol",
    "sg:classifiers":[
        {
            "category":"Retail",
            "subcategory":"Repair Shop",
            "type":"Services"
        }
    ],
    "sg:phone":"+1   ",
    "sg:postcode":"06010",
    "sg:province":"CT",
    "sg:tags":[
        "jewelry"
    ],
    "wof:name":"Heritage Clock",
    "wof:placetype":"venue"
},
  "geometry": {"coordinates":[-72.896655,41.711796],"type":"Point"}
}