{
  "type": "Feature",
  "properties": {
    "iso:country":"US",
    "sg:address":"23 Lyme St",
    "sg:city":"Old Lyme",
    "sg:classifiers":[
        {
            "category":"Building & Trades",
            "subcategory":"Cleaning & Sanitation",
            "type":"Services"
        },
        {
            "category":"Shopping",
            "subcategory":"Antiques",
            "type":"Retail Goods"
        },
        {
            "category":"Home & Garden",
            "subcategory":"Carpets & Floor Coverings",
            "type":"Retail Goods"
        }
    ],
    "sg:phone":"+1 860 434 1167",
    "sg:postcode":"06371",
    "sg:province":"CT",
    "sg:tags":[
        "carpeting"
    ],
    "sg:website":"www.orientalrugsltd.com",
    "wof:name":"Oriental Rugs Ltd",
    "wof:placetype":"venue"
},
  "geometry": {"coordinates":[-72.330299,41.315201],"type":"Point"}
}