{
  "type": "Feature",
  "properties": {
    "iso:country":"US",
    "sg:address":"2300 State St",
    "sg:city":"Hamden",
    "sg:classifiers":[
        {
            "category":"Retail",
            "subcategory":"Auto Repair",
            "type":"Services"
        }
    ],
    "sg:phone":"+1   ",
    "sg:postcode":"06517",
    "sg:province":"CT",
    "sg:tags":[
        "parts",
        "truck"
    ],
    "wof:name":"Superior Spring & Mfg Co",
    "wof:placetype":"venue"
},
  "geometry": {"coordinates":[-72.895303,41.343503],"type":"Point"}
}