{
  "type": "Feature",
  "properties": {
    "addr:full":"171 Charles St Torrington CT 06790",
    "addr:housenumber":"171",
    "addr:postcode":"06790",
    "addr:street":"Charles St",
    "iso:country":"US",
    "sg:address":"171 Charles St",
    "sg:city":"Torrington",
    "sg:classifiers":[
        {
            "category":"Professional",
            "subcategory":"Computer Services",
            "type":"Services"
        }
    ],
    "sg:phone":"+1   ",
    "sg:postcode":"06790",
    "sg:province":"CT",
    "wof:name":"T&M Computer",
    "wof:placetype":"venue"
},
  "geometry": {"coordinates":[-73.106768,41.811114],"type":"Point"}
}