{
  "type": "Feature",
  "properties": {
    "addr:full":"520 Woodtick Rd Wolcott CT 06716",
    "addr:housenumber":"520",
    "addr:postcode":"06716",
    "addr:street":"Woodtick Rd Wolcott Ct",
    "iso:country":"US",
    "sg:address":"520 Woodtick Rd",
    "sg:city":"Wolcott",
    "sg:classifiers":[
        {
            "category":"Freight",
            "type":"Transportation"
        }
    ],
    "sg:phone":"+1 203 879 8577",
    "sg:postcode":"06716",
    "sg:province":"CT",
    "sg:tags":[
        "car",
        "pilot"
    ],
    "wof:name":"Blossom's Escort",
    "wof:placetype":"venue"
},
  "geometry": {"coordinates":[-72.977231,41.579588],"type":"Point"}
}