{
  "type": "Feature",
  "properties": {
    "addr:full":"7 Columbus Ave Greenwich CT 06830",
    "addr:housenumber":"7",
    "addr:postcode":"06830",
    "addr:street":"Columbus Ave",
    "iso:country":"US",
    "sg:address":"7 Columbus Ave",
    "sg:city":"Greenwich",
    "sg:classifiers":[
        {
            "category":"Professional",
            "subcategory":"Management & Consulting",
            "type":"Services"
        }
    ],
    "sg:phone":"+1   ",
    "sg:postcode":"06830",
    "sg:province":"CT",
    "sg:tags":[
        "business"
    ],
    "wof:name":"Pro-Vision",
    "wof:placetype":"venue"
},
  "geometry": {"coordinates":[-73.638814,41.020057],"type":"Point"}
}