{
  "type": "Feature",
  "properties": {
    "addr:full":"38 Orchard Dr Wilton CT 06897",
    "addr:housenumber":"38",
    "addr:postcode":"06897",
    "addr:street":"Orchard Dr",
    "iso:country":"US",
    "sg:address":"38 Orchard Dr",
    "sg:city":"Wilton",
    "sg:classifiers":[
        {
            "category":"Professional",
            "type":"Services"
        }
    ],
    "sg:phone":"+1 203 834 2611",
    "sg:postcode":"06897",
    "sg:province":"CT",
    "wof:name":"Peter Burns",
    "wof:placetype":"venue"
},
  "geometry": {"coordinates":[-73.403817,41.21405],"type":"Point"}
}