{
  "type": "Feature",
  "properties": {
    "addr:full":"1035 Shepard Ave Hamden CT 06514",
    "addr:housenumber":"1035",
    "addr:postcode":"06514",
    "addr:street":"Shepard Ave",
    "iso:country":"US",
    "sg:address":"1035 Shepard Ave",
    "sg:city":"Hamden",
    "sg:classifiers":[
        {
            "category":"Juice Bar",
            "subcategory":"None",
            "type":"Food & Drink"
        },
        {
            "category":"Shopping",
            "subcategory":"Crafts & Fabrics",
            "type":"Retail Goods"
        },
        {
            "category":"Shopping",
            "subcategory":"Party Supplies",
            "type":"Retail Goods"
        },
        {
            "category":"Shopping",
            "subcategory":"Gifts & Souvenirs",
            "type":"Retail Goods"
        },
        {
            "category":"Retail",
            "subcategory":"Funeral Services",
            "type":"Services"
        },
        {
            "category":"Shopping",
            "subcategory":"Florist",
            "type":"Retail Goods"
        }
    ],
    "sg:phone":"+1 800 382 8133",
    "sg:postcode":"06514",
    "sg:province":"CT",
    "sg:tags":[
        "plant",
        "etc-retail",
        "fruit",
        "dried",
        "wedding",
        "basket",
        "trees-silk",
        "flowers"
    ],
    "sg:website":"http://www.flowersfromthefarm.org",
    "wof:name":"Flowers From The Farm",
    "wof:placetype":"venue"
},
  "geometry": {"coordinates":[-72.923928,41.401665],"type":"Point"}
}