{
  "type": "Feature",
  "properties": {
    "addr:full":"4 Artic St Greenwich CT 06830",
    "addr:housenumber":"4",
    "addr:postcode":"06830",
    "addr:street":"Artic St Greenwich Ct",
    "iso:country":"US",
    "sg:address":"4 Artic St",
    "sg:city":"Greenwich",
    "sg:classifiers":[
        {
            "category":"Building & Trades",
            "subcategory":"Electrical",
            "type":"Services"
        }
    ],
    "sg:phone":"+1 203 869 8862",
    "sg:postcode":"06830",
    "sg:province":"CT",
    "sg:tags":[
        "electric",
        "contractor"
    ],
    "wof:name":"John Antonelli Contractors Inc",
    "wof:placetype":"venue"
},
  "geometry": {"coordinates":[-73.64105499999999,41.019667],"type":"Point"}
}