{
  "type": "Feature",
  "properties": {
    "iso:country":"US",
    "sg:address":"54 Kelley St",
    "sg:city":"Bristol",
    "sg:classifiers":[
        {
            "category":"Professional",
            "type":"Services"
        }
    ],
    "sg:phone":"+1 860 582 3252",
    "sg:postcode":"06010",
    "sg:province":"CT",
    "wof:name":"Edgar Marquis Mason LLC",
    "wof:placetype":"venue"
},
  "geometry": {"coordinates":[-72.948403,41.675602],"type":"Point"}
}