{
  "type": "Feature",
  "properties": {
    "addr:full":"24 Prospect St New Hartford CT 06057",
    "addr:housenumber":"24",
    "addr:postcode":"06057",
    "addr:street":"Prospect St New;Ct",
    "iso:country":"US",
    "sg:address":"24 Prospect St",
    "sg:city":"New Hartford",
    "sg:classifiers":[
        {
            "category":"Building & Trades",
            "subcategory":"Electrical",
            "type":"Services"
        }
    ],
    "sg:phone":"+1 860 379 9168",
    "sg:postcode":"06057",
    "sg:province":"CT",
    "sg:tags":[
        "electrical",
        "contractor"
    ],
    "wof:name":"L & D Electric",
    "wof:placetype":"venue"
},
  "geometry": {"coordinates":[-72.976703,41.880646],"type":"Point"}
}