{
  "type": "Feature",
  "properties": {
    "iso:country":"US",
    "sg:address":"5 Rose Ln",
    "sg:city":"North Haven",
    "sg:classifiers":[
        {
            "category":"Professional",
            "subcategory":"Accounting & Tax Preparation",
            "type":"Services"
        }
    ],
    "sg:phone":"+1   ",
    "sg:postcode":"06473",
    "sg:province":"CT",
    "wof:name":"Chester M Katzman",
    "wof:placetype":"venue"
},
  "geometry": {"coordinates":[-72.882743,41.384956],"type":"Point"}
}