{
  "type": "Feature",
  "properties": {
    "iso:country":"US",
    "sg:address":"32 Loughlin Rd",
    "sg:city":"Oxford",
    "sg:classifiers":[
        {
            "category":"Building & Trades",
            "subcategory":"Plumbing",
            "type":"Services"
        }
    ],
    "sg:phone":"+1 203 736 0684",
    "sg:postcode":"06478",
    "sg:province":"CT",
    "sg:tags":[
        "septic"
    ],
    "wof:name":"P & D Septic Svc",
    "wof:placetype":"venue"
},
  "geometry": {"coordinates":[-73.163742,41.397872],"type":"Point"}
}