{
  "type": "Feature",
  "properties": {
    "iso:country":"US",
    "sg:address":"45 Woodmont Rd",
    "sg:city":"Milford",
    "sg:classifiers":[
        {
            "category":"Manufacturing",
            "subcategory":"Tools & Machinery",
            "type":"Manufacturing & Wholesale Goods"
        }
    ],
    "sg:phone":"+1 203 882 5640",
    "sg:postcode":"06460",
    "sg:province":"CT",
    "sg:tags":[
        "computer",
        "parts",
        "supply"
    ],
    "wof:name":"Practical Automation Inc",
    "wof:placetype":"venue"
},
  "geometry": {"coordinates":[-73.026892,41.242173],"type":"Point"}
}