{
  "type": "Feature",
  "properties": {
    "addr:full":"31 Hewitt Dr Uncasville CT 06382",
    "addr:housenumber":"31",
    "addr:postcode":"06382",
    "addr:street":"Hewitt Dr",
    "iso:country":"US",
    "sg:address":"31 Hewitt Dr",
    "sg:city":"Uncasville",
    "sg:classifiers":[
        {
            "category":"Building & Trades",
            "subcategory":"Plumbing",
            "type":"Services"
        }
    ],
    "sg:phone":"+1 860 848 7749",
    "sg:postcode":"06382",
    "sg:province":"CT",
    "sg:tags":[
        "plumbing",
        "contractor"
    ],
    "wof:name":"Maurice C Owen",
    "wof:placetype":"venue"
},
  "geometry": {"coordinates":[-72.10973,41.427787],"type":"Point"}
}