{
  "type": "Feature",
  "properties": {
    "addr:full":"185 Boston Post Rd Orange CT 06477",
    "addr:housenumber":"185",
    "addr:postcode":"06477",
    "addr:street":"Boston Post Rd",
    "iso:country":"US",
    "sg:address":"185 Boston Post Rd",
    "sg:city":"Orange",
    "sg:classifiers":[
        {
            "category":"Travel",
            "subcategory":"Travel Agent",
            "type":"Entertainment"
        }
    ],
    "sg:phone":"+1 203 799 2302",
    "sg:postcode":"06477",
    "sg:province":"CT",
    "sg:tags":[
        "agency",
        "bureau"
    ],
    "wof:name":"Liberty Travel Inc",
    "wof:placetype":"venue"
},
  "geometry": {"coordinates":[-72.99753699999999,41.270151],"type":"Point"}
}