{
  "type": "Feature",
  "properties": {
    "iso:country":"US",
    "sg:address":"13 High Field Ln",
    "sg:city":"Madison",
    "sg:classifiers":[
        {
            "category":"Professional",
            "subcategory":"Management & Consulting",
            "type":"Services"
        }
    ],
    "sg:phone":"+1 203 245 2554",
    "sg:postcode":"06443",
    "sg:province":"CT",
    "sg:tags":[
        "marketing",
        "program"
    ],
    "wof:name":"Pacific Basin Marketing Co",
    "wof:placetype":"venue"
},
  "geometry": {"coordinates":[-72.582222,41.300176],"type":"Point"}
}