{
  "type": "Feature",
  "properties": {
    "iso:country":"US",
    "sg:address":"6 Briar Ln",
    "sg:city":"New Milford",
    "sg:classifiers":[
        {
            "category":"Retail",
            "subcategory":"Repair Shop",
            "type":"Services"
        }
    ],
    "sg:phone":"+1   ",
    "sg:postcode":"06776",
    "sg:province":"CT",
    "wof:name":"RPM Septic Systems",
    "wof:placetype":"venue"
},
  "geometry": {"coordinates":[-73.43123199999999,41.617039],"type":"Point"}
}