{
  "type": "Feature",
  "properties": {
    "addr:full":"1200 Main St Bridgeport CT 06604",
    "addr:housenumber":"1200",
    "addr:postcode":"06604",
    "addr:street":"Main St",
    "iso:country":"US",
    "sg:address":"1200 Main St",
    "sg:city":"Bridgeport",
    "sg:classifiers":[
        {
            "category":"Manufacturing",
            "subcategory":"Printing",
            "type":"Manufacturing & Wholesale Goods"
        }
    ],
    "sg:phone":"+1 203 333 2651",
    "sg:postcode":"06604",
    "sg:province":"CT",
    "sg:tags":[
        "publisher"
    ],
    "wof:name":"International Publishers Assn",
    "wof:placetype":"venue"
},
  "geometry": {"coordinates":[-73.18988400000001,41.180959],"type":"Point"}
}