{
  "type": "Feature",
  "properties": {
    "addr:full":"111 Peaceable Hill Rd Ridgefield CT 06877",
    "addr:housenumber":"111",
    "addr:postcode":"06877",
    "addr:street":"Peaceable Hill Rd",
    "iso:country":"US",
    "sg:address":"111 Peaceable Hill Rd",
    "sg:city":"Ridgefield",
    "sg:classifiers":[
        {
            "category":"Manufacturing",
            "subcategory":"Printing",
            "type":"Manufacturing & Wholesale Goods"
        }
    ],
    "sg:phone":"+1 203 438 6501",
    "sg:postcode":"06877",
    "sg:province":"CT",
    "sg:tags":[
        "newspaper"
    ],
    "wof:name":"Ridgefield Paper",
    "wof:placetype":"venue"
},
  "geometry": {"coordinates":[-73.527552,41.278284],"type":"Point"}
}