{
  "type": "Feature",
  "properties": {
    "addr:full":"28 Mooreland Rd Greenwich NY 06831",
    "addr:housenumber":"28",
    "addr:postcode":"06831",
    "addr:street":"Mooreland Rd",
    "iso:country":"US",
    "sg:address":"28 Mooreland Rd",
    "sg:city":"Greenwich",
    "sg:classifiers":[
        {
            "category":"Organizations",
            "subcategory":"Membership Organization",
            "type":"Services"
        }
    ],
    "sg:phone":"+1   ",
    "sg:postcode":"06831",
    "sg:province":"NY",
    "wof:name":"Nemerov Charitable Foundation",
    "wof:placetype":"venue"
},
  "geometry": {"coordinates":[-73.670373,41.096758],"type":"Point"}
}