{
  "type": "Feature",
  "properties": {
    "addr:full":"103 Caeser Dr Bristol CT 06010",
    "addr:housenumber":"103",
    "addr:postcode":"06010",
    "addr:street":"Caeser Dr Bristol Ct",
    "iso:country":"US",
    "sg:address":"103 Caeser Dr",
    "sg:city":"Bristol",
    "sg:classifiers":[
        {
            "category":"Insurance",
            "subcategory":"Hazard Insurance",
            "type":"Services"
        }
    ],
    "sg:phone":"+1 860 589 2277",
    "sg:postcode":"06010",
    "sg:province":"CT",
    "sg:tags":[
        "carrier"
    ],
    "wof:name":"Michael Michalak",
    "wof:placetype":"venue"
},
  "geometry": {"coordinates":[-72.91875899999999,41.718311],"type":"Point"}
}