{
  "type": "Feature",
  "properties": {
    "iso:country":"US",
    "sg:address":"355 High St",
    "sg:city":"Willimantic",
    "sg:classifiers":[
        {
            "category":"Education",
            "subcategory":"School",
            "type":"Public Place"
        }
    ],
    "sg:phone":"+1 860 465 2460",
    "sg:postcode":"06226",
    "sg:province":"CT",
    "sg:tags":[
        "high",
        "middle",
        "elementary"
    ],
    "wof:name":"Windham School District",
    "wof:placetype":"venue"
},
  "geometry": {"coordinates":[-72.215907,41.723994],"type":"Point"}
}