{
  "type": "Feature",
  "properties": {
    "iso:country":"US",
    "sg:address":"9 Union St",
    "sg:city":"Southbury",
    "sg:classifiers":[
        {
            "category":"Home & Garden",
            "subcategory":"Garden Supply",
            "type":"Retail Goods"
        }
    ],
    "sg:phone":"+1 800 582 8843",
    "sg:postcode":"06483",
    "sg:province":"CT",
    "sg:tags":[
        "control",
        "wholesale",
        "animal",
        "devices",
        "bird"
    ],
    "wof:name":"Jpf Distributors LLC",
    "wof:placetype":"venue"
},
  "geometry": {"coordinates":[-73.06871700000001,41.387969],"type":"Point"}
}