{
  "type": "Feature",
  "properties": {
    "addr:full":"31 Church Hill Rd Washington Depot CT 06794",
    "addr:housenumber":"31",
    "addr:postcode":"06794",
    "addr:street":"Church Hill Rd;Depot Ct",
    "iso:country":"US",
    "sg:address":"31 Church Hill Rd",
    "sg:city":"Washington Depot",
    "sg:classifiers":[
        {
            "category":"Retail",
            "subcategory":"Portrait Studio",
            "type":"Services"
        }
    ],
    "sg:phone":"+1   ",
    "sg:postcode":"06794",
    "sg:province":"CT",
    "sg:tags":[
        "photo"
    ],
    "wof:name":"Rogers Photography",
    "wof:placetype":"venue"
},
  "geometry": {"coordinates":[-73.329168,41.644689],"type":"Point"}
}