{
  "type": "Feature",
  "properties": {
    "addr:full":"164 Main St Danielson CT 06239",
    "addr:housenumber":"164",
    "addr:postcode":"06239",
    "addr:street":"Main St",
    "iso:country":"US",
    "sg:address":"164 Main St",
    "sg:city":"Danielson",
    "sg:classifiers":[
        {
            "category":"Personal",
            "type":"Services"
        }
    ],
    "sg:phone":"+1   ",
    "sg:postcode":"06239",
    "sg:province":"CT",
    "wof:name":"Sacred Ink",
    "wof:placetype":"venue"
},
  "geometry": {"coordinates":[-71.87935299999999,41.808952],"type":"Point"}
}