{
  "type": "Feature",
  "properties": {
    "addr:full":"5 Woodland Rd New Hartford CT 06057",
    "addr:housenumber":"5",
    "addr:postcode":"06057",
    "addr:street":"Woodland Rd;Ct",
    "iso:country":"US",
    "sg:address":"5 Woodland Rd",
    "sg:city":"New Hartford",
    "sg:classifiers":[
        {
            "category":"Professional",
            "subcategory":"Accounting & Tax Preparation",
            "type":"Services"
        }
    ],
    "sg:phone":"+1   ",
    "sg:postcode":"06057",
    "sg:province":"CT",
    "wof:name":"Stephen J Morholt CPA",
    "wof:placetype":"venue"
},
  "geometry": {"coordinates":[-73.058465,41.823476],"type":"Point"}
}