{
  "type": "Feature",
  "properties": {
    "iso:country":"US",
    "sg:address":"285 E Center St",
    "sg:city":"Manchester",
    "sg:classifiers":[
        {
            "category":"Banks & Credit Unions",
            "subcategory":"Bank",
            "type":"Services"
        }
    ],
    "sg:phone":"+1 860 645 4440",
    "sg:postcode":"06040",
    "sg:province":"CT",
    "sg:tags":[
        "federal",
        "savings",
        "institution"
    ],
    "wof:name":"Savings Bank of Manchester",
    "wof:placetype":"venue"
},
  "geometry": {"coordinates":[-72.50912099999999,41.777945],"type":"Point"}
}