{
  "type": "Feature",
  "properties": {
    "iso:country":"US",
    "sg:address":"907 Cove Rd",
    "sg:city":"Stamford",
    "sg:classifiers":[
        {
            "category":"Retail",
            "subcategory":"Auto Repair",
            "type":"Services"
        }
    ],
    "sg:phone":"+1   ",
    "sg:postcode":"06902",
    "sg:province":"CT",
    "sg:tags":[
        "general"
    ],
    "wof:name":"Landauro Service",
    "wof:placetype":"venue"
},
  "geometry": {"coordinates":[-73.508726,41.048872],"type":"Point"}
}