{
  "type": "Feature",
  "properties": {
    "addr:full":"445 Oakland St Manchester CT 06042",
    "addr:housenumber":"445",
    "addr:postcode":"06042",
    "addr:street":"Oakland St",
    "iso:country":"US",
    "sg:address":"445 Oakland St",
    "sg:city":"Manchester",
    "sg:classifiers":[
        {
            "category":"Retail",
            "subcategory":"Repair Shop",
            "type":"Services"
        }
    ],
    "sg:phone":"+1   ",
    "sg:postcode":"06042",
    "sg:province":"CT",
    "wof:name":"B & B",
    "wof:placetype":"venue"
},
  "geometry": {"coordinates":[-72.517054,41.810469],"type":"Point"}
}