{
  "type": "Feature",
  "properties": {
    "addr:full":"28 Hitchcock Rd Westport CT 06880",
    "addr:housenumber":"28",
    "addr:postcode":"06880",
    "addr:street":"Hitchcock Rd",
    "iso:country":"US",
    "sg:address":"28 Hitchcock Rd",
    "sg:city":"Westport",
    "sg:classifiers":[
        {
            "category":"Professional",
            "subcategory":"Business Services",
            "type":"Services"
        }
    ],
    "sg:phone":"+1 203 222 0492",
    "sg:postcode":"06880",
    "sg:province":"CT",
    "sg:tags":[
        "embroidery"
    ],
    "wof:name":"Monogram Express Of Westport",
    "wof:placetype":"venue"
},
  "geometry": {"coordinates":[-73.34958399999999,41.157252],"type":"Point"}
}