{
  "type": "Feature",
  "properties": {
    "iso:country":"US",
    "sg:address":"30 E Franklin St",
    "sg:city":"Danbury",
    "sg:phone":"+1 203 790 1406",
    "sg:postcode":"06810",
    "sg:province":"CT",
    "sg:tags":[
        "oil"
    ],
    "wof:name":"Jennings Oil Co",
    "wof:placetype":"venue"
},
  "geometry": {"coordinates":[-73.457267,41.399941],"type":"Point"}
}