{
  "type": "Feature",
  "properties": {
    "iso:country":"US",
    "sg:address":"457 State St",
    "sg:city":"North Haven",
    "sg:classifiers":[
        {
            "category":"Manufacturing",
            "subcategory":"Tools & Machinery",
            "type":"Manufacturing & Wholesale Goods"
        }
    ],
    "sg:phone":"+1 203 248 6397",
    "sg:postcode":"06473",
    "sg:province":"CT",
    "sg:tags":[
        "power",
        "mechanical"
    ],
    "sg:website":"www.polyclutch.com",
    "wof:name":"Custom Products",
    "wof:placetype":"venue"
},
  "geometry": {"coordinates":[-72.887506,41.363558],"type":"Point"}
}