{
  "type": "Feature",
  "properties": {
    "addr:full":"5 Cherry St East Hartford CT 06108",
    "addr:housenumber":"5",
    "addr:postcode":"06108",
    "addr:street":"Cherry St",
    "iso:country":"US",
    "sg:address":"5 Cherry St",
    "sg:city":"East Hartford",
    "sg:classifiers":[
        {
            "category":"Retail",
            "subcategory":"Car Wash",
            "type":"Services"
        }
    ],
    "sg:phone":"+1   ",
    "sg:postcode":"06108",
    "sg:province":"CT",
    "sg:tags":[
        "carwash"
    ],
    "wof:name":"Diamond Detail",
    "wof:placetype":"venue"
},
  "geometry": {"coordinates":[-72.658734,41.773166],"type":"Point"}
}