{
  "type": "Feature",
  "properties": {
    "addr:full":"1590 E Main St Torrington CT 06790",
    "addr:housenumber":"1590",
    "addr:postcode":"06790",
    "addr:street":"E Main St",
    "iso:country":"US",
    "sg:address":"1590 E Main St",
    "sg:city":"Torrington",
    "sg:classifiers":[
        {
            "category":"Shopping",
            "subcategory":"Clothing, Apparel, & Fashions",
            "type":"Retail Goods"
        }
    ],
    "sg:phone":"+1 860 489 8195",
    "sg:postcode":"06790",
    "sg:province":"CT",
    "sg:tags":[
        "boy",
        "girl",
        "scout",
        "supply"
    ],
    "wof:name":"Jinxs Scout Supply",
    "wof:placetype":"venue"
},
  "geometry": {"coordinates":[-73.086043,41.819993],"type":"Point"}
}