{
  "type": "Feature",
  "properties": {
    "iso:country":"US",
    "sg:address":"125 E Putnam Ave",
    "sg:city":"Greenwich",
    "sg:classifiers":[
        {
            "category":"Banks & Credit Unions",
            "subcategory":"Bank",
            "type":"Services"
        }
    ],
    "sg:phone":"+1 203 622 4943",
    "sg:postcode":"06830",
    "sg:province":"CT",
    "sg:tags":[
        "state"
    ],
    "wof:name":"PNC",
    "wof:placetype":"venue"
},
  "geometry": {"coordinates":[-73.623356,41.034551],"type":"Point"}
}