{
  "type": "Feature",
  "properties": {
    "addr:full":"250 Meriden Rd Waterbury CT 06705",
    "addr:housenumber":"250",
    "addr:postcode":"06705",
    "addr:street":"Meriden Rd",
    "iso:country":"US",
    "sg:address":"250 Meriden Rd",
    "sg:city":"Waterbury",
    "sg:classifiers":[
        {
            "category":"Restaurant",
            "type":"Food & Drink"
        }
    ],
    "sg:phone":"+1 203 753 7500",
    "sg:postcode":"06705",
    "sg:province":"CT",
    "sg:tags":[
        "delicatessen"
    ],
    "wof:name":"Mike's Corner Deli",
    "wof:placetype":"venue"
},
  "geometry": {"coordinates":[-73.010943,41.55019],"type":"Point"}
}