{
  "type": "Feature",
  "properties": {
    "addr:full":"418 Orange St New Haven CT 06511",
    "addr:housenumber":"418",
    "addr:postcode":"06511",
    "addr:street":"Orange St",
    "iso:country":"US",
    "sg:address":"418 Orange St",
    "sg:city":"New Haven",
    "sg:classifiers":[
        {
            "category":"Social Services",
            "type":"Services"
        }
    ],
    "sg:phone":"+1   ",
    "sg:postcode":"06511",
    "sg:province":"CT",
    "wof:name":"Gaynor Mark Clnical Social Wkr",
    "wof:placetype":"venue"
},
  "geometry": {"coordinates":[-72.92013,41.311058],"type":"Point"}
}