{
  "type": "Feature",
  "properties": {
    "addr:full":"12 Echo Ln Simsbury CT 06070",
    "addr:housenumber":"12",
    "addr:postcode":"06070",
    "addr:street":"Echo Ln",
    "iso:country":"US",
    "sg:address":"12 Echo Ln",
    "sg:city":"Simsbury",
    "sg:classifiers":[
        {
            "category":"Professional",
            "subcategory":"Management & Consulting",
            "type":"Services"
        }
    ],
    "sg:phone":"+1   ",
    "sg:postcode":"06070",
    "sg:province":"CT",
    "wof:name":"Tyee Management Associates",
    "wof:placetype":"venue"
},
  "geometry": {"coordinates":[-72.823215,41.886115],"type":"Point"}
}