{
  "type": "Feature",
  "properties": {
    "iso:country":"US",
    "sg:address":"554 Long Hill Rd",
    "sg:city":"Groton",
    "sg:classifiers":[
        {
            "category":"Insurance",
            "subcategory":"Insurance Agent",
            "type":"Services"
        }
    ],
    "sg:phone":"+1 860 449 9060",
    "sg:postcode":"06340",
    "sg:province":"CT",
    "wof:name":"Allstate",
    "wof:placetype":"venue"
},
  "geometry": {"coordinates":[-72.059539,41.353327],"type":"Point"}
}