{
  "type": "Feature",
  "properties": {
    "iso:country":"US",
    "sg:address":"3 Colby Ln",
    "sg:city":"Danbury",
    "sg:classifiers":[
        {
            "category":"Building & Trades",
            "subcategory":"Construction",
            "type":"Services"
        }
    ],
    "sg:phone":"+1 203 797 9729",
    "sg:postcode":"06810",
    "sg:province":"CT",
    "sg:tags":[
        "concrete",
        "contractor"
    ],
    "wof:name":"Aveiro Construction Corp",
    "wof:placetype":"venue"
},
  "geometry": {"coordinates":[-73.43577500000001,41.387756],"type":"Point"}
}