{
  "type": "Feature",
  "properties": {
    "addr:full":"45 Bayberry Ln Easton CT 06612",
    "addr:housenumber":"45",
    "addr:postcode":"06612",
    "addr:street":"Bayberry Ln",
    "iso:country":"US",
    "sg:address":"45 Bayberry Ln",
    "sg:city":"Easton",
    "sg:classifiers":[
        {
            "category":"Building & Trades",
            "subcategory":"Electrical",
            "type":"Services"
        }
    ],
    "sg:phone":"+1 203 268 6777",
    "sg:postcode":"06612",
    "sg:province":"CT",
    "sg:tags":[
        "electrical",
        "contractor"
    ],
    "wof:name":"Bayberry Electric Co",
    "wof:placetype":"venue"
},
  "geometry": {"coordinates":[-73.283632,41.277377],"type":"Point"}
}