{
  "type": "Feature",
  "properties": {
    "iso:country":"US",
    "sg:address":"2 Stamford Pl",
    "sg:city":"Stamford",
    "sg:classifiers":[
        {
            "category":"Professional",
            "subcategory":"Lawyer & Legal Services",
            "type":"Services"
        }
    ],
    "sg:phone":"+1   ",
    "sg:postcode":"06902",
    "sg:province":"CT",
    "wof:name":"Hedin Randi-Jean Atty",
    "wof:placetype":"venue"
},
  "geometry": {"coordinates":[-73.549525,41.044958],"type":"Point"}
}