{
  "type": "Feature",
  "properties": {
    "iso:country":"US",
    "sg:address":"30 Hawleyville Rd",
    "sg:city":"Hawleyville",
    "sg:classifiers":[
        {
            "category":"Government",
            "subcategory":"Post Office",
            "type":"Public Place"
        }
    ],
    "sg:phone":"+1 203 270 6062",
    "sg:postcode":"06470",
    "sg:province":"CT",
    "wof:name":"US Post Office",
    "wof:placetype":"venue"
},
  "geometry": {"coordinates":[-73.35438600000001,41.431799],"type":"Point"}
}