{
  "type": "Feature",
  "properties": {
    "iso:country":"US",
    "sg:address":"134 Medford St",
    "sg:city":"Bristol",
    "sg:classifiers":[
        {
            "category":"Professional",
            "subcategory":"Business Services",
            "type":"Services"
        }
    ],
    "sg:phone":"+1   ",
    "sg:postcode":"06010",
    "sg:province":"CT",
    "wof:name":"L Union Des Franco Americ",
    "wof:placetype":"venue"
},
  "geometry": {"coordinates":[-72.934084,41.692614],"type":"Point"}
}