{
  "type": "Feature",
  "properties": {
    "iso:country":"US",
    "sg:address":"37 Bossie Rd",
    "sg:city":"Waterbury",
    "sg:classifiers":[
        {
            "category":"Building & Trades",
            "subcategory":"Construction",
            "type":"Services"
        }
    ],
    "sg:phone":"+1 203 757 8029",
    "sg:postcode":"06704",
    "sg:province":"CT",
    "sg:tags":[
        "masonry",
        "contractor"
    ],
    "wof:name":"Sammy Masonry",
    "wof:placetype":"venue"
},
  "geometry": {"coordinates":[-73.032304,41.603211],"type":"Point"}
}