{
  "type": "Feature",
  "properties": {
    "iso:country":"US",
    "sg:address":"131 Buckley Hwy",
    "sg:city":"Stafford Springs",
    "sg:classifiers":[
        {
            "category":"Professional",
            "subcategory":"Management & Consulting",
            "type":"Services"
        }
    ],
    "sg:phone":"+1   ",
    "sg:postcode":"06076",
    "sg:province":"CT",
    "wof:name":"Pohle Partners Inc",
    "wof:placetype":"venue"
},
  "geometry": {"coordinates":[-72.27134700000001,41.952327],"type":"Point"}
}