{
  "type": "Feature",
  "properties": {
    "addr:full":"63 Ancient Hwy Oxford CT 06478",
    "addr:housenumber":"63",
    "addr:postcode":"06478",
    "addr:street":"Ancient Hwy Oxford Ct",
    "iso:country":"US",
    "sg:address":"63 Ancient Hwy",
    "sg:city":"Oxford",
    "sg:classifiers":[
        {
            "category":"Organizations",
            "subcategory":"Religious Organization",
            "type":"Services"
        }
    ],
    "sg:phone":"+1 203 888 3663",
    "sg:postcode":"06478",
    "sg:province":"CT",
    "sg:tags":[
        "church"
    ],
    "wof:name":"Woodland Church Of Christ",
    "wof:placetype":"venue"
},
  "geometry": {"coordinates":[-73.130865,41.426912],"type":"Point"}
}