{
  "type": "Feature",
  "properties": {
    "iso:country":"US",
    "sg:address":"1820 E Main St",
    "sg:city":"Waterbury",
    "sg:classifiers":[
        {
            "category":"Food & Beverages",
            "subcategory":"Liquor & Beverages",
            "type":"Retail Goods"
        }
    ],
    "sg:phone":"+1 203 756 3312",
    "sg:postcode":"06705",
    "sg:province":"CT",
    "wof:name":"Hamilton Liquors",
    "wof:placetype":"venue"
},
  "geometry": {"coordinates":[-73.011691,41.544789],"type":"Point"}
}