{
  "type": "Feature",
  "properties": {
    "iso:country":"US",
    "sg:address":"42 Beach Dr",
    "sg:city":"Harwinton",
    "sg:classifiers":[
        {
            "category":"Organizations",
            "subcategory":"Community Association",
            "type":"Services"
        }
    ],
    "sg:phone":"+1   ",
    "sg:postcode":"06791",
    "sg:province":"CT",
    "wof:name":"St Peter Drum Corp Inc",
    "wof:placetype":"venue"
},
  "geometry": {"coordinates":[-73.082476,41.785299],"type":"Point"}
}