{
  "type": "Feature",
  "properties": {
    "iso:country":"US",
    "sg:address":"28 Park St",
    "sg:city":"Putnam",
    "sg:classifiers":[
        {
            "category":"Social Services",
            "type":"Services"
        }
    ],
    "sg:phone":"+1   ",
    "sg:postcode":"06260",
    "sg:province":"CT",
    "wof:name":"Center For Intrprsnal Rlations",
    "wof:placetype":"venue"
},
  "geometry": {"coordinates":[-71.90512099999999,41.908446],"type":"Point"}
}