{
  "type": "Feature",
  "properties": {
    "iso:country":"US",
    "sg:address":"86 E Wharf Rd",
    "sg:city":"Madison",
    "sg:classifiers":[
        {
            "category":"Professional",
            "type":"Services"
        }
    ],
    "sg:phone":"+1 203 245 7993",
    "sg:postcode":"06443",
    "sg:province":"CT",
    "wof:name":"Henry Petry",
    "wof:placetype":"venue"
},
  "geometry": {"coordinates":[-72.59070699999999,41.273752],"type":"Point"}
}