{
  "type": "Feature",
  "properties": {
    "iso:country":"US",
    "sg:address":"154 Grace Church St",
    "sg:city":"Port Chester",
    "sg:classifiers":[
        {
            "category":"Real Estate",
            "subcategory":"Real Estate Agent",
            "type":"Services"
        }
    ],
    "sg:phone":"+1 914 937 2924",
    "sg:postcode":"10573",
    "sg:province":"CT",
    "wof:name":"Rpk Realty",
    "wof:placetype":"venue"
},
  "geometry": {"coordinates":[-73.66593399999999,40.992359],"type":"Point"}
}