{
  "type": "Feature",
  "properties": {
    "addr:full":"163 Elm St New Haven CT 06511",
    "addr:housenumber":"163",
    "addr:postcode":"06511",
    "addr:street":"Elm St",
    "iso:country":"US",
    "sg:address":"163 Elm St",
    "sg:city":"New Haven",
    "sg:classifiers":[
        {
            "category":"Wholesale",
            "subcategory":"Machinery & Supplies",
            "type":"Manufacturing & Wholesale Goods"
        }
    ],
    "sg:phone":"+1 203 865 0107",
    "sg:postcode":"06511",
    "sg:province":"CT",
    "sg:tags":[
        "compressor",
        "gas"
    ],
    "wof:name":"Liner Brothers Inc",
    "wof:placetype":"venue"
},
  "geometry": {"coordinates":[-72.926216,41.309108],"type":"Point"}
}