{
  "type": "Feature",
  "properties": {
    "addr:full":"279 Pearl St Seymour CT 06483",
    "addr:housenumber":"279",
    "addr:postcode":"06483",
    "addr:street":"Pearl St",
    "iso:country":"US",
    "sg:address":"279 Pearl St",
    "sg:city":"Seymour",
    "sg:classifiers":[
        {
            "category":"Manufacturing",
            "subcategory":"Tools & Machinery",
            "type":"Manufacturing & Wholesale Goods"
        }
    ],
    "sg:phone":"+1   ",
    "sg:postcode":"06483",
    "sg:province":"CT",
    "sg:tags":[
        "mfg",
        "repair",
        "industrial",
        "welding"
    ],
    "wof:name":"Phoenix Machine",
    "wof:placetype":"venue"
},
  "geometry": {"coordinates":[-73.061403,41.395188],"type":"Point"}
}