{
  "type": "Feature",
  "properties": {
    "iso:country":"US",
    "sg:address":"988 Poquonnock Rd",
    "sg:city":"Groton",
    "sg:classifiers":[
        {
            "category":"Retail",
            "subcategory":"Laundry & Dry Cleaning",
            "type":"Services"
        }
    ],
    "sg:phone":"+1   ",
    "sg:postcode":"06340",
    "sg:province":"CT",
    "wof:name":"James Laundromat & Dry Clrs",
    "wof:placetype":"venue"
},
  "geometry": {"coordinates":[-72.05190899999999,41.346891],"type":"Point"}
}