{
  "type": "Feature",
  "properties": {
    "iso:country":"US",
    "sg:address":"21 Sanford Rd",
    "sg:city":"Woodbridge",
    "sg:classifiers":[
        {
            "category":"Government",
            "subcategory":"Office",
            "type":"Public Place"
        }
    ],
    "sg:phone":"+1 203 393 0272",
    "sg:postcode":"06525",
    "sg:province":"CT",
    "sg:tags":[
        "conservation"
    ],
    "wof:name":"Wildwatch",
    "wof:placetype":"venue"
},
  "geometry": {"coordinates":[-73.01505899999999,41.387455],"type":"Point"}
}