{
  "type": "Feature",
  "properties": {
    "addr:full":"208 Main St Rockfall CT 06481",
    "addr:housenumber":"208",
    "addr:postcode":"06481",
    "addr:street":"Main St Rockfall Ct",
    "iso:country":"US",
    "sg:address":"208 Main St",
    "sg:city":"Rockfall",
    "sg:classifiers":[
        {
            "category":"Autos & Motor Vehicles",
            "subcategory":"Fuel & Gas Station",
            "type":"Retail Goods"
        }
    ],
    "sg:phone":"+1 860 349 2067",
    "sg:postcode":"06481",
    "sg:province":"CT",
    "sg:tags":[
        "station",
        "gasoline"
    ],
    "wof:name":"Rockfall Garage LLC",
    "wof:placetype":"venue"
},
  "geometry": {"coordinates":[-72.70152299999999,41.525822],"type":"Point"}
}