{
  "type": "Feature",
  "properties": {
    "iso:country":"US",
    "sg:address":"688 Boston Post Rd",
    "sg:city":"Darien",
    "sg:classifiers":[
        {
            "category":"Health Services",
            "subcategory":"Health Practitioner",
            "type":"Services"
        }
    ],
    "sg:phone":"+1 203 559 9179",
    "sg:postcode":"06820",
    "sg:province":"CT",
    "sg:tags":[
        "acupuncture"
    ],
    "wof:name":"Acupuncture Care",
    "wof:placetype":"venue"
},
  "geometry": {"coordinates":[-73.466256,41.081041],"type":"Point"}
}