{
  "type": "Feature",
  "properties": {
    "addr:full":"72 Five Field Rd Madison CT 06443",
    "addr:housenumber":"72",
    "addr:postcode":"06443",
    "addr:street":"Five Field Rd",
    "iso:country":"US",
    "sg:address":"72 Five Field Rd",
    "sg:city":"Madison",
    "sg:classifiers":[
        {
            "category":"Professional",
            "subcategory":"Computer Services",
            "type":"Services"
        }
    ],
    "sg:phone":"+1   ",
    "sg:postcode":"06443",
    "sg:province":"CT",
    "sg:tags":[
        "related"
    ],
    "wof:name":"Carl A Brucher Inc",
    "wof:placetype":"venue"
},
  "geometry": {"coordinates":[-72.57686699999999,41.298998],"type":"Point"}
}