{
  "type": "Feature",
  "properties": {
    "addr:full":"115 Beachside Ave Westport CT 06880",
    "addr:housenumber":"115",
    "addr:postcode":"06880",
    "addr:street":"Beachside Ave",
    "iso:country":"US",
    "sg:address":"115 Beachside Ave",
    "sg:city":"Westport",
    "sg:classifiers":[
        {
            "category":"Professional",
            "subcategory":"Business Services",
            "type":"Services"
        }
    ],
    "sg:phone":"+1   ",
    "sg:postcode":"06880",
    "sg:province":"CT",
    "sg:tags":[
        "development",
        "manufacture",
        "industrial",
        "design"
    ],
    "wof:name":"E I D",
    "wof:placetype":"venue"
},
  "geometry": {"coordinates":[-73.299278,41.124431],"type":"Point"}
}