{
  "type": "Feature",
  "properties": {
    "iso:country":"US",
    "sg:address":"647 Prospect Ave",
    "sg:city":"Hartford",
    "sg:classifiers":[
        {
            "category":"Health Services",
            "subcategory":"Health Practitioner",
            "type":"Services"
        }
    ],
    "sg:phone":"+1   ",
    "sg:postcode":"06105",
    "sg:province":"CT",
    "wof:name":"Jane Rudd PHD",
    "wof:placetype":"venue"
},
  "geometry": {"coordinates":[-72.71628800000001,41.766802],"type":"Point"}
}