{
  "type": "Feature",
  "properties": {
    "iso:country":"US",
    "sg:address":"21 Elys Ferry Rd",
    "sg:city":"Old Lyme",
    "sg:classifiers":[
        {
            "category":"Real Estate",
            "subcategory":"Real Estate Agent",
            "type":"Services"
        }
    ],
    "sg:phone":"+1 860 434 7023",
    "sg:postcode":"06371",
    "sg:province":"CT",
    "wof:name":"Grace Property Management LLC",
    "wof:placetype":"venue"
},
  "geometry": {"coordinates":[-72.354913,41.369108],"type":"Point"}
}