{
  "type": "Feature",
  "properties": {
    "addr:full":"761 Daniels Farm Rd Trumbull CT 06611",
    "addr:housenumber":"761",
    "addr:postcode":"06611",
    "addr:street":"Daniels Farm Rd",
    "iso:country":"US",
    "sg:address":"761 Daniels Farm Rd",
    "sg:city":"Trumbull",
    "sg:classifiers":[
        {
            "category":"Manufacturing",
            "subcategory":"Tools & Machinery",
            "type":"Manufacturing & Wholesale Goods"
        }
    ],
    "sg:phone":"+1 203 877 6838",
    "sg:postcode":"06611",
    "sg:province":"CT",
    "sg:tags":[
        "machine",
        "shop"
    ],
    "wof:name":"J & J Engineering Inc",
    "wof:placetype":"venue"
},
  "geometry": {"coordinates":[-73.200439,41.269273],"type":"Point"}
}