{
  "type": "Feature",
  "properties": {
    "addr:full":"5 Windward Ln Madison CT 06443",
    "addr:housenumber":"5",
    "addr:postcode":"06443",
    "addr:street":"Windward Ln",
    "iso:country":"US",
    "sg:address":"5 Windward Ln",
    "sg:city":"Madison",
    "sg:classifiers":[
        {
            "category":"Professional",
            "subcategory":"Business Services",
            "type":"Services"
        }
    ],
    "sg:phone":"+1   ",
    "sg:postcode":"06443",
    "sg:province":"CT",
    "wof:name":"Blumen Interiors",
    "wof:placetype":"venue"
},
  "geometry": {"coordinates":[-72.602312,41.27467],"type":"Point"}
}