{
  "type": "Feature",
  "properties": {
    "iso:country":"US",
    "sg:address":"46 Clearview Ln",
    "sg:city":"New Canaan",
    "sg:classifiers":[
        {
            "category":"Banks & Credit Unions",
            "subcategory":"Investment Brokerage",
            "type":"Services"
        }
    ],
    "sg:phone":"+1 203 966 3199",
    "sg:postcode":"06840",
    "sg:province":"NY",
    "sg:tags":[
        "advisory"
    ],
    "wof:name":"Pettee Investors Inc",
    "wof:placetype":"venue"
},
  "geometry": {"coordinates":[-73.535249,41.16332],"type":"Point"}
}