{
  "type": "Feature",
  "properties": {
    "addr:full":"44 Dale Rd Avon CT 06001",
    "addr:housenumber":"44",
    "addr:postcode":"06001",
    "addr:street":"Dale Rd",
    "iso:country":"US",
    "sg:address":"44 Dale Rd",
    "sg:city":"Avon",
    "sg:classifiers":[
        {
            "category":"Health Services",
            "subcategory":"Doctor",
            "type":"Services"
        }
    ],
    "sg:phone":"+1 860 674 8830",
    "sg:postcode":"06001",
    "sg:province":"CT",
    "sg:tags":[
        "medicine",
        "internal"
    ],
    "wof:name":"Petruff Carol A MD",
    "wof:placetype":"venue"
},
  "geometry": {"coordinates":[-72.86489899999999,41.815201],"type":"Point"}
}