{
  "type": "Feature",
  "properties": {
    "addr:full":"18 Elm St New Milford CT 06776",
    "addr:housenumber":"18",
    "addr:postcode":"06776",
    "addr:street":"Elm St",
    "iso:country":"US",
    "sg:address":"18 Elm St",
    "sg:city":"New Milford",
    "sg:classifiers":[
        {
            "category":"Social Services",
            "type":"Services"
        }
    ],
    "sg:phone":"+1   ",
    "sg:postcode":"06776",
    "sg:province":"CT",
    "wof:name":"Behavioral Health Svcs of",
    "wof:placetype":"venue"
},
  "geometry": {"coordinates":[-73.411996,41.580469],"type":"Point"}
}