{
  "type": "Feature",
  "properties": {
    "addr:full":"10 Manor Dr Milford CT 06460",
    "addr:housenumber":"10",
    "addr:postcode":"06460",
    "addr:street":"Manor Dr",
    "iso:country":"US",
    "sg:address":"10 Manor Dr",
    "sg:city":"Milford",
    "sg:classifiers":[
        {
            "category":"Professional",
            "subcategory":"Business Services",
            "type":"Services"
        }
    ],
    "sg:phone":"+1   ",
    "sg:postcode":"06460",
    "sg:province":"CT",
    "wof:name":"Tramuta Enterprises LLC",
    "wof:placetype":"venue"
},
  "geometry": {"coordinates":[-73.01087800000001,41.210644],"type":"Point"}
}