{
  "type": "Feature",
  "properties": {
    "addr:full":"66 Prospect St Ridgefield CT 06877",
    "addr:housenumber":"66",
    "addr:postcode":"06877",
    "addr:street":"Prospect St",
    "iso:country":"US",
    "sg:address":"66 Prospect St",
    "sg:city":"Ridgefield",
    "sg:classifiers":[
        {
            "category":"Government",
            "subcategory":"Office",
            "type":"Public Place"
        }
    ],
    "sg:phone":"+1 203 431 2745",
    "sg:postcode":"06877",
    "sg:province":"CT",
    "sg:website":"http://www.informationgeneral.com",
    "wof:name":"Ridgefield Health Dept",
    "wof:placetype":"venue"
},
  "geometry": {"coordinates":[-73.495425,41.283841],"type":"Point"}
}