{
  "type": "Feature",
  "properties": {
    "addr:full":"32 Lafayette Pl Greenwich CT 06830",
    "addr:housenumber":"32",
    "addr:postcode":"06830",
    "addr:street":"Lafayette Pl",
    "iso:country":"US",
    "sg:address":"32 Lafayette Pl",
    "sg:city":"Greenwich",
    "sg:classifiers":[
        {
            "category":"Professional",
            "subcategory":"Art Services",
            "type":"Services"
        }
    ],
    "sg:phone":"+1   ",
    "sg:postcode":"06830",
    "sg:province":"CT",
    "sg:tags":[
        "commercial",
        "consulting",
        "management",
        "design"
    ],
    "wof:name":"Comer Group Inc",
    "wof:placetype":"venue"
},
  "geometry": {"coordinates":[-73.627504,41.03188],"type":"Point"}
}