{
  "type": "Feature",
  "properties": {
    "iso:country":"US",
    "sg:address":"17 Evelyn Dr",
    "sg:city":"Shelton",
    "sg:classifiers":[
        {
            "category":"Professional",
            "type":"Services"
        }
    ],
    "sg:phone":"+1 203 925 0055",
    "sg:postcode":"06484",
    "sg:province":"CT",
    "sg:tags":[
        "establishment"
    ],
    "wof:name":"Kelly Industries",
    "wof:placetype":"venue"
},
  "geometry": {"coordinates":[-73.193862,41.311083],"type":"Point"}
}