{
  "type": "Feature",
  "properties": {
    "iso:country":"US",
    "sg:address":"23 Water St",
    "sg:city":"Guilford",
    "sg:classifiers":[
        {
            "category":"Shopping",
            "subcategory":"Florist",
            "type":"Retail Goods"
        }
    ],
    "sg:phone":"+1 203 453 5730",
    "sg:postcode":"06437",
    "sg:province":"CT",
    "wof:name":"Guilford Greenery Florist",
    "wof:placetype":"venue"
},
  "geometry": {"coordinates":[-72.682745,41.280905],"type":"Point"}
}