{
  "type": "Feature",
  "properties": {
    "iso:country":"US",
    "sg:address":"236 Willetts Ave",
    "sg:city":"New London",
    "sg:classifiers":[
        {
            "category":"Shopping",
            "subcategory":"Music",
            "type":"Retail Goods"
        }
    ],
    "sg:phone":"+1 860 443 6404",
    "sg:postcode":"06320",
    "sg:province":"CT",
    "wof:name":"Rose Petal Rec Ltd Lblty Co",
    "wof:placetype":"venue"
},
  "geometry": {"coordinates":[-72.10853,41.342142],"type":"Point"}
}