{
  "type": "Feature",
  "properties": {
    "addr:full":"275 Union St Waterbury CT 06706",
    "addr:housenumber":"275",
    "addr:postcode":"06706",
    "addr:street":"Union St Waterbury Ct",
    "iso:country":"US",
    "sg:address":"275 Union St",
    "sg:city":"Waterbury",
    "sg:classifiers":[
        {
            "category":"Shopping",
            "subcategory":"Hobbies, Toys, & Games",
            "type":"Retail Goods"
        }
    ],
    "sg:phone":"+1 203 574 4457",
    "sg:postcode":"06706",
    "sg:province":"CT",
    "wof:name":"Toys R Us",
    "wof:placetype":"venue"
},
  "geometry": {"coordinates":[-73.033591,41.552595],"type":"Point"}
}