{
  "type": "Feature",
  "properties": {
    "addr:full":"6 East St Niantic CT 06357",
    "addr:housenumber":"6",
    "addr:postcode":"06357",
    "addr:street":"East St Niantic Ct",
    "iso:country":"US",
    "sg:address":"6 East St",
    "sg:city":"Niantic",
    "sg:classifiers":[
        {
            "category":"Building & Trades",
            "subcategory":"Cleaning & Sanitation",
            "type":"Services"
        }
    ],
    "sg:phone":"+1   ",
    "sg:postcode":"06357",
    "sg:province":"CT",
    "sg:tags":[
        "maintenance"
    ],
    "wof:name":"Kleen All Building Maintenance",
    "wof:placetype":"venue"
},
  "geometry": {"coordinates":[-72.185543,41.339041],"type":"Point"}
}