{
  "type": "Feature",
  "properties": {
    "iso:country":"US",
    "sg:address":"249 Old Middle St",
    "sg:city":"Goshen",
    "sg:classifiers":[
        {
            "category":"Building & Trades",
            "subcategory":"Landscaping Services",
            "type":"Services"
        }
    ],
    "sg:phone":"+1 860 491 3731",
    "sg:postcode":"06756",
    "sg:province":"CT",
    "sg:tags":[
        "landscape"
    ],
    "wof:name":"Korner Kare",
    "wof:placetype":"venue"
},
  "geometry": {"coordinates":[-73.221255,41.821343],"type":"Point"}
}