{
  "type": "Feature",
  "properties": {
    "addr:full":"2 Carriage Hill Rd Woodbridge CT 06525",
    "addr:housenumber":"2",
    "addr:postcode":"06525",
    "addr:street":"Carriage Hill Rd",
    "iso:country":"US",
    "sg:address":"2 Carriage Hill Rd",
    "sg:city":"Woodbridge",
    "sg:classifiers":[
        {
            "category":"Building & Trades",
            "subcategory":"Plumbing",
            "type":"Services"
        }
    ],
    "sg:phone":"+1 203 393 2783",
    "sg:postcode":"06525",
    "sg:province":"CT",
    "sg:tags":[
        "heating",
        "contractor"
    ],
    "wof:name":"F D Plumbing & Heating",
    "wof:placetype":"venue"
},
  "geometry": {"coordinates":[-73.028223,41.384426],"type":"Point"}
}