{
  "type": "Feature",
  "properties": {
    "iso:country":"US",
    "sg:address":"161 Church Hill Rd",
    "sg:city":"Trumbull",
    "sg:classifiers":[
        {
            "category":"Health Services",
            "subcategory":"Doctor",
            "type":"Services"
        }
    ],
    "sg:phone":"+1   ",
    "sg:postcode":"06611",
    "sg:province":"CT",
    "wof:name":"E J Rogalewski DDS",
    "wof:placetype":"venue"
},
  "geometry": {"coordinates":[-73.21352,41.253809],"type":"Point"}
}