{
  "type": "Feature",
  "properties": {
    "addr:full":"40 Temple St New Haven CT 06510",
    "addr:housenumber":"40",
    "addr:postcode":"06510",
    "addr:street":"Temple St;Haven",
    "iso:country":"US",
    "sg:address":"40 Temple St",
    "sg:city":"New Haven",
    "sg:classifiers":[
        {
            "category":"Health Services",
            "subcategory":"Doctor",
            "type":"Services"
        }
    ],
    "sg:phone":"+1 203 498 2020",
    "sg:postcode":"06510",
    "sg:province":"CT",
    "sg:tags":[
        "physician",
        "surgeon",
        "medical"
    ],
    "wof:name":"Yale Eye Laser Center",
    "wof:placetype":"venue"
},
  "geometry": {"coordinates":[-72.92903099999999,41.303823],"type":"Point"}
}