{
  "type": "Feature",
  "properties": {
    "iso:country":"US",
    "sg:address":"263 High Ridge Dr",
    "sg:city":"Bridgeport",
    "sg:classifiers":[
        {
            "category":"Home & Garden",
            "subcategory":"Carpets & Floor Coverings",
            "type":"Retail Goods"
        }
    ],
    "sg:phone":"+1 203 335 8522",
    "sg:postcode":"06606",
    "sg:province":"CT",
    "wof:name":"W F Wood Floor LLC",
    "wof:placetype":"venue"
},
  "geometry": {"coordinates":[-73.211371,41.194601],"type":"Point"}
}