{
  "type": "Feature",
  "properties": {
    "addr:full":"21 Rogers Lake Trl Old Lyme CT 06371",
    "addr:housenumber":"21",
    "addr:postcode":"06371",
    "addr:street":"Rogers Lake Trl;Lyme Ct",
    "iso:country":"US",
    "sg:address":"21 Rogers Lake Trl",
    "sg:city":"Old Lyme",
    "sg:classifiers":[
        {
            "category":"Building & Trades",
            "subcategory":"Landscaping Services",
            "type":"Services"
        }
    ],
    "sg:phone":"+1 860 434 9706",
    "sg:postcode":"06371",
    "sg:province":"CT",
    "sg:tags":[
        "landscape"
    ],
    "wof:name":"Lakeside Landscaping",
    "wof:placetype":"venue"
},
  "geometry": {"coordinates":[-72.302914,41.352697],"type":"Point"}
}