{
  "type": "Feature",
  "properties": {
    "addr:full":"16 Belmont St Bristol CT 06010",
    "addr:housenumber":"16",
    "addr:postcode":"06010",
    "addr:street":"Belmont St",
    "iso:country":"US",
    "sg:address":"16 Belmont St",
    "sg:city":"Bristol",
    "sg:classifiers":[
        {
            "category":"Professional",
            "subcategory":"Business Services",
            "type":"Services"
        }
    ],
    "sg:phone":"+1 860 582 2770",
    "sg:postcode":"06010",
    "sg:province":"CT",
    "sg:tags":[
        "specialty",
        "mfg"
    ],
    "wof:name":"Elms Signs & Designs",
    "wof:placetype":"venue"
},
  "geometry": {"coordinates":[-72.935063,41.663814],"type":"Point"}
}