{
  "type": "Feature",
  "properties": {
    "addr:full":"3000 Dixwell Ave Hamden CT 06518",
    "addr:postcode":"3000;06518",
    "addr:street":"Dixwell Ave",
    "iso:country":"US",
    "sg:address":"3000 Dixwell Ave",
    "sg:city":"Hamden",
    "sg:classifiers":[
        {
            "category":"Health Services",
            "subcategory":"Chiropractor",
            "type":"Services"
        }
    ],
    "sg:phone":"+1   ",
    "sg:postcode":"06518",
    "sg:province":"CT",
    "sg:tags":[
        "business"
    ],
    "wof:name":"Axman David G DC",
    "wof:placetype":"venue"
},
  "geometry": {"coordinates":[-72.90030299999999,41.38339],"type":"Point"}
}