{
  "type": "Feature",
  "properties": {
    "iso:country":"US",
    "sg:address":"99 Pratt Rd",
    "sg:city":"Dayville",
    "sg:classifiers":[
        {
            "category":"Professional",
            "type":"Services"
        }
    ],
    "sg:phone":"+1 860 774 7530",
    "sg:postcode":"06241",
    "sg:province":"CT",
    "wof:name":"Debra F Leish",
    "wof:placetype":"venue"
},
  "geometry": {"coordinates":[-71.843357,41.843657],"type":"Point"}
}