{
  "type": "Feature",
  "properties": {
    "addr:full":"941 Danbury Rd Wilton CT 06897",
    "addr:housenumber":"941",
    "addr:postcode":"06897",
    "addr:street":"Danbury Rd Wilton Ct",
    "iso:country":"US",
    "sg:address":"941 Danbury Rd",
    "sg:city":"Wilton",
    "sg:classifiers":[
        {
            "category":"Retail",
            "subcategory":"Laundry & Dry Cleaning",
            "type":"Services"
        }
    ],
    "sg:phone":"+1 203 544 9454",
    "sg:postcode":"06897",
    "sg:province":"CT",
    "sg:tags":[
        "cleaners"
    ],
    "wof:name":"Sanda Cleaners",
    "wof:placetype":"venue"
},
  "geometry": {"coordinates":[-73.434822,41.255873],"type":"Point"}
}