{
  "type": "Feature",
  "properties": {
    "addr:full":"454 Old Cellar Rd Orange CT 06477",
    "addr:housenumber":"454",
    "addr:postcode":"06477",
    "addr:street":"Old Cellar Rd",
    "iso:country":"US",
    "sg:address":"454 Old Cellar Rd",
    "sg:city":"Orange",
    "sg:classifiers":[
        {
            "category":"Professional",
            "type":"Services"
        }
    ],
    "sg:phone":"+1 203 878 6482",
    "sg:postcode":"06477",
    "sg:province":"CT",
    "wof:name":"Orange Enterprises Inc",
    "wof:placetype":"venue"
},
  "geometry": {"coordinates":[-73.066682,41.273456],"type":"Point"}
}