{
  "type": "Feature",
  "properties": {
    "iso:country":"US",
    "sg:address":"31 Audubon St",
    "sg:city":"New Haven",
    "sg:classifiers":[
        {
            "category":"Professional",
            "subcategory":"Business Services",
            "type":"Services"
        }
    ],
    "sg:phone":"+1   ",
    "sg:postcode":"06511",
    "sg:province":"CT",
    "sg:tags":[
        "interior",
        "design"
    ],
    "wof:name":"Cama Incorporated",
    "wof:placetype":"venue"
},
  "geometry": {"coordinates":[-72.92012,41.310918],"type":"Point"}
}