{
  "type": "Feature",
  "properties": {
    "addr:full":"27 Cherry St Niantic CT 06357",
    "addr:housenumber":"27",
    "addr:postcode":"06357",
    "addr:street":"Cherry St",
    "iso:country":"US",
    "sg:address":"27 Cherry St",
    "sg:city":"Niantic",
    "sg:classifiers":[
        {
            "category":"Marine",
            "type":"Transportation"
        }
    ],
    "sg:phone":"+1 860 739 7983",
    "sg:postcode":"06357",
    "sg:province":"CT",
    "sg:tags":[
        "water",
        "transport"
    ],
    "wof:name":"Ocean Gypsy",
    "wof:placetype":"venue"
},
  "geometry": {"coordinates":[-72.18533600000001,41.336924],"type":"Point"}
}