{
  "type": "Feature",
  "properties": {
    "addr:full":"101 Lafayette Ave East Hartford CT 06118",
    "addr:housenumber":"101",
    "addr:postcode":"06118",
    "addr:street":"Lafayette Ave East Hartford Ct",
    "iso:country":"US",
    "sg:address":"101 Lafayette Ave",
    "sg:city":"East Hartford",
    "sg:classifiers":[
        {
            "category":"Professional",
            "subcategory":"Lawyer & Legal Services",
            "type":"Services"
        }
    ],
    "sg:phone":"+1   ",
    "sg:postcode":"06118",
    "sg:province":"CT",
    "wof:name":"Public Defender",
    "wof:placetype":"venue"
},
  "geometry": {"coordinates":[-72.621369,41.734954],"type":"Point"}
}