{
  "type": "Feature",
  "properties": {
    "iso:country":"US",
    "sg:address":"15 Saranor Dr",
    "sg:city":"Shelton",
    "sg:classifiers":[
        {
            "category":"Professional",
            "subcategory":"Art Services",
            "type":"Services"
        }
    ],
    "sg:phone":"+1   ",
    "sg:postcode":"06484",
    "sg:province":"CT",
    "sg:tags":[
        "photography",
        "commercial"
    ],
    "wof:name":"Split Images",
    "wof:placetype":"venue"
},
  "geometry": {"coordinates":[-73.158958,41.27248],"type":"Point"}
}