{
  "type": "Feature",
  "properties": {
    "iso:country":"US",
    "sg:address":"286 Beacon Rd",
    "sg:city":"Bethany",
    "sg:classifiers":[
        {
            "category":"Health Services",
            "subcategory":"Health Practitioner",
            "type":"Services"
        }
    ],
    "sg:phone":"+1 203 393 2773",
    "sg:postcode":"06524",
    "sg:province":"CT",
    "sg:tags":[
        "acupuncture"
    ],
    "wof:name":"Itshaky Boaz",
    "wof:placetype":"venue"
},
  "geometry": {"coordinates":[-73.014743,41.451602],"type":"Point"}
}