{
  "type": "Feature",
  "properties": {
    "iso:country":"US",
    "sg:address":"136 Naugatuck Ave",
    "sg:city":"Milford",
    "sg:classifiers":[
        {
            "category":"Retail",
            "subcategory":"Auto Repair",
            "type":"Services"
        }
    ],
    "sg:phone":"+1   ",
    "sg:postcode":"06460",
    "sg:province":"CT",
    "sg:tags":[
        "body"
    ],
    "wof:name":"J & A Auto Body Inc",
    "wof:placetype":"venue"
},
  "geometry": {"coordinates":[-73.08752699999999,41.194949],"type":"Point"}
}