{
  "type": "Feature",
  "properties": {
    "iso:country":"US",
    "sg:address":"357 Race Hill Rd",
    "sg:city":"Madison",
    "sg:classifiers":[
        {
            "category":"Building & Trades",
            "subcategory":"Construction",
            "type":"Services"
        }
    ],
    "sg:phone":"+1 203 421 3190",
    "sg:postcode":"06443",
    "sg:province":"CT",
    "sg:tags":[
        "hanging",
        "contractor"
    ],
    "wof:name":"Everett Johnson & Son",
    "wof:placetype":"venue"
},
  "geometry": {"coordinates":[-72.66855099999999,41.366823],"type":"Point"}
}