{
  "type": "Feature",
  "properties": {
    "iso:country":"US",
    "sg:address":"11 Greenfield Ave",
    "sg:city":"Branford",
    "sg:classifiers":[
        {
            "category":"Building & Trades",
            "subcategory":"Plumbing",
            "type":"Services"
        }
    ],
    "sg:phone":"+1 203 488 1982",
    "sg:postcode":"06405",
    "sg:province":"CT",
    "sg:tags":[
        "plumbing",
        "contractor"
    ],
    "wof:name":"Beedles Sewer & Drain LLC",
    "wof:placetype":"venue"
},
  "geometry": {"coordinates":[-72.828723,41.287906],"type":"Point"}
}