{
  "type": "Feature",
  "properties": {
    "iso:country":"US",
    "sg:address":"121 PRATT ST",
    "sg:city":"GLASTONBURY",
    "sg:classifiers":[
        {
            "category":"Retail",
            "subcategory":"Veterinary Services",
            "type":"Services"
        },
        {
            "category":"Retail",
            "subcategory":"Animal Services",
            "type":"Services"
        }
    ],
    "sg:phone":"+1 860 633 3588",
    "sg:postcode":"06033",
    "sg:province":"CT",
    "sg:tags":[
        "emergency",
        "pet",
        "hospital",
        "specialty",
        "clinic",
        "veterinarian"
    ],
    "sg:website":"http://www.glastonburyvet.com",
    "wof:name":"Glastonbury Veterinary",
    "wof:placetype":"venue"
},
  "geometry": {"coordinates":[-72.616619,41.719365],"type":"Point"}
}