{
  "type": "Feature",
  "properties": {
    "addr:full":"26 Prospect Ave Apt F1 Norwalk CT 06850",
    "addr:housenumber":"26",
    "addr:postcode":"06850",
    "addr:street":"Prospect Ave Apt F1",
    "iso:country":"US",
    "sg:address":"26 Prospect Ave Apt F1",
    "sg:city":"Norwalk",
    "sg:classifiers":[
        {
            "category":"Manufacturing",
            "subcategory":"Food",
            "type":"Manufacturing & Wholesale Goods"
        },
        {
            "category":"Food & Beverages",
            "subcategory":"Groceries & Convenience Stores",
            "type":"Retail Goods"
        }
    ],
    "sg:phone":"+1 203 856 8704",
    "sg:postcode":"06850",
    "sg:province":"CT",
    "sg:tags":[
        "product"
    ],
    "wof:name":"Horizon Foods",
    "wof:placetype":"venue"
},
  "geometry": {"coordinates":[-73.422207,41.115246],"type":"Point"}
}