{
  "type": "Feature",
  "properties": {
    "addr:full":"6 Poningo St Port Chester CT 10573",
    "addr:housenumber":"6",
    "addr:postcode":"10573",
    "addr:street":"Poningo St Port Chester Ct",
    "iso:country":"US",
    "sg:address":"6 Poningo St",
    "sg:city":"Port Chester",
    "sg:classifiers":[
        {
            "category":"Shopping",
            "subcategory":"Music",
            "type":"Retail Goods"
        }
    ],
    "sg:phone":"+1 914 935 9843",
    "sg:postcode":"10573",
    "sg:province":"CT",
    "sg:tags":[
        "compact",
        "record",
        "disc",
        "tape"
    ],
    "wof:name":"Barajas Records",
    "wof:placetype":"venue"
},
  "geometry": {"coordinates":[-73.666523,41.002779],"type":"Point"}
}