{
  "type": "Feature",
  "properties": {
    "addr:full":"244 South St Hartford CT 06114",
    "addr:housenumber":"244",
    "addr:postcode":"06114",
    "addr:street":"South St",
    "iso:country":"US",
    "sg:address":"244 South St",
    "sg:city":"Hartford",
    "sg:classifiers":[
        {
            "category":"Food & Beverages",
            "subcategory":"Liquor & Beverages",
            "type":"Retail Goods"
        }
    ],
    "sg:phone":"+1 860 956 1326",
    "sg:postcode":"06114",
    "sg:province":"CT",
    "sg:tags":[
        "alcoholic"
    ],
    "wof:name":"A & A Package Store",
    "wof:placetype":"venue"
},
  "geometry": {"coordinates":[-72.68183999999999,41.734443],"type":"Point"}
}