{
  "type": "Feature",
  "properties": {
    "addr:full":"104 Main St Hartford CT 06106",
    "addr:housenumber":"104",
    "addr:postcode":"06106",
    "addr:street":"Main St",
    "iso:country":"US",
    "sg:address":"104 Main St",
    "sg:city":"Hartford",
    "sg:classifiers":[
        {
            "category":"Retail",
            "subcategory":"Funeral Services",
            "type":"Services"
        }
    ],
    "sg:phone":"+1   ",
    "sg:postcode":"06106",
    "sg:province":"CT",
    "wof:name":"Deleon Funeral Home",
    "wof:placetype":"venue"
},
  "geometry": {"coordinates":[-72.675217,41.756358],"type":"Point"}
}