{
  "type": "Feature",
  "properties": {
    "iso:country":"US",
    "sg:address":"19 Main St",
    "sg:city":"Danbury",
    "sg:classifiers":[
        {
            "category":"Real Estate",
            "subcategory":"Real Estate Operator",
            "type":"Services"
        }
    ],
    "sg:phone":"+1 203 797 1919",
    "sg:postcode":"06810",
    "sg:province":"CT",
    "sg:tags":[
        "building",
        "apartment"
    ],
    "wof:name":"Kimberly Place Apartments",
    "wof:placetype":"venue"
},
  "geometry": {"coordinates":[-73.4466,41.388491],"type":"Point"}
}