{
  "type": "Feature",
  "properties": {
    "addr:full":"179 Coles Rd Cromwell CT 06416",
    "addr:housenumber":"179",
    "addr:postcode":"06416",
    "addr:street":"Coles Rd;Ct",
    "iso:country":"US",
    "sg:address":"179 Coles Rd",
    "sg:city":"Cromwell",
    "sg:classifiers":[
        {
            "category":"Retail",
            "subcategory":"Animal Services",
            "type":"Services"
        }
    ],
    "sg:phone":"+1 860 632 7807",
    "sg:postcode":"06416",
    "sg:province":"CT",
    "wof:name":"Kathys Kitty Kare",
    "wof:placetype":"venue"
},
  "geometry": {"coordinates":[-72.68395,41.620776],"type":"Point"}
}