{
  "type": "Feature",
  "properties": {
    "addr:full":"250 Meriden-Waterbury Tpke Southington CT 06489",
    "addr:housenumber":"250",
    "addr:postcode":"06489",
    "addr:street":"Meriden-Waterbury Tpke",
    "iso:country":"US",
    "sg:address":"250 Meriden-Waterbury Tpke",
    "sg:city":"Southington",
    "sg:classifiers":[
        {
            "category":"Retail",
            "subcategory":"Repair Shop",
            "type":"Services"
        }
    ],
    "sg:phone":"+1   ",
    "sg:postcode":"06489",
    "sg:province":"CT",
    "sg:tags":[
        "television",
        "radio"
    ],
    "wof:name":"Rogus Jr John",
    "wof:placetype":"venue"
},
  "geometry": {"coordinates":[-72.85231400000001,41.55713],"type":"Point"}
}