{
  "type": "Feature",
  "properties": {
    "addr:full":"945 Riverton Ter Stratford CT 06614",
    "addr:housenumber":"945",
    "addr:postcode":"06614",
    "addr:street":"Riverton Ter Stratford Ct",
    "iso:country":"US",
    "sg:address":"945 Riverton Ter",
    "sg:city":"Stratford",
    "sg:classifiers":[
        {
            "category":"Professional",
            "subcategory":"Engineering",
            "type":"Services"
        }
    ],
    "sg:phone":"+1   ",
    "sg:postcode":"06614",
    "sg:province":"CT",
    "wof:name":"Eastwood Engineering LLC",
    "wof:placetype":"venue"
},
  "geometry": {"coordinates":[-73.122168,41.216973],"type":"Point"}
}