{
  "type": "Feature",
  "properties": {
    "iso:country":"US",
    "sg:address":"31 Church St",
    "sg:city":"Broad Brook",
    "sg:classifiers":[
        {
            "category":"Professional",
            "type":"Services"
        }
    ],
    "sg:phone":"+1 860 623 6891",
    "sg:postcode":"06016",
    "sg:province":"CT",
    "wof:name":"Carol Barone",
    "wof:placetype":"venue"
},
  "geometry": {"coordinates":[-72.547721,41.9193],"type":"Point"}
}