{
  "type": "Feature",
  "properties": {
    "iso:country":"US",
    "sg:address":"32 Flower St",
    "sg:city":"Bridgeport",
    "sg:classifiers":[
        {
            "category":"Professional",
            "type":"Services"
        }
    ],
    "sg:phone":"+1 203 367 6030",
    "sg:postcode":"06605",
    "sg:province":"CT",
    "sg:tags":[
        "establishment"
    ],
    "wof:name":"Infinite Technology Group",
    "wof:placetype":"venue"
},
  "geometry": {"coordinates":[-73.226198,41.161081],"type":"Point"}
}