{
  "type": "Feature",
  "properties": {
    "iso:country":"US",
    "sg:address":"512 Middlesex Rd",
    "sg:city":"Darien",
    "sg:classifiers":[
        {
            "category":"Social Services",
            "type":"Services"
        },
        {
            "category":"Professional",
            "subcategory":"Employment Agencies",
            "type":"Services"
        },
        {
            "category":"Organizations",
            "subcategory":"Community Association",
            "type":"Services"
        }
    ],
    "sg:phone":"+1 203 655 2559",
    "sg:postcode":"06820",
    "sg:province":"CT",
    "sg:tags":[
        "club",
        "workers'",
        "placement",
        "volunteer"
    ],
    "sg:website":"http://www.oxridge.com",
    "wof:name":"Ox Ridge Hunt Club",
    "wof:placetype":"venue"
},
  "geometry": {"coordinates":[-73.4854,41.095248],"type":"Point"}
}