{
  "type": "Feature",
  "properties": {
    "iso:country":"US",
    "sg:address":"19 Bayview Dr",
    "sg:city":"Brookfield",
    "sg:classifiers":[
        {
            "category":"Building & Trades",
            "subcategory":"Construction",
            "type":"Services"
        }
    ],
    "sg:phone":"+1 203 994 8772",
    "sg:postcode":"06804",
    "sg:province":"CT",
    "sg:tags":[
        "tile",
        "dealer"
    ],
    "wof:name":"VMT Contractors",
    "wof:placetype":"venue"
},
  "geometry": {"coordinates":[-73.44024899999999,41.475242],"type":"Point"}
}