{
  "type": "Feature",
  "properties": {
    "addr:full":"83 Easton Rd Westport CT 06880",
    "addr:housenumber":"83",
    "addr:postcode":"06880",
    "addr:street":"Easton Rd",
    "iso:country":"US",
    "sg:address":"83 Easton Rd",
    "sg:city":"Westport",
    "sg:classifiers":[
        {
            "category":"Banks & Credit Unions",
            "subcategory":"Investment Brokerage",
            "type":"Services"
        },
        {
            "category":"Professional",
            "subcategory":"Management & Consulting",
            "type":"Services"
        }
    ],
    "sg:phone":"+1 203 341 9233",
    "sg:postcode":"06880",
    "sg:province":"CT",
    "wof:name":"Ithaca Partners LP",
    "wof:placetype":"venue"
},
  "geometry": {"coordinates":[-73.345331,41.180514],"type":"Point"}
}