{
  "type": "Feature",
  "properties": {
    "addr:full":"375 E Cedar St Newington CT 06111",
    "addr:housenumber":"375",
    "addr:postcode":"06111",
    "addr:street":"E Cedar St",
    "iso:country":"US",
    "sg:address":"375 E Cedar St",
    "sg:city":"Newington",
    "sg:classifiers":[
        {
            "category":"Health Services",
            "subcategory":"Doctor",
            "type":"Services"
        }
    ],
    "sg:phone":"+1   ",
    "sg:postcode":"06111",
    "sg:province":"CT",
    "sg:tags":[
        "medical"
    ],
    "wof:name":"Medworks",
    "wof:placetype":"venue"
},
  "geometry": {"coordinates":[-72.705865,41.697825],"type":"Point"}
}