{
  "type": "Feature",
  "properties": {
    "addr:full":"714 Pacific St Stamford CT 06902",
    "addr:housenumber":"714",
    "addr:postcode":"06902",
    "addr:street":"Pacific St",
    "iso:country":"US",
    "sg:address":"714 Pacific St",
    "sg:city":"Stamford",
    "sg:classifiers":[
        {
            "category":"Organizations",
            "subcategory":"Religious Organization",
            "type":"Services"
        }
    ],
    "sg:phone":"+1 203 329 8995",
    "sg:postcode":"06902",
    "sg:province":"CT",
    "sg:tags":[
        "church"
    ],
    "wof:name":"Stamford French SDA Church",
    "wof:placetype":"venue"
},
  "geometry": {"coordinates":[-73.537841,41.043062],"type":"Point"}
}