{
  "type": "Feature",
  "properties": {
    "addr:full":"11 Old Orchard Ln New Milford CT 06776",
    "addr:housenumber":"11",
    "addr:postcode":"06776",
    "addr:street":"Old Orchard Ln;Milford",
    "iso:country":"US",
    "sg:address":"11 Old Orchard Ln",
    "sg:city":"New Milford",
    "sg:classifiers":[
        {
            "category":"Building & Trades",
            "subcategory":"Plumbing",
            "type":"Services"
        }
    ],
    "sg:phone":"+1 860 350 2748",
    "sg:postcode":"06776",
    "sg:province":"CT",
    "sg:tags":[
        "air",
        "heating",
        "conditioning",
        "contractor"
    ],
    "wof:name":"Michael A Elliott",
    "wof:placetype":"venue"
},
  "geometry": {"coordinates":[-73.40834099999999,41.597462],"type":"Point"}
}