{
  "type": "Feature",
  "properties": {
    "iso:country":"US",
    "sg:address":"30 Hillhouse Ave",
    "sg:city":"New Haven",
    "sg:classifiers":[
        {
            "category":"Education",
            "subcategory":"College",
            "type":"Public Place"
        }
    ],
    "sg:phone":"+1   ",
    "sg:postcode":"06511",
    "sg:province":"CT",
    "wof:name":"Cowles Foundation",
    "wof:placetype":"venue"
},
  "geometry": {"coordinates":[-72.92274399999999,41.315735],"type":"Point"}
}