{
  "type": "Feature",
  "properties": {
    "addr:full":"22 Long Ridge Rd Stamford CT 06905",
    "addr:housenumber":"22",
    "addr:postcode":"06905",
    "addr:street":"Long Ridge Rd",
    "iso:country":"US",
    "sg:address":"22 Long Ridge Rd",
    "sg:city":"Stamford",
    "sg:classifiers":[
        {
            "category":"Building & Trades",
            "subcategory":"Equipment Rental",
            "type":"Services"
        }
    ],
    "sg:phone":"+1   ",
    "sg:postcode":"06905",
    "sg:province":"CT",
    "wof:name":"Skc Air Inc",
    "wof:placetype":"venue"
},
  "geometry": {"coordinates":[-73.54977,41.071998],"type":"Point"}
}