{
  "type": "Feature",
  "properties": {
    "addr:full":"899 Whalley Ave New Haven CT 06515",
    "addr:housenumber":"899",
    "addr:postcode":"06515",
    "addr:street":"Whalley Ave",
    "iso:country":"US",
    "sg:address":"899 Whalley Ave",
    "sg:city":"New Haven",
    "sg:classifiers":[
        {
            "category":"Shopping",
            "type":"Retail Goods"
        }
    ],
    "sg:phone":"+1 203 387 2539",
    "sg:postcode":"06515",
    "sg:province":"CT",
    "sg:tags":[
        "merchandise"
    ],
    "wof:name":"Wespville Gallery",
    "wof:placetype":"venue"
},
  "geometry": {"coordinates":[-72.960187,41.327225],"type":"Point"}
}