{
  "type": "Feature",
  "properties": {
    "addr:full":"8 Old E Haddam Rd East Haddam CT 06423",
    "addr:housenumber":"8",
    "addr:postcode":"06423",
    "addr:street":"Old E Haddam Rd East Haddam Ct",
    "iso:country":"US",
    "sg:address":"8 Old E Haddam Rd",
    "sg:city":"East Haddam",
    "sg:classifiers":[
        {
            "category":"Professional",
            "subcategory":"Computer Services",
            "type":"Services"
        }
    ],
    "sg:phone":"+1   ",
    "sg:postcode":"06423",
    "sg:province":"CT",
    "sg:tags":[
        "related"
    ],
    "wof:name":"Certified Network Services",
    "wof:placetype":"venue"
},
  "geometry": {"coordinates":[-72.463826,41.460624],"type":"Point"}
}