{
  "type": "Feature",
  "properties": {
    "addr:full":"1 Shelton Ter Trumbull CT 06611",
    "addr:housenumber":"1",
    "addr:postcode":"06611",
    "addr:street":"Shelton Ter Trumbull Ct",
    "iso:country":"US",
    "sg:address":"1 Shelton Ter",
    "sg:city":"Trumbull",
    "sg:classifiers":[
        {
            "category":"Banks & Credit Unions",
            "subcategory":"Bank",
            "type":"Services"
        }
    ],
    "sg:phone":"+1 203 459 1539",
    "sg:postcode":"06611",
    "sg:province":"CT",
    "sg:tags":[
        "mortgage"
    ],
    "wof:name":"Vision Financial Group LLC",
    "wof:placetype":"venue"
},
  "geometry": {"coordinates":[-73.22351399999999,41.27108],"type":"Point"}
}