{
  "type": "Feature",
  "properties": {
    "iso:country":"US",
    "sg:address":"222 Boston Tpke",
    "sg:city":"Bolton",
    "sg:classifiers":[
        {
            "category":"Retail",
            "subcategory":"Veterinary Services",
            "type":"Services"
        }
    ],
    "sg:phone":"+1 860 646 6134",
    "sg:postcode":"06043",
    "sg:province":"CT",
    "wof:name":"Bolton Veterinary Hospital",
    "wof:placetype":"venue"
},
  "geometry": {"coordinates":[-72.46119899999999,41.784451],"type":"Point"}
}