{
  "type": "Feature",
  "properties": {
    "iso:country":"US",
    "sg:address":"54 Middle Quarter Rd",
    "sg:city":"Woodbury",
    "sg:classifiers":[
        {
            "category":"Manufacturing",
            "subcategory":"Printing",
            "type":"Manufacturing & Wholesale Goods"
        }
    ],
    "sg:phone":"+1   ",
    "sg:postcode":"06798",
    "sg:province":"CT",
    "sg:tags":[
        "shop",
        "barber",
        "periodical"
    ],
    "wof:name":"Yankee Clipper",
    "wof:placetype":"venue"
},
  "geometry": {"coordinates":[-73.20061800000001,41.527287],"type":"Point"}
}