{
  "type": "Feature",
  "properties": {
    "addr:full":"96 Connecticut Blvd East Hartford CT 06108",
    "addr:housenumber":"96",
    "addr:postcode":"06108",
    "addr:street":"Connecticut Blvd East Hartford Ct",
    "iso:country":"US",
    "sg:address":"96 Connecticut Blvd",
    "sg:city":"East Hartford",
    "sg:classifiers":[
        {
            "category":"Professional",
            "type":"Services"
        }
    ],
    "sg:phone":"+1 860 289 8196",
    "sg:postcode":"06108",
    "sg:province":"CT",
    "wof:name":"Sulzinski & Company LLC",
    "wof:placetype":"venue"
},
  "geometry": {"coordinates":[-72.648831,41.769492],"type":"Point"}
}