{
  "type": "Feature",
  "properties": {
    "addr:full":"33 Terra Rd Plainville CT 06062",
    "addr:housenumber":"33",
    "addr:postcode":"06062",
    "addr:street":"Terra Rd",
    "iso:country":"US",
    "sg:address":"33 Terra Rd",
    "sg:city":"Plainville",
    "sg:classifiers":[
        {
            "category":"Personal",
            "subcategory":"Beauty Salon",
            "type":"Services"
        }
    ],
    "sg:phone":"+1   ",
    "sg:postcode":"06062",
    "sg:province":"CT",
    "sg:tags":[
        "shop"
    ],
    "wof:name":"Essentials Hair Salon",
    "wof:placetype":"venue"
},
  "geometry": {"coordinates":[-72.85599499999999,41.655928],"type":"Point"}
}