{
  "type": "Feature",
  "properties": {
    "iso:country":"US",
    "sg:address":"689 Franklin Ave",
    "sg:city":"Hartford",
    "sg:classifiers":[
        {
            "category":"Local Transit",
            "type":"Transportation"
        }
    ],
    "sg:phone":"+1 860 247 4108",
    "sg:postcode":"06114",
    "sg:province":"CT",
    "sg:tags":[
        "limousine"
    ],
    "wof:name":"Castle Sedans & Limousines",
    "wof:placetype":"venue"
},
  "geometry": {"coordinates":[-72.674027,41.729222],"type":"Point"}
}