{
  "type": "Feature",
  "properties": {
    "addr:full":"393 Meloy Rd West Haven CT 06516",
    "addr:housenumber":"393",
    "addr:postcode":"06516",
    "addr:street":"Meloy Rd;Haven",
    "iso:country":"US",
    "sg:address":"393 Meloy Rd",
    "sg:city":"West Haven",
    "sg:classifiers":[
        {
            "category":"Banks & Credit Unions",
            "subcategory":"Bank",
            "type":"Services"
        }
    ],
    "sg:phone":"+1 203 933 6663",
    "sg:postcode":"06516",
    "sg:province":"CT",
    "sg:tags":[
        "mortgage",
        "loan",
        "broker",
        "real estate"
    ],
    "wof:name":"Templeton Mortgage Group LLC",
    "wof:placetype":"venue"
},
  "geometry": {"coordinates":[-72.982985,41.28129],"type":"Point"}
}