{
  "type": "Feature",
  "properties": {
    "addr:full":"44 Elm St Winsted CT 06098",
    "addr:housenumber":"44",
    "addr:postcode":"06098",
    "addr:street":"Elm St Winsted Ct",
    "iso:country":"US",
    "sg:address":"44 Elm St",
    "sg:city":"Winsted",
    "sg:classifiers":[
        {
            "category":"Banks & Credit Unions",
            "subcategory":"Bank",
            "type":"Services"
        }
    ],
    "sg:phone":"+1 860 738 5100",
    "sg:postcode":"06098",
    "sg:province":"CT",
    "sg:tags":[
        "national",
        "commercial"
    ],
    "wof:name":"Fleet",
    "wof:placetype":"venue"
},
  "geometry": {"coordinates":[-73.070752,41.921062],"type":"Point"}
}