{
  "type": "Feature",
  "properties": {
    "addr:full":"552 Congress Ave New Haven CT 06519",
    "addr:housenumber":"552",
    "addr:postcode":"06519",
    "addr:street":"Congress Ave",
    "iso:country":"US",
    "sg:address":"552 Congress Ave",
    "sg:city":"New Haven",
    "sg:classifiers":[
        {
            "category":"Personal",
            "subcategory":"Barber",
            "type":"Services"
        }
    ],
    "sg:phone":"+1   ",
    "sg:postcode":"06519",
    "sg:province":"CT",
    "sg:tags":[
        "shop"
    ],
    "wof:name":"Boys Will Be Boyz Unisex",
    "wof:placetype":"venue"
},
  "geometry": {"coordinates":[-72.938202,41.300458],"type":"Point"}
}