{
  "type": "Feature",
  "properties": {
    "addr:full":"2 Evans Hill S Gaylordsville CT 06755",
    "addr:housenumber":"2",
    "addr:postcode":"06755",
    "addr:street":"Evans Hill S Gaylordsville Ct",
    "iso:country":"US",
    "sg:address":"2 Evans Hill S",
    "sg:city":"Gaylordsville",
    "sg:classifiers":[
        {
            "category":"Building & Trades",
            "subcategory":"Pest Control",
            "type":"Services"
        }
    ],
    "sg:phone":"+1   ",
    "sg:postcode":"06755",
    "sg:province":"CT",
    "wof:name":"Bartow Exterminating",
    "wof:placetype":"venue"
},
  "geometry": {"coordinates":[-73.49143599999999,41.645506],"type":"Point"}
}