{
  "type": "Feature",
  "properties": {
    "iso:country":"US",
    "sg:address":"40 E Putnam Ave",
    "sg:city":"Cos Cob",
    "sg:classifiers":[
        {
            "category":"Health Services",
            "subcategory":"Doctor",
            "type":"Services"
        }
    ],
    "sg:phone":"+1   ",
    "sg:postcode":"06807",
    "sg:province":"CT",
    "wof:name":"Ehud Oppenheimer DMD",
    "wof:placetype":"venue"
},
  "geometry": {"coordinates":[-73.603129,41.036722],"type":"Point"}
}