{
  "type": "Feature",
  "properties": {
    "iso:country":"US",
    "sg:address":"46 Mountain Rd",
    "sg:city":"Tariffville",
    "sg:classifiers":[
        {
            "category":"Retail",
            "subcategory":"Repair Shop",
            "type":"Services"
        }
    ],
    "sg:phone":"+1   ",
    "sg:postcode":"06081",
    "sg:province":"CT",
    "wof:name":"Jlm Machine Repair LLC",
    "wof:placetype":"venue"
},
  "geometry": {"coordinates":[-72.76307,41.905049],"type":"Point"}
}