{
  "type": "Feature",
  "properties": {
    "iso:country":"US",
    "sg:address":"242 Sisson Ave",
    "sg:city":"Hartford",
    "sg:phone":"+1 860 523 1235",
    "sg:postcode":"06105",
    "sg:province":"CT",
    "sg:website":"http://www.devars-phillipsflorist.com/",
    "wof:name":"De Vars-Phillips Florist and Antiques",
    "wof:placetype":"venue"
},
  "geometry": {"coordinates":[-72.707167,41.765464],"type":"Point"}
}