{
  "type": "Feature",
  "properties": {
    "iso:country":"US",
    "sg:address":"20 Williamsburg Cir",
    "sg:city":"Madison",
    "sg:classifiers":[
        {
            "category":"Professional",
            "subcategory":"Lawyer & Legal Services",
            "type":"Services"
        }
    ],
    "sg:phone":"+1   ",
    "sg:postcode":"06443",
    "sg:province":"CT",
    "wof:name":"Lawrence Michaels",
    "wof:placetype":"venue"
},
  "geometry": {"coordinates":[-72.614136,41.341817],"type":"Point"}
}