{
  "type": "Feature",
  "properties": {
    "addr:full":"270 Foxon Blvd New Haven CT 06513",
    "addr:housenumber":"270",
    "addr:postcode":"06513",
    "addr:street":"Foxon Blvd",
    "iso:country":"US",
    "sg:address":"270 Foxon Blvd",
    "sg:city":"New Haven",
    "sg:classifiers":[
        {
            "category":"Travel",
            "subcategory":"Hotels & Motels",
            "type":"Entertainment"
        }
    ],
    "sg:phone":"+1 203 469 0343",
    "sg:postcode":"06513",
    "sg:province":"CT",
    "wof:name":"Days Inn",
    "wof:placetype":"venue"
},
  "geometry": {"coordinates":[-72.860393,41.327981],"type":"Point"}
}