{
  "type": "Feature",
  "properties": {
    "iso:country":"US",
    "sg:address":"18 Wyndover Ln",
    "sg:city":"Stamford",
    "sg:classifiers":[
        {
            "category":"Real Estate",
            "subcategory":"Real Estate Agent",
            "type":"Services"
        }
    ],
    "sg:phone":"+1 203 348 4009",
    "sg:postcode":"06902",
    "sg:province":"CT",
    "wof:name":"New England Properties",
    "wof:placetype":"venue"
},
  "geometry": {"coordinates":[-73.565383,41.072953],"type":"Point"}
}