{
  "type": "Feature",
  "properties": {
    "addr:full":"119 W Norwalk Rd Norwalk CT 06850",
    "addr:housenumber":"119",
    "addr:postcode":"06850",
    "addr:street":"W Norwalk Rd",
    "iso:country":"US",
    "sg:address":"119 W Norwalk Rd",
    "sg:city":"Norwalk",
    "sg:classifiers":[
        {
            "category":"Real Estate",
            "subcategory":"Real Estate Agent",
            "type":"Services"
        }
    ],
    "sg:phone":"+1 203 357 7001",
    "sg:postcode":"06850",
    "sg:province":"CT",
    "sg:tags":[
        "broker"
    ],
    "wof:name":"Gatehouse Group",
    "wof:placetype":"venue"
},
  "geometry": {"coordinates":[-73.45635,41.100094],"type":"Point"}
}