{
  "type": "Feature",
  "properties": {
    "iso:country":"US",
    "sg:address":"364 Laurel St",
    "sg:city":"Hartford",
    "sg:classifiers":[
        {
            "category":"Professional",
            "subcategory":"Art Services",
            "type":"Services"
        }
    ],
    "sg:phone":"+1   ",
    "sg:postcode":"06105",
    "sg:province":"CT",
    "sg:tags":[
        "photography",
        "commercial"
    ],
    "wof:name":"Gary Lewis Photography",
    "wof:placetype":"venue"
},
  "geometry": {"coordinates":[-72.69722,41.768513],"type":"Point"}
}