{
  "type": "Feature",
  "properties": {
    "addr:full":"54 New Haven Rd Prospect CT 06712",
    "addr:housenumber":"54",
    "addr:postcode":"06712",
    "addr:street":"New Haven Rd",
    "iso:country":"US",
    "sg:address":"54 New Haven Rd",
    "sg:city":"Prospect",
    "sg:classifiers":[
        {
            "category":"Professional",
            "subcategory":"Business Services",
            "type":"Services"
        }
    ],
    "sg:phone":"+1   ",
    "sg:postcode":"06712",
    "sg:province":"CT",
    "sg:tags":[
        "interior",
        "home",
        "design",
        "furnishing",
        "furniture"
    ],
    "wof:name":"Louis Nichole Inc",
    "wof:placetype":"venue"
},
  "geometry": {"coordinates":[-72.975418,41.493471],"type":"Point"}
}