{
  "type": "Feature",
  "properties": {
    "iso:country":"US",
    "sg:address":"993 Post Rd",
    "sg:city":"Darien",
    "sg:classifiers":[
        {
            "category":"Professional",
            "type":"Services"
        },
        {
            "category":"Shopping",
            "subcategory":"Clothing, Apparel, & Fashions",
            "type":"Retail Goods"
        }
    ],
    "sg:phone":"+1 203 655 3111",
    "sg:postcode":"06820",
    "sg:province":"CT",
    "sg:tags":[
        "establishment"
    ],
    "wof:name":"Treetops-Tessera",
    "wof:placetype":"venue"
},
  "geometry": {"coordinates":[-73.471204,41.076405],"type":"Point"}
}