{
  "type": "Feature",
  "properties": {
    "addr:full":"30 Highland Ave Danbury CT 06810",
    "addr:housenumber":"30",
    "addr:postcode":"06810",
    "addr:street":"Highland Ave",
    "iso:country":"US",
    "sg:address":"30 Highland Ave",
    "sg:city":"Danbury",
    "sg:classifiers":[
        {
            "category":"Building & Trades",
            "subcategory":"Construction",
            "type":"Services"
        }
    ],
    "sg:phone":"+1 203 798 6103",
    "sg:postcode":"06810",
    "sg:province":"CT",
    "sg:tags":[
        "contractor"
    ],
    "wof:name":"Lees Siding",
    "wof:placetype":"venue"
},
  "geometry": {"coordinates":[-73.46638299999999,41.397597],"type":"Point"}
}