{
  "type": "Feature",
  "properties": {
    "iso:country":"US",
    "sg:address":"784 Old Main St",
    "sg:city":"Rocky Hill",
    "sg:classifiers":[
        {
            "category":"Professional",
            "subcategory":"Computer Services",
            "type":"Services"
        }
    ],
    "sg:phone":"+1   ",
    "sg:postcode":"06067",
    "sg:province":"CT",
    "sg:tags":[
        "design",
        "integrated",
        "system"
    ],
    "wof:name":"Computer Network Integrators",
    "wof:placetype":"venue"
},
  "geometry": {"coordinates":[-72.637033,41.667356],"type":"Point"}
}