{
  "type": "Feature",
  "properties": {
    "iso:country":"US",
    "sg:address":"110 Richards Ave",
    "sg:city":"Norwalk",
    "sg:classifiers":[
        {
            "category":"Professional",
            "subcategory":"Art Services",
            "type":"Services"
        },
        {
            "category":"Professional",
            "subcategory":"Computer Services",
            "type":"Services"
        }
    ],
    "sg:phone":"+1 203 831 8833",
    "sg:postcode":"06854",
    "sg:province":"CT",
    "sg:tags":[
        "commercial",
        "design",
        "graphics"
    ],
    "wof:name":"C W Graphic Imaging",
    "wof:placetype":"venue"
},
  "geometry": {"coordinates":[-73.451487,41.096285],"type":"Point"}
}