{
  "type": "Feature",
  "properties": {
    "iso:country":"US",
    "sg:address":"187 Lake Rd",
    "sg:city":"Andover",
    "sg:classifiers":[
        {
            "category":"Building & Trades",
            "subcategory":"Equipment Rental",
            "type":"Services"
        }
    ],
    "sg:phone":"+1   ",
    "sg:postcode":"06232",
    "sg:province":"CT",
    "wof:name":"REM Real Estate Rentals",
    "wof:placetype":"venue"
},
  "geometry": {"coordinates":[-72.361063,41.712693],"type":"Point"}
}