{
  "type": "Feature",
  "properties": {
    "iso:country":"US",
    "sg:address":"41 Boston Ter",
    "sg:city":"Guilford",
    "sg:classifiers":[
        {
            "category":"Real Estate",
            "subcategory":"Real Estate Agent",
            "type":"Services"
        }
    ],
    "sg:phone":"+1 203 453 4760",
    "sg:postcode":"06437",
    "sg:province":"CT",
    "sg:tags":[
        "authorities",
        "housing"
    ],
    "wof:name":"Guilford Housing Authority",
    "wof:placetype":"venue"
},
  "geometry": {"coordinates":[-72.669889,41.285186],"type":"Point"}
}