{
  "type": "Feature",
  "properties": {
    "addr:full":"190 Everit St New Haven CT 06511",
    "addr:housenumber":"190",
    "addr:postcode":"06511",
    "addr:street":"Everit St",
    "iso:country":"US",
    "sg:address":"190 Everit St",
    "sg:city":"New Haven",
    "sg:classifiers":[
        {
            "category":"Professional",
            "type":"Services"
        }
    ],
    "sg:phone":"+1 203 624 8032",
    "sg:postcode":"06511",
    "sg:province":"CT",
    "wof:name":"Nsp Llc",
    "wof:placetype":"venue"
},
  "geometry": {"coordinates":[-72.913364,41.327063],"type":"Point"}
}