{
  "type": "Feature",
  "properties": {
    "addr:full":"250 Porter St Watertown CT 06795",
    "addr:housenumber":"250",
    "addr:postcode":"06795",
    "addr:street":"Porter St",
    "iso:country":"US",
    "sg:address":"250 Porter St",
    "sg:city":"Watertown",
    "sg:classifiers":[
        {
            "category":"Manufacturing",
            "subcategory":"Metals",
            "type":"Manufacturing & Wholesale Goods"
        }
    ],
    "sg:phone":"+1 860 945 6779",
    "sg:postcode":"06795",
    "sg:province":"CT",
    "sg:tags":[
        "blast",
        "furnace",
        "works"
    ],
    "wof:name":"Advance Tool & Die",
    "wof:placetype":"venue"
},
  "geometry": {"coordinates":[-73.111687,41.607756],"type":"Point"}
}