{
  "type": "Feature",
  "properties": {
    "addr:full":"631 W Main St New Britain CT 06053",
    "addr:housenumber":"631",
    "addr:postcode":"06053",
    "addr:street":"W Main St",
    "iso:country":"US",
    "sg:address":"631 W Main St",
    "sg:city":"New Britain",
    "sg:classifiers":[
        {
            "category":"Personal",
            "subcategory":"Barber",
            "type":"Services"
        }
    ],
    "sg:phone":"+1   ",
    "sg:postcode":"06053",
    "sg:province":"CT",
    "sg:tags":[
        "shop"
    ],
    "wof:name":"Blaze Barber Shop",
    "wof:placetype":"venue"
},
  "geometry": {"coordinates":[-72.803005,41.66599],"type":"Point"}
}