{
  "type": "Feature",
  "properties": {
    "iso:country":"US",
    "sg:address":"236 Grand St",
    "sg:city":"Waterbury",
    "sg:classifiers":[
        {
            "category":"Government",
            "subcategory":"Office",
            "type":"Public Place"
        }
    ],
    "sg:phone":"+1 203 574 6844",
    "sg:postcode":"06702",
    "sg:province":"CT",
    "sg:tags":[
        "village"
    ],
    "wof:name":"Medical Benefits",
    "wof:placetype":"venue"
},
  "geometry": {"coordinates":[-73.043676,41.55454],"type":"Point"}
}