{
  "type": "Feature",
  "properties": {
    "iso:country":"US",
    "sg:address":"850 N Main Street Ext",
    "sg:city":"Wallingford",
    "sg:classifiers":[
        {
            "category":"Health Services",
            "subcategory":"Doctor",
            "type":"Services"
        }
    ],
    "sg:phone":"+1 203 269 0885",
    "sg:postcode":"06492",
    "sg:province":"CT",
    "sg:tags":[
        "gynecology",
        "physician",
        "surgeon",
        "surgeons",
        "obstetrics"
    ],
    "wof:name":"Andrew P Metzger Md",
    "wof:placetype":"venue"
},
  "geometry": {"coordinates":[-72.807503,41.480331],"type":"Point"}
}