{
  "type": "Feature",
  "properties": {
    "iso:country":"US",
    "sg:address":"14 Guyer Rd",
    "sg:city":"Westport",
    "sg:classifiers":[
        {
            "category":"Real Estate",
            "subcategory":"Architect",
            "type":"Services"
        }
    ],
    "sg:phone":"+1   ",
    "sg:postcode":"06880",
    "sg:province":"CT",
    "sg:tags":[
        "architectural"
    ],
    "wof:name":"Wetmore Assoc Architects",
    "wof:placetype":"venue"
},
  "geometry": {"coordinates":[-73.350729,41.127065],"type":"Point"}
}