{
  "type": "Feature",
  "properties": {
    "iso:country":"US",
    "sg:address":"58 Cotswold Close",
    "sg:city":"Glastonbury",
    "sg:classifiers":[
        {
            "category":"Building & Trades",
            "subcategory":"Construction",
            "type":"Services"
        }
    ],
    "sg:phone":"+1 860 633 3774",
    "sg:postcode":"06033",
    "sg:province":"CT",
    "sg:tags":[
        "contractor"
    ],
    "wof:name":"Lenny Calciano General Contr",
    "wof:placetype":"venue"
},
  "geometry": {"coordinates":[-72.578068,41.680238],"type":"Point"}
}