{
  "type": "Feature",
  "properties": {
    "iso:country":"US",
    "sg:address":"2140 Park Ave",
    "sg:city":"Bridgeport",
    "sg:classifiers":[
        {
            "category":"Health Services",
            "subcategory":"Chiropractor",
            "type":"Services"
        }
    ],
    "sg:phone":"+1   ",
    "sg:postcode":"06604",
    "sg:province":"CT",
    "wof:name":"A Chirprctic Rhabilitation Ctr",
    "wof:placetype":"venue"
},
  "geometry": {"coordinates":[-73.21090700000001,41.188191],"type":"Point"}
}