{
  "type": "Feature",
  "properties": {
    "iso:country":"US",
    "sg:address":"916 Hopmeadow St",
    "sg:city":"Simsbury",
    "sg:classifiers":[
        {
            "category":"Insurance",
            "subcategory":"Insurance Agent",
            "type":"Services"
        }
    ],
    "sg:phone":"+1 860 651 4449",
    "sg:postcode":"06070",
    "sg:province":"CT",
    "sg:tags":[
        "information"
    ],
    "wof:name":"Portamedic 927",
    "wof:placetype":"venue"
},
  "geometry": {"coordinates":[-72.79981600000001,41.88108],"type":"Point"}
}