{
  "type": "Feature",
  "properties": {
    "addr:full":"53 Pennsylvania Ave Niantic CT 06357",
    "addr:housenumber":"53",
    "addr:postcode":"06357",
    "addr:street":"Pennsylvania Ave",
    "iso:country":"US",
    "sg:address":"53 Pennsylvania Ave",
    "sg:city":"Niantic",
    "sg:classifiers":[
        {
            "category":"Restaurant",
            "type":"Food & Drink"
        }
    ],
    "sg:phone":"+1 860 739 3385",
    "sg:postcode":"06357",
    "sg:province":"CT",
    "sg:tags":[
        "eating"
    ],
    "wof:name":"Diamond Chinese Restaurant",
    "wof:placetype":"venue"
},
  "geometry": {"coordinates":[-72.193512,41.326834],"type":"Point"}
}