{
  "type": "Feature",
  "properties": {
    "addr:full":"786 Enfield St Enfield CT 06082",
    "addr:housenumber":"786",
    "addr:postcode":"06082",
    "addr:street":"Enfield St Enfield Ct",
    "iso:country":"US",
    "sg:address":"786 Enfield St",
    "sg:city":"Enfield",
    "sg:phone":"+1 860 741 5562",
    "sg:postcode":"06082",
    "sg:province":"CT",
    "wof:name":"Creative School-Hairdressing",
    "wof:placetype":"venue"
},
  "geometry": {"coordinates":[-72.593265,42.002214],"type":"Point"}
}