{
  "type": "Feature",
  "properties": {
    "addr:full":"721 Meriden Ave Southington CT 06489",
    "addr:housenumber":"721",
    "addr:postcode":"06489",
    "addr:street":"Meriden Ave",
    "iso:country":"US",
    "sg:address":"721 Meriden Ave",
    "sg:city":"Southington",
    "sg:classifiers":[
        {
            "category":"Travel",
            "subcategory":"Travel Agent",
            "type":"Entertainment"
        }
    ],
    "sg:phone":"+1 860 621 4955",
    "sg:postcode":"06489",
    "sg:province":"CT",
    "sg:tags":[
        "agency"
    ],
    "wof:name":"Watson Associates LLC",
    "wof:placetype":"venue"
},
  "geometry": {"coordinates":[-72.867919,41.580109],"type":"Point"}
}