{
  "type": "Feature",
  "properties": {
    "addr:full":"1034 Farmington Ave Berlin CT 06037",
    "addr:housenumber":"1034",
    "addr:postcode":"06037",
    "addr:street":"Farmington Ave",
    "iso:country":"US",
    "sg:address":"1034 Farmington Ave",
    "sg:city":"Berlin",
    "sg:classifiers":[
        {
            "category":"Home & Garden",
            "subcategory":"Carpets & Floor Coverings",
            "type":"Retail Goods"
        }
    ],
    "sg:phone":"+1 860 828 5052",
    "sg:postcode":"06037",
    "sg:province":"CT",
    "sg:tags":[
        "laying",
        "contractor"
    ],
    "wof:name":"Slimskey Carpet Center",
    "wof:placetype":"venue"
},
  "geometry": {"coordinates":[-72.760137,41.630808],"type":"Point"}
}