{
  "type": "Feature",
  "properties": {
    "addr:full":"2635 Long Ridge Rd Stamford CT 06903",
    "addr:housenumber":"2635",
    "addr:postcode":"06903",
    "addr:street":"Long Ridge Rd",
    "iso:country":"US",
    "sg:address":"2635 Long Ridge Rd",
    "sg:city":"Stamford",
    "sg:classifiers":[
        {
            "category":"Bars & Pubs",
            "type":"Food & Drink"
        }
    ],
    "sg:phone":"+1 203 329 7818",
    "sg:postcode":"06903",
    "sg:province":"CT",
    "sg:tags":[
        "tavern"
    ],
    "wof:name":"Long Ridge Tavern",
    "wof:placetype":"venue"
},
  "geometry": {"coordinates":[-73.591212,41.147968],"type":"Point"}
}