{
  "type": "Feature",
  "properties": {
    "addr:full":"267 Round Hill Rd Fairfield CT 06457",
    "addr:housenumber":"267",
    "addr:postcode":"06457",
    "addr:street":"Round Hill Rd",
    "iso:country":"US",
    "sg:address":"267 Round Hill Rd",
    "sg:city":"Fairfield",
    "sg:classifiers":[
        {
            "category":"Restaurant",
            "type":"Food & Drink"
        }
    ],
    "sg:phone":"+1 203 259 9815",
    "sg:postcode":"06457",
    "sg:province":"CT",
    "wof:name":"Mc Donald's",
    "wof:placetype":"venue"
},
  "geometry": {"coordinates":[-72.663202,41.505686],"type":"Point"}
}