{
  "type": "Feature",
  "properties": {
    "addr:full":"131 Webster Square Rd Berlin CT 06037",
    "addr:housenumber":"131",
    "addr:postcode":"06037",
    "addr:street":"Webster Square Rd",
    "iso:country":"US",
    "sg:address":"131 Webster Square Rd",
    "sg:city":"Berlin",
    "sg:classifiers":[
        {
            "category":"Shopping",
            "subcategory":"Discount & Variety Stores",
            "type":"Retail Goods"
        }
    ],
    "sg:phone":"+1 860 829 8008",
    "sg:postcode":"06037",
    "sg:province":"CT",
    "wof:name":"Family Dollar Stores",
    "wof:placetype":"venue"
},
  "geometry": {"coordinates":[-72.74663099999999,41.628211],"type":"Point"}
}