{
  "type": "Feature",
  "properties": {
    "addr:full":"411 W Putnam Ave Greenwich CT 06830",
    "addr:housenumber":"411",
    "addr:postcode":"06830",
    "addr:street":"W Putnam Ave",
    "iso:country":"US",
    "sg:address":"411 W Putnam Ave",
    "sg:city":"Greenwich",
    "sg:classifiers":[
        {
            "category":"Banks & Credit Unions",
            "subcategory":"Investment Brokerage",
            "type":"Services"
        }
    ],
    "sg:phone":"+1 203 869 7000",
    "sg:postcode":"06830",
    "sg:province":"CT",
    "sg:tags":[
        "security"
    ],
    "sg:website":"www.agedwards.com",
    "wof:name":"A G Edwards & Sons Inc",
    "wof:placetype":"venue"
},
  "geometry": {"coordinates":[-73.641907,41.020596],"type":"Point"}
}