{
  "type": "Feature",
  "properties": {
    "iso:country":"US",
    "sg:address":"10 Brinsmayd Ave",
    "sg:city":"Stratford",
    "sg:classifiers":[
        {
            "category":"Retail",
            "subcategory":"Portrait Studio",
            "type":"Services"
        }
    ],
    "sg:phone":"+1   ",
    "sg:postcode":"06614",
    "sg:province":"CT",
    "sg:tags":[
        "photo"
    ],
    "wof:name":"William Stewart Photography",
    "wof:placetype":"venue"
},
  "geometry": {"coordinates":[-73.10906,41.261175],"type":"Point"}
}