{
  "type": "Feature",
  "properties": {
    "iso:country":"US",
    "sg:address":"201 W Main St",
    "sg:city":"Plantsville",
    "sg:classifiers":[
        {
            "category":"Social Services",
            "type":"Services"
        }
    ],
    "sg:phone":"+1   ",
    "sg:postcode":"06479",
    "sg:province":"CT",
    "sg:tags":[
        "residential",
        "care"
    ],
    "wof:name":"ARC of Southington Inc",
    "wof:placetype":"venue"
},
  "geometry": {"coordinates":[-72.897504,41.588267],"type":"Point"}
}