{
  "type": "Feature",
  "properties": {
    "addr:full":"29 W Main St Norwalk CT 06851",
    "addr:housenumber":"29",
    "addr:postcode":"06851",
    "addr:street":"W Main St",
    "iso:country":"US",
    "sg:address":"29 W Main St",
    "sg:city":"Norwalk",
    "sg:classifiers":[
        {
            "category":"Sports & Exercise",
            "subcategory":"Gym",
            "type":"Entertainment"
        }
    ],
    "sg:phone":"+1   ",
    "sg:postcode":"06851",
    "sg:province":"CT",
    "sg:tags":[
        "fitness",
        "physical",
        "facility"
    ],
    "wof:name":"Massage Fitness LLC",
    "wof:placetype":"venue"
},
  "geometry": {"coordinates":[-73.42008199999999,41.124697],"type":"Point"}
}