{
  "type": "Feature",
  "properties": {
    "addr:full":"655 Winding Brook Dr Glastonbury CT 06033",
    "addr:housenumber":"655",
    "addr:postcode":"06033",
    "addr:street":"Winding Brook Dr",
    "iso:country":"US",
    "sg:address":"655 Winding Brook Dr",
    "sg:city":"Glastonbury",
    "sg:classifiers":[
        {
            "category":"Wholesale",
            "subcategory":"Office Equipment",
            "type":"Manufacturing & Wholesale Goods"
        }
    ],
    "sg:phone":"+1 860 659 1361",
    "sg:postcode":"06033",
    "sg:province":"CT",
    "sg:tags":[
        "machine",
        "business"
    ],
    "wof:name":"IKON Office Solutions",
    "wof:placetype":"venue"
},
  "geometry": {"coordinates":[-72.592704,41.716549],"type":"Point"}
}