{
  "type": "Feature",
  "properties": {
    "addr:full":"507 New England Ln Orange CT 06477",
    "addr:housenumber":"507",
    "addr:postcode":"06477",
    "addr:street":"New England Ln",
    "iso:country":"US",
    "sg:address":"507 New England Ln",
    "sg:city":"Orange",
    "sg:classifiers":[
        {
            "category":"Retail",
            "subcategory":"Repair Shop",
            "type":"Services"
        }
    ],
    "sg:phone":"+1   ",
    "sg:postcode":"06477",
    "sg:province":"CT",
    "sg:tags":[
        "television",
        "radio"
    ],
    "wof:name":"Edmund Rogers",
    "wof:placetype":"venue"
},
  "geometry": {"coordinates":[-72.99937199999999,41.28915],"type":"Point"}
}