{
  "type": "Feature",
  "properties": {
    "addr:full":"99 Stockhouse Rd Bozrah CT 06334",
    "addr:housenumber":"99",
    "addr:postcode":"06334",
    "addr:street":"Stockhouse Rd Bozrah Ct",
    "iso:country":"US",
    "sg:address":"99 Stockhouse Rd",
    "sg:city":"Bozrah",
    "sg:classifiers":[
        {
            "category":"Wholesale",
            "subcategory":"Machinery & Supplies",
            "type":"Manufacturing & Wholesale Goods"
        }
    ],
    "sg:phone":"+1   ",
    "sg:postcode":"06334",
    "sg:province":"CT",
    "sg:tags":[
        "pump",
        "least"
    ],
    "wof:name":"Godwin Pumps of America Inc",
    "wof:placetype":"venue"
},
  "geometry": {"coordinates":[-72.143807,41.571437],"type":"Point"}
}