{
  "type": "Feature",
  "properties": {
    "addr:full":"353 W Main St Avon CT 06001",
    "addr:housenumber":"353",
    "addr:postcode":"06001",
    "addr:street":"W Main St",
    "iso:country":"US",
    "sg:address":"353 W Main St",
    "sg:city":"Avon",
    "sg:classifiers":[
        {
            "category":"Wholesale",
            "subcategory":"Sporting Goods",
            "type":"Manufacturing & Wholesale Goods"
        }
    ],
    "sg:phone":"+1 860 677 2304",
    "sg:postcode":"06001",
    "sg:province":"CT",
    "sg:tags":[
        "sauna",
        "equipment",
        "hot",
        "tub",
        "bath",
        "whirlpool"
    ],
    "wof:name":"American Leisure",
    "wof:placetype":"venue"
},
  "geometry": {"coordinates":[-72.86003100000001,41.814775],"type":"Point"}
}