{
  "type": "Feature",
  "properties": {
    "iso:country":"US",
    "sg:address":"120 Long Ridge Rd",
    "sg:city":"Stamford",
    "sg:classifiers":[
        {
            "category":"Banks & Credit Unions",
            "subcategory":"Investment Brokerage",
            "type":"Services"
        }
    ],
    "sg:phone":"+1 203 356 2000",
    "sg:postcode":"06902",
    "sg:province":"CT",
    "sg:tags":[
        "advisory"
    ],
    "wof:name":"Hunt Foreign Investment Corp",
    "wof:placetype":"venue"
},
  "geometry": {"coordinates":[-73.552099,41.075559],"type":"Point"}
}