{
  "type": "Feature",
  "properties": {
    "iso:country":"US",
    "sg:address":"2590 Main St",
    "sg:city":"Stratford",
    "sg:classifiers":[
        {
            "category":"Real Estate",
            "subcategory":"Real Estate Agent",
            "type":"Services"
        }
    ],
    "sg:phone":"+1 203 377 6772",
    "sg:postcode":"06615",
    "sg:province":"CT",
    "wof:name":"J & P Services LLC",
    "wof:placetype":"venue"
},
  "geometry": {"coordinates":[-73.131748,41.194605],"type":"Point"}
}