{
  "type": "Feature",
  "properties": {
    "iso:country":"US",
    "sg:address":"550 E Main St",
    "sg:city":"Branford",
    "sg:classifiers":[
        {
            "category":"Wholesale",
            "subcategory":"Durable Goods & Equipment",
            "type":"Manufacturing & Wholesale Goods"
        }
    ],
    "sg:phone":"+1 203 488 6569",
    "sg:postcode":"06405",
    "sg:province":"CT",
    "sg:tags":[
        "importer"
    ],
    "sg:website":"www.p21s.com",
    "wof:name":"Brookside Import Specialties",
    "wof:placetype":"venue"
},
  "geometry": {"coordinates":[-72.769806,41.298438],"type":"Point"}
}