{
  "type": "Feature",
  "properties": {
    "addr:full":"239 Farmingville Rd Ridgefield CT 06877",
    "addr:housenumber":"239",
    "addr:postcode":"06877",
    "addr:street":"Farmingville Rd",
    "iso:country":"US",
    "sg:address":"239 Farmingville Rd",
    "sg:city":"Ridgefield",
    "sg:classifiers":[
        {
            "category":"Farming",
            "subcategory":"Nursery",
            "type":"Manufacturing & Wholesale Goods"
        }
    ],
    "sg:phone":"+1 203 431 5801",
    "sg:postcode":"06877",
    "sg:province":"CT",
    "sg:tags":[
        "tree",
        "nurseries-plants"
    ],
    "wof:name":"Wayne Dimm Enterprises",
    "wof:placetype":"venue"
},
  "geometry": {"coordinates":[-73.47363300000001,41.295589],"type":"Point"}
}