{
  "type": "Feature",
  "properties": {
    "addr:full":"25 Edice Rd Stamford CT 06905",
    "addr:housenumber":"25",
    "addr:postcode":"06905",
    "addr:street":"Edice Rd",
    "iso:country":"US",
    "sg:address":"25 Edice Rd",
    "sg:city":"Stamford",
    "sg:classifiers":[
        {
            "category":"Retail",
            "subcategory":"Auto Repair",
            "type":"Services"
        }
    ],
    "sg:phone":"+1   ",
    "sg:postcode":"06905",
    "sg:province":"CT",
    "sg:tags":[
        "general"
    ],
    "wof:name":"Vasco Automotive LLC",
    "wof:placetype":"venue"
},
  "geometry": {"coordinates":[-73.543869,41.080505],"type":"Point"}
}