{
  "type": "Feature",
  "properties": {
    "iso:country":"US",
    "sg:address":"884 Greenway Rd",
    "sg:city":"Woodbridge",
    "sg:classifiers":[
        {
            "category":"Professional",
            "subcategory":"Management & Consulting",
            "type":"Services"
        }
    ],
    "sg:phone":"+1   ",
    "sg:postcode":"06525",
    "sg:province":"CT",
    "wof:name":"Whitmore Rapid Product",
    "wof:placetype":"venue"
},
  "geometry": {"coordinates":[-73.03698199999999,41.321135],"type":"Point"}
}