{
  "type": "Feature",
  "properties": {
    "addr:full":"6 Hale Ln Darien CT 06820",
    "addr:housenumber":"6",
    "addr:postcode":"06820",
    "addr:street":"Hale Ln Darien Ct",
    "iso:country":"US",
    "sg:address":"6 Hale Ln",
    "sg:city":"Darien",
    "sg:classifiers":[
        {
            "category":"Banks & Credit Unions",
            "subcategory":"Financial Services",
            "type":"Services"
        }
    ],
    "sg:phone":"+1 203 656 3471",
    "sg:postcode":"06820",
    "sg:province":"CT",
    "sg:tags":[
        "company",
        "venture",
        "capital"
    ],
    "wof:name":"James B Kobak & Co",
    "wof:placetype":"venue"
},
  "geometry": {"coordinates":[-73.4761,41.073902],"type":"Point"}
}