{
  "type": "Feature",
  "properties": {
    "iso:country":"US",
    "sg:address":"105 West Rd (Rt.83)",
    "sg:city":"Ellington",
    "sg:classifiers":[
        {
            "category":"Health Services",
            "subcategory":"Doctor",
            "type":"Services"
        }
    ],
    "sg:phone":"+1 860 872 7854",
    "sg:postcode":"06029",
    "sg:province":"CT",
    "sg:tags":[
        "gynecology",
        "physician",
        "surgeons",
        "obstetrics"
    ],
    "sg:website":"http://www.ellingtonob-gyn.com",
    "wof:name":"Ellington OBGYN",
    "wof:placetype":"venue"
},
  "geometry": {"coordinates":[-72.46422200000001,41.882262],"type":"Point"}
}