{
  "type": "Feature",
  "properties": {
    "iso:country":"US",
    "sg:address":"123 Stevenson Rd",
    "sg:city":"Fairfield",
    "sg:classifiers":[
        {
            "category":"Social Services",
            "subcategory":"Child Care",
            "type":"Services"
        }
    ],
    "sg:phone":"+1   ",
    "sg:postcode":"06451",
    "sg:province":"CT",
    "sg:tags":[
        "day"
    ],
    "wof:name":"Jessie Murphy",
    "wof:placetype":"venue"
},
  "geometry": {"coordinates":[-72.846825,41.526893],"type":"Point"}
}