{
  "type": "Feature",
  "properties": {
    "addr:full":"8 Dorlen Rd Stamford CT 06905",
    "addr:housenumber":"8",
    "addr:postcode":"06905",
    "addr:street":"Dorlen Rd",
    "iso:country":"US",
    "sg:address":"8 Dorlen Rd",
    "sg:city":"Stamford",
    "sg:classifiers":[
        {
            "category":"Government",
            "subcategory":"Fire Station",
            "type":"Public Place"
        }
    ],
    "sg:phone":"+1 203 323 0626",
    "sg:postcode":"06905",
    "sg:province":"CT",
    "sg:tags":[
        "protection"
    ],
    "wof:name":"Belltown Fire Department Inc",
    "wof:placetype":"venue"
},
  "geometry": {"coordinates":[-73.534385,41.077734],"type":"Point"}
}