{
  "type": "Feature",
  "properties": {
    "addr:full":"176 Dixwell Ave New Haven CT 06511",
    "addr:housenumber":"176",
    "addr:postcode":"06511",
    "addr:street":"Dixwell Ave",
    "iso:country":"US",
    "sg:address":"176 Dixwell Ave",
    "sg:city":"New Haven",
    "sg:classifiers":[
        {
            "category":"Shopping",
            "type":"Retail Goods"
        }
    ],
    "sg:phone":"+1 203 624 4554",
    "sg:postcode":"06511",
    "sg:province":"CT",
    "sg:tags":[
        "cosmetic",
        "perfume"
    ],
    "wof:name":"Mid-K Beauty Supply",
    "wof:placetype":"venue"
},
  "geometry": {"coordinates":[-72.933398,41.316868],"type":"Point"}
}