{
  "type": "Feature",
  "properties": {
    "iso:country":"US",
    "sg:address":"37 Straitsville Rd",
    "sg:city":"Prospect",
    "sg:classifiers":[
        {
            "category":"Home & Garden",
            "subcategory":"Building Materials",
            "type":"Retail Goods"
        }
    ],
    "sg:phone":"+1 203 758 0502",
    "sg:postcode":"06712",
    "sg:province":"CT",
    "wof:name":"Artistic Etchworks",
    "wof:placetype":"venue"
},
  "geometry": {"coordinates":[-72.984928,41.499222],"type":"Point"}
}