{
  "type": "Feature",
  "properties": {
    "addr:full":"1399 State St New Haven CT 06511",
    "addr:housenumber":"1399",
    "addr:postcode":"06511",
    "addr:street":"State St",
    "iso:country":"US",
    "sg:address":"1399 State St",
    "sg:city":"New Haven",
    "sg:classifiers":[
        {
            "category":"Wholesale",
            "subcategory":"Machinery & Supplies",
            "type":"Manufacturing & Wholesale Goods"
        }
    ],
    "sg:phone":"+1 203 865 1478",
    "sg:postcode":"06511",
    "sg:province":"CT",
    "sg:tags":[
        "slicing",
        "machine"
    ],
    "wof:name":"Globe Slicing Machine Sales",
    "wof:placetype":"venue"
},
  "geometry": {"coordinates":[-72.89801799999999,41.320055],"type":"Point"}
}