{
  "type": "Feature",
  "properties": {
    "iso:country":"US",
    "sg:address":"41 New St",
    "sg:city":"West Haven",
    "sg:classifiers":[
        {
            "category":"Building & Trades",
            "subcategory":"Construction",
            "type":"Services"
        }
    ],
    "sg:phone":"+1 203 934 7193",
    "sg:postcode":"06516",
    "sg:province":"CT",
    "sg:tags":[
        "addition",
        "new",
        "remodeling"
    ],
    "wof:name":"Conniffs Restoration Inc",
    "wof:placetype":"venue"
},
  "geometry": {"coordinates":[-72.947525,41.270823],"type":"Point"}
}