{
  "type": "Feature",
  "properties": {
    "iso:country":"US",
    "sg:address":"1040 Barnum Ave",
    "sg:city":"Stratford",
    "sg:classifiers":[
        {
            "category":"Food & Beverages",
            "subcategory":"Bakery",
            "type":"Retail Goods"
        }
    ],
    "sg:phone":"+1 203 381 9352",
    "sg:postcode":"06614",
    "sg:province":"CT",
    "sg:tags":[
        "baker"
    ],
    "wof:name":"Ambrosia Bakery",
    "wof:placetype":"venue"
},
  "geometry": {"coordinates":[-73.13346,41.198718],"type":"Point"}
}