{
  "type": "Feature",
  "properties": {
    "addr:full":"255 Barstow Rd Canterbury CT 06331",
    "addr:housenumber":"255",
    "addr:postcode":"06331",
    "addr:street":"Barstow Rd",
    "iso:country":"US",
    "sg:address":"255 Barstow Rd",
    "sg:city":"Canterbury",
    "sg:classifiers":[
        {
            "category":"Building & Trades",
            "subcategory":"Electrical",
            "type":"Services"
        }
    ],
    "sg:phone":"+1 860 546 1233",
    "sg:postcode":"06331",
    "sg:province":"CT",
    "sg:tags":[
        "electrical",
        "contractor"
    ],
    "wof:name":"Warmac Electric",
    "wof:placetype":"venue"
},
  "geometry": {"coordinates":[-72.00443,41.724967],"type":"Point"}
}