{
  "type": "Feature",
  "properties": {
    "iso:country":"US",
    "sg:address":"12 Main St",
    "sg:city":"Plainfield",
    "sg:classifiers":[
        {
            "category":"Food & Beverages",
            "subcategory":"Groceries & Convenience Stores",
            "type":"Retail Goods"
        }
    ],
    "sg:phone":"+1 860 564 5028",
    "sg:postcode":"06374",
    "sg:province":"CT",
    "sg:website":"www.cumberlandfarms.com",
    "wof:name":"Cumberland Farms Food Stores",
    "wof:placetype":"venue"
},
  "geometry": {"coordinates":[-71.905672,41.722516],"type":"Point"}
}