{
  "type": "Feature",
  "properties": {
    "addr:full":"65 Water St Norwalk CT 06854",
    "addr:housenumber":"65",
    "addr:postcode":"06854",
    "addr:street":"Water St",
    "iso:country":"US",
    "sg:address":"65 Water St",
    "sg:city":"Norwalk",
    "sg:classifiers":[
        {
            "category":"Professional",
            "subcategory":"Management & Consulting",
            "type":"Services"
        }
    ],
    "sg:phone":"+1   ",
    "sg:postcode":"06854",
    "sg:province":"CT",
    "sg:tags":[
        "development",
        "software"
    ],
    "wof:name":"Sdg Corporation",
    "wof:placetype":"venue"
},
  "geometry": {"coordinates":[-73.41604100000001,41.098894],"type":"Point"}
}