{
  "type": "Feature",
  "properties": {
    "iso:country":"US",
    "sg:address":"18 Clara Dr",
    "sg:city":"Norwalk",
    "sg:classifiers":[
        {
            "category":"Professional",
            "subcategory":"Business Services",
            "type":"Services"
        }
    ],
    "sg:phone":"+1   ",
    "sg:postcode":"06851",
    "sg:province":"CT",
    "wof:name":"Catino Design & Cnstr LLC",
    "wof:placetype":"venue"
},
  "geometry": {"coordinates":[-73.398128,41.135124],"type":"Point"}
}