{
  "type": "Feature",
  "properties": {
    "addr:full":"1925 State St Hamden CT 06517",
    "addr:housenumber":"1925",
    "addr:postcode":"06517",
    "addr:street":"State St",
    "iso:country":"US",
    "sg:address":"1925 State St",
    "sg:city":"Hamden",
    "sg:classifiers":[
        {
            "category":"Retail",
            "subcategory":"Auto Rental",
            "type":"Services"
        }
    ],
    "sg:phone":"+1 203 772 1555",
    "sg:postcode":"06517",
    "sg:province":"CT",
    "sg:tags":[
        "renting",
        "truck",
        "leasing"
    ],
    "wof:name":"Cheap Truck Rental LLC",
    "wof:placetype":"venue"
},
  "geometry": {"coordinates":[-72.90047800000001,41.334512],"type":"Point"}
}