{
  "type": "Feature",
  "properties": {
    "iso:country":"US",
    "sg:address":"36 Round Hill Rd",
    "sg:city":"Farmington",
    "sg:classifiers":[
        {
            "category":"Building & Trades",
            "subcategory":"Construction",
            "type":"Services"
        }
    ],
    "sg:phone":"+1 860 673 4662",
    "sg:postcode":"06032",
    "sg:province":"CT",
    "sg:tags":[
        "masonry",
        "carpentry",
        "sandblasting",
        "contractor"
    ],
    "wof:name":"Strongs Sandblasting Inc",
    "wof:placetype":"venue"
},
  "geometry": {"coordinates":[-72.83197199999999,41.730665],"type":"Point"}
}