{
  "type": "Feature",
  "properties": {
    "iso:country":"US",
    "sg:address":"17 Valley View Dr",
    "sg:city":"Stafford Springs",
    "sg:classifiers":[
        {
            "category":"Professional",
            "subcategory":"Business Services",
            "type":"Services"
        }
    ],
    "sg:phone":"+1   ",
    "sg:postcode":"06076",
    "sg:province":"CT",
    "sg:tags":[
        "engineering"
    ],
    "wof:name":"Applied Infrared Tech LLC",
    "wof:placetype":"venue"
},
  "geometry": {"coordinates":[-72.29659599999999,42.006984],"type":"Point"}
}