{
  "type": "Feature",
  "properties": {
    "addr:full":"500 Purdy Hill Rd Monroe CT 06468",
    "addr:housenumber":"500",
    "addr:postcode":"06468",
    "addr:street":"Purdy Hill Rd",
    "iso:country":"US",
    "sg:address":"500 Purdy Hill Rd",
    "sg:city":"Monroe",
    "sg:classifiers":[
        {
            "category":"Professional",
            "subcategory":"Engineering",
            "type":"Services"
        }
    ],
    "sg:phone":"+1 203 452 1331",
    "sg:postcode":"06468",
    "sg:province":"CT",
    "sg:tags":[
        "engineer"
    ],
    "sg:website":"www.diblasi-engrs.com",
    "wof:name":"Di Blasi Assoc",
    "wof:placetype":"venue"
},
  "geometry": {"coordinates":[-73.250883,41.305245],"type":"Point"}
}