{
  "type": "Feature",
  "properties": {
    "addr:full":"77 Wall St Madison CT 06443",
    "addr:housenumber":"77",
    "addr:postcode":"06443",
    "addr:street":"Wall St",
    "iso:country":"US",
    "sg:address":"77 Wall St",
    "sg:city":"Madison",
    "sg:classifiers":[
        {
            "category":"Real Estate",
            "subcategory":"Architect",
            "type":"Services"
        }
    ],
    "sg:phone":"+1   ",
    "sg:postcode":"06443",
    "sg:province":"CT",
    "sg:tags":[
        "architectural"
    ],
    "wof:name":"Frank B Ryan Jr AIA",
    "wof:placetype":"venue"
},
  "geometry": {"coordinates":[-72.59375900000001,41.282301],"type":"Point"}
}