{
  "type": "Feature",
  "properties": {
    "iso:country":"US",
    "sg:address":"118 S Ridge St",
    "sg:city":"Port Chester",
    "sg:classifiers":[
        {
            "category":"Travel",
            "subcategory":"Travel Agent",
            "type":"Entertainment"
        }
    ],
    "sg:phone":"+1 914 967 3757",
    "sg:postcode":"10573",
    "sg:province":"CT",
    "sg:tags":[
        "cruise"
    ],
    "wof:name":"Sales Cruises & Vacations",
    "wof:placetype":"venue"
},
  "geometry": {"coordinates":[-73.68134499999999,41.002927],"type":"Point"}
}