{
  "type": "Feature",
  "properties": {
    "iso:country":"US",
    "sg:address":"1700 Watertown Ave",
    "sg:city":"Waterbury",
    "sg:classifiers":[
        {
            "category":"Bars & Pubs",
            "type":"Food & Drink"
        },
        {
            "category":"Restaurant",
            "type":"Food & Drink"
        },
        {
            "category":"Retail",
            "subcategory":"Event Space",
            "type":"Services"
        },
        {
            "category":"Professional",
            "type":"Services"
        }
    ],
    "sg:phone":"+1 203 755 3936",
    "sg:postcode":"06708",
    "sg:province":"CT",
    "sg:tags":[
        "facility",
        "banquet",
        "reception",
        "caterer",
        "hall",
        "italian"
    ],
    "sg:website":"http://www.vasisrestaurant.com",
    "wof:name":"Vasi's",
    "wof:placetype":"venue"
},
  "geometry": {"coordinates":[-73.077299,41.585695],"type":"Point"}
}