{
  "type": "Feature",
  "properties": {
    "iso:country":"US",
    "sg:address":"290 Taylor Hill Rd",
    "sg:city":"Jewett City",
    "sg:classifiers":[
        {
            "category":"Professional",
            "type":"Services"
        }
    ],
    "sg:phone":"+1 860 376 5214",
    "sg:postcode":"06351",
    "sg:province":"CT",
    "wof:name":"Bowden III Elbert",
    "wof:placetype":"venue"
},
  "geometry": {"coordinates":[-71.97239999999999,41.600719],"type":"Point"}
}