{
  "type": "Feature",
  "properties": {
    "iso:country":"US",
    "sg:address":"42 Silver Birch Ln",
    "sg:city":"Clinton",
    "sg:classifiers":[
        {
            "category":"Professional",
            "subcategory":"Computer Services",
            "type":"Services"
        }
    ],
    "sg:phone":"+1   ",
    "sg:postcode":"06413",
    "sg:province":"CT",
    "sg:tags":[
        "datum"
    ],
    "wof:name":"Moore Images",
    "wof:placetype":"venue"
},
  "geometry": {"coordinates":[-72.55001300000001,41.323289],"type":"Point"}
}