{
  "type": "Feature",
  "properties": {
    "addr:full":"19 Chestnut St New Britain CT 06051",
    "addr:housenumber":"19",
    "addr:postcode":"06051",
    "addr:street":"Chestnut St",
    "iso:country":"US",
    "sg:address":"19 Chestnut St",
    "sg:city":"New Britain",
    "sg:classifiers":[
        {
            "category":"Organizations",
            "subcategory":"Religious Organization",
            "type":"Services"
        }
    ],
    "sg:phone":"+1   ",
    "sg:postcode":"06051",
    "sg:province":"CT",
    "wof:name":"Trinity Methodist Church",
    "wof:placetype":"venue"
},
  "geometry": {"coordinates":[-72.779228,41.66591],"type":"Point"}
}