{
  "type": "Feature",
  "properties": {
    "addr:full":"81 Ridgeview Cir Guilford CT 06437",
    "addr:housenumber":"81",
    "addr:postcode":"06437",
    "addr:street":"Ridgeview Cir",
    "iso:country":"US",
    "sg:address":"81 Ridgeview Cir",
    "sg:city":"Guilford",
    "sg:classifiers":[
        {
            "category":"Professional",
            "subcategory":"Computer Services",
            "type":"Services"
        }
    ],
    "sg:phone":"+1 203 457 9200",
    "sg:postcode":"06437",
    "sg:province":"CT",
    "sg:tags":[
        "related"
    ],
    "wof:name":"IBM Corp",
    "wof:placetype":"venue"
},
  "geometry": {"coordinates":[-72.703109,41.34993],"type":"Point"}
}