{
  "type": "Feature",
  "properties": {
    "addr:full":"3 Overlook Dr Meriden CT 06450",
    "addr:housenumber":"3",
    "addr:postcode":"06450",
    "addr:street":"Overlook Dr",
    "iso:country":"US",
    "sg:address":"3 Overlook Dr",
    "sg:city":"Meriden",
    "sg:classifiers":[
        {
            "category":"Real Estate",
            "subcategory":"Real Estate Operator",
            "type":"Services"
        }
    ],
    "sg:phone":"+1 203 639 1049",
    "sg:postcode":"06450",
    "sg:province":"CT",
    "sg:tags":[
        "building",
        "nonresidential"
    ],
    "wof:name":"Yankee Property Entps LLC",
    "wof:placetype":"venue"
},
  "geometry": {"coordinates":[-72.78378499999999,41.517757],"type":"Point"}
}