{
  "type": "Feature",
  "properties": {
    "addr:full":"503 Windsor Ave Windsor CT 06095",
    "addr:housenumber":"503",
    "addr:postcode":"06095",
    "addr:street":"Windsor Ave",
    "iso:country":"US",
    "sg:address":"503 Windsor Ave",
    "sg:city":"Windsor",
    "sg:classifiers":[
        {
            "category":"Bakery",
            "type":"Food & Drink"
        },
        {
            "category":"Coffee & Tea",
            "type":"Food & Drink"
        },
        {
            "category":"Bagels",
            "type":"Food & Drink"
        },
        {
            "category":"Donuts",
            "type":"Food & Drink"
        }
    ],
    "sg:menulink":"http://www.allmenus.com/ct/windsor/130238-dunkin-donuts/menu/",
    "sg:phone":"+1 860 524 0094",
    "sg:postcode":"06095",
    "sg:province":"CT",
    "sg:tags":[
        "american",
        "diner",
        "pastry"
    ],
    "wof:name":"Dunkin' Donuts",
    "wof:placetype":"venue"
},
  "geometry": {"coordinates":[-72.657314,41.819237],"type":"Point"}
}