{
  "type": "Feature",
  "properties": {
    "iso:country":"US",
    "sg:address":"48 Mill Plain Rd",
    "sg:city":"Danbury",
    "sg:classifiers":[
        {
            "category":"Real Estate",
            "subcategory":"Real Estate Agent",
            "type":"Services"
        }
    ],
    "sg:phone":"+1 203 794 9494",
    "sg:postcode":"06811",
    "sg:province":"CT",
    "wof:name":"William Raveis Real Estate Inc",
    "wof:placetype":"venue"
},
  "geometry": {"coordinates":[-73.50290800000001,41.390432],"type":"Point"}
}