{
  "type": "Feature",
  "properties": {
    "iso:country":"US",
    "sg:address":"1542 New Haven Rd",
    "sg:city":"Naugatuck",
    "sg:classifiers":[
        {
            "category":"Building & Trades",
            "subcategory":"Cleaning & Sanitation",
            "type":"Services"
        }
    ],
    "sg:phone":"+1   ",
    "sg:postcode":"06770",
    "sg:province":"CT",
    "sg:tags":[
        "maintenance"
    ],
    "wof:name":"Around House Cleaning",
    "wof:placetype":"venue"
},
  "geometry": {"coordinates":[-73.004184,41.467336],"type":"Point"}
}