{
  "type": "Feature",
  "properties": {
    "iso:country":"US",
    "sg:address":"41 Eagle Rd",
    "sg:city":"Danbury",
    "sg:classifiers":[
        {
            "category":"Manufacturing",
            "subcategory":"Tools & Machinery",
            "type":"Manufacturing & Wholesale Goods"
        }
    ],
    "sg:phone":"+1 203 797 8700",
    "sg:postcode":"06810",
    "sg:province":"CT",
    "sg:tags":[
        "machine",
        "shop"
    ],
    "wof:name":"R K Mfg",
    "wof:placetype":"venue"
},
  "geometry": {"coordinates":[-73.420666,41.416602],"type":"Point"}
}