{
  "type": "Feature",
  "properties": {
    "addr:full":"44 Old Gate Ln Milford CT 06460",
    "addr:housenumber":"44",
    "addr:postcode":"06460",
    "addr:street":"Old Gate Ln",
    "iso:country":"US",
    "sg:address":"44 Old Gate Ln",
    "sg:city":"Milford",
    "sg:classifiers":[
        {
            "category":"Building & Trades",
            "subcategory":"Construction",
            "type":"Services"
        }
    ],
    "sg:phone":"+1 203 874 0084",
    "sg:postcode":"06460",
    "sg:province":"CT",
    "sg:tags":[
        "concrete",
        "animal",
        "contractor"
    ],
    "wof:name":"Black Birch Farm LLC",
    "wof:placetype":"venue"
},
  "geometry": {"coordinates":[-73.033062,41.225194],"type":"Point"}
}