{
  "type": "Feature",
  "properties": {
    "iso:country":"US",
    "sg:address":"1 Elm St",
    "sg:city":"New Canaan",
    "sg:classifiers":[
        {
            "category":"Shopping",
            "subcategory":"Florist",
            "type":"Retail Goods"
        }
    ],
    "sg:phone":"+1 203 966 8989",
    "sg:postcode":"06840",
    "sg:province":"NY",
    "wof:name":"Ivy Lane Florist",
    "wof:placetype":"venue"
},
  "geometry": {"coordinates":[-73.493307,41.146896],"type":"Point"}
}