{
  "type": "Feature",
  "properties": {
    "iso:country":"US",
    "sg:address":"255 Old Tavern Rd",
    "sg:city":"Orange",
    "sg:classifiers":[
        {
            "category":"Social Services",
            "type":"Services"
        }
    ],
    "sg:phone":"+1 203 795 5147",
    "sg:postcode":"06477",
    "sg:province":"CT",
    "sg:tags":[
        "guidance",
        "child"
    ],
    "wof:name":"Country Kids Daycare",
    "wof:placetype":"venue"
},
  "geometry": {"coordinates":[-73.019876,41.263081],"type":"Point"}
}