{
  "type": "Feature",
  "properties": {
    "iso:country":"US",
    "sg:address":"29 Berlin Rd",
    "sg:city":"Cromwell",
    "sg:classifiers":[
        {
            "category":"Real Estate",
            "subcategory":"Developer",
            "type":"Services"
        }
    ],
    "sg:phone":"+1 860 635 4500",
    "sg:postcode":"06416",
    "sg:province":"CT",
    "wof:name":"J D A Development Co L L C",
    "wof:placetype":"venue"
},
  "geometry": {"coordinates":[-72.677194,41.599061],"type":"Point"}
}