{
  "type": "Feature",
  "properties": {
    "iso:country":"US",
    "sg:address":"117 John St",
    "sg:city":"Greenwich",
    "sg:classifiers":[
        {
            "category":"Professional",
            "subcategory":"Management & Consulting",
            "type":"Services"
        }
    ],
    "sg:phone":"+1   ",
    "sg:postcode":"06831",
    "sg:province":"CT",
    "sg:tags":[
        "business"
    ],
    "wof:name":"Piman LLC",
    "wof:placetype":"venue"
},
  "geometry": {"coordinates":[-73.686448,41.097322],"type":"Point"}
}