{
  "type": "Feature",
  "properties": {
    "addr:full":"358 Main St Manchester CT 06040",
    "addr:housenumber":"358",
    "addr:postcode":"06040",
    "addr:street":"Main St",
    "iso:country":"US",
    "sg:address":"358 Main St",
    "sg:city":"Manchester",
    "sg:classifiers":[
        {
            "category":"Personal",
            "subcategory":"Beauty Salon",
            "type":"Services"
        }
    ],
    "sg:phone":"+1   ",
    "sg:postcode":"06040",
    "sg:province":"CT",
    "sg:tags":[
        "shop"
    ],
    "wof:name":"Saigon Nails",
    "wof:placetype":"venue"
},
  "geometry": {"coordinates":[-72.52197700000001,41.780722],"type":"Point"}
}