{
  "type": "Feature",
  "properties": {
    "addr:full":"283 Main St N Southbury CT 06488",
    "addr:housenumber":"283",
    "addr:postcode":"06488",
    "addr:street":"Main St N",
    "iso:country":"US",
    "sg:address":"283 Main St N",
    "sg:city":"Southbury",
    "sg:classifiers":[
        {
            "category":"Social Services",
            "subcategory":"Child Care",
            "type":"Services"
        }
    ],
    "sg:phone":"+1 203 264 4749",
    "sg:postcode":"06488",
    "sg:province":"CT",
    "sg:tags":[
        "kindergarten",
        "academic",
        "school"
    ],
    "wof:name":"Preschool Center",
    "wof:placetype":"venue"
},
  "geometry": {"coordinates":[-73.212878,41.484618],"type":"Point"}
}