{
  "type": "Feature",
  "properties": {
    "addr:full":"57 Gun Mill Rd Bloomfield CT 06002",
    "addr:housenumber":"57",
    "addr:postcode":"06002",
    "addr:street":"Gun Mill Rd Bloomfield Ct",
    "iso:country":"US",
    "sg:address":"57 Gun Mill Rd",
    "sg:city":"Bloomfield",
    "sg:classifiers":[
        {
            "category":"Government",
            "subcategory":"Office",
            "type":"Public Place"
        }
    ],
    "sg:phone":"+1 860 242 1158",
    "sg:postcode":"06002",
    "sg:province":"CT",
    "sg:tags":[
        "state",
        "park"
    ],
    "wof:name":"Penwood State Park",
    "wof:placetype":"venue"
},
  "geometry": {"coordinates":[-72.767516,41.873346],"type":"Point"}
}