{
  "type": "Feature",
  "properties": {
    "addr:full":"380 Hitchcock Rd Waterbury CT 06705",
    "addr:housenumber":"380",
    "addr:postcode":"06705",
    "addr:street":"Hitchcock Rd",
    "iso:country":"US",
    "sg:address":"380 Hitchcock Rd",
    "sg:city":"Waterbury",
    "sg:classifiers":[
        {
            "category":"Building & Trades",
            "subcategory":"Construction",
            "type":"Services"
        }
    ],
    "sg:phone":"+1 203 574 3188",
    "sg:postcode":"06705",
    "sg:province":"CT",
    "sg:tags":[
        "general",
        "contractor"
    ],
    "wof:name":"B & D General Contracting",
    "wof:placetype":"venue"
},
  "geometry": {"coordinates":[-72.960843,41.549528],"type":"Point"}
}