{
  "type": "Feature",
  "properties": {
    "iso:country":"US",
    "sg:address":"900 Whalley Ave",
    "sg:city":"New Haven",
    "sg:classifiers":[
        {
            "category":"Shopping",
            "subcategory":"Clothing, Apparel, & Fashions",
            "type":"Retail Goods"
        }
    ],
    "sg:phone":"+1   ",
    "sg:postcode":"06515",
    "sg:province":"CT",
    "sg:tags":[
        "dress",
        "maker",
        "alteration"
    ],
    "wof:name":"Victorias Design",
    "wof:placetype":"venue"
},
  "geometry": {"coordinates":[-72.960155,41.326932],"type":"Point"}
}