{
  "type": "Feature",
  "properties": {
    "iso:country":"US",
    "sg:address":"8 Williams Rd",
    "sg:city":"Sharon",
    "sg:classifiers":[
        {
            "category":"Real Estate",
            "subcategory":"Real Estate Services",
            "type":"Services"
        },
        {
            "category":"Banks & Credit Unions",
            "subcategory":"Financial Services",
            "type":"Services"
        }
    ],
    "sg:phone":"+1 860 364 0661",
    "sg:postcode":"06069",
    "sg:province":"CT",
    "sg:tags":[
        "loan",
        "processing"
    ],
    "wof:name":"Nettleton",
    "wof:placetype":"venue"
},
  "geometry": {"coordinates":[-73.454247,41.8848],"type":"Point"}
}