{
  "type": "Feature",
  "properties": {
    "addr:full":"8 Sound Shore Dr Greenwich CT 06830",
    "addr:housenumber":"8",
    "addr:postcode":"06830",
    "addr:street":"Sound Shore Dr",
    "iso:country":"US",
    "sg:address":"8 Sound Shore Dr",
    "sg:city":"Greenwich",
    "sg:classifiers":[
        {
            "category":"Banks & Credit Unions",
            "subcategory":"Investment Brokerage",
            "type":"Services"
        }
    ],
    "sg:phone":"+1 203 629 9889",
    "sg:postcode":"06830",
    "sg:province":"CT",
    "wof:name":"Haebler Co",
    "wof:placetype":"venue"
},
  "geometry": {"coordinates":[-73.602661,41.028698],"type":"Point"}
}