{
  "type": "Feature",
  "properties": {
    "addr:full":"82 Bridge St East Windsor CT 06088",
    "addr:housenumber":"82",
    "addr:postcode":"06088",
    "addr:street":"Bridge St East Windsor Ct",
    "iso:country":"US",
    "sg:address":"82 Bridge St",
    "sg:city":"East Windsor",
    "sg:classifiers":[
        {
            "category":"Personal",
            "subcategory":"Beauty Salon",
            "type":"Services"
        }
    ],
    "sg:phone":"+1   ",
    "sg:postcode":"06088",
    "sg:province":"CT",
    "sg:tags":[
        "shop"
    ],
    "wof:name":"Classics Styles LLC",
    "wof:placetype":"venue"
},
  "geometry": {"coordinates":[-72.615887,41.92962],"type":"Point"}
}