{
  "type": "Feature",
  "properties": {
    "iso:country":"US",
    "sg:address":"206 Burnside Ave",
    "sg:city":"East Hartford",
    "sg:classifiers":[
        {
            "category":"Personal",
            "subcategory":"Beauty Salon",
            "type":"Services"
        }
    ],
    "sg:phone":"+1   ",
    "sg:postcode":"06108",
    "sg:province":"CT",
    "sg:tags":[
        "shop"
    ],
    "wof:name":"Bandit Unisex Salon",
    "wof:placetype":"venue"
},
  "geometry": {"coordinates":[-72.628221,41.775676],"type":"Point"}
}