{
  "type": "Feature",
  "properties": {
    "iso:country":"US",
    "sg:address":"484 Post Rd",
    "sg:city":"Darien",
    "sg:classifiers":[
        {
            "category":"Professional",
            "subcategory":"Employment Agencies",
            "type":"Services"
        }
    ],
    "sg:phone":"+1 203 655 1590",
    "sg:postcode":"06820",
    "sg:province":"CT",
    "sg:tags":[
        "opportunity"
    ],
    "sg:website":"http://www.ctwt.com",
    "wof:name":"Lindsey &",
    "wof:placetype":"venue"
},
  "geometry": {"coordinates":[-73.46287100000001,41.084392],"type":"Point"}
}