{
  "type": "Feature",
  "properties": {
    "iso:country":"US",
    "sg:address":"15 Autumn Dr",
    "sg:city":"Danbury",
    "sg:classifiers":[
        {
            "category":"Professional",
            "type":"Services"
        }
    ],
    "sg:phone":"+1   ",
    "sg:postcode":"06811",
    "sg:province":"CT",
    "wof:name":"Thyme For All Seasons LLC",
    "wof:placetype":"venue"
},
  "geometry": {"coordinates":[-73.52137999999999,41.417978],"type":"Point"}
}