{
  "type": "Feature",
  "properties": {
    "addr:full":"9 Clover Ln Weatogue CT 06089",
    "addr:housenumber":"9",
    "addr:postcode":"06089",
    "addr:street":"Clover Ln Weatogue Ct",
    "iso:country":"US",
    "sg:address":"9 Clover Ln",
    "sg:city":"Weatogue",
    "sg:classifiers":[
        {
            "category":"Shopping",
            "subcategory":"Jewelry",
            "type":"Retail Goods"
        }
    ],
    "sg:phone":"+1 860 408 1505",
    "sg:postcode":"06089",
    "sg:province":"CT",
    "wof:name":"Visions",
    "wof:placetype":"venue"
},
  "geometry": {"coordinates":[-72.825423,41.842638],"type":"Point"}
}