{
  "type": "Feature",
  "properties": {
    "addr:full":"161 Summerfield Gardens Shelton CT 06484",
    "addr:housenumber":"161",
    "addr:postcode":"06484",
    "addr:street":"Summerfield Gardens",
    "iso:country":"US",
    "sg:address":"161 Summerfield Gardens",
    "sg:city":"Shelton",
    "sg:classifiers":[
        {
            "category":"Professional",
            "subcategory":"Lawyer & Legal Services",
            "type":"Services"
        }
    ],
    "sg:phone":"+1 203 929 3312",
    "sg:postcode":"06484",
    "sg:province":"CT",
    "sg:tags":[
        "attorney"
    ],
    "wof:name":"James W Bracnaro",
    "wof:placetype":"venue"
},
  "geometry": {"coordinates":[-73.126778,41.318311],"type":"Point"}
}