{
  "type": "Feature",
  "properties": {
    "addr:full":"319 Post Rd Darien CT 06820",
    "addr:housenumber":"319",
    "addr:postcode":"06820",
    "addr:street":"Post Rd",
    "iso:country":"US",
    "sg:address":"319 Post Rd",
    "sg:city":"Darien",
    "sg:classifiers":[
        {
            "category":"Restaurant",
            "type":"Food & Drink"
        }
    ],
    "sg:menulink":"http://www.allmenus.com/ct/darien/25325-centro/menu/",
    "sg:phone":"+1 203 655 4772",
    "sg:postcode":"06820",
    "sg:province":"CT",
    "sg:tags":[
        "italian"
    ],
    "wof:name":"Centro",
    "wof:placetype":"venue"
},
  "geometry": {"coordinates":[-73.460311,41.086773],"type":"Point"}
}