{
  "type": "Feature",
  "properties": {
    "addr:full":"523 Ridgebury Rd Ridgefield CT 06877",
    "addr:housenumber":"523",
    "addr:postcode":"06877",
    "addr:street":"Ridgebury Rd",
    "iso:country":"US",
    "sg:address":"523 Ridgebury Rd",
    "sg:city":"Ridgefield",
    "sg:classifiers":[
        {
            "category":"Professional",
            "type":"Services"
        }
    ],
    "sg:phone":"+1 203 431 7979",
    "sg:postcode":"06877",
    "sg:province":"CT",
    "wof:name":"Gravitte Enterp Inc",
    "wof:placetype":"venue"
},
  "geometry": {"coordinates":[-73.52600200000001,41.354636],"type":"Point"}
}