{
  "type": "Feature",
  "properties": {
    "iso:country":"US",
    "sg:address":"1 Deerfield Cir",
    "sg:city":"Enfield",
    "sg:classifiers":[
        {
            "category":"Professional",
            "type":"Services"
        }
    ],
    "sg:phone":"+1 860 741 3805",
    "sg:postcode":"06082",
    "sg:province":"CT",
    "wof:name":"Nmwear Co LLC",
    "wof:placetype":"venue"
},
  "geometry": {"coordinates":[-72.580838,41.950579],"type":"Point"}
}