{
  "type": "Feature",
  "properties": {
    "iso:country":"US",
    "sg:address":"222 Chase Ave",
    "sg:city":"Waterbury",
    "sg:classifiers":[
        {
            "category":"Restaurant",
            "type":"Food & Drink"
        }
    ],
    "sg:phone":"+1 203 755 7878",
    "sg:postcode":"06704",
    "sg:province":"CT",
    "sg:tags":[
        "eating"
    ],
    "wof:name":"Papa Luigi's Sandwich & Coffee",
    "wof:placetype":"venue"
},
  "geometry": {"coordinates":[-73.03322199999999,41.580817],"type":"Point"}
}