{
  "type": "Feature",
  "properties": {
    "addr:full":"607 Fern St Hartford CT 06107",
    "addr:housenumber":"607",
    "addr:postcode":"06107",
    "addr:street":"Fern St",
    "iso:country":"US",
    "sg:address":"607 Fern St",
    "sg:city":"Hartford",
    "sg:classifiers":[
        {
            "category":"Shopping",
            "subcategory":"Gifts & Souvenirs",
            "type":"Retail Goods"
        }
    ],
    "sg:phone":"+1 860 561 3861",
    "sg:postcode":"06107",
    "sg:province":"CT",
    "wof:name":"ABG Products LLC",
    "wof:placetype":"venue"
},
  "geometry": {"coordinates":[-72.755269,41.766965],"type":"Point"}
}