{
  "type": "Feature",
  "properties": {
    "addr:full":"340 Broad St Windsor CT 06095",
    "addr:housenumber":"340",
    "addr:postcode":"06095",
    "addr:street":"Broad St",
    "iso:country":"US",
    "sg:address":"340 Broad St",
    "sg:city":"Windsor",
    "sg:classifiers":[
        {
            "category":"Professional",
            "type":"Services"
        },
        {
            "category":"Professional",
            "subcategory":"Advertising",
            "type":"Services"
        },
        {
            "category":"Retail",
            "subcategory":"Event Space",
            "type":"Services"
        }
    ],
    "sg:phone":"+1 860 640 4881",
    "sg:postcode":"06095",
    "sg:province":"CT",
    "sg:tags":[
        "product",
        "fair",
        "trade",
        "planning",
        "exposition",
        "advertising-promotional",
        "meeting",
        "shows"
    ],
    "wof:name":"A Glamorous Touch",
    "wof:placetype":"venue"
},
  "geometry": {"coordinates":[-72.645248,41.848869],"type":"Point"}
}