{
  "type": "Feature",
  "properties": {
    "addr:full":"2255 Summer St Stamford CT 06905",
    "addr:housenumber":"2255",
    "addr:postcode":"06905",
    "addr:street":"Summer St",
    "iso:country":"US",
    "sg:address":"2255 Summer St",
    "sg:city":"Stamford",
    "sg:classifiers":[
        {
            "category":"Shopping",
            "subcategory":"Gifts & Souvenirs",
            "type":"Retail Goods"
        }
    ],
    "sg:phone":"+1 203 964 4961",
    "sg:postcode":"06905",
    "sg:province":"CT",
    "sg:tags":[
        "party",
        "supply"
    ],
    "sg:website":"www.partycity.com",
    "wof:name":"Party City",
    "wof:placetype":"venue"
},
  "geometry": {"coordinates":[-73.545491,41.066817],"type":"Point"}
}