{
  "type": "Feature",
  "properties": {
    "iso:country":"US",
    "sg:address":"51 Blue Ridge Dr",
    "sg:city":"Weatogue",
    "sg:classifiers":[
        {
            "category":"Professional",
            "type":"Services"
        }
    ],
    "sg:phone":"+1 860 658 2302",
    "sg:postcode":"06089",
    "sg:province":"CT",
    "wof:name":"Little Swings & Strokes LLC",
    "wof:placetype":"venue"
},
  "geometry": {"coordinates":[-72.838993,41.822264],"type":"Point"}
}