{
  "type": "Feature",
  "properties": {
    "addr:full":"11 Avery Rd New Milford CT 06776",
    "addr:housenumber":"11",
    "addr:postcode":"06776",
    "addr:street":"Avery Rd",
    "iso:country":"US",
    "sg:address":"11 Avery Rd",
    "sg:city":"New Milford",
    "sg:classifiers":[
        {
            "category":"Organizations",
            "subcategory":"Community Association",
            "type":"Services"
        }
    ],
    "sg:phone":"+1   ",
    "sg:postcode":"06776",
    "sg:province":"CT",
    "sg:tags":[
        "business"
    ],
    "wof:name":"Veterans of Foreign Wars",
    "wof:placetype":"venue"
},
  "geometry": {"coordinates":[-73.40696800000001,41.601677],"type":"Point"}
}