{
  "type": "Feature",
  "properties": {
    "addr:full":"137 Main St Wethersfield CT 06109",
    "addr:housenumber":"137",
    "addr:postcode":"06109",
    "addr:street":"Main St",
    "iso:country":"US",
    "sg:address":"137 Main St",
    "sg:city":"Wethersfield",
    "sg:classifiers":[
        {
            "category":"Banks & Credit Unions",
            "subcategory":"Bank",
            "type":"Services"
        }
    ],
    "sg:phone":"+1 860 257 4755",
    "sg:postcode":"06109",
    "sg:province":"CT",
    "sg:tags":[
        "mortgage"
    ],
    "wof:name":"CTX Wethersfield",
    "wof:placetype":"venue"
},
  "geometry": {"coordinates":[-72.654889,41.709517],"type":"Point"}
}