{
  "type": "Feature",
  "properties": {
    "iso:country":"US",
    "sg:address":"1411 Norwich Rd",
    "sg:city":"Plainfield",
    "sg:classifiers":[
        {
            "category":"Retail",
            "subcategory":"Auto Repair",
            "type":"Services"
        }
    ],
    "sg:phone":"+1 860 564 4539",
    "sg:postcode":"06374",
    "sg:province":"CT",
    "wof:name":"Carguyz Autocenter Inc",
    "wof:placetype":"venue"
},
  "geometry": {"coordinates":[-71.95246400000001,41.637693],"type":"Point"}
}