{
  "type": "Feature",
  "properties": {
    "addr:full":"333 Cedar St New Haven CT 06510",
    "addr:housenumber":"333",
    "addr:postcode":"06510",
    "addr:street":"Cedar St",
    "iso:country":"US",
    "sg:address":"333 Cedar St",
    "sg:city":"New Haven",
    "sg:classifiers":[
        {
            "category":"Health Services",
            "subcategory":"Doctor",
            "type":"Services"
        }
    ],
    "sg:phone":"+1   ",
    "sg:postcode":"06510",
    "sg:province":"CT",
    "sg:tags":[
        "medical"
    ],
    "wof:name":"Yale Faculty Practice",
    "wof:placetype":"venue"
},
  "geometry": {"coordinates":[-72.93456999999999,41.303762],"type":"Point"}
}