{
  "type": "Feature",
  "properties": {
    "iso:country":"US",
    "sg:address":"152 Westchester Ave",
    "sg:city":"Port Chester",
    "sg:classifiers":[
        {
            "category":"Retail",
            "subcategory":"Repair Shop",
            "type":"Services"
        }
    ],
    "sg:phone":"+1 914 939 7790",
    "sg:postcode":"10573",
    "sg:province":"CT",
    "sg:tags":[
        "equipment",
        "establishment"
    ],
    "wof:name":"Keyman Locksmiths",
    "wof:placetype":"venue"
},
  "geometry": {"coordinates":[-73.665413,41.001063],"type":"Point"}
}