{
  "type": "Feature",
  "properties": {
    "addr:full":"370 Colman St New London CT 06320",
    "addr:housenumber":"370",
    "addr:postcode":"06320",
    "addr:street":"Colman St New London Ct",
    "iso:country":"US",
    "sg:address":"370 Colman St",
    "sg:city":"New London",
    "sg:classifiers":[
        {
            "category":"Restaurant",
            "type":"Food & Drink"
        }
    ],
    "sg:menulink":"http://www.allmenus.com/ct/new-london/169428-wendys/menu/",
    "sg:phone":"+1 860 444 8965",
    "sg:postcode":"06320",
    "sg:province":"CT",
    "sg:tags":[
        "burger",
        "american",
        "soup"
    ],
    "wof:name":"Wendy's",
    "wof:placetype":"venue"
},
  "geometry": {"coordinates":[-72.11597,41.358939],"type":"Point"}
}