{
  "type": "Feature",
  "properties": {
    "iso:country":"US",
    "sg:address":"170 Boston Post Rd",
    "sg:city":"Madison",
    "sg:classifiers":[
        {
            "category":"Building & Trades",
            "subcategory":"Plumbing",
            "type":"Services"
        }
    ],
    "sg:phone":"+1 203 245 1000",
    "sg:postcode":"06443",
    "sg:province":"CT",
    "sg:tags":[
        "plumbing",
        "contractor"
    ],
    "wof:name":"Roger Crampton Plumbing & Htg",
    "wof:placetype":"venue"
},
  "geometry": {"coordinates":[-72.63286600000001,41.282677],"type":"Point"}
}