{
  "type": "Feature",
  "properties": {
    "iso:country":"US",
    "sg:address":"6080 Main St",
    "sg:city":"Stratford",
    "sg:classifiers":[
        {
            "category":"Building & Trades",
            "subcategory":"Construction",
            "type":"Services"
        }
    ],
    "sg:phone":"+1 203 386 9493",
    "sg:postcode":"06614",
    "sg:province":"CT",
    "sg:tags":[
        "painter"
    ],
    "wof:name":"Ken Smith Painting & Deco",
    "wof:placetype":"venue"
},
  "geometry": {"coordinates":[-73.109635,41.23936],"type":"Point"}
}