{
  "type": "Feature",
  "properties": {
    "addr:full":"34 Dann Dr Stamford CT 06905",
    "addr:housenumber":"34",
    "addr:postcode":"06905",
    "addr:street":"Dann Dr",
    "iso:country":"US",
    "sg:address":"34 Dann Dr",
    "sg:city":"Stamford",
    "sg:classifiers":[
        {
            "category":"Building & Trades",
            "subcategory":"Landscaping Services",
            "type":"Services"
        }
    ],
    "sg:phone":"+1 203 329 7719",
    "sg:postcode":"06905",
    "sg:province":"CT",
    "sg:tags":[
        "landscape"
    ],
    "wof:name":"Verses Stphen Prperty Svcs LLC",
    "wof:placetype":"venue"
},
  "geometry": {"coordinates":[-73.541743,41.079005],"type":"Point"}
}