{
  "type": "Feature",
  "properties": {
    "iso:country":"US",
    "sg:address":"52 Whitney Ave",
    "sg:city":"New Haven",
    "sg:classifiers":[
        {
            "category":"Social Services",
            "type":"Services"
        }
    ],
    "sg:phone":"+1 203 773 9233",
    "sg:postcode":"06510",
    "sg:province":"CT",
    "sg:tags":[
        "organization",
        "welfare"
    ],
    "wof:name":"Best Buddies Intl Inc",
    "wof:placetype":"venue"
},
  "geometry": {"coordinates":[-72.92186700000001,41.312894],"type":"Point"}
}