{
  "type": "Feature",
  "properties": {
    "addr:full":"281 Riversville Rd Greenwich CT 06831",
    "addr:housenumber":"281",
    "addr:postcode":"06831",
    "addr:street":"Riversville Rd",
    "iso:country":"US",
    "sg:address":"281 Riversville Rd",
    "sg:city":"Greenwich",
    "sg:classifiers":[
        {
            "category":"Building & Trades",
            "subcategory":"Construction",
            "type":"Services"
        }
    ],
    "sg:phone":"+1 203 661 1218",
    "sg:postcode":"06831",
    "sg:province":"CT",
    "sg:tags":[
        "contractor"
    ],
    "wof:name":"Hvolbeck RC Construction",
    "wof:placetype":"venue"
},
  "geometry": {"coordinates":[-73.669693,41.054114],"type":"Point"}
}