{
  "type": "Feature",
  "properties": {
    "addr:full":"6523 Main St Trumbull CT 06611",
    "addr:housenumber":"6523",
    "addr:postcode":"06611",
    "addr:street":"Main St",
    "iso:country":"US",
    "sg:address":"6523 Main St",
    "sg:city":"Trumbull",
    "sg:classifiers":[
        {
            "category":"Personal",
            "subcategory":"Barber",
            "type":"Services"
        }
    ],
    "sg:phone":"+1 203 445 1321",
    "sg:postcode":"06611",
    "sg:province":"CT",
    "wof:name":"Paul's Hair Cutters",
    "wof:placetype":"venue"
},
  "geometry": {"coordinates":[-73.228289,41.278195],"type":"Point"}
}