{
  "type": "Feature",
  "properties": {
    "iso:country":"US",
    "sg:address":"366 Hebron Ave",
    "sg:city":"Glastonbury",
    "sg:classifiers":[
        {
            "category":"Shopping",
            "subcategory":"Gifts & Souvenirs",
            "type":"Retail Goods"
        }
    ],
    "sg:phone":"+1 860 657 1322",
    "sg:postcode":"06033",
    "sg:province":"CT",
    "sg:tags":[
        "floral",
        "cloth",
        "silk"
    ],
    "wof:name":"Polka Dots",
    "wof:placetype":"venue"
},
  "geometry": {"coordinates":[-72.599341,41.713683],"type":"Point"}
}