{
  "type": "Feature",
  "properties": {
    "addr:full":"88 Van Buren Ave Hartford CT 06107",
    "addr:housenumber":"88",
    "addr:postcode":"06107",
    "addr:street":"Van Buren Ave;Ct",
    "iso:country":"US",
    "sg:address":"88 Van Buren Ave",
    "sg:city":"Hartford",
    "sg:classifiers":[
        {
            "category":"Professional",
            "subcategory":"Management & Consulting",
            "type":"Services"
        }
    ],
    "sg:phone":"+1 860 521 7779",
    "sg:postcode":"06107",
    "sg:province":"CT",
    "sg:tags":[
        "advisory",
        "investment"
    ],
    "wof:name":"More For Less Fncl Sltions LLC",
    "wof:placetype":"venue"
},
  "geometry": {"coordinates":[-72.75100999999999,41.753516],"type":"Point"}
}