{
  "type": "Feature",
  "properties": {
    "iso:country":"US",
    "sg:address":"90 Bridgeport Ave",
    "sg:city":"Shelton",
    "sg:classifiers":[
        {
            "category":"Local Transit",
            "type":"Transportation"
        }
    ],
    "sg:phone":"+1 203 000 1111",
    "sg:postcode":"06484",
    "sg:province":"CT",
    "sg:tags":[
        "ambulance"
    ],
    "wof:name":"American Medical Response",
    "wof:placetype":"venue"
},
  "geometry": {"coordinates":[-73.097466,41.310973],"type":"Point"}
}