{
  "type": "Feature",
  "properties": {
    "addr:full":"1106 S Main St Cheshire CT 06410",
    "addr:housenumber":"1106",
    "addr:postcode":"06410",
    "addr:street":"S Main St",
    "iso:country":"US",
    "sg:address":"1106 S Main St",
    "sg:city":"Cheshire",
    "sg:classifiers":[
        {
            "category":"Travel",
            "subcategory":"Hotels & Motels",
            "type":"Entertainment"
        }
    ],
    "sg:phone":"+1   ",
    "sg:postcode":"06410",
    "sg:province":"CT",
    "sg:tags":[
        "operation"
    ],
    "wof:name":"Cheshire Welcome Inn",
    "wof:placetype":"venue"
},
  "geometry": {"coordinates":[-72.906352,41.474713],"type":"Point"}
}