{
  "type": "Feature",
  "properties": {
    "addr:full":"6 N Main St Branford CT 06405",
    "addr:housenumber":"6",
    "addr:postcode":"06405",
    "addr:street":"N Main St",
    "iso:country":"US",
    "sg:address":"6 N Main St",
    "sg:city":"Branford",
    "sg:phone":"+1 203 483 1260",
    "sg:postcode":"06405",
    "sg:province":"CT",
    "sg:website":"http://www.starbuckscoffee.com",
    "wof:name":"Starbucks Coffee",
    "wof:placetype":"venue"
},
  "geometry": {"coordinates":[-72.82661400000001,41.277945],"type":"Point"}
}