{
  "type": "Feature",
  "properties": {
    "iso:country":"US",
    "sg:address":"1954 Baldwin St",
    "sg:city":"Waterbury",
    "sg:classifiers":[
        {
            "category":"Wholesale",
            "subcategory":"Groceries",
            "type":"Manufacturing & Wholesale Goods"
        }
    ],
    "sg:phone":"+1 203 753 5096",
    "sg:postcode":"06706",
    "sg:province":"CT",
    "sg:tags":[
        "general"
    ],
    "wof:name":"Sweet Life Foods Cash & Carry",
    "wof:placetype":"venue"
},
  "geometry": {"coordinates":[-73.038115,41.527464],"type":"Point"}
}