{
  "type": "Feature",
  "properties": {
    "addr:full":"60 Haig Ave Stamford CT 06905",
    "addr:housenumber":"60",
    "addr:postcode":"06905",
    "addr:street":"Haig Ave",
    "iso:country":"US",
    "sg:address":"60 Haig Ave",
    "sg:city":"Stamford",
    "sg:classifiers":[
        {
            "category":"Professional",
            "type":"Services"
        }
    ],
    "sg:phone":"+1 203 353 9727",
    "sg:postcode":"06905",
    "sg:province":"CT",
    "wof:name":"Adorra Dorivatives RES",
    "wof:placetype":"venue"
},
  "geometry": {"coordinates":[-73.528488,41.0868],"type":"Point"}
}