{
  "type": "Feature",
  "properties": {
    "iso:country":"US",
    "sg:address":"17 Lantern Hill Ln",
    "sg:city":"Guilford",
    "sg:classifiers":[
        {
            "category":"Professional",
            "subcategory":"Management & Consulting",
            "type":"Services"
        }
    ],
    "sg:phone":"+1   ",
    "sg:postcode":"06437",
    "sg:province":"CT",
    "sg:tags":[
        "business"
    ],
    "wof:name":"Financial Management Group LLC",
    "wof:placetype":"venue"
},
  "geometry": {"coordinates":[-72.69135900000001,41.313113],"type":"Point"}
}