{
  "type": "Feature",
  "properties": {
    "iso:country":"US",
    "sg:address":"314 Main St",
    "sg:city":"Farmington",
    "sg:classifiers":[
        {
            "category":"Banks & Credit Unions",
            "subcategory":"Bank",
            "type":"Services"
        }
    ],
    "sg:phone":"+1 860 677 9669",
    "sg:postcode":"06032",
    "sg:province":"CT",
    "sg:tags":[
        "broker",
        "mortgage"
    ],
    "wof:name":"Mortgage Master Inc 3rd Flr",
    "wof:placetype":"venue"
},
  "geometry": {"coordinates":[-72.843344,41.704185],"type":"Point"}
}