{
  "type": "Feature",
  "properties": {
    "iso:country":"US",
    "sg:address":"325 Flanders Rd",
    "sg:city":"Bethlehem",
    "sg:classifiers":[
        {
            "category":"Retail",
            "subcategory":"Animal Services",
            "type":"Services"
        }
    ],
    "sg:phone":"+1 203 266 5150",
    "sg:postcode":"06751",
    "sg:province":"CT",
    "wof:name":"Spodnicks K-9 Services",
    "wof:placetype":"venue"
},
  "geometry": {"coordinates":[-73.210932,41.608247],"type":"Point"}
}