{
  "type": "Feature",
  "properties": {
    "addr:full":"70 Coit St New London CT 06320",
    "addr:housenumber":"70",
    "addr:postcode":"06320",
    "addr:street":"Coit St New London Ct",
    "iso:country":"US",
    "sg:address":"70 Coit St",
    "sg:city":"New London",
    "sg:classifiers":[
        {
            "category":"Recreation",
            "type":"Entertainment"
        }
    ],
    "sg:phone":"+1   ",
    "sg:postcode":"06320",
    "sg:province":"CT",
    "wof:name":"Stephen Desouto",
    "wof:placetype":"venue"
},
  "geometry": {"coordinates":[-72.101393,41.352545],"type":"Point"}
}