{
  "type": "Feature",
  "properties": {
    "iso:country":"US",
    "sg:address":"277 Spring Rd",
    "sg:city":"North Haven",
    "sg:classifiers":[
        {
            "category":"Building & Trades",
            "subcategory":"Electrical",
            "type":"Services"
        }
    ],
    "sg:phone":"+1 203 234 7267",
    "sg:postcode":"06473",
    "sg:province":"CT",
    "sg:tags":[
        "electrical",
        "contractor"
    ],
    "wof:name":"Aero Electric LLC",
    "wof:placetype":"venue"
},
  "geometry": {"coordinates":[-72.84666300000001,41.370336],"type":"Point"}
}