{
  "type": "Feature",
  "properties": {
    "iso:country":"US",
    "sg:address":"2842 Old Dixwell Ave",
    "sg:city":"Hamden",
    "sg:classifiers":[
        {
            "category":"Personal",
            "subcategory":"Beauty Salon",
            "type":"Services"
        }
    ],
    "sg:phone":"+1 203 281 1868",
    "sg:postcode":"06518",
    "sg:province":"CT",
    "wof:name":"Constance Hair & Nail Salon",
    "wof:placetype":"venue"
},
  "geometry": {"coordinates":[-72.90504,41.383938],"type":"Point"}
}