{
  "type": "Feature",
  "properties": {
    "iso:country":"US",
    "sg:address":"541 Wilson St",
    "sg:city":"Waterbury",
    "sg:classifiers":[
        {
            "category":"Building & Trades",
            "subcategory":"Pest Control",
            "type":"Services"
        }
    ],
    "sg:phone":"+1   ",
    "sg:postcode":"06708",
    "sg:province":"CT",
    "sg:tags":[
        "structure"
    ],
    "wof:name":"Kalosky & New Milford Pest Con",
    "wof:placetype":"venue"
},
  "geometry": {"coordinates":[-73.050281,41.542908],"type":"Point"}
}