{
  "type": "Feature",
  "properties": {
    "iso:country":"US",
    "sg:address":"2316 Fairfield Ave",
    "sg:city":"Bridgeport",
    "sg:classifiers":[
        {
            "category":"Autos & Motor Vehicles",
            "subcategory":"Motorcycle Sales",
            "type":"Retail Goods"
        }
    ],
    "sg:phone":"+1 203 366 9191",
    "sg:postcode":"06605",
    "sg:province":"CT",
    "sg:tags":[
        "scooter"
    ],
    "wof:name":"Momentum Cycle",
    "wof:placetype":"venue"
},
  "geometry": {"coordinates":[-73.221182,41.163063],"type":"Point"}
}