{
  "type": "Feature",
  "properties": {
    "iso:country":"US",
    "sg:address":"35 Eastern Steel Rd",
    "sg:city":"Milford",
    "sg:classifiers":[
        {
            "category":"Autos & Motor Vehicles",
            "subcategory":"Auto Supplies",
            "type":"Retail Goods"
        }
    ],
    "sg:phone":"+1 203 783 1422",
    "sg:postcode":"06460",
    "sg:province":"CT",
    "sg:tags":[
        "automobile",
        "parts"
    ],
    "wof:name":"Connecticut Import Performance",
    "wof:placetype":"venue"
},
  "geometry": {"coordinates":[-73.02059800000001,41.234325],"type":"Point"}
}