{
  "type": "Feature",
  "properties": {
    "addr:full":"12 Pasco Dr East Windsor CT 06088",
    "addr:housenumber":"12",
    "addr:postcode":"06088",
    "addr:street":"Pasco Dr East Windsor Ct",
    "iso:country":"US",
    "sg:address":"12 Pasco Dr",
    "sg:city":"East Windsor",
    "sg:classifiers":[
        {
            "category":"Professional",
            "subcategory":"Management & Consulting",
            "type":"Services"
        }
    ],
    "sg:phone":"+1   ",
    "sg:postcode":"06088",
    "sg:province":"CT",
    "wof:name":"Jdi Associates",
    "wof:placetype":"venue"
},
  "geometry": {"coordinates":[-72.60841000000001,41.909998],"type":"Point"}
}