{
  "type": "Feature",
  "properties": {
    "iso:country":"US",
    "sg:address":"817 Chapel St",
    "sg:city":"New Haven",
    "sg:classifiers":[
        {
            "category":"Personal",
            "type":"Services"
        },
        {
            "category":"Personal",
            "subcategory":"Tattoo Parlor",
            "type":"Services"
        }
    ],
    "sg:phone":"+1 203 752 0564",
    "sg:postcode":"06510",
    "sg:province":"CT",
    "sg:tags":[
        "tattooing"
    ],
    "wof:name":"Hope Gallery LLC",
    "wof:placetype":"venue"
},
  "geometry": {"coordinates":[-72.925596,41.306035],"type":"Point"}
}