{
  "type": "Feature",
  "properties": {
    "addr:full":"45 Grandview Dr Baltic CT 06330",
    "addr:housenumber":"45",
    "addr:postcode":"06330",
    "addr:street":"Grandview Dr Baltic Ct",
    "iso:country":"US",
    "sg:address":"45 Grandview Dr",
    "sg:city":"Baltic",
    "sg:classifiers":[
        {
            "category":"Retail",
            "subcategory":"Repair Shop",
            "type":"Services"
        }
    ],
    "sg:phone":"+1   ",
    "sg:postcode":"06330",
    "sg:province":"CT",
    "wof:name":"Caplets Repair LLC",
    "wof:placetype":"venue"
},
  "geometry": {"coordinates":[-72.067273,41.618832],"type":"Point"}
}