{
  "type": "Feature",
  "properties": {
    "iso:country":"US",
    "sg:address":"153 Hazel Plain Rd",
    "sg:city":"Woodbury",
    "sg:classifiers":[
        {
            "category":"Real Estate",
            "subcategory":"Real Estate Operator",
            "type":"Services"
        }
    ],
    "sg:phone":"+1 203 263 5256",
    "sg:postcode":"06798",
    "sg:province":"CT",
    "sg:tags":[
        "building",
        "nonresidential"
    ],
    "wof:name":"Woodbury Properties LLC",
    "wof:placetype":"venue"
},
  "geometry": {"coordinates":[-73.25031199999999,41.575282],"type":"Point"}
}