{
  "type": "Feature",
  "properties": {
    "iso:country":"US",
    "sg:address":"726 Connecticut Ave",
    "sg:city":"Norwalk",
    "sg:classifiers":[
        {
            "category":"Retail",
            "subcategory":"Animal Services",
            "type":"Services"
        }
    ],
    "sg:phone":"+1 203 866 2383",
    "sg:postcode":"06854",
    "sg:province":"CT",
    "sg:tags":[
        "veterinary"
    ],
    "wof:name":"Boarding House Inc",
    "wof:placetype":"venue"
},
  "geometry": {"coordinates":[-73.453344,41.092229],"type":"Point"}
}