{
  "type": "Feature",
  "properties": {
    "addr:full":"440 Hut Hill Rd Bridgewater CT 06752",
    "addr:housenumber":"440",
    "addr:postcode":"06752",
    "addr:street":"Hut Hill Rd",
    "iso:country":"US",
    "sg:address":"440 Hut Hill Rd",
    "sg:city":"Bridgewater",
    "sg:classifiers":[
        {
            "category":"Home & Garden",
            "subcategory":"Garden Supply",
            "type":"Retail Goods"
        }
    ],
    "sg:phone":"+1   ",
    "sg:postcode":"06752",
    "sg:province":"CT",
    "sg:tags":[
        "lawn"
    ],
    "wof:name":"Campbell Services",
    "wof:placetype":"venue"
},
  "geometry": {"coordinates":[-73.33753,41.513487],"type":"Point"}
}