{
  "type": "Feature",
  "properties": {
    "addr:full":"1404 Whalley Ave New Haven CT 06515",
    "addr:housenumber":"1404",
    "addr:postcode":"06515",
    "addr:street":"Whalley Ave",
    "iso:country":"US",
    "sg:address":"1404 Whalley Ave",
    "sg:city":"New Haven",
    "sg:classifiers":[
        {
            "category":"Organizations",
            "subcategory":"Religious Organization",
            "type":"Services"
        }
    ],
    "sg:phone":"+1 203 389 1958",
    "sg:postcode":"06515",
    "sg:province":"CT",
    "sg:tags":[
        "counseling"
    ],
    "wof:name":"Ruzmar",
    "wof:placetype":"venue"
},
  "geometry": {"coordinates":[-72.976339,41.333974],"type":"Point"}
}