{
  "type": "Feature",
  "properties": {
    "addr:full":"250 Day St Brooklyn CT 06234",
    "addr:housenumber":"250",
    "addr:postcode":"06234",
    "addr:street":"Day St",
    "iso:country":"US",
    "sg:address":"250 Day St",
    "sg:city":"Brooklyn",
    "sg:classifiers":[
        {
            "category":"Retail",
            "subcategory":"Animal Services",
            "type":"Services"
        }
    ],
    "sg:phone":"+1 860 779 9138",
    "sg:postcode":"06234",
    "sg:province":"CT",
    "wof:name":"North East Petsitters LLC",
    "wof:placetype":"venue"
},
  "geometry": {"coordinates":[-71.908535,41.812882],"type":"Point"}
}