{
  "type": "Feature",
  "properties": {
    "addr:full":"6 Tree Top Ln Broad Brook CT 06016",
    "addr:housenumber":"6",
    "addr:postcode":"06016",
    "addr:street":"Tree Top Ln Broad Brook Ct",
    "iso:country":"US",
    "sg:address":"6 Tree Top Ln",
    "sg:city":"Broad Brook",
    "sg:classifiers":[
        {
            "category":"Building & Trades",
            "subcategory":"Landscaping Services",
            "type":"Services"
        }
    ],
    "sg:phone":"+1 860 627 4933",
    "sg:postcode":"06016",
    "sg:province":"CT",
    "wof:name":"Tree Top Lawn Service",
    "wof:placetype":"venue"
},
  "geometry": {"coordinates":[-72.527233,41.910998],"type":"Point"}
}