{
  "type": "Feature",
  "properties": {
    "iso:country":"US",
    "sg:address":"416 Highland Ave",
    "sg:city":"Cheshire",
    "sg:classifiers":[
        {
            "category":"Manufacturing",
            "subcategory":"Food",
            "type":"Manufacturing & Wholesale Goods"
        }
    ],
    "sg:phone":"+1 203 271 8005",
    "sg:postcode":"06410",
    "sg:province":"CT",
    "sg:tags":[
        "winery"
    ],
    "wof:name":"Worldwide Wines Of Ny Inc",
    "wof:placetype":"venue"
},
  "geometry": {"coordinates":[-72.899762,41.508456],"type":"Point"}
}