{
  "type": "Feature",
  "properties": {
    "iso:country":"US",
    "sg:address":"38 Park Lane Rd",
    "sg:city":"New Milford",
    "sg:classifiers":[
        {
            "category":"Restaurant",
            "type":"Food & Drink"
        }
    ],
    "sg:phone":"+1 860 350 9596",
    "sg:postcode":"06776",
    "sg:province":"CT",
    "sg:tags":[
        "eating"
    ],
    "wof:name":"Colosseo Restaurant & Pizza",
    "wof:placetype":"venue"
},
  "geometry": {"coordinates":[-73.406414,41.594144],"type":"Point"}
}