{
  "type": "Feature",
  "properties": {
    "addr:full":"3853 Main St Bridgeport CT 06606",
    "addr:housenumber":"3853",
    "addr:postcode":"06606",
    "addr:street":"Main St",
    "iso:country":"US",
    "sg:address":"3853 Main St",
    "sg:city":"Bridgeport",
    "sg:classifiers":[
        {
            "category":"Personal",
            "type":"Services"
        }
    ],
    "sg:phone":"+1   ",
    "sg:postcode":"06606",
    "sg:province":"CT",
    "wof:name":"American SPA",
    "wof:placetype":"venue"
},
  "geometry": {"coordinates":[-73.211072,41.212996],"type":"Point"}
}