{
  "type": "Feature",
  "properties": {
    "iso:country":"US",
    "sg:address":"6 Shelview Dr",
    "sg:city":"Shelton",
    "sg:classifiers":[
        {
            "category":"Building & Trades",
            "subcategory":"Construction",
            "type":"Services"
        }
    ],
    "sg:phone":"+1 203 926 9909",
    "sg:postcode":"06484",
    "sg:province":"CT",
    "sg:tags":[
        "resurfacing",
        "laying",
        "refinishing",
        "floor"
    ],
    "wof:name":"Weiss Floor Covering",
    "wof:placetype":"venue"
},
  "geometry": {"coordinates":[-73.09652199999999,41.288815],"type":"Point"}
}