{
  "type": "Feature",
  "properties": {
    "addr:full":"260 Berkshire Rd Southbury CT 06488",
    "addr:housenumber":"260",
    "addr:postcode":"06488",
    "addr:street":"Berkshire Rd",
    "iso:country":"US",
    "sg:address":"260 Berkshire Rd",
    "sg:city":"Southbury",
    "sg:classifiers":[
        {
            "category":"Professional",
            "type":"Services"
        }
    ],
    "sg:phone":"+1   ",
    "sg:postcode":"06488",
    "sg:province":"CT",
    "wof:name":"Heritage Property Services",
    "wof:placetype":"venue"
},
  "geometry": {"coordinates":[-73.258809,41.439672],"type":"Point"}
}