{
  "type": "Feature",
  "properties": {
    "iso:country":"US",
    "sg:address":"163 Washington St",
    "sg:city":"Norwich",
    "sg:classifiers":[
        {
            "category":"Professional",
            "type":"Services"
        }
    ],
    "sg:phone":"+1 860 887 9919",
    "sg:postcode":"06360",
    "sg:province":"CT",
    "wof:name":"Integral Controls LLC",
    "wof:placetype":"venue"
},
  "geometry": {"coordinates":[-72.082424,41.531876],"type":"Point"}
}