{
  "type": "Feature",
  "properties": {
    "iso:country":"US",
    "sg:address":"321 Hope St",
    "sg:city":"Stamford",
    "sg:classifiers":[
        {
            "category":"Recreation",
            "type":"Entertainment"
        }
    ],
    "sg:phone":"+1   ",
    "sg:postcode":"06906",
    "sg:province":"CT",
    "wof:name":"Blades Services Ltd",
    "wof:placetype":"venue"
},
  "geometry": {"coordinates":[-73.524187,41.071067],"type":"Point"}
}