{
  "type": "Feature",
  "properties": {
    "addr:full":"722 N Colony Rd Wallingford CT 06492",
    "addr:housenumber":"722",
    "addr:postcode":"06492",
    "addr:street":"N Colony Rd",
    "iso:country":"US",
    "sg:address":"722 N Colony Rd",
    "sg:city":"Wallingford",
    "sg:classifiers":[
        {
            "category":"Retail",
            "subcategory":"Auto Repair",
            "type":"Services"
        }
    ],
    "sg:phone":"+1 203 269 4495",
    "sg:postcode":"06492",
    "sg:province":"CT",
    "sg:tags":[
        "body",
        "automobile",
        "painting"
    ],
    "wof:name":"Milici's Auto Inc",
    "wof:placetype":"venue"
},
  "geometry": {"coordinates":[-72.8133,41.475567],"type":"Point"}
}