{
  "type": "Feature",
  "properties": {
    "iso:country":"US",
    "sg:address":"494 Main St",
    "sg:city":"Monroe",
    "sg:classifiers":[
        {
            "category":"Home & Garden",
            "subcategory":"Home Furnishings",
            "type":"Retail Goods"
        }
    ],
    "sg:phone":"+1 203 459 9471",
    "sg:postcode":"06468",
    "sg:province":"CT",
    "sg:tags":[
        "pottery"
    ],
    "wof:name":"Clay Date",
    "wof:placetype":"venue"
},
  "geometry": {"coordinates":[-73.265956,41.323521],"type":"Point"}
}