{
  "type": "Feature",
  "properties": {
    "iso:country":"US",
    "sg:address":"271 Franklin Ave",
    "sg:city":"Hartford",
    "sg:classifiers":[
        {
            "category":"Personal",
            "subcategory":"Beauty Salon",
            "type":"Services"
        }
    ],
    "sg:phone":"+1   ",
    "sg:postcode":"06114",
    "sg:province":"CT",
    "sg:tags":[
        "shop"
    ],
    "wof:name":"Decache Hair Salon",
    "wof:placetype":"venue"
},
  "geometry": {"coordinates":[-72.676286,41.74227],"type":"Point"}
}