{
  "type": "Feature",
  "properties": {
    "addr:full":"364 Main St Ansonia CT 06401",
    "addr:housenumber":"364",
    "addr:postcode":"06401",
    "addr:street":"Main St",
    "iso:country":"US",
    "sg:address":"364 Main St",
    "sg:city":"Ansonia",
    "sg:classifiers":[
        {
            "category":"Restaurant",
            "type":"Food & Drink"
        }
    ],
    "sg:phone":"+1 203 734 6559",
    "sg:postcode":"06401",
    "sg:province":"CT",
    "wof:name":"Osiris Cafe",
    "wof:placetype":"venue"
},
  "geometry": {"coordinates":[-73.077973,41.341211],"type":"Point"}
}