{
  "type": "Feature",
  "properties": {
    "iso:country":"US",
    "sg:address":"145 Highland Ave",
    "sg:city":"Cheshire",
    "sg:classifiers":[
        {
            "category":"Utilities",
            "subcategory":"Mobile Phone",
            "type":"Services"
        }
    ],
    "sg:phone":"+1 203 272 3272",
    "sg:postcode":"06410",
    "sg:province":"CT",
    "sg:tags":[
        "telephone",
        "cellular"
    ],
    "wof:name":"American Cellular",
    "wof:placetype":"venue"
},
  "geometry": {"coordinates":[-72.900738,41.503508],"type":"Point"}
}