{
  "type": "Feature",
  "properties": {
    "addr:full":"23 Avon Rd Branford CT 06405",
    "addr:housenumber":"23",
    "addr:postcode":"06405",
    "addr:street":"Avon Rd",
    "iso:country":"US",
    "sg:address":"23 Avon Rd",
    "sg:city":"Branford",
    "sg:classifiers":[
        {
            "category":"Personal",
            "subcategory":"Beauty Salon",
            "type":"Services"
        }
    ],
    "sg:phone":"+1   ",
    "sg:postcode":"06405",
    "sg:province":"CT",
    "sg:tags":[
        "shop"
    ],
    "wof:name":"Bastians Skin & Body Clinic",
    "wof:placetype":"venue"
},
  "geometry": {"coordinates":[-72.830969,41.290535],"type":"Point"}
}