{
  "type": "Feature",
  "properties": {
    "addr:full":"83 Atlantic St Stamford CT 06901",
    "addr:housenumber":"83",
    "addr:postcode":"06901",
    "addr:street":"Atlantic St",
    "iso:country":"US",
    "sg:address":"83 Atlantic St",
    "sg:city":"Stamford",
    "sg:classifiers":[
        {
            "category":"Restaurant",
            "type":"Food & Drink"
        }
    ],
    "sg:menulink":"http://www.allmenus.com/ct/stamford/251021-fiesta-atlantic/menu/",
    "sg:phone":"+1 203 323 4300",
    "sg:postcode":"06901",
    "sg:province":"CT",
    "sg:tags":[
        "mexican"
    ],
    "wof:name":"Fiesta Atlantic",
    "wof:placetype":"venue"
},
  "geometry": {"coordinates":[-73.53937000000001,41.05383],"type":"Point"}
}