{
  "type": "Feature",
  "properties": {
    "addr:full":"19 Wendover Rd Newtown CT 06470",
    "addr:housenumber":"19",
    "addr:postcode":"06470",
    "addr:street":"Wendover Rd",
    "iso:country":"US",
    "sg:address":"19 Wendover Rd",
    "sg:city":"Newtown",
    "sg:classifiers":[
        {
            "category":"Shopping",
            "subcategory":"Computers & Home Electronics",
            "type":"Retail Goods"
        }
    ],
    "sg:phone":"+1 203 270 9818",
    "sg:postcode":"06470",
    "sg:province":"CT",
    "sg:tags":[
        "publishing"
    ],
    "sg:website":"www.azimuthcomm.com",
    "wof:name":"Azimuth Communications",
    "wof:placetype":"venue"
},
  "geometry": {"coordinates":[-73.30836499999999,41.417678],"type":"Point"}
}