{
  "type": "Feature",
  "properties": {
    "addr:full":"200 Blue Hills Trl Glastonbury CT 06033",
    "addr:housenumber":"200",
    "addr:postcode":"06033",
    "addr:street":"Blue Hills Trl",
    "iso:country":"US",
    "sg:address":"200 Blue Hills Trl",
    "sg:city":"Glastonbury",
    "sg:classifiers":[
        {
            "category":"Building & Trades",
            "subcategory":"Construction",
            "type":"Services"
        }
    ],
    "sg:phone":"+1 860 657 4000",
    "sg:postcode":"06033",
    "sg:province":"CT",
    "sg:tags":[
        "real estate"
    ],
    "wof:name":"Tyler Development Company",
    "wof:placetype":"venue"
},
  "geometry": {"coordinates":[-72.477847,41.688941],"type":"Point"}
}