{
  "type": "Feature",
  "properties": {
    "addr:full":"968 Old Colony Rd Meriden CT 06451",
    "addr:housenumber":"968",
    "addr:postcode":"06451",
    "addr:street":"Old Colony Rd",
    "iso:country":"US",
    "sg:address":"968 Old Colony Rd",
    "sg:city":"Meriden",
    "sg:classifiers":[
        {
            "category":"Freight",
            "type":"Transportation"
        }
    ],
    "sg:phone":"+1 203 237 7496",
    "sg:postcode":"06451",
    "sg:province":"CT",
    "sg:tags":[
        "general"
    ],
    "wof:name":"Triple A Self-Storage",
    "wof:placetype":"venue"
},
  "geometry": {"coordinates":[-72.814798,41.516834],"type":"Point"}
}