{
  "type": "Feature",
  "properties": {
    "addr:full":"17 Moose Hill Rd Oxford CT 06478",
    "addr:housenumber":"17",
    "addr:postcode":"06478",
    "addr:street":"Moose Hill Rd",
    "iso:country":"US",
    "sg:address":"17 Moose Hill Rd",
    "sg:city":"Oxford",
    "sg:classifiers":[
        {
            "category":"Building & Trades",
            "subcategory":"Plumbing",
            "type":"Services"
        }
    ],
    "sg:phone":"+1 203 881 1278",
    "sg:postcode":"06478",
    "sg:province":"CT",
    "sg:tags":[
        "septic"
    ],
    "wof:name":"East Coast Septic Tank Svc",
    "wof:placetype":"venue"
},
  "geometry": {"coordinates":[-73.114734,41.388843],"type":"Point"}
}