{
  "type": "Feature",
  "properties": {
    "addr:full":"689 Maple Ave Hartford CT 06114",
    "addr:housenumber":"689",
    "addr:postcode":"06114",
    "addr:street":"Maple Ave;Ct",
    "iso:country":"US",
    "sg:address":"689 Maple Ave",
    "sg:city":"Hartford",
    "sg:classifiers":[
        {
            "category":"Personal",
            "subcategory":"Barber",
            "type":"Services"
        }
    ],
    "sg:phone":"+1   ",
    "sg:postcode":"06114",
    "sg:province":"CT",
    "sg:tags":[
        "shop",
        "beauty"
    ],
    "wof:name":"Unisex Hair Salon",
    "wof:placetype":"venue"
},
  "geometry": {"coordinates":[-72.683352,41.742097],"type":"Point"}
}