{
  "type": "Feature",
  "properties": {
    "iso:country":"US",
    "sg:address":"30 Conestoga Dr",
    "sg:city":"Madison",
    "sg:classifiers":[
        {
            "category":"Manufacturing",
            "subcategory":"Metals",
            "type":"Manufacturing & Wholesale Goods"
        }
    ],
    "sg:phone":"+1 203 318 8041",
    "sg:postcode":"06443",
    "sg:province":"CT",
    "sg:tags":[
        "mfg",
        "metalwork",
        "structural"
    ],
    "wof:name":"Beverly Bakes",
    "wof:placetype":"venue"
},
  "geometry": {"coordinates":[-72.594154,41.287761],"type":"Point"}
}