{
  "type": "Feature",
  "properties": {
    "iso:country":"US",
    "sg:address":"201 S King St",
    "sg:city":"Danbury",
    "sg:classifiers":[
        {
            "category":"Place Of Worship",
            "subcategory":"Church",
            "type":"Public Place"
        },
        {
            "category":"Place Of Worship",
            "type":"Public Place"
        }
    ],
    "sg:phone":"+1 203 743 5427",
    "sg:postcode":"06811",
    "sg:province":"CT",
    "sg:tags":[
        "churches-united",
        "testament",
        "christ-new",
        "christ",
        "churches-church"
    ],
    "wof:name":"King St. United Church of Christ",
    "wof:placetype":"venue"
},
  "geometry": {"coordinates":[-73.507471,41.429809],"type":"Point"}
}