{
  "type": "Feature",
  "properties": {
    "iso:country":"US",
    "sg:address":"26 Pleasant St",
    "sg:city":"Meriden",
    "sg:classifiers":[
        {
            "category":"Retail",
            "subcategory":"Veterinary Services",
            "type":"Services"
        }
    ],
    "sg:phone":"+1 203 238 9863",
    "sg:postcode":"06450",
    "sg:province":"CT",
    "wof:name":"Tobin Stephen Dr Med Vet",
    "wof:placetype":"venue"
},
  "geometry": {"coordinates":[-72.798089,41.535386],"type":"Point"}
}