{
  "type": "Feature",
  "properties": {
    "addr:full":"5 Glen Rd Manchester CT 06040",
    "addr:housenumber":"5",
    "addr:postcode":"06040",
    "addr:street":"Glen Rd",
    "iso:country":"US",
    "sg:address":"5 Glen Rd",
    "sg:city":"Manchester",
    "sg:classifiers":[
        {
            "category":"Government",
            "subcategory":"Fire Station",
            "type":"Public Place"
        }
    ],
    "sg:phone":"+1 860 646 1146",
    "sg:postcode":"06040",
    "sg:province":"CT",
    "sg:tags":[
        "protection",
        "contractor"
    ],
    "wof:name":"Whe Fire Protection",
    "wof:placetype":"venue"
},
  "geometry": {"coordinates":[-72.490484,41.762221],"type":"Point"}
}