{
  "type": "Feature",
  "properties": {
    "addr:full":"1610 N Broad St Meriden CT 06450",
    "addr:housenumber":"1610",
    "addr:postcode":"06450",
    "addr:street":"N Broad St",
    "iso:country":"US",
    "sg:address":"1610 N Broad St",
    "sg:city":"Meriden",
    "sg:classifiers":[
        {
            "category":"Professional",
            "type":"Services"
        }
    ],
    "sg:phone":"+1 203 235 2460",
    "sg:postcode":"06450",
    "sg:province":"CT",
    "sg:tags":[
        "establishment"
    ],
    "wof:name":"Guardrail Inc",
    "wof:placetype":"venue"
},
  "geometry": {"coordinates":[-72.775367,41.562605],"type":"Point"}
}