{
  "type": "Feature",
  "properties": {
    "iso:country":"US",
    "sg:address":"984 Waterville St",
    "sg:city":"Waterbury",
    "sg:classifiers":[
        {
            "category":"Manufacturing",
            "subcategory":"Metals",
            "type":"Manufacturing & Wholesale Goods"
        }
    ],
    "sg:phone":"+1 203 574 2240",
    "sg:postcode":"06710",
    "sg:province":"CT",
    "sg:tags":[
        "stamping"
    ],
    "wof:name":"Truelove & Maclean Inc",
    "wof:placetype":"venue"
},
  "geometry": {"coordinates":[-73.047466,41.584807],"type":"Point"}
}