{
  "type": "Feature",
  "properties": {
    "iso:country":"US",
    "sg:address":"29 High St",
    "sg:city":"Bristol",
    "sg:classifiers":[
        {
            "category":"Professional",
            "subcategory":"Accounting & Tax Preparation",
            "type":"Services"
        }
    ],
    "sg:phone":"+1   ",
    "sg:postcode":"06010",
    "sg:province":"CT",
    "wof:name":"Joseph A Ableski CPA",
    "wof:placetype":"venue"
},
  "geometry": {"coordinates":[-72.94019299999999,41.673536],"type":"Point"}
}