{
  "type": "Feature",
  "properties": {
    "addr:full":"404 Post Rd E Westport CT 06880",
    "addr:housenumber":"404",
    "addr:postcode":"06880",
    "addr:street":"Post Rd E Westport Ct",
    "iso:country":"US",
    "sg:address":"404 Post Rd E",
    "sg:city":"Westport",
    "sg:classifiers":[
        {
            "category":"Shopping",
            "subcategory":"Luggage & Leather Goods",
            "type":"Retail Goods"
        }
    ],
    "sg:phone":"+1 203 226 0761",
    "sg:postcode":"06880",
    "sg:province":"CT",
    "sg:website":"www.silverofwestport.com",
    "wof:name":"Silver Of Westport Inc",
    "wof:placetype":"venue"
},
  "geometry": {"coordinates":[-73.351237,41.140023],"type":"Point"}
}