{
  "type": "Feature",
  "properties": {
    "iso:country":"US",
    "sg:address":"145 Beecher Rd",
    "sg:city":"Woodbridge",
    "sg:classifiers":[
        {
            "category":"Farming",
            "subcategory":"Farm",
            "type":"Manufacturing & Wholesale Goods"
        }
    ],
    "sg:phone":"+1 203 387 0237",
    "sg:postcode":"06525",
    "sg:province":"CT",
    "sg:tags":[
        "crop",
        "general"
    ],
    "wof:name":"Fellows Hillside Farm LLC",
    "wof:placetype":"venue"
},
  "geometry": {"coordinates":[-73.008335,41.349621],"type":"Point"}
}