{
  "type": "Feature",
  "properties": {
    "addr:full":"805 Village Walk Guilford CT 06437",
    "addr:housenumber":"805",
    "addr:postcode":"06437",
    "addr:street":"Village Walk",
    "iso:country":"US",
    "sg:address":"805 Village Walk",
    "sg:city":"Guilford",
    "sg:classifiers":[
        {
            "category":"Personal",
            "type":"Services"
        }
    ],
    "sg:phone":"+1   ",
    "sg:postcode":"06437",
    "sg:province":"CT",
    "sg:tags":[
        "shop",
        "beauty"
    ],
    "wof:name":"Heads Together",
    "wof:placetype":"venue"
},
  "geometry": {"coordinates":[-72.67490100000001,41.288187],"type":"Point"}
}