{
  "type": "Feature",
  "properties": {
    "iso:country":"US",
    "sg:address":"260 Main St",
    "sg:city":"Danbury",
    "sg:classifiers":[
        {
            "category":"Professional",
            "subcategory":"Accounting & Tax Preparation",
            "type":"Services"
        }
    ],
    "sg:phone":"+1 203 744 0241",
    "sg:postcode":"06810",
    "sg:province":"CT",
    "sg:tags":[
        "accountant"
    ],
    "wof:name":"H J Lubus Inc",
    "wof:placetype":"venue"
},
  "geometry": {"coordinates":[-73.45374,41.395576],"type":"Point"}
}