{
  "type": "Feature",
  "properties": {
    "iso:country":"US",
    "sg:address":"70 Prospect St",
    "sg:city":"Ridgefield",
    "sg:classifiers":[
        {
            "category":"Education",
            "subcategory":"School",
            "type":"Public Place"
        },
        {
            "category":"Government",
            "subcategory":"Office",
            "type":"Public Place"
        }
    ],
    "sg:phone":"+1 203 431 2800",
    "sg:postcode":"06877",
    "sg:province":"CT",
    "sg:website":"http://www.ststephens-ridgefield.org",
    "wof:name":"Ridgefield Public Schools",
    "wof:placetype":"venue"
},
  "geometry": {"coordinates":[-73.494873,41.283901],"type":"Point"}
}