{
  "type": "Feature",
  "properties": {
    "iso:country":"US",
    "sg:address":"427 Winsted Rd",
    "sg:city":"Torrington",
    "sg:classifiers":[
        {
            "category":"Recreation",
            "type":"Entertainment"
        }
    ],
    "sg:phone":"+1   ",
    "sg:postcode":"06790",
    "sg:province":"CT",
    "wof:name":"Northwest Gymnastic",
    "wof:placetype":"venue"
},
  "geometry": {"coordinates":[-73.113817,41.825417],"type":"Point"}
}