{
  "type": "Feature",
  "properties": {
    "iso:country":"US",
    "sg:address":"530 Fort Hale Rd",
    "sg:city":"East Haven",
    "sg:classifiers":[
        {
            "category":"Professional",
            "subcategory":"Computer Services",
            "type":"Services"
        }
    ],
    "sg:phone":"+1   ",
    "sg:postcode":"06512",
    "sg:province":"CT",
    "sg:tags":[
        "motion",
        "design",
        "system"
    ],
    "wof:name":"C M C Studios",
    "wof:placetype":"venue"
},
  "geometry": {"coordinates":[-72.89067300000001,41.271194],"type":"Point"}
}