{
  "type": "Feature",
  "properties": {
    "iso:country":"US",
    "sg:address":"1825 Barnum Ave",
    "sg:city":"Bridgeport",
    "sg:classifiers":[
        {
            "category":"Health Services",
            "subcategory":"Clinic",
            "type":"Services"
        }
    ],
    "sg:phone":"+1 203 331 9104",
    "sg:postcode":"06610",
    "sg:province":"CT",
    "wof:name":"Accident Injury Therapy Ctr",
    "wof:placetype":"venue"
},
  "geometry": {"coordinates":[-73.156853,41.189438],"type":"Point"}
}