{
  "type": "Feature",
  "properties": {
    "addr:full":"767 Ridge Rd Middletown CT 06457",
    "addr:housenumber":"767",
    "addr:postcode":"06457",
    "addr:street":"Ridge Rd",
    "iso:country":"US",
    "sg:address":"767 Ridge Rd",
    "sg:city":"Middletown",
    "sg:classifiers":[
        {
            "category":"Education",
            "subcategory":"School",
            "type":"Public Place"
        }
    ],
    "sg:phone":"+1   ",
    "sg:postcode":"06457",
    "sg:province":"CT",
    "wof:name":"Connecticut School Contracts",
    "wof:placetype":"venue"
},
  "geometry": {"coordinates":[-72.641473,41.527976],"type":"Point"}
}