{
  "type": "Feature",
  "properties": {
    "iso:country":"US",
    "sg:address":"35 Main St",
    "sg:city":"Essex",
    "sg:classifiers":[
        {
            "category":"Real Estate",
            "subcategory":"Real Estate Services",
            "type":"Services"
        }
    ],
    "sg:phone":"+1 860 767 5390",
    "sg:postcode":"06426",
    "sg:province":"CT",
    "sg:website":"www.pagetaft.com",
    "wof:name":"Page-Taft Real Estate",
    "wof:placetype":"venue"
},
  "geometry": {"coordinates":[-72.387336,41.351731],"type":"Point"}
}