{
  "type": "Feature",
  "properties": {
    "iso:country":"US",
    "sg:address":"196 Woodlawn Rd",
    "sg:city":"Berlin",
    "sg:classifiers":[
        {
            "category":"Professional",
            "subcategory":"Testing Lab",
            "type":"Services"
        }
    ],
    "sg:phone":"+1   ",
    "sg:postcode":"06037",
    "sg:province":"CT",
    "sg:tags":[
        "laboratory"
    ],
    "wof:name":"Mqs Super Heat",
    "wof:placetype":"venue"
},
  "geometry": {"coordinates":[-72.74757,41.632706],"type":"Point"}
}