{
  "type": "Feature",
  "properties": {
    "iso:country":"US",
    "sg:address":"102 Old Town Rd",
    "sg:city":"Ashford",
    "sg:classifiers":[
        {
            "category":"Retail",
            "subcategory":"Portrait Studio",
            "type":"Services"
        }
    ],
    "sg:phone":"+1   ",
    "sg:postcode":"06278",
    "sg:province":"CT",
    "sg:tags":[
        "photo"
    ],
    "wof:name":"Doyle JM Photography",
    "wof:placetype":"venue"
},
  "geometry": {"coordinates":[-72.20115199999999,41.937843],"type":"Point"}
}