{
  "type": "Feature",
  "properties": {
    "iso:country":"US",
    "sg:address":"102 Park St",
    "sg:city":"New Canaan",
    "sg:classifiers":[
        {
            "category":"Shopping",
            "subcategory":"Jewelry",
            "type":"Retail Goods"
        }
    ],
    "sg:phone":"+1 203 966 4922",
    "sg:postcode":"06840",
    "sg:province":"NY",
    "wof:name":"ARME Gems & Jewels LTD",
    "wof:placetype":"venue"
},
  "geometry": {"coordinates":[-73.495266,41.14631],"type":"Point"}
}