{
  "type": "Feature",
  "properties": {
    "iso:country":"US",
    "sg:address":"77 Vernon Rd",
    "sg:city":"East Hartford",
    "sg:classifiers":[
        {
            "category":"Personal",
            "subcategory":"Beauty Salon",
            "type":"Services"
        }
    ],
    "sg:phone":"+1   ",
    "sg:postcode":"06108",
    "sg:province":"CT",
    "sg:tags":[
        "shop",
        "health"
    ],
    "wof:name":"Britton & OConnell",
    "wof:placetype":"venue"
},
  "geometry": {"coordinates":[-72.584007,41.785637],"type":"Point"}
}