{
  "type": "Feature",
  "properties": {
    "addr:full":"12 Bittersweet Ln Ivoryton CT 06442",
    "addr:housenumber":"12",
    "addr:postcode":"06442",
    "addr:street":"Bittersweet Ln Ivoryton Ct",
    "iso:country":"US",
    "sg:address":"12 Bittersweet Ln",
    "sg:city":"Ivoryton",
    "sg:classifiers":[
        {
            "category":"Health Services",
            "subcategory":"Doctor",
            "type":"Services"
        }
    ],
    "sg:phone":"+1 860 767 0802",
    "sg:postcode":"06442",
    "sg:province":"CT",
    "sg:tags":[
        "psychiatrist"
    ],
    "wof:name":"Stanberry Mark C MD",
    "wof:placetype":"venue"
},
  "geometry": {"coordinates":[-72.438103,41.353298],"type":"Point"}
}