{
  "type": "Feature",
  "properties": {
    "iso:country":"US",
    "sg:address":"1111 Wordin Ave",
    "sg:city":"Bridgeport",
    "sg:classifiers":[
        {
            "category":"Organizations",
            "subcategory":"Religious Organization",
            "type":"Services"
        }
    ],
    "sg:phone":"+1 203 334 5681",
    "sg:postcode":"06605",
    "sg:province":"CT",
    "sg:tags":[
        "monastery",
        "convent"
    ],
    "wof:name":"Mary Immaculate Convent",
    "wof:placetype":"venue"
},
  "geometry": {"coordinates":[-73.216938,41.162802],"type":"Point"}
}