{
  "type": "Feature",
  "properties": {
    "iso:country":"US",
    "sg:address":"142 Mason St",
    "sg:city":"Greenwich",
    "sg:classifiers":[
        {
            "category":"Retail",
            "subcategory":"Laundry & Dry Cleaning",
            "type":"Services"
        }
    ],
    "sg:phone":"+1   ",
    "sg:postcode":"06830",
    "sg:province":"CT",
    "sg:tags":[
        "drycleaning",
        "plant"
    ],
    "wof:name":"Mason Drive-Thru Cleaners",
    "wof:placetype":"venue"
},
  "geometry": {"coordinates":[-73.62398899999999,41.027737],"type":"Point"}
}