{
  "type": "Feature",
  "properties": {
    "addr:full":"568 Old Colony Rd Meriden CT 06451",
    "addr:housenumber":"568",
    "addr:postcode":"06451",
    "addr:street":"Old Colony Rd",
    "iso:country":"US",
    "sg:address":"568 Old Colony Rd",
    "sg:city":"Meriden",
    "sg:classifiers":[
        {
            "category":"Professional",
            "type":"Services"
        }
    ],
    "sg:phone":"+1 203 235 2160",
    "sg:postcode":"06451",
    "sg:province":"CT",
    "wof:name":"Larwef LLC",
    "wof:placetype":"venue"
},
  "geometry": {"coordinates":[-72.81121400000001,41.523007],"type":"Point"}
}