{
  "type": "Feature",
  "properties": {
    "iso:country":"US",
    "sg:address":"424 Barn Hill Rd",
    "sg:city":"Monroe",
    "sg:classifiers":[
        {
            "category":"Building & Trades",
            "subcategory":"Electrical",
            "type":"Services"
        }
    ],
    "sg:phone":"+1 203 268 5699",
    "sg:postcode":"06468",
    "sg:province":"CT",
    "sg:tags":[
        "electrical",
        "contractor"
    ],
    "wof:name":"Quality Electrical Service LLC",
    "wof:placetype":"venue"
},
  "geometry": {"coordinates":[-73.18656300000001,41.356847],"type":"Point"}
}