{
  "type": "Feature",
  "properties": {
    "iso:country":"US",
    "sg:address":"71 Lee Ave",
    "sg:city":"Norwalk",
    "sg:classifiers":[
        {
            "category":"Professional",
            "type":"Services"
        }
    ],
    "sg:phone":"+1 203 299 1951",
    "sg:postcode":"06810",
    "sg:province":"CT",
    "sg:tags":[
        "establishment"
    ],
    "wof:name":"Steven Sidiropoulos Phd Family",
    "wof:placetype":"venue"
},
  "geometry": {"coordinates":[-73.470984,41.387573],"type":"Point"}
}