{
  "type": "Feature",
  "properties": {
    "addr:full":"63 Hitching Post Ln Milford CT 06460",
    "addr:housenumber":"63",
    "addr:postcode":"06460",
    "addr:street":"Hitching Post Ln",
    "iso:country":"US",
    "sg:address":"63 Hitching Post Ln",
    "sg:city":"Milford",
    "sg:classifiers":[
        {
            "category":"Professional",
            "type":"Services"
        },
        {
            "category":"Professional",
            "subcategory":"Management & Consulting",
            "type":"Services"
        }
    ],
    "sg:phone":"+1 203 874 7730",
    "sg:postcode":"06460",
    "sg:province":"CT",
    "wof:name":"Johnston Dunn & Co Inc",
    "wof:placetype":"venue"
},
  "geometry": {"coordinates":[-73.055227,41.229671],"type":"Point"}
}