{
  "type": "Feature",
  "properties": {
    "addr:full":"1 State St Hartford CT 06103",
    "addr:housenumber":"1",
    "addr:postcode":"06103",
    "addr:street":"State St",
    "iso:country":"US",
    "sg:address":"1 State St",
    "sg:city":"Hartford",
    "sg:classifiers":[
        {
            "category":"Professional",
            "subcategory":"Lawyer & Legal Services",
            "type":"Services"
        }
    ],
    "sg:phone":"+1   ",
    "sg:postcode":"06103",
    "sg:province":"CT",
    "wof:name":"Bernard E Jacques",
    "wof:placetype":"venue"
},
  "geometry": {"coordinates":[-72.671525,41.7658],"type":"Point"}
}