{
  "type": "Feature",
  "properties": {
    "addr:full":"48 Crestwood Rd Bethany CT 06524",
    "addr:housenumber":"48",
    "addr:postcode":"06524",
    "addr:street":"Crestwood Rd Bethany Ct",
    "iso:country":"US",
    "sg:address":"48 Crestwood Rd",
    "sg:city":"Bethany",
    "sg:classifiers":[
        {
            "category":"Real Estate",
            "subcategory":"Real Estate Agent",
            "type":"Services"
        }
    ],
    "sg:phone":"+1 203 393 2500",
    "sg:postcode":"06524",
    "sg:province":"CT",
    "wof:name":"Horizon Properties LLC",
    "wof:placetype":"venue"
},
  "geometry": {"coordinates":[-73.04174,41.412398],"type":"Point"}
}