{
  "type": "Feature",
  "properties": {
    "iso:country":"US",
    "sg:address":"100 Bridgeport Ave",
    "sg:city":"Milford",
    "sg:classifiers":[
        {
            "category":"Building & Trades",
            "subcategory":"Construction",
            "type":"Services"
        }
    ],
    "sg:phone":"+1 203 876 8331",
    "sg:postcode":"06460",
    "sg:province":"CT",
    "sg:tags":[
        "general",
        "contractor"
    ],
    "sg:website":"www.bismarkconstruction.com",
    "wof:name":"Bismark Construction Co",
    "wof:placetype":"venue"
},
  "geometry": {"coordinates":[-73.105566,41.2008],"type":"Point"}
}