{
  "type": "Feature",
  "properties": {
    "addr:full":"124 Old Battery Rd Bridgeport CT 06605",
    "addr:housenumber":"124",
    "addr:postcode":"06605",
    "addr:street":"Old Battery Rd",
    "iso:country":"US",
    "sg:address":"124 Old Battery Rd",
    "sg:city":"Bridgeport",
    "sg:classifiers":[
        {
            "category":"Real Estate",
            "subcategory":"Real Estate Agent",
            "type":"Services"
        }
    ],
    "sg:phone":"+1 203 368 2491",
    "sg:postcode":"06605",
    "sg:province":"CT",
    "wof:name":"Leeder Complex LLC",
    "wof:placetype":"venue"
},
  "geometry": {"coordinates":[-73.22774800000001,41.146227],"type":"Point"}
}