{
  "type": "Feature",
  "properties": {
    "addr:full":"50 Old Orchard Rd Fairfield CT 06413",
    "addr:housenumber":"50",
    "addr:postcode":"06413",
    "addr:street":"Old Orchard Rd",
    "iso:country":"US",
    "sg:address":"50 Old Orchard Rd",
    "sg:city":"Fairfield",
    "sg:classifiers":[
        {
            "category":"Professional",
            "subcategory":"Management & Consulting",
            "type":"Services"
        }
    ],
    "sg:phone":"+1   ",
    "sg:postcode":"06413",
    "sg:province":"CT",
    "sg:tags":[
        "consultant"
    ],
    "wof:name":"Operational Risk Advisors",
    "wof:placetype":"venue"
},
  "geometry": {"coordinates":[-72.567233,41.317462],"type":"Point"}
}