{
  "type": "Feature",
  "properties": {
    "iso:country":"US",
    "sg:address":"10 Otter Rock Rd",
    "sg:city":"Old Lyme",
    "sg:classifiers":[
        {
            "category":"Retail",
            "subcategory":"Self-service Laundry",
            "type":"Services"
        }
    ],
    "sg:phone":"+1   ",
    "sg:postcode":"06371",
    "sg:province":"CT",
    "sg:tags":[
        "coin"
    ],
    "wof:name":"Saybrook Polyclean Center",
    "wof:placetype":"venue"
},
  "geometry": {"coordinates":[-72.292052,41.291362],"type":"Point"}
}