{
  "type": "Feature",
  "properties": {
    "addr:full":"362 Durham Rd Madison CT 06443",
    "addr:housenumber":"362",
    "addr:postcode":"06443",
    "addr:street":"Durham Rd",
    "iso:country":"US",
    "sg:address":"362 Durham Rd",
    "sg:city":"Madison",
    "sg:classifiers":[
        {
            "category":"Professional",
            "type":"Services"
        }
    ],
    "sg:phone":"+1 203 245 1260",
    "sg:postcode":"06443",
    "sg:province":"CT",
    "sg:tags":[
        "establishment"
    ],
    "wof:name":"Kevin Callinan",
    "wof:placetype":"venue"
},
  "geometry": {"coordinates":[-72.604564,41.304775],"type":"Point"}
}