{
  "type": "Feature",
  "properties": {
    "iso:country":"US",
    "sg:address":"1000 Bridgeport Ave",
    "sg:city":"Shelton",
    "sg:classifiers":[
        {
            "category":"Autos & Motor Vehicles",
            "subcategory":"Automobile Sales",
            "type":"Retail Goods"
        },
        {
            "category":"Banks & Credit Unions",
            "subcategory":"Financial Services",
            "type":"Services"
        }
    ],
    "sg:phone":"+1 203 402 0753",
    "sg:postcode":"06484",
    "sg:province":"CT",
    "sg:tags":[
        "new",
        "financing",
        "car"
    ],
    "sg:website":"http://www.toyota.com",
    "wof:name":"Toyota Motor Sales",
    "wof:placetype":"venue"
},
  "geometry": {"coordinates":[-73.140995,41.259325],"type":"Point"}
}