{
  "type": "Feature",
  "properties": {
    "iso:country":"US",
    "sg:address":"392 Merrow Rd",
    "sg:city":"Tolland",
    "sg:classifiers":[
        {
            "category":"Social Services",
            "type":"Services"
        }
    ],
    "sg:phone":"+1   ",
    "sg:postcode":"06084",
    "sg:province":"CT",
    "wof:name":"Big Brothers & Big Sisters",
    "wof:placetype":"venue"
},
  "geometry": {"coordinates":[-72.346215,41.857355],"type":"Point"}
}