{
  "type": "Feature",
  "properties": {
    "iso:country":"US",
    "sg:address":"522 Heritage Rd",
    "sg:city":"Southbury",
    "sg:classifiers":[
        {
            "category":"Restaurant",
            "type":"Food & Drink"
        }
    ],
    "sg:phone":"+1 203 262 6264",
    "sg:postcode":"06488",
    "sg:province":"CT",
    "wof:name":"Shadrach's Revolutionary Tap",
    "wof:placetype":"venue"
},
  "geometry": {"coordinates":[-73.224745,41.488544],"type":"Point"}
}