{
  "type": "Feature",
  "properties": {
    "addr:full":"468 Old Orange Ave West Haven CT 06516",
    "addr:housenumber":"468",
    "addr:postcode":"06516",
    "addr:street":"Old Orange Ave",
    "iso:country":"US",
    "sg:address":"468 Old Orange Ave",
    "sg:city":"West Haven",
    "sg:classifiers":[
        {
            "category":"Manufacturing",
            "subcategory":"Rubber & Plastics",
            "type":"Manufacturing & Wholesale Goods"
        }
    ],
    "sg:phone":"+1 203 934 3451",
    "sg:postcode":"06516",
    "sg:province":"CT",
    "sg:tags":[
        "tire"
    ],
    "wof:name":"Tire Country Of West Haven",
    "wof:placetype":"venue"
},
  "geometry": {"coordinates":[-72.964568,41.291644],"type":"Point"}
}