{
  "type": "Feature",
  "properties": {
    "addr:full":"146 Hazard Ave Enfield CT 06082",
    "addr:housenumber":"146",
    "addr:postcode":"06082",
    "addr:street":"Hazard Ave",
    "iso:country":"US",
    "sg:address":"146 Hazard Ave",
    "sg:city":"Enfield",
    "sg:classifiers":[
        {
            "category":"Shopping",
            "type":"Retail Goods"
        }
    ],
    "sg:phone":"+1 860 763 3243",
    "sg:postcode":"06082",
    "sg:province":"CT",
    "sg:tags":[
        "merchandise"
    ],
    "wof:name":"Myles Kessler",
    "wof:placetype":"venue"
},
  "geometry": {"coordinates":[-72.569619,41.989251],"type":"Point"}
}