{
  "type": "Feature",
  "properties": {
    "iso:country":"US",
    "sg:address":"936 Silas Deane Hwy",
    "sg:city":"Wethersfield",
    "sg:classifiers":[
        {
            "category":"Professional",
            "subcategory":"Business Services",
            "type":"Services"
        }
    ],
    "sg:phone":"+1   ",
    "sg:postcode":"06109",
    "sg:province":"CT",
    "sg:tags":[
        "clothing"
    ],
    "wof:name":"Osborne/Jenks Productions Inc",
    "wof:placetype":"venue"
},
  "geometry": {"coordinates":[-72.65593800000001,41.691465],"type":"Point"}
}