{
  "type": "Feature",
  "properties": {
    "iso:country":"US",
    "sg:address":"198 College St",
    "sg:city":"New Haven",
    "sg:classifiers":[
        {
            "category":"Health Services",
            "subcategory":"Medical Lab",
            "type":"Services"
        }
    ],
    "sg:phone":"+1 203 401 0100",
    "sg:postcode":"06510",
    "sg:province":"CT",
    "sg:tags":[
        "laboratory"
    ],
    "wof:name":"Pfizer Inc",
    "wof:placetype":"venue"
},
  "geometry": {"coordinates":[-72.930105,41.30535],"type":"Point"}
}