{
  "type": "Feature",
  "properties": {
    "iso:country":"US",
    "sg:address":"16 Waterbury Rd",
    "sg:city":"Prospect",
    "sg:classifiers":[
        {
            "category":"Professional",
            "type":"Services"
        }
    ],
    "sg:phone":"+1 203 758 4882",
    "sg:postcode":"06712",
    "sg:province":"CT",
    "sg:tags":[
        "establishment"
    ],
    "sg:website":"www.jobshop.com",
    "wof:name":"JOBSHOP.COM",
    "wof:placetype":"venue"
},
  "geometry": {"coordinates":[-72.979682,41.504937],"type":"Point"}
}