{
  "type": "Feature",
  "properties": {
    "addr:full":"46 Matthew Rd Branford CT 06405",
    "addr:housenumber":"46",
    "addr:postcode":"06405",
    "addr:street":"Matthew Rd",
    "iso:country":"US",
    "sg:address":"46 Matthew Rd",
    "sg:city":"Branford",
    "sg:classifiers":[
        {
            "category":"Retail",
            "subcategory":"Laundry & Dry Cleaning",
            "type":"Services"
        }
    ],
    "sg:phone":"+1 203 481 0040",
    "sg:postcode":"06405",
    "sg:province":"CT",
    "sg:tags":[
        "cleaners",
        "rug",
        "carpet"
    ],
    "wof:name":"Dirtbuster",
    "wof:placetype":"venue"
},
  "geometry": {"coordinates":[-72.84149600000001,41.276252],"type":"Point"}
}