{
  "type": "Feature",
  "properties": {
    "iso:country":"US",
    "sg:address":"12 Dunbar Rd",
    "sg:city":"Milford",
    "sg:classifiers":[
        {
            "category":"Shopping",
            "subcategory":"Computers & Home Electronics",
            "type":"Retail Goods"
        }
    ],
    "sg:phone":"+1 203 783 9626",
    "sg:postcode":"06460",
    "sg:province":"CT",
    "wof:name":"Doctor PC of Milford",
    "wof:placetype":"venue"
},
  "geometry": {"coordinates":[-72.993094,41.228633],"type":"Point"}
}