{
  "type": "Feature",
  "properties": {
    "iso:country":"US",
    "sg:address":"2505 Main St",
    "sg:city":"Stratford",
    "sg:classifiers":[
        {
            "category":"Personal",
            "subcategory":"Beauty Salon",
            "type":"Services"
        }
    ],
    "sg:phone":"+1   ",
    "sg:postcode":"06615",
    "sg:province":"CT",
    "sg:tags":[
        "hair",
        "nail"
    ],
    "wof:name":"Metro Hair and Nail Center",
    "wof:placetype":"venue"
},
  "geometry": {"coordinates":[-73.132034,41.195741],"type":"Point"}
}