{
  "type": "Feature",
  "properties": {
    "addr:full":"18 E Franklin St Danbury CT 06810",
    "addr:housenumber":"18",
    "addr:postcode":"06810",
    "addr:street":"E Franklin St",
    "iso:country":"US",
    "sg:address":"18 E Franklin St",
    "sg:city":"Danbury",
    "sg:classifiers":[
        {
            "category":"Real Estate",
            "subcategory":"Real Estate Operator",
            "type":"Services"
        }
    ],
    "sg:phone":"+1 203 426 5394",
    "sg:postcode":"06810",
    "sg:province":"CT",
    "sg:tags":[
        "building",
        "nonresidential"
    ],
    "wof:name":"Davsco Properties LLC",
    "wof:placetype":"venue"
},
  "geometry": {"coordinates":[-73.45680299999999,41.400231],"type":"Point"}
}