{
  "type": "Feature",
  "properties": {
    "addr:full":"384 State Hwy 148 Killingworth CT 06419",
    "addr:housenumber":"384",
    "addr:postcode":"06419",
    "addr:street":"State Hwy 148",
    "iso:country":"US",
    "sg:address":"384 State Hwy 148",
    "sg:city":"Killingworth",
    "sg:classifiers":[
        {
            "category":"Professional",
            "subcategory":"Management & Consulting",
            "type":"Services"
        }
    ],
    "sg:phone":"+1   ",
    "sg:postcode":"06419",
    "sg:province":"CT",
    "wof:name":"Churchill Systems Corp",
    "wof:placetype":"venue"
},
  "geometry": {"coordinates":[-72.59407,41.385222],"type":"Point"}
}