{
  "type": "Feature",
  "properties": {
    "iso:country":"US",
    "sg:address":"670 Newfield St",
    "sg:city":"Middletown",
    "sg:classifiers":[
        {
            "category":"Health Services",
            "subcategory":"Health Practitioner",
            "type":"Services"
        }
    ],
    "sg:phone":"+1   ",
    "sg:postcode":"06457",
    "sg:province":"CT",
    "wof:name":"Hypnobuilding",
    "wof:placetype":"venue"
},
  "geometry": {"coordinates":[-72.67220500000001,41.577193],"type":"Point"}
}