{
  "type": "Feature",
  "properties": {
    "iso:country":"US",
    "sg:address":"38 Bonwit Rd",
    "sg:city":"Riverside",
    "sg:classifiers":[
        {
            "category":"Marine",
            "type":"Transportation"
        }
    ],
    "sg:phone":"+1 203 698 1689",
    "sg:postcode":"06878",
    "sg:province":"CT",
    "sg:tags":[
        "equipment",
        "supply"
    ],
    "wof:name":"Mianus Marine",
    "wof:placetype":"venue"
},
  "geometry": {"coordinates":[-73.578074,41.049875],"type":"Point"}
}