{
  "type": "Feature",
  "properties": {
    "iso:country":"US",
    "sg:address":"17 Water St",
    "sg:city":"Guilford",
    "sg:classifiers":[
        {
            "category":"Shopping",
            "subcategory":"Clothing, Apparel, & Fashions",
            "type":"Retail Goods"
        }
    ],
    "sg:phone":"+1 203 453 4932",
    "sg:postcode":"06437",
    "sg:province":"CT",
    "sg:tags":[
        "tailor"
    ],
    "wof:name":"Claudia-Village Seamstress",
    "wof:placetype":"venue"
},
  "geometry": {"coordinates":[-72.68305100000001,41.280813],"type":"Point"}
}