{
  "type": "Feature",
  "properties": {
    "iso:country":"US",
    "sg:address":"446 Silas Deane Hwy",
    "sg:city":"Wethersfield",
    "sg:classifiers":[
        {
            "category":"Retail",
            "subcategory":"Veterinary Services",
            "type":"Services"
        }
    ],
    "sg:phone":"+1 860 529 9420",
    "sg:postcode":"06109",
    "sg:province":"CT",
    "sg:tags":[
        "hospital"
    ],
    "wof:name":"Wethersfield Animal Hospital",
    "wof:placetype":"venue"
},
  "geometry": {"coordinates":[-72.66477500000001,41.715639],"type":"Point"}
}