{
  "type": "Feature",
  "properties": {
    "addr:full":"940 Broad St Bridgeport CT 06604",
    "addr:housenumber":"940",
    "addr:postcode":"06604",
    "addr:street":"Broad St",
    "iso:country":"US",
    "sg:address":"940 Broad St",
    "sg:city":"Bridgeport",
    "sg:classifiers":[
        {
            "category":"Shopping",
            "subcategory":"Books",
            "type":"Retail Goods"
        }
    ],
    "sg:phone":"+1 203 336 6911",
    "sg:postcode":"06604",
    "sg:province":"CT",
    "sg:tags":[
        "dealer"
    ],
    "wof:name":"Rainy Faye",
    "wof:placetype":"venue"
},
  "geometry": {"coordinates":[-73.189965,41.175845],"type":"Point"}
}