{
  "type": "Feature",
  "properties": {
    "iso:country":"US",
    "sg:address":"24 Timber Trl",
    "sg:city":"Manchester",
    "sg:classifiers":[
        {
            "category":"Wholesale",
            "subcategory":"Hardware",
            "type":"Manufacturing & Wholesale Goods"
        }
    ],
    "sg:phone":"+1 860 649 7992",
    "sg:postcode":"06040",
    "sg:province":"CT",
    "sg:tags":[
        "refrigeration",
        "equipment-parts",
        "supply"
    ],
    "wof:name":"Ross Sales Agency",
    "wof:placetype":"venue"
},
  "geometry": {"coordinates":[-72.495983,41.758435],"type":"Point"}
}