{
  "type": "Feature",
  "properties": {
    "iso:country":"US",
    "sg:address":"1299 Whalley Ave",
    "sg:city":"New Haven",
    "sg:classifiers":[
        {
            "category":"Manufacturing",
            "subcategory":"Printing",
            "type":"Manufacturing & Wholesale Goods"
        },
        {
            "category":"Shopping",
            "subcategory":"Computers & Home Electronics",
            "type":"Retail Goods"
        }
    ],
    "sg:phone":"+1 203 389 5009",
    "sg:postcode":"06515",
    "sg:province":"CT",
    "sg:tags":[
        "book",
        "publishing"
    ],
    "wof:name":"Praez Media LLC",
    "wof:placetype":"venue"
},
  "geometry": {"coordinates":[-72.973823,41.331764],"type":"Point"}
}