{
  "type": "Feature",
  "properties": {
    "addr:full":"555 Newfield Ave Stamford CT 06905",
    "addr:housenumber":"555",
    "addr:postcode":"06905",
    "addr:street":"Newfield Ave",
    "iso:country":"US",
    "sg:address":"555 Newfield Ave",
    "sg:city":"Stamford",
    "sg:classifiers":[
        {
            "category":"Health Services",
            "subcategory":"Doctor",
            "type":"Services"
        }
    ],
    "sg:phone":"+1   ",
    "sg:postcode":"06905",
    "sg:province":"CT",
    "sg:tags":[
        "dentist"
    ],
    "wof:name":"Alan Barr DDS",
    "wof:placetype":"venue"
},
  "geometry": {"coordinates":[-73.533812,41.078569],"type":"Point"}
}