{
  "type": "Feature",
  "properties": {
    "addr:full":"275 Riverside Ave Riverside CT 06878",
    "addr:housenumber":"275",
    "addr:postcode":"06878",
    "addr:street":"Riverside Ave Riverside Ct",
    "iso:country":"US",
    "sg:address":"275 Riverside Ave",
    "sg:city":"Riverside",
    "sg:classifiers":[
        {
            "category":"Shopping",
            "subcategory":"Stationery & Office Supplies",
            "type":"Retail Goods"
        }
    ],
    "sg:phone":"+1 203 637 2698",
    "sg:postcode":"06878",
    "sg:province":"CT",
    "wof:name":"Ergonomix",
    "wof:placetype":"venue"
},
  "geometry": {"coordinates":[-73.58002399999999,41.028957],"type":"Point"}
}