{
  "type": "Feature",
  "properties": {
    "iso:country":"US",
    "sg:address":"235 Meriden Rd",
    "sg:city":"Waterbury",
    "sg:classifiers":[
        {
            "category":"Shopping",
            "subcategory":"Used Merchandise",
            "type":"Retail Goods"
        }
    ],
    "sg:phone":"+1 203 596 9647",
    "sg:postcode":"06705",
    "sg:province":"CT",
    "sg:tags":[
        "new",
        "household",
        "furniture"
    ],
    "wof:name":"Val-U-Mart of Ct Inc",
    "wof:placetype":"venue"
},
  "geometry": {"coordinates":[-73.010722,41.550375],"type":"Point"}
}