{
  "type": "Feature",
  "properties": {
    "addr:full":"77 Brushy Hill Rd Newtown CT 06470",
    "addr:housenumber":"77",
    "addr:postcode":"06470",
    "addr:street":"Brushy Hill Rd",
    "iso:country":"US",
    "sg:address":"77 Brushy Hill Rd",
    "sg:city":"Newtown",
    "sg:classifiers":[
        {
            "category":"Building & Trades",
            "subcategory":"Construction",
            "type":"Services"
        }
    ],
    "sg:phone":"+1 203 426 3001",
    "sg:postcode":"06470",
    "sg:province":"CT",
    "sg:tags":[
        "contractor"
    ],
    "wof:name":"Gervais Bros Roofing Inc",
    "wof:placetype":"venue"
},
  "geometry": {"coordinates":[-73.304147,41.378803],"type":"Point"}
}