{
  "type": "Feature",
  "properties": {
    "iso:country":"US",
    "sg:address":"156 Daniel Rd",
    "sg:city":"Hamden",
    "sg:classifiers":[
        {
            "category":"Professional",
            "subcategory":"Business Services",
            "type":"Services"
        }
    ],
    "sg:phone":"+1   ",
    "sg:postcode":"06517",
    "sg:province":"CT",
    "wof:name":"Eastide Civic Assoc",
    "wof:placetype":"venue"
},
  "geometry": {"coordinates":[-72.894946,41.35477],"type":"Point"}
}