{
  "type": "Feature",
  "properties": {
    "addr:full":"241 Asylum St Hartford CT 06103",
    "addr:housenumber":"241",
    "addr:postcode":"06103",
    "addr:street":"Asylum St",
    "iso:country":"US",
    "sg:address":"241 Asylum St",
    "sg:city":"Hartford",
    "sg:classifiers":[
        {
            "category":"Professional",
            "subcategory":"Business Services",
            "type":"Services"
        }
    ],
    "sg:phone":"+1   ",
    "sg:postcode":"06103",
    "sg:province":"CT",
    "wof:name":"Odssey Records",
    "wof:placetype":"venue"
},
  "geometry": {"coordinates":[-72.677414,41.767276],"type":"Point"}
}