{
  "type": "Feature",
  "properties": {
    "iso:country":"US",
    "sg:address":"25 Gentile Pl",
    "sg:city":"Branford",
    "sg:classifiers":[
        {
            "category":"Social Services",
            "subcategory":"Child Care",
            "type":"Services"
        }
    ],
    "sg:phone":"+1   ",
    "sg:postcode":"06405",
    "sg:province":"CT",
    "sg:tags":[
        "day"
    ],
    "wof:name":"Totally Kids Child Care",
    "wof:placetype":"venue"
},
  "geometry": {"coordinates":[-72.84665800000001,41.282439],"type":"Point"}
}