{
  "type": "Feature",
  "properties": {
    "iso:country":"US",
    "sg:address":"69 High Ridge Rd",
    "sg:city":"Stamford",
    "sg:classifiers":[
        {
            "category":"Education",
            "subcategory":"Special Training",
            "type":"Public Place"
        }
    ],
    "sg:phone":"+1 203 323 1929",
    "sg:postcode":"06905",
    "sg:province":"CT",
    "sg:tags":[
        "tutoring"
    ],
    "sg:website":"http://tutoringclub.com/localinfo.asp?ClubNumber=2209",
    "wof:name":"Tutoring Club",
    "wof:placetype":"venue"
},
  "geometry": {"coordinates":[-73.548935,41.073606],"type":"Point"}
}