{
  "type": "Feature",
  "properties": {
    "addr:full":"36 Chapel St Bristol CT 06010",
    "addr:housenumber":"36",
    "addr:postcode":"06010",
    "addr:street":"Chapel St",
    "iso:country":"US",
    "sg:address":"36 Chapel St",
    "sg:city":"Bristol",
    "sg:classifiers":[
        {
            "category":"Shopping",
            "subcategory":"Bicycles & Sporting Goods",
            "type":"Retail Goods"
        }
    ],
    "sg:phone":"+1 860 589 1700",
    "sg:postcode":"06010",
    "sg:province":"CT",
    "sg:tags":[
        "ski",
        "accessory"
    ],
    "wof:name":"Ski Shop Mount Southington",
    "wof:placetype":"venue"
},
  "geometry": {"coordinates":[-72.978047,41.711917],"type":"Point"}
}