{
  "type": "Feature",
  "properties": {
    "addr:full":"51 Nashville Rd Exd Bethel CT 06801",
    "addr:housenumber":"51",
    "addr:postcode":"06801",
    "addr:street":"Nashville Rd Exd Bethel Ct",
    "iso:country":"US",
    "sg:address":"51 Nashville Rd Exd",
    "sg:city":"Bethel",
    "sg:classifiers":[
        {
            "category":"Professional",
            "subcategory":"Business Services",
            "type":"Services"
        }
    ],
    "sg:phone":"+1   ",
    "sg:postcode":"06801",
    "sg:province":"CT",
    "sg:tags":[
        "crane"
    ],
    "wof:name":"Healy Crane Service",
    "wof:placetype":"venue"
},
  "geometry": {"coordinates":[-73.400536,41.353898],"type":"Point"}
}