{
  "type": "Feature",
  "properties": {
    "addr:full":"192 Wakefield Cir East Hartford CT 06118",
    "addr:housenumber":"192",
    "addr:postcode":"06118",
    "addr:street":"Wakefield Cir East Hartford Ct",
    "iso:country":"US",
    "sg:address":"192 Wakefield Cir",
    "sg:city":"East Hartford",
    "sg:classifiers":[
        {
            "category":"Taxi",
            "type":"Transportation"
        }
    ],
    "sg:phone":"+1 860 666 6666",
    "sg:postcode":"06118",
    "sg:province":"CT",
    "sg:tags":[
        "taxicab"
    ],
    "wof:name":"Yellow Cab",
    "wof:placetype":"venue"
},
  "geometry": {"coordinates":[-72.605495,41.761221],"type":"Point"}
}