{
  "type": "Feature",
  "properties": {
    "addr:full":"14 Moore Ave East Hartford CT 06108",
    "addr:housenumber":"14",
    "addr:postcode":"06108",
    "addr:street":"Moore Ave East Hartford Ct",
    "iso:country":"US",
    "sg:address":"14 Moore Ave",
    "sg:city":"East Hartford",
    "sg:classifiers":[
        {
            "category":"Professional",
            "subcategory":"Business Services",
            "type":"Services"
        }
    ],
    "sg:phone":"+1   ",
    "sg:postcode":"06108",
    "sg:province":"CT",
    "wof:name":"Vietnamese Cmnty Connecticutt",
    "wof:placetype":"venue"
},
  "geometry": {"coordinates":[-72.616998,41.778618],"type":"Point"}
}