{
  "type": "Feature",
  "properties": {
    "addr:full":"11 Rte 39 S Sherman CT 06784",
    "addr:housenumber":"11",
    "addr:postcode":"06784",
    "addr:street":"Rte 39 S Sherman Ct",
    "iso:country":"US",
    "sg:address":"11 Rte 39 S",
    "sg:city":"Sherman",
    "sg:classifiers":[
        {
            "category":"Real Estate",
            "subcategory":"Real Estate Agent",
            "type":"Services"
        }
    ],
    "sg:phone":"+1 860 350 5478",
    "sg:postcode":"06784",
    "sg:province":"CT",
    "wof:name":"Waldmann RE & HM Svcs LLC",
    "wof:placetype":"venue"
},
  "geometry": {"coordinates":[-73.496393,41.567499],"type":"Point"}
}