{
  "type": "Feature",
  "properties": {
    "addr:full":"300 Russell St Middletown CT 06457",
    "addr:housenumber":"300",
    "addr:postcode":"06457",
    "addr:street":"Russell St",
    "iso:country":"US",
    "sg:address":"300 Russell St",
    "sg:city":"Middletown",
    "sg:classifiers":[
        {
            "category":"Shopping",
            "subcategory":"Shoes",
            "type":"Retail Goods"
        }
    ],
    "sg:phone":"+1 860 841 9288",
    "sg:postcode":"06457",
    "sg:province":"CT",
    "sg:tags":[
        "consulting",
        "footwear",
        "business"
    ],
    "wof:name":"David Wilson & Associates LLC",
    "wof:placetype":"venue"
},
  "geometry": {"coordinates":[-72.649754,41.541588],"type":"Point"}
}