{
  "type": "Feature",
  "properties": {
    "addr:full":"203 Westbourne Pkwy Hartford CT 06112",
    "addr:housenumber":"203",
    "addr:postcode":"06112",
    "addr:street":"Westbourne Pkwy;Ct",
    "iso:country":"US",
    "sg:address":"203 Westbourne Pkwy",
    "sg:city":"Hartford",
    "sg:classifiers":[
        {
            "category":"Building & Trades",
            "subcategory":"Plumbing",
            "type":"Services"
        }
    ],
    "sg:phone":"+1 860 246 0608",
    "sg:postcode":"06112",
    "sg:province":"CT",
    "sg:tags":[
        "air",
        "heating",
        "conditioning",
        "contractor"
    ],
    "wof:name":"Alstons Oil Brner Svc Repr LLC",
    "wof:placetype":"venue"
},
  "geometry": {"coordinates":[-72.696288,41.786987],"type":"Point"}
}