{
  "type": "Feature",
  "properties": {
    "iso:country":"US",
    "sg:address":"58 W Main St",
    "sg:city":"Plainville",
    "sg:classifiers":[
        {
            "category":"Manufacturing",
            "subcategory":"Electronics",
            "type":"Manufacturing & Wholesale Goods"
        }
    ],
    "sg:phone":"+1 860 793 8515",
    "sg:postcode":"06062",
    "sg:province":"CT",
    "sg:tags":[
        "manufacture",
        "equipment",
        "distributes",
        "telecommunication"
    ],
    "wof:name":"Conference Technology Group",
    "wof:placetype":"venue"
},
  "geometry": {"coordinates":[-72.86774,41.671176],"type":"Point"}
}