{
  "type": "Feature",
  "properties": {
    "addr:full":"124 Research Dr Milford CT 06460",
    "addr:housenumber":"124",
    "addr:postcode":"06460",
    "addr:street":"Research Dr",
    "iso:country":"US",
    "sg:address":"124 Research Dr",
    "sg:city":"Milford",
    "sg:classifiers":[
        {
            "category":"Professional",
            "subcategory":"Business Services",
            "type":"Services"
        }
    ],
    "sg:phone":"+1 203 878 4732",
    "sg:postcode":"06460",
    "sg:province":"CT",
    "sg:tags":[
        "interior",
        "consultant",
        "design",
        "decorator"
    ],
    "wof:name":"Designers' Studio",
    "wof:placetype":"venue"
},
  "geometry": {"coordinates":[-73.017494,41.237704],"type":"Point"}
}