{
  "type": "Feature",
  "properties": {
    "addr:full":"303 Monticello Dr Branford CT 06405",
    "addr:housenumber":"303",
    "addr:postcode":"06405",
    "addr:street":"Monticello Dr",
    "iso:country":"US",
    "sg:address":"303 Monticello Dr",
    "sg:city":"Branford",
    "sg:classifiers":[
        {
            "category":"Professional",
            "type":"Services"
        }
    ],
    "sg:phone":"+1   ",
    "sg:postcode":"06405",
    "sg:province":"CT",
    "wof:name":"East Coast Endoscopic Service",
    "wof:placetype":"venue"
},
  "geometry": {"coordinates":[-72.848265,41.276557],"type":"Point"}
}