{
  "type": "Feature",
  "properties": {
    "addr:full":"90 W Washington St Bristol CT 06010",
    "addr:housenumber":"90",
    "addr:postcode":"06010",
    "addr:street":"W Washington St",
    "iso:country":"US",
    "sg:address":"90 W Washington St",
    "sg:city":"Bristol",
    "sg:classifiers":[
        {
            "category":"Education",
            "subcategory":"School",
            "type":"Public Place"
        }
    ],
    "sg:phone":"+1   ",
    "sg:postcode":"06010",
    "sg:province":"CT",
    "wof:name":"Hubbell Elementary School",
    "wof:placetype":"venue"
},
  "geometry": {"coordinates":[-72.908852,41.677742],"type":"Point"}
}