{
  "type": "Feature",
  "properties": {
    "iso:country":"US",
    "sg:address":"59 Peach Hill Rd",
    "sg:city":"Darien",
    "sg:classifiers":[
        {
            "category":"Building & Trades",
            "subcategory":"Plumbing",
            "type":"Services"
        }
    ],
    "sg:phone":"+1 203 655 5436",
    "sg:postcode":"06820",
    "sg:province":"CT",
    "sg:tags":[
        "mfg",
        "i",
        "digital",
        "heating",
        "contractor",
        "ventilation",
        "vacuum"
    ],
    "wof:name":"Fairfield Industries Inc",
    "wof:placetype":"venue"
},
  "geometry": {"coordinates":[-73.47976800000001,41.093562],"type":"Point"}
}