{
  "type": "Feature",
  "properties": {
    "iso:country":"US",
    "sg:address":"83 Joseph St",
    "sg:city":"Waterbury",
    "sg:classifiers":[
        {
            "category":"Home & Garden",
            "subcategory":"Carpets & Floor Coverings",
            "type":"Retail Goods"
        }
    ],
    "sg:phone":"+1 203 597 1504",
    "sg:postcode":"06705",
    "sg:province":"CT",
    "sg:tags":[
        "dealer",
        "rug"
    ],
    "wof:name":"Waterbury Carpeting",
    "wof:placetype":"venue"
},
  "geometry": {"coordinates":[-73.000092,41.561153],"type":"Point"}
}