{
  "type": "Feature",
  "properties": {
    "iso:country":"US",
    "sg:address":"572 White Plains Rd",
    "sg:city":"Trumbull",
    "sg:classifiers":[
        {
            "category":"Professional",
            "subcategory":"Accounting & Tax Preparation",
            "type":"Services"
        }
    ],
    "sg:phone":"+1   ",
    "sg:postcode":"06611",
    "sg:province":"CT",
    "wof:name":"Danny A Pannese",
    "wof:placetype":"venue"
},
  "geometry": {"coordinates":[-73.186446,41.239051],"type":"Point"}
}