{
  "type": "Feature",
  "properties": {
    "addr:full":"187 Guinea Rd Monroe CT 06468",
    "addr:housenumber":"187",
    "addr:postcode":"06468",
    "addr:street":"Guinea Rd",
    "iso:country":"US",
    "sg:address":"187 Guinea Rd",
    "sg:city":"Monroe",
    "sg:classifiers":[
        {
            "category":"Building & Trades",
            "subcategory":"Construction",
            "type":"Services"
        }
    ],
    "sg:phone":"+1 203 452 7865",
    "sg:postcode":"06468",
    "sg:province":"CT",
    "sg:tags":[
        "roofing",
        "contractor"
    ],
    "wof:name":"R & R Siding & Roofing",
    "wof:placetype":"venue"
},
  "geometry": {"coordinates":[-73.27855599999999,41.342027],"type":"Point"}
}