{
  "type": "Feature",
  "properties": {
    "iso:country":"US",
    "sg:address":"219 W Rocks Rd",
    "sg:city":"Norwalk",
    "sg:classifiers":[
        {
            "category":"Building & Trades",
            "subcategory":"Construction",
            "type":"Services"
        }
    ],
    "sg:phone":"+1 203 846 9297",
    "sg:postcode":"06851",
    "sg:province":"CT",
    "sg:tags":[
        "painter"
    ],
    "wof:name":"Tavella Painting Co",
    "wof:placetype":"venue"
},
  "geometry": {"coordinates":[-73.42003699999999,41.151508],"type":"Point"}
}