{
  "type": "Feature",
  "properties": {
    "addr:full":"26 Patmar Cir Monroe CT 06468",
    "addr:housenumber":"26",
    "addr:postcode":"06468",
    "addr:street":"Patmar Cir Monroe Ct",
    "iso:country":"US",
    "sg:address":"26 Patmar Cir",
    "sg:city":"Monroe",
    "sg:classifiers":[
        {
            "category":"Manufacturing",
            "subcategory":"Tools & Machinery",
            "type":"Manufacturing & Wholesale Goods"
        }
    ],
    "sg:phone":"+1 203 452 7310",
    "sg:postcode":"06468",
    "sg:province":"CT",
    "sg:tags":[
        "shop"
    ],
    "wof:name":"Budrad Engineering Co LLC",
    "wof:placetype":"venue"
},
  "geometry": {"coordinates":[-73.266088,41.31028],"type":"Point"}
}