{
  "type": "Feature",
  "properties": {
    "iso:country":"US",
    "sg:address":"57 Pratt St",
    "sg:city":"Hartford",
    "sg:classifiers":[
        {
            "category":"Professional",
            "subcategory":"Computer Services",
            "type":"Services"
        }
    ],
    "sg:phone":"+1   ",
    "sg:postcode":"06103",
    "sg:province":"CT",
    "sg:tags":[
        "development",
        "transl",
        "software",
        "internet"
    ],
    "wof:name":"Alefbehcom",
    "wof:placetype":"venue"
},
  "geometry": {"coordinates":[-72.674559,41.767567],"type":"Point"}
}