{
  "type": "Feature",
  "properties": {
    "addr:full":"73 Pratt St Hartford CT 06103",
    "addr:housenumber":"73",
    "addr:postcode":"06103",
    "addr:street":"Pratt St",
    "iso:country":"US",
    "sg:address":"73 Pratt St",
    "sg:city":"Hartford",
    "sg:classifiers":[
        {
            "category":"Shopping",
            "subcategory":"Clothing, Apparel, & Fashions",
            "type":"Retail Goods"
        }
    ],
    "sg:phone":"+1 860 293 2091",
    "sg:postcode":"06103",
    "sg:province":"CT",
    "wof:name":"Hot Fashion",
    "wof:placetype":"venue"
},
  "geometry": {"coordinates":[-72.67431500000001,41.767527],"type":"Point"}
}