{
  "type": "Feature",
  "properties": {
    "iso:country":"US",
    "sg:address":"66 Oakwood Dr",
    "sg:city":"North Haven",
    "sg:classifiers":[
        {
            "category":"Wholesale",
            "subcategory":"Machinery & Supplies",
            "type":"Manufacturing & Wholesale Goods"
        }
    ],
    "sg:phone":"+1 203 234 7411",
    "sg:postcode":"06473",
    "sg:province":"CT",
    "sg:tags":[
        "equipment",
        "industrial"
    ],
    "wof:name":"Imageteck",
    "wof:placetype":"venue"
},
  "geometry": {"coordinates":[-72.84486,41.39536],"type":"Point"}
}