{
  "type": "Feature",
  "properties": {
    "iso:country":"US",
    "sg:address":"25 Madison St",
    "sg:city":"Manchester",
    "sg:classifiers":[
        {
            "category":"Organizations",
            "subcategory":"Religious Organization",
            "type":"Services"
        }
    ],
    "sg:phone":"+1   ",
    "sg:postcode":"06040",
    "sg:province":"CT",
    "wof:name":"New Horizon Baptist Church",
    "wof:placetype":"venue"
},
  "geometry": {"coordinates":[-72.519666,41.77617],"type":"Point"}
}