{
  "type": "Feature",
  "properties": {
    "addr:full":"6 Woodtick Rd Wolcott CT 06716",
    "addr:housenumber":"6",
    "addr:postcode":"06716",
    "addr:street":"Woodtick Rd Wolcott Ct",
    "iso:country":"US",
    "sg:address":"6 Woodtick Rd",
    "sg:city":"Wolcott",
    "sg:classifiers":[
        {
            "category":"Shopping",
            "subcategory":"Computers & Home Electronics",
            "type":"Retail Goods"
        }
    ],
    "sg:phone":"+1 203 879 3636",
    "sg:postcode":"06716",
    "sg:province":"CT",
    "wof:name":"Gagne Computers LLC",
    "wof:placetype":"venue"
},
  "geometry": {"coordinates":[-72.996077,41.569461],"type":"Point"}
}