{
  "type": "Feature",
  "properties": {
    "iso:country":"US",
    "sg:address":"85 Ridgewood Rd",
    "sg:city":"Wallingford",
    "sg:classifiers":[
        {
            "category":"Professional",
            "subcategory":"Computer Services",
            "type":"Services"
        }
    ],
    "sg:phone":"+1   ",
    "sg:postcode":"06492",
    "sg:province":"CT",
    "sg:tags":[
        "programming"
    ],
    "wof:name":"Intelsun LLC",
    "wof:placetype":"venue"
},
  "geometry": {"coordinates":[-72.84518,41.481936],"type":"Point"}
}