{
  "type": "Feature",
  "properties": {
    "addr:full":"16 Yarmouth Rd Norwalk CT 06853",
    "addr:housenumber":"16",
    "addr:postcode":"06853",
    "addr:street":"Yarmouth Rd",
    "iso:country":"US",
    "sg:address":"16 Yarmouth Rd",
    "sg:city":"Norwalk",
    "sg:classifiers":[
        {
            "category":"Banks & Credit Unions",
            "subcategory":"Financial Services",
            "type":"Services"
        }
    ],
    "sg:phone":"+1 203 656 1965",
    "sg:postcode":"06853",
    "sg:province":"CT",
    "sg:tags":[
        "fund",
        "private",
        "equity"
    ],
    "wof:name":"Logistic Value Stream Fund LLC",
    "wof:placetype":"venue"
},
  "geometry": {"coordinates":[-73.434724,41.058897],"type":"Point"}
}