{
  "type": "Feature",
  "properties": {
    "addr:full":"124 Thimble Islands Rd Branford CT 06405",
    "addr:housenumber":"124",
    "addr:postcode":"06405",
    "addr:street":"Thimble Islands Rd",
    "iso:country":"US",
    "sg:address":"124 Thimble Islands Rd",
    "sg:city":"Branford",
    "sg:classifiers":[
        {
            "category":"Shopping",
            "type":"Retail Goods"
        }
    ],
    "sg:phone":"+1 203 481 0119",
    "sg:postcode":"06405",
    "sg:province":"CT",
    "sg:tags":[
        "art",
        "gallery",
        "dealer"
    ],
    "wof:name":"John Casso Art Gallery",
    "wof:placetype":"venue"
},
  "geometry": {"coordinates":[-72.751966,41.269605],"type":"Point"}
}