{
  "type": "Feature",
  "properties": {
    "addr:full":"48 Lewis St Bristol CT 06010",
    "addr:housenumber":"48",
    "addr:postcode":"06010",
    "addr:street":"Lewis St",
    "iso:country":"US",
    "sg:address":"48 Lewis St",
    "sg:city":"Bristol",
    "sg:classifiers":[
        {
            "category":"Place Of Worship",
            "type":"Public Place"
        },
        {
            "category":"Education",
            "subcategory":"School",
            "type":"Public Place"
        }
    ],
    "sg:phone":"+1 860 589 6813",
    "sg:postcode":"06010",
    "sg:province":"CT",
    "sg:tags":[
        "interest",
        "religious",
        "private",
        "k-",
        "church"
    ],
    "wof:name":"Heritage Christian School",
    "wof:placetype":"venue"
},
  "geometry": {"coordinates":[-72.94066599999999,41.687199],"type":"Point"}
}