{
  "type": "Feature",
  "properties": {
    "addr:full":"8 South Rd Pleasant Valley CT 06063",
    "addr:housenumber":"8",
    "addr:postcode":"06063",
    "addr:street":"South Rd Pleasant Valley Ct",
    "iso:country":"US",
    "sg:address":"8 South Rd",
    "sg:city":"Pleasant Valley",
    "sg:classifiers":[
        {
            "category":"Professional",
            "subcategory":"Secretarial Services",
            "type":"Services"
        }
    ],
    "sg:phone":"+1   ",
    "sg:postcode":"06063",
    "sg:province":"CT",
    "sg:tags":[
        "reporting"
    ],
    "wof:name":"Last Word",
    "wof:placetype":"venue"
},
  "geometry": {"coordinates":[-72.90257200000001,41.942906],"type":"Point"}
}