{
  "type": "Feature",
  "properties": {
    "addr:full":"32 Pleasant Hill Rd Newtown CT 06470",
    "addr:housenumber":"32",
    "addr:postcode":"06470",
    "addr:street":"Pleasant Hill Rd",
    "iso:country":"US",
    "sg:address":"32 Pleasant Hill Rd",
    "sg:city":"Newtown",
    "sg:classifiers":[
        {
            "category":"Arena",
            "subcategory":"Sports Club",
            "type":"Entertainment"
        }
    ],
    "sg:phone":"+1   ",
    "sg:postcode":"06470",
    "sg:province":"CT",
    "wof:name":"Instructional Football Camp",
    "wof:placetype":"venue"
},
  "geometry": {"coordinates":[-73.354263,41.380699],"type":"Point"}
}