{
  "type": "Feature",
  "properties": {
    "addr:full":"30 Mill St Unionville CT 06085",
    "addr:housenumber":"30",
    "addr:postcode":"06085",
    "addr:street":"Mill St Unionville Ct",
    "iso:country":"US",
    "sg:address":"30 Mill St",
    "sg:city":"Unionville",
    "sg:classifiers":[
        {
            "category":"Insurance",
            "subcategory":"Insurance Agent",
            "type":"Services"
        }
    ],
    "sg:phone":"+1 860 675 4227",
    "sg:postcode":"06085",
    "sg:province":"CT",
    "sg:tags":[
        "agency"
    ],
    "wof:name":"ABS",
    "wof:placetype":"venue"
},
  "geometry": {"coordinates":[-72.88931100000001,41.757362],"type":"Point"}
}