{
  "type": "Feature",
  "properties": {
    "addr:full":"101 Bickford Exn Avon CT 06001",
    "addr:housenumber":"101",
    "addr:postcode":"06001",
    "addr:street":"Bickford Exn Avon Ct",
    "iso:country":"US",
    "sg:address":"101 Bickford Exn",
    "sg:city":"Avon",
    "sg:classifiers":[
        {
            "category":"Social Services",
            "subcategory":"Adult Care",
            "type":"Services"
        }
    ],
    "sg:phone":"+1   ",
    "sg:postcode":"06001",
    "sg:province":"CT",
    "sg:tags":[
        "residential"
    ],
    "wof:name":"Laurel Gardens",
    "wof:placetype":"venue"
},
  "geometry": {"coordinates":[-72.842214,41.812516],"type":"Point"}
}