{
  "type": "Feature",
  "properties": {
    "addr:full":"821 N Main St Exd Wallingford CT 06492",
    "addr:housenumber":"821",
    "addr:postcode":"06492",
    "addr:street":"N Main St Exd",
    "iso:country":"US",
    "sg:address":"821 N Main St Exd",
    "sg:city":"Wallingford",
    "sg:classifiers":[
        {
            "category":"Professional",
            "subcategory":"Engineering",
            "type":"Services"
        }
    ],
    "sg:phone":"+1 203 269 2993",
    "sg:postcode":"06492",
    "sg:province":"CT",
    "sg:tags":[
        "engineer"
    ],
    "wof:name":"United International Corp",
    "wof:placetype":"venue"
},
  "geometry": {"coordinates":[-72.808027,41.479327],"type":"Point"}
}