{
  "type": "Feature",
  "properties": {
    "iso:country":"US",
    "sg:address":"21 Capitol Ave",
    "sg:city":"Hartford",
    "sg:classifiers":[
        {
            "category":"Personal",
            "type":"Services"
        }
    ],
    "sg:phone":"+1   ",
    "sg:postcode":"06106",
    "sg:province":"CT",
    "wof:name":"Small Jobs LLC",
    "wof:placetype":"venue"
},
  "geometry": {"coordinates":[-72.675403,41.760784],"type":"Point"}
}