{
  "type": "Feature",
  "properties": {
    "iso:country":"US",
    "sg:address":"242 Newbury St",
    "sg:city":"Hartford",
    "sg:classifiers":[
        {
            "category":"Professional",
            "subcategory":"Advertising",
            "type":"Services"
        }
    ],
    "sg:phone":"+1   ",
    "sg:postcode":"06114",
    "sg:province":"CT",
    "sg:tags":[
        "agency"
    ],
    "wof:name":"Large & Page Communications",
    "wof:placetype":"venue"
},
  "geometry": {"coordinates":[-72.68959599999999,41.734013],"type":"Point"}
}