{
  "type": "Feature",
  "properties": {
    "addr:full":"135 Campville Hill Rd Harwinton CT 06791",
    "addr:housenumber":"135",
    "addr:postcode":"06791",
    "addr:street":"Campville Hill Rd Harwinton Ct",
    "iso:country":"US",
    "sg:address":"135 Campville Hill Rd",
    "sg:city":"Harwinton",
    "sg:classifiers":[
        {
            "category":"Professional",
            "type":"Services"
        }
    ],
    "sg:phone":"+1 860 485 9919",
    "sg:postcode":"06791",
    "sg:province":"CT",
    "wof:name":"Brent M Lafferty",
    "wof:placetype":"venue"
},
  "geometry": {"coordinates":[-73.098682,41.738476],"type":"Point"}
}