{
  "type": "Feature",
  "properties": {
    "iso:country":"US",
    "sg:address":"7 Riverside Ave",
    "sg:city":"Westport",
    "sg:classifiers":[
        {
            "category":"Food & Beverages",
            "subcategory":"Specialty",
            "type":"Retail Goods"
        }
    ],
    "sg:phone":"+1 203 226 5009",
    "sg:postcode":"06880",
    "sg:province":"CT",
    "sg:tags":[
        "gourmet",
        "shop"
    ],
    "wof:name":"Il Panino Gourmet Italian Deli",
    "wof:placetype":"venue"
},
  "geometry": {"coordinates":[-73.36390299999999,41.139425],"type":"Point"}
}