{
  "type": "Feature",
  "properties": {
    "addr:full":"11 Harness Dr Barkhamsted CT 06063",
    "addr:housenumber":"11",
    "addr:postcode":"06063",
    "addr:street":"Harness Dr",
    "iso:country":"US",
    "sg:address":"11 Harness Dr",
    "sg:city":"Barkhamsted",
    "sg:classifiers":[
        {
            "category":"Building & Trades",
            "subcategory":"Electrical",
            "type":"Services"
        }
    ],
    "sg:phone":"+1 860 379 1259",
    "sg:postcode":"06063",
    "sg:province":"CT",
    "sg:tags":[
        "electrician"
    ],
    "wof:name":"Thomas Maragnano",
    "wof:placetype":"venue"
},
  "geometry": {"coordinates":[-73.02269,41.932516],"type":"Point"}
}