{
  "type": "Feature",
  "properties": {
    "iso:country":"US",
    "sg:address":"200 Route 7 N",
    "sg:city":"Falls Village",
    "sg:classifiers":[
        {
            "category":"Food & Beverages",
            "subcategory":"Groceries & Convenience Stores",
            "type":"Retail Goods"
        }
    ],
    "sg:phone":"+1 860 824 8429",
    "sg:postcode":"06031",
    "sg:province":"CT",
    "wof:name":"Drake Petroleum Co",
    "wof:placetype":"venue"
},
  "geometry": {"coordinates":[-73.334187,41.96671],"type":"Point"}
}