{
  "type": "Feature",
  "properties": {
    "addr:full":"1188 Farmington Ave Bristol CT 06010",
    "addr:housenumber":"1188",
    "addr:postcode":"06010",
    "addr:street":"Farmington Ave Bristol Ct",
    "iso:country":"US",
    "sg:address":"1188 Farmington Ave",
    "sg:city":"Bristol",
    "sg:classifiers":[
        {
            "category":"Shopping",
            "subcategory":"Mobile Phones",
            "type":"Retail Goods"
        }
    ],
    "sg:phone":"+1 860 940 6569",
    "sg:postcode":"06010",
    "sg:province":"CT",
    "sg:website":"www.verizonwireless.com/b2c/inde...",
    "wof:name":"Verizon Wireless-Wireless Zone",
    "wof:placetype":"venue"
},
  "geometry": {"coordinates":[-72.90371399999999,41.697339],"type":"Point"}
}