{
  "type": "Feature",
  "properties": {
    "iso:country":"US",
    "sg:address":"136 New London Tpke",
    "sg:city":"Glastonbury",
    "sg:classifiers":[
        {
            "category":"Social Services",
            "type":"Services"
        }
    ],
    "sg:phone":"+1   ",
    "sg:postcode":"06033",
    "sg:province":"CT",
    "sg:tags":[
        "outpatient",
        "treatment"
    ],
    "wof:name":"Rushford Center Inc",
    "wof:placetype":"venue"
},
  "geometry": {"coordinates":[-72.60527399999999,41.711914],"type":"Point"}
}