{
  "type": "Feature",
  "properties": {
    "iso:country":"US",
    "sg:address":"2001 W Main St",
    "sg:city":"Stamford",
    "sg:classifiers":[
        {
            "category":"Insurance",
            "subcategory":"Insurance Agent",
            "type":"Services"
        }
    ],
    "sg:phone":"+1 203 973 2983",
    "sg:postcode":"06902",
    "sg:province":"CT",
    "wof:name":"Wright Insurance Agency LLC",
    "wof:placetype":"venue"
},
  "geometry": {"coordinates":[-73.563479,41.048911],"type":"Point"}
}