{
  "type": "Feature",
  "properties": {
    "addr:full":"6 Muller Industrial Park Norwalk CT 06851",
    "addr:housenumber":"6",
    "addr:postcode":"06851",
    "addr:street":"Muller Industrial Park",
    "iso:country":"US",
    "sg:address":"6 Muller Industrial Park",
    "sg:city":"Norwalk",
    "sg:classifiers":[
        {
            "category":"Home & Garden",
            "subcategory":"Building Materials",
            "type":"Retail Goods"
        }
    ],
    "sg:phone":"+1 203 846 3035",
    "sg:postcode":"06851",
    "sg:province":"CT",
    "sg:tags":[
        "glass",
        "window",
        "plate"
    ],
    "wof:name":"Architectural Glass Industries",
    "wof:placetype":"venue"
},
  "geometry": {"coordinates":[-73.426697,41.133178],"type":"Point"}
}