{
  "type": "Feature",
  "properties": {
    "iso:country":"US",
    "sg:address":"19 Andover Dr",
    "sg:city":"Hartford",
    "sg:classifiers":[
        {
            "category":"Wholesale",
            "subcategory":"Groceries",
            "type":"Manufacturing & Wholesale Goods"
        }
    ],
    "sg:phone":"+1 860 953 8408",
    "sg:postcode":"06110",
    "sg:province":"CT",
    "sg:tags":[
        "frozen",
        "packaged"
    ],
    "wof:name":"Horizon Foods of Hartford",
    "wof:placetype":"venue"
},
  "geometry": {"coordinates":[-72.71769999999999,41.738493],"type":"Point"}
}