{
  "type": "Feature",
  "properties": {
    "addr:full":"10 Maple Ave Beacon Falls CT 06403",
    "addr:housenumber":"10",
    "addr:postcode":"06403",
    "addr:street":"Maple Ave;Falls Ct",
    "iso:country":"US",
    "sg:address":"10 Maple Ave",
    "sg:city":"Beacon Falls",
    "sg:classifiers":[
        {
            "category":"Education",
            "subcategory":"Library",
            "type":"Public Place"
        }
    ],
    "sg:phone":"+1 203 729 1441",
    "sg:postcode":"06403",
    "sg:province":"CT",
    "sg:tags":[
        "executive"
    ],
    "wof:name":"Beacon Falls Public Library",
    "wof:placetype":"venue"
},
  "geometry": {"coordinates":[-73.060524,41.445401],"type":"Point"}
}