{
  "type": "Feature",
  "properties": {
    "addr:full":"502 Saw Mill Rd West Haven CT 06516",
    "addr:housenumber":"502",
    "addr:postcode":"06516",
    "addr:street":"Saw Mill Rd;Haven",
    "iso:country":"US",
    "sg:address":"502 Saw Mill Rd",
    "sg:city":"West Haven",
    "sg:classifiers":[
        {
            "category":"Restaurant",
            "type":"Food & Drink"
        }
    ],
    "sg:menulink":"http://www.allmenus.com/ct/west-haven/144202-subway/menu/",
    "sg:phone":"+1 203 931 9955",
    "sg:postcode":"06516",
    "sg:province":"CT",
    "sg:tags":[
        "american",
        "sandwich"
    ],
    "wof:name":"Subway",
    "wof:placetype":"venue"
},
  "geometry": {"coordinates":[-72.975472,41.26991],"type":"Point"}
}