{
  "type": "Feature",
  "properties": {
    "iso:country":"US",
    "sg:address":"110 Warner Rd",
    "sg:city":"North Haven",
    "sg:classifiers":[
        {
            "category":"Building & Trades",
            "subcategory":"Landscaping Services",
            "type":"Services"
        }
    ],
    "sg:phone":"+1 203 239 3950",
    "sg:postcode":"06473",
    "sg:province":"CT",
    "sg:tags":[
        "landscape",
        "contractor"
    ],
    "wof:name":"De Martino Landscaping",
    "wof:placetype":"venue"
},
  "geometry": {"coordinates":[-72.822586,41.36513],"type":"Point"}
}