{
  "type": "Feature",
  "properties": {
    "iso:country":"US",
    "sg:address":"52 Fawn Meadow Dr",
    "sg:city":"Trumbull",
    "sg:classifiers":[
        {
            "category":"Professional",
            "subcategory":"Engineering",
            "type":"Services"
        }
    ],
    "sg:phone":"+1   ",
    "sg:postcode":"06611",
    "sg:province":"CT",
    "wof:name":"Melvin Garelick",
    "wof:placetype":"venue"
},
  "geometry": {"coordinates":[-73.248305,41.278958],"type":"Point"}
}