{
  "type": "Feature",
  "properties": {
    "iso:country":"US",
    "sg:address":"250 Main St S",
    "sg:city":"Southbury",
    "sg:classifiers":[
        {
            "category":"Real Estate",
            "subcategory":"Real Estate Agent",
            "type":"Services"
        }
    ],
    "sg:phone":"+1 203 267 6254",
    "sg:postcode":"06488",
    "sg:province":"CT",
    "wof:name":"Country View Real Estate",
    "wof:placetype":"venue"
},
  "geometry": {"coordinates":[-73.219481,41.475255],"type":"Point"}
}