{
  "type": "Feature",
  "properties": {
    "addr:full":"12 Wintonbury Ave Bloomfield CT 06002",
    "addr:housenumber":"12",
    "addr:postcode":"06002",
    "addr:street":"Wintonbury Ave Bloomfield Ct",
    "iso:country":"US",
    "sg:address":"12 Wintonbury Ave",
    "sg:city":"Bloomfield",
    "sg:classifiers":[
        {
            "category":"Shopping",
            "subcategory":"Jewelry",
            "type":"Retail Goods"
        }
    ],
    "sg:phone":"+1 860 243 3454",
    "sg:postcode":"06002",
    "sg:province":"CT",
    "wof:name":"Ryan Jewelers",
    "wof:placetype":"venue"
},
  "geometry": {"coordinates":[-72.737196,41.831624],"type":"Point"}
}