{
  "type": "Feature",
  "properties": {
    "iso:country":"US",
    "sg:address":"2 Bittersweet Ln",
    "sg:city":"Avon",
    "sg:classifiers":[
        {
            "category":"Real Estate",
            "subcategory":"Real Estate Operator",
            "type":"Services"
        }
    ],
    "sg:phone":"+1 860 677 4020",
    "sg:postcode":"06073",
    "sg:province":"CT",
    "sg:tags":[
        "condominium"
    ],
    "wof:name":"Forest Mews At Avon",
    "wof:placetype":"venue"
},
  "geometry": {"coordinates":[-72.585731,41.660723],"type":"Point"}
}