{
  "type": "Feature",
  "properties": {
    "addr:full":"117 Boston Post Rd Waterford CT 06385",
    "addr:housenumber":"117",
    "addr:postcode":"06385",
    "addr:street":"Boston Post Rd",
    "iso:country":"US",
    "sg:address":"117 Boston Post Rd",
    "sg:city":"Waterford",
    "sg:classifiers":[
        {
            "category":"Shopping",
            "subcategory":"Discount & Variety Stores",
            "type":"Retail Goods"
        }
    ],
    "sg:phone":"+1 860 444 7908",
    "sg:postcode":"06385",
    "sg:province":"CT",
    "sg:tags":[
        "merchandise"
    ],
    "sg:website":"http://www.dollartree.com/",
    "wof:name":"Dollar Tree",
    "wof:placetype":"venue"
},
  "geometry": {"coordinates":[-72.12450200000001,41.342134],"type":"Point"}
}