{
  "type": "Feature",
  "properties": {
    "addr:full":"80 John St Greenwich CT 06831",
    "addr:housenumber":"80",
    "addr:postcode":"06831",
    "addr:street":"John St",
    "iso:country":"US",
    "sg:address":"80 John St",
    "sg:city":"Greenwich",
    "sg:classifiers":[
        {
            "category":"Real Estate",
            "subcategory":"Architect",
            "type":"Services"
        }
    ],
    "sg:phone":"+1 203 869 3782",
    "sg:postcode":"06831",
    "sg:province":"CT",
    "wof:name":"Dimitri Bulazel",
    "wof:placetype":"venue"
},
  "geometry": {"coordinates":[-73.68051,41.101275],"type":"Point"}
}