{
  "type": "Feature",
  "properties": {
    "addr:full":"339 Beaumont Hwy Lebanon CT 06249",
    "addr:housenumber":"339",
    "addr:postcode":"06249",
    "addr:street":"Beaumont Hwy Lebanon Ct",
    "iso:country":"US",
    "sg:address":"339 Beaumont Hwy",
    "sg:city":"Lebanon",
    "sg:classifiers":[
        {
            "category":"Professional",
            "subcategory":"Business Services",
            "type":"Services"
        }
    ],
    "sg:phone":"+1   ",
    "sg:postcode":"06249",
    "sg:province":"CT",
    "wof:name":"Laibrandt Family Partnership",
    "wof:placetype":"venue"
},
  "geometry": {"coordinates":[-72.237939,41.682466],"type":"Point"}
}