{
  "type": "Feature",
  "properties": {
    "iso:country":"US",
    "sg:address":"398 Butlertown Rd",
    "sg:city":"Oakdale",
    "sg:classifiers":[
        {
            "category":"Building & Trades",
            "subcategory":"Construction",
            "type":"Services"
        }
    ],
    "sg:phone":"+1 860 437 8788",
    "sg:postcode":"06370",
    "sg:province":"CT",
    "sg:tags":[
        "excavation",
        "residential",
        "commercial"
    ],
    "wof:name":"Lindo Construction",
    "wof:placetype":"venue"
},
  "geometry": {"coordinates":[-72.213525,41.423175],"type":"Point"}
}