{
  "type": "Feature",
  "properties": {
    "addr:full":"96 Shore Rd Old Lyme CT 06371",
    "addr:housenumber":"96",
    "addr:postcode":"06371",
    "addr:street":"Shore Rd",
    "iso:country":"US",
    "sg:address":"96 Shore Rd",
    "sg:city":"Old Lyme",
    "sg:classifiers":[
        {
            "category":"Farming",
            "subcategory":"Farm",
            "type":"Manufacturing & Wholesale Goods"
        }
    ],
    "sg:phone":"+1 860 434 3522",
    "sg:postcode":"06371",
    "sg:province":"CT",
    "sg:tags":[
        "crop",
        "general"
    ],
    "wof:name":"Ritter Farms LLC",
    "wof:placetype":"venue"
},
  "geometry": {"coordinates":[-72.31691499999999,41.295823],"type":"Point"}
}