{
  "type": "Feature",
  "properties": {
    "addr:full":"1622 Baldwin St Waterbury CT 06706",
    "addr:housenumber":"1622",
    "addr:postcode":"06706",
    "addr:street":"Baldwin St Waterbury Ct",
    "iso:country":"US",
    "sg:address":"1622 Baldwin St",
    "sg:city":"Waterbury",
    "sg:classifiers":[
        {
            "category":"Restaurant",
            "type":"Food & Drink"
        }
    ],
    "sg:phone":"+1 203 757 4370",
    "sg:postcode":"06706",
    "sg:province":"CT",
    "sg:tags":[
        "eating"
    ],
    "wof:name":"Adriannas Apizza",
    "wof:placetype":"venue"
},
  "geometry": {"coordinates":[-73.036615,41.531087],"type":"Point"}
}