{
  "type": "Feature",
  "properties": {
    "addr:full":"441 Quinebaug Rd North Grosvenordale CT 06255",
    "addr:housenumber":"441",
    "addr:postcode":"06255",
    "addr:street":"Quinebaug Rd;Grosvenordale",
    "iso:country":"US",
    "sg:address":"441 Quinebaug Rd",
    "sg:city":"North Grosvenordale",
    "sg:phone":"+1 860 923 2710",
    "sg:postcode":"06255",
    "sg:province":"CT",
    "sg:tags":[
        "farm"
    ],
    "wof:name":"Blackmer Farm",
    "wof:placetype":"venue"
},
  "geometry": {"coordinates":[-71.923427,42.010362],"type":"Point"}
}