{
  "type": "Feature",
  "properties": {
    "iso:country":"US",
    "sg:address":"26 Felicia Dr",
    "sg:city":"New Haven",
    "sg:classifiers":[
        {
            "category":"Building & Trades",
            "subcategory":"Landscaping Services",
            "type":"Services"
        }
    ],
    "sg:phone":"+1 203 314 2797",
    "sg:postcode":"06513",
    "sg:province":"CT",
    "wof:name":"General Contracting LLC",
    "wof:placetype":"venue"
},
  "geometry": {"coordinates":[-72.853216,41.336259],"type":"Point"}
}