{
  "type": "Feature",
  "properties": {
    "addr:full":"37 Haddam Neck Rd East Hampton CT 06424",
    "addr:housenumber":"37",
    "addr:postcode":"06424",
    "addr:street":"Haddam Neck Rd East Hampton Ct",
    "iso:country":"US",
    "sg:address":"37 Haddam Neck Rd",
    "sg:city":"East Hampton",
    "sg:classifiers":[
        {
            "category":"Professional",
            "type":"Services"
        }
    ],
    "sg:phone":"+1 860 267 9681",
    "sg:postcode":"06424",
    "sg:province":"CT",
    "wof:name":"Raymond Mulligan",
    "wof:placetype":"venue"
},
  "geometry": {"coordinates":[-72.518936,41.520221],"type":"Point"}
}