{
  "type": "Feature",
  "properties": {
    "iso:country":"US",
    "sg:address":"141 Washington St",
    "sg:city":"Hartford",
    "sg:classifiers":[
        {
            "category":"Organizations",
            "subcategory":"Religious Organization",
            "type":"Services"
        }
    ],
    "sg:phone":"+1   ",
    "sg:postcode":"06106",
    "sg:province":"CT",
    "wof:name":"Cruz Otilia",
    "wof:placetype":"venue"
},
  "geometry": {"coordinates":[-72.68198599999999,41.761123],"type":"Point"}
}