{
  "type": "Feature",
  "properties": {
    "addr:full":"44 Old E Haddam Rd East Haddam CT 06423",
    "addr:housenumber":"44",
    "addr:postcode":"06423",
    "addr:street":"Old E Haddam Rd East Haddam Ct",
    "iso:country":"US",
    "sg:address":"44 Old E Haddam Rd",
    "sg:city":"East Haddam",
    "sg:classifiers":[
        {
            "category":"Retail",
            "subcategory":"Animal Services",
            "type":"Services"
        }
    ],
    "sg:phone":"+1 860 873 2572",
    "sg:postcode":"06423",
    "sg:province":"CT",
    "sg:tags":[
        "specialty"
    ],
    "wof:name":"Mar-Bo Kennels",
    "wof:placetype":"venue"
},
  "geometry": {"coordinates":[-72.46389000000001,41.461337],"type":"Point"}
}