{
  "type": "Feature",
  "properties": {
    "addr:full":"170 S Hoop Pole Rd Guilford CT 06437",
    "addr:housenumber":"170",
    "addr:postcode":"06437",
    "addr:street":"S Hoop Pole Rd",
    "iso:country":"US",
    "sg:address":"170 S Hoop Pole Rd",
    "sg:city":"Guilford",
    "sg:classifiers":[
        {
            "category":"Professional",
            "subcategory":"Business Services",
            "type":"Services"
        }
    ],
    "sg:phone":"+1   ",
    "sg:postcode":"06437",
    "sg:province":"CT",
    "wof:name":"Sullivan Fusco & Assoc LLC",
    "wof:placetype":"venue"
},
  "geometry": {"coordinates":[-72.702854,41.341374],"type":"Point"}
}