{
  "type": "Feature",
  "properties": {
    "addr:full":"115 Woodstock Ave Putnam CT 06260",
    "addr:housenumber":"115",
    "addr:postcode":"06260",
    "addr:street":"Woodstock Ave Putnam Ct",
    "iso:country":"US",
    "sg:address":"115 Woodstock Ave",
    "sg:city":"Putnam",
    "sg:classifiers":[
        {
            "category":"Health Services",
            "subcategory":"Hospital",
            "type":"Services"
        }
    ],
    "sg:phone":"+1   ",
    "sg:postcode":"06260",
    "sg:province":"CT",
    "sg:tags":[
        "specialty"
    ],
    "wof:name":"Ralph & Rita Mayotte",
    "wof:placetype":"venue"
},
  "geometry": {"coordinates":[-71.91436299999999,41.922961],"type":"Point"}
}