{
  "type": "Feature",
  "properties": {
    "iso:country":"US",
    "sg:address":"2264 Silas Deane Hwy",
    "sg:city":"Rocky Hill",
    "sg:classifiers":[
        {
            "category":"Social Services",
            "type":"Services"
        }
    ],
    "sg:phone":"+1   ",
    "sg:postcode":"06067",
    "sg:province":"CT",
    "wof:name":"Churchco",
    "wof:placetype":"venue"
},
  "geometry": {"coordinates":[-72.63987299999999,41.665839],"type":"Point"}
}