{
  "type": "Feature",
  "properties": {
    "addr:full":"71 East Ave Bridgeport CT 06610",
    "addr:housenumber":"71",
    "addr:postcode":"06610",
    "addr:street":"East Ave",
    "iso:country":"US",
    "sg:address":"71 East Ave",
    "sg:city":"Bridgeport",
    "sg:classifiers":[
        {
            "category":"Bus Charters",
            "type":"Transportation"
        }
    ],
    "sg:phone":"+1 203 336 3600",
    "sg:postcode":"06610",
    "sg:province":"CT",
    "wof:name":"Show Bus Tours",
    "wof:placetype":"venue"
},
  "geometry": {"coordinates":[-73.158106,41.18866],"type":"Point"}
}