{
  "type": "Feature",
  "properties": {
    "addr:full":"95 Storrs Rd Willimantic CT 06226",
    "addr:housenumber":"95",
    "addr:postcode":"06226",
    "addr:street":"Storrs Rd",
    "iso:country":"US",
    "sg:address":"95 Storrs Rd",
    "sg:city":"Willimantic",
    "sg:classifiers":[
        {
            "category":"Cinema",
            "subcategory":"Movie Rental",
            "type":"Entertainment"
        }
    ],
    "sg:phone":"+1 860 423 3117",
    "sg:postcode":"06226",
    "sg:province":"CT",
    "sg:tags":[
        "game",
        "video"
    ],
    "sg:website":"www.gamestop.com",
    "wof:name":"Gamestop",
    "wof:placetype":"venue"
},
  "geometry": {"coordinates":[-72.201527,41.728751],"type":"Point"}
}