{
  "type": "Feature",
  "properties": {
    "iso:country":"US",
    "sg:address":"15 River Rd",
    "sg:city":"Wilton",
    "sg:classifiers":[
        {
            "category":"Insurance",
            "subcategory":"Health Insurance",
            "type":"Services"
        },
        {
            "category":"Professional",
            "subcategory":"Computer Services",
            "type":"Services"
        }
    ],
    "sg:phone":"+1 203 762 0993",
    "sg:postcode":"06897",
    "sg:province":"CT",
    "sg:tags":[
        "software",
        "plan",
        "developer"
    ],
    "wof:name":"Caresys",
    "wof:placetype":"venue"
},
  "geometry": {"coordinates":[-73.430449,41.18976],"type":"Point"}
}