{
  "type": "Feature",
  "properties": {
    "addr:full":"100 Heights Rd Darien CT 06820",
    "addr:housenumber":"100",
    "addr:postcode":"06820",
    "addr:street":"Heights Rd",
    "iso:country":"US",
    "sg:address":"100 Heights Rd",
    "sg:city":"Darien",
    "sg:classifiers":[
        {
            "category":"Professional",
            "subcategory":"Management & Consulting",
            "type":"Services"
        }
    ],
    "sg:phone":"+1 203 655 3256",
    "sg:postcode":"06820",
    "sg:province":"CT",
    "sg:tags":[
        "marketing",
        "consultant"
    ],
    "wof:name":"Nelson Marketing Group Inc",
    "wof:placetype":"venue"
},
  "geometry": {"coordinates":[-73.498924,41.069511],"type":"Point"}
}