{
  "type": "Feature",
  "properties": {
    "iso:country":"US",
    "sg:address":"10 Selden Ln",
    "sg:city":"Greenwich",
    "sg:classifiers":[
        {
            "category":"Professional",
            "subcategory":"Business Services",
            "type":"Services"
        }
    ],
    "sg:phone":"+1 203 869 4949",
    "sg:postcode":"06831",
    "sg:province":"NY",
    "sg:tags":[
        "interior",
        "consultant",
        "design",
        "decorator"
    ],
    "wof:name":"W D Interiors",
    "wof:placetype":"venue"
},
  "geometry": {"coordinates":[-73.692087,41.078957],"type":"Point"}
}