{
  "type": "Feature",
  "properties": {
    "addr:full":"305 Windsor St South Windsor CT 06074",
    "addr:housenumber":"305",
    "addr:postcode":"06074",
    "addr:street":"Windsor St",
    "iso:country":"US",
    "sg:address":"305 Windsor St",
    "sg:city":"South Windsor",
    "sg:classifiers":[
        {
            "category":"Building & Trades",
            "subcategory":"Landscaping Services",
            "type":"Services"
        }
    ],
    "sg:phone":"+1 860 647 7553",
    "sg:postcode":"06074",
    "sg:province":"CT",
    "sg:tags":[
        "tree"
    ],
    "wof:name":"Hawkes Tree Service",
    "wof:placetype":"venue"
},
  "geometry": {"coordinates":[-72.56398299999999,41.803285],"type":"Point"}
}