{
  "type": "Feature",
  "properties": {
    "addr:full":"37 Manners Ave Willimantic CT 06226",
    "addr:housenumber":"37",
    "addr:postcode":"06226",
    "addr:street":"Manners Ave",
    "iso:country":"US",
    "sg:address":"37 Manners Ave",
    "sg:city":"Willimantic",
    "sg:classifiers":[
        {
            "category":"Personal",
            "subcategory":"Beauty Salon",
            "type":"Services"
        }
    ],
    "sg:phone":"+1   ",
    "sg:postcode":"06226",
    "sg:province":"CT",
    "sg:tags":[
        "shop"
    ],
    "wof:name":"Nancys Hair Salon",
    "wof:placetype":"venue"
},
  "geometry": {"coordinates":[-72.203208,41.707889],"type":"Point"}
}