{
  "type": "Feature",
  "properties": {
    "iso:country":"US",
    "sg:address":"185 Greens Farms Rd",
    "sg:city":"Westport",
    "sg:classifiers":[
        {
            "category":"Building & Trades",
            "subcategory":"Construction",
            "type":"Services"
        }
    ],
    "sg:phone":"+1 203 227 8618",
    "sg:postcode":"06880",
    "sg:province":"CT",
    "sg:tags":[
        "home",
        "improvement"
    ],
    "wof:name":"Basement De-Watering Systems",
    "wof:placetype":"venue"
},
  "geometry": {"coordinates":[-73.332021,41.126947],"type":"Point"}
}