{
  "type": "Feature",
  "properties": {
    "addr:full":"25 Bank St Stamford CT 06901",
    "addr:housenumber":"25",
    "addr:postcode":"06901",
    "addr:street":"Bank St",
    "iso:country":"US",
    "sg:address":"25 Bank St",
    "sg:city":"Stamford",
    "sg:classifiers":[
        {
            "category":"Restaurant",
            "type":"Food & Drink"
        }
    ],
    "sg:menulink":"http://www.allmenus.com/ct/stamford/260639-duo---euro-japanese/menu/",
    "sg:phone":"+1 203 252 2233",
    "sg:postcode":"06901",
    "sg:province":"CT",
    "sg:tags":[
        "new",
        "american",
        "asian",
        "japanese"
    ],
    "wof:name":"Duo - Euro Japanese",
    "wof:placetype":"venue"
},
  "geometry": {"coordinates":[-73.540499,41.0529],"type":"Point"}
}