{
  "type": "Feature",
  "properties": {
    "addr:full":"61 Plants Dam Rd East Lyme CT 06333",
    "addr:housenumber":"61",
    "addr:postcode":"06333",
    "addr:street":"Plants Dam Rd East Lyme Ct",
    "iso:country":"US",
    "sg:address":"61 Plants Dam Rd",
    "sg:city":"East Lyme",
    "sg:classifiers":[
        {
            "category":"Farming",
            "subcategory":"Farm & Veterinary Services",
            "type":"Manufacturing & Wholesale Goods"
        }
    ],
    "sg:phone":"+1 860 739 6691",
    "sg:postcode":"06333",
    "sg:province":"CT",
    "sg:tags":[
        "tank",
        "soil",
        "testing",
        "removal",
        "environmental",
        "con"
    ],
    "wof:name":"Soil & Environmental Services",
    "wof:placetype":"venue"
},
  "geometry": {"coordinates":[-72.258253,41.34402],"type":"Point"}
}