{
  "type": "Feature",
  "properties": {
    "addr:full":"149 Lake Ave Trumbull CT 06611",
    "addr:housenumber":"149",
    "addr:postcode":"06611",
    "addr:street":"Lake Ave",
    "iso:country":"US",
    "sg:address":"149 Lake Ave",
    "sg:city":"Trumbull",
    "sg:classifiers":[
        {
            "category":"Professional",
            "subcategory":"Accounting & Tax Preparation",
            "type":"Services"
        }
    ],
    "sg:phone":"+1   ",
    "sg:postcode":"06611",
    "sg:province":"CT",
    "wof:name":"William Gargano",
    "wof:placetype":"venue"
},
  "geometry": {"coordinates":[-73.23535699999999,41.261071],"type":"Point"}
}