{
  "type": "Feature",
  "properties": {
    "addr:full":"407 Kent Rd New Milford CT 06776",
    "addr:housenumber":"407",
    "addr:postcode":"06776",
    "addr:street":"Kent Rd",
    "iso:country":"US",
    "sg:address":"407 Kent Rd",
    "sg:city":"New Milford",
    "sg:classifiers":[
        {
            "category":"Shopping",
            "subcategory":"Used Merchandise",
            "type":"Retail Goods"
        }
    ],
    "sg:phone":"+1 860 354 8083",
    "sg:postcode":"06776",
    "sg:province":"CT",
    "wof:name":"Bills Garage Inc",
    "wof:placetype":"venue"
},
  "geometry": {"coordinates":[-73.457168,41.599524],"type":"Point"}
}