{
  "type": "Feature",
  "properties": {
    "addr:full":"219 Bridgeport Ave Shelton CT 06484",
    "addr:housenumber":"219",
    "addr:postcode":"06484",
    "addr:street":"Bridgeport Ave",
    "iso:country":"US",
    "sg:address":"219 Bridgeport Ave",
    "sg:city":"Shelton",
    "sg:classifiers":[
        {
            "category":"Retail",
            "subcategory":"Auto Repair",
            "type":"Services"
        }
    ],
    "sg:phone":"+1   ",
    "sg:postcode":"06484",
    "sg:province":"CT",
    "sg:tags":[
        "automotive"
    ],
    "wof:name":"Shelton Radiator",
    "wof:placetype":"venue"
},
  "geometry": {"coordinates":[-73.098664,41.308898],"type":"Point"}
}