{
  "type": "Feature",
  "properties": {
    "iso:country":"US",
    "sg:address":"742 Maple Ave",
    "sg:city":"Hartford",
    "sg:classifiers":[
        {
            "category":"Food & Beverages",
            "subcategory":"Groceries & Convenience Stores",
            "type":"Retail Goods"
        }
    ],
    "sg:phone":"+1 860 547 0625",
    "sg:postcode":"06114",
    "sg:province":"CT",
    "wof:name":"Martinez Mini Market",
    "wof:placetype":"venue"
},
  "geometry": {"coordinates":[-72.684471,41.739488],"type":"Point"}
}