{
  "type": "Feature",
  "properties": {
    "iso:country":"US",
    "sg:address":"9 Evergreen Ter",
    "sg:city":"Seymour",
    "sg:classifiers":[
        {
            "category":"Professional",
            "subcategory":"Engineering",
            "type":"Services"
        }
    ],
    "sg:phone":"+1   ",
    "sg:postcode":"06483",
    "sg:province":"CT",
    "sg:tags":[
        "consulting",
        "design"
    ],
    "wof:name":"Hardware Sftwr Solutions LLC",
    "wof:placetype":"venue"
},
  "geometry": {"coordinates":[-73.056821,41.414703],"type":"Point"}
}