{
  "type": "Feature",
  "properties": {
    "iso:country":"US",
    "sg:address":"120 Wayland Ave",
    "sg:city":"Waterbury",
    "sg:classifiers":[
        {
            "category":"Building & Trades",
            "subcategory":"Construction",
            "type":"Services"
        }
    ],
    "sg:phone":"+1 203 756 9300",
    "sg:postcode":"06708",
    "sg:province":"CT",
    "sg:tags":[
        "repairing",
        "remodeling",
        "contractor"
    ],
    "wof:name":"Pride Remodeling",
    "wof:placetype":"venue"
},
  "geometry": {"coordinates":[-73.06971799999999,41.56788],"type":"Point"}
}