{
  "type": "Feature",
  "properties": {
    "addr:full":"27 Bayberry Ln Westport CT 06880",
    "addr:housenumber":"27",
    "addr:postcode":"06880",
    "addr:street":"Bayberry Ln",
    "iso:country":"US",
    "sg:address":"27 Bayberry Ln",
    "sg:city":"Westport",
    "sg:classifiers":[
        {
            "category":"Professional",
            "subcategory":"Business Services",
            "type":"Services"
        }
    ],
    "sg:phone":"+1   ",
    "sg:postcode":"06880",
    "sg:province":"CT",
    "wof:name":"Interior Concepts",
    "wof:placetype":"venue"
},
  "geometry": {"coordinates":[-73.31605999999999,41.150671],"type":"Point"}
}