{
  "type": "Feature",
  "properties": {
    "iso:country":"US",
    "sg:address":"18 Church St",
    "sg:city":"North Haven",
    "sg:classifiers":[
        {
            "category":"Government",
            "subcategory":"Office",
            "type":"Public Place"
        }
    ],
    "sg:phone":"+1 203 239 5321",
    "sg:postcode":"06473",
    "sg:province":"CT",
    "sg:tags":[
        "village"
    ],
    "wof:name":"North Haven Personnel Dept",
    "wof:placetype":"venue"
},
  "geometry": {"coordinates":[-72.861188,41.387758],"type":"Point"}
}