{
  "type": "Feature",
  "properties": {
    "addr:full":"11 Cottage St Meriden CT 06450",
    "addr:housenumber":"11",
    "addr:postcode":"06450",
    "addr:street":"Cottage St",
    "iso:country":"US",
    "sg:address":"11 Cottage St",
    "sg:city":"Meriden",
    "sg:classifiers":[
        {
            "category":"Shopping",
            "subcategory":"Computers & Home Electronics",
            "type":"Retail Goods"
        }
    ],
    "sg:phone":"+1 203 440 3574",
    "sg:postcode":"06450",
    "sg:province":"CT",
    "sg:tags":[
        "equipment",
        "satellite",
        "system"
    ],
    "wof:name":"Siscom Satellite Inc",
    "wof:placetype":"venue"
},
  "geometry": {"coordinates":[-72.786901,41.534504],"type":"Point"}
}