{
  "type": "Feature",
  "properties": {
    "addr:full":"311 N Granby Rd North Granby CT 06060",
    "addr:housenumber":"311",
    "addr:postcode":"06060",
    "addr:street":"N Granby Rd North Granby Ct",
    "iso:country":"US",
    "sg:address":"311 N Granby Rd",
    "sg:city":"North Granby",
    "sg:classifiers":[
        {
            "category":"Recreation",
            "type":"Entertainment"
        }
    ],
    "sg:phone":"+1   ",
    "sg:postcode":"06060",
    "sg:province":"CT",
    "wof:name":"High Meadow Day Camp",
    "wof:placetype":"venue"
},
  "geometry": {"coordinates":[-72.821906,41.984583],"type":"Point"}
}