{
  "type": "Feature",
  "properties": {
    "iso:country":"US",
    "sg:address":"106 River Rd",
    "sg:city":"East Haddam",
    "sg:classifiers":[
        {
            "category":"Education",
            "subcategory":"School",
            "type":"Public Place"
        }
    ],
    "sg:phone":"+1   ",
    "sg:postcode":"06423",
    "sg:province":"CT",
    "wof:name":"Franklin Academy Inc",
    "wof:placetype":"venue"
},
  "geometry": {"coordinates":[-72.43480599999999,41.440317],"type":"Point"}
}