{
  "type": "Feature",
  "properties": {
    "addr:full":"12 Birch Trl Danbury CT 06811",
    "addr:housenumber":"12",
    "addr:postcode":"06811",
    "addr:street":"Birch Trl",
    "iso:country":"US",
    "sg:address":"12 Birch Trl",
    "sg:city":"Danbury",
    "sg:classifiers":[
        {
            "category":"Building & Trades",
            "subcategory":"Construction",
            "type":"Services"
        }
    ],
    "sg:phone":"+1 203 746 6683",
    "sg:postcode":"06811",
    "sg:province":"CT",
    "sg:tags":[
        "repairing",
        "remodeling",
        "contractor"
    ],
    "wof:name":"Perfection In The Making Inc",
    "wof:placetype":"venue"
},
  "geometry": {"coordinates":[-73.46807699999999,41.45394],"type":"Point"}
}