{
  "type": "Feature",
  "properties": {
    "addr:full":"19 New Haven Rd Seymour CT 06483",
    "addr:housenumber":"19",
    "addr:postcode":"06483",
    "addr:street":"New Haven Rd",
    "iso:country":"US",
    "sg:address":"19 New Haven Rd",
    "sg:city":"Seymour",
    "sg:classifiers":[
        {
            "category":"Insurance",
            "subcategory":"Insurance Agent",
            "type":"Services"
        }
    ],
    "sg:phone":"+1 203 888 2509",
    "sg:postcode":"06483",
    "sg:province":"CT",
    "wof:name":"John H Kolb & Sons Inc",
    "wof:placetype":"venue"
},
  "geometry": {"coordinates":[-73.067908,41.398038],"type":"Point"}
}