{
  "type": "Feature",
  "properties": {
    "addr:full":"58 State St Guilford CT 06437",
    "addr:housenumber":"58",
    "addr:postcode":"06437",
    "addr:street":"State St",
    "iso:country":"US",
    "sg:address":"58 State St",
    "sg:city":"Guilford",
    "sg:classifiers":[
        {
            "category":"Retail",
            "subcategory":"Auto Repair",
            "type":"Services"
        }
    ],
    "sg:phone":"+1   ",
    "sg:postcode":"06437",
    "sg:province":"CT",
    "sg:tags":[
        "body"
    ],
    "wof:name":"Classic Auto Restoration",
    "wof:placetype":"venue"
},
  "geometry": {"coordinates":[-72.68209400000001,41.287929],"type":"Point"}
}