{
  "type": "Feature",
  "properties": {
    "iso:country":"US",
    "sg:address":"955 E Main St",
    "sg:city":"Stamford",
    "sg:classifiers":[
        {
            "category":"Home & Garden",
            "subcategory":"Building Materials",
            "type":"Retail Goods"
        }
    ],
    "sg:phone":"+1 203 348 9822",
    "sg:postcode":"06902",
    "sg:province":"CT",
    "sg:tags":[
        "paint"
    ],
    "wof:name":"Siperstein's Paint & Decorate",
    "wof:placetype":"venue"
},
  "geometry": {"coordinates":[-73.52028799999999,41.056242],"type":"Point"}
}