{
  "type": "Feature",
  "properties": {
    "iso:country":"US",
    "sg:address":"154 Oxford St",
    "sg:city":"Hartford",
    "sg:classifiers":[
        {
            "category":"Professional",
            "subcategory":"Engineering",
            "type":"Services"
        }
    ],
    "sg:phone":"+1   ",
    "sg:postcode":"06105",
    "sg:province":"CT",
    "wof:name":"N S I Inc",
    "wof:placetype":"venue"
},
  "geometry": {"coordinates":[-72.713554,41.766475],"type":"Point"}
}