{
  "type": "Feature",
  "properties": {
    "iso:country":"US",
    "sg:address":"315 W Main St",
    "sg:city":"Avon",
    "sg:classifiers":[
        {
            "category":"Shopping",
            "subcategory":"Crafts & Fabrics",
            "type":"Retail Goods"
        }
    ],
    "sg:phone":"+1 860 676 1006",
    "sg:postcode":"06001",
    "sg:province":"CT",
    "sg:tags":[
        "art",
        "supply"
    ],
    "sg:website":"www.michaels.com",
    "wof:name":"Michael Arts & Crafts",
    "wof:placetype":"venue"
},
  "geometry": {"coordinates":[-72.857101,41.813801],"type":"Point"}
}