{
  "type": "Feature",
  "properties": {
    "iso:country":"US",
    "sg:address":"145 Main St",
    "sg:city":"Norwalk",
    "sg:classifiers":[
        {
            "category":"Wholesale",
            "subcategory":"Auto Parts",
            "type":"Manufacturing & Wholesale Goods"
        }
    ],
    "sg:phone":"+1 203 847 3666",
    "sg:postcode":"06851",
    "sg:province":"CT",
    "sg:tags":[
        "automobile",
        "supply"
    ],
    "wof:name":"Autopart International",
    "wof:placetype":"venue"
},
  "geometry": {"coordinates":[-73.416723,41.124324],"type":"Point"}
}