{
  "type": "Feature",
  "properties": {
    "addr:full":"195 Webb Cir Monroe CT 06468",
    "addr:housenumber":"195",
    "addr:postcode":"06468",
    "addr:street":"Webb Cir Monroe Ct",
    "iso:country":"US",
    "sg:address":"195 Webb Cir",
    "sg:city":"Monroe",
    "sg:classifiers":[
        {
            "category":"Professional",
            "subcategory":"Business Services",
            "type":"Services"
        }
    ],
    "sg:phone":"+1   ",
    "sg:postcode":"06468",
    "sg:province":"CT",
    "sg:tags":[
        "video",
        "distant",
        "learning",
        "surveillance"
    ],
    "wof:name":"Cyvidia Systems",
    "wof:placetype":"venue"
},
  "geometry": {"coordinates":[-73.170232,41.361647],"type":"Point"}
}