{
  "type": "Feature",
  "properties": {
    "addr:full":"19 2nd Ave West Haven CT 06516",
    "addr:housenumber":"19",
    "addr:postcode":"06516",
    "addr:street":"2Nd Ave",
    "iso:country":"US",
    "sg:address":"19 2nd Ave",
    "sg:city":"West Haven",
    "sg:classifiers":[
        {
            "category":"Professional",
            "subcategory":"Accounting & Tax Preparation",
            "type":"Services"
        }
    ],
    "sg:phone":"+1 203 937 0235",
    "sg:postcode":"06516",
    "sg:province":"CT",
    "sg:tags":[
        "bookkeeping",
        "general"
    ],
    "wof:name":"Mindpower Total Business Svc",
    "wof:placetype":"venue"
},
  "geometry": {"coordinates":[-72.932479,41.265562],"type":"Point"}
}