{
  "type": "Feature",
  "properties": {
    "iso:country":"US",
    "sg:address":"22 Lafayette Pl",
    "sg:city":"Greenwich",
    "sg:classifiers":[
        {
            "category":"Personal",
            "type":"Services"
        }
    ],
    "sg:phone":"+1 203 661 4067",
    "sg:postcode":"06830",
    "sg:province":"CT",
    "sg:tags":[
        "therapist",
        "massage"
    ],
    "wof:name":"Avenue Massage Therapy Associa",
    "wof:placetype":"venue"
},
  "geometry": {"coordinates":[-73.627662,41.032063],"type":"Point"}
}