{
  "type": "Feature",
  "properties": {
    "iso:country":"US",
    "sg:address":"560 Silver Sands Rd",
    "sg:city":"East Haven",
    "sg:classifiers":[
        {
            "category":"Professional",
            "subcategory":"Engineering",
            "type":"Services"
        }
    ],
    "sg:phone":"+1   ",
    "sg:postcode":"06512",
    "sg:province":"CT",
    "wof:name":"Paul Francis",
    "wof:placetype":"venue"
},
  "geometry": {"coordinates":[-72.881539,41.248704],"type":"Point"}
}