{
  "type": "Feature",
  "properties": {
    "addr:full":"16 Bouton St W Stamford CT 06907",
    "addr:housenumber":"16",
    "addr:postcode":"06907",
    "addr:street":"Bouton St W",
    "iso:country":"US",
    "sg:address":"16 Bouton St W",
    "sg:city":"Stamford",
    "sg:classifiers":[
        {
            "category":"Local Transit",
            "type":"Transportation"
        }
    ],
    "sg:phone":"+1 203 329 0051",
    "sg:postcode":"06907",
    "sg:province":"CT",
    "sg:tags":[
        "limousine"
    ],
    "wof:name":"Springdale Limousine Svc",
    "wof:placetype":"venue"
},
  "geometry": {"coordinates":[-73.517034,41.100628],"type":"Point"}
}