{
  "type": "Feature",
  "properties": {
    "iso:country":"US",
    "sg:address":"297 Main St",
    "sg:city":"Ansonia",
    "sg:classifiers":[
        {
            "category":"Retail",
            "subcategory":"Auto Repair",
            "type":"Services"
        }
    ],
    "sg:phone":"+1 203 734 9332",
    "sg:postcode":"06401",
    "sg:province":"CT",
    "sg:tags":[
        "repairing",
        "automobile"
    ],
    "wof:name":"Jay's Auto Repair",
    "wof:placetype":"venue"
},
  "geometry": {"coordinates":[-73.078261,41.342041],"type":"Point"}
}