{
  "type": "Feature",
  "properties": {
    "iso:country":"US",
    "sg:address":"112 Gilbert Ave",
    "sg:city":"Rocky Hill",
    "sg:classifiers":[
        {
            "category":"Building & Trades",
            "subcategory":"Construction",
            "type":"Services"
        }
    ],
    "sg:phone":"+1 860 529 8574",
    "sg:postcode":"06067",
    "sg:province":"CT",
    "wof:name":"John Irace",
    "wof:placetype":"venue"
},
  "geometry": {"coordinates":[-72.664798,41.661145],"type":"Point"}
}