{
  "type": "Feature",
  "properties": {
    "addr:full":"10 Split Rock Rd Bethany CT 06524",
    "addr:housenumber":"10",
    "addr:postcode":"06524",
    "addr:street":"Split Rock Rd Bethany Ct",
    "iso:country":"US",
    "sg:address":"10 Split Rock Rd",
    "sg:city":"Bethany",
    "sg:classifiers":[
        {
            "category":"Building & Trades",
            "subcategory":"Construction",
            "type":"Services"
        }
    ],
    "sg:phone":"+1 203 996 7340",
    "sg:postcode":"06524",
    "sg:province":"CT",
    "sg:tags":[
        "contractor",
        "specialty",
        "grading"
    ],
    "wof:name":"Titan Construction",
    "wof:placetype":"venue"
},
  "geometry": {"coordinates":[-73.006586,41.409485],"type":"Point"}
}