{
  "type": "Feature",
  "properties": {
    "addr:full":"332 Main St Middletown CT 06457",
    "addr:housenumber":"332",
    "addr:postcode":"06457",
    "addr:street":"Main St",
    "iso:country":"US",
    "sg:address":"332 Main St",
    "sg:city":"Middletown",
    "sg:classifiers":[
        {
            "category":"Health Services",
            "subcategory":"Optometrist",
            "type":"Services"
        }
    ],
    "sg:phone":"+1   ",
    "sg:postcode":"06457",
    "sg:province":"CT",
    "wof:name":"George Demirjian Od",
    "wof:placetype":"venue"
},
  "geometry": {"coordinates":[-72.648534,41.558916],"type":"Point"}
}