{
  "type": "Feature",
  "properties": {
    "iso:country":"US",
    "sg:address":"81 Halls Rd",
    "sg:city":"Old Lyme",
    "sg:classifiers":[
        {
            "category":"Health Services",
            "subcategory":"Doctor",
            "type":"Services"
        },
        {
            "category":"Health Services",
            "subcategory":"Clinic",
            "type":"Services"
        }
    ],
    "sg:phone":"+1 860 434 5507",
    "sg:postcode":"06371",
    "sg:province":"CT",
    "sg:tags":[
        "counseling",
        "mental"
    ],
    "wof:name":"Small Gloria PHD",
    "wof:placetype":"venue"
},
  "geometry": {"coordinates":[-72.335098,41.324001],"type":"Point"}
}