{
  "type": "Feature",
  "properties": {
    "addr:full":"4 Bartram Dr Redding CT 06896",
    "addr:housenumber":"4",
    "addr:postcode":"06896",
    "addr:street":"Bartram Dr",
    "iso:country":"US",
    "sg:address":"4 Bartram Dr",
    "sg:city":"Redding",
    "sg:classifiers":[
        {
            "category":"Health Services",
            "subcategory":"Doctor",
            "type":"Services"
        }
    ],
    "sg:phone":"+1   ",
    "sg:postcode":"06896",
    "sg:province":"CT",
    "sg:tags":[
        "medical"
    ],
    "wof:name":"Arcuni Loralee A",
    "wof:placetype":"venue"
},
  "geometry": {"coordinates":[-73.390972,41.338454],"type":"Point"}
}