{
  "type": "Feature",
  "properties": {
    "addr:full":"108 Bedford St Stamford CT 06901",
    "addr:housenumber":"108",
    "addr:postcode":"06901",
    "addr:street":"Bedford St",
    "iso:country":"US",
    "sg:address":"108 Bedford St",
    "sg:city":"Stamford",
    "sg:classifiers":[
        {
            "category":"Food & Beverages",
            "subcategory":"Specialty",
            "type":"Retail Goods"
        }
    ],
    "sg:phone":"+1 203 325 1234",
    "sg:postcode":"06901",
    "sg:province":"CT",
    "sg:tags":[
        "health",
        "diet"
    ],
    "wof:name":"Sugar Free Xpress",
    "wof:placetype":"venue"
},
  "geometry": {"coordinates":[-73.537982,41.0553],"type":"Point"}
}