{
  "type": "Feature",
  "properties": {
    "iso:country":"US",
    "sg:address":"159 Main St",
    "sg:city":"Deep River",
    "sg:classifiers":[
        {
            "category":"Food & Beverages",
            "subcategory":"Specialty",
            "type":"Retail Goods"
        }
    ],
    "sg:phone":"+1 860 526 4056",
    "sg:postcode":"06417",
    "sg:province":"CT",
    "sg:website":"www.feastgourmetmarket.com",
    "wof:name":"Feast Gourmet Market & Catering",
    "wof:placetype":"venue"
},
  "geometry": {"coordinates":[-72.435622,41.386204],"type":"Point"}
}