{
  "type": "Feature",
  "properties": {
    "addr:full":"42 Sequin St Newington CT 06111",
    "addr:housenumber":"42",
    "addr:postcode":"06111",
    "addr:street":"Sequin St",
    "iso:country":"US",
    "sg:address":"42 Sequin St",
    "sg:city":"Newington",
    "sg:classifiers":[
        {
            "category":"Building & Trades",
            "subcategory":"Plumbing",
            "type":"Services"
        }
    ],
    "sg:phone":"+1 860 666 2696",
    "sg:postcode":"06111",
    "sg:province":"CT",
    "sg:tags":[
        "contractor"
    ],
    "wof:name":"Campbell James Cooling Llc",
    "wof:placetype":"venue"
},
  "geometry": {"coordinates":[-72.73957900000001,41.683704],"type":"Point"}
}