{
  "type": "Feature",
  "properties": {
    "addr:full":"414 Prospect Ave Hartford CT 06105",
    "addr:housenumber":"414",
    "addr:postcode":"06105",
    "addr:street":"Prospect Ave;Ct",
    "iso:country":"US",
    "sg:address":"414 Prospect Ave",
    "sg:city":"Hartford",
    "sg:classifiers":[
        {
            "category":"Professional",
            "subcategory":"Research",
            "type":"Services"
        }
    ],
    "sg:phone":"+1   ",
    "sg:postcode":"06105",
    "sg:province":"CT",
    "sg:tags":[
        "nonphysical",
        "commercial"
    ],
    "wof:name":"Sylvia Karotkin",
    "wof:placetype":"venue"
},
  "geometry": {"coordinates":[-72.715047,41.758345],"type":"Point"}
}