{
  "type": "Feature",
  "properties": {
    "addr:full":"97 Main St Cheshire CT 06410",
    "addr:housenumber":"97",
    "addr:postcode":"06410",
    "addr:street":"Main St",
    "iso:country":"US",
    "sg:address":"97 Main St",
    "sg:city":"Cheshire",
    "sg:classifiers":[
        {
            "category":"Health Services",
            "subcategory":"Podiatrist",
            "type":"Services"
        }
    ],
    "sg:phone":"+1 203 272 4324",
    "sg:postcode":"06410",
    "sg:province":"CT",
    "wof:name":"Herbert M Karpelman Jr DPM",
    "wof:placetype":"venue"
},
  "geometry": {"coordinates":[-72.90233499999999,41.501682],"type":"Point"}
}