{
  "type": "Feature",
  "properties": {
    "iso:country":"US",
    "sg:address":"113 Elm St",
    "sg:city":"Enfield",
    "sg:classifiers":[
        {
            "category":"Social Services",
            "type":"Services"
        },
        {
            "category":"Health Services",
            "subcategory":"Clinic",
            "type":"Services"
        }
    ],
    "sg:phone":"+1 860 741 3001",
    "sg:postcode":"06082",
    "sg:province":"CT",
    "sg:tags":[
        "information",
        "family",
        "outpatient",
        "individual",
        "marriage",
        "treatment",
        "child",
        "counselor",
        "alcoholism"
    ],
    "sg:website":"http://www.newdirectionsct.org",
    "wof:name":"New Directions Inc Of North Ce",
    "wof:placetype":"venue"
},
  "geometry": {"coordinates":[-72.581062,41.998039],"type":"Point"}
}