{
  "type": "Feature",
  "properties": {
    "addr:full":"2386 Norwich-New London Tpke Uncasville CT 06382",
    "addr:housenumber":"2386",
    "addr:postcode":"06382",
    "addr:street":"Norwich-New;Tpke Uncasville Ct",
    "iso:country":"US",
    "sg:address":"2386 Norwich-New London Tpke",
    "sg:city":"Uncasville",
    "sg:classifiers":[
        {
            "category":"Retail",
            "subcategory":"Repair Shop",
            "type":"Services"
        }
    ],
    "sg:phone":"+1 860 848 7744",
    "sg:postcode":"06382",
    "sg:province":"CT",
    "sg:tags":[
        "machine",
        "metalworking",
        "welding",
        "mfg"
    ],
    "wof:name":"Andrew D Parrish & Son",
    "wof:placetype":"venue"
},
  "geometry": {"coordinates":[-72.10008999999999,41.492026],"type":"Point"}
}