{
  "type": "Feature",
  "properties": {
    "addr:full":"70 Dodgingtown Rd Bethel CT 06801",
    "addr:housenumber":"70",
    "addr:postcode":"06801",
    "addr:street":"Dodgingtown Rd",
    "iso:country":"US",
    "sg:address":"70 Dodgingtown Rd",
    "sg:city":"Bethel",
    "sg:classifiers":[
        {
            "category":"Building & Trades",
            "subcategory":"Cleaning & Sanitation",
            "type":"Services"
        },
        {
            "category":"Building & Trades",
            "subcategory":"Construction",
            "type":"Services"
        }
    ],
    "sg:phone":"+1 203 792 2900",
    "sg:postcode":"06801",
    "sg:province":"CT",
    "sg:tags":[
        "heavy",
        "maid",
        "butler"
    ],
    "wof:name":"Spotless Cleaning Service",
    "wof:placetype":"venue"
},
  "geometry": {"coordinates":[-73.379603,41.377567],"type":"Point"}
}