{
  "type": "Feature",
  "properties": {
    "iso:country":"US",
    "sg:address":"43 Gail Dr",
    "sg:city":"Waterbury",
    "sg:classifiers":[
        {
            "category":"Building & Trades",
            "subcategory":"Construction",
            "type":"Services"
        }
    ],
    "sg:phone":"+1 203 753 0264",
    "sg:postcode":"06704",
    "sg:province":"CT",
    "sg:tags":[
        "repairing",
        "remodeling",
        "contractor"
    ],
    "wof:name":"K & G Builders",
    "wof:placetype":"venue"
},
  "geometry": {"coordinates":[-73.03774300000001,41.579954],"type":"Point"}
}