{
  "type": "Feature",
  "properties": {
    "addr:full":"1 Selleck St Norwalk CT 06855",
    "addr:housenumber":"1",
    "addr:postcode":"06855",
    "addr:street":"Selleck St",
    "iso:country":"US",
    "sg:address":"1 Selleck St",
    "sg:city":"Norwalk",
    "sg:classifiers":[
        {
            "category":"Banks & Credit Unions",
            "subcategory":"Investment Brokerage",
            "type":"Services"
        }
    ],
    "sg:phone":"+1 203 604 1127",
    "sg:postcode":"06855",
    "sg:province":"CT",
    "sg:tags":[
        "consultant",
        "planning",
        "financial"
    ],
    "wof:name":"American Express Financial Adv",
    "wof:placetype":"venue"
},
  "geometry": {"coordinates":[-73.40860499999999,41.107492],"type":"Point"}
}