{
  "type": "Feature",
  "properties": {
    "iso:country":"US",
    "sg:address":"130 Branca Ct",
    "sg:city":"Milford",
    "sg:classifiers":[
        {
            "category":"Professional",
            "subcategory":"Business Services",
            "type":"Services"
        }
    ],
    "sg:phone":"+1   ",
    "sg:postcode":"06461",
    "sg:province":"CT",
    "wof:name":"Arbelo Technology Solutions L",
    "wof:placetype":"venue"
},
  "geometry": {"coordinates":[-73.03626199999999,41.248599],"type":"Point"}
}