{
  "type": "Feature",
  "properties": {
    "addr:full":"70 Akron St Meriden CT 06450",
    "addr:housenumber":"70",
    "addr:postcode":"06450",
    "addr:street":"Akron St",
    "iso:country":"US",
    "sg:address":"70 Akron St",
    "sg:city":"Meriden",
    "sg:classifiers":[
        {
            "category":"Organizations",
            "subcategory":"Religious Organization",
            "type":"Services"
        }
    ],
    "sg:phone":"+1 203 237 1559",
    "sg:postcode":"06450",
    "sg:province":"CT",
    "sg:tags":[
        "monastery",
        "convent"
    ],
    "wof:name":"Saint Stanislaus Convent",
    "wof:placetype":"venue"
},
  "geometry": {"coordinates":[-72.798316,41.533718],"type":"Point"}
}