{
  "type": "Feature",
  "properties": {
    "addr:full":"42 Hull St Shelton CT 06484",
    "addr:housenumber":"42",
    "addr:postcode":"06484",
    "addr:street":"Hull St",
    "iso:country":"US",
    "sg:address":"42 Hull St",
    "sg:city":"Shelton",
    "sg:classifiers":[
        {
            "category":"Restaurant",
            "type":"Food & Drink"
        }
    ],
    "sg:phone":"+1 203 924 0799",
    "sg:postcode":"06484",
    "sg:province":"CT",
    "sg:tags":[
        "eating",
        "merchandise"
    ],
    "wof:name":"Figure It Out",
    "wof:placetype":"venue"
},
  "geometry": {"coordinates":[-73.087098,41.311611],"type":"Point"}
}