{
  "type": "Feature",
  "properties": {
    "iso:country":"US",
    "sg:address":"278 W Main St",
    "sg:city":"Meriden",
    "sg:classifiers":[
        {
            "category":"Bars & Pubs",
            "type":"Food & Drink"
        }
    ],
    "sg:phone":"+1 203 630 6530",
    "sg:postcode":"06451",
    "sg:province":"CT",
    "wof:name":"Alibi",
    "wof:placetype":"venue"
},
  "geometry": {"coordinates":[-72.81253700000001,41.539385],"type":"Point"}
}