{
  "type": "Feature",
  "properties": {
    "addr:full":"5 Hillhouse Ave New Haven CT 06511",
    "addr:housenumber":"5",
    "addr:postcode":"06511",
    "addr:street":"Hillhouse Ave",
    "iso:country":"US",
    "sg:address":"5 Hillhouse Ave",
    "sg:city":"New Haven",
    "sg:classifiers":[
        {
            "category":"Organizations",
            "subcategory":"Religious Organization",
            "type":"Services"
        }
    ],
    "sg:phone":"+1 203 562 9326",
    "sg:postcode":"06511",
    "sg:province":"CT",
    "sg:tags":[
        "church"
    ],
    "wof:name":"Shrine Of The Infant Of Prague",
    "wof:placetype":"venue"
},
  "geometry": {"coordinates":[-72.92395399999999,41.312394],"type":"Point"}
}