{
  "type": "Feature",
  "properties": {
    "iso:country":"US",
    "sg:address":"122 Terrell Farm Rd",
    "sg:city":"Bethlehem",
    "sg:classifiers":[
        {
            "category":"Manufacturing",
            "subcategory":"Tools & Machinery",
            "type":"Manufacturing & Wholesale Goods"
        }
    ],
    "sg:phone":"+1 860 567 4390",
    "sg:postcode":"06751",
    "sg:province":"CT",
    "sg:tags":[
        "measuring",
        "instrument",
        "electrical",
        "mfg"
    ],
    "wof:name":"Whitall Battery",
    "wof:placetype":"venue"
},
  "geometry": {"coordinates":[-73.202854,41.663263],"type":"Point"}
}