{
  "type": "Feature",
  "properties": {
    "addr:full":"7 Alpine Ln Darien CT 06820",
    "addr:housenumber":"7",
    "addr:postcode":"06820",
    "addr:street":"Alpine Ln Darien Ct",
    "iso:country":"US",
    "sg:address":"7 Alpine Ln",
    "sg:city":"Darien",
    "sg:classifiers":[
        {
            "category":"Professional",
            "subcategory":"Management & Consulting",
            "type":"Services"
        }
    ],
    "sg:phone":"+1   ",
    "sg:postcode":"06820",
    "sg:province":"CT",
    "sg:tags":[
        "business"
    ],
    "wof:name":"Success Coach The",
    "wof:placetype":"venue"
},
  "geometry": {"coordinates":[-73.513402,41.083215],"type":"Point"}
}