{
  "type": "Feature",
  "properties": {
    "addr:full":"89 Grandview Ave Bridgeport CT 06606",
    "addr:housenumber":"89",
    "addr:postcode":"06606",
    "addr:street":"Grandview Ave",
    "iso:country":"US",
    "sg:address":"89 Grandview Ave",
    "sg:city":"Bridgeport",
    "sg:classifiers":[
        {
            "category":"Social Services",
            "subcategory":"Child Care",
            "type":"Services"
        }
    ],
    "sg:phone":"+1   ",
    "sg:postcode":"06606",
    "sg:province":"CT",
    "sg:tags":[
        "day"
    ],
    "wof:name":"Angelas Day Care",
    "wof:placetype":"venue"
},
  "geometry": {"coordinates":[-73.18872,41.219935],"type":"Point"}
}