{
  "type": "Feature",
  "properties": {
    "addr:full":"69 Winfield St Norwalk CT 06855",
    "addr:housenumber":"69",
    "addr:postcode":"06855",
    "addr:street":"Winfield St",
    "iso:country":"US",
    "sg:address":"69 Winfield St",
    "sg:city":"Norwalk",
    "sg:classifiers":[
        {
            "category":"Food & Beverages",
            "subcategory":"Groceries & Convenience Stores",
            "type":"Retail Goods"
        }
    ],
    "sg:phone":"+1 203 866 4348",
    "sg:postcode":"06855",
    "sg:province":"CT",
    "wof:name":"Winfield Deli",
    "wof:placetype":"venue"
},
  "geometry": {"coordinates":[-73.39795700000001,41.105728],"type":"Point"}
}