{
  "type": "Feature",
  "properties": {
    "iso:country":"US",
    "sg:address":"75 Main St",
    "sg:city":"Norwalk",
    "sg:classifiers":[
        {
            "category":"Shopping",
            "subcategory":"Clothing, Apparel, & Fashions",
            "type":"Retail Goods"
        },
        {
            "category":"Personal",
            "subcategory":"Beauty Salon",
            "type":"Services"
        },
        {
            "category":"Retail",
            "subcategory":"Laundry & Dry Cleaning",
            "type":"Services"
        }
    ],
    "sg:phone":"+1 203 847 0542",
    "sg:postcode":"06851",
    "sg:province":"CT",
    "sg:tags":[
        "wig",
        "hair",
        "piece",
        "costumes-renting",
        "costume"
    ],
    "sg:website":"http://www.happydazecostumes.com",
    "wof:name":"Happy Daze Costumes",
    "wof:placetype":"venue"
},
  "geometry": {"coordinates":[-73.413225,41.121157],"type":"Point"}
}