{
  "type": "Feature",
  "properties": {
    "iso:country":"US",
    "sg:address":"51 Quorn Hunt Rd",
    "sg:city":"West Simsbury",
    "sg:classifiers":[
        {
            "category":"Professional",
            "subcategory":"Business Services",
            "type":"Services"
        }
    ],
    "sg:phone":"+1   ",
    "sg:postcode":"06092",
    "sg:province":"CT",
    "wof:name":"Wdk Design",
    "wof:placetype":"venue"
},
  "geometry": {"coordinates":[-72.870396,41.858561],"type":"Point"}
}