{
  "type": "Feature",
  "properties": {
    "addr:full":"1010 Village Walk Guilford CT 06437",
    "addr:housenumber":"1010",
    "addr:postcode":"06437",
    "addr:street":"Village Walk",
    "iso:country":"US",
    "sg:address":"1010 Village Walk",
    "sg:city":"Guilford",
    "sg:classifiers":[
        {
            "category":"Shopping",
            "subcategory":"Florist",
            "type":"Retail Goods"
        }
    ],
    "sg:phone":"+1 203 453 3347",
    "sg:postcode":"06437",
    "sg:province":"CT",
    "wof:name":"Guilford Lakes Florist",
    "wof:placetype":"venue"
},
  "geometry": {"coordinates":[-72.674826,41.288524],"type":"Point"}
}