{
  "type": "Feature",
  "properties": {
    "addr:full":"38 Danbury Rd New Milford CT 06776",
    "addr:housenumber":"38",
    "addr:postcode":"06776",
    "addr:street":"Danbury Rd",
    "iso:country":"US",
    "sg:address":"38 Danbury Rd",
    "sg:city":"New Milford",
    "sg:classifiers":[
        {
            "category":"Coffee & Tea",
            "type":"Food & Drink"
        }
    ],
    "sg:menulink":"http://www.allmenus.com/ct/new-milford/108487-starbucks-coffee/menu/",
    "sg:phone":"+1 860 354 2508",
    "sg:postcode":"06776",
    "sg:province":"CT",
    "sg:tags":[
        "american"
    ],
    "wof:name":"Starbucks Coffee",
    "wof:placetype":"venue"
},
  "geometry": {"coordinates":[-73.414461,41.569347],"type":"Point"}
}