{
  "type": "Feature",
  "properties": {
    "addr:full":"180 Post Rd E Westport CT 06880",
    "addr:housenumber":"180",
    "addr:postcode":"06880",
    "addr:street":"Post Rd E Westport Ct",
    "iso:country":"US",
    "sg:address":"180 Post Rd E",
    "sg:city":"Westport",
    "sg:classifiers":[
        {
            "category":"Insurance",
            "subcategory":"Insurance Agent",
            "type":"Services"
        }
    ],
    "sg:phone":"+1 203 226 7178",
    "sg:postcode":"06880",
    "sg:province":"CT",
    "wof:name":"Commercial Insurance MGT",
    "wof:placetype":"venue"
},
  "geometry": {"coordinates":[-73.35809399999999,41.141466],"type":"Point"}
}