{
  "type": "Feature",
  "properties": {
    "addr:full":"1022 Broad St Hartford CT 06106",
    "addr:housenumber":"1022",
    "addr:postcode":"06106",
    "addr:street":"Broad St",
    "iso:country":"US",
    "sg:address":"1022 Broad St",
    "sg:city":"Hartford",
    "sg:classifiers":[
        {
            "category":"Food & Beverages",
            "subcategory":"Groceries & Convenience Stores",
            "type":"Retail Goods"
        }
    ],
    "sg:phone":"+1 860 293 2535",
    "sg:postcode":"06106",
    "sg:province":"CT",
    "wof:name":"Anacaona Grocery Store",
    "wof:placetype":"venue"
},
  "geometry": {"coordinates":[-72.686993,41.756049],"type":"Point"}
}