{
  "type": "Feature",
  "properties": {
    "iso:country":"US",
    "sg:address":"192 S Broad St",
    "sg:city":"Meriden",
    "sg:classifiers":[
        {
            "category":"Retail",
            "subcategory":"Laundry & Dry Cleaning",
            "type":"Services"
        }
    ],
    "sg:phone":"+1   ",
    "sg:postcode":"06450",
    "sg:province":"CT",
    "sg:tags":[
        "janitorial",
        "carpet"
    ],
    "wof:name":"Hank Sawicki & Sons Inc",
    "wof:placetype":"venue"
},
  "geometry": {"coordinates":[-72.804856,41.515778],"type":"Point"}
}