{
  "type": "Feature",
  "properties": {
    "iso:country":"US",
    "sg:address":"23 W Main St",
    "sg:city":"Clinton",
    "sg:classifiers":[
        {
            "category":"Health Services",
            "subcategory":"Podiatrist",
            "type":"Services"
        }
    ],
    "sg:phone":"+1   ",
    "sg:postcode":"06413",
    "sg:province":"CT",
    "wof:name":"Center Podiatry of Clinton",
    "wof:placetype":"venue"
},
  "geometry": {"coordinates":[-72.532608,41.279191],"type":"Point"}
}