{
  "type": "Feature",
  "properties": {
    "addr:full":"374 Main St Niantic CT 06357",
    "addr:housenumber":"374",
    "addr:postcode":"06357",
    "addr:street":"Main St",
    "iso:country":"US",
    "sg:address":"374 Main St",
    "sg:city":"Niantic",
    "sg:classifiers":[
        {
            "category":"Food & Beverages",
            "subcategory":"Specialty",
            "type":"Retail Goods"
        },
        {
            "category":"Manufacturing",
            "subcategory":"Food",
            "type":"Manufacturing & Wholesale Goods"
        },
        {
            "category":"Food & Beverages",
            "subcategory":"Groceries & Convenience Stores",
            "type":"Retail Goods"
        }
    ],
    "sg:phone":"+1 860 739 9916",
    "sg:postcode":"06357",
    "sg:province":"CT",
    "sg:tags":[
        "product",
        "supplement",
        "health",
        "vitamin",
        "diet"
    ],
    "wof:name":"Natural Food Store",
    "wof:placetype":"venue"
},
  "geometry": {"coordinates":[-72.19604,41.322851],"type":"Point"}
}