{
  "type": "Feature",
  "properties": {
    "addr:full":"246 Church St Brooklyn CT 06234",
    "addr:housenumber":"246",
    "addr:postcode":"06234",
    "addr:street":"Church St",
    "iso:country":"US",
    "sg:address":"246 Church St",
    "sg:city":"Brooklyn",
    "sg:classifiers":[
        {
            "category":"Professional",
            "type":"Services"
        }
    ],
    "sg:phone":"+1 860 774 4133",
    "sg:postcode":"06234",
    "sg:province":"CT",
    "wof:name":"Mountainview Landing LLC",
    "wof:placetype":"venue"
},
  "geometry": {"coordinates":[-71.923524,41.813431],"type":"Point"}
}