{
  "type": "Feature",
  "properties": {
    "addr:full":"18 Tower Ln New Haven CT 06519",
    "addr:housenumber":"18",
    "addr:postcode":"06519",
    "addr:street":"Tower Ln",
    "iso:country":"US",
    "sg:address":"18 Tower Ln",
    "sg:city":"New Haven",
    "sg:classifiers":[
        {
            "category":"Professional",
            "subcategory":"Management & Consulting",
            "type":"Services"
        }
    ],
    "sg:phone":"+1 203 624 1566",
    "sg:postcode":"06519",
    "sg:province":"CT",
    "sg:tags":[
        "fuel"
    ],
    "wof:name":"Century Management Systems",
    "wof:placetype":"venue"
},
  "geometry": {"coordinates":[-72.92878,41.301105],"type":"Point"}
}