{
  "type": "Feature",
  "properties": {
    "iso:country":"US",
    "sg:address":"300 Tresser Blvd",
    "sg:city":"Stamford",
    "sg:classifiers":[
        {
            "category":"Government",
            "subcategory":"Office",
            "type":"Public Place"
        }
    ],
    "sg:phone":"+1 203 964 1445",
    "sg:postcode":"06901",
    "sg:province":"CT",
    "sg:tags":[
        "housing",
        "subsidized"
    ],
    "wof:name":"Midland Property Management",
    "wof:placetype":"venue"
},
  "geometry": {"coordinates":[-73.534913,41.052085],"type":"Point"}
}