{
  "type": "Feature",
  "properties": {
    "iso:country":"US",
    "sg:address":"21 Washington Plz",
    "sg:city":"Gaylordsville",
    "sg:classifiers":[
        {
            "category":"Manufacturing",
            "subcategory":"Chemicals & Compounds",
            "type":"Manufacturing & Wholesale Goods"
        }
    ],
    "sg:phone":"+1 860 355 5805",
    "sg:postcode":"06755",
    "sg:province":"CT",
    "sg:tags":[
        "plant",
        "extract"
    ],
    "wof:name":"Microbotanica Inc",
    "wof:placetype":"venue"
},
  "geometry": {"coordinates":[-73.48261599999999,41.639906],"type":"Point"}
}