{
  "type": "Feature",
  "properties": {
    "iso:country":"US",
    "sg:address":"32 Society Rd",
    "sg:city":"Niantic",
    "sg:classifiers":[
        {
            "category":"Organizations",
            "subcategory":"Community Association",
            "type":"Services"
        }
    ],
    "sg:phone":"+1   ",
    "sg:postcode":"06357",
    "sg:province":"CT",
    "wof:name":"Bay View Masonic Temple Assoc",
    "wof:placetype":"venue"
},
  "geometry": {"coordinates":[-72.21357399999999,41.346898],"type":"Point"}
}