{
  "type": "Feature",
  "properties": {
    "addr:full":"730 Boston Post Rd Westbrook CT 06498",
    "addr:housenumber":"730",
    "addr:postcode":"06498",
    "addr:street":"Boston Post Rd",
    "iso:country":"US",
    "sg:address":"730 Boston Post Rd",
    "sg:city":"Westbrook",
    "sg:classifiers":[
        {
            "category":"Professional",
            "type":"Services"
        },
        {
            "category":"Restaurant",
            "type":"Food & Drink"
        }
    ],
    "sg:phone":"+1 860 399 4444",
    "sg:postcode":"06498",
    "sg:province":"CT",
    "sg:tags":[
        "italian",
        "caterer"
    ],
    "sg:website":"www.pazzoprimo.com",
    "wof:name":"Pazzo Ristorante",
    "wof:placetype":"venue"
},
  "geometry": {"coordinates":[-72.462208,41.279082],"type":"Point"}
}