{
  "type": "Feature",
  "properties": {
    "addr:full":"15 New Britain Ave Unionville CT 06085",
    "addr:housenumber":"15",
    "addr:postcode":"06085",
    "addr:street":"New Britain Ave Unionville Ct",
    "iso:country":"US",
    "sg:address":"15 New Britain Ave",
    "sg:city":"Unionville",
    "sg:classifiers":[
        {
            "category":"Insurance",
            "subcategory":"Insurance Agent",
            "type":"Services"
        }
    ],
    "sg:phone":"+1 860 675 5484",
    "sg:postcode":"06085",
    "sg:province":"CT",
    "wof:name":"Delgallo Insur Investments LLC",
    "wof:placetype":"venue"
},
  "geometry": {"coordinates":[-72.886269,41.755124],"type":"Point"}
}