{
  "type": "Feature",
  "properties": {
    "addr:full":"10 Beardsley Ave Stratford CT 06615",
    "addr:housenumber":"10",
    "addr:postcode":"06615",
    "addr:street":"Beardsley Ave",
    "iso:country":"US",
    "sg:address":"10 Beardsley Ave",
    "sg:city":"Stratford",
    "sg:classifiers":[
        {
            "category":"Wholesale",
            "subcategory":"Machinery & Supplies",
            "type":"Manufacturing & Wholesale Goods"
        }
    ],
    "sg:phone":"+1 203 380 9929",
    "sg:postcode":"06615",
    "sg:province":"CT",
    "sg:tags":[
        "industrial",
        "miscellaneous"
    ],
    "wof:name":"Le Blanc's Truck & Equipment",
    "wof:placetype":"venue"
},
  "geometry": {"coordinates":[-73.133836,41.187361],"type":"Point"}
}