{
  "type": "Feature",
  "properties": {
    "iso:country":"US",
    "sg:address":"149 Whalehead Rd",
    "sg:city":"Gales Ferry",
    "sg:classifiers":[
        {
            "category":"Building & Trades",
            "subcategory":"Equipment Rental",
            "type":"Services"
        }
    ],
    "sg:phone":"+1   ",
    "sg:postcode":"06335",
    "sg:province":"CT",
    "wof:name":"Nelson Canopy",
    "wof:placetype":"venue"
},
  "geometry": {"coordinates":[-72.06000899999999,41.444298],"type":"Point"}
}