{
  "type": "Feature",
  "properties": {
    "addr:full":"10 Hemingway Rd North Haven CT 06473",
    "addr:housenumber":"10",
    "addr:postcode":"06473",
    "addr:street":"Hemingway Rd;Haven",
    "iso:country":"US",
    "sg:address":"10 Hemingway Rd",
    "sg:city":"North Haven",
    "sg:classifiers":[
        {
            "category":"Retail",
            "subcategory":"Portrait Studio",
            "type":"Services"
        }
    ],
    "sg:phone":"+1   ",
    "sg:postcode":"06473",
    "sg:province":"CT",
    "sg:tags":[
        "photographer",
        "cultural",
        "product",
        "import",
        "ethnic"
    ],
    "wof:name":"Celtic Photos & Crafts",
    "wof:placetype":"venue"
},
  "geometry": {"coordinates":[-72.855649,41.362217],"type":"Point"}
}