{
  "type": "Feature",
  "properties": {
    "iso:country":"US",
    "sg:address":"840 Wethersfield Ave",
    "sg:city":"Hartford",
    "sg:classifiers":[
        {
            "category":"Retail",
            "subcategory":"Portrait Studio",
            "type":"Services"
        }
    ],
    "sg:phone":"+1   ",
    "sg:postcode":"06114",
    "sg:province":"CT",
    "sg:tags":[
        "photo",
        "commercial",
        "design"
    ],
    "wof:name":"Deguzis Photography",
    "wof:placetype":"venue"
},
  "geometry": {"coordinates":[-72.669961,41.732983],"type":"Point"}
}