{
  "type": "Feature",
  "properties": {
    "iso:country":"US",
    "sg:address":"666 E Main St",
    "sg:city":"Waterbury",
    "sg:classifiers":[
        {
            "category":"Retail",
            "subcategory":"Car Wash",
            "type":"Services"
        }
    ],
    "sg:phone":"+1   ",
    "sg:postcode":"06702",
    "sg:province":"CT",
    "sg:tags":[
        "carwash"
    ],
    "wof:name":"Total Car Care",
    "wof:placetype":"venue"
},
  "geometry": {"coordinates":[-73.02877599999999,41.553749],"type":"Point"}
}