{
  "type": "Feature",
  "properties": {
    "iso:country":"US",
    "sg:address":"188 Riverside Dr",
    "sg:city":"Hamden",
    "sg:classifiers":[
        {
            "category":"Utilities",
            "subcategory":"Telephone",
            "type":"Services"
        }
    ],
    "sg:phone":"+1 203 248 0592",
    "sg:postcode":"06518",
    "sg:province":"CT",
    "sg:tags":[
        "communications"
    ],
    "wof:name":"Global Tech Assoc LLC",
    "wof:placetype":"venue"
},
  "geometry": {"coordinates":[-72.89560299999999,41.39715],"type":"Point"}
}