{
  "type": "Feature",
  "properties": {
    "iso:country":"US",
    "sg:address":"175 Wyassup Rd",
    "sg:city":"North Stonington",
    "sg:classifiers":[
        {
            "category":"Social Services",
            "subcategory":"Adult Care",
            "type":"Services"
        }
    ],
    "sg:phone":"+1   ",
    "sg:postcode":"06359",
    "sg:province":"CT",
    "sg:tags":[
        "residential"
    ],
    "wof:name":"Community Res & Educatn Fund I",
    "wof:placetype":"venue"
},
  "geometry": {"coordinates":[-71.884945,41.465382],"type":"Point"}
}