{
  "type": "Feature",
  "properties": {
    "iso:country":"US",
    "sg:address":"223 Broad St",
    "sg:city":"Bristol",
    "sg:classifiers":[
        {
            "category":"Local Transit",
            "type":"Transportation"
        }
    ],
    "sg:phone":"+1 860 584 5968",
    "sg:postcode":"06010",
    "sg:province":"CT",
    "sg:tags":[
        "passenger"
    ],
    "wof:name":"Affordable Car Rentals Inc",
    "wof:placetype":"venue"
},
  "geometry": {"coordinates":[-72.906724,41.671843],"type":"Point"}
}