{
  "type": "Feature",
  "properties": {
    "iso:country":"US",
    "sg:address":"14 Nickerson Ln",
    "sg:city":"Darien",
    "sg:classifiers":[
        {
            "category":"Professional",
            "subcategory":"Art Services",
            "type":"Services"
        }
    ],
    "sg:phone":"+1 203 655 6088",
    "sg:postcode":"06820",
    "sg:province":"CT",
    "sg:tags":[
        "graphic",
        "designer"
    ],
    "wof:name":"Wiggin & Wiggin",
    "wof:placetype":"venue"
},
  "geometry": {"coordinates":[-73.49089600000001,41.054652],"type":"Point"}
}