{
  "type": "Feature",
  "properties": {
    "addr:full":"1 New St Greenwich CT 06830",
    "addr:housenumber":"1",
    "addr:postcode":"06830",
    "addr:street":"New St",
    "iso:country":"US",
    "sg:address":"1 New St",
    "sg:city":"Greenwich",
    "sg:classifiers":[
        {
            "category":"Farming",
            "subcategory":"Farm",
            "type":"Manufacturing & Wholesale Goods"
        }
    ],
    "sg:phone":"+1 203 661 8889",
    "sg:postcode":"06830",
    "sg:province":"CT",
    "wof:name":"Conyers Farm Gatehouse",
    "wof:placetype":"venue"
},
  "geometry": {"coordinates":[-73.65534,41.006541],"type":"Point"}
}