{
  "type": "Feature",
  "properties": {
    "iso:country":"US",
    "sg:address":"83 Creamery Rd",
    "sg:city":"Durham",
    "sg:classifiers":[
        {
            "category":"Building & Trades",
            "subcategory":"Construction",
            "type":"Services"
        }
    ],
    "sg:phone":"+1 860 349 9609",
    "sg:postcode":"06422",
    "sg:province":"CT",
    "sg:tags":[
        "house",
        "construct",
        "contractor"
    ],
    "wof:name":"J Burtt & Son",
    "wof:placetype":"venue"
},
  "geometry": {"coordinates":[-72.69440400000001,41.443869],"type":"Point"}
}