{
  "type": "Feature",
  "properties": {
    "addr:full":"17 Jencks St East Hartford CT 06108",
    "addr:housenumber":"17",
    "addr:postcode":"06108",
    "addr:street":"Jencks St East;Ct",
    "iso:country":"US",
    "sg:address":"17 Jencks St",
    "sg:city":"East Hartford",
    "sg:classifiers":[
        {
            "category":"Building & Trades",
            "subcategory":"Plumbing",
            "type":"Services"
        }
    ],
    "sg:phone":"+1 860 289 6662",
    "sg:postcode":"06108",
    "sg:province":"CT",
    "sg:tags":[
        "contractor"
    ],
    "wof:name":"Preston Plumbing",
    "wof:placetype":"venue"
},
  "geometry": {"coordinates":[-72.65822799999999,41.774348],"type":"Point"}
}