{
  "type": "Feature",
  "properties": {
    "iso:country":"US",
    "sg:address":"252 Stillwater Ave",
    "sg:city":"Stamford",
    "sg:classifiers":[
        {
            "category":"Building & Trades",
            "subcategory":"Plumbing",
            "type":"Services"
        }
    ],
    "sg:phone":"+1 203 325 8247",
    "sg:postcode":"06902",
    "sg:province":"CT",
    "sg:tags":[
        "plumbing",
        "contractor"
    ],
    "wof:name":"Tuccinardi Plumbing & Heating",
    "wof:placetype":"venue"
},
  "geometry": {"coordinates":[-73.557086,41.053568],"type":"Point"}
}