{
  "type": "Feature",
  "properties": {
    "iso:country":"US",
    "sg:address":"150 W Side Dr",
    "sg:city":"New Haven",
    "sg:classifiers":[
        {
            "category":"Government",
            "subcategory":"Office",
            "type":"Public Place"
        }
    ],
    "sg:phone":"+1 203 773 2040",
    "sg:postcode":"06514",
    "sg:province":"CT",
    "sg:tags":[
        "entry",
        "port"
    ],
    "wof:name":"Port of Entry-New Haven",
    "wof:placetype":"venue"
},
  "geometry": {"coordinates":[-72.949827,41.351664],"type":"Point"}
}