{
  "type": "Feature",
  "properties": {
    "iso:country":"US",
    "sg:address":"18 Griffing Ave",
    "sg:city":"Danbury",
    "sg:classifiers":[
        {
            "category":"Building & Trades",
            "subcategory":"Landscaping Services",
            "type":"Services"
        }
    ],
    "sg:phone":"+1 203 798 9781",
    "sg:postcode":"06810",
    "sg:province":"CT",
    "sg:tags":[
        "tree"
    ],
    "wof:name":"Marc Ruiz Tree & Shrub",
    "wof:placetype":"venue"
},
  "geometry": {"coordinates":[-73.449653,41.401673],"type":"Point"}
}