{
  "type": "Feature",
  "properties": {
    "iso:country":"US",
    "sg:address":"1988 Middletown Ave",
    "sg:city":"Northford",
    "sg:classifiers":[
        {
            "category":"Professional",
            "subcategory":"Business Services",
            "type":"Services"
        }
    ],
    "sg:phone":"+1   ",
    "sg:postcode":"06472",
    "sg:province":"CT",
    "sg:tags":[
        "broker"
    ],
    "wof:name":"Dp Graphics Inc",
    "wof:placetype":"venue"
},
  "geometry": {"coordinates":[-72.74545500000001,41.417252],"type":"Point"}
}