{
  "type": "Feature",
  "properties": {
    "addr:full":"1 State St Norwalk CT 06854",
    "addr:housenumber":"1",
    "addr:postcode":"06854",
    "addr:street":"State St",
    "iso:country":"US",
    "sg:address":"1 State St",
    "sg:city":"Norwalk",
    "sg:classifiers":[
        {
            "category":"Government",
            "subcategory":"Office",
            "type":"Public Place"
        }
    ],
    "sg:phone":"+1 203 866 3366",
    "sg:postcode":"06854",
    "sg:province":"CT",
    "sg:tags":[
        "village"
    ],
    "sg:website":"www.snew.org",
    "wof:name":"South Norwalk Electric Works",
    "wof:placetype":"venue"
},
  "geometry": {"coordinates":[-73.423647,41.095829],"type":"Point"}
}