{
  "type": "Feature",
  "properties": {
    "iso:country":"US",
    "sg:address":"181 Bank St",
    "sg:city":"New London",
    "sg:classifiers":[
        {
            "category":"Retail",
            "subcategory":"Repair Shop",
            "type":"Services"
        }
    ],
    "sg:phone":"+1   ",
    "sg:postcode":"06320",
    "sg:province":"CT",
    "wof:name":"Starr of New London Antiques",
    "wof:placetype":"venue"
},
  "geometry": {"coordinates":[-72.096541,41.351931],"type":"Point"}
}