{
  "type": "Feature",
  "properties": {
    "addr:full":"45 Indian Trl Woodbridge CT 06525",
    "addr:housenumber":"45",
    "addr:postcode":"06525",
    "addr:street":"Indian Trl",
    "iso:country":"US",
    "sg:address":"45 Indian Trl",
    "sg:city":"Woodbridge",
    "sg:classifiers":[
        {
            "category":"Banks & Credit Unions",
            "subcategory":"Bank",
            "type":"Services"
        }
    ],
    "sg:phone":"+1 203 389 6300",
    "sg:postcode":"06525",
    "sg:province":"CT",
    "sg:tags":[
        "national",
        "commercial"
    ],
    "wof:name":"Colony Mortgage Bankers",
    "wof:placetype":"venue"
},
  "geometry": {"coordinates":[-73.022925,41.365018],"type":"Point"}
}