{
  "type": "Feature",
  "properties": {
    "addr:full":"251 S Main St Torrington CT 06790",
    "addr:housenumber":"251",
    "addr:postcode":"06790",
    "addr:street":"S Main St",
    "iso:country":"US",
    "sg:address":"251 S Main St",
    "sg:city":"Torrington",
    "sg:classifiers":[
        {
            "category":"Building & Trades",
            "subcategory":"Plumbing",
            "type":"Services"
        }
    ],
    "sg:phone":"+1 860 496 0492",
    "sg:postcode":"06790",
    "sg:province":"CT",
    "sg:tags":[
        "equipment",
        "systems-repairing",
        "heating",
        "contractor"
    ],
    "wof:name":"Dumont Plumbing & Heating",
    "wof:placetype":"venue"
},
  "geometry": {"coordinates":[-73.12053,41.795216],"type":"Point"}
}