{
  "type": "Feature",
  "properties": {
    "addr:full":"50 Montowese Ave North Haven CT 06473",
    "addr:housenumber":"50",
    "addr:postcode":"06473",
    "addr:street":"Montowese Ave;Haven",
    "iso:country":"US",
    "sg:address":"50 Montowese Ave",
    "sg:city":"North Haven",
    "sg:classifiers":[
        {
            "category":"Wholesale",
            "subcategory":"Seafood",
            "type":"Manufacturing & Wholesale Goods"
        }
    ],
    "sg:phone":"+1 203 865 5725",
    "sg:postcode":"06473",
    "sg:province":"CT",
    "sg:tags":[
        "distribution"
    ],
    "wof:name":"G & A Seafood",
    "wof:placetype":"venue"
},
  "geometry": {"coordinates":[-72.863716,41.350799],"type":"Point"}
}