{
  "type": "Feature",
  "properties": {
    "addr:full":"95 Willow St Waterbury CT 06710",
    "addr:housenumber":"95",
    "addr:postcode":"06710",
    "addr:street":"Willow St",
    "iso:country":"US",
    "sg:address":"95 Willow St",
    "sg:city":"Waterbury",
    "sg:classifiers":[
        {
            "category":"Retail",
            "subcategory":"Funeral Services",
            "type":"Services"
        }
    ],
    "sg:phone":"+1 203 753 1146",
    "sg:postcode":"06710",
    "sg:province":"CT",
    "sg:tags":[
        "director",
        "home"
    ],
    "wof:name":"Maiorano Funeral Home Inc",
    "wof:placetype":"venue"
},
  "geometry": {"coordinates":[-73.04755299999999,41.56168],"type":"Point"}
}