{
  "type": "Feature",
  "properties": {
    "addr:full":"330 Bishop St Waterbury CT 06704",
    "addr:housenumber":"330",
    "addr:postcode":"06704",
    "addr:street":"Bishop St Waterbury Ct",
    "iso:country":"US",
    "sg:address":"330 Bishop St",
    "sg:city":"Waterbury",
    "sg:classifiers":[
        {
            "category":"Real Estate",
            "subcategory":"Real Estate Operator",
            "type":"Services"
        }
    ],
    "sg:phone":"+1 203 574 0363",
    "sg:postcode":"06704",
    "sg:province":"CT",
    "sg:tags":[
        "apartment"
    ],
    "wof:name":"Waterbury Omega",
    "wof:placetype":"venue"
},
  "geometry": {"coordinates":[-73.03807500000001,41.565749],"type":"Point"}
}