{
  "type": "Feature",
  "properties": {
    "addr:full":"490 Cherry Brook Rd Canton CT 06020",
    "addr:housenumber":"490",
    "addr:postcode":"06020",
    "addr:street":"Cherry Brook Rd",
    "iso:country":"US",
    "sg:address":"490 Cherry Brook Rd",
    "sg:city":"Canton",
    "sg:classifiers":[
        {
            "category":"Retail",
            "subcategory":"Animal Services",
            "type":"Services"
        }
    ],
    "sg:phone":"+1 860 693 4658",
    "sg:postcode":"06020",
    "sg:province":"CT",
    "wof:name":"Brook Cherry Kennels LLC",
    "wof:placetype":"venue"
},
  "geometry": {"coordinates":[-72.893829,41.887131],"type":"Point"}
}