{
  "type": "Feature",
  "properties": {
    "addr:full":"5 Goodrow St Norwalk CT 06855",
    "addr:housenumber":"5",
    "addr:postcode":"06855",
    "addr:street":"Goodrow St",
    "iso:country":"US",
    "sg:address":"5 Goodrow St",
    "sg:city":"Norwalk",
    "sg:classifiers":[
        {
            "category":"Building & Trades",
            "subcategory":"Cleaning & Sanitation",
            "type":"Services"
        }
    ],
    "sg:phone":"+1 203 227 7435",
    "sg:postcode":"06855",
    "sg:province":"CT",
    "sg:tags":[
        "house"
    ],
    "wof:name":"Ace Maintenance Co",
    "wof:placetype":"venue"
},
  "geometry": {"coordinates":[-73.405535,41.099518],"type":"Point"}
}