{
  "type": "Feature",
  "properties": {
    "iso:country":"US",
    "sg:address":"69 Clairmont Ave",
    "sg:city":"Waterbury",
    "sg:classifiers":[
        {
            "category":"Personal",
            "subcategory":"Beauty Salon",
            "type":"Services"
        }
    ],
    "sg:phone":"+1 203 753 7917",
    "sg:postcode":"06708",
    "sg:province":"CT",
    "sg:tags":[
        "shop"
    ],
    "wof:name":"Jo's Beauty Shoppe",
    "wof:placetype":"venue"
},
  "geometry": {"coordinates":[-73.050771,41.538815],"type":"Point"}
}