{
  "type": "Feature",
  "properties": {
    "addr:full":"51 Lexington St Bristol CT 06010",
    "addr:housenumber":"51",
    "addr:postcode":"06010",
    "addr:street":"Lexington St",
    "iso:country":"US",
    "sg:address":"51 Lexington St",
    "sg:city":"Bristol",
    "sg:classifiers":[
        {
            "category":"Building & Trades",
            "subcategory":"Plumbing",
            "type":"Services"
        }
    ],
    "sg:phone":"+1 860 314 0588",
    "sg:postcode":"06010",
    "sg:province":"CT",
    "sg:tags":[
        "plumbing",
        "air",
        "heating",
        "conditioning",
        "contractor"
    ],
    "wof:name":"Plumbing Htg By Don Twiggs LLC",
    "wof:placetype":"venue"
},
  "geometry": {"coordinates":[-72.940381,41.689228],"type":"Point"}
}