{
  "type": "Feature",
  "properties": {
    "addr:full":"137 Dow Rd Plainfield CT 06374",
    "addr:housenumber":"137",
    "addr:postcode":"06374",
    "addr:street":"Dow Rd",
    "iso:country":"US",
    "sg:address":"137 Dow Rd",
    "sg:city":"Plainfield",
    "sg:classifiers":[
        {
            "category":"Personal",
            "subcategory":"Beauty Salon",
            "type":"Services"
        }
    ],
    "sg:phone":"+1   ",
    "sg:postcode":"06374",
    "sg:province":"CT",
    "sg:tags":[
        "shop"
    ],
    "wof:name":"P JS Hair Salon",
    "wof:placetype":"venue"
},
  "geometry": {"coordinates":[-71.902931,41.669091],"type":"Point"}
}