{
  "type": "Feature",
  "properties": {
    "iso:country":"US",
    "sg:address":"101 Water St",
    "sg:city":"Norwich",
    "sg:classifiers":[
        {
            "category":"Government",
            "subcategory":"Office",
            "type":"Public Place"
        }
    ],
    "sg:phone":"+1 860 886 7118",
    "sg:postcode":"06360",
    "sg:province":"CT",
    "sg:tags":[
        "security",
        "social"
    ],
    "wof:name":"Social Security Administration",
    "wof:placetype":"venue"
},
  "geometry": {"coordinates":[-72.079398,41.524001],"type":"Point"}
}