{
  "type": "Feature",
  "properties": {
    "iso:country":"US",
    "sg:address":"19 Oakdale St",
    "sg:city":"Milford",
    "sg:classifiers":[
        {
            "category":"Professional",
            "type":"Services"
        }
    ],
    "sg:phone":"+1   ",
    "sg:postcode":"06460",
    "sg:province":"CT",
    "wof:name":"Lionworks Limited",
    "wof:placetype":"venue"
},
  "geometry": {"coordinates":[-73.09415199999999,41.188066],"type":"Point"}
}