{
  "type": "Feature",
  "properties": {
    "addr:full":"29 Drummer Ln Redding CT 06896",
    "addr:housenumber":"29",
    "addr:postcode":"06896",
    "addr:street":"Drummer Ln",
    "iso:country":"US",
    "sg:address":"29 Drummer Ln",
    "sg:city":"Redding",
    "sg:classifiers":[
        {
            "category":"Communications",
            "subcategory":"Film & Video Production",
            "type":"Services"
        }
    ],
    "sg:phone":"+1   ",
    "sg:postcode":"06896",
    "sg:province":"CT",
    "sg:tags":[
        "motion"
    ],
    "wof:name":"Pleasure Time Productions",
    "wof:placetype":"venue"
},
  "geometry": {"coordinates":[-73.39788799999999,41.317642],"type":"Point"}
}