{
  "type": "Feature",
  "properties": {
    "iso:country":"US",
    "sg:address":"7 Rayo Dr",
    "sg:city":"Shelton",
    "sg:classifiers":[
        {
            "category":"Real Estate",
            "subcategory":"Real Estate Agent",
            "type":"Services"
        }
    ],
    "sg:phone":"+1 203 395 8086",
    "sg:postcode":"06484",
    "sg:province":"CT",
    "wof:name":"Sound Partners Realty",
    "wof:placetype":"venue"
},
  "geometry": {"coordinates":[-73.190507,41.300135],"type":"Point"}
}