{
  "type": "Feature",
  "properties": {
    "iso:country":"US",
    "sg:address":"3 Hawthorn Ct",
    "sg:city":"Cromwell",
    "sg:classifiers":[
        {
            "category":"Professional",
            "subcategory":"Management & Consulting",
            "type":"Services"
        }
    ],
    "sg:phone":"+1   ",
    "sg:postcode":"06416",
    "sg:province":"CT",
    "wof:name":"Vista Marketing Resources",
    "wof:placetype":"venue"
},
  "geometry": {"coordinates":[-72.68329799999999,41.608051],"type":"Point"}
}