{
  "type": "Feature",
  "properties": {
    "iso:country":"US",
    "sg:address":"46 Main St",
    "sg:city":"Danbury",
    "sg:classifiers":[
        {
            "category":"Professional",
            "subcategory":"Lawyer & Legal Services",
            "type":"Services"
        }
    ],
    "sg:phone":"+1   ",
    "sg:postcode":"06810",
    "sg:province":"CT",
    "wof:name":"Phillip F Spillane",
    "wof:placetype":"venue"
},
  "geometry": {"coordinates":[-73.44525400000001,41.387021],"type":"Point"}
}