{
  "type": "Feature",
  "properties": {
    "iso:country":"US",
    "sg:address":"134 Main St S",
    "sg:city":"Southbury",
    "sg:classifiers":[
        {
            "category":"Freight",
            "type":"Transportation"
        }
    ],
    "sg:phone":"+1 203 267 5335",
    "sg:postcode":"06488",
    "sg:province":"CT",
    "sg:tags":[
        "arrangement"
    ],
    "wof:name":"Associated Dist Logistics",
    "wof:placetype":"venue"
},
  "geometry": {"coordinates":[-73.217889,41.476715],"type":"Point"}
}