{
  "type": "Feature",
  "properties": {
    "iso:country":"US",
    "sg:address":"60 Long Ridge Road",
    "sg:city":"Stamford",
    "sg:classifiers":[
        {
            "category":"Professional",
            "subcategory":"Computer Services",
            "type":"Services"
        }
    ],
    "sg:phone":"+1 203 487 7900",
    "sg:postcode":"06902",
    "sg:province":"CT",
    "sg:website":"http://www.basware.com/US/Pages/default.aspx",
    "wof:name":"Basware",
    "wof:placetype":"venue"
},
  "geometry": {"coordinates":[-73.550579,41.073078],"type":"Point"}
}