{
  "type": "Feature",
  "properties": {
    "iso:country":"US",
    "sg:address":"38 Union Ave",
    "sg:city":"Bridgeport",
    "sg:classifiers":[
        {
            "category":"Manufacturing",
            "subcategory":"Tools & Machinery",
            "type":"Manufacturing & Wholesale Goods"
        }
    ],
    "sg:phone":"+1 203 366 3874",
    "sg:postcode":"06607",
    "sg:province":"CT",
    "sg:tags":[
        "equipment",
        "electric"
    ],
    "wof:name":"Arc-Co Elec Boxes & Fittings",
    "wof:placetype":"venue"
},
  "geometry": {"coordinates":[-73.16299600000001,41.172826],"type":"Point"}
}