{
  "type": "Feature",
  "properties": {
    "iso:country":"US",
    "sg:address":"23 Fresh Meadow Rd",
    "sg:city":"West Haven",
    "sg:classifiers":[
        {
            "category":"Wholesale",
            "subcategory":"Durable Goods & Equipment",
            "type":"Manufacturing & Wholesale Goods"
        }
    ],
    "sg:phone":"+1 203 934 3444",
    "sg:postcode":"06516",
    "sg:province":"CT",
    "sg:tags":[
        "sawdust",
        "shaving"
    ],
    "wof:name":"A & D Pallet Co",
    "wof:placetype":"venue"
},
  "geometry": {"coordinates":[-72.979067,41.288522],"type":"Point"}
}