{
  "type": "Feature",
  "properties": {
    "iso:country":"US",
    "sg:address":"93 Mill Plain Rd",
    "sg:city":"Danbury",
    "sg:classifiers":[
        {
            "category":"Shopping",
            "subcategory":"Hobbies, Toys, & Games",
            "type":"Retail Goods"
        }
    ],
    "sg:phone":"+1 203 794 0577",
    "sg:postcode":"06811",
    "sg:province":"CT",
    "sg:website":"www.teachingplanet.com",
    "wof:name":"Creative Toymaker",
    "wof:placetype":"venue"
},
  "geometry": {"coordinates":[-73.510158,41.393751],"type":"Point"}
}