{
  "type": "Feature",
  "properties": {
    "iso:country":"US",
    "sg:address":"859 Westfield St",
    "sg:city":"Middletown",
    "sg:classifiers":[
        {
            "category":"Building & Trades",
            "subcategory":"Construction",
            "type":"Services"
        }
    ],
    "sg:phone":"+1 860 346 8480",
    "sg:postcode":"06457",
    "sg:province":"CT",
    "sg:tags":[
        "contractor"
    ],
    "wof:name":"Turner Michael J Enterprises",
    "wof:placetype":"venue"
},
  "geometry": {"coordinates":[-72.701218,41.563308],"type":"Point"}
}