{
  "type": "Feature",
  "properties": {
    "iso:country":"US",
    "sg:address":"48 Reilly Rd",
    "sg:city":"Easton",
    "sg:classifiers":[
        {
            "category":"Manufacturing",
            "subcategory":"Jewelry",
            "type":"Manufacturing & Wholesale Goods"
        }
    ],
    "sg:phone":"+1 203 445 1953",
    "sg:postcode":"06612",
    "sg:province":"CT",
    "wof:name":"Totally Out Of Hand",
    "wof:placetype":"venue"
},
  "geometry": {"coordinates":[-73.276956,41.230687],"type":"Point"}
}