{
  "type": "Feature",
  "properties": {
    "addr:full":"25 Silk St Norwalk CT 06850",
    "addr:housenumber":"25",
    "addr:postcode":"06850",
    "addr:street":"Silk St",
    "iso:country":"US",
    "sg:address":"25 Silk St",
    "sg:city":"Norwalk",
    "sg:classifiers":[
        {
            "category":"Professional",
            "subcategory":"Advertising",
            "type":"Services"
        }
    ],
    "sg:phone":"+1   ",
    "sg:postcode":"06850",
    "sg:province":"CT",
    "sg:tags":[
        "medium",
        "planning",
        "buying"
    ],
    "wof:name":"Direct Advantage",
    "wof:placetype":"venue"
},
  "geometry": {"coordinates":[-73.42947599999999,41.119436],"type":"Point"}
}