{
  "type": "Feature",
  "properties": {
    "addr:full":"2283 Main St Stratford CT 06615",
    "addr:housenumber":"2283",
    "addr:postcode":"06615",
    "addr:street":"Main St",
    "iso:country":"US",
    "sg:address":"2283 Main St",
    "sg:city":"Stratford",
    "sg:classifiers":[
        {
            "category":"Education",
            "subcategory":"Special Training",
            "type":"Public Place"
        }
    ],
    "sg:phone":"+1 203 268 6040",
    "sg:postcode":"06615",
    "sg:province":"CT",
    "sg:tags":[
        "instruction",
        "driving"
    ],
    "wof:name":"Gary Knepler Driving School",
    "wof:placetype":"venue"
},
  "geometry": {"coordinates":[-73.130375,41.192064],"type":"Point"}
}