{
  "type": "Feature",
  "properties": {
    "iso:country":"US",
    "sg:address":"1 Lafayette Pl",
    "sg:city":"Greenwich",
    "sg:classifiers":[
        {
            "category":"Professional",
            "subcategory":"Lawyer & Legal Services",
            "type":"Services"
        },
        {
            "category":"Government",
            "subcategory":"Court House",
            "type":"Public Place"
        }
    ],
    "sg:phone":"+1 203 622 0350",
    "sg:postcode":"06830",
    "sg:province":"CT",
    "sg:tags":[
        "attorney"
    ],
    "wof:name":"Barnett & Associates",
    "wof:placetype":"venue"
},
  "geometry": {"coordinates":[-73.62790099999999,41.032462],"type":"Point"}
}