{
  "type": "Feature",
  "properties": {
    "addr:full":"1 Schuyler Ave Stamford CT 06902",
    "addr:housenumber":"1",
    "addr:postcode":"06902",
    "addr:street":"Schuyler Ave",
    "iso:country":"US",
    "sg:address":"1 Schuyler Ave",
    "sg:city":"Stamford",
    "sg:classifiers":[
        {
            "category":"Education",
            "subcategory":"School",
            "type":"Public Place"
        }
    ],
    "sg:phone":"+1 203 323 4844",
    "sg:postcode":"06902",
    "sg:province":"CT",
    "wof:name":"Sacred Heart Elementary School",
    "wof:placetype":"venue"
},
  "geometry": {"coordinates":[-73.547455,41.054884],"type":"Point"}
}