{
  "type": "Feature",
  "properties": {
    "addr:full":"37 Thorson Rd Oxford CT 06478",
    "addr:housenumber":"37",
    "addr:postcode":"06478",
    "addr:street":"Thorson Rd",
    "iso:country":"US",
    "sg:address":"37 Thorson Rd",
    "sg:city":"Oxford",
    "sg:classifiers":[
        {
            "category":"Professional",
            "subcategory":"Management & Consulting",
            "type":"Services"
        }
    ],
    "sg:phone":"+1   ",
    "sg:postcode":"06478",
    "sg:province":"CT",
    "sg:tags":[
        "business"
    ],
    "wof:name":"Vital Connections Inc",
    "wof:placetype":"venue"
},
  "geometry": {"coordinates":[-73.17710099999999,41.439153],"type":"Point"}
}