{
  "type": "Feature",
  "properties": {
    "addr:full":"6 Fieldstone Dr Danbury CT 06811",
    "addr:housenumber":"6",
    "addr:postcode":"06811",
    "addr:street":"Fieldstone Dr",
    "iso:country":"US",
    "sg:address":"6 Fieldstone Dr",
    "sg:city":"Danbury",
    "sg:classifiers":[
        {
            "category":"Professional",
            "type":"Services"
        }
    ],
    "sg:phone":"+1 203 746 7017",
    "sg:postcode":"06811",
    "sg:province":"CT",
    "wof:name":"Allan Tarsi",
    "wof:placetype":"venue"
},
  "geometry": {"coordinates":[-73.47877200000001,41.434222],"type":"Point"}
}