{
  "type": "Feature",
  "properties": {
    "iso:country":"US",
    "sg:address":"366 Main St",
    "sg:city":"Danbury",
    "sg:classifiers":[
        {
            "category":"Real Estate",
            "subcategory":"Real Estate Agent",
            "type":"Services"
        }
    ],
    "sg:phone":"+1 203 778 6544",
    "sg:postcode":"06810",
    "sg:province":"CT",
    "wof:name":"Alam Enterprises",
    "wof:placetype":"venue"
},
  "geometry": {"coordinates":[-73.45869500000001,41.400927],"type":"Point"}
}