{
  "type": "Feature",
  "properties": {
    "addr:full":"600 Boston Post Rd Madison CT 06443",
    "addr:housenumber":"600",
    "addr:postcode":"06443",
    "addr:street":"Boston Post Rd",
    "iso:country":"US",
    "sg:address":"600 Boston Post Rd",
    "sg:city":"Madison",
    "sg:classifiers":[
        {
            "category":"Banks & Credit Unions",
            "subcategory":"Bank",
            "type":"Services"
        },
        {
            "category":"Banks & Credit Unions",
            "subcategory":"Financial Services",
            "type":"Services"
        }
    ],
    "sg:phone":"+1 203 245 2706",
    "sg:postcode":"06443",
    "sg:province":"CT",
    "sg:tags":[
        "commercial",
        "loan",
        "saving",
        "mortgage"
    ],
    "sg:website":"https://www.wachovia.com/?DCMP=KNL-CPS-DS-Directory-0703&HBX_PK=Banks&HBX_OU=71",
    "wof:name":"Wachovia Bank",
    "wof:placetype":"venue"
},
  "geometry": {"coordinates":[-72.598518,41.279301],"type":"Point"}
}