{
  "type": "Feature",
  "properties": {
    "iso:country":"US",
    "sg:address":"210 Municipal Rd",
    "sg:city":"Waterbury",
    "sg:classifiers":[
        {
            "category":"Government",
            "subcategory":"Office",
            "type":"Public Place"
        }
    ],
    "sg:phone":"+1 203 574 8265",
    "sg:postcode":"06708",
    "sg:province":"CT",
    "sg:tags":[
        "village"
    ],
    "wof:name":"Waterbury Sewage Treatment Ofc",
    "wof:placetype":"venue"
},
  "geometry": {"coordinates":[-73.04325300000001,41.523573],"type":"Point"}
}