{
  "type": "Feature",
  "properties": {
    "addr:full":"14 Wren Rd Suffield CT 06078",
    "addr:housenumber":"14",
    "addr:postcode":"06078",
    "addr:street":"Wren Rd",
    "iso:country":"US",
    "sg:address":"14 Wren Rd",
    "sg:city":"Suffield",
    "sg:classifiers":[
        {
            "category":"Shopping",
            "subcategory":"Beauty & Cosmetics",
            "type":"Retail Goods"
        }
    ],
    "sg:phone":"+1 860 668 0156",
    "sg:postcode":"06078",
    "sg:province":"CT",
    "sg:tags":[
        "perfume",
        "salons-equipment",
        "supply"
    ],
    "wof:name":"Timeless Beauty Permanent Cosm",
    "wof:placetype":"venue"
},
  "geometry": {"coordinates":[-72.63675600000001,41.996662],"type":"Point"}
}