{
  "type": "Feature",
  "properties": {
    "addr:full":"1 Riverside Rd Sandy Hook CT 06482",
    "addr:housenumber":"1",
    "addr:postcode":"06482",
    "addr:street":"Riverside Rd;Hook Ct",
    "iso:country":"US",
    "sg:address":"1 Riverside Rd",
    "sg:city":"Sandy Hook",
    "sg:classifiers":[
        {
            "category":"Professional",
            "subcategory":"Business Services",
            "type":"Services"
        }
    ],
    "sg:phone":"+1 203 364 1367",
    "sg:postcode":"06482",
    "sg:province":"CT",
    "sg:tags":[
        "packaging"
    ],
    "wof:name":"Georgia-Pacific Corp",
    "wof:placetype":"venue"
},
  "geometry": {"coordinates":[-73.278702,41.42257],"type":"Point"}
}