{
  "type": "Feature",
  "properties": {
    "addr:full":"1 Minerva Pl Old Greenwich CT 06870",
    "addr:housenumber":"1",
    "addr:postcode":"06870",
    "addr:street":"Minerva Pl",
    "iso:country":"US",
    "sg:address":"1 Minerva Pl",
    "sg:city":"Old Greenwich",
    "sg:classifiers":[
        {
            "category":"Banks & Credit Unions",
            "subcategory":"Investment Brokerage",
            "type":"Services"
        }
    ],
    "sg:phone":"+1 203 637 7802",
    "sg:postcode":"06870",
    "sg:province":"CT",
    "sg:tags":[
        "consultant",
        "financing"
    ],
    "wof:name":"Dragon Capital Management",
    "wof:placetype":"venue"
},
  "geometry": {"coordinates":[-73.560039,41.018744],"type":"Point"}
}