{
  "type": "Feature",
  "properties": {
    "addr:full":"20 Ox Yoke Dr Simsbury CT 06070",
    "addr:housenumber":"20",
    "addr:postcode":"06070",
    "addr:street":"Ox Yoke Dr",
    "iso:country":"US",
    "sg:address":"20 Ox Yoke Dr",
    "sg:city":"Simsbury",
    "sg:classifiers":[
        {
            "category":"Banks & Credit Unions",
            "subcategory":"Financial Services",
            "type":"Services"
        }
    ],
    "sg:phone":"+1 860 658 7150",
    "sg:postcode":"06070",
    "sg:province":"CT",
    "sg:tags":[
        "investor"
    ],
    "wof:name":"Grn Assoc LLC",
    "wof:placetype":"venue"
},
  "geometry": {"coordinates":[-72.808376,41.895839],"type":"Point"}
}