{
  "type": "Feature",
  "properties": {
    "addr:full":"46 Clinton Ave New Haven CT 06513",
    "addr:housenumber":"46",
    "addr:postcode":"06513",
    "addr:street":"Clinton Ave",
    "iso:country":"US",
    "sg:address":"46 Clinton Ave",
    "sg:city":"New Haven",
    "sg:classifiers":[
        {
            "category":"Building & Trades",
            "subcategory":"Construction",
            "type":"Services"
        }
    ],
    "sg:phone":"+1 203 752 9237",
    "sg:postcode":"06513",
    "sg:province":"CT",
    "sg:tags":[
        "painter"
    ],
    "sg:website":"www.kmorganassociates.com",
    "wof:name":"K Morgan Assoc LLC",
    "wof:placetype":"venue"
},
  "geometry": {"coordinates":[-72.891139,41.31164],"type":"Point"}
}