{
  "type": "Feature",
  "properties": {
    "iso:country":"US",
    "sg:address":"68 Webb St",
    "sg:city":"Windsor Locks",
    "sg:classifiers":[
        {
            "category":"Building & Trades",
            "subcategory":"Construction",
            "type":"Services"
        }
    ],
    "sg:phone":"+1 860 627 8893",
    "sg:postcode":"06096",
    "sg:province":"CT",
    "sg:tags":[
        "carpentry",
        "contractor"
    ],
    "wof:name":"Davco",
    "wof:placetype":"venue"
},
  "geometry": {"coordinates":[-72.633973,41.918808],"type":"Point"}
}