{
  "type": "Feature",
  "properties": {
    "addr:full":"92 Westland St Hartford CT 06120",
    "addr:housenumber":"92",
    "addr:postcode":"06120",
    "addr:street":"Westland St",
    "iso:country":"US",
    "sg:address":"92 Westland St",
    "sg:city":"Hartford",
    "sg:classifiers":[
        {
            "category":"Shopping",
            "subcategory":"Music",
            "type":"Retail Goods"
        }
    ],
    "sg:phone":"+1 860 241 0845",
    "sg:postcode":"06120",
    "sg:province":"CT",
    "wof:name":"Redeemed Records",
    "wof:placetype":"venue"
},
  "geometry": {"coordinates":[-72.676498,41.79021],"type":"Point"}
}