{
  "type": "Feature",
  "properties": {
    "addr:full":"182 Grassy Plain St Bethel CT 06801",
    "addr:housenumber":"182",
    "addr:postcode":"06801",
    "addr:street":"Grassy Plain St Bethel Ct",
    "iso:country":"US",
    "sg:address":"182 Grassy Plain St",
    "sg:city":"Bethel",
    "sg:classifiers":[
        {
            "category":"Professional",
            "subcategory":"Engineering",
            "type":"Services"
        }
    ],
    "sg:phone":"+1 203 798 7969",
    "sg:postcode":"06801",
    "sg:province":"CT",
    "sg:tags":[
        "engineer"
    ],
    "wof:name":"K Mark Davis PE",
    "wof:placetype":"venue"
},
  "geometry": {"coordinates":[-73.418719,41.357849],"type":"Point"}
}