{
  "type": "Feature",
  "properties": {
    "addr:full":"1809 Whitney Ave Hamden CT 06517",
    "addr:housenumber":"1809",
    "addr:postcode":"06517",
    "addr:street":"Whitney Ave",
    "iso:country":"US",
    "sg:address":"1809 Whitney Ave",
    "sg:city":"Hamden",
    "sg:classifiers":[
        {
            "category":"Organizations",
            "subcategory":"Religious Organization",
            "type":"Services"
        }
    ],
    "sg:phone":"+1 203 288 7748",
    "sg:postcode":"06517",
    "sg:province":"CT",
    "sg:tags":[
        "synagogue"
    ],
    "wof:name":"Temple Beth Sholom",
    "wof:placetype":"venue"
},
  "geometry": {"coordinates":[-72.908801,41.364166],"type":"Point"}
}