{
  "type": "Feature",
  "properties": {
    "addr:full":"520 Main St Cromwell CT 06416",
    "addr:housenumber":"520",
    "addr:postcode":"06416",
    "addr:street":"Main St;Ct",
    "iso:country":"US",
    "sg:address":"520 Main St",
    "sg:city":"Cromwell",
    "sg:classifiers":[
        {
            "category":"Retail",
            "subcategory":"Repair Shop",
            "type":"Services"
        }
    ],
    "sg:phone":"+1   ",
    "sg:postcode":"06416",
    "sg:province":"CT",
    "sg:tags":[
        "welding"
    ],
    "wof:name":"Jack & Son Welding Co Inc",
    "wof:placetype":"venue"
},
  "geometry": {"coordinates":[-72.653194,41.616119],"type":"Point"}
}