{
  "type": "Feature",
  "properties": {
    "iso:country":"US",
    "sg:address":"26 Strawberry Hill Ave",
    "sg:city":"Stamford",
    "sg:classifiers":[
        {
            "category":"Professional",
            "subcategory":"Printing & Photocopies",
            "type":"Services"
        }
    ],
    "sg:phone":"+1   ",
    "sg:postcode":"06902",
    "sg:province":"CT",
    "sg:tags":[
        "photocopying"
    ],
    "wof:name":"Docuserve LLC",
    "wof:placetype":"venue"
},
  "geometry": {"coordinates":[-73.533191,41.061565],"type":"Point"}
}