{
  "type": "Feature",
  "properties": {
    "iso:country":"US",
    "sg:address":"653 East St",
    "sg:city":"Middletown",
    "sg:classifiers":[
        {
            "category":"Government",
            "subcategory":"Office",
            "type":"Public Place"
        }
    ],
    "sg:phone":"+1 860 632 0377",
    "sg:postcode":"06457",
    "sg:province":"CT",
    "sg:tags":[
        "policy"
    ],
    "wof:name":"Westfield Fire Dist-Tax Coll",
    "wof:placetype":"venue"
},
  "geometry": {"coordinates":[-72.70214300000001,41.5812],"type":"Point"}
}