{
  "type": "Feature",
  "properties": {
    "iso:country":"US",
    "sg:address":"123 Court St",
    "sg:city":"New Haven",
    "sg:classifiers":[
        {
            "category":"Personal",
            "subcategory":"Beauty Salon",
            "type":"Services"
        }
    ],
    "sg:phone":"+1 203 772 2085",
    "sg:postcode":"06511",
    "sg:province":"CT",
    "wof:name":"Cryptonnite Beauty Salon",
    "wof:placetype":"venue"
},
  "geometry": {"coordinates":[-72.92277300000001,41.30616],"type":"Point"}
}