{
  "type": "Feature",
  "properties": {
    "iso:country":"US",
    "sg:address":"337 Jackson Ave",
    "sg:city":"Stratford",
    "sg:classifiers":[
        {
            "category":"Health Services",
            "subcategory":"Clinic",
            "type":"Services"
        }
    ],
    "sg:phone":"+1   ",
    "sg:postcode":"06615",
    "sg:province":"CT",
    "sg:tags":[
        "home",
        "care"
    ],
    "wof:name":"Passionate Care Services LLC",
    "wof:placetype":"venue"
},
  "geometry": {"coordinates":[-73.149844,41.18598],"type":"Point"}
}