{
  "type": "Feature",
  "properties": {
    "addr:full":"1013 Long Cove Rd Gales Ferry CT 06335",
    "addr:housenumber":"1013",
    "addr:postcode":"06335",
    "addr:street":"Long Cove Rd Gales Ferry Ct",
    "iso:country":"US",
    "sg:address":"1013 Long Cove Rd",
    "sg:city":"Gales Ferry",
    "sg:classifiers":[
        {
            "category":"Building & Trades",
            "subcategory":"Landscaping Services",
            "type":"Services"
        }
    ],
    "sg:phone":"+1 860 464 2032",
    "sg:postcode":"06335",
    "sg:province":"CT",
    "sg:tags":[
        "landscape"
    ],
    "wof:name":"Smith EJ Landscaping",
    "wof:placetype":"venue"
},
  "geometry": {"coordinates":[-72.07201999999999,41.407409],"type":"Point"}
}