{
  "type": "Feature",
  "properties": {
    "addr:full":"3573 Berlin Tpke Newington CT 06111",
    "addr:housenumber":"3573",
    "addr:postcode":"06111",
    "addr:street":"Berlin Tpke",
    "iso:country":"US",
    "sg:address":"3573 Berlin Tpke",
    "sg:city":"Newington",
    "sg:classifiers":[
        {
            "category":"Bars & Pubs",
            "subcategory":"Sports Bar",
            "type":"Food & Drink"
        },
        {
            "category":"Organizations",
            "subcategory":"Community Association",
            "type":"Services"
        }
    ],
    "sg:phone":"+1 860 666 6559",
    "sg:postcode":"06111",
    "sg:province":"CT",
    "sg:tags":[
        "club"
    ],
    "sg:website":"http://www.maguiressportsbar.com",
    "wof:name":"Maguires Sports Bar & Grill",
    "wof:placetype":"venue"
},
  "geometry": {"coordinates":[-72.728264,41.650906],"type":"Point"}
}