{
  "type": "Feature",
  "properties": {
    "iso:country":"US",
    "sg:address":"33 Church St",
    "sg:city":"East Hartford",
    "sg:classifiers":[
        {
            "category":"Organizations",
            "subcategory":"Religious Organization",
            "type":"Services"
        }
    ],
    "sg:phone":"+1   ",
    "sg:postcode":"06108",
    "sg:province":"CT",
    "wof:name":"Saint Rose Church",
    "wof:placetype":"venue"
},
  "geometry": {"coordinates":[-72.609205,41.778436],"type":"Point"}
}