{
  "type": "Feature",
  "properties": {
    "iso:country":"US",
    "sg:address":"132 Pepes Farm Rd",
    "sg:city":"Milford",
    "sg:classifiers":[
        {
            "category":"Freight",
            "type":"Transportation"
        }
    ],
    "sg:phone":"+1 203 874 1453",
    "sg:postcode":"06460",
    "sg:province":"CT",
    "sg:tags":[
        "warehouse"
    ],
    "wof:name":"GSR Warehouse",
    "wof:placetype":"venue"
},
  "geometry": {"coordinates":[-73.01525700000001,41.233718],"type":"Point"}
}