{
  "type": "Feature",
  "properties": {
    "iso:country":"US",
    "sg:address":"21 Valley St",
    "sg:city":"Willimantic",
    "sg:classifiers":[
        {
            "category":"Education",
            "subcategory":"Special Training",
            "type":"Public Place"
        }
    ],
    "sg:phone":"+1   ",
    "sg:postcode":"06226",
    "sg:province":"CT",
    "wof:name":"Eastconn Adult Learning",
    "wof:placetype":"venue"
},
  "geometry": {"coordinates":[-72.208755,41.712906],"type":"Point"}
}