{
  "type": "Feature",
  "properties": {
    "addr:full":"8 Rte 37 S Sherman CT 06784",
    "addr:housenumber":"8",
    "addr:postcode":"06784",
    "addr:street":"Rte 37 S Sherman Ct",
    "iso:country":"US",
    "sg:address":"8 Rte 37 S",
    "sg:city":"Sherman",
    "sg:classifiers":[
        {
            "category":"Government",
            "subcategory":"Office",
            "type":"Public Place"
        }
    ],
    "sg:phone":"+1 860 354 2414",
    "sg:postcode":"06784",
    "sg:province":"CT",
    "sg:tags":[
        "city",
        "resource",
        "human"
    ],
    "wof:name":"Sherman Committee On Aging",
    "wof:placetype":"venue"
},
  "geometry": {"coordinates":[-73.500156,41.572284],"type":"Point"}
}