{
  "type": "Feature",
  "properties": {
    "addr:full":"108 High St Manchester CT 06040",
    "addr:housenumber":"108",
    "addr:postcode":"06040",
    "addr:street":"High St",
    "iso:country":"US",
    "sg:address":"108 High St",
    "sg:city":"Manchester",
    "sg:classifiers":[
        {
            "category":"Professional",
            "type":"Services"
        }
    ],
    "sg:phone":"+1 860 647 9230",
    "sg:postcode":"06040",
    "sg:province":"CT",
    "wof:name":"Delois Art LLC",
    "wof:placetype":"venue"
},
  "geometry": {"coordinates":[-72.53429199999999,41.768761],"type":"Point"}
}