{
  "type": "Feature",
  "properties": {
    "iso:country":"US",
    "sg:address":"21 Four Mile River Rd",
    "sg:city":"Old Lyme",
    "sg:classifiers":[
        {
            "category":"Professional",
            "type":"Services"
        }
    ],
    "sg:phone":"+1 860 434 3619",
    "sg:postcode":"06371",
    "sg:province":"CT",
    "wof:name":"Dan Kensel",
    "wof:placetype":"venue"
},
  "geometry": {"coordinates":[-72.25644,41.313378],"type":"Point"}
}