{
  "type": "Feature",
  "properties": {
    "addr:full":"29 Argyle Ave Hartford CT 06107",
    "addr:housenumber":"29",
    "addr:postcode":"06107",
    "addr:street":"Argyle Ave;Ct",
    "iso:country":"US",
    "sg:address":"29 Argyle Ave",
    "sg:city":"Hartford",
    "sg:classifiers":[
        {
            "category":"Banks & Credit Unions",
            "subcategory":"Bank",
            "type":"Services"
        }
    ],
    "sg:phone":"+1 860 561 8801",
    "sg:postcode":"06107",
    "sg:province":"CT",
    "sg:tags":[
        "mortgage"
    ],
    "wof:name":"J & R Funding",
    "wof:placetype":"venue"
},
  "geometry": {"coordinates":[-72.74923200000001,41.763382],"type":"Point"}
}