{
  "type": "Feature",
  "properties": {
    "addr:full":"1934 Huntington Tpke Trumbull CT 06611",
    "addr:housenumber":"1934",
    "addr:postcode":"06611",
    "addr:street":"Huntington Tpke",
    "iso:country":"US",
    "sg:address":"1934 Huntington Tpke",
    "sg:city":"Trumbull",
    "sg:classifiers":[
        {
            "category":"Professional",
            "subcategory":"Lawyer & Legal Services",
            "type":"Services"
        }
    ],
    "sg:phone":"+1   ",
    "sg:postcode":"06611",
    "sg:province":"CT",
    "wof:name":"John Crozier Huntington",
    "wof:placetype":"venue"
},
  "geometry": {"coordinates":[-73.162198,41.2476],"type":"Point"}
}