{
  "type": "Feature",
  "properties": {
    "iso:country":"US",
    "sg:address":"333 Scott Swamp Rd",
    "sg:city":"Farmington",
    "sg:classifiers":[
        {
            "category":"Personal",
            "subcategory":"Massage",
            "type":"Services"
        }
    ],
    "sg:phone":"+1 860 678 1265",
    "sg:postcode":"06032",
    "sg:province":"CT",
    "wof:name":"Body Logic",
    "wof:placetype":"venue"
},
  "geometry": {"coordinates":[-72.885696,41.7038],"type":"Point"}
}