{
  "type": "Feature",
  "properties": {
    "addr:full":"1731 Berlin Tpke Wethersfield CT 06109",
    "addr:housenumber":"1731",
    "addr:postcode":"06109",
    "addr:street":"Berlin Tpke Wethersfield Ct",
    "iso:country":"US",
    "sg:address":"1731 Berlin Tpke",
    "sg:city":"Wethersfield",
    "sg:classifiers":[
        {
            "category":"Restaurant",
            "type":"Food & Drink"
        }
    ],
    "sg:menulink":"http://www.allmenus.com/ct/wethersfield/8655-hooters/menu/",
    "sg:phone":"+1 860 563 8083",
    "sg:postcode":"06109",
    "sg:province":"CT",
    "sg:tags":[
        "american",
        "wing"
    ],
    "wof:name":"Hooters",
    "wof:placetype":"venue"
},
  "geometry": {"coordinates":[-72.70160199999999,41.706358],"type":"Point"}
}