{
  "type": "Feature",
  "properties": {
    "addr:full":"613 Redding Rd Redding CT 06896",
    "addr:housenumber":"613",
    "addr:postcode":"06896",
    "addr:street":"Redding Rd",
    "iso:country":"US",
    "sg:address":"613 Redding Rd",
    "sg:city":"Redding",
    "sg:classifiers":[
        {
            "category":"Freight",
            "type":"Transportation"
        }
    ],
    "sg:phone":"+1 203 938 3179",
    "sg:postcode":"06896",
    "sg:province":"CT",
    "sg:tags":[
        "local",
        "without",
        "storage",
        "trucking"
    ],
    "wof:name":"Little York Trucking",
    "wof:placetype":"venue"
},
  "geometry": {"coordinates":[-73.401388,41.303238],"type":"Point"}
}