{
  "type": "Feature",
  "properties": {
    "addr:full":"502 W Thompson Rd Thompson CT 06277",
    "addr:housenumber":"502",
    "addr:postcode":"06277",
    "addr:street":"W Thompson Rd Thompson Ct",
    "iso:country":"US",
    "sg:address":"502 W Thompson Rd",
    "sg:city":"Thompson",
    "sg:classifiers":[
        {
            "category":"Professional",
            "subcategory":"Computer Services",
            "type":"Services"
        }
    ],
    "sg:phone":"+1   ",
    "sg:postcode":"06277",
    "sg:province":"CT",
    "wof:name":"Guile Technology",
    "wof:placetype":"venue"
},
  "geometry": {"coordinates":[-71.92681899999999,41.930105],"type":"Point"}
}