{
  "type": "Feature",
  "properties": {
    "iso:country":"US",
    "sg:address":"7 Brown Dr",
    "sg:city":"Andover",
    "sg:classifiers":[
        {
            "category":"Arts & Performance",
            "subcategory":"Theater",
            "type":"Entertainment"
        }
    ],
    "sg:phone":"+1   ",
    "sg:postcode":"06232",
    "sg:province":"CT",
    "sg:tags":[
        "group"
    ],
    "wof:name":"Slug Nickel Band",
    "wof:placetype":"venue"
},
  "geometry": {"coordinates":[-72.36248399999999,41.713415],"type":"Point"}
}