{
  "type": "Feature",
  "properties": {
    "iso:country":"US",
    "sg:address":"16 Maple Tree Rd",
    "sg:city":"Brookfield",
    "sg:classifiers":[
        {
            "category":"Building & Trades",
            "subcategory":"Construction",
            "type":"Services"
        }
    ],
    "sg:phone":"+1 203 775 5528",
    "sg:postcode":"06804",
    "sg:province":"CT",
    "sg:tags":[
        "excavation",
        "contractor"
    ],
    "wof:name":"Maple Valley Excavating LLC",
    "wof:placetype":"venue"
},
  "geometry": {"coordinates":[-73.36000300000001,41.473513],"type":"Point"}
}