{
  "type": "Feature",
  "properties": {
    "iso:country":"US",
    "sg:address":"9 Partridge Ln",
    "sg:city":"Clinton",
    "sg:classifiers":[
        {
            "category":"Professional",
            "subcategory":"Computer Services",
            "type":"Services"
        }
    ],
    "sg:phone":"+1   ",
    "sg:postcode":"06413",
    "sg:province":"CT",
    "sg:tags":[
        "system",
        "integration"
    ],
    "wof:name":"Customconnect LLC",
    "wof:placetype":"venue"
},
  "geometry": {"coordinates":[-72.513634,41.284545],"type":"Point"}
}