{
  "type": "Feature",
  "properties": {
    "iso:country":"US",
    "sg:address":"26 Barrett Hill Rd",
    "sg:city":"Brooklyn",
    "sg:classifiers":[
        {
            "category":"Utilities",
            "subcategory":"Telephone",
            "type":"Services"
        }
    ],
    "sg:phone":"+1 860 774 2607",
    "sg:postcode":"06234",
    "sg:province":"CT",
    "sg:tags":[
        "communications"
    ],
    "wof:name":"Morrone & Associates",
    "wof:placetype":"venue"
},
  "geometry": {"coordinates":[-71.941653,41.813525],"type":"Point"}
}