{
  "type": "Feature",
  "properties": {
    "addr:full":"955 Ferry Blvd Stratford CT 06614",
    "addr:housenumber":"955",
    "addr:postcode":"06614",
    "addr:street":"Ferry Blvd",
    "iso:country":"US",
    "sg:address":"955 Ferry Blvd",
    "sg:city":"Stratford",
    "sg:classifiers":[
        {
            "category":"Food & Beverages",
            "subcategory":"Liquor & Beverages",
            "type":"Retail Goods"
        }
    ],
    "sg:phone":"+1 203 380 1870",
    "sg:postcode":"06614",
    "sg:province":"CT",
    "sg:tags":[
        "alcoholic"
    ],
    "wof:name":"Yacht High Spirits",
    "wof:placetype":"venue"
},
  "geometry": {"coordinates":[-73.115084,41.199878],"type":"Point"}
}