{
  "type": "Feature",
  "properties": {
    "iso:country":"US",
    "sg:address":"40 River Walk Dr",
    "sg:city":"Weatogue",
    "sg:classifiers":[
        {
            "category":"Professional",
            "subcategory":"Business Services",
            "type":"Services"
        }
    ],
    "sg:phone":"+1   ",
    "sg:postcode":"06089",
    "sg:province":"CT",
    "wof:name":"Golf Promos",
    "wof:placetype":"venue"
},
  "geometry": {"coordinates":[-72.81161,41.841198],"type":"Point"}
}