{
  "type": "Feature",
  "properties": {
    "iso:country":"US",
    "sg:address":"165 Whisconier Rd",
    "sg:city":"Brookfield",
    "sg:classifiers":[
        {
            "category":"Museum",
            "type":"Entertainment"
        }
    ],
    "sg:phone":"+1 203 740 8140",
    "sg:postcode":"06804",
    "sg:province":"CT",
    "wof:name":"Brookfield Historial Society",
    "wof:placetype":"venue"
},
  "geometry": {"coordinates":[-73.38821299999999,41.466566],"type":"Point"}
}