{
  "type": "Feature",
  "properties": {
    "addr:full":"187 Willard St New Haven CT 06515",
    "addr:housenumber":"187",
    "addr:postcode":"06515",
    "addr:street":"Willard St",
    "iso:country":"US",
    "sg:address":"187 Willard St",
    "sg:city":"New Haven",
    "sg:classifiers":[
        {
            "category":"Professional",
            "subcategory":"Business Services",
            "type":"Services"
        }
    ],
    "sg:phone":"+1   ",
    "sg:postcode":"06515",
    "sg:province":"CT",
    "sg:tags":[
        "translation"
    ],
    "wof:name":"Rebecca Weiner",
    "wof:placetype":"venue"
},
  "geometry": {"coordinates":[-72.967114,41.325537],"type":"Point"}
}