{
  "type": "Feature",
  "properties": {
    "addr:full":"302 State St New London CT 06320",
    "addr:housenumber":"302",
    "addr:postcode":"06320",
    "addr:street":"State St;London Ct",
    "iso:country":"US",
    "sg:address":"302 State St",
    "sg:city":"New London",
    "sg:classifiers":[
        {
            "category":"Professional",
            "subcategory":"Lawyer & Legal Services",
            "type":"Services"
        }
    ],
    "sg:phone":"+1   ",
    "sg:postcode":"06320",
    "sg:province":"CT",
    "wof:name":"Synodi & Videll LLC",
    "wof:placetype":"venue"
},
  "geometry": {"coordinates":[-72.09957,41.355125],"type":"Point"}
}