{
  "type": "Feature",
  "properties": {
    "addr:full":"1 Honeycomb Ln North Haven CT 06473",
    "addr:housenumber":"1",
    "addr:postcode":"06473",
    "addr:street":"Honeycomb Ln;Haven",
    "iso:country":"US",
    "sg:address":"1 Honeycomb Ln",
    "sg:city":"North Haven",
    "sg:classifiers":[
        {
            "category":"Professional",
            "subcategory":"Management & Consulting",
            "type":"Services"
        }
    ],
    "sg:phone":"+1   ",
    "sg:postcode":"06473",
    "sg:province":"CT",
    "sg:tags":[
        "business"
    ],
    "wof:name":"Nocturnal Consulting LLC",
    "wof:placetype":"venue"
},
  "geometry": {"coordinates":[-72.864441,41.425311],"type":"Point"}
}