{
  "type": "Feature",
  "properties": {
    "iso:country":"US",
    "sg:address":"825 Park St",
    "sg:city":"Hartford",
    "sg:classifiers":[
        {
            "category":"Cinema",
            "subcategory":"Movie Rental",
            "type":"Entertainment"
        }
    ],
    "sg:phone":"+1 860 247 5103",
    "sg:postcode":"06106",
    "sg:province":"CT",
    "sg:tags":[
        "building",
        "operator",
        "video",
        "tape",
        "nonresidential"
    ],
    "wof:name":"Botanica Chango Assoc",
    "wof:placetype":"venue"
},
  "geometry": {"coordinates":[-72.691563,41.758068],"type":"Point"}
}