{
  "type": "Feature",
  "properties": {
    "iso:country":"US",
    "sg:address":"7 Milltown Rd",
    "sg:city":"New Fairfield",
    "sg:classifiers":[
        {
            "category":"Manufacturing",
            "subcategory":"Printing",
            "type":"Manufacturing & Wholesale Goods"
        }
    ],
    "sg:phone":"+1 203 746 8881",
    "sg:postcode":"06812",
    "sg:province":"CT",
    "sg:tags":[
        "lithographic",
        "commercial"
    ],
    "wof:name":"AG Assoc",
    "wof:placetype":"venue"
},
  "geometry": {"coordinates":[-73.52541600000001,41.446996],"type":"Point"}
}