{
  "type": "Feature",
  "properties": {
    "addr:full":"197 Liberty Sq Norwalk CT 06855",
    "addr:housenumber":"197",
    "addr:postcode":"06855",
    "addr:street":"Liberty Sq",
    "iso:country":"US",
    "sg:address":"197 Liberty Sq",
    "sg:city":"Norwalk",
    "sg:classifiers":[
        {
            "category":"Personal",
            "subcategory":"Beauty Salon",
            "type":"Services"
        }
    ],
    "sg:phone":"+1 203 857 4247",
    "sg:postcode":"06855",
    "sg:province":"CT",
    "wof:name":"Seaport Salon",
    "wof:placetype":"venue"
},
  "geometry": {"coordinates":[-73.41357600000001,41.099155],"type":"Point"}
}