{
  "type": "Feature",
  "properties": {
    "iso:country":"US",
    "sg:address":"53 Shadow Ridge Rd",
    "sg:city":"Stamford",
    "sg:classifiers":[
        {
            "category":"Building & Trades",
            "subcategory":"Plumbing",
            "type":"Services"
        }
    ],
    "sg:phone":"+1 203 322 5311",
    "sg:postcode":"06905",
    "sg:province":"CT",
    "sg:tags":[
        "plumbing",
        "heating",
        "contractor"
    ],
    "wof:name":"James E Hogan",
    "wof:placetype":"venue"
},
  "geometry": {"coordinates":[-73.550721,41.10328],"type":"Point"}
}