{
  "type": "Feature",
  "properties": {
    "iso:country":"US",
    "sg:address":"16 Norton St",
    "sg:city":"New Haven",
    "sg:classifiers":[
        {
            "category":"Restaurant",
            "type":"Food & Drink"
        }
    ],
    "sg:phone":"+1 203 562 3701",
    "sg:postcode":"06511",
    "sg:province":"CT",
    "sg:tags":[
        "eating"
    ],
    "wof:name":"Mother's Homestyle Kitchen",
    "wof:placetype":"venue"
},
  "geometry": {"coordinates":[-72.94932300000001,41.310945],"type":"Point"}
}