{
  "type": "Feature",
  "properties": {
    "addr:full":"48 Paula Ln Waterford CT 06385",
    "addr:housenumber":"48",
    "addr:postcode":"06385",
    "addr:street":"Paula Ln",
    "iso:country":"US",
    "sg:address":"48 Paula Ln",
    "sg:city":"Waterford",
    "sg:classifiers":[
        {
            "category":"Professional",
            "subcategory":"Accounting & Tax Preparation",
            "type":"Services"
        }
    ],
    "sg:phone":"+1   ",
    "sg:postcode":"06385",
    "sg:province":"CT",
    "sg:tags":[
        "return"
    ],
    "wof:name":"National Assoc Tax Reporting",
    "wof:placetype":"venue"
},
  "geometry": {"coordinates":[-72.17288600000001,41.347367],"type":"Point"}
}