{
  "type": "Feature",
  "properties": {
    "iso:country":"US",
    "sg:address":"21 Crabapple Rd",
    "sg:city":"Windsor",
    "sg:classifiers":[
        {
            "category":"Building & Trades",
            "subcategory":"Landscaping Services",
            "type":"Services"
        }
    ],
    "sg:phone":"+1 860 688 3371",
    "sg:postcode":"06095",
    "sg:province":"CT",
    "wof:name":"Philip Thulen 3",
    "wof:placetype":"venue"
},
  "geometry": {"coordinates":[-72.672473,41.877312],"type":"Point"}
}