{
  "type": "Feature",
  "properties": {
    "iso:country":"US",
    "sg:address":"777 Federal Rd",
    "sg:city":"Brookfield",
    "sg:classifiers":[
        {
            "category":"Recreation",
            "type":"Entertainment"
        },
        {
            "category":"Sports & Exercise",
            "subcategory":"Gym",
            "type":"Entertainment"
        }
    ],
    "sg:phone":"+1 203 775 6220",
    "sg:postcode":"06804",
    "sg:province":"CT",
    "sg:tags":[
        "club",
        "health",
        "studio",
        "gymnasium"
    ],
    "wof:name":"Yoga Space",
    "wof:placetype":"venue"
},
  "geometry": {"coordinates":[-73.408958,41.480123],"type":"Point"}
}