{
  "type": "Feature",
  "properties": {
    "addr:full":"75 Russell St Jewett City CT 06351",
    "addr:housenumber":"75",
    "addr:postcode":"06351",
    "addr:street":"Russell St Jewett City Ct",
    "iso:country":"US",
    "sg:address":"75 Russell St",
    "sg:city":"Jewett City",
    "sg:classifiers":[
        {
            "category":"Building & Trades",
            "subcategory":"Plumbing",
            "type":"Services"
        }
    ],
    "sg:phone":"+1 860 376 1166",
    "sg:postcode":"06351",
    "sg:province":"CT",
    "sg:tags":[
        "contractor"
    ],
    "wof:name":"Delta Mechanical",
    "wof:placetype":"venue"
},
  "geometry": {"coordinates":[-71.973169,41.613361],"type":"Point"}
}