{
  "type": "Feature",
  "properties": {
    "addr:full":"94 Painter Ridge Rd Washington CT 06793",
    "addr:housenumber":"94",
    "addr:postcode":"06793",
    "addr:street":"Painter Ridge Rd",
    "iso:country":"US",
    "sg:address":"94 Painter Ridge Rd",
    "sg:city":"Washington",
    "sg:classifiers":[
        {
            "category":"Farming",
            "subcategory":"Nursery",
            "type":"Manufacturing & Wholesale Goods"
        }
    ],
    "sg:phone":"+1 860 868 2743",
    "sg:postcode":"06793",
    "sg:province":"CT",
    "sg:tags":[
        "ornamental"
    ],
    "wof:name":"Painter Ridge Farm",
    "wof:placetype":"venue"
},
  "geometry": {"coordinates":[-73.295446,41.611154],"type":"Point"}
}