{
  "type": "Feature",
  "properties": {
    "iso:country":"US",
    "sg:address":"30 Goff Brook Cir",
    "sg:city":"Wethersfield",
    "sg:classifiers":[
        {
            "category":"Building & Trades",
            "subcategory":"Electrical",
            "type":"Services"
        }
    ],
    "sg:phone":"+1 860 563 9205",
    "sg:postcode":"06109",
    "sg:province":"CT",
    "sg:tags":[
        "electrical",
        "contractor"
    ],
    "wof:name":"Albert J Fedash",
    "wof:placetype":"venue"
},
  "geometry": {"coordinates":[-72.68471700000001,41.673567],"type":"Point"}
}