{
  "type": "Feature",
  "properties": {
    "addr:full":"779 Prospect Ave Hartford CT 06105",
    "addr:housenumber":"779",
    "addr:postcode":"06105",
    "addr:street":"Prospect Ave;Ct",
    "iso:country":"US",
    "sg:address":"779 Prospect Ave",
    "sg:city":"Hartford",
    "sg:classifiers":[
        {
            "category":"Professional",
            "subcategory":"Management & Consulting",
            "type":"Services"
        }
    ],
    "sg:phone":"+1   ",
    "sg:postcode":"06105",
    "sg:province":"CT",
    "wof:name":"RLM Healthcare Consulting LLC",
    "wof:placetype":"venue"
},
  "geometry": {"coordinates":[-72.714286,41.776454],"type":"Point"}
}