{
  "type": "Feature",
  "properties": {
    "iso:country":"US",
    "sg:address":"64 Blakeslee Ave",
    "sg:city":"North Haven",
    "sg:classifiers":[
        {
            "category":"Wholesale",
            "subcategory":"Durable Goods & Equipment",
            "type":"Manufacturing & Wholesale Goods"
        }
    ],
    "sg:phone":"+1 203 239 3597",
    "sg:postcode":"06473",
    "sg:province":"CT",
    "sg:tags":[
        "importer"
    ],
    "sg:website":"www.alliedinternationalinc.com",
    "wof:name":"Allied International Corp",
    "wof:placetype":"venue"
},
  "geometry": {"coordinates":[-72.848052,41.395165],"type":"Point"}
}