{
  "type": "Feature",
  "properties": {
    "addr:full":"1902 N Main St Waterbury CT 06704",
    "addr:housenumber":"1902",
    "addr:postcode":"06704",
    "addr:street":"N Main St",
    "iso:country":"US",
    "sg:address":"1902 N Main St",
    "sg:city":"Waterbury",
    "sg:classifiers":[
        {
            "category":"Food & Beverages",
            "subcategory":"Groceries & Convenience Stores",
            "type":"Retail Goods"
        }
    ],
    "sg:phone":"+1 203 597 8009",
    "sg:postcode":"06704",
    "sg:province":"CT",
    "wof:name":"Coffee & Smoke Convenience LLC",
    "wof:placetype":"venue"
},
  "geometry": {"coordinates":[-73.026286,41.576655],"type":"Point"}
}