{
  "type": "Feature",
  "properties": {
    "addr:full":"1755 Highland Ave Cheshire CT 06410",
    "addr:housenumber":"1755",
    "addr:postcode":"06410",
    "addr:street":"Highland Ave",
    "iso:country":"US",
    "sg:address":"1755 Highland Ave",
    "sg:city":"Cheshire",
    "sg:classifiers":[
        {
            "category":"Manufacturing",
            "subcategory":"Electronics",
            "type":"Manufacturing & Wholesale Goods"
        }
    ],
    "sg:phone":"+1 203 272 2291",
    "sg:postcode":"06410",
    "sg:province":"CT",
    "sg:tags":[
        "telephone",
        "apparatus",
        "telegraph"
    ],
    "sg:website":"www.nutmegutility.com",
    "wof:name":"Nutmeg Utility Products Inc",
    "wof:placetype":"venue"
},
  "geometry": {"coordinates":[-72.891364,41.549662],"type":"Point"}
}