{
  "type": "Feature",
  "properties": {
    "iso:country":"US",
    "sg:address":"2268 Main St",
    "sg:city":"Stratford",
    "sg:classifiers":[
        {
            "category":"Professional",
            "subcategory":"Lawyer & Legal Services",
            "type":"Services"
        }
    ],
    "sg:phone":"+1   ",
    "sg:postcode":"06615",
    "sg:province":"CT",
    "wof:name":"Little Mrgret A Attrney At Law",
    "wof:placetype":"venue"
},
  "geometry": {"coordinates":[-73.130253,41.191701],"type":"Point"}
}