{
  "type": "Feature",
  "properties": {
    "iso:country":"US",
    "sg:address":"168 Homer St",
    "sg:city":"Waterbury",
    "sg:classifiers":[
        {
            "category":"Retail",
            "subcategory":"Auto Repair",
            "type":"Services"
        }
    ],
    "sg:phone":"+1   ",
    "sg:postcode":"06704",
    "sg:province":"CT",
    "sg:tags":[
        "transmission",
        "automotive",
        "shop"
    ],
    "wof:name":"All-Tech Transm & Gen RPS",
    "wof:placetype":"venue"
},
  "geometry": {"coordinates":[-73.044839,41.585604],"type":"Point"}
}