{
  "type": "Feature",
  "properties": {
    "iso:country":"US",
    "sg:address":"4 Hale Dr",
    "sg:city":"Ansonia",
    "sg:classifiers":[
        {
            "category":"Building & Trades",
            "subcategory":"Landscaping Services",
            "type":"Services"
        }
    ],
    "sg:phone":"+1 203 735 8986",
    "sg:postcode":"06401",
    "sg:province":"CT",
    "sg:tags":[
        "landscape"
    ],
    "wof:name":"A & A Lawn Service",
    "wof:placetype":"venue"
},
  "geometry": {"coordinates":[-73.049334,41.327333],"type":"Point"}
}