{
  "type": "Feature",
  "properties": {
    "addr:full":"1 Windsor Rd Shelton CT 06484",
    "addr:housenumber":"1",
    "addr:postcode":"06484",
    "addr:street":"Windsor Rd",
    "iso:country":"US",
    "sg:address":"1 Windsor Rd",
    "sg:city":"Shelton",
    "sg:classifiers":[
        {
            "category":"Building & Trades",
            "subcategory":"Electrical",
            "type":"Services"
        }
    ],
    "sg:phone":"+1 203 929 7137",
    "sg:postcode":"06484",
    "sg:province":"CT",
    "sg:tags":[
        "electric",
        "contractor"
    ],
    "wof:name":"Borona Electric",
    "wof:placetype":"venue"
},
  "geometry": {"coordinates":[-73.173475,41.297875],"type":"Point"}
}