{
  "type": "Feature",
  "properties": {
    "iso:country":"US",
    "sg:address":"708 Southington Rd",
    "sg:city":"Berlin",
    "sg:classifiers":[
        {
            "category":"Real Estate",
            "subcategory":"Developer",
            "type":"Services"
        }
    ],
    "sg:phone":"+1 860 828 4274",
    "sg:postcode":"06037",
    "sg:province":"CT",
    "sg:tags":[
        "cemetery"
    ],
    "wof:name":"South Burying Ground Assn",
    "wof:placetype":"venue"
},
  "geometry": {"coordinates":[-72.823831,41.597255],"type":"Point"}
}