{
  "type": "Feature",
  "properties": {
    "iso:country":"US",
    "sg:address":"102 Wall St",
    "sg:city":"Madison",
    "sg:classifiers":[
        {
            "category":"Personal",
            "subcategory":"Beauty Salon",
            "type":"Services"
        }
    ],
    "sg:phone":"+1 203 245 7196",
    "sg:postcode":"06443",
    "sg:province":"CT",
    "wof:name":"Hair We Are",
    "wof:placetype":"venue"
},
  "geometry": {"coordinates":[-72.593277,41.283297],"type":"Point"}
}