{
  "type": "Feature",
  "properties": {
    "addr:full":"2800 Main St Glastonbury CT 06033",
    "addr:housenumber":"2800",
    "addr:postcode":"06033",
    "addr:street":"Main St",
    "iso:country":"US",
    "sg:address":"2800 Main St",
    "sg:city":"Glastonbury",
    "sg:classifiers":[
        {
            "category":"Insurance",
            "subcategory":"Insurance Agent",
            "type":"Services"
        }
    ],
    "sg:phone":"+1 860 633 5261",
    "sg:postcode":"06033",
    "sg:province":"CT",
    "sg:tags":[
        "agency"
    ],
    "wof:name":"Nickel Insurance Associates",
    "wof:placetype":"venue"
},
  "geometry": {"coordinates":[-72.613292,41.718398],"type":"Point"}
}