{
  "type": "Feature",
  "properties": {
    "addr:full":"874 State St New Haven CT 06511",
    "addr:housenumber":"874",
    "addr:postcode":"06511",
    "addr:street":"State St",
    "iso:country":"US",
    "sg:address":"874 State St",
    "sg:city":"New Haven",
    "sg:classifiers":[
        {
            "category":"Restaurant",
            "type":"Food & Drink"
        }
    ],
    "sg:menulink":"http://www.allmenus.com/ct/new-haven/48313-moderns/menu/",
    "sg:phone":"+1 203 776 5306",
    "sg:postcode":"06511",
    "sg:province":"CT",
    "sg:tags":[
        "american",
        "pizza"
    ],
    "wof:name":"Modern's",
    "wof:placetype":"venue"
},
  "geometry": {"coordinates":[-72.91273200000001,41.313756],"type":"Point"}
}