{
  "type": "Feature",
  "properties": {
    "iso:country":"US",
    "sg:address":"6 Academy St",
    "sg:city":"Danielson",
    "sg:classifiers":[
        {
            "category":"Place Of Worship",
            "subcategory":"Church",
            "type":"Public Place"
        },
        {
            "category":"Place Of Worship",
            "type":"Public Place"
        }
    ],
    "sg:phone":"+1 860 774 3564",
    "sg:postcode":"06239",
    "sg:province":"CT",
    "sg:tags":[
        "churches-pentecostal-independent",
        "churches-pentecostal"
    ],
    "wof:name":"First Apostolic Church of Danielson",
    "wof:placetype":"venue"
},
  "geometry": {"coordinates":[-71.88360400000001,41.806194],"type":"Point"}
}