{
  "type": "Feature",
  "properties": {
    "addr:full":"10 Senkow Dr Quaker Hill CT 06375",
    "addr:housenumber":"10",
    "addr:postcode":"06375",
    "addr:street":"Senkow Dr Quaker Hill Ct",
    "iso:country":"US",
    "sg:address":"10 Senkow Dr",
    "sg:city":"Quaker Hill",
    "sg:classifiers":[
        {
            "category":"Retail",
            "subcategory":"Laundry & Dry Cleaning",
            "type":"Services"
        }
    ],
    "sg:phone":"+1   ",
    "sg:postcode":"06375",
    "sg:province":"CT",
    "wof:name":"Sew What",
    "wof:placetype":"venue"
},
  "geometry": {"coordinates":[-72.105706,41.388909],"type":"Point"}
}