{
  "type": "Feature",
  "properties": {
    "iso:country":"US",
    "sg:address":"104 Dann Dr",
    "sg:city":"Stamford",
    "sg:classifiers":[
        {
            "category":"Professional",
            "subcategory":"Lawyer & Legal Services",
            "type":"Services"
        }
    ],
    "sg:phone":"+1   ",
    "sg:postcode":"06905",
    "sg:province":"CT",
    "wof:name":"Terry Hazen",
    "wof:placetype":"venue"
},
  "geometry": {"coordinates":[-73.54316,41.082893],"type":"Point"}
}