{
  "type": "Feature",
  "properties": {
    "iso:country":"US",
    "sg:address":"190 Main St",
    "sg:city":"Southington",
    "sg:classifiers":[
        {
            "category":"Personal",
            "subcategory":"Beauty Salon",
            "type":"Services"
        }
    ],
    "sg:phone":"+1   ",
    "sg:postcode":"06489",
    "sg:province":"CT",
    "sg:tags":[
        "shop"
    ],
    "wof:name":"Jacquelines Nail Boutique",
    "wof:placetype":"venue"
},
  "geometry": {"coordinates":[-72.87818799999999,41.60039],"type":"Point"}
}