{
  "type": "Feature",
  "properties": {
    "addr:full":"127 E High St East Hampton CT 06424",
    "addr:housenumber":"127",
    "addr:postcode":"06424",
    "addr:street":"E High St East Hampton Ct",
    "iso:country":"US",
    "sg:address":"127 E High St",
    "sg:city":"East Hampton",
    "sg:classifiers":[
        {
            "category":"Personal",
            "subcategory":"Beauty Salon",
            "type":"Services"
        }
    ],
    "sg:phone":"+1   ",
    "sg:postcode":"06424",
    "sg:province":"CT",
    "sg:tags":[
        "shop"
    ],
    "wof:name":"Hairitage",
    "wof:placetype":"venue"
},
  "geometry": {"coordinates":[-72.490374,41.593181],"type":"Point"}
}