{
  "type": "Feature",
  "properties": {
    "iso:country":"US",
    "sg:address":"9 Waterhorse Brook Dr",
    "sg:city":"Bethel",
    "sg:classifiers":[
        {
            "category":"Professional",
            "subcategory":"Management & Consulting",
            "type":"Services"
        }
    ],
    "sg:phone":"+1   ",
    "sg:postcode":"06801",
    "sg:province":"CT",
    "wof:name":"Bulldog Associates LLC",
    "wof:placetype":"venue"
},
  "geometry": {"coordinates":[-73.40226,41.369683],"type":"Point"}
}