{
  "type": "Feature",
  "properties": {
    "iso:country":"US",
    "sg:address":"13 Marian Rd",
    "sg:city":"Branford",
    "sg:classifiers":[
        {
            "category":"Building & Trades",
            "subcategory":"Landscaping Services",
            "type":"Services"
        }
    ],
    "sg:phone":"+1 203 483 5920",
    "sg:postcode":"06405",
    "sg:province":"CT",
    "wof:name":"Dunn Landscape Construction LL",
    "wof:placetype":"venue"
},
  "geometry": {"coordinates":[-72.83376199999999,41.27236],"type":"Point"}
}