{
  "type": "Feature",
  "properties": {
    "addr:full":"157 Main St Danbury CT 06810",
    "addr:housenumber":"157",
    "addr:postcode":"06810",
    "addr:street":"Main St",
    "iso:country":"US",
    "sg:address":"157 Main St",
    "sg:city":"Danbury",
    "sg:classifiers":[
        {
            "category":"Professional",
            "subcategory":"Accounting & Tax Preparation",
            "type":"Services"
        }
    ],
    "sg:phone":"+1 203 207 3245",
    "sg:postcode":"06810",
    "sg:province":"CT",
    "sg:tags":[
        "return",
        "filing"
    ],
    "wof:name":"H & R Block Tax Svc",
    "wof:placetype":"venue"
},
  "geometry": {"coordinates":[-73.45104000000001,41.393437],"type":"Point"}
}