{
  "type": "Feature",
  "properties": {
    "addr:full":"3 Brianwood Ln Granby CT 06035",
    "addr:housenumber":"3",
    "addr:postcode":"06035",
    "addr:street":"Brianwood Ln",
    "iso:country":"US",
    "sg:address":"3 Brianwood Ln",
    "sg:city":"Granby",
    "sg:classifiers":[
        {
            "category":"Professional",
            "subcategory":"Business Services",
            "type":"Services"
        }
    ],
    "sg:phone":"+1   ",
    "sg:postcode":"06035",
    "sg:province":"CT",
    "wof:name":"Tims Automotive",
    "wof:placetype":"venue"
},
  "geometry": {"coordinates":[-72.803663,41.919039],"type":"Point"}
}