{
  "type": "Feature",
  "properties": {
    "iso:country":"US",
    "sg:address":"31 Gulfview Ct",
    "sg:city":"Milford",
    "sg:classifiers":[
        {
            "category":"Professional",
            "subcategory":"Management & Consulting",
            "type":"Services"
        }
    ],
    "sg:phone":"+1   ",
    "sg:postcode":"06460",
    "sg:province":"CT",
    "wof:name":"Ken Kayes",
    "wof:placetype":"venue"
},
  "geometry": {"coordinates":[-73.04100200000001,41.211821],"type":"Point"}
}