{
  "type": "Feature",
  "properties": {
    "addr:full":"67 Posa Dr Bristol CT 06010",
    "addr:housenumber":"67",
    "addr:postcode":"06010",
    "addr:street":"Posa Dr Bristol Ct",
    "iso:country":"US",
    "sg:address":"67 Posa Dr",
    "sg:city":"Bristol",
    "sg:classifiers":[
        {
            "category":"Professional",
            "subcategory":"Computer Services",
            "type":"Services"
        }
    ],
    "sg:phone":"+1   ",
    "sg:postcode":"06010",
    "sg:province":"CT",
    "sg:tags":[
        "prepackaged",
        "software"
    ],
    "wof:name":"Langlais Computer Cons LLC",
    "wof:placetype":"venue"
},
  "geometry": {"coordinates":[-72.91009699999999,41.680923],"type":"Point"}
}