{
  "type": "Feature",
  "properties": {
    "iso:country":"US",
    "sg:address":"142 Churchill Dr",
    "sg:city":"Newington",
    "sg:classifiers":[
        {
            "category":"Professional",
            "subcategory":"Management & Consulting",
            "type":"Services"
        }
    ],
    "sg:phone":"+1   ",
    "sg:postcode":"06111",
    "sg:province":"CT",
    "sg:tags":[
        "engineering",
        "public",
        "relations"
    ],
    "wof:name":"Central Promotion Resources",
    "wof:placetype":"venue"
},
  "geometry": {"coordinates":[-72.71781300000001,41.676968],"type":"Point"}
}