{
  "type": "Feature",
  "properties": {
    "addr:full":"180 Church St Naugatuck CT 06770",
    "addr:housenumber":"180",
    "addr:postcode":"06770",
    "addr:street":"Church St Naugatuck Ct",
    "iso:country":"US",
    "sg:address":"180 Church St",
    "sg:city":"Naugatuck",
    "sg:classifiers":[
        {
            "category":"Professional",
            "type":"Services"
        }
    ],
    "sg:phone":"+1 203 729 3100",
    "sg:postcode":"06770",
    "sg:province":"CT",
    "wof:name":"North American Marching",
    "wof:placetype":"venue"
},
  "geometry": {"coordinates":[-73.05553999999999,41.490039],"type":"Point"}
}