{
  "type": "Feature",
  "properties": {
    "addr:full":"675 Nichols Ave Stratford CT 06614",
    "addr:housenumber":"675",
    "addr:postcode":"06614",
    "addr:street":"Nichols Ave",
    "iso:country":"US",
    "sg:address":"675 Nichols Ave",
    "sg:city":"Stratford",
    "sg:classifiers":[
        {
            "category":"Professional",
            "subcategory":"Business Services",
            "type":"Services"
        }
    ],
    "sg:phone":"+1   ",
    "sg:postcode":"06614",
    "sg:province":"CT",
    "wof:name":"Rkb Assoc",
    "wof:placetype":"venue"
},
  "geometry": {"coordinates":[-73.142481,41.20534],"type":"Point"}
}