{
  "type": "Feature",
  "properties": {
    "iso:country":"US",
    "sg:address":"688 Bridgeport Ave",
    "sg:city":"Milford",
    "sg:classifiers":[
        {
            "category":"Retail",
            "subcategory":"Auto Repair",
            "type":"Services"
        }
    ],
    "sg:phone":"+1   ",
    "sg:postcode":"06460",
    "sg:province":"CT",
    "sg:tags":[
        "automotive"
    ],
    "wof:name":"F & S Auto Detailing",
    "wof:placetype":"venue"
},
  "geometry": {"coordinates":[-73.082835,41.209925],"type":"Point"}
}