{
  "type": "Feature",
  "properties": {
    "iso:country":"US",
    "sg:address":"97 Five Field Rd",
    "sg:city":"Madison",
    "sg:classifiers":[
        {
            "category":"Professional",
            "type":"Services"
        }
    ],
    "sg:phone":"+1 203 245 8933",
    "sg:postcode":"06443",
    "sg:province":"CT",
    "wof:name":"Air Alpha America Inc",
    "wof:placetype":"venue"
},
  "geometry": {"coordinates":[-72.576359,41.300099],"type":"Point"}
}