{
  "type": "Feature",
  "properties": {
    "iso:country":"US",
    "sg:address":"95 Brewster Rd",
    "sg:city":"Jewett City",
    "sg:classifiers":[
        {
            "category":"Building & Trades",
            "subcategory":"Landscaping Services",
            "type":"Services"
        }
    ],
    "sg:phone":"+1 860 376 0060",
    "sg:postcode":"06351",
    "sg:province":"CT",
    "sg:tags":[
        "landscape"
    ],
    "wof:name":"Deguire Daniel J III",
    "wof:placetype":"venue"
},
  "geometry": {"coordinates":[-71.964589,41.578678],"type":"Point"}
}