{
  "type": "Feature",
  "properties": {
    "iso:country":"US",
    "sg:address":"1330 E Putnam Ave",
    "sg:city":"Old Greenwich",
    "sg:classifiers":[
        {
            "category":"Retail",
            "subcategory":"Auto Repair",
            "type":"Services"
        }
    ],
    "sg:phone":"+1 203 637 1711",
    "sg:postcode":"06870",
    "sg:province":"CT",
    "sg:tags":[
        "repairing",
        "automobile"
    ],
    "wof:name":"Karl Automotive Svc-Greenwich",
    "wof:placetype":"venue"
},
  "geometry": {"coordinates":[-73.574538,41.043235],"type":"Point"}
}