{
  "type": "Feature",
  "properties": {
    "addr:full":"113 Waterbury Rd Prospect CT 06712",
    "addr:housenumber":"113",
    "addr:postcode":"06712",
    "addr:street":"Waterbury Rd",
    "iso:country":"US",
    "sg:address":"113 Waterbury Rd",
    "sg:city":"Prospect",
    "sg:classifiers":[
        {
            "category":"Health Services",
            "subcategory":"Health Practitioner",
            "type":"Services"
        }
    ],
    "sg:phone":"+1 203 758 0301",
    "sg:postcode":"06712",
    "sg:province":"CT",
    "sg:tags":[
        "nurse",
        "registry"
    ],
    "wof:name":"T Dyer",
    "wof:placetype":"venue"
},
  "geometry": {"coordinates":[-72.993165,41.521246],"type":"Point"}
}