{
  "type": "Feature",
  "properties": {
    "addr:full":"18 Arcadia Rd Old Greenwich CT 06870",
    "addr:housenumber":"18",
    "addr:postcode":"06870",
    "addr:street":"Arcadia Rd;Greenwich",
    "iso:country":"US",
    "sg:address":"18 Arcadia Rd",
    "sg:city":"Old Greenwich",
    "sg:classifiers":[
        {
            "category":"Professional",
            "subcategory":"Research",
            "type":"Services"
        }
    ],
    "sg:phone":"+1 203 698 3344",
    "sg:postcode":"06870",
    "sg:province":"CT",
    "sg:tags":[
        "market",
        "analysis"
    ],
    "sg:website":"www.matrixalliance.com",
    "wof:name":"Matrix Alliance Market Rsrch",
    "wof:placetype":"venue"
},
  "geometry": {"coordinates":[-73.567097,41.032215],"type":"Point"}
}