{
  "type": "Feature",
  "properties": {
    "addr:full":"10 Colton Rd East Lyme CT 06333",
    "addr:housenumber":"10",
    "addr:postcode":"06333",
    "addr:street":"Colton Rd East Lyme Ct",
    "iso:country":"US",
    "sg:address":"10 Colton Rd",
    "sg:city":"East Lyme",
    "sg:classifiers":[
        {
            "category":"Retail",
            "subcategory":"Auto Rental",
            "type":"Services"
        }
    ],
    "sg:phone":"+1   ",
    "sg:postcode":"06333",
    "sg:province":"CT",
    "sg:tags":[
        "truck"
    ],
    "wof:name":"Edart Truck Leasing Corp",
    "wof:placetype":"venue"
},
  "geometry": {"coordinates":[-72.254909,41.32145],"type":"Point"}
}