{
  "type": "Feature",
  "properties": {
    "iso:country":"US",
    "sg:address":"1500 Wolcott Rd",
    "sg:city":"Wolcott",
    "sg:classifiers":[
        {
            "category":"Food & Beverages",
            "subcategory":"Liquor & Beverages",
            "type":"Retail Goods"
        }
    ],
    "sg:phone":"+1 203 879 9112",
    "sg:postcode":"06716",
    "sg:province":"CT",
    "sg:tags":[
        "alcoholic"
    ],
    "wof:name":"North End Liquors",
    "wof:placetype":"venue"
},
  "geometry": {"coordinates":[-72.961467,41.628792],"type":"Point"}
}