{
  "type": "Feature",
  "properties": {
    "iso:country":"US",
    "sg:address":"2 Grandview Dr",
    "sg:city":"Danbury",
    "sg:classifiers":[
        {
            "category":"Government",
            "subcategory":"Office",
            "type":"Public Place"
        }
    ],
    "sg:phone":"+1 203 790 8883",
    "sg:postcode":"06811",
    "sg:province":"CT",
    "sg:tags":[
        "management"
    ],
    "wof:name":"Steven Bradsell Home Impr",
    "wof:placetype":"venue"
},
  "geometry": {"coordinates":[-73.496983,41.413608],"type":"Point"}
}