{
  "type": "Feature",
  "properties": {
    "iso:country":"US",
    "sg:address":"397 Fairlea Rd",
    "sg:city":"Orange",
    "sg:classifiers":[
        {
            "category":"Professional",
            "subcategory":"Management & Consulting",
            "type":"Services"
        }
    ],
    "sg:phone":"+1   ",
    "sg:postcode":"06477",
    "sg:province":"CT",
    "sg:tags":[
        "business"
    ],
    "wof:name":"H C Planning Consultants Inc",
    "wof:placetype":"venue"
},
  "geometry": {"coordinates":[-73.016777,41.26168],"type":"Point"}
}