{
  "type": "Feature",
  "properties": {
    "iso:country":"US",
    "sg:address":"180 Franklin Ave",
    "sg:city":"Hartford",
    "sg:classifiers":[
        {
            "category":"Personal",
            "subcategory":"Barber",
            "type":"Services"
        }
    ],
    "sg:phone":"+1   ",
    "sg:postcode":"06114",
    "sg:province":"CT",
    "sg:tags":[
        "shop"
    ],
    "wof:name":"Fade Away Barber Salon",
    "wof:placetype":"venue"
},
  "geometry": {"coordinates":[-72.676773,41.74593],"type":"Point"}
}