{
  "type": "Feature",
  "properties": {
    "addr:full":"6 The Grn Collinsville CT 06019",
    "addr:housenumber":"6",
    "addr:postcode":"06019",
    "addr:street":"The Grn Collinsville Ct",
    "iso:country":"US",
    "sg:address":"6 The Grn",
    "sg:city":"Collinsville",
    "sg:classifiers":[
        {
            "category":"Health Services",
            "subcategory":"Doctor",
            "type":"Services"
        },
        {
            "category":"Health Services",
            "subcategory":"Clinic",
            "type":"Services"
        }
    ],
    "sg:phone":"+1 860 693 8020",
    "sg:postcode":"06019",
    "sg:province":"CT",
    "sg:tags":[
        "counseling",
        "mental"
    ],
    "wof:name":"Rubinstein Karel PHD",
    "wof:placetype":"venue"
},
  "geometry": {"coordinates":[-72.9216,41.809898],"type":"Point"}
}