{
  "type": "Feature",
  "properties": {
    "addr:full":"26 E Franklin St Danbury CT 06810",
    "addr:housenumber":"26",
    "addr:postcode":"06810",
    "addr:street":"E Franklin St",
    "iso:country":"US",
    "sg:address":"26 E Franklin St",
    "sg:city":"Danbury",
    "sg:classifiers":[
        {
            "category":"Wholesale",
            "subcategory":"Hardware",
            "type":"Manufacturing & Wholesale Goods"
        }
    ],
    "sg:phone":"+1 203 744 1045",
    "sg:postcode":"06810",
    "sg:province":"CT",
    "sg:tags":[
        "equipment",
        "heating",
        "system"
    ],
    "wof:name":"Donnelly Heating",
    "wof:placetype":"venue"
},
  "geometry": {"coordinates":[-73.457112,41.400037],"type":"Point"}
}