{
  "type": "Feature",
  "properties": {
    "addr:full":"12 Fairport Rd Westport CT 06880",
    "addr:housenumber":"12",
    "addr:postcode":"06880",
    "addr:street":"Fairport Rd",
    "iso:country":"US",
    "sg:address":"12 Fairport Rd",
    "sg:city":"Westport",
    "sg:classifiers":[
        {
            "category":"Building & Trades",
            "subcategory":"Construction",
            "type":"Services"
        }
    ],
    "sg:phone":"+1 203 255 6108",
    "sg:postcode":"06880",
    "sg:province":"CT",
    "sg:tags":[
        "contractor"
    ],
    "wof:name":"Doyle Housewrights Inc",
    "wof:placetype":"venue"
},
  "geometry": {"coordinates":[-73.30259100000001,41.139986],"type":"Point"}
}