{
  "type": "Feature",
  "properties": {
    "iso:country":"US",
    "sg:address":"70 Mill Plain Rd",
    "sg:city":"Danbury",
    "sg:classifiers":[
        {
            "category":"Building & Trades",
            "subcategory":"Landscaping Services",
            "type":"Services"
        }
    ],
    "sg:phone":"+1 203 794 1111",
    "sg:postcode":"06811",
    "sg:province":"CT",
    "sg:tags":[
        "lawn",
        "maintenance",
        "grounds"
    ],
    "wof:name":"Trugreen Chemlawn",
    "wof:placetype":"venue"
},
  "geometry": {"coordinates":[-73.50727999999999,41.392403],"type":"Point"}
}