{
  "type": "Feature",
  "properties": {
    "iso:country":"US",
    "sg:address":"46 Barnabas Rd",
    "sg:city":"Newtown",
    "sg:classifiers":[
        {
            "category":"Professional",
            "type":"Services"
        }
    ],
    "sg:phone":"+1 203 426 9401",
    "sg:postcode":"06470",
    "sg:province":"CT",
    "sg:tags":[
        "establishment"
    ],
    "wof:name":"Braun Paving",
    "wof:placetype":"venue"
},
  "geometry": {"coordinates":[-73.348555,41.426576],"type":"Point"}
}