{
  "type": "Feature",
  "properties": {
    "iso:country":"US",
    "sg:address":"19 Bellmere Ave",
    "sg:city":"Stamford",
    "sg:classifiers":[
        {
            "category":"Professional",
            "subcategory":"Art Services",
            "type":"Services"
        }
    ],
    "sg:phone":"+1   ",
    "sg:postcode":"06906",
    "sg:province":"CT",
    "sg:tags":[
        "photography",
        "commercial"
    ],
    "wof:name":"Don Hamerman",
    "wof:placetype":"venue"
},
  "geometry": {"coordinates":[-73.529686,41.075987],"type":"Point"}
}