{
  "type": "Feature",
  "properties": {
    "addr:full":"522 Heritage Rd Southbury CT 06488",
    "addr:housenumber":"522",
    "addr:postcode":"06488",
    "addr:street":"Heritage Rd",
    "iso:country":"US",
    "sg:address":"522 Heritage Rd",
    "sg:city":"Southbury",
    "sg:classifiers":[
        {
            "category":"Professional",
            "subcategory":"Business Services",
            "type":"Services"
        }
    ],
    "sg:phone":"+1 203 264 8200",
    "sg:postcode":"06488",
    "sg:province":"CT",
    "sg:tags":[
        "conference",
        "center"
    ],
    "wof:name":"Heritage A Dolce Conference",
    "wof:placetype":"venue"
},
  "geometry": {"coordinates":[-73.224745,41.488544],"type":"Point"}
}