{
  "type": "Feature",
  "properties": {
    "iso:country":"US",
    "sg:address":"307 Columbus Ave",
    "sg:city":"New Haven",
    "sg:classifiers":[
        {
            "category":"Home & Garden",
            "subcategory":"Household Appliances",
            "type":"Retail Goods"
        }
    ],
    "sg:phone":"+1 203 214 8223",
    "sg:postcode":"06519",
    "sg:province":"CT",
    "wof:name":"Tony's Appliances",
    "wof:placetype":"venue"
},
  "geometry": {"coordinates":[-72.934512,41.297871],"type":"Point"}
}