{
  "type": "Feature",
  "properties": {
    "addr:full":"80 Spruce St Stamford CT 06902",
    "addr:housenumber":"80",
    "addr:postcode":"06902",
    "addr:street":"Spruce St",
    "iso:country":"US",
    "sg:address":"80 Spruce St",
    "sg:city":"Stamford",
    "sg:classifiers":[
        {
            "category":"Real Estate",
            "subcategory":"Real Estate Agent",
            "type":"Services"
        }
    ],
    "sg:phone":"+1 203 359 4342",
    "sg:postcode":"06902",
    "sg:province":"CT",
    "wof:name":"H & H Property MGT & Dev",
    "wof:placetype":"venue"
},
  "geometry": {"coordinates":[-73.549841,41.050171],"type":"Point"}
}