{
  "type": "Feature",
  "properties": {
    "iso:country":"US",
    "sg:address":"2246 Norwich-New London Tpke",
    "sg:city":"Uncasville",
    "sg:classifiers":[
        {
            "category":"Autos & Motor Vehicles",
            "subcategory":"Automobile Sales",
            "type":"Retail Goods"
        }
    ],
    "sg:phone":"+1 860 848 7731",
    "sg:postcode":"06382",
    "sg:province":"CT",
    "sg:tags":[
        "used"
    ],
    "wof:name":"Shantok Motors",
    "wof:placetype":"venue"
},
  "geometry": {"coordinates":[-72.10025400000001,41.486235],"type":"Point"}
}