{
  "type": "Feature",
  "properties": {
    "iso:country":"US",
    "sg:address":"25 Ashburn Ln",
    "sg:city":"Milford",
    "sg:classifiers":[
        {
            "category":"Retail",
            "subcategory":"Laundry & Dry Cleaning",
            "type":"Services"
        }
    ],
    "sg:phone":"+1   ",
    "sg:postcode":"06460",
    "sg:province":"CT",
    "wof:name":"Carpet Master",
    "wof:placetype":"venue"
},
  "geometry": {"coordinates":[-73.000426,41.23747],"type":"Point"}
}