{
  "type": "Feature",
  "properties": {
    "addr:full":"1200 E Putnam Ave Riverside CT 06878",
    "addr:housenumber":"1200",
    "addr:postcode":"06878",
    "addr:street":"E Putnam Ave Riverside Ct",
    "iso:country":"US",
    "sg:address":"1200 E Putnam Ave",
    "sg:city":"Riverside",
    "sg:classifiers":[
        {
            "category":"Banks & Credit Unions",
            "subcategory":"Bank",
            "type":"Services"
        }
    ],
    "sg:phone":"+1 203 637 7864",
    "sg:postcode":"06878",
    "sg:province":"CT",
    "sg:tags":[
        "mortgage"
    ],
    "wof:name":"Bank of America",
    "wof:placetype":"venue"
},
  "geometry": {"coordinates":[-73.57924300000001,41.041532],"type":"Point"}
}