{
  "type": "Feature",
  "properties": {
    "addr:full":"61 Greenwood St East Hartford CT 06118",
    "addr:housenumber":"61",
    "addr:postcode":"06118",
    "addr:street":"Greenwood St East;Ct",
    "iso:country":"US",
    "sg:address":"61 Greenwood St",
    "sg:city":"East Hartford",
    "sg:classifiers":[
        {
            "category":"Professional",
            "subcategory":"Business Services",
            "type":"Services"
        }
    ],
    "sg:phone":"+1   ",
    "sg:postcode":"06118",
    "sg:province":"CT",
    "wof:name":"Carrolls Carrier Service LLC",
    "wof:placetype":"venue"
},
  "geometry": {"coordinates":[-72.59810899999999,41.743317],"type":"Point"}
}