{
  "type": "Feature",
  "properties": {
    "addr:full":"1 Prestige Dr Meriden CT 06450",
    "addr:housenumber":"1",
    "addr:postcode":"06450",
    "addr:street":"Prestige Dr",
    "iso:country":"US",
    "sg:address":"1 Prestige Dr",
    "sg:city":"Meriden",
    "sg:classifiers":[
        {
            "category":"Professional",
            "subcategory":"Employment Agencies",
            "type":"Services"
        }
    ],
    "sg:phone":"+1 203 630 2090",
    "sg:postcode":"06450",
    "sg:province":"CT",
    "sg:tags":[
        "opportunity"
    ],
    "sg:website":"www.modisit.com",
    "wof:name":"Modis",
    "wof:placetype":"venue"
},
  "geometry": {"coordinates":[-72.761934,41.521831],"type":"Point"}
}