{
  "type": "Feature",
  "properties": {
    "iso:country":"US",
    "sg:address":"151 Westport Ave",
    "sg:city":"Norwalk",
    "sg:classifiers":[
        {
            "category":"Professional",
            "type":"Services"
        }
    ],
    "sg:phone":"+1 203 846 0291",
    "sg:postcode":"06851",
    "sg:province":"CT",
    "sg:tags":[
        "establishment"
    ],
    "wof:name":"Fortunoff",
    "wof:placetype":"venue"
},
  "geometry": {"coordinates":[-73.400052,41.123836],"type":"Point"}
}