{
  "type": "Feature",
  "properties": {
    "addr:full":"288 Highland Ave Cheshire CT 06410",
    "addr:housenumber":"288",
    "addr:postcode":"06410",
    "addr:street":"Highland Ave",
    "iso:country":"US",
    "sg:address":"288 Highland Ave",
    "sg:city":"Cheshire",
    "sg:classifiers":[
        {
            "category":"Professional",
            "subcategory":"Engineering",
            "type":"Services"
        }
    ],
    "sg:phone":"+1 203 272 0400",
    "sg:postcode":"06410",
    "sg:province":"CT",
    "sg:tags":[
        "engineer"
    ],
    "wof:name":"Bubaris Traffic Assoc",
    "wof:placetype":"venue"
},
  "geometry": {"coordinates":[-72.900177,41.506425],"type":"Point"}
}