{
  "type": "Feature",
  "properties": {
    "iso:country":"US",
    "sg:address":"11 E Main St",
    "sg:city":"Canaan",
    "sg:classifiers":[
        {
            "category":"Shopping",
            "subcategory":"Pharmacy",
            "type":"Retail Goods"
        }
    ],
    "sg:phone":"+1 860 824 8000",
    "sg:postcode":"06018",
    "sg:province":"CT",
    "sg:tags":[
        "drugstore"
    ],
    "wof:name":"Canaan Apothecary",
    "wof:placetype":"venue"
},
  "geometry": {"coordinates":[-73.322237,42.023964],"type":"Point"}
}