{
  "type": "Feature",
  "properties": {
    "addr:full":"565 Long Hill Rd Groton CT 06340",
    "addr:housenumber":"565",
    "addr:postcode":"06340",
    "addr:street":"Long Hill Rd Groton Ct",
    "iso:country":"US",
    "sg:address":"565 Long Hill Rd",
    "sg:city":"Groton",
    "sg:classifiers":[
        {
            "category":"Health Services",
            "subcategory":"Health Practitioner",
            "type":"Services"
        }
    ],
    "sg:phone":"+1   ",
    "sg:postcode":"06340",
    "sg:province":"CT",
    "wof:name":"Carl Center Physical Therapy",
    "wof:placetype":"venue"
},
  "geometry": {"coordinates":[-72.058617,41.352223],"type":"Point"}
}