{
  "type": "Feature",
  "properties": {
    "iso:country":"US",
    "sg:address":"143 Lowrey Pl",
    "sg:city":"Newington",
    "sg:classifiers":[
        {
            "category":"Food & Beverages",
            "subcategory":"Liquor & Beverages",
            "type":"Retail Goods"
        }
    ],
    "sg:phone":"+1 860 667 0000",
    "sg:postcode":"06111",
    "sg:province":"CT",
    "sg:tags":[
        "store"
    ],
    "wof:name":"Roma Enterprises",
    "wof:placetype":"venue"
},
  "geometry": {"coordinates":[-72.718825,41.696114],"type":"Point"}
}