{
  "type": "Feature",
  "properties": {
    "iso:country":"US",
    "sg:address":"42 Ives St",
    "sg:city":"Waterbury",
    "sg:classifiers":[
        {
            "category":"Building & Trades",
            "subcategory":"Construction",
            "type":"Services"
        }
    ],
    "sg:phone":"+1 203 597 0332",
    "sg:postcode":"06704",
    "sg:province":"CT",
    "sg:tags":[
        "maintenance",
        "contractor"
    ],
    "wof:name":"Royal Maintenance LLC",
    "wof:placetype":"venue"
},
  "geometry": {"coordinates":[-73.02655300000001,41.559818],"type":"Point"}
}