{
  "type": "Feature",
  "properties": {
    "iso:country":"US",
    "sg:address":"400 W Main St",
    "sg:city":"Stamford",
    "sg:classifiers":[
        {
            "category":"Manufacturing",
            "subcategory":"Textiles",
            "type":"Manufacturing & Wholesale Goods"
        }
    ],
    "sg:phone":"+1 203 327 7471",
    "sg:postcode":"06902",
    "sg:province":"CT",
    "sg:tags":[
        "rug",
        "carpet"
    ],
    "wof:name":"Triple S Carpet & Drapery",
    "wof:placetype":"venue"
},
  "geometry": {"coordinates":[-73.553454,41.048055],"type":"Point"}
}