{
  "type": "Feature",
  "properties": {
    "iso:country":"US",
    "sg:address":"324 Deming St",
    "sg:city":"South Windsor",
    "sg:classifiers":[
        {
            "category":"Building & Trades",
            "subcategory":"Construction",
            "type":"Services"
        }
    ],
    "sg:phone":"+1 860 523 4182",
    "sg:postcode":"06074",
    "sg:province":"CT",
    "sg:tags":[
        "concrete",
        "contractor"
    ],
    "wof:name":"Quality Paving Inc",
    "wof:placetype":"venue"
},
  "geometry": {"coordinates":[-72.551868,41.820862],"type":"Point"}
}