{
  "type": "Feature",
  "properties": {
    "iso:country":"US",
    "sg:address":"242 E Main St",
    "sg:city":"Clinton",
    "sg:classifiers":[
        {
            "category":"Personal",
            "subcategory":"Nail Salon",
            "type":"Services"
        }
    ],
    "sg:phone":"+1 860 669 6100",
    "sg:postcode":"06413",
    "sg:province":"CT",
    "wof:name":"Clinton Nail & Spa",
    "wof:placetype":"venue"
},
  "geometry": {"coordinates":[-72.503668,41.271424],"type":"Point"}
}