{
  "type": "Feature",
  "properties": {
    "iso:country":"US",
    "sg:address":"104 Shore Dr",
    "sg:city":"Branford",
    "sg:classifiers":[
        {
            "category":"Recreation",
            "type":"Entertainment"
        }
    ],
    "sg:phone":"+1   ",
    "sg:postcode":"06405",
    "sg:province":"CT",
    "sg:tags":[
        "club",
        "membership"
    ],
    "wof:name":"Branford Soccer Club Inc",
    "wof:placetype":"venue"
},
  "geometry": {"coordinates":[-72.848223,41.258385],"type":"Point"}
}