{
  "type": "Feature",
  "properties": {
    "addr:full":"15 Grant Hill Rd Tolland CT 06084",
    "addr:housenumber":"15",
    "addr:postcode":"06084",
    "addr:street":"Grant Hill Rd Tolland Ct",
    "iso:country":"US",
    "sg:address":"15 Grant Hill Rd",
    "sg:city":"Tolland",
    "sg:classifiers":[
        {
            "category":"Retail",
            "subcategory":"Auto Repair",
            "type":"Services"
        }
    ],
    "sg:phone":"+1   ",
    "sg:postcode":"06084",
    "sg:province":"CT",
    "sg:tags":[
        "general"
    ],
    "wof:name":"Spruce Street Repair",
    "wof:placetype":"venue"
},
  "geometry": {"coordinates":[-72.368559,41.85155],"type":"Point"}
}