{
  "type": "Feature",
  "properties": {
    "iso:country":"US",
    "sg:address":"489 Candlewood Hill Rd",
    "sg:city":"Higganum",
    "sg:classifiers":[
        {
            "category":"Farming",
            "subcategory":"Berry Farm",
            "type":"Manufacturing & Wholesale Goods"
        }
    ],
    "sg:phone":"+1 860 345 4609",
    "sg:postcode":"06441",
    "sg:province":"CT",
    "sg:tags":[
        "crop"
    ],
    "wof:name":"Halfinger Farms",
    "wof:placetype":"venue"
},
  "geometry": {"coordinates":[-72.595418,41.474458],"type":"Point"}
}