{
  "type": "Feature",
  "properties": {
    "addr:full":"25 Cherry Ln Willimantic CT 06226",
    "addr:housenumber":"25",
    "addr:postcode":"06226",
    "addr:street":"Cherry Ln",
    "iso:country":"US",
    "sg:address":"25 Cherry Ln",
    "sg:city":"Willimantic",
    "sg:classifiers":[
        {
            "category":"Professional",
            "subcategory":"Management & Consulting",
            "type":"Services"
        }
    ],
    "sg:phone":"+1   ",
    "sg:postcode":"06226",
    "sg:province":"CT",
    "sg:tags":[
        "business"
    ],
    "wof:name":"A & R Communications LLC",
    "wof:placetype":"venue"
},
  "geometry": {"coordinates":[-72.20885199999999,41.699243],"type":"Point"}
}