{
  "type": "Feature",
  "properties": {
    "iso:country":"US",
    "sg:address":"531 Campbell Ave",
    "sg:city":"West Haven",
    "sg:classifiers":[
        {
            "category":"Professional",
            "subcategory":"Lawyer & Legal Services",
            "type":"Services"
        }
    ],
    "sg:phone":"+1 203 937 7400",
    "sg:postcode":"06516",
    "sg:province":"CT",
    "sg:tags":[
        "attorney"
    ],
    "wof:name":"Vincent N Amendola Jr Law Ofc",
    "wof:placetype":"venue"
},
  "geometry": {"coordinates":[-72.950407,41.27316],"type":"Point"}
}