{
  "type": "Feature",
  "properties": {
    "iso:country":"US",
    "sg:address":"409 Treadwell St",
    "sg:city":"Hamden",
    "sg:classifiers":[
        {
            "category":"Retail",
            "subcategory":"Auto Repair",
            "type":"Services"
        }
    ],
    "sg:phone":"+1 203 288 3707",
    "sg:postcode":"06514",
    "sg:province":"CT",
    "sg:tags":[
        "automobile",
        "used",
        "general"
    ],
    "wof:name":"Scarpo H P & Son Automotive",
    "wof:placetype":"venue"
},
  "geometry": {"coordinates":[-72.929478,41.353961],"type":"Point"}
}