{
  "type": "Feature",
  "properties": {
    "addr:full":"33 Water St Chester CT 06412",
    "addr:housenumber":"33",
    "addr:postcode":"06412",
    "addr:street":"Water St",
    "iso:country":"US",
    "sg:address":"33 Water St",
    "sg:city":"Chester",
    "sg:classifiers":[
        {
            "category":"Social Services",
            "subcategory":"Adult Care",
            "type":"Services"
        }
    ],
    "sg:phone":"+1   ",
    "sg:postcode":"06412",
    "sg:province":"CT",
    "sg:tags":[
        "residential"
    ],
    "wof:name":"Water Street Supported Living",
    "wof:placetype":"venue"
},
  "geometry": {"coordinates":[-72.447791,41.404998],"type":"Point"}
}