{
  "type": "Feature",
  "properties": {
    "iso:country":"US",
    "sg:address":"269 Bedford St",
    "sg:city":"Stamford",
    "sg:classifiers":[
        {
            "category":"Restaurant",
            "type":"Food & Drink"
        }
    ],
    "sg:menulink":"http://www.allmenus.com/ct/stamford/25233-sabatiellos-italian-grille/menu/",
    "sg:phone":"+1 203 353 3300",
    "sg:postcode":"06901",
    "sg:province":"CT",
    "sg:tags":[
        "italian"
    ],
    "wof:name":"Sabatiello's Italian Grille",
    "wof:placetype":"venue"
},
  "geometry": {"coordinates":[-73.537854,41.057756],"type":"Point"}
}