{
  "type": "Feature",
  "properties": {
    "iso:country":"US",
    "sg:address":"1575 Main St",
    "sg:city":"Coventry",
    "sg:classifiers":[
        {
            "category":"Building & Trades",
            "subcategory":"Electrical",
            "type":"Services"
        }
    ],
    "sg:phone":"+1 860 742 9230",
    "sg:postcode":"06238",
    "sg:province":"CT",
    "sg:tags":[
        "electrical",
        "contractor"
    ],
    "wof:name":"R & B Electric",
    "wof:placetype":"venue"
},
  "geometry": {"coordinates":[-72.308154,41.775319],"type":"Point"}
}