{
  "type": "Feature",
  "properties": {
    "iso:country":"US",
    "sg:address":"104 Evergreen Ln",
    "sg:city":"Glastonbury",
    "sg:classifiers":[
        {
            "category":"Organizations",
            "subcategory":"Membership Organization",
            "type":"Services"
        }
    ],
    "sg:phone":"+1   ",
    "sg:postcode":"06033",
    "sg:province":"CT",
    "wof:name":"Pineledge Inc",
    "wof:placetype":"venue"
},
  "geometry": {"coordinates":[-72.583681,41.680205],"type":"Point"}
}