{
  "type": "Feature",
  "properties": {
    "iso:country":"US",
    "sg:address":"3 Pickwick St",
    "sg:city":"Greenwich",
    "sg:classifiers":[
        {
            "category":"Banks & Credit Unions",
            "subcategory":"Bank",
            "type":"Services"
        }
    ],
    "sg:phone":"+1 203 000 1111",
    "sg:postcode":"06825",
    "sg:province":"CT",
    "wof:name":"Chase",
    "wof:placetype":"venue"
},
  "geometry": {"coordinates":[-73.22493299999999,41.178194],"type":"Point"}
}