{
  "type": "Feature",
  "properties": {
    "iso:country":"US",
    "sg:address":"100 Klondike Ave",
    "sg:city":"Stamford",
    "sg:classifiers":[
        {
            "category":"Professional",
            "subcategory":"Management & Consulting",
            "type":"Services"
        }
    ],
    "sg:phone":"+1   ",
    "sg:postcode":"06907",
    "sg:province":"CT",
    "sg:tags":[
        "business"
    ],
    "wof:name":"Nama Capital LLC",
    "wof:placetype":"venue"
},
  "geometry": {"coordinates":[-73.52665,41.088713],"type":"Point"}
}