{
  "type": "Feature",
  "properties": {
    "iso:country":"US",
    "sg:address":"44 Westfield Ave",
    "sg:city":"Danielson",
    "sg:classifiers":[
        {
            "category":"Real Estate",
            "subcategory":"Real Estate Operator",
            "type":"Services"
        }
    ],
    "sg:phone":"+1 860 774 1644",
    "sg:postcode":"06239",
    "sg:province":"CT",
    "sg:tags":[
        "housing",
        "management"
    ],
    "wof:name":"Westfield Village",
    "wof:placetype":"venue"
},
  "geometry": {"coordinates":[-71.878871,41.813451],"type":"Point"}
}