{
  "type": "Feature",
  "properties": {
    "addr:full":"223 Kent Rd New Milford CT 06776",
    "addr:housenumber":"223",
    "addr:postcode":"06776",
    "addr:street":"Kent Rd",
    "iso:country":"US",
    "sg:address":"223 Kent Rd",
    "sg:city":"New Milford",
    "sg:classifiers":[
        {
            "category":"Professional",
            "subcategory":"Business Services",
            "type":"Services"
        }
    ],
    "sg:phone":"+1   ",
    "sg:postcode":"06776",
    "sg:province":"CT",
    "wof:name":"Woodcraft Interiors Inc",
    "wof:placetype":"venue"
},
  "geometry": {"coordinates":[-73.436308,41.582647],"type":"Point"}
}