{
  "type": "Feature",
  "properties": {
    "addr:full":"1685 Reinhard Rd Cheshire CT 06410",
    "addr:housenumber":"1685",
    "addr:postcode":"06410",
    "addr:street":"Reinhard Rd",
    "iso:country":"US",
    "sg:address":"1685 Reinhard Rd",
    "sg:city":"Cheshire",
    "sg:classifiers":[
        {
            "category":"Manufacturing",
            "subcategory":"Retail Goods",
            "type":"Manufacturing & Wholesale Goods"
        }
    ],
    "sg:phone":"+1 203 271 2385",
    "sg:postcode":"06410",
    "sg:province":"CT",
    "sg:tags":[
        "manufacture",
        "flower",
        "dried",
        "sup"
    ],
    "wof:name":"Dried Materials Unlimited",
    "wof:placetype":"venue"
},
  "geometry": {"coordinates":[-72.892943,41.549129],"type":"Point"}
}