{
  "type": "Feature",
  "properties": {
    "addr:full":"750 Straits Tpke Middlebury CT 06762",
    "addr:housenumber":"750",
    "addr:postcode":"06762",
    "addr:street":"Straits Tpke",
    "iso:country":"US",
    "sg:address":"750 Straits Tpke",
    "sg:city":"Middlebury",
    "sg:classifiers":[
        {
            "category":"Restaurant",
            "type":"Food & Drink"
        }
    ],
    "sg:menulink":"http://www.allmenus.com/ct/middlebury/144255-subway/menu/",
    "sg:phone":"+1 203 598 7827",
    "sg:postcode":"06762",
    "sg:province":"CT",
    "sg:tags":[
        "american",
        "sandwich"
    ],
    "wof:name":"Subway",
    "wof:placetype":"venue"
},
  "geometry": {"coordinates":[-73.084536,41.530731],"type":"Point"}
}