{
  "type": "Feature",
  "properties": {
    "addr:full":"22 Gatehouse Rd Stamford CT 06902",
    "addr:housenumber":"22",
    "addr:postcode":"06902",
    "addr:street":"Gatehouse Rd",
    "iso:country":"US",
    "sg:address":"22 Gatehouse Rd",
    "sg:city":"Stamford",
    "sg:classifiers":[
        {
            "category":"Personal",
            "type":"Services"
        }
    ],
    "sg:phone":"+1   ",
    "sg:postcode":"06902",
    "sg:province":"CT",
    "wof:name":"Stamford Corporate Child Care",
    "wof:placetype":"venue"
},
  "geometry": {"coordinates":[-73.55074,41.029066],"type":"Point"}
}