{
  "type": "Feature",
  "properties": {
    "addr:full":"17 Whitewood Dr Branford CT 06405",
    "addr:housenumber":"17",
    "addr:postcode":"06405",
    "addr:street":"Whitewood Dr",
    "iso:country":"US",
    "sg:address":"17 Whitewood Dr",
    "sg:city":"Branford",
    "sg:classifiers":[
        {
            "category":"Building & Trades",
            "subcategory":"Electrical",
            "type":"Services"
        }
    ],
    "sg:phone":"+1   ",
    "sg:postcode":"06405",
    "sg:province":"CT",
    "sg:tags":[
        "consulting",
        "electrical",
        "business",
        "contractor"
    ],
    "wof:name":"Gunther Dannheim",
    "wof:placetype":"venue"
},
  "geometry": {"coordinates":[-72.75081400000001,41.280499],"type":"Point"}
}