{
  "type": "Feature",
  "properties": {
    "addr:full":"62 South Rd Groton CT 06340",
    "addr:housenumber":"62",
    "addr:postcode":"06340",
    "addr:street":"South Rd Groton Ct",
    "iso:country":"US",
    "sg:address":"62 South Rd",
    "sg:city":"Groton",
    "sg:classifiers":[
        {
            "category":"Health Services",
            "subcategory":"Chiropractor",
            "type":"Services"
        }
    ],
    "sg:phone":"+1   ",
    "sg:postcode":"06340",
    "sg:province":"CT",
    "wof:name":"Joshua Beebe DC",
    "wof:placetype":"venue"
},
  "geometry": {"coordinates":[-72.039051,41.346576],"type":"Point"}
}