{
  "type": "Feature",
  "properties": {
    "iso:country":"US",
    "sg:address":"270 Rowe Ave",
    "sg:city":"Milford",
    "sg:classifiers":[
        {
            "category":"Building & Trades",
            "subcategory":"Plumbing",
            "type":"Services"
        }
    ],
    "sg:phone":"+1 203 877 4070",
    "sg:postcode":"06460",
    "sg:province":"CT",
    "sg:tags":[
        "conditioning",
        "air",
        "system",
        "contractor"
    ],
    "sg:website":"www.ctairsys.com",
    "wof:name":"Connecticut Air Systems",
    "wof:placetype":"venue"
},
  "geometry": {"coordinates":[-73.097556,41.208689],"type":"Point"}
}