{
  "type": "Feature",
  "properties": {
    "addr:full":"1270 Boston Post Rd Milford CT 06460",
    "addr:housenumber":"1270",
    "addr:postcode":"06460",
    "addr:street":"Boston Post Rd",
    "iso:country":"US",
    "sg:address":"1270 Boston Post Rd",
    "sg:city":"Milford",
    "sg:classifiers":[
        {
            "category":"Restaurant",
            "type":"Food & Drink"
        }
    ],
    "sg:menulink":"http://www.allmenus.com/ct/milford/152260-honeybaked-ham/menu/",
    "sg:phone":"+1 203 874 4800",
    "sg:postcode":"06460",
    "sg:province":"CT",
    "sg:tags":[
        "american"
    ],
    "wof:name":"The HoneyBaked Ham Company",
    "wof:placetype":"venue"
},
  "geometry": {"coordinates":[-73.03679700000001,41.238157],"type":"Point"}
}