{
  "type": "Feature",
  "properties": {
    "addr:full":"1298 Silas Deane Hwy Wethersfield CT 06109",
    "addr:housenumber":"1298",
    "addr:postcode":"06109",
    "addr:street":"Silas Deane Hwy Wethersfield Ct",
    "iso:country":"US",
    "sg:address":"1298 Silas Deane Hwy",
    "sg:city":"Wethersfield",
    "sg:classifiers":[
        {
            "category":"Restaurant",
            "type":"Food & Drink"
        }
    ],
    "sg:menulink":"http://www.allmenus.com/ct/wethersfield/11647-dennys/menu/",
    "sg:phone":"+1 860 529 4225",
    "sg:postcode":"06109",
    "sg:province":"CT",
    "sg:tags":[
        "american",
        "diner"
    ],
    "wof:name":"Denny's",
    "wof:placetype":"venue"
},
  "geometry": {"coordinates":[-72.65482900000001,41.685541],"type":"Point"}
}