{
  "type": "Feature",
  "properties": {
    "iso:country":"US",
    "sg:address":"2001 Whitney Ave",
    "sg:city":"North Haven",
    "sg:classifiers":[
        {
            "category":"Personal",
            "subcategory":"Beauty Salon",
            "type":"Services"
        }
    ],
    "sg:phone":"+1 203 407 1014",
    "sg:postcode":"06473",
    "sg:province":"CT",
    "sg:tags":[
        "shop"
    ],
    "wof:name":"Studio Bella A Salon",
    "wof:placetype":"venue"
},
  "geometry": {"coordinates":[-72.906018,41.371569],"type":"Point"}
}