{
  "type": "Feature",
  "properties": {
    "iso:country":"US",
    "sg:address":"65 Benedict St",
    "sg:city":"Waterbury",
    "sg:classifiers":[
        {
            "category":"Building & Trades",
            "subcategory":"Cleaning & Sanitation",
            "type":"Services"
        },
        {
            "category":"Retail",
            "subcategory":"Repair Shop",
            "type":"Services"
        },
        {
            "category":"Home & Garden",
            "subcategory":"Hardware",
            "type":"Retail Goods"
        },
        {
            "category":"Manufacturing",
            "subcategory":"Paper Products",
            "type":"Manufacturing & Wholesale Goods"
        },
        {
            "category":"Home & Garden",
            "subcategory":"Kitchen Supply",
            "type":"Retail Goods"
        }
    ],
    "sg:phone":"+1 800 443 0325",
    "sg:postcode":"06706",
    "sg:province":"CT",
    "sg:tags":[
        "restaurant",
        "commercial",
        "paper-wholesale",
        "cleaners-industrial",
        "equipment",
        "cleaners-repair",
        "vacuum",
        "janitor",
        "manufacturer"
    ],
    "sg:website":"http://www.dumo.com",
    "wof:name":"Dumouchel Paper Co",
    "wof:placetype":"venue"
},
  "geometry": {"coordinates":[-73.040724,41.54944],"type":"Point"}
}