{
  "type": "Feature",
  "properties": {
    "addr:full":"1480 Boston Post Rd Old Saybrook CT 06475",
    "addr:housenumber":"1480",
    "addr:postcode":"06475",
    "addr:street":"Boston Post Rd Old Saybrook Ct",
    "iso:country":"US",
    "sg:address":"1480 Boston Post Rd",
    "sg:city":"Old Saybrook",
    "sg:classifiers":[
        {
            "category":"Health Services",
            "subcategory":"Doctor",
            "type":"Services"
        }
    ],
    "sg:phone":"+1   ",
    "sg:postcode":"06475",
    "sg:province":"CT",
    "sg:tags":[
        "surgeon",
        "oral"
    ],
    "wof:name":"Shoreline Oral & Maxifacial",
    "wof:placetype":"venue"
},
  "geometry": {"coordinates":[-72.40910100000001,41.286516],"type":"Point"}
}