{
  "type": "Feature",
  "properties": {
    "addr:full":"2748 Post Rd Darien CT 06820",
    "addr:housenumber":"2748",
    "addr:postcode":"06820",
    "addr:street":"Post Rd",
    "iso:country":"US",
    "sg:address":"2748 Post Rd",
    "sg:city":"Darien",
    "sg:classifiers":[
        {
            "category":"Real Estate",
            "subcategory":"Real Estate Operator",
            "type":"Services"
        }
    ],
    "sg:phone":"+1 203 967 9369",
    "sg:postcode":"06820",
    "sg:province":"CT",
    "sg:tags":[
        "building",
        "apartment"
    ],
    "wof:name":"Waters Edge",
    "wof:placetype":"venue"
},
  "geometry": {"coordinates":[-73.504447,41.060058],"type":"Point"}
}