{
  "type": "Feature",
  "properties": {
    "iso:country":"US",
    "sg:address":"17 Main St",
    "sg:city":"Danbury",
    "sg:classifiers":[
        {
            "category":"Shopping",
            "subcategory":"Used Merchandise",
            "type":"Retail Goods"
        }
    ],
    "sg:phone":"+1 203 792 2033",
    "sg:postcode":"06810",
    "sg:province":"CT",
    "sg:tags":[
        "shop",
        "thrift"
    ],
    "wof:name":"South Main Street Consignments",
    "wof:placetype":"venue"
},
  "geometry": {"coordinates":[-73.44668799999999,41.388598],"type":"Point"}
}