{
  "type": "Feature",
  "properties": {
    "iso:country":"US",
    "sg:address":"2 Enterprise Dr",
    "sg:city":"Shelton",
    "sg:classifiers":[
        {
            "category":"Professional",
            "subcategory":"Business Services",
            "type":"Services"
        },
        {
            "category":"Banks & Credit Unions",
            "subcategory":"Bank",
            "type":"Services"
        }
    ],
    "sg:phone":"+1 203 402 0444",
    "sg:postcode":"06484",
    "sg:province":"CT",
    "sg:tags":[
        "financing"
    ],
    "wof:name":"GMAC Business Credit",
    "wof:placetype":"venue"
},
  "geometry": {"coordinates":[-73.123756,41.277186],"type":"Point"}
}