{
  "type": "Feature",
  "properties": {
    "addr:full":"47 Deborah Rd Windsor Locks CT 06096",
    "addr:housenumber":"47",
    "addr:postcode":"06096",
    "addr:street":"Deborah Rd Windsor Locks Ct",
    "iso:country":"US",
    "sg:address":"47 Deborah Rd",
    "sg:city":"Windsor Locks",
    "sg:classifiers":[
        {
            "category":"Building & Trades",
            "subcategory":"Plumbing",
            "type":"Services"
        }
    ],
    "sg:phone":"+1 860 623 1795",
    "sg:postcode":"06096",
    "sg:province":"CT",
    "sg:tags":[
        "heating",
        "contractor"
    ],
    "wof:name":"Philip Desovich III",
    "wof:placetype":"venue"
},
  "geometry": {"coordinates":[-72.65888699999999,41.935618],"type":"Point"}
}