{
  "type": "Feature",
  "properties": {
    "addr:full":"3 Long Hill Rd Bethel CT 06801",
    "addr:housenumber":"3",
    "addr:postcode":"06801",
    "addr:street":"Long Hill Rd",
    "iso:country":"US",
    "sg:address":"3 Long Hill Rd",
    "sg:city":"Bethel",
    "sg:classifiers":[
        {
            "category":"Retail",
            "subcategory":"Repair Shop",
            "type":"Services"
        }
    ],
    "sg:phone":"+1   ",
    "sg:postcode":"06801",
    "sg:province":"CT",
    "wof:name":"Clearview Service",
    "wof:placetype":"venue"
},
  "geometry": {"coordinates":[-73.39125900000001,41.424604],"type":"Point"}
}