{
  "type": "Feature",
  "properties": {
    "addr:full":"61 Hill Dr New Milford CT 06776",
    "addr:housenumber":"61",
    "addr:postcode":"06776",
    "addr:street":"Hill Dr",
    "iso:country":"US",
    "sg:address":"61 Hill Dr",
    "sg:city":"New Milford",
    "sg:classifiers":[
        {
            "category":"Education",
            "subcategory":"Special Training",
            "type":"Public Place"
        }
    ],
    "sg:phone":"+1   ",
    "sg:postcode":"06776",
    "sg:province":"CT",
    "sg:tags":[
        "computer"
    ],
    "wof:name":"DEsgaille Artemia Vega",
    "wof:placetype":"venue"
},
  "geometry": {"coordinates":[-73.408761,41.585336],"type":"Point"}
}