{
  "type": "Feature",
  "properties": {
    "addr:full":"428 Glen Ave Port Chester CT 10573",
    "addr:housenumber":"428",
    "addr:postcode":"10573",
    "addr:street":"Glen Ave;Chester",
    "iso:country":"US",
    "sg:address":"428 Glen Ave",
    "sg:city":"Port Chester",
    "sg:classifiers":[
        {
            "category":"Professional",
            "subcategory":"Art Services",
            "type":"Services"
        }
    ],
    "sg:phone":"+1 914 939 7722",
    "sg:postcode":"10573",
    "sg:province":"CT",
    "sg:tags":[
        "photographer"
    ],
    "wof:name":"Tom Young Photography",
    "wof:placetype":"venue"
},
  "geometry": {"coordinates":[-73.673812,41.016333],"type":"Point"}
}