{
  "type": "Feature",
  "properties": {
    "iso:country":"US",
    "sg:address":"181 Elizabeth St",
    "sg:city":"Norwich",
    "sg:classifiers":[
        {
            "category":"Organizations",
            "subcategory":"Religious Organization",
            "type":"Services"
        }
    ],
    "sg:phone":"+1   ",
    "sg:postcode":"06360",
    "sg:province":"CT",
    "sg:tags":[
        "catholic",
        "roman",
        "church"
    ],
    "wof:name":"Saint Peter & Pauls Church",
    "wof:placetype":"venue"
},
  "geometry": {"coordinates":[-72.09118700000001,41.518366],"type":"Point"}
}