{
  "type": "Feature",
  "properties": {
    "iso:country":"US",
    "sg:address":"215 Frank St",
    "sg:city":"Bridgeport",
    "sg:classifiers":[
        {
            "category":"Restaurant",
            "type":"Food & Drink"
        }
    ],
    "sg:phone":"+1 203 335 1071",
    "sg:postcode":"06604",
    "sg:province":"CT",
    "wof:name":"Pantanal Restaurant",
    "wof:placetype":"venue"
},
  "geometry": {"coordinates":[-73.198204,41.187005],"type":"Point"}
}