{
  "type": "Feature",
  "properties": {
    "iso:country":"US",
    "sg:address":"288 Alling St",
    "sg:city":"Berlin",
    "sg:classifiers":[
        {
            "category":"Professional",
            "type":"Services"
        }
    ],
    "sg:phone":"+1   ",
    "sg:postcode":"06037",
    "sg:province":"CT",
    "wof:name":"Jay Mac Technical Services LLC",
    "wof:placetype":"venue"
},
  "geometry": {"coordinates":[-72.776158,41.634254],"type":"Point"}
}