{
  "type": "Feature",
  "properties": {
    "addr:full":"8 Winterbrook Rd Wolcott CT 06716",
    "addr:housenumber":"8",
    "addr:postcode":"06716",
    "addr:street":"Winterbrook Rd Wolcott Ct",
    "iso:country":"US",
    "sg:address":"8 Winterbrook Rd",
    "sg:city":"Wolcott",
    "sg:classifiers":[
        {
            "category":"Building & Trades",
            "subcategory":"Construction",
            "type":"Services"
        }
    ],
    "sg:phone":"+1 203 879 8796",
    "sg:postcode":"06716",
    "sg:province":"CT",
    "sg:tags":[
        "company"
    ],
    "wof:name":"Skyline Construction",
    "wof:placetype":"venue"
},
  "geometry": {"coordinates":[-72.96407499999999,41.632168],"type":"Point"}
}