{
  "type": "Feature",
  "properties": {
    "addr:full":"703 Whitney Ave New Haven CT 06511",
    "addr:housenumber":"703",
    "addr:postcode":"06511",
    "addr:street":"Whitney Ave",
    "iso:country":"US",
    "sg:address":"703 Whitney Ave",
    "sg:city":"New Haven",
    "sg:classifiers":[
        {
            "category":"Professional",
            "subcategory":"Management & Consulting",
            "type":"Services"
        }
    ],
    "sg:phone":"+1   ",
    "sg:postcode":"06511",
    "sg:province":"CT",
    "sg:tags":[
        "business"
    ],
    "wof:name":"New Haven Public Educatn Fund",
    "wof:placetype":"venue"
},
  "geometry": {"coordinates":[-72.91367,41.330498],"type":"Point"}
}