{
  "type": "Feature",
  "properties": {
    "iso:country":"US",
    "sg:address":"2660 E Main St",
    "sg:city":"Bridgeport",
    "sg:classifiers":[
        {
            "category":"Restaurant",
            "type":"Food & Drink"
        }
    ],
    "sg:phone":"+1 203 334 8679",
    "sg:postcode":"06610",
    "sg:province":"CT",
    "sg:tags":[
        "delicatessen"
    ],
    "wof:name":"Chaves Bakery & Deli",
    "wof:placetype":"venue"
},
  "geometry": {"coordinates":[-73.178978,41.211144],"type":"Point"}
}