{
  "type": "Feature",
  "properties": {
    "iso:country":"US",
    "sg:address":"265 Post Rd W",
    "sg:city":"Westport",
    "sg:classifiers":[
        {
            "category":"Professional",
            "subcategory":"Business Services",
            "type":"Services"
        }
    ],
    "sg:phone":"+1   ",
    "sg:postcode":"06880",
    "sg:province":"CT",
    "wof:name":"Gunderson Group",
    "wof:placetype":"venue"
},
  "geometry": {"coordinates":[-73.373527,41.133509],"type":"Point"}
}