{
  "type": "Feature",
  "properties": {
    "addr:full":"41 Wood Creek Rd Burlington CT 06013",
    "addr:housenumber":"41",
    "addr:postcode":"06013",
    "addr:street":"Wood Creek Rd",
    "iso:country":"US",
    "sg:address":"41 Wood Creek Rd",
    "sg:city":"Burlington",
    "sg:classifiers":[
        {
            "category":"Building & Trades",
            "subcategory":"Construction",
            "type":"Services"
        }
    ],
    "sg:phone":"+1 860 675 4261",
    "sg:postcode":"06013",
    "sg:province":"CT",
    "sg:tags":[
        "new",
        "commercial",
        "contractor"
    ],
    "wof:name":"Richline Company Inc",
    "wof:placetype":"venue"
},
  "geometry": {"coordinates":[-72.915184,41.749708],"type":"Point"}
}