{
  "type": "Feature",
  "properties": {
    "iso:country":"US",
    "sg:address":"1363 Boston Post Rd",
    "sg:city":"Old Saybrook",
    "sg:classifiers":[
        {
            "category":"Home & Garden",
            "subcategory":"Hardware",
            "type":"Retail Goods"
        }
    ],
    "sg:phone":"+1 860 388 4240",
    "sg:postcode":"06475",
    "sg:province":"CT",
    "sg:tags":[
        "store"
    ],
    "wof:name":"ABC Enterprises",
    "wof:placetype":"venue"
},
  "geometry": {"coordinates":[-72.402,41.287201],"type":"Point"}
}