{
  "type": "Feature",
  "properties": {
    "iso:country":"US",
    "sg:address":"150 Centre Pike",
    "sg:city":"Eastford",
    "sg:classifiers":[
        {
            "category":"Education",
            "subcategory":"Special Training",
            "type":"Public Place"
        }
    ],
    "sg:phone":"+1   ",
    "sg:postcode":"06242",
    "sg:province":"CT",
    "wof:name":"Yale Graduate School For Es",
    "wof:placetype":"venue"
},
  "geometry": {"coordinates":[-72.117964,41.949558],"type":"Point"}
}