{
  "type": "Feature",
  "properties": {
    "iso:country":"US",
    "sg:address":"240 Chapel St",
    "sg:city":"Milford",
    "sg:classifiers":[
        {
            "category":"Education",
            "subcategory":"School",
            "type":"Public Place"
        }
    ],
    "sg:phone":"+1   ",
    "sg:postcode":"06460",
    "sg:province":"CT",
    "wof:name":"East Shore Middle School",
    "wof:placetype":"venue"
},
  "geometry": {"coordinates":[-73.001699,41.228194],"type":"Point"}
}