{
  "type": "Feature",
  "properties": {
    "iso:country":"US",
    "sg:address":"33 Oxford Way",
    "sg:city":"Torrington",
    "sg:classifiers":[
        {
            "category":"Building & Trades",
            "subcategory":"Construction",
            "type":"Services"
        }
    ],
    "sg:phone":"+1 860 489 9546",
    "sg:postcode":"06790",
    "sg:province":"CT",
    "sg:tags":[
        "contractor"
    ],
    "wof:name":"PR Contracting LLC",
    "wof:placetype":"venue"
},
  "geometry": {"coordinates":[-73.074833,41.864324],"type":"Point"}
}