{
  "type": "Feature",
  "properties": {
    "addr:full":"110 Hunters Ln Newington CT 06111",
    "addr:housenumber":"110",
    "addr:postcode":"06111",
    "addr:street":"Hunters Ln",
    "iso:country":"US",
    "sg:address":"110 Hunters Ln",
    "sg:city":"Newington",
    "sg:classifiers":[
        {
            "category":"Building & Trades",
            "subcategory":"Plumbing",
            "type":"Services"
        }
    ],
    "sg:phone":"+1 860 828 8816",
    "sg:postcode":"06111",
    "sg:province":"CT",
    "sg:tags":[
        "air",
        "heating",
        "conditioning",
        "contractor"
    ],
    "wof:name":"Ernesto M Manuele",
    "wof:placetype":"venue"
},
  "geometry": {"coordinates":[-72.72655399999999,41.672539],"type":"Point"}
}