{
  "type": "Feature",
  "properties": {
    "iso:country":"US",
    "sg:address":"41 Pepper Ridge Rd",
    "sg:city":"Stamford",
    "sg:classifiers":[
        {
            "category":"Professional",
            "subcategory":"Management & Consulting",
            "type":"Services"
        }
    ],
    "sg:phone":"+1   ",
    "sg:postcode":"06905",
    "sg:province":"CT",
    "sg:tags":[
        "business"
    ],
    "wof:name":"Pepper Ridge Consulting LLC",
    "wof:placetype":"venue"
},
  "geometry": {"coordinates":[-73.53904300000001,41.080583],"type":"Point"}
}