{
  "type": "Feature",
  "properties": {
    "iso:country":"US",
    "sg:address":"549 Post Rd",
    "sg:city":"Darien",
    "sg:classifiers":[
        {
            "category":"Shopping",
            "type":"Retail Goods"
        }
    ],
    "sg:phone":"+1 203 655 7387",
    "sg:postcode":"06820",
    "sg:province":"CT",
    "sg:tags":[
        "pet",
        "shop"
    ],
    "wof:name":"TLC Pets Of Darien",
    "wof:placetype":"venue"
},
  "geometry": {"coordinates":[-73.464941,41.082512],"type":"Point"}
}