{
  "type": "Feature",
  "properties": {
    "iso:country":"US",
    "sg:address":"32 Belmont Ave",
    "sg:city":"Shelton",
    "sg:classifiers":[
        {
            "category":"Arts & Performance",
            "subcategory":"Theater",
            "type":"Entertainment"
        }
    ],
    "sg:phone":"+1 203 922 1066",
    "sg:postcode":"06484",
    "sg:province":"CT",
    "sg:tags":[
        "arranging",
        "contest",
        "judging"
    ],
    "wof:name":"Couto Pageant Productions Inc",
    "wof:placetype":"venue"
},
  "geometry": {"coordinates":[-73.079151,41.296445],"type":"Point"}
}