{
  "type": "Feature",
  "properties": {
    "iso:country":"US",
    "sg:address":"55 Elm St",
    "sg:city":"Hartford",
    "sg:classifiers":[
        {
            "category":"Government",
            "subcategory":"Court House",
            "type":"Public Place"
        }
    ],
    "sg:phone":"+1 860 808 5340",
    "sg:postcode":"06106",
    "sg:province":"CT",
    "sg:tags":[
        "right",
        "employment"
    ],
    "wof:name":"Employee Rights Department",
    "wof:placetype":"venue"
},
  "geometry": {"coordinates":[-72.677373,41.762983],"type":"Point"}
}