{
  "type": "Feature",
  "properties": {
    "addr:full":"273 Danbury Rd Ridgefield CT 06877",
    "addr:housenumber":"273",
    "addr:postcode":"06877",
    "addr:street":"Danbury Rd",
    "iso:country":"US",
    "sg:address":"273 Danbury Rd",
    "sg:city":"Ridgefield",
    "sg:classifiers":[
        {
            "category":"Building & Trades",
            "subcategory":"Construction",
            "type":"Services"
        }
    ],
    "sg:phone":"+1 203 431 8821",
    "sg:postcode":"06877",
    "sg:province":"CT",
    "sg:tags":[
        "roofing",
        "contractor"
    ],
    "wof:name":"Ted Burke Wood Roof",
    "wof:placetype":"venue"
},
  "geometry": {"coordinates":[-73.491173,41.303633],"type":"Point"}
}