{
  "type": "Feature",
  "properties": {
    "addr:full":"9 Avonwood Rd Avon CT 06001",
    "addr:housenumber":"9",
    "addr:postcode":"06001",
    "addr:street":"Avonwood Rd",
    "iso:country":"US",
    "sg:address":"9 Avonwood Rd",
    "sg:city":"Avon",
    "sg:classifiers":[
        {
            "category":"Personal",
            "subcategory":"Beauty Salon",
            "type":"Services"
        },
        {
            "category":"Personal",
            "subcategory":"Nail Salon",
            "type":"Services"
        }
    ],
    "sg:phone":"+1 860 677 6100",
    "sg:postcode":"06001",
    "sg:province":"CT",
    "sg:tags":[
        "hair"
    ],
    "wof:name":"Avon Hair Co",
    "wof:placetype":"venue"
},
  "geometry": {"coordinates":[-72.819298,41.8008],"type":"Point"}
}