{
  "type": "Feature",
  "properties": {
    "addr:full":"39 High Ledge Cir Manchester CT 06040",
    "addr:housenumber":"39",
    "addr:postcode":"06040",
    "addr:street":"High Ledge Cir",
    "iso:country":"US",
    "sg:address":"39 High Ledge Cir",
    "sg:city":"Manchester",
    "sg:classifiers":[
        {
            "category":"Wholesale",
            "subcategory":"Home Furnishings",
            "type":"Manufacturing & Wholesale Goods"
        }
    ],
    "sg:phone":"+1 860 289 5497",
    "sg:postcode":"06040",
    "sg:province":"CT",
    "wof:name":"Tupperware",
    "wof:placetype":"venue"
},
  "geometry": {"coordinates":[-72.475516,41.749622],"type":"Point"}
}