{
  "type": "Feature",
  "properties": {
    "addr:full":"2 Brookdale Ln Brookfield CT 06804",
    "addr:housenumber":"2",
    "addr:postcode":"06804",
    "addr:street":"Brookdale Ln",
    "iso:country":"US",
    "sg:address":"2 Brookdale Ln",
    "sg:city":"Brookfield",
    "sg:classifiers":[
        {
            "category":"Professional",
            "subcategory":"Management & Consulting",
            "type":"Services"
        }
    ],
    "sg:phone":"+1 203 775 1552",
    "sg:postcode":"06804",
    "sg:province":"CT",
    "sg:tags":[
        "consultant",
        "business"
    ],
    "wof:name":"Asset Resources",
    "wof:placetype":"venue"
},
  "geometry": {"coordinates":[-73.37841899999999,41.46992],"type":"Point"}
}