{
  "type": "Feature",
  "properties": {
    "iso:country":"US",
    "sg:address":"8 Northview Dr",
    "sg:city":"Vernon Rockville",
    "sg:classifiers":[
        {
            "category":"Professional",
            "subcategory":"Computer Services",
            "type":"Services"
        }
    ],
    "sg:phone":"+1   ",
    "sg:postcode":"06066",
    "sg:province":"CT",
    "sg:tags":[
        "related"
    ],
    "wof:name":"Gene Ambeau Services LLC",
    "wof:placetype":"venue"
},
  "geometry": {"coordinates":[-72.464885,41.860938],"type":"Point"}
}