{
  "type": "Feature",
  "properties": {
    "iso:country":"US",
    "sg:address":"79 Grey Rock Rd",
    "sg:city":"Bridgeport",
    "sg:classifiers":[
        {
            "category":"Professional",
            "type":"Services"
        }
    ],
    "sg:phone":"+1   ",
    "sg:postcode":"06606",
    "sg:province":"CT",
    "wof:name":"S&R Service LLC",
    "wof:placetype":"venue"
},
  "geometry": {"coordinates":[-73.198634,41.225505],"type":"Point"}
}