{
  "type": "Feature",
  "properties": {
    "iso:country":"US",
    "sg:address":"289 S Main St",
    "sg:city":"West Hartford",
    "sg:classifiers":[
        {
            "category":"Restaurant",
            "type":"Food & Drink"
        }
    ],
    "sg:menulink":"http://www.allmenus.com/ct/west-hartford/270462-angelos-on-main/menu/",
    "sg:phone":"+1 860 313 0460",
    "sg:postcode":"06107",
    "sg:province":"CT",
    "sg:tags":[
        "american"
    ],
    "wof:name":"Angelo's on Main",
    "wof:placetype":"venue"
},
  "geometry": {"coordinates":[-72.744918,41.742901],"type":"Point"}
}