{
  "type": "Feature",
  "properties": {
    "iso:country":"US",
    "sg:address":"77 Bedford St",
    "sg:city":"Stamford",
    "sg:classifiers":[
        {
            "category":"Organizations",
            "subcategory":"Labor Organization",
            "type":"Services"
        }
    ],
    "sg:phone":"+1   ",
    "sg:postcode":"06901",
    "sg:province":"CT",
    "wof:name":"AF L-C I O",
    "wof:placetype":"venue"
},
  "geometry": {"coordinates":[-73.537752,41.055502],"type":"Point"}
}