{
  "type": "Feature",
  "properties": {
    "addr:full":"200 Glastonbury Blvd Glastonbury CT 06033",
    "addr:housenumber":"200",
    "addr:postcode":"06033",
    "addr:street":"Glastonbury Blvd",
    "iso:country":"US",
    "sg:address":"200 Glastonbury Blvd",
    "sg:city":"Glastonbury",
    "sg:classifiers":[
        {
            "category":"Professional",
            "subcategory":"Computer Services",
            "type":"Services"
        }
    ],
    "sg:phone":"+1   ",
    "sg:postcode":"06033",
    "sg:province":"CT",
    "sg:tags":[
        "development",
        "software"
    ],
    "wof:name":"Veritas Software Corporation",
    "wof:placetype":"venue"
},
  "geometry": {"coordinates":[-72.623172,41.721029],"type":"Point"}
}