{
  "type": "Feature",
  "properties": {
    "iso:country":"US",
    "sg:address":"10 Railroad Ave",
    "sg:city":"Beacon Falls",
    "sg:classifiers":[
        {
            "category":"Professional",
            "type":"Services"
        }
    ],
    "sg:phone":"+1 203 723 6664",
    "sg:postcode":"06403",
    "sg:province":"CT",
    "sg:tags":[
        "establishment"
    ],
    "sg:website":"www.franzus.com",
    "wof:name":"Franzus Co Inc",
    "wof:placetype":"venue"
},
  "geometry": {"coordinates":[-73.064441,41.442417],"type":"Point"}
}