{
  "type": "Feature",
  "properties": {
    "iso:country":"US",
    "sg:address":"111 Kendall St",
    "sg:city":"New Haven",
    "sg:classifiers":[
        {
            "category":"Manufacturing",
            "subcategory":"Metals",
            "type":"Manufacturing & Wholesale Goods"
        }
    ],
    "sg:phone":"+1 203 469 2309",
    "sg:postcode":"06512",
    "sg:province":"CT",
    "wof:name":"Metal Masters",
    "wof:placetype":"venue"
},
  "geometry": {"coordinates":[-72.896063,41.291747],"type":"Point"}
}