{
  "type": "Feature",
  "properties": {
    "iso:country":"US",
    "sg:address":"41 Moody Ln",
    "sg:city":"Danbury",
    "sg:classifiers":[
        {
            "category":"Professional",
            "type":"Services"
        }
    ],
    "sg:phone":"+1 203 743 4777",
    "sg:postcode":"06811",
    "sg:province":"CT",
    "sg:tags":[
        "establishment"
    ],
    "wof:name":"Netcon",
    "wof:placetype":"venue"
},
  "geometry": {"coordinates":[-73.45352200000001,41.436738],"type":"Point"}
}