{
  "type": "Feature",
  "properties": {
    "iso:country":"US",
    "sg:address":"250 Harbor Dr Fl 3",
    "sg:city":"Stamford",
    "sg:classifiers":[
        {
            "category":"Communications",
            "subcategory":"Television Station",
            "type":"Services"
        }
    ],
    "sg:phone":"+1 203 965 6900",
    "sg:postcode":"06902",
    "sg:province":"CT",
    "sg:tags":[
        "broadcast",
        "representative"
    ],
    "wof:name":"Yankees Entertainment & Sports Network",
    "wof:placetype":"venue"
},
  "geometry": {"coordinates":[-73.53368399999999,41.034531],"type":"Point"}
}