{
  "type": "Feature",
  "properties": {
    "iso:country":"US",
    "sg:address":"1525 Stratford Ave",
    "sg:city":"Stratford",
    "sg:classifiers":[
        {
            "category":"Wholesale",
            "subcategory":"Chemicals & Plastics",
            "type":"Manufacturing & Wholesale Goods"
        }
    ],
    "sg:phone":"+1 203 377 5550",
    "sg:postcode":"06615",
    "sg:province":"CT",
    "sg:website":"www.flowpolymers.com",
    "wof:name":"Flow Polymers Inc",
    "wof:placetype":"venue"
},
  "geometry": {"coordinates":[-73.141074,41.185919],"type":"Point"}
}