{
  "type": "Feature",
  "properties": {
    "iso:country":"US",
    "sg:address":"4235 Madison Ave",
    "sg:city":"Trumbull",
    "sg:classifiers":[
        {
            "category":"Food & Beverages",
            "subcategory":"Groceries & Convenience Stores",
            "type":"Retail Goods"
        }
    ],
    "sg:phone":"+1 203 459 0248",
    "sg:postcode":"06611",
    "sg:province":"CT",
    "wof:name":"Best Edibles Market",
    "wof:placetype":"venue"
},
  "geometry": {"coordinates":[-73.23138400000001,41.23344],"type":"Point"}
}