{
  "type": "Feature",
  "properties": {
    "iso:country":"US",
    "sg:address":"191 Center St",
    "sg:city":"Wolcott",
    "sg:classifiers":[
        {
            "category":"Organizations",
            "subcategory":"Religious Organization",
            "type":"Services"
        }
    ],
    "sg:phone":"+1 203 879 2808",
    "sg:postcode":"06716",
    "sg:province":"CT",
    "sg:tags":[
        "clergy"
    ],
    "wof:name":"F P Haggard",
    "wof:placetype":"venue"
},
  "geometry": {"coordinates":[-72.97586699999999,41.601822],"type":"Point"}
}