{
  "type": "Feature",
  "properties": {
    "addr:full":"4150 Main St Bridgeport CT 06606",
    "addr:housenumber":"4150",
    "addr:postcode":"06606",
    "addr:street":"Main St",
    "iso:country":"US",
    "sg:address":"4150 Main St",
    "sg:city":"Bridgeport",
    "sg:classifiers":[
        {
            "category":"Bakery",
            "type":"Food & Drink"
        },
        {
            "category":"Coffee & Tea",
            "type":"Food & Drink"
        },
        {
            "category":"Bagels",
            "type":"Food & Drink"
        },
        {
            "category":"Donuts",
            "type":"Food & Drink"
        }
    ],
    "sg:menulink":"http://www.allmenus.com/ct/bridgeport/129786-dunkin-donuts/menu/",
    "sg:phone":"+1 203 374 0400",
    "sg:postcode":"06606",
    "sg:province":"CT",
    "sg:tags":[
        "american",
        "diner",
        "pastry"
    ],
    "wof:name":"Dunkin' Donuts",
    "wof:placetype":"venue"
},
  "geometry": {"coordinates":[-73.213753,41.216877],"type":"Point"}
}