{
  "type": "Feature",
  "properties": {
    "addr:full":"4 Hatch St Mystic CT 06355",
    "addr:housenumber":"4",
    "addr:postcode":"06355",
    "addr:street":"Hatch St",
    "iso:country":"US",
    "sg:address":"4 Hatch St",
    "sg:city":"Mystic",
    "sg:classifiers":[
        {
            "category":"Personal",
            "subcategory":"Beauty Salon",
            "type":"Services"
        }
    ],
    "sg:phone":"+1   ",
    "sg:postcode":"06355",
    "sg:province":"CT",
    "sg:tags":[
        "shop"
    ],
    "wof:name":"Peggys Cutting Crew",
    "wof:placetype":"venue"
},
  "geometry": {"coordinates":[-71.95732099999999,41.348706],"type":"Point"}
}