{
  "type": "Feature",
  "properties": {
    "iso:country":"US",
    "sg:address":"5051 Durham Rd",
    "sg:city":"Guilford",
    "sg:classifiers":[
        {
            "category":"Building & Trades",
            "subcategory":"Plumbing",
            "type":"Services"
        }
    ],
    "sg:phone":"+1 203 457 1017",
    "sg:postcode":"06437",
    "sg:province":"CT",
    "sg:tags":[
        "contractor"
    ],
    "wof:name":"Dae Plumb Heat Excavating",
    "wof:placetype":"venue"
},
  "geometry": {"coordinates":[-72.690152,41.417046],"type":"Point"}
}