{
  "type": "Feature",
  "properties": {
    "addr:full":"15 Branch St Waterbury CT 06704",
    "addr:housenumber":"15",
    "addr:postcode":"06704",
    "addr:street":"Branch St Waterbury Ct",
    "iso:country":"US",
    "sg:address":"15 Branch St",
    "sg:city":"Waterbury",
    "sg:classifiers":[
        {
            "category":"Utilities",
            "subcategory":"Refuse",
            "type":"Services"
        }
    ],
    "sg:phone":"+1 203 759 5768",
    "sg:postcode":"06704",
    "sg:province":"CT",
    "sg:tags":[
        "system"
    ],
    "wof:name":"Lees Rubbish Removal Melv",
    "wof:placetype":"venue"
},
  "geometry": {"coordinates":[-73.02522500000001,41.563607],"type":"Point"}
}