{
  "type": "Feature",
  "properties": {
    "addr:full":"72 Ball Pond Rd Danbury CT 06811",
    "addr:housenumber":"72",
    "addr:postcode":"06811",
    "addr:street":"Ball Pond Rd",
    "iso:country":"US",
    "sg:address":"72 Ball Pond Rd",
    "sg:city":"Danbury",
    "sg:classifiers":[
        {
            "category":"Wholesale",
            "subcategory":"Motor Vehicles",
            "type":"Manufacturing & Wholesale Goods"
        }
    ],
    "sg:phone":"+1 203 746 9935",
    "sg:postcode":"06811",
    "sg:province":"CT",
    "wof:name":"Auto Brokers",
    "wof:placetype":"venue"
},
  "geometry": {"coordinates":[-73.517138,41.444165],"type":"Point"}
}