{
  "type": "Feature",
  "properties": {
    "iso:country":"US",
    "sg:address":"133 School St",
    "sg:city":"Danielson",
    "sg:classifiers":[
        {
            "category":"Professional",
            "subcategory":"Lawyer & Legal Services",
            "type":"Services"
        }
    ],
    "sg:phone":"+1 860 774 4163",
    "sg:postcode":"06239",
    "sg:province":"CT",
    "sg:tags":[
        "employee",
        "benefit",
        "worker",
        "attorney",
        "compensation"
    ],
    "sg:website":"http://www.theweisslawfirm.com",
    "wof:name":"Weiss & Associates LLC",
    "wof:placetype":"venue"
},
  "geometry": {"coordinates":[-71.88189800000001,41.8053],"type":"Point"}
}