{
  "type": "Feature",
  "properties": {
    "iso:country":"US",
    "sg:address":"1870 E Main St",
    "sg:city":"Waterbury",
    "sg:classifiers":[
        {
            "category":"Food & Beverages",
            "subcategory":"Bakery",
            "type":"Retail Goods"
        }
    ],
    "sg:phone":"+1 203 756 2789",
    "sg:postcode":"06705",
    "sg:province":"CT",
    "sg:tags":[
        "baker"
    ],
    "wof:name":"Dacruz Cafe & Bakery",
    "wof:placetype":"venue"
},
  "geometry": {"coordinates":[-73.011932,41.544919],"type":"Point"}
}