{
  "type": "Feature",
  "properties": {
    "iso:country":"US",
    "sg:address":"5 Silver Hill Rd",
    "sg:city":"Easton",
    "sg:classifiers":[
        {
            "category":"Recreation",
            "type":"Entertainment"
        }
    ],
    "sg:phone":"+1 203 268 9994",
    "sg:postcode":"06612",
    "sg:province":"CT",
    "sg:tags":[
        "camp"
    ],
    "wof:name":"Pee Wee Horse Farm",
    "wof:placetype":"venue"
},
  "geometry": {"coordinates":[-73.30638500000001,41.2757],"type":"Point"}
}