{
  "type": "Feature",
  "properties": {
    "iso:country":"US",
    "sg:address":"44 Elm St",
    "sg:city":"West Haven",
    "sg:classifiers":[
        {
            "category":"Autos & Motor Vehicles",
            "subcategory":"Fuel & Gas Station",
            "type":"Retail Goods"
        }
    ],
    "sg:phone":"+1 203 932 6322",
    "sg:postcode":"06516",
    "sg:province":"CT",
    "sg:tags":[
        "oil"
    ],
    "wof:name":"Superior Amoco",
    "wof:placetype":"venue"
},
  "geometry": {"coordinates":[-72.94086799999999,41.279427],"type":"Point"}
}