{
  "type": "Feature",
  "properties": {
    "addr:full":"15 Mullen Rd Enfield CT 06082",
    "addr:housenumber":"15",
    "addr:postcode":"06082",
    "addr:street":"Mullen Rd",
    "iso:country":"US",
    "sg:address":"15 Mullen Rd",
    "sg:city":"Enfield",
    "sg:classifiers":[
        {
            "category":"Utilities",
            "subcategory":"Refuse",
            "type":"Services"
        }
    ],
    "sg:phone":"+1 860 749 5279",
    "sg:postcode":"06082",
    "sg:province":"CT",
    "sg:tags":[
        "system"
    ],
    "wof:name":"F&G Realty Recycling LLC",
    "wof:placetype":"venue"
},
  "geometry": {"coordinates":[-72.586966,41.944241],"type":"Point"}
}