{
  "type": "Feature",
  "properties": {
    "iso:country":"US",
    "sg:address":"183 North St",
    "sg:city":"Watertown",
    "sg:classifiers":[
        {
            "category":"Real Estate",
            "subcategory":"Developer",
            "type":"Services"
        }
    ],
    "sg:phone":"+1 860 274 4151",
    "sg:postcode":"06795",
    "sg:province":"CT",
    "sg:tags":[
        "cemetery"
    ],
    "wof:name":"Evergreen Cemetery Assoc",
    "wof:placetype":"venue"
},
  "geometry": {"coordinates":[-73.122434,41.607067],"type":"Point"}
}