{
  "type": "Feature",
  "properties": {
    "addr:full":"1201 Boston Post Rd Meriden CT 06437",
    "addr:housenumber":"1201",
    "addr:postcode":"06437",
    "addr:street":"Boston Post Rd",
    "iso:country":"US",
    "sg:address":"1201 Boston Post Rd",
    "sg:city":"Meriden",
    "sg:classifiers":[
        {
            "category":"Shopping",
            "subcategory":"Computers & Home Electronics",
            "type":"Retail Goods"
        }
    ],
    "sg:phone":"+1 203 238 3564",
    "sg:postcode":"06437",
    "sg:province":"CT",
    "sg:tags":[
        "game",
        "video"
    ],
    "wof:name":"EBX",
    "wof:placetype":"venue"
},
  "geometry": {"coordinates":[-72.68938199999999,41.287727],"type":"Point"}
}