{
  "type": "Feature",
  "properties": {
    "iso:country":"US",
    "sg:address":"81 Beaver Brook Rd",
    "sg:city":"Danbury",
    "sg:classifiers":[
        {
            "category":"Professional",
            "subcategory":"Business Services",
            "type":"Services"
        }
    ],
    "sg:phone":"+1   ",
    "sg:postcode":"06810",
    "sg:province":"CT",
    "wof:name":"Cahalan Design LLC",
    "wof:placetype":"venue"
},
  "geometry": {"coordinates":[-73.42700499999999,41.406817],"type":"Point"}
}