{
  "type": "Feature",
  "properties": {
    "iso:country":"US",
    "sg:address":"54 Lake Rd",
    "sg:city":"Middlefield",
    "sg:classifiers":[
        {
            "category":"Building & Trades",
            "subcategory":"Plumbing",
            "type":"Services"
        }
    ],
    "sg:phone":"+1 860 349 8092",
    "sg:postcode":"06455",
    "sg:province":"CT",
    "sg:tags":[
        "plumbing",
        "contractor"
    ],
    "wof:name":"Frederick L Neils",
    "wof:placetype":"venue"
},
  "geometry": {"coordinates":[-72.730411,41.52101],"type":"Point"}
}