{
  "type": "Feature",
  "properties": {
    "addr:full":"71 Grist Mill Rd Monroe CT 06468",
    "addr:housenumber":"71",
    "addr:postcode":"06468",
    "addr:street":"Grist Mill Rd",
    "iso:country":"US",
    "sg:address":"71 Grist Mill Rd",
    "sg:city":"Monroe",
    "sg:classifiers":[
        {
            "category":"Manufacturing",
            "subcategory":"Paper Products",
            "type":"Manufacturing & Wholesale Goods"
        }
    ],
    "sg:phone":"+1 203 445 8004",
    "sg:postcode":"06468",
    "sg:province":"CT",
    "sg:tags":[
        "box"
    ],
    "wof:name":"Rock-Tenn Co",
    "wof:placetype":"venue"
},
  "geometry": {"coordinates":[-73.206216,41.365848],"type":"Point"}
}