{
  "type": "Feature",
  "properties": {
    "iso:country":"US",
    "sg:address":"31 Crest Rd",
    "sg:city":"Ridgefield",
    "sg:classifiers":[
        {
            "category":"Building & Trades",
            "subcategory":"Landscaping Services",
            "type":"Services"
        }
    ],
    "sg:phone":"+1 203 431 2924",
    "sg:postcode":"06877",
    "sg:province":"CT",
    "sg:tags":[
        "landscape"
    ],
    "wof:name":"Custom Lawn Care",
    "wof:placetype":"venue"
},
  "geometry": {"coordinates":[-73.49433399999999,41.337335],"type":"Point"}
}