{
  "type": "Feature",
  "properties": {
    "addr:full":"9 Standish Dr Marlborough CT 06447",
    "addr:housenumber":"9",
    "addr:postcode":"06447",
    "addr:street":"Standish Dr",
    "iso:country":"US",
    "sg:address":"9 Standish Dr",
    "sg:city":"Marlborough",
    "sg:classifiers":[
        {
            "category":"Professional",
            "type":"Services"
        }
    ],
    "sg:phone":"+1 860 295 0385",
    "sg:postcode":"06447",
    "sg:province":"CT",
    "wof:name":"Dennis Duchesneau",
    "wof:placetype":"venue"
},
  "geometry": {"coordinates":[-72.464861,41.6748],"type":"Point"}
}