{
  "type": "Feature",
  "properties": {
    "addr:full":"9 Benham Hill Pl Hamden CT 06514",
    "addr:housenumber":"9",
    "addr:postcode":"06514",
    "addr:street":"Benham Hill Pl",
    "iso:country":"US",
    "sg:address":"9 Benham Hill Pl",
    "sg:city":"Hamden",
    "sg:classifiers":[
        {
            "category":"Building & Trades",
            "subcategory":"Construction",
            "type":"Services"
        }
    ],
    "sg:phone":"+1 203 407 1120",
    "sg:postcode":"06514",
    "sg:province":"CT",
    "sg:tags":[
        "designer",
        "dealer",
        "pool",
        "swimming"
    ],
    "wof:name":"Florio's Pool Table Instltn",
    "wof:placetype":"venue"
},
  "geometry": {"coordinates":[-72.95887500000001,41.367013],"type":"Point"}
}