{
  "type": "Feature",
  "properties": {
    "iso:country":"US",
    "sg:address":"30 Christian Ln",
    "sg:city":"Newington",
    "sg:classifiers":[
        {
            "category":"Professional",
            "subcategory":"Engineering",
            "type":"Services"
        }
    ],
    "sg:phone":"+1   ",
    "sg:postcode":"06111",
    "sg:province":"CT",
    "sg:tags":[
        "consultant"
    ],
    "wof:name":"Washington Infrastructure Svcs",
    "wof:placetype":"venue"
},
  "geometry": {"coordinates":[-72.750124,41.652678],"type":"Point"}
}