{
  "type": "Feature",
  "properties": {
    "addr:full":"387 N Windham Rd North Windham CT 06256",
    "addr:housenumber":"387",
    "addr:postcode":"06256",
    "addr:street":"N Windham Rd North Windham Ct",
    "iso:country":"US",
    "sg:address":"387 N Windham Rd",
    "sg:city":"North Windham",
    "sg:classifiers":[
        {
            "category":"Health Services",
            "subcategory":"Doctor",
            "type":"Services"
        }
    ],
    "sg:phone":"+1   ",
    "sg:postcode":"06256",
    "sg:province":"CT",
    "sg:tags":[
        "medical"
    ],
    "wof:name":"Windham Pediatrics",
    "wof:placetype":"venue"
},
  "geometry": {"coordinates":[-72.166774,41.719221],"type":"Point"}
}