{
  "type": "Feature",
  "properties": {
    "iso:country":"US",
    "sg:address":"325 Main St",
    "sg:city":"Portland",
    "sg:classifiers":[
        {
            "category":"Health Services",
            "subcategory":"Hospital",
            "type":"Services"
        }
    ],
    "sg:phone":"+1   ",
    "sg:postcode":"06480",
    "sg:province":"CT",
    "sg:tags":[
        "specialty"
    ],
    "wof:name":"Stonehaven Program",
    "wof:placetype":"venue"
},
  "geometry": {"coordinates":[-72.637259,41.577442],"type":"Point"}
}