{
  "type": "Feature",
  "properties": {
    "iso:country":"US",
    "sg:address":"123 Pratt St",
    "sg:city":"Fairfield",
    "sg:classifiers":[
        {
            "category":"Professional",
            "subcategory":"Computer Services",
            "type":"Services"
        }
    ],
    "sg:phone":"+1   ",
    "sg:postcode":"06489",
    "sg:province":"CT",
    "sg:tags":[
        "engineering",
        "system"
    ],
    "wof:name":"Rob-Techcom",
    "wof:placetype":"venue"
},
  "geometry": {"coordinates":[-72.853911,41.555721],"type":"Point"}
}