{
  "type": "Feature",
  "properties": {
    "addr:full":"82 Hartford Tpke Hampton CT 06247",
    "addr:housenumber":"82",
    "addr:postcode":"06247",
    "addr:street":"Hartford Tpke Hampton Ct",
    "iso:country":"US",
    "sg:address":"82 Hartford Tpke",
    "sg:city":"Hampton",
    "sg:classifiers":[
        {
            "category":"Insurance",
            "subcategory":"Insurance Agent",
            "type":"Services"
        }
    ],
    "sg:phone":"+1 860 455 2015",
    "sg:postcode":"06247",
    "sg:province":"CT",
    "wof:name":"Baio Insurance Agency",
    "wof:placetype":"venue"
},
  "geometry": {"coordinates":[-72.071225,41.775343],"type":"Point"}
}