{
  "type": "Feature",
  "properties": {
    "addr:full":"80 Simmons Rd East Hartford CT 06118",
    "addr:housenumber":"80",
    "addr:postcode":"06118",
    "addr:street":"Simmons Rd East;Ct",
    "iso:country":"US",
    "sg:address":"80 Simmons Rd",
    "sg:city":"East Hartford",
    "sg:classifiers":[
        {
            "category":"Real Estate",
            "subcategory":"Real Estate Operator",
            "type":"Services"
        }
    ],
    "sg:phone":"+1 860 568 7700",
    "sg:postcode":"06118",
    "sg:province":"CT",
    "sg:tags":[
        "building",
        "apartment"
    ],
    "wof:name":"Eastbrook Towers Apts",
    "wof:placetype":"venue"
},
  "geometry": {"coordinates":[-72.618109,41.766184],"type":"Point"}
}