{
  "type": "Feature",
  "properties": {
    "addr:full":"34 Bellefair Rd Port Chester CT 10573",
    "addr:housenumber":"34",
    "addr:postcode":"10573",
    "addr:street":"Bellefair Rd",
    "iso:country":"US",
    "sg:address":"34 Bellefair Rd",
    "sg:city":"Port Chester",
    "sg:classifiers":[
        {
            "category":"Wholesale",
            "subcategory":"Poultry",
            "type":"Manufacturing & Wholesale Goods"
        }
    ],
    "sg:phone":"+1 914 690 2831",
    "sg:postcode":"10573",
    "sg:province":"CT",
    "sg:tags":[
        "turkey",
        "product",
        "broker",
        "processed"
    ],
    "wof:name":"Ross Enterprises Inc",
    "wof:placetype":"venue"
},
  "geometry": {"coordinates":[-73.69288400000001,41.051156],"type":"Point"}
}