{
  "type": "Feature",
  "properties": {
    "iso:country":"US",
    "sg:address":"153 1st Ave",
    "sg:city":"Stratford",
    "sg:classifiers":[
        {
            "category":"Professional",
            "type":"Services"
        }
    ],
    "sg:phone":"+1 203 375 9600",
    "sg:postcode":"06615",
    "sg:province":"CT",
    "wof:name":"Lilly Model Corp",
    "wof:placetype":"venue"
},
  "geometry": {"coordinates":[-73.12724900000001,41.151654],"type":"Point"}
}