{
  "type": "Feature",
  "properties": {
    "addr:full":"54 Columbus Ave Stratford CT 06615",
    "addr:housenumber":"54",
    "addr:postcode":"06615",
    "addr:street":"Columbus Ave",
    "iso:country":"US",
    "sg:address":"54 Columbus Ave",
    "sg:city":"Stratford",
    "sg:classifiers":[
        {
            "category":"Shopping",
            "subcategory":"Gifts & Souvenirs",
            "type":"Retail Goods"
        }
    ],
    "sg:phone":"+1 203 377 8742",
    "sg:postcode":"06615",
    "sg:province":"CT",
    "sg:tags":[
        "shop"
    ],
    "wof:name":"Michael Burnett",
    "wof:placetype":"venue"
},
  "geometry": {"coordinates":[-73.14453399999999,41.176556],"type":"Point"}
}