{
  "type": "Feature",
  "properties": {
    "addr:full":"25 Lemont Rd Groton CT 06340",
    "addr:housenumber":"25",
    "addr:postcode":"06340",
    "addr:street":"Lemont Rd Groton Ct",
    "iso:country":"US",
    "sg:address":"25 Lemont Rd",
    "sg:city":"Groton",
    "sg:classifiers":[
        {
            "category":"Recreation",
            "type":"Entertainment"
        }
    ],
    "sg:phone":"+1   ",
    "sg:postcode":"06340",
    "sg:province":"CT",
    "wof:name":"2b Sailing LLC",
    "wof:placetype":"venue"
},
  "geometry": {"coordinates":[-72.013167,41.349069],"type":"Point"}
}