{
  "type": "Feature",
  "properties": {
    "iso:country":"US",
    "sg:address":"136 Mountain View Rd",
    "sg:city":"Somers",
    "sg:classifiers":[
        {
            "category":"Professional",
            "type":"Services"
        }
    ],
    "sg:phone":"+1 860 749 1197",
    "sg:postcode":"06071",
    "sg:province":"CT",
    "wof:name":"Garry Ball",
    "wof:placetype":"venue"
},
  "geometry": {"coordinates":[-72.43797000000001,41.969939],"type":"Point"}
}