{
  "type": "Feature",
  "properties": {
    "iso:country":"US",
    "sg:address":"12 Chimney Dr",
    "sg:city":"Bethel",
    "sg:classifiers":[
        {
            "category":"Banks & Credit Unions",
            "subcategory":"Investment Brokerage",
            "type":"Services"
        }
    ],
    "sg:phone":"+1 203 743 1141",
    "sg:postcode":"06801",
    "sg:province":"CT",
    "sg:tags":[
        "company",
        "holding"
    ],
    "wof:name":"Value Asset Management Inc",
    "wof:placetype":"venue"
},
  "geometry": {"coordinates":[-73.400064,41.410449],"type":"Point"}
}