{
  "type": "Feature",
  "properties": {
    "iso:country":"US",
    "sg:address":"592 North St",
    "sg:city":"Greenwich",
    "sg:classifiers":[
        {
            "category":"Social Services",
            "type":"Services"
        }
    ],
    "sg:phone":"+1 203 869 0440",
    "sg:postcode":"06830",
    "sg:province":"CT",
    "wof:name":"Susan Ruben",
    "wof:placetype":"venue"
},
  "geometry": {"coordinates":[-73.62786199999999,41.086643],"type":"Point"}
}