{
  "type": "Feature",
  "properties": {
    "iso:country":"US",
    "sg:address":"108 Stetson Rd",
    "sg:city":"Brooklyn",
    "sg:classifiers":[
        {
            "category":"Organizations",
            "subcategory":"Religious Organization",
            "type":"Services"
        }
    ],
    "sg:phone":"+1   ",
    "sg:postcode":"06234",
    "sg:province":"CT",
    "wof:name":"Unitarian Unvrslist Soc Brklyn",
    "wof:placetype":"venue"
},
  "geometry": {"coordinates":[-72.008279,41.778863],"type":"Point"}
}