{
  "type": "Feature",
  "properties": {
    "addr:full":"1593 King St Enfield CT 06082",
    "addr:housenumber":"1593",
    "addr:postcode":"06082",
    "addr:street":"King St Enfield Ct",
    "iso:country":"US",
    "sg:address":"1593 King St",
    "sg:city":"Enfield",
    "sg:classifiers":[
        {
            "category":"Personal",
            "subcategory":"Beauty Salon",
            "type":"Services"
        }
    ],
    "sg:phone":"+1   ",
    "sg:postcode":"06082",
    "sg:province":"CT",
    "sg:tags":[
        "shop"
    ],
    "wof:name":"One On One Hair Design",
    "wof:placetype":"venue"
},
  "geometry": {"coordinates":[-72.60105299999999,41.953257],"type":"Point"}
}