{
  "type": "Feature",
  "properties": {
    "iso:country":"US",
    "sg:address":"26 W Whisconier Rd",
    "sg:city":"Brookfield",
    "sg:classifiers":[
        {
            "category":"Building & Trades",
            "subcategory":"Construction",
            "type":"Services"
        }
    ],
    "sg:phone":"+1 203 775 3326",
    "sg:postcode":"06804",
    "sg:province":"CT",
    "sg:tags":[
        "excavating",
        "contractor"
    ],
    "wof:name":"Skippy Paving & Excavation Co",
    "wof:placetype":"venue"
},
  "geometry": {"coordinates":[-73.377893,41.441518],"type":"Point"}
}