{
  "type": "Feature",
  "properties": {
    "addr:full":"30 Forest Pkwy Shelton CT 06484",
    "addr:housenumber":"30",
    "addr:postcode":"06484",
    "addr:street":"Forest Pkwy",
    "iso:country":"US",
    "sg:address":"30 Forest Pkwy",
    "sg:city":"Shelton",
    "sg:classifiers":[
        {
            "category":"Manufacturing",
            "subcategory":"Metals",
            "type":"Manufacturing & Wholesale Goods"
        }
    ],
    "sg:phone":"+1 203 925 8525",
    "sg:postcode":"06484",
    "sg:province":"CT",
    "sg:tags":[
        "stamp"
    ],
    "sg:website":"www.preferredtool.com",
    "wof:name":"Preferred Tool & Die Inc",
    "wof:placetype":"venue"
},
  "geometry": {"coordinates":[-73.107868,41.286189],"type":"Point"}
}