{
  "type": "Feature",
  "properties": {
    "addr:full":"43 Summer Hill Rd Middletown CT 06457",
    "addr:housenumber":"43",
    "addr:postcode":"06457",
    "addr:street":"Summer Hill Rd",
    "iso:country":"US",
    "sg:address":"43 Summer Hill Rd",
    "sg:city":"Middletown",
    "sg:classifiers":[
        {
            "category":"Food & Beverages",
            "subcategory":"Bakery",
            "type":"Retail Goods"
        }
    ],
    "sg:phone":"+1 860 632 2143",
    "sg:postcode":"06457",
    "sg:province":"CT",
    "wof:name":"Delightful Desserts Bakery",
    "wof:placetype":"venue"
},
  "geometry": {"coordinates":[-72.612208,41.53029],"type":"Point"}
}