{
  "type": "Feature",
  "properties": {
    "iso:country":"US",
    "sg:address":"697 W Main St",
    "sg:city":"Cheshire",
    "sg:classifiers":[
        {
            "category":"Professional",
            "subcategory":"Management & Consulting",
            "type":"Services"
        }
    ],
    "sg:phone":"+1   ",
    "sg:postcode":"06410",
    "sg:province":"CT",
    "wof:name":"Robert Sutak",
    "wof:placetype":"venue"
},
  "geometry": {"coordinates":[-72.919483,41.511991],"type":"Point"}
}