{
  "type": "Feature",
  "properties": {
    "iso:country":"US",
    "sg:address":"941 Main St",
    "sg:city":"Hartford",
    "sg:classifiers":[
        {
            "category":"Shopping",
            "subcategory":"Clothing, Apparel, & Fashions",
            "type":"Retail Goods"
        }
    ],
    "sg:phone":"+1 860 527 2350",
    "sg:postcode":"06103",
    "sg:province":"CT",
    "wof:name":"Abes Fashions",
    "wof:placetype":"venue"
},
  "geometry": {"coordinates":[-72.67313900000001,41.768102],"type":"Point"}
}