{
  "type": "Feature",
  "properties": {
    "iso:country":"US",
    "sg:address":"92 Seventy Acres Rd",
    "sg:city":"Redding",
    "sg:classifiers":[
        {
            "category":"Retail",
            "subcategory":"Self-service Laundry",
            "type":"Services"
        }
    ],
    "sg:phone":"+1   ",
    "sg:postcode":"06896",
    "sg:province":"CT",
    "sg:tags":[
        "coin"
    ],
    "wof:name":"Washing Well",
    "wof:placetype":"venue"
},
  "geometry": {"coordinates":[-73.42944799999999,41.286557],"type":"Point"}
}