{
  "type": "Feature",
  "properties": {
    "addr:full":"62 Pine St Bristol CT 06010",
    "addr:housenumber":"62",
    "addr:postcode":"06010",
    "addr:street":"Pine St",
    "iso:country":"US",
    "sg:address":"62 Pine St",
    "sg:city":"Bristol",
    "sg:classifiers":[
        {
            "category":"Real Estate",
            "subcategory":"Real Estate Agent",
            "type":"Services"
        }
    ],
    "sg:phone":"+1 860 589 4834",
    "sg:postcode":"06010",
    "sg:province":"CT",
    "wof:name":"Michele Dominic RE Brk",
    "wof:placetype":"venue"
},
  "geometry": {"coordinates":[-72.92132700000001,41.666654],"type":"Point"}
}