{
  "type": "Feature",
  "properties": {
    "iso:country":"US",
    "sg:address":"127 Main St N",
    "sg:city":"Woodbury",
    "sg:classifiers":[
        {
            "category":"Real Estate",
            "subcategory":"Real Estate Operator",
            "type":"Services"
        }
    ],
    "sg:phone":"+1 203 263 0006",
    "sg:postcode":"06798",
    "sg:province":"CT",
    "sg:tags":[
        "property",
        "lessor"
    ],
    "wof:name":"Northwood LLC",
    "wof:placetype":"venue"
},
  "geometry": {"coordinates":[-73.20374099999999,41.552796],"type":"Point"}
}