{
  "type": "Feature",
  "properties": {
    "iso:country":"US",
    "sg:address":"1 Bartlett St",
    "sg:city":"Meriden",
    "sg:classifiers":[
        {
            "category":"Retail",
            "subcategory":"Laundry & Dry Cleaning",
            "type":"Services"
        }
    ],
    "sg:phone":"+1   ",
    "sg:postcode":"06451",
    "sg:province":"CT",
    "wof:name":"Naci Elvita",
    "wof:placetype":"venue"
},
  "geometry": {"coordinates":[-72.804244,41.543133],"type":"Point"}
}