{
  "type": "Feature",
  "properties": {
    "addr:full":"1839 Silas Deane Hwy Rocky Hill CT 06067",
    "addr:housenumber":"1839",
    "addr:postcode":"06067",
    "addr:street":"Silas Deane Hwy Rocky Hill Ct",
    "iso:country":"US",
    "sg:address":"1839 Silas Deane Hwy",
    "sg:city":"Rocky Hill",
    "sg:classifiers":[
        {
            "category":"Professional",
            "subcategory":"Lawyer & Legal Services",
            "type":"Services"
        }
    ],
    "sg:phone":"+1   ",
    "sg:postcode":"06067",
    "sg:province":"CT",
    "wof:name":"Cathryn-Jean Fleming",
    "wof:placetype":"venue"
},
  "geometry": {"coordinates":[-72.651357,41.677529],"type":"Point"}
}