{
  "type": "Feature",
  "properties": {
    "addr:full":"117 Brushy Hill Rd Danbury CT 06810",
    "addr:housenumber":"117",
    "addr:postcode":"06810",
    "addr:street":"Brushy Hill Rd",
    "iso:country":"US",
    "sg:address":"117 Brushy Hill Rd",
    "sg:city":"Danbury",
    "sg:classifiers":[
        {
            "category":"Building & Trades",
            "subcategory":"Construction",
            "type":"Services"
        }
    ],
    "sg:phone":"+1 203 790 6083",
    "sg:postcode":"06810",
    "sg:province":"CT",
    "sg:tags":[
        "wallcoverings-installation",
        "wallpaper",
        "painting",
        "contractor"
    ],
    "wof:name":"Petes Painting & Decorating",
    "wof:placetype":"venue"
},
  "geometry": {"coordinates":[-73.4461,41.365224],"type":"Point"}
}