{
  "type": "Feature",
  "properties": {
    "iso:country":"US",
    "sg:address":"510 W Main St",
    "sg:city":"Branford",
    "sg:classifiers":[
        {
            "category":"Personal",
            "subcategory":"Beauty Salon",
            "type":"Services"
        }
    ],
    "sg:phone":"+1   ",
    "sg:postcode":"06405",
    "sg:province":"CT",
    "sg:tags":[
        "shop",
        "barber"
    ],
    "wof:name":"European Touch Unisex Salon",
    "wof:placetype":"venue"
},
  "geometry": {"coordinates":[-72.84554,41.279572],"type":"Point"}
}