{
  "type": "Feature",
  "properties": {
    "iso:country":"US",
    "sg:address":"8 Timber Ln",
    "sg:city":"Darien",
    "sg:classifiers":[
        {
            "category":"Real Estate",
            "subcategory":"Real Estate Agent",
            "type":"Services"
        }
    ],
    "sg:phone":"+1 203 655 0657",
    "sg:postcode":"06820",
    "sg:province":"CT",
    "sg:tags":[
        "manager",
        "or"
    ],
    "wof:name":"Barton Properties",
    "wof:placetype":"venue"
},
  "geometry": {"coordinates":[-73.495795,41.10256],"type":"Point"}
}