{
  "type": "Feature",
  "properties": {
    "addr:full":"1100 Boston Ave Bridgeport CT 06610",
    "addr:housenumber":"1100",
    "addr:postcode":"06610",
    "addr:street":"Boston Ave",
    "iso:country":"US",
    "sg:address":"1100 Boston Ave",
    "sg:city":"Bridgeport",
    "sg:classifiers":[
        {
            "category":"Real Estate",
            "subcategory":"Real Estate Operator",
            "type":"Services"
        }
    ],
    "sg:phone":"+1 203 367 0725",
    "sg:postcode":"06610",
    "sg:province":"CT",
    "sg:tags":[
        "industrial",
        "parks"
    ],
    "wof:name":"Boston Avenue Industrial Park",
    "wof:placetype":"venue"
},
  "geometry": {"coordinates":[-73.172139,41.193368],"type":"Point"}
}