{
  "type": "Feature",
  "properties": {
    "iso:country":"US",
    "sg:address":"15 Forest Ln",
    "sg:city":"Wilton",
    "sg:classifiers":[
        {
            "category":"Building & Trades",
            "subcategory":"Construction",
            "type":"Services"
        }
    ],
    "sg:phone":"+1 203 762 8018",
    "sg:postcode":"06897",
    "sg:province":"CT",
    "sg:tags":[
        "excavation",
        "contractor"
    ],
    "wof:name":"David Smith Excavating",
    "wof:placetype":"venue"
},
  "geometry": {"coordinates":[-73.47388599999999,41.204545],"type":"Point"}
}