{
  "type": "Feature",
  "properties": {
    "addr:full":"115 E Common Rd Easton CT 06612",
    "addr:housenumber":"115",
    "addr:postcode":"06612",
    "addr:street":"E Common Rd",
    "iso:country":"US",
    "sg:address":"115 E Common Rd",
    "sg:city":"Easton",
    "sg:classifiers":[
        {
            "category":"Travel",
            "subcategory":"Hotels & Motels",
            "type":"Entertainment"
        }
    ],
    "sg:phone":"+1   ",
    "sg:postcode":"06612",
    "sg:province":"CT",
    "wof:name":"Smilezzz Hospitality LLC",
    "wof:placetype":"venue"
},
  "geometry": {"coordinates":[-73.314305,41.216194],"type":"Point"}
}