{
  "type": "Feature",
  "properties": {
    "iso:country":"US",
    "sg:address":"508 Roxbury Rd",
    "sg:city":"Stamford",
    "sg:classifiers":[
        {
            "category":"Professional",
            "type":"Services"
        }
    ],
    "sg:phone":"+1 203 329 0216",
    "sg:postcode":"06902",
    "sg:province":"CT",
    "wof:name":"Tupelo Tree & Land Inc",
    "wof:placetype":"venue"
},
  "geometry": {"coordinates":[-73.57802,41.097965],"type":"Point"}
}