{
  "type": "Feature",
  "properties": {
    "iso:country":"US",
    "sg:address":"757 Madison Ave",
    "sg:city":"Bridgeport",
    "sg:classifiers":[
        {
            "category":"Restaurant",
            "type":"Food & Drink"
        }
    ],
    "sg:phone":"+1 203 696 0303",
    "sg:postcode":"06606",
    "sg:province":"CT",
    "sg:tags":[
        "caterer"
    ],
    "wof:name":"Madison Portugues Catering",
    "wof:placetype":"venue"
},
  "geometry": {"coordinates":[-73.204514,41.192192],"type":"Point"}
}