{
  "type": "Feature",
  "properties": {
    "addr:full":"173 Quaker Farms Rd Oxford CT 06478",
    "addr:housenumber":"173",
    "addr:postcode":"06478",
    "addr:street":"Quaker Farms Rd",
    "iso:country":"US",
    "sg:address":"173 Quaker Farms Rd",
    "sg:city":"Oxford",
    "sg:classifiers":[
        {
            "category":"Shopping",
            "subcategory":"Clothing, Apparel, & Fashions",
            "type":"Retail Goods"
        }
    ],
    "sg:phone":"+1 203 888 9456",
    "sg:postcode":"06478",
    "sg:province":"CT",
    "sg:tags":[
        "shop",
        "bridal"
    ],
    "wof:name":"Lizabeth's Bridal Salon",
    "wof:placetype":"venue"
},
  "geometry": {"coordinates":[-73.141345,41.396896],"type":"Point"}
}