{
  "type": "Feature",
  "properties": {
    "iso:country":"US",
    "sg:address":"700 Burnside Ave",
    "sg:city":"East Hartford",
    "sg:classifiers":[
        {
            "category":"Shopping",
            "subcategory":"Pharmacy",
            "type":"Retail Goods"
        }
    ],
    "sg:phone":"+1 860 289 2488",
    "sg:postcode":"06108",
    "sg:province":"CT",
    "wof:name":"Arthur Drugs 7",
    "wof:placetype":"venue"
},
  "geometry": {"coordinates":[-72.608411,41.779617],"type":"Point"}
}