{
  "type": "Feature",
  "properties": {
    "addr:full":"500 Woodside Ave Middlebury CT 06762",
    "addr:housenumber":"500",
    "addr:postcode":"06762",
    "addr:street":"Woodside Ave",
    "iso:country":"US",
    "sg:address":"500 Woodside Ave",
    "sg:city":"Middlebury",
    "sg:classifiers":[
        {
            "category":"Health Services",
            "subcategory":"Nursing And Care Facility",
            "type":"Services"
        }
    ],
    "sg:phone":"+1 203 758 2936",
    "sg:postcode":"06762",
    "sg:province":"CT",
    "sg:tags":[
        "home",
        "rest"
    ],
    "wof:name":"Woodside Heights",
    "wof:placetype":"venue"
},
  "geometry": {"coordinates":[-73.08827700000001,41.53824],"type":"Point"}
}