{
  "type": "Feature",
  "properties": {
    "iso:country":"US",
    "sg:address":"600 Mount Carmel Ave",
    "sg:city":"Hamden",
    "sg:classifiers":[
        {
            "category":"Professional",
            "subcategory":"Lawyer & Legal Services",
            "type":"Services"
        }
    ],
    "sg:phone":"+1 203 248 8545",
    "sg:postcode":"06518",
    "sg:province":"CT",
    "sg:tags":[
        "attorney"
    ],
    "wof:name":"Amerizone",
    "wof:placetype":"venue"
},
  "geometry": {"coordinates":[-72.89144400000001,41.422494],"type":"Point"}
}