{
  "type": "Feature",
  "properties": {
    "addr:full":"1140 Main St Stratford CT 06615",
    "addr:housenumber":"1140",
    "addr:postcode":"06615",
    "addr:street":"Main St",
    "iso:country":"US",
    "sg:address":"1140 Main St",
    "sg:city":"Stratford",
    "sg:classifiers":[
        {
            "category":"Restaurant",
            "type":"Food & Drink"
        }
    ],
    "sg:menulink":"http://www.allmenus.com/ct/stratford/144036-subway/menu/",
    "sg:phone":"+1 203 378 4020",
    "sg:postcode":"06615",
    "sg:province":"CT",
    "sg:tags":[
        "american",
        "sandwich"
    ],
    "wof:name":"Subway",
    "wof:placetype":"venue"
},
  "geometry": {"coordinates":[-73.13001300000001,41.175716],"type":"Point"}
}