{
  "type": "Feature",
  "properties": {
    "iso:country":"US",
    "sg:address":"353 Main St",
    "sg:city":"Terryville",
    "sg:classifiers":[
        {
            "category":"Personal",
            "subcategory":"Beauty Salon",
            "type":"Services"
        }
    ],
    "sg:phone":"+1   ",
    "sg:postcode":"06786",
    "sg:province":"CT",
    "sg:tags":[
        "shop"
    ],
    "wof:name":"Davids",
    "wof:placetype":"venue"
},
  "geometry": {"coordinates":[-73.024163,41.678658],"type":"Point"}
}