{
  "type": "Feature",
  "properties": {
    "iso:country":"US",
    "sg:address":"296 E Main St",
    "sg:city":"Branford",
    "sg:classifiers":[
        {
            "category":"Professional",
            "subcategory":"Computer Services",
            "type":"Services"
        }
    ],
    "sg:phone":"+1 203 481 5349",
    "sg:postcode":"06405",
    "sg:province":"CT",
    "sg:tags":[
        "repair"
    ],
    "sg:website":"www.aosinc.com",
    "wof:name":"Advanced Office Systems",
    "wof:placetype":"venue"
},
  "geometry": {"coordinates":[-72.790291,41.292802],"type":"Point"}
}