{
  "type": "Feature",
  "properties": {
    "iso:country":"US",
    "sg:address":"292 Laurel St",
    "sg:city":"East Haven",
    "sg:classifiers":[
        {
            "category":"Professional",
            "subcategory":"Business Services",
            "type":"Services"
        }
    ],
    "sg:phone":"+1   ",
    "sg:postcode":"06512",
    "sg:province":"CT",
    "wof:name":"Anistrum Technologies LLC",
    "wof:placetype":"venue"
},
  "geometry": {"coordinates":[-72.871313,41.289373],"type":"Point"}
}