{
  "type": "Feature",
  "properties": {
    "addr:full":"122 W Cedar St Norwalk CT 06854",
    "addr:housenumber":"122",
    "addr:postcode":"06854",
    "addr:street":"W Cedar St",
    "iso:country":"US",
    "sg:address":"122 W Cedar St",
    "sg:city":"Norwalk",
    "sg:classifiers":[
        {
            "category":"Professional",
            "subcategory":"Advertising",
            "type":"Services"
        },
        {
            "category":"Professional",
            "subcategory":"Art Services",
            "type":"Services"
        },
        {
            "category":"Professional",
            "subcategory":"Computer Services",
            "type":"Services"
        }
    ],
    "sg:phone":"+1 203 286 8919",
    "sg:postcode":"06854",
    "sg:province":"CT",
    "sg:tags":[
        "web",
        "designer",
        "marketing",
        "site",
        "hosting",
        "graphic",
        "design",
        "internet",
        "animation"
    ],
    "sg:website":"http://www.dfscomputers.com",
    "wof:name":"Cobra Web Design",
    "wof:placetype":"venue"
},
  "geometry": {"coordinates":[-73.431361,41.105548],"type":"Point"}
}