{
  "type": "Feature",
  "properties": {
    "iso:country":"US",
    "sg:address":"13 Fern Dr",
    "sg:city":"Bloomfield",
    "sg:classifiers":[
        {
            "category":"Organizations",
            "subcategory":"Religious Organization",
            "type":"Services"
        }
    ],
    "sg:phone":"+1   ",
    "sg:postcode":"06002",
    "sg:province":"CT",
    "wof:name":"Fashioned By Faith",
    "wof:placetype":"venue"
},
  "geometry": {"coordinates":[-72.710285,41.820438],"type":"Point"}
}