{
  "type": "Feature",
  "properties": {
    "addr:full":"75 Rampart Rd Norwalk CT 06854",
    "addr:housenumber":"75",
    "addr:postcode":"06854",
    "addr:street":"Rampart Rd",
    "iso:country":"US",
    "sg:address":"75 Rampart Rd",
    "sg:city":"Norwalk",
    "sg:classifiers":[
        {
            "category":"Manufacturing",
            "subcategory":"Printing",
            "type":"Manufacturing & Wholesale Goods"
        }
    ],
    "sg:phone":"+1 203 852 0070",
    "sg:postcode":"06854",
    "sg:province":"CT",
    "sg:tags":[
        "photocopy",
        "offset"
    ],
    "wof:name":"Total Printing Center The",
    "wof:placetype":"venue"
},
  "geometry": {"coordinates":[-73.441064,41.099163],"type":"Point"}
}