{
  "type": "Feature",
  "properties": {
    "iso:country":"US",
    "sg:address":"369 W Main St",
    "sg:city":"Avon",
    "sg:classifiers":[
        {
            "category":"Professional",
            "subcategory":"Printing & Photocopies",
            "type":"Services"
        }
    ],
    "sg:phone":"+1 860 677 2458",
    "sg:postcode":"06001",
    "sg:province":"CT",
    "wof:name":"Lightning Press Inc",
    "wof:placetype":"venue"
},
  "geometry": {"coordinates":[-72.862396,41.81537],"type":"Point"}
}