{
  "type": "Feature",
  "properties": {
    "addr:full":"605 Broad St Stratford CT 06615",
    "addr:housenumber":"605",
    "addr:postcode":"06615",
    "addr:street":"Broad St",
    "iso:country":"US",
    "sg:address":"605 Broad St",
    "sg:city":"Stratford",
    "sg:classifiers":[
        {
            "category":"Recreation",
            "subcategory":"Marina",
            "type":"Entertainment"
        }
    ],
    "sg:phone":"+1 203 377 4477",
    "sg:postcode":"06615",
    "sg:province":"CT",
    "sg:website":"www.byy.com",
    "wof:name":"Brewers Stratford Marina",
    "wof:placetype":"venue"
},
  "geometry": {"coordinates":[-73.123836,41.18991],"type":"Point"}
}