{
  "type": "Feature",
  "properties": {
    "addr:full":"148 Saint Stephens Rd Bridgeport CT 06605",
    "addr:housenumber":"148",
    "addr:postcode":"06605",
    "addr:street":"Saint Stephens Rd",
    "iso:country":"US",
    "sg:address":"148 Saint Stephens Rd",
    "sg:city":"Bridgeport",
    "sg:classifiers":[
        {
            "category":"Personal",
            "subcategory":"Beauty Salon",
            "type":"Services"
        }
    ],
    "sg:phone":"+1 203 332 7491",
    "sg:postcode":"06605",
    "sg:province":"CT",
    "wof:name":"Maria's Salon",
    "wof:placetype":"venue"
},
  "geometry": {"coordinates":[-73.21684399999999,41.161533],"type":"Point"}
}