{
  "type": "Feature",
  "properties": {
    "iso:country":"US",
    "sg:address":"42 Winthrop St",
    "sg:city":"Tariffville",
    "sg:classifiers":[
        {
            "category":"Education",
            "subcategory":"School",
            "type":"Public Place"
        }
    ],
    "sg:phone":"+1 860 658 5825",
    "sg:postcode":"06081",
    "sg:province":"CT",
    "sg:tags":[
        "executive"
    ],
    "wof:name":"Tariffville Elementary School",
    "wof:placetype":"venue"
},
  "geometry": {"coordinates":[-72.766695,41.909638],"type":"Point"}
}