{
  "type": "Feature",
  "properties": {
    "addr:full":"268 Wilton Rd Westport CT 06880",
    "addr:housenumber":"268",
    "addr:postcode":"06880",
    "addr:street":"Wilton Rd",
    "iso:country":"US",
    "sg:address":"268 Wilton Rd",
    "sg:city":"Westport",
    "sg:classifiers":[
        {
            "category":"Professional",
            "subcategory":"Management & Consulting",
            "type":"Services"
        }
    ],
    "sg:phone":"+1   ",
    "sg:postcode":"06880",
    "sg:province":"CT",
    "sg:tags":[
        "marketing",
        "consultant"
    ],
    "wof:name":"Corolle Dolls",
    "wof:placetype":"venue"
},
  "geometry": {"coordinates":[-73.374313,41.158322],"type":"Point"}
}