{
  "type": "Feature",
  "properties": {
    "addr:full":"64 Leffert Rd Trumbull CT 06611",
    "addr:housenumber":"64",
    "addr:postcode":"06611",
    "addr:street":"Leffert Rd",
    "iso:country":"US",
    "sg:address":"64 Leffert Rd",
    "sg:city":"Trumbull",
    "sg:classifiers":[
        {
            "category":"Professional",
            "subcategory":"Business Services",
            "type":"Services"
        }
    ],
    "sg:phone":"+1   ",
    "sg:postcode":"06611",
    "sg:province":"CT",
    "wof:name":"Balloon & Magic",
    "wof:placetype":"venue"
},
  "geometry": {"coordinates":[-73.171862,41.234491],"type":"Point"}
}