{
  "type": "Feature",
  "properties": {
    "addr:full":"48 Fitch Ave Darien CT 06820",
    "addr:housenumber":"48",
    "addr:postcode":"06820",
    "addr:street":"Fitch Ave Darien Ct",
    "iso:country":"US",
    "sg:address":"48 Fitch Ave",
    "sg:city":"Darien",
    "sg:classifiers":[
        {
            "category":"Professional",
            "subcategory":"Management & Consulting",
            "type":"Services"
        }
    ],
    "sg:phone":"+1   ",
    "sg:postcode":"06820",
    "sg:province":"CT",
    "sg:tags":[
        "business"
    ],
    "wof:name":"Bowen Consulting Inc",
    "wof:placetype":"venue"
},
  "geometry": {"coordinates":[-73.485637,41.066298],"type":"Point"}
}