{
  "type": "Feature",
  "properties": {
    "iso:country":"US",
    "sg:address":"89 Merlot Way",
    "sg:city":"Tolland",
    "sg:classifiers":[
        {
            "category":"Building & Trades",
            "subcategory":"Construction",
            "type":"Services"
        }
    ],
    "sg:phone":"+1 860 508 4624",
    "sg:postcode":"06084",
    "sg:province":"CT",
    "sg:tags":[
        "hanging",
        "contractor"
    ],
    "wof:name":"C & S Wallworks Plus LLC",
    "wof:placetype":"venue"
},
  "geometry": {"coordinates":[-72.3312,41.899566],"type":"Point"}
}