{
  "type": "Feature",
  "properties": {
    "addr:full":"560 Old Main St Rocky Hill CT 06067",
    "addr:housenumber":"560",
    "addr:postcode":"06067",
    "addr:street":"Old Main St",
    "iso:country":"US",
    "sg:address":"560 Old Main St",
    "sg:city":"Rocky Hill",
    "sg:classifiers":[
        {
            "category":"Building & Trades",
            "subcategory":"Construction",
            "type":"Services"
        }
    ],
    "sg:phone":"+1 860 529 4255",
    "sg:postcode":"06067",
    "sg:province":"CT",
    "sg:tags":[
        "concrete",
        "contractor"
    ],
    "wof:name":"Coelho Joseph Inc",
    "wof:placetype":"venue"
},
  "geometry": {"coordinates":[-72.64017,41.672175],"type":"Point"}
}