{
  "type": "Feature",
  "properties": {
    "addr:full":"375 W Main St Avon CT 06001",
    "addr:housenumber":"375",
    "addr:postcode":"06001",
    "addr:street":"W Main St",
    "iso:country":"US",
    "sg:address":"375 W Main St",
    "sg:city":"Avon",
    "sg:classifiers":[
        {
            "category":"Home & Garden",
            "subcategory":"Home Furnishings",
            "type":"Retail Goods"
        },
        {
            "category":"Manufacturing",
            "subcategory":"Pottery",
            "type":"Manufacturing & Wholesale Goods"
        },
        {
            "category":"Community Center",
            "type":"Public Place"
        },
        {
            "category":"Home & Garden",
            "subcategory":"Furniture",
            "type":"Retail Goods"
        },
        {
            "category":"Home & Garden",
            "subcategory":"Carpets & Floor Coverings",
            "type":"Retail Goods"
        },
        {
            "category":"Manufacturing",
            "subcategory":"Chemicals & Compounds",
            "type":"Manufacturing & Wholesale Goods"
        },
        {
            "category":"Manufacturing",
            "subcategory":"Glass & Minerals",
            "type":"Manufacturing & Wholesale Goods"
        }
    ],
    "sg:phone":"+1 860 677 0594",
    "sg:postcode":"06001",
    "sg:province":"CT",
    "sg:tags":[
        "decor",
        "products-decorative",
        "house",
        "ceramic",
        "product",
        "housewares",
        "rug",
        "crystal",
        "china",
        "wicker",
        "basket",
        "candle",
        "glassware",
        "store"
    ],
    "sg:website":"http://www.pier1.com",
    "wof:name":"Pier 1 Imports",
    "wof:placetype":"venue"
},
  "geometry": {"coordinates":[-72.863321,41.815765],"type":"Point"}
}