{
  "type": "Feature",
  "properties": {
    "addr:full":"34 Hazard Ave Enfield CT 06082",
    "addr:housenumber":"34",
    "addr:postcode":"06082",
    "addr:street":"Hazard Ave",
    "iso:country":"US",
    "sg:address":"34 Hazard Ave",
    "sg:city":"Enfield",
    "sg:classifiers":[
        {
            "category":"Retail",
            "subcategory":"Laundry & Dry Cleaning",
            "type":"Services"
        }
    ],
    "sg:phone":"+1   ",
    "sg:postcode":"06082",
    "sg:province":"CT",
    "sg:tags":[
        "garment",
        "agent"
    ],
    "wof:name":"Superior Cleaner",
    "wof:placetype":"venue"
},
  "geometry": {"coordinates":[-72.583269,41.989992],"type":"Point"}
}