{
  "type": "Feature",
  "properties": {
    "addr:full":"24 Cooke Rd Wallingford CT 06492",
    "addr:housenumber":"24",
    "addr:postcode":"06492",
    "addr:street":"Cooke Rd",
    "iso:country":"US",
    "sg:address":"24 Cooke Rd",
    "sg:city":"Wallingford",
    "sg:classifiers":[
        {
            "category":"Restaurant",
            "type":"Food & Drink"
        }
    ],
    "sg:phone":"+1 203 679 0867",
    "sg:postcode":"06492",
    "sg:province":"CT",
    "wof:name":"Swerl Corp",
    "wof:placetype":"venue"
},
  "geometry": {"coordinates":[-72.77064300000001,41.421269],"type":"Point"}
}