{
  "type": "Feature",
  "properties": {
    "addr:full":"30 Washington Ave North Haven CT 06473",
    "addr:housenumber":"30",
    "addr:postcode":"06473",
    "addr:street":"Washington Ave;Haven",
    "iso:country":"US",
    "sg:address":"30 Washington Ave",
    "sg:city":"North Haven",
    "sg:classifiers":[
        {
            "category":"Professional",
            "subcategory":"Lawyer & Legal Services",
            "type":"Services"
        }
    ],
    "sg:phone":"+1 203 234 8844",
    "sg:postcode":"06473",
    "sg:province":"CT",
    "sg:tags":[
        "attorney"
    ],
    "wof:name":"William V Gambardella",
    "wof:placetype":"venue"
},
  "geometry": {"coordinates":[-72.859599,41.390721],"type":"Point"}
}