{
  "type": "Feature",
  "properties": {
    "iso:country":"US",
    "sg:address":"63 Liberty St",
    "sg:city":"Pawcatuck",
    "sg:classifiers":[
        {
            "category":"Education",
            "subcategory":"School",
            "type":"Public Place"
        }
    ],
    "sg:phone":"+1   ",
    "sg:postcode":"06379",
    "sg:province":"CT",
    "wof:name":"St Michael School",
    "wof:placetype":"venue"
},
  "geometry": {"coordinates":[-71.83645799999999,41.379813],"type":"Point"}
}