{
  "type": "Feature",
  "properties": {
    "addr:full":"705 Bloomfield Ave Bloomfield CT 06002",
    "addr:housenumber":"705",
    "addr:postcode":"06002",
    "addr:street":"Bloomfield Ave Bloomfield Ct",
    "iso:country":"US",
    "sg:address":"705 Bloomfield Ave",
    "sg:city":"Bloomfield",
    "sg:classifiers":[
        {
            "category":"Health Services",
            "subcategory":"Doctor",
            "type":"Services"
        }
    ],
    "sg:phone":"+1   ",
    "sg:postcode":"06002",
    "sg:province":"CT",
    "sg:tags":[
        "medical"
    ],
    "wof:name":"Herbert J Werner MD",
    "wof:placetype":"venue"
},
  "geometry": {"coordinates":[-72.737528,41.830962],"type":"Point"}
}