{
  "type": "Feature",
  "properties": {
    "addr:full":"131 Vernon Ave Vernon Rockville CT 06066",
    "addr:housenumber":"131",
    "addr:postcode":"06066",
    "addr:street":"Vernon Ave",
    "iso:country":"US",
    "sg:address":"131 Vernon Ave",
    "sg:city":"Vernon Rockville",
    "sg:classifiers":[
        {
            "category":"Building & Trades",
            "subcategory":"Construction",
            "type":"Services"
        }
    ],
    "sg:phone":"+1 860 871 8532",
    "sg:postcode":"06066",
    "sg:province":"CT",
    "sg:tags":[
        "contractor"
    ],
    "wof:name":"E & E Fence",
    "wof:placetype":"venue"
},
  "geometry": {"coordinates":[-72.44942399999999,41.857873],"type":"Point"}
}