{
  "type": "Feature",
  "properties": {
    "addr:full":"416 South Rd Somers CT 06071",
    "addr:housenumber":"416",
    "addr:postcode":"06071",
    "addr:street":"South Rd Somers Ct",
    "iso:country":"US",
    "sg:address":"416 South Rd",
    "sg:city":"Somers",
    "sg:classifiers":[
        {
            "category":"Retail",
            "subcategory":"Portrait Studio",
            "type":"Services"
        }
    ],
    "sg:phone":"+1   ",
    "sg:postcode":"06071",
    "sg:province":"CT",
    "sg:tags":[
        "photo"
    ],
    "wof:name":"Bill Lipton Photography",
    "wof:placetype":"venue"
},
  "geometry": {"coordinates":[-72.444743,41.957271],"type":"Point"}
}