{
  "type": "Feature",
  "properties": {
    "iso:country":"US",
    "sg:address":"31 Mead Ave",
    "sg:city":"Greenwich",
    "sg:classifiers":[
        {
            "category":"Personal",
            "type":"Services"
        }
    ],
    "sg:phone":"+1   ",
    "sg:postcode":"06830",
    "sg:province":"CT",
    "sg:tags":[
        "building",
        "maintenance"
    ],
    "wof:name":"Husband For Hire",
    "wof:placetype":"venue"
},
  "geometry": {"coordinates":[-73.655973,41.001248],"type":"Point"}
}