{
  "type": "Feature",
  "properties": {
    "addr:full":"80 Prospect Hill Dr East Windsor CT 06088",
    "addr:housenumber":"80",
    "addr:postcode":"06088",
    "addr:street":"Prospect Hill Dr East Windsor Ct",
    "iso:country":"US",
    "sg:address":"80 Prospect Hill Dr",
    "sg:city":"East Windsor",
    "sg:classifiers":[
        {
            "category":"Professional",
            "type":"Services"
        }
    ],
    "sg:phone":"+1 860 623 2948",
    "sg:postcode":"06088",
    "sg:province":"CT",
    "wof:name":"Mr Phillip Lasher",
    "wof:placetype":"venue"
},
  "geometry": {"coordinates":[-72.595432,41.927369],"type":"Point"}
}