{
  "type": "Feature",
  "properties": {
    "addr:full":"211 Nott Hwy Ashford CT 06278",
    "addr:housenumber":"211",
    "addr:postcode":"06278",
    "addr:street":"Nott Hwy Ashford Ct",
    "iso:country":"US",
    "sg:address":"211 Nott Hwy",
    "sg:city":"Ashford",
    "sg:phone":"+1 860 429 7900",
    "sg:postcode":"06278",
    "sg:province":"CT",
    "wof:name":"His & Her Elegance Edge Hair Salon",
    "wof:placetype":"venue"
},
  "geometry": {"coordinates":[-72.193442,41.864892],"type":"Point"}
}