{
  "type": "Feature",
  "properties": {
    "addr:full":"27 Cottage Grove Ln Waterbury CT 06706",
    "addr:housenumber":"27",
    "addr:postcode":"06706",
    "addr:street":"Cottage Grove Ln",
    "iso:country":"US",
    "sg:address":"27 Cottage Grove Ln",
    "sg:city":"Waterbury",
    "sg:classifiers":[
        {
            "category":"Home & Garden",
            "subcategory":"Building Materials",
            "type":"Retail Goods"
        }
    ],
    "sg:phone":"+1 203 756 2335",
    "sg:postcode":"06706",
    "sg:province":"CT",
    "sg:tags":[
        "contractor"
    ],
    "wof:name":"Verraster Construction",
    "wof:placetype":"venue"
},
  "geometry": {"coordinates":[-73.01703500000001,41.532645],"type":"Point"}
}