{
  "type": "Feature",
  "properties": {
    "iso:country":"US",
    "sg:address":"39 Union St",
    "sg:city":"Meriden",
    "sg:classifiers":[
        {
            "category":"Arts & Performance",
            "subcategory":"Theater",
            "type":"Entertainment"
        }
    ],
    "sg:phone":"+1   ",
    "sg:postcode":"06451",
    "sg:province":"CT",
    "sg:tags":[
        "group"
    ],
    "wof:name":"Phazon Entertainment",
    "wof:placetype":"venue"
},
  "geometry": {"coordinates":[-72.80288899999999,41.541355],"type":"Point"}
}