{
  "type": "Feature",
  "properties": {
    "addr:full":"20 Amsterdam Ave Bridgeport CT 06606",
    "addr:housenumber":"20",
    "addr:postcode":"06606",
    "addr:street":"Amsterdam Ave",
    "iso:country":"US",
    "sg:address":"20 Amsterdam Ave",
    "sg:city":"Bridgeport",
    "sg:classifiers":[
        {
            "category":"Social Services",
            "subcategory":"Adult Care",
            "type":"Services"
        }
    ],
    "sg:phone":"+1 203 366 5784",
    "sg:postcode":"06606",
    "sg:province":"CT",
    "sg:tags":[
        "handicapped",
        "home",
        "group",
        "for",
        "mentally"
    ],
    "wof:name":"Condo's North",
    "wof:placetype":"venue"
},
  "geometry": {"coordinates":[-73.210252,41.199624],"type":"Point"}
}