{
  "type": "Feature",
  "properties": {
    "iso:country":"US",
    "sg:address":"159 Acme Dr",
    "sg:city":"Middlebury",
    "sg:classifiers":[
        {
            "category":"Building & Trades",
            "subcategory":"Construction",
            "type":"Services"
        }
    ],
    "sg:phone":"+1 203 758 1182",
    "sg:postcode":"06762",
    "sg:province":"CT",
    "sg:tags":[
        "contractor"
    ],
    "wof:name":"Gene R Hubbard",
    "wof:placetype":"venue"
},
  "geometry": {"coordinates":[-73.10719,41.546732],"type":"Point"}
}