{
  "type": "Feature",
  "properties": {
    "addr:full":"90 William St Norwalk CT 06851",
    "addr:housenumber":"90",
    "addr:postcode":"06851",
    "addr:street":"William St",
    "iso:country":"US",
    "sg:address":"90 William St",
    "sg:city":"Norwalk",
    "sg:classifiers":[
        {
            "category":"Building & Trades",
            "subcategory":"Plumbing",
            "type":"Services"
        }
    ],
    "sg:phone":"+1 203 853 7159",
    "sg:postcode":"06851",
    "sg:province":"CT",
    "sg:tags":[
        "contractor"
    ],
    "wof:name":"Hilltop Plumbing & Heating",
    "wof:placetype":"venue"
},
  "geometry": {"coordinates":[-73.384221,41.12039],"type":"Point"}
}