{
  "type": "Feature",
  "properties": {
    "addr:full":"6 N Main St Wallingford CT 06492",
    "addr:housenumber":"6",
    "addr:postcode":"06492",
    "addr:street":"N Main St",
    "iso:country":"US",
    "sg:address":"6 N Main St",
    "sg:city":"Wallingford",
    "sg:classifiers":[
        {
            "category":"Professional",
            "subcategory":"Management & Consulting",
            "type":"Services"
        }
    ],
    "sg:phone":"+1   ",
    "sg:postcode":"06492",
    "sg:province":"CT",
    "sg:tags":[
        "conference",
        "center"
    ],
    "wof:name":"Confernce Ctr Consulting Group",
    "wof:placetype":"venue"
},
  "geometry": {"coordinates":[-72.81781100000001,41.455121],"type":"Point"}
}