{
  "type": "Feature",
  "properties": {
    "addr:full":"78 Russ Rd Trumbull CT 06611",
    "addr:housenumber":"78",
    "addr:postcode":"06611",
    "addr:street":"Russ Rd",
    "iso:country":"US",
    "sg:address":"78 Russ Rd",
    "sg:city":"Trumbull",
    "sg:classifiers":[
        {
            "category":"Personal",
            "subcategory":"Beauty Salon",
            "type":"Services"
        }
    ],
    "sg:phone":"+1 203 372 6972",
    "sg:postcode":"06611",
    "sg:province":"CT",
    "sg:tags":[
        "treatment",
        "skin"
    ],
    "sg:website":"www.ecogenics.com",
    "wof:name":"Ecogenics",
    "wof:placetype":"venue"
},
  "geometry": {"coordinates":[-73.246244,41.230497],"type":"Point"}
}