{
  "type": "Feature",
  "properties": {
    "addr:full":"17 Skyridge Rd Greenwich NY 06831",
    "addr:housenumber":"17",
    "addr:postcode":"06831",
    "addr:street":"Skyridge Rd",
    "iso:country":"US",
    "sg:address":"17 Skyridge Rd",
    "sg:city":"Greenwich",
    "sg:classifiers":[
        {
            "category":"Professional",
            "subcategory":"Business Services",
            "type":"Services"
        }
    ],
    "sg:phone":"+1   ",
    "sg:postcode":"06831",
    "sg:province":"NY",
    "wof:name":"Flying Colors Interiors",
    "wof:placetype":"venue"
},
  "geometry": {"coordinates":[-73.618196,41.100595],"type":"Point"}
}