{
  "type": "Feature",
  "properties": {
    "addr:full":"276 Post Rd W Westport CT 06880",
    "addr:housenumber":"276",
    "addr:postcode":"06880",
    "addr:street":"Post Rd W Westport Ct",
    "iso:country":"US",
    "sg:address":"276 Post Rd W",
    "sg:city":"Westport",
    "sg:classifiers":[
        {
            "category":"Banks & Credit Unions",
            "subcategory":"Investment Brokerage",
            "type":"Services"
        }
    ],
    "sg:phone":"+1 203 341 7800",
    "sg:postcode":"06880",
    "sg:province":"CT",
    "sg:tags":[
        "advisory",
        "financial"
    ],
    "sg:website":"www.iridian.com",
    "wof:name":"Iridian Asset Management",
    "wof:placetype":"venue"
},
  "geometry": {"coordinates":[-73.373408,41.133943],"type":"Point"}
}