{
  "type": "Feature",
  "properties": {
    "iso:country":"US",
    "sg:address":"51 Willow St",
    "sg:city":"Wethersfield",
    "sg:classifiers":[
        {
            "category":"Education",
            "subcategory":"School",
            "type":"Public Place"
        }
    ],
    "sg:phone":"+1   ",
    "sg:postcode":"06109",
    "sg:province":"CT",
    "sg:tags":[
        "district"
    ],
    "wof:name":"Wethersfield Board Education",
    "wof:placetype":"venue"
},
  "geometry": {"coordinates":[-72.691013,41.699479],"type":"Point"}
}