{
  "type": "Feature",
  "properties": {
    "addr:full":"1103 Farmington Ave Berlin CT 06037",
    "addr:housenumber":"1103",
    "addr:postcode":"06037",
    "addr:street":"Farmington Ave",
    "iso:country":"US",
    "sg:address":"1103 Farmington Ave",
    "sg:city":"Berlin",
    "sg:classifiers":[
        {
            "category":"Personal",
            "subcategory":"Beauty Salon",
            "type":"Services"
        }
    ],
    "sg:phone":"+1   ",
    "sg:postcode":"06037",
    "sg:province":"CT",
    "sg:tags":[
        "shop"
    ],
    "wof:name":"Nancy Soares",
    "wof:placetype":"venue"
},
  "geometry": {"coordinates":[-72.75852500000001,41.629944],"type":"Point"}
}