{
  "type": "Feature",
  "properties": {
    "addr:full":"24 Lyon Rd Burlington CT 06013",
    "addr:housenumber":"24",
    "addr:postcode":"06013",
    "addr:street":"Lyon Rd",
    "iso:country":"US",
    "sg:address":"24 Lyon Rd",
    "sg:city":"Burlington",
    "sg:classifiers":[
        {
            "category":"Education",
            "subcategory":"School",
            "type":"Public Place"
        }
    ],
    "sg:phone":"+1 860 673 2538",
    "sg:postcode":"06013",
    "sg:province":"CT",
    "sg:tags":[
        "high",
        "middle",
        "elementary"
    ],
    "wof:name":"Burlington Town of",
    "wof:placetype":"venue"
},
  "geometry": {"coordinates":[-72.991176,41.77877],"type":"Point"}
}