{
  "type": "Feature",
  "properties": {
    "iso:country":"US",
    "sg:address":"363 Saint Ronan St",
    "sg:city":"New Haven",
    "sg:classifiers":[
        {
            "category":"Education",
            "subcategory":"School",
            "type":"Public Place"
        }
    ],
    "sg:phone":"+1 203 787 6172",
    "sg:postcode":"06511",
    "sg:province":"CT",
    "wof:name":"Yale University",
    "wof:placetype":"venue"
},
  "geometry": {"coordinates":[-72.917475,41.328036],"type":"Point"}
}