{
  "type": "Feature",
  "properties": {
    "addr:full":"102 Grove St New Milford CT 06776",
    "addr:housenumber":"102",
    "addr:postcode":"06776",
    "addr:street":"Grove St",
    "iso:country":"US",
    "sg:address":"102 Grove St",
    "sg:city":"New Milford",
    "sg:classifiers":[
        {
            "category":"Professional",
            "subcategory":"Secretarial Services",
            "type":"Services"
        }
    ],
    "sg:phone":"+1   ",
    "sg:postcode":"06776",
    "sg:province":"CT",
    "sg:tags":[
        "clerical"
    ],
    "wof:name":"Bostwick Typing Service",
    "wof:placetype":"venue"
},
  "geometry": {"coordinates":[-73.406465,41.571894],"type":"Point"}
}