{
  "type": "Feature",
  "properties": {
    "addr:full":"919 State St New Haven CT 06511",
    "addr:housenumber":"919",
    "addr:postcode":"06511",
    "addr:street":"State St",
    "iso:country":"US",
    "sg:address":"919 State St",
    "sg:city":"New Haven",
    "sg:classifiers":[
        {
            "category":"Professional",
            "subcategory":"Detective & Security Services",
            "type":"Services"
        }
    ],
    "sg:phone":"+1   ",
    "sg:postcode":"06511",
    "sg:province":"CT",
    "sg:tags":[
        "system"
    ],
    "wof:name":"Reliable Detection Systems LLC",
    "wof:placetype":"venue"
},
  "geometry": {"coordinates":[-72.91111600000001,41.314623],"type":"Point"}
}