{
  "type": "Feature",
  "properties": {
    "addr:full":"748 Church St Amston CT 06231",
    "addr:housenumber":"748",
    "addr:postcode":"06231",
    "addr:street":"Church St Amston Ct",
    "iso:country":"US",
    "sg:address":"748 Church St",
    "sg:city":"Amston",
    "sg:classifiers":[
        {
            "category":"Real Estate",
            "subcategory":"Real Estate Agent",
            "type":"Services"
        }
    ],
    "sg:phone":"+1 860 228 2502",
    "sg:postcode":"06231",
    "sg:province":"CT",
    "wof:name":"Lawrence E Green",
    "wof:placetype":"venue"
},
  "geometry": {"coordinates":[-72.344003,41.614537],"type":"Point"}
}