{
  "type": "Feature",
  "properties": {
    "iso:country":"US",
    "sg:address":"8 West St",
    "sg:city":"New Haven",
    "sg:classifiers":[
        {
            "category":"Organizations",
            "subcategory":"Religious Organization",
            "type":"Services"
        }
    ],
    "sg:phone":"+1 203 624 8255",
    "sg:postcode":"06519",
    "sg:province":"CT",
    "sg:tags":[
        "church"
    ],
    "wof:name":"Holy Nation Church",
    "wof:placetype":"venue"
},
  "geometry": {"coordinates":[-72.93885299999999,41.295266],"type":"Point"}
}