{
  "type": "Feature",
  "properties": {
    "addr:full":"79 Treadwell St Hamden CT 06517",
    "addr:housenumber":"79",
    "addr:postcode":"06517",
    "addr:street":"Treadwell St",
    "iso:country":"US",
    "sg:address":"79 Treadwell St",
    "sg:city":"Hamden",
    "sg:classifiers":[
        {
            "category":"Manufacturing",
            "subcategory":"Retail Goods",
            "type":"Manufacturing & Wholesale Goods"
        }
    ],
    "sg:phone":"+1 203 288 0975",
    "sg:postcode":"06517",
    "sg:province":"CT",
    "sg:tags":[
        "product",
        "group",
        "mfg"
    ],
    "wof:name":"M & M Puppet Theatre",
    "wof:placetype":"venue"
},
  "geometry": {"coordinates":[-72.916849,41.348378],"type":"Point"}
}