{
  "type": "Feature",
  "properties": {
    "iso:country":"US",
    "sg:address":"1187 Highland Ave",
    "sg:city":"Cheshire",
    "sg:classifiers":[
        {
            "category":"Retail",
            "subcategory":"Auto Rental",
            "type":"Services"
        }
    ],
    "sg:phone":"+1   ",
    "sg:postcode":"06410",
    "sg:province":"CT",
    "sg:tags":[
        "passenger",
        "car"
    ],
    "wof:name":"M0029 Rent A Center",
    "wof:placetype":"venue"
},
  "geometry": {"coordinates":[-72.894687,41.53233],"type":"Point"}
}