{
  "type": "Feature",
  "properties": {
    "addr:full":"170 Thompson St Bridgeport CT 06604",
    "addr:housenumber":"170",
    "addr:postcode":"06604",
    "addr:street":"Thompson St",
    "iso:country":"US",
    "sg:address":"170 Thompson St",
    "sg:city":"Bridgeport",
    "sg:classifiers":[
        {
            "category":"Organizations",
            "subcategory":"Religious Organization",
            "type":"Services"
        }
    ],
    "sg:phone":"+1 203 335 0106",
    "sg:postcode":"06604",
    "sg:province":"CT",
    "sg:tags":[
        "church"
    ],
    "wof:name":"St Patrick's Rc Church",
    "wof:placetype":"venue"
},
  "geometry": {"coordinates":[-73.196246,41.191968],"type":"Point"}
}