{
  "type": "Feature",
  "properties": {
    "iso:country":"US",
    "sg:address":"400 Main St",
    "sg:city":"Wethersfield",
    "sg:classifiers":[
        {
            "category":"Social Services",
            "subcategory":"Child Care",
            "type":"Services"
        }
    ],
    "sg:phone":"+1   ",
    "sg:postcode":"06109",
    "sg:province":"CT",
    "sg:tags":[
        "day"
    ],
    "wof:name":"Jump Start Jazz Productions LL",
    "wof:placetype":"venue"
},
  "geometry": {"coordinates":[-72.652585,41.718679],"type":"Point"}
}