{
  "type": "Feature",
  "properties": {
    "addr:full":"687 Portland-Cobalt Rd Portland CT 06480",
    "addr:housenumber":"687",
    "addr:postcode":"06480",
    "addr:street":"Portland-Cobalt Rd",
    "iso:country":"US",
    "sg:address":"687 Portland-Cobalt Rd",
    "sg:city":"Portland",
    "sg:classifiers":[
        {
            "category":"Retail",
            "subcategory":"Auto Repair",
            "type":"Services"
        }
    ],
    "sg:phone":"+1   ",
    "sg:postcode":"06480",
    "sg:province":"CT",
    "sg:tags":[
        "body",
        "general"
    ],
    "wof:name":"Moore Brothers Inc",
    "wof:placetype":"venue"
},
  "geometry": {"coordinates":[-72.61613699999999,41.570921],"type":"Point"}
}