{
  "type": "Feature",
  "properties": {
    "addr:full":"61 Arrow Rd Wethersfield CT 06109",
    "addr:housenumber":"61",
    "addr:postcode":"06109",
    "addr:street":"Arrow Rd",
    "iso:country":"US",
    "sg:address":"61 Arrow Rd",
    "sg:city":"Wethersfield",
    "sg:classifiers":[
        {
            "category":"Wholesale",
            "subcategory":"Machinery & Supplies",
            "type":"Manufacturing & Wholesale Goods"
        }
    ],
    "sg:phone":"+1 860 563 4322",
    "sg:postcode":"06109",
    "sg:province":"CT",
    "sg:tags":[
        "equipment",
        "industrial"
    ],
    "wof:name":"Compumachine Inc",
    "wof:placetype":"venue"
},
  "geometry": {"coordinates":[-72.703492,41.703369],"type":"Point"}
}