{
  "type": "Feature",
  "properties": {
    "addr:full":"100 Abendroth Ave Port Chester CT 10573",
    "addr:housenumber":"100",
    "addr:postcode":"10573",
    "addr:street":"Abendroth Ave;Chester",
    "iso:country":"US",
    "sg:address":"100 Abendroth Ave",
    "sg:city":"Port Chester",
    "sg:classifiers":[
        {
            "category":"Organizations",
            "subcategory":"Non-profit Organization",
            "type":"Services"
        }
    ],
    "sg:phone":"+1 914 939 2878",
    "sg:postcode":"10573",
    "sg:province":"CT",
    "wof:name":"Human Development Svc",
    "wof:placetype":"venue"
},
  "geometry": {"coordinates":[-73.660408,41.002966],"type":"Point"}
}