{
  "type": "Feature",
  "properties": {
    "addr:full":"61 S Main St Hartford CT 06107",
    "addr:housenumber":"61",
    "addr:postcode":"06107",
    "addr:street":"S Main St",
    "iso:country":"US",
    "sg:address":"61 S Main St",
    "sg:city":"Hartford",
    "sg:classifiers":[
        {
            "category":"Health Services",
            "subcategory":"Doctor",
            "type":"Services"
        }
    ],
    "sg:phone":"+1   ",
    "sg:postcode":"06107",
    "sg:province":"CT",
    "sg:tags":[
        "medical"
    ],
    "wof:name":"Parsons Jlian Intrnal Medicine",
    "wof:placetype":"venue"
},
  "geometry": {"coordinates":[-72.743135,41.757731],"type":"Point"}
}