{
  "type": "Feature",
  "properties": {
    "iso:country":"US",
    "sg:address":"73 Norwich Ave",
    "sg:city":"Norwich",
    "sg:classifiers":[
        {
            "category":"Retail",
            "subcategory":"Auto Repair",
            "type":"Services"
        }
    ],
    "sg:phone":"+1   ",
    "sg:postcode":"06360",
    "sg:province":"CT",
    "sg:tags":[
        "body",
        "automotive"
    ],
    "wof:name":"Rays Auto Body",
    "wof:placetype":"venue"
},
  "geometry": {"coordinates":[-72.051847,41.553156],"type":"Point"}
}