{
  "type": "Feature",
  "properties": {
    "iso:country":"US",
    "sg:address":"16 Bridge Sq",
    "sg:city":"Westport",
    "sg:classifiers":[
        {
            "category":"Professional",
            "subcategory":"Management & Consulting",
            "type":"Services"
        }
    ],
    "sg:phone":"+1 203 227 6299",
    "sg:postcode":"06880",
    "sg:province":"CT",
    "sg:tags":[
        "consultant",
        "business"
    ],
    "wof:name":"Pro Group Inc",
    "wof:placetype":"venue"
},
  "geometry": {"coordinates":[-73.370081,41.122195],"type":"Point"}
}