{
  "type": "Feature",
  "properties": {
    "addr:full":"70 West Rd Ellington CT 06029",
    "addr:housenumber":"70",
    "addr:postcode":"06029",
    "addr:street":"West Rd Ellington Ct",
    "iso:country":"US",
    "sg:address":"70 West Rd",
    "sg:city":"Ellington",
    "sg:classifiers":[
        {
            "category":"Banks & Credit Unions",
            "subcategory":"Bank",
            "type":"Services"
        }
    ],
    "sg:phone":"+1 860 872 7341",
    "sg:postcode":"06029",
    "sg:province":"CT",
    "sg:tags":[
        "state",
        "commercial"
    ],
    "wof:name":"Webster Bank",
    "wof:placetype":"venue"
},
  "geometry": {"coordinates":[-72.464291,41.881824],"type":"Point"}
}