{
  "type": "Feature",
  "properties": {
    "addr:full":"41 Tanglewood Ln Naugatuck CT 06770",
    "addr:housenumber":"41",
    "addr:postcode":"06770",
    "addr:street":"Tanglewood Ln Naugatuck Ct",
    "iso:country":"US",
    "sg:address":"41 Tanglewood Ln",
    "sg:city":"Naugatuck",
    "sg:classifiers":[
        {
            "category":"Professional",
            "type":"Services"
        }
    ],
    "sg:phone":"+1 203 729 3931",
    "sg:postcode":"06770",
    "sg:province":"CT",
    "wof:name":"Ray Kloc LLC",
    "wof:placetype":"venue"
},
  "geometry": {"coordinates":[-73.076306,41.505447],"type":"Point"}
}