{
  "type": "Feature",
  "properties": {
    "iso:country":"US",
    "sg:address":"139 McKinley Ave",
    "sg:city":"Norwich",
    "sg:classifiers":[
        {
            "category":"Organizations",
            "subcategory":"Membership Organization",
            "type":"Services"
        }
    ],
    "sg:phone":"+1   ",
    "sg:postcode":"06360",
    "sg:province":"CT",
    "wof:name":"Oxford House",
    "wof:placetype":"venue"
},
  "geometry": {"coordinates":[-72.07791899999999,41.534738],"type":"Point"}
}