{
  "type": "Feature",
  "properties": {
    "addr:full":"57 Palomba Dr Enfield CT 06082",
    "addr:housenumber":"57",
    "addr:postcode":"06082",
    "addr:street":"Palomba Dr",
    "iso:country":"US",
    "sg:address":"57 Palomba Dr",
    "sg:city":"Enfield",
    "sg:classifiers":[
        {
            "category":"Personal",
            "subcategory":"Beauty Salon",
            "type":"Services"
        }
    ],
    "sg:phone":"+1   ",
    "sg:postcode":"06082",
    "sg:province":"CT",
    "sg:tags":[
        "shop"
    ],
    "wof:name":"Cost Cutters",
    "wof:placetype":"venue"
},
  "geometry": {"coordinates":[-72.574287,41.998521],"type":"Point"}
}