{
  "type": "Feature",
  "properties": {
    "iso:country":"US",
    "sg:address":"41 Paugussett Rd",
    "sg:city":"Sandy Hook",
    "sg:classifiers":[
        {
            "category":"Real Estate",
            "subcategory":"Real Estate Agent",
            "type":"Services"
        }
    ],
    "sg:phone":"+1 203 270 7676",
    "sg:postcode":"06482",
    "sg:province":"CT",
    "sg:tags":[
        "appraiser"
    ],
    "wof:name":"Storms & Assoc LLC",
    "wof:placetype":"venue"
},
  "geometry": {"coordinates":[-73.21071600000001,41.396659],"type":"Point"}
}