{
  "type": "Feature",
  "properties": {
    "addr:full":"116 Village Dr Torrington CT 06790",
    "addr:housenumber":"116",
    "addr:postcode":"06790",
    "addr:street":"Village Dr",
    "iso:country":"US",
    "sg:address":"116 Village Dr",
    "sg:city":"Torrington",
    "sg:classifiers":[
        {
            "category":"Organizations",
            "subcategory":"Membership Organization",
            "type":"Services"
        }
    ],
    "sg:phone":"+1   ",
    "sg:postcode":"06790",
    "sg:province":"CT",
    "wof:name":"East Farms Village Association",
    "wof:placetype":"venue"
},
  "geometry": {"coordinates":[-73.07733,41.805172],"type":"Point"}
}