{
  "type": "Feature",
  "properties": {
    "addr:full":"466 Long Ridge Rd Stamford CT 06902",
    "addr:housenumber":"466",
    "addr:postcode":"06902",
    "addr:street":"Long Ridge Rd",
    "iso:country":"US",
    "sg:address":"466 Long Ridge Rd",
    "sg:city":"Stamford",
    "sg:classifiers":[
        {
            "category":"Professional",
            "subcategory":"Business Services",
            "type":"Services"
        }
    ],
    "sg:phone":"+1   ",
    "sg:postcode":"06902",
    "sg:province":"CT",
    "wof:name":"3t Enterprises LLC",
    "wof:placetype":"venue"
},
  "geometry": {"coordinates":[-73.557287,41.08605],"type":"Point"}
}