{
  "type": "Feature",
  "properties": {
    "addr:full":"269 Peck St New Haven CT 06513",
    "addr:housenumber":"269",
    "addr:postcode":"06513",
    "addr:street":"Peck St",
    "iso:country":"US",
    "sg:address":"269 Peck St",
    "sg:city":"New Haven",
    "sg:classifiers":[
        {
            "category":"Retail",
            "subcategory":"Auto Repair",
            "type":"Services"
        }
    ],
    "sg:phone":"+1   ",
    "sg:postcode":"06513",
    "sg:province":"CT",
    "sg:tags":[
        "transmission"
    ],
    "wof:name":"Stop & Go Transmission",
    "wof:placetype":"venue"
},
  "geometry": {"coordinates":[-72.899317,41.315945],"type":"Point"}
}