{
  "type": "Feature",
  "properties": {
    "iso:country":"US",
    "sg:address":"1158 Yale Ave",
    "sg:city":"Wallingford",
    "sg:classifiers":[
        {
            "category":"Professional",
            "subcategory":"Accounting & Tax Preparation",
            "type":"Services"
        }
    ],
    "sg:phone":"+1 203 284 2624",
    "sg:postcode":"06492",
    "sg:province":"CT",
    "sg:tags":[
        "bookkeeping",
        "general"
    ],
    "wof:name":"Gibby's Business Svc",
    "wof:placetype":"venue"
},
  "geometry": {"coordinates":[-72.796943,41.501594],"type":"Point"}
}