{
  "type": "Feature",
  "properties": {
    "iso:country":"US",
    "sg:address":"50 Tower Ln",
    "sg:city":"Avon",
    "sg:classifiers":[
        {
            "category":"Professional",
            "subcategory":"Computer Services",
            "type":"Services"
        }
    ],
    "sg:phone":"+1 240 514 3183",
    "sg:postcode":"06001",
    "sg:province":"CT",
    "sg:tags":[
        "designer",
        "technical",
        "consultant",
        "assistance",
        "system",
        "support"
    ],
    "wof:name":"50 Tower Lane",
    "wof:placetype":"venue"
},
  "geometry": {"coordinates":[-72.841531,41.806286],"type":"Point"}
}