{
  "type": "Feature",
  "properties": {
    "addr:full":"1103 E Putnam Ave Riverside CT 06878",
    "addr:housenumber":"1103",
    "addr:postcode":"06878",
    "addr:street":"E Putnam Ave Riverside Ct",
    "iso:country":"US",
    "sg:address":"1103 E Putnam Ave",
    "sg:city":"Riverside",
    "sg:classifiers":[
        {
            "category":"Banks & Credit Unions",
            "subcategory":"Bank",
            "type":"Services"
        }
    ],
    "sg:phone":"+1 203 698 4030",
    "sg:postcode":"06878",
    "sg:province":"CT",
    "sg:tags":[
        "commercial"
    ],
    "wof:name":"Greenwich Bank and Trust Co",
    "wof:placetype":"venue"
},
  "geometry": {"coordinates":[-73.58398200000001,41.040922],"type":"Point"}
}