{
  "type": "Feature",
  "properties": {
    "addr:full":"143 Sawmill Hill Rd Sterling CT 06377",
    "addr:housenumber":"143",
    "addr:postcode":"06377",
    "addr:street":"Sawmill Hill Rd",
    "iso:country":"US",
    "sg:address":"143 Sawmill Hill Rd",
    "sg:city":"Sterling",
    "sg:classifiers":[
        {
            "category":"Manufacturing",
            "subcategory":"Metals",
            "type":"Manufacturing & Wholesale Goods"
        }
    ],
    "sg:phone":"+1 860 779 3194",
    "sg:postcode":"06377",
    "sg:province":"CT",
    "sg:tags":[
        "metalwork",
        "sheet",
        "mfg"
    ],
    "wof:name":"Saw Mill Sheet Metal",
    "wof:placetype":"venue"
},
  "geometry": {"coordinates":[-71.82638,41.763938],"type":"Point"}
}