{
  "type": "Feature",
  "properties": {
    "addr:full":"1194 N Colony Rd Wallingford CT 06492",
    "addr:housenumber":"1194",
    "addr:postcode":"06492",
    "addr:street":"N Colony Rd",
    "iso:country":"US",
    "sg:address":"1194 N Colony Rd",
    "sg:city":"Wallingford",
    "sg:classifiers":[
        {
            "category":"Autos & Motor Vehicles",
            "subcategory":"Automobile Sales",
            "type":"Retail Goods"
        },
        {
            "category":"Retail",
            "subcategory":"Auto Repair",
            "type":"Services"
        }
    ],
    "sg:phone":"+1 203 949 7420",
    "sg:postcode":"06492",
    "sg:province":"CT",
    "sg:tags":[
        "body",
        "repairing",
        "painting",
        "new",
        "car"
    ],
    "wof:name":"Executive Auto Group Body Shop",
    "wof:placetype":"venue"
},
  "geometry": {"coordinates":[-72.837813,41.427285],"type":"Point"}
}