{
  "type": "Feature",
  "properties": {
    "addr:full":"242 Post Rd E Westport CT 06880",
    "addr:housenumber":"242",
    "addr:postcode":"06880",
    "addr:street":"Post Rd E Westport Ct",
    "iso:country":"US",
    "sg:address":"242 Post Rd E",
    "sg:city":"Westport",
    "sg:classifiers":[
        {
            "category":"Shopping",
            "subcategory":"Clothing, Apparel, & Fashions",
            "type":"Retail Goods"
        }
    ],
    "sg:phone":"+1 203 341 9960",
    "sg:postcode":"06880",
    "sg:province":"CT",
    "wof:name":"Seychelles LLC",
    "wof:placetype":"venue"
},
  "geometry": {"coordinates":[-73.355919,41.140984],"type":"Point"}
}