{
  "type": "Feature",
  "properties": {
    "iso:country":"US",
    "sg:address":"1 Blachley Rd",
    "sg:city":"Stamford",
    "sg:classifiers":[
        {
            "category":"Banks & Credit Unions",
            "subcategory":"Bank",
            "type":"Services"
        }
    ],
    "sg:phone":"+1 203 357 5458",
    "sg:postcode":"06902",
    "sg:province":"CT",
    "wof:name":"Clairol Employee Federal CU",
    "wof:placetype":"venue"
},
  "geometry": {"coordinates":[-73.51557099999999,41.056329],"type":"Point"}
}