{
  "type": "Feature",
  "properties": {
    "addr:full":"39 Regency Hill Waterbury CT 06708",
    "addr:housenumber":"39",
    "addr:postcode":"06708",
    "addr:street":"Regency Hill Waterbury Ct",
    "iso:country":"US",
    "sg:address":"39 Regency Hill",
    "sg:city":"Waterbury",
    "sg:classifiers":[
        {
            "category":"Professional",
            "type":"Services"
        }
    ],
    "sg:phone":"+1 203 575 0039",
    "sg:postcode":"06708",
    "sg:province":"CT",
    "wof:name":"Radio Emrgncy MBL Cmmnctons or",
    "wof:placetype":"venue"
},
  "geometry": {"coordinates":[-73.086467,41.568336],"type":"Point"}
}