{
  "type": "Feature",
  "properties": {
    "iso:country":"US",
    "sg:address":"280 Tesiny Ave",
    "sg:city":"Bridgeport",
    "sg:classifiers":[
        {
            "category":"Organizations",
            "subcategory":"Professional Association",
            "type":"Services"
        }
    ],
    "sg:phone":"+1 203 371 4617",
    "sg:postcode":"06606",
    "sg:province":"CT",
    "wof:name":"School Volunteer Assn",
    "wof:placetype":"venue"
},
  "geometry": {"coordinates":[-73.20764699999999,41.214727],"type":"Point"}
}