{
  "type": "Feature",
  "properties": {
    "iso:country":"US",
    "sg:address":"95 Miles St",
    "sg:city":"Bridgeport",
    "sg:classifiers":[
        {
            "category":"Manufacturing",
            "subcategory":"Apparel",
            "type":"Manufacturing & Wholesale Goods"
        }
    ],
    "sg:phone":"+1 203 576 6768",
    "sg:postcode":"06607",
    "sg:province":"CT",
    "wof:name":"U K Mfg LLC",
    "wof:placetype":"venue"
},
  "geometry": {"coordinates":[-73.156524,41.181264],"type":"Point"}
}