{
  "type": "Feature",
  "properties": {
    "iso:country":"US",
    "sg:address":"29 Lockwood St",
    "sg:city":"Meriden",
    "sg:classifiers":[
        {
            "category":"Building & Trades",
            "subcategory":"Pest Control",
            "type":"Services"
        }
    ],
    "sg:phone":"+1 860 482 6565",
    "sg:postcode":"06451",
    "sg:province":"CT",
    "wof:name":"J & J Pest Control",
    "wof:placetype":"venue"
},
  "geometry": {"coordinates":[-72.815011,41.543768],"type":"Point"}
}