{
  "type": "Feature",
  "properties": {
    "addr:full":"339 Hunting Hill Ave Middletown CT 06457",
    "addr:housenumber":"339",
    "addr:postcode":"06457",
    "addr:street":"Hunting Hill Ave",
    "iso:country":"US",
    "sg:address":"339 Hunting Hill Ave",
    "sg:city":"Middletown",
    "sg:classifiers":[
        {
            "category":"Shopping",
            "subcategory":"Jewelry",
            "type":"Retail Goods"
        }
    ],
    "sg:phone":"+1 860 704 8185",
    "sg:postcode":"06457",
    "sg:province":"CT",
    "wof:name":"East Wind Jewelry",
    "wof:placetype":"venue"
},
  "geometry": {"coordinates":[-72.647316,41.541109],"type":"Point"}
}