{
  "type": "Feature",
  "properties": {
    "addr:full":"267 Beach St West Haven CT 06516",
    "addr:housenumber":"267",
    "addr:postcode":"06516",
    "addr:street":"Beach St",
    "iso:country":"US",
    "sg:address":"267 Beach St",
    "sg:city":"West Haven",
    "sg:classifiers":[
        {
            "category":"Shopping",
            "subcategory":"Bicycles & Sporting Goods",
            "type":"Retail Goods"
        }
    ],
    "sg:phone":"+1 203 933 9483",
    "sg:postcode":"06516",
    "sg:province":"CT",
    "sg:tags":[
        "bait",
        "fishing"
    ],
    "wof:name":"Outdoor Sports Shop",
    "wof:placetype":"venue"
},
  "geometry": {"coordinates":[-72.937708,41.2597],"type":"Point"}
}