{
  "type": "Feature",
  "properties": {
    "iso:country":"US",
    "sg:address":"11 Dickinson Rd",
    "sg:city":"Marlborough",
    "sg:classifiers":[
        {
            "category":"Retail",
            "subcategory":"Repair Shop",
            "type":"Services"
        }
    ],
    "sg:phone":"+1   ",
    "sg:postcode":"06447",
    "sg:province":"CT",
    "wof:name":"Mr Rooter",
    "wof:placetype":"venue"
},
  "geometry": {"coordinates":[-72.47652600000001,41.6293],"type":"Point"}
}