{
  "type": "Feature",
  "properties": {
    "iso:country":"US",
    "sg:address":"24 Sunrise Ridge",
    "sg:city":"Rockfall",
    "sg:classifiers":[
        {
            "category":"Building & Trades",
            "subcategory":"Cleaning & Sanitation",
            "type":"Services"
        }
    ],
    "sg:phone":"+1   ",
    "sg:postcode":"06481",
    "sg:province":"CT",
    "sg:tags":[
        "maintenance"
    ],
    "wof:name":"Kathleen Paulson Clng Servi",
    "wof:placetype":"venue"
},
  "geometry": {"coordinates":[-72.696754,41.541785],"type":"Point"}
}