{
  "type": "Feature",
  "properties": {
    "iso:country":"US",
    "sg:address":"850 N Main Street Ext",
    "sg:city":"Wallingford",
    "sg:classifiers":[
        {
            "category":"Health Services",
            "subcategory":"Dentist",
            "type":"Services"
        }
    ],
    "sg:phone":"+1 203 949 1701",
    "sg:postcode":"06492",
    "sg:province":"CT",
    "sg:tags":[
        "dentists-cosmetic",
        "dentists-periodontists",
        "dentists-endodontists",
        "dentistry",
        "implant",
        "dentists-implantology"
    ],
    "sg:website":"http://www.wallingfordfamilydental.com",
    "wof:name":"Wallingford Family Dental",
    "wof:placetype":"venue"
},
  "geometry": {"coordinates":[-72.807503,41.480331],"type":"Point"}
}