{
  "type": "Feature",
  "properties": {
    "addr:full":"594 Pepper St Monroe CT 06468",
    "addr:housenumber":"594",
    "addr:postcode":"06468",
    "addr:street":"Pepper St",
    "iso:country":"US",
    "sg:address":"594 Pepper St",
    "sg:city":"Monroe",
    "sg:classifiers":[
        {
            "category":"Wholesale",
            "subcategory":"Furniture",
            "type":"Manufacturing & Wholesale Goods"
        }
    ],
    "sg:phone":"+1 203 445 2770",
    "sg:postcode":"06468",
    "sg:province":"CT",
    "wof:name":"AMOTEK/Lusa",
    "wof:placetype":"venue"
},
  "geometry": {"coordinates":[-73.25934700000001,41.348901],"type":"Point"}
}