{
  "type": "Feature",
  "properties": {
    "iso:country":"US",
    "sg:address":"57 Taylor Ave",
    "sg:city":"Norwalk",
    "sg:classifiers":[
        {
            "category":"Building & Trades",
            "subcategory":"Construction",
            "type":"Services"
        }
    ],
    "sg:phone":"+1 203 625 7022",
    "sg:postcode":"06854",
    "sg:province":"CT",
    "sg:tags":[
        "painter"
    ],
    "wof:name":"Juliani's Painting Co",
    "wof:placetype":"venue"
},
  "geometry": {"coordinates":[-73.428809,41.100531],"type":"Point"}
}