{
  "type": "Feature",
  "properties": {
    "addr:full":"206 Chipman St Waterbury CT 06708",
    "addr:housenumber":"206",
    "addr:postcode":"06708",
    "addr:street":"Chipman St Waterbury Ct",
    "iso:country":"US",
    "sg:address":"206 Chipman St",
    "sg:city":"Waterbury",
    "sg:classifiers":[
        {
            "category":"Real Estate",
            "subcategory":"Real Estate Agent",
            "type":"Services"
        }
    ],
    "sg:phone":"+1 203 756 4538",
    "sg:postcode":"06708",
    "sg:province":"CT",
    "wof:name":"E & D Enterprises",
    "wof:placetype":"venue"
},
  "geometry": {"coordinates":[-73.058183,41.542091],"type":"Point"}
}