{
  "type": "Feature",
  "properties": {
    "addr:full":"132 N Main St Port Chester CT 10573",
    "addr:housenumber":"132",
    "addr:postcode":"10573",
    "addr:street":"N Main St;Chester",
    "iso:country":"US",
    "sg:address":"132 N Main St",
    "sg:city":"Port Chester",
    "sg:classifiers":[
        {
            "category":"Personal",
            "subcategory":"Beauty Salon",
            "type":"Services"
        }
    ],
    "sg:phone":"+1 914 939 1630",
    "sg:postcode":"10573",
    "sg:province":"CT",
    "sg:tags":[
        "manicuring"
    ],
    "wof:name":"Susan's Beauty Shop",
    "wof:placetype":"venue"
},
  "geometry": {"coordinates":[-73.661017,41.003457],"type":"Point"}
}