{
  "type": "Feature",
  "properties": {
    "addr:full":"842 Farmington Ave Hartford CT 06119",
    "addr:housenumber":"842",
    "addr:postcode":"06119",
    "addr:street":"Farmington Ave;Ct",
    "iso:country":"US",
    "sg:address":"842 Farmington Ave",
    "sg:city":"Hartford",
    "sg:classifiers":[
        {
            "category":"Shopping",
            "subcategory":"Florist",
            "type":"Retail Goods"
        }
    ],
    "sg:phone":"+1 860 523 1734",
    "sg:postcode":"06119",
    "sg:province":"CT",
    "sg:tags":[
        "gift"
    ],
    "wof:name":"West Flowers",
    "wof:placetype":"venue"
},
  "geometry": {"coordinates":[-72.73095499999999,41.764415],"type":"Point"}
}