{
  "type": "Feature",
  "properties": {
    "iso:country":"US",
    "sg:address":"1 Academy Rd",
    "sg:city":"Oxford",
    "sg:classifiers":[
        {
            "category":"Professional",
            "type":"Services"
        }
    ],
    "sg:phone":"+1   ",
    "sg:postcode":"06478",
    "sg:province":"CT",
    "sg:tags":[
        "photo",
        "studio",
        "portrait"
    ],
    "wof:name":"Portrait Artist Terry Waldron",
    "wof:placetype":"venue"
},
  "geometry": {"coordinates":[-73.115931,41.435756],"type":"Point"}
}