{
  "type": "Feature",
  "properties": {
    "addr:full":"65 Willard Ter Stamford CT 06903",
    "addr:housenumber":"65",
    "addr:postcode":"06903",
    "addr:street":"Willard Ter",
    "iso:country":"US",
    "sg:address":"65 Willard Ter",
    "sg:city":"Stamford",
    "sg:classifiers":[
        {
            "category":"Professional",
            "subcategory":"Management & Consulting",
            "type":"Services"
        }
    ],
    "sg:phone":"+1   ",
    "sg:postcode":"06903",
    "sg:province":"CT",
    "sg:tags":[
        "business"
    ],
    "wof:name":"Mando Consulting LLC",
    "wof:placetype":"venue"
},
  "geometry": {"coordinates":[-73.54526799999999,41.114299],"type":"Point"}
}