{
  "type": "Feature",
  "properties": {
    "addr:full":"286 Sandbank Rd Cheshire CT 06410",
    "addr:housenumber":"286",
    "addr:postcode":"06410",
    "addr:street":"Sandbank Rd",
    "iso:country":"US",
    "sg:address":"286 Sandbank Rd",
    "sg:city":"Cheshire",
    "sg:classifiers":[
        {
            "category":"Manufacturing",
            "subcategory":"Metals",
            "type":"Manufacturing & Wholesale Goods"
        }
    ],
    "sg:phone":"+1 203 272 6413",
    "sg:postcode":"06410",
    "sg:province":"CT",
    "sg:tags":[
        "machine",
        "screw",
        "product"
    ],
    "wof:name":"Peerless Screw Products",
    "wof:placetype":"venue"
},
  "geometry": {"coordinates":[-72.90127200000001,41.534954],"type":"Point"}
}