{
  "type": "Feature",
  "properties": {
    "iso:country":"US",
    "sg:address":"40 NE Industrial Dr",
    "sg:city":"Branford",
    "sg:classifiers":[
        {
            "category":"Professional",
            "subcategory":"Computer Services",
            "type":"Services"
        }
    ],
    "sg:phone":"+1 203 483 4232",
    "sg:postcode":"06405",
    "sg:province":"CT",
    "sg:tags":[
        "repair"
    ],
    "wof:name":"Sbctec LLC",
    "wof:placetype":"venue"
},
  "geometry": {"coordinates":[-72.770055,41.300014],"type":"Point"}
}