{
  "type": "Feature",
  "properties": {
    "addr:full":"235 Ridgewood Dr Mystic CT 06355",
    "addr:housenumber":"235",
    "addr:postcode":"06355",
    "addr:street":"Ridgewood Dr Mystic Ct",
    "iso:country":"US",
    "sg:address":"235 Ridgewood Dr",
    "sg:city":"Mystic",
    "sg:classifiers":[
        {
            "category":"Professional",
            "subcategory":"Management & Consulting",
            "type":"Services"
        }
    ],
    "sg:phone":"+1   ",
    "sg:postcode":"06355",
    "sg:province":"CT",
    "sg:tags":[
        "technical"
    ],
    "wof:name":"Collier Associates Inc",
    "wof:placetype":"venue"
},
  "geometry": {"coordinates":[-72.005955,41.351756],"type":"Point"}
}