{
  "type": "Feature",
  "properties": {
    "addr:full":"66 Woodside Ave Westport CT 06880",
    "addr:housenumber":"66",
    "addr:postcode":"06880",
    "addr:street":"Woodside Ave",
    "iso:country":"US",
    "sg:address":"66 Woodside Ave",
    "sg:city":"Westport",
    "sg:classifiers":[
        {
            "category":"Professional",
            "subcategory":"Business Services",
            "type":"Services"
        }
    ],
    "sg:phone":"+1   ",
    "sg:postcode":"06880",
    "sg:province":"CT",
    "wof:name":"DAbbe Interiors",
    "wof:placetype":"venue"
},
  "geometry": {"coordinates":[-73.378378,41.14405],"type":"Point"}
}