{
  "type": "Feature",
  "properties": {
    "addr:full":"611 Campbell Ave West Haven CT 06516",
    "addr:housenumber":"611",
    "addr:postcode":"06516",
    "addr:street":"Campbell Ave",
    "iso:country":"US",
    "sg:address":"611 Campbell Ave",
    "sg:city":"West Haven",
    "sg:classifiers":[
        {
            "category":"Manufacturing",
            "subcategory":"Printing",
            "type":"Manufacturing & Wholesale Goods"
        }
    ],
    "sg:phone":"+1 203 933 8732",
    "sg:postcode":"06516",
    "sg:province":"CT",
    "sg:tags":[
        "copy",
        "xerox",
        "offset",
        "center"
    ],
    "wof:name":"Ross Copy & Print LLC",
    "wof:placetype":"venue"
},
  "geometry": {"coordinates":[-72.95234600000001,41.275429],"type":"Point"}
}