{
  "type": "Feature",
  "properties": {
    "iso:country":"US",
    "sg:address":"20 Hillandale Ave",
    "sg:city":"Stamford",
    "sg:classifiers":[
        {
            "category":"Banks & Credit Unions",
            "subcategory":"Financial Services",
            "type":"Services"
        }
    ],
    "sg:phone":"+1 203 324 1134",
    "sg:postcode":"06902",
    "sg:province":"CT",
    "sg:tags":[
        "company",
        "holding"
    ],
    "wof:name":"Scv Holdings",
    "wof:placetype":"venue"
},
  "geometry": {"coordinates":[-73.53169699999999,41.060672],"type":"Point"}
}