{
  "type": "Feature",
  "properties": {
    "iso:country":"US",
    "sg:address":"970 E Main St",
    "sg:city":"Bridgeport",
    "sg:classifiers":[
        {
            "category":"Health Services",
            "subcategory":"Clinic",
            "type":"Services"
        }
    ],
    "sg:phone":"+1 203 331 9504",
    "sg:postcode":"06608",
    "sg:province":"CT",
    "sg:tags":[
        "agency",
        "welfare"
    ],
    "wof:name":"Greater Bridgeport Pregnancy",
    "wof:placetype":"venue"
},
  "geometry": {"coordinates":[-73.180667,41.187476],"type":"Point"}
}