{
  "type": "Feature",
  "properties": {
    "addr:full":"310 Flanders Rd East Lyme CT 06333",
    "addr:housenumber":"310",
    "addr:postcode":"06333",
    "addr:street":"Flanders Rd East Lyme Ct",
    "iso:country":"US",
    "sg:address":"310 Flanders Rd",
    "sg:city":"East Lyme",
    "sg:classifiers":[
        {
            "category":"Personal",
            "subcategory":"Beauty Salon",
            "type":"Services"
        }
    ],
    "sg:phone":"+1   ",
    "sg:postcode":"06333",
    "sg:province":"CT",
    "sg:tags":[
        "shop"
    ],
    "wof:name":"Flanders Hair Design",
    "wof:placetype":"venue"
},
  "geometry": {"coordinates":[-72.210247,41.358885],"type":"Point"}
}