{
  "type": "Feature",
  "properties": {
    "iso:country":"US",
    "sg:address":"572 Boston Post Rd",
    "sg:city":"Milford",
    "sg:classifiers":[
        {
            "category":"Shopping",
            "subcategory":"Stationery & Office Supplies",
            "type":"Retail Goods"
        },
        {
            "category":"Shopping",
            "subcategory":"Bicycles & Sporting Goods",
            "type":"Retail Goods"
        },
        {
            "category":"Wholesale",
            "subcategory":"Machinery & Supplies",
            "type":"Manufacturing & Wholesale Goods"
        },
        {
            "category":"Travel",
            "subcategory":"Resort",
            "type":"Entertainment"
        },
        {
            "category":"Education",
            "subcategory":"Dance Studio",
            "type":"Public Place"
        }
    ],
    "sg:phone":"+1 203 882 0502",
    "sg:postcode":"06460",
    "sg:province":"CT",
    "sg:tags":[
        "skating",
        "square",
        "dancing",
        "machine",
        "equipment",
        "gymnastics",
        "apparel",
        "copy"
    ],
    "sg:website":"http://www.jitterbugsdancewear.com",
    "wof:name":"Jitterbugs",
    "wof:placetype":"venue"
},
  "geometry": {"coordinates":[-73.06463599999999,41.230353],"type":"Point"}
}