{
  "type": "Feature",
  "properties": {
    "iso:country":"US",
    "sg:address":"2480 Black Rock Tpke",
    "sg:city":"Fairfield",
    "sg:classifiers":[
        {
            "category":"Professional",
            "type":"Services"
        },
        {
            "category":"Restaurant",
            "type":"Food & Drink"
        }
    ],
    "sg:phone":"+1 203 374 6868",
    "sg:postcode":"06825",
    "sg:province":"CT",
    "sg:tags":[
        "caterer",
        "asian",
        "chinese",
        "pan"
    ],
    "wof:name":"Lilac House",
    "wof:placetype":"venue"
},
  "geometry": {"coordinates":[-73.2565,41.184975],"type":"Point"}
}