{
  "type": "Feature",
  "properties": {
    "addr:full":"63 Bank St Waterbury CT 06702",
    "addr:housenumber":"63",
    "addr:postcode":"06702",
    "addr:street":"Bank St Waterbury Ct",
    "iso:country":"US",
    "sg:address":"63 Bank St",
    "sg:city":"Waterbury",
    "sg:classifiers":[
        {
            "category":"Social Services",
            "type":"Services"
        }
    ],
    "sg:phone":"+1 203 754 6172",
    "sg:postcode":"06702",
    "sg:province":"CT",
    "sg:tags":[
        "organization",
        "welfare"
    ],
    "wof:name":"Hispanic Coalition",
    "wof:placetype":"venue"
},
  "geometry": {"coordinates":[-73.04076000000001,41.555678],"type":"Point"}
}