{
  "type": "Feature",
  "properties": {
    "iso:country":"US",
    "sg:address":"108 Bank St",
    "sg:city":"Waterbury",
    "sg:classifiers":[
        {
            "category":"Professional",
            "subcategory":"Computer Services",
            "type":"Services"
        }
    ],
    "sg:phone":"+1   ",
    "sg:postcode":"06702",
    "sg:province":"CT",
    "sg:tags":[
        "hardware",
        "development",
        "security",
        "software"
    ],
    "wof:name":"Clear Edge Networks LLC",
    "wof:placetype":"venue"
},
  "geometry": {"coordinates":[-73.041146,41.55387],"type":"Point"}
}