{
  "type": "Feature",
  "properties": {
    "addr:full":"2252 Main St Stratford CT 06615",
    "addr:housenumber":"2252",
    "addr:postcode":"06615",
    "addr:street":"Main St",
    "iso:country":"US",
    "sg:address":"2252 Main St",
    "sg:city":"Stratford",
    "sg:classifiers":[
        {
            "category":"Real Estate",
            "subcategory":"Real Estate Operator",
            "type":"Services"
        }
    ],
    "sg:phone":"+1 203 375 0457",
    "sg:postcode":"06615",
    "sg:province":"CT",
    "sg:tags":[
        "building",
        "nonresidential"
    ],
    "wof:name":"St James Building Assn Inc",
    "wof:placetype":"venue"
},
  "geometry": {"coordinates":[-73.13022599999999,41.192028],"type":"Point"}
}