{
  "type": "Feature",
  "properties": {
    "addr:full":"7 Backus Ave Danbury CT 06810",
    "addr:housenumber":"7",
    "addr:postcode":"06810",
    "addr:street":"Backus Ave",
    "iso:country":"US",
    "sg:address":"7 Backus Ave",
    "sg:city":"Danbury",
    "sg:classifiers":[
        {
            "category":"Shopping",
            "type":"Retail Goods"
        },
        {
            "category":"Museum",
            "type":"Entertainment"
        }
    ],
    "sg:phone":"+1 203 778 8049",
    "sg:postcode":"06810",
    "sg:province":"CT",
    "sg:tags":[
        "picture",
        "frame",
        "gallery"
    ],
    "wof:name":"Executive Gallery Inc",
    "wof:placetype":"venue"
},
  "geometry": {"coordinates":[-73.47560799999999,41.380075],"type":"Point"}
}