{
  "type": "Feature",
  "properties": {
    "iso:country":"US",
    "sg:address":"96 Tulip Tree Ct",
    "sg:city":"Milford",
    "sg:classifiers":[
        {
            "category":"Professional",
            "subcategory":"Business Services",
            "type":"Services"
        }
    ],
    "sg:phone":"+1   ",
    "sg:postcode":"06461",
    "sg:province":"CT",
    "wof:name":"Sound Marine Solutions Inc",
    "wof:placetype":"venue"
},
  "geometry": {"coordinates":[-73.076325,41.237261],"type":"Point"}
}