{
  "type": "Feature",
  "properties": {
    "addr:full":"1477 New Haven Ave Milford CT 06460",
    "addr:housenumber":"1477",
    "addr:postcode":"06460",
    "addr:street":"New Haven Ave",
    "iso:country":"US",
    "sg:address":"1477 New Haven Ave",
    "sg:city":"Milford",
    "sg:classifiers":[
        {
            "category":"Building & Trades",
            "subcategory":"Construction",
            "type":"Services"
        }
    ],
    "sg:phone":"+1 203 877 2679",
    "sg:postcode":"06460",
    "sg:province":"CT",
    "sg:tags":[
        "repairing",
        "remodeling",
        "contractor"
    ],
    "wof:name":"Creative Builders",
    "wof:placetype":"venue"
},
  "geometry": {"coordinates":[-72.991564,41.230347],"type":"Point"}
}