{
  "type": "Feature",
  "properties": {
    "iso:country":"US",
    "sg:address":"101 Eastern Steel Rd",
    "sg:city":"Milford",
    "sg:classifiers":[
        {
            "category":"Retail",
            "subcategory":"Auto Repair",
            "type":"Services"
        }
    ],
    "sg:phone":"+1 203 877 4270",
    "sg:postcode":"06460",
    "sg:province":"CT",
    "sg:tags":[
        "heavy",
        "truck"
    ],
    "wof:name":"Petry's Truck & Diesel Inc",
    "wof:placetype":"venue"
},
  "geometry": {"coordinates":[-73.019975,41.234612],"type":"Point"}
}