{
  "type": "Feature",
  "properties": {
    "iso:country":"US",
    "sg:address":"425 Laurel Hill Ave",
    "sg:city":"Norwich",
    "sg:classifiers":[
        {
            "category":"Restaurant",
            "type":"Food & Drink"
        }
    ],
    "sg:phone":"+1 860 887 2289",
    "sg:postcode":"06360",
    "sg:province":"CT",
    "wof:name":"Sunset Pizza Inc",
    "wof:placetype":"venue"
},
  "geometry": {"coordinates":[-72.07576400000001,41.508268],"type":"Point"}
}