{
  "type": "Feature",
  "properties": {
    "addr:full":"20 Michael Dr Farmington CT 06032",
    "addr:housenumber":"20",
    "addr:postcode":"06032",
    "addr:street":"Michael Dr",
    "iso:country":"US",
    "sg:address":"20 Michael Dr",
    "sg:city":"Farmington",
    "sg:classifiers":[
        {
            "category":"Banks & Credit Unions",
            "subcategory":"Investment Brokerage",
            "type":"Services"
        }
    ],
    "sg:phone":"+1 860 678 7783",
    "sg:postcode":"06032",
    "sg:province":"CT",
    "sg:tags":[
        "advisory"
    ],
    "wof:name":"Zarius Financial Inc",
    "wof:placetype":"venue"
},
  "geometry": {"coordinates":[-72.860934,41.755714],"type":"Point"}
}