{
  "type": "Feature",
  "properties": {
    "addr:full":"13 Harmony St Danbury CT 06810",
    "addr:housenumber":"13",
    "addr:postcode":"06810",
    "addr:street":"Harmony St",
    "iso:country":"US",
    "sg:address":"13 Harmony St",
    "sg:city":"Danbury",
    "sg:classifiers":[
        {
            "category":"Professional",
            "subcategory":"Lawyer & Legal Services",
            "type":"Services"
        }
    ],
    "sg:phone":"+1   ",
    "sg:postcode":"06810",
    "sg:province":"CT",
    "wof:name":"Sakellares George S",
    "wof:placetype":"venue"
},
  "geometry": {"coordinates":[-73.457769,41.393125],"type":"Point"}
}