{
  "type": "Feature",
  "properties": {
    "addr:full":"500 Bridge St Groton CT 06340",
    "addr:housenumber":"500",
    "addr:postcode":"06340",
    "addr:street":"Bridge St",
    "iso:country":"US",
    "sg:address":"500 Bridge St",
    "sg:city":"Groton",
    "sg:classifiers":[
        {
            "category":"Real Estate",
            "subcategory":"Real Estate Agent",
            "type":"Services"
        }
    ],
    "sg:phone":"+1 860 445 4663",
    "sg:postcode":"06340",
    "sg:province":"CT",
    "wof:name":"Re/Max Property Consultants",
    "wof:placetype":"venue"
},
  "geometry": {"coordinates":[-72.067072,41.36136],"type":"Point"}
}