{
  "type": "Feature",
  "properties": {
    "iso:country":"US",
    "sg:address":"94 Mill Plain Rd",
    "sg:city":"Danbury",
    "sg:classifiers":[
        {
            "category":"Autos & Motor Vehicles",
            "subcategory":"Automobile Sales",
            "type":"Retail Goods"
        }
    ],
    "sg:phone":"+1 203 748 1945",
    "sg:postcode":"06811",
    "sg:province":"CT",
    "sg:tags":[
        "car",
        "dealer"
    ],
    "wof:name":"Weeks Pre-Owned Ctr",
    "wof:placetype":"venue"
},
  "geometry": {"coordinates":[-73.512934,41.394373],"type":"Point"}
}