{
  "type": "Feature",
  "properties": {
    "addr:full":"2687 High Ridge Rd Stamford CT 06903",
    "addr:housenumber":"2687",
    "addr:postcode":"06903",
    "addr:street":"High Ridge Rd",
    "iso:country":"US",
    "sg:address":"2687 High Ridge Rd",
    "sg:city":"Stamford",
    "sg:classifiers":[
        {
            "category":"Real Estate",
            "subcategory":"Real Estate Services",
            "type":"Services"
        },
        {
            "category":"Building & Trades",
            "subcategory":"Cleaning & Sanitation",
            "type":"Services"
        }
    ],
    "sg:phone":"+1 203 869 6093",
    "sg:postcode":"06903",
    "sg:province":"CT",
    "sg:tags":[
        "cleaners-interior",
        "cleaning-industrial",
        "maintenance",
        "contractor"
    ],
    "wof:name":"Julianna's Housekeeping",
    "wof:placetype":"venue"
},
  "geometry": {"coordinates":[-73.560458,41.159139],"type":"Point"}
}