{
  "type": "Feature",
  "properties": {
    "addr:full":"1799 Summer St Stamford CT 06905",
    "addr:housenumber":"1799",
    "addr:postcode":"06905",
    "addr:street":"Summer St",
    "iso:country":"US",
    "sg:address":"1799 Summer St",
    "sg:city":"Stamford",
    "sg:classifiers":[
        {
            "category":"Real Estate",
            "subcategory":"Real Estate Agent",
            "type":"Services"
        }
    ],
    "sg:phone":"+1 203 869 6994",
    "sg:postcode":"06905",
    "sg:province":"CT",
    "wof:name":"Lane Wilmot Corp Inc",
    "wof:placetype":"venue"
},
  "geometry": {"coordinates":[-73.543239,41.064304],"type":"Point"}
}