{
  "type": "Feature",
  "properties": {
    "addr:full":"104 Universal Dr North Haven CT 06473",
    "addr:housenumber":"104",
    "addr:postcode":"06473",
    "addr:street":"Universal Dr;Haven",
    "iso:country":"US",
    "sg:address":"104 Universal Dr",
    "sg:city":"North Haven",
    "sg:classifiers":[
        {
            "category":"Restaurant",
            "type":"Food & Drink"
        }
    ],
    "sg:menulink":"http://www.allmenus.com/ct/north-haven/123997-quiznos-sub/menu/",
    "sg:phone":"+1 203 234 2560",
    "sg:postcode":"06473",
    "sg:province":"CT",
    "sg:tags":[
        "wrap",
        "american",
        "sandwich"
    ],
    "wof:name":"Quiznos Sub",
    "wof:placetype":"venue"
},
  "geometry": {"coordinates":[-72.869317,41.345426],"type":"Point"}
}