{
  "type": "Feature",
  "properties": {
    "iso:country":"US",
    "sg:address":"63 Osborne Hill Rd",
    "sg:city":"Sandy Hook",
    "sg:classifiers":[
        {
            "category":"Professional",
            "subcategory":"Art Services",
            "type":"Services"
        }
    ],
    "sg:phone":"+1   ",
    "sg:postcode":"06482",
    "sg:province":"CT",
    "sg:tags":[
        "commercial",
        "design"
    ],
    "wof:name":"Ultra Maroon Design",
    "wof:placetype":"venue"
},
  "geometry": {"coordinates":[-73.213055,41.400422],"type":"Point"}
}