{
  "type": "Feature",
  "properties": {
    "addr:full":"247 Laurel St East Haven CT 06512",
    "addr:housenumber":"247",
    "addr:postcode":"06512",
    "addr:street":"Laurel St;Haven",
    "iso:country":"US",
    "sg:address":"247 Laurel St",
    "sg:city":"East Haven",
    "sg:classifiers":[
        {
            "category":"Personal",
            "subcategory":"Beauty Salon",
            "type":"Services"
        }
    ],
    "sg:phone":"+1 203 467 2467",
    "sg:postcode":"06512",
    "sg:province":"CT",
    "sg:tags":[
        "shop"
    ],
    "wof:name":"Chetta's Hair Studio",
    "wof:placetype":"venue"
},
  "geometry": {"coordinates":[-72.87072499999999,41.290803],"type":"Point"}
}