{
  "type": "Feature",
  "properties": {
    "iso:country":"US",
    "sg:address":"3510 Main St",
    "sg:city":"Bridgeport",
    "sg:classifiers":[
        {
            "category":"Real Estate",
            "subcategory":"Developer",
            "type":"Services"
        }
    ],
    "sg:phone":"+1 203 373 5969",
    "sg:postcode":"06606",
    "sg:province":"CT",
    "sg:tags":[
        "cemetery"
    ],
    "wof:name":"Mountain Grove Cemetery Easton",
    "wof:placetype":"venue"
},
  "geometry": {"coordinates":[-73.208232,41.209246],"type":"Point"}
}