{
  "type": "Feature",
  "properties": {
    "addr:full":"55 Spring Hill Ave Norwalk CT 06850",
    "addr:housenumber":"55",
    "addr:postcode":"06850",
    "addr:street":"Spring Hill Ave",
    "iso:country":"US",
    "sg:address":"55 Spring Hill Ave",
    "sg:city":"Norwalk",
    "sg:classifiers":[
        {
            "category":"Building & Trades",
            "subcategory":"Landscaping Services",
            "type":"Services"
        }
    ],
    "sg:phone":"+1 203 846 9057",
    "sg:postcode":"06850",
    "sg:province":"CT",
    "wof:name":"H & M Landscaping Company",
    "wof:placetype":"venue"
},
  "geometry": {"coordinates":[-73.426434,41.120244],"type":"Point"}
}