{
  "type": "Feature",
  "properties": {
    "iso:country":"US",
    "sg:address":"171 Ball Pond Rd",
    "sg:city":"New Fairfield",
    "sg:classifiers":[
        {
            "category":"Communications",
            "subcategory":"Film & Video Production",
            "type":"Services"
        }
    ],
    "sg:phone":"+1   ",
    "sg:postcode":"06812",
    "sg:province":"CT",
    "wof:name":"Digital Video Productions",
    "wof:placetype":"venue"
},
  "geometry": {"coordinates":[-73.51014499999999,41.47071],"type":"Point"}
}