{
  "type": "Feature",
  "properties": {
    "iso:country":"US",
    "sg:address":"1024 Broad St",
    "sg:city":"Meriden",
    "sg:classifiers":[
        {
            "category":"Food & Beverages",
            "subcategory":"Liquor & Beverages",
            "type":"Retail Goods"
        }
    ],
    "sg:phone":"+1 203 235 6971",
    "sg:postcode":"06450",
    "sg:province":"CT",
    "wof:name":"Brookside Package Store",
    "wof:placetype":"venue"
},
  "geometry": {"coordinates":[-72.78388200000001,41.545773],"type":"Point"}
}