{
  "type": "Feature",
  "properties": {
    "iso:country":"US",
    "sg:address":"567 Main St",
    "sg:city":"Branford",
    "sg:classifiers":[
        {
            "category":"Shopping",
            "subcategory":"Jewelry",
            "type":"Retail Goods"
        }
    ],
    "sg:phone":"+1 203 488 4653",
    "sg:postcode":"06405",
    "sg:province":"CT",
    "sg:tags":[
        "repair"
    ],
    "wof:name":"Branford Jewelers",
    "wof:placetype":"venue"
},
  "geometry": {"coordinates":[-72.81756799999999,41.278164],"type":"Point"}
}