{
  "type": "Feature",
  "properties": {
    "addr:full":"236 Cherry St Naugatuck CT 06770",
    "addr:housenumber":"236",
    "addr:postcode":"06770",
    "addr:street":"Cherry St Naugatuck Ct",
    "iso:country":"US",
    "sg:address":"236 Cherry St",
    "sg:city":"Naugatuck",
    "sg:classifiers":[
        {
            "category":"Organizations",
            "subcategory":"Religious Organization",
            "type":"Services"
        }
    ],
    "sg:phone":"+1 203 597 8188",
    "sg:postcode":"06770",
    "sg:province":"CT",
    "sg:tags":[
        "monastery",
        "convent"
    ],
    "wof:name":"Brothers Of Holy Cross",
    "wof:placetype":"venue"
},
  "geometry": {"coordinates":[-73.055791,41.479929],"type":"Point"}
}