{
  "type": "Feature",
  "properties": {
    "iso:country":"US",
    "sg:address":"235 Norton Rd",
    "sg:city":"Berlin",
    "sg:classifiers":[
        {
            "category":"Manufacturing",
            "subcategory":"Tools & Machinery",
            "type":"Manufacturing & Wholesale Goods"
        }
    ],
    "sg:phone":"+1 860 828 1942",
    "sg:postcode":"06037",
    "sg:province":"CT",
    "sg:tags":[
        "industry",
        "mfg"
    ],
    "wof:name":"B&J Assoc",
    "wof:placetype":"venue"
},
  "geometry": {"coordinates":[-72.784964,41.612301],"type":"Point"}
}