{
  "type": "Feature",
  "properties": {
    "iso:country":"US",
    "sg:address":"1 Eastern Steel Rd",
    "sg:city":"Milford",
    "sg:classifiers":[
        {
            "category":"Wholesale",
            "subcategory":"Construction Materials",
            "type":"Manufacturing & Wholesale Goods"
        }
    ],
    "sg:phone":"+1 203 878 9381",
    "sg:postcode":"06460",
    "sg:province":"CT",
    "wof:name":"Olympic Steel Co",
    "wof:placetype":"venue"
},
  "geometry": {"coordinates":[-73.019975,41.234612],"type":"Point"}
}