{
  "type": "Feature",
  "properties": {
    "addr:full":"720 N Colony Rd Wallingford CT 06492",
    "addr:housenumber":"720",
    "addr:postcode":"06492",
    "addr:street":"N Colony Rd",
    "iso:country":"US",
    "sg:address":"720 N Colony Rd",
    "sg:city":"Wallingford",
    "sg:classifiers":[
        {
            "category":"Food & Beverages",
            "subcategory":"Groceries & Convenience Stores",
            "type":"Retail Goods"
        }
    ],
    "sg:phone":"+1 203 284 0490",
    "sg:postcode":"06492",
    "sg:province":"CT",
    "wof:name":"Fasmart",
    "wof:placetype":"venue"
},
  "geometry": {"coordinates":[-72.813275,41.475625],"type":"Point"}
}