{
  "type": "Feature",
  "properties": {
    "iso:country":"US",
    "sg:address":"232 Providence-New London Tpke",
    "sg:city":"North Stonington",
    "sg:classifiers":[
        {
            "category":"Organizations",
            "subcategory":"Membership Organization",
            "type":"Services"
        }
    ],
    "sg:phone":"+1   ",
    "sg:postcode":"06359",
    "sg:province":"CT",
    "wof:name":"Stonington Dragers",
    "wof:placetype":"venue"
},
  "geometry": {"coordinates":[-71.858647,41.425059],"type":"Point"}
}