{
  "type": "Feature",
  "properties": {
    "addr:full":"72 Bissell St Manchester CT 06040",
    "addr:housenumber":"72",
    "addr:postcode":"06040",
    "addr:street":"Bissell St",
    "iso:country":"US",
    "sg:address":"72 Bissell St",
    "sg:city":"Manchester",
    "sg:classifiers":[
        {
            "category":"Social Services",
            "type":"Services"
        }
    ],
    "sg:phone":"+1   ",
    "sg:postcode":"06040",
    "sg:province":"CT",
    "wof:name":"Psycoterapy Associates",
    "wof:placetype":"venue"
},
  "geometry": {"coordinates":[-72.51640999999999,41.77248],"type":"Point"}
}