{
  "type": "Feature",
  "properties": {
    "iso:country":"US",
    "sg:address":"155 Thomaston Ave",
    "sg:city":"Waterbury",
    "sg:classifiers":[
        {
            "category":"Food & Beverages",
            "subcategory":"Groceries & Convenience Stores",
            "type":"Retail Goods"
        }
    ],
    "sg:phone":"+1 203 841 0050",
    "sg:postcode":"06702",
    "sg:province":"CT",
    "sg:tags":[
        "grocer"
    ],
    "wof:name":"Shop Fresh",
    "wof:placetype":"venue"
},
  "geometry": {"coordinates":[-73.05448199999999,41.563749],"type":"Point"}
}