{
  "type": "Feature",
  "properties": {
    "iso:country":"US",
    "sg:address":"23 Rock St",
    "sg:city":"Milford",
    "sg:classifiers":[
        {
            "category":"Arts & Performance",
            "subcategory":"Theater",
            "type":"Entertainment"
        }
    ],
    "sg:phone":"+1   ",
    "sg:postcode":"06460",
    "sg:province":"CT",
    "sg:tags":[
        "performing"
    ],
    "wof:name":"Ginga Brasileira Inc",
    "wof:placetype":"venue"
},
  "geometry": {"coordinates":[-73.004537,41.222808],"type":"Point"}
}