{
  "type": "Feature",
  "properties": {
    "addr:full":"109 Washington St Waterbury CT 06706",
    "addr:housenumber":"109",
    "addr:postcode":"06706",
    "addr:street":"Washington St Waterbury Ct",
    "iso:country":"US",
    "sg:address":"109 Washington St",
    "sg:city":"Waterbury",
    "sg:classifiers":[
        {
            "category":"Recreation",
            "type":"Entertainment"
        }
    ],
    "sg:phone":"+1 203 754 8541",
    "sg:postcode":"06706",
    "sg:province":"CT",
    "sg:tags":[
        "church",
        "place",
        "worship",
        "hall",
        "auditorium"
    ],
    "wof:name":"Saint Francis Xavier Hall",
    "wof:placetype":"venue"
},
  "geometry": {"coordinates":[-73.033376,41.54372],"type":"Point"}
}