{
  "type": "Feature",
  "properties": {
    "addr:full":"214 Reed Ave Windsor Locks CT 06096",
    "addr:housenumber":"214",
    "addr:postcode":"06096",
    "addr:street":"Reed Ave;Locks Ct",
    "iso:country":"US",
    "sg:address":"214 Reed Ave",
    "sg:city":"Windsor Locks",
    "sg:classifiers":[
        {
            "category":"Building & Trades",
            "subcategory":"Landscaping Services",
            "type":"Services"
        }
    ],
    "sg:phone":"+1 860 623 7367",
    "sg:postcode":"06096",
    "sg:province":"CT",
    "wof:name":"Jay & Sons Lawncare LLC",
    "wof:placetype":"venue"
},
  "geometry": {"coordinates":[-72.64041400000001,41.933686],"type":"Point"}
}