{
  "type": "Feature",
  "properties": {
    "iso:country":"US",
    "sg:address":"1328 Whalley Ave",
    "sg:city":"New Haven",
    "sg:classifiers":[
        {
            "category":"Shopping",
            "type":"Retail Goods"
        }
    ],
    "sg:phone":"+1 203 387 5565",
    "sg:postcode":"06515",
    "sg:province":"CT",
    "sg:tags":[
        "equipment",
        "care",
        "health",
        "home"
    ],
    "wof:name":"Comfort Home Med Supplies LLC",
    "wof:placetype":"venue"
},
  "geometry": {"coordinates":[-72.973455,41.331254],"type":"Point"}
}