{
  "type": "Feature",
  "properties": {
    "iso:country":"US",
    "sg:address":"82 Iroquois Rd",
    "sg:city":"Stamford",
    "sg:classifiers":[
        {
            "category":"Restaurant",
            "type":"Food & Drink"
        }
    ],
    "sg:phone":"+1 203 323 1787",
    "sg:postcode":"06902",
    "sg:province":"CT",
    "wof:name":"Brennan's Restaurant",
    "wof:placetype":"venue"
},
  "geometry": {"coordinates":[-73.52370500000001,41.03753],"type":"Point"}
}