{
  "type": "Feature",
  "properties": {
    "addr:full":"133 Roosevelt Dr Trumbull CT 06611",
    "addr:housenumber":"133",
    "addr:postcode":"06611",
    "addr:street":"Roosevelt Dr",
    "iso:country":"US",
    "sg:address":"133 Roosevelt Dr",
    "sg:city":"Trumbull",
    "sg:classifiers":[
        {
            "category":"Professional",
            "subcategory":"Business Services",
            "type":"Services"
        }
    ],
    "sg:phone":"+1   ",
    "sg:postcode":"06611",
    "sg:province":"CT",
    "wof:name":"Premier Pools",
    "wof:placetype":"venue"
},
  "geometry": {"coordinates":[-73.20209,41.269268],"type":"Point"}
}