{
  "type": "Feature",
  "properties": {
    "addr:full":"117 Flax Mill Rd Branford CT 06405",
    "addr:housenumber":"117",
    "addr:postcode":"06405",
    "addr:street":"Flax Mill Rd",
    "iso:country":"US",
    "sg:address":"117 Flax Mill Rd",
    "sg:city":"Branford",
    "sg:classifiers":[
        {
            "category":"Building & Trades",
            "subcategory":"Construction",
            "type":"Services"
        }
    ],
    "sg:phone":"+1 203 481 9326",
    "sg:postcode":"06405",
    "sg:province":"CT",
    "sg:tags":[
        "excavation",
        "contractor"
    ],
    "wof:name":"Massey Brothers Cnstr LLC",
    "wof:placetype":"venue"
},
  "geometry": {"coordinates":[-72.778499,41.306486],"type":"Point"}
}