{
  "type": "Feature",
  "properties": {
    "iso:country":"US",
    "sg:address":"84 Ridge Hill Rd",
    "sg:city":"Oakdale",
    "sg:phone":"+1 860 625 0224",
    "sg:postcode":"06370",
    "sg:province":"CT",
    "sg:website":"http://www.boucheybuilders.com",
    "wof:name":"Bouchey Builders",
    "wof:placetype":"venue"
},
  "geometry": {"coordinates":[-72.18868999999999,41.42355],"type":"Point"}
}