{
  "type": "Feature",
  "properties": {
    "iso:country":"US",
    "sg:address":"4 Briarwood Dr",
    "sg:city":"Sherman",
    "sg:classifiers":[
        {
            "category":"Manufacturing",
            "subcategory":"Glass & Minerals",
            "type":"Manufacturing & Wholesale Goods"
        }
    ],
    "sg:phone":"+1 860 210 1286",
    "sg:postcode":"06784",
    "sg:province":"CT",
    "sg:tags":[
        "cut",
        "mfg"
    ],
    "wof:name":"Godfrey Cemetary Maint LLC",
    "wof:placetype":"venue"
},
  "geometry": {"coordinates":[-73.499183,41.595148],"type":"Point"}
}