{
  "type": "Feature",
  "properties": {
    "addr:full":"233 Broad St Milford CT 06460",
    "addr:housenumber":"233",
    "addr:postcode":"06460",
    "addr:street":"Broad St",
    "iso:country":"US",
    "sg:address":"233 Broad St",
    "sg:city":"Milford",
    "sg:classifiers":[
        {
            "category":"Shopping",
            "subcategory":"Pharmacy",
            "type":"Retail Goods"
        }
    ],
    "sg:phone":"+1 203 877 8127",
    "sg:postcode":"06460",
    "sg:province":"CT",
    "wof:name":"CVS Pharmacy",
    "wof:placetype":"venue"
},
  "geometry": {"coordinates":[-73.06345399999999,41.218754],"type":"Point"}
}