{
  "type": "Feature",
  "properties": {
    "iso:country":"US",
    "sg:address":"3 Meadowbank Rd",
    "sg:city":"Old Greenwich",
    "sg:classifiers":[
        {
            "category":"Professional",
            "subcategory":"Lawyer & Legal Services",
            "type":"Services"
        }
    ],
    "sg:phone":"+1   ",
    "sg:postcode":"06870",
    "sg:province":"CT",
    "wof:name":"Stephen Pierson",
    "wof:placetype":"venue"
},
  "geometry": {"coordinates":[-73.558307,41.017822],"type":"Point"}
}