{
  "type": "Feature",
  "properties": {
    "addr:full":"1114 Federal Rd Brookfield CT 06804",
    "addr:housenumber":"1114",
    "addr:postcode":"06804",
    "addr:street":"Federal Rd",
    "iso:country":"US",
    "sg:address":"1114 Federal Rd",
    "sg:city":"Brookfield",
    "sg:classifiers":[
        {
            "category":"Manufacturing",
            "subcategory":"Electronics",
            "type":"Manufacturing & Wholesale Goods"
        }
    ],
    "sg:phone":"+1 203 740 9333",
    "sg:postcode":"06804",
    "sg:province":"CT",
    "sg:tags":[
        "printers-equipment",
        "supply"
    ],
    "sg:website":"http://www.itwinc.com",
    "wof:name":"Illinois Tool Works Inc.",
    "wof:placetype":"venue"
},
  "geometry": {"coordinates":[-73.417732,41.497931],"type":"Point"}
}