{
  "type": "Feature",
  "properties": {
    "iso:country":"US",
    "sg:address":"19 Thomas Dr",
    "sg:city":"Tolland",
    "sg:classifiers":[
        {
            "category":"Shopping",
            "subcategory":"Computers & Home Electronics",
            "type":"Retail Goods"
        }
    ],
    "sg:phone":"+1 860 871 9263",
    "sg:postcode":"06084",
    "sg:province":"CT",
    "wof:name":"Tri Star Computers LLC",
    "wof:placetype":"venue"
},
  "geometry": {"coordinates":[-72.329168,41.875],"type":"Point"}
}