{
  "type": "Feature",
  "properties": {
    "iso:country":"US",
    "sg:address":"6 Shady Ln",
    "sg:city":"Greenwich",
    "sg:classifiers":[
        {
            "category":"Real Estate",
            "subcategory":"Architect",
            "type":"Services"
        }
    ],
    "sg:phone":"+1 203 531 1774",
    "sg:postcode":"06831",
    "sg:province":"NY",
    "wof:name":"Pat M Pulitano",
    "wof:placetype":"venue"
},
  "geometry": {"coordinates":[-73.67148,41.036267],"type":"Point"}
}