{
  "type": "Feature",
  "properties": {
    "addr:full":"391 Post Rd W Westport CT 06880",
    "addr:housenumber":"391",
    "addr:postcode":"06880",
    "addr:street":"Post Rd W Westport Ct",
    "iso:country":"US",
    "sg:address":"391 Post Rd W",
    "sg:city":"Westport",
    "sg:classifiers":[
        {
            "category":"Home & Garden",
            "subcategory":"Furniture",
            "type":"Retail Goods"
        }
    ],
    "sg:phone":"+1 203 227 7443",
    "sg:postcode":"06880",
    "sg:province":"CT",
    "sg:tags":[
        "bedding",
        "mattress",
        "including",
        "headboard"
    ],
    "wof:name":"Sleepys Inc",
    "wof:placetype":"venue"
},
  "geometry": {"coordinates":[-73.377666,41.129983],"type":"Point"}
}