{
  "type": "Feature",
  "properties": {
    "iso:country":"US",
    "sg:address":"53 Clint Eldredge Rd",
    "sg:city":"Willington",
    "sg:classifiers":[
        {
            "category":"Home & Garden",
            "subcategory":"Carpets & Floor Coverings",
            "type":"Retail Goods"
        }
    ],
    "sg:phone":"+1 888 649 5554",
    "sg:postcode":"06279",
    "sg:province":"CT",
    "sg:tags":[
        "flooring",
        "hardwood",
        "lining",
        "material",
        "rug",
        "accessory",
        "pads",
        "contractor"
    ],
    "wof:name":"Kibbe Bros Custom Floors",
    "wof:placetype":"venue"
},
  "geometry": {"coordinates":[-72.255349,41.861484],"type":"Point"}
}