{
  "type": "Feature",
  "properties": {
    "addr:full":"146 Main St Monroe CT 06468",
    "addr:housenumber":"146",
    "addr:postcode":"06468",
    "addr:street":"Main St",
    "iso:country":"US",
    "sg:address":"146 Main St",
    "sg:city":"Monroe",
    "sg:classifiers":[
        {
            "category":"Professional",
            "subcategory":"Computer Services",
            "type":"Services"
        }
    ],
    "sg:phone":"+1   ",
    "sg:postcode":"06468",
    "sg:province":"CT",
    "sg:tags":[
        "prepackaged",
        "software"
    ],
    "wof:name":"Technology Store",
    "wof:placetype":"venue"
},
  "geometry": {"coordinates":[-73.25704399999999,41.309082],"type":"Point"}
}