{
  "type": "Feature",
  "properties": {
    "iso:country":"US",
    "sg:address":"112 Country Club Rd",
    "sg:city":"Avon",
    "sg:classifiers":[
        {
            "category":"Professional",
            "subcategory":"Management & Consulting",
            "type":"Services"
        }
    ],
    "sg:phone":"+1   ",
    "sg:postcode":"06001",
    "sg:province":"CT",
    "wof:name":"Impact Training Service",
    "wof:placetype":"venue"
},
  "geometry": {"coordinates":[-72.842895,41.792545],"type":"Point"}
}