{
  "type": "Feature",
  "properties": {
    "iso:country":"US",
    "sg:address":"58 Van Zant St",
    "sg:city":"Norwalk",
    "sg:classifiers":[
        {
            "category":"Autos & Motor Vehicles",
            "subcategory":"Boat Sales",
            "type":"Retail Goods"
        },
        {
            "category":"Recreation",
            "subcategory":"Marina",
            "type":"Entertainment"
        }
    ],
    "sg:phone":"+1 203 899 0051",
    "sg:postcode":"06855",
    "sg:province":"CT",
    "sg:tags":[
        "repair",
        "operation",
        "sales",
        "dealer"
    ],
    "wof:name":"Boat Connections LLC",
    "wof:placetype":"venue"
},
  "geometry": {"coordinates":[-73.40426100000001,41.101911],"type":"Point"}
}