{
  "type": "Feature",
  "properties": {
    "iso:country":"US",
    "sg:address":"115 Main St",
    "sg:city":"New Haven",
    "sg:classifiers":[
        {
            "category":"Autos & Motor Vehicles",
            "subcategory":"Fuel & Gas Station",
            "type":"Retail Goods"
        }
    ],
    "sg:phone":"+1 203 777 2454",
    "sg:postcode":"06513",
    "sg:province":"CT",
    "sg:tags":[
        "oil"
    ],
    "wof:name":"Bousquet's Service Ctr",
    "wof:placetype":"venue"
},
  "geometry": {"coordinates":[-72.90299899999999,41.314578],"type":"Point"}
}