{
  "type": "Feature",
  "properties": {
    "iso:country":"US",
    "sg:address":"281 Burnside Ave",
    "sg:city":"East Hartford",
    "sg:classifiers":[
        {
            "category":"Food & Beverages",
            "subcategory":"Groceries & Convenience Stores",
            "type":"Retail Goods"
        }
    ],
    "sg:phone":"+1 860 282 7744",
    "sg:postcode":"06108",
    "sg:province":"CT",
    "wof:name":"Kotoko International Fd & Prod",
    "wof:placetype":"venue"
},
  "geometry": {"coordinates":[-72.627,41.775776],"type":"Point"}
}