{
  "type": "Feature",
  "properties": {
    "iso:country":"US",
    "sg:address":"52 Helena Rd",
    "sg:city":"Avon",
    "sg:classifiers":[
        {
            "category":"Professional",
            "type":"Services"
        }
    ],
    "sg:phone":"+1 860 675 0466",
    "sg:postcode":"06001",
    "sg:province":"CT",
    "wof:name":"Kids Protecting Kids",
    "wof:placetype":"venue"
},
  "geometry": {"coordinates":[-72.887929,41.802347],"type":"Point"}
}