{
  "type": "Feature",
  "properties": {
    "iso:country":"US",
    "sg:address":"181 Josies Ring Rd",
    "sg:city":"Monroe",
    "sg:classifiers":[
        {
            "category":"Professional",
            "subcategory":"Business Services",
            "type":"Services"
        }
    ],
    "sg:phone":"+1   ",
    "sg:postcode":"06468",
    "sg:province":"CT",
    "wof:name":"Lk Assoc LLC",
    "wof:placetype":"venue"
},
  "geometry": {"coordinates":[-73.194495,41.368282],"type":"Point"}
}