{
  "type": "Feature",
  "properties": {
    "iso:country":"US",
    "sg:address":"52 Court St",
    "sg:city":"New Haven",
    "sg:classifiers":[
        {
            "category":"Food & Beverages",
            "subcategory":"Meat & Fish",
            "type":"Retail Goods"
        }
    ],
    "sg:phone":"+1 203 934 3466",
    "sg:postcode":"06511",
    "sg:province":"CT",
    "wof:name":"Fess Halal Meat Market Corp",
    "wof:placetype":"venue"
},
  "geometry": {"coordinates":[-72.92080900000001,41.305309],"type":"Point"}
}