{
  "type": "Feature",
  "properties": {
    "addr:full":"4 Loretta Ct Westport CT 06880",
    "addr:housenumber":"4",
    "addr:postcode":"06880",
    "addr:street":"Loretta Ct",
    "iso:country":"US",
    "sg:address":"4 Loretta Ct",
    "sg:city":"Westport",
    "sg:classifiers":[
        {
            "category":"Professional",
            "subcategory":"Management & Consulting",
            "type":"Services"
        }
    ],
    "sg:phone":"+1   ",
    "sg:postcode":"06880",
    "sg:province":"CT",
    "sg:tags":[
        "business"
    ],
    "wof:name":"Robert Brannagan Association",
    "wof:placetype":"venue"
},
  "geometry": {"coordinates":[-73.34755,41.120387],"type":"Point"}
}