{
  "type": "Feature",
  "properties": {
    "iso:country":"US",
    "sg:address":"43 Huntington Hts",
    "sg:city":"Shelton",
    "sg:classifiers":[
        {
            "category":"Health Services",
            "subcategory":"Doctor",
            "type":"Services"
        }
    ],
    "sg:phone":"+1   ",
    "sg:postcode":"06484",
    "sg:province":"CT",
    "sg:tags":[
        "medical"
    ],
    "wof:name":"Daniel J Mizak MD",
    "wof:placetype":"venue"
},
  "geometry": {"coordinates":[-73.10849399999999,41.316236],"type":"Point"}
}