{
  "type": "Feature",
  "properties": {
    "addr:full":"203 Grove St Bridgeport CT 06605",
    "addr:housenumber":"203",
    "addr:postcode":"06605",
    "addr:street":"Grove St",
    "iso:country":"US",
    "sg:address":"203 Grove St",
    "sg:city":"Bridgeport",
    "sg:classifiers":[
        {
            "category":"Building & Trades",
            "subcategory":"Construction",
            "type":"Services"
        }
    ],
    "sg:phone":"+1 203 367 6868",
    "sg:postcode":"06605",
    "sg:province":"CT",
    "sg:tags":[
        "downspouts",
        "gutter"
    ],
    "wof:name":"Nutmeg Seamless Gutters",
    "wof:placetype":"venue"
},
  "geometry": {"coordinates":[-73.207334,41.175623],"type":"Point"}
}