{
  "type": "Feature",
  "properties": {
    "addr:full":"30 Pinnacle Mountain Rd Simsbury CT 06070",
    "addr:housenumber":"30",
    "addr:postcode":"06070",
    "addr:street":"Pinnacle Mountain Rd Simsbury Ct",
    "iso:country":"US",
    "sg:address":"30 Pinnacle Mountain Rd",
    "sg:city":"Simsbury",
    "sg:classifiers":[
        {
            "category":"Communications",
            "subcategory":"Film & Video Production",
            "type":"Services"
        }
    ],
    "sg:phone":"+1   ",
    "sg:postcode":"06070",
    "sg:province":"CT",
    "sg:tags":[
        "television",
        "commercial"
    ],
    "wof:name":"Brickwall Inc",
    "wof:placetype":"venue"
},
  "geometry": {"coordinates":[-72.786373,41.871057],"type":"Point"}
}