{
  "type": "Feature",
  "properties": {
    "addr:full":"958 Middlesex Tpke Old Saybrook CT 06475",
    "addr:housenumber":"958",
    "addr:postcode":"06475",
    "addr:street":"Middlesex Tpke Old Saybrook Ct",
    "iso:country":"US",
    "sg:address":"958 Middlesex Tpke",
    "sg:city":"Old Saybrook",
    "sg:classifiers":[
        {
            "category":"Sports & Exercise",
            "subcategory":"Gym",
            "type":"Entertainment"
        }
    ],
    "sg:phone":"+1 860 388 1807",
    "sg:postcode":"06475",
    "sg:province":"CT",
    "sg:tags":[
        "yoga"
    ],
    "wof:name":"Yoga Studio the",
    "wof:placetype":"venue"
},
  "geometry": {"coordinates":[-72.378601,41.3298],"type":"Point"}
}