{
  "type": "Feature",
  "properties": {
    "addr:full":"61 Gillette St Hartford CT 06119",
    "addr:housenumber":"61",
    "addr:postcode":"06119",
    "addr:street":"Gillette St",
    "iso:country":"US",
    "sg:address":"61 Gillette St",
    "sg:city":"Hartford",
    "sg:classifiers":[
        {
            "category":"Professional",
            "type":"Services"
        }
    ],
    "sg:phone":"+1 860 231 0662",
    "sg:postcode":"06119",
    "sg:province":"CT",
    "wof:name":"Foresight Systems Inc",
    "wof:placetype":"venue"
},
  "geometry": {"coordinates":[-72.721613,41.755242],"type":"Point"}
}