{
  "type": "Feature",
  "properties": {
    "iso:country":"US",
    "sg:address":"74 Mack St",
    "sg:city":"Windsor",
    "sg:classifiers":[
        {
            "category":"Health Services",
            "subcategory":"Doctor",
            "type":"Services"
        }
    ],
    "sg:phone":"+1   ",
    "sg:postcode":"06095",
    "sg:province":"CT",
    "sg:tags":[
        "medical"
    ],
    "wof:name":"Medical Imaging Center PC",
    "wof:placetype":"venue"
},
  "geometry": {"coordinates":[-72.65013500000001,41.855672],"type":"Point"}
}