{
  "type": "Feature",
  "properties": {
    "addr:full":"97 Burton St Waterbury CT 06704",
    "addr:housenumber":"97",
    "addr:postcode":"06704",
    "addr:street":"Burton St Waterbury Ct",
    "iso:country":"US",
    "sg:address":"97 Burton St",
    "sg:city":"Waterbury",
    "sg:classifiers":[
        {
            "category":"Building & Trades",
            "subcategory":"Construction",
            "type":"Services"
        }
    ],
    "sg:phone":"+1 203 756 4444",
    "sg:postcode":"06704",
    "sg:province":"CT",
    "sg:tags":[
        "house"
    ],
    "wof:name":"Zappone Construction Corp",
    "wof:placetype":"venue"
},
  "geometry": {"coordinates":[-73.03612699999999,41.562576],"type":"Point"}
}