{
  "type": "Feature",
  "properties": {
    "addr:full":"194 Hamilton St New Haven CT 06511",
    "addr:housenumber":"194",
    "addr:postcode":"06511",
    "addr:street":"Hamilton St",
    "iso:country":"US",
    "sg:address":"194 Hamilton St",
    "sg:city":"New Haven",
    "sg:classifiers":[
        {
            "category":"Building & Trades",
            "subcategory":"Construction",
            "type":"Services"
        }
    ],
    "sg:phone":"+1 203 773 1730",
    "sg:postcode":"06511",
    "sg:province":"CT",
    "sg:tags":[
        "general",
        "contractor"
    ],
    "wof:name":"Four C's Construction LLC",
    "wof:placetype":"venue"
},
  "geometry": {"coordinates":[-72.912301,41.309297],"type":"Point"}
}