{
  "type": "Feature",
  "properties": {
    "iso:country":"US",
    "sg:address":"102 Heather Glen Ln",
    "sg:city":"Mystic",
    "sg:classifiers":[
        {
            "category":"Shopping",
            "subcategory":"Hobbies, Toys, & Games",
            "type":"Retail Goods"
        }
    ],
    "sg:phone":"+1 860 572 4489",
    "sg:postcode":"06355",
    "sg:province":"CT",
    "sg:tags":[
        "house",
        "doll",
        "miniature"
    ],
    "wof:name":"More Than Miniatures",
    "wof:placetype":"venue"
},
  "geometry": {"coordinates":[-71.984807,41.395529],"type":"Point"}
}