{
  "type": "Feature",
  "properties": {
    "iso:country":"US",
    "sg:address":"117 Dodgingtown Rd",
    "sg:city":"Bethel",
    "sg:classifiers":[
        {
            "category":"Banks & Credit Unions",
            "subcategory":"Investment Brokerage",
            "type":"Services"
        }
    ],
    "sg:phone":"+1 203 748 2594",
    "sg:postcode":"06801",
    "sg:province":"CT",
    "wof:name":"Technology Investments",
    "wof:placetype":"venue"
},
  "geometry": {"coordinates":[-73.365735,41.38236],"type":"Point"}
}