{
  "type": "Feature",
  "properties": {
    "addr:full":"77 Riverford Rd Brookfield CT 06804",
    "addr:housenumber":"77",
    "addr:postcode":"06804",
    "addr:street":"Riverford Rd",
    "iso:country":"US",
    "sg:address":"77 Riverford Rd",
    "sg:city":"Brookfield",
    "sg:classifiers":[
        {
            "category":"Building & Trades",
            "subcategory":"Construction",
            "type":"Services"
        }
    ],
    "sg:phone":"+1 203 775 5046",
    "sg:postcode":"06804",
    "sg:province":"CT",
    "sg:tags":[
        "roofing",
        "contractor"
    ],
    "wof:name":"Aiello Roofing Co",
    "wof:placetype":"venue"
},
  "geometry": {"coordinates":[-73.38263499999999,41.494769],"type":"Point"}
}