{
  "type": "Feature",
  "properties": {
    "addr:full":"801 New Haven Rd Naugatuck CT 06770",
    "addr:housenumber":"801",
    "addr:postcode":"06770",
    "addr:street":"New Haven Rd Naugatuck Ct",
    "iso:country":"US",
    "sg:address":"801 New Haven Rd",
    "sg:city":"Naugatuck",
    "sg:classifiers":[
        {
            "category":"Cinema",
            "subcategory":"Movie Rental",
            "type":"Entertainment"
        }
    ],
    "sg:phone":"+1   ",
    "sg:postcode":"06770",
    "sg:province":"CT",
    "sg:tags":[
        "video",
        "tape"
    ],
    "wof:name":"Video Spotlight",
    "wof:placetype":"venue"
},
  "geometry": {"coordinates":[-73.042759,41.474478],"type":"Point"}
}