{
  "type": "Feature",
  "properties": {
    "addr:full":"113 Bowman Ave Rye Brook CT 10573",
    "addr:housenumber":"113",
    "addr:postcode":"10573",
    "addr:street":"Bowman Ave;Brook Ct",
    "iso:country":"US",
    "sg:address":"113 Bowman Ave",
    "sg:city":"Rye Brook",
    "sg:classifiers":[
        {
            "category":"Education",
            "subcategory":"School",
            "type":"Public Place"
        }
    ],
    "sg:phone":"+1 914 934 7930",
    "sg:postcode":"10573",
    "sg:province":"CT",
    "wof:name":"Port Chester Middle School",
    "wof:placetype":"venue"
},
  "geometry": {"coordinates":[-73.691858,41.004665],"type":"Point"}
}