{
  "type": "Feature",
  "properties": {
    "addr:full":"17 Berkshire Rd Sandy Hook CT 06482",
    "addr:housenumber":"17",
    "addr:postcode":"06482",
    "addr:street":"Berkshire Rd;Hook Ct",
    "iso:country":"US",
    "sg:address":"17 Berkshire Rd",
    "sg:city":"Sandy Hook",
    "sg:classifiers":[
        {
            "category":"Building & Trades",
            "subcategory":"Construction",
            "type":"Services"
        }
    ],
    "sg:phone":"+1 203 270 4500",
    "sg:postcode":"06482",
    "sg:province":"CT",
    "sg:tags":[
        "general",
        "contractor"
    ],
    "sg:website":"www.caldwellandwalsh.com",
    "wof:name":"Caldwell & Walsh Building Cons",
    "wof:placetype":"venue"
},
  "geometry": {"coordinates":[-73.273921,41.413314],"type":"Point"}
}