{
  "type": "Feature",
  "properties": {
    "addr:full":"145 N Main St Branford CT 06405",
    "addr:housenumber":"145",
    "addr:postcode":"06405",
    "addr:street":"N Main St",
    "iso:country":"US",
    "sg:address":"145 N Main St",
    "sg:city":"Branford",
    "sg:classifiers":[
        {
            "category":"Wholesale",
            "subcategory":"Painting Supplies",
            "type":"Manufacturing & Wholesale Goods"
        },
        {
            "category":"Home & Garden",
            "subcategory":"Home Furnishings",
            "type":"Retail Goods"
        },
        {
            "category":"Building & Trades",
            "subcategory":"Construction",
            "type":"Services"
        },
        {
            "category":"Home & Garden",
            "subcategory":"Carpets & Floor Coverings",
            "type":"Retail Goods"
        }
    ],
    "sg:phone":"+1 203 488 5637",
    "sg:postcode":"06405",
    "sg:province":"CT",
    "sg:tags":[
        "flooring",
        "vertical",
        "rug",
        "contractor",
        "paint",
        "blinds-venetian",
        "tile-contractors"
    ],
    "sg:website":"http://www.joesfloorstore.com",
    "wof:name":"Joe's Paint & Floor Store",
    "wof:placetype":"venue"
},
  "geometry": {"coordinates":[-72.814728,41.287479],"type":"Point"}
}