{
  "type": "Feature",
  "properties": {
    "iso:country":"US",
    "sg:address":"110 Riverbank Dr",
    "sg:city":"Stamford",
    "sg:classifiers":[
        {
            "category":"Communications",
            "subcategory":"Television Station",
            "type":"Services"
        }
    ],
    "sg:phone":"+1   ",
    "sg:postcode":"06903",
    "sg:province":"CT",
    "sg:tags":[
        "motion",
        "picture"
    ],
    "wof:name":"Colorcast Video",
    "wof:placetype":"venue"
},
  "geometry": {"coordinates":[-73.596951,41.114629],"type":"Point"}
}