{
  "type": "Feature",
  "properties": {
    "addr:full":"37 Adelaide Rd Manchester CT 06040",
    "addr:housenumber":"37",
    "addr:postcode":"06040",
    "addr:street":"Adelaide Rd",
    "iso:country":"US",
    "sg:address":"37 Adelaide Rd",
    "sg:city":"Manchester",
    "sg:classifiers":[
        {
            "category":"Building & Trades",
            "subcategory":"Construction",
            "type":"Services"
        }
    ],
    "sg:phone":"+1 860 643 8001",
    "sg:postcode":"06040",
    "sg:province":"CT",
    "sg:tags":[
        "contractor"
    ],
    "wof:name":"Arctic Seamless Gutters",
    "wof:placetype":"venue"
},
  "geometry": {"coordinates":[-72.497637,41.774648],"type":"Point"}
}