{
  "type": "Feature",
  "properties": {
    "addr:full":"99 Scrub Oak Rd North Haven CT 06473",
    "addr:housenumber":"99",
    "addr:postcode":"06473",
    "addr:street":"Scrub Oak Rd;Haven",
    "iso:country":"US",
    "sg:address":"99 Scrub Oak Rd",
    "sg:city":"North Haven",
    "sg:classifiers":[
        {
            "category":"Wholesale",
            "subcategory":"Groceries",
            "type":"Manufacturing & Wholesale Goods"
        }
    ],
    "sg:phone":"+1 203 239 9093",
    "sg:postcode":"06473",
    "sg:province":"CT",
    "sg:tags":[
        "food",
        "broker"
    ],
    "wof:name":"Sesco",
    "wof:placetype":"venue"
},
  "geometry": {"coordinates":[-72.83278799999999,41.422613],"type":"Point"}
}