{
  "type": "Feature",
  "properties": {
    "addr:full":"25 Meadow Rd Windsor CT 06095",
    "addr:housenumber":"25",
    "addr:postcode":"06095",
    "addr:street":"Meadow Rd",
    "iso:country":"US",
    "sg:address":"25 Meadow Rd",
    "sg:city":"Windsor",
    "sg:classifiers":[
        {
            "category":"Arts & Performance",
            "subcategory":"Art Gallery",
            "type":"Entertainment"
        },
        {
            "category":"Shopping",
            "subcategory":"Antiques",
            "type":"Retail Goods"
        },
        {
            "category":"Professional",
            "subcategory":"Business Services",
            "type":"Services"
        },
        {
            "category":"Banks & Credit Unions",
            "subcategory":"Bank",
            "type":"Services"
        },
        {
            "category":"Shopping",
            "subcategory":"Used Merchandise",
            "type":"Retail Goods"
        }
    ],
    "sg:phone":"+1 860 246 2444",
    "sg:postcode":"06095",
    "sg:province":"CT",
    "sg:tags":[
        "shop",
        "appraisers-business",
        "industrial",
        "auction",
        "consultant",
        "galleries",
        "commercial",
        "auctioneer",
        "resale",
        "second",
        "hand",
        "appraiser",
        "furniture"
    ],
    "sg:website":"http://www.nadeausauction.com",
    "wof:name":"Nadeau's Auction Gallery",
    "wof:placetype":"venue"
},
  "geometry": {"coordinates":[-72.65703999999999,41.806015],"type":"Point"}
}