{
  "type": "Feature",
  "properties": {
    "iso:country":"US",
    "sg:address":"54 W North St",
    "sg:city":"Stamford",
    "sg:classifiers":[
        {
            "category":"Shopping",
            "subcategory":"Hobbies, Toys, & Games",
            "type":"Retail Goods"
        }
    ],
    "sg:phone":"+1 203 327 9575",
    "sg:postcode":"06902",
    "sg:province":"CT",
    "sg:tags":[
        "shop",
        "hobby",
        "model",
        "supply"
    ],
    "wof:name":"Hobby S",
    "wof:placetype":"venue"
},
  "geometry": {"coordinates":[-73.548855,41.058717],"type":"Point"}
}