{
  "type": "Feature",
  "properties": {
    "addr:full":"281 Lakemere Southbury CT 06488",
    "addr:housenumber":"281",
    "addr:postcode":"06488",
    "addr:street":"Lakemere Southbury Ct",
    "iso:country":"US",
    "sg:address":"281 Lakemere",
    "sg:city":"Southbury",
    "sg:classifiers":[
        {
            "category":"Professional",
            "type":"Services"
        }
    ],
    "sg:phone":"+1 203 264 8123",
    "sg:postcode":"06488",
    "sg:province":"CT",
    "wof:name":"Joseph B Dempsey",
    "wof:placetype":"venue"
},
  "geometry": {"coordinates":[-73.233694,41.429862],"type":"Point"}
}