{
  "type": "Feature",
  "properties": {
    "iso:country":"US",
    "sg:address":"63 Douglas Dr",
    "sg:city":"Meriden",
    "sg:classifiers":[
        {
            "category":"Building & Trades",
            "subcategory":"Construction",
            "type":"Services"
        }
    ],
    "sg:phone":"+1 203 634 3790",
    "sg:postcode":"06451",
    "sg:province":"CT",
    "sg:tags":[
        "house"
    ],
    "wof:name":"Gac General Contractors",
    "wof:placetype":"venue"
},
  "geometry": {"coordinates":[-72.83645300000001,41.51906],"type":"Point"}
}