{
  "type": "Feature",
  "properties": {
    "addr:full":"25 N Whittlesey Ave Wallingford CT 06492",
    "addr:housenumber":"25",
    "addr:postcode":"06492",
    "addr:street":"N Whittlesey Ave",
    "iso:country":"US",
    "sg:address":"25 N Whittlesey Ave",
    "sg:city":"Wallingford",
    "sg:classifiers":[
        {
            "category":"Organizations",
            "subcategory":"Religious Organization",
            "type":"Services"
        }
    ],
    "sg:phone":"+1   ",
    "sg:postcode":"06492",
    "sg:province":"CT",
    "wof:name":"Most Holy Trinity Parish Ctr",
    "wof:placetype":"venue"
},
  "geometry": {"coordinates":[-72.81928000000001,41.455888],"type":"Point"}
}