{
  "type": "Feature",
  "properties": {
    "iso:country":"US",
    "sg:address":"32 Tuttle St",
    "sg:city":"East Haven",
    "sg:classifiers":[
        {
            "category":"Organizations",
            "subcategory":"Religious Organization",
            "type":"Services"
        }
    ],
    "sg:phone":"+1   ",
    "sg:postcode":"06512",
    "sg:province":"CT",
    "wof:name":"Sisters of Charity",
    "wof:placetype":"venue"
},
  "geometry": {"coordinates":[-72.89600900000001,41.278204],"type":"Point"}
}