{
  "type": "Feature",
  "properties": {
    "addr:full":"18 Murray St Norwalk CT 06851",
    "addr:housenumber":"18",
    "addr:postcode":"06851",
    "addr:street":"Murray St",
    "iso:country":"US",
    "sg:address":"18 Murray St",
    "sg:city":"Norwalk",
    "sg:classifiers":[
        {
            "category":"Professional",
            "subcategory":"Business Services",
            "type":"Services"
        }
    ],
    "sg:phone":"+1   ",
    "sg:postcode":"06851",
    "sg:province":"CT",
    "wof:name":"Charles Hiravy Estimating",
    "wof:placetype":"venue"
},
  "geometry": {"coordinates":[-73.397886,41.135909],"type":"Point"}
}