{
  "type": "Feature",
  "properties": {
    "iso:country":"US",
    "sg:address":"115 Long Neck Point Rd",
    "sg:city":"Darien",
    "sg:classifiers":[
        {
            "category":"Arts & Performance",
            "subcategory":"Theater",
            "type":"Entertainment"
        }
    ],
    "sg:phone":"+1   ",
    "sg:postcode":"06820",
    "sg:province":"CT",
    "sg:tags":[
        "theatrical"
    ],
    "wof:name":"Harmill Communications Inc",
    "wof:placetype":"venue"
},
  "geometry": {"coordinates":[-73.478724,41.045649],"type":"Point"}
}