{
  "type": "Feature",
  "properties": {
    "iso:country":"US",
    "sg:address":"1190 Dixwell Ave",
    "sg:city":"Hamden",
    "sg:classifiers":[
        {
            "category":"Home & Garden",
            "subcategory":"Furniture",
            "type":"Retail Goods"
        }
    ],
    "sg:phone":"+1 203 562 0111",
    "sg:postcode":"06514",
    "sg:province":"CT",
    "wof:name":"Peace & Rich Home Furnishings",
    "wof:placetype":"venue"
},
  "geometry": {"coordinates":[-72.93432,41.344776],"type":"Point"}
}