{
  "type": "Feature",
  "properties": {
    "addr:full":"127 Thompson St New Haven CT 06511",
    "addr:housenumber":"127",
    "addr:postcode":"06511",
    "addr:street":"Thompson St",
    "iso:country":"US",
    "sg:address":"127 Thompson St",
    "sg:city":"New Haven",
    "sg:classifiers":[
        {
            "category":"Organizations",
            "subcategory":"Religious Organization",
            "type":"Services"
        }
    ],
    "sg:phone":"+1 203 777 4628",
    "sg:postcode":"06511",
    "sg:province":"CT",
    "sg:tags":[
        "church"
    ],
    "wof:name":"Temple Of Deliverence",
    "wof:placetype":"venue"
},
  "geometry": {"coordinates":[-72.932828,41.327683],"type":"Point"}
}