{
  "type": "Feature",
  "properties": {
    "iso:country":"US",
    "sg:address":"13 Park St",
    "sg:city":"Vernon Rockville",
    "sg:classifiers":[
        {
            "category":"Professional",
            "subcategory":"Lawyer & Legal Services",
            "type":"Services"
        }
    ],
    "sg:phone":"+1   ",
    "sg:postcode":"06066",
    "sg:province":"CT",
    "wof:name":"Seidman David",
    "wof:placetype":"venue"
},
  "geometry": {"coordinates":[-72.44816400000001,41.868292],"type":"Point"}
}