{
  "type": "Feature",
  "properties": {
    "iso:country":"US",
    "sg:address":"711 Broad St Exd",
    "sg:city":"Waterford",
    "sg:classifiers":[
        {
            "category":"Professional",
            "subcategory":"Business Services",
            "type":"Services"
        }
    ],
    "sg:phone":"+1   ",
    "sg:postcode":"06385",
    "sg:province":"CT",
    "wof:name":"National Hotel Properties",
    "wof:placetype":"venue"
},
  "geometry": {"coordinates":[-72.126831,41.368033],"type":"Point"}
}