{
  "type": "Feature",
  "properties": {
    "iso:country":"US",
    "sg:address":"89 Valley Dr",
    "sg:city":"Greenwich",
    "sg:classifiers":[
        {
            "category":"Professional",
            "subcategory":"Business Services",
            "type":"Services"
        }
    ],
    "sg:phone":"+1   ",
    "sg:postcode":"06831",
    "sg:province":"NY",
    "sg:tags":[
        "financial"
    ],
    "wof:name":"Altgate Capital Inc",
    "wof:placetype":"venue"
},
  "geometry": {"coordinates":[-73.643703,41.023675],"type":"Point"}
}