{
  "type": "Feature",
  "properties": {
    "iso:country":"US",
    "sg:address":"931 Queen St",
    "sg:city":"Southington",
    "sg:classifiers":[
        {
            "category":"Home & Garden",
            "subcategory":"Home Furnishings",
            "type":"Retail Goods"
        },
        {
            "category":"Building & Trades",
            "subcategory":"Construction",
            "type":"Services"
        },
        {
            "category":"Home & Garden",
            "subcategory":"Furniture",
            "type":"Retail Goods"
        },
        {
            "category":"Home & Garden",
            "subcategory":"Household Appliances",
            "type":"Retail Goods"
        },
        {
            "category":"Home & Garden",
            "subcategory":"Building Materials",
            "type":"Retail Goods"
        },
        {
            "category":"Manufacturing",
            "subcategory":"Building Materials",
            "type":"Manufacturing & Wholesale Goods"
        }
    ],
    "sg:phone":"+1 860 620 0500",
    "sg:postcode":"06489",
    "sg:province":"CT",
    "sg:tags":[
        "bathroom",
        "industrial",
        "equipment-household",
        "cabinetmakers-commercial",
        "major",
        "appliances-small",
        "cabinet",
        "refacing",
        "resurfacing",
        "planning",
        "fixtures",
        "accessory",
        "remodeling",
        "maker",
        "cabinets-refinishing",
        "kitchen"
    ],
    "sg:website":"http://www.kitchencabinetoutlets.com",
    "wof:name":"Kitchen Cabinet Outlet",
    "wof:placetype":"venue"
},
  "geometry": {"coordinates":[-72.87399000000001,41.64184],"type":"Point"}
}