{
  "type": "Feature",
  "properties": {
    "iso:country":"US",
    "sg:address":"272 Meriden Rd",
    "sg:city":"Waterbury",
    "sg:classifiers":[
        {
            "category":"Professional",
            "subcategory":"Computer Services",
            "type":"Services"
        }
    ],
    "sg:phone":"+1 203 573 0734",
    "sg:postcode":"06705",
    "sg:province":"CT",
    "sg:tags":[
        "repair"
    ],
    "wof:name":"CTEK Intl",
    "wof:placetype":"venue"
},
  "geometry": {"coordinates":[-73.00761900000001,41.551676],"type":"Point"}
}