{
  "type": "Feature",
  "properties": {
    "iso:country":"US",
    "sg:address":"10 Norden Pl",
    "sg:city":"Norwalk",
    "sg:classifiers":[
        {
            "category":"Banks & Credit Unions",
            "subcategory":"Bank",
            "type":"Services"
        }
    ],
    "sg:phone":"+1 203 852 4901",
    "sg:postcode":"06855",
    "sg:province":"CT",
    "wof:name":"Sikorskiy Credit Union",
    "wof:placetype":"venue"
},
  "geometry": {"coordinates":[-73.39342499999999,41.109026],"type":"Point"}
}