{
  "type": "Feature",
  "properties": {
    "iso:country":"US",
    "sg:address":"23 Sugar Hollow Rd",
    "sg:city":"Danbury",
    "sg:classifiers":[
        {
            "category":"Autos & Motor Vehicles",
            "subcategory":"Automobile Sales",
            "type":"Retail Goods"
        }
    ],
    "sg:phone":"+1 203 744 5203",
    "sg:postcode":"06810",
    "sg:province":"CT",
    "sg:tags":[
        "car",
        "dealer"
    ],
    "wof:name":"Danbury Porsche",
    "wof:placetype":"venue"
},
  "geometry": {"coordinates":[-73.47404,41.375973],"type":"Point"}
}