{
  "type": "Feature",
  "properties": {
    "addr:full":"8 Mimosa Dr Cos Cob CT 06807",
    "addr:housenumber":"8",
    "addr:postcode":"06807",
    "addr:street":"Mimosa Dr",
    "iso:country":"US",
    "sg:address":"8 Mimosa Dr",
    "sg:city":"Cos Cob",
    "sg:classifiers":[
        {
            "category":"Restaurant",
            "type":"Food & Drink"
        }
    ],
    "sg:phone":"+1 203 629 2674",
    "sg:postcode":"06807",
    "sg:province":"CT",
    "sg:tags":[
        "caterer"
    ],
    "wof:name":"Enterprises Caterers & Party",
    "wof:placetype":"venue"
},
  "geometry": {"coordinates":[-73.579993,41.07001],"type":"Point"}
}