{
  "type": "Feature",
  "properties": {
    "addr:full":"111 Hartford Tpke Tolland CT 06084",
    "addr:housenumber":"111",
    "addr:postcode":"06084",
    "addr:street":"Hartford Tpke Tolland Ct",
    "iso:country":"US",
    "sg:address":"111 Hartford Tpke",
    "sg:city":"Tolland",
    "sg:classifiers":[
        {
            "category":"Education",
            "subcategory":"Special Training",
            "type":"Public Place"
        }
    ],
    "sg:phone":"+1   ",
    "sg:postcode":"06084",
    "sg:province":"CT",
    "wof:name":"Childrens Choice Lgn Center",
    "wof:placetype":"venue"
},
  "geometry": {"coordinates":[-72.41422900000001,41.867788],"type":"Point"}
}