{
  "type": "Feature",
  "properties": {
    "iso:country":"US",
    "sg:address":"17 Clark Rd",
    "sg:city":"Naugatuck",
    "sg:classifiers":[
        {
            "category":"Manufacturing",
            "subcategory":"Metals",
            "type":"Manufacturing & Wholesale Goods"
        }
    ],
    "sg:phone":"+1 203 729 2244",
    "sg:postcode":"06770",
    "sg:province":"CT",
    "sg:tags":[
        "fabricator",
        "sheet"
    ],
    "wof:name":"Quality Sheet Metal Inc",
    "wof:placetype":"venue"
},
  "geometry": {"coordinates":[-73.00461799999999,41.46913],"type":"Point"}
}