{
  "type": "Feature",
  "properties": {
    "iso:country":"US",
    "sg:address":"390 Danbury Rd",
    "sg:city":"Wilton",
    "sg:classifiers":[
        {
            "category":"Utilities",
            "subcategory":"Fuel Oil & Lpg",
            "type":"Services"
        }
    ],
    "sg:phone":"+1 203 761 9784",
    "sg:postcode":"06897",
    "sg:province":"CT",
    "wof:name":"Harrick's Fuel",
    "wof:placetype":"venue"
},
  "geometry": {"coordinates":[-73.43047799999999,41.206704],"type":"Point"}
}