{
  "type": "Feature",
  "properties": {
    "addr:full":"100 Nicholson Rd East Granby CT 06026",
    "addr:housenumber":"100",
    "addr:postcode":"06026",
    "addr:street":"Nicholson Rd East Granby Ct",
    "iso:country":"US",
    "sg:address":"100 Nicholson Rd",
    "sg:city":"East Granby",
    "sg:classifiers":[
        {
            "category":"Government",
            "subcategory":"Office",
            "type":"Public Place"
        }
    ],
    "sg:phone":"+1 860 292 2740",
    "sg:postcode":"06026",
    "sg:province":"CT",
    "sg:tags":[
        "national",
        "guard",
        "air"
    ],
    "wof:name":"Bradley Air National Guard",
    "wof:placetype":"venue"
},
  "geometry": {"coordinates":[-72.70591899999999,41.936363],"type":"Point"}
}