{
  "type": "Feature",
  "properties": {
    "addr:full":"13 Penncove Rd Niantic CT 06357",
    "addr:housenumber":"13",
    "addr:postcode":"06357",
    "addr:street":"Penncove Rd",
    "iso:country":"US",
    "sg:address":"13 Penncove Rd",
    "sg:city":"Niantic",
    "sg:classifiers":[
        {
            "category":"Professional",
            "subcategory":"Management & Consulting",
            "type":"Services"
        }
    ],
    "sg:phone":"+1   ",
    "sg:postcode":"06357",
    "sg:province":"CT",
    "sg:tags":[
        "consultant",
        "education"
    ],
    "wof:name":"Communitas",
    "wof:placetype":"venue"
},
  "geometry": {"coordinates":[-72.192977,41.332603],"type":"Point"}
}