{
  "type": "Feature",
  "properties": {
    "iso:country":"US",
    "sg:address":"1921 Boston Post Rd",
    "sg:city":"Westbrook",
    "sg:classifiers":[
        {
            "category":"Education",
            "subcategory":"Dance Studio",
            "type":"Public Place"
        }
    ],
    "sg:phone":"+1   ",
    "sg:postcode":"06498",
    "sg:province":"CT",
    "wof:name":"Dances Outlet",
    "wof:placetype":"venue"
},
  "geometry": {"coordinates":[-72.42300299999999,41.28152],"type":"Point"}
}