{
  "type": "Feature",
  "properties": {
    "iso:country":"US",
    "sg:address":"88 Parsonage Rd",
    "sg:city":"Greenwich",
    "sg:classifiers":[
        {
            "category":"Social Services",
            "type":"Services"
        }
    ],
    "sg:phone":"+1 203 869 6226",
    "sg:postcode":"06830",
    "sg:province":"CT",
    "sg:tags":[
        "organization",
        "welfare"
    ],
    "wof:name":"Parsonage Cottage Senior",
    "wof:placetype":"venue"
},
  "geometry": {"coordinates":[-73.627555,41.061449],"type":"Point"}
}