{
  "type": "Feature",
  "properties": {
    "addr:full":"1608 Whitney Ave Hamden CT 06517",
    "addr:housenumber":"1608",
    "addr:postcode":"06517",
    "addr:street":"Whitney Ave",
    "iso:country":"US",
    "sg:address":"1608 Whitney Ave",
    "sg:city":"Hamden",
    "sg:classifiers":[
        {
            "category":"Professional",
            "subcategory":"Engineering",
            "type":"Services"
        }
    ],
    "sg:phone":"+1   ",
    "sg:postcode":"06517",
    "sg:province":"CT",
    "wof:name":"James McCarthy",
    "wof:placetype":"venue"
},
  "geometry": {"coordinates":[-72.91023,41.357572],"type":"Point"}
}