{
  "type": "Feature",
  "properties": {
    "iso:country":"US",
    "sg:address":"39 N Plains Industrial Rd",
    "sg:city":"Wallingford",
    "sg:classifiers":[
        {
            "category":"Manufacturing",
            "subcategory":"Food",
            "type":"Manufacturing & Wholesale Goods"
        }
    ],
    "sg:phone":"+1 203 284 0299",
    "sg:postcode":"06492",
    "sg:province":"CT",
    "sg:tags":[
        "bakery",
        "prod",
        "cookie"
    ],
    "wof:name":"Krafty Kakes",
    "wof:placetype":"venue"
},
  "geometry": {"coordinates":[-72.8163,41.483436],"type":"Point"}
}