{
  "type": "Feature",
  "properties": {
    "addr:full":"1201 Boston Post Rd Milford CT 06460",
    "addr:housenumber":"1201",
    "addr:postcode":"06460",
    "addr:street":"Boston Post Rd",
    "iso:country":"US",
    "sg:address":"1201 Boston Post Rd",
    "sg:city":"Milford",
    "sg:classifiers":[
        {
            "category":"Utilities",
            "subcategory":"Cable",
            "type":"Services"
        }
    ],
    "sg:phone":"+1 203 882 1889",
    "sg:postcode":"06460",
    "sg:province":"CT",
    "sg:tags":[
        "television"
    ],
    "wof:name":"As Seen On TV",
    "wof:placetype":"venue"
},
  "geometry": {"coordinates":[-73.04134999999999,41.234572],"type":"Point"}
}