{
  "type": "Feature",
  "properties": {
    "iso:country":"US",
    "sg:address":"14 Willow St",
    "sg:city":"Bridgeport",
    "sg:classifiers":[
        {
            "category":"Wholesale",
            "subcategory":"Hardware",
            "type":"Manufacturing & Wholesale Goods"
        }
    ],
    "sg:phone":"+1 203 335 8129",
    "sg:postcode":"06610",
    "sg:province":"CT",
    "sg:tags":[
        "tool"
    ],
    "wof:name":"Abingdon Tool LTD",
    "wof:placetype":"venue"
},
  "geometry": {"coordinates":[-73.15885299999999,41.18849],"type":"Point"}
}