{
  "type": "Feature",
  "properties": {
    "iso:country":"US",
    "sg:address":"130 Gregory St",
    "sg:city":"Bridgeport",
    "sg:classifiers":[
        {
            "category":"Shopping",
            "subcategory":"Books",
            "type":"Retail Goods"
        }
    ],
    "sg:phone":"+1 203 336 5273",
    "sg:postcode":"06604",
    "sg:province":"CT",
    "wof:name":"Heavenly Doves Christian Book",
    "wof:placetype":"venue"
},
  "geometry": {"coordinates":[-73.189215,41.168708],"type":"Point"}
}