{
  "type": "Feature",
  "properties": {
    "addr:full":"7 Devonshire Dr Danbury CT 06811",
    "addr:housenumber":"7",
    "addr:postcode":"06811",
    "addr:street":"Devonshire Dr",
    "iso:country":"US",
    "sg:address":"7 Devonshire Dr",
    "sg:city":"Danbury",
    "sg:classifiers":[
        {
            "category":"Landmark",
            "subcategory":"Tourist Information",
            "type":"Public Place"
        }
    ],
    "sg:phone":"+1 203 797 0284",
    "sg:postcode":"06811",
    "sg:province":"CT",
    "sg:tags":[
        "promoter",
        "tours-operators"
    ],
    "wof:name":"Himalayan Travel, Inc.",
    "wof:placetype":"venue"
},
  "geometry": {"coordinates":[-73.503336,41.398366],"type":"Point"}
}