{
  "type": "Feature",
  "properties": {
    "iso:country":"US",
    "sg:address":"49 Riverside Ave",
    "sg:city":"Westport",
    "sg:classifiers":[
        {
            "category":"Professional",
            "subcategory":"Management & Consulting",
            "type":"Services"
        }
    ],
    "sg:phone":"+1   ",
    "sg:postcode":"06880",
    "sg:province":"CT",
    "sg:tags":[
        "money",
        "investment",
        "equity"
    ],
    "wof:name":"Lawhill Capital Partners LLC",
    "wof:placetype":"venue"
},
  "geometry": {"coordinates":[-73.364332,41.140287],"type":"Point"}
}