{
  "type": "Feature",
  "properties": {
    "addr:full":"181 Queen St Southington CT 06489",
    "addr:housenumber":"181",
    "addr:postcode":"06489",
    "addr:street":"Queen St",
    "iso:country":"US",
    "sg:address":"181 Queen St",
    "sg:city":"Southington",
    "sg:classifiers":[
        {
            "category":"Autos & Motor Vehicles",
            "subcategory":"Fuel & Gas Station",
            "type":"Retail Goods"
        }
    ],
    "sg:phone":"+1 860 621 8714",
    "sg:postcode":"06489",
    "sg:province":"CT",
    "sg:tags":[
        "station",
        "gasoline"
    ],
    "wof:name":"Southington Hess",
    "wof:placetype":"venue"
},
  "geometry": {"coordinates":[-72.87343300000001,41.619686],"type":"Point"}
}