{
  "type": "Feature",
  "properties": {
    "addr:full":"1882 Main St Bridgeport CT 06604",
    "addr:housenumber":"1882",
    "addr:postcode":"06604",
    "addr:street":"Main St",
    "iso:country":"US",
    "sg:address":"1882 Main St",
    "sg:city":"Bridgeport",
    "sg:classifiers":[
        {
            "category":"Autos & Motor Vehicles",
            "subcategory":"Auto Supplies",
            "type":"Retail Goods"
        }
    ],
    "sg:phone":"+1 203 336 2523",
    "sg:postcode":"06604",
    "sg:province":"CT",
    "sg:tags":[
        "automobile",
        "parts"
    ],
    "wof:name":"Fair Auto Supply",
    "wof:placetype":"venue"
},
  "geometry": {"coordinates":[-73.195283,41.189176],"type":"Point"}
}