{
  "type": "Feature",
  "properties": {
    "addr:full":"147 Carey St Southington CT 06489",
    "addr:housenumber":"147",
    "addr:postcode":"06489",
    "addr:street":"Carey St Southington Ct",
    "iso:country":"US",
    "sg:address":"147 Carey St",
    "sg:city":"Southington",
    "sg:classifiers":[
        {
            "category":"Building & Trades",
            "subcategory":"Construction",
            "type":"Services"
        }
    ],
    "sg:phone":"+1 860 621 1329",
    "sg:postcode":"06489",
    "sg:province":"CT",
    "sg:tags":[
        "contractor"
    ],
    "wof:name":"MD Contractors",
    "wof:placetype":"venue"
},
  "geometry": {"coordinates":[-72.819963,41.611892],"type":"Point"}
}