{
  "type": "Feature",
  "properties": {
    "iso:country":"US",
    "sg:address":"21 Ciro Rd",
    "sg:city":"North Branford",
    "sg:classifiers":[
        {
            "category":"Freight",
            "type":"Transportation"
        }
    ],
    "sg:phone":"+1 203 481 0886",
    "sg:postcode":"06471",
    "sg:province":"CT",
    "sg:tags":[
        "trucking"
    ],
    "wof:name":"Agra Industrial Supply",
    "wof:placetype":"venue"
},
  "geometry": {"coordinates":[-72.757425,41.332499],"type":"Point"}
}