{
  "type": "Feature",
  "properties": {
    "iso:country":"US",
    "sg:address":"1465 E. Putnam Avenue Unit 615",
    "sg:city":"Old Greenwich",
    "sg:classifiers":[
        {
            "category":"Manufacturing",
            "subcategory":"Electronics",
            "type":"Manufacturing & Wholesale Goods"
        }
    ],
    "sg:postcode":"06870",
    "sg:province":"CT",
    "sg:tags":[
        "assistive-technology",
        "disabilities",
        "disability-communications",
        "disability-marketing"
    ],
    "sg:website":"http://abledbody.com",
    "wof:name":"abledbody",
    "wof:placetype":"venue"
},
  "geometry": {"coordinates":[-73.566163,41.048376],"type":"Point"}
}