{
  "type": "Feature",
  "properties": {
    "iso:country":"US",
    "sg:address":"18 Henry St",
    "sg:city":"Danbury",
    "sg:classifiers":[
        {
            "category":"Food & Beverages",
            "subcategory":"Specialty",
            "type":"Retail Goods"
        },
        {
            "category":"Food & Beverages",
            "subcategory":"Groceries & Convenience Stores",
            "type":"Retail Goods"
        },
        {
            "category":"Food & Beverages",
            "subcategory":"Meat & Fish",
            "type":"Retail Goods"
        }
    ],
    "sg:phone":"+1 203 748 5474",
    "sg:postcode":"06810",
    "sg:province":"CT",
    "sg:tags":[
        "grocers-specialty",
        "market"
    ],
    "wof:name":"Henry Street Market Inc",
    "wof:placetype":"venue"
},
  "geometry": {"coordinates":[-73.46631600000001,41.399416],"type":"Point"}
}