{
  "type": "Feature",
  "properties": {
    "addr:full":"235 Nicoll St New Haven CT 06511",
    "addr:housenumber":"235",
    "addr:postcode":"06511",
    "addr:street":"Nicoll St",
    "iso:country":"US",
    "sg:address":"235 Nicoll St",
    "sg:city":"New Haven",
    "sg:classifiers":[
        {
            "category":"Social Services",
            "type":"Services"
        }
    ],
    "sg:phone":"+1 203 777 8833",
    "sg:postcode":"06511",
    "sg:province":"CT",
    "sg:tags":[
        "youth",
        "organization",
        "center"
    ],
    "wof:name":"Youth With A Mission Axiom",
    "wof:placetype":"venue"
},
  "geometry": {"coordinates":[-72.90763699999999,41.321407],"type":"Point"}
}