{
  "type": "Feature",
  "properties": {
    "iso:country":"US",
    "sg:address":"348 Greenwich Ave",
    "sg:city":"Greenwich",
    "sg:classifiers":[
        {
            "category":"Shopping",
            "subcategory":"Department Store",
            "type":"Retail Goods"
        }
    ],
    "sg:phone":"+1 203 769 4290",
    "sg:postcode":"06830",
    "sg:province":"CT",
    "sg:tags":[
        "shop"
    ],
    "wof:name":"Zegna Sport",
    "wof:placetype":"venue"
},
  "geometry": {"coordinates":[-73.62564500000001,41.024814],"type":"Point"}
}