{
  "type": "Feature",
  "properties": {
    "iso:country":"US",
    "sg:address":"18 Scalise Dr",
    "sg:city":"Columbia",
    "sg:classifiers":[
        {
            "category":"Building & Trades",
            "subcategory":"Construction",
            "type":"Services"
        }
    ],
    "sg:phone":"+1 860 228 6899",
    "sg:postcode":"06237",
    "sg:province":"CT",
    "sg:tags":[
        "contractor"
    ],
    "wof:name":"Mf Barrea Contractors LLC",
    "wof:placetype":"venue"
},
  "geometry": {"coordinates":[-72.252212,41.705711],"type":"Point"}
}