{
  "type": "Feature",
  "properties": {
    "addr:full":"99 Whitfield St Guilford CT 06437",
    "addr:housenumber":"99",
    "addr:postcode":"06437",
    "addr:street":"Whitfield St",
    "iso:country":"US",
    "sg:address":"99 Whitfield St",
    "sg:city":"Guilford",
    "sg:classifiers":[
        {
            "category":"Wholesale",
            "subcategory":"Stationery",
            "type":"Manufacturing & Wholesale Goods"
        },
        {
            "category":"Professional",
            "type":"Services"
        }
    ],
    "sg:phone":"+1 203 458 2071",
    "sg:postcode":"06437",
    "sg:province":"CT",
    "sg:tags":[
        "paper",
        "establishment",
        "pulp"
    ],
    "wof:name":"Atlantic Cellulose LLC",
    "wof:placetype":"venue"
},
  "geometry": {"coordinates":[-72.679698,41.279747],"type":"Point"}
}