{
  "type": "Feature",
  "properties": {
    "iso:country":"US",
    "sg:address":"750 Old Main St",
    "sg:city":"Rocky Hill",
    "sg:classifiers":[
        {
            "category":"Professional",
            "subcategory":"Management & Consulting",
            "type":"Services"
        }
    ],
    "sg:phone":"+1   ",
    "sg:postcode":"06067",
    "sg:province":"CT",
    "wof:name":"Lifeworx Associates",
    "wof:placetype":"venue"
},
  "geometry": {"coordinates":[-72.63756600000001,41.666817],"type":"Point"}
}