{
  "type": "Feature",
  "properties": {
    "addr:full":"10 Walnut St Danbury CT 06811",
    "addr:housenumber":"10",
    "addr:postcode":"06811",
    "addr:street":"Walnut St",
    "iso:country":"US",
    "sg:address":"10 Walnut St",
    "sg:city":"Danbury",
    "sg:classifiers":[
        {
            "category":"Building & Trades",
            "subcategory":"Construction",
            "type":"Services"
        }
    ],
    "sg:phone":"+1 203 790 0004",
    "sg:postcode":"06811",
    "sg:province":"CT",
    "sg:tags":[
        "repairing",
        "remodeling",
        "contractor"
    ],
    "wof:name":"Great Eastern Remodeling",
    "wof:placetype":"venue"
},
  "geometry": {"coordinates":[-73.45447,41.41123],"type":"Point"}
}