{
  "type": "Feature",
  "properties": {
    "iso:country":"US",
    "sg:address":"108 Main St",
    "sg:city":"New Canaan",
    "sg:classifiers":[
        {
            "category":"Bakery",
            "type":"Food & Drink"
        },
        {
            "category":"Restaurant",
            "type":"Food & Drink"
        },
        {
            "category":"Food & Beverages",
            "subcategory":"Bakery",
            "type":"Retail Goods"
        }
    ],
    "sg:menulink":"http://www.allmenus.com/ct/new-canaan/25307-connecticut-muffin/menu/",
    "sg:phone":"+1 203 972 7557",
    "sg:postcode":"06840",
    "sg:province":"CT",
    "sg:tags":[
        "american",
        "bakery",
        "pastry"
    ],
    "wof:name":"Connecticut Muffin",
    "wof:placetype":"venue"
},
  "geometry": {"coordinates":[-73.49226299999999,41.147412],"type":"Point"}
}