{
  "type": "Feature",
  "properties": {
    "iso:country":"US",
    "sg:address":"3 Heritage Rd",
    "sg:city":"Southbury",
    "sg:classifiers":[
        {
            "category":"Insurance",
            "subcategory":"Insurance Agent",
            "type":"Services"
        }
    ],
    "sg:phone":"+1 203 264 8261",
    "sg:postcode":"06488",
    "sg:province":"CT",
    "wof:name":"Pomperaug Valley Insurance",
    "wof:placetype":"venue"
},
  "geometry": {"coordinates":[-73.224805,41.488482],"type":"Point"}
}