{
  "type": "Feature",
  "properties": {
    "addr:full":"405 Highland Ave Waterbury CT 06708",
    "addr:housenumber":"405",
    "addr:postcode":"06708",
    "addr:street":"Highland Ave",
    "iso:country":"US",
    "sg:address":"405 Highland Ave",
    "sg:city":"Waterbury",
    "sg:classifiers":[
        {
            "category":"Health Services",
            "subcategory":"Optometrist",
            "type":"Services"
        }
    ],
    "sg:phone":"+1   ",
    "sg:postcode":"06708",
    "sg:province":"CT",
    "wof:name":"Terri Cyr-Bebrin Dr",
    "wof:placetype":"venue"
},
  "geometry": {"coordinates":[-73.05599599999999,41.545812],"type":"Point"}
}