{
  "type": "Feature",
  "properties": {
    "iso:country":"US",
    "sg:address":"693 Farmington Ave",
    "sg:city":"Hartford",
    "sg:classifiers":[
        {
            "category":"Education",
            "subcategory":"Dance Studio",
            "type":"Public Place"
        }
    ],
    "sg:phone":"+1   ",
    "sg:postcode":"06119",
    "sg:province":"CT",
    "wof:name":"Premier Dance Studio",
    "wof:placetype":"venue"
},
  "geometry": {"coordinates":[-72.72006399999999,41.765363],"type":"Point"}
}