{
  "type": "Feature",
  "properties": {
    "iso:country":"US",
    "sg:address":"720 Bishop Ave",
    "sg:city":"Bridgeport",
    "sg:classifiers":[
        {
            "category":"Professional",
            "type":"Services"
        }
    ],
    "sg:phone":"+1 203 333 5018",
    "sg:postcode":"06610",
    "sg:province":"CT",
    "wof:name":"Carmen Burgos",
    "wof:placetype":"venue"
},
  "geometry": {"coordinates":[-73.157444,41.192694],"type":"Point"}
}