{
  "type": "Feature",
  "properties": {
    "iso:country":"US",
    "sg:address":"113 Danbury Rd",
    "sg:city":"Ridgefield",
    "sg:classifiers":[
        {
            "category":"Personal",
            "subcategory":"Nail Salon",
            "type":"Services"
        }
    ],
    "sg:phone":"+1 203 894 8877",
    "sg:postcode":"06877",
    "sg:province":"CT",
    "wof:name":"Nail Plaza",
    "wof:placetype":"venue"
},
  "geometry": {"coordinates":[-73.492943,41.294079],"type":"Point"}
}