{
  "type": "Feature",
  "properties": {
    "iso:country":"US",
    "sg:address":"100 Aunt Hack Rd",
    "sg:city":"Danbury",
    "sg:classifiers":[
        {
            "category":"Arts & Performance",
            "subcategory":"Theater",
            "type":"Entertainment"
        },
        {
            "category":"Cinema",
            "subcategory":"Movie Theater",
            "type":"Entertainment"
        }
    ],
    "sg:phone":"+1 203 748 6873",
    "sg:postcode":"06811",
    "sg:province":"CT",
    "sg:tags":[
        "theatrical"
    ],
    "wof:name":"Musicals At Richer",
    "wof:placetype":"venue"
},
  "geometry": {"coordinates":[-73.518299,41.411104],"type":"Point"}
}