{
  "type": "Feature",
  "properties": {
    "addr:full":"6 Bates Pl Danbury CT 06810",
    "addr:housenumber":"6",
    "addr:postcode":"06810",
    "addr:street":"Bates Pl",
    "iso:country":"US",
    "sg:address":"6 Bates Pl",
    "sg:city":"Danbury",
    "sg:classifiers":[
        {
            "category":"Recreation",
            "type":"Entertainment"
        }
    ],
    "sg:phone":"+1   ",
    "sg:postcode":"06810",
    "sg:province":"CT",
    "wof:name":"Danbury Ski Club",
    "wof:placetype":"venue"
},
  "geometry": {"coordinates":[-73.44696399999999,41.398361],"type":"Point"}
}