{
  "type": "Feature",
  "properties": {
    "iso:country":"US",
    "sg:address":"2475 Whitney Ave",
    "sg:city":"Hamden",
    "sg:classifiers":[
        {
            "category":"Retail",
            "subcategory":"Car Wash",
            "type":"Services"
        }
    ],
    "sg:phone":"+1   ",
    "sg:postcode":"06518",
    "sg:province":"CT",
    "sg:tags":[
        "carwash"
    ],
    "wof:name":"Auto Image LLC",
    "wof:placetype":"venue"
},
  "geometry": {"coordinates":[-72.900113,41.388115],"type":"Point"}
}