{
  "type": "Feature",
  "properties": {
    "iso:country":"US",
    "sg:address":"171 Roberts St",
    "sg:city":"East Hartford",
    "sg:classifiers":[
        {
            "category":"Freight",
            "type":"Transportation"
        }
    ],
    "sg:phone":"+1 860 528 0600",
    "sg:postcode":"06108",
    "sg:province":"CT",
    "sg:tags":[
        "warehouse",
        "self",
        "storage",
        "facility"
    ],
    "wof:name":"Susa Partnership LP",
    "wof:placetype":"venue"
},
  "geometry": {"coordinates":[-72.61599200000001,41.770605],"type":"Point"}
}