{
  "type": "Feature",
  "properties": {
    "addr:full":"901 Highland Ave Cheshire CT 06410",
    "addr:housenumber":"901",
    "addr:postcode":"06410",
    "addr:street":"Highland Ave",
    "iso:country":"US",
    "sg:address":"901 Highland Ave",
    "sg:city":"Cheshire",
    "sg:classifiers":[
        {
            "category":"Government",
            "subcategory":"Jail",
            "type":"Public Place"
        }
    ],
    "sg:phone":"+1 203 250 2649",
    "sg:postcode":"06410",
    "sg:province":"CT",
    "sg:tags":[
        "correctional",
        "institution"
    ],
    "wof:name":"Commissary",
    "wof:placetype":"venue"
},
  "geometry": {"coordinates":[-72.896693,41.522508],"type":"Point"}
}