{
  "type": "Feature",
  "properties": {
    "addr:full":"180 Fairfield Ave Hartford CT 06114",
    "addr:housenumber":"180",
    "addr:postcode":"06114",
    "addr:street":"Fairfield Ave;Ct",
    "iso:country":"US",
    "sg:address":"180 Fairfield Ave",
    "sg:city":"Hartford",
    "sg:classifiers":[
        {
            "category":"Building & Trades",
            "subcategory":"Landscaping Services",
            "type":"Services"
        }
    ],
    "sg:phone":"+1 860 956 8155",
    "sg:postcode":"06114",
    "sg:province":"CT",
    "wof:name":"Alexandre Landscaping",
    "wof:placetype":"venue"
},
  "geometry": {"coordinates":[-72.69272100000001,41.73534],"type":"Point"}
}