{
  "type": "Feature",
  "properties": {
    "addr:full":"Tresser Blvd Stamford CT 06901",
    "addr:postcode":"06901",
    "addr:street":"Tresser Blvd",
    "iso:country":"US",
    "sg:address":"Tresser Blvd",
    "sg:city":"Stamford",
    "sg:classifiers":[
        {
            "category":"Restaurant",
            "type":"Food & Drink"
        }
    ],
    "sg:phone":"+1 866 732 4264",
    "sg:postcode":"06901",
    "sg:province":"CT",
    "sg:tags":[
        "asian",
        "chinese",
        "pan"
    ],
    "sg:website":"http://www.pfchangs.com/",
    "wof:name":"P.F. Chang's China Bistro",
    "wof:placetype":"venue"
},
  "geometry": {"coordinates":[-73.542484,41.050949],"type":"Point"}
}