{
  "type": "Feature",
  "properties": {
    "addr:full":"60 Lovely St Canton CT 06019",
    "addr:housenumber":"60",
    "addr:postcode":"06019",
    "addr:street":"Lovely St",
    "iso:country":"US",
    "sg:address":"60 Lovely St",
    "sg:city":"Canton",
    "sg:classifiers":[
        {
            "category":"Retail",
            "subcategory":"Veterinary Services",
            "type":"Services"
        }
    ],
    "sg:phone":"+1 860 693 0214",
    "sg:postcode":"06019",
    "sg:province":"CT",
    "sg:tags":[
        "veterinarian"
    ],
    "wof:name":"Van Der Giessen Jacoba DVM",
    "wof:placetype":"venue"
},
  "geometry": {"coordinates":[-72.888817,41.816584],"type":"Point"}
}