{
  "type": "Feature",
  "properties": {
    "addr:full":"130 Cricket Ln Orange CT 06477",
    "addr:housenumber":"130",
    "addr:postcode":"06477",
    "addr:street":"Cricket Ln",
    "iso:country":"US",
    "sg:address":"130 Cricket Ln",
    "sg:city":"Orange",
    "sg:classifiers":[
        {
            "category":"Building & Trades",
            "subcategory":"Construction",
            "type":"Services"
        }
    ],
    "sg:phone":"+1 203 795 3588",
    "sg:postcode":"06477",
    "sg:province":"CT",
    "sg:tags":[
        "roofing",
        "contractor"
    ],
    "wof:name":"Harrison Roofing",
    "wof:placetype":"venue"
},
  "geometry": {"coordinates":[-72.995288,41.282971],"type":"Point"}
}