{
  "type": "Feature",
  "properties": {
    "addr:full":"524 Wordin Ave Bridgeport CT 06605",
    "addr:housenumber":"524",
    "addr:postcode":"06605",
    "addr:street":"Wordin Ave",
    "iso:country":"US",
    "sg:address":"524 Wordin Ave",
    "sg:city":"Bridgeport",
    "sg:classifiers":[
        {
            "category":"Manufacturing",
            "subcategory":"Glass & Minerals",
            "type":"Manufacturing & Wholesale Goods"
        }
    ],
    "sg:phone":"+1 203 366 4455",
    "sg:postcode":"06605",
    "sg:province":"CT",
    "sg:tags":[
        "refractory",
        "mfg"
    ],
    "wof:name":"Martin Marietta",
    "wof:placetype":"venue"
},
  "geometry": {"coordinates":[-73.207292,41.164287],"type":"Point"}
}