{
  "type": "Feature",
  "properties": {
    "iso:country":"US",
    "sg:address":"5 State Hwy 39",
    "sg:city":"New Fairfield",
    "sg:classifiers":[
        {
            "category":"Shopping",
            "subcategory":"Pharmacy",
            "type":"Retail Goods"
        }
    ],
    "sg:phone":"+1 203 312 9818",
    "sg:postcode":"06812",
    "sg:province":"CT",
    "wof:name":"Osco Drug",
    "wof:placetype":"venue"
},
  "geometry": {"coordinates":[-73.523011,41.44475],"type":"Point"}
}