{
  "type": "Feature",
  "properties": {
    "addr:full":"123 Pierce Rd South Windsor CT 06074",
    "addr:housenumber":"123",
    "addr:postcode":"06074",
    "addr:street":"Pierce Rd",
    "iso:country":"US",
    "sg:address":"123 Pierce Rd",
    "sg:city":"South Windsor",
    "sg:classifiers":[
        {
            "category":"Building & Trades",
            "subcategory":"Construction",
            "type":"Services"
        }
    ],
    "sg:phone":"+1 860 644 4098",
    "sg:postcode":"06074",
    "sg:province":"CT",
    "sg:tags":[
        "general",
        "contractor"
    ],
    "wof:name":"Brownstone Builders Inc",
    "wof:placetype":"venue"
},
  "geometry": {"coordinates":[-72.565023,41.831109],"type":"Point"}
}