{
  "type": "Feature",
  "properties": {
    "addr:full":"1369 Southford Rd Southbury CT 06488",
    "addr:housenumber":"1369",
    "addr:postcode":"06488",
    "addr:street":"Southford Rd",
    "iso:country":"US",
    "sg:address":"1369 Southford Rd",
    "sg:city":"Southbury",
    "sg:classifiers":[
        {
            "category":"Real Estate",
            "subcategory":"Real Estate Agent",
            "type":"Services"
        }
    ],
    "sg:phone":"+1 203 264 3247",
    "sg:postcode":"06488",
    "sg:province":"CT",
    "wof:name":"Boyds Appraisal Group",
    "wof:placetype":"venue"
},
  "geometry": {"coordinates":[-73.16560800000001,41.465602],"type":"Point"}
}