{
  "type": "Feature",
  "properties": {
    "iso:country":"US",
    "sg:address":"57 D Welton Way",
    "sg:city":"Thomaston",
    "sg:classifiers":[
        {
            "category":"Professional",
            "subcategory":"Art Services",
            "type":"Services"
        }
    ],
    "sg:phone":"+1   ",
    "sg:postcode":"06787",
    "sg:province":"CT",
    "sg:tags":[
        "commercial",
        "design"
    ],
    "wof:name":"Potter Dauphin Studios",
    "wof:placetype":"venue"
},
  "geometry": {"coordinates":[-73.081993,41.681338],"type":"Point"}
}