{
  "type": "Feature",
  "properties": {
    "iso:country":"US",
    "sg:address":"212 Universal Dr N",
    "sg:city":"North Haven",
    "sg:classifiers":[
        {
            "category":"Home & Garden",
            "subcategory":"Building Materials",
            "type":"Retail Goods"
        }
    ],
    "sg:phone":"+1 203 234 8380",
    "sg:postcode":"06473",
    "sg:province":"CT",
    "sg:tags":[
        "plumbing",
        "fixture",
        "supply"
    ],
    "wof:name":"Country Corner Kitchen & Bath",
    "wof:placetype":"venue"
},
  "geometry": {"coordinates":[-72.871978,41.355899],"type":"Point"}
}