{
  "type": "Feature",
  "properties": {
    "iso:country":"US",
    "sg:address":"16 Cross St",
    "sg:city":"New Canaan",
    "sg:classifiers":[
        {
            "category":"Building & Trades",
            "subcategory":"Landscaping Services",
            "type":"Services"
        }
    ],
    "sg:phone":"+1 203 966 3673",
    "sg:postcode":"06840",
    "sg:province":"NY",
    "sg:tags":[
        "landscape",
        "contractor"
    ],
    "wof:name":"Peter Lanni Inc",
    "wof:placetype":"venue"
},
  "geometry": {"coordinates":[-73.488479,41.149649],"type":"Point"}
}