{
  "type": "Feature",
  "properties": {
    "addr:full":"20 King St Hamden CT 06517",
    "addr:housenumber":"20",
    "addr:postcode":"06517",
    "addr:street":"King St",
    "iso:country":"US",
    "sg:address":"20 King St",
    "sg:city":"Hamden",
    "sg:classifiers":[
        {
            "category":"Education",
            "subcategory":"Special Training",
            "type":"Public Place"
        }
    ],
    "sg:phone":"+1   ",
    "sg:postcode":"06517",
    "sg:province":"CT",
    "wof:name":"Mazzacane Music Studio",
    "wof:placetype":"venue"
},
  "geometry": {"coordinates":[-72.91623,41.349571],"type":"Point"}
}