{
  "type": "Feature",
  "properties": {
    "addr:full":"463 Lisbon Rd Canterbury CT 06331",
    "addr:housenumber":"463",
    "addr:postcode":"06331",
    "addr:street":"Lisbon Rd",
    "iso:country":"US",
    "sg:address":"463 Lisbon Rd",
    "sg:city":"Canterbury",
    "sg:classifiers":[
        {
            "category":"Retail",
            "subcategory":"Auto Repair",
            "type":"Services"
        }
    ],
    "sg:phone":"+1   ",
    "sg:postcode":"06331",
    "sg:province":"CT",
    "sg:tags":[
        "automotive"
    ],
    "wof:name":"Doug Sogolow",
    "wof:placetype":"venue"
},
  "geometry": {"coordinates":[-72.011748,41.655115],"type":"Point"}
}