{
  "type": "Feature",
  "properties": {
    "addr:full":"3580 Main St Hartford CT 06120",
    "addr:housenumber":"3580",
    "addr:postcode":"06120",
    "addr:street":"Main St",
    "iso:country":"US",
    "sg:address":"3580 Main St",
    "sg:city":"Hartford",
    "sg:classifiers":[
        {
            "category":"Professional",
            "subcategory":"Management & Consulting",
            "type":"Services"
        }
    ],
    "sg:phone":"+1   ",
    "sg:postcode":"06120",
    "sg:province":"CT",
    "wof:name":"Henkels & McCoy",
    "wof:placetype":"venue"
},
  "geometry": {"coordinates":[-72.661264,41.800412],"type":"Point"}
}