{
  "type": "Feature",
  "properties": {
    "addr:full":"659 Norwich-Westerly Rd North Stonington CT 06359",
    "addr:housenumber":"659",
    "addr:postcode":"06359",
    "addr:street":"Norwich-Westerly Rd North Stonington Ct",
    "iso:country":"US",
    "sg:address":"659 Norwich-Westerly Rd",
    "sg:city":"North Stonington",
    "sg:classifiers":[
        {
            "category":"Wholesale",
            "subcategory":"Motor Vehicles",
            "type":"Manufacturing & Wholesale Goods"
        }
    ],
    "sg:phone":"+1 860 535 0031",
    "sg:postcode":"06359",
    "sg:province":"CT",
    "wof:name":"Jordans Auto",
    "wof:placetype":"venue"
},
  "geometry": {"coordinates":[-71.91899100000001,41.467033],"type":"Point"}
}