{
  "type": "Feature",
  "properties": {
    "iso:country":"US",
    "sg:address":"368 Colebrook River Rd",
    "sg:city":"Riverton",
    "sg:classifiers":[
        {
            "category":"Building & Trades",
            "subcategory":"Construction",
            "type":"Services"
        }
    ],
    "sg:phone":"+1 860 379 8664",
    "sg:postcode":"06065",
    "sg:province":"CT",
    "sg:tags":[
        "industrial"
    ],
    "wof:name":"Scanlon Building & Rmdlg LLC",
    "wof:placetype":"venue"
},
  "geometry": {"coordinates":[-73.055513,42.03129],"type":"Point"}
}