{
  "type": "Feature",
  "properties": {
    "iso:country":"US",
    "sg:address":"598 Horse Hill Rd",
    "sg:city":"Westbrook",
    "sg:classifiers":[
        {
            "category":"Arts & Performance",
            "subcategory":"Theater",
            "type":"Entertainment"
        }
    ],
    "sg:phone":"+1   ",
    "sg:postcode":"06498",
    "sg:province":"CT",
    "sg:tags":[
        "group"
    ],
    "wof:name":"High Horses Inc",
    "wof:placetype":"venue"
},
  "geometry": {"coordinates":[-72.49222399999999,41.308841],"type":"Point"}
}