{
  "type": "Feature",
  "properties": {
    "addr:full":"9 Amity Rd Bethany CT 06524",
    "addr:housenumber":"9",
    "addr:postcode":"06524",
    "addr:street":"Amity Rd Bethany Ct",
    "iso:country":"US",
    "sg:address":"9 Amity Rd",
    "sg:city":"Bethany",
    "sg:classifiers":[
        {
            "category":"Shopping",
            "subcategory":"Pets & Pet Supplies",
            "type":"Retail Goods"
        },
        {
            "category":"Retail",
            "subcategory":"Veterinary Services",
            "type":"Services"
        },
        {
            "category":"Retail",
            "subcategory":"Animal Services",
            "type":"Services"
        }
    ],
    "sg:phone":"+1 203 393 7387",
    "sg:postcode":"06524",
    "sg:province":"CT",
    "sg:tags":[
        "product",
        "hospital",
        "specialty",
        "clinic",
        "health",
        "veterinarian"
    ],
    "sg:website":"http://www.countrycompanionsvet.com",
    "wof:name":"Country Companions Veterinary Service",
    "wof:placetype":"venue"
},
  "geometry": {"coordinates":[-73.00060999999999,41.391349],"type":"Point"}
}