{
  "type": "Feature",
  "properties": {
    "iso:country":"US",
    "sg:address":"250 State St",
    "sg:city":"North Haven",
    "sg:classifiers":[
        {
            "category":"Professional",
            "subcategory":"Management & Consulting",
            "type":"Services"
        }
    ],
    "sg:phone":"+1   ",
    "sg:postcode":"06473",
    "sg:province":"CT",
    "sg:tags":[
        "business"
    ],
    "wof:name":"Conlon Francis X &",
    "wof:placetype":"venue"
},
  "geometry": {"coordinates":[-72.883618,41.375333],"type":"Point"}
}