{
  "type": "Feature",
  "properties": {
    "iso:country":"US",
    "sg:address":"115 Roosevelt St",
    "sg:city":"Bridgeport",
    "sg:classifiers":[
        {
            "category":"Building & Trades",
            "subcategory":"Construction",
            "type":"Services"
        }
    ],
    "sg:phone":"+1 203 336 2969",
    "sg:postcode":"06608",
    "sg:province":"CT",
    "sg:tags":[
        "carpenter"
    ],
    "wof:name":"J C Carpentry",
    "wof:placetype":"venue"
},
  "geometry": {"coordinates":[-73.184584,41.198246],"type":"Point"}
}