{
  "type": "Feature",
  "properties": {
    "iso:country":"US",
    "sg:address":"58 Alna Ln",
    "sg:city":"East Hartford",
    "sg:classifiers":[
        {
            "category":"Building & Trades",
            "subcategory":"Construction",
            "type":"Services"
        }
    ],
    "sg:phone":"+1 860 610 1093",
    "sg:postcode":"06108",
    "sg:province":"CT",
    "sg:tags":[
        "house"
    ],
    "wof:name":"Olsen Construction Co",
    "wof:placetype":"venue"
},
  "geometry": {"coordinates":[-72.610923,41.797282],"type":"Point"}
}