{
  "type": "Feature",
  "properties": {
    "iso:country":"US",
    "sg:address":"16 Railroad Pl",
    "sg:city":"Westport",
    "sg:classifiers":[
        {
            "category":"Professional",
            "subcategory":"Business Services",
            "type":"Services"
        }
    ],
    "sg:phone":"+1   ",
    "sg:postcode":"06880",
    "sg:province":"CT",
    "wof:name":"Parth Trading Corporation",
    "wof:placetype":"venue"
},
  "geometry": {"coordinates":[-73.37169299999999,41.119087],"type":"Point"}
}