{
  "type": "Feature",
  "properties": {
    "addr:full":"1673 Barnum Ave Bridgeport CT 06610",
    "addr:housenumber":"1673",
    "addr:postcode":"06610",
    "addr:street":"Barnum Ave",
    "iso:country":"US",
    "sg:address":"1673 Barnum Ave",
    "sg:city":"Bridgeport",
    "sg:classifiers":[
        {
            "category":"Retail",
            "subcategory":"Car Wash",
            "type":"Services"
        }
    ],
    "sg:phone":"+1   ",
    "sg:postcode":"06610",
    "sg:province":"CT",
    "sg:tags":[
        "carwash"
    ],
    "wof:name":"Diamond Car Wash LLC",
    "wof:placetype":"venue"
},
  "geometry": {"coordinates":[-73.15975400000001,41.188446],"type":"Point"}
}