{
  "type": "Feature",
  "properties": {
    "addr:full":"641 Farmington Ave Bristol CT 06010",
    "addr:housenumber":"641",
    "addr:postcode":"06010",
    "addr:street":"Farmington Ave Bristol Ct",
    "iso:country":"US",
    "sg:address":"641 Farmington Ave",
    "sg:city":"Bristol",
    "sg:classifiers":[
        {
            "category":"Coffee & Tea",
            "type":"Food & Drink"
        }
    ],
    "sg:menulink":"http://www.allmenus.com/ct/bristol/108454-starbucks-coffee/menu/",
    "sg:phone":"+1 860 585 8232",
    "sg:postcode":"06010",
    "sg:province":"CT",
    "sg:tags":[
        "american"
    ],
    "wof:name":"Starbucks Coffee",
    "wof:placetype":"venue"
},
  "geometry": {"coordinates":[-72.922783,41.692044],"type":"Point"}
}