{
  "type": "Feature",
  "properties": {
    "iso:country":"US",
    "sg:address":"158 Montowese St",
    "sg:city":"Branford",
    "sg:classifiers":[
        {
            "category":"Professional",
            "subcategory":"Lawyer & Legal Services",
            "type":"Services"
        }
    ],
    "sg:phone":"+1 203 483 8400",
    "sg:postcode":"06405",
    "sg:province":"CT",
    "sg:tags":[
        "attorney"
    ],
    "wof:name":"Kenneth J Papa Law Offices",
    "wof:placetype":"venue"
},
  "geometry": {"coordinates":[-72.808511,41.280555],"type":"Point"}
}