{
  "type": "Feature",
  "properties": {
    "iso:country":"US",
    "sg:address":"494 Bridgeport Ave",
    "sg:city":"Shelton",
    "sg:classifiers":[
        {
            "category":"Utilities",
            "subcategory":"Mobile Phone",
            "type":"Services"
        }
    ],
    "sg:phone":"+1 203 929 8221",
    "sg:postcode":"06484",
    "sg:province":"CT",
    "sg:tags":[
        "telephone",
        "cellular"
    ],
    "wof:name":"Nextel Customer Ctr Of Shelton",
    "wof:placetype":"venue"
},
  "geometry": {"coordinates":[-73.111616,41.290786],"type":"Point"}
}