{
  "type": "Feature",
  "properties": {
    "addr:full":"18 Old Mill Rd Redding CT 06896",
    "addr:housenumber":"18",
    "addr:postcode":"06896",
    "addr:street":"Old Mill Rd",
    "iso:country":"US",
    "sg:address":"18 Old Mill Rd",
    "sg:city":"Redding",
    "sg:classifiers":[
        {
            "category":"Real Estate",
            "subcategory":"Real Estate Agent",
            "type":"Services"
        }
    ],
    "sg:phone":"+1 203 544 8700",
    "sg:postcode":"06896",
    "sg:province":"CT",
    "wof:name":"Granite Properties",
    "wof:placetype":"venue"
},
  "geometry": {"coordinates":[-73.428012,41.25645],"type":"Point"}
}