{
  "type": "Feature",
  "properties": {
    "addr:full":"301 Moose Hill Rd Monroe CT 06468",
    "addr:housenumber":"301",
    "addr:postcode":"06468",
    "addr:street":"Moose Hill Rd",
    "iso:country":"US",
    "sg:address":"301 Moose Hill Rd",
    "sg:city":"Monroe",
    "sg:classifiers":[
        {
            "category":"Arts & Performance",
            "subcategory":"Theater",
            "type":"Entertainment"
        }
    ],
    "sg:phone":"+1   ",
    "sg:postcode":"06468",
    "sg:province":"CT",
    "sg:tags":[
        "group"
    ],
    "wof:name":"B K Music Group",
    "wof:placetype":"venue"
},
  "geometry": {"coordinates":[-73.204587,41.311661],"type":"Point"}
}