{
  "type": "Feature",
  "properties": {
    "iso:country":"US",
    "sg:address":"457 Bantam Rd",
    "sg:city":"Litchfield",
    "sg:classifiers":[
        {
            "category":"Personal",
            "subcategory":"Beauty Salon",
            "type":"Services"
        }
    ],
    "sg:phone":"+1   ",
    "sg:postcode":"06759",
    "sg:province":"CT",
    "sg:tags":[
        "shop"
    ],
    "wof:name":"Haircuts Etc",
    "wof:placetype":"venue"
},
  "geometry": {"coordinates":[-73.217061,41.731085],"type":"Point"}
}