{
  "type": "Feature",
  "properties": {
    "addr:full":"371 Hammertown Rd Monroe CT 06468",
    "addr:housenumber":"371",
    "addr:postcode":"06468",
    "addr:street":"Hammertown Rd",
    "iso:country":"US",
    "sg:address":"371 Hammertown Rd",
    "sg:city":"Monroe",
    "sg:classifiers":[
        {
            "category":"Professional",
            "type":"Services"
        }
    ],
    "sg:phone":"+1 203 452 9119",
    "sg:postcode":"06468",
    "sg:province":"CT",
    "wof:name":"Colonial Housewrights LLC",
    "wof:placetype":"venue"
},
  "geometry": {"coordinates":[-73.22201200000001,41.363298],"type":"Point"}
}