{
  "type": "Feature",
  "properties": {
    "iso:country":"US",
    "sg:address":"2562 Main St",
    "sg:city":"Hartford",
    "sg:classifiers":[
        {
            "category":"Food & Beverages",
            "subcategory":"Liquor & Beverages",
            "type":"Retail Goods"
        }
    ],
    "sg:phone":"+1 860 522 7856",
    "sg:postcode":"06120",
    "sg:province":"CT",
    "sg:tags":[
        "alcoholic"
    ],
    "wof:name":"N & C Package Store",
    "wof:placetype":"venue"
},
  "geometry": {"coordinates":[-72.67117399999999,41.789685],"type":"Point"}
}