{
  "type": "Feature",
  "properties": {
    "addr:full":"520 Stonehouse Rd Trumbull CT 06611",
    "addr:housenumber":"520",
    "addr:postcode":"06611",
    "addr:street":"Stonehouse Rd",
    "iso:country":"US",
    "sg:address":"520 Stonehouse Rd",
    "sg:city":"Trumbull",
    "sg:classifiers":[
        {
            "category":"Building & Trades",
            "subcategory":"Construction",
            "type":"Services"
        }
    ],
    "sg:phone":"+1 203 445 9583",
    "sg:postcode":"06611",
    "sg:province":"CT",
    "sg:tags":[
        "concrete",
        "contractor"
    ],
    "wof:name":"Atilho Construction",
    "wof:placetype":"venue"
},
  "geometry": {"coordinates":[-73.248228,41.274208],"type":"Point"}
}