{
  "type": "Feature",
  "properties": {
    "addr:full":"150 Dirienzo Hts Derby CT 06418",
    "addr:housenumber":"150",
    "addr:postcode":"06418",
    "addr:street":"Dirienzo Hts Derby Ct",
    "iso:country":"US",
    "sg:address":"150 Dirienzo Hts",
    "sg:city":"Derby",
    "sg:classifiers":[
        {
            "category":"Building & Trades",
            "subcategory":"Cleaning & Sanitation",
            "type":"Services"
        }
    ],
    "sg:phone":"+1   ",
    "sg:postcode":"06418",
    "sg:province":"CT",
    "sg:tags":[
        "maintenance"
    ],
    "wof:name":"Tonys Cleaning Service",
    "wof:placetype":"venue"
},
  "geometry": {"coordinates":[-73.060902,41.321249],"type":"Point"}
}