{
  "type": "Feature",
  "properties": {
    "addr:full":"354 W Main St Waterbury CT 06702",
    "addr:housenumber":"354",
    "addr:postcode":"06702",
    "addr:street":"W Main St",
    "iso:country":"US",
    "sg:address":"354 W Main St",
    "sg:city":"Waterbury",
    "sg:classifiers":[
        {
            "category":"Restaurant",
            "type":"Food & Drink"
        }
    ],
    "sg:phone":"+1 203 754 9850",
    "sg:postcode":"06702",
    "sg:province":"CT",
    "wof:name":"LA Cazuela",
    "wof:placetype":"venue"
},
  "geometry": {"coordinates":[-73.04800899999999,41.558085],"type":"Point"}
}