{
  "type": "Feature",
  "properties": {
    "iso:country":"US",
    "sg:address":"54 Hayes St",
    "sg:city":"Torrington",
    "sg:classifiers":[
        {
            "category":"Social Services",
            "type":"Services"
        }
    ],
    "sg:phone":"+1   ",
    "sg:postcode":"06790",
    "sg:province":"CT",
    "wof:name":"Dudley Daline Lcsw",
    "wof:placetype":"venue"
},
  "geometry": {"coordinates":[-73.114885,41.792131],"type":"Point"}
}