{
  "type": "Feature",
  "properties": {
    "iso:country":"US",
    "sg:address":"40 Meadow St",
    "sg:city":"Stamford",
    "sg:classifiers":[
        {
            "category":"Wholesale",
            "subcategory":"Machinery & Supplies",
            "type":"Manufacturing & Wholesale Goods"
        },
        {
            "category":"Home & Garden",
            "subcategory":"Building Materials",
            "type":"Retail Goods"
        }
    ],
    "sg:phone":"+1 203 323 1111",
    "sg:postcode":"06902",
    "sg:province":"CT",
    "sg:tags":[
        "ready",
        "concrete",
        "contractor",
        "mason",
        "mfg"
    ],
    "sg:website":"www.ogind.com",
    "wof:name":"O & G Industries Inc",
    "wof:placetype":"venue"
},
  "geometry": {"coordinates":[-73.532943,41.048452],"type":"Point"}
}