{
  "type": "Feature",
  "properties": {
    "iso:country":"US",
    "sg:address":"16 Elm Dr",
    "sg:city":"Newtown",
    "sg:classifiers":[
        {
            "category":"Building & Trades",
            "subcategory":"Landscaping Services",
            "type":"Services"
        }
    ],
    "sg:phone":"+1 203 426 8609",
    "sg:postcode":"06470",
    "sg:province":"CT",
    "sg:tags":[
        "landscape",
        "contractor"
    ],
    "wof:name":"Elm Glade Landscaping",
    "wof:placetype":"venue"
},
  "geometry": {"coordinates":[-73.30293399999999,41.404547],"type":"Point"}
}