{
  "type": "Feature",
  "properties": {
    "addr:full":"143 Cedar Ridge Ter Glastonbury CT 06033",
    "addr:housenumber":"143",
    "addr:postcode":"06033",
    "addr:street":"Cedar Ridge Ter Glastonbury Ct",
    "iso:country":"US",
    "sg:address":"143 Cedar Ridge Ter",
    "sg:city":"Glastonbury",
    "sg:classifiers":[
        {
            "category":"Wholesale",
            "subcategory":"Non-durable Goods",
            "type":"Manufacturing & Wholesale Goods"
        }
    ],
    "sg:phone":"+1 860 647 9958",
    "sg:postcode":"06033",
    "sg:province":"CT",
    "wof:name":"Hickory Laminates",
    "wof:placetype":"venue"
},
  "geometry": {"coordinates":[-72.523796,41.726101],"type":"Point"}
}