{
  "type": "Feature",
  "properties": {
    "iso:country":"US",
    "sg:address":"59 Center St",
    "sg:city":"Westport",
    "sg:classifiers":[
        {
            "category":"Home & Garden",
            "subcategory":"Garden Supply",
            "type":"Retail Goods"
        }
    ],
    "sg:phone":"+1 203 226 5245",
    "sg:postcode":"06880",
    "sg:province":"CT",
    "sg:tags":[
        "fountain",
        "display"
    ],
    "wof:name":"Bedford Gardens",
    "wof:placetype":"venue"
},
  "geometry": {"coordinates":[-73.32977,41.128378],"type":"Point"}
}