{
  "type": "Feature",
  "properties": {
    "addr:full":"36 Hale Ln Darien CT 06820",
    "addr:housenumber":"36",
    "addr:postcode":"06820",
    "addr:street":"Hale Ln Darien Ct",
    "iso:country":"US",
    "sg:address":"36 Hale Ln",
    "sg:city":"Darien",
    "sg:classifiers":[
        {
            "category":"Shopping",
            "subcategory":"Jewelry",
            "type":"Retail Goods"
        }
    ],
    "sg:phone":"+1 203 656 2545",
    "sg:postcode":"06820",
    "sg:province":"CT",
    "wof:name":"Something Extra",
    "wof:placetype":"venue"
},
  "geometry": {"coordinates":[-73.475545,41.073851],"type":"Point"}
}