{
  "type": "Feature",
  "properties": {
    "addr:full":"1011 High Ridge Rd Stamford CT 06905",
    "addr:housenumber":"1011",
    "addr:postcode":"06905",
    "addr:street":"High Ridge Rd",
    "iso:country":"US",
    "sg:address":"1011 High Ridge Rd",
    "sg:city":"Stamford",
    "sg:classifiers":[
        {
            "category":"Professional",
            "type":"Services"
        }
    ],
    "sg:phone":"+1 203 329 9666",
    "sg:postcode":"06905",
    "sg:province":"CT",
    "wof:name":"Greenwich Adolescent Medicine",
    "wof:placetype":"venue"
},
  "geometry": {"coordinates":[-73.548332,41.104841],"type":"Point"}
}