{
  "type": "Feature",
  "properties": {
    "addr:full":"216 Signal Hill Rd Wilton CT 06897",
    "addr:housenumber":"216",
    "addr:postcode":"06897",
    "addr:street":"Signal Hill Rd Wilton Ct",
    "iso:country":"US",
    "sg:address":"216 Signal Hill Rd",
    "sg:city":"Wilton",
    "sg:classifiers":[
        {
            "category":"Professional",
            "type":"Services"
        }
    ],
    "sg:phone":"+1 203 762 2706",
    "sg:postcode":"06897",
    "sg:province":"CT",
    "wof:name":"Wilton Education Foundation",
    "wof:placetype":"venue"
},
  "geometry": {"coordinates":[-73.461493,41.203672],"type":"Point"}
}