{
  "type": "Feature",
  "properties": {
    "addr:full":"124 Knapp St Stamford CT 06907",
    "addr:housenumber":"124",
    "addr:postcode":"06907",
    "addr:street":"Knapp St",
    "iso:country":"US",
    "sg:address":"124 Knapp St",
    "sg:city":"Stamford",
    "sg:classifiers":[
        {
            "category":"Health Services",
            "subcategory":"Health Practitioner",
            "type":"Services"
        }
    ],
    "sg:phone":"+1 203 253 6839",
    "sg:postcode":"06907",
    "sg:province":"CT",
    "sg:tags":[
        "pathologist",
        "speech"
    ],
    "wof:name":"Lynne Lane",
    "wof:placetype":"venue"
},
  "geometry": {"coordinates":[-73.52387899999999,41.093864],"type":"Point"}
}