{
  "type": "Feature",
  "properties": {
    "addr:full":"276 Hazard Ave Enfield CT 06082",
    "addr:housenumber":"276",
    "addr:postcode":"06082",
    "addr:street":"Hazard Ave",
    "iso:country":"US",
    "sg:address":"276 Hazard Ave",
    "sg:city":"Enfield",
    "sg:classifiers":[
        {
            "category":"Professional",
            "subcategory":"Computer Services",
            "type":"Services"
        }
    ],
    "sg:phone":"+1   ",
    "sg:postcode":"06082",
    "sg:province":"CT",
    "sg:tags":[
        "programming",
        "software"
    ],
    "wof:name":"Design Automation Associates",
    "wof:placetype":"venue"
},
  "geometry": {"coordinates":[-72.543792,41.987056],"type":"Point"}
}