{
  "type": "Feature",
  "properties": {
    "iso:country":"US",
    "sg:address":"119 Mount Pleasant Rd",
    "sg:city":"Newtown",
    "sg:classifiers":[
        {
            "category":"Retail",
            "subcategory":"Veterinary Services",
            "type":"Services"
        }
    ],
    "sg:phone":"+1 203 426 8585",
    "sg:postcode":"06470",
    "sg:province":"CT",
    "sg:tags":[
        "hospital",
        "animal"
    ],
    "wof:name":"Mt Pleasant Hospital-Animals",
    "wof:placetype":"venue"
},
  "geometry": {"coordinates":[-73.356016,41.417637],"type":"Point"}
}