{
  "type": "Feature",
  "properties": {
    "addr:full":"2165 Dixwell Ave Hamden CT 06514",
    "addr:housenumber":"2165",
    "addr:postcode":"06514",
    "addr:street":"Dixwell Ave",
    "iso:country":"US",
    "sg:address":"2165 Dixwell Ave",
    "sg:city":"Hamden",
    "sg:classifiers":[
        {
            "category":"Shopping",
            "subcategory":"Clothing, Apparel, & Fashions",
            "type":"Retail Goods"
        }
    ],
    "sg:phone":"+1 203 230 3229",
    "sg:postcode":"06514",
    "sg:province":"CT",
    "wof:name":"Avenue",
    "wof:placetype":"venue"
},
  "geometry": {"coordinates":[-72.919999,41.367776],"type":"Point"}
}