{
  "type": "Feature",
  "properties": {
    "addr:full":"39 Rosedale Rd Hartford CT 06107",
    "addr:housenumber":"39",
    "addr:postcode":"06107",
    "addr:street":"Rosedale Rd",
    "iso:country":"US",
    "sg:address":"39 Rosedale Rd",
    "sg:city":"Hartford",
    "sg:classifiers":[
        {
            "category":"Building & Trades",
            "subcategory":"Electrical",
            "type":"Services"
        }
    ],
    "sg:phone":"+1 860 561 2086",
    "sg:postcode":"06107",
    "sg:province":"CT",
    "sg:tags":[
        "electrical",
        "contractor"
    ],
    "wof:name":"Robert Preston",
    "wof:placetype":"venue"
},
  "geometry": {"coordinates":[-72.762342,41.748161],"type":"Point"}
}