{
  "type": "Feature",
  "properties": {
    "addr:full":"315 W River Rd Orange CT 06477",
    "addr:housenumber":"315",
    "addr:postcode":"06477",
    "addr:street":"W River Rd",
    "iso:country":"US",
    "sg:address":"315 W River Rd",
    "sg:city":"Orange",
    "sg:classifiers":[
        {
            "category":"Professional",
            "subcategory":"Art Services",
            "type":"Services"
        }
    ],
    "sg:phone":"+1   ",
    "sg:postcode":"06477",
    "sg:province":"CT",
    "sg:tags":[
        "commercial",
        "consulting",
        "management",
        "design"
    ],
    "wof:name":"Reid Robert J Associates",
    "wof:placetype":"venue"
},
  "geometry": {"coordinates":[-73.05509000000001,41.261675],"type":"Point"}
}