{
  "type": "Feature",
  "properties": {
    "addr:full":"46 Averyll Ave Wolcott CT 06716",
    "addr:housenumber":"46",
    "addr:postcode":"06716",
    "addr:street":"Averyll Ave",
    "iso:country":"US",
    "sg:address":"46 Averyll Ave",
    "sg:city":"Wolcott",
    "sg:classifiers":[
        {
            "category":"Food & Beverages",
            "subcategory":"Groceries & Convenience Stores",
            "type":"Retail Goods"
        }
    ],
    "sg:phone":"+1 860 583 9177",
    "sg:postcode":"06716",
    "sg:province":"CT",
    "sg:tags":[
        "grocer"
    ],
    "wof:name":"Terryville IGA LLC",
    "wof:placetype":"venue"
},
  "geometry": {"coordinates":[-72.966362,41.637502],"type":"Point"}
}