{
  "type": "Feature",
  "properties": {
    "addr:full":"1455 Washington Blvd Stamford CT 06902",
    "addr:housenumber":"1455",
    "addr:postcode":"06902",
    "addr:street":"Washington Blvd",
    "iso:country":"US",
    "sg:address":"1455 Washington Blvd",
    "sg:city":"Stamford",
    "sg:classifiers":[
        {
            "category":"Real Estate",
            "subcategory":"Real Estate Operator",
            "type":"Services"
        }
    ],
    "sg:phone":"+1 877 272 4660",
    "sg:postcode":"06902",
    "sg:province":"CT",
    "sg:tags":[
        "apartment"
    ],
    "sg:website":"http://local.ingenio.com/Listings/Details.aspx?NUM=a%3a10313599%3a13%3a4859924%3a14%3a0%3a7",
    "wof:name":"Stamford Corners Apartments",
    "wof:placetype":"venue"
},
  "geometry": {"coordinates":[-73.54346,41.058709],"type":"Point"}
}