{
  "type": "Feature",
  "properties": {
    "iso:country":"US",
    "sg:address":"41 E Main St",
    "sg:city":"Avon",
    "sg:classifiers":[
        {
            "category":"Restaurant",
            "type":"Food & Drink"
        }
    ],
    "sg:postcode":"06001",
    "sg:province":"CT",
    "sg:tags":[
        "southern"
    ],
    "wof:name":"Good2Go",
    "wof:placetype":"venue"
},
  "geometry": {"coordinates":[-72.827956,41.808576],"type":"Point"}
}