{
  "type": "Feature",
  "properties": {
    "addr:full":"90 Eileen Rd West Haven CT 06516",
    "addr:housenumber":"90",
    "addr:postcode":"06516",
    "addr:street":"Eileen Rd;Haven",
    "iso:country":"US",
    "sg:address":"90 Eileen Rd",
    "sg:city":"West Haven",
    "sg:classifiers":[
        {
            "category":"Social Services",
            "subcategory":"Child Care",
            "type":"Services"
        }
    ],
    "sg:phone":"+1 203 931 0340",
    "sg:postcode":"06516",
    "sg:province":"CT",
    "wof:name":"Little Blessing Day Care",
    "wof:placetype":"venue"
},
  "geometry": {"coordinates":[-72.977175,41.273798],"type":"Point"}
}