{
  "type": "Feature",
  "properties": {
    "iso:country":"US",
    "sg:address":"700 May St",
    "sg:city":"Naugatuck",
    "sg:classifiers":[
        {
            "category":"Freight",
            "type":"Transportation"
        }
    ],
    "sg:phone":"+1 203 729 5571",
    "sg:postcode":"06770",
    "sg:province":"CT",
    "sg:tags":[
        "operator",
        "local",
        "trucking"
    ],
    "wof:name":"Kollar Transport",
    "wof:placetype":"venue"
},
  "geometry": {"coordinates":[-73.027979,41.491684],"type":"Point"}
}