{
  "type": "Feature",
  "properties": {
    "addr:full":"59 Broad St Stamford CT 06901",
    "addr:housenumber":"59",
    "addr:postcode":"06901",
    "addr:street":"Broad St",
    "iso:country":"US",
    "sg:address":"59 Broad St",
    "sg:city":"Stamford",
    "sg:classifiers":[
        {
            "category":"Professional",
            "subcategory":"Accounting & Tax Preparation",
            "type":"Services"
        }
    ],
    "sg:phone":"+1 203 348 7755",
    "sg:postcode":"06901",
    "sg:province":"CT",
    "sg:tags":[
        "accountant"
    ],
    "wof:name":"Robert G Davidson CPA",
    "wof:placetype":"venue"
},
  "geometry": {"coordinates":[-73.540819,41.055382],"type":"Point"}
}