{
  "type": "Feature",
  "properties": {
    "addr:full":"206 Hungary Rd Granby CT 06035",
    "addr:housenumber":"206",
    "addr:postcode":"06035",
    "addr:street":"Hungary Rd",
    "iso:country":"US",
    "sg:address":"206 Hungary Rd",
    "sg:city":"Granby",
    "sg:classifiers":[
        {
            "category":"Building & Trades",
            "subcategory":"Landscaping Services",
            "type":"Services"
        }
    ],
    "sg:phone":"+1 860 653 3629",
    "sg:postcode":"06035",
    "sg:province":"CT",
    "wof:name":"Farmington Valley Tree",
    "wof:placetype":"venue"
},
  "geometry": {"coordinates":[-72.77347399999999,41.983243],"type":"Point"}
}