{
  "type": "Feature",
  "properties": {
    "addr:full":"1027 Voluntown Rd Jewett City CT 06351",
    "addr:housenumber":"1027",
    "addr:postcode":"06351",
    "addr:street":"Voluntown Rd Jewett City Ct",
    "iso:country":"US",
    "sg:address":"1027 Voluntown Rd",
    "sg:city":"Jewett City",
    "sg:classifiers":[
        {
            "category":"Personal",
            "subcategory":"Beauty Salon",
            "type":"Services"
        }
    ],
    "sg:phone":"+1   ",
    "sg:postcode":"06351",
    "sg:province":"CT",
    "sg:tags":[
        "shop"
    ],
    "wof:name":"Lindas Country Curls LLC",
    "wof:placetype":"venue"
},
  "geometry": {"coordinates":[-71.921519,41.58399],"type":"Point"}
}