{
  "type": "Feature",
  "properties": {
    "iso:country":"US",
    "sg:address":"9 Hartford Tpke",
    "sg:city":"Tolland",
    "sg:classifiers":[
        {
            "category":"Place Of Worship",
            "subcategory":"Church",
            "type":"Public Place"
        },
        {
            "category":"Place Of Worship",
            "type":"Public Place"
        }
    ],
    "sg:phone":"+1 860 875 0450",
    "sg:postcode":"06084",
    "sg:province":"CT",
    "sg:tags":[
        "churches-seventh-day",
        "adventist",
        "christian",
        "churches-advent"
    ],
    "sg:website":"http://www.adventist.org",
    "wof:name":"Seventh -Day Adventist Church",
    "wof:placetype":"venue"
},
  "geometry": {"coordinates":[-72.40771700000001,41.870895],"type":"Point"}
}