{
  "type": "Feature",
  "properties": {
    "iso:country":"US",
    "sg:address":"410 Main St",
    "sg:city":"Danbury",
    "sg:classifiers":[
        {
            "category":"Personal",
            "subcategory":"Beauty Salon",
            "type":"Services"
        }
    ],
    "sg:phone":"+1 203 730 8831",
    "sg:postcode":"06810",
    "sg:province":"CT",
    "wof:name":"First Place Barber Shop",
    "wof:placetype":"venue"
},
  "geometry": {"coordinates":[-73.459096,41.402333],"type":"Point"}
}