{
  "type": "Feature",
  "properties": {
    "addr:full":"6 N Pearl St Port Chester CT 10573",
    "addr:housenumber":"6",
    "addr:postcode":"10573",
    "addr:street":"N Pearl St Port Chester Ct",
    "iso:country":"US",
    "sg:address":"6 N Pearl St",
    "sg:city":"Port Chester",
    "sg:classifiers":[
        {
            "category":"Professional",
            "subcategory":"Business Services",
            "type":"Services"
        }
    ],
    "sg:phone":"+1 914 939 5503",
    "sg:postcode":"10573",
    "sg:province":"CT",
    "sg:tags":[
        "embroidery"
    ],
    "wof:name":"Stitchcraft Lettering",
    "wof:placetype":"venue"
},
  "geometry": {"coordinates":[-73.665447,41.002226],"type":"Point"}
}