{
  "type": "Feature",
  "properties": {
    "addr:full":"801 N Main St Exd Wallingford CT 06492",
    "addr:housenumber":"801",
    "addr:postcode":"06492",
    "addr:street":"N Main St Exd",
    "iso:country":"US",
    "sg:address":"801 N Main St Exd",
    "sg:city":"Wallingford",
    "sg:classifiers":[
        {
            "category":"Building & Trades",
            "subcategory":"Electrical",
            "type":"Services"
        }
    ],
    "sg:phone":"+1 203 269 9602",
    "sg:postcode":"06492",
    "sg:province":"CT",
    "sg:tags":[
        "electric",
        "contractor"
    ],
    "wof:name":"Unlimited Electric Co",
    "wof:placetype":"venue"
},
  "geometry": {"coordinates":[-72.80852299999999,41.476865],"type":"Point"}
}