{
  "type": "Feature",
  "properties": {
    "addr:full":"69 Bridge St Willimantic CT 06226",
    "addr:housenumber":"69",
    "addr:postcode":"06226",
    "addr:street":"Bridge St",
    "iso:country":"US",
    "sg:address":"69 Bridge St",
    "sg:city":"Willimantic",
    "sg:classifiers":[
        {
            "category":"Personal",
            "subcategory":"Beauty Salon",
            "type":"Services"
        }
    ],
    "sg:phone":"+1   ",
    "sg:postcode":"06226",
    "sg:province":"CT",
    "sg:tags":[
        "shop"
    ],
    "wof:name":"Dawns Designs",
    "wof:placetype":"venue"
},
  "geometry": {"coordinates":[-72.22014299999999,41.711597],"type":"Point"}
}