{
  "type": "Feature",
  "properties": {
    "addr:full":"19 Coley Dr Weston CT 06883",
    "addr:housenumber":"19",
    "addr:postcode":"06883",
    "addr:street":"Coley Dr",
    "iso:country":"US",
    "sg:address":"19 Coley Dr",
    "sg:city":"Weston",
    "sg:classifiers":[
        {
            "category":"Professional",
            "subcategory":"Business Services",
            "type":"Services"
        }
    ],
    "sg:phone":"+1   ",
    "sg:postcode":"06883",
    "sg:province":"CT",
    "wof:name":"Libra Interiors",
    "wof:placetype":"venue"
},
  "geometry": {"coordinates":[-73.36319,41.189521],"type":"Point"}
}