{
  "type": "Feature",
  "properties": {
    "iso:country":"US",
    "sg:address":"1254 Storrs Rd",
    "sg:city":"Storrs Mansfield",
    "sg:classifiers":[
        {
            "category":"Restaurant",
            "type":"Food & Drink"
        }
    ],
    "sg:menulink":"http://www.allmenus.com/ct/mansfield/18732-wings-over-storrs/menu/",
    "sg:phone":"+1 860 429 6666",
    "sg:postcode":"06268",
    "sg:province":"CT",
    "sg:tags":[
        "sandwich",
        "american",
        "wrap",
        "barbecue",
        "chicken",
        "wing"
    ],
    "wof:name":"Wings Over Storrs",
    "wof:placetype":"venue"
},
  "geometry": {"coordinates":[-72.244793,41.805684],"type":"Point"}
}