{
  "type": "Feature",
  "properties": {
    "addr:full":"316 Cedar Mountain Rd Thomaston CT 06787",
    "addr:housenumber":"316",
    "addr:postcode":"06787",
    "addr:street":"Cedar Mountain Rd Thomaston Ct",
    "iso:country":"US",
    "sg:address":"316 Cedar Mountain Rd",
    "sg:city":"Thomaston",
    "sg:classifiers":[
        {
            "category":"Home & Garden",
            "subcategory":"Carpets & Floor Coverings",
            "type":"Retail Goods"
        }
    ],
    "sg:phone":"+1 860 283 9201",
    "sg:postcode":"06787",
    "sg:province":"CT",
    "sg:tags":[
        "laying",
        "contractor"
    ],
    "wof:name":"Carpet Concepts",
    "wof:placetype":"venue"
},
  "geometry": {"coordinates":[-73.06948800000001,41.648808],"type":"Point"}
}