{
  "type": "Feature",
  "properties": {
    "iso:country":"US",
    "sg:address":"12 Stanton Rd",
    "sg:city":"North Haven",
    "sg:classifiers":[
        {
            "category":"Utilities",
            "subcategory":"Fuel Oil & Lpg",
            "type":"Services"
        }
    ],
    "sg:phone":"+1 203 234 2244",
    "sg:postcode":"06473",
    "sg:province":"CT",
    "sg:tags":[
        "dealer"
    ],
    "wof:name":"Golden Oil Co Inc",
    "wof:placetype":"venue"
},
  "geometry": {"coordinates":[-72.849029,41.370203],"type":"Point"}
}