{
  "type": "Feature",
  "properties": {
    "iso:country":"US",
    "sg:address":"47 Evelyn St",
    "sg:city":"Stratford",
    "sg:classifiers":[
        {
            "category":"Professional",
            "subcategory":"Business Services",
            "type":"Services"
        }
    ],
    "sg:phone":"+1   ",
    "sg:postcode":"06615",
    "sg:province":"CT",
    "wof:name":"Pfx Design",
    "wof:placetype":"venue"
},
  "geometry": {"coordinates":[-73.13712,41.184728],"type":"Point"}
}