{
  "type": "Feature",
  "properties": {
    "iso:country":"US",
    "sg:address":"7 Gatewood",
    "sg:city":"Avon",
    "sg:classifiers":[
        {
            "category":"Professional",
            "subcategory":"Business Services",
            "type":"Services"
        }
    ],
    "sg:phone":"+1   ",
    "sg:postcode":"06001",
    "sg:province":"CT",
    "wof:name":"Creative Space",
    "wof:placetype":"venue"
},
  "geometry": {"coordinates":[-72.80844999999999,41.810356],"type":"Point"}
}