{
  "type": "Feature",
  "properties": {
    "iso:country":"US",
    "sg:address":"268 Atlantic St",
    "sg:city":"Stamford",
    "sg:classifiers":[
        {
            "category":"Bars & Pubs",
            "type":"Food & Drink"
        },
        {
            "category":"Coffee & Tea",
            "type":"Food & Drink"
        },
        {
            "category":"Restaurant",
            "type":"Food & Drink"
        }
    ],
    "sg:phone":"+1 203 964 9222",
    "sg:postcode":"06901",
    "sg:province":"CT",
    "sg:tags":[
        "brew",
        "grill",
        "espresso"
    ],
    "wof:name":"Rack & Roll Cafe",
    "wof:placetype":"venue"
},
  "geometry": {"coordinates":[-73.539503,41.051577],"type":"Point"}
}