{
  "type": "Feature",
  "properties": {
    "addr:full":"117 Ash St Willimantic CT 06226",
    "addr:housenumber":"117",
    "addr:postcode":"06226",
    "addr:street":"Ash St Willimantic Ct",
    "iso:country":"US",
    "sg:address":"117 Ash St",
    "sg:city":"Willimantic",
    "sg:classifiers":[
        {
            "category":"Recreation",
            "type":"Entertainment"
        }
    ],
    "sg:phone":"+1   ",
    "sg:postcode":"06226",
    "sg:province":"CT",
    "wof:name":"YMCA of Willimantic",
    "wof:placetype":"venue"
},
  "geometry": {"coordinates":[-72.199713,41.719111],"type":"Point"}
}