{
  "type": "Feature",
  "properties": {
    "addr:full":"533 S Broad St Meriden CT 06450",
    "addr:housenumber":"533",
    "addr:postcode":"06450",
    "addr:street":"S Broad St",
    "iso:country":"US",
    "sg:address":"533 S Broad St",
    "sg:city":"Meriden",
    "sg:classifiers":[
        {
            "category":"Restaurant",
            "type":"Food & Drink"
        }
    ],
    "sg:phone":"+1 203 630 0332",
    "sg:postcode":"06450",
    "sg:province":"CT",
    "sg:tags":[
        "chinese"
    ],
    "wof:name":"Ting Ho Restaurant",
    "wof:placetype":"venue"
},
  "geometry": {"coordinates":[-72.808312,41.508936],"type":"Point"}
}