{
  "type": "Feature",
  "properties": {
    "iso:country":"US",
    "sg:address":"1804 Thomaston Ave",
    "sg:city":"Waterbury",
    "sg:classifiers":[
        {
            "category":"Retail",
            "subcategory":"Auto Repair",
            "type":"Services"
        }
    ],
    "sg:phone":"+1   ",
    "sg:postcode":"06704",
    "sg:province":"CT",
    "sg:tags":[
        "automotive",
        "general"
    ],
    "wof:name":"Orsatti Auto Sales & Repair",
    "wof:placetype":"venue"
},
  "geometry": {"coordinates":[-73.05564200000001,41.593118],"type":"Point"}
}