{
  "type": "Feature",
  "properties": {
    "iso:country":"US",
    "sg:address":"477 Connecticut Blvd",
    "sg:city":"East Hartford",
    "sg:classifiers":[
        {
            "category":"Professional",
            "subcategory":"Employment Agencies",
            "type":"Services"
        }
    ],
    "sg:phone":"+1   ",
    "sg:postcode":"06108",
    "sg:province":"CT",
    "wof:name":"Diversified Staffing Group",
    "wof:placetype":"venue"
},
  "geometry": {"coordinates":[-72.65595500000001,41.769387],"type":"Point"}
}