{
  "type": "Feature",
  "properties": {
    "addr:full":"71 Cogwheel Ln Seymour CT 06483",
    "addr:housenumber":"71",
    "addr:postcode":"06483",
    "addr:street":"Cogwheel Ln",
    "iso:country":"US",
    "sg:address":"71 Cogwheel Ln",
    "sg:city":"Seymour",
    "sg:classifiers":[
        {
            "category":"Manufacturing",
            "subcategory":"Tools & Machinery",
            "type":"Manufacturing & Wholesale Goods"
        }
    ],
    "sg:phone":"+1 203 377 4902",
    "sg:postcode":"06483",
    "sg:province":"CT",
    "wof:name":"J V Precision Machine Co",
    "wof:placetype":"venue"
},
  "geometry": {"coordinates":[-73.050359,41.388594],"type":"Point"}
}