{
  "type": "Feature",
  "properties": {
    "iso:country":"US",
    "sg:address":"646 West Rd",
    "sg:city":"New Canaan",
    "sg:classifiers":[
        {
            "category":"Professional",
            "type":"Services"
        }
    ],
    "sg:phone":"+1   ",
    "sg:postcode":"06840",
    "sg:province":"NY",
    "wof:name":"K&L Stone Services LLC",
    "wof:placetype":"venue"
},
  "geometry": {"coordinates":[-73.524342,41.169982],"type":"Point"}
}