{
  "type": "Feature",
  "properties": {
    "iso:country":"US",
    "sg:address":"97 Sturges Hwy",
    "sg:city":"Westport",
    "sg:classifiers":[
        {
            "category":"Professional",
            "subcategory":"Business Services",
            "type":"Services"
        }
    ],
    "sg:phone":"+1   ",
    "sg:postcode":"06880",
    "sg:province":"CT",
    "wof:name":"Judith K Douglass Co",
    "wof:placetype":"venue"
},
  "geometry": {"coordinates":[-73.31709499999999,41.165569],"type":"Point"}
}