{
  "type": "Feature",
  "properties": {
    "addr:full":"1651 Boston Post Rd Milford CT 06460",
    "addr:housenumber":"1651",
    "addr:postcode":"06460",
    "addr:street":"Boston Post Rd",
    "iso:country":"US",
    "sg:address":"1651 Boston Post Rd",
    "sg:city":"Milford",
    "sg:classifiers":[
        {
            "category":"Restaurant",
            "type":"Food & Drink"
        }
    ],
    "sg:menulink":"http://www.allmenus.com/ct/milford/249232-dakota-steakhouse-of-milford/menu/",
    "sg:phone":"+1 203 882 1234",
    "sg:postcode":"06460",
    "sg:province":"CT",
    "sg:tags":[
        "american",
        "steakhouse"
    ],
    "wof:name":"Dakota Steakhouse Of Milford",
    "wof:placetype":"venue"
},
  "geometry": {"coordinates":[-73.024618,41.247148],"type":"Point"}
}