{
  "type": "Feature",
  "properties": {
    "addr:full":"143 Bridge St Naugatuck CT 06770",
    "addr:housenumber":"143",
    "addr:postcode":"06770",
    "addr:street":"Bridge St Naugatuck Ct",
    "iso:country":"US",
    "sg:address":"143 Bridge St",
    "sg:city":"Naugatuck",
    "sg:classifiers":[
        {
            "category":"Food & Beverages",
            "subcategory":"Liquor & Beverages",
            "type":"Retail Goods"
        }
    ],
    "sg:phone":"+1 203 729 7371",
    "sg:postcode":"06770",
    "sg:province":"CT",
    "wof:name":"D & D Liquors",
    "wof:placetype":"venue"
},
  "geometry": {"coordinates":[-73.049415,41.501795],"type":"Point"}
}