{
  "type": "Feature",
  "properties": {
    "iso:country":"US",
    "sg:address":"321 Indian River Rd",
    "sg:city":"Orange",
    "sg:classifiers":[
        {
            "category":"Building & Trades",
            "subcategory":"Plumbing",
            "type":"Services"
        }
    ],
    "sg:phone":"+1 203 799 2393",
    "sg:postcode":"06477",
    "sg:province":"CT",
    "sg:tags":[
        "sheet",
        "work",
        "metal",
        "contractor"
    ],
    "wof:name":"Industrial Sheet Metal Corp",
    "wof:placetype":"venue"
},
  "geometry": {"coordinates":[-72.99805000000001,41.267183],"type":"Point"}
}