{
  "type": "Feature",
  "properties": {
    "addr:full":"160 W Church St Seymour CT 06483",
    "addr:housenumber":"160",
    "addr:postcode":"06483",
    "addr:street":"W Church St",
    "iso:country":"US",
    "sg:address":"160 W Church St",
    "sg:city":"Seymour",
    "sg:classifiers":[
        {
            "category":"Building & Trades",
            "subcategory":"Electrical",
            "type":"Services"
        }
    ],
    "sg:phone":"+1 203 248 8005",
    "sg:postcode":"06483",
    "sg:province":"CT",
    "sg:tags":[
        "electrical",
        "contractor"
    ],
    "wof:name":"Mad Electric LLC",
    "wof:placetype":"venue"
},
  "geometry": {"coordinates":[-73.08038000000001,41.391806],"type":"Point"}
}