{
  "type": "Feature",
  "properties": {
    "iso:country":"US",
    "sg:address":"8 Revere Rd",
    "sg:city":"Darien",
    "sg:classifiers":[
        {
            "category":"Professional",
            "subcategory":"Computer Services",
            "type":"Services"
        }
    ],
    "sg:phone":"+1   ",
    "sg:postcode":"06820",
    "sg:province":"CT",
    "sg:tags":[
        "related"
    ],
    "wof:name":"Software Consulting Co",
    "wof:placetype":"venue"
},
  "geometry": {"coordinates":[-73.493065,41.079922],"type":"Point"}
}