{
  "type": "Feature",
  "properties": {
    "addr:full":"206 Boston Post Rd Orange CT 06477",
    "addr:housenumber":"206",
    "addr:postcode":"06477",
    "addr:street":"Boston Post Rd",
    "iso:country":"US",
    "sg:address":"206 Boston Post Rd",
    "sg:city":"Orange",
    "sg:classifiers":[
        {
            "category":"Government",
            "subcategory":"Office",
            "type":"Public Place"
        }
    ],
    "sg:phone":"+1 203 795 2999",
    "sg:postcode":"06477",
    "sg:province":"CT",
    "sg:tags":[
        "national",
        "state",
        "guard",
        "security",
        "air"
    ],
    "wof:name":"Orange Air National Guard",
    "wof:placetype":"venue"
},
  "geometry": {"coordinates":[-72.99614200000001,41.271197],"type":"Point"}
}