{
  "type": "Feature",
  "properties": {
    "addr:full":"9 Putnam Green Greenwich CT 06830",
    "addr:housenumber":"9",
    "addr:postcode":"06830",
    "addr:street":"Putnam Green Greenwich Ct",
    "iso:country":"US",
    "sg:address":"9 Putnam Green",
    "sg:city":"Greenwich",
    "sg:classifiers":[
        {
            "category":"Professional",
            "subcategory":"Accounting & Tax Preparation",
            "type":"Services"
        }
    ],
    "sg:phone":"+1   ",
    "sg:postcode":"06830",
    "sg:province":"CT",
    "wof:name":"Badolato Inc",
    "wof:placetype":"venue"
},
  "geometry": {"coordinates":[-73.649407,41.012873],"type":"Point"}
}