{
  "type": "Feature",
  "properties": {
    "addr:full":"228 Old Hartford Rd Colchester CT 06415",
    "addr:housenumber":"228",
    "addr:postcode":"06415",
    "addr:street":"Old Hartford Rd",
    "iso:country":"US",
    "sg:address":"228 Old Hartford Rd",
    "sg:city":"Colchester",
    "sg:classifiers":[
        {
            "category":"Professional",
            "subcategory":"Computer Services",
            "type":"Services"
        }
    ],
    "sg:phone":"+1 860 537 9002",
    "sg:postcode":"06415",
    "sg:province":"CT",
    "sg:tags":[
        "related"
    ],
    "wof:name":"Computer Connection",
    "wof:placetype":"venue"
},
  "geometry": {"coordinates":[-72.360685,41.582931],"type":"Point"}
}