{
  "type": "Feature",
  "properties": {
    "iso:country":"US",
    "sg:address":"31 Willow St",
    "sg:city":"Mystic",
    "sg:classifiers":[
        {
            "category":"Personal",
            "subcategory":"Beauty Salon",
            "type":"Services"
        }
    ],
    "sg:phone":"+1   ",
    "sg:postcode":"06355",
    "sg:province":"CT",
    "sg:tags":[
        "shop"
    ],
    "wof:name":"Lee & Company",
    "wof:placetype":"venue"
},
  "geometry": {"coordinates":[-71.96708099999999,41.353567],"type":"Point"}
}