{
  "type": "Feature",
  "properties": {
    "iso:country":"US",
    "sg:address":"50 Faire Harbour Pl",
    "sg:city":"New London",
    "sg:classifiers":[
        {
            "category":"Health Services",
            "subcategory":"Doctor",
            "type":"Services"
        }
    ],
    "sg:phone":"+1   ",
    "sg:postcode":"06320",
    "sg:province":"CT",
    "sg:tags":[
        "medical"
    ],
    "wof:name":"Joslin Diabetes Center AF",
    "wof:placetype":"venue"
},
  "geometry": {"coordinates":[-72.105789,41.337254],"type":"Point"}
}