{
  "type": "Feature",
  "properties": {
    "addr:full":"1201 Boston Post Rd Milford CT 06460",
    "addr:housenumber":"1201",
    "addr:postcode":"06460",
    "addr:street":"Boston Post Rd",
    "iso:country":"US",
    "sg:address":"1201 Boston Post Rd",
    "sg:city":"Milford",
    "sg:classifiers":[
        {
            "category":"Shopping",
            "subcategory":"Books",
            "type":"Retail Goods"
        }
    ],
    "sg:phone":"+1 203 876 2258",
    "sg:postcode":"06460",
    "sg:province":"CT",
    "sg:tags":[
        "dealer"
    ],
    "wof:name":"Waldenbooks & Waldenkids",
    "wof:placetype":"venue"
},
  "geometry": {"coordinates":[-73.04134999999999,41.234572],"type":"Point"}
}