{
  "type": "Feature",
  "properties": {
    "addr:full":"18 Sunset Ln Ridgefield CT 06877",
    "addr:housenumber":"18",
    "addr:postcode":"06877",
    "addr:street":"Sunset Ln",
    "iso:country":"US",
    "sg:address":"18 Sunset Ln",
    "sg:city":"Ridgefield",
    "sg:classifiers":[
        {
            "category":"Building & Trades",
            "subcategory":"Construction",
            "type":"Services"
        }
    ],
    "sg:phone":"+1 203 438 1069",
    "sg:postcode":"06877",
    "sg:province":"CT",
    "sg:tags":[
        "restoration",
        "cleaning",
        "patio",
        "deck"
    ],
    "wof:name":"Quality Housewashing",
    "wof:placetype":"venue"
},
  "geometry": {"coordinates":[-73.494298,41.285545],"type":"Point"}
}