{
  "type": "Feature",
  "properties": {
    "iso:country":"US",
    "sg:address":"39 Orchard Pk Rd",
    "sg:city":"Madison",
    "sg:classifiers":[
        {
            "category":"Building & Trades",
            "subcategory":"Cleaning & Sanitation",
            "type":"Services"
        }
    ],
    "sg:phone":"+1 203 245 8647",
    "sg:postcode":"06443",
    "sg:province":"CT",
    "sg:tags":[
        "house"
    ],
    "wof:name":"Rowell Cleaning Svc",
    "wof:placetype":"venue"
},
  "geometry": {"coordinates":[-72.626093,41.283345],"type":"Point"}
}