{
  "type": "Feature",
  "properties": {
    "addr:full":"215 Tuthill St West Haven CT 06516",
    "addr:housenumber":"215",
    "addr:postcode":"06516",
    "addr:street":"Tuthill St;Haven",
    "iso:country":"US",
    "sg:address":"215 Tuthill St",
    "sg:city":"West Haven",
    "sg:classifiers":[
        {
            "category":"Food & Beverages",
            "subcategory":"Groceries & Convenience Stores",
            "type":"Retail Goods"
        }
    ],
    "sg:phone":"+1 203 933 1200",
    "sg:postcode":"06516",
    "sg:province":"CT",
    "wof:name":"S-Smart LLC",
    "wof:placetype":"venue"
},
  "geometry": {"coordinates":[-72.97968400000001,41.284124],"type":"Point"}
}