{
  "type": "Feature",
  "properties": {
    "iso:country":"US",
    "sg:address":"76 Newfield Ave",
    "sg:city":"Bridgeport",
    "sg:classifiers":[
        {
            "category":"Building & Trades",
            "subcategory":"Construction",
            "type":"Services"
        }
    ],
    "sg:phone":"+1 203 335 0211",
    "sg:postcode":"06607",
    "sg:province":"CT",
    "sg:tags":[
        "painter"
    ],
    "wof:name":"Mowatt Painting & Home Improv",
    "wof:placetype":"venue"
},
  "geometry": {"coordinates":[-73.170241,41.169811],"type":"Point"}
}