{
  "type": "Feature",
  "properties": {
    "addr:full":"29 Mon-Tar Dr Monroe CT 06468",
    "addr:housenumber":"29",
    "addr:postcode":"06468",
    "addr:street":"Mon-Tar Dr Monroe Ct",
    "iso:country":"US",
    "sg:address":"29 Mon-Tar Dr",
    "sg:city":"Monroe",
    "sg:classifiers":[
        {
            "category":"Professional",
            "subcategory":"Art Services",
            "type":"Services"
        }
    ],
    "sg:phone":"+1   ",
    "sg:postcode":"06468",
    "sg:province":"CT",
    "sg:tags":[
        "commercial",
        "design"
    ],
    "wof:name":"Designs By Dawn",
    "wof:placetype":"venue"
},
  "geometry": {"coordinates":[-73.210779,41.317644],"type":"Point"}
}