{
  "type": "Feature",
  "properties": {
    "iso:country":"US",
    "sg:address":"223 E Main St",
    "sg:city":"Branford",
    "sg:classifiers":[
        {
            "category":"Restaurant",
            "type":"Food & Drink"
        }
    ],
    "sg:menulink":"http://www.allmenus.com/ct/branford/45931-da-carmine-pizzeria/menu/",
    "sg:phone":"+1 203 481 3208",
    "sg:postcode":"06405",
    "sg:province":"CT",
    "sg:tags":[
        "american",
        "pizza"
    ],
    "wof:name":"Da' Carmine Pizzeria",
    "wof:placetype":"venue"
},
  "geometry": {"coordinates":[-72.79891499999999,41.289845],"type":"Point"}
}