{
  "type": "Feature",
  "properties": {
    "addr:full":"20 Essex Ln Woodbury CT 06798",
    "addr:housenumber":"20",
    "addr:postcode":"06798",
    "addr:street":"Essex Ln",
    "iso:country":"US",
    "sg:address":"20 Essex Ln",
    "sg:city":"Woodbury",
    "sg:classifiers":[
        {
            "category":"Professional",
            "subcategory":"Engineering",
            "type":"Services"
        }
    ],
    "sg:phone":"+1   ",
    "sg:postcode":"06798",
    "sg:province":"CT",
    "sg:tags":[
        "scientific"
    ],
    "wof:name":"Sternberg Associates",
    "wof:placetype":"venue"
},
  "geometry": {"coordinates":[-73.248301,41.557867],"type":"Point"}
}