{
  "type": "Feature",
  "properties": {
    "addr:full":"340 Main St Manchester CT 06040",
    "addr:housenumber":"340",
    "addr:postcode":"06040",
    "addr:street":"Main St",
    "iso:country":"US",
    "sg:address":"340 Main St",
    "sg:city":"Manchester",
    "sg:classifiers":[
        {
            "category":"Shopping",
            "subcategory":"Computers & Home Electronics",
            "type":"Retail Goods"
        }
    ],
    "sg:phone":"+1 860 649 8360",
    "sg:postcode":"06040",
    "sg:province":"CT",
    "wof:name":"HI Tech Computer Warehouse",
    "wof:placetype":"venue"
},
  "geometry": {"coordinates":[-72.52248899999999,41.781735],"type":"Point"}
}