{
  "type": "Feature",
  "properties": {
    "addr:full":"196 S Montowese St Branford CT 06405",
    "addr:housenumber":"196",
    "addr:postcode":"06405",
    "addr:street":"S Montowese St",
    "iso:country":"US",
    "sg:address":"196 S Montowese St",
    "sg:city":"Branford",
    "sg:classifiers":[
        {
            "category":"Retail",
            "subcategory":"Auto Repair",
            "type":"Services"
        }
    ],
    "sg:phone":"+1   ",
    "sg:postcode":"06405",
    "sg:province":"CT",
    "sg:tags":[
        "general"
    ],
    "wof:name":"Indian Neck Garage",
    "wof:placetype":"venue"
},
  "geometry": {"coordinates":[-72.80121800000001,41.264212],"type":"Point"}
}