{
  "type": "Feature",
  "properties": {
    "addr:full":"918 Farmington Ave Bristol CT 06010",
    "addr:housenumber":"918",
    "addr:postcode":"06010",
    "addr:street":"Farmington Ave Bristol Ct",
    "iso:country":"US",
    "sg:address":"918 Farmington Ave",
    "sg:city":"Bristol",
    "sg:classifiers":[
        {
            "category":"Insurance",
            "subcategory":"Insurance Agent",
            "type":"Services"
        }
    ],
    "sg:phone":"+1 860 582 6029",
    "sg:postcode":"06010",
    "sg:province":"CT",
    "sg:tags":[
        "agency"
    ],
    "wof:name":"Allstate",
    "wof:placetype":"venue"
},
  "geometry": {"coordinates":[-72.91274799999999,41.694059],"type":"Point"}
}