{
  "type": "Feature",
  "properties": {
    "addr:full":"149 Sturbridge Ln Monroe CT 06468",
    "addr:housenumber":"149",
    "addr:postcode":"06468",
    "addr:street":"Sturbridge Ln",
    "iso:country":"US",
    "sg:address":"149 Sturbridge Ln",
    "sg:city":"Monroe",
    "sg:classifiers":[
        {
            "category":"Shopping",
            "subcategory":"Florist",
            "type":"Retail Goods"
        }
    ],
    "sg:phone":"+1 203 268 7974",
    "sg:postcode":"06468",
    "sg:province":"CT",
    "wof:name":"Cedar Village Flower Shop",
    "wof:placetype":"venue"
},
  "geometry": {"coordinates":[-73.26560600000001,41.295545],"type":"Point"}
}