{
  "type": "Feature",
  "properties": {
    "addr:full":"83 Overlook Rd Glastonbury CT 06033",
    "addr:housenumber":"83",
    "addr:postcode":"06033",
    "addr:street":"Overlook Rd",
    "iso:country":"US",
    "sg:address":"83 Overlook Rd",
    "sg:city":"Glastonbury",
    "sg:classifiers":[
        {
            "category":"Professional",
            "subcategory":"Computer Services",
            "type":"Services"
        }
    ],
    "sg:phone":"+1   ",
    "sg:postcode":"06033",
    "sg:province":"CT",
    "sg:tags":[
        "integration"
    ],
    "wof:name":"From Ground Up",
    "wof:placetype":"venue"
},
  "geometry": {"coordinates":[-72.595842,41.682534],"type":"Point"}
}