{
  "type": "Feature",
  "properties": {
    "addr:full":"3 Pembroke Rd Danbury CT 06811",
    "addr:housenumber":"3",
    "addr:postcode":"06811",
    "addr:street":"Pembroke Rd",
    "iso:country":"US",
    "sg:address":"3 Pembroke Rd",
    "sg:city":"Danbury",
    "sg:classifiers":[
        {
            "category":"Personal",
            "subcategory":"Beauty Salon",
            "type":"Services"
        }
    ],
    "sg:phone":"+1   ",
    "sg:postcode":"06811",
    "sg:province":"CT",
    "sg:tags":[
        "shop"
    ],
    "wof:name":"Frans Hair Design",
    "wof:placetype":"venue"
},
  "geometry": {"coordinates":[-73.47127999999999,41.428699],"type":"Point"}
}