{
  "type": "Feature",
  "properties": {
    "iso:country":"US",
    "sg:address":"266 Dixwell Ave",
    "sg:city":"New Haven",
    "sg:classifiers":[
        {
            "category":"Professional",
            "type":"Services"
        }
    ],
    "sg:phone":"+1 203 786 5141",
    "sg:postcode":"06511",
    "sg:province":"CT",
    "wof:name":"Gmu House",
    "wof:placetype":"venue"
},
  "geometry": {"coordinates":[-72.934296,41.320222],"type":"Point"}
}