{
  "type": "Feature",
  "properties": {
    "addr:full":"46 Parsonage Rd Greenwich CT 06830",
    "addr:housenumber":"46",
    "addr:postcode":"06830",
    "addr:street":"Parsonage Rd",
    "iso:country":"US",
    "sg:address":"46 Parsonage Rd",
    "sg:city":"Greenwich",
    "sg:classifiers":[
        {
            "category":"Real Estate",
            "subcategory":"Architect",
            "type":"Services"
        }
    ],
    "sg:phone":"+1 203 661 6395",
    "sg:postcode":"06830",
    "sg:province":"CT",
    "wof:name":"William N Bonham",
    "wof:placetype":"venue"
},
  "geometry": {"coordinates":[-73.622197,41.055101],"type":"Point"}
}