{
  "type": "Feature",
  "properties": {
    "addr:full":"5065 Main St Trumbull CT 06611",
    "addr:housenumber":"5065",
    "addr:postcode":"06611",
    "addr:street":"Main St",
    "iso:country":"US",
    "sg:address":"5065 Main St",
    "sg:city":"Trumbull",
    "sg:classifiers":[
        {
            "category":"Shopping",
            "subcategory":"Hobbies, Toys, & Games",
            "type":"Retail Goods"
        }
    ],
    "sg:phone":"+1 203 372 4788",
    "sg:postcode":"06611",
    "sg:province":"CT",
    "sg:website":"www.kbtoys.com",
    "wof:name":"K-B Toys",
    "wof:placetype":"venue"
},
  "geometry": {"coordinates":[-73.220235,41.230382],"type":"Point"}
}