{
  "type": "Feature",
  "properties": {
    "iso:country":"US",
    "sg:address":"534 Boston Post Rd",
    "sg:city":"Guilford",
    "sg:classifiers":[
        {
            "category":"Retail",
            "subcategory":"Animal Services",
            "type":"Services"
        }
    ],
    "sg:phone":"+1 203 453 6259",
    "sg:postcode":"06437",
    "sg:province":"CT",
    "wof:name":"A Dogs Day Out",
    "wof:placetype":"venue"
},
  "geometry": {"coordinates":[-72.670196,41.288706],"type":"Point"}
}