{
  "type": "Feature",
  "properties": {
    "addr:full":"246 Church St New Haven CT 06510",
    "addr:housenumber":"246",
    "addr:postcode":"06510",
    "addr:street":"Church St",
    "iso:country":"US",
    "sg:address":"246 Church St",
    "sg:city":"New Haven",
    "sg:classifiers":[
        {
            "category":"Education",
            "subcategory":"College",
            "type":"Public Place"
        }
    ],
    "sg:phone":"+1   ",
    "sg:postcode":"06510",
    "sg:province":"CT",
    "wof:name":"Yale University Dining Hall",
    "wof:placetype":"venue"
},
  "geometry": {"coordinates":[-72.92281,41.31009],"type":"Point"}
}