{
  "type": "Feature",
  "properties": {
    "iso:country":"US",
    "sg:address":"6 Executive Dr",
    "sg:city":"Farmington",
    "sg:classifiers":[
        {
            "category":"Real Estate",
            "subcategory":"Real Estate Operator",
            "type":"Services"
        }
    ],
    "sg:phone":"+1 860 674 5620",
    "sg:postcode":"06032",
    "sg:province":"CT",
    "sg:tags":[
        "a",
        "commercial",
        "manager",
        "property",
        "renovation",
        "con"
    ],
    "wof:name":"Metro Realty Group Ltd",
    "wof:placetype":"venue"
},
  "geometry": {"coordinates":[-72.85590500000001,41.699824],"type":"Point"}
}