{
  "type": "Feature",
  "properties": {
    "iso:country":"US",
    "sg:address":"62 Stanton Dr",
    "sg:city":"Stamford",
    "sg:classifiers":[
        {
            "category":"Building & Trades",
            "subcategory":"Construction",
            "type":"Services"
        }
    ],
    "sg:phone":"+1 203 961 1114",
    "sg:postcode":"06902",
    "sg:province":"CT",
    "sg:tags":[
        "masonry",
        "contractor"
    ],
    "wof:name":"Mauro Fidaleo Construction",
    "wof:placetype":"venue"
},
  "geometry": {"coordinates":[-73.560624,41.080251],"type":"Point"}
}