{
  "type": "Feature",
  "properties": {
    "addr:full":"186 Black Rock Tpke Redding CT 06896",
    "addr:housenumber":"186",
    "addr:postcode":"06896",
    "addr:street":"Black Rock Tpke",
    "iso:country":"US",
    "sg:address":"186 Black Rock Tpke",
    "sg:city":"Redding",
    "sg:classifiers":[
        {
            "category":"Government",
            "subcategory":"Fire Station",
            "type":"Public Place"
        }
    ],
    "sg:phone":"+1 203 938 2520",
    "sg:postcode":"06896",
    "sg:province":"CT",
    "sg:tags":[
        "protection"
    ],
    "wof:name":"Redding Fire Dept",
    "wof:placetype":"venue"
},
  "geometry": {"coordinates":[-73.346802,41.306339],"type":"Point"}
}