{
  "type": "Feature",
  "properties": {
    "iso:country":"US",
    "sg:address":"8 Roundhill Rd",
    "sg:city":"Granby",
    "sg:classifiers":[
        {
            "category":"Professional",
            "subcategory":"Computer Services",
            "type":"Services"
        }
    ],
    "sg:phone":"+1   ",
    "sg:postcode":"06035",
    "sg:province":"CT",
    "sg:tags":[
        "related"
    ],
    "wof:name":"PC Jones Consulting",
    "wof:placetype":"venue"
},
  "geometry": {"coordinates":[-72.779792,41.963489],"type":"Point"}
}