{
  "type": "Feature",
  "properties": {
    "addr:full":"12 Monroe St Norwalk CT 06854",
    "addr:housenumber":"12",
    "addr:postcode":"06854",
    "addr:street":"Monroe St",
    "iso:country":"US",
    "sg:address":"12 Monroe St",
    "sg:city":"Norwalk",
    "sg:classifiers":[
        {
            "category":"Personal",
            "subcategory":"Beauty Salon",
            "type":"Services"
        }
    ],
    "sg:phone":"+1   ",
    "sg:postcode":"06854",
    "sg:province":"CT",
    "sg:tags":[
        "shop"
    ],
    "wof:name":"Klassy Kutts",
    "wof:placetype":"venue"
},
  "geometry": {"coordinates":[-73.41949099999999,41.09652],"type":"Point"}
}