{
  "type": "Feature",
  "properties": {
    "addr:full":"78 Willington Ave Stafford Springs CT 06076",
    "addr:housenumber":"78",
    "addr:postcode":"06076",
    "addr:street":"Willington Ave",
    "iso:country":"US",
    "sg:address":"78 Willington Ave",
    "sg:city":"Stafford Springs",
    "sg:classifiers":[
        {
            "category":"Building & Trades",
            "subcategory":"Electrical",
            "type":"Services"
        }
    ],
    "sg:phone":"+1 860 684 3102",
    "sg:postcode":"06076",
    "sg:province":"CT",
    "sg:tags":[
        "electrical",
        "contractor"
    ],
    "wof:name":"Langworthy Electrical Contract",
    "wof:placetype":"venue"
},
  "geometry": {"coordinates":[-72.300933,41.946868],"type":"Point"}
}