{
  "type": "Feature",
  "properties": {
    "addr:full":"27 Pell Mell Dr Bethel CT 06801",
    "addr:housenumber":"27",
    "addr:postcode":"06801",
    "addr:street":"Pell Mell Dr Bethel Ct",
    "iso:country":"US",
    "sg:address":"27 Pell Mell Dr",
    "sg:city":"Bethel",
    "sg:classifiers":[
        {
            "category":"Social Services",
            "subcategory":"Child Care",
            "type":"Services"
        }
    ],
    "sg:phone":"+1   ",
    "sg:postcode":"06801",
    "sg:province":"CT",
    "sg:tags":[
        "day"
    ],
    "wof:name":"Genevieve Lanuto",
    "wof:placetype":"venue"
},
  "geometry": {"coordinates":[-73.38468399999999,41.38356],"type":"Point"}
}