{
  "type": "Feature",
  "properties": {
    "iso:country":"US",
    "sg:address":"661 Gold Star Hwy",
    "sg:city":"Groton",
    "sg:phone":"+1 860 446 1378",
    "sg:postcode":"06340",
    "sg:province":"CT",
    "sg:tags":[
        "product",
        "petroleum"
    ],
    "wof:name":"Aviation Lubricants",
    "wof:placetype":"venue"
},
  "geometry": {"coordinates":[-72.04667600000001,41.374248],"type":"Point"}
}