{
  "type": "Feature",
  "properties": {
    "iso:country":"US",
    "sg:address":"18 Lourdes Ct",
    "sg:city":"Meriden",
    "sg:classifiers":[
        {
            "category":"Social Services",
            "type":"Services"
        }
    ],
    "sg:phone":"+1 203 634 7617",
    "sg:postcode":"06451",
    "sg:province":"CT",
    "sg:tags":[
        "organization",
        "welfare"
    ],
    "wof:name":"Headstart",
    "wof:placetype":"venue"
},
  "geometry": {"coordinates":[-72.81372500000001,41.545979],"type":"Point"}
}