{
  "type": "Feature",
  "properties": {
    "addr:full":"1457 Fairfield Ave Bridgeport CT 06605",
    "addr:housenumber":"1457",
    "addr:postcode":"06605",
    "addr:street":"Fairfield Ave",
    "iso:country":"US",
    "sg:address":"1457 Fairfield Ave",
    "sg:city":"Bridgeport",
    "sg:classifiers":[
        {
            "category":"Food & Beverages",
            "subcategory":"Groceries & Convenience Stores",
            "type":"Retail Goods"
        }
    ],
    "sg:phone":"+1 203 330 1094",
    "sg:postcode":"06605",
    "sg:province":"CT",
    "sg:tags":[
        "grocer"
    ],
    "wof:name":"Compare Foods",
    "wof:placetype":"venue"
},
  "geometry": {"coordinates":[-73.211437,41.171967],"type":"Point"}
}