{
  "type": "Feature",
  "properties": {
    "iso:country":"US",
    "sg:address":"446 Main St",
    "sg:city":"Monroe",
    "sg:classifiers":[
        {
            "category":"Education",
            "subcategory":"Special Training",
            "type":"Public Place"
        }
    ],
    "sg:phone":"+1 203 268 6040",
    "sg:postcode":"06468",
    "sg:province":"CT",
    "sg:tags":[
        "instruction",
        "driving"
    ],
    "wof:name":"Gary Knepler Driving School",
    "wof:placetype":"venue"
},
  "geometry": {"coordinates":[-73.267078,41.325822],"type":"Point"}
}