{
  "type": "Feature",
  "properties": {
    "iso:country":"US",
    "sg:address":"9 Meadowpark Ave W",
    "sg:city":"Stamford",
    "sg:classifiers":[
        {
            "category":"Building & Trades",
            "subcategory":"Construction",
            "type":"Services"
        }
    ],
    "sg:phone":"+1 203 329 8533",
    "sg:postcode":"06905",
    "sg:province":"CT",
    "sg:tags":[
        "carpenter"
    ],
    "wof:name":"Wilson Carpentry Svc",
    "wof:placetype":"venue"
},
  "geometry": {"coordinates":[-73.554902,41.091042],"type":"Point"}
}