{
  "type": "Feature",
  "properties": {
    "addr:full":"632 Cromwell Ave Rocky Hill CT 06067",
    "addr:housenumber":"632",
    "addr:postcode":"06067",
    "addr:street":"Cromwell Ave;Hill Ct",
    "iso:country":"US",
    "sg:address":"632 Cromwell Ave",
    "sg:city":"Rocky Hill",
    "sg:classifiers":[
        {
            "category":"Shopping",
            "subcategory":"Florist",
            "type":"Retail Goods"
        }
    ],
    "sg:phone":"+1 860 257 8805",
    "sg:postcode":"06067",
    "sg:province":"CT",
    "wof:name":"Bonettis Floral Studio",
    "wof:placetype":"venue"
},
  "geometry": {"coordinates":[-72.67988800000001,41.654251],"type":"Point"}
}