{
  "type": "Feature",
  "properties": {
    "iso:country":"US",
    "sg:address":"311 Main St",
    "sg:city":"Terryville",
    "sg:classifiers":[
        {
            "category":"Restaurant",
            "type":"Food & Drink"
        }
    ],
    "sg:phone":"+1 860 583 2775",
    "sg:postcode":"06786",
    "sg:province":"CT",
    "sg:tags":[
        "eating"
    ],
    "wof:name":"Josephines Apizza",
    "wof:placetype":"venue"
},
  "geometry": {"coordinates":[-73.01966299999999,41.679804],"type":"Point"}
}