{
  "type": "Feature",
  "properties": {
    "addr:full":"70 Danbury Rd Wilton CT 06897",
    "addr:housenumber":"70",
    "addr:postcode":"06897",
    "addr:street":"Danbury Rd Wilton Ct",
    "iso:country":"US",
    "sg:address":"70 Danbury Rd",
    "sg:city":"Wilton",
    "sg:classifiers":[
        {
            "category":"Insurance",
            "subcategory":"Insurance Agent",
            "type":"Services"
        }
    ],
    "sg:phone":"+1 203 762 0817",
    "sg:postcode":"06897",
    "sg:province":"CT",
    "sg:tags":[
        "agency"
    ],
    "wof:name":"Allstate",
    "wof:placetype":"venue"
},
  "geometry": {"coordinates":[-73.41818499999999,41.164733],"type":"Point"}
}