{
  "type": "Feature",
  "properties": {
    "addr:full":"317 Long Hill Rd Groton CT 06340",
    "addr:housenumber":"317",
    "addr:postcode":"06340",
    "addr:street":"Long Hill Rd Groton Ct",
    "iso:country":"US",
    "sg:address":"317 Long Hill Rd",
    "sg:city":"Groton",
    "sg:classifiers":[
        {
            "category":"Personal",
            "subcategory":"Beauty Salon",
            "type":"Services"
        }
    ],
    "sg:phone":"+1   ",
    "sg:postcode":"06340",
    "sg:province":"CT",
    "sg:tags":[
        "shop"
    ],
    "wof:name":"Hairs Place LLC",
    "wof:placetype":"venue"
},
  "geometry": {"coordinates":[-72.06258200000001,41.358167],"type":"Point"}
}