{
  "type": "Feature",
  "properties": {
    "iso:country":"US",
    "sg:address":"77 Danbury Rd",
    "sg:city":"Ridgefield",
    "sg:classifiers":[
        {
            "category":"Professional",
            "subcategory":"Management & Consulting",
            "type":"Services"
        }
    ],
    "sg:phone":"+1 203 438 0615",
    "sg:postcode":"06877",
    "sg:province":"CT",
    "sg:tags":[
        "consultant",
        "business"
    ],
    "sg:website":"www.relocationconsult.com",
    "wof:name":"Relocation Consultants",
    "wof:placetype":"venue"
},
  "geometry": {"coordinates":[-73.494568,41.291229],"type":"Point"}
}