{
  "type": "Feature",
  "properties": {
    "addr:full":"357 Main St Durham CT 06422",
    "addr:housenumber":"357",
    "addr:postcode":"06422",
    "addr:street":"Main St",
    "iso:country":"US",
    "sg:address":"357 Main St",
    "sg:city":"Durham",
    "sg:classifiers":[
        {
            "category":"Banks & Credit Unions",
            "subcategory":"Bank",
            "type":"Services"
        }
    ],
    "sg:phone":"+1 860 349 7130",
    "sg:postcode":"06422",
    "sg:province":"CT",
    "sg:tags":[
        "savings",
        "institution"
    ],
    "wof:name":"Liberty Bank",
    "wof:placetype":"venue"
},
  "geometry": {"coordinates":[-72.68190300000001,41.484926],"type":"Point"}
}