{
  "type": "Feature",
  "properties": {
    "iso:country":"US",
    "sg:address":"33 Rte 37 S",
    "sg:city":"Sherman",
    "sg:classifiers":[
        {
            "category":"Farming",
            "subcategory":"Farm",
            "type":"Manufacturing & Wholesale Goods"
        }
    ],
    "sg:phone":"+1 860 355 8155",
    "sg:postcode":"06784",
    "sg:province":"CT",
    "sg:tags":[
        "crop",
        "general"
    ],
    "wof:name":"Jmc Woodwinds Farm LLC",
    "wof:placetype":"venue"
},
  "geometry": {"coordinates":[-73.50084099999999,41.572237],"type":"Point"}
}