{
  "type": "Feature",
  "properties": {
    "iso:country":"US",
    "sg:address":"355 W Mountain Rd",
    "sg:city":"West Simsbury",
    "sg:classifiers":[
        {
            "category":"Professional",
            "subcategory":"Management & Consulting",
            "type":"Services"
        }
    ],
    "sg:phone":"+1   ",
    "sg:postcode":"06092",
    "sg:province":"CT",
    "wof:name":"Anduril Assoc",
    "wof:placetype":"venue"
},
  "geometry": {"coordinates":[-72.867225,41.828927],"type":"Point"}
}