{
  "type": "Feature",
  "properties": {
    "iso:country":"US",
    "sg:address":"108 Okenuck Way",
    "sg:city":"Shelton",
    "sg:classifiers":[
        {
            "category":"Building & Trades",
            "subcategory":"Plumbing",
            "type":"Services"
        }
    ],
    "sg:phone":"+1 203 925 8725",
    "sg:postcode":"06484",
    "sg:province":"CT",
    "sg:tags":[
        "plumbing",
        "contractor"
    ],
    "wof:name":"R L Batterson Plumbing Svc",
    "wof:placetype":"venue"
},
  "geometry": {"coordinates":[-73.151278,41.36511],"type":"Point"}
}