{
  "type": "Feature",
  "properties": {
    "addr:full":"12 Davenport St Stamford CT 06902",
    "addr:housenumber":"12",
    "addr:postcode":"06902",
    "addr:street":"Davenport St",
    "iso:country":"US",
    "sg:address":"12 Davenport St",
    "sg:city":"Stamford",
    "sg:classifiers":[
        {
            "category":"Retail",
            "subcategory":"Auto Repair",
            "type":"Services"
        }
    ],
    "sg:phone":"+1 203 327 5120",
    "sg:postcode":"06902",
    "sg:province":"CT",
    "sg:tags":[
        "repairing",
        "automobile",
        "general"
    ],
    "wof:name":"Nelson Automotive & Machine Sp",
    "wof:placetype":"venue"
},
  "geometry": {"coordinates":[-73.546712,41.04025],"type":"Point"}
}