{
  "type": "Feature",
  "properties": {
    "addr:full":"95 Main St Meriden CT 06451",
    "addr:housenumber":"95",
    "addr:postcode":"06451",
    "addr:street":"Main St",
    "iso:country":"US",
    "sg:address":"95 Main St",
    "sg:city":"Meriden",
    "sg:classifiers":[
        {
            "category":"Retail",
            "subcategory":"Animal Services",
            "type":"Services"
        }
    ],
    "sg:phone":"+1 203 886 7074",
    "sg:postcode":"06451",
    "sg:province":"CT",
    "sg:tags":[
        "training",
        "dog"
    ],
    "wof:name":"Canine Training Ctr",
    "wof:placetype":"venue"
},
  "geometry": {"coordinates":[-72.828014,41.518729],"type":"Point"}
}