{
  "type": "Feature",
  "properties": {
    "addr:full":"11 New Rd Ridgefield CT 06877",
    "addr:housenumber":"11",
    "addr:postcode":"06877",
    "addr:street":"New Rd",
    "iso:country":"US",
    "sg:address":"11 New Rd",
    "sg:city":"Ridgefield",
    "sg:classifiers":[
        {
            "category":"Social Services",
            "type":"Services"
        }
    ],
    "sg:phone":"+1 203 438 2111",
    "sg:postcode":"06877",
    "sg:province":"CT",
    "sg:tags":[
        "youth",
        "organization",
        "center"
    ],
    "wof:name":"Ridgefield Little League",
    "wof:placetype":"venue"
},
  "geometry": {"coordinates":[-73.470123,41.296297],"type":"Point"}
}