{
  "type": "Feature",
  "properties": {
    "iso:country":"US",
    "sg:address":"8 Station St",
    "sg:city":"Simsbury",
    "sg:classifiers":[
        {
            "category":"Professional",
            "subcategory":"Lawyer & Legal Services",
            "type":"Services"
        }
    ],
    "sg:phone":"+1   ",
    "sg:postcode":"06070",
    "sg:province":"CT",
    "wof:name":"Gutman Jewel A",
    "wof:placetype":"venue"
},
  "geometry": {"coordinates":[-72.800399,41.874645],"type":"Point"}
}