{
  "type": "Feature",
  "properties": {
    "iso:country":"US",
    "sg:address":"91 Dora St",
    "sg:city":"Stamford",
    "sg:classifiers":[
        {
            "category":"Real Estate",
            "subcategory":"Real Estate Services",
            "type":"Services"
        }
    ],
    "sg:phone":"+1 203 348 6994",
    "sg:postcode":"06902",
    "sg:province":"CT",
    "sg:tags":[
        "company",
        "title"
    ],
    "wof:name":"Pro Search",
    "wof:placetype":"venue"
},
  "geometry": {"coordinates":[-73.50807399999999,41.053693],"type":"Point"}
}