{
  "type": "Feature",
  "properties": {
    "addr:full":"110 Newell St Southington CT 06489",
    "addr:housenumber":"110",
    "addr:postcode":"06489",
    "addr:street":"Newell St",
    "iso:country":"US",
    "sg:address":"110 Newell St",
    "sg:city":"Southington",
    "sg:classifiers":[
        {
            "category":"Building & Trades",
            "subcategory":"Electrical",
            "type":"Services"
        }
    ],
    "sg:phone":"+1 860 426 9063",
    "sg:postcode":"06489",
    "sg:province":"CT",
    "sg:tags":[
        "electrical",
        "contractor"
    ],
    "wof:name":"Griffin Electrical Contractors",
    "wof:placetype":"venue"
},
  "geometry": {"coordinates":[-72.875962,41.641373],"type":"Point"}
}