{
  "type": "Feature",
  "properties": {
    "addr:full":"82 Main St East Hampton CT 06424",
    "addr:housenumber":"82",
    "addr:postcode":"06424",
    "addr:street":"Main St East Hampton Ct",
    "iso:country":"US",
    "sg:address":"82 Main St",
    "sg:city":"East Hampton",
    "sg:classifiers":[
        {
            "category":"Professional",
            "subcategory":"Engineering",
            "type":"Services"
        }
    ],
    "sg:phone":"+1   ",
    "sg:postcode":"06424",
    "sg:province":"CT",
    "wof:name":"Yankee Gems & Jewelry",
    "wof:placetype":"venue"
},
  "geometry": {"coordinates":[-72.502416,41.575472],"type":"Point"}
}