{
  "type": "Feature",
  "properties": {
    "addr:full":"44 Old State Rd New Milford CT 06776",
    "addr:housenumber":"44",
    "addr:postcode":"06776",
    "addr:street":"Old State Rd",
    "iso:country":"US",
    "sg:address":"44 Old State Rd",
    "sg:city":"New Milford",
    "sg:classifiers":[
        {
            "category":"Professional",
            "type":"Services"
        }
    ],
    "sg:phone":"+1 860 350 6102",
    "sg:postcode":"06776",
    "sg:province":"CT",
    "wof:name":"Joy Scatter",
    "wof:placetype":"venue"
},
  "geometry": {"coordinates":[-73.422781,41.537918],"type":"Point"}
}