{
  "type": "Feature",
  "properties": {
    "iso:country":"US",
    "sg:address":"11 Main St",
    "sg:city":"Westport",
    "sg:classifiers":[
        {
            "category":"Professional",
            "subcategory":"Business Services",
            "type":"Services"
        }
    ],
    "sg:phone":"+1 203 226 0934",
    "sg:postcode":"06880",
    "sg:province":"CT",
    "sg:tags":[
        "interior",
        "consultant",
        "design",
        "decorator"
    ],
    "wof:name":"Cole Harris Assoc",
    "wof:placetype":"venue"
},
  "geometry": {"coordinates":[-73.361921,41.142919],"type":"Point"}
}