{
  "type": "Feature",
  "properties": {
    "iso:country":"US",
    "sg:address":"10 Glen Rd",
    "sg:city":"Sandy Hook",
    "sg:classifiers":[
        {
            "category":"Organizations",
            "subcategory":"Non-profit Organization",
            "type":"Services"
        }
    ],
    "sg:phone":"+1 203 270 4335",
    "sg:postcode":"06482",
    "sg:province":"CT",
    "wof:name":"Youth Services In Newtown",
    "wof:placetype":"venue"
},
  "geometry": {"coordinates":[-73.28192900000001,41.42145],"type":"Point"}
}