{
  "type": "Feature",
  "properties": {
    "iso:country":"US",
    "sg:address":"21 Centennial Dr",
    "sg:city":"Danbury",
    "sg:classifiers":[
        {
            "category":"Professional",
            "type":"Services"
        }
    ],
    "sg:phone":"+1   ",
    "sg:postcode":"06811",
    "sg:province":"CT",
    "wof:name":"Kozlowksi & Tancredi",
    "wof:placetype":"venue"
},
  "geometry": {"coordinates":[-73.50447699999999,41.414815],"type":"Point"}
}