{
  "type": "Feature",
  "properties": {
    "iso:country":"US",
    "sg:address":"963 N Colony St",
    "sg:city":"Meriden",
    "sg:classifiers":[
        {
            "category":"Manufacturing",
            "subcategory":"Motor Vehicles & Parts",
            "type":"Manufacturing & Wholesale Goods"
        }
    ],
    "sg:phone":"+1 203 237 2619",
    "sg:postcode":"06450",
    "sg:province":"CT",
    "sg:tags":[
        "automobile",
        "wrecker"
    ],
    "wof:name":"North End Auto Parts Inc",
    "wof:placetype":"venue"
},
  "geometry": {"coordinates":[-72.78511399999999,41.560665],"type":"Point"}
}