{
  "type": "Feature",
  "properties": {
    "addr:full":"358 Gaylord Dr Waterbury CT 06708",
    "addr:housenumber":"358",
    "addr:postcode":"06708",
    "addr:street":"Gaylord Dr",
    "iso:country":"US",
    "sg:address":"358 Gaylord Dr",
    "sg:city":"Waterbury",
    "sg:classifiers":[
        {
            "category":"Building & Trades",
            "subcategory":"Landscaping Services",
            "type":"Services"
        }
    ],
    "sg:phone":"+1 203 574 4778",
    "sg:postcode":"06708",
    "sg:province":"CT",
    "sg:tags":[
        "tree"
    ],
    "wof:name":"Charter Oak Tree Svc",
    "wof:placetype":"venue"
},
  "geometry": {"coordinates":[-73.070982,41.567855],"type":"Point"}
}