{
  "type": "Feature",
  "properties": {
    "addr:full":"358 Washington Ave Waterbury CT 06708",
    "addr:housenumber":"358",
    "addr:postcode":"06708",
    "addr:street":"Washington Ave",
    "iso:country":"US",
    "sg:address":"358 Washington Ave",
    "sg:city":"Waterbury",
    "sg:classifiers":[
        {
            "category":"Organizations",
            "subcategory":"Religious Organization",
            "type":"Services"
        }
    ],
    "sg:phone":"+1 203 597 8992",
    "sg:postcode":"06708",
    "sg:province":"CT",
    "sg:tags":[
        "church"
    ],
    "wof:name":"Iglesia Dios Pentecostal Mi",
    "wof:placetype":"venue"
},
  "geometry": {"coordinates":[-73.04682200000001,41.543977],"type":"Point"}
}