{
  "type": "Feature",
  "properties": {
    "addr:full":"900 Straits Tpke Middlebury CT 06762",
    "addr:housenumber":"900",
    "addr:postcode":"06762",
    "addr:street":"Straits Tpke",
    "iso:country":"US",
    "sg:address":"900 Straits Tpke",
    "sg:city":"Middlebury",
    "sg:classifiers":[
        {
            "category":"Real Estate",
            "subcategory":"Real Estate Agent",
            "type":"Services"
        }
    ],
    "sg:phone":"+1 203 598 7421",
    "sg:postcode":"06762",
    "sg:province":"CT",
    "wof:name":"Ravels William",
    "wof:placetype":"venue"
},
  "geometry": {"coordinates":[-73.08689699999999,41.535824],"type":"Point"}
}