{
  "type": "Feature",
  "properties": {
    "iso:country":"US",
    "sg:address":"167 W Granby Rd",
    "sg:city":"Granby",
    "sg:classifiers":[
        {
            "category":"Travel",
            "subcategory":"Hotels & Motels",
            "type":"Entertainment"
        }
    ],
    "sg:phone":"+1   ",
    "sg:postcode":"06035",
    "sg:province":"CT",
    "sg:tags":[
        "operation"
    ],
    "wof:name":"Interlaken Inn",
    "wof:placetype":"venue"
},
  "geometry": {"coordinates":[-72.81327,41.953386],"type":"Point"}
}