{
  "type": "Feature",
  "properties": {
    "iso:country":"US",
    "sg:address":"1437 Hanover Ave",
    "sg:city":"Meriden",
    "sg:classifiers":[
        {
            "category":"Freight",
            "type":"Transportation"
        },
        {
            "category":"Utilities",
            "subcategory":"Refuse",
            "type":"Services"
        }
    ],
    "sg:phone":"+1 203 237 6007",
    "sg:postcode":"06451",
    "sg:province":"CT",
    "sg:tags":[
        "operator",
        "local",
        "garbage",
        "collection",
        "trucking"
    ],
    "wof:name":"Artic Trucking Services Inc",
    "wof:placetype":"venue"
},
  "geometry": {"coordinates":[-72.819948,41.511653],"type":"Point"}
}