{
  "type": "Feature",
  "properties": {
    "iso:country":"US",
    "sg:address":"655 Reservoir Ave",
    "sg:city":"Bridgeport",
    "sg:classifiers":[
        {
            "category":"Professional",
            "subcategory":"Engineering",
            "type":"Services"
        }
    ],
    "sg:phone":"+1   ",
    "sg:postcode":"06606",
    "sg:province":"CT",
    "wof:name":"Hofbauer & Assoc",
    "wof:placetype":"venue"
},
  "geometry": {"coordinates":[-73.19178599999999,41.209715],"type":"Point"}
}