{
  "type": "Feature",
  "properties": {
    "addr:full":"175 W Main St Avon CT 06001",
    "addr:housenumber":"175",
    "addr:postcode":"06001",
    "addr:street":"W Main St",
    "iso:country":"US",
    "sg:address":"175 W Main St",
    "sg:city":"Avon",
    "sg:classifiers":[
        {
            "category":"Shopping",
            "subcategory":"Clothing, Apparel, & Fashions",
            "type":"Retail Goods"
        }
    ],
    "sg:phone":"+1 860 589 2224",
    "sg:postcode":"06001",
    "sg:province":"CT",
    "wof:name":"Maynards Bridal Corner Inc",
    "wof:placetype":"venue"
},
  "geometry": {"coordinates":[-72.847172,41.811558],"type":"Point"}
}