{
  "type": "Feature",
  "properties": {
    "addr:full":"157 Hillside Ave Waterbury CT 06710",
    "addr:housenumber":"157",
    "addr:postcode":"06710",
    "addr:street":"Hillside Ave",
    "iso:country":"US",
    "sg:address":"157 Hillside Ave",
    "sg:city":"Waterbury",
    "sg:classifiers":[
        {
            "category":"Health Services",
            "subcategory":"Nursing And Care Facility",
            "type":"Services"
        }
    ],
    "sg:phone":"+1 203 574 2317",
    "sg:postcode":"06710",
    "sg:province":"CT",
    "sg:tags":[
        "home",
        "rest"
    ],
    "wof:name":"Carriage Manor LLC",
    "wof:placetype":"venue"
},
  "geometry": {"coordinates":[-73.046375,41.56244],"type":"Point"}
}