{
  "type": "Feature",
  "properties": {
    "addr:full":"22 Addison St Hartford CT 06120",
    "addr:housenumber":"22",
    "addr:postcode":"06120",
    "addr:street":"Addison St",
    "iso:country":"US",
    "sg:address":"22 Addison St",
    "sg:city":"Hartford",
    "sg:classifiers":[
        {
            "category":"Social Services",
            "subcategory":"Child Care",
            "type":"Services"
        }
    ],
    "sg:phone":"+1   ",
    "sg:postcode":"06120",
    "sg:province":"CT",
    "sg:tags":[
        "day"
    ],
    "wof:name":"Blair Childcare",
    "wof:placetype":"venue"
},
  "geometry": {"coordinates":[-72.66398,41.797524],"type":"Point"}
}