{
  "type": "Feature",
  "properties": {
    "iso:country":"US",
    "sg:address":"2440 Whitney Ave",
    "sg:city":"Hamden",
    "sg:classifiers":[
        {
            "category":"Health Services",
            "subcategory":"Doctor",
            "type":"Services"
        }
    ],
    "sg:phone":"+1   ",
    "sg:postcode":"06518",
    "sg:province":"CT",
    "sg:tags":[
        "medical"
    ],
    "wof:name":"Vahjen Glen A MD",
    "wof:placetype":"venue"
},
  "geometry": {"coordinates":[-72.901535,41.384599],"type":"Point"}
}