{
  "type": "Feature",
  "properties": {
    "iso:country":"US",
    "sg:address":"110 Valley Cir",
    "sg:city":"Bridgeport",
    "sg:classifiers":[
        {
            "category":"Organizations",
            "subcategory":"Membership Organization",
            "type":"Services"
        }
    ],
    "sg:phone":"+1   ",
    "sg:postcode":"06606",
    "sg:province":"CT",
    "wof:name":"Chapter 4 Corp",
    "wof:placetype":"venue"
},
  "geometry": {"coordinates":[-73.201713,41.214353],"type":"Point"}
}