{
  "type": "Feature",
  "properties": {
    "iso:country":"US",
    "sg:address":"1201 Boston Post Rd",
    "sg:city":"Milford",
    "sg:classifiers":[
        {
            "category":"Shopping",
            "type":"Retail Goods"
        }
    ],
    "sg:phone":"+1 203 882 9824",
    "sg:postcode":"06460",
    "sg:province":"CT",
    "sg:tags":[
        "art",
        "gallery",
        "dealer"
    ],
    "wof:name":"HNS Art Gallery Inc",
    "wof:placetype":"venue"
},
  "geometry": {"coordinates":[-73.04134999999999,41.234572],"type":"Point"}
}