{
  "type": "Feature",
  "properties": {
    "iso:country":"US",
    "sg:address":"189 N Main St",
    "sg:city":"Port Chester",
    "sg:classifiers":[
        {
            "category":"Professional",
            "subcategory":"Lawyer & Legal Services",
            "type":"Services"
        }
    ],
    "sg:phone":"+1 914 934 2627",
    "sg:postcode":"10573",
    "sg:province":"CT",
    "sg:tags":[
        "attorney"
    ],
    "wof:name":"Jeffrey Galperin",
    "wof:placetype":"venue"
},
  "geometry": {"coordinates":[-73.659829,41.0046],"type":"Point"}
}