{
  "type": "Feature",
  "properties": {
    "iso:country":"US",
    "sg:address":"29 Wampanoag Dr",
    "sg:city":"Hartford",
    "sg:classifiers":[
        {
            "category":"Education",
            "subcategory":"School",
            "type":"Public Place"
        }
    ],
    "sg:phone":"+1   ",
    "sg:postcode":"06117",
    "sg:province":"CT",
    "sg:tags":[
        "organization",
        "religious"
    ],
    "wof:name":"Northwest Catholic High School",
    "wof:placetype":"venue"
},
  "geometry": {"coordinates":[-72.75610399999999,41.799899],"type":"Point"}
}