{
  "type": "Feature",
  "properties": {
    "addr:full":"2600 Dixwell Ave Hamden CT 06514",
    "addr:housenumber":"2600",
    "addr:postcode":"06514",
    "addr:street":"Dixwell Ave",
    "iso:country":"US",
    "sg:address":"2600 Dixwell Ave",
    "sg:city":"Hamden",
    "sg:classifiers":[
        {
            "category":"Real Estate",
            "subcategory":"Real Estate Agent",
            "type":"Services"
        }
    ],
    "sg:phone":"+1 203 281 3071",
    "sg:postcode":"06514",
    "sg:province":"CT",
    "wof:name":"Executive Realty Hamden LLC",
    "wof:placetype":"venue"
},
  "geometry": {"coordinates":[-72.91437999999999,41.378449],"type":"Point"}
}