{
  "type": "Feature",
  "properties": {
    "addr:full":"25 Meadow Ridge Dr Easton CT 06612",
    "addr:housenumber":"25",
    "addr:postcode":"06612",
    "addr:street":"Meadow Ridge Dr",
    "iso:country":"US",
    "sg:address":"25 Meadow Ridge Dr",
    "sg:city":"Easton",
    "sg:classifiers":[
        {
            "category":"Professional",
            "subcategory":"Management & Consulting",
            "type":"Services"
        }
    ],
    "sg:phone":"+1 203 268 8643",
    "sg:postcode":"06612",
    "sg:province":"CT",
    "sg:tags":[
        "consultant",
        "business"
    ],
    "wof:name":"Scarabaeus Corp",
    "wof:placetype":"venue"
},
  "geometry": {"coordinates":[-73.295618,41.267087],"type":"Point"}
}