{
  "type": "Feature",
  "properties": {
    "addr:full":"38 Putnam Green Greenwich CT 06830",
    "addr:housenumber":"38",
    "addr:postcode":"06830",
    "addr:street":"Putnam Green Greenwich Ct",
    "iso:country":"US",
    "sg:address":"38 Putnam Green",
    "sg:city":"Greenwich",
    "sg:classifiers":[
        {
            "category":"Food & Beverages",
            "subcategory":"Specialty",
            "type":"Retail Goods"
        },
        {
            "category":"Professional",
            "subcategory":"Business Services",
            "type":"Services"
        }
    ],
    "sg:phone":"+1 203 532 4538",
    "sg:postcode":"06830",
    "sg:province":"CT",
    "sg:tags":[
        "vitamin"
    ],
    "wof:name":"Healthy Living Solutions",
    "wof:placetype":"venue"
},
  "geometry": {"coordinates":[-73.649411,41.012644],"type":"Point"}
}