{
  "type": "Feature",
  "properties": {
    "iso:country":"US",
    "sg:address":"314 Flat Rock Pl Unit D103",
    "sg:city":"Westbrook",
    "sg:classifiers":[
        {
            "category":"Personal",
            "subcategory":"Barber",
            "type":"Services"
        }
    ],
    "sg:phone":"+1 860 399 0141",
    "sg:postcode":"06498",
    "sg:province":"CT",
    "sg:website":"www.costcutters.com",
    "wof:name":"Cost Cutters Salon & Products Outlet",
    "wof:placetype":"venue"
},
  "geometry": {"coordinates":[-72.444397,41.289799],"type":"Point"}
}