{
  "type": "Feature",
  "properties": {
    "addr:full":"375 Morgan Ln West Haven CT 06516",
    "addr:housenumber":"375",
    "addr:postcode":"06516",
    "addr:street":"Morgan Ln",
    "iso:country":"US",
    "sg:address":"375 Morgan Ln",
    "sg:city":"West Haven",
    "sg:classifiers":[
        {
            "category":"Shopping",
            "subcategory":"Computers & Home Electronics",
            "type":"Retail Goods"
        }
    ],
    "sg:phone":"+1 203 932 9894",
    "sg:postcode":"06516",
    "sg:province":"CT",
    "wof:name":"Wang Laboratories",
    "wof:placetype":"venue"
},
  "geometry": {"coordinates":[-72.984506,41.259749],"type":"Point"}
}