{
  "type": "Feature",
  "properties": {
    "addr:full":"123 Sharon Valley Rd Sharon CT 06069",
    "addr:housenumber":"123",
    "addr:postcode":"06069",
    "addr:street":"Sharon Valley Rd Sharon Ct",
    "iso:country":"US",
    "sg:address":"123 Sharon Valley Rd",
    "sg:city":"Sharon",
    "sg:classifiers":[
        {
            "category":"Professional",
            "type":"Services"
        }
    ],
    "sg:phone":"+1 860 364 2279",
    "sg:postcode":"06069",
    "sg:province":"CT",
    "wof:name":"Mill House",
    "wof:placetype":"venue"
},
  "geometry": {"coordinates":[-73.49683,41.873426],"type":"Point"}
}