{
  "type": "Feature",
  "properties": {
    "iso:country":"US",
    "sg:address":"654 Wethersfield Ave",
    "sg:city":"Hartford",
    "sg:classifiers":[
        {
            "category":"Wholesale",
            "subcategory":"Auto Parts",
            "type":"Manufacturing & Wholesale Goods"
        }
    ],
    "sg:phone":"+1 860 296 9319",
    "sg:postcode":"06114",
    "sg:province":"CT",
    "wof:name":"Motor Service Incorporated",
    "wof:placetype":"venue"
},
  "geometry": {"coordinates":[-72.671252,41.73819],"type":"Point"}
}