{
  "type": "Feature",
  "properties": {
    "iso:country":"US",
    "sg:address":"58 Yantic Flats Rd",
    "sg:city":"Yantic",
    "sg:classifiers":[
        {
            "category":"Building & Trades",
            "subcategory":"Plumbing",
            "type":"Services"
        }
    ],
    "sg:phone":"+1   ",
    "sg:postcode":"06360",
    "sg:province":"CT",
    "sg:tags":[
        "plumbing",
        "repair",
        "contractor"
    ],
    "wof:name":"Mr Rooter",
    "wof:placetype":"venue"
},
  "geometry": {"coordinates":[-72.11637899999999,41.557752],"type":"Point"}
}