{
  "type": "Feature",
  "properties": {
    "addr:full":"75 N Mountain Rd New Britain CT 06053",
    "addr:housenumber":"75",
    "addr:postcode":"06053",
    "addr:street":"N Mountain Rd",
    "iso:country":"US",
    "sg:address":"75 N Mountain Rd",
    "sg:city":"New Britain",
    "sg:classifiers":[
        {
            "category":"Health Services",
            "subcategory":"Medical Lab",
            "type":"Services"
        }
    ],
    "sg:phone":"+1   ",
    "sg:postcode":"06053",
    "sg:province":"CT",
    "sg:tags":[
        "laboratory"
    ],
    "wof:name":"Quest Diagnostics",
    "wof:placetype":"venue"
},
  "geometry": {"coordinates":[-72.819002,41.668976],"type":"Point"}
}