{
  "type": "Feature",
  "properties": {
    "addr:full":"906 N Colony Rd Wallingford CT 06492",
    "addr:housenumber":"906",
    "addr:postcode":"06492",
    "addr:street":"N Colony Rd",
    "iso:country":"US",
    "sg:address":"906 N Colony Rd",
    "sg:city":"Wallingford",
    "sg:classifiers":[
        {
            "category":"Personal",
            "type":"Services"
        }
    ],
    "sg:phone":"+1   ",
    "sg:postcode":"06492",
    "sg:province":"CT",
    "wof:name":"Villa Capri Inc",
    "wof:placetype":"venue"
},
  "geometry": {"coordinates":[-72.809712,41.483788],"type":"Point"}
}