{
  "type": "Feature",
  "properties": {
    "iso:country":"US",
    "sg:address":"6 Lunar Dr",
    "sg:city":"Woodbridge",
    "sg:classifiers":[
        {
            "category":"Social Services",
            "subcategory":"Adult Care",
            "type":"Services"
        }
    ],
    "sg:phone":"+1   ",
    "sg:postcode":"06525",
    "sg:province":"CT",
    "sg:tags":[
        "program",
        "rehabilitation"
    ],
    "wof:name":"Marrakech Express",
    "wof:placetype":"venue"
},
  "geometry": {"coordinates":[-72.975122,41.34664],"type":"Point"}
}