{
  "type": "Feature",
  "properties": {
    "addr:full":"51 East Ave New Canaan NY 06840",
    "addr:housenumber":"51",
    "addr:postcode":"06840",
    "addr:street":"East Ave",
    "iso:country":"US",
    "sg:address":"51 East Ave",
    "sg:city":"New Canaan",
    "sg:classifiers":[
        {
            "category":"Retail",
            "subcategory":"Laundry & Dry Cleaning",
            "type":"Services"
        }
    ],
    "sg:phone":"+1 203 966 8109",
    "sg:postcode":"06840",
    "sg:province":"NY",
    "sg:tags":[
        "clothing",
        "w"
    ],
    "wof:name":"New Canaan Custom Tailor",
    "wof:placetype":"venue"
},
  "geometry": {"coordinates":[-73.48957,41.14752],"type":"Point"}
}