{
  "type": "Feature",
  "properties": {
    "addr:full":"114 Center St Wallingford CT 06492",
    "addr:housenumber":"114",
    "addr:postcode":"06492",
    "addr:street":"Center St",
    "iso:country":"US",
    "sg:address":"114 Center St",
    "sg:city":"Wallingford",
    "sg:classifiers":[
        {
            "category":"Real Estate",
            "subcategory":"Real Estate Agent",
            "type":"Services"
        }
    ],
    "sg:phone":"+1 203 265 4601",
    "sg:postcode":"06492",
    "sg:province":"CT",
    "wof:name":"T C Realty LLC",
    "wof:placetype":"venue"
},
  "geometry": {"coordinates":[-72.82145199999999,41.455407],"type":"Point"}
}