{
  "type": "Feature",
  "properties": {
    "iso:country":"US",
    "sg:address":"5866 Main St",
    "sg:city":"Trumbull",
    "sg:classifiers":[
        {
            "category":"Government",
            "subcategory":"Court House",
            "type":"Public Place"
        }
    ],
    "sg:phone":"+1 203 452 5035",
    "sg:postcode":"06611",
    "sg:province":"CT",
    "wof:name":"Trumbull Town Clerk",
    "wof:placetype":"venue"
},
  "geometry": {"coordinates":[-73.219388,41.256711],"type":"Point"}
}