{
  "type": "Feature",
  "properties": {
    "addr:full":"54 Hillside Ave Hartford CT 06106",
    "addr:housenumber":"54",
    "addr:postcode":"06106",
    "addr:street":"Hillside Ave;Ct",
    "iso:country":"US",
    "sg:address":"54 Hillside Ave",
    "sg:city":"Hartford",
    "sg:classifiers":[
        {
            "category":"Retail",
            "subcategory":"Auto Repair",
            "type":"Services"
        }
    ],
    "sg:phone":"+1   ",
    "sg:postcode":"06106",
    "sg:province":"CT",
    "sg:tags":[
        "general"
    ],
    "wof:name":"Hillside Automotive Center",
    "wof:placetype":"venue"
},
  "geometry": {"coordinates":[-72.69747,41.752768],"type":"Point"}
}