{
  "type": "Feature",
  "properties": {
    "addr:full":"29 Plains Rd Essex CT 06426",
    "addr:housenumber":"29",
    "addr:postcode":"06426",
    "addr:street":"Plains Rd",
    "iso:country":"US",
    "sg:address":"29 Plains Rd",
    "sg:city":"Essex",
    "sg:classifiers":[
        {
            "category":"Manufacturing",
            "subcategory":"Tools & Machinery",
            "type":"Manufacturing & Wholesale Goods"
        }
    ],
    "sg:phone":"+1 860 767 3235",
    "sg:postcode":"06426",
    "sg:province":"CT",
    "sg:tags":[
        "mfg",
        "optical",
        "con"
    ],
    "wof:name":"Ken-Labs",
    "wof:placetype":"venue"
},
  "geometry": {"coordinates":[-72.403148,41.350336],"type":"Point"}
}