{
  "type": "Feature",
  "properties": {
    "addr:full":"3698 Main St Stratford CT 06614",
    "addr:housenumber":"3698",
    "addr:postcode":"06614",
    "addr:street":"Main St",
    "iso:country":"US",
    "sg:address":"3698 Main St",
    "sg:city":"Stratford",
    "sg:classifiers":[
        {
            "category":"Retail",
            "subcategory":"Self-service Laundry",
            "type":"Services"
        }
    ],
    "sg:phone":"+1 203 378 0786",
    "sg:postcode":"06614",
    "sg:province":"CT",
    "wof:name":"S & R Laundromat & Bulk Dry",
    "wof:placetype":"venue"
},
  "geometry": {"coordinates":[-73.12947699999999,41.210095],"type":"Point"}
}