{
  "type": "Feature",
  "properties": {
    "addr:full":"59 Dayton Rd Waterford CT 06385",
    "addr:housenumber":"59",
    "addr:postcode":"06385",
    "addr:street":"Dayton Rd",
    "iso:country":"US",
    "sg:address":"59 Dayton Rd",
    "sg:city":"Waterford",
    "sg:classifiers":[
        {
            "category":"Professional",
            "subcategory":"Management & Consulting",
            "type":"Services"
        }
    ],
    "sg:phone":"+1   ",
    "sg:postcode":"06385",
    "sg:province":"CT",
    "sg:tags":[
        "development",
        "training"
    ],
    "wof:name":"Southern Conneticut Training",
    "wof:placetype":"venue"
},
  "geometry": {"coordinates":[-72.1405,41.378196],"type":"Point"}
}