{
  "type": "Feature",
  "properties": {
    "addr:full":"239 Hamilton Ave Stamford CT 06902",
    "addr:housenumber":"239",
    "addr:postcode":"06902",
    "addr:street":"Hamilton Ave",
    "iso:country":"US",
    "sg:address":"239 Hamilton Ave",
    "sg:city":"Stamford",
    "sg:classifiers":[
        {
            "category":"Health Services",
            "subcategory":"Health Practitioner",
            "type":"Services"
        }
    ],
    "sg:phone":"+1 203 359 4560",
    "sg:postcode":"06902",
    "sg:province":"CT",
    "sg:tags":[
        "psychologist"
    ],
    "wof:name":"Leo P Donovan Jr PHD",
    "wof:placetype":"venue"
},
  "geometry": {"coordinates":[-73.51161399999999,41.063775],"type":"Point"}
}