{
  "type": "Feature",
  "properties": {
    "iso:country":"US",
    "sg:address":"11 Glenn Hollow Ln",
    "sg:city":"West Simsbury",
    "sg:classifiers":[
        {
            "category":"Professional",
            "subcategory":"Business Services",
            "type":"Services"
        }
    ],
    "sg:phone":"+1   ",
    "sg:postcode":"06092",
    "sg:province":"CT",
    "wof:name":"Gallant Group Inc",
    "wof:placetype":"venue"
},
  "geometry": {"coordinates":[-72.86035699999999,41.848366],"type":"Point"}
}