{
  "type": "Feature",
  "properties": {
    "addr:full":"239 Ethan Allen Hwy Ridgefield CT 06877",
    "addr:housenumber":"239",
    "addr:postcode":"06877",
    "addr:street":"Ethan Allen Hwy Ridgefield Ct",
    "iso:country":"US",
    "sg:address":"239 Ethan Allen Hwy",
    "sg:city":"Ridgefield",
    "sg:classifiers":[
        {
            "category":"Manufacturing",
            "subcategory":"Electronics",
            "type":"Manufacturing & Wholesale Goods"
        }
    ],
    "sg:phone":"+1 203 438 7070",
    "sg:postcode":"06877",
    "sg:province":"CT",
    "sg:tags":[
        "phonograph",
        "tape"
    ],
    "wof:name":"Hard Core Marketing",
    "wof:placetype":"venue"
},
  "geometry": {"coordinates":[-73.445004,41.278513],"type":"Point"}
}