{
  "type": "Feature",
  "properties": {
    "addr:full":"828 Wood Ave Bridgeport CT 06604",
    "addr:housenumber":"828",
    "addr:postcode":"06604",
    "addr:street":"Wood Ave",
    "iso:country":"US",
    "sg:address":"828 Wood Ave",
    "sg:city":"Bridgeport",
    "sg:classifiers":[
        {
            "category":"Retail",
            "subcategory":"Repair Shop",
            "type":"Services"
        }
    ],
    "sg:phone":"+1 203 334 8118",
    "sg:postcode":"06604",
    "sg:province":"CT",
    "sg:tags":[
        "upholsterer"
    ],
    "wof:name":"Randy's Carpet & Upholstery",
    "wof:placetype":"venue"
},
  "geometry": {"coordinates":[-73.21221300000001,41.182624],"type":"Point"}
}