{
  "type": "Feature",
  "properties": {
    "iso:country":"US",
    "sg:address":"35 Barber Pond Rd",
    "sg:city":"Bloomfield",
    "sg:classifiers":[
        {
            "category":"Building & Trades",
            "subcategory":"Construction",
            "type":"Services"
        }
    ],
    "sg:phone":"+1 860 242 7068",
    "sg:postcode":"06002",
    "sg:province":"CT",
    "sg:tags":[
        "contractor"
    ],
    "wof:name":"Abatement Plus",
    "wof:placetype":"venue"
},
  "geometry": {"coordinates":[-72.691602,41.861809],"type":"Point"}
}