{
  "type": "Feature",
  "properties": {
    "addr:full":"94 Mamanasco Rd Ridgefield CT 06877",
    "addr:housenumber":"94",
    "addr:postcode":"06877",
    "addr:street":"Mamanasco Rd",
    "iso:country":"US",
    "sg:address":"94 Mamanasco Rd",
    "sg:city":"Ridgefield",
    "sg:classifiers":[
        {
            "category":"Professional",
            "type":"Services"
        }
    ],
    "sg:phone":"+1   ",
    "sg:postcode":"06877",
    "sg:province":"CT",
    "wof:name":"Lisa Scroggins",
    "wof:placetype":"venue"
},
  "geometry": {"coordinates":[-73.523734,41.31498],"type":"Point"}
}