{
  "type": "Feature",
  "properties": {
    "iso:country":"US",
    "sg:address":"70 Wooster Ave",
    "sg:city":"Waterbury",
    "sg:classifiers":[
        {
            "category":"Local Transit",
            "type":"Transportation"
        }
    ],
    "sg:phone":"+1 203 757 1432",
    "sg:postcode":"06708",
    "sg:province":"CT",
    "sg:tags":[
        "passenger"
    ],
    "wof:name":"Appropriate Limousine LLC",
    "wof:placetype":"venue"
},
  "geometry": {"coordinates":[-73.08160599999999,41.54382],"type":"Point"}
}