{
  "type": "Feature",
  "properties": {
    "iso:country":"US",
    "sg:address":"12 Roger Dr",
    "sg:city":"Danbury",
    "sg:classifiers":[
        {
            "category":"Professional",
            "type":"Services"
        }
    ],
    "sg:phone":"+1 203 748 8208",
    "sg:postcode":"06811",
    "sg:province":"CT",
    "wof:name":"Pedro Lesmes",
    "wof:placetype":"venue"
},
  "geometry": {"coordinates":[-73.445848,41.413739],"type":"Point"}
}