{
  "type": "Feature",
  "properties": {
    "addr:full":"41 River Rd Clinton CT 06413",
    "addr:housenumber":"41",
    "addr:postcode":"06413",
    "addr:street":"River Rd",
    "iso:country":"US",
    "sg:address":"41 River Rd",
    "sg:city":"Clinton",
    "sg:classifiers":[
        {
            "category":"Real Estate",
            "subcategory":"Real Estate Services",
            "type":"Services"
        }
    ],
    "sg:phone":"+1 860 664 0118",
    "sg:postcode":"06413",
    "sg:province":"CT",
    "sg:tags":[
        "vacancy",
        "apartment",
        "rental",
        "finder",
        "listing"
    ],
    "wof:name":"Studio Works",
    "wof:placetype":"venue"
},
  "geometry": {"coordinates":[-72.575636,41.303815],"type":"Point"}
}