{
  "type": "Feature",
  "properties": {
    "iso:country":"US",
    "sg:address":"14 Larson Dr Exd",
    "sg:city":"North Haven",
    "sg:classifiers":[
        {
            "category":"Freight",
            "type":"Transportation"
        }
    ],
    "sg:phone":"+1 203 234 6268",
    "sg:postcode":"06473",
    "sg:province":"CT",
    "sg:tags":[
        "delivery"
    ],
    "wof:name":"Cunningham Delivery Svc",
    "wof:placetype":"venue"
},
  "geometry": {"coordinates":[-72.84939199999999,41.392492],"type":"Point"}
}