{
  "type": "Feature",
  "properties": {
    "iso:country":"US",
    "sg:address":"246 Deer Run Rd",
    "sg:city":"Wilton",
    "sg:classifiers":[
        {
            "category":"Real Estate",
            "subcategory":"Real Estate Operator",
            "type":"Services"
        }
    ],
    "sg:phone":"+1 203 762 5726",
    "sg:postcode":"06897",
    "sg:province":"CT",
    "sg:tags":[
        "building",
        "nonresidential"
    ],
    "wof:name":"Christiano Properties Inc",
    "wof:placetype":"venue"
},
  "geometry": {"coordinates":[-73.46825800000001,41.240368],"type":"Point"}
}