{
  "type": "Feature",
  "properties": {
    "iso:country":"US",
    "sg:address":"17 Granville Ave",
    "sg:city":"Milford",
    "sg:classifiers":[
        {
            "category":"Professional",
            "subcategory":"Research",
            "type":"Services"
        }
    ],
    "sg:phone":"+1 203 874 9481",
    "sg:postcode":"06460",
    "sg:province":"CT",
    "sg:tags":[
        "development",
        "marketing",
        "product"
    ],
    "wof:name":"Beth Communications",
    "wof:placetype":"venue"
},
  "geometry": {"coordinates":[-73.10244,41.196297],"type":"Point"}
}