{
  "type": "Feature",
  "properties": {
    "addr:full":"27 Overlook Ter Simsbury CT 06070",
    "addr:housenumber":"27",
    "addr:postcode":"06070",
    "addr:street":"Overlook Ter Simsbury Ct",
    "iso:country":"US",
    "sg:address":"27 Overlook Ter",
    "sg:city":"Simsbury",
    "sg:classifiers":[
        {
            "category":"Shopping",
            "subcategory":"Stationery & Office Supplies",
            "type":"Retail Goods"
        }
    ],
    "sg:phone":"+1 860 651 5540",
    "sg:postcode":"06070",
    "sg:province":"CT",
    "sg:tags":[
        "equipment"
    ],
    "wof:name":"Smith Business Machines",
    "wof:placetype":"venue"
},
  "geometry": {"coordinates":[-72.838402,41.842201],"type":"Point"}
}