{
  "type": "Feature",
  "properties": {
    "addr:full":"165 Pearl St Seymour CT 06483",
    "addr:housenumber":"165",
    "addr:postcode":"06483",
    "addr:street":"Pearl St",
    "iso:country":"US",
    "sg:address":"165 Pearl St",
    "sg:city":"Seymour",
    "sg:classifiers":[
        {
            "category":"Organizations",
            "subcategory":"Membership Organization",
            "type":"Services"
        }
    ],
    "sg:phone":"+1   ",
    "sg:postcode":"06483",
    "sg:province":"CT",
    "wof:name":"Polish Natl Alliance of US",
    "wof:placetype":"venue"
},
  "geometry": {"coordinates":[-73.066338,41.389998],"type":"Point"}
}