{
  "type": "Feature",
  "properties": {
    "iso:country":"US",
    "sg:address":"15 June St",
    "sg:city":"Woodbridge",
    "sg:classifiers":[
        {
            "category":"Personal",
            "subcategory":"Beauty Salon",
            "type":"Services"
        }
    ],
    "sg:phone":"+1 203 397 2644",
    "sg:postcode":"06525",
    "sg:province":"CT",
    "sg:tags":[
        "treatment",
        "skin"
    ],
    "wof:name":"Marsha Adams Electrologists",
    "wof:placetype":"venue"
},
  "geometry": {"coordinates":[-72.981739,41.338494],"type":"Point"}
}