{
  "type": "Feature",
  "properties": {
    "iso:country":"US",
    "sg:address":"53740 Route 25",
    "sg:city":"Southold",
    "sg:classifiers":[
        {
            "category":"Home & Garden",
            "subcategory":"Furniture",
            "type":"Retail Goods"
        }
    ],
    "sg:phone":"+1 631 765 2211",
    "sg:postcode":"11971",
    "sg:province":"NY",
    "sg:tags":[
        "store"
    ],
    "wof:name":"B Home",
    "wof:placetype":"venue"
},
  "geometry": {"coordinates":[-72.428447,41.39478],"type":"Point"}
}