{
  "type": "Feature",
  "properties": {
    "addr:full":"67 Deer Hill Rd Redding CT 06896",
    "addr:housenumber":"67",
    "addr:postcode":"06896",
    "addr:street":"Deer Hill Rd",
    "iso:country":"US",
    "sg:address":"67 Deer Hill Rd",
    "sg:city":"Redding",
    "sg:classifiers":[
        {
            "category":"Building & Trades",
            "subcategory":"Construction",
            "type":"Services"
        }
    ],
    "sg:phone":"+1 203 938 3924",
    "sg:postcode":"06896",
    "sg:province":"CT",
    "sg:tags":[
        "clearing",
        "mulch",
        "land",
        "logging",
        "mfg"
    ],
    "wof:name":"Smith Bros Woodland Mgmt LLC",
    "wof:placetype":"venue"
},
  "geometry": {"coordinates":[-73.37714200000001,41.294912],"type":"Point"}
}