{
  "type": "Feature",
  "properties": {
    "iso:country":"US",
    "sg:address":"37 Trumbull St",
    "sg:city":"New Haven",
    "sg:classifiers":[
        {
            "category":"Personal",
            "type":"Services"
        }
    ],
    "sg:phone":"+1   ",
    "sg:postcode":"06510",
    "sg:province":"CT",
    "sg:tags":[
        "general"
    ],
    "wof:name":"Crescent Group LLC",
    "wof:placetype":"venue"
},
  "geometry": {"coordinates":[-72.920191,41.312442],"type":"Point"}
}