{
  "type": "Feature",
  "properties": {
    "iso:country":"US",
    "sg:address":"252 Terryville Rd",
    "sg:city":"Bristol",
    "sg:classifiers":[
        {
            "category":"Professional",
            "subcategory":"Business Services",
            "type":"Services"
        }
    ],
    "sg:phone":"+1 860 583 8284",
    "sg:postcode":"06010",
    "sg:province":"CT",
    "sg:tags":[
        "specialty",
        "mfg"
    ],
    "wof:name":"Joe Carucci Signs",
    "wof:placetype":"venue"
},
  "geometry": {"coordinates":[-72.976879,41.671397],"type":"Point"}
}