{
  "type": "Feature",
  "properties": {
    "iso:country":"US",
    "sg:address":"56 Misty View Ave",
    "sg:city":"Mystic",
    "sg:classifiers":[
        {
            "category":"Professional",
            "subcategory":"Computer Services",
            "type":"Services"
        }
    ],
    "sg:phone":"+1   ",
    "sg:postcode":"06355",
    "sg:province":"CT",
    "sg:tags":[
        "related",
        "programing",
        "custom"
    ],
    "wof:name":"Software Frameworks Inc",
    "wof:placetype":"venue"
},
  "geometry": {"coordinates":[-71.98149600000001,41.352261],"type":"Point"}
}