{
  "type": "Feature",
  "properties": {
    "addr:full":"18 Lindman St Manchester CT 06040",
    "addr:housenumber":"18",
    "addr:postcode":"06040",
    "addr:street":"Lindman St",
    "iso:country":"US",
    "sg:address":"18 Lindman St",
    "sg:city":"Manchester",
    "sg:classifiers":[
        {
            "category":"Professional",
            "type":"Services"
        }
    ],
    "sg:phone":"+1 860 643 9640",
    "sg:postcode":"06040",
    "sg:province":"CT",
    "wof:name":"Edward Hicks",
    "wof:placetype":"venue"
},
  "geometry": {"coordinates":[-72.506868,41.769721],"type":"Point"}
}