{
  "type": "Feature",
  "properties": {
    "addr:full":"1257 Old Colony Rd Wallingford CT 06492",
    "addr:housenumber":"1257",
    "addr:postcode":"06492",
    "addr:street":"Old Colony Rd",
    "iso:country":"US",
    "sg:address":"1257 Old Colony Rd",
    "sg:city":"Wallingford",
    "sg:classifiers":[
        {
            "category":"Restaurant",
            "type":"Food & Drink"
        }
    ],
    "sg:phone":"+1 203 269 2999",
    "sg:postcode":"06492",
    "sg:province":"CT",
    "sg:tags":[
        "cafe"
    ],
    "wof:name":"Easy Street Saloon",
    "wof:placetype":"venue"
},
  "geometry": {"coordinates":[-72.81654899999999,41.505754],"type":"Point"}
}