{
  "type": "Feature",
  "properties": {
    "addr:full":"185 Park Rd Putnam CT 06260",
    "addr:housenumber":"185",
    "addr:postcode":"06260",
    "addr:street":"Park Rd",
    "iso:country":"US",
    "sg:address":"185 Park Rd",
    "sg:city":"Putnam",
    "sg:classifiers":[
        {
            "category":"Freight",
            "type":"Transportation"
        }
    ],
    "sg:phone":"+1 860 963 9018",
    "sg:postcode":"06260",
    "sg:province":"CT",
    "sg:tags":[
        "operator",
        "local",
        "trucking"
    ],
    "wof:name":"M & M Transport Services Inc",
    "wof:placetype":"venue"
},
  "geometry": {"coordinates":[-71.892613,41.887249],"type":"Point"}
}