{
  "type": "Feature",
  "properties": {
    "addr:full":"7 Backus Ave Danbury CT 06810",
    "addr:housenumber":"7",
    "addr:postcode":"06810",
    "addr:street":"Backus Ave",
    "iso:country":"US",
    "sg:address":"7 Backus Ave",
    "sg:city":"Danbury",
    "sg:classifiers":[
        {
            "category":"Shopping",
            "type":"Retail Goods"
        },
        {
            "category":"Personal",
            "subcategory":"Beauty Salon",
            "type":"Services"
        }
    ],
    "sg:phone":"+1 203 798 0676",
    "sg:postcode":"06810",
    "sg:province":"CT",
    "sg:tags":[
        "shop",
        "cosmetic",
        "merchandise",
        "perfume"
    ],
    "wof:name":"Merle Norman Cosmetics",
    "wof:placetype":"venue"
},
  "geometry": {"coordinates":[-73.47560799999999,41.380075],"type":"Point"}
}