{
  "type": "Feature",
  "properties": {
    "iso:country":"US",
    "sg:address":"1028 Maplewood Ave",
    "sg:city":"Bridgeport",
    "sg:classifiers":[
        {
            "category":"Building & Trades",
            "subcategory":"Cleaning & Sanitation",
            "type":"Services"
        }
    ],
    "sg:phone":"+1   ",
    "sg:postcode":"06605",
    "sg:province":"CT",
    "sg:tags":[
        "maintenance"
    ],
    "wof:name":"Roseboro Cleaning Services LLC",
    "wof:placetype":"venue"
},
  "geometry": {"coordinates":[-73.218424,41.172434],"type":"Point"}
}