{
  "type": "Feature",
  "properties": {
    "addr:full":"55 Nye Rd Glastonbury CT 06033",
    "addr:housenumber":"55",
    "addr:postcode":"06033",
    "addr:street":"Nye Rd",
    "iso:country":"US",
    "sg:address":"55 Nye Rd",
    "sg:city":"Glastonbury",
    "sg:classifiers":[
        {
            "category":"Health Services",
            "subcategory":"Optometrist",
            "type":"Services"
        }
    ],
    "sg:phone":"+1   ",
    "sg:postcode":"06033",
    "sg:province":"CT",
    "wof:name":"Hartford Eye Physicians PC",
    "wof:placetype":"venue"
},
  "geometry": {"coordinates":[-72.60086200000001,41.7196],"type":"Point"}
}