{
  "type": "Feature",
  "properties": {
    "addr:full":"30 N Main St Port Chester CT 10573",
    "addr:housenumber":"30",
    "addr:postcode":"10573",
    "addr:street":"N Main St;Chester",
    "iso:country":"US",
    "sg:address":"30 N Main St",
    "sg:city":"Port Chester",
    "sg:classifiers":[
        {
            "category":"Health Services",
            "subcategory":"Chiropractor",
            "type":"Services"
        }
    ],
    "sg:phone":"+1   ",
    "sg:postcode":"10573",
    "sg:province":"CT",
    "wof:name":"Louise Minutella",
    "wof:placetype":"venue"
},
  "geometry": {"coordinates":[-73.662916,41.001166],"type":"Point"}
}