{
  "type": "Feature",
  "properties": {
    "iso:country":"US",
    "sg:address":"81 Hobart Ave",
    "sg:city":"Port Chester",
    "sg:classifiers":[
        {
            "category":"Wholesale",
            "subcategory":"Scrap",
            "type":"Manufacturing & Wholesale Goods"
        }
    ],
    "sg:phone":"+1 914 690 0864",
    "sg:postcode":"10573",
    "sg:province":"NY",
    "sg:tags":[
        "miscellaneous",
        "merchandise"
    ],
    "wof:name":"Matts Marketing",
    "wof:placetype":"venue"
},
  "geometry": {"coordinates":[-73.66350799999999,41.01625],"type":"Point"}
}