{
  "type": "Feature",
  "properties": {
    "iso:country":"US",
    "sg:address":"198 Center St",
    "sg:city":"Wallingford",
    "sg:classifiers":[
        {
            "category":"Professional",
            "subcategory":"Advertising",
            "type":"Services"
        }
    ],
    "sg:phone":"+1 203 294 1656",
    "sg:postcode":"06492",
    "sg:province":"CT",
    "sg:website":"www.shirtgraphix.com",
    "wof:name":"Shirt Graphix Screen Printing",
    "wof:placetype":"venue"
},
  "geometry": {"coordinates":[-72.820207,41.45517],"type":"Point"}
}