{
  "type": "Feature",
  "properties": {
    "addr:full":"2 Coult Ln Old Lyme CT 06371",
    "addr:housenumber":"2",
    "addr:postcode":"06371",
    "addr:street":"Coult Ln",
    "iso:country":"US",
    "sg:address":"2 Coult Ln",
    "sg:city":"Old Lyme",
    "sg:classifiers":[
        {
            "category":"Retail",
            "subcategory":"Repair Shop",
            "type":"Services"
        }
    ],
    "sg:phone":"+1   ",
    "sg:postcode":"06371",
    "sg:province":"CT",
    "wof:name":"Septic Solutions LLC",
    "wof:placetype":"venue"
},
  "geometry": {"coordinates":[-72.34240200000001,41.341989],"type":"Point"}
}