{
  "type": "Feature",
  "properties": {
    "addr:full":"189 Josies Ring Rd Monroe CT 06468",
    "addr:housenumber":"189",
    "addr:postcode":"06468",
    "addr:street":"Josies Ring Rd",
    "iso:country":"US",
    "sg:address":"189 Josies Ring Rd",
    "sg:city":"Monroe",
    "sg:classifiers":[
        {
            "category":"Professional",
            "subcategory":"Computer Services",
            "type":"Services"
        }
    ],
    "sg:phone":"+1 203 261 4328",
    "sg:postcode":"06468",
    "sg:province":"CT",
    "sg:tags":[
        "datum",
        "typesetting"
    ],
    "wof:name":"Kiagraphics",
    "wof:placetype":"venue"
},
  "geometry": {"coordinates":[-73.194733,41.368246],"type":"Point"}
}