{
  "type": "Feature",
  "properties": {
    "addr:full":"105 Dawson Ave West Haven CT 06516",
    "addr:housenumber":"105",
    "addr:postcode":"06516",
    "addr:street":"Dawson Ave",
    "iso:country":"US",
    "sg:address":"105 Dawson Ave",
    "sg:city":"West Haven",
    "sg:classifiers":[
        {
            "category":"Professional",
            "subcategory":"Art Services",
            "type":"Services"
        }
    ],
    "sg:phone":"+1   ",
    "sg:postcode":"06516",
    "sg:province":"CT",
    "sg:tags":[
        "commercial",
        "design"
    ],
    "wof:name":"Creating Home Decor",
    "wof:placetype":"venue"
},
  "geometry": {"coordinates":[-72.967581,41.248944],"type":"Point"}
}