{
  "type": "Feature",
  "properties": {
    "iso:country":"US",
    "sg:address":"2015 Whitney Ave",
    "sg:city":"North Haven",
    "sg:classifiers":[
        {
            "category":"Retail",
            "subcategory":"Auto Repair",
            "type":"Services"
        }
    ],
    "sg:phone":"+1 203 248 1955",
    "sg:postcode":"06473",
    "sg:province":"CT",
    "sg:tags":[
        "repairing",
        "automobile"
    ],
    "wof:name":"Saf-T Auto Ctr",
    "wof:placetype":"venue"
},
  "geometry": {"coordinates":[-72.906189,41.371095],"type":"Point"}
}