{
  "type": "Feature",
  "properties": {
    "iso:country":"US",
    "sg:address":"256 Main St",
    "sg:city":"Durham",
    "sg:classifiers":[
        {
            "category":"Professional",
            "subcategory":"Management & Consulting",
            "type":"Services"
        }
    ],
    "sg:phone":"+1   ",
    "sg:postcode":"06422",
    "sg:province":"CT",
    "sg:tags":[
        "business"
    ],
    "wof:name":"Gillespie Consulting Group LLC",
    "wof:placetype":"venue"
},
  "geometry": {"coordinates":[-72.68138500000001,41.479428],"type":"Point"}
}