{
  "type": "Feature",
  "properties": {
    "addr:full":"13 Brookhill Ln Norwalk CT 06851",
    "addr:housenumber":"13",
    "addr:postcode":"06851",
    "addr:street":"Brookhill Ln",
    "iso:country":"US",
    "sg:address":"13 Brookhill Ln",
    "sg:city":"Norwalk",
    "sg:classifiers":[
        {
            "category":"Professional",
            "subcategory":"Engineering",
            "type":"Services"
        }
    ],
    "sg:phone":"+1 203 847 8357",
    "sg:postcode":"06851",
    "sg:province":"CT",
    "sg:tags":[
        "engineer"
    ],
    "wof:name":"Spice Simulations",
    "wof:placetype":"venue"
},
  "geometry": {"coordinates":[-73.41074399999999,41.142058],"type":"Point"}
}