{
  "type": "Feature",
  "properties": {
    "addr:full":"10 Bassett St Ansonia CT 06401",
    "addr:housenumber":"10",
    "addr:postcode":"06401",
    "addr:street":"Bassett St",
    "iso:country":"US",
    "sg:address":"10 Bassett St",
    "sg:city":"Ansonia",
    "sg:classifiers":[
        {
            "category":"Organizations",
            "subcategory":"Religious Organization",
            "type":"Services"
        }
    ],
    "sg:phone":"+1   ",
    "sg:postcode":"06401",
    "sg:province":"CT",
    "wof:name":"Christian Life Fellowship",
    "wof:placetype":"venue"
},
  "geometry": {"coordinates":[-73.084918,41.34005],"type":"Point"}
}