{
  "type": "Feature",
  "properties": {
    "iso:country":"US",
    "sg:address":"101 West St",
    "sg:city":"Danbury",
    "sg:classifiers":[
        {
            "category":"Personal",
            "subcategory":"Beauty Salon",
            "type":"Services"
        }
    ],
    "sg:phone":"+1 203 743 6820",
    "sg:postcode":"06810",
    "sg:province":"CT",
    "wof:name":"Anita's Beauty Salon",
    "wof:placetype":"venue"
},
  "geometry": {"coordinates":[-73.46119,41.392699],"type":"Point"}
}