{
  "type": "Feature",
  "properties": {
    "addr:full":"8 Lincoln St Westport CT 06880",
    "addr:housenumber":"8",
    "addr:postcode":"06880",
    "addr:street":"Lincoln St",
    "iso:country":"US",
    "sg:address":"8 Lincoln St",
    "sg:city":"Westport",
    "sg:classifiers":[
        {
            "category":"Personal",
            "type":"Services"
        }
    ],
    "sg:phone":"+1 203 226 8897",
    "sg:postcode":"06880",
    "sg:province":"CT",
    "sg:tags":[
        "therapist",
        "massage"
    ],
    "wof:name":"Patricia Singer",
    "wof:placetype":"venue"
},
  "geometry": {"coordinates":[-73.36466900000001,41.137259],"type":"Point"}
}