{
  "type": "Feature",
  "properties": {
    "addr:full":"35 Charter Rd Tolland CT 06084",
    "addr:housenumber":"35",
    "addr:postcode":"06084",
    "addr:street":"Charter Rd Tolland Ct",
    "iso:country":"US",
    "sg:address":"35 Charter Rd",
    "sg:city":"Tolland",
    "sg:classifiers":[
        {
            "category":"Retail",
            "subcategory":"Auto Repair",
            "type":"Services"
        }
    ],
    "sg:phone":"+1   ",
    "sg:postcode":"06084",
    "sg:province":"CT",
    "sg:tags":[
        "shop"
    ],
    "wof:name":"Charlies Auto Body",
    "wof:placetype":"venue"
},
  "geometry": {"coordinates":[-72.350882,41.891557],"type":"Point"}
}