{
  "type": "Feature",
  "properties": {
    "iso:country":"US",
    "sg:address":"190 Laurel Brook Rd",
    "sg:city":"Middlefield",
    "sg:classifiers":[
        {
            "category":"Professional",
            "subcategory":"Business Services",
            "type":"Services"
        }
    ],
    "sg:phone":"+1   ",
    "sg:postcode":"06455",
    "sg:province":"CT",
    "wof:name":"Rikk Associates",
    "wof:placetype":"venue"
},
  "geometry": {"coordinates":[-72.681073,41.515802],"type":"Point"}
}