{
  "type": "Feature",
  "properties": {
    "addr:full":"94 Mohegan Dr Hartford CT 06117",
    "addr:housenumber":"94",
    "addr:postcode":"06117",
    "addr:street":"Mohegan Dr",
    "iso:country":"US",
    "sg:address":"94 Mohegan Dr",
    "sg:city":"Hartford",
    "sg:classifiers":[
        {
            "category":"Professional",
            "subcategory":"Management & Consulting",
            "type":"Services"
        }
    ],
    "sg:phone":"+1   ",
    "sg:postcode":"06117",
    "sg:province":"CT",
    "sg:tags":[
        "franchise",
        "consultant",
        "business"
    ],
    "wof:name":"Seid Michael H & Assoc LLC",
    "wof:placetype":"venue"
},
  "geometry": {"coordinates":[-72.736525,41.792807],"type":"Point"}
}