{
  "type": "Feature",
  "properties": {
    "iso:country":"US",
    "sg:address":"311 Brimfield Rd",
    "sg:city":"Wethersfield",
    "sg:classifiers":[
        {
            "category":"Professional",
            "subcategory":"Business Services",
            "type":"Services"
        }
    ],
    "sg:phone":"+1   ",
    "sg:postcode":"06109",
    "sg:province":"CT",
    "wof:name":"Rose OConner Interiors",
    "wof:placetype":"venue"
},
  "geometry": {"coordinates":[-72.673063,41.696327],"type":"Point"}
}