{
  "type": "Feature",
  "properties": {
    "iso:country":"US",
    "sg:address":"84 Spring St",
    "sg:city":"New Britain",
    "sg:classifiers":[
        {
            "category":"Organizations",
            "subcategory":"Religious Organization",
            "type":"Services"
        }
    ],
    "sg:phone":"+1   ",
    "sg:postcode":"06051",
    "sg:province":"CT",
    "wof:name":"New Life In Christ Church",
    "wof:placetype":"venue"
},
  "geometry": {"coordinates":[-72.77704799999999,41.673426],"type":"Point"}
}