{
  "type": "Feature",
  "properties": {
    "iso:country":"US",
    "sg:address":"36 Woodside Ln",
    "sg:city":"Plainville",
    "sg:classifiers":[
        {
            "category":"Building & Trades",
            "subcategory":"Cleaning & Sanitation",
            "type":"Services"
        }
    ],
    "sg:phone":"+1   ",
    "sg:postcode":"06062",
    "sg:province":"CT",
    "sg:tags":[
        "maintenance"
    ],
    "wof:name":"Ray JS Cleaning",
    "wof:placetype":"venue"
},
  "geometry": {"coordinates":[-72.855251,41.688609],"type":"Point"}
}