{
  "type": "Feature",
  "properties": {
    "iso:country":"US",
    "sg:address":"15 Knollwood Rd",
    "sg:city":"East Hartford",
    "sg:classifiers":[
        {
            "category":"Real Estate",
            "subcategory":"Real Estate Agent",
            "type":"Services"
        }
    ],
    "sg:phone":"+1 860 569 4293",
    "sg:postcode":"06118",
    "sg:province":"CT",
    "wof:name":"Keating Appraisal",
    "wof:placetype":"venue"
},
  "geometry": {"coordinates":[-72.59064600000001,41.762578],"type":"Point"}
}