{
  "type": "Feature",
  "properties": {
    "addr:full":"50 Ridgefield Ave Bridgeport CT 06610",
    "addr:housenumber":"50",
    "addr:postcode":"06610",
    "addr:street":"Ridgefield Ave",
    "iso:country":"US",
    "sg:address":"50 Ridgefield Ave",
    "sg:city":"Bridgeport",
    "sg:classifiers":[
        {
            "category":"Organizations",
            "subcategory":"Labor Organization",
            "type":"Services"
        }
    ],
    "sg:phone":"+1 203 333 4685",
    "sg:postcode":"06610",
    "sg:province":"CT",
    "wof:name":"American Postal Workers Union",
    "wof:placetype":"venue"
},
  "geometry": {"coordinates":[-73.164158,41.18799],"type":"Point"}
}