{
  "type": "Feature",
  "properties": {
    "iso:country":"US",
    "sg:address":"250 Totoket Rd",
    "sg:city":"North Branford",
    "sg:classifiers":[
        {
            "category":"Wholesale",
            "subcategory":"Machinery & Supplies",
            "type":"Manufacturing & Wholesale Goods"
        }
    ],
    "sg:phone":"+1 203 484 2651",
    "sg:postcode":"06471",
    "sg:province":"CT",
    "sg:tags":[
        "printing"
    ],
    "wof:name":"Cutter & Drill Parts",
    "wof:placetype":"venue"
},
  "geometry": {"coordinates":[-72.81698799999999,41.336131],"type":"Point"}
}