{
  "type": "Feature",
  "properties": {
    "addr:full":"47 Orchard Pl New Haven CT 06511",
    "addr:housenumber":"47",
    "addr:postcode":"06511",
    "addr:street":"Orchard Pl",
    "iso:country":"US",
    "sg:address":"47 Orchard Pl",
    "sg:city":"New Haven",
    "sg:classifiers":[
        {
            "category":"Organizations",
            "subcategory":"Community Association",
            "type":"Services"
        }
    ],
    "sg:phone":"+1   ",
    "sg:postcode":"06511",
    "sg:province":"CT",
    "wof:name":"Salt & Pepper Gospel Singers",
    "wof:placetype":"venue"
},
  "geometry": {"coordinates":[-72.936357,41.318322],"type":"Point"}
}