{
  "type": "Feature",
  "properties": {
    "iso:country":"US",
    "sg:address":"23 Benedict Pl",
    "sg:city":"Greenwich",
    "sg:classifiers":[
        {
            "category":"Personal",
            "subcategory":"Beauty Salon",
            "type":"Services"
        }
    ],
    "sg:phone":"+1 203 622 9300",
    "sg:postcode":"06830",
    "sg:province":"CT",
    "sg:tags":[
        "unisex",
        "hair"
    ],
    "wof:name":"David Hair Care and Color",
    "wof:placetype":"venue"
},
  "geometry": {"coordinates":[-73.62770999999999,41.027876],"type":"Point"}
}