{
  "type": "Feature",
  "properties": {
    "iso:country":"US",
    "sg:address":"41 Longhini Ln",
    "sg:city":"New Haven",
    "sg:classifiers":[
        {
            "category":"Wholesale",
            "subcategory":"Meat",
            "type":"Manufacturing & Wholesale Goods"
        }
    ],
    "sg:phone":"+1 203 624 7110",
    "sg:postcode":"06519",
    "sg:province":"CT",
    "sg:tags":[
        "prod",
        "prepared"
    ],
    "wof:name":"Longhini Sausage Inc",
    "wof:placetype":"venue"
},
  "geometry": {"coordinates":[-72.947687,41.296094],"type":"Point"}
}