{
  "type": "Feature",
  "properties": {
    "iso:country":"US",
    "sg:address":"888 Grand Ave",
    "sg:city":"New Haven",
    "sg:classifiers":[
        {
            "category":"Food & Beverages",
            "subcategory":"Liquor & Beverages",
            "type":"Retail Goods"
        }
    ],
    "sg:phone":"+1 203 776 4100",
    "sg:postcode":"06511",
    "sg:province":"CT",
    "sg:tags":[
        "alcoholic"
    ],
    "wof:name":"Hollywood Package Store",
    "wof:placetype":"venue"
},
  "geometry": {"coordinates":[-72.91762,41.307613],"type":"Point"}
}