{
  "type": "Feature",
  "properties": {
    "iso:country":"US",
    "sg:address":"562 Westchester Ave",
    "sg:city":"Port Chester",
    "sg:classifiers":[
        {
            "category":"Real Estate",
            "subcategory":"Real Estate Agent",
            "type":"Services"
        }
    ],
    "sg:phone":"+1 914 937 4494",
    "sg:postcode":"10573",
    "sg:province":"CT",
    "sg:tags":[
        "management"
    ],
    "wof:name":"CDM Property Management LLC",
    "wof:placetype":"venue"
},
  "geometry": {"coordinates":[-73.68172800000001,41.005922],"type":"Point"}
}