{
  "type": "Feature",
  "properties": {
    "addr:full":"48 Union St Stamford CT 06906",
    "addr:housenumber":"48",
    "addr:postcode":"06906",
    "addr:street":"Union St",
    "iso:country":"US",
    "sg:address":"48 Union St",
    "sg:city":"Stamford",
    "sg:classifiers":[
        {
            "category":"Communications",
            "subcategory":"Film & Video Production",
            "type":"Services"
        }
    ],
    "sg:phone":"+1 203 975 8560",
    "sg:postcode":"06906",
    "sg:province":"CT",
    "sg:tags":[
        "taping"
    ],
    "sg:website":"www.sciencefriday.com",
    "wof:name":"Samanna Productions",
    "wof:placetype":"venue"
},
  "geometry": {"coordinates":[-73.521326,41.073419],"type":"Point"}
}