{
  "type": "Feature",
  "properties": {
    "addr:full":"21 King Ln Ridgefield CT 06877",
    "addr:housenumber":"21",
    "addr:postcode":"06877",
    "addr:street":"King Ln",
    "iso:country":"US",
    "sg:address":"21 King Ln",
    "sg:city":"Ridgefield",
    "sg:classifiers":[
        {
            "category":"Organizations",
            "subcategory":"Community Association",
            "type":"Services"
        }
    ],
    "sg:phone":"+1 203 438 2026",
    "sg:postcode":"06877",
    "sg:province":"CT",
    "sg:tags":[
        "fraternal"
    ],
    "wof:name":"IOOF",
    "wof:placetype":"venue"
},
  "geometry": {"coordinates":[-73.49996400000001,41.276261],"type":"Point"}
}