{
  "type": "Feature",
  "properties": {
    "addr:full":"126 Swain Ave Meriden CT 06450",
    "addr:housenumber":"126",
    "addr:postcode":"06450",
    "addr:street":"Swain Ave",
    "iso:country":"US",
    "sg:address":"126 Swain Ave",
    "sg:city":"Meriden",
    "sg:classifiers":[
        {
            "category":"Real Estate",
            "subcategory":"Real Estate Operator",
            "type":"Services"
        }
    ],
    "sg:phone":"+1 203 639 9885",
    "sg:postcode":"06450",
    "sg:province":"CT",
    "sg:tags":[
        "building",
        "nonresidential"
    ],
    "wof:name":"JM Property Assoc LLC",
    "wof:placetype":"venue"
},
  "geometry": {"coordinates":[-72.781018,41.527132],"type":"Point"}
}