{
  "type": "Feature",
  "properties": {
    "iso:country":"US",
    "sg:address":"525 New Britain Ave",
    "sg:city":"Unionville",
    "sg:classifiers":[
        {
            "category":"Health Services",
            "subcategory":"Clinic",
            "type":"Services"
        }
    ],
    "sg:phone":"+1   ",
    "sg:postcode":"06085",
    "sg:province":"CT",
    "sg:tags":[
        "respiratory"
    ],
    "wof:name":"Nutmeg Rspiratory HM Care Svcs",
    "wof:placetype":"venue"
},
  "geometry": {"coordinates":[-72.870538,41.744632],"type":"Point"}
}