{
  "type": "Feature",
  "properties": {
    "iso:country":"US",
    "sg:address":"25 Lewis St",
    "sg:city":"Greenwich",
    "sg:classifiers":[
        {
            "category":"Health Services",
            "subcategory":"Chiropractor",
            "type":"Services"
        }
    ],
    "sg:phone":"+1 203 661 8122",
    "sg:postcode":"06830",
    "sg:province":"CT",
    "wof:name":"William Trebing Chiropractors",
    "wof:placetype":"venue"
},
  "geometry": {"coordinates":[-73.62427,41.029069],"type":"Point"}
}