{
  "type": "Feature",
  "properties": {
    "iso:country":"US",
    "sg:address":"9 Anderson Rd",
    "sg:city":"Greenwich",
    "sg:classifiers":[
        {
            "category":"Arts & Performance",
            "subcategory":"Theater",
            "type":"Entertainment"
        }
    ],
    "sg:phone":"+1   ",
    "sg:postcode":"06830",
    "sg:province":"CT",
    "sg:tags":[
        "group"
    ],
    "wof:name":"Joe Delia Music Agency",
    "wof:placetype":"venue"
},
  "geometry": {"coordinates":[-73.619438,41.030297],"type":"Point"}
}