{
  "type": "Feature",
  "properties": {
    "addr:full":"604 Ella T Grasso Blvd New Haven CT 06519",
    "addr:housenumber":"604",
    "addr:postcode":"06519",
    "addr:street":"Ella T Grasso Blvd",
    "iso:country":"US",
    "sg:address":"604 Ella T Grasso Blvd",
    "sg:city":"New Haven",
    "sg:classifiers":[
        {
            "category":"Shopping",
            "subcategory":"Used Merchandise",
            "type":"Retail Goods"
        }
    ],
    "sg:phone":"+1 203 498 7296",
    "sg:postcode":"06519",
    "sg:province":"CT",
    "sg:tags":[
        "pawnbroker"
    ],
    "wof:name":"Discover Discounts & Pawn Shop",
    "wof:placetype":"venue"
},
  "geometry": {"coordinates":[-72.947481,41.296054],"type":"Point"}
}