{
  "type": "Feature",
  "properties": {
    "iso:country":"US",
    "sg:address":"7 High Hill Rd",
    "sg:city":"Canton",
    "sg:classifiers":[
        {
            "category":"Professional",
            "subcategory":"Management & Consulting",
            "type":"Services"
        }
    ],
    "sg:phone":"+1   ",
    "sg:postcode":"06019",
    "sg:province":"CT",
    "wof:name":"N R S Associates LLC",
    "wof:placetype":"venue"
},
  "geometry": {"coordinates":[-72.890767,41.839804],"type":"Point"}
}