{
  "type": "Feature",
  "properties": {
    "addr:full":"39 Woodtick Rd Waterbury CT 06705",
    "addr:housenumber":"39",
    "addr:postcode":"06705",
    "addr:street":"Woodtick Rd",
    "iso:country":"US",
    "sg:address":"39 Woodtick Rd",
    "sg:city":"Waterbury",
    "sg:classifiers":[
        {
            "category":"Personal",
            "subcategory":"Beauty Salon",
            "type":"Services"
        }
    ],
    "sg:phone":"+1 203 757 3782",
    "sg:postcode":"06705",
    "sg:province":"CT",
    "sg:tags":[
        "shop"
    ],
    "wof:name":"Studio At Rack's",
    "wof:placetype":"venue"
},
  "geometry": {"coordinates":[-73.005944,41.553369],"type":"Point"}
}