{
  "type": "Feature",
  "properties": {
    "addr:full":"1561 E Main St Meriden CT 06450",
    "addr:housenumber":"1561",
    "addr:postcode":"06450",
    "addr:street":"E Main St",
    "iso:country":"US",
    "sg:address":"1561 E Main St",
    "sg:city":"Meriden",
    "sg:classifiers":[
        {
            "category":"Building & Trades",
            "subcategory":"Construction",
            "type":"Services"
        }
    ],
    "sg:phone":"+1 203 686 1752",
    "sg:postcode":"06450",
    "sg:province":"CT",
    "sg:tags":[
        "contractor"
    ],
    "wof:name":"Ron Przech Contracting",
    "wof:placetype":"venue"
},
  "geometry": {"coordinates":[-72.74704699999999,41.527199],"type":"Point"}
}