{
  "type": "Feature",
  "properties": {
    "iso:country":"US",
    "sg:address":"146 Fay Rd",
    "sg:city":"Pomfret Center",
    "sg:classifiers":[
        {
            "category":"Building & Trades",
            "subcategory":"Construction",
            "type":"Services"
        }
    ],
    "sg:phone":"+1 860 974 1386",
    "sg:postcode":"06259",
    "sg:province":"CT",
    "sg:tags":[
        "home",
        "family",
        "contractor"
    ],
    "wof:name":"Champany & Son Inc",
    "wof:placetype":"venue"
},
  "geometry": {"coordinates":[-72.027946,41.841401],"type":"Point"}
}