{
  "type": "Feature",
  "properties": {
    "addr:full":"124 Kellogg Dr Wilton CT 06897",
    "addr:housenumber":"124",
    "addr:postcode":"06897",
    "addr:street":"Kellogg Dr",
    "iso:country":"US",
    "sg:address":"124 Kellogg Dr",
    "sg:city":"Wilton",
    "sg:classifiers":[
        {
            "category":"Shopping",
            "type":"Retail Goods"
        }
    ],
    "sg:phone":"+1 203 834 0209",
    "sg:postcode":"06897",
    "sg:province":"CT",
    "sg:tags":[
        "merchandise"
    ],
    "wof:name":"Rendeiro Collectibles Inc",
    "wof:placetype":"venue"
},
  "geometry": {"coordinates":[-73.490917,41.231035],"type":"Point"}
}