{
  "type": "Feature",
  "properties": {
    "iso:country":"US",
    "sg:address":"15 Smoke Ridge Rd",
    "sg:city":"Sherman",
    "sg:classifiers":[
        {
            "category":"Real Estate",
            "subcategory":"Real Estate Agent",
            "type":"Services"
        }
    ],
    "sg:phone":"+1 860 355 1888",
    "sg:postcode":"06784",
    "sg:province":"CT",
    "sg:tags":[
        "investment"
    ],
    "wof:name":"T H Properties",
    "wof:placetype":"venue"
},
  "geometry": {"coordinates":[-73.508517,41.63775],"type":"Point"}
}