{
  "type": "Feature",
  "properties": {
    "iso:country":"US",
    "sg:address":"104 New Hartford Rd",
    "sg:city":"Pleasant Valley",
    "sg:classifiers":[
        {
            "category":"Personal",
            "subcategory":"Beauty Salon",
            "type":"Services"
        }
    ],
    "sg:phone":"+1   ",
    "sg:postcode":"06063",
    "sg:province":"CT",
    "sg:tags":[
        "shop"
    ],
    "wof:name":"Natural Wave",
    "wof:placetype":"venue"
},
  "geometry": {"coordinates":[-72.997624,41.904776],"type":"Point"}
}