{
  "type": "Feature",
  "properties": {
    "addr:full":"2 Boston Post Rd Orange CT 06477",
    "addr:housenumber":"2",
    "addr:postcode":"06477",
    "addr:street":"Boston Post Rd",
    "iso:country":"US",
    "sg:address":"2 Boston Post Rd",
    "sg:city":"Orange",
    "sg:classifiers":[
        {
            "category":"Utilities",
            "subcategory":"Mobile Phone",
            "type":"Services"
        }
    ],
    "sg:phone":"+1 203 799 0859",
    "sg:postcode":"06477",
    "sg:province":"CT",
    "sg:tags":[
        "communication",
        "telephone",
        "cellular",
        "radiotelephone"
    ],
    "wof:name":"Wireless Retail Inc",
    "wof:placetype":"venue"
},
  "geometry": {"coordinates":[-72.98487799999999,41.280059],"type":"Point"}
}