{
  "type": "Feature",
  "properties": {
    "iso:country":"US",
    "sg:address":"38 Magnolia Rd",
    "sg:city":"Trumbull",
    "sg:classifiers":[
        {
            "category":"Organizations",
            "subcategory":"Religious Organization",
            "type":"Services"
        }
    ],
    "sg:phone":"+1   ",
    "sg:postcode":"06611",
    "sg:province":"CT",
    "wof:name":"James P Marshall Rev",
    "wof:placetype":"venue"
},
  "geometry": {"coordinates":[-73.22920499999999,41.265898],"type":"Point"}
}