{
  "type": "Feature",
  "properties": {
    "iso:country":"US",
    "sg:address":"9 Broad St",
    "sg:city":"Danbury",
    "sg:classifiers":[
        {
            "category":"Building & Trades",
            "subcategory":"Construction",
            "type":"Services"
        }
    ],
    "sg:phone":"+1 203 743 5448",
    "sg:postcode":"06810",
    "sg:province":"CT",
    "sg:tags":[
        "siding",
        "contractor"
    ],
    "wof:name":"Advance Siding & Replacement",
    "wof:placetype":"venue"
},
  "geometry": {"coordinates":[-73.425674,41.40598],"type":"Point"}
}