{
  "type": "Feature",
  "properties": {
    "addr:full":"47 Old Ridgefield Rd Wilton CT 06897",
    "addr:housenumber":"47",
    "addr:postcode":"06897",
    "addr:street":"Old Ridgefield Rd Wilton Ct",
    "iso:country":"US",
    "sg:address":"47 Old Ridgefield Rd",
    "sg:city":"Wilton",
    "sg:classifiers":[
        {
            "category":"Insurance",
            "subcategory":"Insurance Agent",
            "type":"Services"
        },
        {
            "category":"Social Services",
            "type":"Services"
        }
    ],
    "sg:phone":"+1 203 563 0885",
    "sg:postcode":"06897",
    "sg:province":"CT",
    "sg:tags":[
        "claim",
        "medical",
        "instruction",
        "health",
        "dental",
        "care"
    ],
    "sg:website":"www.ebs-tpa.com",
    "wof:name":"Employee Benefits Solutions",
    "wof:placetype":"venue"
},
  "geometry": {"coordinates":[-73.435827,41.195043],"type":"Point"}
}