{
  "type": "Feature",
  "properties": {
    "iso:country":"US",
    "sg:address":"220 Middle Patent Rd",
    "sg:city":"Bedford",
    "sg:classifiers":[
        {
            "category":"Health Services",
            "subcategory":"Doctor",
            "type":"Services"
        }
    ],
    "sg:phone":"+1 914 241 0220",
    "sg:postcode":"10506",
    "sg:province":"NY",
    "sg:tags":[
        "dentist"
    ],
    "wof:name":"Robert G Hart DDS",
    "wof:placetype":"venue"
},
  "geometry": {"coordinates":[-73.627309,41.187566],"type":"Point"}
}