{
  "type": "Feature",
  "properties": {
    "iso:country":"US",
    "sg:address":"16 Hospital Ave",
    "sg:city":"Danbury",
    "sg:classifiers":[
        {
            "category":"Health Services",
            "subcategory":"Doctor",
            "type":"Services"
        }
    ],
    "sg:phone":"+1   ",
    "sg:postcode":"06810",
    "sg:province":"CT",
    "sg:tags":[
        "medical"
    ],
    "wof:name":"Victor Ylagan",
    "wof:placetype":"venue"
},
  "geometry": {"coordinates":[-73.447457,41.403287],"type":"Point"}
}