{
  "type": "Feature",
  "properties": {
    "addr:full":"201 W Norwalk Rd Norwalk CT 06850",
    "addr:housenumber":"201",
    "addr:postcode":"06850",
    "addr:street":"W Norwalk Rd",
    "iso:country":"US",
    "sg:address":"201 W Norwalk Rd",
    "sg:city":"Norwalk",
    "sg:classifiers":[
        {
            "category":"Professional",
            "subcategory":"Management & Consulting",
            "type":"Services"
        }
    ],
    "sg:phone":"+1   ",
    "sg:postcode":"06850",
    "sg:province":"CT",
    "wof:name":"A S Caruso Constructions",
    "wof:placetype":"venue"
},
  "geometry": {"coordinates":[-73.46518399999999,41.111408],"type":"Point"}
}