{
  "type": "Feature",
  "properties": {
    "iso:country":"US",
    "sg:address":"28 Toilsome Ave",
    "sg:city":"Norwalk",
    "sg:classifiers":[
        {
            "category":"Social Services",
            "subcategory":"Adult Care",
            "type":"Services"
        }
    ],
    "sg:phone":"+1   ",
    "sg:postcode":"06851",
    "sg:province":"CT",
    "sg:tags":[
        "residential"
    ],
    "wof:name":"Ryan House",
    "wof:placetype":"venue"
},
  "geometry": {"coordinates":[-73.403508,41.141705],"type":"Point"}
}