{
  "type": "Feature",
  "properties": {
    "addr:full":"3540 Main St Stratford CT 06614",
    "addr:housenumber":"3540",
    "addr:postcode":"06614",
    "addr:street":"Main St",
    "iso:country":"US",
    "sg:address":"3540 Main St",
    "sg:city":"Stratford",
    "sg:classifiers":[
        {
            "category":"Shopping",
            "subcategory":"Hobbies, Toys, & Games",
            "type":"Retail Goods"
        }
    ],
    "sg:phone":"+1 203 385 0888",
    "sg:postcode":"06614",
    "sg:province":"CT",
    "sg:tags":[
        "house",
        "doll",
        "accessory"
    ],
    "wof:name":"Cottages To Castles",
    "wof:placetype":"venue"
},
  "geometry": {"coordinates":[-73.130843,41.2082],"type":"Point"}
}