{
  "type": "Feature",
  "properties": {
    "iso:country":"US",
    "sg:address":"3288 Main St",
    "sg:city":"Stratford",
    "sg:classifiers":[
        {
            "category":"Insurance",
            "subcategory":"Insurance Agent",
            "type":"Services"
        }
    ],
    "sg:phone":"+1 203 377 2300",
    "sg:postcode":"06614",
    "sg:province":"CT",
    "wof:name":"Lamburt Corp",
    "wof:placetype":"venue"
},
  "geometry": {"coordinates":[-73.131918,41.206492],"type":"Point"}
}