{
  "type": "Feature",
  "properties": {
    "addr:full":"20 N Plains Industrial Rd Wallingford CT 06492",
    "addr:housenumber":"20",
    "addr:postcode":"06492",
    "addr:street":"N Plains Industrial Rd",
    "iso:country":"US",
    "sg:address":"20 N Plains Industrial Rd",
    "sg:city":"Wallingford",
    "sg:classifiers":[
        {
            "category":"Shopping",
            "subcategory":"Books",
            "type":"Retail Goods"
        }
    ],
    "sg:phone":"+1 203 265 2013",
    "sg:postcode":"06492",
    "sg:province":"CT",
    "wof:name":"Barnett Books",
    "wof:placetype":"venue"
},
  "geometry": {"coordinates":[-72.813523,41.485856],"type":"Point"}
}