{
  "type": "Feature",
  "properties": {
    "addr:full":"125 Nells Rock Rd Shelton CT 06484",
    "addr:housenumber":"125",
    "addr:postcode":"06484",
    "addr:street":"Nells Rock Rd",
    "iso:country":"US",
    "sg:address":"125 Nells Rock Rd",
    "sg:city":"Shelton",
    "sg:classifiers":[
        {
            "category":"Health Services",
            "subcategory":"Chiropractor",
            "type":"Services"
        }
    ],
    "sg:phone":"+1 203 926 9295",
    "sg:postcode":"06484",
    "sg:province":"CT",
    "wof:name":"Jeff A Forte DC",
    "wof:placetype":"venue"
},
  "geometry": {"coordinates":[-73.11195499999999,41.302733],"type":"Point"}
}