{
  "type": "Feature",
  "properties": {
    "iso:country":"US",
    "sg:address":"33 Winton Rd",
    "sg:city":"East Windsor",
    "sg:classifiers":[
        {
            "category":"Organizations",
            "subcategory":"Religious Organization",
            "type":"Services"
        }
    ],
    "sg:phone":"+1   ",
    "sg:postcode":"06088",
    "sg:province":"CT",
    "wof:name":"Reorgnized Church Jesus Christ",
    "wof:placetype":"venue"
},
  "geometry": {"coordinates":[-72.613331,41.89718],"type":"Point"}
}