{
  "type": "Feature",
  "properties": {
    "addr:full":"100 Three Mile Hill Rd Middlebury CT 06762",
    "addr:housenumber":"100",
    "addr:postcode":"06762",
    "addr:street":"Three Mile Hill Rd",
    "iso:country":"US",
    "sg:address":"100 Three Mile Hill Rd",
    "sg:city":"Middlebury",
    "sg:classifiers":[
        {
            "category":"Professional",
            "subcategory":"Business Services",
            "type":"Services"
        }
    ],
    "sg:phone":"+1   ",
    "sg:postcode":"06762",
    "sg:province":"CT",
    "wof:name":"GSM Enterprises LLC",
    "wof:placetype":"venue"
},
  "geometry": {"coordinates":[-73.10239199999999,41.545512],"type":"Point"}
}