{
  "type": "Feature",
  "properties": {
    "addr:full":"303 Tunxis Rd Farmington CT 06032",
    "addr:housenumber":"303",
    "addr:postcode":"06032",
    "addr:street":"Tunxis Rd",
    "iso:country":"US",
    "sg:address":"303 Tunxis Rd",
    "sg:city":"Farmington",
    "sg:classifiers":[
        {
            "category":"Organizations",
            "subcategory":"Religious Organization",
            "type":"Services"
        }
    ],
    "sg:phone":"+1   ",
    "sg:postcode":"06032",
    "sg:province":"CT",
    "wof:name":"Passinist Wrshp-Hlth Care Offs",
    "wof:placetype":"venue"
},
  "geometry": {"coordinates":[-72.772699,41.736861],"type":"Point"}
}