{
  "type": "Feature",
  "properties": {
    "addr:full":"22 Falls Bashan Rd Moodus CT 06469",
    "addr:housenumber":"22",
    "addr:postcode":"06469",
    "addr:street":"Falls Bashan Rd Moodus Ct",
    "iso:country":"US",
    "sg:address":"22 Falls Bashan Rd",
    "sg:city":"Moodus",
    "sg:classifiers":[
        {
            "category":"Personal",
            "type":"Services"
        }
    ],
    "sg:phone":"+1   ",
    "sg:postcode":"06469",
    "sg:province":"CT",
    "wof:name":"Intouch Body Therapies LLC",
    "wof:placetype":"venue"
},
  "geometry": {"coordinates":[-72.424125,41.506609],"type":"Point"}
}