{
  "type": "Feature",
  "properties": {
    "iso:country":"US",
    "sg:address":"191 Four Mile Rd",
    "sg:city":"Hartford",
    "sg:classifiers":[
        {
            "category":"Professional",
            "type":"Services"
        }
    ],
    "sg:phone":"+1   ",
    "sg:postcode":"06107",
    "sg:province":"CT",
    "wof:name":"Executive Support Services LLC",
    "wof:placetype":"venue"
},
  "geometry": {"coordinates":[-72.747208,41.753771],"type":"Point"}
}