{
  "type": "Feature",
  "properties": {
    "iso:country":"US",
    "sg:address":"1237 E Main St",
    "sg:city":"Meriden",
    "sg:classifiers":[
        {
            "category":"Insurance",
            "subcategory":"Insurance Agent",
            "type":"Services"
        }
    ],
    "sg:phone":"+1 203 634 4082",
    "sg:postcode":"06450",
    "sg:province":"CT",
    "wof:name":"James F Canning Agency & Assoc",
    "wof:placetype":"venue"
},
  "geometry": {"coordinates":[-72.759945,41.525541],"type":"Point"}
}