{
  "type": "Feature",
  "properties": {
    "iso:country":"US",
    "sg:address":"297 Ashley Falls Rd",
    "sg:city":"Canaan",
    "sg:classifiers":[
        {
            "category":"Autos & Motor Vehicles",
            "subcategory":"Fuel & Gas Station",
            "type":"Retail Goods"
        }
    ],
    "sg:phone":"+1 860 824 4944",
    "sg:postcode":"06018",
    "sg:province":"CT",
    "wof:name":"Canaan Auto Supply",
    "wof:placetype":"venue"
},
  "geometry": {"coordinates":[-73.325864,42.038648],"type":"Point"}
}