{
  "type": "Feature",
  "properties": {
    "addr:full":"80 Webber Rd Tolland CT 06084",
    "addr:housenumber":"80",
    "addr:postcode":"06084",
    "addr:street":"Webber Rd Tolland Ct",
    "iso:country":"US",
    "sg:address":"80 Webber Rd",
    "sg:city":"Tolland",
    "sg:classifiers":[
        {
            "category":"Professional",
            "subcategory":"Business Services",
            "type":"Services"
        }
    ],
    "sg:phone":"+1   ",
    "sg:postcode":"06084",
    "sg:province":"CT",
    "wof:name":"A & R Environmental LLC",
    "wof:placetype":"venue"
},
  "geometry": {"coordinates":[-72.394316,41.90431],"type":"Point"}
}