{
  "type": "Feature",
  "properties": {
    "addr:full":"30 New Park Ave Hartford CT 06106",
    "addr:housenumber":"30",
    "addr:postcode":"06106",
    "addr:street":"New Park Ave;Ct",
    "iso:country":"US",
    "sg:address":"30 New Park Ave",
    "sg:city":"Hartford",
    "sg:classifiers":[
        {
            "category":"Building & Trades",
            "subcategory":"Cleaning & Sanitation",
            "type":"Services"
        }
    ],
    "sg:phone":"+1   ",
    "sg:postcode":"06106",
    "sg:province":"CT",
    "sg:tags":[
        "maintenance"
    ],
    "wof:name":"A R S Janitorial",
    "wof:placetype":"venue"
},
  "geometry": {"coordinates":[-72.706681,41.756225],"type":"Point"}
}