{
  "type": "Feature",
  "properties": {
    "iso:country":"US",
    "sg:address":"1293 Main St",
    "sg:city":"Hartford",
    "sg:classifiers":[
        {
            "category":"Food & Beverages",
            "subcategory":"Liquor & Beverages",
            "type":"Retail Goods"
        }
    ],
    "sg:phone":"+1 860 527 0677",
    "sg:postcode":"06103",
    "sg:province":"CT",
    "sg:tags":[
        "store",
        "package"
    ],
    "wof:name":"Bashners",
    "wof:placetype":"venue"
},
  "geometry": {"coordinates":[-72.67665,41.772915],"type":"Point"}
}