{
  "type": "Feature",
  "properties": {
    "addr:full":"105 Danbury Rd Wilton CT 06897",
    "addr:housenumber":"105",
    "addr:postcode":"06897",
    "addr:street":"Danbury Rd Wilton Ct",
    "iso:country":"US",
    "sg:address":"105 Danbury Rd",
    "sg:city":"Wilton",
    "sg:classifiers":[
        {
            "category":"Health Services",
            "subcategory":"Doctor",
            "type":"Services"
        }
    ],
    "sg:phone":"+1   ",
    "sg:postcode":"06897",
    "sg:province":"CT",
    "wof:name":"Cucharale Nicholas A DMD",
    "wof:placetype":"venue"
},
  "geometry": {"coordinates":[-73.416535,41.175008],"type":"Point"}
}