{
  "type": "Feature",
  "properties": {
    "addr:full":"2100 Thomaston Ave Waterbury CT 06704",
    "addr:housenumber":"2100",
    "addr:postcode":"06704",
    "addr:street":"Thomaston Ave",
    "iso:country":"US",
    "sg:address":"2100 Thomaston Ave",
    "sg:city":"Waterbury",
    "sg:classifiers":[
        {
            "category":"Freight",
            "type":"Transportation"
        },
        {
            "category":"Professional",
            "subcategory":"Business Services",
            "type":"Services"
        }
    ],
    "sg:phone":"+1 203 753 0303",
    "sg:postcode":"06704",
    "sg:province":"CT",
    "sg:tags":[
        "packaging"
    ],
    "wof:name":"Craters & Freighters Of Ct",
    "wof:placetype":"venue"
},
  "geometry": {"coordinates":[-73.05838,41.605805],"type":"Point"}
}