{
  "type": "Feature",
  "properties": {
    "iso:country":"US",
    "sg:address":"110 Main St",
    "sg:city":"East Windsor",
    "sg:classifiers":[
        {
            "category":"Personal",
            "subcategory":"Beauty Salon",
            "type":"Services"
        }
    ],
    "sg:phone":"+1   ",
    "sg:postcode":"06088",
    "sg:province":"CT",
    "sg:tags":[
        "shop"
    ],
    "wof:name":"Express Nails",
    "wof:placetype":"venue"
},
  "geometry": {"coordinates":[-72.61808600000001,41.928396],"type":"Point"}
}