{
  "type": "Feature",
  "properties": {
    "iso:country":"US",
    "sg:address":"5 Homesdale Ave",
    "sg:city":"Southington",
    "sg:classifiers":[
        {
            "category":"Arts & Performance",
            "subcategory":"Theater",
            "type":"Entertainment"
        }
    ],
    "sg:phone":"+1   ",
    "sg:postcode":"06489",
    "sg:province":"CT",
    "sg:tags":[
        "group"
    ],
    "wof:name":"33 1/3 Music Service",
    "wof:placetype":"venue"
},
  "geometry": {"coordinates":[-72.864814,41.593945],"type":"Point"}
}