{
  "type": "Feature",
  "properties": {
    "addr:full":"1033 Farmington Ave Bristol CT 06010",
    "addr:housenumber":"1033",
    "addr:postcode":"06010",
    "addr:street":"Farmington Ave Bristol Ct",
    "iso:country":"US",
    "sg:address":"1033 Farmington Ave",
    "sg:city":"Bristol",
    "sg:classifiers":[
        {
            "category":"Restaurant",
            "type":"Food & Drink"
        }
    ],
    "sg:menulink":"http://www.allmenus.com/ct/bristol/166430-burger-king/menu/",
    "sg:phone":"+1 860 582 0802",
    "sg:postcode":"06010",
    "sg:province":"CT",
    "sg:tags":[
        "burger",
        "american"
    ],
    "wof:name":"Burger King",
    "wof:placetype":"venue"
},
  "geometry": {"coordinates":[-72.909459,41.69566],"type":"Point"}
}