{
  "type": "Feature",
  "properties": {
    "addr:full":"70 New Canaan Ave Norwalk CT 06850",
    "addr:housenumber":"70",
    "addr:postcode":"06850",
    "addr:street":"New Canaan Ave",
    "iso:country":"US",
    "sg:address":"70 New Canaan Ave",
    "sg:city":"Norwalk",
    "sg:classifiers":[
        {
            "category":"Banks & Credit Unions",
            "subcategory":"Investment Brokerage",
            "type":"Services"
        }
    ],
    "sg:phone":"+1 203 847 5300",
    "sg:postcode":"06850",
    "sg:province":"CT",
    "sg:tags":[
        "counselor",
        "stock",
        "bond"
    ],
    "sg:website":"www.oldham-mutual.com",
    "wof:name":"Oldham Resource Group Inc",
    "wof:placetype":"venue"
},
  "geometry": {"coordinates":[-73.43039400000001,41.126629],"type":"Point"}
}