{
  "type": "Feature",
  "properties": {
    "addr:full":"516 Old Toll Rd Madison CT 06443",
    "addr:housenumber":"516",
    "addr:postcode":"06443",
    "addr:street":"Old Toll Rd",
    "iso:country":"US",
    "sg:address":"516 Old Toll Rd",
    "sg:city":"Madison",
    "sg:classifiers":[
        {
            "category":"Retail",
            "subcategory":"Laundry & Dry Cleaning",
            "type":"Services"
        }
    ],
    "sg:phone":"+1 203 421 3634",
    "sg:postcode":"06443",
    "sg:province":"CT",
    "sg:tags":[
        "drycleaning",
        "plant",
        "cleaners"
    ],
    "wof:name":"Crystal Hangers",
    "wof:placetype":"venue"
},
  "geometry": {"coordinates":[-72.627588,41.359701],"type":"Point"}
}