{
  "type": "Feature",
  "properties": {
    "addr:full":"161 Hodge Ave Ansonia CT 06401",
    "addr:housenumber":"161",
    "addr:postcode":"06401",
    "addr:street":"Hodge Ave",
    "iso:country":"US",
    "sg:address":"161 Hodge Ave",
    "sg:city":"Ansonia",
    "sg:classifiers":[
        {
            "category":"Building & Trades",
            "subcategory":"Cleaning & Sanitation",
            "type":"Services"
        }
    ],
    "sg:phone":"+1 203 732 4026",
    "sg:postcode":"06401",
    "sg:province":"CT",
    "sg:tags":[
        "house"
    ],
    "wof:name":"Personal House Cleaning",
    "wof:placetype":"venue"
},
  "geometry": {"coordinates":[-73.072479,41.336487],"type":"Point"}
}