{
  "type": "Feature",
  "properties": {
    "addr:full":"103 Hamden Ave Waterbury CT 06704",
    "addr:housenumber":"103",
    "addr:postcode":"06704",
    "addr:street":"Hamden Ave",
    "iso:country":"US",
    "sg:address":"103 Hamden Ave",
    "sg:city":"Waterbury",
    "sg:classifiers":[
        {
            "category":"Freight",
            "type":"Transportation"
        }
    ],
    "sg:phone":"+1 203 757 7976",
    "sg:postcode":"06704",
    "sg:province":"CT",
    "wof:name":"Reliable Freight Services",
    "wof:placetype":"venue"
},
  "geometry": {"coordinates":[-73.023737,41.573303],"type":"Point"}
}