{
  "type": "Feature",
  "properties": {
    "addr:full":"799 Hopmeadow St Simsbury CT 06070",
    "addr:housenumber":"799",
    "addr:postcode":"06070",
    "addr:street":"Hopmeadow St Simsbury Ct",
    "iso:country":"US",
    "sg:address":"799 Hopmeadow St",
    "sg:city":"Simsbury",
    "sg:classifiers":[
        {
            "category":"Social Services",
            "subcategory":"Child Care",
            "type":"Services"
        }
    ],
    "sg:phone":"+1 860 408 9467",
    "sg:postcode":"06070",
    "sg:province":"CT",
    "sg:tags":[
        "day"
    ],
    "wof:name":"Little Lambs & Ivy Child Care Center",
    "wof:placetype":"venue"
},
  "geometry": {"coordinates":[-72.801498,41.8759],"type":"Point"}
}