{
  "type": "Feature",
  "properties": {
    "addr:full":"1185 Nichols Ave Stratford CT 06614",
    "addr:housenumber":"1185",
    "addr:postcode":"06614",
    "addr:street":"Nichols Ave",
    "iso:country":"US",
    "sg:address":"1185 Nichols Ave",
    "sg:city":"Stratford",
    "sg:classifiers":[
        {
            "category":"Professional",
            "type":"Services"
        }
    ],
    "sg:phone":"+1 203 375 8865",
    "sg:postcode":"06614",
    "sg:province":"CT",
    "wof:name":"A Untenberg",
    "wof:placetype":"venue"
},
  "geometry": {"coordinates":[-73.143928,41.210931],"type":"Point"}
}