{
  "type": "Feature",
  "properties": {
    "iso:country":"US",
    "sg:address":"9 Stonegate Cir",
    "sg:city":"Branford",
    "sg:classifiers":[
        {
            "category":"Professional",
            "subcategory":"Computer Services",
            "type":"Services"
        }
    ],
    "sg:phone":"+1   ",
    "sg:postcode":"06405",
    "sg:province":"CT",
    "sg:tags":[
        "related"
    ],
    "wof:name":"Walter Jakubiak",
    "wof:placetype":"venue"
},
  "geometry": {"coordinates":[-72.83412800000001,41.269067],"type":"Point"}
}