{
  "type": "Feature",
  "properties": {
    "addr:full":"15 Alma Rock Rd Stamford CT 06903",
    "addr:housenumber":"15",
    "addr:postcode":"06903",
    "addr:street":"Alma Rock Rd",
    "iso:country":"US",
    "sg:address":"15 Alma Rock Rd",
    "sg:city":"Stamford",
    "sg:classifiers":[
        {
            "category":"Building & Trades",
            "subcategory":"Landscaping Services",
            "type":"Services"
        }
    ],
    "sg:phone":"+1 203 968 1696",
    "sg:postcode":"06903",
    "sg:province":"CT",
    "sg:tags":[
        "landscape",
        "contractor"
    ],
    "wof:name":"D'Amico Landscaping",
    "wof:placetype":"venue"
},
  "geometry": {"coordinates":[-73.548073,41.139793],"type":"Point"}
}