{
  "type": "Feature",
  "properties": {
    "addr:full":"21 Garfield St Newington CT 06111",
    "addr:housenumber":"21",
    "addr:postcode":"06111",
    "addr:street":"Garfield St",
    "iso:country":"US",
    "sg:address":"21 Garfield St",
    "sg:city":"Newington",
    "sg:classifiers":[
        {
            "category":"Shopping",
            "subcategory":"Catalog Store",
            "type":"Retail Goods"
        }
    ],
    "sg:phone":"+1   ",
    "sg:postcode":"06111",
    "sg:province":"CT",
    "sg:tags":[
        "mail",
        "repair",
        "radio",
        "communications"
    ],
    "wof:name":"Lentini Communications Inc",
    "wof:placetype":"venue"
},
  "geometry": {"coordinates":[-72.72454,41.695846],"type":"Point"}
}