{
  "type": "Feature",
  "properties": {
    "addr:full":"256 Robertson St Bristol CT 06010",
    "addr:housenumber":"256",
    "addr:postcode":"06010",
    "addr:street":"Robertson St",
    "iso:country":"US",
    "sg:address":"256 Robertson St",
    "sg:city":"Bristol",
    "sg:classifiers":[
        {
            "category":"Building & Trades",
            "subcategory":"Construction",
            "type":"Services"
        }
    ],
    "sg:phone":"+1 860 589 8467",
    "sg:postcode":"06010",
    "sg:province":"CT",
    "sg:tags":[
        "house"
    ],
    "wof:name":"Augustyn Skurski",
    "wof:placetype":"venue"
},
  "geometry": {"coordinates":[-72.89200200000001,41.683361],"type":"Point"}
}