{
  "type": "Feature",
  "properties": {
    "addr:full":"136 Riverside Ave Bristol CT 06010",
    "addr:housenumber":"136",
    "addr:postcode":"06010",
    "addr:street":"Riverside Ave Bristol Ct",
    "iso:country":"US",
    "sg:address":"136 Riverside Ave",
    "sg:city":"Bristol",
    "sg:classifiers":[
        {
            "category":"Professional",
            "subcategory":"Computer Services",
            "type":"Services"
        }
    ],
    "sg:phone":"+1   ",
    "sg:postcode":"06010",
    "sg:province":"CT",
    "sg:tags":[
        "development",
        "licensing",
        "software"
    ],
    "wof:name":"Bosins LLC",
    "wof:placetype":"venue"
},
  "geometry": {"coordinates":[-72.936623,41.670452],"type":"Point"}
}