{
  "type": "Feature",
  "properties": {
    "iso:country":"US",
    "sg:address":"237 Woodcreek Rd",
    "sg:city":"Bethlehem",
    "sg:classifiers":[
        {
            "category":"Retail",
            "subcategory":"Repair Shop",
            "type":"Services"
        }
    ],
    "sg:phone":"+1   ",
    "sg:postcode":"06751",
    "sg:province":"CT",
    "wof:name":"Mahards Piano Service",
    "wof:placetype":"venue"
},
  "geometry": {"coordinates":[-73.22829400000001,41.645997],"type":"Point"}
}