{
  "type": "Feature",
  "properties": {
    "addr:full":"29 W Main St Vernon Rockville CT 06066",
    "addr:housenumber":"29",
    "addr:postcode":"06066",
    "addr:street":"W Main St",
    "iso:country":"US",
    "sg:address":"29 W Main St",
    "sg:city":"Vernon Rockville",
    "sg:classifiers":[
        {
            "category":"Shopping",
            "subcategory":"Gifts & Souvenirs",
            "type":"Retail Goods"
        }
    ],
    "sg:phone":"+1 860 875 4745",
    "sg:postcode":"06066",
    "sg:province":"CT",
    "sg:tags":[
        "balloon",
        "furniture",
        "rattan",
        "decal",
        "t"
    ],
    "wof:name":"Crystals Personal Touch",
    "wof:placetype":"venue"
},
  "geometry": {"coordinates":[-72.449572,41.866987],"type":"Point"}
}