{
  "type": "Feature",
  "properties": {
    "addr:full":"122 W Norwalk Rd Norwalk CT 06850",
    "addr:housenumber":"122",
    "addr:postcode":"06850",
    "addr:street":"W Norwalk Rd",
    "iso:country":"US",
    "sg:address":"122 W Norwalk Rd",
    "sg:city":"Norwalk",
    "sg:classifiers":[
        {
            "category":"Health Services",
            "subcategory":"Doctor",
            "type":"Services"
        }
    ],
    "sg:phone":"+1 203 855 8877",
    "sg:postcode":"06850",
    "sg:province":"CT",
    "sg:tags":[
        "dentist"
    ],
    "wof:name":"Santo De Lallo DMD",
    "wof:placetype":"venue"
},
  "geometry": {"coordinates":[-73.458878,41.103778],"type":"Point"}
}