{
  "type": "Feature",
  "properties": {
    "addr:full":"207 E Main St Middletown CT 06457",
    "addr:housenumber":"207",
    "addr:postcode":"06457",
    "addr:street":"E Main St",
    "iso:country":"US",
    "sg:address":"207 E Main St",
    "sg:city":"Middletown",
    "sg:classifiers":[
        {
            "category":"Personal",
            "subcategory":"Beauty Salon",
            "type":"Services"
        }
    ],
    "sg:phone":"+1   ",
    "sg:postcode":"06457",
    "sg:province":"CT",
    "sg:tags":[
        "shop"
    ],
    "wof:name":"Stylz By Q",
    "wof:placetype":"venue"
},
  "geometry": {"coordinates":[-72.64098199999999,41.550708],"type":"Point"}
}