{
  "type": "Feature",
  "properties": {
    "iso:country":"US",
    "sg:address":"431 Sherman Hill Rd",
    "sg:city":"Woodbury",
    "sg:classifiers":[
        {
            "category":"Retail",
            "subcategory":"Veterinary Services",
            "type":"Services"
        }
    ],
    "sg:phone":"+1 203 263 4222",
    "sg:postcode":"06798",
    "sg:province":"CT",
    "wof:name":"Kennett Paul D Dvm",
    "wof:placetype":"venue"
},
  "geometry": {"coordinates":[-73.16050799999999,41.524337],"type":"Point"}
}