{
  "type": "Feature",
  "properties": {
    "iso:country":"US",
    "sg:address":"1776 Boston Tpke",
    "sg:city":"Coventry",
    "sg:classifiers":[
        {
            "category":"Professional",
            "subcategory":"Computer Services",
            "type":"Services"
        }
    ],
    "sg:phone":"+1   ",
    "sg:postcode":"06238",
    "sg:province":"CT",
    "sg:tags":[
        "programming",
        "custom"
    ],
    "wof:name":"Etaxsys",
    "wof:placetype":"venue"
},
  "geometry": {"coordinates":[-72.37685500000001,41.798307],"type":"Point"}
}