{
  "type": "Feature",
  "properties": {
    "addr:full":"376 Main St Ansonia CT 06401",
    "addr:housenumber":"376",
    "addr:postcode":"06401",
    "addr:street":"Main St",
    "iso:country":"US",
    "sg:address":"376 Main St",
    "sg:city":"Ansonia",
    "sg:classifiers":[
        {
            "category":"Building & Trades",
            "subcategory":"Electrical",
            "type":"Services"
        }
    ],
    "sg:phone":"+1 203 734 4067",
    "sg:postcode":"06401",
    "sg:province":"CT",
    "sg:tags":[
        "electric",
        "contractor"
    ],
    "wof:name":"R S Electrical Contractors",
    "wof:placetype":"venue"
},
  "geometry": {"coordinates":[-73.077927,41.341062],"type":"Point"}
}