{
  "type": "Feature",
  "properties": {
    "addr:full":"150 Munson Street, 25 Science Park at Yale New Haven CT 06511",
    "addr:housenumber":"150;25",
    "addr:postcode":"06511",
    "addr:street":"Munson Street;Science Park;Haven",
    "iso:country":"US",
    "sg:address":"150 Munson Street, 25 Science Park at Yale",
    "sg:city":"New Haven",
    "sg:classifiers":[
        {
            "category":"Professional",
            "subcategory":"Computer Services",
            "type":"Services"
        }
    ],
    "sg:phone":"+1 203 903 0124",
    "sg:postcode":"06511",
    "sg:province":"CT",
    "sg:website":"http://www.continuity.net",
    "wof:name":"Continuity Engine",
    "wof:placetype":"venue"
},
  "geometry": {"coordinates":[-72.92924499999999,41.321497],"type":"Point"}
}