{
  "type": "Feature",
  "properties": {
    "iso:country":"US",
    "sg:address":"165 Main St",
    "sg:city":"Monroe",
    "sg:classifiers":[
        {
            "category":"Retail",
            "subcategory":"Auto Repair",
            "type":"Services"
        }
    ],
    "sg:phone":"+1 203 459 0336",
    "sg:postcode":"06468",
    "sg:province":"CT",
    "sg:tags":[
        "brake"
    ],
    "wof:name":"APM Monroe Auto Svc",
    "wof:placetype":"venue"
},
  "geometry": {"coordinates":[-73.25610399999999,41.306964],"type":"Point"}
}