{
  "type": "Feature",
  "properties": {
    "iso:country":"US",
    "sg:address":"164 Melius Rd",
    "sg:city":"Warren",
    "sg:classifiers":[
        {
            "category":"Farming",
            "subcategory":"Nursery",
            "type":"Manufacturing & Wholesale Goods"
        }
    ],
    "sg:phone":"+1 860 868 9899",
    "sg:postcode":"06754",
    "sg:province":"CT",
    "sg:tags":[
        "grower",
        "nursery-wholesale"
    ],
    "wof:name":"Warren Woods Nursery",
    "wof:placetype":"venue"
},
  "geometry": {"coordinates":[-73.337551,41.763865],"type":"Point"}
}