{
  "type": "Feature",
  "properties": {
    "addr:full":"725 Hebron Ave Glastonbury CT 06033",
    "addr:housenumber":"725",
    "addr:postcode":"06033",
    "addr:street":"Hebron Ave",
    "iso:country":"US",
    "sg:address":"725 Hebron Ave",
    "sg:city":"Glastonbury",
    "sg:classifiers":[
        {
            "category":"Retail",
            "subcategory":"Funeral Services",
            "type":"Services"
        }
    ],
    "sg:phone":"+1   ",
    "sg:postcode":"06033",
    "sg:province":"CT",
    "wof:name":"Mulryan Funeral Home",
    "wof:placetype":"venue"
},
  "geometry": {"coordinates":[-72.58720099999999,41.715169],"type":"Point"}
}