{
  "type": "Feature",
  "properties": {
    "addr:full":"61 Old Quarry Rd Woodbridge CT 06525",
    "addr:housenumber":"61",
    "addr:postcode":"06525",
    "addr:street":"Old Quarry Rd",
    "iso:country":"US",
    "sg:address":"61 Old Quarry Rd",
    "sg:city":"Woodbridge",
    "sg:classifiers":[
        {
            "category":"Professional",
            "type":"Services"
        }
    ],
    "sg:phone":"+1 203 393 2498",
    "sg:postcode":"06525",
    "sg:province":"CT",
    "wof:name":"Stock Steven Schnittman &",
    "wof:placetype":"venue"
},
  "geometry": {"coordinates":[-73.044329,41.373623],"type":"Point"}
}