{
  "type": "Feature",
  "properties": {
    "iso:country":"US",
    "sg:address":"163 Wakeley Dr",
    "sg:city":"Southbury",
    "sg:classifiers":[
        {
            "category":"Shopping",
            "type":"Retail Goods"
        }
    ],
    "sg:phone":"+1 203 267 5656",
    "sg:postcode":"06488",
    "sg:province":"CT",
    "sg:tags":[
        "merchandise"
    ],
    "wof:name":"TLC Pet Sitters",
    "wof:placetype":"venue"
},
  "geometry": {"coordinates":[-73.246343,41.444216],"type":"Point"}
}