{
  "type": "Feature",
  "properties": {
    "iso:country":"US",
    "sg:address":"606 Post Rd E",
    "sg:city":"Westport",
    "sg:classifiers":[
        {
            "category":"Professional",
            "subcategory":"Management & Consulting",
            "type":"Services"
        }
    ],
    "sg:phone":"+1 203 221 0808",
    "sg:postcode":"06880",
    "sg:province":"CT",
    "sg:tags":[
        "consultant",
        "business"
    ],
    "wof:name":"Insource Partners",
    "wof:placetype":"venue"
},
  "geometry": {"coordinates":[-73.343678,41.138243],"type":"Point"}
}