{
  "type": "Feature",
  "properties": {
    "iso:country":"US",
    "sg:address":"22 East Ave",
    "sg:city":"New Canaan",
    "sg:classifiers":[
        {
            "category":"Food & Beverages",
            "subcategory":"Specialty",
            "type":"Retail Goods"
        }
    ],
    "sg:phone":"+1 203 972 1233",
    "sg:postcode":"06840",
    "sg:province":"NY",
    "sg:tags":[
        "eating"
    ],
    "wof:name":"Plum Tree Catering",
    "wof:placetype":"venue"
},
  "geometry": {"coordinates":[-73.491675,41.147774],"type":"Point"}
}