{
  "type": "Feature",
  "properties": {
    "addr:full":"497 W Main St Meriden CT 06451",
    "addr:housenumber":"497",
    "addr:postcode":"06451",
    "addr:street":"W Main St",
    "iso:country":"US",
    "sg:address":"497 W Main St",
    "sg:city":"Meriden",
    "sg:classifiers":[
        {
            "category":"Personal",
            "subcategory":"Beauty Salon",
            "type":"Services"
        }
    ],
    "sg:phone":"+1 203 235 1454",
    "sg:postcode":"06451",
    "sg:province":"CT",
    "sg:tags":[
        "shop"
    ],
    "wof:name":"Paul's Hair Design",
    "wof:placetype":"venue"
},
  "geometry": {"coordinates":[-72.818636,41.540415],"type":"Point"}
}