{
  "type": "Feature",
  "properties": {
    "iso:country":"US",
    "sg:address":"19 Staples Ct",
    "sg:city":"Norwalk",
    "sg:classifiers":[
        {
            "category":"Professional",
            "type":"Services"
        }
    ],
    "sg:phone":"+1 203 838 9347",
    "sg:postcode":"06855",
    "sg:province":"CT",
    "wof:name":"Rosemary Eula",
    "wof:placetype":"venue"
},
  "geometry": {"coordinates":[-73.39997700000001,41.097969],"type":"Point"}
}