{
  "type": "Feature",
  "properties": {
    "addr:full":"19 Pumpkin Hill Rd Trumbull CT 06611",
    "addr:housenumber":"19",
    "addr:postcode":"06611",
    "addr:street":"Pumpkin Hill Rd",
    "iso:country":"US",
    "sg:address":"19 Pumpkin Hill Rd",
    "sg:city":"Trumbull",
    "sg:classifiers":[
        {
            "category":"Health Services",
            "subcategory":"Doctor",
            "type":"Services"
        }
    ],
    "sg:phone":"+1   ",
    "sg:postcode":"06611",
    "sg:province":"CT",
    "sg:tags":[
        "medical"
    ],
    "wof:name":"Germano A Guadagnoli MD",
    "wof:placetype":"venue"
},
  "geometry": {"coordinates":[-73.242318,41.27843],"type":"Point"}
}