{
  "type": "Feature",
  "properties": {
    "iso:country":"US",
    "sg:address":"46 Gracey Ave",
    "sg:city":"Meriden",
    "sg:classifiers":[
        {
            "category":"Manufacturing",
            "subcategory":"Retail Goods",
            "type":"Manufacturing & Wholesale Goods"
        }
    ],
    "sg:phone":"+1 203 634 4468",
    "sg:postcode":"06451",
    "sg:province":"CT",
    "sg:tags":[
        "assembly",
        "fabricating"
    ],
    "sg:website":"www.hintperipherals.com",
    "wof:name":"Hint Peripherals Corp",
    "wof:placetype":"venue"
},
  "geometry": {"coordinates":[-72.79330400000001,41.552347],"type":"Point"}
}