{
  "type": "Feature",
  "properties": {
    "iso:country":"US",
    "sg:address":"275 Middlesex Tpke",
    "sg:city":"Old Saybrook",
    "sg:classifiers":[
        {
            "category":"Autos & Motor Vehicles",
            "subcategory":"Automobile Sales",
            "type":"Retail Goods"
        },
        {
            "category":"Retail",
            "subcategory":"Auto Repair",
            "type":"Services"
        }
    ],
    "sg:phone":"+1 860 388 1300",
    "sg:postcode":"06475",
    "sg:province":"CT",
    "sg:tags":[
        "body",
        "shop",
        "car"
    ],
    "sg:website":"www.kiaofoldsaybrook.com",
    "wof:name":"Kia of Old Saybrook",
    "wof:placetype":"venue"
},
  "geometry": {"coordinates":[-72.381897,41.3078],"type":"Point"}
}