{
  "type": "Feature",
  "properties": {
    "addr:full":"3 E Main St Avon CT 06001",
    "addr:housenumber":"3",
    "addr:postcode":"06001",
    "addr:street":"E Main St",
    "iso:country":"US",
    "sg:address":"3 E Main St",
    "sg:city":"Avon",
    "sg:classifiers":[
        {
            "category":"Museum",
            "type":"Entertainment"
        }
    ],
    "sg:phone":"+1   ",
    "sg:postcode":"06001",
    "sg:province":"CT",
    "sg:tags":[
        "organization",
        "membership",
        "gallery"
    ],
    "wof:name":"Avon Historical Society",
    "wof:placetype":"venue"
},
  "geometry": {"coordinates":[-72.830027,41.809309],"type":"Point"}
}