{
  "type": "Feature",
  "properties": {
    "addr:full":"55 Rentschler St East Hartford CT 06118",
    "addr:housenumber":"55",
    "addr:postcode":"06118",
    "addr:street":"Rentschler St East;Ct",
    "iso:country":"US",
    "sg:address":"55 Rentschler St",
    "sg:city":"East Hartford",
    "sg:classifiers":[
        {
            "category":"Building & Trades",
            "subcategory":"Construction",
            "type":"Services"
        }
    ],
    "sg:phone":"+1 860 568 2515",
    "sg:postcode":"06118",
    "sg:province":"CT",
    "sg:tags":[
        "contractor"
    ],
    "wof:name":"K P King Masonry",
    "wof:placetype":"venue"
},
  "geometry": {"coordinates":[-72.60372,41.745384],"type":"Point"}
}