{
  "type": "Feature",
  "properties": {
    "addr:full":"137 Goose Ln Tolland CT 06084",
    "addr:housenumber":"137",
    "addr:postcode":"06084",
    "addr:street":"Goose Ln Tolland Ct",
    "iso:country":"US",
    "sg:address":"137 Goose Ln",
    "sg:city":"Tolland",
    "sg:classifiers":[
        {
            "category":"Professional",
            "subcategory":"Computer Services",
            "type":"Services"
        }
    ],
    "sg:phone":"+1   ",
    "sg:postcode":"06084",
    "sg:province":"CT",
    "sg:tags":[
        "programing",
        "custom"
    ],
    "wof:name":"Power System Solutions",
    "wof:placetype":"venue"
},
  "geometry": {"coordinates":[-72.349869,41.847259],"type":"Point"}
}