{
  "type": "Feature",
  "properties": {
    "iso:country":"US",
    "sg:address":"150 Tower Ave",
    "sg:city":"Hartford",
    "sg:classifiers":[
        {
            "category":"Education",
            "subcategory":"School",
            "type":"Public Place"
        }
    ],
    "sg:phone":"+1   ",
    "sg:postcode":"06120",
    "sg:province":"CT",
    "wof:name":"Barbour C A School",
    "wof:placetype":"venue"
},
  "geometry": {"coordinates":[-72.66988600000001,41.797623],"type":"Point"}
}