{
  "type": "Feature",
  "properties": {
    "addr:full":"14 Ives St Danbury CT 06810",
    "addr:housenumber":"14",
    "addr:postcode":"06810",
    "addr:street":"Ives St",
    "iso:country":"US",
    "sg:address":"14 Ives St",
    "sg:city":"Danbury",
    "sg:classifiers":[
        {
            "category":"Restaurant",
            "type":"Food & Drink"
        }
    ],
    "sg:phone":"+1 203 743 0447",
    "sg:postcode":"06810",
    "sg:province":"CT",
    "wof:name":"Manny's Diner",
    "wof:placetype":"venue"
},
  "geometry": {"coordinates":[-73.45303199999999,41.396259],"type":"Point"}
}