{
  "type": "Feature",
  "properties": {
    "addr:full":"88 Birchbank Rd Shelton CT 06484",
    "addr:housenumber":"88",
    "addr:postcode":"06484",
    "addr:street":"Birchbank Rd",
    "iso:country":"US",
    "sg:address":"88 Birchbank Rd",
    "sg:city":"Shelton",
    "sg:classifiers":[
        {
            "category":"Building & Trades",
            "subcategory":"Construction",
            "type":"Services"
        }
    ],
    "sg:phone":"+1 203 924 0122",
    "sg:postcode":"06484",
    "sg:province":"CT",
    "sg:tags":[
        "general",
        "contractor"
    ],
    "wof:name":"Glover Construction Co",
    "wof:placetype":"venue"
},
  "geometry": {"coordinates":[-73.14825399999999,41.367218],"type":"Point"}
}