{
  "type": "Feature",
  "properties": {
    "addr:full":"748 Post Rd E Westport CT 06880",
    "addr:housenumber":"748",
    "addr:postcode":"06880",
    "addr:street":"Post Rd E Westport Ct",
    "iso:country":"US",
    "sg:address":"748 Post Rd E",
    "sg:city":"Westport",
    "sg:classifiers":[
        {
            "category":"Retail",
            "subcategory":"Portrait Studio",
            "type":"Services"
        }
    ],
    "sg:phone":"+1 203 226 6553",
    "sg:postcode":"06880",
    "sg:province":"CT",
    "sg:tags":[
        "photographer"
    ],
    "wof:name":"Albanese Liborio Photography",
    "wof:placetype":"venue"
},
  "geometry": {"coordinates":[-73.34013,41.137379],"type":"Point"}
}