{
  "type": "Feature",
  "properties": {
    "addr:full":"241 Roosevelt Dr Stevenson CT 06468",
    "addr:housenumber":"241",
    "addr:postcode":"06468",
    "addr:street":"Roosevelt Dr Stevenson Ct",
    "iso:country":"US",
    "sg:address":"241 Roosevelt Dr",
    "sg:city":"Stevenson",
    "sg:classifiers":[
        {
            "category":"Autos & Motor Vehicles",
            "subcategory":"Fuel & Gas Station",
            "type":"Retail Goods"
        }
    ],
    "sg:phone":"+1 203 268 0961",
    "sg:postcode":"06468",
    "sg:province":"CT",
    "sg:tags":[
        "oil"
    ],
    "wof:name":"Lake Zoar Gulf Svc Station",
    "wof:placetype":"venue"
},
  "geometry": {"coordinates":[-73.17498999999999,41.381055],"type":"Point"}
}