{
  "type": "Feature",
  "properties": {
    "addr:full":"327 Huntington Tpke Bridgeport CT 06610",
    "addr:housenumber":"327",
    "addr:postcode":"06610",
    "addr:street":"Huntington Tpke Bridgeport Ct",
    "iso:country":"US",
    "sg:address":"327 Huntington Tpke",
    "sg:city":"Bridgeport",
    "sg:classifiers":[
        {
            "category":"Wholesale",
            "subcategory":"Electrical",
            "type":"Manufacturing & Wholesale Goods"
        }
    ],
    "sg:phone":"+1 203 367 9008",
    "sg:postcode":"06610",
    "sg:province":"CT",
    "sg:tags":[
        "communication",
        "radio",
        "system"
    ],
    "wof:name":"Northeastern Communications",
    "wof:placetype":"venue"
},
  "geometry": {"coordinates":[-73.17442200000001,41.214529],"type":"Point"}
}