{
  "type": "Feature",
  "properties": {
    "iso:country":"US",
    "sg:address":"320 Depot Ln Unit 4",
    "sg:city":"Cutchogue",
    "sg:classifiers":[
        {
            "category":"Social Services",
            "subcategory":"Child Care",
            "type":"Services"
        }
    ],
    "sg:phone":"+1 631 734 8457",
    "sg:postcode":"11935",
    "sg:province":"NY",
    "sg:tags":[
        "day"
    ],
    "sg:website":"www.maritimedayschool.com",
    "wof:name":"Maritime Day School",
    "wof:placetype":"venue"
},
  "geometry": {"coordinates":[-72.484305,41.365052],"type":"Point"}
}