{
  "type": "Feature",
  "properties": {
    "iso:country":"US",
    "sg:address":"313 State Hwy 87",
    "sg:city":"Columbia",
    "sg:classifiers":[
        {
            "category":"Shopping",
            "subcategory":"Music",
            "type":"Retail Goods"
        }
    ],
    "sg:phone":"+1 860 228 8797",
    "sg:postcode":"06237",
    "sg:province":"CT",
    "wof:name":"Records E",
    "wof:placetype":"venue"
},
  "geometry": {"coordinates":[-72.302953,41.703246],"type":"Point"}
}