{
  "type": "Feature",
  "properties": {
    "iso:country":"US",
    "sg:address":"66 Georges Hill Rd",
    "sg:city":"Newtown",
    "sg:classifiers":[
        {
            "category":"Home & Garden",
            "subcategory":"Household Appliances",
            "type":"Retail Goods"
        }
    ],
    "sg:phone":"+1 203 426 0400",
    "sg:postcode":"06470",
    "sg:province":"CT",
    "wof:name":"Westconn Electrical Appliance",
    "wof:placetype":"venue"
},
  "geometry": {"coordinates":[-73.33969500000001,41.447818],"type":"Point"}
}