{
  "type": "Feature",
  "properties": {
    "iso:country":"US",
    "sg:address":"656 New Haven Ave",
    "sg:city":"Derby",
    "sg:classifiers":[
        {
            "category":"Food & Beverages",
            "subcategory":"Liquor & Beverages",
            "type":"Retail Goods"
        }
    ],
    "sg:phone":"+1 203 734 4664",
    "sg:postcode":"06418",
    "sg:province":"CT",
    "wof:name":"Woodland Wine & Spirits",
    "wof:placetype":"venue"
},
  "geometry": {"coordinates":[-73.056556,41.312242],"type":"Point"}
}