{
  "type": "Feature",
  "properties": {
    "addr:full":"26 Newton St Hamden CT 06514",
    "addr:housenumber":"26",
    "addr:postcode":"06514",
    "addr:street":"Newton St",
    "iso:country":"US",
    "sg:address":"26 Newton St",
    "sg:city":"Hamden",
    "sg:classifiers":[
        {
            "category":"Personal",
            "type":"Services"
        }
    ],
    "sg:phone":"+1   ",
    "sg:postcode":"06514",
    "sg:province":"CT",
    "wof:name":"Little Home Improvement LLC",
    "wof:placetype":"venue"
},
  "geometry": {"coordinates":[-72.934275,41.349474],"type":"Point"}
}