{
  "type": "Feature",
  "properties": {
    "iso:country":"US",
    "sg:address":"1103 Barnum Ave",
    "sg:city":"Stratford",
    "sg:classifiers":[
        {
            "category":"Retail",
            "subcategory":"Auto Repair",
            "type":"Services"
        }
    ],
    "sg:phone":"+1 203 375 9049",
    "sg:postcode":"06614",
    "sg:province":"CT",
    "sg:tags":[
        "repairing",
        "automobile"
    ],
    "wof:name":"Brake Centers Of America/Tire",
    "wof:placetype":"venue"
},
  "geometry": {"coordinates":[-73.132104,41.198928],"type":"Point"}
}