{
  "type": "Feature",
  "properties": {
    "addr:full":"965 State St New Haven CT 06511",
    "addr:housenumber":"965",
    "addr:postcode":"06511",
    "addr:street":"State St",
    "iso:country":"US",
    "sg:address":"965 State St",
    "sg:city":"New Haven",
    "sg:classifiers":[
        {
            "category":"Wholesale",
            "subcategory":"Tobacco Products",
            "type":"Manufacturing & Wholesale Goods"
        }
    ],
    "sg:phone":"+1 203 865 0074",
    "sg:postcode":"06511",
    "sg:province":"CT",
    "sg:tags":[
        "cigarette",
        "cigar",
        "dealer"
    ],
    "wof:name":"Squillo Distributing Co",
    "wof:placetype":"venue"
},
  "geometry": {"coordinates":[-72.909755,41.315532],"type":"Point"}
}