{
  "type": "Feature",
  "properties": {
    "addr:full":"9 Tower Dr Norwalk CT 06850",
    "addr:housenumber":"9",
    "addr:postcode":"06850",
    "addr:street":"Tower Dr",
    "iso:country":"US",
    "sg:address":"9 Tower Dr",
    "sg:city":"Norwalk",
    "sg:classifiers":[
        {
            "category":"Building & Trades",
            "subcategory":"Landscaping Services",
            "type":"Services"
        }
    ],
    "sg:phone":"+1 203 849 9485",
    "sg:postcode":"06850",
    "sg:province":"CT",
    "wof:name":"Raricks Lawn & Handyman Servi",
    "wof:placetype":"venue"
},
  "geometry": {"coordinates":[-73.434337,41.124191],"type":"Point"}
}