{
  "type": "Feature",
  "properties": {
    "addr:full":"24 Indian Rd Trumbull CT 06611",
    "addr:housenumber":"24",
    "addr:postcode":"06611",
    "addr:street":"Indian Rd",
    "iso:country":"US",
    "sg:address":"24 Indian Rd",
    "sg:city":"Trumbull",
    "sg:classifiers":[
        {
            "category":"Professional",
            "subcategory":"Business Services",
            "type":"Services"
        }
    ],
    "sg:phone":"+1   ",
    "sg:postcode":"06611",
    "sg:province":"CT",
    "wof:name":"Donley Associates Inc",
    "wof:placetype":"venue"
},
  "geometry": {"coordinates":[-73.22971200000001,41.238552],"type":"Point"}
}