{
  "type": "Feature",
  "properties": {
    "addr:full":"271 Tryon St South Glastonbury CT 06073",
    "addr:housenumber":"271",
    "addr:postcode":"06073",
    "addr:street":"Tryon St South",
    "iso:country":"US",
    "sg:address":"271 Tryon St",
    "sg:city":"South Glastonbury",
    "sg:classifiers":[
        {
            "category":"Professional",
            "type":"Services"
        }
    ],
    "sg:phone":"+1 860 633 0612",
    "sg:postcode":"06073",
    "sg:province":"CT",
    "wof:name":"National Sojourners Inc 5",
    "wof:placetype":"venue"
},
  "geometry": {"coordinates":[-72.61617699999999,41.663785],"type":"Point"}
}