{
  "type": "Feature",
  "properties": {
    "addr:full":"5 Davis Ln Westport CT 06880",
    "addr:housenumber":"5",
    "addr:postcode":"06880",
    "addr:street":"Davis Ln",
    "iso:country":"US",
    "sg:address":"5 Davis Ln",
    "sg:city":"Westport",
    "sg:classifiers":[
        {
            "category":"Professional",
            "subcategory":"Advertising",
            "type":"Services"
        }
    ],
    "sg:phone":"+1   ",
    "sg:postcode":"06880",
    "sg:province":"CT",
    "sg:tags":[
        "radio"
    ],
    "wof:name":"Radio Agency",
    "wof:placetype":"venue"
},
  "geometry": {"coordinates":[-73.3081,41.140444],"type":"Point"}
}