{
  "type": "Feature",
  "properties": {
    "iso:country":"US",
    "sg:address":"272 Woodlawn Rd",
    "sg:city":"Berlin",
    "sg:classifiers":[
        {
            "category":"Professional",
            "subcategory":"Accounting & Tax Preparation",
            "type":"Services"
        }
    ],
    "sg:phone":"+1   ",
    "sg:postcode":"06037",
    "sg:province":"CT",
    "wof:name":"Harvey Industries Cpd",
    "wof:placetype":"venue"
},
  "geometry": {"coordinates":[-72.744731,41.63193],"type":"Point"}
}