{
  "type": "Feature",
  "properties": {
    "addr:full":"28 W Main St Plantsville CT 06479",
    "addr:housenumber":"28",
    "addr:postcode":"06479",
    "addr:street":"W Main St",
    "iso:country":"US",
    "sg:address":"28 W Main St",
    "sg:city":"Plantsville",
    "sg:classifiers":[
        {
            "category":"Bars & Pubs",
            "type":"Food & Drink"
        }
    ],
    "sg:phone":"+1 860 276 9326",
    "sg:postcode":"06479",
    "sg:province":"CT",
    "sg:tags":[
        "drinking"
    ],
    "wof:name":"Quinns Tavern",
    "wof:placetype":"venue"
},
  "geometry": {"coordinates":[-72.891862,41.587561],"type":"Point"}
}