{
  "type": "Feature",
  "properties": {
    "addr:full":"24 Fitch Ave Darien CT 06820",
    "addr:housenumber":"24",
    "addr:postcode":"06820",
    "addr:street":"Fitch Ave Darien Ct",
    "iso:country":"US",
    "sg:address":"24 Fitch Ave",
    "sg:city":"Darien",
    "sg:classifiers":[
        {
            "category":"Building & Trades",
            "subcategory":"Electrical",
            "type":"Services"
        }
    ],
    "sg:phone":"+1 203 655 0880",
    "sg:postcode":"06820",
    "sg:province":"CT",
    "sg:tags":[
        "general",
        "electrical",
        "contractor"
    ],
    "wof:name":"Vogue Electric Inc",
    "wof:placetype":"venue"
},
  "geometry": {"coordinates":[-73.485894,41.066818],"type":"Point"}
}