{
  "type": "Feature",
  "properties": {
    "addr:full":"66 S King St Danbury CT 06811",
    "addr:housenumber":"66",
    "addr:postcode":"06811",
    "addr:street":"S King St",
    "iso:country":"US",
    "sg:address":"66 S King St",
    "sg:city":"Danbury",
    "sg:classifiers":[
        {
            "category":"Building & Trades",
            "subcategory":"Construction",
            "type":"Services"
        }
    ],
    "sg:phone":"+1 203 748 9263",
    "sg:postcode":"06811",
    "sg:province":"CT",
    "sg:tags":[
        "contractor"
    ],
    "wof:name":"Seth E Wibling",
    "wof:placetype":"venue"
},
  "geometry": {"coordinates":[-73.492199,41.418194],"type":"Point"}
}