{
  "type": "Feature",
  "properties": {
    "addr:full":"10 Cardinal Ct Ridgefield CT 06877",
    "addr:housenumber":"10",
    "addr:postcode":"06877",
    "addr:street":"Cardinal Ct",
    "iso:country":"US",
    "sg:address":"10 Cardinal Ct",
    "sg:city":"Ridgefield",
    "sg:classifiers":[
        {
            "category":"Autos & Motor Vehicles",
            "subcategory":"Automobile Sales",
            "type":"Retail Goods"
        }
    ],
    "sg:phone":"+1 203 431 6983",
    "sg:postcode":"06877",
    "sg:province":"CT",
    "sg:tags":[
        "used"
    ],
    "wof:name":"Pesce Used Cars",
    "wof:placetype":"venue"
},
  "geometry": {"coordinates":[-73.52118,41.285985],"type":"Point"}
}