{
  "type": "Feature",
  "properties": {
    "addr:full":"141 King Philip Dr Hartford CT 06117",
    "addr:housenumber":"141",
    "addr:postcode":"06117",
    "addr:street":"King Philip Dr",
    "iso:country":"US",
    "sg:address":"141 King Philip Dr",
    "sg:city":"Hartford",
    "sg:classifiers":[
        {
            "category":"Social Services",
            "subcategory":"Child Care",
            "type":"Services"
        }
    ],
    "sg:phone":"+1   ",
    "sg:postcode":"06117",
    "sg:province":"CT",
    "sg:tags":[
        "day"
    ],
    "wof:name":"Normas Day Care Pro",
    "wof:placetype":"venue"
},
  "geometry": {"coordinates":[-72.744288,41.796101],"type":"Point"}
}