{
  "type": "Feature",
  "properties": {
    "addr:full":"560 N Washington Ave Bridgeport CT 06604",
    "addr:housenumber":"560",
    "addr:postcode":"06604",
    "addr:street":"N Washington Ave",
    "iso:country":"US",
    "sg:address":"560 N Washington Ave",
    "sg:city":"Bridgeport",
    "sg:classifiers":[
        {
            "category":"Banks & Credit Unions",
            "subcategory":"Financial Services",
            "type":"Services"
        }
    ],
    "sg:phone":"+1 203 384 1273",
    "sg:postcode":"06604",
    "sg:province":"CT",
    "sg:tags":[
        "company",
        "holding"
    ],
    "wof:name":"Unit 5 Holding Co",
    "wof:placetype":"venue"
},
  "geometry": {"coordinates":[-73.191232,41.192665],"type":"Point"}
}