{
  "type": "Feature",
  "properties": {
    "iso:country":"US",
    "sg:address":"38 Holmes St",
    "sg:city":"East Haven",
    "sg:classifiers":[
        {
            "category":"Building & Trades",
            "subcategory":"Landscaping Services",
            "type":"Services"
        }
    ],
    "sg:phone":"+1 203 467 5062",
    "sg:postcode":"06512",
    "sg:province":"CT",
    "wof:name":"Fallen Leaf Lawn & Yard Care",
    "wof:placetype":"venue"
},
  "geometry": {"coordinates":[-72.88634999999999,41.274501],"type":"Point"}
}