{
  "type": "Feature",
  "properties": {
    "addr:full":"267 Beardsley Rd Shelton CT 06484",
    "addr:housenumber":"267",
    "addr:postcode":"06484",
    "addr:street":"Beardsley Rd",
    "iso:country":"US",
    "sg:address":"267 Beardsley Rd",
    "sg:city":"Shelton",
    "sg:classifiers":[
        {
            "category":"Professional",
            "subcategory":"Detective & Security Services",
            "type":"Services"
        }
    ],
    "sg:phone":"+1   ",
    "sg:postcode":"06484",
    "sg:province":"CT",
    "wof:name":"M S M Security Systems",
    "wof:placetype":"venue"
},
  "geometry": {"coordinates":[-73.164252,41.350948],"type":"Point"}
}