{
  "type": "Feature",
  "properties": {
    "iso:country":"US",
    "sg:address":"108 Brandy St",
    "sg:city":"Bolton",
    "sg:classifiers":[
        {
            "category":"Recreation",
            "type":"Entertainment"
        }
    ],
    "sg:phone":"+1   ",
    "sg:postcode":"06043",
    "sg:province":"CT",
    "wof:name":"Firefly Astrology",
    "wof:placetype":"venue"
},
  "geometry": {"coordinates":[-72.420935,41.754337],"type":"Point"}
}