{
  "type": "Feature",
  "properties": {
    "addr:full":"511 Danbury Rd New Milford CT 06776",
    "addr:housenumber":"511",
    "addr:postcode":"06776",
    "addr:street":"Danbury Rd",
    "iso:country":"US",
    "sg:address":"511 Danbury Rd",
    "sg:city":"New Milford",
    "sg:classifiers":[
        {
            "category":"Freight",
            "type":"Transportation"
        }
    ],
    "sg:phone":"+1 860 355 7063",
    "sg:postcode":"06776",
    "sg:province":"CT",
    "sg:tags":[
        "operator",
        "local",
        "trucking"
    ],
    "wof:name":"Conklin Trucking Co",
    "wof:placetype":"venue"
},
  "geometry": {"coordinates":[-73.420349,41.50927],"type":"Point"}
}