{
  "type": "Feature",
  "properties": {
    "iso:country":"US",
    "sg:address":"204 Griffin Ave",
    "sg:city":"Bridgeport",
    "sg:classifiers":[
        {
            "category":"Professional",
            "subcategory":"Computer Services",
            "type":"Services"
        }
    ],
    "sg:phone":"+1   ",
    "sg:postcode":"06606",
    "sg:province":"CT",
    "sg:tags":[
        "wholesale",
        "inspection",
        "equipment"
    ],
    "wof:name":"New England Metrology",
    "wof:placetype":"venue"
},
  "geometry": {"coordinates":[-73.207025,41.217156],"type":"Point"}
}