{
  "type": "Feature",
  "properties": {
    "iso:country":"US",
    "sg:address":"17 Khakum Wood Rd",
    "sg:city":"Greenwich",
    "sg:classifiers":[
        {
            "category":"Building & Trades",
            "subcategory":"Construction",
            "type":"Services"
        }
    ],
    "sg:phone":"+1 203 629 3299",
    "sg:postcode":"06831",
    "sg:province":"CT",
    "wof:name":"Mark Mariani Inc",
    "wof:placetype":"venue"
},
  "geometry": {"coordinates":[-73.64754000000001,41.063817],"type":"Point"}
}