{
  "type": "Feature",
  "properties": {
    "iso:country":"US",
    "sg:address":"80 Field Point Rd",
    "sg:city":"Greenwich",
    "sg:classifiers":[
        {
            "category":"Banks & Credit Unions",
            "subcategory":"Investment Brokerage",
            "type":"Services"
        }
    ],
    "sg:phone":"+1 203 622 5200",
    "sg:postcode":"06830",
    "sg:province":"CT",
    "sg:tags":[
        "management"
    ],
    "wof:name":"Frontpoint Partners LLC",
    "wof:placetype":"venue"
},
  "geometry": {"coordinates":[-73.62976999999999,41.025115],"type":"Point"}
}