{
  "type": "Feature",
  "properties": {
    "addr:full":"768 Farmington Ave Farmington CT 06032",
    "addr:housenumber":"768",
    "addr:postcode":"06032",
    "addr:street":"Farmington Ave",
    "iso:country":"US",
    "sg:address":"768 Farmington Ave",
    "sg:city":"Farmington",
    "sg:classifiers":[
        {
            "category":"Professional",
            "subcategory":"Business Services",
            "type":"Services"
        }
    ],
    "sg:phone":"+1   ",
    "sg:postcode":"06032",
    "sg:province":"CT",
    "wof:name":"Lightspeed Technology",
    "wof:placetype":"venue"
},
  "geometry": {"coordinates":[-72.82328699999999,41.725767],"type":"Point"}
}