{
  "type": "Feature",
  "properties": {
    "iso:country":"US",
    "sg:address":"90 Woodland Ave",
    "sg:city":"Bloomfield",
    "sg:classifiers":[
        {
            "category":"Professional",
            "type":"Services"
        }
    ],
    "sg:phone":"+1 860 242 5861",
    "sg:postcode":"06002",
    "sg:province":"CT",
    "wof:name":"Ritson Family LLC",
    "wof:placetype":"venue"
},
  "geometry": {"coordinates":[-72.73333,41.840435],"type":"Point"}
}