{
  "type": "Feature",
  "properties": {
    "addr:full":"30 Sherman St Hartford CT 06110",
    "addr:housenumber":"30",
    "addr:postcode":"06110",
    "addr:street":"Sherman St",
    "iso:country":"US",
    "sg:address":"30 Sherman St",
    "sg:city":"Hartford",
    "sg:classifiers":[
        {
            "category":"Organizations",
            "subcategory":"Professional Association",
            "type":"Services"
        }
    ],
    "sg:phone":"+1   ",
    "sg:postcode":"06110",
    "sg:province":"CT",
    "wof:name":"Uniformed Professional Fire FI",
    "wof:placetype":"venue"
},
  "geometry": {"coordinates":[-72.724035,41.726202],"type":"Point"}
}