{
  "type": "Feature",
  "properties": {
    "iso:country":"US",
    "sg:address":"340 Whitney Ave",
    "sg:city":"New Haven",
    "sg:classifiers":[
        {
            "category":"Professional",
            "subcategory":"Management & Consulting",
            "type":"Services"
        },
        {
            "category":"Health Services",
            "subcategory":"Clinic",
            "type":"Services"
        }
    ],
    "sg:phone":"+1 203 785 0650",
    "sg:postcode":"06511",
    "sg:province":"CT",
    "sg:tags":[
        "welfare",
        "agency",
        "social"
    ],
    "sg:website":"www.rdrg.com",
    "wof:name":"Health Systems Consultants Inc",
    "wof:placetype":"venue"
},
  "geometry": {"coordinates":[-72.91867000000001,41.320241],"type":"Point"}
}