{
  "type": "Feature",
  "properties": {
    "addr:full":"762 Broad St Exd Waterford CT 06385",
    "addr:housenumber":"762",
    "addr:postcode":"06385",
    "addr:street":"Broad St Exd Waterford Ct",
    "iso:country":"US",
    "sg:address":"762 Broad St Exd",
    "sg:city":"Waterford",
    "sg:classifiers":[
        {
            "category":"Shopping",
            "subcategory":"Clothing, Apparel, & Fashions",
            "type":"Retail Goods"
        }
    ],
    "sg:phone":"+1 860 447 2737",
    "sg:postcode":"06385",
    "sg:province":"CT",
    "wof:name":"Hot Flashes Boutique",
    "wof:placetype":"venue"
},
  "geometry": {"coordinates":[-72.130815,41.36942],"type":"Point"}
}