{
  "type": "Feature",
  "properties": {
    "iso:country":"US",
    "sg:address":"481 Pinney Rd",
    "sg:city":"Somers",
    "sg:classifiers":[
        {
            "category":"Building & Trades",
            "subcategory":"Plumbing",
            "type":"Services"
        }
    ],
    "sg:phone":"+1 860 763 1164",
    "sg:postcode":"06071",
    "sg:province":"CT",
    "sg:tags":[
        "air",
        "heating",
        "conditioning",
        "contractor"
    ],
    "wof:name":"Robert D Auguste",
    "wof:placetype":"venue"
},
  "geometry": {"coordinates":[-72.48238000000001,41.951904],"type":"Point"}
}