{
  "type": "Feature",
  "properties": {
    "addr:full":"92 Locust Ave Danbury CT 06810",
    "addr:housenumber":"92",
    "addr:postcode":"06810",
    "addr:street":"Locust Ave",
    "iso:country":"US",
    "sg:address":"92 Locust Ave",
    "sg:city":"Danbury",
    "sg:classifiers":[
        {
            "category":"Health Services",
            "subcategory":"Doctor",
            "type":"Services"
        }
    ],
    "sg:phone":"+1 203 744 4511",
    "sg:postcode":"06810",
    "sg:province":"CT",
    "sg:tags":[
        "physician",
        "surgeon"
    ],
    "wof:name":"Danbury Internal Med Assoc",
    "wof:placetype":"venue"
},
  "geometry": {"coordinates":[-73.44240000000001,41.403477],"type":"Point"}
}