{
  "type": "Feature",
  "properties": {
    "addr:full":"562 N Main St Bristol CT 06010",
    "addr:housenumber":"562",
    "addr:postcode":"06010",
    "addr:street":"N Main St",
    "iso:country":"US",
    "sg:address":"562 N Main St",
    "sg:city":"Bristol",
    "sg:classifiers":[
        {
            "category":"Recreation",
            "type":"Entertainment"
        }
    ],
    "sg:phone":"+1   ",
    "sg:postcode":"06010",
    "sg:province":"CT",
    "sg:tags":[
        "club",
        "membership"
    ],
    "wof:name":"Post 2",
    "wof:placetype":"venue"
},
  "geometry": {"coordinates":[-72.94730800000001,41.682666],"type":"Point"}
}