{
  "type": "Feature",
  "properties": {
    "iso:country":"US",
    "sg:address":"7 Church Ln",
    "sg:city":"Uncasville",
    "sg:classifiers":[
        {
            "category":"Retail",
            "subcategory":"Repair Shop",
            "type":"Services"
        }
    ],
    "sg:phone":"+1 860 848 3097",
    "sg:postcode":"06382",
    "sg:province":"CT",
    "sg:tags":[
        "tank",
        "septic",
        "excavation",
        "snow",
        "cleaning",
        "plowing"
    ],
    "wof:name":"Bobs Septic Tank Cleaning",
    "wof:placetype":"venue"
},
  "geometry": {"coordinates":[-72.09808700000001,41.473389],"type":"Point"}
}