{
  "type": "Feature",
  "properties": {
    "addr:full":"436 N Lake St Litchfield CT 06759",
    "addr:housenumber":"436",
    "addr:postcode":"06759",
    "addr:street":"N Lake St",
    "iso:country":"US",
    "sg:address":"436 N Lake St",
    "sg:city":"Litchfield",
    "sg:classifiers":[
        {
            "category":"Banks & Credit Unions",
            "subcategory":"Investment Brokerage",
            "type":"Services"
        }
    ],
    "sg:phone":"+1 860 567 3633",
    "sg:postcode":"06759",
    "sg:province":"CT",
    "sg:tags":[
        "advisory"
    ],
    "wof:name":"Moreau Investment Management",
    "wof:placetype":"venue"
},
  "geometry": {"coordinates":[-73.20157399999999,41.768797],"type":"Point"}
}