{
  "type": "Feature",
  "properties": {
    "addr:full":"245 Bittersweet Rd Orange CT 06477",
    "addr:housenumber":"245",
    "addr:postcode":"06477",
    "addr:street":"Bittersweet Rd",
    "iso:country":"US",
    "sg:address":"245 Bittersweet Rd",
    "sg:city":"Orange",
    "sg:classifiers":[
        {
            "category":"Building & Trades",
            "subcategory":"Construction",
            "type":"Services"
        }
    ],
    "sg:phone":"+1 203 397 1142",
    "sg:postcode":"06477",
    "sg:province":"CT",
    "sg:tags":[
        "contractor"
    ],
    "wof:name":"W C Parfetto Building & Rmdlng",
    "wof:placetype":"venue"
},
  "geometry": {"coordinates":[-72.992469,41.295526],"type":"Point"}
}