{
  "type": "Feature",
  "properties": {
    "iso:country":"US",
    "sg:address":"1117 Flanders Rd",
    "sg:city":"Coventry",
    "sg:classifiers":[
        {
            "category":"Retail",
            "subcategory":"Repair Shop",
            "type":"Services"
        }
    ],
    "sg:phone":"+1   ",
    "sg:postcode":"06238",
    "sg:province":"CT",
    "wof:name":"Joes Taxidermy Studio",
    "wof:placetype":"venue"
},
  "geometry": {"coordinates":[-72.291487,41.756427],"type":"Point"}
}