{
  "type": "Feature",
  "properties": {
    "iso:country":"US",
    "sg:address":"5 Bright Meadow Blvd",
    "sg:city":"Enfield",
    "sg:classifiers":[
        {
            "category":"Social Services",
            "subcategory":"Child Care",
            "type":"Services"
        }
    ],
    "sg:phone":"+1   ",
    "sg:postcode":"06082",
    "sg:province":"CT",
    "sg:tags":[
        "day"
    ],
    "wof:name":"Childrens Center",
    "wof:placetype":"venue"
},
  "geometry": {"coordinates":[-72.58630100000001,42.022219],"type":"Point"}
}