{
  "type": "Feature",
  "properties": {
    "iso:country":"US",
    "sg:address":"684 Boston Post Rd",
    "sg:city":"Madison",
    "sg:classifiers":[
        {
            "category":"Cinema",
            "subcategory":"Movie Rental",
            "type":"Entertainment"
        }
    ],
    "sg:phone":"+1 203 245 3136",
    "sg:postcode":"06443",
    "sg:province":"CT",
    "sg:tags":[
        "leasing",
        "video",
        "disc",
        "tape"
    ],
    "wof:name":"Now Playing",
    "wof:placetype":"venue"
},
  "geometry": {"coordinates":[-72.59607099999999,41.279462],"type":"Point"}
}