{
  "type": "Feature",
  "properties": {
    "iso:country":"US",
    "sg:address":"137 Farmcliff Dr",
    "sg:city":"Glastonbury",
    "sg:classifiers":[
        {
            "category":"Professional",
            "type":"Services"
        }
    ],
    "sg:phone":"+1 860 659 4637",
    "sg:postcode":"06033",
    "sg:province":"CT",
    "wof:name":"Greenleaf Systems LLC",
    "wof:placetype":"venue"
},
  "geometry": {"coordinates":[-72.587491,41.674673],"type":"Point"}
}