{
  "type": "Feature",
  "properties": {
    "addr:full":"329 Dixwell Ave New Haven CT 06511",
    "addr:housenumber":"329",
    "addr:postcode":"06511",
    "addr:street":"Dixwell Ave",
    "iso:country":"US",
    "sg:address":"329 Dixwell Ave",
    "sg:city":"New Haven",
    "sg:classifiers":[
        {
            "category":"Organizations",
            "subcategory":"Religious Organization",
            "type":"Services"
        }
    ],
    "sg:phone":"+1   ",
    "sg:postcode":"06511",
    "sg:province":"CT",
    "wof:name":"Freedom Temple Holiness Church",
    "wof:placetype":"venue"
},
  "geometry": {"coordinates":[-72.93496,41.322759],"type":"Point"}
}