{
  "type": "Feature",
  "properties": {
    "addr:full":"111 Wilcox St Bristol CT 06010",
    "addr:housenumber":"111",
    "addr:postcode":"06010",
    "addr:street":"Wilcox St",
    "iso:country":"US",
    "sg:address":"111 Wilcox St",
    "sg:city":"Bristol",
    "sg:classifiers":[
        {
            "category":"Personal",
            "type":"Services"
        }
    ],
    "sg:phone":"+1   ",
    "sg:postcode":"06010",
    "sg:province":"CT",
    "sg:tags":[
        "company",
        "assembly"
    ],
    "wof:name":"Assemble A-Z LLC",
    "wof:placetype":"venue"
},
  "geometry": {"coordinates":[-72.93225099999999,41.666657],"type":"Point"}
}