{
  "type": "Feature",
  "properties": {
    "iso:country":"US",
    "sg:address":"9 Main St",
    "sg:city":"Cromwell",
    "sg:classifiers":[
        {
            "category":"Education",
            "subcategory":"School",
            "type":"Public Place"
        }
    ],
    "sg:phone":"+1 860 635 6061",
    "sg:postcode":"06416",
    "sg:province":"CT",
    "sg:tags":[
        "executive"
    ],
    "wof:name":"Cromwell Middle School",
    "wof:placetype":"venue"
},
  "geometry": {"coordinates":[-72.64735899999999,41.585075],"type":"Point"}
}