{
  "type": "Feature",
  "properties": {
    "iso:country":"US",
    "sg:address":"164 Seaside Ave",
    "sg:city":"Bridgeport",
    "sg:classifiers":[
        {
            "category":"Professional",
            "type":"Services"
        }
    ],
    "sg:phone":"+1 203 367 7664",
    "sg:postcode":"06605",
    "sg:province":"CT",
    "wof:name":"Executive Impressions",
    "wof:placetype":"venue"
},
  "geometry": {"coordinates":[-73.225752,41.151193],"type":"Point"}
}