{
  "type": "Feature",
  "properties": {
    "addr:full":"157 Brushy Hill Rd Newtown CT 06470",
    "addr:housenumber":"157",
    "addr:postcode":"06470",
    "addr:street":"Brushy Hill Rd",
    "iso:country":"US",
    "sg:address":"157 Brushy Hill Rd",
    "sg:city":"Newtown",
    "sg:classifiers":[
        {
            "category":"Farming",
            "subcategory":"Farm",
            "type":"Manufacturing & Wholesale Goods"
        }
    ],
    "sg:phone":"+1 203 426 5094",
    "sg:postcode":"06470",
    "sg:province":"CT",
    "sg:tags":[
        "crop",
        "general"
    ],
    "wof:name":"Long Field Hills Inc",
    "wof:placetype":"venue"
},
  "geometry": {"coordinates":[-73.298761,41.364194],"type":"Point"}
}