{
  "type": "Feature",
  "properties": {
    "iso:country":"US",
    "sg:address":"95 South Rd",
    "sg:city":"Somers",
    "sg:classifiers":[
        {
            "category":"Food & Beverages",
            "subcategory":"Liquor & Beverages",
            "type":"Retail Goods"
        },
        {
            "category":"Wholesale",
            "subcategory":"Wine & Distilled Alcoholic Beverages",
            "type":"Manufacturing & Wholesale Goods"
        }
    ],
    "sg:phone":"+1 860 749 9463",
    "sg:postcode":"06071",
    "sg:province":"CT",
    "sg:tags":[
        "liquors-wholesale",
        "store"
    ],
    "wof:name":"Kaman's Wine & Liquors",
    "wof:placetype":"venue"
},
  "geometry": {"coordinates":[-72.44685,41.980127],"type":"Point"}
}