{
  "type": "Feature",
  "properties": {
    "iso:country":"US",
    "sg:address":"21 Arts Center Ct",
    "sg:city":"Avon",
    "sg:classifiers":[
        {
            "category":"Professional",
            "subcategory":"Management & Consulting",
            "type":"Services"
        }
    ],
    "sg:phone":"+1   ",
    "sg:postcode":"06001",
    "sg:province":"CT",
    "sg:tags":[
        "consultant"
    ],
    "wof:name":"Presscott Associates Ltd",
    "wof:placetype":"venue"
},
  "geometry": {"coordinates":[-72.83297899999999,41.811303],"type":"Point"}
}