{
  "type": "Feature",
  "properties": {
    "iso:country":"US",
    "sg:address":"171 Mountain Ave",
    "sg:city":"Bloomfield",
    "sg:classifiers":[
        {
            "category":"Manufacturing",
            "subcategory":"Lumber",
            "type":"Manufacturing & Wholesale Goods"
        }
    ],
    "sg:phone":"+1 860 242 3003",
    "sg:postcode":"06002",
    "sg:province":"CT",
    "sg:tags":[
        "material",
        "sawmill",
        "floor"
    ],
    "sg:website":"http://www.mooressawmill.com",
    "wof:name":"Moore's Sawmill Inc",
    "wof:placetype":"venue"
},
  "geometry": {"coordinates":[-72.770042,41.83535],"type":"Point"}
}