{
  "type": "Feature",
  "properties": {
    "iso:country":"US",
    "sg:address":"40 Temple St",
    "sg:city":"New Haven",
    "sg:classifiers":[
        {
            "category":"Health Services",
            "subcategory":"Doctor",
            "type":"Services"
        }
    ],
    "sg:phone":"+1 203 787 2114",
    "sg:postcode":"06510",
    "sg:province":"CT",
    "sg:tags":[
        "physician",
        "surgeon",
        "medical"
    ],
    "wof:name":"Cameron J Kirchner MD",
    "wof:placetype":"venue"
},
  "geometry": {"coordinates":[-72.92903099999999,41.303823],"type":"Point"}
}