{
  "type": "Feature",
  "properties": {
    "addr:full":"55 Cross St Danbury CT 06810",
    "addr:housenumber":"55",
    "addr:postcode":"06810",
    "addr:street":"Cross St",
    "iso:country":"US",
    "sg:address":"55 Cross St",
    "sg:city":"Danbury",
    "sg:classifiers":[
        {
            "category":"Building & Trades",
            "subcategory":"Construction",
            "type":"Services"
        }
    ],
    "sg:phone":"+1 203 798 7457",
    "sg:postcode":"06810",
    "sg:province":"CT",
    "sg:tags":[
        "maintenance",
        "contractor"
    ],
    "wof:name":"Thomas Cleaning & Maintenance",
    "wof:placetype":"venue"
},
  "geometry": {"coordinates":[-73.428326,41.393464],"type":"Point"}
}