{
  "type": "Feature",
  "properties": {
    "addr:full":"441 Clark Ln Orange CT 06477",
    "addr:housenumber":"441",
    "addr:postcode":"06477",
    "addr:street":"Clark Ln",
    "iso:country":"US",
    "sg:address":"441 Clark Ln",
    "sg:city":"Orange",
    "sg:classifiers":[
        {
            "category":"Sports & Exercise",
            "subcategory":"Golf",
            "type":"Entertainment"
        }
    ],
    "sg:phone":"+1 203 795 3100",
    "sg:postcode":"06477",
    "sg:province":"CT",
    "sg:tags":[
        "course"
    ],
    "sg:website":"www.grassyhillcountryclub.com",
    "wof:name":"Grassy Hill Country Club",
    "wof:placetype":"venue"
},
  "geometry": {"coordinates":[-73.045767,41.265309],"type":"Point"}
}