{
  "type": "Feature",
  "properties": {
    "iso:country":"US",
    "sg:address":"245 Main St",
    "sg:city":"Terryville",
    "sg:classifiers":[
        {
            "category":"Organizations",
            "subcategory":"Community Association",
            "type":"Services"
        }
    ],
    "sg:phone":"+1   ",
    "sg:postcode":"06786",
    "sg:province":"CT",
    "wof:name":"Plymouth Post 20 Amrcn Legion",
    "wof:placetype":"venue"
},
  "geometry": {"coordinates":[-73.01066,41.678359],"type":"Point"}
}