{
  "type": "Feature",
  "properties": {
    "addr:full":"234 Main St Westport CT 06880",
    "addr:housenumber":"234",
    "addr:postcode":"06880",
    "addr:street":"Main St",
    "iso:country":"US",
    "sg:address":"234 Main St",
    "sg:city":"Westport",
    "sg:classifiers":[
        {
            "category":"Professional",
            "subcategory":"Lawyer & Legal Services",
            "type":"Services"
        }
    ],
    "sg:phone":"+1 203 227 9066",
    "sg:postcode":"06880",
    "sg:province":"CT",
    "sg:tags":[
        "attorney"
    ],
    "wof:name":"Hammer & White",
    "wof:placetype":"venue"
},
  "geometry": {"coordinates":[-73.361357,41.145114],"type":"Point"}
}