{
  "type": "Feature",
  "properties": {
    "iso:country":"US",
    "sg:address":"527 Boston Post Rd",
    "sg:city":"Orange",
    "sg:classifiers":[
        {
            "category":"Insurance",
            "subcategory":"Insurance Agent",
            "type":"Services"
        }
    ],
    "sg:phone":"+1 203 765 4222",
    "sg:postcode":"06477",
    "sg:province":"CT",
    "wof:name":"AAA Club Insurance Agency Inc",
    "wof:placetype":"venue"
},
  "geometry": {"coordinates":[-73.01355700000001,41.257191],"type":"Point"}
}