{
  "type": "Feature",
  "properties": {
    "addr:full":"24 Danbury Rd Wilton CT 06897",
    "addr:housenumber":"24",
    "addr:postcode":"06897",
    "addr:street":"Danbury Rd Wilton Ct",
    "iso:country":"US",
    "sg:address":"24 Danbury Rd",
    "sg:city":"Wilton",
    "sg:classifiers":[
        {
            "category":"Professional",
            "subcategory":"Employment Agencies",
            "type":"Services"
        }
    ],
    "sg:phone":"+1 203 834 2100",
    "sg:postcode":"06897",
    "sg:province":"CT",
    "sg:tags":[
        "opportunity"
    ],
    "wof:name":"L Kohler & Co",
    "wof:placetype":"venue"
},
  "geometry": {"coordinates":[-73.41818499999999,41.164733],"type":"Point"}
}