{
  "type": "Feature",
  "properties": {
    "iso:country":"US",
    "sg:address":"35 Hickory Hill Ln",
    "sg:city":"Branford",
    "sg:classifiers":[
        {
            "category":"Building & Trades",
            "subcategory":"Electrical",
            "type":"Services"
        }
    ],
    "sg:phone":"+1 203 481 2181",
    "sg:postcode":"06405",
    "sg:province":"CT",
    "sg:tags":[
        "electrical",
        "contractor"
    ],
    "wof:name":"Spin Electric Inc",
    "wof:placetype":"venue"
},
  "geometry": {"coordinates":[-72.799768,41.298605],"type":"Point"}
}