{
  "type": "Feature",
  "properties": {
    "iso:country":"US",
    "sg:address":"1310 Washington Blvd",
    "sg:city":"Stamford",
    "sg:classifiers":[
        {
            "category":"Personal",
            "subcategory":"Beauty Salon",
            "type":"Services"
        },
        {
            "category":"Personal",
            "subcategory":"Barber",
            "type":"Services"
        },
        {
            "category":"Shopping",
            "subcategory":"Beauty & Cosmetics",
            "type":"Retail Goods"
        }
    ],
    "sg:phone":"+1 203 348 3488",
    "sg:postcode":"06902",
    "sg:province":"CT",
    "sg:tags":[
        "supply",
        "accessory",
        "hair",
        "equipment",
        "salons-equipment",
        "perfume"
    ],
    "sg:website":"http://www.hairlogic.com",
    "wof:name":"Iso Cosmetics Inc",
    "wof:placetype":"venue"
},
  "geometry": {"coordinates":[-73.54326399999999,41.057398],"type":"Point"}
}