{
  "type": "Feature",
  "properties": {
    "iso:country":"US",
    "sg:address":"370 E Main St",
    "sg:city":"Branford",
    "sg:classifiers":[
        {
            "category":"Freight",
            "type":"Transportation"
        }
    ],
    "sg:phone":"+1 203 481 3421",
    "sg:postcode":"06405",
    "sg:province":"CT",
    "sg:tags":[
        "bulk",
        "product"
    ],
    "wof:name":"Groendyke Transport Inc",
    "wof:placetype":"venue"
},
  "geometry": {"coordinates":[-72.782476,41.295002],"type":"Point"}
}