{
  "type": "Feature",
  "properties": {
    "addr:full":"12 Knoll Rd Woodbury CT 06798",
    "addr:housenumber":"12",
    "addr:postcode":"06798",
    "addr:street":"Knoll Rd",
    "iso:country":"US",
    "sg:address":"12 Knoll Rd",
    "sg:city":"Woodbury",
    "sg:classifiers":[
        {
            "category":"Professional",
            "subcategory":"Business Services",
            "type":"Services"
        }
    ],
    "sg:phone":"+1   ",
    "sg:postcode":"06798",
    "sg:province":"CT",
    "wof:name":"Big Sky Enterprises LLC",
    "wof:placetype":"venue"
},
  "geometry": {"coordinates":[-73.238314,41.543132],"type":"Point"}
}