{
  "type": "Feature",
  "properties": {
    "addr:full":"50 Columbus Blvd Hartford CT 06103",
    "addr:housenumber":"50",
    "addr:postcode":"06103",
    "addr:street":"Columbus Blvd;Ct",
    "iso:country":"US",
    "sg:address":"50 Columbus Blvd",
    "sg:city":"Hartford",
    "sg:classifiers":[
        {
            "category":"Professional",
            "subcategory":"Lawyer & Legal Services",
            "type":"Services"
        }
    ],
    "sg:phone":"+1   ",
    "sg:postcode":"06103",
    "sg:province":"CT",
    "wof:name":"Gilbert L Rosenbaum",
    "wof:placetype":"venue"
},
  "geometry": {"coordinates":[-72.669415,41.758909],"type":"Point"}
}