{
  "type": "Feature",
  "properties": {
    "addr:full":"11 Woodtick Rd Waterbury CT 06705",
    "addr:housenumber":"11",
    "addr:postcode":"06705",
    "addr:street":"Woodtick Rd",
    "iso:country":"US",
    "sg:address":"11 Woodtick Rd",
    "sg:city":"Waterbury",
    "sg:classifiers":[
        {
            "category":"Restaurant",
            "type":"Food & Drink"
        }
    ],
    "sg:phone":"+1 203 574 9288",
    "sg:postcode":"06705",
    "sg:province":"CT",
    "sg:tags":[
        "eating"
    ],
    "wof:name":"Pines II Cafe",
    "wof:placetype":"venue"
},
  "geometry": {"coordinates":[-73.00718000000001,41.552242],"type":"Point"}
}