{
  "type": "Feature",
  "properties": {
    "iso:country":"US",
    "sg:address":"10 Willowbrook Ct",
    "sg:city":"Stamford",
    "sg:classifiers":[
        {
            "category":"Banks & Credit Unions",
            "subcategory":"Bank",
            "type":"Services"
        }
    ],
    "sg:phone":"+1 203 324 7979",
    "sg:postcode":"06902",
    "sg:province":"CT",
    "sg:tags":[
        "loan",
        "real estate"
    ],
    "wof:name":"United Lending Co",
    "wof:placetype":"venue"
},
  "geometry": {"coordinates":[-73.51320800000001,41.0458],"type":"Point"}
}