{
  "type": "Feature",
  "properties": {
    "addr:full":"275 W Town St Norwich CT 06360",
    "addr:housenumber":"275",
    "addr:postcode":"06360",
    "addr:street":"W Town St Norwich Ct",
    "iso:country":"US",
    "sg:address":"275 W Town St",
    "sg:city":"Norwich",
    "sg:classifiers":[
        {
            "category":"Restaurant",
            "type":"Food & Drink"
        }
    ],
    "sg:menulink":"http://www.allmenus.com/ct/norwich/144136-subway/menu/",
    "sg:phone":"+1 860 823 1924",
    "sg:postcode":"06360",
    "sg:province":"CT",
    "sg:tags":[
        "american",
        "sandwich"
    ],
    "wof:name":"Subway",
    "wof:placetype":"venue"
},
  "geometry": {"coordinates":[-72.116229,41.557954],"type":"Point"}
}