{
  "type": "Feature",
  "properties": {
    "addr:full":"561 Westchester Ave Port Chester CT 10573",
    "addr:housenumber":"561",
    "addr:postcode":"10573",
    "addr:street":"Westchester Ave;Chester",
    "iso:country":"US",
    "sg:address":"561 Westchester Ave",
    "sg:city":"Port Chester",
    "sg:classifiers":[
        {
            "category":"Professional",
            "subcategory":"Management & Consulting",
            "type":"Services"
        }
    ],
    "sg:phone":"+1 914 937 1241",
    "sg:postcode":"10573",
    "sg:province":"CT",
    "sg:tags":[
        "business"
    ],
    "wof:name":"R R C-L C S Accounting Svcs",
    "wof:placetype":"venue"
},
  "geometry": {"coordinates":[-73.68172800000001,41.005922],"type":"Point"}
}