{
  "type": "Feature",
  "properties": {
    "addr:full":"83 Liberty St Danbury CT 06810",
    "addr:housenumber":"83",
    "addr:postcode":"06810",
    "addr:street":"Liberty St",
    "iso:country":"US",
    "sg:address":"83 Liberty St",
    "sg:city":"Danbury",
    "sg:classifiers":[
        {
            "category":"Building & Trades",
            "subcategory":"Construction",
            "type":"Services"
        }
    ],
    "sg:phone":"+1 203 748 7234",
    "sg:postcode":"06810",
    "sg:province":"CT",
    "sg:tags":[
        "siding",
        "contractor"
    ],
    "wof:name":"Somers Siding Inc",
    "wof:placetype":"venue"
},
  "geometry": {"coordinates":[-73.44618,41.394053],"type":"Point"}
}