{
  "type": "Feature",
  "properties": {
    "addr:full":"442 River Rd Shelton CT 06484",
    "addr:housenumber":"442",
    "addr:postcode":"06484",
    "addr:street":"River Rd",
    "iso:country":"US",
    "sg:address":"442 River Rd",
    "sg:city":"Shelton",
    "sg:classifiers":[
        {
            "category":"Food & Beverages",
            "subcategory":"Groceries & Convenience Stores",
            "type":"Retail Goods"
        }
    ],
    "sg:phone":"+1 203 924 5859",
    "sg:postcode":"06484",
    "sg:province":"CT",
    "wof:name":"General Equities Inc",
    "wof:placetype":"venue"
},
  "geometry": {"coordinates":[-73.07629300000001,41.290122],"type":"Point"}
}