{
  "type": "Feature",
  "properties": {
    "addr:full":"127 S Main St Beacon Falls CT 06403",
    "addr:housenumber":"127",
    "addr:postcode":"06403",
    "addr:street":"S Main St Beacon Falls Ct",
    "iso:country":"US",
    "sg:address":"127 S Main St",
    "sg:city":"Beacon Falls",
    "sg:classifiers":[
        {
            "category":"Banks & Credit Unions",
            "subcategory":"Bank",
            "type":"Services"
        }
    ],
    "sg:phone":"+1 203 720 4013",
    "sg:postcode":"06403",
    "sg:province":"CT",
    "sg:tags":[
        "mortgage"
    ],
    "wof:name":"Naugatuck Valley Savings",
    "wof:placetype":"venue"
},
  "geometry": {"coordinates":[-73.06044,41.439828],"type":"Point"}
}