{
  "type": "Feature",
  "properties": {
    "addr:full":"2839 Main St Bridgeport CT 06606",
    "addr:housenumber":"2839",
    "addr:postcode":"06606",
    "addr:street":"Main St",
    "iso:country":"US",
    "sg:address":"2839 Main St",
    "sg:city":"Bridgeport",
    "sg:classifiers":[
        {
            "category":"Health Services",
            "subcategory":"Clinic",
            "type":"Services"
        }
    ],
    "sg:phone":"+1 203 335 8859",
    "sg:postcode":"06606",
    "sg:province":"CT",
    "sg:tags":[
        "home"
    ],
    "sg:website":"www.almost-family.com",
    "wof:name":"Almost Family",
    "wof:placetype":"venue"
},
  "geometry": {"coordinates":[-73.20272799999999,41.200121],"type":"Point"}
}