{
  "type": "Feature",
  "properties": {
    "iso:country":"US",
    "sg:address":"19 Oakland Rd",
    "sg:city":"South Windsor",
    "sg:classifiers":[
        {
            "category":"Restaurant",
            "type":"Food & Drink"
        }
    ],
    "sg:menulink":"http://www.allmenus.com/ct/south-windsor/271353-little-taste-of-texas/menu/",
    "sg:phone":"+1 860 436 1232",
    "sg:postcode":"06074",
    "sg:province":"CT",
    "sg:tags":[
        "barbecue",
        "american"
    ],
    "wof:name":"Little Taste of Texas",
    "wof:placetype":"venue"
},
  "geometry": {"coordinates":[-72.552384,41.826637],"type":"Point"}
}