{
  "type": "Feature",
  "properties": {
    "addr:full":"300 Elizabeth St Derby CT 06418",
    "addr:housenumber":"300",
    "addr:postcode":"06418",
    "addr:street":"Elizabeth St",
    "iso:country":"US",
    "sg:address":"300 Elizabeth St",
    "sg:city":"Derby",
    "sg:classifiers":[
        {
            "category":"Organizations",
            "subcategory":"Religious Organization",
            "type":"Services"
        }
    ],
    "sg:phone":"+1 203 734 8544",
    "sg:postcode":"06418",
    "sg:province":"CT",
    "sg:tags":[
        "church"
    ],
    "sg:website":"www.newlifect.com",
    "wof:name":"New Life Community Church",
    "wof:placetype":"venue"
},
  "geometry": {"coordinates":[-73.089161,41.326634],"type":"Point"}
}