{
  "type": "Feature",
  "properties": {
    "addr:full":"139 Tower Ave Groton CT 06340",
    "addr:housenumber":"139",
    "addr:postcode":"06340",
    "addr:street":"Tower Ave",
    "iso:country":"US",
    "sg:address":"139 Tower Ave",
    "sg:city":"Groton",
    "sg:classifiers":[
        {
            "category":"Government",
            "subcategory":"Office",
            "type":"Public Place"
        }
    ],
    "sg:phone":"+1 860 441 2970",
    "sg:postcode":"06340",
    "sg:province":"CT",
    "sg:tags":[
        "military",
        "affairs"
    ],
    "wof:name":"Avcrad",
    "wof:placetype":"venue"
},
  "geometry": {"coordinates":[-72.040831,41.337261],"type":"Point"}
}