{
  "type": "Feature",
  "properties": {
    "addr:full":"25 Padanaram Rd Danbury CT 06811",
    "addr:housenumber":"25",
    "addr:postcode":"06811",
    "addr:street":"Padanaram Rd",
    "iso:country":"US",
    "sg:address":"25 Padanaram Rd",
    "sg:city":"Danbury",
    "sg:classifiers":[
        {
            "category":"Communications",
            "subcategory":"Film & Video Production",
            "type":"Services"
        }
    ],
    "sg:phone":"+1   ",
    "sg:postcode":"06811",
    "sg:province":"CT",
    "sg:tags":[
        "motion"
    ],
    "wof:name":"100 St Productions",
    "wof:placetype":"venue"
},
  "geometry": {"coordinates":[-73.46330399999999,41.417615],"type":"Point"}
}