{
  "type": "Feature",
  "properties": {
    "addr:full":"750 Washington Blvd Stamford CT 06901",
    "addr:housenumber":"750",
    "addr:postcode":"06901",
    "addr:street":"Washington Blvd",
    "iso:country":"US",
    "sg:address":"750 Washington Blvd",
    "sg:city":"Stamford",
    "sg:classifiers":[
        {
            "category":"Restaurant",
            "type":"Food & Drink"
        }
    ],
    "sg:phone":"+1 203 921 1815",
    "sg:postcode":"06901",
    "sg:province":"CT",
    "wof:name":"Ashton's Cafe",
    "wof:placetype":"venue"
},
  "geometry": {"coordinates":[-73.542444,41.050498],"type":"Point"}
}