{
  "type": "Feature",
  "properties": {
    "iso:country":"US",
    "sg:address":"10 Main St",
    "sg:city":"Bethel",
    "sg:classifiers":[
        {
            "category":"Building & Trades",
            "subcategory":"Construction",
            "type":"Services"
        }
    ],
    "sg:phone":"+1 203 778 9412",
    "sg:postcode":"06801",
    "sg:province":"CT",
    "sg:tags":[
        "repairing",
        "remodeling",
        "contractor"
    ],
    "wof:name":"D B Construction LLC",
    "wof:placetype":"venue"
},
  "geometry": {"coordinates":[-73.410264,41.372365],"type":"Point"}
}