{
  "type": "Feature",
  "properties": {
    "addr:full":"542 Allen Hill Rd Brooklyn CT 06234",
    "addr:housenumber":"542",
    "addr:postcode":"06234",
    "addr:street":"Allen Hill Rd",
    "iso:country":"US",
    "sg:address":"542 Allen Hill Rd",
    "sg:city":"Brooklyn",
    "sg:classifiers":[
        {
            "category":"Manufacturing",
            "subcategory":"Lumber",
            "type":"Manufacturing & Wholesale Goods"
        }
    ],
    "sg:phone":"+1 860 774 7064",
    "sg:postcode":"06234",
    "sg:province":"CT",
    "sg:tags":[
        "operation",
        "timber",
        "tract"
    ],
    "wof:name":"Allen Hill Farm",
    "wof:placetype":"venue"
},
  "geometry": {"coordinates":[-71.921767,41.764401],"type":"Point"}
}