{
  "type": "Feature",
  "properties": {
    "iso:country":"US",
    "sg:address":"20 Glen Pkwy",
    "sg:city":"Hamden",
    "sg:classifiers":[
        {
            "category":"Organizations",
            "subcategory":"Religious Organization",
            "type":"Services"
        }
    ],
    "sg:phone":"+1 203 288 3381",
    "sg:postcode":"06517",
    "sg:province":"CT",
    "sg:tags":[
        "church"
    ],
    "wof:name":"Spring Glen Church",
    "wof:placetype":"venue"
},
  "geometry": {"coordinates":[-72.90732800000001,41.365413],"type":"Point"}
}