{
  "type": "Feature",
  "properties": {
    "iso:country":"US",
    "sg:address":"144 Oxford Rd",
    "sg:city":"Oxford",
    "sg:classifiers":[
        {
            "category":"Health Services",
            "subcategory":"Doctor",
            "type":"Services"
        }
    ],
    "sg:phone":"+1 203 888 5527",
    "sg:postcode":"06478",
    "sg:province":"CT",
    "sg:tags":[
        "physician",
        "surgeon"
    ],
    "wof:name":"Eugene Constantinou MD",
    "wof:placetype":"venue"
},
  "geometry": {"coordinates":[-73.097705,41.411042],"type":"Point"}
}