{
  "type": "Feature",
  "properties": {
    "iso:country":"US",
    "sg:address":"87 W Broad St",
    "sg:city":"Pawcatuck",
    "sg:classifiers":[
        {
            "category":"Autos & Motor Vehicles",
            "subcategory":"Fuel & Gas Station",
            "type":"Retail Goods"
        }
    ],
    "sg:phone":"+1   ",
    "sg:postcode":"06379",
    "sg:province":"CT",
    "sg:tags":[
        "general",
        "automotive",
        "station",
        "gasoline",
        "repair"
    ],
    "wof:name":"Evans Mobil",
    "wof:placetype":"venue"
},
  "geometry": {"coordinates":[-71.834343,41.377035],"type":"Point"}
}