{
  "type": "Feature",
  "properties": {
    "iso:country":"US",
    "sg:address":"2584 Dixwell Ave",
    "sg:city":"Hamden",
    "sg:classifiers":[
        {
            "category":"Banks & Credit Unions",
            "subcategory":"Bank",
            "type":"Services"
        }
    ],
    "sg:phone":"+1 203 498 3733",
    "sg:postcode":"06514",
    "sg:province":"CT",
    "sg:tags":[
        "advisory",
        "state",
        "commercial",
        "investment"
    ],
    "wof:name":"Citizens Bank",
    "wof:placetype":"venue"
},
  "geometry": {"coordinates":[-72.91417300000001,41.378895],"type":"Point"}
}