{
  "type": "Feature",
  "properties": {
    "addr:full":"7 Blind Brook Ln Greenwich CT 06831",
    "addr:housenumber":"7",
    "addr:postcode":"06831",
    "addr:street":"Blind Brook Ln",
    "iso:country":"US",
    "sg:address":"7 Blind Brook Ln",
    "sg:city":"Greenwich",
    "sg:classifiers":[
        {
            "category":"Shopping",
            "subcategory":"Hobbies, Toys, & Games",
            "type":"Retail Goods"
        }
    ],
    "sg:phone":"+1 203 531 1153",
    "sg:postcode":"06831",
    "sg:province":"CT",
    "sg:tags":[
        "basket"
    ],
    "wof:name":"Greenwich Basket Co",
    "wof:placetype":"venue"
},
  "geometry": {"coordinates":[-73.67298700000001,41.045512],"type":"Point"}
}