{
  "type": "Feature",
  "properties": {
    "iso:country":"US",
    "sg:address":"87 S Main St",
    "sg:city":"Newtown",
    "sg:classifiers":[
        {
            "category":"Personal",
            "subcategory":"Beauty Salon",
            "type":"Services"
        }
    ],
    "sg:phone":"+1   ",
    "sg:postcode":"06470",
    "sg:province":"CT",
    "sg:tags":[
        "shop"
    ],
    "wof:name":"Thomas E Salon Inc",
    "wof:placetype":"venue"
},
  "geometry": {"coordinates":[-73.29176,41.394425],"type":"Point"}
}