{
  "type": "Feature",
  "properties": {
    "addr:full":"30 Crooked Mile Rd Darien CT 06820",
    "addr:housenumber":"30",
    "addr:postcode":"06820",
    "addr:street":"Crooked Mile Rd",
    "iso:country":"US",
    "sg:address":"30 Crooked Mile Rd",
    "sg:city":"Darien",
    "sg:classifiers":[
        {
            "category":"Banks & Credit Unions",
            "subcategory":"Financial Services",
            "type":"Services"
        }
    ],
    "sg:phone":"+1 203 655 3744",
    "sg:postcode":"06820",
    "sg:province":"CT",
    "sg:tags":[
        "trust",
        "nonprofit",
        "management"
    ],
    "wof:name":"Watkins Family Foundation",
    "wof:placetype":"venue"
},
  "geometry": {"coordinates":[-73.496222,41.106297],"type":"Point"}
}