{
  "type": "Feature",
  "properties": {
    "iso:country":"US",
    "sg:address":"5 Great Hollow Rd",
    "sg:city":"Monroe",
    "sg:classifiers":[
        {
            "category":"Building & Trades",
            "subcategory":"Construction",
            "type":"Services"
        }
    ],
    "sg:phone":"+1 203 452 0675",
    "sg:postcode":"06468",
    "sg:province":"CT",
    "sg:tags":[
        "contractor"
    ],
    "wof:name":"James E Mahon Cnstr Conslt",
    "wof:placetype":"venue"
},
  "geometry": {"coordinates":[-73.23428699999999,41.309502],"type":"Point"}
}