{
  "type": "Feature",
  "properties": {
    "iso:country":"US",
    "sg:address":"1 Regency Dr",
    "sg:city":"Bloomfield",
    "sg:classifiers":[
        {
            "category":"Real Estate",
            "subcategory":"Real Estate Agent",
            "type":"Services"
        }
    ],
    "sg:phone":"+1 860 243 0007",
    "sg:postcode":"06002",
    "sg:province":"CT",
    "wof:name":"Budkofsky Appraisal Co",
    "wof:placetype":"venue"
},
  "geometry": {"coordinates":[-72.74054599999999,41.828782],"type":"Point"}
}