{
  "type": "Feature",
  "properties": {
    "iso:country":"US",
    "sg:address":"61 Dodgingtown Rd",
    "sg:city":"Newtown",
    "sg:classifiers":[
        {
            "category":"Retail",
            "subcategory":"Auto Repair",
            "type":"Services"
        }
    ],
    "sg:phone":"+1 203 426 9525",
    "sg:postcode":"06470",
    "sg:province":"CT",
    "sg:tags":[
        "repairing",
        "automobile",
        "station",
        "gasoline",
        "general"
    ],
    "wof:name":"Dodgingtown Garage Inc",
    "wof:placetype":"venue"
},
  "geometry": {"coordinates":[-73.356313,41.379386],"type":"Point"}
}