{
  "type": "Feature",
  "properties": {
    "addr:full":"3671 Post Rd Southport CT 06890",
    "addr:housenumber":"3671",
    "addr:postcode":"06890",
    "addr:street":"Post Rd",
    "iso:country":"US",
    "sg:address":"3671 Post Rd",
    "sg:city":"Southport",
    "sg:classifiers":[
        {
            "category":"Ice Cream",
            "type":"Food & Drink"
        }
    ],
    "sg:menulink":"http://www.allmenus.com/ct/fairfield/99028-friendlys/menu/",
    "sg:phone":"+1 203 255 9779",
    "sg:postcode":"06890",
    "sg:province":"CT",
    "sg:tags":[
        "burger",
        "american"
    ],
    "wof:name":"Friendly's",
    "wof:placetype":"venue"
},
  "geometry": {"coordinates":[-73.29727699999999,41.138259],"type":"Point"}
}