{
  "type": "Feature",
  "properties": {
    "iso:country":"US",
    "sg:address":"230 White Birch Rd",
    "sg:city":"East Hampton",
    "sg:classifiers":[
        {
            "category":"Manufacturing",
            "subcategory":"Lumber",
            "type":"Manufacturing & Wholesale Goods"
        }
    ],
    "sg:phone":"+1 860 267 0128",
    "sg:postcode":"06424",
    "sg:province":"CT",
    "sg:tags":[
        "timber",
        "tract"
    ],
    "wof:name":"Coopers Tree Works",
    "wof:placetype":"venue"
},
  "geometry": {"coordinates":[-72.506364,41.639521],"type":"Point"}
}