{
  "type": "Feature",
  "properties": {
    "iso:country":"US",
    "sg:address":"1019 Farmington Ave",
    "sg:city":"Bristol",
    "sg:classifiers":[
        {
            "category":"Real Estate",
            "subcategory":"Real Estate Agent",
            "type":"Services"
        }
    ],
    "sg:phone":"+1 860 589 5492",
    "sg:postcode":"06010",
    "sg:province":"CT",
    "sg:tags":[
        "building",
        "opera",
        "nonresidential"
    ],
    "wof:name":"O V Realty",
    "wof:placetype":"venue"
},
  "geometry": {"coordinates":[-72.910265,41.695066],"type":"Point"}
}