{
  "type": "Feature",
  "properties": {
    "iso:country":"US",
    "sg:address":"2 Post Rd W",
    "sg:city":"Westport",
    "sg:classifiers":[
        {
            "category":"Travel",
            "subcategory":"Hotels & Motels",
            "type":"Entertainment"
        }
    ],
    "sg:phone":"+1   ",
    "sg:postcode":"06880",
    "sg:province":"CT",
    "wof:name":"Inn At National Hall",
    "wof:placetype":"venue"
},
  "geometry": {"coordinates":[-73.364566,41.140609],"type":"Point"}
}