{
  "type": "Feature",
  "properties": {
    "iso:country":"US",
    "sg:address":"100 Melrose Ave",
    "sg:city":"Greenwich",
    "sg:classifiers":[
        {
            "category":"Building & Trades",
            "subcategory":"Construction",
            "type":"Services"
        }
    ],
    "sg:phone":"+1 203 869 2457",
    "sg:postcode":"06830",
    "sg:province":"CT",
    "sg:tags":[
        "excavating",
        "contractor"
    ],
    "wof:name":"Ricciardi Brothers Inc",
    "wof:placetype":"venue"
},
  "geometry": {"coordinates":[-73.640539,41.020564],"type":"Point"}
}