{
  "type": "Feature",
  "properties": {
    "iso:country":"US",
    "sg:address":"24 Hoyt St",
    "sg:city":"Stamford",
    "sg:classifiers":[
        {
            "category":"Professional",
            "subcategory":"Lawyer & Legal Services",
            "type":"Services"
        }
    ],
    "sg:phone":"+1   ",
    "sg:postcode":"06905",
    "sg:province":"CT",
    "wof:name":"Mark Melzer",
    "wof:placetype":"venue"
},
  "geometry": {"coordinates":[-73.53724800000001,41.060861],"type":"Point"}
}