{
  "type": "Feature",
  "properties": {
    "iso:country":"US",
    "sg:address":"991 S Main St",
    "sg:city":"Plantsville",
    "sg:classifiers":[
        {
            "category":"Restaurant",
            "type":"Food & Drink"
        }
    ],
    "sg:phone":"+1 860 426 2266",
    "sg:postcode":"06479",
    "sg:province":"CT",
    "sg:tags":[
        "pizza"
    ],
    "wof:name":"Rosina's Pizzeria",
    "wof:placetype":"venue"
},
  "geometry": {"coordinates":[-72.894746,41.579357],"type":"Point"}
}