{
  "type": "Feature",
  "properties": {
    "addr:full":"30 Foster Ln Windsor CT 06095",
    "addr:housenumber":"30",
    "addr:postcode":"06095",
    "addr:street":"Foster Ln",
    "iso:country":"US",
    "sg:address":"30 Foster Ln",
    "sg:city":"Windsor",
    "sg:classifiers":[
        {
            "category":"Professional",
            "subcategory":"Management & Consulting",
            "type":"Services"
        }
    ],
    "sg:phone":"+1   ",
    "sg:postcode":"06095",
    "sg:province":"CT",
    "wof:name":"Senior Benifit Services",
    "wof:placetype":"venue"
},
  "geometry": {"coordinates":[-72.634857,41.863093],"type":"Point"}
}