{
  "type": "Feature",
  "properties": {
    "iso:country":"US",
    "sg:address":"51 Emily Rd",
    "sg:city":"Marlborough",
    "sg:classifiers":[
        {
            "category":"Real Estate",
            "subcategory":"Real Estate Agent",
            "type":"Services"
        }
    ],
    "sg:phone":"+1 860 295 8881",
    "sg:postcode":"06447",
    "sg:province":"CT",
    "wof:name":"Rizza Management Services Inc",
    "wof:placetype":"venue"
},
  "geometry": {"coordinates":[-72.458635,41.612124],"type":"Point"}
}