{
  "type": "Feature",
  "properties": {
    "iso:country":"US",
    "sg:address":"40 Hathaway Dr",
    "sg:city":"Stratford",
    "sg:classifiers":[
        {
            "category":"Wholesale",
            "subcategory":"Durable Goods & Equipment",
            "type":"Manufacturing & Wholesale Goods"
        }
    ],
    "sg:phone":"+1 203 377 3525",
    "sg:postcode":"06615",
    "sg:province":"CT",
    "sg:tags":[
        "representative",
        "manufacturer"
    ],
    "sg:website":"www.maselmon.com",
    "wof:name":"M A Selmon Co",
    "wof:placetype":"venue"
},
  "geometry": {"coordinates":[-73.144536,41.170875],"type":"Point"}
}