{
  "type": "Feature",
  "properties": {
    "addr:full":"77 S Main St Newtown CT 06470",
    "addr:housenumber":"77",
    "addr:postcode":"06470",
    "addr:street":"S Main St",
    "iso:country":"US",
    "sg:address":"77 S Main St",
    "sg:city":"Newtown",
    "sg:classifiers":[
        {
            "category":"Professional",
            "subcategory":"Testing Lab",
            "type":"Services"
        },
        {
            "category":"Building & Trades",
            "subcategory":"Construction",
            "type":"Services"
        }
    ],
    "sg:phone":"+1 203 426 7196",
    "sg:postcode":"06470",
    "sg:province":"CT",
    "sg:tags":[
        "correction",
        "radon",
        "gas",
        "removal"
    ],
    "sg:website":"www.buzzanocontracting.com",
    "wof:name":"Buzzano Contracting LLC",
    "wof:placetype":"venue"
},
  "geometry": {"coordinates":[-73.29410799999999,41.397334],"type":"Point"}
}