{
  "type": "Feature",
  "properties": {
    "iso:country":"US",
    "sg:address":"187 Ferry Blvd",
    "sg:city":"Stratford",
    "sg:classifiers":[
        {
            "category":"Food & Beverages",
            "subcategory":"Bakery",
            "type":"Retail Goods"
        }
    ],
    "sg:phone":"+1 203 386 8414",
    "sg:postcode":"06615",
    "sg:province":"CT",
    "sg:tags":[
        "baker"
    ],
    "wof:name":"Annemarie's Goodies",
    "wof:placetype":"venue"
},
  "geometry": {"coordinates":[-73.12364100000001,41.191609],"type":"Point"}
}