{
  "type": "Feature",
  "properties": {
    "iso:country":"US",
    "sg:address":"604 School St",
    "sg:city":"Putnam",
    "sg:classifiers":[
        {
            "category":"Food & Beverages",
            "subcategory":"Farmers Market",
            "type":"Retail Goods"
        }
    ],
    "sg:phone":"+1 860 928 3663",
    "sg:postcode":"06260",
    "sg:province":"CT",
    "sg:tags":[
        "vegetable",
        "fruit"
    ],
    "wof:name":"Root 44 Produce & More",
    "wof:placetype":"venue"
},
  "geometry": {"coordinates":[-71.890518,41.924759],"type":"Point"}
}