{
  "type": "Feature",
  "properties": {
    "iso:country":"US",
    "sg:address":"252 E Main St",
    "sg:city":"Clinton",
    "sg:classifiers":[
        {
            "category":"Home & Garden",
            "subcategory":"Building Materials",
            "type":"Retail Goods"
        }
    ],
    "sg:phone":"+1 860 669 8842",
    "sg:postcode":"06413",
    "sg:province":"CT",
    "sg:tags":[
        "paint",
        "painting",
        "supply"
    ],
    "wof:name":"Clinton Paint & Decorating LLC",
    "wof:placetype":"venue"
},
  "geometry": {"coordinates":[-72.499349,41.270939],"type":"Point"}
}