{
  "type": "Feature",
  "properties": {
    "addr:full":"17 Westminster Ct Milford CT 06477",
    "addr:housenumber":"17",
    "addr:postcode":"06477",
    "addr:street":"Westminster Ct",
    "iso:country":"US",
    "sg:address":"17 Westminster Ct",
    "sg:city":"Milford",
    "sg:classifiers":[
        {
            "category":"Building & Trades",
            "subcategory":"Construction",
            "type":"Services"
        }
    ],
    "sg:phone":"+1 203 367 9415",
    "sg:postcode":"06477",
    "sg:province":"CT",
    "sg:tags":[
        "house"
    ],
    "wof:name":"Homestead Construction Co",
    "wof:placetype":"venue"
},
  "geometry": {"coordinates":[-73.066034,41.265161],"type":"Point"}
}