{
  "type": "Feature",
  "properties": {
    "addr:full":"75 Poplar St New Haven CT 06513",
    "addr:housenumber":"75",
    "addr:postcode":"06513",
    "addr:street":"Poplar St",
    "iso:country":"US",
    "sg:address":"75 Poplar St",
    "sg:city":"New Haven",
    "sg:classifiers":[
        {
            "category":"Autos & Motor Vehicles",
            "subcategory":"Automobile Sales",
            "type":"Retail Goods"
        }
    ],
    "sg:phone":"+1 203 752 0683",
    "sg:postcode":"06513",
    "sg:province":"CT",
    "sg:tags":[
        "performance",
        "race",
        "dealer"
    ],
    "wof:name":"Auto Authority",
    "wof:placetype":"venue"
},
  "geometry": {"coordinates":[-72.89622300000001,41.303709],"type":"Point"}
}