{
  "type": "Feature",
  "properties": {
    "iso:country":"US",
    "sg:address":"4 Washington Rd",
    "sg:city":"Cromwell",
    "sg:classifiers":[
        {
            "category":"Professional",
            "subcategory":"Business Services",
            "type":"Services"
        }
    ],
    "sg:phone":"+1   ",
    "sg:postcode":"06416",
    "sg:province":"CT",
    "wof:name":"Klug Enterprises",
    "wof:placetype":"venue"
},
  "geometry": {"coordinates":[-72.66725099999999,41.607139],"type":"Point"}
}