{
  "type": "Feature",
  "properties": {
    "iso:country":"US",
    "sg:address":"555 Dixwell Ave",
    "sg:city":"New Haven",
    "sg:classifiers":[
        {
            "category":"Organizations",
            "subcategory":"Religious Organization",
            "type":"Services"
        }
    ],
    "sg:phone":"+1 203 562 3932",
    "sg:postcode":"06511",
    "sg:province":"CT",
    "sg:tags":[
        "church"
    ],
    "wof:name":"Mount Hope Temple U H C",
    "wof:placetype":"venue"
},
  "geometry": {"coordinates":[-72.93515499999999,41.327574],"type":"Point"}
}