{
  "type": "Feature",
  "properties": {
    "addr:full":"19 River St Milford CT 06460",
    "addr:housenumber":"19",
    "addr:postcode":"06460",
    "addr:street":"River St",
    "iso:country":"US",
    "sg:address":"19 River St",
    "sg:city":"Milford",
    "sg:classifiers":[
        {
            "category":"Shopping",
            "subcategory":"Used Merchandise",
            "type":"Retail Goods"
        }
    ],
    "sg:phone":"+1 203 877 7239",
    "sg:postcode":"06460",
    "sg:province":"CT",
    "sg:tags":[
        "antique"
    ],
    "wof:name":"Yankee Doodle Dandies",
    "wof:placetype":"venue"
},
  "geometry": {"coordinates":[-73.056825,41.222737],"type":"Point"}
}