{
  "type": "Feature",
  "properties": {
    "addr:full":"36 Coley Rd Wilton CT 06897",
    "addr:housenumber":"36",
    "addr:postcode":"06897",
    "addr:street":"Coley Rd Wilton Ct",
    "iso:country":"US",
    "sg:address":"36 Coley Rd",
    "sg:city":"Wilton",
    "sg:classifiers":[
        {
            "category":"Professional",
            "subcategory":"Business Services",
            "type":"Services"
        },
        {
            "category":"Building & Trades",
            "subcategory":"Construction",
            "type":"Services"
        }
    ],
    "sg:phone":"+1 203 762 5097",
    "sg:postcode":"06897",
    "sg:province":"CT",
    "sg:tags":[
        "water",
        "well",
        "drilling",
        "treatment"
    ],
    "wof:name":"John Findorak & Sons Inc",
    "wof:placetype":"venue"
},
  "geometry": {"coordinates":[-73.400897,41.212008],"type":"Point"}
}