{
  "type": "Feature",
  "properties": {
    "iso:country":"US",
    "sg:address":"162 S Main St",
    "sg:city":"Thomaston",
    "sg:classifiers":[
        {
            "category":"Wholesale",
            "subcategory":"Machinery & Supplies",
            "type":"Manufacturing & Wholesale Goods"
        }
    ],
    "sg:phone":"+1 860 283 9840",
    "sg:postcode":"06787",
    "sg:province":"CT",
    "sg:tags":[
        "equipment",
        "industrial"
    ],
    "wof:name":"Hoist Away",
    "wof:placetype":"venue"
},
  "geometry": {"coordinates":[-73.07788600000001,41.669253],"type":"Point"}
}