{
  "type": "Feature",
  "properties": {
    "iso:country":"US",
    "sg:address":"171 Atwood Ave",
    "sg:city":"Waterbury",
    "sg:classifiers":[
        {
            "category":"Building & Trades",
            "subcategory":"Plumbing",
            "type":"Services"
        }
    ],
    "sg:phone":"+1 203 753 4061",
    "sg:postcode":"06705",
    "sg:province":"CT",
    "sg:tags":[
        "plumbing",
        "contractor"
    ],
    "wof:name":"Rinaldi Plumbing & Heating",
    "wof:placetype":"venue"
},
  "geometry": {"coordinates":[-73.00778099999999,41.556976],"type":"Point"}
}