{
  "type": "Feature",
  "properties": {
    "addr:full":"35 Lake Ave Danbury CT 06810",
    "addr:housenumber":"35",
    "addr:postcode":"06810",
    "addr:street":"Lake Ave",
    "iso:country":"US",
    "sg:address":"35 Lake Ave",
    "sg:city":"Danbury",
    "sg:classifiers":[
        {
            "category":"Restaurant",
            "type":"Food & Drink"
        }
    ],
    "sg:phone":"+1 203 730 0004",
    "sg:postcode":"06810",
    "sg:province":"CT",
    "wof:name":"Brickyard Steak & Seafood",
    "wof:placetype":"venue"
},
  "geometry": {"coordinates":[-73.46583200000001,41.391263],"type":"Point"}
}