{
  "type": "Feature",
  "properties": {
    "iso:country":"US",
    "sg:address":"20 Trumbull St",
    "sg:city":"New Haven",
    "sg:classifiers":[
        {
            "category":"Professional",
            "subcategory":"Lawyer & Legal Services",
            "type":"Services"
        }
    ],
    "sg:phone":"+1 203 772 0070",
    "sg:postcode":"06511",
    "sg:province":"CT",
    "sg:tags":[
        "attorney"
    ],
    "wof:name":"Caplan Hecht Scanlon & Mendel",
    "wof:placetype":"venue"
},
  "geometry": {"coordinates":[-72.918412,41.311286],"type":"Point"}
}