{
  "type": "Feature",
  "properties": {
    "iso:country":"US",
    "sg:address":"79 Main St",
    "sg:city":"Torrington",
    "sg:classifiers":[
        {
            "category":"Retail",
            "subcategory":"Portrait Studio",
            "type":"Services"
        }
    ],
    "sg:phone":"+1   ",
    "sg:postcode":"06790",
    "sg:province":"CT",
    "sg:tags":[
        "photo"
    ],
    "wof:name":"Steven Thomas Photography",
    "wof:placetype":"venue"
},
  "geometry": {"coordinates":[-73.121415,41.801205],"type":"Point"}
}