{
  "type": "Feature",
  "properties": {
    "addr:full":"55 Old Long Ridge Rd Stamford CT 06903",
    "addr:housenumber":"55",
    "addr:postcode":"06903",
    "addr:street":"Old Long Ridge Rd",
    "iso:country":"US",
    "sg:address":"55 Old Long Ridge Rd",
    "sg:city":"Stamford",
    "sg:classifiers":[
        {
            "category":"Professional",
            "subcategory":"Accounting & Tax Preparation",
            "type":"Services"
        }
    ],
    "sg:phone":"+1 203 329 8195",
    "sg:postcode":"06903",
    "sg:province":"CT",
    "sg:tags":[
        "billing"
    ],
    "wof:name":"Medical Claims & Billing Svc",
    "wof:placetype":"venue"
},
  "geometry": {"coordinates":[-73.58989,41.143919],"type":"Point"}
}