{
  "type": "Feature",
  "properties": {
    "iso:country":"US",
    "sg:address":"17 Hoyt St",
    "sg:city":"Stamford",
    "sg:classifiers":[
        {
            "category":"Banks & Credit Unions",
            "subcategory":"Financial Services",
            "type":"Services"
        }
    ],
    "sg:phone":"+1 203 324 2931",
    "sg:postcode":"06905",
    "sg:province":"CT",
    "sg:tags":[
        "investor"
    ],
    "wof:name":"Nelson RE Investment I LLC",
    "wof:placetype":"venue"
},
  "geometry": {"coordinates":[-73.53706699999999,41.060696],"type":"Point"}
}