{
  "type": "Feature",
  "properties": {
    "addr:full":"160 W Main St Vernon Rockville CT 06066",
    "addr:housenumber":"160",
    "addr:postcode":"06066",
    "addr:street":"W Main St",
    "iso:country":"US",
    "sg:address":"160 W Main St",
    "sg:city":"Vernon Rockville",
    "sg:classifiers":[
        {
            "category":"Banks & Credit Unions",
            "subcategory":"Investment Brokerage",
            "type":"Services"
        }
    ],
    "sg:phone":"+1 860 871 7472",
    "sg:postcode":"06066",
    "sg:province":"CT",
    "sg:tags":[
        "advisory"
    ],
    "wof:name":"Sadlak S T Co",
    "wof:placetype":"venue"
},
  "geometry": {"coordinates":[-72.45537299999999,41.865191],"type":"Point"}
}