{
  "type": "Feature",
  "properties": {
    "iso:country":"US",
    "sg:address":"250 Lamberton Rd",
    "sg:city":"Windsor",
    "sg:classifiers":[
        {
            "category":"Health Services",
            "subcategory":"Doctor",
            "type":"Services"
        }
    ],
    "sg:phone":"+1   ",
    "sg:postcode":"06095",
    "sg:province":"CT",
    "sg:tags":[
        "dentist"
    ],
    "wof:name":"New England Dental Center PC",
    "wof:placetype":"venue"
},
  "geometry": {"coordinates":[-72.664794,41.866908],"type":"Point"}
}