{
  "type": "Feature",
  "properties": {
    "iso:country":"US",
    "sg:address":"602 Pomeroy Ave",
    "sg:city":"Meriden",
    "sg:classifiers":[
        {
            "category":"Manufacturing",
            "subcategory":"Metals",
            "type":"Manufacturing & Wholesale Goods"
        }
    ],
    "sg:phone":"+1 203 237 2297",
    "sg:postcode":"06450",
    "sg:province":"CT",
    "sg:tags":[
        "wire"
    ],
    "sg:website":"www.q-stechnologies.com",
    "wof:name":"Q-S Technologies Inc",
    "wof:placetype":"venue"
},
  "geometry": {"coordinates":[-72.758819,41.520176],"type":"Point"}
}