{
  "type": "Feature",
  "properties": {
    "iso:country":"US",
    "sg:address":"44 Jackson Ln",
    "sg:city":"Northford",
    "sg:classifiers":[
        {
            "category":"Arts & Performance",
            "subcategory":"Theater",
            "type":"Entertainment"
        }
    ],
    "sg:phone":"+1 203 484 9022",
    "sg:postcode":"06472",
    "sg:province":"CT",
    "sg:tags":[
        "entertainer",
        "business"
    ],
    "wof:name":"Laugh Out Loud Photos",
    "wof:placetype":"venue"
},
  "geometry": {"coordinates":[-72.791158,41.3712],"type":"Point"}
}