{
  "type": "Feature",
  "properties": {
    "addr:full":"1228 Farmington Ave Hartford CT 06107",
    "addr:housenumber":"1228",
    "addr:postcode":"06107",
    "addr:street":"Farmington Ave;Ct",
    "iso:country":"US",
    "sg:address":"1228 Farmington Ave",
    "sg:city":"Hartford",
    "sg:classifiers":[
        {
            "category":"Food & Beverages",
            "subcategory":"Liquor & Beverages",
            "type":"Retail Goods"
        }
    ],
    "sg:phone":"+1 860 521 5209",
    "sg:postcode":"06107",
    "sg:province":"CT",
    "sg:tags":[
        "beer",
        "wine"
    ],
    "wof:name":"London Shop Package Store",
    "wof:placetype":"venue"
},
  "geometry": {"coordinates":[-72.764645,41.755293],"type":"Point"}
}