{
  "type": "Feature",
  "properties": {
    "addr:full":"429 Woodbine Rd Stamford CT 06903",
    "addr:housenumber":"429",
    "addr:postcode":"06903",
    "addr:street":"Woodbine Rd",
    "iso:country":"US",
    "sg:address":"429 Woodbine Rd",
    "sg:city":"Stamford",
    "sg:classifiers":[
        {
            "category":"Building & Trades",
            "subcategory":"Landscaping Services",
            "type":"Services"
        }
    ],
    "sg:phone":"+1 203 329 2731",
    "sg:postcode":"06903",
    "sg:province":"CT",
    "wof:name":"Highland Tree Service",
    "wof:placetype":"venue"
},
  "geometry": {"coordinates":[-73.548377,41.161959],"type":"Point"}
}