{
  "type": "Feature",
  "properties": {
    "iso:country":"US",
    "sg:address":"55 Hillside Ave",
    "sg:city":"Hartford",
    "sg:classifiers":[
        {
            "category":"Recreation",
            "type":"Entertainment"
        }
    ],
    "sg:phone":"+1   ",
    "sg:postcode":"06106",
    "sg:province":"CT",
    "wof:name":"Driving Range",
    "wof:placetype":"venue"
},
  "geometry": {"coordinates":[-72.697625,41.752727],"type":"Point"}
}