{
  "type": "Feature",
  "properties": {
    "iso:country":"US",
    "sg:address":"200 S Main St",
    "sg:city":"Cheshire",
    "sg:classifiers":[
        {
            "category":"Restaurant",
            "type":"Food & Drink"
        }
    ],
    "sg:phone":"+1 203 271 1910",
    "sg:postcode":"06410",
    "sg:province":"CT",
    "wof:name":"Downey's Restaurant",
    "wof:placetype":"venue"
},
  "geometry": {"coordinates":[-72.902874,41.496209],"type":"Point"}
}