{
  "type": "Feature",
  "properties": {
    "iso:country":"US",
    "sg:address":"89 Stanwell Rd",
    "sg:city":"Newington",
    "sg:classifiers":[
        {
            "category":"Building & Trades",
            "subcategory":"Construction",
            "type":"Services"
        }
    ],
    "sg:phone":"+1 860 666 2035",
    "sg:postcode":"06111",
    "sg:province":"CT",
    "sg:tags":[
        "contractor"
    ],
    "wof:name":"Pelletier Roofing & Siding Co",
    "wof:placetype":"venue"
},
  "geometry": {"coordinates":[-72.72661100000001,41.667454],"type":"Point"}
}