{
  "type": "Feature",
  "properties": {
    "addr:full":"154 Elm St Thomaston CT 06787",
    "addr:housenumber":"154",
    "addr:postcode":"06787",
    "addr:street":"Elm St Thomaston Ct",
    "iso:country":"US",
    "sg:address":"154 Elm St",
    "sg:city":"Thomaston",
    "sg:classifiers":[
        {
            "category":"Health Services",
            "subcategory":"Chiropractor",
            "type":"Services"
        }
    ],
    "sg:phone":"+1   ",
    "sg:postcode":"06787",
    "sg:province":"CT",
    "wof:name":"Paul M Didomizio DC",
    "wof:placetype":"venue"
},
  "geometry": {"coordinates":[-73.07290399999999,41.671436],"type":"Point"}
}