{
  "type": "Feature",
  "properties": {
    "iso:country":"US",
    "sg:address":"371 E Main St",
    "sg:city":"Middletown",
    "sg:classifiers":[
        {
            "category":"Banks & Credit Unions",
            "subcategory":"Bank",
            "type":"Services"
        }
    ],
    "sg:phone":"+1 860 638 6996",
    "sg:postcode":"06457",
    "sg:province":"CT",
    "sg:tags":[
        "federal",
        "savings",
        "institution"
    ],
    "wof:name":"Webster Bank",
    "wof:placetype":"venue"
},
  "geometry": {"coordinates":[-72.638566,41.54498],"type":"Point"}
}