{
  "type": "Feature",
  "properties": {
    "addr:full":"58 Farms Rd Stamford CT 06903",
    "addr:housenumber":"58",
    "addr:postcode":"06903",
    "addr:street":"Farms Rd",
    "iso:country":"US",
    "sg:address":"58 Farms Rd",
    "sg:city":"Stamford",
    "sg:classifiers":[
        {
            "category":"Professional",
            "subcategory":"Accounting & Tax Preparation",
            "type":"Services"
        }
    ],
    "sg:phone":"+1   ",
    "sg:postcode":"06903",
    "sg:province":"CT",
    "wof:name":"Stamford Health",
    "wof:placetype":"venue"
},
  "geometry": {"coordinates":[-73.600854,41.123877],"type":"Point"}
}