{
  "type": "Feature",
  "properties": {
    "iso:country":"US",
    "sg:address":"15 Woodacre Ln",
    "sg:city":"Monroe",
    "sg:classifiers":[
        {
            "category":"Building & Trades",
            "subcategory":"Cleaning & Sanitation",
            "type":"Services"
        }
    ],
    "sg:phone":"+1   ",
    "sg:postcode":"06468",
    "sg:province":"CT",
    "sg:tags":[
        "maintenance"
    ],
    "wof:name":"Guarna Lndscpng & Maint Dvlpmt",
    "wof:placetype":"venue"
},
  "geometry": {"coordinates":[-73.262078,41.330405],"type":"Point"}
}