{
  "type": "Feature",
  "properties": {
    "addr:full":"95 N Main St Branford CT 06405",
    "addr:housenumber":"95",
    "addr:postcode":"06405",
    "addr:street":"N Main St",
    "iso:country":"US",
    "sg:address":"95 N Main St",
    "sg:city":"Branford",
    "sg:classifiers":[
        {
            "category":"Personal",
            "type":"Services"
        }
    ],
    "sg:phone":"+1   ",
    "sg:postcode":"06405",
    "sg:province":"CT",
    "sg:tags":[
        "shop",
        "beauty"
    ],
    "wof:name":"X S A Salon",
    "wof:placetype":"venue"
},
  "geometry": {"coordinates":[-72.820493,41.283987],"type":"Point"}
}