{
  "type": "Feature",
  "properties": {
    "iso:country":"US",
    "sg:address":"1257 S Broad St",
    "sg:city":"Wallingford",
    "sg:classifiers":[
        {
            "category":"Banks & Credit Unions",
            "subcategory":"Bank",
            "type":"Services"
        }
    ],
    "sg:phone":"+1 203 265 9753",
    "sg:postcode":"06492",
    "sg:province":"CT",
    "sg:tags":[
        "financing"
    ],
    "wof:name":"Beneficial Connecticut Inc",
    "wof:placetype":"venue"
},
  "geometry": {"coordinates":[-72.809808,41.506111],"type":"Point"}
}