{
  "type": "Feature",
  "properties": {
    "addr:full":"1757 Post Rd E Westport CT 06880",
    "addr:housenumber":"1757",
    "addr:postcode":"06880",
    "addr:street":"Post Rd E Westport Ct",
    "iso:country":"US",
    "sg:address":"1757 Post Rd E",
    "sg:city":"Westport",
    "sg:classifiers":[
        {
            "category":"Restaurant",
            "type":"Food & Drink"
        },
        {
            "category":"Food & Beverages",
            "subcategory":"Ethnic Foods",
            "type":"Retail Goods"
        }
    ],
    "sg:phone":"+1 203 256 8882",
    "sg:postcode":"06880",
    "sg:province":"CT",
    "sg:tags":[
        "asian",
        "pan",
        "vietnamese"
    ],
    "wof:name":"Asian Cafe Of Westport",
    "wof:placetype":"venue"
},
  "geometry": {"coordinates":[-73.30164499999999,41.138335],"type":"Point"}
}