{
  "type": "Feature",
  "properties": {
    "iso:country":"US",
    "sg:address":"80 Halstead Ave",
    "sg:city":"Port Chester",
    "sg:classifiers":[
        {
            "category":"Building & Trades",
            "subcategory":"Construction",
            "type":"Services"
        }
    ],
    "sg:phone":"+1 914 690 9191",
    "sg:postcode":"10573",
    "sg:province":"CT",
    "sg:tags":[
        "painter"
    ],
    "wof:name":"H Roberto Zanetti",
    "wof:placetype":"venue"
},
  "geometry": {"coordinates":[-73.659875,41.016356],"type":"Point"}
}