{
  "type": "Feature",
  "properties": {
    "iso:country":"US",
    "sg:address":"59 Main St",
    "sg:city":"Winsted",
    "sg:classifiers":[
        {
            "category":"Ice Cream",
            "type":"Food & Drink"
        }
    ],
    "sg:menulink":"http://www.allmenus.com/ct/winchester/164958-dairy-queen/menu/",
    "sg:phone":"+1 860 379 6733",
    "sg:postcode":"06098",
    "sg:province":"CT",
    "sg:tags":[
        "burger",
        "american"
    ],
    "wof:name":"Dairy Queen",
    "wof:placetype":"venue"
},
  "geometry": {"coordinates":[-73.060267,41.920927],"type":"Point"}
}