{
  "type": "Feature",
  "properties": {
    "addr:full":"2 Elizabeth St West Haven CT 06516",
    "addr:housenumber":"2",
    "addr:postcode":"06516",
    "addr:street":"Elizabeth St;Haven",
    "iso:country":"US",
    "sg:address":"2 Elizabeth St",
    "sg:city":"West Haven",
    "sg:classifiers":[
        {
            "category":"Building & Trades",
            "subcategory":"Construction",
            "type":"Services"
        }
    ],
    "sg:phone":"+1 203 387 2400",
    "sg:postcode":"06516",
    "sg:province":"CT",
    "sg:tags":[
        "contractor"
    ],
    "wof:name":"American Environmental",
    "wof:placetype":"venue"
},
  "geometry": {"coordinates":[-72.973868,41.30347],"type":"Point"}
}