{
  "type": "Feature",
  "properties": {
    "iso:country":"US",
    "sg:address":"145 W Woods Rd",
    "sg:city":"Hamden",
    "sg:classifiers":[
        {
            "category":"Professional",
            "subcategory":"Computer Services",
            "type":"Services"
        }
    ],
    "sg:phone":"+1   ",
    "sg:postcode":"06518",
    "sg:province":"CT",
    "sg:tags":[
        "applied",
        "consulting",
        "technology",
        "research"
    ],
    "wof:name":"Infotronix Research Intl",
    "wof:placetype":"venue"
},
  "geometry": {"coordinates":[-72.917208,41.419923],"type":"Point"}
}