{
  "type": "Feature",
  "properties": {
    "iso:country":"US",
    "sg:address":"126 Middlebrook Rd",
    "sg:city":"Hartford",
    "sg:classifiers":[
        {
            "category":"Building & Trades",
            "subcategory":"Cleaning & Sanitation",
            "type":"Services"
        }
    ],
    "sg:phone":"+1   ",
    "sg:postcode":"06119",
    "sg:province":"CT",
    "sg:tags":[
        "maintenance"
    ],
    "wof:name":"Nicks Cleaning Service",
    "wof:placetype":"venue"
},
  "geometry": {"coordinates":[-72.73526099999999,41.776192],"type":"Point"}
}