{
  "type": "Feature",
  "properties": {
    "iso:country":"US",
    "sg:address":"685 State St",
    "sg:city":"New Haven",
    "sg:classifiers":[
        {
            "category":"Professional",
            "subcategory":"Lawyer & Legal Services",
            "type":"Services"
        }
    ],
    "sg:phone":"+1 203 787 4431",
    "sg:postcode":"06511",
    "sg:province":"CT",
    "sg:tags":[
        "attorney"
    ],
    "wof:name":"Kinney & Secola",
    "wof:placetype":"venue"
},
  "geometry": {"coordinates":[-72.918116,41.310007],"type":"Point"}
}