{
  "type": "Feature",
  "properties": {
    "addr:full":"3190 Whitney Ave Hamden CT 06518",
    "addr:housenumber":"3190",
    "addr:postcode":"06518",
    "addr:street":"Whitney Ave",
    "iso:country":"US",
    "sg:address":"3190 Whitney Ave",
    "sg:city":"Hamden",
    "sg:classifiers":[
        {
            "category":"Professional",
            "subcategory":"Lawyer & Legal Services",
            "type":"Services"
        }
    ],
    "sg:phone":"+1   ",
    "sg:postcode":"06518",
    "sg:province":"CT",
    "wof:name":"Doherty Francis J",
    "wof:placetype":"venue"
},
  "geometry": {"coordinates":[-72.901003,41.410657],"type":"Point"}
}