{
  "type": "Feature",
  "properties": {
    "iso:country":"US",
    "sg:address":"915 E Main St",
    "sg:city":"Meriden",
    "sg:classifiers":[
        {
            "category":"Organizations",
            "subcategory":"Religious Organization",
            "type":"Services"
        }
    ],
    "sg:phone":"+1   ",
    "sg:postcode":"06450",
    "sg:province":"CT",
    "wof:name":"Holy Angels Rectory",
    "wof:placetype":"venue"
},
  "geometry": {"coordinates":[-72.772324,41.527135],"type":"Point"}
}