{
  "type": "Feature",
  "properties": {
    "addr:full":"30 Kent Cornwall Rd Kent CT 06757",
    "addr:housenumber":"30",
    "addr:postcode":"06757",
    "addr:street":"Kent Cornwall Rd",
    "iso:country":"US",
    "sg:address":"30 Kent Cornwall Rd",
    "sg:city":"Kent",
    "sg:classifiers":[
        {
            "category":"Shopping",
            "subcategory":"Used Merchandise",
            "type":"Retail Goods"
        }
    ],
    "sg:phone":"+1 860 927 3430",
    "sg:postcode":"06757",
    "sg:province":"CT",
    "sg:tags":[
        "durable"
    ],
    "wof:name":"Company Store Antiques",
    "wof:placetype":"venue"
},
  "geometry": {"coordinates":[-73.46627599999999,41.739523],"type":"Point"}
}