{
  "type": "Feature",
  "properties": {
    "addr:full":"161 Main St Deep River CT 06417",
    "addr:housenumber":"161",
    "addr:postcode":"06417",
    "addr:street":"Main St",
    "iso:country":"US",
    "sg:address":"161 Main St",
    "sg:city":"Deep River",
    "sg:classifiers":[
        {
            "category":"Shopping",
            "subcategory":"Gifts & Souvenirs",
            "type":"Retail Goods"
        }
    ],
    "sg:phone":"+1 860 526 5134",
    "sg:postcode":"06417",
    "sg:province":"CT",
    "sg:tags":[
        "clothing"
    ],
    "wof:name":"Celebrations",
    "wof:placetype":"venue"
},
  "geometry": {"coordinates":[-72.435694,41.385591],"type":"Point"}
}