{
  "type": "Feature",
  "properties": {
    "addr:full":"167 Long Hill Rd Waterbury CT 06704",
    "addr:housenumber":"167",
    "addr:postcode":"06704",
    "addr:street":"Long Hill Rd",
    "iso:country":"US",
    "sg:address":"167 Long Hill Rd",
    "sg:city":"Waterbury",
    "sg:classifiers":[
        {
            "category":"Food & Beverages",
            "subcategory":"Liquor & Beverages",
            "type":"Retail Goods"
        }
    ],
    "sg:phone":"+1 203 753 2444",
    "sg:postcode":"06704",
    "sg:province":"CT",
    "sg:tags":[
        "alcoholic"
    ],
    "wof:name":"Harold's Package Store",
    "wof:placetype":"venue"
},
  "geometry": {"coordinates":[-73.02185,41.56227],"type":"Point"}
}