{
  "type": "Feature",
  "properties": {
    "addr:full":"33 Water St Guilford CT 06437",
    "addr:housenumber":"33",
    "addr:postcode":"06437",
    "addr:street":"Water St",
    "iso:country":"US",
    "sg:address":"33 Water St",
    "sg:city":"Guilford",
    "sg:classifiers":[
        {
            "category":"Health Services",
            "subcategory":"Clinic",
            "type":"Services"
        }
    ],
    "sg:phone":"+1   ",
    "sg:postcode":"06437",
    "sg:province":"CT",
    "sg:tags":[
        "specialty",
        "outpatient"
    ],
    "wof:name":"Sarah Inc",
    "wof:placetype":"venue"
},
  "geometry": {"coordinates":[-72.68240299999999,41.281079],"type":"Point"}
}