{
  "type": "Feature",
  "properties": {
    "iso:country":"US",
    "sg:address":"3 Longview Dr",
    "sg:city":"Bloomfield",
    "sg:classifiers":[
        {
            "category":"Professional",
            "subcategory":"Accounting & Tax Preparation",
            "type":"Services"
        }
    ],
    "sg:phone":"+1   ",
    "sg:postcode":"06002",
    "sg:province":"CT",
    "wof:name":"Johnny G Wilson CPA",
    "wof:placetype":"venue"
},
  "geometry": {"coordinates":[-72.72748300000001,41.840808],"type":"Point"}
}