{
  "type": "Feature",
  "properties": {
    "addr:full":"614 New Britain Ave Hartford CT 06106",
    "addr:housenumber":"614",
    "addr:postcode":"06106",
    "addr:street":"New Britain Ave;Ct",
    "iso:country":"US",
    "sg:address":"614 New Britain Ave",
    "sg:city":"Hartford",
    "sg:classifiers":[
        {
            "category":"Social Services",
            "type":"Services"
        }
    ],
    "sg:phone":"+1   ",
    "sg:postcode":"06106",
    "sg:province":"CT",
    "wof:name":"Maple Leaf Manor Inc",
    "wof:placetype":"venue"
},
  "geometry": {"coordinates":[-72.70144000000001,41.734377],"type":"Point"}
}