{
  "type": "Feature",
  "properties": {
    "iso:country":"US",
    "sg:address":"1191 Ridge Rd",
    "sg:city":"North Haven",
    "sg:classifiers":[
        {
            "category":"Health Services",
            "subcategory":"Clinic",
            "type":"Services"
        }
    ],
    "sg:phone":"+1   ",
    "sg:postcode":"06473",
    "sg:province":"CT",
    "sg:tags":[
        "home",
        "care"
    ],
    "wof:name":"Environment & Human Healt",
    "wof:placetype":"venue"
},
  "geometry": {"coordinates":[-72.898506,41.367304],"type":"Point"}
}