{
  "type": "Feature",
  "properties": {
    "addr:full":"26 Chestnut Hill Rd Norwalk CT 06851",
    "addr:housenumber":"26",
    "addr:postcode":"06851",
    "addr:street":"Chestnut Hill Rd",
    "iso:country":"US",
    "sg:address":"26 Chestnut Hill Rd",
    "sg:city":"Norwalk",
    "sg:classifiers":[
        {
            "category":"Banks & Credit Unions",
            "subcategory":"Bank",
            "type":"Services"
        }
    ],
    "sg:phone":"+1 203 857 5577",
    "sg:postcode":"06851",
    "sg:province":"CT",
    "wof:name":"Fairfield County Bank",
    "wof:placetype":"venue"
},
  "geometry": {"coordinates":[-73.394904,41.147863],"type":"Point"}
}