{
  "type": "Feature",
  "properties": {
    "addr:full":"20 Perkins Rd Pleasant Valley CT 06098",
    "addr:housenumber":"20",
    "addr:postcode":"06098",
    "addr:street":"Perkins Rd Pleasant Valley Ct",
    "iso:country":"US",
    "sg:address":"20 Perkins Rd",
    "sg:city":"Pleasant Valley",
    "sg:classifiers":[
        {
            "category":"Shopping",
            "type":"Retail Goods"
        }
    ],
    "sg:phone":"+1 860 379 0076",
    "sg:postcode":"06098",
    "sg:province":"CT",
    "sg:tags":[
        "merchandise"
    ],
    "wof:name":"North End Store",
    "wof:placetype":"venue"
},
  "geometry": {"coordinates":[-73.034323,41.890316],"type":"Point"}
}