{
  "type": "Feature",
  "properties": {
    "addr:full":"30 Hickory Hill Ln Newington CT 06111",
    "addr:housenumber":"30",
    "addr:postcode":"06111",
    "addr:street":"Hickory Hill Ln",
    "iso:country":"US",
    "sg:address":"30 Hickory Hill Ln",
    "sg:city":"Newington",
    "sg:classifiers":[
        {
            "category":"Professional",
            "subcategory":"Management & Consulting",
            "type":"Services"
        }
    ],
    "sg:phone":"+1   ",
    "sg:postcode":"06111",
    "sg:province":"CT",
    "wof:name":"Assoc For Cons Trng",
    "wof:placetype":"venue"
},
  "geometry": {"coordinates":[-72.74922599999999,41.66355],"type":"Point"}
}