{
  "type": "Feature",
  "properties": {
    "iso:country":"US",
    "sg:address":"38 Fairchild Rd",
    "sg:city":"Sharon",
    "sg:classifiers":[
        {
            "category":"Sports & Exercise",
            "subcategory":"Race Track",
            "type":"Entertainment"
        }
    ],
    "sg:phone":"+1   ",
    "sg:postcode":"06069",
    "sg:province":"CT",
    "sg:tags":[
        "operation",
        "racing",
        "or"
    ],
    "wof:name":"Idle Hour Motor Sports LLC",
    "wof:placetype":"venue"
},
  "geometry": {"coordinates":[-73.44355899999999,41.872787],"type":"Point"}
}