{
  "type": "Feature",
  "properties": {
    "addr:full":"2 Higby Dr Meriden CT 06450",
    "addr:housenumber":"2",
    "addr:postcode":"06450",
    "addr:street":"Higby Dr",
    "iso:country":"US",
    "sg:address":"2 Higby Dr",
    "sg:city":"Meriden",
    "sg:classifiers":[
        {
            "category":"Building & Trades",
            "subcategory":"Construction",
            "type":"Services"
        }
    ],
    "sg:phone":"+1 203 639 9514",
    "sg:postcode":"06450",
    "sg:province":"CT",
    "sg:tags":[
        "roofing",
        "contractor"
    ],
    "wof:name":"Triple R Construction LLC",
    "wof:placetype":"venue"
},
  "geometry": {"coordinates":[-72.760144,41.542795],"type":"Point"}
}