{
  "type": "Feature",
  "properties": {
    "iso:country":"US",
    "sg:address":"400 Central Ave",
    "sg:city":"New Haven",
    "sg:classifiers":[
        {
            "category":"Professional",
            "type":"Services"
        }
    ],
    "sg:phone":"+1 203 387 1283",
    "sg:postcode":"06515",
    "sg:province":"CT",
    "wof:name":"Bop Audio Inc",
    "wof:placetype":"venue"
},
  "geometry": {"coordinates":[-72.96217,41.320318],"type":"Point"}
}