{
  "type": "Feature",
  "properties": {
    "iso:country":"US",
    "sg:address":"60 Larkspur Rd",
    "sg:city":"Stamford",
    "sg:classifiers":[
        {
            "category":"Professional",
            "subcategory":"Accounting & Tax Preparation",
            "type":"Services"
        }
    ],
    "sg:phone":"+1   ",
    "sg:postcode":"06903",
    "sg:province":"CT",
    "wof:name":"Tisch Frederic",
    "wof:placetype":"venue"
},
  "geometry": {"coordinates":[-73.55033299999999,41.137692],"type":"Point"}
}