{
  "type": "Feature",
  "properties": {
    "iso:country":"US",
    "sg:address":"48 Elm St",
    "sg:city":"New Canaan",
    "sg:classifiers":[
        {
            "category":"Restaurant",
            "type":"Food & Drink"
        }
    ],
    "sg:menulink":"http://www.allmenus.com/ct/new-canaan/25306-villarinas-pasta--foods/menu/",
    "sg:phone":"+1 203 972 7860",
    "sg:postcode":"06840",
    "sg:province":"CT",
    "sg:tags":[
        "italian"
    ],
    "wof:name":"Villarina's Pasta & Foods",
    "wof:placetype":"venue"
},
  "geometry": {"coordinates":[-73.493032,41.14693],"type":"Point"}
}