{
  "type": "Feature",
  "properties": {
    "iso:country":"US",
    "sg:address":"1 Nettle Ln",
    "sg:city":"Ridgefield",
    "sg:classifiers":[
        {
            "category":"Professional",
            "type":"Services"
        }
    ],
    "sg:phone":"+1 203 438 8801",
    "sg:postcode":"06877",
    "sg:province":"CT",
    "sg:tags":[
        "establishment"
    ],
    "wof:name":"Avanti",
    "wof:placetype":"venue"
},
  "geometry": {"coordinates":[-73.49185799999999,41.300489],"type":"Point"}
}