{
  "type": "Feature",
  "properties": {
    "addr:full":"95 Broad St New Britain CT 06053",
    "addr:housenumber":"95",
    "addr:postcode":"06053",
    "addr:street":"Broad St",
    "iso:country":"US",
    "sg:address":"95 Broad St",
    "sg:city":"New Britain",
    "sg:classifiers":[
        {
            "category":"Food & Beverages",
            "subcategory":"Groceries & Convenience Stores",
            "type":"Retail Goods"
        }
    ],
    "sg:phone":"+1 860 826 7797",
    "sg:postcode":"06053",
    "sg:province":"CT",
    "sg:tags":[
        "product",
        "produce",
        "dairy",
        "bakery"
    ],
    "wof:name":"Zieleniak A Garden Grocer",
    "wof:placetype":"venue"
},
  "geometry": {"coordinates":[-72.78683599999999,41.673406],"type":"Point"}
}