{
  "type": "Feature",
  "properties": {
    "iso:country":"US",
    "sg:address":"36 E Grand Ave",
    "sg:city":"New Haven",
    "sg:classifiers":[
        {
            "category":"Restaurant",
            "type":"Food & Drink"
        }
    ],
    "sg:menulink":"http://www.allmenus.com/ct/new-haven/280751-ziggys-pizza-restaurant/menu/",
    "sg:phone":"+1 203 466 3637",
    "sg:postcode":"06513",
    "sg:province":"CT",
    "sg:tags":[
        "american",
        "pizza"
    ],
    "wof:name":"Ziggy's Pizza Restaurant",
    "wof:placetype":"venue"
},
  "geometry": {"coordinates":[-72.88629,41.308289],"type":"Point"}
}