{
  "type": "Feature",
  "properties": {
    "iso:country":"US",
    "sg:address":"1315 Main St",
    "sg:city":"Willimantic",
    "sg:classifiers":[
        {
            "category":"Health Services",
            "subcategory":"Doctor",
            "type":"Services"
        }
    ],
    "sg:phone":"+1   ",
    "sg:postcode":"06226",
    "sg:province":"CT",
    "sg:tags":[
        "federally",
        "qualified",
        "center",
        "community"
    ],
    "wof:name":"GENERATIONS",
    "wof:placetype":"venue"
},
  "geometry": {"coordinates":[-72.22921700000001,41.715439],"type":"Point"}
}