{
  "type": "Feature",
  "properties": {
    "addr:full":"80 Liberty Hill E Wethersfield CT 06109",
    "addr:housenumber":"80",
    "addr:postcode":"06109",
    "addr:street":"Liberty Hill E Wethersfield Ct",
    "iso:country":"US",
    "sg:address":"80 Liberty Hill E",
    "sg:city":"Wethersfield",
    "sg:classifiers":[
        {
            "category":"Professional",
            "subcategory":"Business Services",
            "type":"Services"
        }
    ],
    "sg:phone":"+1   ",
    "sg:postcode":"06109",
    "sg:province":"CT",
    "sg:tags":[
        "personal",
        "bureau",
        "broker",
        "agent"
    ],
    "wof:name":"Rjd Development Co",
    "wof:placetype":"venue"
},
  "geometry": {"coordinates":[-72.70043699999999,41.673743],"type":"Point"}
}