{
  "type": "Feature",
  "properties": {
    "addr:full":"64 Avonwood Rd Avon CT 06001",
    "addr:housenumber":"64",
    "addr:postcode":"06001",
    "addr:street":"Avonwood Rd",
    "iso:country":"US",
    "sg:address":"64 Avonwood Rd",
    "sg:city":"Avon",
    "sg:classifiers":[
        {
            "category":"Professional",
            "subcategory":"Employment Agencies",
            "type":"Services"
        }
    ],
    "sg:phone":"+1   ",
    "sg:postcode":"06001",
    "sg:province":"CT",
    "wof:name":"Osland LLC",
    "wof:placetype":"venue"
},
  "geometry": {"coordinates":[-72.820549,41.800933],"type":"Point"}
}