{
  "type": "Feature",
  "properties": {
    "addr:full":"22 Little Plain Rd Trumbull CT 06611",
    "addr:housenumber":"22",
    "addr:postcode":"06611",
    "addr:street":"Little Plain Rd",
    "iso:country":"US",
    "sg:address":"22 Little Plain Rd",
    "sg:city":"Trumbull",
    "sg:classifiers":[
        {
            "category":"Building & Trades",
            "subcategory":"Construction",
            "type":"Services"
        }
    ],
    "sg:phone":"+1 203 459 1500",
    "sg:postcode":"06611",
    "sg:province":"CT",
    "sg:tags":[
        "contractor"
    ],
    "wof:name":"Sunsplash Pools Inc",
    "wof:placetype":"venue"
},
  "geometry": {"coordinates":[-73.195127,41.248041],"type":"Point"}
}