{
  "type": "Feature",
  "properties": {
    "addr:full":"160 Main St Thomaston CT 06787",
    "addr:housenumber":"160",
    "addr:postcode":"06787",
    "addr:street":"Main St",
    "iso:country":"US",
    "sg:address":"160 Main St",
    "sg:city":"Thomaston",
    "sg:classifiers":[
        {
            "category":"Organizations",
            "subcategory":"Religious Organization",
            "type":"Services"
        }
    ],
    "sg:phone":"+1   ",
    "sg:postcode":"06787",
    "sg:province":"CT",
    "wof:name":"Saint Peters Trnty Epscpl Chu",
    "wof:placetype":"venue"
},
  "geometry": {"coordinates":[-73.074352,41.673448],"type":"Point"}
}