{
  "type": "Feature",
  "properties": {
    "iso:country":"US",
    "sg:address":"656 Bridgeport Ave",
    "sg:city":"Shelton",
    "sg:classifiers":[
        {
            "category":"Shopping",
            "subcategory":"Florist",
            "type":"Retail Goods"
        }
    ],
    "sg:phone":"+1 203 926 0524",
    "sg:postcode":"06484",
    "sg:province":"CT",
    "sg:tags":[
        "plant",
        "shrub"
    ],
    "wof:name":"Wells Hollow Farms",
    "wof:placetype":"venue"
},
  "geometry": {"coordinates":[-73.12561599999999,41.273334],"type":"Point"}
}