{
  "type": "Feature",
  "properties": {
    "addr:full":"34 Shunpike Rd Cromwell CT 06416",
    "addr:housenumber":"34",
    "addr:postcode":"06416",
    "addr:street":"Shunpike Rd Cromwell Ct",
    "iso:country":"US",
    "sg:address":"34 Shunpike Rd",
    "sg:city":"Cromwell",
    "sg:classifiers":[
        {
            "category":"Shopping",
            "subcategory":"Gifts & Souvenirs",
            "type":"Retail Goods"
        }
    ],
    "sg:phone":"+1 860 635 5037",
    "sg:postcode":"06416",
    "sg:province":"CT",
    "wof:name":"Wild Rasberry",
    "wof:placetype":"venue"
},
  "geometry": {"coordinates":[-72.675995,41.602799],"type":"Point"}
}