{
  "type": "Feature",
  "properties": {
    "iso:country":"US",
    "sg:address":"15 Kings Ct",
    "sg:city":"Derby",
    "sg:classifiers":[
        {
            "category":"Manufacturing",
            "subcategory":"Printing",
            "type":"Manufacturing & Wholesale Goods"
        }
    ],
    "sg:phone":"+1 203 924 9926",
    "sg:postcode":"06418",
    "sg:province":"CT",
    "sg:tags":[
        "screen",
        "silk"
    ],
    "wof:name":"Yankee Screen Printing",
    "wof:placetype":"venue"
},
  "geometry": {"coordinates":[-73.064485,41.322142],"type":"Point"}
}