{
  "type": "Feature",
  "properties": {
    "iso:country":"US",
    "sg:address":"30 Village View Ter",
    "sg:city":"Meriden",
    "sg:classifiers":[
        {
            "category":"Organizations",
            "subcategory":"Membership Organization",
            "type":"Services"
        }
    ],
    "sg:phone":"+1 203 639 7225",
    "sg:postcode":"06451",
    "sg:province":"CT",
    "wof:name":"Cushing's Disease Foundation",
    "wof:placetype":"venue"
},
  "geometry": {"coordinates":[-72.83958699999999,41.52102],"type":"Point"}
}