{
  "type": "Feature",
  "properties": {
    "iso:country":"US",
    "sg:address":"43 Jones St",
    "sg:city":"West Haven",
    "sg:classifiers":[
        {
            "category":"Professional",
            "subcategory":"Management & Consulting",
            "type":"Services"
        }
    ],
    "sg:phone":"+1   ",
    "sg:postcode":"06516",
    "sg:province":"CT",
    "sg:tags":[
        "business"
    ],
    "wof:name":"Donna Matthews Candles",
    "wof:placetype":"venue"
},
  "geometry": {"coordinates":[-72.93658600000001,41.270698],"type":"Point"}
}