{
  "type": "Feature",
  "properties": {
    "addr:full":"1461 S Britain Rd Southbury CT 06488",
    "addr:housenumber":"1461",
    "addr:postcode":"06488",
    "addr:street":"S Britain Rd",
    "iso:country":"US",
    "sg:address":"1461 S Britain Rd",
    "sg:city":"Southbury",
    "sg:classifiers":[
        {
            "category":"Health Services",
            "subcategory":"Medical Lab",
            "type":"Services"
        }
    ],
    "sg:phone":"+1 203 264 0840",
    "sg:postcode":"06488",
    "sg:province":"CT",
    "sg:tags":[
        "laboratory"
    ],
    "wof:name":"Hartford Medical Laboratories",
    "wof:placetype":"venue"
},
  "geometry": {"coordinates":[-73.26099000000001,41.489472],"type":"Point"}
}