{
  "type": "Feature",
  "properties": {
    "iso:country":"US",
    "sg:address":"28 Whalley St",
    "sg:city":"Meriden",
    "sg:phone":"+1 203 237 1404",
    "sg:postcode":"06451",
    "sg:province":"CT",
    "sg:tags":[
        "oil"
    ],
    "wof:name":"Barillaro Heating & Fuel Oil",
    "wof:placetype":"venue"
},
  "geometry": {"coordinates":[-72.813541,41.553028],"type":"Point"}
}