{
  "type": "Feature",
  "properties": {
    "addr:full":"607 Main Ave Norwalk CT 06851",
    "addr:housenumber":"607",
    "addr:postcode":"06851",
    "addr:street":"Main Ave",
    "iso:country":"US",
    "sg:address":"607 Main Ave",
    "sg:city":"Norwalk",
    "sg:classifiers":[
        {
            "category":"Education",
            "subcategory":"Special Training",
            "type":"Public Place"
        }
    ],
    "sg:phone":"+1 203 750 8886",
    "sg:postcode":"06851",
    "sg:province":"CT",
    "sg:tags":[
        "tutoring"
    ],
    "wof:name":"Tutoring Club",
    "wof:placetype":"venue"
},
  "geometry": {"coordinates":[-73.421443,41.15767],"type":"Point"}
}