{
  "type": "Feature",
  "properties": {
    "addr:full":"17 Park St Norwalk CT 06851",
    "addr:housenumber":"17",
    "addr:postcode":"06851",
    "addr:street":"Park St",
    "iso:country":"US",
    "sg:address":"17 Park St",
    "sg:city":"Norwalk",
    "sg:classifiers":[
        {
            "category":"Retail",
            "subcategory":"Animal Services",
            "type":"Services"
        }
    ],
    "sg:phone":"+1 203 750 9772",
    "sg:postcode":"06851",
    "sg:province":"CT",
    "wof:name":"Four Paws Grmng Sln Anmal Hosp",
    "wof:placetype":"venue"
},
  "geometry": {"coordinates":[-73.40871,41.121215],"type":"Point"}
}