{
  "type": "Feature",
  "properties": {
    "addr:full":"27 Depot St Watertown CT 06795",
    "addr:housenumber":"27",
    "addr:postcode":"06795",
    "addr:street":"Depot St",
    "iso:country":"US",
    "sg:address":"27 Depot St",
    "sg:city":"Watertown",
    "sg:classifiers":[
        {
            "category":"Health Services",
            "subcategory":"Health Practitioner",
            "type":"Services"
        }
    ],
    "sg:phone":"+1   ",
    "sg:postcode":"06795",
    "sg:province":"CT",
    "wof:name":"Charles A Opsahl PHD",
    "wof:placetype":"venue"
},
  "geometry": {"coordinates":[-73.115447,41.601958],"type":"Point"}
}