{
  "type": "Feature",
  "properties": {
    "iso:country":"US",
    "sg:address":"57 Stevens St",
    "sg:city":"Norwalk",
    "sg:classifiers":[
        {
            "category":"Food & Beverages",
            "subcategory":"Groceries & Convenience Stores",
            "type":"Retail Goods"
        },
        {
            "category":"Shopping",
            "subcategory":"Discount & Variety Stores",
            "type":"Retail Goods"
        }
    ],
    "sg:phone":"+1 203 852 8089",
    "sg:postcode":"06850",
    "sg:province":"CT",
    "sg:tags":[
        "grocer",
        "general"
    ],
    "wof:name":"Hill Confectionery & Grocery",
    "wof:placetype":"venue"
},
  "geometry": {"coordinates":[-73.42446700000001,41.110217],"type":"Point"}
}