{
  "type": "Feature",
  "properties": {
    "iso:country":"US",
    "sg:address":"158 Seaside Ave",
    "sg:city":"Stamford",
    "sg:classifiers":[
        {
            "category":"Professional",
            "subcategory":"Management & Consulting",
            "type":"Services"
        }
    ],
    "sg:phone":"+1 203 324 7555",
    "sg:postcode":"06902",
    "sg:province":"CT",
    "sg:tags":[
        "consultant",
        "business"
    ],
    "sg:website":"www.save-a-cent.com",
    "wof:name":"Havens Associate",
    "wof:placetype":"venue"
},
  "geometry": {"coordinates":[-73.509505,41.054476],"type":"Point"}
}