{
  "type": "Feature",
  "properties": {
    "iso:country":"US",
    "sg:address":"1477 N Grand St",
    "sg:city":"West Suffield",
    "sg:classifiers":[
        {
            "category":"Professional",
            "subcategory":"Accounting & Tax Preparation",
            "type":"Services"
        }
    ],
    "sg:phone":"+1   ",
    "sg:postcode":"06093",
    "sg:province":"CT",
    "wof:name":"Post Road Pub Accounting Off",
    "wof:placetype":"venue"
},
  "geometry": {"coordinates":[-72.691952,42.01957],"type":"Point"}
}