{
  "type": "Feature",
  "properties": {
    "addr:full":"1074 S Main St Cheshire CT 06410",
    "addr:housenumber":"1074",
    "addr:postcode":"06410",
    "addr:street":"S Main St",
    "iso:country":"US",
    "sg:address":"1074 S Main St",
    "sg:city":"Cheshire",
    "sg:classifiers":[
        {
            "category":"Wholesale",
            "subcategory":"Furniture",
            "type":"Manufacturing & Wholesale Goods"
        }
    ],
    "sg:phone":"+1 203 272 2088",
    "sg:postcode":"06410",
    "sg:province":"CT",
    "wof:name":"Timberline Office Supply Inc",
    "wof:placetype":"venue"
},
  "geometry": {"coordinates":[-72.906255,41.475494],"type":"Point"}
}