{
  "type": "Feature",
  "properties": {
    "iso:country":"US",
    "sg:address":"940 Boston Post Rd",
    "sg:city":"Milford",
    "sg:classifiers":[
        {
            "category":"Building & Trades",
            "subcategory":"Construction",
            "type":"Services"
        }
    ],
    "sg:phone":"+1 203 874 5754",
    "sg:postcode":"06460",
    "sg:province":"CT",
    "sg:tags":[
        "installs",
        "glass"
    ],
    "wof:name":"Eastern Shower Door",
    "wof:placetype":"venue"
},
  "geometry": {"coordinates":[-73.04890899999999,41.231899],"type":"Point"}
}