{
  "type": "Feature",
  "properties": {
    "addr:full":"191 Oak St Bridgeport CT 06604",
    "addr:housenumber":"191",
    "addr:postcode":"06604",
    "addr:street":"Oak St",
    "iso:country":"US",
    "sg:address":"191 Oak St",
    "sg:city":"Bridgeport",
    "sg:classifiers":[
        {
            "category":"Real Estate",
            "subcategory":"Real Estate Operator",
            "type":"Services"
        }
    ],
    "sg:phone":"+1 203 371 5339",
    "sg:postcode":"06604",
    "sg:province":"CT",
    "sg:tags":[
        "apartment",
        "complex"
    ],
    "wof:name":"Nu Site Realty Co",
    "wof:placetype":"venue"
},
  "geometry": {"coordinates":[-73.20194600000001,41.187247],"type":"Point"}
}