{
  "type": "Feature",
  "properties": {
    "iso:country":"US",
    "sg:address":"5 Heath St",
    "sg:city":"Hartford",
    "sg:classifiers":[
        {
            "category":"Personal",
            "subcategory":"Beauty Salon",
            "type":"Services"
        }
    ],
    "sg:phone":"+1   ",
    "sg:postcode":"06106",
    "sg:province":"CT",
    "sg:tags":[
        "shop"
    ],
    "wof:name":"Elite Beauty Salon",
    "wof:placetype":"venue"
},
  "geometry": {"coordinates":[-72.71091199999999,41.757273],"type":"Point"}
}