{
  "type": "Feature",
  "properties": {
    "addr:full":"118 Main St Hampton CT 06247",
    "addr:housenumber":"118",
    "addr:postcode":"06247",
    "addr:street":"Main St",
    "iso:country":"US",
    "sg:address":"118 Main St",
    "sg:city":"Hampton",
    "sg:classifiers":[
        {
            "category":"Professional",
            "subcategory":"Business Services",
            "type":"Services"
        }
    ],
    "sg:phone":"+1   ",
    "sg:postcode":"06247",
    "sg:province":"CT",
    "wof:name":"Curry Enterprises LLC",
    "wof:placetype":"venue"
},
  "geometry": {"coordinates":[-72.05495999999999,41.78316],"type":"Point"}
}