{
  "type": "Feature",
  "properties": {
    "iso:country":"US",
    "sg:address":"98 Round Hill Rd",
    "sg:city":"Guilford",
    "sg:classifiers":[
        {
            "category":"Professional",
            "subcategory":"Management & Consulting",
            "type":"Services"
        }
    ],
    "sg:phone":"+1   ",
    "sg:postcode":"06437",
    "sg:province":"CT",
    "sg:tags":[
        "business"
    ],
    "wof:name":"General Business Service",
    "wof:placetype":"venue"
},
  "geometry": {"coordinates":[-72.688822,41.346744],"type":"Point"}
}