{
  "type": "Feature",
  "properties": {
    "iso:country":"US",
    "sg:address":"470 Lewis Ave",
    "sg:city":"Meriden",
    "sg:classifiers":[
        {
            "category":"Shopping",
            "subcategory":"Computers & Home Electronics",
            "type":"Retail Goods"
        }
    ],
    "sg:phone":"+1 203 235 8788",
    "sg:postcode":"06451",
    "sg:province":"CT",
    "sg:tags":[
        "software"
    ],
    "wof:name":"Software Etc",
    "wof:placetype":"venue"
},
  "geometry": {"coordinates":[-72.803605,41.550627],"type":"Point"}
}