{
  "type": "Feature",
  "properties": {
    "iso:country":"US",
    "sg:address":"74 Main St",
    "sg:city":"Ansonia",
    "sg:classifiers":[
        {
            "category":"Professional",
            "subcategory":"Art Services",
            "type":"Services"
        }
    ],
    "sg:phone":"+1 203 734 2645",
    "sg:postcode":"06401",
    "sg:province":"CT",
    "sg:tags":[
        "photographer"
    ],
    "wof:name":"Rene's Pictures",
    "wof:placetype":"venue"
},
  "geometry": {"coordinates":[-73.079677,41.345325],"type":"Point"}
}