{
  "type": "Feature",
  "properties": {
    "addr:full":"17 Gleason Ave Stamford CT 06902",
    "addr:housenumber":"17",
    "addr:postcode":"06902",
    "addr:street":"Gleason Ave",
    "iso:country":"US",
    "sg:address":"17 Gleason Ave",
    "sg:city":"Stamford",
    "sg:classifiers":[
        {
            "category":"Retail",
            "subcategory":"Auto Repair",
            "type":"Services"
        }
    ],
    "sg:phone":"+1 203 327 1524",
    "sg:postcode":"06902",
    "sg:province":"CT",
    "sg:tags":[
        "repairing",
        "automobile",
        "automotive",
        "general"
    ],
    "wof:name":"T Murphy Auto Repair Inc",
    "wof:placetype":"venue"
},
  "geometry": {"coordinates":[-73.527714,41.047972],"type":"Point"}
}