{
  "type": "Feature",
  "properties": {
    "addr:full":"95 Old Post Rd Southport CT 06475",
    "addr:housenumber":"95",
    "addr:postcode":"06475",
    "addr:street":"Old Post Rd",
    "iso:country":"US",
    "sg:address":"95 Old Post Rd",
    "sg:city":"Southport",
    "sg:classifiers":[
        {
            "category":"Personal",
            "subcategory":"Beauty Salon",
            "type":"Services"
        }
    ],
    "sg:phone":"+1   ",
    "sg:postcode":"06475",
    "sg:province":"CT",
    "sg:tags":[
        "shop"
    ],
    "wof:name":"Arthurs of Southport Inc",
    "wof:placetype":"venue"
},
  "geometry": {"coordinates":[-72.399047,41.285292],"type":"Point"}
}