{
  "type": "Feature",
  "properties": {
    "addr:full":"69 Talcott Rd Hartford CT 06110",
    "addr:housenumber":"69",
    "addr:postcode":"06110",
    "addr:street":"Talcott Rd",
    "iso:country":"US",
    "sg:address":"69 Talcott Rd",
    "sg:city":"Hartford",
    "sg:classifiers":[
        {
            "category":"Wholesale",
            "subcategory":"Chemicals & Plastics",
            "type":"Manufacturing & Wholesale Goods"
        }
    ],
    "sg:phone":"+1 860 233 1611",
    "sg:postcode":"06110",
    "sg:province":"CT",
    "wof:name":"Aiudi A & Sons Llc",
    "wof:placetype":"venue"
},
  "geometry": {"coordinates":[-72.72255699999999,41.737021],"type":"Point"}
}