{
  "type": "Feature",
  "properties": {
    "iso:country":"US",
    "sg:address":"10 Sanford St",
    "sg:city":"Fairfield",
    "sg:classifiers":[
        {
            "category":"Home & Garden",
            "subcategory":"Household Appliances",
            "type":"Retail Goods"
        }
    ],
    "sg:phone":"+1 203 256 9750",
    "sg:postcode":"06483",
    "sg:province":"CT",
    "wof:name":"Affordable Appliance Repair",
    "wof:placetype":"venue"
},
  "geometry": {"coordinates":[-73.069783,41.395642],"type":"Point"}
}