{
  "type": "Feature",
  "properties": {
    "addr:full":"25 Research Pkwy Wallingford CT 06492",
    "addr:housenumber":"25",
    "addr:postcode":"06492",
    "addr:street":"Research Pkwy",
    "iso:country":"US",
    "sg:address":"25 Research Pkwy",
    "sg:city":"Wallingford",
    "sg:classifiers":[
        {
            "category":"Home & Garden",
            "subcategory":"Furniture",
            "type":"Retail Goods"
        }
    ],
    "sg:phone":"+1 203 294 8890",
    "sg:postcode":"06492",
    "sg:province":"CT",
    "sg:tags":[
        "cabinet"
    ],
    "sg:website":"www.durhammfg.com",
    "wof:name":"Durham Mfg Co",
    "wof:placetype":"venue"
},
  "geometry": {"coordinates":[-72.764123,41.495574],"type":"Point"}
}