{
  "type": "Feature",
  "properties": {
    "iso:country":"US",
    "sg:address":"55 Sarah Dr",
    "sg:city":"Avon",
    "sg:classifiers":[
        {
            "category":"Health Services",
            "subcategory":"Doctor",
            "type":"Services"
        }
    ],
    "sg:phone":"+1   ",
    "sg:postcode":"06001",
    "sg:province":"CT",
    "sg:tags":[
        "medical",
        "expert"
    ],
    "wof:name":"Kevin P Shea MD",
    "wof:placetype":"venue"
},
  "geometry": {"coordinates":[-72.867028,41.808598],"type":"Point"}
}