{
  "type": "Feature",
  "properties": {
    "iso:country":"US",
    "sg:address":"47 Sherwood Rd",
    "sg:city":"Stamford",
    "sg:classifiers":[
        {
            "category":"Health Services",
            "subcategory":"Health Practitioner",
            "type":"Services"
        }
    ],
    "sg:phone":"+1 203 329 3553",
    "sg:postcode":"06905",
    "sg:province":"CT",
    "sg:tags":[
        "psychologist"
    ],
    "wof:name":"Roberta Stiel",
    "wof:placetype":"venue"
},
  "geometry": {"coordinates":[-73.540987,41.08187],"type":"Point"}
}