{
  "type": "Feature",
  "properties": {
    "addr:full":"1038 Middletown Ave Northford CT 06472",
    "addr:housenumber":"1038",
    "addr:postcode":"06472",
    "addr:street":"Middletown Ave Northford Ct",
    "iso:country":"US",
    "sg:address":"1038 Middletown Ave",
    "sg:city":"Northford",
    "sg:classifiers":[
        {
            "category":"Professional",
            "subcategory":"Lawyer & Legal Services",
            "type":"Services"
        }
    ],
    "sg:phone":"+1   ",
    "sg:postcode":"06472",
    "sg:province":"CT",
    "wof:name":"Sawyer & Dubin",
    "wof:placetype":"venue"
},
  "geometry": {"coordinates":[-72.814886,41.379089],"type":"Point"}
}