{
  "type": "Feature",
  "properties": {
    "addr:full":"264 Spielman Hwy Burlington CT 06013",
    "addr:housenumber":"264",
    "addr:postcode":"06013",
    "addr:street":"Spielman Hwy",
    "iso:country":"US",
    "sg:address":"264 Spielman Hwy",
    "sg:city":"Burlington",
    "sg:classifiers":[
        {
            "category":"Social Services",
            "subcategory":"Child Care",
            "type":"Services"
        }
    ],
    "sg:phone":"+1 860 675 1591",
    "sg:postcode":"06013",
    "sg:province":"CT",
    "sg:tags":[
        "day"
    ],
    "wof:name":"Young Beginnings Children's Center",
    "wof:placetype":"venue"
},
  "geometry": {"coordinates":[-72.96199799999999,41.769699],"type":"Point"}
}