{
  "type": "Feature",
  "properties": {
    "addr:full":"18 Sunnyfield Dr Windsor CT 06095",
    "addr:housenumber":"18",
    "addr:postcode":"06095",
    "addr:street":"Sunnyfield Dr",
    "iso:country":"US",
    "sg:address":"18 Sunnyfield Dr",
    "sg:city":"Windsor",
    "sg:classifiers":[
        {
            "category":"Wholesale",
            "subcategory":"Sporting Goods",
            "type":"Manufacturing & Wholesale Goods"
        }
    ],
    "sg:phone":"+1 860 285 0322",
    "sg:postcode":"06095",
    "sg:province":"CT",
    "sg:tags":[
        "tackle",
        "fishing"
    ],
    "wof:name":"Reel Colors",
    "wof:placetype":"venue"
},
  "geometry": {"coordinates":[-72.667779,41.837371],"type":"Point"}
}