{
  "type": "Feature",
  "properties": {
    "iso:country":"US",
    "sg:address":"392 Main St",
    "sg:city":"Danbury",
    "sg:classifiers":[
        {
            "category":"Restaurant",
            "type":"Food & Drink"
        }
    ],
    "sg:menulink":"http://www.allmenus.com/ct/danbury/207951-taco-bell/menu/",
    "sg:phone":"+1 203 730 0332",
    "sg:postcode":"06810",
    "sg:province":"CT",
    "sg:tags":[
        "mexican"
    ],
    "wof:name":"Taco Bell",
    "wof:placetype":"venue"
},
  "geometry": {"coordinates":[-73.458941,41.401891],"type":"Point"}
}