{
  "type": "Feature",
  "properties": {
    "iso:country":"US",
    "sg:address":"260 S Frontage Rd",
    "sg:city":"New London",
    "sg:classifiers":[
        {
            "category":"Professional",
            "subcategory":"Research",
            "type":"Services"
        }
    ],
    "sg:phone":"+1   ",
    "sg:postcode":"06320",
    "sg:province":"CT",
    "sg:tags":[
        "organization",
        "noncommercial"
    ],
    "wof:name":"Galen Institute",
    "wof:placetype":"venue"
},
  "geometry": {"coordinates":[-72.11035099999999,41.366365],"type":"Point"}
}