{
  "type": "Feature",
  "properties": {
    "iso:country":"US",
    "sg:address":"254 Main St",
    "sg:city":"Danbury",
    "sg:classifiers":[
        {
            "category":"Government",
            "subcategory":"Office",
            "type":"Public Place"
        }
    ],
    "sg:phone":"+1 203 797 4569",
    "sg:postcode":"06810",
    "sg:province":"CT",
    "sg:tags":[
        "city",
        "resource",
        "human"
    ],
    "wof:name":"Danbury Welfare Dept",
    "wof:placetype":"venue"
},
  "geometry": {"coordinates":[-73.452512,41.394505],"type":"Point"}
}