{
  "type": "Feature",
  "properties": {
    "addr:full":"35 Sargent Dr Bethany CT 06524",
    "addr:housenumber":"35",
    "addr:postcode":"06524",
    "addr:street":"Sargent Dr Bethany Ct",
    "iso:country":"US",
    "sg:address":"35 Sargent Dr",
    "sg:city":"Bethany",
    "sg:classifiers":[
        {
            "category":"Manufacturing",
            "subcategory":"Electronics",
            "type":"Manufacturing & Wholesale Goods"
        }
    ],
    "sg:phone":"+1 203 393 9301",
    "sg:postcode":"06524",
    "sg:province":"CT",
    "sg:tags":[
        "equipment",
        "electronic",
        "supply"
    ],
    "wof:name":"Afcon Products Inc",
    "wof:placetype":"venue"
},
  "geometry": {"coordinates":[-72.989996,41.436574],"type":"Point"}
}