{
  "type": "Feature",
  "properties": {
    "iso:country":"US",
    "sg:address":"1566 Park Ave",
    "sg:city":"Bridgeport",
    "sg:classifiers":[
        {
            "category":"Professional",
            "subcategory":"Lawyer & Legal Services",
            "type":"Services"
        }
    ],
    "sg:phone":"+1 203 336 1861",
    "sg:postcode":"06604",
    "sg:province":"CT",
    "sg:tags":[
        "attorney"
    ],
    "wof:name":"Lawrence V Parnoff",
    "wof:placetype":"venue"
},
  "geometry": {"coordinates":[-73.20563199999999,41.182108],"type":"Point"}
}