{
  "type": "Feature",
  "properties": {
    "addr:full":"140 Derby Ave New Haven CT 06511",
    "addr:housenumber":"140",
    "addr:postcode":"06511",
    "addr:street":"Derby Ave",
    "iso:country":"US",
    "sg:address":"140 Derby Ave",
    "sg:city":"New Haven",
    "sg:classifiers":[
        {
            "category":"Organizations",
            "subcategory":"Religious Organization",
            "type":"Services"
        }
    ],
    "sg:phone":"+1 203 777 5652",
    "sg:postcode":"06511",
    "sg:province":"CT",
    "sg:tags":[
        "church"
    ],
    "wof:name":"Christ Power & Deliverance Chr",
    "wof:placetype":"venue"
},
  "geometry": {"coordinates":[-72.95044300000001,41.310574],"type":"Point"}
}