{
  "type": "Feature",
  "properties": {
    "addr:full":"6 Colt Hwy Farmington CT 06032",
    "addr:housenumber":"6",
    "addr:postcode":"06032",
    "addr:street":"Colt Hwy",
    "iso:country":"US",
    "sg:address":"6 Colt Hwy",
    "sg:city":"Farmington",
    "sg:classifiers":[
        {
            "category":"Bakery",
            "type":"Food & Drink"
        },
        {
            "category":"Coffee & Tea",
            "type":"Food & Drink"
        },
        {
            "category":"Bagels",
            "type":"Food & Drink"
        },
        {
            "category":"Donuts",
            "type":"Food & Drink"
        }
    ],
    "sg:menulink":"http://www.allmenus.com/ct/farmington/129860-dunkin-donuts/menu/",
    "sg:phone":"+1 860 674 1595",
    "sg:postcode":"06032",
    "sg:province":"CT",
    "sg:tags":[
        "american",
        "diner",
        "pastry"
    ],
    "wof:name":"Dunkin' Donuts",
    "wof:placetype":"venue"
},
  "geometry": {"coordinates":[-72.846588,41.70527],"type":"Point"}
}