{
  "type": "Feature",
  "properties": {
    "iso:country":"US",
    "sg:address":"3045 Main St",
    "sg:city":"Stratford",
    "sg:classifiers":[
        {
            "category":"Social Services",
            "type":"Services"
        }
    ],
    "sg:phone":"+1 203 375 5844",
    "sg:postcode":"06614",
    "sg:province":"CT",
    "sg:tags":[
        "organization",
        "welfare"
    ],
    "wof:name":"YMCA",
    "wof:placetype":"venue"
},
  "geometry": {"coordinates":[-73.13130700000001,41.201228],"type":"Point"}
}