{
  "type": "Feature",
  "properties": {
    "iso:country":"US",
    "sg:address":"34 Dale Rd",
    "sg:city":"Avon",
    "sg:classifiers":[
        {
            "category":"Community Center",
            "type":"Public Place"
        }
    ],
    "sg:phone":"+1 800 639 0456",
    "sg:postcode":"06001",
    "sg:province":"CT",
    "sg:tags":[
        "medical"
    ],
    "sg:website":"www.localstdtesting.com/15",
    "wof:name":"Avon Local HIV/STD Testing",
    "wof:placetype":"venue"
},
  "geometry": {"coordinates":[-72.864036,41.813624],"type":"Point"}
}