{
  "type": "Feature",
  "properties": {
    "iso:country":"US",
    "sg:address":"14 Railroad Ave",
    "sg:city":"Madison",
    "sg:classifiers":[
        {
            "category":"Building & Trades",
            "subcategory":"Plumbing",
            "type":"Services"
        }
    ],
    "sg:phone":"+1 203 245 2541",
    "sg:postcode":"06443",
    "sg:province":"CT",
    "sg:tags":[
        "tank",
        "septic"
    ],
    "wof:name":"Henry Cooney Co Sanitation Svc",
    "wof:placetype":"venue"
},
  "geometry": {"coordinates":[-72.592173,41.28359],"type":"Point"}
}