{
  "type": "Feature",
  "properties": {
    "iso:country":"US",
    "sg:address":"354 Saw Mill Rd",
    "sg:city":"West Haven",
    "sg:classifiers":[
        {
            "category":"Restaurant",
            "type":"Food & Drink"
        }
    ],
    "sg:menulink":"http://www.allmenus.com/ct/west-haven/257162-american-steak-house/menu/",
    "sg:phone":"+1 203 937 7818",
    "sg:postcode":"06516",
    "sg:province":"CT",
    "sg:tags":[
        "seafood",
        "steakhouse",
        "american"
    ],
    "wof:name":"American Steak House",
    "wof:placetype":"venue"
},
  "geometry": {"coordinates":[-72.972487,41.271822],"type":"Point"}
}