{
  "type": "Feature",
  "properties": {
    "addr:full":"144 Craigemore Cir Avon CT 06001",
    "addr:housenumber":"144",
    "addr:postcode":"06001",
    "addr:street":"Craigemore Cir Avon Ct",
    "iso:country":"US",
    "sg:address":"144 Craigemore Cir",
    "sg:city":"Avon",
    "sg:classifiers":[
        {
            "category":"Shopping",
            "subcategory":"Computers & Home Electronics",
            "type":"Retail Goods"
        }
    ],
    "sg:phone":"+1 860 673 9691",
    "sg:postcode":"06001",
    "sg:province":"CT",
    "wof:name":"Advanced Computer LLC",
    "wof:placetype":"venue"
},
  "geometry": {"coordinates":[-72.880472,41.80703],"type":"Point"}
}