{
  "type": "Feature",
  "properties": {
    "iso:country":"US",
    "sg:address":"128 Dwight St",
    "sg:city":"New Haven",
    "sg:classifiers":[
        {
            "category":"Retail",
            "subcategory":"Funeral Services",
            "type":"Services"
        }
    ],
    "sg:phone":"+1 203 865 5100",
    "sg:postcode":"06511",
    "sg:province":"CT",
    "sg:tags":[
        "director"
    ],
    "wof:name":"Council Curvin K Funeral Home",
    "wof:placetype":"venue"
},
  "geometry": {"coordinates":[-72.937579,41.308817],"type":"Point"}
}