{
  "type": "Feature",
  "properties": {
    "addr:full":"27 Marne St Hamden CT 06514",
    "addr:housenumber":"27",
    "addr:postcode":"06514",
    "addr:street":"Marne St",
    "iso:country":"US",
    "sg:address":"27 Marne St",
    "sg:city":"Hamden",
    "sg:classifiers":[
        {
            "category":"Manufacturing",
            "subcategory":"Electronics",
            "type":"Manufacturing & Wholesale Goods"
        }
    ],
    "sg:phone":"+1 203 288 5605",
    "sg:postcode":"06514",
    "sg:province":"CT",
    "sg:tags":[
        "equipment",
        "electronic",
        "supply"
    ],
    "wof:name":"Carlton Industries Corp",
    "wof:placetype":"venue"
},
  "geometry": {"coordinates":[-72.928425,41.353563],"type":"Point"}
}