{
  "type": "Feature",
  "properties": {
    "addr:full":"170 Center Hill Rd Pleasant Valley CT 06063",
    "addr:housenumber":"170",
    "addr:postcode":"06063",
    "addr:street":"Center Hill Rd Pleasant Valley Ct",
    "iso:country":"US",
    "sg:address":"170 Center Hill Rd",
    "sg:city":"Pleasant Valley",
    "sg:classifiers":[
        {
            "category":"Building & Trades",
            "subcategory":"Construction",
            "type":"Services"
        }
    ],
    "sg:phone":"+1 860 379 9079",
    "sg:postcode":"06063",
    "sg:province":"CT",
    "sg:tags":[
        "house"
    ],
    "wof:name":"Althen Builders",
    "wof:placetype":"venue"
},
  "geometry": {"coordinates":[-72.97044099999999,41.93684],"type":"Point"}
}