{
  "type": "Feature",
  "properties": {
    "addr:full":"10 Mill St East Haven CT 06512",
    "addr:housenumber":"10",
    "addr:postcode":"06512",
    "addr:street":"Mill St;Haven",
    "iso:country":"US",
    "sg:address":"10 Mill St",
    "sg:city":"East Haven",
    "sg:classifiers":[
        {
            "category":"Autos & Motor Vehicles",
            "subcategory":"Automobile Sales",
            "type":"Retail Goods"
        }
    ],
    "sg:phone":"+1 203 467 6645",
    "sg:postcode":"06512",
    "sg:province":"CT",
    "wof:name":"10 Mill Street Assoc LLC",
    "wof:placetype":"venue"
},
  "geometry": {"coordinates":[-72.84948799999999,41.314536],"type":"Point"}
}