{
  "type": "Feature",
  "properties": {
    "iso:country":"US",
    "sg:address":"95 Cody Cir",
    "sg:city":"South Windsor",
    "sg:classifiers":[
        {
            "category":"Manufacturing",
            "subcategory":"Printing",
            "type":"Manufacturing & Wholesale Goods"
        }
    ],
    "sg:phone":"+1 860 291 0798",
    "sg:postcode":"06074",
    "sg:province":"CT",
    "sg:tags":[
        "lithographic",
        "commercial"
    ],
    "wof:name":"Springfield Print Paper P",
    "wof:placetype":"venue"
},
  "geometry": {"coordinates":[-72.59184399999999,41.825445],"type":"Point"}
}