{
  "type": "Feature",
  "properties": {
    "addr:full":"79 Swanson Ave Stratford CT 06614",
    "addr:housenumber":"79",
    "addr:postcode":"06614",
    "addr:street":"Swanson Ave",
    "iso:country":"US",
    "sg:address":"79 Swanson Ave",
    "sg:city":"Stratford",
    "sg:classifiers":[
        {
            "category":"Building & Trades",
            "subcategory":"Construction",
            "type":"Services"
        }
    ],
    "sg:phone":"+1 203 377 0705",
    "sg:postcode":"06614",
    "sg:province":"CT",
    "sg:tags":[
        "contractor"
    ],
    "wof:name":"ADR Builders",
    "wof:placetype":"venue"
},
  "geometry": {"coordinates":[-73.152069,41.19995],"type":"Point"}
}