{
  "type": "Feature",
  "properties": {
    "iso:country":"US",
    "sg:address":"123 Huntington St",
    "sg:city":"New Haven",
    "sg:classifiers":[
        {
            "category":"Building & Trades",
            "subcategory":"Construction",
            "type":"Services"
        }
    ],
    "sg:phone":"+1 203 772 2611",
    "sg:postcode":"06511",
    "sg:province":"CT",
    "wof:name":"Salce Contracting Assoc",
    "wof:placetype":"venue"
},
  "geometry": {"coordinates":[-72.920299,41.33055],"type":"Point"}
}