{
  "type": "Feature",
  "properties": {
    "iso:country":"US",
    "sg:address":"775 Main St",
    "sg:city":"Stratford",
    "sg:classifiers":[
        {
            "category":"Health Services",
            "subcategory":"Optometrist",
            "type":"Services"
        }
    ],
    "sg:phone":"+1 203 377 2020",
    "sg:postcode":"06615",
    "sg:province":"CT",
    "sg:tags":[
        "eye",
        "wear"
    ],
    "wof:name":"Family Vision Center",
    "wof:placetype":"venue"
},
  "geometry": {"coordinates":[-73.12841899999999,41.172739],"type":"Point"}
}