{
  "type": "Feature",
  "properties": {
    "addr:full":"28 Gorman Pl East Hartford CT 06108",
    "addr:housenumber":"28",
    "addr:postcode":"06108",
    "addr:street":"Gorman Pl East Hartford Ct",
    "iso:country":"US",
    "sg:address":"28 Gorman Pl",
    "sg:city":"East Hartford",
    "sg:classifiers":[
        {
            "category":"Social Services",
            "type":"Services"
        }
    ],
    "sg:phone":"+1   ",
    "sg:postcode":"06108",
    "sg:province":"CT",
    "wof:name":"Gorman Place",
    "wof:placetype":"venue"
},
  "geometry": {"coordinates":[-72.597172,41.792415],"type":"Point"}
}