{
  "type": "Feature",
  "properties": {
    "iso:country":"US",
    "sg:address":"51 Brookfield Ave",
    "sg:city":"Bridgeport",
    "sg:classifiers":[
        {
            "category":"Manufacturing",
            "subcategory":"Metals",
            "type":"Manufacturing & Wholesale Goods"
        }
    ],
    "sg:phone":"+1 203 333 3191",
    "sg:postcode":"06610",
    "sg:province":"CT",
    "sg:tags":[
        "wire"
    ],
    "wof:name":"Bridgeport Insulated Wire Co",
    "wof:placetype":"venue"
},
  "geometry": {"coordinates":[-73.156206,41.187962],"type":"Point"}
}