{
  "type": "Feature",
  "properties": {
    "iso:country":"US",
    "sg:address":"39 Larkin St",
    "sg:city":"Stamford",
    "sg:classifiers":[
        {
            "category":"Retail",
            "subcategory":"Repair Shop",
            "type":"Services"
        }
    ],
    "sg:phone":"+1   ",
    "sg:postcode":"06907",
    "sg:province":"CT",
    "wof:name":"Sears Service Center 7484",
    "wof:placetype":"venue"
},
  "geometry": {"coordinates":[-73.51863400000001,41.078163],"type":"Point"}
}