{
  "type": "Feature",
  "properties": {
    "addr:full":"1088 Main St East Hartford CT 06108",
    "addr:housenumber":"1088",
    "addr:postcode":"06108",
    "addr:street":"Main St",
    "iso:country":"US",
    "sg:address":"1088 Main St",
    "sg:city":"East Hartford",
    "sg:classifiers":[
        {
            "category":"Restaurant",
            "type":"Food & Drink"
        }
    ],
    "sg:menulink":"http://www.allmenus.com/ct/east-hartford/124010-quiznos-sub/menu/",
    "sg:phone":"+1 860 291 8325",
    "sg:postcode":"06108",
    "sg:province":"CT",
    "sg:tags":[
        "wrap",
        "american",
        "sandwich"
    ],
    "wof:name":"Quiznos Sub",
    "wof:placetype":"venue"
},
  "geometry": {"coordinates":[-72.641587,41.772649],"type":"Point"}
}