{
  "type": "Feature",
  "properties": {
    "iso:country":"US",
    "sg:address":"106 Stamford Ave",
    "sg:city":"Stamford",
    "sg:classifiers":[
        {
            "category":"Professional",
            "subcategory":"Lawyer & Legal Services",
            "type":"Services"
        }
    ],
    "sg:phone":"+1 203 977 7044",
    "sg:postcode":"06902",
    "sg:province":"CT",
    "sg:tags":[
        "attorney"
    ],
    "wof:name":"Christopher Hynes",
    "wof:placetype":"venue"
},
  "geometry": {"coordinates":[-73.526507,41.027869],"type":"Point"}
}