{
  "type": "Feature",
  "properties": {
    "addr:full":"48 Rosinoff Pl Bridgeport CT 06606",
    "addr:housenumber":"48",
    "addr:postcode":"06606",
    "addr:street":"Rosinoff Pl",
    "iso:country":"US",
    "sg:address":"48 Rosinoff Pl",
    "sg:city":"Bridgeport",
    "sg:classifiers":[
        {
            "category":"Building & Trades",
            "subcategory":"Construction",
            "type":"Services"
        }
    ],
    "sg:phone":"+1 203 331 1222",
    "sg:postcode":"06606",
    "sg:province":"CT",
    "sg:tags":[
        "masonry",
        "contractor",
        "general"
    ],
    "wof:name":"Delmar Construction Inc",
    "wof:placetype":"venue"
},
  "geometry": {"coordinates":[-73.20352099999999,41.191985],"type":"Point"}
}