{
  "type": "Feature",
  "properties": {
    "addr:full":"191 Highland Ave Cheshire CT 06410",
    "addr:housenumber":"191",
    "addr:postcode":"06410",
    "addr:street":"Highland Ave",
    "iso:country":"US",
    "sg:address":"191 Highland Ave",
    "sg:city":"Cheshire",
    "sg:classifiers":[
        {
            "category":"Shopping",
            "subcategory":"Gifts & Souvenirs",
            "type":"Retail Goods"
        }
    ],
    "sg:phone":"+1 203 272 1444",
    "sg:postcode":"06410",
    "sg:province":"CT",
    "sg:tags":[
        "shop"
    ],
    "wof:name":"Holly's Hallmark Shop",
    "wof:placetype":"venue"
},
  "geometry": {"coordinates":[-72.900651,41.50449],"type":"Point"}
}