{
  "type": "Feature",
  "properties": {
    "iso:country":"US",
    "sg:address":"21 Rice Ter",
    "sg:city":"Branford",
    "sg:classifiers":[
        {
            "category":"Building & Trades",
            "subcategory":"Construction",
            "type":"Services"
        }
    ],
    "sg:phone":"+1 203 481 5632",
    "sg:postcode":"06405",
    "sg:province":"CT",
    "sg:tags":[
        "general",
        "contractor"
    ],
    "wof:name":"Merit Associates Inc",
    "wof:placetype":"venue"
},
  "geometry": {"coordinates":[-72.80752,41.280132],"type":"Point"}
}