{
  "type": "Feature",
  "properties": {
    "iso:country":"US",
    "sg:address":"733 E Main St",
    "sg:city":"Torrington",
    "sg:classifiers":[
        {
            "category":"Health Services",
            "subcategory":"Health Practitioner",
            "type":"Services"
        },
        {
            "category":"Health Services",
            "subcategory":"Chiropractor",
            "type":"Services"
        }
    ],
    "sg:phone":"+1 860 626 1167",
    "sg:postcode":"06790",
    "sg:province":"CT",
    "sg:tags":[
        "acupuncture",
        "chiropractic"
    ],
    "sg:website":"http://www.acuhealingcenter.com",
    "wof:name":"Acupunture Healing Arts Center",
    "wof:placetype":"venue"
},
  "geometry": {"coordinates":[-73.105707,41.810187],"type":"Point"}
}