{
  "type": "Feature",
  "properties": {
    "addr:full":"1601 Great Hill Rd Guilford CT 06437",
    "addr:housenumber":"1601",
    "addr:postcode":"06437",
    "addr:street":"Great Hill Rd",
    "iso:country":"US",
    "sg:address":"1601 Great Hill Rd",
    "sg:city":"Guilford",
    "sg:classifiers":[
        {
            "category":"Wholesale",
            "subcategory":"Electrical",
            "type":"Manufacturing & Wholesale Goods"
        }
    ],
    "sg:phone":"+1 203 457 1818",
    "sg:postcode":"06437",
    "sg:province":"CT",
    "sg:tags":[
        "telephone"
    ],
    "wof:name":"Donald L Hurteau Assoc",
    "wof:placetype":"venue"
},
  "geometry": {"coordinates":[-72.707793,41.403493],"type":"Point"}
}