{
  "type": "Feature",
  "properties": {
    "iso:country":"US",
    "sg:address":"50 Shady Crest Rd",
    "sg:city":"Meriden",
    "sg:classifiers":[
        {
            "category":"Organizations",
            "subcategory":"Religious Organization",
            "type":"Services"
        }
    ],
    "sg:phone":"+1   ",
    "sg:postcode":"06450",
    "sg:province":"CT",
    "wof:name":"Timothy Lowe Rev",
    "wof:placetype":"venue"
},
  "geometry": {"coordinates":[-72.77389100000001,41.556789],"type":"Point"}
}