{
  "type": "Feature",
  "properties": {
    "iso:country":"US",
    "sg:address":"105 Martin Ter",
    "sg:city":"Glastonbury",
    "sg:classifiers":[
        {
            "category":"Professional",
            "subcategory":"Management & Consulting",
            "type":"Services"
        }
    ],
    "sg:phone":"+1   ",
    "sg:postcode":"06033",
    "sg:province":"CT",
    "sg:tags":[
        "business"
    ],
    "wof:name":"Slangen & Associates LLC",
    "wof:placetype":"venue"
},
  "geometry": {"coordinates":[-72.528531,41.700353],"type":"Point"}
}