{
  "type": "Feature",
  "properties": {
    "iso:country":"US",
    "sg:address":"40 Abbott Ave",
    "sg:city":"Danbury",
    "sg:classifiers":[
        {
            "category":"Farming",
            "subcategory":"Farm",
            "type":"Manufacturing & Wholesale Goods"
        }
    ],
    "sg:phone":"+1 203 744 7695",
    "sg:postcode":"06810",
    "sg:province":"CT",
    "sg:tags":[
        "crop",
        "general"
    ],
    "wof:name":"Lounsbury Construction",
    "wof:placetype":"venue"
},
  "geometry": {"coordinates":[-73.472742,41.39427],"type":"Point"}
}