{
  "type": "Feature",
  "properties": {
    "iso:country":"US",
    "sg:address":"53 Greenfield Dr",
    "sg:city":"Weston",
    "sg:classifiers":[
        {
            "category":"Professional",
            "subcategory":"Management & Consulting",
            "type":"Services"
        }
    ],
    "sg:phone":"+1   ",
    "sg:postcode":"06883",
    "sg:province":"CT",
    "wof:name":"English Consulting Advisors",
    "wof:placetype":"venue"
},
  "geometry": {"coordinates":[-73.366052,41.225064],"type":"Point"}
}