{
  "type": "Feature",
  "properties": {
    "iso:country":"US",
    "sg:address":"54 Kane St",
    "sg:city":"West Hartford",
    "sg:classifiers":[
        {
            "category":"Restaurant",
            "type":"Food & Drink"
        }
    ],
    "sg:menulink":"http://www.allmenus.com/ct/west-hartford/253561-prospect-pizza/menu/",
    "sg:phone":"+1 860 523 9948",
    "sg:postcode":"06119",
    "sg:province":"CT",
    "sg:tags":[
        "pasta",
        "calzones",
        "american",
        "wing",
        "pizza"
    ],
    "wof:name":"Prospect Pizza",
    "wof:placetype":"venue"
},
  "geometry": {"coordinates":[-72.71710299999999,41.751544],"type":"Point"}
}