{
  "type": "Feature",
  "properties": {
    "iso:country":"US",
    "sg:address":"6 Muller Ave",
    "sg:city":"Norwalk",
    "sg:classifiers":[
        {
            "category":"Shopping",
            "subcategory":"Computers & Home Electronics",
            "type":"Retail Goods"
        }
    ],
    "sg:phone":"+1 203 847 0180",
    "sg:postcode":"06851",
    "sg:province":"CT",
    "sg:tags":[
        "software"
    ],
    "wof:name":"Component Innovations LLC",
    "wof:placetype":"venue"
},
  "geometry": {"coordinates":[-73.428027,41.132681],"type":"Point"}
}