{
  "type": "Feature",
  "properties": {
    "addr:full":"50 Lake Rd Woodbury CT 06798",
    "addr:housenumber":"50",
    "addr:postcode":"06798",
    "addr:street":"Lake Rd",
    "iso:country":"US",
    "sg:address":"50 Lake Rd",
    "sg:city":"Woodbury",
    "sg:classifiers":[
        {
            "category":"Arts & Performance",
            "subcategory":"Theater",
            "type":"Entertainment"
        }
    ],
    "sg:phone":"+1   ",
    "sg:postcode":"06798",
    "sg:province":"CT",
    "sg:tags":[
        "group"
    ],
    "wof:name":"Julies Piano Workshop",
    "wof:placetype":"venue"
},
  "geometry": {"coordinates":[-73.15136699999999,41.573107],"type":"Point"}
}