{
  "type": "Feature",
  "properties": {
    "iso:country":"US",
    "sg:address":"6 Edgewood Ct",
    "sg:city":"Simsbury",
    "sg:classifiers":[
        {
            "category":"Professional",
            "subcategory":"Business Services",
            "type":"Services"
        }
    ],
    "sg:phone":"+1   ",
    "sg:postcode":"06070",
    "sg:province":"CT",
    "wof:name":"Rustle Meadow Associates LLC",
    "wof:placetype":"venue"
},
  "geometry": {"coordinates":[-72.82422699999999,41.86727],"type":"Point"}
}