{
  "type": "Feature",
  "properties": {
    "iso:country":"US",
    "sg:address":"115 Barlow Mountain Rd",
    "sg:city":"Ridgefield",
    "sg:classifiers":[
        {
            "category":"Education",
            "subcategory":"School",
            "type":"Public Place"
        }
    ],
    "sg:phone":"+1 203 894 7700",
    "sg:postcode":"06877",
    "sg:province":"CT",
    "wof:name":"Barlow Mountain Elementary Sch",
    "wof:placetype":"venue"
},
  "geometry": {"coordinates":[-73.509574,41.319982],"type":"Point"}
}