{
  "type": "Feature",
  "properties": {
    "addr:full":"94 Berkeley Dr Vernon Rockville CT 06066",
    "addr:housenumber":"94",
    "addr:postcode":"06066",
    "addr:street":"Berkeley Dr",
    "iso:country":"US",
    "sg:address":"94 Berkeley Dr",
    "sg:city":"Vernon Rockville",
    "sg:classifiers":[
        {
            "category":"Professional",
            "type":"Services"
        }
    ],
    "sg:phone":"+1 860 649 0668",
    "sg:postcode":"06066",
    "sg:province":"CT",
    "wof:name":"John Lajeunesse",
    "wof:placetype":"venue"
},
  "geometry": {"coordinates":[-72.471858,41.8045],"type":"Point"}
}