{
  "type": "Feature",
  "properties": {
    "addr:full":"43 Hood Ter West Haven CT 06516",
    "addr:housenumber":"43",
    "addr:postcode":"06516",
    "addr:street":"Hood Ter West Haven Ct",
    "iso:country":"US",
    "sg:address":"43 Hood Ter",
    "sg:city":"West Haven",
    "sg:classifiers":[
        {
            "category":"Retail",
            "subcategory":"Auto Repair",
            "type":"Services"
        }
    ],
    "sg:phone":"+1   ",
    "sg:postcode":"06516",
    "sg:province":"CT",
    "sg:tags":[
        "automotive"
    ],
    "wof:name":"Chucks Garage",
    "wof:placetype":"venue"
},
  "geometry": {"coordinates":[-72.962822,41.270671],"type":"Point"}
}