{
  "type": "Feature",
  "properties": {
    "iso:country":"US",
    "sg:address":"10 Wright St",
    "sg:city":"Westport",
    "sg:classifiers":[
        {
            "category":"Professional",
            "subcategory":"Business Services",
            "type":"Services"
        }
    ],
    "sg:phone":"+1   ",
    "sg:postcode":"06880",
    "sg:province":"CT",
    "sg:tags":[
        "conference",
        "speaker"
    ],
    "wof:name":"Motivators Conference Speaker",
    "wof:placetype":"venue"
},
  "geometry": {"coordinates":[-73.367069,41.14059],"type":"Point"}
}