{
  "type": "Feature",
  "properties": {
    "iso:country":"US",
    "sg:address":"31 Bradford Dr",
    "sg:city":"Cheshire",
    "sg:classifiers":[
        {
            "category":"Professional",
            "subcategory":"Computer Services",
            "type":"Services"
        }
    ],
    "sg:phone":"+1   ",
    "sg:postcode":"06410",
    "sg:province":"CT",
    "sg:tags":[
        "consulting",
        "related"
    ],
    "wof:name":"Techies On Call",
    "wof:placetype":"venue"
},
  "geometry": {"coordinates":[-72.912378,41.458824],"type":"Point"}
}