{
  "type": "Feature",
  "properties": {
    "addr:full":"6 Linden Pl Branford CT 06405",
    "addr:housenumber":"6",
    "addr:postcode":"06405",
    "addr:street":"Linden Pl;Ct",
    "iso:country":"US",
    "sg:address":"6 Linden Pl",
    "sg:city":"Branford",
    "sg:classifiers":[
        {
            "category":"Professional",
            "subcategory":"Accounting & Tax Preparation",
            "type":"Services"
        }
    ],
    "sg:phone":"+1   ",
    "sg:postcode":"06405",
    "sg:province":"CT",
    "wof:name":"Demchak Thomas J CPA",
    "wof:placetype":"venue"
},
  "geometry": {"coordinates":[-72.80917100000001,41.253987],"type":"Point"}
}