{
  "type": "Feature",
  "properties": {
    "addr:full":"2210 Thomaston Ave Waterbury CT 06704",
    "addr:housenumber":"2210",
    "addr:postcode":"06704",
    "addr:street":"Thomaston Ave",
    "iso:country":"US",
    "sg:address":"2210 Thomaston Ave",
    "sg:city":"Waterbury",
    "sg:classifiers":[
        {
            "category":"Government",
            "subcategory":"Office",
            "type":"Public Place"
        }
    ],
    "sg:phone":"+1 203 596 4290",
    "sg:postcode":"06704",
    "sg:province":"CT",
    "sg:tags":[
        "state",
        "program",
        "licensing",
        "motor",
        "vehicle",
        "inspection"
    ],
    "wof:name":"Motor Vehicles Conn Dept",
    "wof:placetype":"venue"
},
  "geometry": {"coordinates":[-73.05817500000001,41.603441],"type":"Point"}
}