{
  "type": "Feature",
  "properties": {
    "addr:full":"1 Highwood Simsbury CT 06070",
    "addr:housenumber":"1",
    "addr:postcode":"06070",
    "addr:street":"Highwood Simsbury Ct",
    "iso:country":"US",
    "sg:address":"1 Highwood",
    "sg:city":"Simsbury",
    "sg:classifiers":[
        {
            "category":"Food & Beverages",
            "subcategory":"Liquor & Beverages",
            "type":"Retail Goods"
        }
    ],
    "sg:phone":"+1 860 651 4682",
    "sg:postcode":"06070",
    "sg:province":"CT",
    "sg:tags":[
        "alcoholic"
    ],
    "wof:name":"Shore Discount Liquors 2",
    "wof:placetype":"venue"
},
  "geometry": {"coordinates":[-72.788742,41.848271],"type":"Point"}
}