{
  "type": "Feature",
  "properties": {
    "addr:full":"102 Clinton Ave Stamford CT 06901",
    "addr:housenumber":"102",
    "addr:postcode":"06901",
    "addr:street":"Clinton Ave",
    "iso:country":"US",
    "sg:address":"102 Clinton Ave",
    "sg:city":"Stamford",
    "sg:classifiers":[
        {
            "category":"Social Services",
            "type":"Services"
        }
    ],
    "sg:phone":"+1 203 348 4880",
    "sg:postcode":"06901",
    "sg:province":"CT",
    "sg:tags":[
        "organization",
        "welfare"
    ],
    "wof:name":"Domus Foundation Inc",
    "wof:placetype":"venue"
},
  "geometry": {"coordinates":[-73.544652,41.049451],"type":"Point"}
}