{
  "type": "Feature",
  "properties": {
    "addr:full":"1267 Fairfield Ave Bridgeport CT 06605",
    "addr:housenumber":"1267",
    "addr:postcode":"06605",
    "addr:street":"Fairfield Ave",
    "iso:country":"US",
    "sg:address":"1267 Fairfield Ave",
    "sg:city":"Bridgeport",
    "sg:classifiers":[
        {
            "category":"Retail",
            "subcategory":"Car Wash",
            "type":"Services"
        }
    ],
    "sg:phone":"+1 203 331 9521",
    "sg:postcode":"06605",
    "sg:province":"CT",
    "sg:tags":[
        "polishing",
        "washing"
    ],
    "wof:name":"Pro Shine Auto Detailing",
    "wof:placetype":"venue"
},
  "geometry": {"coordinates":[-73.207554,41.173838],"type":"Point"}
}