{
  "type": "Feature",
  "properties": {
    "addr:full":"521 Main St Cromwell CT 06416",
    "addr:housenumber":"521",
    "addr:postcode":"06416",
    "addr:street":"Main St;Ct",
    "iso:country":"US",
    "sg:address":"521 Main St",
    "sg:city":"Cromwell",
    "sg:classifiers":[
        {
            "category":"Shopping",
            "subcategory":"Used Merchandise",
            "type":"Retail Goods"
        }
    ],
    "sg:phone":"+1 860 635 5957",
    "sg:postcode":"06416",
    "sg:province":"CT",
    "wof:name":"Broyles Barn Antiques",
    "wof:placetype":"venue"
},
  "geometry": {"coordinates":[-72.653284,41.615837],"type":"Point"}
}