{
  "type": "Feature",
  "properties": {
    "iso:country":"US",
    "sg:address":"839 Main St",
    "sg:city":"Torrington",
    "sg:classifiers":[
        {
            "category":"Building & Trades",
            "subcategory":"Construction",
            "type":"Services"
        }
    ],
    "sg:phone":"+1 860 482 3691",
    "sg:postcode":"06790",
    "sg:province":"CT",
    "sg:tags":[
        "contractor"
    ],
    "wof:name":"Hahn Building Collc",
    "wof:placetype":"venue"
},
  "geometry": {"coordinates":[-73.121956,41.818151],"type":"Point"}
}