{
  "type": "Feature",
  "properties": {
    "iso:country":"US",
    "sg:address":"919 Enfield St",
    "sg:city":"Enfield",
    "sg:classifiers":[
        {
            "category":"Retail",
            "subcategory":"Laundry & Dry Cleaning",
            "type":"Services"
        }
    ],
    "sg:phone":"+1   ",
    "sg:postcode":"06082",
    "sg:province":"CT",
    "sg:tags":[
        "power"
    ],
    "wof:name":"Julies Laundromat & Cleaners",
    "wof:placetype":"venue"
},
  "geometry": {"coordinates":[-72.594368,41.996855],"type":"Point"}
}