{
  "type": "Feature",
  "properties": {
    "addr:full":"24 Lyon Rd Burlington CT 06013",
    "addr:housenumber":"24",
    "addr:postcode":"06013",
    "addr:street":"Lyon Rd",
    "iso:country":"US",
    "sg:address":"24 Lyon Rd",
    "sg:city":"Burlington",
    "sg:classifiers":[
        {
            "category":"Education",
            "subcategory":"School",
            "type":"Public Place"
        }
    ],
    "sg:phone":"+1   ",
    "sg:postcode":"06013",
    "sg:province":"CT",
    "sg:tags":[
        "district"
    ],
    "wof:name":"Regional School District No 10",
    "wof:placetype":"venue"
},
  "geometry": {"coordinates":[-72.986222,41.786917],"type":"Point"}
}