{
  "type": "Feature",
  "properties": {
    "iso:country":"US",
    "sg:address":"20 E Main St",
    "sg:city":"Waterbury",
    "sg:classifiers":[
        {
            "category":"Health Services",
            "subcategory":"Optometrist",
            "type":"Services"
        }
    ],
    "sg:phone":"+1 203 754 7752",
    "sg:postcode":"06702",
    "sg:province":"CT",
    "wof:name":"Louis R Neumann OD",
    "wof:placetype":"venue"
},
  "geometry": {"coordinates":[-73.03993800000001,41.555576],"type":"Point"}
}