{
  "type": "Feature",
  "properties": {
    "iso:country":"US",
    "sg:address":"476 N Colony St",
    "sg:city":"Wallingford",
    "sg:classifiers":[
        {
            "category":"Building & Trades",
            "subcategory":"Construction",
            "type":"Services"
        }
    ],
    "sg:phone":"+1 203 284 1880",
    "sg:postcode":"06492",
    "sg:province":"CT",
    "sg:tags":[
        "coping",
        "plastering",
        "tiling",
        "pool",
        "swimming"
    ],
    "sg:website":"www.nedive.com",
    "wof:name":"New England Diving-Connecticut",
    "wof:placetype":"venue"
},
  "geometry": {"coordinates":[-72.818978,41.465672],"type":"Point"}
}