{
  "type": "Feature",
  "properties": {
    "iso:country":"US",
    "sg:address":"431 New State Rd",
    "sg:city":"Manchester",
    "sg:classifiers":[
        {
            "category":"Professional",
            "subcategory":"Management & Consulting",
            "type":"Services"
        }
    ],
    "sg:phone":"+1   ",
    "sg:postcode":"06042",
    "sg:province":"CT",
    "wof:name":"North Star Construction & Dev",
    "wof:placetype":"venue"
},
  "geometry": {"coordinates":[-72.553836,41.789696],"type":"Point"}
}