{
  "type": "Feature",
  "properties": {
    "iso:country":"US",
    "sg:address":"155 Brewster St",
    "sg:city":"Bridgeport",
    "sg:classifiers":[
        {
            "category":"Real Estate",
            "subcategory":"Real Estate Operator",
            "type":"Services"
        }
    ],
    "sg:phone":"+1 203 333 3304",
    "sg:postcode":"06605",
    "sg:province":"CT",
    "sg:tags":[
        "condominium"
    ],
    "wof:name":"Fayerweather Towers",
    "wof:placetype":"venue"
},
  "geometry": {"coordinates":[-73.220754,41.154063],"type":"Point"}
}