{
  "type": "Feature",
  "properties": {
    "iso:country":"US",
    "sg:address":"127 W Main St",
    "sg:city":"Stafford Springs",
    "sg:classifiers":[
        {
            "category":"Retail",
            "subcategory":"Car Wash",
            "type":"Services"
        }
    ],
    "sg:phone":"+1   ",
    "sg:postcode":"06076",
    "sg:province":"CT",
    "sg:tags":[
        "carwash"
    ],
    "wof:name":"Dicksons Car Wash",
    "wof:placetype":"venue"
},
  "geometry": {"coordinates":[-72.315395,41.962346],"type":"Point"}
}