{
  "type": "Feature",
  "properties": {
    "iso:country":"US",
    "sg:address":"400 Captain Neville Dr",
    "sg:city":"Waterbury",
    "sg:classifiers":[
        {
            "category":"Professional",
            "subcategory":"Management & Consulting",
            "type":"Services"
        }
    ],
    "sg:phone":"+1   ",
    "sg:postcode":"06705",
    "sg:province":"CT",
    "sg:tags":[
        "business"
    ],
    "wof:name":"Mason Lite",
    "wof:placetype":"venue"
},
  "geometry": {"coordinates":[-72.976133,41.53894],"type":"Point"}
}