{
  "type": "Feature",
  "properties": {
    "addr:full":"48 Bassetts Bridge Rd Mansfield Center CT 06250",
    "addr:housenumber":"48",
    "addr:postcode":"06250",
    "addr:street":"Bassetts Bridge Rd",
    "iso:country":"US",
    "sg:address":"48 Bassetts Bridge Rd",
    "sg:city":"Mansfield Center",
    "sg:classifiers":[
        {
            "category":"Social Services",
            "subcategory":"Child Care",
            "type":"Services"
        }
    ],
    "sg:phone":"+1 860 423 1070",
    "sg:postcode":"06250",
    "sg:province":"CT",
    "sg:tags":[
        "day"
    ],
    "wof:name":"Montessori-Mt Hope School",
    "wof:placetype":"venue"
},
  "geometry": {"coordinates":[-72.17559799999999,41.7649],"type":"Point"}
}