{
  "type": "Feature",
  "properties": {
    "iso:country":"US",
    "sg:address":"1458 Durham Rd",
    "sg:city":"Wallingford",
    "sg:classifiers":[
        {
            "category":"Retail",
            "subcategory":"Repair Shop",
            "type":"Services"
        }
    ],
    "sg:phone":"+1   ",
    "sg:postcode":"06492",
    "sg:province":"CT",
    "wof:name":"TLC Press Repair Sales",
    "wof:placetype":"venue"
},
  "geometry": {"coordinates":[-72.749814,41.471018],"type":"Point"}
}