{
  "type": "Feature",
  "properties": {
    "addr:full":"27 Naek Rd Vernon Rockville CT 06066",
    "addr:housenumber":"27",
    "addr:postcode":"06066",
    "addr:street":"Naek Rd",
    "iso:country":"US",
    "sg:address":"27 Naek Rd",
    "sg:city":"Vernon Rockville",
    "sg:classifiers":[
        {
            "category":"Professional",
            "subcategory":"Engineering",
            "type":"Services"
        }
    ],
    "sg:phone":"+1   ",
    "sg:postcode":"06066",
    "sg:province":"CT",
    "sg:tags":[
        "consulting",
        "business"
    ],
    "wof:name":"Gza",
    "wof:placetype":"venue"
},
  "geometry": {"coordinates":[-72.493679,41.838485],"type":"Point"}
}