{
  "type": "Feature",
  "properties": {
    "addr:full":"279 Candlewood Lake Rd Brookfield CT 06804",
    "addr:housenumber":"279",
    "addr:postcode":"06804",
    "addr:street":"Candlewood Lake Rd",
    "iso:country":"US",
    "sg:address":"279 Candlewood Lake Rd",
    "sg:city":"Brookfield",
    "sg:classifiers":[
        {
            "category":"Professional",
            "subcategory":"Business Services",
            "type":"Services"
        }
    ],
    "sg:phone":"+1   ",
    "sg:postcode":"06804",
    "sg:province":"CT",
    "wof:name":"Barry M Klein Assoc",
    "wof:placetype":"venue"
},
  "geometry": {"coordinates":[-73.42880599999999,41.469493],"type":"Point"}
}