{
  "type": "Feature",
  "properties": {
    "iso:country":"US",
    "sg:address":"4 Main St",
    "sg:city":"Monroe",
    "sg:classifiers":[
        {
            "category":"Wholesale",
            "subcategory":"Plants",
            "type":"Manufacturing & Wholesale Goods"
        }
    ],
    "sg:phone":"+1 203 445 0841",
    "sg:postcode":"06468",
    "sg:province":"CT",
    "sg:tags":[
        "nursery",
        "tree"
    ],
    "wof:name":"L & L Evergreen Inc",
    "wof:placetype":"venue"
},
  "geometry": {"coordinates":[-73.24634500000001,41.296278],"type":"Point"}
}