{
  "type": "Feature",
  "properties": {
    "addr:full":"1856 Storrs Rd Storrs Mansfield CT 06268",
    "addr:housenumber":"1856",
    "addr:postcode":"06268",
    "addr:street":"Storrs Rd;Mansfield Ct",
    "iso:country":"US",
    "sg:address":"1856 Storrs Rd",
    "sg:city":"Storrs Mansfield",
    "sg:classifiers":[
        {
            "category":"Retail",
            "subcategory":"Auto Repair",
            "type":"Services"
        }
    ],
    "sg:phone":"+1   ",
    "sg:postcode":"06268",
    "sg:province":"CT",
    "sg:tags":[
        "general"
    ],
    "wof:name":"Tonys Garage Ltd",
    "wof:placetype":"venue"
},
  "geometry": {"coordinates":[-72.290932,41.830214],"type":"Point"}
}