{
  "type": "Feature",
  "properties": {
    "addr:full":"151 Post Rd E Westport CT 06880",
    "addr:housenumber":"151",
    "addr:postcode":"06880",
    "addr:street":"Post Rd E Westport Ct",
    "iso:country":"US",
    "sg:address":"151 Post Rd E",
    "sg:city":"Westport",
    "sg:classifiers":[
        {
            "category":"Organizations",
            "subcategory":"Membership Organization",
            "type":"Services"
        }
    ],
    "sg:phone":"+1 203 227 5047",
    "sg:postcode":"06880",
    "sg:province":"CT",
    "sg:tags":[
        "science",
        "reading",
        "christian",
        "rooms"
    ],
    "wof:name":"First Church-Christ Scientist",
    "wof:placetype":"venue"
},
  "geometry": {"coordinates":[-73.360606,41.141517],"type":"Point"}
}