{
  "type": "Feature",
  "properties": {
    "addr:full":"114 W Main St New Britain CT 06052",
    "addr:housenumber":"114",
    "addr:postcode":"06052",
    "addr:street":"W Main St",
    "iso:country":"US",
    "sg:address":"114 W Main St",
    "sg:city":"New Britain",
    "sg:classifiers":[
        {
            "category":"Health Services",
            "subcategory":"Doctor",
            "type":"Services"
        }
    ],
    "sg:phone":"+1   ",
    "sg:postcode":"06052",
    "sg:province":"CT",
    "sg:tags":[
        "medical"
    ],
    "wof:name":"Joseph Aferzon Md LLC",
    "wof:placetype":"venue"
},
  "geometry": {"coordinates":[-72.784768,41.667164],"type":"Point"}
}