{
  "type": "Feature",
  "properties": {
    "iso:country":"US",
    "sg:address":"425 Montauk Ave",
    "sg:city":"New London",
    "sg:classifiers":[
        {
            "category":"Health Services",
            "subcategory":"Doctor",
            "type":"Services"
        }
    ],
    "sg:phone":"+1   ",
    "sg:postcode":"06320",
    "sg:province":"CT",
    "sg:tags":[
        "medical"
    ],
    "wof:name":"Dermatlgic Assoc Stheastern CT",
    "wof:placetype":"venue"
},
  "geometry": {"coordinates":[-72.10193200000001,41.335076],"type":"Point"}
}