{
  "type": "Feature",
  "properties": {
    "addr:full":"32 W Avon Rd Avon CT 06001",
    "addr:housenumber":"32",
    "addr:postcode":"06001",
    "addr:street":"W Avon Rd",
    "iso:country":"US",
    "sg:address":"32 W Avon Rd",
    "sg:city":"Avon",
    "sg:classifiers":[
        {
            "category":"Restaurant",
            "type":"Food & Drink"
        }
    ],
    "sg:phone":"+1 860 675 1999",
    "sg:postcode":"06001",
    "sg:province":"CT",
    "sg:tags":[
        "mexican"
    ],
    "sg:website":"www.puertovallartausa.com",
    "wof:name":"Puerto Vallerta",
    "wof:placetype":"venue"
},
  "geometry": {"coordinates":[-72.86708400000001,41.814983],"type":"Point"}
}