{
  "type": "Feature",
  "properties": {
    "iso:country":"US",
    "sg:address":"72 Sedgewick Ave",
    "sg:city":"Darien",
    "sg:classifiers":[
        {
            "category":"Professional",
            "type":"Services"
        }
    ],
    "sg:phone":"+1 203 662 0381",
    "sg:postcode":"06820",
    "sg:province":"CT",
    "wof:name":"Robin Minton",
    "wof:placetype":"venue"
},
  "geometry": {"coordinates":[-73.47405999999999,41.080181],"type":"Point"}
}