{
  "type": "Feature",
  "properties": {
    "addr:full":"316 Maple Ave Cheshire CT 06410",
    "addr:housenumber":"316",
    "addr:postcode":"06410",
    "addr:street":"Maple Ave",
    "iso:country":"US",
    "sg:address":"316 Maple Ave",
    "sg:city":"Cheshire",
    "sg:classifiers":[
        {
            "category":"Building & Trades",
            "subcategory":"Construction",
            "type":"Services"
        }
    ],
    "sg:phone":"+1 203 271 0601",
    "sg:postcode":"06410",
    "sg:province":"CT",
    "sg:tags":[
        "masonry"
    ],
    "wof:name":"Antonios Masonry",
    "wof:placetype":"venue"
},
  "geometry": {"coordinates":[-72.902986,41.507419],"type":"Point"}
}