{
  "type": "Feature",
  "properties": {
    "addr:full":"38 Warehouse Point Rd Wallingford CT 06492",
    "addr:housenumber":"38",
    "addr:postcode":"06492",
    "addr:street":"Warehouse Point Rd",
    "iso:country":"US",
    "sg:address":"38 Warehouse Point Rd",
    "sg:city":"Wallingford",
    "sg:classifiers":[
        {
            "category":"Wholesale",
            "subcategory":"Auto Parts",
            "type":"Manufacturing & Wholesale Goods"
        }
    ],
    "sg:phone":"+1 203 269 5505",
    "sg:postcode":"06492",
    "sg:province":"CT",
    "wof:name":"Old Car Whse LLC Ltd Lblty Co",
    "wof:placetype":"venue"
},
  "geometry": {"coordinates":[-72.81401700000001,41.48895],"type":"Point"}
}