{
  "type": "Feature",
  "properties": {
    "addr:full":"827 Bridgeport Ave Milford CT 06460",
    "addr:housenumber":"827",
    "addr:postcode":"06460",
    "addr:street":"Bridgeport Ave",
    "iso:country":"US",
    "sg:address":"827 Bridgeport Ave",
    "sg:city":"Milford",
    "sg:classifiers":[
        {
            "category":"Sports & Exercise",
            "subcategory":"Gym",
            "type":"Entertainment"
        }
    ],
    "sg:phone":"+1   ",
    "sg:postcode":"06460",
    "sg:province":"CT",
    "sg:tags":[
        "club",
        "health"
    ],
    "wof:name":"Planet Fitness",
    "wof:placetype":"venue"
},
  "geometry": {"coordinates":[-73.07826300000001,41.212614],"type":"Point"}
}