{
  "type": "Feature",
  "properties": {
    "addr:full":"48 Prospect St Ansonia CT 06401",
    "addr:housenumber":"48",
    "addr:postcode":"06401",
    "addr:street":"Prospect St",
    "iso:country":"US",
    "sg:address":"48 Prospect St",
    "sg:city":"Ansonia",
    "sg:classifiers":[
        {
            "category":"Building & Trades",
            "subcategory":"Landscaping Services",
            "type":"Services"
        }
    ],
    "sg:phone":"+1 203 734 2751",
    "sg:postcode":"06401",
    "sg:province":"CT",
    "sg:tags":[
        "landscape"
    ],
    "wof:name":"Valley Landscaping",
    "wof:placetype":"venue"
},
  "geometry": {"coordinates":[-73.075868,41.347357],"type":"Point"}
}