{
  "type": "Feature",
  "properties": {
    "iso:country":"US",
    "sg:address":"5 Brookside Dr",
    "sg:city":"Wallingford",
    "sg:classifiers":[
        {
            "category":"Travel",
            "subcategory":"Travel Agent",
            "type":"Entertainment"
        }
    ],
    "sg:phone":"+1 203 284 6060",
    "sg:postcode":"06492",
    "sg:province":"CT",
    "sg:tags":[
        "agency"
    ],
    "wof:name":"Travel Sciences",
    "wof:placetype":"venue"
},
  "geometry": {"coordinates":[-72.798945,41.490568],"type":"Point"}
}