{
  "type": "Feature",
  "properties": {
    "iso:country":"US",
    "sg:address":"1455 State St",
    "sg:city":"New Haven",
    "sg:classifiers":[
        {
            "category":"Building & Trades",
            "subcategory":"Construction",
            "type":"Services"
        }
    ],
    "sg:phone":"+1 203 624 1345",
    "sg:postcode":"06511",
    "sg:province":"CT",
    "sg:tags":[
        "spray",
        "painting",
        "finishing"
    ],
    "wof:name":"Suraci Metal Finishing",
    "wof:placetype":"venue"
},
  "geometry": {"coordinates":[-72.89712299999999,41.321051],"type":"Point"}
}