{
  "type": "Feature",
  "properties": {
    "addr:full":"668 Arch St New Britain CT 06051",
    "addr:housenumber":"668",
    "addr:postcode":"06051",
    "addr:street":"Arch St",
    "iso:country":"US",
    "sg:address":"668 Arch St",
    "sg:city":"New Britain",
    "sg:classifiers":[
        {
            "category":"Professional",
            "subcategory":"Business Services",
            "type":"Services"
        }
    ],
    "sg:phone":"+1   ",
    "sg:postcode":"06051",
    "sg:province":"CT",
    "wof:name":"Little Amsterdam",
    "wof:placetype":"venue"
},
  "geometry": {"coordinates":[-72.785583,41.655105],"type":"Point"}
}