{
  "type": "Feature",
  "properties": {
    "addr:full":"65 N Sound Beach Ave Riverside CT 06878",
    "addr:housenumber":"65",
    "addr:postcode":"06878",
    "addr:street":"N Sound Beach Ave Riverside Ct",
    "iso:country":"US",
    "sg:address":"65 N Sound Beach Ave",
    "sg:city":"Riverside",
    "sg:classifiers":[
        {
            "category":"Home & Garden",
            "subcategory":"Garden Supply",
            "type":"Retail Goods"
        }
    ],
    "sg:phone":"+1 203 637 3134",
    "sg:postcode":"06878",
    "sg:province":"CT",
    "sg:tags":[
        "landscaping",
        "equipment"
    ],
    "wof:name":"Greenskeeper",
    "wof:placetype":"venue"
},
  "geometry": {"coordinates":[-73.579764,41.046237],"type":"Point"}
}