{
  "type": "Feature",
  "properties": {
    "iso:country":"US",
    "sg:address":"61 Seaview Ave",
    "sg:city":"Stamford",
    "sg:classifiers":[
        {
            "category":"Professional",
            "subcategory":"Business Services",
            "type":"Services"
        }
    ],
    "sg:phone":"+1 203 973 0905",
    "sg:postcode":"06902",
    "sg:province":"CT",
    "sg:tags":[
        "event"
    ],
    "wof:name":"Events R Us",
    "wof:placetype":"venue"
},
  "geometry": {"coordinates":[-73.522679,41.040948],"type":"Point"}
}