{
  "type": "Feature",
  "properties": {
    "addr:full":"56 Catoona Ln Stamford CT 06902",
    "addr:housenumber":"56",
    "addr:postcode":"06902",
    "addr:street":"Catoona Ln",
    "iso:country":"US",
    "sg:address":"56 Catoona Ln",
    "sg:city":"Stamford",
    "sg:classifiers":[
        {
            "category":"Retail",
            "subcategory":"Auto Rental",
            "type":"Services"
        },
        {
            "category":"Airport",
            "type":"Transportation"
        }
    ],
    "sg:phone":"+1 203 356 1107",
    "sg:postcode":"06902",
    "sg:province":"CT",
    "sg:tags":[
        "limousine"
    ],
    "sg:website":"http://www.bestcarriagelimousine.com",
    "wof:name":"Best Carriage Limo",
    "wof:placetype":"venue"
},
  "geometry": {"coordinates":[-73.564307,41.051685],"type":"Point"}
}