{
  "type": "Feature",
  "properties": {
    "addr:full":"5 Pheasant Hill Ln Old Saybrook CT 06475",
    "addr:housenumber":"5",
    "addr:postcode":"06475",
    "addr:street":"Pheasant Hill Ln;Saybrook Ct",
    "iso:country":"US",
    "sg:address":"5 Pheasant Hill Ln",
    "sg:city":"Old Saybrook",
    "sg:classifiers":[
        {
            "category":"Professional",
            "subcategory":"Management & Consulting",
            "type":"Services"
        }
    ],
    "sg:phone":"+1   ",
    "sg:postcode":"06475",
    "sg:province":"CT",
    "wof:name":"Joseph C Andress Consulting",
    "wof:placetype":"venue"
},
  "geometry": {"coordinates":[-72.400899,41.313936],"type":"Point"}
}