{
  "type": "Feature",
  "properties": {
    "addr:full":"38 Grove St Ridgefield CT 06877",
    "addr:housenumber":"38",
    "addr:postcode":"06877",
    "addr:street":"Grove St",
    "iso:country":"US",
    "sg:address":"38 Grove St",
    "sg:city":"Ridgefield",
    "sg:classifiers":[
        {
            "category":"Personal",
            "type":"Services"
        }
    ],
    "sg:phone":"+1 203 431 8278",
    "sg:postcode":"06877",
    "sg:province":"CT",
    "sg:tags":[
        "clinic",
        "therapist",
        "therapy",
        "massage",
        "physical"
    ],
    "wof:name":"Massage Thru Heart & Hands",
    "wof:placetype":"venue"
},
  "geometry": {"coordinates":[-73.494377,41.286709],"type":"Point"}
}