{
  "type": "Feature",
  "properties": {
    "iso:country":"US",
    "sg:address":"345 Albany Tpke",
    "sg:city":"Canton",
    "sg:classifiers":[
        {
            "category":"Shopping",
            "subcategory":"Bicycles & Sporting Goods",
            "type":"Retail Goods"
        }
    ],
    "sg:phone":"+1 860 693 9220",
    "sg:postcode":"06019",
    "sg:province":"CT",
    "wof:name":"Fitness & Martial Arts Sup LLC",
    "wof:placetype":"venue"
},
  "geometry": {"coordinates":[-72.91421200000001,41.832027],"type":"Point"}
}