{
  "type": "Feature",
  "properties": {
    "iso:country":"US",
    "sg:address":"911 E Main St",
    "sg:city":"Torrington",
    "sg:classifiers":[
        {
            "category":"Retail",
            "subcategory":"Self-service Laundry",
            "type":"Services"
        }
    ],
    "sg:phone":"+1   ",
    "sg:postcode":"06790",
    "sg:province":"CT",
    "sg:tags":[
        "dry",
        "cleaning"
    ],
    "wof:name":"Globe Cleaners",
    "wof:placetype":"venue"
},
  "geometry": {"coordinates":[-73.100362,41.812788],"type":"Point"}
}