{
  "type": "Feature",
  "properties": {
    "addr:full":"148 Cross Hill Rd Monroe CT 06468",
    "addr:housenumber":"148",
    "addr:postcode":"06468",
    "addr:street":"Cross Hill Rd",
    "iso:country":"US",
    "sg:address":"148 Cross Hill Rd",
    "sg:city":"Monroe",
    "sg:classifiers":[
        {
            "category":"Shopping",
            "type":"Retail Goods"
        }
    ],
    "sg:phone":"+1 203 445 8363",
    "sg:postcode":"06468",
    "sg:province":"CT",
    "sg:tags":[
        "equipment",
        "telephone",
        "supply"
    ],
    "wof:name":"American Business Comms",
    "wof:placetype":"venue"
},
  "geometry": {"coordinates":[-73.210069,41.315629],"type":"Point"}
}