{
  "type": "Feature",
  "properties": {
    "iso:country":"US",
    "sg:address":"1231 E Main St",
    "sg:city":"Meriden",
    "sg:classifiers":[
        {
            "category":"Home & Garden",
            "subcategory":"Furniture",
            "type":"Retail Goods"
        }
    ],
    "sg:phone":"+1 203 634 6944",
    "sg:postcode":"06450",
    "sg:province":"CT",
    "wof:name":"Galleria Furniture Store LLC",
    "wof:placetype":"venue"
},
  "geometry": {"coordinates":[-72.762575,41.525348],"type":"Point"}
}