{
  "type": "Feature",
  "properties": {
    "addr:full":"281 Tresser Blvd Stamford CT 06901",
    "addr:housenumber":"281",
    "addr:postcode":"06901",
    "addr:street":"Tresser Blvd",
    "iso:country":"US",
    "sg:address":"281 Tresser Blvd",
    "sg:city":"Stamford",
    "sg:classifiers":[
        {
            "category":"Professional",
            "subcategory":"Employment Agencies",
            "type":"Services"
        }
    ],
    "sg:phone":"+1 203 978 2760",
    "sg:postcode":"06901",
    "sg:province":"CT",
    "sg:tags":[
        "consultant",
        "search",
        "executive"
    ],
    "wof:name":"Nuvsion Heidrick & Struggles",
    "wof:placetype":"venue"
},
  "geometry": {"coordinates":[-73.53377399999999,41.05243],"type":"Point"}
}