{
  "type": "Feature",
  "properties": {
    "iso:country":"US",
    "sg:address":"9 Mann Memorial Dr",
    "sg:city":"Cromwell",
    "sg:classifiers":[
        {
            "category":"Education",
            "subcategory":"School",
            "type":"Public Place"
        }
    ],
    "sg:phone":"+1 860 632 4830",
    "sg:postcode":"06416",
    "sg:province":"CT",
    "sg:tags":[
        "executive"
    ],
    "wof:name":"Cromwell Board of Education",
    "wof:placetype":"venue"
},
  "geometry": {"coordinates":[-72.655721,41.627093],"type":"Point"}
}