{
  "type": "Feature",
  "properties": {
    "iso:country":"US",
    "sg:address":"61 Main St",
    "sg:city":"Centerbrook",
    "sg:classifiers":[
        {
            "category":"Health Services",
            "subcategory":"Dentist",
            "type":"Services"
        }
    ],
    "sg:phone":"+1 860 767 3003",
    "sg:postcode":"06409",
    "sg:province":"CT",
    "sg:tags":[
        "orthodontist"
    ],
    "wof:name":"Carlough Burzin & Gagnon",
    "wof:placetype":"venue"
},
  "geometry": {"coordinates":[-72.4058,41.351601],"type":"Point"}
}