{
  "type": "Feature",
  "properties": {
    "addr:full":"235 Westport Ave Norwalk CT 06851",
    "addr:housenumber":"235",
    "addr:postcode":"06851",
    "addr:street":"Westport Ave",
    "iso:country":"US",
    "sg:address":"235 Westport Ave",
    "sg:city":"Norwalk",
    "sg:classifiers":[
        {
            "category":"Home & Garden",
            "subcategory":"Home Furnishings",
            "type":"Retail Goods"
        }
    ],
    "sg:phone":"+1 203 847 1572",
    "sg:postcode":"06851",
    "sg:province":"CT",
    "sg:tags":[
        "bathroom",
        "accessory",
        "fixtures",
        "cabinet"
    ],
    "sg:website":"http://kohler.com",
    "wof:name":"Pacific Baths",
    "wof:placetype":"venue"
},
  "geometry": {"coordinates":[-73.397728,41.124358],"type":"Point"}
}