{
  "type": "Feature",
  "properties": {
    "addr:full":"109 Greenwich Ave Greenwich CT 06830",
    "addr:housenumber":"109",
    "addr:postcode":"06830",
    "addr:street":"Greenwich Ave",
    "iso:country":"US",
    "sg:address":"109 Greenwich Ave",
    "sg:city":"Greenwich",
    "sg:classifiers":[
        {
            "category":"Building & Trades",
            "subcategory":"Pest Control",
            "type":"Services"
        }
    ],
    "sg:phone":"+1 203 869 5440",
    "sg:postcode":"06830",
    "sg:province":"CT",
    "wof:name":"Bliss Exterminator Company",
    "wof:placetype":"venue"
},
  "geometry": {"coordinates":[-73.626407,41.029602],"type":"Point"}
}