{
  "type": "Feature",
  "properties": {
    "addr:full":"66 Garden St New Britain CT 06052",
    "addr:housenumber":"66",
    "addr:postcode":"06052",
    "addr:street":"Garden St",
    "iso:country":"US",
    "sg:address":"66 Garden St",
    "sg:city":"New Britain",
    "sg:classifiers":[
        {
            "category":"Retail",
            "subcategory":"Repair Shop",
            "type":"Services"
        }
    ],
    "sg:phone":"+1   ",
    "sg:postcode":"06052",
    "sg:province":"CT",
    "wof:name":"New England Taxidermy",
    "wof:placetype":"venue"
},
  "geometry": {"coordinates":[-72.800743,41.662472],"type":"Point"}
}