{
  "type": "Feature",
  "properties": {
    "iso:country":"US",
    "sg:address":"66 N Main St",
    "sg:city":"Suffield",
    "sg:classifiers":[
        {
            "category":"Professional",
            "subcategory":"Detective & Security Services",
            "type":"Services"
        }
    ],
    "sg:phone":"+1 860 668 5728",
    "sg:postcode":"06078",
    "sg:province":"CT",
    "sg:tags":[
        "private",
        "investigator"
    ],
    "wof:name":"Impact Investigations",
    "wof:placetype":"venue"
},
  "geometry": {"coordinates":[-72.650786,41.982833],"type":"Point"}
}