{
  "type": "Feature",
  "properties": {
    "iso:country":"US",
    "sg:address":"355 James St",
    "sg:city":"New Haven",
    "sg:classifiers":[
        {
            "category":"Wholesale",
            "subcategory":"Machinery & Supplies",
            "type":"Manufacturing & Wholesale Goods"
        }
    ],
    "sg:phone":"+1 203 562 6657",
    "sg:postcode":"06513",
    "sg:province":"CT",
    "sg:tags":[
        "equipment",
        "masonry"
    ],
    "wof:name":"New Haven Masonry & Bldg Sup",
    "wof:placetype":"venue"
},
  "geometry": {"coordinates":[-72.903882,41.313796],"type":"Point"}
}