{
  "type": "Feature",
  "properties": {
    "addr:full":"70 Bruce Park Ave Greenwich CT 06830",
    "addr:housenumber":"70",
    "addr:postcode":"06830",
    "addr:street":"Bruce Park Ave",
    "iso:country":"US",
    "sg:address":"70 Bruce Park Ave",
    "sg:city":"Greenwich",
    "sg:classifiers":[
        {
            "category":"Professional",
            "subcategory":"Business Services",
            "type":"Services"
        }
    ],
    "sg:phone":"+1 203 861 7820",
    "sg:postcode":"06830",
    "sg:province":"CT",
    "sg:tags":[
        "import",
        "importer",
        "representative"
    ],
    "sg:website":"http://www.provipoland.com",
    "wof:name":"Provi International Co",
    "wof:placetype":"venue"
},
  "geometry": {"coordinates":[-73.621224,41.022493],"type":"Point"}
}