{
  "type": "Feature",
  "properties": {
    "addr:full":"13 Park St Norwalk CT 06851",
    "addr:housenumber":"13",
    "addr:postcode":"06851",
    "addr:street":"Park St",
    "iso:country":"US",
    "sg:address":"13 Park St",
    "sg:city":"Norwalk",
    "sg:classifiers":[
        {
            "category":"Health Services",
            "subcategory":"Doctor",
            "type":"Services"
        }
    ],
    "sg:phone":"+1   ",
    "sg:postcode":"06851",
    "sg:province":"CT",
    "sg:tags":[
        "medical"
    ],
    "wof:name":"Steven W Lutzker MD",
    "wof:placetype":"venue"
},
  "geometry": {"coordinates":[-73.408686,41.121382],"type":"Point"}
}