{
  "type": "Feature",
  "properties": {
    "iso:country":"US",
    "sg:address":"210 Prospect St",
    "sg:city":"New Haven",
    "sg:classifiers":[
        {
            "category":"Health Services",
            "subcategory":"Health Practitioner",
            "type":"Services"
        }
    ],
    "sg:phone":"+1   ",
    "sg:postcode":"06511",
    "sg:province":"CT",
    "wof:name":"Derose Sandra M PHD",
    "wof:placetype":"venue"
},
  "geometry": {"coordinates":[-72.923295,41.320252],"type":"Point"}
}