{
  "type": "Feature",
  "properties": {
    "iso:country":"US",
    "sg:address":"243 W Spring St",
    "sg:city":"West Haven",
    "sg:classifiers":[
        {
            "category":"Social Services",
            "type":"Services"
        }
    ],
    "sg:phone":"+1   ",
    "sg:postcode":"06516",
    "sg:province":"CT",
    "wof:name":"Mothers Love Day Care",
    "wof:placetype":"venue"
},
  "geometry": {"coordinates":[-72.964842,41.279889],"type":"Point"}
}