{
  "type": "Feature",
  "properties": {
    "iso:country":"US",
    "sg:address":"105 Clark Dr",
    "sg:city":"East Berlin",
    "sg:classifiers":[
        {
            "category":"Building & Trades",
            "subcategory":"Pest Control",
            "type":"Services"
        }
    ],
    "sg:phone":"+1   ",
    "sg:postcode":"06023",
    "sg:province":"CT",
    "wof:name":"Orkin Pest Control 993",
    "wof:placetype":"venue"
},
  "geometry": {"coordinates":[-72.71866199999999,41.62272],"type":"Point"}
}