{
  "type": "Feature",
  "properties": {
    "addr:full":"551 Post Rd Darien CT 06820",
    "addr:housenumber":"551",
    "addr:postcode":"06820",
    "addr:street":"Post Rd",
    "iso:country":"US",
    "sg:address":"551 Post Rd",
    "sg:city":"Darien",
    "sg:classifiers":[
        {
            "category":"Personal",
            "subcategory":"Beauty Salon",
            "type":"Services"
        }
    ],
    "sg:phone":"+1 203 656 0438",
    "sg:postcode":"06820",
    "sg:province":"CT",
    "sg:tags":[
        "treatment",
        "skin"
    ],
    "wof:name":"Elysian Fields Facial Spa",
    "wof:placetype":"venue"
},
  "geometry": {"coordinates":[-73.46490900000001,41.082553],"type":"Point"}
}