{
  "type": "Feature",
  "properties": {
    "iso:country":"US",
    "sg:address":"34 Climax Rd",
    "sg:city":"Simsbury",
    "sg:classifiers":[
        {
            "category":"Wholesale",
            "subcategory":"Non-durable Goods",
            "type":"Manufacturing & Wholesale Goods"
        }
    ],
    "sg:phone":"+1 860 658 9611",
    "sg:postcode":"06070",
    "sg:province":"CT",
    "wof:name":"Penelope Imports Llc",
    "wof:placetype":"venue"
},
  "geometry": {"coordinates":[-72.84961699999999,41.823435],"type":"Point"}
}