{
  "type": "Feature",
  "properties": {
    "iso:country":"US",
    "sg:address":"6 Clearview Dr",
    "sg:city":"Ridgefield",
    "sg:classifiers":[
        {
            "category":"Retail",
            "subcategory":"Auto Repair",
            "type":"Services"
        }
    ],
    "sg:phone":"+1 203 438 9671",
    "sg:postcode":"06877",
    "sg:province":"CT",
    "sg:tags":[
        "body",
        "automobile",
        "painting"
    ],
    "wof:name":"Body Tech",
    "wof:placetype":"venue"
},
  "geometry": {"coordinates":[-73.493514,41.340511],"type":"Point"}
}