{
  "type": "Feature",
  "properties": {
    "iso:country":"US",
    "sg:address":"819 Main St",
    "sg:city":"South Windsor",
    "sg:classifiers":[
        {
            "category":"Professional",
            "subcategory":"Management & Consulting",
            "type":"Services"
        }
    ],
    "sg:phone":"+1   ",
    "sg:postcode":"06074",
    "sg:province":"CT",
    "wof:name":"Gateway Financial Group",
    "wof:placetype":"venue"
},
  "geometry": {"coordinates":[-72.61802299999999,41.829053],"type":"Point"}
}