{
  "type": "Feature",
  "properties": {
    "addr:full":"105 Mill Plain Rd Danbury CT 06811",
    "addr:housenumber":"105",
    "addr:postcode":"06811",
    "addr:street":"Mill Plain Rd",
    "iso:country":"US",
    "sg:address":"105 Mill Plain Rd",
    "sg:city":"Danbury",
    "sg:classifiers":[
        {
            "category":"Banks & Credit Unions",
            "subcategory":"Bank",
            "type":"Services"
        }
    ],
    "sg:phone":"+1 203 748 6628",
    "sg:postcode":"06811",
    "sg:province":"CT",
    "sg:tags":[
        "national",
        "commercial"
    ],
    "wof:name":"Summit",
    "wof:placetype":"venue"
},
  "geometry": {"coordinates":[-73.520928,41.391915],"type":"Point"}
}