{
  "type": "Feature",
  "properties": {
    "addr:full":"12 Burnham Dr Hartford CT 06110",
    "addr:housenumber":"12",
    "addr:postcode":"06110",
    "addr:street":"Burnham Dr",
    "iso:country":"US",
    "sg:address":"12 Burnham Dr",
    "sg:city":"Hartford",
    "sg:classifiers":[
        {
            "category":"Building & Trades",
            "subcategory":"Construction",
            "type":"Services"
        }
    ],
    "sg:phone":"+1 860 561 1651",
    "sg:postcode":"06110",
    "sg:province":"CT",
    "sg:tags":[
        "hanging",
        "contractor",
        "carpentry"
    ],
    "wof:name":"Contract Painting Services LLC",
    "wof:placetype":"venue"
},
  "geometry": {"coordinates":[-72.755443,41.725188],"type":"Point"}
}