{
  "type": "Feature",
  "properties": {
    "addr:full":"33 Nausset Ave Danielson CT 06239",
    "addr:housenumber":"33",
    "addr:postcode":"06239",
    "addr:street":"Nausset Ave",
    "iso:country":"US",
    "sg:address":"33 Nausset Ave",
    "sg:city":"Danielson",
    "sg:classifiers":[
        {
            "category":"Professional",
            "type":"Services"
        }
    ],
    "sg:phone":"+1 860 774 8711",
    "sg:postcode":"06239",
    "sg:province":"CT",
    "wof:name":"Vinnie Thipavong",
    "wof:placetype":"venue"
},
  "geometry": {"coordinates":[-71.847379,41.808886],"type":"Point"}
}