{
  "type": "Feature",
  "properties": {
    "addr:full":"2 Sherman St Fairfield CT 06475",
    "addr:housenumber":"2",
    "addr:postcode":"06475",
    "addr:street":"Sherman St",
    "iso:country":"US",
    "sg:address":"2 Sherman St",
    "sg:city":"Fairfield",
    "sg:classifiers":[
        {
            "category":"Professional",
            "subcategory":"Lawyer & Legal Services",
            "type":"Services"
        }
    ],
    "sg:phone":"+1   ",
    "sg:postcode":"06475",
    "sg:province":"CT",
    "wof:name":"McGuinness Pter J The Law Offs",
    "wof:placetype":"venue"
},
  "geometry": {"coordinates":[-72.37604399999999,41.281983],"type":"Point"}
}