{
  "type": "Feature",
  "properties": {
    "iso:country":"US",
    "sg:address":"221 Brainard Rd",
    "sg:city":"Hartford",
    "sg:classifiers":[
        {
            "category":"Home & Garden",
            "subcategory":"Building Materials",
            "type":"Retail Goods"
        }
    ],
    "sg:phone":"+1 860 527 8434",
    "sg:postcode":"06114",
    "sg:province":"CT",
    "wof:name":"Husky Hardwood Flooring",
    "wof:placetype":"venue"
},
  "geometry": {"coordinates":[-72.659312,41.732402],"type":"Point"}
}