{
  "type": "Feature",
  "properties": {
    "iso:country":"US",
    "sg:address":"141 N Main St",
    "sg:city":"Branford",
    "sg:classifiers":[
        {
            "category":"Personal",
            "subcategory":"Beauty Salon",
            "type":"Services"
        }
    ],
    "sg:phone":"+1 203 481 1858",
    "sg:postcode":"06405",
    "sg:province":"CT",
    "sg:tags":[
        "shop"
    ],
    "wof:name":"Joseph Anthony Hair Nail Salon",
    "wof:placetype":"venue"
},
  "geometry": {"coordinates":[-72.816754,41.286396],"type":"Point"}
}