{
  "type": "Feature",
  "properties": {
    "iso:country":"US",
    "sg:address":"160 Mohegan Dr",
    "sg:city":"Hartford",
    "sg:classifiers":[
        {
            "category":"Organizations",
            "subcategory":"Religious Organization",
            "type":"Services"
        }
    ],
    "sg:phone":"+1   ",
    "sg:postcode":"06117",
    "sg:province":"CT",
    "sg:tags":[
        "elementary",
        "school"
    ],
    "wof:name":"Emanuel Synagogue",
    "wof:placetype":"venue"
},
  "geometry": {"coordinates":[-72.73568899999999,41.798351],"type":"Point"}
}