{
  "type": "Feature",
  "properties": {
    "addr:full":"22 Fennway Hartford CT 06119",
    "addr:housenumber":"22",
    "addr:postcode":"06119",
    "addr:street":"Fennway Hartford Ct",
    "iso:country":"US",
    "sg:address":"22 Fennway",
    "sg:city":"Hartford",
    "sg:classifiers":[
        {
            "category":"Health Services",
            "subcategory":"Nursing And Care Facility",
            "type":"Services"
        }
    ],
    "sg:phone":"+1   ",
    "sg:postcode":"06119",
    "sg:province":"CT",
    "sg:tags":[
        "home",
        "aged",
        "for"
    ],
    "wof:name":"Tracy Manor Inc",
    "wof:placetype":"venue"
},
  "geometry": {"coordinates":[-72.719296,41.763466],"type":"Point"}
}