{
  "type": "Feature",
  "properties": {
    "iso:country":"US",
    "sg:address":"1261 Meriden Rd",
    "sg:city":"Waterbury",
    "sg:classifiers":[
        {
            "category":"Wholesale",
            "subcategory":"Groceries",
            "type":"Manufacturing & Wholesale Goods"
        }
    ],
    "sg:phone":"+1 203 756 9866",
    "sg:postcode":"06705",
    "sg:province":"CT",
    "sg:tags":[
        "baker"
    ],
    "wof:name":"Bakery and Patisserie Beirut L",
    "wof:placetype":"venue"
},
  "geometry": {"coordinates":[-72.977824,41.553249],"type":"Point"}
}