{
  "type": "Feature",
  "properties": {
    "iso:country":"US",
    "sg:address":"314 Wilton Rd W",
    "sg:city":"Ridgefield",
    "sg:classifiers":[
        {
            "category":"Building & Trades",
            "subcategory":"Electrical",
            "type":"Services"
        }
    ],
    "sg:phone":"+1 203 431 9016",
    "sg:postcode":"06877",
    "sg:province":"CT",
    "sg:tags":[
        "electrical",
        "contractor"
    ],
    "wof:name":"Kendall Electric",
    "wof:placetype":"venue"
},
  "geometry": {"coordinates":[-73.494972,41.262418],"type":"Point"}
}