{
  "type": "Feature",
  "properties": {
    "addr:full":"360 Main St Hartford CT 06106",
    "addr:housenumber":"360",
    "addr:postcode":"06106",
    "addr:street":"Main St",
    "iso:country":"US",
    "sg:address":"360 Main St",
    "sg:city":"Hartford",
    "sg:classifiers":[
        {
            "category":"Real Estate",
            "subcategory":"Real Estate Operator",
            "type":"Services"
        }
    ],
    "sg:phone":"+1 860 278 3018",
    "sg:postcode":"06106",
    "sg:province":"CT",
    "sg:tags":[
        "building",
        "apartment"
    ],
    "wof:name":"Saint Christophers Apts",
    "wof:placetype":"venue"
},
  "geometry": {"coordinates":[-72.674758,41.760471],"type":"Point"}
}