{
  "type": "Feature",
  "properties": {
    "addr:full":"197 Scott Swamp Rd Farmington CT 06032",
    "addr:housenumber":"197",
    "addr:postcode":"06032",
    "addr:street":"Scott Swamp Rd",
    "iso:country":"US",
    "sg:address":"197 Scott Swamp Rd",
    "sg:city":"Farmington",
    "sg:classifiers":[
        {
            "category":"Insurance",
            "subcategory":"Life Insurance",
            "type":"Services"
        }
    ],
    "sg:phone":"+1 860 677 2600",
    "sg:postcode":"06032",
    "sg:province":"CT",
    "sg:tags":[
        "agency"
    ],
    "wof:name":"Guardian Life Insur Co of Amer",
    "wof:placetype":"venue"
},
  "geometry": {"coordinates":[-72.86758500000001,41.705045],"type":"Point"}
}