{
  "type": "Feature",
  "properties": {
    "iso:country":"US",
    "sg:address":"25 W Spring St",
    "sg:city":"West Haven",
    "sg:classifiers":[
        {
            "category":"Building & Trades",
            "subcategory":"Plumbing",
            "type":"Services"
        }
    ],
    "sg:phone":"+1 203 934 7984",
    "sg:postcode":"06516",
    "sg:province":"CT",
    "sg:tags":[
        "heating",
        "contractor"
    ],
    "wof:name":"Air Specialties Air Cond & Htg",
    "wof:placetype":"venue"
},
  "geometry": {"coordinates":[-72.958945,41.282318],"type":"Point"}
}