{
  "type": "Feature",
  "properties": {
    "iso:country":"US",
    "sg:address":"105 Harbor Dr",
    "sg:city":"Stamford",
    "sg:classifiers":[
        {
            "category":"Professional",
            "subcategory":"Management & Consulting",
            "type":"Services"
        }
    ],
    "sg:phone":"+1   ",
    "sg:postcode":"06902",
    "sg:province":"CT",
    "wof:name":"Andlinger Capital 31 LLC",
    "wof:placetype":"venue"
},
  "geometry": {"coordinates":[-73.52947899999999,41.039069],"type":"Point"}
}