{
  "type": "Feature",
  "properties": {
    "addr:full":"66 Nicholdale Rd Shelton CT 06484",
    "addr:housenumber":"66",
    "addr:postcode":"06484",
    "addr:street":"Nicholdale Rd",
    "iso:country":"US",
    "sg:address":"66 Nicholdale Rd",
    "sg:city":"Shelton",
    "sg:classifiers":[
        {
            "category":"Professional",
            "subcategory":"Advertising",
            "type":"Services"
        }
    ],
    "sg:phone":"+1   ",
    "sg:postcode":"06484",
    "sg:province":"CT",
    "sg:tags":[
        "agency",
        "reporting"
    ],
    "wof:name":"Marbud Communications",
    "wof:placetype":"venue"
},
  "geometry": {"coordinates":[-73.156865,41.335481],"type":"Point"}
}