{
  "type": "Feature",
  "properties": {
    "addr:full":"57 Greens Farms Rd Westport CT 06880",
    "addr:housenumber":"57",
    "addr:postcode":"06880",
    "addr:street":"Greens Farms Rd",
    "iso:country":"US",
    "sg:address":"57 Greens Farms Rd",
    "sg:city":"Westport",
    "sg:classifiers":[
        {
            "category":"Insurance",
            "subcategory":"Insurance Agent",
            "type":"Services"
        }
    ],
    "sg:phone":"+1 203 221 3300",
    "sg:postcode":"06880",
    "sg:province":"CT",
    "wof:name":"Metropolitan Care Group",
    "wof:placetype":"venue"
},
  "geometry": {"coordinates":[-73.345826,41.123561],"type":"Point"}
}