{
  "type": "Feature",
  "properties": {
    "addr:full":"2625 Park Ave Bridgeport CT 06604",
    "addr:housenumber":"2625",
    "addr:postcode":"06604",
    "addr:street":"Park Ave",
    "iso:country":"US",
    "sg:address":"2625 Park Ave",
    "sg:city":"Bridgeport",
    "sg:classifiers":[
        {
            "category":"Real Estate",
            "subcategory":"Real Estate Agent",
            "type":"Services"
        }
    ],
    "sg:phone":"+1 203 333 5835",
    "sg:postcode":"06604",
    "sg:province":"CT",
    "wof:name":"J J Garamella Real Estate",
    "wof:placetype":"venue"
},
  "geometry": {"coordinates":[-73.21574099999999,41.193857],"type":"Point"}
}