{
  "type": "Feature",
  "properties": {
    "addr:full":"105 Mill Rock Rd Hamden CT 06517",
    "addr:housenumber":"105",
    "addr:postcode":"06517",
    "addr:street":"Mill Rock Rd",
    "iso:country":"US",
    "sg:address":"105 Mill Rock Rd",
    "sg:city":"Hamden",
    "sg:classifiers":[
        {
            "category":"Health Services",
            "subcategory":"Doctor",
            "type":"Services"
        }
    ],
    "sg:phone":"+1 203 624 6996",
    "sg:postcode":"06517",
    "sg:province":"CT",
    "sg:tags":[
        "physician",
        "surgeon"
    ],
    "wof:name":"Stephen V Flagg MD",
    "wof:placetype":"venue"
},
  "geometry": {"coordinates":[-72.916443,41.337936],"type":"Point"}
}