{
  "type": "Feature",
  "properties": {
    "addr:full":"140 Albany Tpke Canton CT 06019",
    "addr:housenumber":"140",
    "addr:postcode":"06019",
    "addr:street":"Albany Tpke Canton Ct",
    "iso:country":"US",
    "sg:address":"140 Albany Tpke",
    "sg:city":"Canton",
    "sg:classifiers":[
        {
            "category":"Personal",
            "subcategory":"Massage",
            "type":"Services"
        },
        {
            "category":"Personal",
            "subcategory":"Nail Salon",
            "type":"Services"
        }
    ],
    "sg:phone":"+1 860 693 9205",
    "sg:postcode":"06019",
    "sg:province":"CT",
    "wof:name":"Shear Bliss",
    "wof:placetype":"venue"
},
  "geometry": {"coordinates":[-72.885803,41.8242],"type":"Point"}
}