{
  "type": "Feature",
  "properties": {
    "addr:full":"1481 Quinnipiac Ave New Haven CT 06513",
    "addr:housenumber":"1481",
    "addr:postcode":"06513",
    "addr:street":"Quinnipiac Ave",
    "iso:country":"US",
    "sg:address":"1481 Quinnipiac Ave",
    "sg:city":"New Haven",
    "sg:classifiers":[
        {
            "category":"Education",
            "subcategory":"School",
            "type":"Public Place"
        }
    ],
    "sg:phone":"+1 203 946 8623",
    "sg:postcode":"06513",
    "sg:province":"CT",
    "wof:name":"Bishop Woods School",
    "wof:placetype":"venue"
},
  "geometry": {"coordinates":[-72.870364,41.326516],"type":"Point"}
}