{
  "type": "Feature",
  "properties": {
    "iso:country":"US",
    "sg:address":"147 South Ave",
    "sg:city":"New Canaan",
    "sg:classifiers":[
        {
            "category":"Health Services",
            "subcategory":"Health Practitioner",
            "type":"Services"
        }
    ],
    "sg:phone":"+1 203 966 9445",
    "sg:postcode":"06840",
    "sg:province":"NY",
    "sg:tags":[
        "psychologist"
    ],
    "wof:name":"Denkin Associates",
    "wof:placetype":"venue"
},
  "geometry": {"coordinates":[-73.491547,41.141423],"type":"Point"}
}