{
  "type": "Feature",
  "properties": {
    "addr:full":"2 Enterprise Dr Shelton CT 06484",
    "addr:housenumber":"2",
    "addr:postcode":"06484",
    "addr:street":"Enterprise Dr",
    "iso:country":"US",
    "sg:address":"2 Enterprise Dr",
    "sg:city":"Shelton",
    "sg:classifiers":[
        {
            "category":"Professional",
            "type":"Services"
        }
    ],
    "sg:phone":"+1 203 929 4673",
    "sg:postcode":"06484",
    "sg:province":"CT",
    "sg:tags":[
        "establishment"
    ],
    "wof:name":"XCHB Inc",
    "wof:placetype":"venue"
},
  "geometry": {"coordinates":[-73.123756,41.277186],"type":"Point"}
}