{
  "type": "Feature",
  "properties": {
    "iso:country":"US",
    "sg:address":"700 Canal St",
    "sg:city":"Stamford",
    "sg:classifiers":[
        {
            "category":"Professional",
            "type":"Services"
        },
        {
            "category":"Professional",
            "subcategory":"Management & Consulting",
            "type":"Services"
        }
    ],
    "sg:phone":"+1 203 357 9000",
    "sg:postcode":"06902",
    "sg:province":"CT",
    "sg:tags":[
        "development",
        "product",
        "marketing",
        "strategic",
        "new",
        "establishment"
    ],
    "wof:name":"500 Group Inc",
    "wof:placetype":"venue"
},
  "geometry": {"coordinates":[-73.532608,41.045159],"type":"Point"}
}