{
  "type": "Feature",
  "properties": {
    "addr:full":"48 Shore Rd Jewett City CT 06351",
    "addr:housenumber":"48",
    "addr:postcode":"06351",
    "addr:street":"Shore Rd",
    "iso:country":"US",
    "sg:address":"48 Shore Rd",
    "sg:city":"Jewett City",
    "sg:classifiers":[
        {
            "category":"Real Estate",
            "subcategory":"Developer",
            "type":"Services"
        }
    ],
    "sg:phone":"+1 860 889 4493",
    "sg:postcode":"06351",
    "sg:province":"CT",
    "wof:name":"G V Construction Co Inc",
    "wof:placetype":"venue"
},
  "geometry": {"coordinates":[-71.87723200000001,41.561859],"type":"Point"}
}