{
  "type": "Feature",
  "properties": {
    "iso:country":"US",
    "sg:address":"1707 Torringford St",
    "sg:city":"Torrington",
    "sg:classifiers":[
        {
            "category":"Building & Trades",
            "subcategory":"Landscaping Services",
            "type":"Services"
        }
    ],
    "sg:phone":"+1 860 626 0889",
    "sg:postcode":"06790",
    "sg:province":"CT",
    "sg:tags":[
        "landscape"
    ],
    "wof:name":"Garden Imaging LLC",
    "wof:placetype":"venue"
},
  "geometry": {"coordinates":[-73.077276,41.834315],"type":"Point"}
}