{
  "type": "Feature",
  "properties": {
    "addr:full":"46 Riverside Ave Westport CT 06880",
    "addr:housenumber":"46",
    "addr:postcode":"06880",
    "addr:street":"Riverside Ave",
    "iso:country":"US",
    "sg:address":"46 Riverside Ave",
    "sg:city":"Westport",
    "sg:classifiers":[
        {
            "category":"Professional",
            "subcategory":"Lawyer & Legal Services",
            "type":"Services"
        }
    ],
    "sg:phone":"+1 203 226 5601",
    "sg:postcode":"06880",
    "sg:province":"CT",
    "sg:tags":[
        "attorney"
    ],
    "wof:name":"Kenneth R Sosnoski Jr Atty",
    "wof:placetype":"venue"
},
  "geometry": {"coordinates":[-73.36421,41.137525],"type":"Point"}
}