{
  "type": "Feature",
  "properties": {
    "addr:full":"101 River Rd Canton CT 06019",
    "addr:housenumber":"101",
    "addr:postcode":"06019",
    "addr:street":"River Rd",
    "iso:country":"US",
    "sg:address":"101 River Rd",
    "sg:city":"Canton",
    "sg:classifiers":[
        {
            "category":"Health Services",
            "subcategory":"Clinic",
            "type":"Services"
        },
        {
            "category":"Personal",
            "subcategory":"Beauty Salon",
            "type":"Services"
        }
    ],
    "sg:phone":"+1 860 294 1296",
    "sg:postcode":"06019",
    "sg:province":"CT",
    "sg:tags":[
        "spa",
        "medical"
    ],
    "sg:website":"www.panaceahealing.com/",
    "wof:name":"Panacea",
    "wof:placetype":"venue"
},
  "geometry": {"coordinates":[-72.927531,41.833094],"type":"Point"}
}