{
  "type": "Feature",
  "properties": {
    "iso:country":"US",
    "sg:address":"606 S Main St",
    "sg:city":"Waterbury",
    "sg:classifiers":[
        {
            "category":"Food & Beverages",
            "subcategory":"Bakery",
            "type":"Retail Goods"
        }
    ],
    "sg:phone":"+1 203 573 1590",
    "sg:postcode":"06706",
    "sg:province":"CT",
    "wof:name":"Panaderia Y Reposteria Pan Del",
    "wof:placetype":"venue"
},
  "geometry": {"coordinates":[-73.03819799999999,41.547434],"type":"Point"}
}