{
  "type": "Feature",
  "properties": {
    "iso:country":"US",
    "sg:address":"652 Boston Post Rd",
    "sg:city":"Guilford",
    "sg:classifiers":[
        {
            "category":"Health Services",
            "subcategory":"Health Practitioner",
            "type":"Services"
        }
    ],
    "sg:phone":"+1 203 453 2844",
    "sg:postcode":"06437",
    "sg:province":"CT",
    "sg:tags":[
        "therapist",
        "physical"
    ],
    "wof:name":"Physical Therapy & Sports Med",
    "wof:placetype":"venue"
},
  "geometry": {"coordinates":[-72.665798,41.288595],"type":"Point"}
}