{
  "type": "Feature",
  "properties": {
    "iso:country":"US",
    "sg:address":"56 Under Mountain Rd",
    "sg:city":"Salisbury",
    "sg:classifiers":[
        {
            "category":"Personal",
            "subcategory":"Tanning Parlor",
            "type":"Services"
        },
        {
            "category":"Personal",
            "subcategory":"Beauty Salon",
            "type":"Services"
        },
        {
            "category":"Personal",
            "subcategory":"Nail Salon",
            "type":"Services"
        }
    ],
    "sg:phone":"+1 860 435 3541",
    "sg:postcode":"06068",
    "sg:province":"CT",
    "wof:name":"Tiffany's Beauty Salon",
    "wof:placetype":"venue"
},
  "geometry": {"coordinates":[-73.42364000000001,41.987493],"type":"Point"}
}