{
  "type": "Feature",
  "properties": {
    "addr:full":"22 Yew St Norwalk CT 06850",
    "addr:housenumber":"22",
    "addr:postcode":"06850",
    "addr:street":"Yew St",
    "iso:country":"US",
    "sg:address":"22 Yew St",
    "sg:city":"Norwalk",
    "sg:classifiers":[
        {
            "category":"Professional",
            "subcategory":"Computer Services",
            "type":"Services"
        }
    ],
    "sg:phone":"+1   ",
    "sg:postcode":"06850",
    "sg:province":"CT",
    "sg:tags":[
        "datum"
    ],
    "wof:name":"Cnrg Enterprises Inc",
    "wof:placetype":"venue"
},
  "geometry": {"coordinates":[-73.434195,41.148623],"type":"Point"}
}