{
  "type": "Feature",
  "properties": {
    "iso:country":"US",
    "sg:address":"8 Devils Garden Rd",
    "sg:city":"Norwalk",
    "sg:classifiers":[
        {
            "category":"Professional",
            "subcategory":"Management & Consulting",
            "type":"Services"
        }
    ],
    "sg:phone":"+1 203 857 4220",
    "sg:postcode":"06854",
    "sg:province":"CT",
    "sg:tags":[
        "construction",
        "architectural"
    ],
    "wof:name":"Beacon Projects Group The",
    "wof:placetype":"venue"
},
  "geometry": {"coordinates":[-73.43668,41.0857],"type":"Point"}
}