{
  "type": "Feature",
  "properties": {
    "addr:full":"29 Mist Hill Dr Brookfield CT 06804",
    "addr:housenumber":"29",
    "addr:postcode":"06804",
    "addr:street":"Mist Hill Dr",
    "iso:country":"US",
    "sg:address":"29 Mist Hill Dr",
    "sg:city":"Brookfield",
    "sg:classifiers":[
        {
            "category":"Building & Trades",
            "subcategory":"Construction",
            "type":"Services"
        }
    ],
    "sg:phone":"+1 203 775 1448",
    "sg:postcode":"06804",
    "sg:province":"CT",
    "sg:tags":[
        "painter"
    ],
    "wof:name":"Happy Homes Paint Craftsmen",
    "wof:placetype":"venue"
},
  "geometry": {"coordinates":[-73.42783300000001,41.472923],"type":"Point"}
}