{
  "type": "Feature",
  "properties": {
    "iso:country":"US",
    "sg:address":"61 Wappingwood Rd",
    "sg:city":"Ellington",
    "sg:classifiers":[
        {
            "category":"Professional",
            "type":"Services"
        }
    ],
    "sg:phone":"+1 860 875 1074",
    "sg:postcode":"06029",
    "sg:province":"CT",
    "wof:name":"Fund Raiser Specialties LLC",
    "wof:placetype":"venue"
},
  "geometry": {"coordinates":[-72.51515999999999,41.857548],"type":"Point"}
}