{
  "type": "Feature",
  "properties": {
    "addr:full":"242 Crest Rd Southington CT 06489",
    "addr:housenumber":"242",
    "addr:postcode":"06489",
    "addr:street":"Crest Rd",
    "iso:country":"US",
    "sg:address":"242 Crest Rd",
    "sg:city":"Southington",
    "sg:classifiers":[
        {
            "category":"Professional",
            "subcategory":"Computer Services",
            "type":"Services"
        }
    ],
    "sg:phone":"+1   ",
    "sg:postcode":"06489",
    "sg:province":"CT",
    "sg:tags":[
        "programming"
    ],
    "wof:name":"JC Computer Solutions LLC",
    "wof:placetype":"venue"
},
  "geometry": {"coordinates":[-72.84810400000001,41.609529],"type":"Point"}
}