{
  "type": "Feature",
  "properties": {
    "addr:full":"2136 High Ridge Rd Stamford CT 06903",
    "addr:housenumber":"2136",
    "addr:postcode":"06903",
    "addr:street":"High Ridge Rd",
    "iso:country":"US",
    "sg:address":"2136 High Ridge Rd",
    "sg:city":"Stamford",
    "sg:classifiers":[
        {
            "category":"Organizations",
            "subcategory":"Religious Organization",
            "type":"Services"
        }
    ],
    "sg:phone":"+1 203 329 8995",
    "sg:postcode":"06903",
    "sg:province":"CT",
    "sg:tags":[
        "church"
    ],
    "wof:name":"North Stamford Seventh Day Chr",
    "wof:placetype":"venue"
},
  "geometry": {"coordinates":[-73.54617500000001,41.142265],"type":"Point"}
}