{
  "type": "Feature",
  "properties": {
    "addr:full":"253 West St Seymour CT 06483",
    "addr:housenumber":"253",
    "addr:postcode":"06483",
    "addr:street":"West St",
    "iso:country":"US",
    "sg:address":"253 West St",
    "sg:city":"Seymour",
    "sg:classifiers":[
        {
            "category":"Utilities",
            "subcategory":"Mobile Phone",
            "type":"Services"
        },
        {
            "category":"Personal",
            "subcategory":"Nail Salon",
            "type":"Services"
        }
    ],
    "sg:phone":"+1 203 888 2882",
    "sg:postcode":"06483",
    "sg:province":"CT",
    "sg:tags":[
        "wi-fi",
        "hotspot"
    ],
    "wof:name":"Tiffany Nails & Spa",
    "wof:placetype":"venue"
},
  "geometry": {"coordinates":[-73.086611,41.39769],"type":"Point"}
}