{
  "type": "Feature",
  "properties": {
    "addr:full":"31 Stevens Rd Middlebury CT 06762",
    "addr:housenumber":"31",
    "addr:postcode":"06762",
    "addr:street":"Stevens Rd",
    "iso:country":"US",
    "sg:address":"31 Stevens Rd",
    "sg:city":"Middlebury",
    "sg:classifiers":[
        {
            "category":"Wholesale",
            "subcategory":"Stationery",
            "type":"Manufacturing & Wholesale Goods"
        }
    ],
    "sg:phone":"+1 203 758 1648",
    "sg:postcode":"06762",
    "sg:province":"CT",
    "sg:tags":[
        "supply"
    ],
    "wof:name":"Amer Bus Forms Splys",
    "wof:placetype":"venue"
},
  "geometry": {"coordinates":[-73.101107,41.53606],"type":"Point"}
}