{
  "type": "Feature",
  "properties": {
    "addr:full":"38 Doolittle Rd Stamford CT 06902",
    "addr:housenumber":"38",
    "addr:postcode":"06902",
    "addr:street":"Doolittle Rd",
    "iso:country":"US",
    "sg:address":"38 Doolittle Rd",
    "sg:city":"Stamford",
    "sg:classifiers":[
        {
            "category":"Professional",
            "subcategory":"Business Services",
            "type":"Services"
        }
    ],
    "sg:phone":"+1   ",
    "sg:postcode":"06902",
    "sg:province":"CT",
    "wof:name":"Timothy Gelling Design Group",
    "wof:placetype":"venue"
},
  "geometry": {"coordinates":[-73.574288,41.097588],"type":"Point"}
}