{
  "type": "Feature",
  "properties": {
    "addr:full":"131 Birch Rd Storrs Mansfield CT 06268",
    "addr:housenumber":"131",
    "addr:postcode":"06268",
    "addr:street":"Birch Rd",
    "iso:country":"US",
    "sg:address":"131 Birch Rd",
    "sg:city":"Storrs Mansfield",
    "sg:classifiers":[
        {
            "category":"Professional",
            "subcategory":"Management & Consulting",
            "type":"Services"
        }
    ],
    "sg:phone":"+1   ",
    "sg:postcode":"06268",
    "sg:province":"CT",
    "sg:tags":[
        "public",
        "relations"
    ],
    "wof:name":"Xiuchun Tian",
    "wof:placetype":"venue"
},
  "geometry": {"coordinates":[-72.283338,41.815992],"type":"Point"}
}