{
  "type": "Feature",
  "properties": {
    "addr:full":"1010 Slater Rd New Britain CT 06053",
    "addr:housenumber":"1010",
    "addr:postcode":"06053",
    "addr:street":"Slater Rd",
    "iso:country":"US",
    "sg:address":"1010 Slater Rd",
    "sg:city":"New Britain",
    "sg:classifiers":[
        {
            "category":"Organizations",
            "subcategory":"Religious Organization",
            "type":"Services"
        }
    ],
    "sg:phone":"+1   ",
    "sg:postcode":"06053",
    "sg:province":"CT",
    "wof:name":"Saint Jeromes Church",
    "wof:placetype":"venue"
},
  "geometry": {"coordinates":[-72.80067699999999,41.696903],"type":"Point"}
}