{
  "type": "Feature",
  "properties": {
    "addr:full":"14 Ave D Beacon Falls CT 06403",
    "addr:postcode":"06403",
    "addr:street":"14 Ave D Beacon Falls Ct",
    "iso:country":"US",
    "sg:address":"14 Ave D",
    "sg:city":"Beacon Falls",
    "sg:classifiers":[
        {
            "category":"Social Services",
            "subcategory":"Child Care",
            "type":"Services"
        }
    ],
    "sg:phone":"+1   ",
    "sg:postcode":"06403",
    "sg:province":"CT",
    "sg:tags":[
        "day"
    ],
    "wof:name":"Computertots",
    "wof:placetype":"venue"
},
  "geometry": {"coordinates":[-73.05554100000001,41.439321],"type":"Point"}
}