{
  "type": "Feature",
  "properties": {
    "iso:country":"US",
    "sg:address":"37 Danbury Rd",
    "sg:city":"Ridgefield",
    "sg:classifiers":[
        {
            "category":"Professional",
            "subcategory":"Lawyer & Legal Services",
            "type":"Services"
        }
    ],
    "sg:phone":"+1 203 431 2188",
    "sg:postcode":"06877",
    "sg:province":"CT",
    "sg:tags":[
        "attorney"
    ],
    "wof:name":"Giustino Capodilupo Law Office",
    "wof:placetype":"venue"
},
  "geometry": {"coordinates":[-73.49752599999999,41.290095],"type":"Point"}
}