{
  "type": "Feature",
  "properties": {
    "addr:full":"57 Phelps Rd Woodstock CT 06281",
    "addr:housenumber":"57",
    "addr:postcode":"06281",
    "addr:street":"Phelps Rd",
    "iso:country":"US",
    "sg:address":"57 Phelps Rd",
    "sg:city":"Woodstock",
    "sg:classifiers":[
        {
            "category":"Retail",
            "subcategory":"Repair Shop",
            "type":"Services"
        }
    ],
    "sg:phone":"+1   ",
    "sg:postcode":"06281",
    "sg:province":"CT",
    "sg:tags":[
        "tank",
        "septic"
    ],
    "wof:name":"A-1 Septic Service Inc",
    "wof:placetype":"venue"
},
  "geometry": {"coordinates":[-72.005163,41.967859],"type":"Point"}
}