{
  "type": "Feature",
  "properties": {
    "iso:country":"US",
    "sg:address":"179 Prospect Dr",
    "sg:city":"Stratford",
    "sg:classifiers":[
        {
            "category":"Social Services",
            "subcategory":"Child Care",
            "type":"Services"
        }
    ],
    "sg:phone":"+1 203 375 5631",
    "sg:postcode":"06615",
    "sg:province":"CT",
    "wof:name":"Lordship Community Preschool",
    "wof:placetype":"venue"
},
  "geometry": {"coordinates":[-73.12282,41.155164],"type":"Point"}
}