{
  "type": "Feature",
  "properties": {
    "addr:full":"127 W Main St Plainville CT 06062",
    "addr:housenumber":"127",
    "addr:postcode":"06062",
    "addr:street":"W Main St",
    "iso:country":"US",
    "sg:address":"127 W Main St",
    "sg:city":"Plainville",
    "sg:classifiers":[
        {
            "category":"Personal",
            "subcategory":"Shoe Repair & Shine",
            "type":"Services"
        }
    ],
    "sg:phone":"+1   ",
    "sg:postcode":"06062",
    "sg:province":"CT",
    "sg:tags":[
        "parlor"
    ],
    "wof:name":"Normans Shoe Repair",
    "wof:placetype":"venue"
},
  "geometry": {"coordinates":[-72.872488,41.670252],"type":"Point"}
}