{
  "type": "Feature",
  "properties": {
    "iso:country":"US",
    "sg:address":"402 Highland Ave",
    "sg:city":"Cheshire",
    "sg:classifiers":[
        {
            "category":"Real Estate",
            "subcategory":"Real Estate Agent",
            "type":"Services"
        }
    ],
    "sg:phone":"+1 203 250 6677",
    "sg:postcode":"06410",
    "sg:province":"CT",
    "wof:name":"Cheshire Real Estate Coml",
    "wof:placetype":"venue"
},
  "geometry": {"coordinates":[-72.899822,41.50819],"type":"Point"}
}