{
  "type": "Feature",
  "properties": {
    "addr:full":"23 Saint George Ave Stamford CT 06905",
    "addr:housenumber":"23",
    "addr:postcode":"06905",
    "addr:street":"Saint George Ave",
    "iso:country":"US",
    "sg:address":"23 Saint George Ave",
    "sg:city":"Stamford",
    "sg:classifiers":[
        {
            "category":"Organizations",
            "subcategory":"Community Association",
            "type":"Services"
        }
    ],
    "sg:phone":"+1   ",
    "sg:postcode":"06905",
    "sg:province":"CT",
    "wof:name":"Kiwanis International",
    "wof:placetype":"venue"
},
  "geometry": {"coordinates":[-73.553151,41.057411],"type":"Point"}
}