{
  "type": "Feature",
  "properties": {
    "addr:full":"1033 S Main St Cheshire CT 06410",
    "addr:housenumber":"1033",
    "addr:postcode":"06410",
    "addr:street":"S Main St",
    "iso:country":"US",
    "sg:address":"1033 S Main St",
    "sg:city":"Cheshire",
    "sg:classifiers":[
        {
            "category":"Retail",
            "subcategory":"Laundry & Dry Cleaning",
            "type":"Services"
        }
    ],
    "sg:phone":"+1   ",
    "sg:postcode":"06410",
    "sg:province":"CT",
    "sg:tags":[
        "drycleaning",
        "plant"
    ],
    "wof:name":"Jet Cleaners",
    "wof:placetype":"venue"
},
  "geometry": {"coordinates":[-72.90625300000001,41.476624],"type":"Point"}
}