{
  "type": "Feature",
  "properties": {
    "addr:full":"23 Southridge Rd Southbury CT 06488",
    "addr:housenumber":"23",
    "addr:postcode":"06488",
    "addr:street":"Southridge Rd",
    "iso:country":"US",
    "sg:address":"23 Southridge Rd",
    "sg:city":"Southbury",
    "sg:classifiers":[
        {
            "category":"Shopping",
            "subcategory":"Computers & Home Electronics",
            "type":"Retail Goods"
        }
    ],
    "sg:phone":"+1 203 264 7600",
    "sg:postcode":"06488",
    "sg:province":"CT",
    "sg:tags":[
        "equipment",
        "dealer"
    ],
    "wof:name":"Data Storage Depot",
    "wof:placetype":"venue"
},
  "geometry": {"coordinates":[-73.200879,41.503102],"type":"Point"}
}