{
  "type": "Feature",
  "properties": {
    "addr:full":"92 Greenwich Ave Greenwich CT 06830",
    "addr:housenumber":"92",
    "addr:postcode":"06830",
    "addr:street":"Greenwich Ave",
    "iso:country":"US",
    "sg:address":"92 Greenwich Ave",
    "sg:city":"Greenwich",
    "sg:classifiers":[
        {
            "category":"Shopping",
            "subcategory":"Clothing, Apparel, & Fashions",
            "type":"Retail Goods"
        }
    ],
    "sg:phone":"+1 203 661 3563",
    "sg:postcode":"06830",
    "sg:province":"CT",
    "wof:name":"April Cornell",
    "wof:placetype":"venue"
},
  "geometry": {"coordinates":[-73.626475,41.029211],"type":"Point"}
}