{
  "type": "Feature",
  "properties": {
    "iso:country":"US",
    "sg:address":"46 Southfield Ave",
    "sg:city":"Stamford",
    "sg:classifiers":[
        {
            "category":"Restaurant",
            "type":"Food & Drink"
        }
    ],
    "sg:phone":"+1 203 967 7229",
    "sg:postcode":"06902",
    "sg:province":"CT",
    "sg:website":"www.crabshell.com",
    "wof:name":"Crab Shell",
    "wof:placetype":"venue"
},
  "geometry": {"coordinates":[-73.547766,41.039188],"type":"Point"}
}