{
  "type": "Feature",
  "properties": {
    "addr:full":"230 Woodlawn Cir East Hartford CT 06108",
    "addr:housenumber":"230",
    "addr:postcode":"06108",
    "addr:street":"Woodlawn Cir East Hartford Ct",
    "iso:country":"US",
    "sg:address":"230 Woodlawn Cir",
    "sg:city":"East Hartford",
    "sg:classifiers":[
        {
            "category":"Professional",
            "type":"Services"
        }
    ],
    "sg:phone":"+1 860 559 8727",
    "sg:postcode":"06108",
    "sg:province":"CT",
    "wof:name":"Richard C Halton",
    "wof:placetype":"venue"
},
  "geometry": {"coordinates":[-72.589541,41.776938],"type":"Point"}
}