{
  "type": "Feature",
  "properties": {
    "iso:country":"US",
    "sg:address":"800 Albany Ave",
    "sg:city":"Hartford",
    "sg:classifiers":[
        {
            "category":"Organizations",
            "subcategory":"Religious Organization",
            "type":"Services"
        }
    ],
    "sg:phone":"+1   ",
    "sg:postcode":"06112",
    "sg:province":"CT",
    "wof:name":"Pentecstal Hlness Chrch Dlvran",
    "wof:placetype":"venue"
},
  "geometry": {"coordinates":[-72.688889,41.779143],"type":"Point"}
}