{
  "type": "Feature",
  "properties": {
    "iso:country":"US",
    "sg:address":"171 Braemar Dr",
    "sg:city":"Cheshire",
    "sg:classifiers":[
        {
            "category":"Professional",
            "subcategory":"Business Services",
            "type":"Services"
        }
    ],
    "sg:phone":"+1   ",
    "sg:postcode":"06410",
    "sg:province":"CT",
    "wof:name":"Forster Grge Crtif Fncl Plnner",
    "wof:placetype":"venue"
},
  "geometry": {"coordinates":[-72.885841,41.530284],"type":"Point"}
}