{
  "type": "Feature",
  "properties": {
    "iso:country":"US",
    "sg:address":"275 Bridgeport Ave",
    "sg:city":"Shelton",
    "sg:classifiers":[
        {
            "category":"Manufacturing",
            "subcategory":"Toys & Sporting Goods",
            "type":"Manufacturing & Wholesale Goods"
        }
    ],
    "sg:phone":"+1 203 924 4643",
    "sg:postcode":"06484",
    "sg:province":"CT",
    "sg:website":"www.wiffle.org",
    "wof:name":"Wiffle Ball Inc",
    "wof:placetype":"venue"
},
  "geometry": {"coordinates":[-73.10126700000001,41.303457],"type":"Point"}
}