{
  "type": "Feature",
  "properties": {
    "iso:country":"US",
    "sg:address":"111 Scrub Oak Rd",
    "sg:city":"North Haven",
    "sg:classifiers":[
        {
            "category":"Restaurant",
            "type":"Food & Drink"
        }
    ],
    "sg:phone":"+1 203 239 1961",
    "sg:postcode":"06473",
    "sg:province":"CT",
    "sg:tags":[
        "banquet",
        "rooms"
    ],
    "wof:name":"LA Mirage",
    "wof:placetype":"venue"
},
  "geometry": {"coordinates":[-72.827044,41.422197],"type":"Point"}
}