{
  "type": "Feature",
  "properties": {
    "iso:country":"US",
    "sg:address":"41 Benson Dr",
    "sg:city":"Danbury",
    "sg:classifiers":[
        {
            "category":"Shopping",
            "type":"Retail Goods"
        }
    ],
    "sg:phone":"+1 203 792 1477",
    "sg:postcode":"06810",
    "sg:province":"CT",
    "sg:tags":[
        "pet",
        "shop"
    ],
    "wof:name":"Help For Pets",
    "wof:placetype":"venue"
},
  "geometry": {"coordinates":[-73.518261,41.377454],"type":"Point"}
}