{
  "type": "Feature",
  "properties": {
    "addr:full":"1681 Park Ave Bridgeport CT 06604",
    "addr:housenumber":"1681",
    "addr:postcode":"06604",
    "addr:street":"Park Ave",
    "iso:country":"US",
    "sg:address":"1681 Park Ave",
    "sg:city":"Bridgeport",
    "sg:classifiers":[
        {
            "category":"Personal",
            "subcategory":"Beauty Salon",
            "type":"Services"
        }
    ],
    "sg:phone":"+1 203 362 1623",
    "sg:postcode":"06604",
    "sg:province":"CT",
    "sg:tags":[
        "shop"
    ],
    "wof:name":"Chantel African Hair Salon LLC",
    "wof:placetype":"venue"
},
  "geometry": {"coordinates":[-73.205834,41.182264],"type":"Point"}
}