{
  "type": "Feature",
  "properties": {
    "addr:full":"249 Bridgeport Ave Milford CT 06460",
    "addr:housenumber":"249",
    "addr:postcode":"06460",
    "addr:street":"Bridgeport Ave",
    "iso:country":"US",
    "sg:address":"249 Bridgeport Ave",
    "sg:city":"Milford",
    "sg:classifiers":[
        {
            "category":"Restaurant",
            "type":"Food & Drink"
        }
    ],
    "sg:phone":"+1 203 878 5121",
    "sg:postcode":"06460",
    "sg:province":"CT",
    "wof:name":"Bridgeport Flyer Diner",
    "wof:placetype":"venue"
},
  "geometry": {"coordinates":[-73.101912,41.202185],"type":"Point"}
}