{
  "type": "Feature",
  "properties": {
    "iso:country":"US",
    "sg:address":"1116 N Colony Rd",
    "sg:city":"Wallingford",
    "sg:classifiers":[
        {
            "category":"Shopping",
            "subcategory":"Department Store",
            "type":"Retail Goods"
        }
    ],
    "sg:phone":"+1 203 949 0477",
    "sg:postcode":"06492",
    "sg:province":"CT",
    "sg:tags":[
        "shop"
    ],
    "wof:name":"Nishi's Dollar Land",
    "wof:placetype":"venue"
},
  "geometry": {"coordinates":[-72.81054,41.503561],"type":"Point"}
}