{
  "type": "Feature",
  "properties": {
    "iso:country":"US",
    "sg:address":"18 Clifford Ave",
    "sg:city":"Stamford",
    "sg:classifiers":[
        {
            "category":"Organizations",
            "subcategory":"Community Association",
            "type":"Services"
        }
    ],
    "sg:phone":"+1   ",
    "sg:postcode":"06905",
    "sg:province":"CT",
    "wof:name":"Turn River Condominium Assn",
    "wof:placetype":"venue"
},
  "geometry": {"coordinates":[-73.536905,41.07816],"type":"Point"}
}