{
  "type": "Feature",
  "properties": {
    "iso:country":"US",
    "sg:address":"133 Park Rd",
    "sg:city":"Hamden",
    "sg:classifiers":[
        {
            "category":"Banks & Credit Unions",
            "subcategory":"Financial Services",
            "type":"Services"
        }
    ],
    "sg:phone":"+1 203 789 8254",
    "sg:postcode":"06517",
    "sg:province":"CT",
    "sg:tags":[
        "investment",
        "closed"
    ],
    "wof:name":"Land Trust Inc",
    "wof:placetype":"venue"
},
  "geometry": {"coordinates":[-72.899247,41.329687],"type":"Point"}
}