{
  "type": "Feature",
  "properties": {
    "iso:country":"US",
    "sg:address":"27 High Ridge Dr",
    "sg:city":"Waterford",
    "sg:classifiers":[
        {
            "category":"Social Services",
            "subcategory":"Adult Care",
            "type":"Services"
        }
    ],
    "sg:phone":"+1   ",
    "sg:postcode":"06385",
    "sg:province":"CT",
    "sg:tags":[
        "residential"
    ],
    "wof:name":"Sunrise Northeast Group Home",
    "wof:placetype":"venue"
},
  "geometry": {"coordinates":[-72.16995199999999,41.331235],"type":"Point"}
}