{
  "type": "Feature",
  "properties": {
    "addr:full":"148 Main St Cheshire CT 06410",
    "addr:housenumber":"148",
    "addr:postcode":"06410",
    "addr:street":"Main St",
    "iso:country":"US",
    "sg:address":"148 Main St",
    "sg:city":"Cheshire",
    "sg:classifiers":[
        {
            "category":"Personal",
            "subcategory":"Beauty Salon",
            "type":"Services"
        }
    ],
    "sg:phone":"+1 203 272 7739",
    "sg:postcode":"06410",
    "sg:province":"CT",
    "sg:tags":[
        "shop",
        "manicuring"
    ],
    "wof:name":"Unique Nails 2",
    "wof:placetype":"venue"
},
  "geometry": {"coordinates":[-72.903325,41.502973],"type":"Point"}
}