{
  "type": "Feature",
  "properties": {
    "addr:full":"938 Chapel St New Haven CT 06510",
    "addr:housenumber":"938",
    "addr:postcode":"06510",
    "addr:street":"Chapel St",
    "iso:country":"US",
    "sg:address":"938 Chapel St",
    "sg:city":"New Haven",
    "sg:classifiers":[
        {
            "category":"Professional",
            "subcategory":"Business Services",
            "type":"Services"
        }
    ],
    "sg:phone":"+1 203 773 1883",
    "sg:postcode":"06510",
    "sg:province":"CT",
    "sg:tags":[
        "translator",
        "interpreter"
    ],
    "wof:name":"Expertise Translations",
    "wof:placetype":"venue"
},
  "geometry": {"coordinates":[-72.928567,41.307112],"type":"Point"}
}