{
  "type": "Feature",
  "properties": {
    "addr:full":"375 Newtown Ave Norwalk CT 06851",
    "addr:housenumber":"375",
    "addr:postcode":"06851",
    "addr:street":"Newtown Ave",
    "iso:country":"US",
    "sg:address":"375 Newtown Ave",
    "sg:city":"Norwalk",
    "sg:classifiers":[
        {
            "category":"Organizations",
            "subcategory":"Religious Organization",
            "type":"Services"
        }
    ],
    "sg:phone":"+1 203 845 9043",
    "sg:postcode":"06851",
    "sg:province":"CT",
    "sg:tags":[
        "clergy"
    ],
    "wof:name":"Ronald W Kresge Rev",
    "wof:placetype":"venue"
},
  "geometry": {"coordinates":[-73.39284600000001,41.149299],"type":"Point"}
}