{
  "type": "Feature",
  "properties": {
    "addr:full":"5 E Main St Clinton CT 06413",
    "addr:housenumber":"5",
    "addr:postcode":"06413",
    "addr:street":"E Main St",
    "iso:country":"US",
    "sg:address":"5 E Main St",
    "sg:city":"Clinton",
    "sg:classifiers":[
        {
            "category":"Education",
            "subcategory":"Special Training",
            "type":"Public Place"
        }
    ],
    "sg:phone":"+1   ",
    "sg:postcode":"06413",
    "sg:province":"CT",
    "wof:name":"Russell Becker Woodwind Studio",
    "wof:placetype":"venue"
},
  "geometry": {"coordinates":[-72.52544899999999,41.278587],"type":"Point"}
}