{
  "type": "Feature",
  "properties": {
    "addr:full":"55 Wake Robin Ln Stamford CT 06903",
    "addr:housenumber":"55",
    "addr:postcode":"06903",
    "addr:street":"Wake Robin Ln",
    "iso:country":"US",
    "sg:address":"55 Wake Robin Ln",
    "sg:city":"Stamford",
    "sg:classifiers":[
        {
            "category":"Shopping",
            "subcategory":"Computers & Home Electronics",
            "type":"Retail Goods"
        }
    ],
    "sg:phone":"+1 203 329 0329",
    "sg:postcode":"06903",
    "sg:province":"CT",
    "sg:tags":[
        "equipment",
        "dealer"
    ],
    "sg:website":"www.isiconsulting.com",
    "wof:name":"Integrated Solutions Inc",
    "wof:placetype":"venue"
},
  "geometry": {"coordinates":[-73.556737,41.114749],"type":"Point"}
}