{
  "type": "Feature",
  "properties": {
    "iso:country":"US",
    "sg:address":"2370 Barnum Ave",
    "sg:city":"Stratford",
    "sg:classifiers":[
        {
            "category":"Retail",
            "subcategory":"Self-service Laundry",
            "type":"Services"
        }
    ],
    "sg:phone":"+1 203 380 8263",
    "sg:postcode":"06615",
    "sg:province":"CT",
    "wof:name":"S & R Laundromat & Bulk Clnng",
    "wof:placetype":"venue"
},
  "geometry": {"coordinates":[-73.15329,41.190664],"type":"Point"}
}