{
  "type": "Feature",
  "properties": {
    "iso:country":"US",
    "sg:address":"74 Mitchell St",
    "sg:city":"Stamford",
    "sg:classifiers":[
        {
            "category":"Professional",
            "subcategory":"Art Services",
            "type":"Services"
        }
    ],
    "sg:phone":"+1 203 356 0342",
    "sg:postcode":"06902",
    "sg:province":"CT",
    "sg:tags":[
        "graphic",
        "designer"
    ],
    "wof:name":"Timothy Anderson Design",
    "wof:placetype":"venue"
},
  "geometry": {"coordinates":[-73.52795,41.035294],"type":"Point"}
}