{
  "type": "Feature",
  "properties": {
    "addr:full":"110 Betsy Brown Rd Port Chester CT 10573",
    "addr:housenumber":"110",
    "addr:postcode":"10573",
    "addr:street":"Betsy Brown Rd",
    "iso:country":"US",
    "sg:address":"110 Betsy Brown Rd",
    "sg:city":"Port Chester",
    "sg:classifiers":[
        {
            "category":"Insurance",
            "subcategory":"Insurance Agent",
            "type":"Services"
        }
    ],
    "sg:phone":"+1 914 921 3516",
    "sg:postcode":"10573",
    "sg:province":"CT",
    "wof:name":"Aquarius Capital",
    "wof:placetype":"venue"
},
  "geometry": {"coordinates":[-73.67244100000001,41.020111],"type":"Point"}
}