{
  "type": "Feature",
  "properties": {
    "iso:country":"US",
    "sg:address":"472 Wolcott Rd",
    "sg:city":"Wolcott",
    "sg:classifiers":[
        {
            "category":"Professional",
            "subcategory":"Lawyer & Legal Services",
            "type":"Services"
        }
    ],
    "sg:phone":"+1 203 879 4644",
    "sg:postcode":"06716",
    "sg:province":"CT",
    "sg:tags":[
        "attorney"
    ],
    "wof:name":"Borghesi Harbanuk & Wilson",
    "wof:placetype":"venue"
},
  "geometry": {"coordinates":[-72.98955100000001,41.591793],"type":"Point"}
}