{
  "type": "Feature",
  "properties": {
    "addr:full":"6 Valley Rd Norwalk CT 06854",
    "addr:housenumber":"6",
    "addr:postcode":"06854",
    "addr:street":"Valley Rd",
    "iso:country":"US",
    "sg:address":"6 Valley Rd",
    "sg:city":"Norwalk",
    "sg:classifiers":[
        {
            "category":"Communications",
            "subcategory":"Film & Video Production",
            "type":"Services"
        }
    ],
    "sg:phone":"+1   ",
    "sg:postcode":"06854",
    "sg:province":"CT",
    "sg:tags":[
        "motion"
    ],
    "wof:name":"Pipedream Productions Inc",
    "wof:placetype":"venue"
},
  "geometry": {"coordinates":[-73.42247500000001,41.075501],"type":"Point"}
}