{
  "type": "Feature",
  "properties": {
    "iso:country":"US",
    "sg:address":"257 Water St",
    "sg:city":"Canterbury",
    "sg:classifiers":[
        {
            "category":"Building & Trades",
            "subcategory":"Construction",
            "type":"Services"
        }
    ],
    "sg:phone":"+1 860 546 9174",
    "sg:postcode":"06331",
    "sg:province":"CT",
    "sg:tags":[
        "carpenter"
    ],
    "wof:name":"Jeff Warcholik Carpentry",
    "wof:placetype":"venue"
},
  "geometry": {"coordinates":[-72.022577,41.684189],"type":"Point"}
}