{
  "type": "Feature",
  "properties": {
    "iso:country":"US",
    "sg:address":"168 Mayfield Dr",
    "sg:city":"Trumbull",
    "sg:classifiers":[
        {
            "category":"Professional",
            "subcategory":"Advertising",
            "type":"Services"
        }
    ],
    "sg:phone":"+1   ",
    "sg:postcode":"06611",
    "sg:province":"CT",
    "sg:tags":[
        "creative"
    ],
    "wof:name":"Creative Film Vdeo Productions",
    "wof:placetype":"venue"
},
  "geometry": {"coordinates":[-73.220223,41.25656],"type":"Point"}
}