{
  "type": "Feature",
  "properties": {
    "iso:country":"US",
    "sg:address":"19 Barnum Ct",
    "sg:city":"Danbury",
    "sg:classifiers":[
        {
            "category":"Building & Trades",
            "subcategory":"Construction",
            "type":"Services"
        }
    ],
    "sg:phone":"+1 203 746 8211",
    "sg:postcode":"06810",
    "sg:province":"CT",
    "sg:tags":[
        "resurfacing",
        "refinishing",
        "floor"
    ],
    "wof:name":"Modern Flooring",
    "wof:placetype":"venue"
},
  "geometry": {"coordinates":[-73.45705599999999,41.402905],"type":"Point"}
}