{
  "type": "Feature",
  "properties": {
    "iso:country":"US",
    "sg:address":"163 Cynthia Ln",
    "sg:city":"Middletown",
    "sg:classifiers":[
        {
            "category":"Arts & Performance",
            "subcategory":"Theater",
            "type":"Entertainment"
        }
    ],
    "sg:phone":"+1   ",
    "sg:postcode":"06457",
    "sg:province":"CT",
    "sg:tags":[
        "theatrical"
    ],
    "wof:name":"Whittaker Productions",
    "wof:placetype":"venue"
},
  "geometry": {"coordinates":[-72.68073099999999,41.575512],"type":"Point"}
}