{
  "type": "Feature",
  "properties": {
    "addr:full":"27 N Main St Old Saybrook CT 06475",
    "addr:housenumber":"27",
    "addr:postcode":"06475",
    "addr:street":"N Main St",
    "iso:country":"US",
    "sg:address":"27 N Main St",
    "sg:city":"Old Saybrook",
    "sg:classifiers":[
        {
            "category":"Shopping",
            "subcategory":"Crafts & Fabrics",
            "type":"Retail Goods"
        }
    ],
    "sg:phone":"+1 860 388 1832",
    "sg:postcode":"06475",
    "sg:province":"CT",
    "sg:tags":[
        "store"
    ],
    "sg:website":"www.coastalsewing.com",
    "wof:name":"Coastal Sewing Machines",
    "wof:placetype":"venue"
},
  "geometry": {"coordinates":[-72.377701,41.298302],"type":"Point"}
}