{
  "type": "Feature",
  "properties": {
    "addr:full":"1 Farm Springs Rd Farmington CT 06032",
    "addr:housenumber":"1",
    "addr:postcode":"06032",
    "addr:street":"Farm Springs Rd",
    "iso:country":"US",
    "sg:address":"1 Farm Springs Rd",
    "sg:city":"Farmington",
    "sg:classifiers":[
        {
            "category":"Retail",
            "subcategory":"Repair Shop",
            "type":"Services"
        }
    ],
    "sg:phone":"+1   ",
    "sg:postcode":"06032",
    "sg:province":"CT",
    "sg:tags":[
        "installation",
        "elevator"
    ],
    "wof:name":"Amtech Elevator Services",
    "wof:placetype":"venue"
},
  "geometry": {"coordinates":[-72.803882,41.713516],"type":"Point"}
}