{
  "type": "Feature",
  "properties": {
    "iso:country":"US",
    "sg:address":"80 Stockings Brook Rd",
    "sg:city":"Berlin",
    "sg:classifiers":[
        {
            "category":"Building & Trades",
            "subcategory":"Electrical",
            "type":"Services"
        }
    ],
    "sg:phone":"+1 860 828 6990",
    "sg:postcode":"06037",
    "sg:province":"CT",
    "sg:tags":[
        "electrical",
        "contractor"
    ],
    "wof:name":"Pucci Eugene",
    "wof:placetype":"venue"
},
  "geometry": {"coordinates":[-72.811463,41.597743],"type":"Point"}
}