{
  "type": "Feature",
  "properties": {
    "iso:country":"US",
    "sg:address":"35 Tunxis Ave",
    "sg:city":"Bloomfield",
    "sg:classifiers":[
        {
            "category":"Retail",
            "subcategory":"Auto Repair",
            "type":"Services"
        }
    ],
    "sg:phone":"+1   ",
    "sg:postcode":"06002",
    "sg:province":"CT",
    "sg:tags":[
        "automotive"
    ],
    "wof:name":"Allied Auto Center Inc",
    "wof:placetype":"venue"
},
  "geometry": {"coordinates":[-72.73743,41.831034],"type":"Point"}
}