{
  "type": "Feature",
  "properties": {
    "addr:full":"237 Wells St Bridgeport CT 06606",
    "addr:housenumber":"237",
    "addr:postcode":"06606",
    "addr:street":"Wells St",
    "iso:country":"US",
    "sg:address":"237 Wells St",
    "sg:city":"Bridgeport",
    "sg:classifiers":[
        {
            "category":"Social Services",
            "subcategory":"Child Care",
            "type":"Services"
        }
    ],
    "sg:phone":"+1   ",
    "sg:postcode":"06606",
    "sg:province":"CT",
    "sg:tags":[
        "day"
    ],
    "wof:name":"C J T Little Tots",
    "wof:placetype":"venue"
},
  "geometry": {"coordinates":[-73.197549,41.194221],"type":"Point"}
}