{
  "type": "Feature",
  "properties": {
    "addr:full":"23 Sunnyside Ln Westport CT 06880",
    "addr:housenumber":"23",
    "addr:postcode":"06880",
    "addr:street":"Sunnyside Ln",
    "iso:country":"US",
    "sg:address":"23 Sunnyside Ln",
    "sg:city":"Westport",
    "sg:classifiers":[
        {
            "category":"Professional",
            "type":"Services"
        }
    ],
    "sg:phone":"+1 203 454 5684",
    "sg:postcode":"06880",
    "sg:province":"CT",
    "wof:name":"Lordship Landing LLC",
    "wof:placetype":"venue"
},
  "geometry": {"coordinates":[-73.334733,41.182018],"type":"Point"}
}