{
  "type": "Feature",
  "properties": {
    "iso:country":"US",
    "sg:address":"5 Patricia Ter",
    "sg:city":"Beacon Falls",
    "sg:classifiers":[
        {
            "category":"Arts & Performance",
            "subcategory":"Theater",
            "type":"Entertainment"
        }
    ],
    "sg:phone":"+1   ",
    "sg:postcode":"06403",
    "sg:province":"CT",
    "sg:tags":[
        "group"
    ],
    "wof:name":"Entertainment Solutions",
    "wof:placetype":"venue"
},
  "geometry": {"coordinates":[-73.033033,41.446609],"type":"Point"}
}