{
  "type": "Feature",
  "properties": {
    "addr:full":"51 Pemberwick Rd Greenwich CT 06831",
    "addr:housenumber":"51",
    "addr:postcode":"06831",
    "addr:street":"Pemberwick Rd",
    "iso:country":"US",
    "sg:address":"51 Pemberwick Rd",
    "sg:city":"Greenwich",
    "sg:classifiers":[
        {
            "category":"Building & Trades",
            "subcategory":"Electrical",
            "type":"Services"
        }
    ],
    "sg:phone":"+1 203 531 5248",
    "sg:postcode":"06831",
    "sg:province":"CT",
    "sg:tags":[
        "electric",
        "contractor"
    ],
    "wof:name":"AEE Svc",
    "wof:placetype":"venue"
},
  "geometry": {"coordinates":[-73.654673,41.018576],"type":"Point"}
}