{
  "type": "Feature",
  "properties": {
    "addr:full":"655 Brentwood Rd Orange CT 06477",
    "addr:housenumber":"655",
    "addr:postcode":"06477",
    "addr:street":"Brentwood Rd",
    "iso:country":"US",
    "sg:address":"655 Brentwood Rd",
    "sg:city":"Orange",
    "sg:classifiers":[
        {
            "category":"Real Estate",
            "subcategory":"Real Estate Agent",
            "type":"Services"
        }
    ],
    "sg:phone":"+1 203 795 4646",
    "sg:postcode":"06477",
    "sg:province":"CT",
    "wof:name":"S Yontef Real Estate",
    "wof:placetype":"venue"
},
  "geometry": {"coordinates":[-73.05594600000001,41.267816],"type":"Point"}
}