{
  "type": "Feature",
  "properties": {
    "iso:country":"US",
    "sg:address":"26 Indian Woods Rd",
    "sg:city":"Branford",
    "sg:classifiers":[
        {
            "category":"Professional",
            "type":"Services"
        }
    ],
    "sg:phone":"+1 203 481 0506",
    "sg:postcode":"06405",
    "sg:province":"CT",
    "sg:tags":[
        "establishment"
    ],
    "wof:name":"Decision Technology",
    "wof:placetype":"venue"
},
  "geometry": {"coordinates":[-72.789654,41.278495],"type":"Point"}
}