{
  "type": "Feature",
  "properties": {
    "iso:country":"US",
    "sg:address":"89 Eastern Steel Rd",
    "sg:city":"Milford",
    "sg:classifiers":[
        {
            "category":"Professional",
            "subcategory":"Advertising",
            "type":"Services"
        }
    ],
    "sg:phone":"+1 203 328 2763",
    "sg:postcode":"06460",
    "sg:province":"CT",
    "sg:tags":[
        "transportation"
    ],
    "wof:name":"Amherst Media",
    "wof:placetype":"venue"
},
  "geometry": {"coordinates":[-73.02017499999999,41.234496],"type":"Point"}
}