{
  "type": "Feature",
  "properties": {
    "iso:country":"US",
    "sg:address":"96 Nolan Rd",
    "sg:city":"Hamden",
    "sg:classifiers":[
        {
            "category":"Communications",
            "subcategory":"Film & Video Production",
            "type":"Services"
        }
    ],
    "sg:phone":"+1 203 288 6740",
    "sg:postcode":"06514",
    "sg:province":"CT",
    "sg:tags":[
        "duplication",
        "tape"
    ],
    "wof:name":"Mc Namara Video Svc",
    "wof:placetype":"venue"
},
  "geometry": {"coordinates":[-72.924972,41.40545],"type":"Point"}
}