{
  "type": "Feature",
  "properties": {
    "addr:full":"839 Forest Rd Northford CT 06472",
    "addr:housenumber":"839",
    "addr:postcode":"06472",
    "addr:street":"Forest Rd Northford Ct",
    "iso:country":"US",
    "sg:address":"839 Forest Rd",
    "sg:city":"Northford",
    "sg:classifiers":[
        {
            "category":"Professional",
            "type":"Services"
        }
    ],
    "sg:phone":"+1 203 484 2606",
    "sg:postcode":"06472",
    "sg:province":"CT",
    "wof:name":"JRS Storage Facility LLC",
    "wof:placetype":"venue"
},
  "geometry": {"coordinates":[-72.792366,41.390934],"type":"Point"}
}