{
  "type": "Feature",
  "properties": {
    "addr:full":"111 Forest St Unionville CT 06085",
    "addr:housenumber":"111",
    "addr:postcode":"06085",
    "addr:street":"Forest St Unionville Ct",
    "iso:country":"US",
    "sg:address":"111 Forest St",
    "sg:city":"Unionville",
    "sg:classifiers":[
        {
            "category":"Professional",
            "subcategory":"Lawyer & Legal Services",
            "type":"Services"
        }
    ],
    "sg:phone":"+1   ",
    "sg:postcode":"06085",
    "sg:province":"CT",
    "wof:name":"Tuttle H J Atty At Law",
    "wof:placetype":"venue"
},
  "geometry": {"coordinates":[-72.88601,41.752327],"type":"Point"}
}