{
  "type": "Feature",
  "properties": {
    "iso:country":"US",
    "sg:address":"894 N Colony Rd",
    "sg:city":"Wallingford",
    "sg:classifiers":[
        {
            "category":"Food & Beverages",
            "subcategory":"Meat & Fish",
            "type":"Retail Goods"
        }
    ],
    "sg:phone":"+1 203 284 0055",
    "sg:postcode":"06492",
    "sg:province":"CT",
    "sg:tags":[
        "seafood"
    ],
    "wof:name":"Village Fish Market",
    "wof:placetype":"venue"
},
  "geometry": {"coordinates":[-72.809641,41.48447],"type":"Point"}
}