{
  "type": "Feature",
  "properties": {
    "addr:full":"201 Idlewood Dr Stamford CT 06905",
    "addr:housenumber":"201",
    "addr:postcode":"06905",
    "addr:street":"Idlewood Dr",
    "iso:country":"US",
    "sg:address":"201 Idlewood Dr",
    "sg:city":"Stamford",
    "sg:classifiers":[
        {
            "category":"Shopping",
            "subcategory":"Jewelry",
            "type":"Retail Goods"
        }
    ],
    "sg:phone":"+1 203 324 4350",
    "sg:postcode":"06905",
    "sg:province":"CT",
    "sg:tags":[
        "jeweler"
    ],
    "wof:name":"William Gordon Jewelers",
    "wof:placetype":"venue"
},
  "geometry": {"coordinates":[-73.542732,41.097871],"type":"Point"}
}