{
  "type": "Feature",
  "properties": {
    "iso:country":"US",
    "sg:address":"72 Berkeley Dr",
    "sg:city":"Vernon Rockville",
    "sg:classifiers":[
        {
            "category":"Building & Trades",
            "subcategory":"Landscaping Services",
            "type":"Services"
        }
    ],
    "sg:phone":"+1 860 649 4457",
    "sg:postcode":"06066",
    "sg:province":"CT",
    "wof:name":"Bosse Lawn Care",
    "wof:placetype":"venue"
},
  "geometry": {"coordinates":[-72.472652,41.805382],"type":"Point"}
}