{
  "type": "Feature",
  "properties": {
    "addr:full":"961 Boston Post Rd Guilford CT 06437",
    "addr:housenumber":"961",
    "addr:postcode":"06437",
    "addr:street":"Boston Post Rd",
    "iso:country":"US",
    "sg:address":"961 Boston Post Rd",
    "sg:city":"Guilford",
    "sg:classifiers":[
        {
            "category":"Restaurant",
            "type":"Food & Drink"
        },
        {
            "category":"Ice Cream",
            "type":"Food & Drink"
        }
    ],
    "sg:menulink":"http://www.allmenus.com/ct/guilford/98997-friendlys/menu/",
    "sg:phone":"+1 203 453 6727",
    "sg:postcode":"06437",
    "sg:province":"CT",
    "sg:tags":[
        "burger",
        "american",
        "ice",
        "cream"
    ],
    "wof:name":"Friendly's",
    "wof:placetype":"venue"
},
  "geometry": {"coordinates":[-72.680937,41.288383],"type":"Point"}
}