{
  "type": "Feature",
  "properties": {
    "addr:full":"116 Greenwich Ave Greenwich CT 06830",
    "addr:housenumber":"116",
    "addr:postcode":"06830",
    "addr:street":"Greenwich Ave",
    "iso:country":"US",
    "sg:address":"116 Greenwich Ave",
    "sg:city":"Greenwich",
    "sg:classifiers":[
        {
            "category":"Shopping",
            "subcategory":"Clothing, Apparel, & Fashions",
            "type":"Retail Goods"
        }
    ],
    "sg:phone":"+1 203 629 2010",
    "sg:postcode":"06830",
    "sg:province":"CT",
    "wof:name":"Reflection",
    "wof:placetype":"venue"
},
  "geometry": {"coordinates":[-73.626571,41.029653],"type":"Point"}
}