{
  "type": "Feature",
  "properties": {
    "iso:country":"US",
    "sg:address":"52 Ravenwood Dr",
    "sg:city":"Weston",
    "sg:classifiers":[
        {
            "category":"Professional",
            "type":"Services"
        }
    ],
    "sg:phone":"+1 203 227 4331",
    "sg:postcode":"06883",
    "sg:province":"CT",
    "sg:tags":[
        "establishment"
    ],
    "wof:name":"Metropolitan Looseleaf Co",
    "wof:placetype":"venue"
},
  "geometry": {"coordinates":[-73.36770300000001,41.242074],"type":"Point"}
}