{
  "type": "Feature",
  "properties": {
    "iso:country":"US",
    "sg:address":"80 Fleming Rd",
    "sg:city":"Fairfield",
    "sg:classifiers":[
        {
            "category":"Professional",
            "subcategory":"Business Services",
            "type":"Services"
        }
    ],
    "sg:phone":"+1 203 259 7584",
    "sg:postcode":"06450",
    "sg:province":"CT",
    "sg:tags":[
        "convention",
        "meeting",
        "facility"
    ],
    "wof:name":"A J Favata & Assoc",
    "wof:placetype":"venue"
},
  "geometry": {"coordinates":[-72.758016,41.501585],"type":"Point"}
}