{
  "type": "Feature",
  "properties": {
    "addr:full":"7 Gleason Ave Stamford CT 06902",
    "addr:housenumber":"7",
    "addr:postcode":"06902",
    "addr:street":"Gleason Ave",
    "iso:country":"US",
    "sg:address":"7 Gleason Ave",
    "sg:city":"Stamford",
    "sg:classifiers":[
        {
            "category":"Shopping",
            "subcategory":"Hobbies, Toys, & Games",
            "type":"Retail Goods"
        },
        {
            "category":"Arena",
            "subcategory":"Auto Racetrack",
            "type":"Entertainment"
        },
        {
            "category":"Shopping",
            "subcategory":"Party Supplies",
            "type":"Retail Goods"
        },
        {
            "category":"Wholesale",
            "subcategory":"Vending Machines",
            "type":"Manufacturing & Wholesale Goods"
        },
        {
            "category":"Recreation",
            "subcategory":"Amusement Park",
            "type":"Entertainment"
        },
        {
            "category":"Professional",
            "subcategory":"Accounting & Tax Preparation",
            "type":"Services"
        }
    ],
    "sg:phone":"+1 203 359 2504",
    "sg:postcode":"06902",
    "sg:province":"CT",
    "sg:tags":[
        "pinball",
        "equipment",
        "billiard",
        "device",
        "rental",
        "jukebox"
    ],
    "sg:website":"http://www.amusementsunlimited.net",
    "wof:name":"Amusements Unlimited",
    "wof:placetype":"venue"
},
  "geometry": {"coordinates":[-73.527591,41.049494],"type":"Point"}
}