{
  "type": "Feature",
  "properties": {
    "iso:country":"US",
    "sg:address":"3550 Whitney Ave",
    "sg:city":"Hamden",
    "sg:classifiers":[
        {
            "category":"Personal",
            "subcategory":"Beauty Salon",
            "type":"Services"
        }
    ],
    "sg:phone":"+1   ",
    "sg:postcode":"06518",
    "sg:province":"CT",
    "sg:tags":[
        "chair",
        "design"
    ],
    "wof:name":"Studio Of Hair Design LLC",
    "wof:placetype":"venue"
},
  "geometry": {"coordinates":[-72.904659,41.42102],"type":"Point"}
}