{
  "type": "Feature",
  "properties": {
    "iso:country":"US",
    "sg:address":"342 Industrial Ave",
    "sg:city":"Cheshire",
    "sg:classifiers":[
        {
            "category":"Manufacturing",
            "subcategory":"Glass & Minerals",
            "type":"Manufacturing & Wholesale Goods"
        }
    ],
    "sg:phone":"+1 203 271 0647",
    "sg:postcode":"06410",
    "sg:province":"CT",
    "sg:tags":[
        "graphite"
    ],
    "wof:name":"CMS Graphite",
    "wof:placetype":"venue"
},
  "geometry": {"coordinates":[-72.90062399999999,41.537003],"type":"Point"}
}