{
  "type": "Feature",
  "properties": {
    "iso:country":"US",
    "sg:address":"191 Washington St",
    "sg:city":"Vernon Rockville",
    "sg:classifiers":[
        {
            "category":"Organizations",
            "subcategory":"Religious Organization",
            "type":"Services"
        }
    ],
    "sg:phone":"+1   ",
    "sg:postcode":"06066",
    "sg:province":"CT",
    "wof:name":"Evidence of Resurrection",
    "wof:placetype":"venue"
},
  "geometry": {"coordinates":[-72.48161399999999,41.820166],"type":"Point"}
}