{
  "type": "Feature",
  "properties": {
    "addr:full":"58 Asylum St New Haven CT 06519",
    "addr:housenumber":"58",
    "addr:postcode":"06519",
    "addr:street":"Asylum St",
    "iso:country":"US",
    "sg:address":"58 Asylum St",
    "sg:city":"New Haven",
    "sg:classifiers":[
        {
            "category":"Professional",
            "type":"Services"
        }
    ],
    "sg:phone":"+1 203 777 4498",
    "sg:postcode":"06519",
    "sg:province":"CT",
    "wof:name":"Josh Brown",
    "wof:placetype":"venue"
},
  "geometry": {"coordinates":[-72.940341,41.303918],"type":"Point"}
}