{
  "type": "Feature",
  "properties": {
    "addr:full":"1173 N Colony Rd Wallingford CT 06492",
    "addr:housenumber":"1173",
    "addr:postcode":"06492",
    "addr:street":"N Colony Rd",
    "iso:country":"US",
    "sg:address":"1173 N Colony Rd",
    "sg:city":"Wallingford",
    "sg:classifiers":[
        {
            "category":"Shopping",
            "subcategory":"Clothing, Apparel, & Fashions",
            "type":"Retail Goods"
        }
    ],
    "sg:phone":"+1 203 269 6400",
    "sg:postcode":"06492",
    "sg:province":"CT",
    "sg:tags":[
        "infant",
        "wear"
    ],
    "wof:name":"Kid's Outlet",
    "wof:placetype":"venue"
},
  "geometry": {"coordinates":[-72.810655,41.502181],"type":"Point"}
}