{
  "type": "Feature",
  "properties": {
    "iso:country":"US",
    "sg:address":"5718 Main St",
    "sg:city":"Trumbull",
    "sg:classifiers":[
        {
            "category":"Health Services",
            "subcategory":"Health Practitioner",
            "type":"Services"
        }
    ],
    "sg:phone":"+1 203 445 0845",
    "sg:postcode":"06611",
    "sg:province":"CT",
    "sg:tags":[
        "therapist",
        "physical"
    ],
    "wof:name":"Physical Therapy For Women PC",
    "wof:placetype":"venue"
},
  "geometry": {"coordinates":[-73.21982199999999,41.252099],"type":"Point"}
}