{
  "type": "Feature",
  "properties": {
    "addr:full":"161 Kings Hwy Exd Fairfield CT 06484",
    "addr:housenumber":"161",
    "addr:postcode":"06484",
    "addr:street":"Kings Hwy Exd",
    "iso:country":"US",
    "sg:address":"161 Kings Hwy Exd",
    "sg:city":"Fairfield",
    "sg:classifiers":[
        {
            "category":"Real Estate",
            "subcategory":"Real Estate Agent",
            "type":"Services"
        }
    ],
    "sg:phone":"+1 203 362 2855",
    "sg:postcode":"06484",
    "sg:province":"CT",
    "wof:name":"Home Shoppers Realty",
    "wof:placetype":"venue"
},
  "geometry": {"coordinates":[-73.112494,41.311654],"type":"Point"}
}