{
  "type": "Feature",
  "properties": {
    "addr:full":"3 Church St New Milford CT 06776",
    "addr:housenumber":"3",
    "addr:postcode":"06776",
    "addr:street":"Church St",
    "iso:country":"US",
    "sg:address":"3 Church St",
    "sg:city":"New Milford",
    "sg:classifiers":[
        {
            "category":"Shopping",
            "type":"Retail Goods"
        }
    ],
    "sg:phone":"+1 860 354 6575",
    "sg:postcode":"06776",
    "sg:province":"CT",
    "sg:tags":[
        "merchandise"
    ],
    "wof:name":"Hearing Aid Specialist",
    "wof:placetype":"venue"
},
  "geometry": {"coordinates":[-73.41078899999999,41.577843],"type":"Point"}
}