{
  "type": "Feature",
  "properties": {
    "addr:full":"69 Orland St Bridgeport CT 06605",
    "addr:housenumber":"69",
    "addr:postcode":"06605",
    "addr:street":"Orland St",
    "iso:country":"US",
    "sg:address":"69 Orland St",
    "sg:city":"Bridgeport",
    "sg:classifiers":[
        {
            "category":"Professional",
            "subcategory":"Lawyer & Legal Services",
            "type":"Services"
        }
    ],
    "sg:phone":"+1   ",
    "sg:postcode":"06605",
    "sg:province":"CT",
    "wof:name":"David H Dworski",
    "wof:placetype":"venue"
},
  "geometry": {"coordinates":[-73.219582,41.165379],"type":"Point"}
}