{
  "type": "Feature",
  "properties": {
    "iso:country":"US",
    "sg:address":"150 Marlborough St",
    "sg:city":"Portland",
    "sg:classifiers":[
        {
            "category":"Education",
            "subcategory":"Dance Studio",
            "type":"Public Place"
        }
    ],
    "sg:phone":"+1   ",
    "sg:postcode":"06480",
    "sg:province":"CT",
    "wof:name":"Encore Dance Studio",
    "wof:placetype":"venue"
},
  "geometry": {"coordinates":[-72.627793,41.568522],"type":"Point"}
}