{
  "type": "Feature",
  "properties": {
    "addr:full":"2580 Main St Stratford CT 06615",
    "addr:housenumber":"2580",
    "addr:postcode":"06615",
    "addr:street":"Main St",
    "iso:country":"US",
    "sg:address":"2580 Main St",
    "sg:city":"Stratford",
    "sg:classifiers":[
        {
            "category":"Real Estate",
            "subcategory":"Real Estate Operator",
            "type":"Services"
        }
    ],
    "sg:phone":"+1 203 375 8654",
    "sg:postcode":"06615",
    "sg:province":"CT",
    "sg:tags":[
        "owner",
        "building",
        "apartment"
    ],
    "wof:name":"Camelot Propties",
    "wof:placetype":"venue"
},
  "geometry": {"coordinates":[-73.13179599999999,41.194832],"type":"Point"}
}