{
  "type": "Feature",
  "properties": {
    "addr:full":"4 Clarks Ln Old Lyme CT 06371",
    "addr:housenumber":"4",
    "addr:postcode":"06371",
    "addr:street":"Clarks Ln",
    "iso:country":"US",
    "sg:address":"4 Clarks Ln",
    "sg:city":"Old Lyme",
    "sg:classifiers":[
        {
            "category":"Professional",
            "subcategory":"Business Services",
            "type":"Services"
        }
    ],
    "sg:phone":"+1   ",
    "sg:postcode":"06371",
    "sg:province":"CT",
    "wof:name":"International Office Centers",
    "wof:placetype":"venue"
},
  "geometry": {"coordinates":[-72.33308700000001,41.329858],"type":"Point"}
}