{
  "type": "Feature",
  "properties": {
    "addr:full":"1 Whitney Ave New Haven CT 06510",
    "addr:housenumber":"1",
    "addr:postcode":"06510",
    "addr:street":"Whitney Ave",
    "iso:country":"US",
    "sg:address":"1 Whitney Ave",
    "sg:city":"New Haven",
    "sg:classifiers":[
        {
            "category":"Bakery",
            "type":"Food & Drink"
        },
        {
            "category":"Coffee & Tea",
            "type":"Food & Drink"
        },
        {
            "category":"Bagels",
            "type":"Food & Drink"
        }
    ],
    "sg:menulink":"http://www.allmenus.com/ct/new-haven/25377-brueggers/menu/",
    "sg:phone":"+1 203 773 3199",
    "sg:postcode":"06510",
    "sg:province":"CT",
    "sg:tags":[
        "sandwich",
        "salad",
        "soup",
        "american",
        "pastry",
        "wrap"
    ],
    "wof:name":"Bruegger's",
    "wof:placetype":"venue"
},
  "geometry": {"coordinates":[-72.922556,41.310547],"type":"Point"}
}