{
  "type": "Feature",
  "properties": {
    "addr:full":"29 Forest St Stamford CT 06901",
    "addr:housenumber":"29",
    "addr:postcode":"06901",
    "addr:street":"Forest St",
    "iso:country":"US",
    "sg:address":"29 Forest St",
    "sg:city":"Stamford",
    "sg:classifiers":[
        {
            "category":"Social Services",
            "type":"Services"
        }
    ],
    "sg:phone":"+1   ",
    "sg:postcode":"06901",
    "sg:province":"CT",
    "sg:tags":[
        "adult",
        "day",
        "care"
    ],
    "wof:name":"Almost Family",
    "wof:placetype":"venue"
},
  "geometry": {"coordinates":[-73.537137,41.05688],"type":"Point"}
}