{
  "type": "Feature",
  "properties": {
    "iso:country":"US",
    "sg:address":"392 Naugatuck Ave",
    "sg:city":"Milford",
    "sg:classifiers":[
        {
            "category":"Autos & Motor Vehicles",
            "subcategory":"Automobile Sales",
            "type":"Retail Goods"
        }
    ],
    "sg:phone":"+1 203 878 4661",
    "sg:postcode":"06460",
    "sg:province":"CT",
    "sg:tags":[
        "new",
        "car"
    ],
    "wof:name":"Zee Buick",
    "wof:placetype":"venue"
},
  "geometry": {"coordinates":[-73.098056,41.19705],"type":"Point"}
}