{
  "type": "Feature",
  "properties": {
    "addr:full":"1 Salem St Hartford CT 06114",
    "addr:housenumber":"1",
    "addr:postcode":"06114",
    "addr:street":"Salem St",
    "iso:country":"US",
    "sg:address":"1 Salem St",
    "sg:city":"Hartford",
    "sg:classifiers":[
        {
            "category":"Personal",
            "subcategory":"Barber",
            "type":"Services"
        }
    ],
    "sg:phone":"+1   ",
    "sg:postcode":"06114",
    "sg:province":"CT",
    "sg:tags":[
        "shop"
    ],
    "wof:name":"Bank Lane Barber Shop",
    "wof:placetype":"venue"
},
  "geometry": {"coordinates":[-72.690169,41.730121],"type":"Point"}
}