{
  "type": "Feature",
  "properties": {
    "addr:full":"32 Lower Cross Rd Greenwich CT 06831",
    "addr:housenumber":"32",
    "addr:postcode":"06831",
    "addr:street":"Lower Cross Rd",
    "iso:country":"US",
    "sg:address":"32 Lower Cross Rd",
    "sg:city":"Greenwich",
    "sg:classifiers":[
        {
            "category":"Professional",
            "type":"Services"
        }
    ],
    "sg:phone":"+1 203 552 1680",
    "sg:postcode":"06831",
    "sg:province":"CT",
    "wof:name":"Alex Troy",
    "wof:placetype":"venue"
},
  "geometry": {"coordinates":[-73.640406,41.1121],"type":"Point"}
}