{
  "type": "Feature",
  "properties": {
    "addr:full":"115 Pond Hill Rd Wallingford CT 06492",
    "addr:housenumber":"115",
    "addr:postcode":"06492",
    "addr:street":"Pond Hill Rd",
    "iso:country":"US",
    "sg:address":"115 Pond Hill Rd",
    "sg:city":"Wallingford",
    "sg:classifiers":[
        {
            "category":"Organizations",
            "subcategory":"Religious Organization",
            "type":"Services"
        }
    ],
    "sg:phone":"+1 203 265 1694",
    "sg:postcode":"06492",
    "sg:province":"CT",
    "sg:tags":[
        "church"
    ],
    "wof:name":"Church of Ressurrection",
    "wof:placetype":"venue"
},
  "geometry": {"coordinates":[-72.81924600000001,41.433095],"type":"Point"}
}