{
  "type": "Feature",
  "properties": {
    "iso:country":"US",
    "sg:address":"25 Knowles Rd",
    "sg:city":"Middle Haddam",
    "sg:classifiers":[
        {
            "category":"Manufacturing",
            "subcategory":"Food",
            "type":"Manufacturing & Wholesale Goods"
        }
    ],
    "sg:phone":"+1 860 267 2097",
    "sg:postcode":"06456",
    "sg:province":"CT",
    "sg:tags":[
        "distributor",
        "coffee"
    ],
    "wof:name":"Java Distributors LLC",
    "wof:placetype":"venue"
},
  "geometry": {"coordinates":[-72.551996,41.550993],"type":"Point"}
}