{
  "type": "Feature",
  "properties": {
    "iso:country":"US",
    "sg:address":"55 McLennan Dr",
    "sg:city":"Oakville",
    "sg:classifiers":[
        {
            "category":"Professional",
            "subcategory":"Business Services",
            "type":"Services"
        }
    ],
    "sg:phone":"+1 860 274 6833",
    "sg:postcode":"06779",
    "sg:province":"CT",
    "sg:tags":[
        "specialty",
        "mfg"
    ],
    "wof:name":"Ram Arts Signs",
    "wof:placetype":"venue"
},
  "geometry": {"coordinates":[-73.076843,41.598244],"type":"Point"}
}