{
  "type": "Feature",
  "properties": {
    "iso:country":"US",
    "sg:address":"1770 Boston Post Rd",
    "sg:city":"Milford",
    "sg:classifiers":[
        {
            "category":"Home & Garden",
            "subcategory":"Furniture",
            "type":"Retail Goods"
        }
    ],
    "sg:phone":"+1 203 877 2337",
    "sg:postcode":"06460",
    "sg:province":"CT",
    "wof:name":"Trendsetter Contemporary Furn",
    "wof:placetype":"venue"
},
  "geometry": {"coordinates":[-73.022778,41.249562],"type":"Point"}
}