{
  "type": "Feature",
  "properties": {
    "addr:full":"14 Turkey Plain Rd Bethel CT 06801",
    "addr:housenumber":"14",
    "addr:postcode":"06801",
    "addr:street":"Turkey Plain Rd",
    "iso:country":"US",
    "sg:address":"14 Turkey Plain Rd",
    "sg:city":"Bethel",
    "sg:classifiers":[
        {
            "category":"Retail",
            "subcategory":"Auto Repair",
            "type":"Services"
        }
    ],
    "sg:phone":"+1 203 743 9122",
    "sg:postcode":"06801",
    "sg:province":"CT",
    "sg:tags":[
        "body",
        "automobile",
        "painting"
    ],
    "wof:name":"Smitty's Auto Body",
    "wof:placetype":"venue"
},
  "geometry": {"coordinates":[-73.413934,41.351493],"type":"Point"}
}