{
  "type": "Feature",
  "properties": {
    "iso:country":"US",
    "sg:address":"1201 Boston Post Rd",
    "sg:city":"Milford",
    "sg:classifiers":[
        {
            "category":"Bakery",
            "type":"Food & Drink"
        }
    ],
    "sg:menulink":"http://www.allmenus.com/ct/milford/235694-pretzel-time/menu/",
    "sg:phone":"+1 203 877 5269",
    "sg:postcode":"06460",
    "sg:province":"CT",
    "sg:tags":[
        "new",
        "american",
        "pastry"
    ],
    "wof:name":"Pretzel Time",
    "wof:placetype":"venue"
},
  "geometry": {"coordinates":[-73.038588,41.236565],"type":"Point"}
}