{
  "type": "Feature",
  "properties": {
    "iso:country":"US",
    "sg:address":"148 Amity Rd",
    "sg:city":"New Haven",
    "sg:classifiers":[
        {
            "category":"Sports & Exercise",
            "subcategory":"Gym",
            "type":"Entertainment"
        }
    ],
    "sg:phone":"+1   ",
    "sg:postcode":"06515",
    "sg:province":"CT",
    "sg:tags":[
        "fitness",
        "physical",
        "facility"
    ],
    "wof:name":"Island Sun Tanning & Day Spa L",
    "wof:placetype":"venue"
},
  "geometry": {"coordinates":[-72.97986299999999,41.338073],"type":"Point"}
}