{
  "type": "Feature",
  "properties": {
    "addr:full":"27 Main St Stamford CT 06901",
    "addr:housenumber":"27",
    "addr:postcode":"06901",
    "addr:street":"Main St",
    "iso:country":"US",
    "sg:address":"27 Main St",
    "sg:city":"Stamford",
    "sg:classifiers":[
        {
            "category":"Shopping",
            "type":"Retail Goods"
        }
    ],
    "sg:phone":"+1 203 921 2622",
    "sg:postcode":"06901",
    "sg:province":"CT",
    "sg:tags":[
        "cosmetic",
        "perfume"
    ],
    "wof:name":"Glorias' Beauty Supply",
    "wof:placetype":"venue"
},
  "geometry": {"coordinates":[-73.54513300000001,41.052271],"type":"Point"}
}