{
  "type": "Feature",
  "properties": {
    "iso:country":"US",
    "sg:address":"20 Eastwood Rd",
    "sg:city":"Storrs Mansfield",
    "sg:classifiers":[
        {
            "category":"Professional",
            "subcategory":"Management & Consulting",
            "type":"Services"
        }
    ],
    "sg:phone":"+1   ",
    "sg:postcode":"06268",
    "sg:province":"CT",
    "wof:name":"Poultry Perspective",
    "wof:placetype":"venue"
},
  "geometry": {"coordinates":[-72.246908,41.798433],"type":"Point"}
}