{
  "type": "Feature",
  "properties": {
    "addr:full":"27 Rushleigh Rd Hartford CT 06117",
    "addr:housenumber":"27",
    "addr:postcode":"06117",
    "addr:street":"Rushleigh Rd",
    "iso:country":"US",
    "sg:address":"27 Rushleigh Rd",
    "sg:city":"Hartford",
    "sg:classifiers":[
        {
            "category":"Travel",
            "subcategory":"Travel Agent",
            "type":"Entertainment"
        }
    ],
    "sg:phone":"+1 860 561 3272",
    "sg:postcode":"06117",
    "sg:province":"CT",
    "sg:tags":[
        "operator",
        "tour"
    ],
    "wof:name":"Goode Tours LLC",
    "wof:placetype":"venue"
},
  "geometry": {"coordinates":[-72.777394,41.778955],"type":"Point"}
}