{
  "type": "Feature",
  "properties": {
    "addr:full":"1122 E Main St Stamford CT 06902",
    "addr:housenumber":"1122",
    "addr:postcode":"06902",
    "addr:street":"E Main St",
    "iso:country":"US",
    "sg:address":"1122 E Main St",
    "sg:city":"Stamford",
    "sg:classifiers":[
        {
            "category":"Education",
            "subcategory":"Dance Studio",
            "type":"Public Place"
        }
    ],
    "sg:phone":"+1 203 975 2850",
    "sg:postcode":"06902",
    "sg:province":"CT",
    "sg:tags":[
        "instruction",
        "dancing"
    ],
    "wof:name":"Jennifer Wiesner Dance LLC",
    "wof:placetype":"venue"
},
  "geometry": {"coordinates":[-73.513684,41.058255],"type":"Point"}
}