{
  "type": "Feature",
  "properties": {
    "addr:full":"701 Farmington Ave New Britain CT 06053",
    "addr:housenumber":"701",
    "addr:postcode":"06053",
    "addr:street":"Farmington Ave",
    "iso:country":"US",
    "sg:address":"701 Farmington Ave",
    "sg:city":"New Britain",
    "sg:classifiers":[
        {
            "category":"Bakery",
            "type":"Food & Drink"
        },
        {
            "category":"Coffee & Tea",
            "type":"Food & Drink"
        },
        {
            "category":"Bagels",
            "type":"Food & Drink"
        },
        {
            "category":"Donuts",
            "type":"Food & Drink"
        }
    ],
    "sg:menulink":"http://www.allmenus.com/ct/new-britain/129954-dunkin-donuts/menu/",
    "sg:phone":"+1 860 223 8155",
    "sg:postcode":"06053",
    "sg:province":"CT",
    "sg:tags":[
        "american",
        "diner",
        "pastry"
    ],
    "wof:name":"Dunkin' Donuts",
    "wof:placetype":"venue"
},
  "geometry": {"coordinates":[-72.791105,41.696839],"type":"Point"}
}