{
  "type": "Feature",
  "properties": {
    "addr:full":"7 Old Schoolhouse Rd Prospect CT 06712",
    "addr:housenumber":"7",
    "addr:postcode":"06712",
    "addr:street":"Old Schoolhouse Rd",
    "iso:country":"US",
    "sg:address":"7 Old Schoolhouse Rd",
    "sg:city":"Prospect",
    "sg:classifiers":[
        {
            "category":"Personal",
            "subcategory":"Barber",
            "type":"Services"
        }
    ],
    "sg:phone":"+1   ",
    "sg:postcode":"06712",
    "sg:province":"CT",
    "sg:tags":[
        "shop"
    ],
    "wof:name":"Prospect Barber Shop",
    "wof:placetype":"venue"
},
  "geometry": {"coordinates":[-72.982161,41.505313],"type":"Point"}
}