{
  "type": "Feature",
  "properties": {
    "iso:country":"US",
    "sg:address":"49 Penn Dr",
    "sg:city":"Hartford",
    "sg:classifiers":[
        {
            "category":"Building & Trades",
            "subcategory":"Construction",
            "type":"Services"
        }
    ],
    "sg:phone":"+1 860 529 4000",
    "sg:postcode":"06119",
    "sg:province":"CT",
    "sg:tags":[
        "hanging",
        "contractor"
    ],
    "wof:name":"Connecticut Home Services",
    "wof:placetype":"venue"
},
  "geometry": {"coordinates":[-72.73294799999999,41.771969],"type":"Point"}
}