{
  "type": "Feature",
  "properties": {
    "iso:country":"US",
    "sg:address":"124 S Main St",
    "sg:city":"Cheshire",
    "sg:classifiers":[
        {
            "category":"Shopping",
            "subcategory":"Clothing, Apparel, & Fashions",
            "type":"Retail Goods"
        }
    ],
    "sg:phone":"+1 203 272 2685",
    "sg:postcode":"06410",
    "sg:province":"CT",
    "sg:tags":[
        "garment"
    ],
    "wof:name":"Le Femme Apparel",
    "wof:placetype":"venue"
},
  "geometry": {"coordinates":[-72.902249,41.497122],"type":"Point"}
}