{
  "type": "Feature",
  "properties": {
    "iso:country":"US",
    "sg:address":"474 Main St",
    "sg:city":"Monroe",
    "sg:classifiers":[
        {
            "category":"Building & Trades",
            "subcategory":"Landscaping Services",
            "type":"Services"
        }
    ],
    "sg:phone":"+1 203 268 6964",
    "sg:postcode":"06468",
    "sg:province":"CT",
    "sg:tags":[
        "landscape",
        "contractor"
    ],
    "wof:name":"Tlc Tree Landscape Care",
    "wof:placetype":"venue"
},
  "geometry": {"coordinates":[-73.26672600000001,41.324413],"type":"Point"}
}