{
  "type": "Feature",
  "properties": {
    "iso:country":"US",
    "sg:address":"1438 Park Ave",
    "sg:city":"Bridgeport",
    "sg:classifiers":[
        {
            "category":"Social Services",
            "type":"Services"
        }
    ],
    "sg:phone":"+1 203 333 4105",
    "sg:postcode":"06604",
    "sg:province":"CT",
    "sg:tags":[
        "organization",
        "welfare"
    ],
    "wof:name":"Regional Adolescent Program",
    "wof:placetype":"venue"
},
  "geometry": {"coordinates":[-73.203829,41.180326],"type":"Point"}
}