{
  "type": "Feature",
  "properties": {
    "iso:country":"US",
    "sg:address":"153 S Main St",
    "sg:city":"Newtown",
    "sg:classifiers":[
        {
            "category":"Banks & Credit Unions",
            "subcategory":"Investment Brokerage",
            "type":"Services"
        },
        {
            "category":"Professional",
            "subcategory":"Management & Consulting",
            "type":"Services"
        }
    ],
    "sg:phone":"+1 203 270 4664",
    "sg:postcode":"06470",
    "sg:province":"CT",
    "sg:tags":[
        "consultant",
        "planning",
        "financial"
    ],
    "wof:name":"Wellfleet Financial Services",
    "wof:placetype":"venue"
},
  "geometry": {"coordinates":[-73.28501900000001,41.386069],"type":"Point"}
}