{
  "type": "Feature",
  "properties": {
    "addr:full":"163 Webster Ct Newington CT 06111",
    "addr:housenumber":"163",
    "addr:postcode":"06111",
    "addr:street":"Webster Ct",
    "iso:country":"US",
    "sg:address":"163 Webster Ct",
    "sg:city":"Newington",
    "sg:classifiers":[
        {
            "category":"Professional",
            "subcategory":"Business Services",
            "type":"Services"
        }
    ],
    "sg:phone":"+1   ",
    "sg:postcode":"06111",
    "sg:province":"CT",
    "wof:name":"Deleon Services LLC",
    "wof:placetype":"venue"
},
  "geometry": {"coordinates":[-72.722977,41.653851],"type":"Point"}
}