{
  "type": "Feature",
  "properties": {
    "addr:full":"105 Sanford St Hamden CT 06514",
    "addr:housenumber":"105",
    "addr:postcode":"06514",
    "addr:street":"Sanford St",
    "iso:country":"US",
    "sg:address":"105 Sanford St",
    "sg:city":"Hamden",
    "sg:classifiers":[
        {
            "category":"Professional",
            "subcategory":"Accounting & Tax Preparation",
            "type":"Services"
        }
    ],
    "sg:phone":"+1 203 230 1040",
    "sg:postcode":"06514",
    "sg:province":"CT",
    "sg:tags":[
        "accountant"
    ],
    "wof:name":"Howard G Gold CPA",
    "wof:placetype":"venue"
},
  "geometry": {"coordinates":[-72.91565199999999,41.381784],"type":"Point"}
}