{
  "type": "Feature",
  "properties": {
    "iso:country":"US",
    "sg:address":"5 Rabbit Trl",
    "sg:city":"Burlington",
    "sg:classifiers":[
        {
            "category":"Professional",
            "subcategory":"Secretarial Services",
            "type":"Services"
        }
    ],
    "sg:phone":"+1   ",
    "sg:postcode":"06013",
    "sg:province":"CT",
    "sg:tags":[
        "reporting"
    ],
    "wof:name":"Roxanne Sessions",
    "wof:placetype":"venue"
},
  "geometry": {"coordinates":[-73.00726,41.78556],"type":"Point"}
}