{
  "type": "Feature",
  "properties": {
    "addr:full":"254 Old Post Rd Fairfield CT 06413",
    "addr:housenumber":"254",
    "addr:postcode":"06413",
    "addr:street":"Old Post Rd",
    "iso:country":"US",
    "sg:address":"254 Old Post Rd",
    "sg:city":"Fairfield",
    "sg:classifiers":[
        {
            "category":"Personal",
            "subcategory":"Beauty Salon",
            "type":"Services"
        }
    ],
    "sg:phone":"+1 203 259 6261",
    "sg:postcode":"06413",
    "sg:province":"CT",
    "wof:name":"Scissors",
    "wof:placetype":"venue"
},
  "geometry": {"coordinates":[-72.492649,41.286728],"type":"Point"}
}