{
  "type": "Feature",
  "properties": {
    "addr:full":"244 White St Danbury CT 06810",
    "addr:housenumber":"244",
    "addr:postcode":"06810",
    "addr:street":"White St",
    "iso:country":"US",
    "sg:address":"244 White St",
    "sg:city":"Danbury",
    "sg:classifiers":[
        {
            "category":"Shopping",
            "subcategory":"Clothing, Apparel, & Fashions",
            "type":"Retail Goods"
        }
    ],
    "sg:phone":"+1 203 778 1331",
    "sg:postcode":"06810",
    "sg:province":"CT",
    "sg:tags":[
        "t"
    ],
    "wof:name":"T-Shirt Express",
    "wof:placetype":"venue"
},
  "geometry": {"coordinates":[-73.439566,41.399993],"type":"Point"}
}