{
  "type": "Feature",
  "properties": {
    "iso:country":"US",
    "sg:address":"140 S Main St",
    "sg:city":"East Windsor",
    "sg:classifiers":[
        {
            "category":"Retail",
            "subcategory":"Auto Repair",
            "type":"Services"
        }
    ],
    "sg:phone":"+1   ",
    "sg:postcode":"06088",
    "sg:province":"CT",
    "sg:tags":[
        "shop",
        "automotive"
    ],
    "wof:name":"Roberts Auto Service",
    "wof:placetype":"venue"
},
  "geometry": {"coordinates":[-72.60806599999999,41.888846],"type":"Point"}
}