{
  "type": "Feature",
  "properties": {
    "iso:country":"US",
    "sg:address":"452 South Rd",
    "sg:city":"Somers",
    "sg:classifiers":[
        {
            "category":"Recreation",
            "type":"Entertainment"
        }
    ],
    "sg:phone":"+1 860 749 0400",
    "sg:postcode":"06071",
    "sg:province":"CT",
    "sg:tags":[
        "real",
        "mini",
        "golf",
        "driving",
        "lessor",
        "course",
        "range",
        "es"
    ],
    "wof:name":"Pleasant View Golf Center",
    "wof:placetype":"venue"
},
  "geometry": {"coordinates":[-72.444225,41.958806],"type":"Point"}
}