{
  "type": "Feature",
  "properties": {
    "addr:full":"4 Daniel St Milford CT 06460",
    "addr:housenumber":"4",
    "addr:postcode":"06460",
    "addr:street":"Daniel St",
    "iso:country":"US",
    "sg:address":"4 Daniel St",
    "sg:city":"Milford",
    "sg:classifiers":[
        {
            "category":"Shopping",
            "subcategory":"Gifts & Souvenirs",
            "type":"Retail Goods"
        }
    ],
    "sg:phone":"+1 203 878 2625",
    "sg:postcode":"06460",
    "sg:province":"CT",
    "sg:tags":[
        "shop"
    ],
    "wof:name":"Given To Gauche",
    "wof:placetype":"venue"
},
  "geometry": {"coordinates":[-73.056653,41.223142],"type":"Point"}
}