{
  "type": "Feature",
  "properties": {
    "addr:full":"587 Elm St Stamford CT 06902",
    "addr:housenumber":"587",
    "addr:postcode":"06902",
    "addr:street":"Elm St",
    "iso:country":"US",
    "sg:address":"587 Elm St",
    "sg:city":"Stamford",
    "sg:classifiers":[
        {
            "category":"Food & Beverages",
            "subcategory":"Liquor & Beverages",
            "type":"Retail Goods"
        }
    ],
    "sg:phone":"+1 203 324 5988",
    "sg:postcode":"06902",
    "sg:province":"CT",
    "wof:name":"Three Seas Liquors",
    "wof:placetype":"venue"
},
  "geometry": {"coordinates":[-73.525476,41.049312],"type":"Point"}
}