{
  "type": "Feature",
  "properties": {
    "addr:full":"851 W Main St Meriden CT 06451",
    "addr:housenumber":"851",
    "addr:postcode":"06451",
    "addr:street":"W Main St",
    "iso:country":"US",
    "sg:address":"851 W Main St",
    "sg:city":"Meriden",
    "sg:classifiers":[
        {
            "category":"Retail",
            "subcategory":"Auto Repair",
            "type":"Services"
        }
    ],
    "sg:phone":"+1   ",
    "sg:postcode":"06451",
    "sg:province":"CT",
    "wof:name":"Parkside Motors",
    "wof:placetype":"venue"
},
  "geometry": {"coordinates":[-72.83135799999999,41.545898],"type":"Point"}
}