{
  "type": "Feature",
  "properties": {
    "iso:country":"US",
    "sg:address":"5 Robin Ct",
    "sg:city":"Fairfield",
    "sg:classifiers":[
        {
            "category":"Utilities",
            "subcategory":"Refuse",
            "type":"Services"
        }
    ],
    "sg:phone":"+1 203 368 6274",
    "sg:postcode":"06473",
    "sg:province":"CT",
    "sg:tags":[
        "garbage",
        "collection"
    ],
    "wof:name":"Conn Assoc Sanitation Haulers",
    "wof:placetype":"venue"
},
  "geometry": {"coordinates":[-72.839991,41.408772],"type":"Point"}
}