{
  "type": "Feature",
  "properties": {
    "addr:full":"34 Collimore Rd East Hartford CT 06108",
    "addr:housenumber":"34",
    "addr:postcode":"06108",
    "addr:street":"Collimore Rd East;Ct",
    "iso:country":"US",
    "sg:address":"34 Collimore Rd",
    "sg:city":"East Hartford",
    "sg:classifiers":[
        {
            "category":"Retail",
            "subcategory":"Repair Shop",
            "type":"Services"
        }
    ],
    "sg:phone":"+1   ",
    "sg:postcode":"06108",
    "sg:province":"CT",
    "wof:name":"Office Seating Service Co",
    "wof:placetype":"venue"
},
  "geometry": {"coordinates":[-72.626311,41.795093],"type":"Point"}
}