{
  "type": "Feature",
  "properties": {
    "iso:country":"US",
    "sg:address":"273 Whisconier Rd",
    "sg:city":"Brookfield",
    "sg:classifiers":[
        {
            "category":"Food & Beverages",
            "subcategory":"Groceries & Convenience Stores",
            "type":"Retail Goods"
        }
    ],
    "sg:phone":"+1 203 775 9373",
    "sg:postcode":"06804",
    "sg:province":"CT",
    "sg:tags":[
        "grocer"
    ],
    "wof:name":"Brookfield Market",
    "wof:placetype":"venue"
},
  "geometry": {"coordinates":[-73.40687699999999,41.48139],"type":"Point"}
}