{
  "type": "Feature",
  "properties": {
    "addr:full":"107 West Ave Stamford CT 06902",
    "addr:housenumber":"107",
    "addr:postcode":"06902",
    "addr:street":"West Ave",
    "iso:country":"US",
    "sg:address":"107 West Ave",
    "sg:city":"Stamford",
    "sg:classifiers":[
        {
            "category":"Recreation",
            "type":"Entertainment"
        },
        {
            "category":"Organizations",
            "subcategory":"Community Association",
            "type":"Services"
        }
    ],
    "sg:phone":"+1 203 323 4252",
    "sg:postcode":"06902",
    "sg:province":"CT",
    "sg:tags":[
        "club",
        "membership"
    ],
    "wof:name":"San Manghese Social Club Inc",
    "wof:placetype":"venue"
},
  "geometry": {"coordinates":[-73.55774,41.049732],"type":"Point"}
}