{
  "type": "Feature",
  "properties": {
    "addr:full":"801 Terryville Ave Bristol CT 06010",
    "addr:housenumber":"801",
    "addr:postcode":"06010",
    "addr:street":"Terryville Ave Bristol Ct",
    "iso:country":"US",
    "sg:address":"801 Terryville Ave",
    "sg:city":"Bristol",
    "sg:classifiers":[
        {
            "category":"Professional",
            "subcategory":"Business Services",
            "type":"Services"
        }
    ],
    "sg:phone":"+1   ",
    "sg:postcode":"06010",
    "sg:province":"CT",
    "wof:name":"Rose Garden Florist",
    "wof:placetype":"venue"
},
  "geometry": {"coordinates":[-72.979117,41.681132],"type":"Point"}
}