{
  "type": "Feature",
  "properties": {
    "addr:full":"22 High St Farmington CT 06032",
    "addr:housenumber":"22",
    "addr:postcode":"06032",
    "addr:street":"High St",
    "iso:country":"US",
    "sg:address":"22 High St",
    "sg:city":"Farmington",
    "sg:classifiers":[
        {
            "category":"Professional",
            "subcategory":"Management & Consulting",
            "type":"Services"
        }
    ],
    "sg:phone":"+1   ",
    "sg:postcode":"06032",
    "sg:province":"CT",
    "sg:tags":[
        "business"
    ],
    "wof:name":"Leach Consulting Company LLC",
    "wof:placetype":"venue"
},
  "geometry": {"coordinates":[-72.825869,41.721237],"type":"Point"}
}