{
  "type": "Feature",
  "properties": {
    "addr:full":"1056 Main St Branford CT 06405",
    "addr:housenumber":"1056",
    "addr:postcode":"06405",
    "addr:street":"Main St",
    "iso:country":"US",
    "sg:address":"1056 Main St",
    "sg:city":"Branford",
    "sg:classifiers":[
        {
            "category":"Personal",
            "subcategory":"Beauty Salon",
            "type":"Services"
        }
    ],
    "sg:phone":"+1   ",
    "sg:postcode":"06405",
    "sg:province":"CT",
    "sg:tags":[
        "nail"
    ],
    "wof:name":"Sera Nails",
    "wof:placetype":"venue"
},
  "geometry": {"coordinates":[-72.810962,41.282116],"type":"Point"}
}