{
  "type": "Feature",
  "properties": {
    "addr:full":"110 Broad St Danielson CT 06239",
    "addr:housenumber":"110",
    "addr:postcode":"06239",
    "addr:street":"Broad St",
    "iso:country":"US",
    "sg:address":"110 Broad St",
    "sg:city":"Danielson",
    "sg:classifiers":[
        {
            "category":"Health Services",
            "subcategory":"Chiropractor",
            "type":"Services"
        }
    ],
    "sg:phone":"+1   ",
    "sg:postcode":"06239",
    "sg:province":"CT",
    "wof:name":"Digregorio Philip J Dr",
    "wof:placetype":"venue"
},
  "geometry": {"coordinates":[-71.88025,41.801871],"type":"Point"}
}