{
  "type": "Feature",
  "properties": {
    "addr:full":"2 Commercial Pkwy Branford CT 06405",
    "addr:housenumber":"2",
    "addr:postcode":"06405",
    "addr:street":"Commercial Pkwy;Ct",
    "iso:country":"US",
    "sg:address":"2 Commercial Pkwy",
    "sg:city":"Branford",
    "sg:classifiers":[
        {
            "category":"Personal",
            "subcategory":"Beauty Salon",
            "type":"Services"
        }
    ],
    "sg:phone":"+1 203 481 0504",
    "sg:postcode":"06405",
    "sg:province":"CT",
    "sg:tags":[
        "shop",
        "manicuring"
    ],
    "wof:name":"Modern Nails",
    "wof:placetype":"venue"
},
  "geometry": {"coordinates":[-72.83140299999999,41.279641],"type":"Point"}
}