{
  "type": "Feature",
  "properties": {
    "iso:country":"US",
    "sg:address":"24 Rose Park Ave",
    "sg:city":"Stamford",
    "sg:classifiers":[
        {
            "category":"Professional",
            "subcategory":"Lawyer & Legal Services",
            "type":"Services"
        }
    ],
    "sg:phone":"+1 203 570 0268",
    "sg:postcode":"06902",
    "sg:province":"CT",
    "sg:tags":[
        "plan"
    ],
    "wof:name":"Pre-Paid Legal Svc",
    "wof:placetype":"venue"
},
  "geometry": {"coordinates":[-73.54788600000001,41.049886],"type":"Point"}
}