{
  "type": "Feature",
  "properties": {
    "iso:country":"US",
    "sg:address":"22 Church Hill Rd",
    "sg:city":"Newtown",
    "sg:classifiers":[
        {
            "category":"Shopping",
            "subcategory":"Tobacco",
            "type":"Retail Goods"
        },
        {
            "category":"Autos & Motor Vehicles",
            "subcategory":"Fuel & Gas Station",
            "type":"Retail Goods"
        }
    ],
    "sg:phone":"+1 203 426 0300",
    "sg:postcode":"06470",
    "sg:province":"CT",
    "sg:tags":[
        "cigarette",
        "convenience",
        "cigar",
        "dealer",
        "store"
    ],
    "wof:name":"Newtown Convenience Store",
    "wof:placetype":"venue"
},
  "geometry": {"coordinates":[-73.300749,41.414782],"type":"Point"}
}