{
  "type": "Feature",
  "properties": {
    "iso:country":"US",
    "sg:address":"83 Carrington Ave",
    "sg:city":"Milford",
    "sg:classifiers":[
        {
            "category":"Professional",
            "subcategory":"Business Services",
            "type":"Services"
        }
    ],
    "sg:phone":"+1   ",
    "sg:postcode":"06460",
    "sg:province":"CT",
    "wof:name":"Aymara Property Group",
    "wof:placetype":"venue"
},
  "geometry": {"coordinates":[-73.05267499999999,41.217027],"type":"Point"}
}