{
  "type": "Feature",
  "properties": {
    "addr:full":"299 Sturges Hwy Westport CT 06880",
    "addr:housenumber":"299",
    "addr:postcode":"06880",
    "addr:street":"Sturges Hwy Westport Ct",
    "iso:country":"US",
    "sg:address":"299 Sturges Hwy",
    "sg:city":"Westport",
    "sg:classifiers":[
        {
            "category":"Professional",
            "type":"Services"
        }
    ],
    "sg:phone":"+1 203 341 8646",
    "sg:postcode":"06880",
    "sg:province":"CT",
    "wof:name":"Charles Hellman",
    "wof:placetype":"venue"
},
  "geometry": {"coordinates":[-73.33632,41.191598],"type":"Point"}
}