{
  "type": "Feature",
  "properties": {
    "addr:full":"43 W Washington St Bristol CT 06010",
    "addr:housenumber":"43",
    "addr:postcode":"06010",
    "addr:street":"W Washington St",
    "iso:country":"US",
    "sg:address":"43 W Washington St",
    "sg:city":"Bristol",
    "sg:classifiers":[
        {
            "category":"Utilities",
            "subcategory":"Refuse",
            "type":"Services"
        }
    ],
    "sg:phone":"+1 860 585 8724",
    "sg:postcode":"06010",
    "sg:province":"CT",
    "sg:tags":[
        "system"
    ],
    "wof:name":"BFI",
    "wof:placetype":"venue"
},
  "geometry": {"coordinates":[-72.90871199999999,41.677231],"type":"Point"}
}