{
  "type": "Feature",
  "properties": {
    "addr:full":"544 New Park Ave Hartford CT 06110",
    "addr:housenumber":"544",
    "addr:postcode":"06110",
    "addr:street":"New Park Ave;Ct",
    "iso:country":"US",
    "sg:address":"544 New Park Ave",
    "sg:city":"Hartford",
    "sg:classifiers":[
        {
            "category":"Manufacturing",
            "subcategory":"Food",
            "type":"Manufacturing & Wholesale Goods"
        }
    ],
    "sg:phone":"+1 860 523 4003",
    "sg:postcode":"06110",
    "sg:province":"CT",
    "sg:tags":[
        "product",
        "mfg"
    ],
    "wof:name":"Wonder Hostess Bakery Outlet",
    "wof:placetype":"venue"
},
  "geometry": {"coordinates":[-72.720692,41.73748],"type":"Point"}
}