{
  "type": "Feature",
  "properties": {
    "iso:country":"US",
    "sg:address":"24 Katonne Ave",
    "sg:city":"Waterbury",
    "sg:classifiers":[
        {
            "category":"Professional",
            "subcategory":"Art Services",
            "type":"Services"
        }
    ],
    "sg:phone":"+1   ",
    "sg:postcode":"06710",
    "sg:province":"CT",
    "sg:tags":[
        "commercial",
        "design",
        "publishing"
    ],
    "wof:name":"Anl Graphic Design",
    "wof:placetype":"venue"
},
  "geometry": {"coordinates":[-73.042795,41.570622],"type":"Point"}
}