{
  "type": "Feature",
  "properties": {
    "iso:country":"US",
    "sg:address":"191 Middlesex Ave",
    "sg:city":"Chester",
    "sg:classifiers":[
        {
            "category":"Personal",
            "type":"Services"
        },
        {
            "category":"Retail",
            "subcategory":"Laundry & Dry Cleaning",
            "type":"Services"
        }
    ],
    "sg:phone":"+1 860 526 4077",
    "sg:postcode":"06412",
    "sg:province":"CT",
    "sg:tags":[
        "sewing",
        "alteration"
    ],
    "wof:name":"Reliable Cleaners & Tailoring",
    "wof:placetype":"venue"
},
  "geometry": {"coordinates":[-72.439903,41.411301],"type":"Point"}
}