{
  "type": "Feature",
  "properties": {
    "iso:country":"US",
    "sg:address":"340 Broad St",
    "sg:city":"Windsor",
    "sg:classifiers":[
        {
            "category":"Health Services",
            "subcategory":"Doctor",
            "type":"Services"
        }
    ],
    "sg:phone":"+1 860 688 8888",
    "sg:postcode":"06095",
    "sg:province":"CT",
    "sg:tags":[
        "physician",
        "family",
        "medical",
        "practice",
        "surgeons",
        "medicine"
    ],
    "wof:name":"Total Medical Care",
    "wof:placetype":"venue"
},
  "geometry": {"coordinates":[-72.645248,41.848869],"type":"Point"}
}