{
  "type": "Feature",
  "properties": {
    "addr:full":"185 N Main St Winsted CT 06098",
    "addr:housenumber":"185",
    "addr:postcode":"06098",
    "addr:street":"N Main St",
    "iso:country":"US",
    "sg:address":"185 N Main St",
    "sg:city":"Winsted",
    "sg:classifiers":[
        {
            "category":"Professional",
            "subcategory":"Engineering",
            "type":"Services"
        }
    ],
    "sg:phone":"+1   ",
    "sg:postcode":"06098",
    "sg:province":"CT",
    "wof:name":"Ajaks Engineering  LLC",
    "wof:placetype":"venue"
},
  "geometry": {"coordinates":[-73.059832,41.925558],"type":"Point"}
}