{
  "type": "Feature",
  "properties": {
    "addr:full":"4 3rd St Norwalk CT 06855",
    "addr:housenumber":"4",
    "addr:postcode":"06855",
    "addr:street":"3Rd St",
    "iso:country":"US",
    "sg:address":"4 3rd St",
    "sg:city":"Norwalk",
    "sg:classifiers":[
        {
            "category":"Building & Trades",
            "subcategory":"Landscaping Services",
            "type":"Services"
        }
    ],
    "sg:phone":"+1 203 854 4721",
    "sg:postcode":"06855",
    "sg:province":"CT",
    "sg:tags":[
        "designer",
        "landscape"
    ],
    "wof:name":"Malagisi Landscaping",
    "wof:placetype":"venue"
},
  "geometry": {"coordinates":[-73.400003,41.097003],"type":"Point"}
}