{
  "type": "Feature",
  "properties": {
    "iso:country":"US",
    "sg:address":"186 West St",
    "sg:city":"Bristol",
    "sg:classifiers":[
        {
            "category":"Building & Trades",
            "subcategory":"Plumbing",
            "type":"Services"
        }
    ],
    "sg:phone":"+1 860 584 0012",
    "sg:postcode":"06010",
    "sg:province":"CT",
    "sg:tags":[
        "contractor"
    ],
    "wof:name":"Positano Plumbing Inc",
    "wof:placetype":"venue"
},
  "geometry": {"coordinates":[-72.949686,41.672626],"type":"Point"}
}