{
  "type": "Feature",
  "properties": {
    "addr:full":"307 Biehl Rd Hamden CT 06518",
    "addr:housenumber":"307",
    "addr:postcode":"06518",
    "addr:street":"Biehl Rd",
    "iso:country":"US",
    "sg:address":"307 Biehl Rd",
    "sg:city":"Hamden",
    "sg:classifiers":[
        {
            "category":"Recreation",
            "type":"Entertainment"
        }
    ],
    "sg:phone":"+1   ",
    "sg:postcode":"06518",
    "sg:province":"CT",
    "wof:name":"Needham Karate Academy LLC",
    "wof:placetype":"venue"
},
  "geometry": {"coordinates":[-72.910977,41.401542],"type":"Point"}
}