{
  "type": "Feature",
  "properties": {
    "addr:full":"101 W Prospect St West Haven CT 06516",
    "addr:housenumber":"101",
    "addr:postcode":"06516",
    "addr:street":"W Prospect St;Haven",
    "iso:country":"US",
    "sg:address":"101 W Prospect St",
    "sg:city":"West Haven",
    "sg:classifiers":[
        {
            "category":"Freight",
            "type":"Transportation"
        }
    ],
    "sg:phone":"+1 203 937 5958",
    "sg:postcode":"06516",
    "sg:province":"CT",
    "wof:name":"Saafco Inc",
    "wof:placetype":"venue"
},
  "geometry": {"coordinates":[-72.962727,41.276175],"type":"Point"}
}