{
  "type": "Feature",
  "properties": {
    "addr:full":"180 Peck Hill Rd Woodbridge CT 06525",
    "addr:housenumber":"180",
    "addr:postcode":"06525",
    "addr:street":"Peck Hill Rd",
    "iso:country":"US",
    "sg:address":"180 Peck Hill Rd",
    "sg:city":"Woodbridge",
    "sg:classifiers":[
        {
            "category":"Arts & Performance",
            "subcategory":"Theater",
            "type":"Entertainment"
        }
    ],
    "sg:phone":"+1   ",
    "sg:postcode":"06525",
    "sg:province":"CT",
    "sg:tags":[
        "group"
    ],
    "wof:name":"Metroland Limited",
    "wof:placetype":"venue"
},
  "geometry": {"coordinates":[-73.03645400000001,41.376188],"type":"Point"}
}