{
  "type": "Feature",
  "properties": {
    "iso:country":"US",
    "sg:address":"2320 Main St",
    "sg:city":"Bridgeport",
    "sg:classifiers":[
        {
            "category":"Retail",
            "subcategory":"Repair Shop",
            "type":"Services"
        }
    ],
    "sg:phone":"+1 203 335 4684",
    "sg:postcode":"06606",
    "sg:province":"CT",
    "sg:tags":[
        "upholsterer"
    ],
    "wof:name":"Sandro's Home Decorating Foam",
    "wof:placetype":"venue"
},
  "geometry": {"coordinates":[-73.198722,41.194371],"type":"Point"}
}