{
  "type": "Feature",
  "properties": {
    "iso:country":"US",
    "sg:address":"1 Wilderman Way",
    "sg:city":"Middletown",
    "sg:classifiers":[
        {
            "category":"Education",
            "subcategory":"School",
            "type":"Public Place"
        }
    ],
    "sg:phone":"+1 860 347 8594",
    "sg:postcode":"06457",
    "sg:province":"CT",
    "sg:tags":[
        "executive"
    ],
    "wof:name":"Woodrow Wilson Middle School",
    "wof:placetype":"venue"
},
  "geometry": {"coordinates":[-72.677071,41.577681],"type":"Point"}
}