{
  "type": "Feature",
  "properties": {
    "addr:full":"70 Rosewood Dr Suffield CT 06010",
    "addr:housenumber":"70",
    "addr:postcode":"06010",
    "addr:street":"Rosewood Dr Suffield Ct",
    "iso:country":"US",
    "sg:address":"70 Rosewood Dr",
    "sg:city":"Suffield",
    "sg:classifiers":[
        {
            "category":"Health Services",
            "subcategory":"Clinic",
            "type":"Services"
        }
    ],
    "sg:phone":"+1   ",
    "sg:postcode":"06010",
    "sg:province":"CT",
    "sg:tags":[
        "specialty",
        "outpatient"
    ],
    "wof:name":"Yukon Rehab Services",
    "wof:placetype":"venue"
},
  "geometry": {"coordinates":[-72.903617,41.701566],"type":"Point"}
}