{
  "type": "Feature",
  "properties": {
    "addr:full":"21 Capitol Ave New Britain CT 06053",
    "addr:housenumber":"21",
    "addr:postcode":"06053",
    "addr:street":"Capitol Ave",
    "iso:country":"US",
    "sg:address":"21 Capitol Ave",
    "sg:city":"New Britain",
    "sg:classifiers":[
        {
            "category":"Professional",
            "subcategory":"Management & Consulting",
            "type":"Services"
        }
    ],
    "sg:phone":"+1   ",
    "sg:postcode":"06053",
    "sg:province":"CT",
    "wof:name":"Pinnacle Consulting LLC",
    "wof:placetype":"venue"
},
  "geometry": {"coordinates":[-72.792722,41.678249],"type":"Point"}
}