{
  "type": "Feature",
  "properties": {
    "addr:full":"304 Main Ave Norwalk CT 06851",
    "addr:housenumber":"304",
    "addr:postcode":"06851",
    "addr:street":"Main Ave",
    "iso:country":"US",
    "sg:address":"304 Main Ave",
    "sg:city":"Norwalk",
    "sg:classifiers":[
        {
            "category":"Professional",
            "subcategory":"Management & Consulting",
            "type":"Services"
        }
    ],
    "sg:phone":"+1   ",
    "sg:postcode":"06851",
    "sg:province":"CT",
    "sg:tags":[
        "consultant",
        "planning",
        "financial"
    ],
    "wof:name":"Freedman Planning and Mgt",
    "wof:placetype":"venue"
},
  "geometry": {"coordinates":[-73.423706,41.131771],"type":"Point"}
}