{
  "type": "Feature",
  "properties": {
    "iso:country":"US",
    "sg:address":"737 Canal St",
    "sg:city":"Stamford",
    "sg:classifiers":[
        {
            "category":"Building & Trades",
            "subcategory":"Construction",
            "type":"Services"
        }
    ],
    "sg:phone":"+1 203 602 0503",
    "sg:postcode":"06902",
    "sg:province":"CT",
    "sg:tags":[
        "general",
        "contractor"
    ],
    "wof:name":"Mason & Krabbe Genrl Construc",
    "wof:placetype":"venue"
},
  "geometry": {"coordinates":[-73.533036,41.045548],"type":"Point"}
}