{
  "type": "Feature",
  "properties": {
    "addr:full":"70 Seaview Ave Ste 6 Stamford CT 06902",
    "addr:housenumber":"70",
    "addr:postcode":"06902",
    "addr:street":"Seaview Ave Ste 6",
    "iso:country":"US",
    "sg:address":"70 Seaview Ave Ste 6",
    "sg:city":"Stamford",
    "sg:classifiers":[
        {
            "category":"Insurance",
            "subcategory":"Hazard Insurance",
            "type":"Services"
        },
        {
            "category":"Insurance",
            "subcategory":"Health Insurance",
            "type":"Services"
        }
    ],
    "sg:phone":"+1 203 353 1203",
    "sg:postcode":"06902",
    "sg:province":"CT",
    "sg:website":"http://www.elementre.com",
    "wof:name":"Xl Weather & Energy, Inc",
    "wof:placetype":"venue"
},
  "geometry": {"coordinates":[-73.52290000000001,41.041261],"type":"Point"}
}