{
  "type": "Feature",
  "properties": {
    "iso:country":"US",
    "sg:address":"61 Maple Ave",
    "sg:city":"Wallingford",
    "sg:classifiers":[
        {
            "category":"Organizations",
            "subcategory":"Community Association",
            "type":"Services"
        }
    ],
    "sg:phone":"+1   ",
    "sg:postcode":"06492",
    "sg:province":"CT",
    "wof:name":"Saint Pierre Social Club",
    "wof:placetype":"venue"
},
  "geometry": {"coordinates":[-72.830161,41.458833],"type":"Point"}
}