{
  "type": "Feature",
  "properties": {
    "iso:country":"US",
    "sg:address":"64 Windward Way",
    "sg:city":"Waterford",
    "sg:classifiers":[
        {
            "category":"Professional",
            "subcategory":"Research",
            "type":"Services"
        }
    ],
    "sg:phone":"+1   ",
    "sg:postcode":"06385",
    "sg:province":"CT",
    "sg:tags":[
        "development"
    ],
    "wof:name":"P C Photonics Corporation",
    "wof:placetype":"venue"
},
  "geometry": {"coordinates":[-72.159155,41.314581],"type":"Point"}
}