{
  "type": "Feature",
  "properties": {
    "addr:full":"33 Edgewater Hillside Westport CT 06880",
    "addr:housenumber":"33",
    "addr:postcode":"06880",
    "addr:street":"Edgewater Hillside",
    "iso:country":"US",
    "sg:address":"33 Edgewater Hillside",
    "sg:city":"Westport",
    "sg:classifiers":[
        {
            "category":"Professional",
            "type":"Services"
        }
    ],
    "sg:phone":"+1 203 222 7513",
    "sg:postcode":"06880",
    "sg:province":"CT",
    "wof:name":"Creative Environments LLC",
    "wof:placetype":"venue"
},
  "geometry": {"coordinates":[-73.343564,41.118488],"type":"Point"}
}