{
  "type": "Feature",
  "properties": {
    "iso:country":"US",
    "sg:address":"290 White St",
    "sg:city":"Danbury",
    "sg:classifiers":[
        {
            "category":"Retail",
            "subcategory":"Laundry & Dry Cleaning",
            "type":"Services"
        }
    ],
    "sg:phone":"+1 203 744 3222",
    "sg:postcode":"06810",
    "sg:province":"CT",
    "sg:tags":[
        "cleaners"
    ],
    "wof:name":"Executive Custom Care Cleaners",
    "wof:placetype":"venue"
},
  "geometry": {"coordinates":[-73.431562,41.399196],"type":"Point"}
}