{
  "type": "Feature",
  "properties": {
    "addr:full":"26 Riverside Dr Branford CT 06405",
    "addr:housenumber":"26",
    "addr:postcode":"06405",
    "addr:street":"Riverside Dr",
    "iso:country":"US",
    "sg:address":"26 Riverside Dr",
    "sg:city":"Branford",
    "sg:classifiers":[
        {
            "category":"Retail",
            "subcategory":"Photofinishing",
            "type":"Services"
        }
    ],
    "sg:phone":"+1   ",
    "sg:postcode":"06405",
    "sg:province":"CT",
    "sg:tags":[
        "laboratory"
    ],
    "wof:name":"Seaside Photo",
    "wof:placetype":"venue"
},
  "geometry": {"coordinates":[-72.801721,41.280552],"type":"Point"}
}