{
  "type": "Feature",
  "properties": {
    "iso:country":"US",
    "sg:address":"61 Soundview Rd",
    "sg:city":"Guilford",
    "sg:classifiers":[
        {
            "category":"Manufacturing",
            "subcategory":"Printing",
            "type":"Manufacturing & Wholesale Goods"
        }
    ],
    "sg:phone":"+1 203 453 6077",
    "sg:postcode":"06437",
    "sg:province":"CT",
    "sg:tags":[
        "commercial"
    ],
    "wof:name":"Beauvais Printing Inc",
    "wof:placetype":"venue"
},
  "geometry": {"coordinates":[-72.663122,41.286446],"type":"Point"}
}