{
  "type": "Feature",
  "properties": {
    "addr:full":"1 Rte 37 S Sherman CT 06784",
    "addr:housenumber":"1",
    "addr:postcode":"06784",
    "addr:street":"Rte 37 S Sherman Ct",
    "iso:country":"US",
    "sg:address":"1 Rte 37 S",
    "sg:city":"Sherman",
    "sg:classifiers":[
        {
            "category":"Professional",
            "subcategory":"Management & Consulting",
            "type":"Services"
        }
    ],
    "sg:phone":"+1   ",
    "sg:postcode":"06784",
    "sg:province":"CT",
    "sg:tags":[
        "publication",
        "mfg"
    ],
    "wof:name":"Phocuswright Incorporated",
    "wof:placetype":"venue"
},
  "geometry": {"coordinates":[-73.50233299999999,41.573071],"type":"Point"}
}