{
  "type": "Feature",
  "properties": {
    "addr:full":"35 Lasalle Rd Hartford CT 06107",
    "addr:housenumber":"35",
    "addr:postcode":"06107",
    "addr:street":"Lasalle Rd",
    "iso:country":"US",
    "sg:address":"35 Lasalle Rd",
    "sg:city":"Hartford",
    "sg:classifiers":[
        {
            "category":"Wholesale",
            "subcategory":"Groceries",
            "type":"Manufacturing & Wholesale Goods"
        }
    ],
    "sg:phone":"+1 860 232 2227",
    "sg:postcode":"06107",
    "sg:province":"CT",
    "wof:name":"Sinfully Chocolate",
    "wof:placetype":"venue"
},
  "geometry": {"coordinates":[-72.74457700000001,41.760261],"type":"Point"}
}