{
  "type": "Feature",
  "properties": {
    "addr:full":"18 Quintard Ter Stamford CT 06902",
    "addr:housenumber":"18",
    "addr:postcode":"06902",
    "addr:street":"Quintard Ter",
    "iso:country":"US",
    "sg:address":"18 Quintard Ter",
    "sg:city":"Stamford",
    "sg:classifiers":[
        {
            "category":"Social Services",
            "type":"Services"
        }
    ],
    "sg:phone":"+1   ",
    "sg:postcode":"06902",
    "sg:province":"CT",
    "wof:name":"Senior Support Services",
    "wof:placetype":"venue"
},
  "geometry": {"coordinates":[-73.525825,41.056723],"type":"Point"}
}