{
  "type": "Feature",
  "properties": {
    "iso:country":"US",
    "sg:address":"437 N Main St",
    "sg:city":"Wallingford",
    "sg:classifiers":[
        {
            "category":"Professional",
            "subcategory":"Management & Consulting",
            "type":"Services"
        }
    ],
    "sg:phone":"+1   ",
    "sg:postcode":"06492",
    "sg:province":"CT",
    "sg:tags":[
        "business"
    ],
    "wof:name":"D Elkin Special Consulting",
    "wof:placetype":"venue"
},
  "geometry": {"coordinates":[-72.812825,41.463549],"type":"Point"}
}