{
  "type": "Feature",
  "properties": {
    "iso:country":"US",
    "sg:address":"182 Robbins St",
    "sg:city":"Waterbury",
    "sg:classifiers":[
        {
            "category":"Organizations",
            "subcategory":"Religious Organization",
            "type":"Services"
        }
    ],
    "sg:phone":"+1   ",
    "sg:postcode":"06708",
    "sg:province":"CT",
    "wof:name":"Blessed Sacrament Church",
    "wof:placetype":"venue"
},
  "geometry": {"coordinates":[-73.06231099999999,41.557594],"type":"Point"}
}