{
  "type": "Feature",
  "properties": {
    "iso:country":"US",
    "sg:address":"433 S Main St",
    "sg:city":"Hartford",
    "sg:classifiers":[
        {
            "category":"Organizations",
            "subcategory":"Professional Association",
            "type":"Services"
        }
    ],
    "sg:phone":"+1   ",
    "sg:postcode":"06110",
    "sg:province":"CT",
    "sg:tags":[
        "business"
    ],
    "wof:name":"Greater Hartford Multiple List",
    "wof:placetype":"venue"
},
  "geometry": {"coordinates":[-72.743202,41.734041],"type":"Point"}
}