{
  "type": "Feature",
  "properties": {
    "addr:full":"70 S Washington St Milford CT 06460",
    "addr:housenumber":"70",
    "addr:postcode":"06460",
    "addr:street":"S Washington St",
    "iso:country":"US",
    "sg:address":"70 S Washington St",
    "sg:city":"Milford",
    "sg:classifiers":[
        {
            "category":"Wholesale",
            "subcategory":"Auto Parts",
            "type":"Manufacturing & Wholesale Goods"
        }
    ],
    "sg:phone":"+1 203 878 0645",
    "sg:postcode":"06460",
    "sg:province":"CT",
    "sg:tags":[
        "automobile",
        "rebuilt"
    ],
    "wof:name":"Milford Auto Recycling Co",
    "wof:placetype":"venue"
},
  "geometry": {"coordinates":[-73.078599,41.213582],"type":"Point"}
}