{
  "type": "Feature",
  "properties": {
    "iso:country":"US",
    "sg:address":"10 Town Hill Rd",
    "sg:city":"Cornwall Bridge",
    "sg:classifiers":[
        {
            "category":"Professional",
            "type":"Services"
        }
    ],
    "sg:phone":"+1 860 868 8087",
    "sg:postcode":"06754",
    "sg:province":"CT",
    "wof:name":"Shai Rah Foundation Inc",
    "wof:placetype":"venue"
},
  "geometry": {"coordinates":[-73.340508,41.739516],"type":"Point"}
}