{
  "type": "Feature",
  "properties": {
    "iso:country":"US",
    "sg:address":"32 Ken Ct",
    "sg:city":"Stamford",
    "sg:classifiers":[
        {
            "category":"Retail",
            "subcategory":"Laundry & Dry Cleaning",
            "type":"Services"
        }
    ],
    "sg:phone":"+1   ",
    "sg:postcode":"06905",
    "sg:province":"CT",
    "sg:tags":[
        "floor",
        "laying",
        "contractor"
    ],
    "wof:name":"Superior Rug Cleaning",
    "wof:placetype":"venue"
},
  "geometry": {"coordinates":[-73.553515,41.107946],"type":"Point"}
}