{
  "type": "Feature",
  "properties": {
    "iso:country":"US",
    "sg:address":"96 Mansfield Rd",
    "sg:city":"Ashford",
    "sg:classifiers":[
        {
            "category":"Professional",
            "type":"Services"
        }
    ],
    "sg:phone":"+1   ",
    "sg:postcode":"06278",
    "sg:province":"CT",
    "wof:name":"Cabinet Rep Services LLC",
    "wof:placetype":"venue"
},
  "geometry": {"coordinates":[-72.162806,41.858266],"type":"Point"}
}