{
  "type": "Feature",
  "properties": {
    "iso:country":"US",
    "sg:address":"26 Canaan Way",
    "sg:city":"Simsbury",
    "sg:classifiers":[
        {
            "category":"Professional",
            "subcategory":"Business Services",
            "type":"Services"
        }
    ],
    "sg:phone":"+1   ",
    "sg:postcode":"06070",
    "sg:province":"CT",
    "sg:tags":[
        "interior",
        "decorating"
    ],
    "wof:name":"Studio K",
    "wof:placetype":"venue"
},
  "geometry": {"coordinates":[-72.841067,41.885375],"type":"Point"}
}