{
  "type": "Feature",
  "properties": {
    "iso:country":"US",
    "sg:address":"155 Bunker Hill Rd",
    "sg:city":"Guilford",
    "sg:classifiers":[
        {
            "category":"Professional",
            "subcategory":"Business Services",
            "type":"Services"
        }
    ],
    "sg:phone":"+1   ",
    "sg:postcode":"06437",
    "sg:province":"CT",
    "wof:name":"Mjc Design Group LLC",
    "wof:placetype":"venue"
},
  "geometry": {"coordinates":[-72.698993,41.327259],"type":"Point"}
}