{
  "type": "Feature",
  "properties": {
    "addr:full":"22 Seyms St Hartford CT 06120",
    "addr:housenumber":"22",
    "addr:postcode":"06120",
    "addr:street":"Seyms St",
    "iso:country":"US",
    "sg:address":"22 Seyms St",
    "sg:city":"Hartford",
    "sg:classifiers":[
        {
            "category":"Shopping",
            "subcategory":"Music",
            "type":"Retail Goods"
        }
    ],
    "sg:phone":"+1 860 796 8008",
    "sg:postcode":"06120",
    "sg:province":"CT",
    "wof:name":"Goobersnattch Records",
    "wof:placetype":"venue"
},
  "geometry": {"coordinates":[-72.67815,41.77781],"type":"Point"}
}