{
  "type": "Feature",
  "properties": {
    "iso:country":"US",
    "sg:address":"245 Keeler Rd",
    "sg:city":"Bridgewater",
    "sg:classifiers":[
        {
            "category":"Health Services",
            "subcategory":"Health Practitioner",
            "type":"Services"
        }
    ],
    "sg:phone":"+1   ",
    "sg:postcode":"06752",
    "sg:province":"CT",
    "wof:name":"Young Virginia B",
    "wof:placetype":"venue"
},
  "geometry": {"coordinates":[-73.355369,41.536812],"type":"Point"}
}