{
  "type": "Feature",
  "properties": {
    "iso:country":"US",
    "sg:address":"11 Worthington Dr",
    "sg:city":"Farmington",
    "sg:classifiers":[
        {
            "category":"Professional",
            "type":"Services"
        }
    ],
    "sg:phone":"+1 860 674 0844",
    "sg:postcode":"06032",
    "sg:province":"CT",
    "wof:name":"George Crowley",
    "wof:placetype":"venue"
},
  "geometry": {"coordinates":[-72.846722,41.746105],"type":"Point"}
}