{
  "type": "Feature",
  "properties": {
    "addr:full":"62 Silver Spring Rd Ridgefield CT 06877",
    "addr:housenumber":"62",
    "addr:postcode":"06877",
    "addr:street":"Silver Spring Rd",
    "iso:country":"US",
    "sg:address":"62 Silver Spring Rd",
    "sg:city":"Ridgefield",
    "sg:classifiers":[
        {
            "category":"Professional",
            "type":"Services"
        }
    ],
    "sg:phone":"+1 203 438 6533",
    "sg:postcode":"06877",
    "sg:province":"CT",
    "sg:tags":[
        "establishment"
    ],
    "wof:name":"R H Inc",
    "wof:placetype":"venue"
},
  "geometry": {"coordinates":[-73.500676,41.242971],"type":"Point"}
}