{
  "type": "Feature",
  "properties": {
    "iso:country":"US",
    "sg:address":"902 Albany Ave",
    "sg:city":"Hartford",
    "sg:classifiers":[
        {
            "category":"Health Services",
            "subcategory":"Doctor",
            "type":"Services"
        }
    ],
    "sg:phone":"+1   ",
    "sg:postcode":"06112",
    "sg:province":"CT",
    "wof:name":"Sadler George BJ DDS",
    "wof:placetype":"venue"
},
  "geometry": {"coordinates":[-72.691309,41.780379],"type":"Point"}
}