{
  "type": "Feature",
  "properties": {
    "iso:country":"US",
    "sg:address":"213 Maple St",
    "sg:city":"New Haven",
    "sg:classifiers":[
        {
            "category":"Professional",
            "subcategory":"Accounting & Tax Preparation",
            "type":"Services"
        }
    ],
    "sg:phone":"+1 203 787 0496",
    "sg:postcode":"06511",
    "sg:province":"CT",
    "sg:tags":[
        "bookkeeping",
        "general"
    ],
    "wof:name":"Personalized Bookkeeping",
    "wof:placetype":"venue"
},
  "geometry": {"coordinates":[-72.950486,41.316486],"type":"Point"}
}