{
  "type": "Feature",
  "properties": {
    "addr:full":"247 Great Hill Rd Ridgefield CT 06877",
    "addr:housenumber":"247",
    "addr:postcode":"06877",
    "addr:street":"Great Hill Rd",
    "iso:country":"US",
    "sg:address":"247 Great Hill Rd",
    "sg:city":"Ridgefield",
    "sg:classifiers":[
        {
            "category":"Professional",
            "subcategory":"Business Services",
            "type":"Services"
        }
    ],
    "sg:phone":"+1   ",
    "sg:postcode":"06877",
    "sg:province":"CT",
    "wof:name":"Gaudet Bernard J",
    "wof:placetype":"venue"
},
  "geometry": {"coordinates":[-73.484954,41.325555],"type":"Point"}
}