{
  "type": "Feature",
  "properties": {
    "addr:full":"750 Main St Willimantic CT 06226",
    "addr:housenumber":"750",
    "addr:postcode":"06226",
    "addr:street":"Main St",
    "iso:country":"US",
    "sg:address":"750 Main St",
    "sg:city":"Willimantic",
    "sg:classifiers":[
        {
            "category":"Shopping",
            "subcategory":"Photographic Equipment",
            "type":"Retail Goods"
        }
    ],
    "sg:phone":"+1   ",
    "sg:postcode":"06226",
    "sg:province":"CT",
    "sg:tags":[
        "repair",
        "camera",
        "supply"
    ],
    "wof:name":"Willimantic Camera & Video",
    "wof:placetype":"venue"
},
  "geometry": {"coordinates":[-72.212551,41.711798],"type":"Point"}
}