{
  "type": "Feature",
  "properties": {
    "addr:full":"10 Spruce St Southport CT 06451",
    "addr:housenumber":"10",
    "addr:postcode":"06451",
    "addr:street":"Spruce St",
    "iso:country":"US",
    "sg:address":"10 Spruce St",
    "sg:city":"Southport",
    "sg:classifiers":[
        {
            "category":"Professional",
            "subcategory":"Management & Consulting",
            "type":"Services"
        }
    ],
    "sg:phone":"+1   ",
    "sg:postcode":"06451",
    "sg:province":"CT",
    "sg:tags":[
        "business"
    ],
    "wof:name":"Indepndent Maritime Consulting",
    "wof:placetype":"venue"
},
  "geometry": {"coordinates":[-72.837034,41.543545],"type":"Point"}
}