{
  "type": "Feature",
  "properties": {
    "iso:country":"US",
    "sg:address":"805 S End Rd",
    "sg:city":"Southington",
    "sg:classifiers":[
        {
            "category":"Building & Trades",
            "subcategory":"Electrical",
            "type":"Services"
        }
    ],
    "sg:phone":"+1 860 621 7087",
    "sg:postcode":"06479",
    "sg:province":"CT",
    "sg:tags":[
        "electrical",
        "contractor"
    ],
    "wof:name":"Curtiss Electrical Services",
    "wof:placetype":"venue"
},
  "geometry": {"coordinates":[-72.870329,41.557131],"type":"Point"}
}