{
  "type": "Feature",
  "properties": {
    "iso:country":"US",
    "sg:address":"34 S Water St",
    "sg:city":"Greenwich",
    "sg:classifiers":[
        {
            "category":"Autos & Motor Vehicles",
            "subcategory":"Boat Sales",
            "type":"Retail Goods"
        },
        {
            "category":"Recreation",
            "subcategory":"Marina",
            "type":"Entertainment"
        }
    ],
    "sg:phone":"+1 203 531 9207",
    "sg:postcode":"06830",
    "sg:province":"CT",
    "sg:tags":[
        "a",
        "used",
        "supply",
        "automobile",
        "sales",
        "general",
        "dealer"
    ],
    "wof:name":"Catalano J & Sons Inc",
    "wof:placetype":"venue"
},
  "geometry": {"coordinates":[-73.65808699999999,41.003003],"type":"Point"}
}