{
  "type": "Feature",
  "properties": {
    "iso:country":"US",
    "sg:address":"81 River Rd",
    "sg:city":"Collinsville",
    "sg:classifiers":[
        {
            "category":"Building & Trades",
            "subcategory":"Construction",
            "type":"Services"
        }
    ],
    "sg:phone":"+1 860 693 0040",
    "sg:postcode":"06019",
    "sg:province":"CT",
    "sg:tags":[
        "contractor"
    ],
    "wof:name":"Amber Construction & Design",
    "wof:placetype":"venue"
},
  "geometry": {"coordinates":[-72.925102,41.824902],"type":"Point"}
}