{
  "type": "Feature",
  "properties": {
    "iso:country":"US",
    "sg:address":"1411 Middletown Ave",
    "sg:city":"Northford",
    "sg:classifiers":[
        {
            "category":"Personal",
            "subcategory":"Barber",
            "type":"Services"
        }
    ],
    "sg:phone":"+1 203 484 4831",
    "sg:postcode":"06472",
    "sg:province":"CT",
    "wof:name":"Simmy's Haircutters",
    "wof:placetype":"venue"
},
  "geometry": {"coordinates":[-72.788066,41.39582],"type":"Point"}
}