{
  "type": "Feature",
  "properties": {
    "addr:full":"565 Windsor St Hartford CT 06120",
    "addr:housenumber":"565",
    "addr:postcode":"06120",
    "addr:street":"Windsor St",
    "iso:country":"US",
    "sg:address":"565 Windsor St",
    "sg:city":"Hartford",
    "sg:classifiers":[
        {
            "category":"Home & Garden",
            "subcategory":"Hardware",
            "type":"Retail Goods"
        }
    ],
    "sg:phone":"+1 860 527 7700",
    "sg:postcode":"06120",
    "sg:province":"CT",
    "wof:name":"Gatsbys",
    "wof:placetype":"venue"
},
  "geometry": {"coordinates":[-72.671239,41.78327],"type":"Point"}
}