{
  "type": "Feature",
  "properties": {
    "addr:full":"1591 Boston Post Rd Guilford CT 06437",
    "addr:housenumber":"1591",
    "addr:postcode":"06437",
    "addr:street":"Boston Post Rd",
    "iso:country":"US",
    "sg:address":"1591 Boston Post Rd",
    "sg:city":"Guilford",
    "sg:classifiers":[
        {
            "category":"Health Services",
            "subcategory":"Optometrist",
            "type":"Services"
        }
    ],
    "sg:phone":"+1 203 458 2020",
    "sg:postcode":"06437",
    "sg:province":"CT",
    "wof:name":"Elgart Pinn Gordon & Elgart",
    "wof:placetype":"venue"
},
  "geometry": {"coordinates":[-72.70134400000001,41.295005],"type":"Point"}
}