{
  "type": "Feature",
  "properties": {
    "addr:full":"36 Warwick St Middletown CT 06457",
    "addr:housenumber":"36",
    "addr:postcode":"06457",
    "addr:street":"Warwick St",
    "iso:country":"US",
    "sg:address":"36 Warwick St",
    "sg:city":"Middletown",
    "sg:classifiers":[
        {
            "category":"Freight",
            "type":"Transportation"
        }
    ],
    "sg:phone":"+1 203 537 0040",
    "sg:postcode":"06457",
    "sg:province":"CT",
    "sg:tags":[
        "operator",
        "local",
        "trucking"
    ],
    "wof:name":"Sws Trucking LLC",
    "wof:placetype":"venue"
},
  "geometry": {"coordinates":[-72.65156399999999,41.54948],"type":"Point"}
}