{
  "type": "Feature",
  "properties": {
    "addr:full":"187 Middletown Rd Berlin CT 06037",
    "addr:housenumber":"187",
    "addr:postcode":"06037",
    "addr:street":"Middletown Rd",
    "iso:country":"US",
    "sg:address":"187 Middletown Rd",
    "sg:city":"Berlin",
    "sg:classifiers":[
        {
            "category":"Food & Beverages",
            "subcategory":"Bakery",
            "type":"Retail Goods"
        }
    ],
    "sg:phone":"+1 860 828 8365",
    "sg:postcode":"06037",
    "sg:province":"CT",
    "wof:name":"Intermission LLC",
    "wof:placetype":"venue"
},
  "geometry": {"coordinates":[-72.735736,41.615578],"type":"Point"}
}