{
  "type": "Feature",
  "properties": {
    "iso:country":"US",
    "sg:address":"468 Huntington Tpke",
    "sg:city":"Bridgeport",
    "sg:classifiers":[
        {
            "category":"Restaurant",
            "type":"Food & Drink"
        }
    ],
    "sg:phone":"+1 203 372 4718",
    "sg:postcode":"06610",
    "sg:province":"CT",
    "sg:tags":[
        "eating",
        "store",
        "variety"
    ],
    "wof:name":"Kathys Lunchenette",
    "wof:placetype":"venue"
},
  "geometry": {"coordinates":[-73.173709,41.215002],"type":"Point"}
}