{
  "type": "Feature",
  "properties": {
    "iso:country":"US",
    "sg:address":"300 W Main St",
    "sg:city":"Stamford",
    "sg:classifiers":[
        {
            "category":"Manufacturing",
            "subcategory":"Metals",
            "type":"Manufacturing & Wholesale Goods"
        },
        {
            "category":"Building & Trades",
            "subcategory":"Cleaning & Sanitation",
            "type":"Services"
        }
    ],
    "sg:phone":"+1 203 977 0494",
    "sg:postcode":"06902",
    "sg:province":"CT",
    "sg:tags":[
        "plating",
        "finishing"
    ],
    "wof:name":"AAS Greenwich Metal Finishing",
    "wof:placetype":"venue"
},
  "geometry": {"coordinates":[-73.551194,41.048753],"type":"Point"}
}