{
  "type": "Feature",
  "properties": {
    "addr:full":"80 Garfield Ave Stratford CT 06615",
    "addr:housenumber":"80",
    "addr:postcode":"06615",
    "addr:street":"Garfield Ave",
    "iso:country":"US",
    "sg:address":"80 Garfield Ave",
    "sg:city":"Stratford",
    "sg:classifiers":[
        {
            "category":"Real Estate",
            "subcategory":"Real Estate Operator",
            "type":"Services"
        }
    ],
    "sg:phone":"+1 203 377 7491",
    "sg:postcode":"06615",
    "sg:province":"CT",
    "sg:tags":[
        "building",
        "nonresidential"
    ],
    "wof:name":"Berwood Associates",
    "wof:placetype":"venue"
},
  "geometry": {"coordinates":[-73.14841699999999,41.172815],"type":"Point"}
}