{
  "type": "Feature",
  "properties": {
    "iso:country":"US",
    "sg:address":"84 Brian Dr",
    "sg:city":"Trumbull",
    "sg:classifiers":[
        {
            "category":"Building & Trades",
            "subcategory":"Electrical",
            "type":"Services"
        }
    ],
    "sg:phone":"+1 203 374 5109",
    "sg:postcode":"06611",
    "sg:province":"CT",
    "sg:tags":[
        "electrical",
        "contractor"
    ],
    "wof:name":"Woods Electrical Servi",
    "wof:placetype":"venue"
},
  "geometry": {"coordinates":[-73.241591,41.231797],"type":"Point"}
}