{
  "type": "Feature",
  "properties": {
    "addr:full":"141 Barberry Rd North Haven CT 06473",
    "addr:housenumber":"141",
    "addr:postcode":"06473",
    "addr:street":"Barberry Rd;Haven",
    "iso:country":"US",
    "sg:address":"141 Barberry Rd",
    "sg:city":"North Haven",
    "sg:classifiers":[
        {
            "category":"Building & Trades",
            "subcategory":"Construction",
            "type":"Services"
        }
    ],
    "sg:phone":"+1 203 239 2002",
    "sg:postcode":"06473",
    "sg:province":"CT",
    "sg:tags":[
        "excavating",
        "contractor"
    ],
    "wof:name":"Stoneyridge Corp",
    "wof:placetype":"venue"
},
  "geometry": {"coordinates":[-72.82042199999999,41.349253],"type":"Point"}
}