{
  "type": "Feature",
  "properties": {
    "addr:full":"3872 Main St Bridgeport CT 06606",
    "addr:housenumber":"3872",
    "addr:postcode":"06606",
    "addr:street":"Main St",
    "iso:country":"US",
    "sg:address":"3872 Main St",
    "sg:city":"Bridgeport",
    "sg:classifiers":[
        {
            "category":"Professional",
            "subcategory":"Accounting & Tax Preparation",
            "type":"Services"
        }
    ],
    "sg:phone":"+1   ",
    "sg:postcode":"06606",
    "sg:province":"CT",
    "sg:tags":[
        "full",
        "payroll",
        "bookkeeping"
    ],
    "wof:name":"Superior Data Pro LLC",
    "wof:placetype":"venue"
},
  "geometry": {"coordinates":[-73.211201,41.21326],"type":"Point"}
}