{
  "type": "Feature",
  "properties": {
    "iso:country":"US",
    "sg:address":"2434 Berlin Tpke",
    "sg:city":"Newington",
    "sg:classifiers":[
        {
            "category":"Personal",
            "type":"Services"
        }
    ],
    "sg:phone":"+1   ",
    "sg:postcode":"06111",
    "sg:province":"CT",
    "wof:name":"Formal Elegance",
    "wof:placetype":"venue"
},
  "geometry": {"coordinates":[-72.70957,41.683703],"type":"Point"}
}