{
  "type": "Feature",
  "properties": {
    "iso:country":"US",
    "sg:address":"68 Sycamore Ln",
    "sg:city":"Manchester",
    "sg:classifiers":[
        {
            "category":"Building & Trades",
            "subcategory":"Cleaning & Sanitation",
            "type":"Services"
        }
    ],
    "sg:phone":"+1   ",
    "sg:postcode":"06040",
    "sg:province":"CT",
    "sg:tags":[
        "maintenance"
    ],
    "wof:name":"Hedys Home & Office Maint",
    "wof:placetype":"venue"
},
  "geometry": {"coordinates":[-72.50818599999999,41.763045],"type":"Point"}
}