{
  "type": "Feature",
  "properties": {
    "iso:country":"US",
    "sg:address":"4 High Ridge Park Rd",
    "sg:city":"Stamford",
    "sg:classifiers":[
        {
            "category":"Wholesale",
            "subcategory":"Durable Goods & Equipment",
            "type":"Manufacturing & Wholesale Goods"
        }
    ],
    "sg:phone":"+1 203 321 1340",
    "sg:postcode":"06905",
    "sg:province":"CT",
    "sg:tags":[
        "exporter"
    ],
    "sg:website":"www.miltsam.com",
    "wof:name":"Miltenberg & Samton",
    "wof:placetype":"venue"
},
  "geometry": {"coordinates":[-73.540156,41.1104],"type":"Point"}
}