{
  "type": "Feature",
  "properties": {
    "addr:full":"20 Beaver Rd Wethersfield CT 06109",
    "addr:housenumber":"20",
    "addr:postcode":"06109",
    "addr:street":"Beaver Rd",
    "iso:country":"US",
    "sg:address":"20 Beaver Rd",
    "sg:city":"Wethersfield",
    "sg:classifiers":[
        {
            "category":"Health Services",
            "subcategory":"Doctor",
            "type":"Services"
        }
    ],
    "sg:phone":"+1   ",
    "sg:postcode":"06109",
    "sg:province":"CT",
    "wof:name":"Dental Assoc of Wethersfield",
    "wof:placetype":"venue"
},
  "geometry": {"coordinates":[-72.661402,41.708824],"type":"Point"}
}