{
  "type": "Feature",
  "properties": {
    "addr:full":"29 Giles Hill Rd Redding CT 06896",
    "addr:housenumber":"29",
    "addr:postcode":"06896",
    "addr:street":"Giles Hill Rd",
    "iso:country":"US",
    "sg:address":"29 Giles Hill Rd",
    "sg:city":"Redding",
    "sg:classifiers":[
        {
            "category":"Farming",
            "subcategory":"Livestock Farm",
            "type":"Manufacturing & Wholesale Goods"
        }
    ],
    "sg:phone":"+1 203 938 3760",
    "sg:postcode":"06896",
    "sg:province":"CT",
    "sg:tags":[
        "track",
        "operation",
        "racing",
        "equine",
        "or"
    ],
    "wof:name":"Brook Whimsy Farm Ltd",
    "wof:placetype":"venue"
},
  "geometry": {"coordinates":[-73.35001099999999,41.298784],"type":"Point"}
}