{
  "type": "Feature",
  "properties": {
    "iso:country":"US",
    "sg:address":"89 Plaza Ct",
    "sg:city":"Groton",
    "sg:classifiers":[
        {
            "category":"Building & Trades",
            "subcategory":"Construction",
            "type":"Services"
        }
    ],
    "sg:phone":"+1 860 448 0101",
    "sg:postcode":"06340",
    "sg:province":"CT",
    "sg:tags":[
        "commercial",
        "maintenance",
        "contractor"
    ],
    "wof:name":"Regan Commercial Maint Co LLC",
    "wof:placetype":"venue"
},
  "geometry": {"coordinates":[-72.04918600000001,41.346058],"type":"Point"}
}