{
  "type": "Feature",
  "properties": {
    "iso:country":"US",
    "sg:address":"2100 Dixwell Ave",
    "sg:city":"Hamden",
    "sg:classifiers":[
        {
            "category":"Food & Beverages",
            "subcategory":"Groceries & Convenience Stores",
            "type":"Retail Goods"
        }
    ],
    "sg:phone":"+1 203 230 5000",
    "sg:postcode":"06514",
    "sg:province":"CT",
    "sg:tags":[
        "grocer"
    ],
    "sg:website":"www.shaws.com",
    "wof:name":"Shaw's Supermarket",
    "wof:placetype":"venue"
},
  "geometry": {"coordinates":[-72.91930000000001,41.369238],"type":"Point"}
}