{
  "type": "Feature",
  "properties": {
    "addr:full":"15 Cady St Danielson CT 06239",
    "addr:housenumber":"15",
    "addr:postcode":"06239",
    "addr:street":"Cady St",
    "iso:country":"US",
    "sg:address":"15 Cady St",
    "sg:city":"Danielson",
    "sg:classifiers":[
        {
            "category":"Personal",
            "type":"Services"
        }
    ],
    "sg:phone":"+1   ",
    "sg:postcode":"06239",
    "sg:province":"CT",
    "wof:name":"Herbalife Distributor",
    "wof:placetype":"venue"
},
  "geometry": {"coordinates":[-71.88573700000001,41.790078],"type":"Point"}
}