{
  "type": "Feature",
  "properties": {
    "addr:full":"55 Dutton St Wallingford CT 06492",
    "addr:housenumber":"55",
    "addr:postcode":"06492",
    "addr:street":"Dutton St",
    "iso:country":"US",
    "sg:address":"55 Dutton St",
    "sg:city":"Wallingford",
    "sg:classifiers":[
        {
            "category":"Building & Trades",
            "subcategory":"Construction",
            "type":"Services"
        }
    ],
    "sg:phone":"+1 203 265 4406",
    "sg:postcode":"06492",
    "sg:province":"CT",
    "sg:tags":[
        "repairing",
        "remodeling",
        "contractor"
    ],
    "wof:name":"Fritz Remodeling",
    "wof:placetype":"venue"
},
  "geometry": {"coordinates":[-72.810438,41.466023],"type":"Point"}
}