{
  "type": "Feature",
  "properties": {
    "iso:country":"US",
    "sg:address":"57 Danbury Rd",
    "sg:city":"Wilton",
    "sg:classifiers":[
        {
            "category":"Arts & Performance",
            "subcategory":"Theater",
            "type":"Entertainment"
        }
    ],
    "sg:phone":"+1   ",
    "sg:postcode":"06897",
    "sg:province":"CT",
    "sg:tags":[
        "group"
    ],
    "wof:name":"Friederici",
    "wof:placetype":"venue"
},
  "geometry": {"coordinates":[-73.417456,41.166322],"type":"Point"}
}