{
  "type": "Feature",
  "properties": {
    "iso:country":"US",
    "sg:address":"18 Leffingwell Rd",
    "sg:city":"Clinton",
    "sg:classifiers":[
        {
            "category":"Professional",
            "subcategory":"Art Services",
            "type":"Services"
        }
    ],
    "sg:phone":"+1   ",
    "sg:postcode":"06413",
    "sg:province":"CT",
    "sg:tags":[
        "commercial",
        "design"
    ],
    "wof:name":"Its A Looloo Crtv",
    "wof:placetype":"venue"
},
  "geometry": {"coordinates":[-72.53014899999999,41.274581],"type":"Point"}
}