{
  "type": "Feature",
  "properties": {
    "addr:full":"99 Indian Field Rd Greenwich CT 06830",
    "addr:housenumber":"99",
    "addr:postcode":"06830",
    "addr:street":"Indian Field Rd",
    "iso:country":"US",
    "sg:address":"99 Indian Field Rd",
    "sg:city":"Greenwich",
    "sg:classifiers":[
        {
            "category":"Organizations",
            "subcategory":"Non-profit Organization",
            "type":"Services"
        }
    ],
    "sg:phone":"+1 203 869 8445",
    "sg:postcode":"06830",
    "sg:province":"CT",
    "wof:name":"Safe Rides",
    "wof:placetype":"venue"
},
  "geometry": {"coordinates":[-73.605655,41.029509],"type":"Point"}
}