{
  "type": "Feature",
  "properties": {
    "addr:full":"63 Church St Norwich CT 06360",
    "addr:housenumber":"63",
    "addr:postcode":"06360",
    "addr:street":"Church St",
    "iso:country":"US",
    "sg:address":"63 Church St",
    "sg:city":"Norwich",
    "sg:classifiers":[
        {
            "category":"Organizations",
            "subcategory":"Religious Organization",
            "type":"Services"
        }
    ],
    "sg:phone":"+1   ",
    "sg:postcode":"06360",
    "sg:province":"CT",
    "wof:name":"Beulah Land Church of God In C",
    "wof:placetype":"venue"
},
  "geometry": {"coordinates":[-72.078694,41.524713],"type":"Point"}
}