{
  "type": "Feature",
  "properties": {
    "addr:full":"184 Deerbrooke Cir Southington CT 06489",
    "addr:housenumber":"184",
    "addr:postcode":"06489",
    "addr:street":"Deerbrooke Cir",
    "iso:country":"US",
    "sg:address":"184 Deerbrooke Cir",
    "sg:city":"Southington",
    "sg:classifiers":[
        {
            "category":"Organizations",
            "subcategory":"Community Association",
            "type":"Services"
        }
    ],
    "sg:phone":"+1   ",
    "sg:postcode":"06489",
    "sg:province":"CT",
    "wof:name":"Interntnal Assn of Lions Clubs",
    "wof:placetype":"venue"
},
  "geometry": {"coordinates":[-72.918645,41.60475],"type":"Point"}
}