{
  "type": "Feature",
  "properties": {
    "iso:country":"US",
    "sg:address":"587 Middle Tpke W",
    "sg:city":"Manchester",
    "sg:classifiers":[
        {
            "category":"Social Services",
            "type":"Services"
        }
    ],
    "sg:phone":"+1   ",
    "sg:postcode":"06040",
    "sg:province":"CT",
    "wof:name":"Connecticut Adult Probation",
    "wof:placetype":"venue"
},
  "geometry": {"coordinates":[-72.549784,41.781077],"type":"Point"}
}