{
  "type": "Feature",
  "properties": {
    "addr:full":"99 Orange St Stamford CT 06902",
    "addr:housenumber":"99",
    "addr:postcode":"06902",
    "addr:street":"Orange St",
    "iso:country":"US",
    "sg:address":"99 Orange St",
    "sg:city":"Stamford",
    "sg:classifiers":[
        {
            "category":"Building & Trades",
            "subcategory":"Landscaping Services",
            "type":"Services"
        }
    ],
    "sg:phone":"+1 203 348 4561",
    "sg:postcode":"06902",
    "sg:province":"CT",
    "sg:tags":[
        "landscape"
    ],
    "wof:name":"R & D Lawn Service",
    "wof:placetype":"venue"
},
  "geometry": {"coordinates":[-73.516649,41.054437],"type":"Point"}
}