{
  "type": "Feature",
  "properties": {
    "addr:full":"261 Buckley Hill Rd Colchester CT 06415",
    "addr:housenumber":"261",
    "addr:postcode":"06415",
    "addr:street":"Buckley Hill Rd",
    "iso:country":"US",
    "sg:address":"261 Buckley Hill Rd",
    "sg:city":"Colchester",
    "sg:classifiers":[
        {
            "category":"Professional",
            "subcategory":"Computer Services",
            "type":"Services"
        }
    ],
    "sg:phone":"+1   ",
    "sg:postcode":"06415",
    "sg:province":"CT",
    "sg:tags":[
        "related"
    ],
    "wof:name":"Rezource LLC",
    "wof:placetype":"venue"
},
  "geometry": {"coordinates":[-72.342123,41.540563],"type":"Point"}
}