{
  "type": "Feature",
  "properties": {
    "addr:full":"1376 Boston Post Rd Milford CT 06460",
    "addr:housenumber":"1376",
    "addr:postcode":"06460",
    "addr:street":"Boston Post Rd",
    "iso:country":"US",
    "sg:address":"1376 Boston Post Rd",
    "sg:city":"Milford",
    "sg:classifiers":[
        {
            "category":"Restaurant",
            "type":"Food & Drink"
        }
    ],
    "sg:phone":"+1 203 874 9604",
    "sg:postcode":"06460",
    "sg:province":"CT",
    "wof:name":"Mc Donald's",
    "wof:placetype":"venue"
},
  "geometry": {"coordinates":[-73.032319,41.241722],"type":"Point"}
}