{
  "type": "Feature",
  "properties": {
    "addr:full":"17 Wendover Rd Newtown CT 06470",
    "addr:housenumber":"17",
    "addr:postcode":"06470",
    "addr:street":"Wendover Rd",
    "iso:country":"US",
    "sg:address":"17 Wendover Rd",
    "sg:city":"Newtown",
    "sg:classifiers":[
        {
            "category":"Professional",
            "subcategory":"Art Services",
            "type":"Services"
        }
    ],
    "sg:phone":"+1   ",
    "sg:postcode":"06470",
    "sg:province":"CT",
    "sg:tags":[
        "commercial",
        "design"
    ],
    "wof:name":"Cottingham Graphic Design",
    "wof:placetype":"venue"
},
  "geometry": {"coordinates":[-73.308443,41.418023],"type":"Point"}
}