{
  "type": "Feature",
  "properties": {
    "iso:country":"US",
    "sg:address":"148 N Main St",
    "sg:city":"Port Chester",
    "sg:classifiers":[
        {
            "category":"Wholesale",
            "subcategory":"Seafood",
            "type":"Manufacturing & Wholesale Goods"
        }
    ],
    "sg:phone":"+1 914 939 3095",
    "sg:postcode":"10573",
    "sg:province":"CT",
    "wof:name":"Nico's Seafood",
    "wof:placetype":"venue"
},
  "geometry": {"coordinates":[-73.661316,41.002995],"type":"Point"}
}