{
  "type": "Feature",
  "properties": {
    "iso:country":"US",
    "sg:address":"6 Golden Hill Rd",
    "sg:city":"Danbury",
    "sg:classifiers":[
        {
            "category":"Professional",
            "type":"Services"
        }
    ],
    "sg:phone":"+1 203 797 8087",
    "sg:postcode":"06811",
    "sg:province":"CT",
    "wof:name":"Dennis Petrino",
    "wof:placetype":"venue"
},
  "geometry": {"coordinates":[-73.463252,41.407271],"type":"Point"}
}