{
  "type": "Feature",
  "properties": {
    "iso:country":"US",
    "sg:address":"2729 High Ridge Rd",
    "sg:city":"Stamford",
    "sg:classifiers":[
        {
            "category":"Home & Garden",
            "subcategory":"Home Furnishings",
            "type":"Retail Goods"
        },
        {
            "category":"Home & Garden",
            "subcategory":"Kitchen Supply",
            "type":"Retail Goods"
        },
        {
            "category":"Home & Garden",
            "subcategory":"Furniture",
            "type":"Retail Goods"
        }
    ],
    "sg:phone":"+1 203 964 9416",
    "sg:postcode":"06903",
    "sg:province":"CT",
    "sg:tags":[
        "decor",
        "house",
        "bedding",
        "accessory",
        "housewares",
        "store"
    ],
    "sg:website":"http://www.homegoods.com",
    "wof:name":"HomeGoods",
    "wof:placetype":"venue"
},
  "geometry": {"coordinates":[-73.56038700000001,41.160679],"type":"Point"}
}