{
  "type": "Feature",
  "properties": {
    "addr:full":"50 Pheasant Run Dr Gales Ferry CT 06335",
    "addr:housenumber":"50",
    "addr:postcode":"06335",
    "addr:street":"Pheasant Run Dr;Ferry Ct",
    "iso:country":"US",
    "sg:address":"50 Pheasant Run Dr",
    "sg:city":"Gales Ferry",
    "sg:classifiers":[
        {
            "category":"Professional",
            "subcategory":"Computer Services",
            "type":"Services"
        }
    ],
    "sg:phone":"+1   ",
    "sg:postcode":"06335",
    "sg:province":"CT",
    "sg:tags":[
        "programing",
        "custom"
    ],
    "wof:name":"Nu Sym Inc",
    "wof:placetype":"venue"
},
  "geometry": {"coordinates":[-72.05452,41.413119],"type":"Point"}
}