{
  "type": "Feature",
  "properties": {
    "addr:full":"49 Miry Brook Rd Danbury CT 06810",
    "addr:housenumber":"49",
    "addr:postcode":"06810",
    "addr:street":"Miry Brook Rd",
    "iso:country":"US",
    "sg:address":"49 Miry Brook Rd",
    "sg:city":"Danbury",
    "sg:classifiers":[
        {
            "category":"Real Estate",
            "subcategory":"Real Estate Agent",
            "type":"Services"
        }
    ],
    "sg:phone":"+1 203 743 3300",
    "sg:postcode":"06810",
    "sg:province":"CT",
    "sg:tags":[
        "fueling",
        "aircraft",
        "management"
    ],
    "wof:name":"Executive Air Service",
    "wof:placetype":"venue"
},
  "geometry": {"coordinates":[-73.483954,41.367076],"type":"Point"}
}