{
  "type": "Feature",
  "properties": {
    "addr:full":"340 N Main St Southington CT 06489",
    "addr:housenumber":"340",
    "addr:postcode":"06489",
    "addr:street":"N Main St",
    "iso:country":"US",
    "sg:address":"340 N Main St",
    "sg:city":"Southington",
    "sg:classifiers":[
        {
            "category":"Health Services",
            "subcategory":"Doctor",
            "type":"Services"
        }
    ],
    "sg:phone":"+1   ",
    "sg:postcode":"06489",
    "sg:province":"CT",
    "sg:tags":[
        "medical"
    ],
    "wof:name":"Dr Arthur T Blumer MD",
    "wof:placetype":"venue"
},
  "geometry": {"coordinates":[-72.87581900000001,41.611795],"type":"Point"}
}