{
  "type": "Feature",
  "properties": {
    "addr:full":"40 Linden Ave Branford CT 06405",
    "addr:housenumber":"40",
    "addr:postcode":"06405",
    "addr:street":"Linden Ave",
    "iso:country":"US",
    "sg:address":"40 Linden Ave",
    "sg:city":"Branford",
    "sg:classifiers":[
        {
            "category":"Travel",
            "subcategory":"Hotels & Motels",
            "type":"Entertainment"
        }
    ],
    "sg:phone":"+1 203 488 3805",
    "sg:postcode":"06405",
    "sg:province":"CT",
    "sg:tags":[
        "resort"
    ],
    "wof:name":"Owenego Inn",
    "wof:placetype":"venue"
},
  "geometry": {"coordinates":[-72.80470699999999,41.257155],"type":"Point"}
}