{
  "type": "Feature",
  "properties": {
    "addr:full":"601 Center St Wallingford CT 06492",
    "addr:housenumber":"601",
    "addr:postcode":"06492",
    "addr:street":"Center St",
    "iso:country":"US",
    "sg:address":"601 Center St",
    "sg:city":"Wallingford",
    "sg:classifiers":[
        {
            "category":"Autos & Motor Vehicles",
            "subcategory":"Fuel & Gas Station",
            "type":"Retail Goods"
        },
        {
            "category":"Retail",
            "subcategory":"Auto Repair",
            "type":"Services"
        }
    ],
    "sg:phone":"+1 203 265 2994",
    "sg:postcode":"06492",
    "sg:province":"CT",
    "sg:tags":[
        "repairing",
        "automobile",
        "station"
    ],
    "wof:name":"Adamo's Garage",
    "wof:placetype":"venue"
},
  "geometry": {"coordinates":[-72.812302,41.451548],"type":"Point"}
}