{
  "type": "Feature",
  "properties": {
    "addr:full":"1 Grays Bridge Rd Brookfield CT 06804",
    "addr:housenumber":"1",
    "addr:postcode":"06804",
    "addr:street":"Grays Bridge Rd",
    "iso:country":"US",
    "sg:address":"1 Grays Bridge Rd",
    "sg:city":"Brookfield",
    "sg:classifiers":[
        {
            "category":"Health Services",
            "subcategory":"Clinic",
            "type":"Services"
        }
    ],
    "sg:phone":"+1   ",
    "sg:postcode":"06804",
    "sg:province":"CT",
    "sg:tags":[
        "home",
        "care"
    ],
    "wof:name":"Cura Script",
    "wof:placetype":"venue"
},
  "geometry": {"coordinates":[-73.41080100000001,41.433789],"type":"Point"}
}