{
  "type": "Feature",
  "properties": {
    "addr:full":"91 Willow Brook Dr Berlin CT 06037",
    "addr:housenumber":"91",
    "addr:postcode":"06037",
    "addr:street":"Willow Brook Dr",
    "iso:country":"US",
    "sg:address":"91 Willow Brook Dr",
    "sg:city":"Berlin",
    "sg:classifiers":[
        {
            "category":"Manufacturing",
            "subcategory":"Tools & Machinery",
            "type":"Manufacturing & Wholesale Goods"
        }
    ],
    "sg:phone":"+1 860 829 0004",
    "sg:postcode":"06037",
    "sg:province":"CT",
    "sg:tags":[
        "aircraft",
        "industrial",
        "m",
        "mfg"
    ],
    "wof:name":"Hard Manufacturing",
    "wof:placetype":"venue"
},
  "geometry": {"coordinates":[-72.747651,41.640799],"type":"Point"}
}