{
  "type": "Feature",
  "properties": {
    "iso:country":"US",
    "sg:address":"522 Pequonnock St",
    "sg:city":"Bridgeport",
    "sg:classifiers":[
        {
            "category":"Shopping",
            "subcategory":"Pharmacy",
            "type":"Retail Goods"
        }
    ],
    "sg:phone":"+1 203 338 9709",
    "sg:postcode":"06604",
    "sg:province":"CT",
    "wof:name":"Ethical Pharmacy",
    "wof:placetype":"venue"
},
  "geometry": {"coordinates":[-73.205898,41.182621],"type":"Point"}
}