{
  "type": "Feature",
  "properties": {
    "addr:full":"22 Leetes Island Rd Branford CT 06405",
    "addr:housenumber":"22",
    "addr:postcode":"06405",
    "addr:street":"Leetes Island Rd",
    "iso:country":"US",
    "sg:address":"22 Leetes Island Rd",
    "sg:city":"Branford",
    "sg:classifiers":[
        {
            "category":"Utilities",
            "subcategory":"Mobile Phone",
            "type":"Services"
        }
    ],
    "sg:phone":"+1 203 481 0104",
    "sg:postcode":"06405",
    "sg:province":"CT",
    "sg:tags":[
        "communication",
        "telephone",
        "cellular",
        "radiotelephone"
    ],
    "wof:name":"Wireless Zone",
    "wof:placetype":"venue"
},
  "geometry": {"coordinates":[-72.76475000000001,41.298144],"type":"Point"}
}