{
  "type": "Feature",
  "properties": {
    "addr:full":"100 Old Ridgefield Rd Wilton CT 06897",
    "addr:housenumber":"100",
    "addr:postcode":"06897",
    "addr:street":"Old Ridgefield Rd Wilton Ct",
    "iso:country":"US",
    "sg:address":"100 Old Ridgefield Rd",
    "sg:city":"Wilton",
    "sg:classifiers":[
        {
            "category":"Personal",
            "subcategory":"Barber",
            "type":"Services"
        }
    ],
    "sg:phone":"+1 203 834 7622",
    "sg:postcode":"06897",
    "sg:province":"CT",
    "wof:name":"Village Barber Shop",
    "wof:placetype":"venue"
},
  "geometry": {"coordinates":[-73.431161,41.193027],"type":"Point"}
}