{
  "type": "Feature",
  "properties": {
    "iso:country":"US",
    "sg:address":"2640 Main St",
    "sg:city":"Bridgeport",
    "sg:classifiers":[
        {
            "category":"Restaurant",
            "type":"Food & Drink"
        }
    ],
    "sg:phone":"+1 203 331 0108",
    "sg:postcode":"06606",
    "sg:province":"CT",
    "wof:name":"Jade Lee Kitchen",
    "wof:placetype":"venue"
},
  "geometry": {"coordinates":[-73.201218,41.198129],"type":"Point"}
}