{
  "type": "Feature",
  "properties": {
    "iso:country":"US",
    "sg:address":"627 Main St",
    "sg:city":"Monroe",
    "sg:classifiers":[
        {
            "category":"Professional",
            "subcategory":"Testing Lab",
            "type":"Services"
        }
    ],
    "sg:phone":"+1   ",
    "sg:postcode":"06468",
    "sg:province":"CT",
    "sg:tags":[
        "laboratory",
        "consulting",
        "business"
    ],
    "wof:name":"Enviroanalytical Inc",
    "wof:placetype":"venue"
},
  "geometry": {"coordinates":[-73.263918,41.334306],"type":"Point"}
}