{
  "type": "Feature",
  "properties": {
    "iso:country":"US",
    "sg:address":"32 Atwater St",
    "sg:city":"New Haven",
    "sg:classifiers":[
        {
            "category":"Building & Trades",
            "subcategory":"Construction",
            "type":"Services"
        }
    ],
    "sg:phone":"+1 203 789 9991",
    "sg:postcode":"06513",
    "sg:province":"CT",
    "sg:tags":[
        "general",
        "contractor"
    ],
    "wof:name":"ADR General Contracting",
    "wof:placetype":"venue"
},
  "geometry": {"coordinates":[-72.89287,41.311521],"type":"Point"}
}