{
  "type": "Feature",
  "properties": {
    "iso:country":"US",
    "sg:address":"1 Strawberry Hill Ct",
    "sg:city":"Stamford",
    "sg:classifiers":[
        {
            "category":"Health Services",
            "subcategory":"Chiropractor",
            "type":"Services"
        }
    ],
    "sg:phone":"+1 203 325 2990",
    "sg:postcode":"06902",
    "sg:province":"CT",
    "wof:name":"Strawberry Hill Chiropractic",
    "wof:placetype":"venue"
},
  "geometry": {"coordinates":[-73.535687,41.065411],"type":"Point"}
}