{
  "type": "Feature",
  "properties": {
    "iso:country":"US",
    "sg:address":"106 Windrow Rd",
    "sg:city":"Norfolk",
    "sg:classifiers":[
        {
            "category":"Banks & Credit Unions",
            "subcategory":"Investment Brokerage",
            "type":"Services"
        }
    ],
    "sg:phone":"+1 860 542 5569",
    "sg:postcode":"06058",
    "sg:province":"CT",
    "sg:tags":[
        "advice"
    ],
    "wof:name":"Eecos",
    "wof:placetype":"venue"
},
  "geometry": {"coordinates":[-73.219741,41.972191],"type":"Point"}
}