{
  "type": "Feature",
  "properties": {
    "iso:country":"US",
    "sg:address":"731 Campbell Ave",
    "sg:city":"West Haven",
    "sg:classifiers":[
        {
            "category":"Personal",
            "subcategory":"Beauty Salon",
            "type":"Services"
        }
    ],
    "sg:phone":"+1   ",
    "sg:postcode":"06516",
    "sg:province":"CT",
    "sg:tags":[
        "shop"
    ],
    "wof:name":"Faith Beauty Salon Cosmetologi",
    "wof:placetype":"venue"
},
  "geometry": {"coordinates":[-72.954223,41.27813],"type":"Point"}
}