{
  "type": "Feature",
  "properties": {
    "iso:country":"US",
    "sg:address":"65 August Ave",
    "sg:city":"Wolcott",
    "sg:classifiers":[
        {
            "category":"Wholesale",
            "subcategory":"Durable Goods & Equipment",
            "type":"Manufacturing & Wholesale Goods"
        }
    ],
    "sg:phone":"+1 203 879 6959",
    "sg:postcode":"06716",
    "sg:province":"CT",
    "sg:tags":[
        "control",
        "representative"
    ],
    "wof:name":"Jwb Company",
    "wof:placetype":"venue"
},
  "geometry": {"coordinates":[-72.9717,41.615352],"type":"Point"}
}