{
  "type": "Feature",
  "properties": {
    "addr:full":"119 Everit St New Haven CT 06511",
    "addr:housenumber":"119",
    "addr:postcode":"06511",
    "addr:street":"Everit St",
    "iso:country":"US",
    "sg:address":"119 Everit St",
    "sg:city":"New Haven",
    "sg:classifiers":[
        {
            "category":"Retail",
            "subcategory":"Portrait Studio",
            "type":"Services"
        }
    ],
    "sg:phone":"+1   ",
    "sg:postcode":"06511",
    "sg:province":"CT",
    "sg:tags":[
        "photo"
    ],
    "wof:name":"Michael Doolittle Photography",
    "wof:placetype":"venue"
},
  "geometry": {"coordinates":[-72.91235399999999,41.32892],"type":"Point"}
}