{
  "type": "Feature",
  "properties": {
    "addr:full":"290 Davenport Ave New Haven CT 06519",
    "addr:housenumber":"290",
    "addr:postcode":"06519",
    "addr:street":"Davenport Ave",
    "iso:country":"US",
    "sg:address":"290 Davenport Ave",
    "sg:city":"New Haven",
    "sg:classifiers":[
        {
            "category":"Retail",
            "subcategory":"Auto Repair",
            "type":"Services"
        }
    ],
    "sg:phone":"+1   ",
    "sg:postcode":"06519",
    "sg:province":"CT",
    "sg:tags":[
        "general"
    ],
    "wof:name":"Discovery Auto Repair",
    "wof:placetype":"venue"
},
  "geometry": {"coordinates":[-72.94367699999999,41.30024],"type":"Point"}
}