{
  "type": "Feature",
  "properties": {
    "iso:country":"US",
    "sg:address":"34 Evergreen Rd",
    "sg:city":"Manchester",
    "sg:classifiers":[
        {
            "category":"Home & Garden",
            "subcategory":"Home Furnishings",
            "type":"Retail Goods"
        }
    ],
    "sg:phone":"+1 860 533 1884",
    "sg:postcode":"06001",
    "sg:province":"CT",
    "wof:name":"C Js Pellet Depot LLC",
    "wof:placetype":"venue"
},
  "geometry": {"coordinates":[-72.88505000000001,41.811876],"type":"Point"}
}