{
  "type": "Feature",
  "properties": {
    "iso:country":"US",
    "sg:address":"362 Heights Rd",
    "sg:city":"Darien",
    "sg:classifiers":[
        {
            "category":"Shopping",
            "subcategory":"Florist",
            "type":"Retail Goods"
        }
    ],
    "sg:phone":"+1 203 662 1236",
    "sg:postcode":"06820",
    "sg:province":"CT",
    "wof:name":"Bloomers",
    "wof:placetype":"venue"
},
  "geometry": {"coordinates":[-73.495761,41.069194],"type":"Point"}
}