{
  "type": "Feature",
  "properties": {
    "iso:country":"US",
    "sg:address":"1 Market Cir",
    "sg:city":"Windsor",
    "sg:classifiers":[
        {
            "category":"Wholesale",
            "subcategory":"Groceries",
            "type":"Manufacturing & Wholesale Goods"
        }
    ],
    "sg:phone":"+1   ",
    "sg:postcode":"06095",
    "sg:province":"CT",
    "sg:tags":[
        "general"
    ],
    "wof:name":"Vsa of New England",
    "wof:placetype":"venue"
},
  "geometry": {"coordinates":[-72.630505,41.899612],"type":"Point"}
}