{
  "type": "Feature",
  "properties": {
    "addr:full":"2 S Smith St Norwalk CT 06855",
    "addr:housenumber":"2",
    "addr:postcode":"06855",
    "addr:street":"S Smith St",
    "iso:country":"US",
    "sg:address":"2 S Smith St",
    "sg:city":"Norwalk",
    "sg:classifiers":[
        {
            "category":"Manufacturing",
            "subcategory":"Motor Vehicles & Parts",
            "type":"Manufacturing & Wholesale Goods"
        }
    ],
    "sg:phone":"+1 203 831 0824",
    "sg:postcode":"06855",
    "sg:province":"CT",
    "sg:tags":[
        "body",
        "truck"
    ],
    "wof:name":"Ferrara's Industries",
    "wof:placetype":"venue"
},
  "geometry": {"coordinates":[-73.411293,41.103237],"type":"Point"}
}