{
  "type": "Feature",
  "properties": {
    "iso:country":"US",
    "sg:address":"27 Willow St",
    "sg:city":"Mystic",
    "sg:classifiers":[
        {
            "category":"Professional",
            "subcategory":"Management & Consulting",
            "type":"Services"
        }
    ],
    "sg:phone":"+1   ",
    "sg:postcode":"06355",
    "sg:province":"CT",
    "sg:tags":[
        "engineering",
        "quality",
        "improvement"
    ],
    "wof:name":"Rose Associates Indus Cons",
    "wof:placetype":"venue"
},
  "geometry": {"coordinates":[-71.966064,41.354331],"type":"Point"}
}