{
  "type": "Feature",
  "properties": {
    "addr:full":"103 Ripton Rd Shelton CT 06484",
    "addr:housenumber":"103",
    "addr:postcode":"06484",
    "addr:street":"Ripton Rd",
    "iso:country":"US",
    "sg:address":"103 Ripton Rd",
    "sg:city":"Shelton",
    "sg:classifiers":[
        {
            "category":"Professional",
            "subcategory":"Computer Services",
            "type":"Services"
        }
    ],
    "sg:phone":"+1 203 929 9727",
    "sg:postcode":"06484",
    "sg:province":"CT",
    "sg:tags":[
        "home",
        "consulting",
        "page",
        "dev",
        "internet"
    ],
    "wof:name":"Darrin Scottt Studios",
    "wof:placetype":"venue"
},
  "geometry": {"coordinates":[-73.15700699999999,41.29978],"type":"Point"}
}