{
  "type": "Feature",
  "properties": {
    "addr:full":"223 Browning Rd Norwich CT 06360",
    "addr:housenumber":"223",
    "addr:postcode":"06360",
    "addr:street":"Browning Rd",
    "iso:country":"US",
    "sg:address":"223 Browning Rd",
    "sg:city":"Norwich",
    "sg:classifiers":[
        {
            "category":"Professional",
            "subcategory":"Management & Consulting",
            "type":"Services"
        }
    ],
    "sg:phone":"+1   ",
    "sg:postcode":"06360",
    "sg:province":"CT",
    "sg:tags":[
        "business"
    ],
    "wof:name":"Szarka & Son Incorporated",
    "wof:placetype":"venue"
},
  "geometry": {"coordinates":[-72.131056,41.547414],"type":"Point"}
}