{
  "type": "Feature",
  "properties": {
    "addr:full":"25 Alexander Dr East Lyme CT 06333",
    "addr:housenumber":"25",
    "addr:postcode":"06333",
    "addr:street":"Alexander Dr",
    "iso:country":"US",
    "sg:address":"25 Alexander Dr",
    "sg:city":"East Lyme",
    "sg:classifiers":[
        {
            "category":"Professional",
            "type":"Services"
        }
    ],
    "sg:phone":"+1 860 739 3542",
    "sg:postcode":"06333",
    "sg:province":"CT",
    "wof:name":"Drkr Inc",
    "wof:placetype":"venue"
},
  "geometry": {"coordinates":[-72.22837199999999,41.348506],"type":"Point"}
}