{
  "type": "Feature",
  "properties": {
    "addr:full":"31 Willie Cir Tolland CT 06084",
    "addr:housenumber":"31",
    "addr:postcode":"06084",
    "addr:street":"Willie Cir Tolland Ct",
    "iso:country":"US",
    "sg:address":"31 Willie Cir",
    "sg:city":"Tolland",
    "sg:classifiers":[
        {
            "category":"Real Estate",
            "subcategory":"Real Estate Agent",
            "type":"Services"
        }
    ],
    "sg:phone":"+1 860 871 1829",
    "sg:postcode":"06084",
    "sg:province":"CT",
    "wof:name":"Pattavina Family LLC",
    "wof:placetype":"venue"
},
  "geometry": {"coordinates":[-72.406265,41.888273],"type":"Point"}
}