{
  "type": "Feature",
  "properties": {
    "addr:full":"355 Research Pkwy Meriden CT 06450",
    "addr:housenumber":"355",
    "addr:postcode":"06450",
    "addr:street":"Research Pkwy",
    "iso:country":"US",
    "sg:address":"355 Research Pkwy",
    "sg:city":"Meriden",
    "sg:classifiers":[
        {
            "category":"Professional",
            "subcategory":"Engineering",
            "type":"Services"
        }
    ],
    "sg:phone":"+1   ",
    "sg:postcode":"06450",
    "sg:province":"CT",
    "sg:tags":[
        "environmental",
        "architecture",
        "se",
        "surveying"
    ],
    "wof:name":"Bl Companies",
    "wof:placetype":"venue"
},
  "geometry": {"coordinates":[-72.76236900000001,41.518871],"type":"Point"}
}