{
  "type": "Feature",
  "properties": {
    "iso:country":"US",
    "sg:address":"482 Summer St",
    "sg:city":"Stamford",
    "sg:classifiers":[
        {
            "category":"Real Estate",
            "subcategory":"Real Estate Agent",
            "type":"Services"
        },
        {
            "category":"Professional",
            "subcategory":"Business Services",
            "type":"Services"
        }
    ],
    "sg:phone":"+1 203 964 3000",
    "sg:postcode":"06901",
    "sg:province":"CT",
    "wof:name":"Sunbelt Sales & Development Co",
    "wof:placetype":"venue"
},
  "geometry": {"coordinates":[-73.54056300000001,41.055686],"type":"Point"}
}