{
  "type": "Feature",
  "properties": {
    "addr:full":"225 West St Seymour CT 06483",
    "addr:housenumber":"225",
    "addr:postcode":"06483",
    "addr:street":"West St",
    "iso:country":"US",
    "sg:address":"225 West St",
    "sg:city":"Seymour",
    "sg:classifiers":[
        {
            "category":"Restaurant",
            "type":"Food & Drink"
        }
    ],
    "sg:phone":"+1 203 888 3702",
    "sg:postcode":"06483",
    "sg:province":"CT",
    "sg:tags":[
        "pizza"
    ],
    "wof:name":"Mamma Mia Restaurant",
    "wof:placetype":"venue"
},
  "geometry": {"coordinates":[-73.085044,41.395818],"type":"Point"}
}