{
  "type": "Feature",
  "properties": {
    "iso:country":"US",
    "sg:address":"179 W High St",
    "sg:city":"East Hampton",
    "sg:classifiers":[
        {
            "category":"Retail",
            "subcategory":"Auto Repair",
            "type":"Services"
        }
    ],
    "sg:phone":"+1   ",
    "sg:postcode":"06424",
    "sg:province":"CT",
    "sg:tags":[
        "automotive"
    ],
    "wof:name":"Chippys Garage",
    "wof:placetype":"venue"
},
  "geometry": {"coordinates":[-72.52959799999999,41.569311],"type":"Point"}
}