{
  "type": "Feature",
  "properties": {
    "iso:country":"US",
    "sg:address":"124 Edin Ave",
    "sg:city":"Waterbury",
    "sg:classifiers":[
        {
            "category":"Building & Trades",
            "subcategory":"Construction",
            "type":"Services"
        }
    ],
    "sg:phone":"+1 203 757 7031",
    "sg:postcode":"06706",
    "sg:province":"CT",
    "sg:tags":[
        "builder",
        "repairer",
        "chimney"
    ],
    "wof:name":"Done Rite Home Improvements",
    "wof:placetype":"venue"
},
  "geometry": {"coordinates":[-73.03299,41.530852],"type":"Point"}
}