{
  "type": "Feature",
  "properties": {
    "addr:full":"101 Pitkin St East Hartford CT 06108",
    "addr:housenumber":"101",
    "addr:postcode":"06108",
    "addr:street":"Pitkin St East;Ct",
    "iso:country":"US",
    "sg:address":"101 Pitkin St",
    "sg:city":"East Hartford",
    "sg:classifiers":[
        {
            "category":"Government",
            "subcategory":"Office",
            "type":"Public Place"
        }
    ],
    "sg:phone":"+1 860 291 6740",
    "sg:postcode":"06108",
    "sg:province":"CT",
    "sg:tags":[
        "water",
        "surveying"
    ],
    "wof:name":"Cost Ctr 2404-CT Wtr Dst Off",
    "wof:placetype":"venue"
},
  "geometry": {"coordinates":[-72.65051200000001,41.763699],"type":"Point"}
}