{
  "type": "Feature",
  "properties": {
    "addr:full":"427 Campbell Ave West Haven CT 06516",
    "addr:housenumber":"427",
    "addr:postcode":"06516",
    "addr:street":"Campbell Ave",
    "iso:country":"US",
    "sg:address":"427 Campbell Ave",
    "sg:city":"West Haven",
    "sg:classifiers":[
        {
            "category":"Personal",
            "subcategory":"Beauty Salon",
            "type":"Services"
        }
    ],
    "sg:phone":"+1 203 479 4088",
    "sg:postcode":"06516",
    "sg:province":"CT",
    "wof:name":"Elcily Hair Salon",
    "wof:placetype":"venue"
},
  "geometry": {"coordinates":[-72.948959,41.269896],"type":"Point"}
}