{
  "type": "Feature",
  "properties": {
    "iso:country":"US",
    "sg:address":"1764 Litchfield Tpke",
    "sg:city":"Woodbridge",
    "sg:classifiers":[
        {
            "category":"Banks & Credit Unions",
            "subcategory":"Investment Brokerage",
            "type":"Services"
        },
        {
            "category":"Professional",
            "subcategory":"Management & Consulting",
            "type":"Services"
        }
    ],
    "sg:phone":"+1 203 397 3977",
    "sg:postcode":"06525",
    "sg:province":"CT",
    "sg:tags":[
        "company"
    ],
    "wof:name":"M & M Investments LLC",
    "wof:placetype":"venue"
},
  "geometry": {"coordinates":[-72.980338,41.345241],"type":"Point"}
}