{
  "type": "Feature",
  "properties": {
    "iso:country":"US",
    "sg:address":"1620 Musso View Ave",
    "sg:city":"Cheshire",
    "sg:classifiers":[
        {
            "category":"Building & Trades",
            "subcategory":"Construction",
            "type":"Services"
        }
    ],
    "sg:phone":"+1   ",
    "sg:postcode":"06410",
    "sg:province":"CT",
    "sg:tags":[
        "work",
        "iron",
        "structural"
    ],
    "wof:name":"Tino Welding & Iron Works",
    "wof:placetype":"venue"
},
  "geometry": {"coordinates":[-72.958234,41.549409],"type":"Point"}
}