{
  "type": "Feature",
  "properties": {
    "addr:full":"41 Grey Ledge Dr Guilford CT 06437",
    "addr:housenumber":"41",
    "addr:postcode":"06437",
    "addr:street":"Grey Ledge Dr",
    "iso:country":"US",
    "sg:address":"41 Grey Ledge Dr",
    "sg:city":"Guilford",
    "sg:classifiers":[
        {
            "category":"Professional",
            "subcategory":"Engineering",
            "type":"Services"
        }
    ],
    "sg:phone":"+1 203 453 6499",
    "sg:postcode":"06437",
    "sg:province":"CT",
    "sg:tags":[
        "machinery"
    ],
    "wof:name":"Hesse Engineering",
    "wof:placetype":"venue"
},
  "geometry": {"coordinates":[-72.701689,41.291855],"type":"Point"}
}