{
  "type": "Feature",
  "properties": {
    "iso:country":"US",
    "sg:address":"189 Bridgeport Ave",
    "sg:city":"Milford",
    "sg:classifiers":[
        {
            "category":"Education",
            "subcategory":"Music School",
            "type":"Public Place"
        },
        {
            "category":"Shopping",
            "subcategory":"Musical Instruments",
            "type":"Retail Goods"
        },
        {
            "category":"Arts & Performance",
            "subcategory":"Music",
            "type":"Entertainment"
        }
    ],
    "sg:phone":"+1 203 783 9828",
    "sg:postcode":"06460",
    "sg:province":"CT",
    "sg:tags":[
        "guitar",
        "amplifier",
        "instruction-instrumental"
    ],
    "wof:name":"Route 1 Guitars",
    "wof:placetype":"venue"
},
  "geometry": {"coordinates":[-73.102339,41.202079],"type":"Point"}
}