{
  "type": "Feature",
  "properties": {
    "addr:full":"18 Founders Vlg Clinton CT 06413",
    "addr:housenumber":"18",
    "addr:postcode":"06413",
    "addr:street":"Founders Vlg Clinton Ct",
    "iso:country":"US",
    "sg:address":"18 Founders Vlg",
    "sg:city":"Clinton",
    "sg:classifiers":[
        {
            "category":"Building & Trades",
            "subcategory":"Plumbing",
            "type":"Services"
        }
    ],
    "sg:phone":"+1 860 664 9514",
    "sg:postcode":"06413",
    "sg:province":"CT",
    "sg:tags":[
        "plumber",
        "industrial",
        "contractors-commercial"
    ],
    "wof:name":"Roger Crampton",
    "wof:placetype":"venue"
},
  "geometry": {"coordinates":[-72.509501,41.276063],"type":"Point"}
}