{
  "type": "Feature",
  "properties": {
    "addr:full":"12 Aspenwood Weatogue CT 06089",
    "addr:housenumber":"12",
    "addr:postcode":"06089",
    "addr:street":"Aspenwood Weatogue Ct",
    "iso:country":"US",
    "sg:address":"12 Aspenwood",
    "sg:city":"Weatogue",
    "sg:classifiers":[
        {
            "category":"Banks & Credit Unions",
            "subcategory":"Investment Brokerage",
            "type":"Services"
        }
    ],
    "sg:phone":"+1 860 651 5779",
    "sg:postcode":"06089",
    "sg:province":"CT",
    "sg:tags":[
        "security"
    ],
    "wof:name":"Lighthouse Ventures Inc",
    "wof:placetype":"venue"
},
  "geometry": {"coordinates":[-72.82266,41.851488],"type":"Point"}
}