{
  "type": "Feature",
  "properties": {
    "iso:country":"US",
    "sg:address":"19 Riverside Ave",
    "sg:city":"Riverside",
    "sg:classifiers":[
        {
            "category":"Health Services",
            "subcategory":"Doctor",
            "type":"Services"
        }
    ],
    "sg:phone":"+1 203 637 5252",
    "sg:postcode":"06878",
    "sg:province":"CT",
    "sg:tags":[
        "dentist"
    ],
    "wof:name":"John J Schinto III DDS",
    "wof:placetype":"venue"
},
  "geometry": {"coordinates":[-73.586358,41.040715],"type":"Point"}
}