{
  "type": "Feature",
  "properties": {
    "addr:full":"61 Atwater St Bridgeport CT 06604",
    "addr:housenumber":"61",
    "addr:postcode":"06604",
    "addr:street":"Atwater St",
    "iso:country":"US",
    "sg:address":"61 Atwater St",
    "sg:city":"Bridgeport",
    "sg:classifiers":[
        {
            "category":"Building & Trades",
            "subcategory":"Construction",
            "type":"Services"
        }
    ],
    "sg:phone":"+1 203 333 7629",
    "sg:postcode":"06604",
    "sg:province":"CT",
    "sg:tags":[
        "general",
        "improvement"
    ],
    "wof:name":"Triton Contracting Inc",
    "wof:placetype":"venue"
},
  "geometry": {"coordinates":[-73.208502,41.183165],"type":"Point"}
}