{
  "type": "Feature",
  "properties": {
    "addr:full":"243 Vanderbilt Rd Bristol CT 06010",
    "addr:housenumber":"243",
    "addr:postcode":"06010",
    "addr:street":"Vanderbilt Rd",
    "iso:country":"US",
    "sg:address":"243 Vanderbilt Rd",
    "sg:city":"Bristol",
    "sg:classifiers":[
        {
            "category":"Professional",
            "type":"Services"
        }
    ],
    "sg:phone":"+1   ",
    "sg:postcode":"06010",
    "sg:province":"CT",
    "wof:name":"Rj Services LLC",
    "wof:placetype":"venue"
},
  "geometry": {"coordinates":[-72.93794800000001,41.692627],"type":"Point"}
}