{
  "type": "Feature",
  "properties": {
    "iso:country":"US",
    "sg:address":"100 Quarry Rd",
    "sg:city":"Trumbull",
    "sg:classifiers":[
        {
            "category":"Cinema",
            "subcategory":"Movie Theater",
            "type":"Entertainment"
        }
    ],
    "sg:phone":"+1   ",
    "sg:postcode":"06611",
    "sg:province":"CT",
    "sg:tags":[
        "motion",
        "picture"
    ],
    "wof:name":"Crown Theaters",
    "wof:placetype":"venue"
},
  "geometry": {"coordinates":[-73.181023,41.225736],"type":"Point"}
}