{
  "type": "Feature",
  "properties": {
    "iso:country":"US",
    "sg:address":"106 Gillotti Rd",
    "sg:city":"New Fairfield",
    "sg:classifiers":[
        {
            "category":"Professional",
            "type":"Services"
        }
    ],
    "sg:phone":"+1 203 746 5057",
    "sg:postcode":"06812",
    "sg:province":"CT",
    "wof:name":"PDC Crafts LLC",
    "wof:placetype":"venue"
},
  "geometry": {"coordinates":[-73.512359,41.455709],"type":"Point"}
}