{
  "type": "Feature",
  "properties": {
    "addr:full":"9 Grove St Putnam CT 06260",
    "addr:housenumber":"9",
    "addr:postcode":"06260",
    "addr:street":"Grove St Putnam Ct",
    "iso:country":"US",
    "sg:address":"9 Grove St",
    "sg:city":"Putnam",
    "sg:classifiers":[
        {
            "category":"Recreation",
            "type":"Entertainment"
        }
    ],
    "sg:phone":"+1   ",
    "sg:postcode":"06260",
    "sg:province":"CT",
    "wof:name":"Ricks Billiards LLC",
    "wof:placetype":"venue"
},
  "geometry": {"coordinates":[-71.907143,41.912663],"type":"Point"}
}