{
  "type": "Feature",
  "properties": {
    "addr:full":"52 Belvidere Dr Stratford CT 06614",
    "addr:housenumber":"52",
    "addr:postcode":"06614",
    "addr:street":"Belvidere Dr",
    "iso:country":"US",
    "sg:address":"52 Belvidere Dr",
    "sg:city":"Stratford",
    "sg:classifiers":[
        {
            "category":"Professional",
            "subcategory":"Business Services",
            "type":"Services"
        }
    ],
    "sg:phone":"+1   ",
    "sg:postcode":"06614",
    "sg:province":"CT",
    "wof:name":"Beale Associates Ltd Partnr",
    "wof:placetype":"venue"
},
  "geometry": {"coordinates":[-73.12873500000001,41.203038],"type":"Point"}
}