{
  "type": "Feature",
  "properties": {
    "addr:full":"9 Creeping Hemlock Dr Norwalk CT 06851",
    "addr:housenumber":"9",
    "addr:postcode":"06851",
    "addr:street":"Creeping Hemlock Dr",
    "iso:country":"US",
    "sg:address":"9 Creeping Hemlock Dr",
    "sg:city":"Norwalk",
    "sg:classifiers":[
        {
            "category":"Organizations",
            "subcategory":"Religious Organization",
            "type":"Services"
        }
    ],
    "sg:phone":"+1   ",
    "sg:postcode":"06851",
    "sg:province":"CT",
    "wof:name":"Assembly Required",
    "wof:placetype":"venue"
},
  "geometry": {"coordinates":[-73.422021,41.151239],"type":"Point"}
}