{
  "type": "Feature",
  "properties": {
    "iso:country":"US",
    "sg:address":"32 Austin St",
    "sg:city":"Danbury",
    "sg:classifiers":[
        {
            "category":"Professional",
            "type":"Services"
        }
    ],
    "sg:phone":"+1 203 778 1464",
    "sg:postcode":"06810",
    "sg:province":"CT",
    "wof:name":"Minos Kitchen/Bathroom Rmdlng",
    "wof:placetype":"venue"
},
  "geometry": {"coordinates":[-73.43860100000001,41.396508],"type":"Point"}
}