{
  "type": "Feature",
  "properties": {
    "iso:country":"US",
    "sg:address":"1136 Albany Ave",
    "sg:city":"Hartford",
    "sg:classifiers":[
        {
            "category":"Professional",
            "subcategory":"Accounting & Tax Preparation",
            "type":"Services"
        }
    ],
    "sg:phone":"+1   ",
    "sg:postcode":"06112",
    "sg:province":"CT",
    "sg:tags":[
        "return"
    ],
    "wof:name":"Albany Accounting Service",
    "wof:placetype":"venue"
},
  "geometry": {"coordinates":[-72.695345,41.781884],"type":"Point"}
}