{
  "type": "Feature",
  "properties": {
    "iso:country":"US",
    "sg:address":"8 Phillips Dr",
    "sg:city":"Bethel",
    "sg:classifiers":[
        {
            "category":"Building & Trades",
            "subcategory":"Plumbing",
            "type":"Services"
        }
    ],
    "sg:phone":"+1 203 744 0035",
    "sg:postcode":"06801",
    "sg:province":"CT",
    "sg:tags":[
        "plumbing",
        "contractor"
    ],
    "wof:name":"Rotella Plumbing & Heating",
    "wof:placetype":"venue"
},
  "geometry": {"coordinates":[-73.360969,41.373961],"type":"Point"}
}