{
  "type": "Feature",
  "properties": {
    "iso:country":"US",
    "sg:address":"501 Jamestown Rd",
    "sg:city":"Stratford",
    "sg:classifiers":[
        {
            "category":"Real Estate",
            "subcategory":"Real Estate Agent",
            "type":"Services"
        }
    ],
    "sg:phone":"+1 203 378 3440",
    "sg:postcode":"06614",
    "sg:province":"CT",
    "sg:tags":[
        "management"
    ],
    "wof:name":"Patricia J Dolan Family",
    "wof:placetype":"venue"
},
  "geometry": {"coordinates":[-73.098741,41.2432],"type":"Point"}
}