{
  "type": "Feature",
  "properties": {
    "iso:country":"US",
    "sg:address":"2 Ferro Ct",
    "sg:city":"East Lyme",
    "sg:classifiers":[
        {
            "category":"Professional",
            "type":"Services"
        }
    ],
    "sg:phone":"+1 860 739 9365",
    "sg:postcode":"06333",
    "sg:province":"CT",
    "wof:name":"Careco Shoreline LLC",
    "wof:placetype":"venue"
},
  "geometry": {"coordinates":[-72.23758599999999,41.34791],"type":"Point"}
}