{
  "type": "Feature",
  "properties": {
    "iso:country":"US",
    "sg:address":"125 East Ave",
    "sg:city":"Norwalk",
    "sg:classifiers":[
        {
            "category":"Government",
            "subcategory":"Office",
            "type":"Public Place"
        }
    ],
    "sg:phone":"+1 203 854 7870",
    "sg:postcode":"06851",
    "sg:province":"CT",
    "sg:tags":[
        "village"
    ],
    "wof:name":"Norwalk Finance Director",
    "wof:placetype":"venue"
},
  "geometry": {"coordinates":[-73.407546,41.111064],"type":"Point"}
}