{
  "type": "Feature",
  "properties": {
    "addr:full":"136 Whiting St Plainville CT 06062",
    "addr:housenumber":"136",
    "addr:postcode":"06062",
    "addr:street":"Whiting St",
    "iso:country":"US",
    "sg:address":"136 Whiting St",
    "sg:city":"Plainville",
    "sg:classifiers":[
        {
            "category":"Food & Beverages",
            "subcategory":"Liquor & Beverages",
            "type":"Retail Goods"
        }
    ],
    "sg:phone":"+1 860 747 0570",
    "sg:postcode":"06062",
    "sg:province":"CT",
    "sg:tags":[
        "alcoholic"
    ],
    "wof:name":"Lostoccos Country Liquors",
    "wof:placetype":"venue"
},
  "geometry": {"coordinates":[-72.867057,41.664429],"type":"Point"}
}