{
  "type": "Feature",
  "properties": {
    "addr:full":"26 Campbell Dr Stamford CT 06903",
    "addr:housenumber":"26",
    "addr:postcode":"06903",
    "addr:street":"Campbell Dr",
    "iso:country":"US",
    "sg:address":"26 Campbell Dr",
    "sg:city":"Stamford",
    "sg:classifiers":[
        {
            "category":"Wholesale",
            "subcategory":"Motor Vehicles",
            "type":"Manufacturing & Wholesale Goods"
        }
    ],
    "sg:phone":"+1 203 322 3723",
    "sg:postcode":"06903",
    "sg:province":"CT",
    "sg:tags":[
        "trailer"
    ],
    "wof:name":"Transport Systems & Products",
    "wof:placetype":"venue"
},
  "geometry": {"coordinates":[-73.56024499999999,41.126614],"type":"Point"}
}