{
  "type": "Feature",
  "properties": {
    "iso:country":"US",
    "sg:address":"40 William Dr",
    "sg:city":"Jewett City",
    "sg:classifiers":[
        {
            "category":"Arts & Performance",
            "subcategory":"Theater",
            "type":"Entertainment"
        }
    ],
    "sg:phone":"+1   ",
    "sg:postcode":"06351",
    "sg:province":"CT",
    "sg:tags":[
        "theatrical"
    ],
    "wof:name":"Griswold Players Scholars",
    "wof:placetype":"venue"
},
  "geometry": {"coordinates":[-71.98017900000001,41.589118],"type":"Point"}
}