{
  "type": "Feature",
  "properties": {
    "iso:country":"US",
    "sg:address":"31 Woodchuck Ln",
    "sg:city":"Ridgefield",
    "sg:classifiers":[
        {
            "category":"Manufacturing",
            "subcategory":"Chemicals & Compounds",
            "type":"Manufacturing & Wholesale Goods"
        }
    ],
    "sg:phone":"+1 203 431 6287",
    "sg:postcode":"06877",
    "sg:province":"CT",
    "wof:name":"Dauntless Chemical",
    "wof:placetype":"venue"
},
  "geometry": {"coordinates":[-73.490064,41.259446],"type":"Point"}
}