{
  "type": "Feature",
  "properties": {
    "addr:full":"50 Clearview Ave Danbury CT 06811",
    "addr:housenumber":"50",
    "addr:postcode":"06811",
    "addr:street":"Clearview Ave",
    "iso:country":"US",
    "sg:address":"50 Clearview Ave",
    "sg:city":"Danbury",
    "sg:classifiers":[
        {
            "category":"Building & Trades",
            "subcategory":"Cleaning & Sanitation",
            "type":"Services"
        }
    ],
    "sg:phone":"+1   ",
    "sg:postcode":"06811",
    "sg:province":"CT",
    "sg:tags":[
        "janitorial"
    ],
    "wof:name":"ABC Janitorial Service",
    "wof:placetype":"venue"
},
  "geometry": {"coordinates":[-73.435132,41.450515],"type":"Point"}
}