{
  "type": "Feature",
  "properties": {
    "addr:full":"623 Steamboat Rd Greenwich CT 06830",
    "addr:housenumber":"623",
    "addr:postcode":"06830",
    "addr:street":"Steamboat Rd",
    "iso:country":"US",
    "sg:address":"623 Steamboat Rd",
    "sg:city":"Greenwich",
    "sg:classifiers":[
        {
            "category":"Health Services",
            "subcategory":"Doctor",
            "type":"Services"
        }
    ],
    "sg:phone":"+1 203 661 7129",
    "sg:postcode":"06830",
    "sg:province":"CT",
    "sg:tags":[
        "physician",
        "surgeon"
    ],
    "wof:name":"Roland Foraste MD",
    "wof:placetype":"venue"
},
  "geometry": {"coordinates":[-73.622163,41.013372],"type":"Point"}
}