{
  "type": "Feature",
  "properties": {
    "iso:country":"US",
    "sg:address":"35 Woods End Dr",
    "sg:city":"Wilton",
    "sg:classifiers":[
        {
            "category":"Banks & Credit Unions",
            "subcategory":"Investment Brokerage",
            "type":"Services"
        }
    ],
    "sg:phone":"+1 203 762 5661",
    "sg:postcode":"06897",
    "sg:province":"CT",
    "sg:tags":[
        "security"
    ],
    "wof:name":"Thayer Pond Capital",
    "wof:placetype":"venue"
},
  "geometry": {"coordinates":[-73.46507699999999,41.181141],"type":"Point"}
}