{
  "type": "Feature",
  "properties": {
    "addr:full":"81 Arkay Dr Higganum CT 06441",
    "addr:housenumber":"81",
    "addr:postcode":"06441",
    "addr:street":"Arkay Dr Higganum Ct",
    "iso:country":"US",
    "sg:address":"81 Arkay Dr",
    "sg:city":"Higganum",
    "sg:classifiers":[
        {
            "category":"Professional",
            "subcategory":"Business Services",
            "type":"Services"
        }
    ],
    "sg:phone":"+1   ",
    "sg:postcode":"06441",
    "sg:province":"CT",
    "wof:name":"Precourt Home Inspection Ltd",
    "wof:placetype":"venue"
},
  "geometry": {"coordinates":[-72.582125,41.461697],"type":"Point"}
}