{
  "type": "Feature",
  "properties": {
    "addr:full":"38 W Flat Hill Rd Southbury CT 06488",
    "addr:housenumber":"38",
    "addr:postcode":"06488",
    "addr:street":"W Flat Hill Rd",
    "iso:country":"US",
    "sg:address":"38 W Flat Hill Rd",
    "sg:city":"Southbury",
    "sg:classifiers":[
        {
            "category":"Wholesale",
            "subcategory":"Electrical",
            "type":"Manufacturing & Wholesale Goods"
        }
    ],
    "sg:phone":"+1 203 264 4147",
    "sg:postcode":"06488",
    "sg:province":"CT",
    "sg:tags":[
        "e",
        "electronic",
        "contractor"
    ],
    "wof:name":"Communication Concepts",
    "wof:placetype":"venue"
},
  "geometry": {"coordinates":[-73.278064,41.477773],"type":"Point"}
}