{
  "type": "Feature",
  "properties": {
    "addr:full":"78 Butler St New Haven CT 06511",
    "addr:housenumber":"78",
    "addr:postcode":"06511",
    "addr:street":"Butler St",
    "iso:country":"US",
    "sg:address":"78 Butler St",
    "sg:city":"New Haven",
    "sg:classifiers":[
        {
            "category":"Organizations",
            "subcategory":"Religious Organization",
            "type":"Services"
        }
    ],
    "sg:phone":"+1   ",
    "sg:postcode":"06511",
    "sg:province":"CT",
    "wof:name":"People Mssionary Baptst Church",
    "wof:placetype":"venue"
},
  "geometry": {"coordinates":[-72.930233,41.331969],"type":"Point"}
}