{
  "type": "Feature",
  "properties": {
    "addr:full":"383 Grand Ave New Haven CT 06513",
    "addr:housenumber":"383",
    "addr:postcode":"06513",
    "addr:street":"Grand Ave",
    "iso:country":"US",
    "sg:address":"383 Grand Ave",
    "sg:city":"New Haven",
    "sg:classifiers":[
        {
            "category":"Freight",
            "type":"Transportation"
        }
    ],
    "sg:phone":"+1 203 410 2073",
    "sg:postcode":"06513",
    "sg:province":"CT",
    "sg:tags":[
        "arrangement"
    ],
    "wof:name":"Greenery",
    "wof:placetype":"venue"
},
  "geometry": {"coordinates":[-72.902961,41.308541],"type":"Point"}
}