{
  "type": "Feature",
  "properties": {
    "addr:full":"1666 Meriden Ave Southington CT 06489",
    "addr:housenumber":"1666",
    "addr:postcode":"06489",
    "addr:street":"Meriden Ave",
    "iso:country":"US",
    "sg:address":"1666 Meriden Ave",
    "sg:city":"Southington",
    "sg:phone":"+1 860 621 5534",
    "sg:postcode":"06489",
    "sg:province":"CT",
    "wof:name":"Ace Appliance Sales Svc & Part",
    "wof:placetype":"venue"
},
  "geometry": {"coordinates":[-72.853047,41.558935],"type":"Point"}
}