{
  "type": "Feature",
  "properties": {
    "iso:country":"US",
    "sg:address":"108 Hickory Hill Rd",
    "sg:city":"New Britain",
    "sg:classifiers":[
        {
            "category":"Building & Trades",
            "subcategory":"Construction",
            "type":"Services"
        }
    ],
    "sg:phone":"+1 860 224 7171",
    "sg:postcode":"06052",
    "sg:province":"CT",
    "sg:tags":[
        "floor",
        "laying",
        "contractor"
    ],
    "wof:name":"Prep Inc",
    "wof:placetype":"venue"
},
  "geometry": {"coordinates":[-72.819428,41.658056],"type":"Point"}
}