{
  "type": "Feature",
  "properties": {
    "addr:full":"20 High Ridge Rd Hamden CT 06514",
    "addr:housenumber":"20",
    "addr:postcode":"06514",
    "addr:street":"High Ridge Rd",
    "iso:country":"US",
    "sg:address":"20 High Ridge Rd",
    "sg:city":"Hamden",
    "sg:classifiers":[
        {
            "category":"Professional",
            "subcategory":"Engineering",
            "type":"Services"
        }
    ],
    "sg:phone":"+1   ",
    "sg:postcode":"06514",
    "sg:province":"CT",
    "sg:tags":[
        "consulting",
        "computer",
        "network"
    ],
    "wof:name":"Engineering Networks LLC",
    "wof:placetype":"venue"
},
  "geometry": {"coordinates":[-72.952657,41.370591],"type":"Point"}
}