{
  "type": "Feature",
  "properties": {
    "iso:country":"US",
    "sg:address":"625 E Main St",
    "sg:city":"Branford",
    "sg:classifiers":[
        {
            "category":"Professional",
            "subcategory":"Accounting & Tax Preparation",
            "type":"Services"
        }
    ],
    "sg:phone":"+1 203 488 1334",
    "sg:postcode":"06405",
    "sg:province":"CT",
    "sg:tags":[
        "accountant"
    ],
    "wof:name":"Richard B Keller CPA",
    "wof:placetype":"venue"
},
  "geometry": {"coordinates":[-72.76477800000001,41.299448],"type":"Point"}
}