{
  "type": "Feature",
  "properties": {
    "iso:country":"US",
    "sg:address":"388 Salmon Brook St",
    "sg:city":"Granby",
    "sg:classifiers":[
        {
            "category":"Retail",
            "subcategory":"Auto Repair",
            "type":"Services"
        }
    ],
    "sg:phone":"+1   ",
    "sg:postcode":"06035",
    "sg:province":"CT",
    "sg:tags":[
        "general"
    ],
    "wof:name":"Granby Garage",
    "wof:placetype":"venue"
},
  "geometry": {"coordinates":[-72.794631,41.969032],"type":"Point"}
}