{
  "type": "Feature",
  "properties": {
    "addr:full":"233 Meriden Rd Waterbury CT 06705",
    "addr:housenumber":"233",
    "addr:postcode":"06705",
    "addr:street":"Meriden Rd",
    "iso:country":"US",
    "sg:address":"233 Meriden Rd",
    "sg:city":"Waterbury",
    "sg:classifiers":[
        {
            "category":"Retail",
            "subcategory":"Laundry & Dry Cleaning",
            "type":"Services"
        }
    ],
    "sg:phone":"+1 203 755 1374",
    "sg:postcode":"06705",
    "sg:province":"CT",
    "sg:tags":[
        "cleaners"
    ],
    "wof:name":"Clean Shop",
    "wof:placetype":"venue"
},
  "geometry": {"coordinates":[-73.010575,41.550383],"type":"Point"}
}