{
  "type": "Feature",
  "properties": {
    "iso:country":"US",
    "sg:address":"62 Long Hill Dr",
    "sg:city":"Glastonbury",
    "sg:classifiers":[
        {
            "category":"Professional",
            "subcategory":"Advertising",
            "type":"Services"
        }
    ],
    "sg:phone":"+1   ",
    "sg:postcode":"06033",
    "sg:province":"CT",
    "sg:tags":[
        "agency"
    ],
    "wof:name":"Andy Zeldins Advertising",
    "wof:placetype":"venue"
},
  "geometry": {"coordinates":[-72.601569,41.729063],"type":"Point"}
}