{
  "type": "Feature",
  "properties": {
    "addr:full":"60 Riding Club Rd Wilton CT 06897",
    "addr:housenumber":"60",
    "addr:postcode":"06897",
    "addr:street":"Riding Club Rd",
    "iso:country":"US",
    "sg:address":"60 Riding Club Rd",
    "sg:city":"Wilton",
    "sg:classifiers":[
        {
            "category":"Organizations",
            "subcategory":"Community Association",
            "type":"Services"
        }
    ],
    "sg:phone":"+1 203 762 1727",
    "sg:postcode":"06897",
    "sg:province":"CT",
    "sg:tags":[
        "club"
    ],
    "wof:name":"Wilton Riding Club Barn",
    "wof:placetype":"venue"
},
  "geometry": {"coordinates":[-73.45080799999999,41.214864],"type":"Point"}
}