{
  "type": "Feature",
  "properties": {
    "iso:country":"US",
    "sg:address":"92 Trolley Crossing Ln",
    "sg:city":"Middletown",
    "sg:classifiers":[
        {
            "category":"Personal",
            "subcategory":"Beauty Salon",
            "type":"Services"
        }
    ],
    "sg:phone":"+1   ",
    "sg:postcode":"06457",
    "sg:province":"CT",
    "sg:tags":[
        "shop"
    ],
    "wof:name":"Advanced Hair & Transplant Cen",
    "wof:placetype":"venue"
},
  "geometry": {"coordinates":[-72.698621,41.599383],"type":"Point"}
}