{
  "type": "Feature",
  "properties": {
    "addr:full":"79 Washington Ave North Haven CT 06473",
    "addr:housenumber":"79",
    "addr:postcode":"06473",
    "addr:street":"Washington Ave;Haven",
    "iso:country":"US",
    "sg:address":"79 Washington Ave",
    "sg:city":"North Haven",
    "sg:classifiers":[
        {
            "category":"Banks & Credit Unions",
            "subcategory":"Bank",
            "type":"Services"
        }
    ],
    "sg:phone":"+1 203 234 1554",
    "sg:postcode":"06473",
    "sg:province":"CT",
    "sg:tags":[
        "state",
        "chartered",
        "savings"
    ],
    "wof:name":"Peoples Bank",
    "wof:placetype":"venue"
},
  "geometry": {"coordinates":[-72.85919,41.391773],"type":"Point"}
}