{
  "type": "Feature",
  "properties": {
    "addr:full":"139 Hartford Rd Manchester CT 06040",
    "addr:housenumber":"139",
    "addr:postcode":"06040",
    "addr:street":"Hartford Rd",
    "iso:country":"US",
    "sg:address":"139 Hartford Rd",
    "sg:city":"Manchester",
    "sg:classifiers":[
        {
            "category":"Travel",
            "subcategory":"Hotels & Motels",
            "type":"Entertainment"
        }
    ],
    "sg:phone":"+1   ",
    "sg:postcode":"06040",
    "sg:province":"CT",
    "sg:tags":[
        "operation"
    ],
    "wof:name":"Mansion Inn Bed and Breakfast",
    "wof:placetype":"venue"
},
  "geometry": {"coordinates":[-72.52431300000001,41.764559],"type":"Point"}
}