{
  "type": "Feature",
  "properties": {
    "iso:country":"US",
    "sg:address":"17 Laurel Ln",
    "sg:city":"Greenwich",
    "sg:classifiers":[
        {
            "category":"Professional",
            "subcategory":"Business Services",
            "type":"Services"
        }
    ],
    "sg:phone":"+1   ",
    "sg:postcode":"06830",
    "sg:province":"CT",
    "wof:name":"Ktb Design LLC",
    "wof:placetype":"venue"
},
  "geometry": {"coordinates":[-73.633088,41.059617],"type":"Point"}
}