{
  "type": "Feature",
  "properties": {
    "addr:full":"572 Washington St Middletown CT 06457",
    "addr:housenumber":"572",
    "addr:postcode":"06457",
    "addr:street":"Washington St",
    "iso:country":"US",
    "sg:address":"572 Washington St",
    "sg:city":"Middletown",
    "sg:classifiers":[
        {
            "category":"Autos & Motor Vehicles",
            "subcategory":"Fuel & Gas Station",
            "type":"Retail Goods"
        }
    ],
    "sg:phone":"+1 860 346 7803",
    "sg:postcode":"06457",
    "sg:province":"CT",
    "wof:name":"Citgo",
    "wof:placetype":"venue"
},
  "geometry": {"coordinates":[-72.67072,41.55563],"type":"Point"}
}