{
  "type": "Feature",
  "properties": {
    "iso:country":"US",
    "sg:address":"11 Riverdale Ave",
    "sg:city":"Port Chester",
    "sg:classifiers":[
        {
            "category":"Professional",
            "subcategory":"Engineering",
            "type":"Services"
        }
    ],
    "sg:phone":"+1 914 939 0224",
    "sg:postcode":"10573",
    "sg:province":"CT",
    "sg:tags":[
        "civil",
        "surveyor",
        "land",
        "engineer"
    ],
    "wof:name":"J A Kirby Company LLP",
    "wof:placetype":"venue"
},
  "geometry": {"coordinates":[-73.656789,41.014333],"type":"Point"}
}