{
  "type": "Feature",
  "properties": {
    "addr:full":"6 Cortland Pl Oxford CT 06478",
    "addr:housenumber":"6",
    "addr:postcode":"06478",
    "addr:street":"Cortland Pl",
    "iso:country":"US",
    "sg:address":"6 Cortland Pl",
    "sg:city":"Oxford",
    "sg:classifiers":[
        {
            "category":"Professional",
            "subcategory":"Business Services",
            "type":"Services"
        }
    ],
    "sg:phone":"+1   ",
    "sg:postcode":"06478",
    "sg:province":"CT",
    "sg:tags":[
        "commerce",
        "retail"
    ],
    "wof:name":"Innovtive Tchnical Systems LLC",
    "wof:placetype":"venue"
},
  "geometry": {"coordinates":[-73.145399,41.434744],"type":"Point"}
}