{
  "type": "Feature",
  "properties": {
    "addr:full":"190 Trumbull St Hartford CT 06103",
    "addr:housenumber":"190",
    "addr:postcode":"06103",
    "addr:street":"Trumbull St",
    "iso:country":"US",
    "sg:address":"190 Trumbull St",
    "sg:city":"Hartford",
    "sg:classifiers":[
        {
            "category":"Banks & Credit Unions",
            "subcategory":"Investment Brokerage",
            "type":"Services"
        }
    ],
    "sg:phone":"+1 860 524 0900",
    "sg:postcode":"06103",
    "sg:province":"CT",
    "sg:tags":[
        "firm",
        "brokerage"
    ],
    "wof:name":"Charles Schwab",
    "wof:placetype":"venue"
},
  "geometry": {"coordinates":[-72.675477,41.767555],"type":"Point"}
}