{
  "type": "Feature",
  "properties": {
    "addr:full":"7 Pickett District Rd New Milford CT 06776",
    "addr:housenumber":"7",
    "addr:postcode":"06776",
    "addr:street":"Pickett District Rd",
    "iso:country":"US",
    "sg:address":"7 Pickett District Rd",
    "sg:city":"New Milford",
    "sg:classifiers":[
        {
            "category":"Health Services",
            "subcategory":"Doctor",
            "type":"Services"
        }
    ],
    "sg:phone":"+1   ",
    "sg:postcode":"06776",
    "sg:province":"CT",
    "wof:name":"Lambert Katherine M DMD",
    "wof:placetype":"venue"
},
  "geometry": {"coordinates":[-73.41418899999999,41.565208],"type":"Point"}
}