{
  "type": "Feature",
  "properties": {
    "iso:country":"US",
    "sg:address":"60 Connolly Pkwy",
    "sg:city":"Hamden",
    "sg:classifiers":[
        {
            "category":"Real Estate",
            "subcategory":"Real Estate Agent",
            "type":"Services"
        }
    ],
    "sg:phone":"+1 203 230 1929",
    "sg:postcode":"06514",
    "sg:province":"CT",
    "sg:tags":[
        "management"
    ],
    "wof:name":"Prime Property Management",
    "wof:placetype":"venue"
},
  "geometry": {"coordinates":[-72.918402,41.366723],"type":"Point"}
}