{
  "type": "Feature",
  "properties": {
    "iso:country":"US",
    "sg:address":"360 W Putnam Ave",
    "sg:city":"Greenwich",
    "sg:classifiers":[
        {
            "category":"Social Services",
            "type":"Services"
        }
    ],
    "sg:phone":"+1 203 869 7303",
    "sg:postcode":"06830",
    "sg:province":"CT",
    "sg:tags":[
        "counselor",
        "marriage",
        "family"
    ],
    "wof:name":"Wendy Aronsson",
    "wof:placetype":"venue"
},
  "geometry": {"coordinates":[-73.639337,41.022293],"type":"Point"}
}