{
  "type": "Feature",
  "properties": {
    "addr:full":"831 Rubber Ave Naugatuck CT 06770",
    "addr:housenumber":"831",
    "addr:postcode":"06770",
    "addr:street":"Rubber Ave Naugatuck Ct",
    "iso:country":"US",
    "sg:address":"831 Rubber Ave",
    "sg:city":"Naugatuck",
    "sg:classifiers":[
        {
            "category":"Retail",
            "subcategory":"Auto Repair",
            "type":"Services"
        }
    ],
    "sg:phone":"+1   ",
    "sg:postcode":"06770",
    "sg:province":"CT",
    "sg:tags":[
        "body"
    ],
    "wof:name":"Rays Sales and Service",
    "wof:placetype":"venue"
},
  "geometry": {"coordinates":[-73.083866,41.494],"type":"Point"}
}