{
  "type": "Feature",
  "properties": {
    "iso:country":"US",
    "sg:address":"32 Forest St Exd",
    "sg:city":"Branford",
    "sg:classifiers":[
        {
            "category":"Professional",
            "subcategory":"Art Services",
            "type":"Services"
        }
    ],
    "sg:phone":"+1   ",
    "sg:postcode":"06405",
    "sg:province":"CT",
    "sg:tags":[
        "commercial",
        "design"
    ],
    "wof:name":"Kazmercyk Design",
    "wof:placetype":"venue"
},
  "geometry": {"coordinates":[-72.840946,41.263139],"type":"Point"}
}