{
  "type": "Feature",
  "properties": {
    "addr:full":"18 Banks Dr Wilton CT 06897",
    "addr:housenumber":"18",
    "addr:postcode":"06897",
    "addr:street":"Banks Dr",
    "iso:country":"US",
    "sg:address":"18 Banks Dr",
    "sg:city":"Wilton",
    "sg:classifiers":[
        {
            "category":"Building & Trades",
            "subcategory":"Construction",
            "type":"Services"
        }
    ],
    "sg:phone":"+1 203 762 8033",
    "sg:postcode":"06897",
    "sg:province":"CT",
    "sg:tags":[
        "general",
        "contractor"
    ],
    "wof:name":"Polito Home Builders",
    "wof:placetype":"venue"
},
  "geometry": {"coordinates":[-73.403481,41.195406],"type":"Point"}
}