{
  "type": "Feature",
  "properties": {
    "addr:full":"88 Vernon St Waterbury CT 06708",
    "addr:housenumber":"88",
    "addr:postcode":"06708",
    "addr:street":"Vernon St Waterbury Ct",
    "iso:country":"US",
    "sg:address":"88 Vernon St",
    "sg:city":"Waterbury",
    "sg:classifiers":[
        {
            "category":"Freight",
            "type":"Transportation"
        }
    ],
    "sg:phone":"+1 203 573 8026",
    "sg:postcode":"06708",
    "sg:province":"CT",
    "sg:tags":[
        "cartage",
        "trucking"
    ],
    "wof:name":"P & M Trucking",
    "wof:placetype":"venue"
},
  "geometry": {"coordinates":[-73.060975,41.550675],"type":"Point"}
}