{
  "type": "Feature",
  "properties": {
    "addr:full":"1151 Washington St Middletown CT 06457",
    "addr:housenumber":"1151",
    "addr:postcode":"06457",
    "addr:street":"Washington St",
    "iso:country":"US",
    "sg:address":"1151 Washington St",
    "sg:city":"Middletown",
    "sg:classifiers":[
        {
            "category":"Real Estate",
            "subcategory":"Real Estate Agent",
            "type":"Services"
        }
    ],
    "sg:phone":"+1 860 344 8815",
    "sg:postcode":"06457",
    "sg:province":"CT",
    "wof:name":"Tarragon Management Inc",
    "wof:placetype":"venue"
},
  "geometry": {"coordinates":[-72.689774,41.550455],"type":"Point"}
}