{
  "type": "Feature",
  "properties": {
    "addr:full":"933 E Main St Bridgeport CT 06608",
    "addr:housenumber":"933",
    "addr:postcode":"06608",
    "addr:street":"E Main St",
    "iso:country":"US",
    "sg:address":"933 E Main St",
    "sg:city":"Bridgeport",
    "sg:classifiers":[
        {
            "category":"Home & Garden",
            "subcategory":"Home Furnishings",
            "type":"Retail Goods"
        }
    ],
    "sg:phone":"+1 203 367 6280",
    "sg:postcode":"06608",
    "sg:province":"CT",
    "sg:tags":[
        "bedspread"
    ],
    "wof:name":"Factory Bedding & Furniture",
    "wof:placetype":"venue"
},
  "geometry": {"coordinates":[-73.180796,41.188011],"type":"Point"}
}