{
  "type": "Feature",
  "properties": {
    "addr:full":"10 Camphill Rd Northfield CT 06778",
    "addr:housenumber":"10",
    "addr:postcode":"06778",
    "addr:street":"Camphill Rd",
    "iso:country":"US",
    "sg:address":"10 Camphill Rd",
    "sg:city":"Northfield",
    "sg:classifiers":[
        {
            "category":"Organizations",
            "subcategory":"Religious Organization",
            "type":"Services"
        }
    ],
    "sg:phone":"+1   ",
    "sg:postcode":"06778",
    "sg:province":"CT",
    "wof:name":"Northfeld Cngregational Church",
    "wof:placetype":"venue"
},
  "geometry": {"coordinates":[-73.11134800000001,41.695435],"type":"Point"}
}