{
  "type": "Feature",
  "properties": {
    "addr:full":"331 Griffin Ave Bridgeport CT 06606",
    "addr:housenumber":"331",
    "addr:postcode":"06606",
    "addr:street":"Griffin Ave",
    "iso:country":"US",
    "sg:address":"331 Griffin Ave",
    "sg:city":"Bridgeport",
    "sg:classifiers":[
        {
            "category":"Real Estate",
            "subcategory":"Developer",
            "type":"Services"
        }
    ],
    "sg:phone":"+1 203 371 8834",
    "sg:postcode":"06606",
    "sg:province":"CT",
    "wof:name":"Eaton Enterprises",
    "wof:placetype":"venue"
},
  "geometry": {"coordinates":[-73.20398400000001,41.219376],"type":"Point"}
}