{
  "type": "Feature",
  "properties": {
    "iso:country":"US",
    "sg:address":"40 Jennings Rd",
    "sg:city":"Hartford",
    "sg:classifiers":[
        {
            "category":"Government",
            "subcategory":"Office",
            "type":"Public Place"
        }
    ],
    "sg:phone":"+1 860 543 8753",
    "sg:postcode":"06120",
    "sg:province":"CT",
    "sg:tags":[
        "management"
    ],
    "wof:name":"Public Works Dept",
    "wof:placetype":"venue"
},
  "geometry": {"coordinates":[-72.653143,41.785726],"type":"Point"}
}