{
  "type": "Feature",
  "properties": {
    "addr:full":"200 Henry St Stamford CT 06902",
    "addr:housenumber":"200",
    "addr:postcode":"06902",
    "addr:street":"Henry St",
    "iso:country":"US",
    "sg:address":"200 Henry St",
    "sg:city":"Stamford",
    "sg:classifiers":[
        {
            "category":"Real Estate",
            "subcategory":"Real Estate Agent",
            "type":"Services"
        }
    ],
    "sg:phone":"+1 203 348 2024",
    "sg:postcode":"06902",
    "sg:province":"CT",
    "wof:name":"Stamford Industrial Dev",
    "wof:placetype":"venue"
},
  "geometry": {"coordinates":[-73.534554,41.044063],"type":"Point"}
}