{
  "type": "Feature",
  "properties": {
    "iso:country":"US",
    "sg:address":"250 Freight St",
    "sg:city":"Waterbury",
    "sg:classifiers":[
        {
            "category":"Government",
            "subcategory":"Office",
            "type":"Public Place"
        }
    ],
    "sg:phone":"+1 203 805 7400",
    "sg:postcode":"06702",
    "sg:province":"CT",
    "sg:tags":[
        "state",
        "program",
        "health"
    ],
    "wof:name":"Connecticut Mental Retardation",
    "wof:placetype":"venue"
},
  "geometry": {"coordinates":[-73.051059,41.554014],"type":"Point"}
}