{
  "type": "Feature",
  "properties": {
    "iso:country":"US",
    "sg:address":"139 Center St",
    "sg:city":"Bristol",
    "sg:classifiers":[
        {
            "category":"Manufacturing",
            "subcategory":"Printing",
            "type":"Manufacturing & Wholesale Goods"
        }
    ],
    "sg:phone":"+1 860 584 8218",
    "sg:postcode":"06010",
    "sg:province":"CT",
    "sg:tags":[
        "lithographic",
        "commercial"
    ],
    "wof:name":"Rapid Print & Copy LLC",
    "wof:placetype":"venue"
},
  "geometry": {"coordinates":[-72.944391,41.676225],"type":"Point"}
}