{
  "type": "Feature",
  "properties": {
    "addr:full":"140 Sunny Meadow Rd Branford CT 06405",
    "addr:housenumber":"140",
    "addr:postcode":"06405",
    "addr:street":"Sunny Meadow Rd",
    "iso:country":"US",
    "sg:address":"140 Sunny Meadow Rd",
    "sg:city":"Branford",
    "sg:classifiers":[
        {
            "category":"Building & Trades",
            "subcategory":"Construction",
            "type":"Services"
        }
    ],
    "sg:phone":"+1 203 481 6842",
    "sg:postcode":"06405",
    "sg:province":"CT",
    "sg:tags":[
        "hanging",
        "contractor"
    ],
    "wof:name":"Valentino Painting",
    "wof:placetype":"venue"
},
  "geometry": {"coordinates":[-72.85089000000001,41.27625],"type":"Point"}
}