{
  "type": "Feature",
  "properties": {
    "iso:country":"US",
    "sg:address":"95 E Main St",
    "sg:city":"Meriden",
    "sg:classifiers":[
        {
            "category":"Professional",
            "subcategory":"Advertising",
            "type":"Services"
        }
    ],
    "sg:phone":"+1 203 238 7028",
    "sg:postcode":"06450",
    "sg:province":"CT",
    "wof:name":"Marketing Graphics",
    "wof:placetype":"venue"
},
  "geometry": {"coordinates":[-72.80009800000001,41.537108],"type":"Point"}
}