{
  "type": "Feature",
  "properties": {
    "addr:full":"53 Linden St New Haven CT 06511",
    "addr:housenumber":"53",
    "addr:postcode":"06511",
    "addr:street":"Linden St",
    "iso:country":"US",
    "sg:address":"53 Linden St",
    "sg:city":"New Haven",
    "sg:classifiers":[
        {
            "category":"Building & Trades",
            "subcategory":"Plumbing",
            "type":"Services"
        }
    ],
    "sg:phone":"+1 203 932 5960",
    "sg:postcode":"06511",
    "sg:province":"CT",
    "sg:tags":[
        "contractor"
    ],
    "wof:name":"G Hotchkiss Hvac Consultant LL",
    "wof:placetype":"venue"
},
  "geometry": {"coordinates":[-72.910737,41.32065],"type":"Point"}
}