{
  "type": "Feature",
  "properties": {
    "iso:country":"US",
    "sg:address":"2 Brewery Sq",
    "sg:city":"New Haven",
    "sg:classifiers":[
        {
            "category":"Professional",
            "subcategory":"Lawyer & Legal Services",
            "type":"Services"
        }
    ],
    "sg:phone":"+1 203 785 9240",
    "sg:postcode":"06513",
    "sg:province":"CT",
    "sg:tags":[
        "attorney"
    ],
    "wof:name":"Mark A Shiffrin",
    "wof:placetype":"venue"
},
  "geometry": {"coordinates":[-72.891683,41.304939],"type":"Point"}
}