{
  "type": "Feature",
  "properties": {
    "addr:full":"8 Mill Plain Rd Danbury CT 06811",
    "addr:housenumber":"8",
    "addr:postcode":"06811",
    "addr:street":"Mill Plain Rd",
    "iso:country":"US",
    "sg:address":"8 Mill Plain Rd",
    "sg:city":"Danbury",
    "sg:classifiers":[
        {
            "category":"Shopping",
            "subcategory":"Florist",
            "type":"Retail Goods"
        }
    ],
    "sg:phone":"+1 203 790 1881",
    "sg:postcode":"06811",
    "sg:province":"CT",
    "wof:name":"Driscoll's Florist",
    "wof:placetype":"venue"
},
  "geometry": {"coordinates":[-73.493537,41.387238],"type":"Point"}
}