{
  "type": "Feature",
  "properties": {
    "iso:country":"US",
    "sg:address":"1036 Main St",
    "sg:city":"Branford",
    "sg:classifiers":[
        {
            "category":"Wholesale",
            "subcategory":"Durable Goods & Equipment",
            "type":"Manufacturing & Wholesale Goods"
        }
    ],
    "sg:phone":"+1 203 488 7603",
    "sg:postcode":"06405",
    "sg:province":"CT",
    "sg:tags":[
        "importer"
    ],
    "wof:name":"Tuscan Shamrock",
    "wof:placetype":"venue"
},
  "geometry": {"coordinates":[-72.810811,41.282341],"type":"Point"}
}