{
  "type": "Feature",
  "properties": {
    "iso:country":"US",
    "sg:address":"184 Danbury Rd",
    "sg:city":"New Milford",
    "sg:classifiers":[
        {
            "category":"Health Services",
            "subcategory":"Doctor",
            "type":"Services"
        }
    ],
    "sg:phone":"+1   ",
    "sg:postcode":"06776",
    "sg:province":"CT",
    "wof:name":"Dorrance T Kelly DDS",
    "wof:placetype":"venue"
},
  "geometry": {"coordinates":[-73.418482,41.549701],"type":"Point"}
}