{
  "type": "Feature",
  "properties": {
    "addr:full":"75 Cedar St Norwalk CT 06854",
    "addr:housenumber":"75",
    "addr:postcode":"06854",
    "addr:street":"Cedar St",
    "iso:country":"US",
    "sg:address":"75 Cedar St",
    "sg:city":"Norwalk",
    "sg:classifiers":[
        {
            "category":"Home & Garden",
            "subcategory":"Furniture",
            "type":"Retail Goods"
        }
    ],
    "sg:phone":"+1 203 854 6687",
    "sg:postcode":"06854",
    "sg:province":"CT",
    "sg:tags":[
        "repair"
    ],
    "wof:name":"Francos Refinishing and Sales",
    "wof:placetype":"venue"
},
  "geometry": {"coordinates":[-73.425961,41.103894],"type":"Point"}
}