{
  "type": "Feature",
  "properties": {
    "addr:full":"15 Charter Oak Rd Southbury CT 06488",
    "addr:housenumber":"15",
    "addr:postcode":"06488",
    "addr:street":"Charter Oak Rd",
    "iso:country":"US",
    "sg:address":"15 Charter Oak Rd",
    "sg:city":"Southbury",
    "sg:classifiers":[
        {
            "category":"Professional",
            "subcategory":"Computer Services",
            "type":"Services"
        }
    ],
    "sg:phone":"+1 203 267 7710",
    "sg:postcode":"06488",
    "sg:province":"CT",
    "sg:tags":[
        "cd-rom",
        "software"
    ],
    "wof:name":"Vibrant Technologies Inc.",
    "wof:placetype":"venue"
},
  "geometry": {"coordinates":[-73.24988,41.501499],"type":"Point"}
}