{
  "type": "Feature",
  "properties": {
    "addr:full":"33 Locust Ln Farmington CT 06032",
    "addr:housenumber":"33",
    "addr:postcode":"06032",
    "addr:street":"Locust Ln",
    "iso:country":"US",
    "sg:address":"33 Locust Ln",
    "sg:city":"Farmington",
    "sg:classifiers":[
        {
            "category":"Professional",
            "type":"Services"
        }
    ],
    "sg:phone":"+1 860 676 9418",
    "sg:postcode":"06032",
    "sg:province":"CT",
    "wof:name":"4kids2wear",
    "wof:placetype":"venue"
},
  "geometry": {"coordinates":[-72.87326400000001,41.730829],"type":"Point"}
}