{
  "type": "Feature",
  "properties": {
    "iso:country":"US",
    "sg:address":"273 Canal St E",
    "sg:city":"Shelton",
    "sg:classifiers":[
        {
            "category":"Professional",
            "subcategory":"Computer Services",
            "type":"Services"
        }
    ],
    "sg:phone":"+1   ",
    "sg:postcode":"06484",
    "sg:province":"CT",
    "sg:tags":[
        "programing",
        "custom"
    ],
    "wof:name":"Ibis Jewelry Systems",
    "wof:placetype":"venue"
},
  "geometry": {"coordinates":[-73.09616800000001,41.321103],"type":"Point"}
}