{
  "type": "Feature",
  "properties": {
    "iso:country":"US",
    "sg:address":"66 Birchwood Dr",
    "sg:city":"Bristol",
    "sg:classifiers":[
        {
            "category":"Professional",
            "subcategory":"Business Services",
            "type":"Services"
        }
    ],
    "sg:phone":"+1   ",
    "sg:postcode":"06010",
    "sg:province":"CT",
    "wof:name":"Edward J Eichner",
    "wof:placetype":"venue"
},
  "geometry": {"coordinates":[-72.913167,41.712045],"type":"Point"}
}