{
  "type": "Feature",
  "properties": {
    "addr:full":"31 Oxford Ct Simsbury CT 06070",
    "addr:housenumber":"31",
    "addr:postcode":"06070",
    "addr:street":"Oxford Ct",
    "iso:country":"US",
    "sg:address":"31 Oxford Ct",
    "sg:city":"Simsbury",
    "sg:classifiers":[
        {
            "category":"Home & Garden",
            "subcategory":"Furniture",
            "type":"Retail Goods"
        }
    ],
    "sg:phone":"+1 860 651 6054",
    "sg:postcode":"06070",
    "sg:province":"CT",
    "wof:name":"Naked Mountain LLC",
    "wof:placetype":"venue"
},
  "geometry": {"coordinates":[-72.80083999999999,41.884276],"type":"Point"}
}