{
  "type": "Feature",
  "properties": {
    "iso:country":"US",
    "sg:address":"506 Old Whitfield St",
    "sg:city":"Guilford",
    "sg:classifiers":[
        {
            "category":"Restaurant",
            "type":"Food & Drink"
        }
    ],
    "sg:menulink":"http://www.allmenus.com/ct/guilford/47580-the-stone-house-restaurant/menu/",
    "sg:phone":"+1 203 458 3700",
    "sg:postcode":"06437",
    "sg:province":"CT",
    "sg:tags":[
        "seafood",
        "american"
    ],
    "wof:name":"The Stone House Restaurant",
    "wof:placetype":"venue"
},
  "geometry": {"coordinates":[-72.666635,41.272651],"type":"Point"}
}