{
  "type": "Feature",
  "properties": {
    "iso:country":"US",
    "sg:address":"548 Spring St",
    "sg:city":"Windsor Locks",
    "sg:classifiers":[
        {
            "category":"Autos & Motor Vehicles",
            "subcategory":"Recreational Vehicle Sales",
            "type":"Retail Goods"
        }
    ],
    "sg:phone":"+1 860 627 6971",
    "sg:postcode":"06096",
    "sg:province":"CT",
    "wof:name":"El Monte R V",
    "wof:placetype":"venue"
},
  "geometry": {"coordinates":[-72.66825900000001,41.932294],"type":"Point"}
}