{
  "type": "Feature",
  "properties": {
    "addr:full":"171 Main St Ansonia CT 06401",
    "addr:housenumber":"171",
    "addr:postcode":"06401",
    "addr:street":"Main St",
    "iso:country":"US",
    "sg:address":"171 Main St",
    "sg:city":"Ansonia",
    "sg:classifiers":[
        {
            "category":"Professional",
            "subcategory":"Accounting & Tax Preparation",
            "type":"Services"
        }
    ],
    "sg:phone":"+1 203 734 6958",
    "sg:postcode":"06401",
    "sg:province":"CT",
    "sg:tags":[
        "return",
        "filing"
    ],
    "wof:name":"Glenn D Beck & Co",
    "wof:placetype":"venue"
},
  "geometry": {"coordinates":[-73.079083,41.343813],"type":"Point"}
}