{
  "type": "Feature",
  "properties": {
    "iso:country":"US",
    "sg:address":"62 Millstone Dr",
    "sg:city":"Marlborough",
    "sg:classifiers":[
        {
            "category":"Professional",
            "subcategory":"Computer Services",
            "type":"Services"
        }
    ],
    "sg:phone":"+1   ",
    "sg:postcode":"06447",
    "sg:province":"CT",
    "sg:tags":[
        "related"
    ],
    "wof:name":"Sara Lee Enterprises",
    "wof:placetype":"venue"
},
  "geometry": {"coordinates":[-72.425921,41.602717],"type":"Point"}
}