{
  "type": "Feature",
  "properties": {
    "addr:full":"2268 Fairfield Ave Bridgeport CT 06605",
    "addr:housenumber":"2268",
    "addr:postcode":"06605",
    "addr:street":"Fairfield Ave",
    "iso:country":"US",
    "sg:address":"2268 Fairfield Ave",
    "sg:city":"Bridgeport",
    "sg:classifiers":[
        {
            "category":"Banks & Credit Unions",
            "subcategory":"Bank",
            "type":"Services"
        }
    ],
    "sg:phone":"+1 203 335 9653",
    "sg:postcode":"06605",
    "sg:province":"CT",
    "sg:tags":[
        "cashing",
        "check"
    ],
    "wof:name":"Connecticut St Chk Cash Ser",
    "wof:placetype":"venue"
},
  "geometry": {"coordinates":[-73.220645,41.163629],"type":"Point"}
}