{
  "type": "Feature",
  "properties": {
    "iso:country":"US",
    "sg:address":"460 Smith St",
    "sg:city":"Middletown",
    "sg:classifiers":[
        {
            "category":"Wholesale",
            "subcategory":"Hardware",
            "type":"Manufacturing & Wholesale Goods"
        }
    ],
    "sg:phone":"+1 860 613 1091",
    "sg:postcode":"06457",
    "sg:province":"CT",
    "sg:tags":[
        "plumbing"
    ],
    "wof:name":"Northland Corp",
    "wof:placetype":"venue"
},
  "geometry": {"coordinates":[-72.72011500000001,41.584272],"type":"Point"}
}