{
  "type": "Feature",
  "properties": {
    "addr:full":"5 Cypress Ln Wallingford CT 06492",
    "addr:housenumber":"5",
    "addr:postcode":"06492",
    "addr:street":"Cypress Ln",
    "iso:country":"US",
    "sg:address":"5 Cypress Ln",
    "sg:city":"Wallingford",
    "sg:classifiers":[
        {
            "category":"Professional",
            "subcategory":"Business Services",
            "type":"Services"
        }
    ],
    "sg:phone":"+1   ",
    "sg:postcode":"06492",
    "sg:province":"CT",
    "wof:name":"J & J Prof Pool Svcs LLC",
    "wof:placetype":"venue"
},
  "geometry": {"coordinates":[-72.82405799999999,41.439153],"type":"Point"}
}