{
  "type": "Feature",
  "properties": {
    "iso:country":"US",
    "sg:address":"1 Washington Ave",
    "sg:city":"Old Lyme",
    "sg:classifiers":[
        {
            "category":"Professional",
            "subcategory":"Business Services",
            "type":"Services"
        }
    ],
    "sg:phone":"+1   ",
    "sg:postcode":"06371",
    "sg:province":"CT",
    "wof:name":"Art By Sacaduras LLC",
    "wof:placetype":"venue"
},
  "geometry": {"coordinates":[-72.283924,41.287586],"type":"Point"}
}