{
  "type": "Feature",
  "properties": {
    "iso:country":"US",
    "sg:address":"905 Shepard Ave",
    "sg:city":"Hamden",
    "sg:classifiers":[
        {
            "category":"Sports & Exercise",
            "subcategory":"Gym",
            "type":"Entertainment"
        }
    ],
    "sg:phone":"+1   ",
    "sg:postcode":"06514",
    "sg:province":"CT",
    "wof:name":"Djc",
    "wof:placetype":"venue"
},
  "geometry": {"coordinates":[-72.924147,41.39964],"type":"Point"}
}