{
  "type": "Feature",
  "properties": {
    "iso:country":"US",
    "sg:address":"37 2nd Ave",
    "sg:city":"Norwalk",
    "sg:classifiers":[
        {
            "category":"Health Services",
            "subcategory":"Health Practitioner",
            "type":"Services"
        }
    ],
    "sg:phone":"+1 203 845 8000",
    "sg:postcode":"06810",
    "sg:province":"CT",
    "sg:tags":[
        "therapist",
        "physical"
    ],
    "wof:name":"Norwalk Rehabilitation Svc Inc",
    "wof:placetype":"venue"
},
  "geometry": {"coordinates":[-73.45360100000001,41.408646],"type":"Point"}
}