{
  "type": "Feature",
  "properties": {
    "iso:country":"US",
    "sg:address":"41 Elmer St",
    "sg:city":"Stamford",
    "sg:classifiers":[
        {
            "category":"Real Estate",
            "subcategory":"Real Estate Agent",
            "type":"Services"
        }
    ],
    "sg:phone":"+1 203 329 2606",
    "sg:postcode":"06907",
    "sg:province":"CT",
    "wof:name":"Pioneer Properties",
    "wof:placetype":"venue"
},
  "geometry": {"coordinates":[-73.52275899999999,41.097635],"type":"Point"}
}