{
  "type": "Feature",
  "properties": {
    "iso:country":"US",
    "sg:address":"88 Woodland Dr",
    "sg:city":"Harwinton",
    "sg:classifiers":[
        {
            "category":"Real Estate",
            "subcategory":"Real Estate Agent",
            "type":"Services"
        }
    ],
    "sg:phone":"+1 860 485 1808",
    "sg:postcode":"06791",
    "sg:province":"CT",
    "wof:name":"Marlene Parker Real Estate",
    "wof:placetype":"venue"
},
  "geometry": {"coordinates":[-73.073184,41.788307],"type":"Point"}
}