{
  "type": "Feature",
  "properties": {
    "addr:full":"503 Middlebury Rd Middlebury CT 06762",
    "addr:housenumber":"503",
    "addr:postcode":"06762",
    "addr:street":"Middlebury Rd",
    "iso:country":"US",
    "sg:address":"503 Middlebury Rd",
    "sg:city":"Middlebury",
    "sg:classifiers":[
        {
            "category":"Banks & Credit Unions",
            "subcategory":"Bank",
            "type":"Services"
        }
    ],
    "sg:phone":"+1 203 758 1970",
    "sg:postcode":"06762",
    "sg:province":"CT",
    "wof:name":"Banknorth",
    "wof:placetype":"venue"
},
  "geometry": {"coordinates":[-73.104567,41.537758],"type":"Point"}
}