{
  "type": "Feature",
  "properties": {
    "iso:country":"US",
    "sg:address":"141 Short Beach Rd",
    "sg:city":"Branford",
    "sg:classifiers":[
        {
            "category":"Personal",
            "subcategory":"Beauty Salon",
            "type":"Services"
        }
    ],
    "sg:phone":"+1   ",
    "sg:postcode":"06405",
    "sg:province":"CT",
    "sg:tags":[
        "shop"
    ],
    "wof:name":"Just Your Style",
    "wof:placetype":"venue"
},
  "geometry": {"coordinates":[-72.831165,41.265612],"type":"Point"}
}