{
  "type": "Feature",
  "properties": {
    "iso:country":"US",
    "sg:address":"220 Lead Mine Brook Rd",
    "sg:city":"Harwinton",
    "sg:classifiers":[
        {
            "category":"Health Services",
            "subcategory":"Health Practitioner",
            "type":"Services"
        }
    ],
    "sg:phone":"+1   ",
    "sg:postcode":"06791",
    "sg:province":"CT",
    "wof:name":"McMannus Dnna Mssage Therapist",
    "wof:placetype":"venue"
},
  "geometry": {"coordinates":[-73.074603,41.79269],"type":"Point"}
}