{
  "type": "Feature",
  "properties": {
    "addr:full":"240 Glen St New Britain CT 06051",
    "addr:housenumber":"240",
    "addr:postcode":"06051",
    "addr:street":"Glen St",
    "iso:country":"US",
    "sg:address":"240 Glen St",
    "sg:city":"New Britain",
    "sg:classifiers":[
        {
            "category":"Professional",
            "type":"Services"
        }
    ],
    "sg:phone":"+1 860 224 0131",
    "sg:postcode":"06051",
    "sg:province":"CT",
    "wof:name":"V I B E Athletics",
    "wof:placetype":"venue"
},
  "geometry": {"coordinates":[-72.781345,41.657822],"type":"Point"}
}