{
  "type": "Feature",
  "properties": {
    "iso:country":"US",
    "sg:address":"52 Pomfret St",
    "sg:city":"Putnam",
    "sg:classifiers":[
        {
            "category":"Professional",
            "type":"Services"
        }
    ],
    "sg:phone":"+1 860 928 1500",
    "sg:postcode":"06260",
    "sg:province":"CT",
    "wof:name":"Custom Research LLC",
    "wof:placetype":"venue"
},
  "geometry": {"coordinates":[-71.91098,41.915038],"type":"Point"}
}