{
  "type": "Feature",
  "properties": {
    "iso:country":"US",
    "sg:address":"33 Ash Ln",
    "sg:city":"Southbury",
    "sg:classifiers":[
        {
            "category":"Social Services",
            "subcategory":"Adult Care",
            "type":"Services"
        }
    ],
    "sg:phone":"+1   ",
    "sg:postcode":"06488",
    "sg:province":"CT",
    "sg:tags":[
        "residential",
        "membership",
        "organization"
    ],
    "wof:name":"Community Systems",
    "wof:placetype":"venue"
},
  "geometry": {"coordinates":[-73.178072,41.4632],"type":"Point"}
}