{
  "type": "Feature",
  "properties": {
    "addr:full":"301 Boston Post Rd Guilford CT 06437",
    "addr:housenumber":"301",
    "addr:postcode":"06437",
    "addr:street":"Boston Post Rd",
    "iso:country":"US",
    "sg:address":"301 Boston Post Rd",
    "sg:city":"Guilford",
    "sg:classifiers":[
        {
            "category":"Autos & Motor Vehicles",
            "subcategory":"Automobile Sales",
            "type":"Retail Goods"
        }
    ],
    "sg:phone":"+1 203 453 5251",
    "sg:postcode":"06437",
    "sg:province":"CT",
    "sg:tags":[
        "car",
        "dealer"
    ],
    "wof:name":"Mannix Chevrolet-Pontiac Inc",
    "wof:placetype":"venue"
},
  "geometry": {"coordinates":[-72.65670799999999,41.287748],"type":"Point"}
}