{
  "type": "Feature",
  "properties": {
    "iso:country":"US",
    "sg:address":"1 Michael Rd",
    "sg:city":"Simsbury",
    "sg:classifiers":[
        {
            "category":"Utilities",
            "subcategory":"Water",
            "type":"Services"
        },
        {
            "category":"Utilities",
            "type":"Services"
        }
    ],
    "sg:phone":"+1 860 651 6545",
    "sg:postcode":"06070",
    "sg:province":"CT",
    "sg:tags":[
        "company-utility",
        "contractor"
    ],
    "wof:name":"Underground Systems Inc",
    "wof:placetype":"venue"
},
  "geometry": {"coordinates":[-72.822754,41.8881],"type":"Point"}
}