{
  "type": "Feature",
  "properties": {
    "iso:country":"US",
    "sg:address":"82 Hoyts Hill",
    "sg:city":"Bethel",
    "sg:classifiers":[
        {
            "category":"Professional",
            "subcategory":"Management & Consulting",
            "type":"Services"
        }
    ],
    "sg:phone":"+1   ",
    "sg:postcode":"06801",
    "sg:province":"CT",
    "sg:tags":[
        "business"
    ],
    "wof:name":"Academy Associates",
    "wof:placetype":"venue"
},
  "geometry": {"coordinates":[-73.400235,41.371178],"type":"Point"}
}