{
  "type": "Feature",
  "properties": {
    "addr:full":"81 Middle Beach Rd Madison CT 06443",
    "addr:housenumber":"81",
    "addr:postcode":"06443",
    "addr:street":"Middle Beach Rd",
    "iso:country":"US",
    "sg:address":"81 Middle Beach Rd",
    "sg:city":"Madison",
    "sg:classifiers":[
        {
            "category":"Real Estate",
            "subcategory":"Architect",
            "type":"Services"
        }
    ],
    "sg:phone":"+1   ",
    "sg:postcode":"06443",
    "sg:province":"CT",
    "sg:tags":[
        "architectural"
    ],
    "wof:name":"John U Parker",
    "wof:placetype":"venue"
},
  "geometry": {"coordinates":[-72.59519299999999,41.270177],"type":"Point"}
}