{
  "type": "Feature",
  "properties": {
    "addr:full":"102 Perry Ave Norwalk CT 06850",
    "addr:housenumber":"102",
    "addr:postcode":"06850",
    "addr:street":"Perry Ave",
    "iso:country":"US",
    "sg:address":"102 Perry Ave",
    "sg:city":"Norwalk",
    "sg:classifiers":[
        {
            "category":"Building & Trades",
            "subcategory":"Construction",
            "type":"Services"
        }
    ],
    "sg:phone":"+1 203 847 2959",
    "sg:postcode":"06850",
    "sg:province":"CT",
    "sg:tags":[
        "residential"
    ],
    "wof:name":"Wayne Dimm Enterprises Inc",
    "wof:placetype":"venue"
},
  "geometry": {"coordinates":[-73.435491,41.142957],"type":"Point"}
}