{
  "type": "Feature",
  "properties": {
    "iso:country":"US",
    "sg:address":"73 Lake Dr",
    "sg:city":"New Milford",
    "sg:classifiers":[
        {
            "category":"Shopping",
            "type":"Retail Goods"
        }
    ],
    "sg:phone":"+1 860 355 7007",
    "sg:postcode":"06776",
    "sg:province":"CT",
    "sg:tags":[
        "merchandise"
    ],
    "wof:name":"New Milford Monument Co",
    "wof:placetype":"venue"
},
  "geometry": {"coordinates":[-73.442307,41.540725],"type":"Point"}
}