{
  "type": "Feature",
  "properties": {
    "addr:full":"850 N Main St Exd Wallingford CT 06492",
    "addr:housenumber":"850",
    "addr:postcode":"06492",
    "addr:street":"N Main St Exd",
    "iso:country":"US",
    "sg:address":"850 N Main St Exd",
    "sg:city":"Wallingford",
    "sg:classifiers":[
        {
            "category":"Banks & Credit Unions",
            "subcategory":"Investment Brokerage",
            "type":"Services"
        }
    ],
    "sg:phone":"+1 203 284 1990",
    "sg:postcode":"06492",
    "sg:province":"CT",
    "sg:tags":[
        "security",
        "stock",
        "bond"
    ],
    "wof:name":"Oppenheimer & Co Inc",
    "wof:placetype":"venue"
},
  "geometry": {"coordinates":[-72.80591699999999,41.484795],"type":"Point"}
}