{
  "type": "Feature",
  "properties": {
    "iso:country":"US",
    "sg:address":"19 Bernhard Rd",
    "sg:city":"North Haven",
    "sg:classifiers":[
        {
            "category":"Organizations",
            "subcategory":"Membership Organization",
            "type":"Services"
        }
    ],
    "sg:phone":"+1   ",
    "sg:postcode":"06473",
    "sg:province":"CT",
    "wof:name":"M A D D",
    "wof:placetype":"venue"
},
  "geometry": {"coordinates":[-72.87504199999999,41.334455],"type":"Point"}
}