{
  "type": "Feature",
  "properties": {
    "addr:full":"66 Cedar St Newington CT 06111",
    "addr:housenumber":"66",
    "addr:postcode":"06111",
    "addr:street":"Cedar St",
    "iso:country":"US",
    "sg:address":"66 Cedar St",
    "sg:city":"Newington",
    "sg:classifiers":[
        {
            "category":"Health Services",
            "subcategory":"Doctor",
            "type":"Services"
        }
    ],
    "sg:phone":"+1   ",
    "sg:postcode":"06111",
    "sg:province":"CT",
    "sg:tags":[
        "clinic",
        "medical"
    ],
    "wof:name":"Newington Diagnostic Center",
    "wof:placetype":"venue"
},
  "geometry": {"coordinates":[-72.724519,41.698009],"type":"Point"}
}