{
  "type": "Feature",
  "properties": {
    "addr:full":"93 Old Ridgefield Rd Wilton CT 06897",
    "addr:housenumber":"93",
    "addr:postcode":"06897",
    "addr:street":"Old Ridgefield Rd Wilton Ct",
    "iso:country":"US",
    "sg:address":"93 Old Ridgefield Rd",
    "sg:city":"Wilton",
    "sg:classifiers":[
        {
            "category":"Wholesale",
            "subcategory":"Drugs",
            "type":"Manufacturing & Wholesale Goods"
        }
    ],
    "sg:phone":"+1 203 762 5020",
    "sg:postcode":"06897",
    "sg:province":"CT",
    "wof:name":"CVS",
    "wof:placetype":"venue"
},
  "geometry": {"coordinates":[-73.43324800000001,41.194249],"type":"Point"}
}