{
  "type": "Feature",
  "properties": {
    "iso:country":"US",
    "sg:address":"93 Midland Rd",
    "sg:city":"Waterbury",
    "sg:classifiers":[
        {
            "category":"Shopping",
            "subcategory":"Hobbies, Toys, & Games",
            "type":"Retail Goods"
        },
        {
            "category":"Education",
            "subcategory":"Special Training",
            "type":"Public Place"
        }
    ],
    "sg:phone":"+1 203 757 9229",
    "sg:postcode":"06705",
    "sg:province":"CT",
    "sg:tags":[
        "equipment",
        "ceramic",
        "supply"
    ],
    "wof:name":"Lil' Shoppe Of Ceramics",
    "wof:placetype":"venue"
},
  "geometry": {"coordinates":[-72.989344,41.546804],"type":"Point"}
}