{
  "type": "Feature",
  "properties": {
    "iso:country":"US",
    "sg:address":"80 E Main St",
    "sg:city":"Middletown",
    "sg:classifiers":[
        {
            "category":"Social Services",
            "type":"Services"
        }
    ],
    "sg:phone":"+1   ",
    "sg:postcode":"06457",
    "sg:province":"CT",
    "wof:name":"M A R C",
    "wof:placetype":"venue"
},
  "geometry": {"coordinates":[-72.642472,41.552582],"type":"Point"}
}