{
  "type": "Feature",
  "properties": {
    "addr:full":"251 Edwards St New Haven CT 06511",
    "addr:housenumber":"251",
    "addr:postcode":"06511",
    "addr:street":"Edwards St",
    "iso:country":"US",
    "sg:address":"251 Edwards St",
    "sg:city":"New Haven",
    "sg:classifiers":[
        {
            "category":"Health Services",
            "subcategory":"Doctor",
            "type":"Services"
        }
    ],
    "sg:phone":"+1   ",
    "sg:postcode":"06511",
    "sg:province":"CT",
    "sg:tags":[
        "medical"
    ],
    "wof:name":"Nancy Olson",
    "wof:placetype":"venue"
},
  "geometry": {"coordinates":[-72.917576,41.319233],"type":"Point"}
}