{
  "type": "Feature",
  "properties": {
    "addr:full":"106 Windmill Hill Wethersfield CT 06109",
    "addr:housenumber":"106",
    "addr:postcode":"06109",
    "addr:street":"Windmill;Wethersfield",
    "iso:country":"US",
    "sg:address":"106 Windmill Hill",
    "sg:city":"Wethersfield",
    "sg:classifiers":[
        {
            "category":"Building & Trades",
            "subcategory":"Landscaping Services",
            "type":"Services"
        }
    ],
    "sg:phone":"+1 860 257 3146",
    "sg:postcode":"06109",
    "sg:province":"CT",
    "wof:name":"Griffin Landscaping",
    "wof:placetype":"venue"
},
  "geometry": {"coordinates":[-72.695651,41.694944],"type":"Point"}
}