{
  "type": "Feature",
  "properties": {
    "iso:country":"US",
    "sg:address":"1 Wilton Rd",
    "sg:city":"Westport",
    "sg:classifiers":[
        {
            "category":"Sports & Exercise",
            "subcategory":"Gym",
            "type":"Entertainment"
        }
    ],
    "sg:phone":"+1   ",
    "sg:postcode":"06880",
    "sg:province":"CT",
    "sg:tags":[
        "fitness",
        "physical",
        "facility"
    ],
    "wof:name":"Life Fitness Inc",
    "wof:placetype":"venue"
},
  "geometry": {"coordinates":[-73.365363,41.144068],"type":"Point"}
}