{
  "type": "Feature",
  "properties": {
    "iso:country":"US",
    "sg:address":"826 Spindle Hill Rd",
    "sg:city":"Wolcott",
    "sg:classifiers":[
        {
            "category":"Retail",
            "subcategory":"Animal Services",
            "type":"Services"
        }
    ],
    "sg:phone":"+1 203 879 3456",
    "sg:postcode":"06716",
    "sg:province":"CT",
    "wof:name":"Nails To Tails",
    "wof:placetype":"venue"
},
  "geometry": {"coordinates":[-72.991485,41.625271],"type":"Point"}
}