{
  "type": "Feature",
  "properties": {
    "addr:full":"111 Whalley Ave New Haven CT 06511",
    "addr:housenumber":"111",
    "addr:postcode":"06511",
    "addr:street":"Whalley Ave",
    "iso:country":"US",
    "sg:address":"111 Whalley Ave",
    "sg:city":"New Haven",
    "sg:classifiers":[
        {
            "category":"Organizations",
            "subcategory":"Religious Organization",
            "type":"Services"
        }
    ],
    "sg:phone":"+1 203 865 0141",
    "sg:postcode":"06511",
    "sg:province":"CT",
    "sg:tags":[
        "church"
    ],
    "wof:name":"St Lukes Episcopal Church",
    "wof:placetype":"venue"
},
  "geometry": {"coordinates":[-72.93893199999999,41.315475],"type":"Point"}
}