{
  "type": "Feature",
  "properties": {
    "addr:full":"37 Elizabeth St Ansonia CT 06401",
    "addr:housenumber":"37",
    "addr:postcode":"06401",
    "addr:street":"Elizabeth St",
    "iso:country":"US",
    "sg:address":"37 Elizabeth St",
    "sg:city":"Ansonia",
    "sg:classifiers":[
        {
            "category":"Travel",
            "subcategory":"Travel Agent",
            "type":"Entertainment"
        }
    ],
    "sg:phone":"+1 203 735 3000",
    "sg:postcode":"06401",
    "sg:province":"CT",
    "sg:tags":[
        "agency",
        "bureau"
    ],
    "wof:name":"Happy Holiday Travel Agency",
    "wof:placetype":"venue"
},
  "geometry": {"coordinates":[-73.07243800000001,41.34897],"type":"Point"}
}