{
  "type": "Feature",
  "properties": {
    "iso:country":"US",
    "sg:address":"963 Bow Ln",
    "sg:city":"Middletown",
    "sg:classifiers":[
        {
            "category":"Retail",
            "subcategory":"Animal Services",
            "type":"Services"
        }
    ],
    "sg:phone":"+1 860 347 0642",
    "sg:postcode":"06457",
    "sg:province":"CT",
    "wof:name":"Lynn Acres LLC",
    "wof:placetype":"venue"
},
  "geometry": {"coordinates":[-72.601072,41.551006],"type":"Point"}
}