{
  "type": "Feature",
  "properties": {
    "addr:full":"100 Cumberland Dr Bridgeport CT 06606",
    "addr:housenumber":"100",
    "addr:postcode":"06606",
    "addr:street":"Cumberland Dr",
    "iso:country":"US",
    "sg:address":"100 Cumberland Dr",
    "sg:city":"Bridgeport",
    "sg:classifiers":[
        {
            "category":"Professional",
            "subcategory":"Management & Consulting",
            "type":"Services"
        }
    ],
    "sg:phone":"+1   ",
    "sg:postcode":"06606",
    "sg:province":"CT",
    "wof:name":"Financial Consultant",
    "wof:placetype":"venue"
},
  "geometry": {"coordinates":[-73.206962,41.22639],"type":"Point"}
}