{
  "type": "Feature",
  "properties": {
    "iso:country":"US",
    "sg:address":"665 Boston Post Rd",
    "sg:city":"Old Saybrook",
    "sg:classifiers":[
        {
            "category":"Shopping",
            "subcategory":"Department Store",
            "type":"Retail Goods"
        }
    ],
    "sg:phone":"+1 860 388 1444",
    "sg:postcode":"06475",
    "sg:province":"CT",
    "sg:website":"www.marshallsonline.com",
    "wof:name":"Marshalls",
    "wof:placetype":"venue"
},
  "geometry": {"coordinates":[-72.37840300000001,41.2962],"type":"Point"}
}