{
  "type": "Feature",
  "properties": {
    "addr:full":"385 Main St West Haven CT 06516",
    "addr:housenumber":"385",
    "addr:postcode":"06516",
    "addr:street":"Main St",
    "iso:country":"US",
    "sg:address":"385 Main St",
    "sg:city":"West Haven",
    "sg:classifiers":[
        {
            "category":"Health Services",
            "subcategory":"Medical Lab",
            "type":"Services"
        }
    ],
    "sg:phone":"+1 203 949 1260",
    "sg:postcode":"06516",
    "sg:province":"CT",
    "sg:tags":[
        "laboratory"
    ],
    "wof:name":"Quest Diagnostics Inc",
    "wof:placetype":"venue"
},
  "geometry": {"coordinates":[-72.950559,41.272209],"type":"Point"}
}