{
  "type": "Feature",
  "properties": {
    "iso:country":"US",
    "sg:address":"400 Atlantic St",
    "sg:city":"Stamford",
    "sg:classifiers":[
        {
            "category":"Restaurant",
            "type":"Food & Drink"
        }
    ],
    "sg:phone":"+1 203 348 1199",
    "sg:postcode":"06901",
    "sg:province":"CT",
    "sg:tags":[
        "cafeteria"
    ],
    "sg:website":"http://www.corporateculinary.com",
    "wof:name":"Corporate Culinary Service, Inc.",
    "wof:placetype":"venue"
},
  "geometry": {"coordinates":[-73.539649,41.049776],"type":"Point"}
}