{
  "type": "Feature",
  "properties": {
    "iso:country":"US",
    "sg:address":"350 Windsor St",
    "sg:city":"South Windsor",
    "sg:classifiers":[
        {
            "category":"Manufacturing",
            "subcategory":"Tools & Machinery",
            "type":"Manufacturing & Wholesale Goods"
        }
    ],
    "sg:phone":"+1 860 289 2881",
    "sg:postcode":"06074",
    "sg:province":"CT",
    "sg:tags":[
        "industrial",
        "sheet",
        "metalwork",
        "mfg"
    ],
    "wof:name":"Geneeva Machining Services",
    "wof:placetype":"venue"
},
  "geometry": {"coordinates":[-72.565524,41.803914],"type":"Point"}
}