{
  "type": "Feature",
  "properties": {
    "iso:country":"US",
    "sg:address":"29 Black Point Rd",
    "sg:city":"Niantic",
    "sg:classifiers":[
        {
            "category":"Social Services",
            "type":"Services"
        }
    ],
    "sg:phone":"+1   ",
    "sg:postcode":"06357",
    "sg:province":"CT",
    "wof:name":"Black Point Counseling Center",
    "wof:placetype":"venue"
},
  "geometry": {"coordinates":[-72.20307699999999,41.321729],"type":"Point"}
}