{
  "type": "Feature",
  "properties": {
    "addr:full":"507 Westport Ave Norwalk CT 06851",
    "addr:housenumber":"507",
    "addr:postcode":"06851",
    "addr:street":"Westport Ave",
    "iso:country":"US",
    "sg:address":"507 Westport Ave",
    "sg:city":"Norwalk",
    "sg:classifiers":[
        {
            "category":"Sports & Exercise",
            "subcategory":"Gym",
            "type":"Entertainment"
        }
    ],
    "sg:phone":"+1   ",
    "sg:postcode":"06851",
    "sg:province":"CT",
    "sg:tags":[
        "fitness",
        "physical",
        "facility"
    ],
    "wof:name":"Perfect Fit Home Training Inc",
    "wof:placetype":"venue"
},
  "geometry": {"coordinates":[-73.38487600000001,41.127534],"type":"Point"}
}