{
  "type": "Feature",
  "properties": {
    "iso:country":"US",
    "sg:address":"114 Hartley Dr",
    "sg:city":"Waterbury",
    "sg:classifiers":[
        {
            "category":"Building & Trades",
            "subcategory":"Landscaping Services",
            "type":"Services"
        }
    ],
    "sg:phone":"+1 203 509 3685",
    "sg:postcode":"06705",
    "sg:province":"CT",
    "sg:tags":[
        "landscape",
        "contractor"
    ],
    "wof:name":"Dreamscape",
    "wof:placetype":"venue"
},
  "geometry": {"coordinates":[-72.98270599999999,41.536033],"type":"Point"}
}