{
  "type": "Feature",
  "properties": {
    "addr:full":"51 Sage Dr Manchester CT 06042",
    "addr:housenumber":"51",
    "addr:postcode":"06042",
    "addr:street":"Sage Dr",
    "iso:country":"US",
    "sg:address":"51 Sage Dr",
    "sg:city":"Manchester",
    "sg:classifiers":[
        {
            "category":"Education",
            "subcategory":"Vocational School",
            "type":"Public Place"
        }
    ],
    "sg:phone":"+1   ",
    "sg:postcode":"06042",
    "sg:province":"CT",
    "sg:tags":[
        "processing",
        "datum"
    ],
    "wof:name":"Northeast Cmpt Training Group",
    "wof:placetype":"venue"
},
  "geometry": {"coordinates":[-72.492273,41.80511],"type":"Point"}
}