{
  "type": "Feature",
  "properties": {
    "iso:country":"US",
    "sg:address":"155 Hobart St",
    "sg:city":"Southington",
    "sg:classifiers":[
        {
            "category":"Building & Trades",
            "subcategory":"Construction",
            "type":"Services"
        }
    ],
    "sg:phone":"+1 860 621 0922",
    "sg:postcode":"06489",
    "sg:province":"CT",
    "sg:tags":[
        "excavating",
        "work"
    ],
    "wof:name":"O & D Excavating Co Inc",
    "wof:placetype":"venue"
},
  "geometry": {"coordinates":[-72.871748,41.607706],"type":"Point"}
}