{
  "type": "Feature",
  "properties": {
    "iso:country":"US",
    "sg:address":"9 Ferris Rd",
    "sg:city":"Newtown",
    "sg:classifiers":[
        {
            "category":"Building & Trades",
            "subcategory":"Landscaping Services",
            "type":"Services"
        }
    ],
    "sg:phone":"+1 203 426 5605",
    "sg:postcode":"06470",
    "sg:province":"CT",
    "sg:tags":[
        "tree"
    ],
    "wof:name":"Our Town Tree Svc",
    "wof:placetype":"venue"
},
  "geometry": {"coordinates":[-73.337262,41.390032],"type":"Point"}
}