{
  "type": "Feature",
  "properties": {
    "addr:full":"90 Prindle Hill Rd Orange CT 06477",
    "addr:housenumber":"90",
    "addr:postcode":"06477",
    "addr:street":"Prindle Hill Rd",
    "iso:country":"US",
    "sg:address":"90 Prindle Hill Rd",
    "sg:city":"Orange",
    "sg:classifiers":[
        {
            "category":"Utilities",
            "subcategory":"Refuse",
            "type":"Services"
        },
        {
            "category":"Utilities",
            "subcategory":"Recycling",
            "type":"Services"
        }
    ],
    "sg:phone":"+1 203 934 5599",
    "sg:postcode":"06477",
    "sg:province":"CT",
    "sg:tags":[
        "container",
        "garbage",
        "rubbish",
        "removal"
    ],
    "wof:name":"Latella Rubbish Removal",
    "wof:placetype":"venue"
},
  "geometry": {"coordinates":[-72.992384,41.264428],"type":"Point"}
}