{
  "type": "Feature",
  "properties": {
    "iso:country":"US",
    "sg:address":"9 Hawthorne Hill Rd",
    "sg:city":"Newtown",
    "sg:classifiers":[
        {
            "category":"Professional",
            "subcategory":"Advertising",
            "type":"Services"
        }
    ],
    "sg:phone":"+1   ",
    "sg:postcode":"06470",
    "sg:province":"CT",
    "sg:tags":[
        "agency"
    ],
    "wof:name":"Charlie Browne Communications",
    "wof:placetype":"venue"
},
  "geometry": {"coordinates":[-73.347003,41.415794],"type":"Point"}
}