{
  "type": "Feature",
  "properties": {
    "iso:country":"US",
    "sg:address":"141 Briar Brae Rd",
    "sg:city":"Stamford",
    "sg:classifiers":[
        {
            "category":"Professional",
            "subcategory":"Business Services",
            "type":"Services"
        }
    ],
    "sg:phone":"+1   ",
    "sg:postcode":"06903",
    "sg:province":"CT",
    "wof:name":"Eisenbud & Assoc Ltd",
    "wof:placetype":"venue"
},
  "geometry": {"coordinates":[-73.568417,41.15474],"type":"Point"}
}