{
  "type": "Feature",
  "properties": {
    "iso:country":"US",
    "sg:address":"361 Masarik Ave",
    "sg:city":"Stratford",
    "sg:classifiers":[
        {
            "category":"Building & Trades",
            "subcategory":"Construction",
            "type":"Services"
        }
    ],
    "sg:phone":"+1 203 381 1942",
    "sg:postcode":"06615",
    "sg:province":"CT",
    "sg:tags":[
        "general",
        "contractor"
    ],
    "wof:name":"Scotty's Paving & Sealing",
    "wof:placetype":"venue"
},
  "geometry": {"coordinates":[-73.141498,41.173442],"type":"Point"}
}