{
  "type": "Feature",
  "properties": {
    "iso:country":"US",
    "sg:address":"1151 Wolcott Rd",
    "sg:city":"Wolcott",
    "sg:classifiers":[
        {
            "category":"Retail",
            "subcategory":"Auto Repair",
            "type":"Services"
        }
    ],
    "sg:phone":"+1   ",
    "sg:postcode":"06716",
    "sg:province":"CT",
    "sg:tags":[
        "body"
    ],
    "wof:name":"Crocketts Auto Body",
    "wof:placetype":"venue"
},
  "geometry": {"coordinates":[-72.97627,41.617827],"type":"Point"}
}