{
  "type": "Feature",
  "properties": {
    "addr:full":"1127 W Main St Waterbury CT 06708",
    "addr:housenumber":"1127",
    "addr:postcode":"06708",
    "addr:street":"W Main St",
    "iso:country":"US",
    "sg:address":"1127 W Main St",
    "sg:city":"Waterbury",
    "sg:classifiers":[
        {
            "category":"Real Estate",
            "subcategory":"Real Estate Agent",
            "type":"Services"
        }
    ],
    "sg:phone":"+1 203 754 6147",
    "sg:postcode":"06708",
    "sg:province":"CT",
    "wof:name":"Century 21",
    "wof:placetype":"venue"
},
  "geometry": {"coordinates":[-73.061238,41.554898],"type":"Point"}
}