{
  "type": "Feature",
  "properties": {
    "addr:full":"137 Genesee Ln Madison CT 06443",
    "addr:housenumber":"137",
    "addr:postcode":"06443",
    "addr:street":"Genesee Ln",
    "iso:country":"US",
    "sg:address":"137 Genesee Ln",
    "sg:city":"Madison",
    "sg:classifiers":[
        {
            "category":"Real Estate",
            "subcategory":"Real Estate Operator",
            "type":"Services"
        }
    ],
    "sg:phone":"+1 203 421 3337",
    "sg:postcode":"06443",
    "sg:province":"CT",
    "sg:tags":[
        "building",
        "nonresidential"
    ],
    "wof:name":"Seabrook Properties LLC",
    "wof:placetype":"venue"
},
  "geometry": {"coordinates":[-72.665616,41.372514],"type":"Point"}
}