{
  "type": "Feature",
  "properties": {
    "iso:country":"US",
    "sg:address":"152 Crestwood Rd",
    "sg:city":"Torrington",
    "sg:classifiers":[
        {
            "category":"Real Estate",
            "subcategory":"Real Estate Operator",
            "type":"Services"
        }
    ],
    "sg:phone":"+1 860 489 7572",
    "sg:postcode":"06790",
    "sg:province":"CT",
    "sg:tags":[
        "building",
        "nonresidential"
    ],
    "wof:name":"Canton Property LLC",
    "wof:placetype":"venue"
},
  "geometry": {"coordinates":[-73.101793,41.809159],"type":"Point"}
}