{
  "type": "Feature",
  "properties": {
    "iso:country":"US",
    "sg:address":"17 Reynolds St",
    "sg:city":"Danielson",
    "sg:classifiers":[
        {
            "category":"Real Estate",
            "subcategory":"Real Estate Agent",
            "type":"Services"
        }
    ],
    "sg:phone":"+1 860 774 3661",
    "sg:postcode":"06239",
    "sg:province":"CT",
    "sg:tags":[
        "broker"
    ],
    "wof:name":"Diversified Realestate",
    "wof:placetype":"venue"
},
  "geometry": {"coordinates":[-71.88132899999999,41.806929],"type":"Point"}
}