{
  "type": "Feature",
  "properties": {
    "iso:country":"US",
    "sg:address":"165 Meadows End Rd",
    "sg:city":"Milford",
    "sg:classifiers":[
        {
            "category":"Professional",
            "subcategory":"Employment Agencies",
            "type":"Services"
        }
    ],
    "sg:phone":"+1   ",
    "sg:postcode":"06460",
    "sg:province":"CT",
    "sg:tags":[
        "help",
        "supply"
    ],
    "wof:name":"Small Office Services",
    "wof:placetype":"venue"
},
  "geometry": {"coordinates":[-73.08363199999999,41.204989],"type":"Point"}
}