{
  "type": "Feature",
  "properties": {
    "addr:full":"1331 Silas Deane Hwy Wethersfield CT 06109",
    "addr:housenumber":"1331",
    "addr:postcode":"06109",
    "addr:street":"Silas Deane Hwy Wethersfield Ct",
    "iso:country":"US",
    "sg:address":"1331 Silas Deane Hwy",
    "sg:city":"Wethersfield",
    "sg:classifiers":[
        {
            "category":"Professional",
            "subcategory":"Lawyer & Legal Services",
            "type":"Services"
        }
    ],
    "sg:phone":"+1   ",
    "sg:postcode":"06109",
    "sg:province":"CT",
    "wof:name":"Kearns Law Center",
    "wof:placetype":"venue"
},
  "geometry": {"coordinates":[-72.654545,41.683889],"type":"Point"}
}