{
  "type": "Feature",
  "properties": {
    "addr:full":"185 Albany Tpke Canton CT 06019",
    "addr:housenumber":"185",
    "addr:postcode":"06019",
    "addr:street":"Albany Tpke Canton Ct",
    "iso:country":"US",
    "sg:address":"185 Albany Tpke",
    "sg:city":"Canton",
    "sg:classifiers":[
        {
            "category":"Professional",
            "subcategory":"Accounting & Tax Preparation",
            "type":"Services"
        }
    ],
    "sg:phone":"+1   ",
    "sg:postcode":"06019",
    "sg:province":"CT",
    "wof:name":"Ludwig Phillip K",
    "wof:placetype":"venue"
},
  "geometry": {"coordinates":[-72.894802,41.825075],"type":"Point"}
}