{
  "type": "Feature",
  "properties": {
    "addr:full":"1111 Summer St Stamford CT 06905",
    "addr:housenumber":"1111",
    "addr:postcode":"06905",
    "addr:street":"Summer St",
    "iso:country":"US",
    "sg:address":"1111 Summer St",
    "sg:city":"Stamford",
    "sg:classifiers":[
        {
            "category":"Professional",
            "type":"Services"
        }
    ],
    "sg:phone":"+1 203 324 1167",
    "sg:postcode":"06905",
    "sg:province":"CT",
    "sg:tags":[
        "establishment"
    ],
    "wof:name":"Stamford Executive Ctr",
    "wof:placetype":"venue"
},
  "geometry": {"coordinates":[-73.541397,41.061572],"type":"Point"}
}