{
  "type": "Feature",
  "properties": {
    "iso:country":"US",
    "sg:address":"30 Old Kings Hwy S",
    "sg:city":"Darien",
    "sg:classifiers":[
        {
            "category":"Banks & Credit Unions",
            "subcategory":"Investment Brokerage",
            "type":"Services"
        }
    ],
    "sg:phone":"+1 203 656 5500",
    "sg:postcode":"06820",
    "sg:province":"CT",
    "sg:tags":[
        "consultant",
        "planning",
        "financial"
    ],
    "sg:website":"www.hhg.net",
    "wof:name":"Hynes Himmelreich Glennon & Co",
    "wof:placetype":"venue"
},
  "geometry": {"coordinates":[-73.46949499999999,41.075733],"type":"Point"}
}