{
  "type": "Feature",
  "properties": {
    "iso:country":"US",
    "sg:address":"850 Hartford Tpke",
    "sg:city":"Waterford",
    "sg:classifiers":[
        {
            "category":"Shopping",
            "subcategory":"Computers & Home Electronics",
            "type":"Retail Goods"
        }
    ],
    "sg:phone":"+1 860 443 6905",
    "sg:postcode":"06385",
    "sg:province":"CT",
    "wof:name":"Radio Shack",
    "wof:placetype":"venue"
},
  "geometry": {"coordinates":[-72.141065,41.374832],"type":"Point"}
}