{
  "type": "Feature",
  "properties": {
    "iso:country":"US",
    "sg:address":"4 Fox Run Dr",
    "sg:city":"Wallingford",
    "sg:classifiers":[
        {
            "category":"Building & Trades",
            "subcategory":"Construction",
            "type":"Services"
        }
    ],
    "sg:phone":"+1 203 949 1526",
    "sg:postcode":"06492",
    "sg:province":"CT",
    "sg:tags":[
        "concrete",
        "contractor"
    ],
    "wof:name":"Cosmetic Concrete",
    "wof:placetype":"venue"
},
  "geometry": {"coordinates":[-72.81006499999999,41.412249],"type":"Point"}
}