{
  "type": "Feature",
  "properties": {
    "iso:country":"US",
    "sg:address":"6 Beech Rd",
    "sg:city":"Tolland",
    "sg:classifiers":[
        {
            "category":"Manufacturing",
            "subcategory":"Metals",
            "type":"Manufacturing & Wholesale Goods"
        }
    ],
    "sg:phone":"+1 860 875 0252",
    "sg:postcode":"06084",
    "sg:province":"CT",
    "wof:name":"Pape Electroplating Co",
    "wof:placetype":"venue"
},
  "geometry": {"coordinates":[-72.38298,41.838666],"type":"Point"}
}