{
  "type": "Feature",
  "properties": {
    "iso:country":"US",
    "sg:address":"18 Liberty St",
    "sg:city":"Stamford",
    "sg:classifiers":[
        {
            "category":"Retail",
            "subcategory":"Laundry & Dry Cleaning",
            "type":"Services"
        }
    ],
    "sg:phone":"+1 203 356 9390",
    "sg:postcode":"06902",
    "sg:province":"CT",
    "sg:tags":[
        "cleaner",
        "upholstery"
    ],
    "wof:name":"Angelo Bordonaro Upholstery",
    "wof:placetype":"venue"
},
  "geometry": {"coordinates":[-73.554332,41.048703],"type":"Point"}
}