{
  "type": "Feature",
  "properties": {
    "iso:country":"US",
    "sg:address":"111 Thomaston Ave",
    "sg:city":"Waterbury",
    "sg:classifiers":[
        {
            "category":"Food & Beverages",
            "subcategory":"Bakery",
            "type":"Retail Goods"
        }
    ],
    "sg:phone":"+1 203 596 9020",
    "sg:postcode":"06702",
    "sg:province":"CT",
    "sg:tags":[
        "bagel",
        "shop"
    ],
    "wof:name":"Amis Hot Bagels",
    "wof:placetype":"venue"
},
  "geometry": {"coordinates":[-73.054802,41.564706],"type":"Point"}
}