{
  "type": "Feature",
  "properties": {
    "addr:full":"1944 North Ave Bridgeport CT 06604",
    "addr:housenumber":"1944",
    "addr:postcode":"06604",
    "addr:street":"North Ave",
    "iso:country":"US",
    "sg:address":"1944 North Ave",
    "sg:city":"Bridgeport",
    "sg:classifiers":[
        {
            "category":"Building & Trades",
            "subcategory":"Construction",
            "type":"Services"
        }
    ],
    "sg:phone":"+1 203 333 1807",
    "sg:postcode":"06604",
    "sg:province":"CT",
    "sg:tags":[
        "nonresidential"
    ],
    "wof:name":"American Professional Bui",
    "wof:placetype":"venue"
},
  "geometry": {"coordinates":[-73.209548,41.181769],"type":"Point"}
}