{
  "type": "Feature",
  "properties": {
    "iso:country":"US",
    "sg:address":"144 Kenyon Rd",
    "sg:city":"Lakeside",
    "sg:classifiers":[
        {
            "category":"Building & Trades",
            "subcategory":"Construction",
            "type":"Services"
        }
    ],
    "sg:phone":"+1 860 567 5316",
    "sg:postcode":"06763",
    "sg:province":"CT",
    "sg:tags":[
        "hanging",
        "contractor"
    ],
    "wof:name":"Roden Patrick Painting &",
    "wof:placetype":"venue"
},
  "geometry": {"coordinates":[-73.24254999999999,41.669004],"type":"Point"}
}