{
  "type": "Feature",
  "properties": {
    "addr:full":"110 Hopmeadow St Simsbury CT 06089",
    "addr:housenumber":"110",
    "addr:postcode":"06089",
    "addr:street":"Hopmeadow St Simsbury Ct",
    "iso:country":"US",
    "sg:address":"110 Hopmeadow St",
    "sg:city":"Simsbury",
    "sg:classifiers":[
        {
            "category":"Health Services",
            "subcategory":"Health Practitioner",
            "type":"Services"
        }
    ],
    "sg:phone":"+1 860 651 3381",
    "sg:postcode":"06089",
    "sg:province":"CT",
    "sg:tags":[
        "therapy",
        "physical"
    ],
    "sg:website":"www.vrcpt.com",
    "wof:name":"Valley Rehabilitation Center Inc",
    "wof:placetype":"venue"
},
  "geometry": {"coordinates":[-72.82347,41.828824],"type":"Point"}
}