{
  "type": "Feature",
  "properties": {
    "iso:country":"US",
    "sg:address":"308 Main St Exd",
    "sg:city":"Middletown",
    "sg:classifiers":[
        {
            "category":"Shopping",
            "subcategory":"Clothing, Apparel, & Fashions",
            "type":"Retail Goods"
        }
    ],
    "sg:phone":"+1 860 347 2889",
    "sg:postcode":"06457",
    "sg:province":"CT",
    "wof:name":"Regal Mens Shop",
    "wof:placetype":"venue"
},
  "geometry": {"coordinates":[-72.641075,41.549396],"type":"Point"}
}