{
  "type": "Feature",
  "properties": {
    "addr:full":"264 Amity Rd Woodbridge CT 06525",
    "addr:housenumber":"264",
    "addr:postcode":"06525",
    "addr:street":"Amity Rd",
    "iso:country":"US",
    "sg:address":"264 Amity Rd",
    "sg:city":"Woodbridge",
    "sg:classifiers":[
        {
            "category":"Social Services",
            "type":"Services"
        }
    ],
    "sg:phone":"+1   ",
    "sg:postcode":"06525",
    "sg:province":"CT",
    "wof:name":"Stacey G Bland Msw Lcsw",
    "wof:placetype":"venue"
},
  "geometry": {"coordinates":[-72.985181,41.343956],"type":"Point"}
}