{
  "type": "Feature",
  "properties": {
    "addr:full":"7 Ave B Westbrook CT 06498",
    "addr:postcode":"06498",
    "addr:street":"7 Ave B Westbrook Ct",
    "iso:country":"US",
    "sg:address":"7 Ave B",
    "sg:city":"Westbrook",
    "sg:classifiers":[
        {
            "category":"Professional",
            "subcategory":"Business Services",
            "type":"Services"
        }
    ],
    "sg:phone":"+1   ",
    "sg:postcode":"06498",
    "sg:province":"CT",
    "wof:name":"Cottages Castls Desgnng Women",
    "wof:placetype":"venue"
},
  "geometry": {"coordinates":[-72.43601700000001,41.27868],"type":"Point"}
}