{
  "type": "Feature",
  "properties": {
    "iso:country":"US",
    "sg:address":"55 Herman Ln",
    "sg:city":"Easton",
    "sg:classifiers":[
        {
            "category":"Professional",
            "subcategory":"Business Services",
            "type":"Services"
        }
    ],
    "sg:phone":"+1   ",
    "sg:postcode":"06612",
    "sg:province":"CT",
    "wof:name":"Silverman Nancy Associates LLC",
    "wof:placetype":"venue"
},
  "geometry": {"coordinates":[-73.301085,41.322363],"type":"Point"}
}