{
  "type": "Feature",
  "properties": {
    "addr:full":"8 Audubon Close Milford CT 06461",
    "addr:housenumber":"8",
    "addr:postcode":"06461",
    "addr:street":"Audubon Close",
    "iso:country":"US",
    "sg:address":"8 Audubon Close",
    "sg:city":"Milford",
    "sg:classifiers":[
        {
            "category":"Professional",
            "type":"Services"
        }
    ],
    "sg:phone":"+1   ",
    "sg:postcode":"06461",
    "sg:province":"CT",
    "wof:name":"Neihardt J B Studio LLC",
    "wof:placetype":"venue"
},
  "geometry": {"coordinates":[-73.086117,41.220242],"type":"Point"}
}