{
  "type": "Feature",
  "properties": {
    "addr:full":"72 Holmes Ave Darien CT 06820",
    "addr:housenumber":"72",
    "addr:postcode":"06820",
    "addr:street":"Holmes Ave Darien Ct",
    "iso:country":"US",
    "sg:address":"72 Holmes Ave",
    "sg:city":"Darien",
    "sg:classifiers":[
        {
            "category":"Real Estate",
            "subcategory":"Real Estate Agent",
            "type":"Services"
        }
    ],
    "sg:phone":"+1 203 667 5295",
    "sg:postcode":"06820",
    "sg:province":"CT",
    "wof:name":"Pinti Development LLC",
    "wof:placetype":"venue"
},
  "geometry": {"coordinates":[-73.509531,41.071491],"type":"Point"}
}