{
  "type": "Feature",
  "properties": {
    "addr:full":"98 Mountain Terrace Rd Hartford CT 06107",
    "addr:housenumber":"98",
    "addr:postcode":"06107",
    "addr:street":"Mountain Terrace Rd",
    "iso:country":"US",
    "sg:address":"98 Mountain Terrace Rd",
    "sg:city":"Hartford",
    "sg:classifiers":[
        {
            "category":"Banks & Credit Unions",
            "subcategory":"Financial Services",
            "type":"Services"
        }
    ],
    "sg:phone":"+1 860 521 5757",
    "sg:postcode":"06107",
    "sg:province":"CT",
    "sg:tags":[
        "trust",
        "nonprofit",
        "management"
    ],
    "wof:name":"Godbout Family Foundation",
    "wof:placetype":"venue"
},
  "geometry": {"coordinates":[-72.770324,41.757294],"type":"Point"}
}