{
  "type": "Feature",
  "properties": {
    "addr:full":"200 Connecticut Ave Norwalk CT 06854",
    "addr:housenumber":"200",
    "addr:postcode":"06854",
    "addr:street":"Connecticut Ave",
    "iso:country":"US",
    "sg:address":"200 Connecticut Ave",
    "sg:city":"Norwalk",
    "sg:classifiers":[
        {
            "category":"Professional",
            "subcategory":"Engineering",
            "type":"Services"
        }
    ],
    "sg:phone":"+1   ",
    "sg:postcode":"06854",
    "sg:province":"CT",
    "wof:name":"Day & Zimmermann Group Inc",
    "wof:placetype":"venue"
},
  "geometry": {"coordinates":[-73.43598,41.102664],"type":"Point"}
}