{
  "type": "Feature",
  "properties": {
    "iso:country":"US",
    "sg:address":"10 Tanager Ln",
    "sg:city":"Trumbull",
    "sg:classifiers":[
        {
            "category":"Education",
            "subcategory":"Special Training",
            "type":"Public Place"
        }
    ],
    "sg:phone":"+1   ",
    "sg:postcode":"06611",
    "sg:province":"CT",
    "sg:tags":[
        "nutrition",
        "health",
        "fitness"
    ],
    "wof:name":"Body Blast",
    "wof:placetype":"venue"
},
  "geometry": {"coordinates":[-73.175118,41.245329],"type":"Point"}
}