{
  "type": "Feature",
  "properties": {
    "iso:country":"US",
    "sg:address":"79 Whitfield St",
    "sg:city":"Guilford",
    "sg:classifiers":[
        {
            "category":"Food & Beverages",
            "subcategory":"Candy",
            "type":"Retail Goods"
        }
    ],
    "sg:phone":"+1 203 453 5226",
    "sg:postcode":"06437",
    "sg:province":"CT",
    "sg:tags":[
        "confectionery"
    ],
    "wof:name":"Village Chocolatier",
    "wof:placetype":"venue"
},
  "geometry": {"coordinates":[-72.68297200000001,41.283744],"type":"Point"}
}