{
  "type": "Feature",
  "properties": {
    "addr:full":"23 Glen Rd New Fairfield CT 06812",
    "addr:housenumber":"23",
    "addr:postcode":"06812",
    "addr:street":"Glen Rd New Fairfield Ct",
    "iso:country":"US",
    "sg:address":"23 Glen Rd",
    "sg:city":"New Fairfield",
    "sg:classifiers":[
        {
            "category":"Building & Trades",
            "subcategory":"Construction",
            "type":"Services"
        }
    ],
    "sg:phone":"+1 203 746 2279",
    "sg:postcode":"06812",
    "sg:province":"CT",
    "sg:tags":[
        "general",
        "contractor"
    ],
    "wof:name":"Purdy & Sons",
    "wof:placetype":"venue"
},
  "geometry": {"coordinates":[-73.487004,41.454926],"type":"Point"}
}