{
  "type": "Feature",
  "properties": {
    "iso:country":"US",
    "sg:address":"24 Cooley Ave",
    "sg:city":"Middletown",
    "sg:classifiers":[
        {
            "category":"Professional",
            "type":"Services"
        }
    ],
    "sg:phone":"+1 860 347 2299",
    "sg:postcode":"06457",
    "sg:province":"CT",
    "wof:name":"Richard A Pelc",
    "wof:placetype":"venue"
},
  "geometry": {"coordinates":[-72.645597,41.552088],"type":"Point"}
}