{
  "type": "Feature",
  "properties": {
    "iso:country":"US",
    "sg:address":"1115 Main St",
    "sg:city":"Bridgeport",
    "sg:classifiers":[
        {
            "category":"Real Estate",
            "subcategory":"Real Estate Agent",
            "type":"Services"
        }
    ],
    "sg:phone":"+1 203 332 0000",
    "sg:postcode":"06604",
    "sg:province":"CT",
    "wof:name":"Oak Bluff LLC",
    "wof:placetype":"venue"
},
  "geometry": {"coordinates":[-73.189634,41.179601],"type":"Point"}
}