{
  "type": "Feature",
  "properties": {
    "iso:country":"US",
    "sg:address":"5 Greenwood St",
    "sg:city":"Hartford",
    "sg:classifiers":[
        {
            "category":"Health Services",
            "subcategory":"Nursing And Care Facility",
            "type":"Services"
        }
    ],
    "sg:phone":"+1   ",
    "sg:postcode":"06106",
    "sg:province":"CT",
    "sg:tags":[
        "home"
    ],
    "wof:name":"Park Place Health Center",
    "wof:placetype":"venue"
},
  "geometry": {"coordinates":[-72.709987,41.755612],"type":"Point"}
}