{
  "type": "Feature",
  "properties": {
    "addr:full":"67 Andrews Ave Milford CT 06460",
    "addr:housenumber":"67",
    "addr:postcode":"06460",
    "addr:street":"Andrews Ave",
    "iso:country":"US",
    "sg:address":"67 Andrews Ave",
    "sg:city":"Milford",
    "sg:classifiers":[
        {
            "category":"Manufacturing",
            "subcategory":"Glass & Minerals",
            "type":"Manufacturing & Wholesale Goods"
        }
    ],
    "sg:phone":"+1 203 877 8903",
    "sg:postcode":"06460",
    "sg:province":"CT",
    "sg:tags":[
        "stone",
        "cut",
        "product"
    ],
    "wof:name":"Joe Passarelli & Co",
    "wof:placetype":"venue"
},
  "geometry": {"coordinates":[-73.090693,41.188577],"type":"Point"}
}