{
  "type": "Feature",
  "properties": {
    "addr:full":"1074 Hope St Stamford CT 06907",
    "addr:housenumber":"1074",
    "addr:postcode":"06907",
    "addr:street":"Hope St",
    "iso:country":"US",
    "sg:address":"1074 Hope St",
    "sg:city":"Stamford",
    "sg:classifiers":[
        {
            "category":"Building & Trades",
            "subcategory":"Construction",
            "type":"Services"
        }
    ],
    "sg:phone":"+1 203 322 2266",
    "sg:postcode":"06907",
    "sg:province":"CT",
    "sg:tags":[
        "designer",
        "dealer",
        "pool",
        "swimming"
    ],
    "wof:name":"Zelem Pool Co Inc",
    "wof:placetype":"venue"
},
  "geometry": {"coordinates":[-73.518435,41.094471],"type":"Point"}
}