{
  "type": "Feature",
  "properties": {
    "iso:country":"US",
    "sg:address":"203 Church St",
    "sg:city":"Naugatuck",
    "sg:classifiers":[
        {
            "category":"Professional",
            "subcategory":"Lawyer & Legal Services",
            "type":"Services"
        }
    ],
    "sg:phone":"+1 203 723 6691",
    "sg:postcode":"06770",
    "sg:province":"CT",
    "sg:tags":[
        "attorney"
    ],
    "wof:name":"Morrissey & Morrissey",
    "wof:placetype":"venue"
},
  "geometry": {"coordinates":[-73.05550100000001,41.489637],"type":"Point"}
}