{
  "type": "Feature",
  "properties": {
    "addr:full":"1410 Essex Rd Westbrook CT 06498",
    "addr:housenumber":"1410",
    "addr:postcode":"06498",
    "addr:street":"Essex Rd",
    "iso:country":"US",
    "sg:address":"1410 Essex Rd",
    "sg:city":"Westbrook",
    "sg:classifiers":[
        {
            "category":"Real Estate",
            "subcategory":"Real Estate Operator",
            "type":"Services"
        }
    ],
    "sg:phone":"+1 860 399 8442",
    "sg:postcode":"06498",
    "sg:province":"CT",
    "sg:tags":[
        "building",
        "nonresidential"
    ],
    "wof:name":"Shoebrook Properties LLC",
    "wof:placetype":"venue"
},
  "geometry": {"coordinates":[-72.434072,41.314489],"type":"Point"}
}