{
  "type": "Feature",
  "properties": {
    "iso:country":"US",
    "sg:address":"1068 Hartford Tpke",
    "sg:city":"Waterford",
    "sg:classifiers":[
        {
            "category":"Retail",
            "subcategory":"Repair Shop",
            "type":"Services"
        }
    ],
    "sg:phone":"+1   ",
    "sg:postcode":"06385",
    "sg:province":"CT",
    "wof:name":"Motorola",
    "wof:placetype":"venue"
},
  "geometry": {"coordinates":[-72.17192,41.398408],"type":"Point"}
}