{
  "type": "Feature",
  "properties": {
    "iso:country":"US",
    "sg:address":"40 Corporate Ave",
    "sg:city":"Plainville",
    "sg:classifiers":[
        {
            "category":"Insurance",
            "subcategory":"Insurance Agent",
            "type":"Services"
        }
    ],
    "sg:phone":"+1 860 953 0509",
    "sg:postcode":"06062",
    "sg:province":"CT",
    "sg:tags":[
        "employee",
        "benefit"
    ],
    "wof:name":"Health Consultants Group",
    "wof:placetype":"venue"
},
  "geometry": {"coordinates":[-72.859949,41.691071],"type":"Point"}
}