{
  "type": "Feature",
  "properties": {
    "addr:full":"102 Lake Shore Dr Middlefield CT 06455",
    "addr:housenumber":"102",
    "addr:postcode":"06455",
    "addr:street":"Lake Shore Dr",
    "iso:country":"US",
    "sg:address":"102 Lake Shore Dr",
    "sg:city":"Middlefield",
    "sg:classifiers":[
        {
            "category":"Building & Trades",
            "subcategory":"Electrical",
            "type":"Services"
        }
    ],
    "sg:phone":"+1 860 349 9528",
    "sg:postcode":"06455",
    "sg:province":"CT",
    "sg:tags":[
        "electrical",
        "contractor"
    ],
    "wof:name":"Monthei Brothers Elec Contrs",
    "wof:placetype":"venue"
},
  "geometry": {"coordinates":[-72.735854,41.513186],"type":"Point"}
}