{
  "type": "Feature",
  "properties": {
    "iso:country":"US",
    "sg:address":"1608 Sturbridge Ct",
    "sg:city":"Cheshire",
    "sg:classifiers":[
        {
            "category":"Health Services",
            "subcategory":"Doctor",
            "type":"Services"
        }
    ],
    "sg:phone":"+1 203 272 1364",
    "sg:postcode":"06410",
    "sg:province":"CT",
    "sg:tags":[
        "equipment",
        "surgeon",
        "physician",
        "supply"
    ],
    "sg:website":"http://www.cheshire-medical.com",
    "wof:name":"Cheshire Medical Specialties Inc.",
    "wof:placetype":"venue"
},
  "geometry": {"coordinates":[-72.902598,41.461473],"type":"Point"}
}