{
  "type": "Feature",
  "properties": {
    "addr:full":"3241 Main St Stratford CT 06614",
    "addr:housenumber":"3241",
    "addr:postcode":"06614",
    "addr:street":"Main St",
    "iso:country":"US",
    "sg:address":"3241 Main St",
    "sg:city":"Stratford",
    "sg:classifiers":[
        {
            "category":"Banks & Credit Unions",
            "subcategory":"Investment Brokerage",
            "type":"Services"
        }
    ],
    "sg:phone":"+1 203 378 6357",
    "sg:postcode":"06614",
    "sg:province":"CT",
    "sg:tags":[
        "stock",
        "bond"
    ],
    "sg:website":"www.wachovia.com",
    "wof:name":"Wachovia Securities",
    "wof:placetype":"venue"
},
  "geometry": {"coordinates":[-73.131888,41.204712],"type":"Point"}
}