{
  "type": "Feature",
  "properties": {
    "iso:country":"US",
    "sg:address":"14 Bank St",
    "sg:city":"Seymour",
    "sg:classifiers":[
        {
            "category":"Home & Garden",
            "subcategory":"Furniture",
            "type":"Retail Goods"
        }
    ],
    "sg:phone":"+1 203 888 3917",
    "sg:postcode":"06483",
    "sg:province":"CT",
    "wof:name":"Eckhardt Furniture Co Inc",
    "wof:placetype":"venue"
},
  "geometry": {"coordinates":[-73.073182,41.395563],"type":"Point"}
}