{
  "type": "Feature",
  "properties": {
    "iso:country":"US",
    "sg:address":"495 Meadow St",
    "sg:city":"Waterbury",
    "sg:classifiers":[
        {
            "category":"Professional",
            "subcategory":"Employment Agencies",
            "type":"Services"
        }
    ],
    "sg:phone":"+1 203 757 5187",
    "sg:postcode":"06702",
    "sg:province":"CT",
    "sg:tags":[
        "help",
        "contractor"
    ],
    "wof:name":"Labor Ready Inc",
    "wof:placetype":"venue"
},
  "geometry": {"coordinates":[-73.046628,41.557039],"type":"Point"}
}