{
  "type": "Feature",
  "properties": {
    "addr:full":"47 Rocky Ridge Rd Easton CT 06612",
    "addr:housenumber":"47",
    "addr:postcode":"06612",
    "addr:street":"Rocky Ridge Rd",
    "iso:country":"US",
    "sg:address":"47 Rocky Ridge Rd",
    "sg:city":"Easton",
    "sg:classifiers":[
        {
            "category":"Building & Trades",
            "subcategory":"Construction",
            "type":"Services"
        }
    ],
    "sg:phone":"+1 203 268 4282",
    "sg:postcode":"06612",
    "sg:province":"CT",
    "sg:tags":[
        "house"
    ],
    "wof:name":"DAmato Builders LLC",
    "wof:placetype":"venue"
},
  "geometry": {"coordinates":[-73.292389,41.303295],"type":"Point"}
}