{
  "type": "Feature",
  "properties": {
    "iso:country":"US",
    "sg:address":"225 Ocean Dr W",
    "sg:city":"Stamford",
    "sg:classifiers":[
        {
            "category":"Professional",
            "subcategory":"Management & Consulting",
            "type":"Services"
        }
    ],
    "sg:phone":"+1   ",
    "sg:postcode":"06902",
    "sg:province":"CT",
    "wof:name":"Marilyn Feinstein Sommer Csw",
    "wof:placetype":"venue"
},
  "geometry": {"coordinates":[-73.529175,41.029682],"type":"Point"}
}