{
  "type": "Feature",
  "properties": {
    "iso:country":"US",
    "sg:address":"168 Bradley St",
    "sg:city":"New Haven",
    "sg:classifiers":[
        {
            "category":"Professional",
            "subcategory":"Lawyer & Legal Services",
            "type":"Services"
        }
    ],
    "sg:phone":"+1 203 785 8929",
    "sg:postcode":"06511",
    "sg:province":"CT",
    "sg:tags":[
        "attorney"
    ],
    "wof:name":"Lasala Walsh Wicklow & Velardi",
    "wof:placetype":"venue"
},
  "geometry": {"coordinates":[-72.917203,41.312307],"type":"Point"}
}