{
  "type": "Feature",
  "properties": {
    "iso:country":"US",
    "sg:address":"380 W Main St",
    "sg:city":"Waterbury",
    "sg:classifiers":[
        {
            "category":"Freight",
            "type":"Transportation"
        }
    ],
    "sg:phone":"+1 203 597 9549",
    "sg:postcode":"06702",
    "sg:province":"CT",
    "wof:name":"Julias Express Movers",
    "wof:placetype":"venue"
},
  "geometry": {"coordinates":[-73.047318,41.557963],"type":"Point"}
}