{
  "type": "Feature",
  "properties": {
    "addr:full":"19 E Main St Mystic CT 06355",
    "addr:housenumber":"19",
    "addr:postcode":"06355",
    "addr:street":"E Main St",
    "iso:country":"US",
    "sg:address":"19 E Main St",
    "sg:city":"Mystic",
    "sg:classifiers":[
        {
            "category":"Professional",
            "subcategory":"Lawyer & Legal Services",
            "type":"Services"
        }
    ],
    "sg:phone":"+1   ",
    "sg:postcode":"06355",
    "sg:province":"CT",
    "wof:name":"Kathleen M Harkins",
    "wof:placetype":"venue"
},
  "geometry": {"coordinates":[-71.96693,41.354478],"type":"Point"}
}