{
  "type": "Feature",
  "properties": {
    "addr:full":"46 Poningo St Port Chester CT 10573",
    "addr:housenumber":"46",
    "addr:postcode":"10573",
    "addr:street":"Poningo St Port Chester Ct",
    "iso:country":"US",
    "sg:address":"46 Poningo St",
    "sg:city":"Port Chester",
    "sg:classifiers":[
        {
            "category":"Retail",
            "subcategory":"Self-service Laundry",
            "type":"Services"
        }
    ],
    "sg:phone":"+1 914 939 6210",
    "sg:postcode":"10573",
    "sg:province":"CT",
    "wof:name":"Wash & Dry",
    "wof:placetype":"venue"
},
  "geometry": {"coordinates":[-73.66604599999999,41.004152],"type":"Point"}
}