{
  "type": "Feature",
  "properties": {
    "iso:country":"US",
    "sg:address":"26 Shagbark Dr",
    "sg:city":"New Canaan",
    "sg:classifiers":[
        {
            "category":"Professional",
            "subcategory":"Management & Consulting",
            "type":"Services"
        }
    ],
    "sg:phone":"+1   ",
    "sg:postcode":"06840",
    "sg:province":"NY",
    "sg:tags":[
        "advisory",
        "financial"
    ],
    "wof:name":"Canaan Financial Group LLC",
    "wof:placetype":"venue"
},
  "geometry": {"coordinates":[-73.474839,41.125347],"type":"Point"}
}