{
  "type": "Feature",
  "properties": {
    "addr:full":"30 Miltiades Ave Riverside CT 06878",
    "addr:housenumber":"30",
    "addr:postcode":"06878",
    "addr:street":"Miltiades Ave Riverside Ct",
    "iso:country":"US",
    "sg:address":"30 Miltiades Ave",
    "sg:city":"Riverside",
    "sg:classifiers":[
        {
            "category":"Professional",
            "type":"Services"
        }
    ],
    "sg:phone":"+1 203 356 4947",
    "sg:postcode":"06878",
    "sg:province":"CT",
    "wof:name":"Gpq Inc",
    "wof:placetype":"venue"
},
  "geometry": {"coordinates":[-73.591381,41.030698],"type":"Point"}
}