{
  "type": "Feature",
  "properties": {
    "iso:country":"US",
    "sg:address":"2325 Summer St",
    "sg:city":"Stamford",
    "sg:classifiers":[
        {
            "category":"Personal",
            "subcategory":"Beauty Salon",
            "type":"Services"
        }
    ],
    "sg:phone":"+1 203 323 1600",
    "sg:postcode":"06905",
    "sg:province":"CT",
    "sg:tags":[
        "shop"
    ],
    "wof:name":"Elan Total Beauty Centre",
    "wof:placetype":"venue"
},
  "geometry": {"coordinates":[-73.545343,41.066735],"type":"Point"}
}