{
  "type": "Feature",
  "properties": {
    "iso:country":"US",
    "sg:address":"269 E Main St",
    "sg:city":"Branford",
    "sg:classifiers":[
        {
            "category":"Ice Cream",
            "type":"Food & Drink"
        }
    ],
    "sg:menulink":"http://www.allmenus.com/ct/branford/234481-ritas-ice-custard-happiness/menu/",
    "sg:phone":"+1 203 488 3263",
    "sg:postcode":"06405",
    "sg:province":"CT",
    "sg:tags":[
        "american"
    ],
    "wof:name":"Rita's Ice Custard Happiness",
    "wof:placetype":"venue"
},
  "geometry": {"coordinates":[-72.79602199999999,41.291003],"type":"Point"}
}