{
  "type": "Feature",
  "properties": {
    "addr:full":"55 Brittany Ln Naugatuck CT 06770",
    "addr:housenumber":"55",
    "addr:postcode":"06770",
    "addr:street":"Brittany Ln Naugatuck Ct",
    "iso:country":"US",
    "sg:address":"55 Brittany Ln",
    "sg:city":"Naugatuck",
    "sg:classifiers":[
        {
            "category":"Home & Garden",
            "subcategory":"Building Materials",
            "type":"Retail Goods"
        },
        {
            "category":"Building & Trades",
            "subcategory":"Construction",
            "type":"Services"
        }
    ],
    "sg:phone":"+1 203 723 7408",
    "sg:postcode":"06770",
    "sg:province":"CT",
    "sg:tags":[
        "concrete",
        "staining",
        "contractor"
    ],
    "wof:name":"The Original Concrete Crafter Inc",
    "wof:placetype":"venue"
},
  "geometry": {"coordinates":[-73.03663299999999,41.509472],"type":"Point"}
}