{
  "type": "Feature",
  "properties": {
    "iso:country":"US",
    "sg:address":"11 South Ave",
    "sg:city":"New Canaan",
    "sg:classifiers":[
        {
            "category":"Coffee & Tea",
            "type":"Food & Drink"
        },
        {
            "category":"Bagels",
            "type":"Food & Drink"
        }
    ],
    "sg:menulink":"http://www.allmenus.com/ct/new-canaan/25374-brueggers/menu/",
    "sg:phone":"+1 203 972 6610",
    "sg:postcode":"06840",
    "sg:province":"CT",
    "sg:tags":[
        "wrap",
        "soup",
        "american",
        "sandwich",
        "salad"
    ],
    "wof:name":"Bruegger's",
    "wof:placetype":"venue"
},
  "geometry": {"coordinates":[-73.49320400000001,41.146606],"type":"Point"}
}