{
  "type": "Feature",
  "properties": {
    "iso:country":"US",
    "sg:address":"54 Gifford Rd",
    "sg:city":"Hartford",
    "sg:classifiers":[
        {
            "category":"Professional",
            "subcategory":"Business Services",
            "type":"Services"
        }
    ],
    "sg:phone":"+1   ",
    "sg:postcode":"06119",
    "sg:province":"CT",
    "wof:name":"MB Assoc LLC",
    "wof:placetype":"venue"
},
  "geometry": {"coordinates":[-72.733121,41.753266],"type":"Point"}
}