{
  "type": "Feature",
  "properties": {
    "addr:full":"40 Old Ridgebury Rd Danbury CT 06810",
    "addr:housenumber":"40",
    "addr:postcode":"06810",
    "addr:street":"Old Ridgebury Rd",
    "iso:country":"US",
    "sg:address":"40 Old Ridgebury Rd",
    "sg:city":"Danbury",
    "sg:classifiers":[
        {
            "category":"Real Estate",
            "subcategory":"Real Estate Services",
            "type":"Services"
        }
    ],
    "sg:phone":"+1 203 794 9293",
    "sg:postcode":"06810",
    "sg:province":"CT",
    "sg:tags":[
        "management"
    ],
    "wof:name":"Danbury General Partners",
    "wof:placetype":"venue"
},
  "geometry": {"coordinates":[-73.51531199999999,41.38475],"type":"Point"}
}