{
  "type": "Feature",
  "properties": {
    "iso:country":"US",
    "sg:address":"1290 Boston Ave",
    "sg:city":"Bridgeport",
    "sg:classifiers":[
        {
            "category":"Retail",
            "subcategory":"Auto Repair",
            "type":"Services"
        }
    ],
    "sg:phone":"+1 203 332 1854",
    "sg:postcode":"06610",
    "sg:province":"CT",
    "sg:tags":[
        "muffler",
        "exhaust",
        "system"
    ],
    "wof:name":"Yankee Discount Muffler",
    "wof:placetype":"venue"
},
  "geometry": {"coordinates":[-73.169989,41.193292],"type":"Point"}
}