{
  "type": "Feature",
  "properties": {
    "iso:country":"US",
    "sg:address":"931 Main St",
    "sg:city":"Willimantic",
    "sg:classifiers":[
        {
            "category":"Restaurant",
            "type":"Food & Drink"
        }
    ],
    "sg:phone":"+1   ",
    "sg:postcode":"06226",
    "sg:province":"CT",
    "sg:tags":[
        "consulting",
        "management",
        "eating"
    ],
    "wof:name":"Thread City Cafe",
    "wof:placetype":"venue"
},
  "geometry": {"coordinates":[-72.216555,41.712794],"type":"Point"}
}