{
  "type": "Feature",
  "properties": {
    "addr:full":"32 Brookhill Ln Norwalk CT 06851",
    "addr:housenumber":"32",
    "addr:postcode":"06851",
    "addr:street":"Brookhill Ln",
    "iso:country":"US",
    "sg:address":"32 Brookhill Ln",
    "sg:city":"Norwalk",
    "sg:classifiers":[
        {
            "category":"Professional",
            "subcategory":"Business Services",
            "type":"Services"
        }
    ],
    "sg:phone":"+1   ",
    "sg:postcode":"06851",
    "sg:province":"CT",
    "wof:name":"FL Enterprises LLC",
    "wof:placetype":"venue"
},
  "geometry": {"coordinates":[-73.411337,41.142544],"type":"Point"}
}