{
  "type": "Feature",
  "properties": {
    "iso:country":"US",
    "sg:address":"185 N Timber Ln",
    "sg:city":"Cheshire",
    "sg:classifiers":[
        {
            "category":"Building & Trades",
            "subcategory":"Construction",
            "type":"Services"
        }
    ],
    "sg:phone":"+1 203 272 0454",
    "sg:postcode":"06410",
    "sg:province":"CT",
    "sg:tags":[
        "hanging",
        "contractor"
    ],
    "wof:name":"Jardim Painting",
    "wof:placetype":"venue"
},
  "geometry": {"coordinates":[-72.92706200000001,41.509087],"type":"Point"}
}