{
  "type": "Feature",
  "properties": {
    "iso:country":"US",
    "sg:address":"33 Sherwood Pl",
    "sg:city":"Greenwich",
    "sg:classifiers":[
        {
            "category":"Professional",
            "subcategory":"Advertising",
            "type":"Services"
        }
    ],
    "sg:phone":"+1   ",
    "sg:postcode":"06830",
    "sg:province":"CT",
    "sg:tags":[
        "mail",
        "direct"
    ],
    "wof:name":"Williamson Agency",
    "wof:placetype":"venue"
},
  "geometry": {"coordinates":[-73.624814,41.033403],"type":"Point"}
}