{
  "type": "Feature",
  "properties": {
    "iso:country":"US",
    "sg:address":"491 Howard Ave",
    "sg:city":"New Haven",
    "sg:classifiers":[
        {
            "category":"Food & Beverages",
            "subcategory":"Groceries & Convenience Stores",
            "type":"Retail Goods"
        }
    ],
    "sg:phone":"+1 203 785 1113",
    "sg:postcode":"06519",
    "sg:province":"CT",
    "sg:tags":[
        "grocer"
    ],
    "wof:name":"Victor's Market",
    "wof:placetype":"venue"
},
  "geometry": {"coordinates":[-72.933446,41.295254],"type":"Point"}
}