{
  "type": "Feature",
  "properties": {
    "addr:full":"33 Adams Ave Stamford CT 06902",
    "addr:housenumber":"33",
    "addr:postcode":"06902",
    "addr:street":"Adams Ave",
    "iso:country":"US",
    "sg:address":"33 Adams Ave",
    "sg:city":"Stamford",
    "sg:classifiers":[
        {
            "category":"Professional",
            "type":"Services"
        }
    ],
    "sg:phone":"+1 203 357 9188",
    "sg:postcode":"06902",
    "sg:province":"CT",
    "wof:name":"Gerald Apollon",
    "wof:placetype":"venue"
},
  "geometry": {"coordinates":[-73.547606,41.056937],"type":"Point"}
}