{
  "type": "Feature",
  "properties": {
    "addr:full":"169 Sturges Ridge Rd Wilton CT 06897",
    "addr:housenumber":"169",
    "addr:postcode":"06897",
    "addr:street":"Sturges Ridge Rd Wilton Ct",
    "iso:country":"US",
    "sg:address":"169 Sturges Ridge Rd",
    "sg:city":"Wilton",
    "sg:classifiers":[
        {
            "category":"Professional",
            "type":"Services"
        }
    ],
    "sg:phone":"+1 203 834 8836",
    "sg:postcode":"06897",
    "sg:province":"CT",
    "wof:name":"Kenneth Kupersmith",
    "wof:placetype":"venue"
},
  "geometry": {"coordinates":[-73.40378699999999,41.210587],"type":"Point"}
}