{
  "type": "Feature",
  "properties": {
    "addr:full":"595 Chapel St New Haven CT 06511",
    "addr:housenumber":"595",
    "addr:postcode":"06511",
    "addr:street":"Chapel St",
    "iso:country":"US",
    "sg:address":"595 Chapel St",
    "sg:city":"New Haven",
    "sg:classifiers":[
        {
            "category":"Shopping",
            "subcategory":"Florist",
            "type":"Retail Goods"
        }
    ],
    "sg:phone":"+1 203 865 3671",
    "sg:postcode":"06511",
    "sg:province":"CT",
    "sg:tags":[
        "grocery"
    ],
    "wof:name":"Wooster Square Flower & Gift",
    "wof:placetype":"venue"
},
  "geometry": {"coordinates":[-72.919747,41.303953],"type":"Point"}
}