{
  "type": "Feature",
  "properties": {
    "addr:full":"14 Catlin Dr Wallingford CT 06492",
    "addr:housenumber":"14",
    "addr:postcode":"06492",
    "addr:street":"Catlin Dr",
    "iso:country":"US",
    "sg:address":"14 Catlin Dr",
    "sg:city":"Wallingford",
    "sg:classifiers":[
        {
            "category":"Professional",
            "subcategory":"Business Services",
            "type":"Services"
        }
    ],
    "sg:phone":"+1   ",
    "sg:postcode":"06492",
    "sg:province":"CT",
    "wof:name":"Spring Break Solutions LLC",
    "wof:placetype":"venue"
},
  "geometry": {"coordinates":[-72.79210399999999,41.474169],"type":"Point"}
}