{
  "type": "Feature",
  "properties": {
    "addr:full":"315 Lane St Hamden CT 06514",
    "addr:housenumber":"315",
    "addr:postcode":"06514",
    "addr:street":"Lane St",
    "iso:country":"US",
    "sg:address":"315 Lane St",
    "sg:city":"Hamden",
    "sg:classifiers":[
        {
            "category":"Education",
            "subcategory":"School",
            "type":"Public Place"
        }
    ],
    "sg:phone":"+1 203 407 2025",
    "sg:postcode":"06514",
    "sg:province":"CT",
    "sg:website":"www.hamden.org",
    "wof:name":"Dunbar Hill School",
    "wof:placetype":"venue"
},
  "geometry": {"coordinates":[-72.94121699999999,41.365328],"type":"Point"}
}