{
  "type": "Feature",
  "properties": {
    "iso:country":"US",
    "sg:address":"11 Joe Sabbath Dr",
    "sg:city":"Tolland",
    "sg:classifiers":[
        {
            "category":"Building & Trades",
            "subcategory":"Construction",
            "type":"Services"
        }
    ],
    "sg:phone":"+1 860 871 9055",
    "sg:postcode":"06084",
    "sg:province":"CT",
    "sg:tags":[
        "home",
        "general",
        "contractor"
    ],
    "wof:name":"Nordic Builders Tolland LLC",
    "wof:placetype":"venue"
},
  "geometry": {"coordinates":[-72.394381,41.887002],"type":"Point"}
}