{
  "type": "Feature",
  "properties": {
    "iso:country":"US",
    "sg:address":"239 Flanders Rd",
    "sg:city":"Niantic",
    "sg:classifiers":[
        {
            "category":"Travel",
            "subcategory":"Hotels & Motels",
            "type":"Entertainment"
        }
    ],
    "sg:phone":"+1   ",
    "sg:postcode":"06357",
    "sg:province":"CT",
    "wof:name":"Jai Shri Krishna LLC",
    "wof:placetype":"venue"
},
  "geometry": {"coordinates":[-72.210354,41.356021],"type":"Point"}
}