{
  "type": "Feature",
  "properties": {
    "iso:country":"US",
    "sg:address":"600 Middlebury Rd",
    "sg:city":"Middlebury",
    "sg:classifiers":[
        {
            "category":"Banks & Credit Unions",
            "subcategory":"Bank",
            "type":"Services"
        }
    ],
    "sg:phone":"+1 203 598 7777",
    "sg:postcode":"06762",
    "sg:province":"CT",
    "wof:name":"Naugatuck Savings Bank",
    "wof:placetype":"venue"
},
  "geometry": {"coordinates":[-73.108583,41.537766],"type":"Point"}
}