{
  "type": "Feature",
  "properties": {
    "addr:full":"530 Preston Ave Shelton CT 06450",
    "addr:housenumber":"530",
    "addr:postcode":"06450",
    "addr:street":"Preston Ave",
    "iso:country":"US",
    "sg:address":"530 Preston Ave",
    "sg:city":"Shelton",
    "sg:classifiers":[
        {
            "category":"Insurance",
            "subcategory":"Insurance Agent",
            "type":"Services"
        }
    ],
    "sg:phone":"+1 203 225 7960",
    "sg:postcode":"06450",
    "sg:province":"CT",
    "wof:name":"Leader Insurance",
    "wof:placetype":"venue"
},
  "geometry": {"coordinates":[-72.75178,41.539459],"type":"Point"}
}