{
  "type": "Feature",
  "properties": {
    "iso:country":"US",
    "sg:address":"215 1st Ave",
    "sg:city":"West Haven",
    "sg:classifiers":[
        {
            "category":"Building & Trades",
            "subcategory":"Cleaning & Sanitation",
            "type":"Services"
        }
    ],
    "sg:phone":"+1 203 265 2619",
    "sg:postcode":"06516",
    "sg:province":"CT",
    "sg:tags":[
        "janitor"
    ],
    "wof:name":"Squeeky Kleen",
    "wof:placetype":"venue"
},
  "geometry": {"coordinates":[-72.938029,41.274267],"type":"Point"}
}