{
  "type": "Feature",
  "properties": {
    "addr:full":"116 Avon St Stratford CT 06615",
    "addr:housenumber":"116",
    "addr:postcode":"06615",
    "addr:street":"Avon St",
    "iso:country":"US",
    "sg:address":"116 Avon St",
    "sg:city":"Stratford",
    "sg:classifiers":[
        {
            "category":"Personal",
            "subcategory":"Beauty Salon",
            "type":"Services"
        }
    ],
    "sg:phone":"+1   ",
    "sg:postcode":"06615",
    "sg:province":"CT",
    "sg:tags":[
        "shop"
    ],
    "wof:name":"Shear Talent",
    "wof:placetype":"venue"
},
  "geometry": {"coordinates":[-73.146788,41.182931],"type":"Point"}
}