{
  "type": "Feature",
  "properties": {
    "iso:country":"US",
    "sg:address":"1230 Thomaston Ave",
    "sg:city":"Waterbury",
    "sg:classifiers":[
        {
            "category":"Restaurant",
            "type":"Food & Drink"
        }
    ],
    "sg:phone":"+1 203 755 1173",
    "sg:postcode":"06704",
    "sg:province":"CT",
    "wof:name":"Bacco's",
    "wof:placetype":"venue"
},
  "geometry": {"coordinates":[-73.054256,41.568488],"type":"Point"}
}