{
  "type": "Feature",
  "properties": {
    "addr:full":"50 E Industrial Dr Branford CT 06405",
    "addr:housenumber":"50",
    "addr:postcode":"06405",
    "addr:street":"E Industrial Dr",
    "iso:country":"US",
    "sg:address":"50 E Industrial Dr",
    "sg:city":"Branford",
    "sg:classifiers":[
        {
            "category":"Manufacturing",
            "subcategory":"Tools & Machinery",
            "type":"Manufacturing & Wholesale Goods"
        }
    ],
    "sg:phone":"+1 203 481 0500",
    "sg:postcode":"06405",
    "sg:province":"CT",
    "sg:tags":[
        "physician",
        "surgeon"
    ],
    "sg:website":"www.aplicare.com",
    "wof:name":"Aplicare Inc",
    "wof:placetype":"venue"
},
  "geometry": {"coordinates":[-72.76405099999999,41.297065],"type":"Point"}
}