{
  "type": "Feature",
  "properties": {
    "iso:country":"US",
    "sg:address":"59 Taft St",
    "sg:city":"Waterbury",
    "sg:classifiers":[
        {
            "category":"Professional",
            "subcategory":"Business Services",
            "type":"Services"
        }
    ],
    "sg:phone":"+1   ",
    "sg:postcode":"06708",
    "sg:province":"CT",
    "sg:tags":[
        "interior",
        "design"
    ],
    "wof:name":"C & J Interiors",
    "wof:placetype":"venue"
},
  "geometry": {"coordinates":[-73.04965199999999,41.535405],"type":"Point"}
}