{
  "type": "Feature",
  "properties": {
    "addr:full":"527 Elm St New Haven CT 06511",
    "addr:housenumber":"527",
    "addr:postcode":"06511",
    "addr:street":"Elm St",
    "iso:country":"US",
    "sg:address":"527 Elm St",
    "sg:city":"New Haven",
    "sg:classifiers":[
        {
            "category":"Building & Trades",
            "subcategory":"Equipment Rental",
            "type":"Services"
        }
    ],
    "sg:phone":"+1 203 865 5152",
    "sg:postcode":"06511",
    "sg:province":"CT",
    "sg:tags":[
        "yard"
    ],
    "wof:name":"Rent-A-Center",
    "wof:placetype":"venue"
},
  "geometry": {"coordinates":[-72.937397,41.313338],"type":"Point"}
}