{
  "type": "Feature",
  "properties": {
    "addr:full":"441 Bishop Ave Bridgeport CT 06610",
    "addr:housenumber":"441",
    "addr:postcode":"06610",
    "addr:street":"Bishop Ave",
    "iso:country":"US",
    "sg:address":"441 Bishop Ave",
    "sg:city":"Bridgeport",
    "sg:classifiers":[
        {
            "category":"Organizations",
            "subcategory":"Religious Organization",
            "type":"Services"
        }
    ],
    "sg:phone":"+1 203 367 4998",
    "sg:postcode":"06610",
    "sg:province":"CT",
    "sg:tags":[
        "church"
    ],
    "wof:name":"Christian Revival Assembly God",
    "wof:placetype":"venue"
},
  "geometry": {"coordinates":[-73.157112,41.187482],"type":"Point"}
}