{
  "type": "Feature",
  "properties": {
    "addr:full":"284 School St Putnam CT 06260",
    "addr:housenumber":"284",
    "addr:postcode":"06260",
    "addr:street":"School St Putnam Ct",
    "iso:country":"US",
    "sg:address":"284 School St",
    "sg:city":"Putnam",
    "sg:classifiers":[
        {
            "category":"Manufacturing",
            "subcategory":"Tools & Machinery",
            "type":"Manufacturing & Wholesale Goods"
        }
    ],
    "sg:phone":"+1 860 928 5279",
    "sg:postcode":"06260",
    "sg:province":"CT",
    "sg:tags":[
        "industrial",
        "mfg"
    ],
    "wof:name":"Reliable Machining Associates",
    "wof:placetype":"venue"
},
  "geometry": {"coordinates":[-71.902198,41.920978],"type":"Point"}
}