{
  "type": "Feature",
  "properties": {
    "addr:full":"1216 Hartford Tpke Vernon Rockville CT 06066",
    "addr:housenumber":"1216",
    "addr:postcode":"06066",
    "addr:street":"Hartford Tpke",
    "iso:country":"US",
    "sg:address":"1216 Hartford Tpke",
    "sg:city":"Vernon Rockville",
    "sg:classifiers":[
        {
            "category":"Education",
            "subcategory":"Dance Studio",
            "type":"Public Place"
        }
    ],
    "sg:phone":"+1   ",
    "sg:postcode":"06066",
    "sg:province":"CT",
    "wof:name":"Toriography Dance Center",
    "wof:placetype":"venue"
},
  "geometry": {"coordinates":[-72.437758,41.856515],"type":"Point"}
}