{
  "type": "Feature",
  "properties": {
    "addr:full":"1717 Foxon Rd North Branford CT 06471",
    "addr:housenumber":"1717",
    "addr:postcode":"06471",
    "addr:street":"Foxon Rd North Branford Ct",
    "iso:country":"US",
    "sg:address":"1717 Foxon Rd",
    "sg:city":"North Branford",
    "sg:classifiers":[
        {
            "category":"Sports & Exercise",
            "subcategory":"Gym",
            "type":"Entertainment"
        }
    ],
    "sg:phone":"+1 203 483 9788",
    "sg:postcode":"06471",
    "sg:province":"CT",
    "sg:tags":[
        "club",
        "health",
        "studio",
        "gymnasium"
    ],
    "wof:name":"Curves For Women",
    "wof:placetype":"venue"
},
  "geometry": {"coordinates":[-72.765529,41.328578],"type":"Point"}
}