{
  "type": "Feature",
  "properties": {
    "addr:full":"247 Kimberly Ave New Haven CT 06519",
    "addr:housenumber":"247",
    "addr:postcode":"06519",
    "addr:street":"Kimberly Ave",
    "iso:country":"US",
    "sg:address":"247 Kimberly Ave",
    "sg:city":"New Haven",
    "sg:classifiers":[
        {
            "category":"Autos & Motor Vehicles",
            "subcategory":"Automobile Sales",
            "type":"Retail Goods"
        }
    ],
    "sg:phone":"+1 203 624 0279",
    "sg:postcode":"06519",
    "sg:province":"CT",
    "sg:tags":[
        "car",
        "dealer"
    ],
    "wof:name":"Gumbo's Auto Sales",
    "wof:placetype":"venue"
},
  "geometry": {"coordinates":[-72.937516,41.284202],"type":"Point"}
}