{
  "type": "Feature",
  "properties": {
    "addr:full":"91 Golf Ln Ridgefield CT 06877",
    "addr:housenumber":"91",
    "addr:postcode":"06877",
    "addr:street":"Golf",
    "iso:country":"US",
    "sg:address":"91 Golf Ln",
    "sg:city":"Ridgefield",
    "sg:classifiers":[
        {
            "category":"Building & Trades",
            "subcategory":"Construction",
            "type":"Services"
        }
    ],
    "sg:phone":"+1 203 431 6359",
    "sg:postcode":"06877",
    "sg:province":"CT",
    "sg:tags":[
        "residential"
    ],
    "wof:name":"A J Czyr Inc",
    "wof:placetype":"venue"
},
  "geometry": {"coordinates":[-73.51061900000001,41.27048],"type":"Point"}
}