{
  "type": "Feature",
  "properties": {
    "iso:country":"US",
    "sg:address":"33 Doe Meadow Ct",
    "sg:city":"Southington",
    "sg:classifiers":[
        {
            "category":"Real Estate",
            "subcategory":"Real Estate Agent",
            "type":"Services"
        }
    ],
    "sg:phone":"+1 860 628 9984",
    "sg:postcode":"06489",
    "sg:province":"CT",
    "wof:name":"JM Property Management Co",
    "wof:placetype":"venue"
},
  "geometry": {"coordinates":[-72.84672999999999,41.583221],"type":"Point"}
}