{
  "type": "Feature",
  "properties": {
    "iso:country":"US",
    "sg:address":"350 Chapel Rd",
    "sg:city":"South Windsor",
    "sg:classifiers":[
        {
            "category":"Building & Trades",
            "subcategory":"Construction",
            "type":"Services"
        }
    ],
    "sg:phone":"+1 860 436 4340",
    "sg:postcode":"06074",
    "sg:province":"CT",
    "sg:tags":[
        "contractor"
    ],
    "wof:name":"MB Masonry",
    "wof:placetype":"venue"
},
  "geometry": {"coordinates":[-72.608097,41.811158],"type":"Point"}
}