{
  "type": "Feature",
  "properties": {
    "iso:country":"US",
    "sg:address":"139 Moody St",
    "sg:city":"Bristol",
    "sg:classifiers":[
        {
            "category":"Wholesale",
            "subcategory":"Machinery & Supplies",
            "type":"Manufacturing & Wholesale Goods"
        }
    ],
    "sg:phone":"+1 860 585 7459",
    "sg:postcode":"06010",
    "sg:province":"CT",
    "sg:tags":[
        "equipment",
        "industrial"
    ],
    "wof:name":"Mal Machine Tools LLC",
    "wof:placetype":"venue"
},
  "geometry": {"coordinates":[-72.926776,41.687954],"type":"Point"}
}