{
  "type": "Feature",
  "properties": {
    "addr:full":"79 Lenox St Manchester CT 06040",
    "addr:housenumber":"79",
    "addr:postcode":"06040",
    "addr:street":"Lenox St",
    "iso:country":"US",
    "sg:address":"79 Lenox St",
    "sg:city":"Manchester",
    "sg:classifiers":[
        {
            "category":"Building & Trades",
            "subcategory":"Construction",
            "type":"Services"
        }
    ],
    "sg:phone":"+1 860 646 8967",
    "sg:postcode":"06040",
    "sg:province":"CT",
    "sg:tags":[
        "house"
    ],
    "wof:name":"GSC Construction LLC",
    "wof:placetype":"venue"
},
  "geometry": {"coordinates":[-72.511081,41.778723],"type":"Point"}
}