{
  "type": "Feature",
  "properties": {
    "addr:full":"236 Wauregan Rd Danielson CT 06239",
    "addr:housenumber":"236",
    "addr:postcode":"06239",
    "addr:street":"Wauregan Rd",
    "iso:country":"US",
    "sg:address":"236 Wauregan Rd",
    "sg:city":"Danielson",
    "sg:classifiers":[
        {
            "category":"Shopping",
            "type":"Retail Goods"
        }
    ],
    "sg:phone":"+1 860 774 8920",
    "sg:postcode":"06239",
    "sg:province":"CT",
    "sg:tags":[
        "merchandise"
    ],
    "wof:name":"Houles Music Shop",
    "wof:placetype":"venue"
},
  "geometry": {"coordinates":[-71.89000799999999,41.781885],"type":"Point"}
}