{
  "type": "Feature",
  "properties": {
    "addr:full":"35 Copps Hill Rd Ridgefield CT 06877",
    "addr:housenumber":"35",
    "addr:postcode":"06877",
    "addr:street":"Copps Hill Rd",
    "iso:country":"US",
    "sg:address":"35 Copps Hill Rd",
    "sg:city":"Ridgefield",
    "sg:classifiers":[
        {
            "category":"Social Services",
            "subcategory":"Child Care",
            "type":"Services"
        },
        {
            "category":"Education",
            "subcategory":"Preschool",
            "type":"Public Place"
        },
        {
            "category":"Education",
            "subcategory":"School",
            "type":"Public Place"
        }
    ],
    "sg:phone":"+1 203 438 6118",
    "sg:postcode":"06877",
    "sg:province":"CT",
    "sg:tags":[
        "kindergarten",
        "nursery",
        "day"
    ],
    "sg:website":"http://www.almosthomecc.com",
    "wof:name":"Almost Home Childcare",
    "wof:placetype":"venue"
},
  "geometry": {"coordinates":[-73.495155,41.295497],"type":"Point"}
}