{
  "type": "Feature",
  "properties": {
    "iso:country":"US",
    "sg:address":"3250 Fairfield Ave",
    "sg:city":"Bridgeport",
    "sg:classifiers":[
        {
            "category":"Autos & Motor Vehicles",
            "subcategory":"Auto Supplies",
            "type":"Retail Goods"
        }
    ],
    "sg:phone":"+1 203 334 5139",
    "sg:postcode":"06605",
    "sg:province":"CT",
    "wof:name":"Motors Pba Millennium",
    "wof:placetype":"venue"
},
  "geometry": {"coordinates":[-73.231936,41.155675],"type":"Point"}
}