{
  "type": "Feature",
  "properties": {
    "addr:full":"6 Daniel Ct Westport CT 06880",
    "addr:housenumber":"6",
    "addr:postcode":"06880",
    "addr:street":"Daniel Ct",
    "iso:country":"US",
    "sg:address":"6 Daniel Ct",
    "sg:city":"Westport",
    "sg:classifiers":[
        {
            "category":"Professional",
            "type":"Services"
        }
    ],
    "sg:phone":"+1 203 254 9594",
    "sg:postcode":"06880",
    "sg:province":"CT",
    "wof:name":"John D & Sharon W Miller",
    "wof:placetype":"venue"
},
  "geometry": {"coordinates":[-73.319463,41.164933],"type":"Point"}
}