{
  "type": "Feature",
  "properties": {
    "addr:full":"323 Broad St Windsor CT 06095",
    "addr:housenumber":"323",
    "addr:postcode":"06095",
    "addr:street":"Broad St",
    "iso:country":"US",
    "sg:address":"323 Broad St",
    "sg:city":"Windsor",
    "sg:classifiers":[
        {
            "category":"Education",
            "subcategory":"Library",
            "type":"Public Place"
        }
    ],
    "sg:phone":"+1 860 285 1910",
    "sg:postcode":"06095",
    "sg:province":"CT",
    "sg:tags":[
        "executive"
    ],
    "wof:name":"Windsor Public Library",
    "wof:placetype":"venue"
},
  "geometry": {"coordinates":[-72.644879,41.848909],"type":"Point"}
}