{
  "type": "Feature",
  "properties": {
    "iso:country":"US",
    "sg:address":"1031 S Main St",
    "sg:city":"Cheshire",
    "sg:classifiers":[
        {
            "category":"Restaurant",
            "type":"Food & Drink"
        }
    ],
    "sg:menulink":"http://www.allmenus.com/ct/cheshire/144028-subway/menu/",
    "sg:phone":"+1 203 250 8225",
    "sg:postcode":"06410",
    "sg:province":"CT",
    "sg:tags":[
        "american",
        "sandwich"
    ],
    "wof:name":"Subway",
    "wof:placetype":"venue"
},
  "geometry": {"coordinates":[-72.906195,41.476379],"type":"Point"}
}