{
  "type": "Feature",
  "properties": {
    "addr:full":"809 Wolcott St Waterbury CT 06705",
    "addr:housenumber":"809",
    "addr:postcode":"06705",
    "addr:street":"Wolcott St Waterbury Ct",
    "iso:country":"US",
    "sg:address":"809 Wolcott St",
    "sg:city":"Waterbury",
    "sg:classifiers":[
        {
            "category":"Autos & Motor Vehicles",
            "subcategory":"Auto Supplies",
            "type":"Retail Goods"
        }
    ],
    "sg:phone":"+1 203 754 6119",
    "sg:postcode":"06705",
    "sg:province":"CT",
    "sg:tags":[
        "tire"
    ],
    "wof:name":"Firestone Tire & Auto Ctr",
    "wof:placetype":"venue"
},
  "geometry": {"coordinates":[-73.010825,41.562017],"type":"Point"}
}