{
  "type": "Feature",
  "properties": {
    "iso:country":"US",
    "sg:address":"10 Roberts Ln",
    "sg:city":"Ridgefield",
    "sg:classifiers":[
        {
            "category":"Real Estate",
            "subcategory":"Real Estate Agent",
            "type":"Services"
        }
    ],
    "sg:phone":"+1 203 438 0433",
    "sg:postcode":"06877",
    "sg:province":"CT",
    "wof:name":"Eppoliti Realty Co Inc",
    "wof:placetype":"venue"
},
  "geometry": {"coordinates":[-73.498183,41.289858],"type":"Point"}
}