{
  "type": "Feature",
  "properties": {
    "addr:full":"73 Beachside Ave Westport CT 06880",
    "addr:housenumber":"73",
    "addr:postcode":"06880",
    "addr:street":"Beachside Ave",
    "iso:country":"US",
    "sg:address":"73 Beachside Ave",
    "sg:city":"Westport",
    "sg:classifiers":[
        {
            "category":"Real Estate",
            "subcategory":"Real Estate Agent",
            "type":"Services"
        }
    ],
    "sg:phone":"+1 203 372 1252",
    "sg:postcode":"06880",
    "sg:province":"CT",
    "wof:name":"Donald J Sherman",
    "wof:placetype":"venue"
},
  "geometry": {"coordinates":[-73.311305,41.116896],"type":"Point"}
}