{
  "type": "Feature",
  "properties": {
    "iso:country":"US",
    "sg:address":"12 Great Pond Ln",
    "sg:city":"Redding",
    "sg:classifiers":[
        {
            "category":"Professional",
            "subcategory":"Management & Consulting",
            "type":"Services"
        }
    ],
    "sg:phone":"+1   ",
    "sg:postcode":"06896",
    "sg:province":"CT",
    "wof:name":"Walder Consulting",
    "wof:placetype":"venue"
},
  "geometry": {"coordinates":[-73.46655699999999,41.316266],"type":"Point"}
}