{
  "type": "Feature",
  "properties": {
    "addr:full":"350 Amsterdam Ave Bridgeport CT 06606",
    "addr:housenumber":"350",
    "addr:postcode":"06606",
    "addr:street":"Amsterdam Ave",
    "iso:country":"US",
    "sg:address":"350 Amsterdam Ave",
    "sg:city":"Bridgeport",
    "sg:classifiers":[
        {
            "category":"Building & Trades",
            "subcategory":"Landscaping Services",
            "type":"Services"
        }
    ],
    "sg:phone":"+1 203 371 5591",
    "sg:postcode":"06606",
    "sg:province":"CT",
    "wof:name":"Bella Landscaping",
    "wof:placetype":"venue"
},
  "geometry": {"coordinates":[-73.210751,41.203094],"type":"Point"}
}