{
  "type": "Feature",
  "properties": {
    "addr:full":"93 Long Ridge Rd Danbury CT 06810",
    "addr:housenumber":"93",
    "addr:postcode":"06810",
    "addr:street":"Long Ridge Rd",
    "iso:country":"US",
    "sg:address":"93 Long Ridge Rd",
    "sg:city":"Danbury",
    "sg:classifiers":[
        {
            "category":"Organizations",
            "subcategory":"Membership Organization",
            "type":"Services"
        }
    ],
    "sg:phone":"+1 203 743 2299",
    "sg:postcode":"06810",
    "sg:province":"CT",
    "wof:name":"Stamp Collectors Society-Amer",
    "wof:placetype":"venue"
},
  "geometry": {"coordinates":[-73.43559500000001,41.362975],"type":"Point"}
}