{
  "type": "Feature",
  "properties": {
    "iso:country":"US",
    "sg:address":"151 Booth Hill Rd",
    "sg:city":"Trumbull",
    "sg:classifiers":[
        {
            "category":"Real Estate",
            "subcategory":"Developer",
            "type":"Services"
        }
    ],
    "sg:phone":"+1 203 378 7318",
    "sg:postcode":"06611",
    "sg:province":"CT",
    "wof:name":"Rst Associates",
    "wof:placetype":"venue"
},
  "geometry": {"coordinates":[-73.17195700000001,41.2428],"type":"Point"}
}