{
  "type": "Feature",
  "properties": {
    "iso:country":"US",
    "sg:address":"14 Middle Rd",
    "sg:city":"Southbury",
    "sg:classifiers":[
        {
            "category":"Professional",
            "subcategory":"Management & Consulting",
            "type":"Services"
        }
    ],
    "sg:phone":"+1   ",
    "sg:postcode":"06488",
    "sg:province":"CT",
    "sg:tags":[
        "business"
    ],
    "wof:name":"Tbc Training & Consulting LLC",
    "wof:placetype":"venue"
},
  "geometry": {"coordinates":[-73.24932,41.468652],"type":"Point"}
}