{
  "type": "Feature",
  "properties": {
    "addr:full":"835 Hope St Stamford CT 06907",
    "addr:housenumber":"835",
    "addr:postcode":"06907",
    "addr:street":"Hope St",
    "iso:country":"US",
    "sg:address":"835 Hope St",
    "sg:city":"Stamford",
    "sg:classifiers":[
        {
            "category":"Education",
            "subcategory":"Special Training",
            "type":"Public Place"
        }
    ],
    "sg:phone":"+1 203 323 4974",
    "sg:postcode":"06907",
    "sg:province":"CT",
    "sg:tags":[
        "center"
    ],
    "wof:name":"Learning In Retirement",
    "wof:placetype":"venue"
},
  "geometry": {"coordinates":[-73.518585,41.088127],"type":"Point"}
}