{
  "type": "Feature",
  "properties": {
    "addr:full":"316 Boston Post Rd Waterford CT 06385",
    "addr:housenumber":"316",
    "addr:postcode":"06385",
    "addr:street":"Boston Post Rd",
    "iso:country":"US",
    "sg:address":"316 Boston Post Rd",
    "sg:city":"Waterford",
    "sg:classifiers":[
        {
            "category":"Banks & Credit Unions",
            "subcategory":"Investment Brokerage",
            "type":"Services"
        }
    ],
    "sg:phone":"+1 860 443 0803",
    "sg:postcode":"06385",
    "sg:province":"CT",
    "sg:tags":[
        "security"
    ],
    "wof:name":"Edward Jones 19382",
    "wof:placetype":"venue"
},
  "geometry": {"coordinates":[-72.156255,41.351358],"type":"Point"}
}