{
  "type": "Feature",
  "properties": {
    "addr:full":"15 Pomeroy Ave Wallingford CT 06492",
    "addr:housenumber":"15",
    "addr:postcode":"06492",
    "addr:street":"Pomeroy Ave",
    "iso:country":"US",
    "sg:address":"15 Pomeroy Ave",
    "sg:city":"Wallingford",
    "sg:classifiers":[
        {
            "category":"Building & Trades",
            "subcategory":"Construction",
            "type":"Services"
        }
    ],
    "sg:phone":"+1 203 269 3559",
    "sg:postcode":"06492",
    "sg:province":"CT",
    "sg:tags":[
        "roofing",
        "contractor"
    ],
    "wof:name":"Empire Construction",
    "wof:placetype":"venue"
},
  "geometry": {"coordinates":[-72.813197,41.450566],"type":"Point"}
}