{
  "type": "Feature",
  "properties": {
    "iso:country":"US",
    "sg:address":"562 Lakewood Rd",
    "sg:city":"Waterbury",
    "sg:classifiers":[
        {
            "category":"Sports & Exercise",
            "subcategory":"Gym",
            "type":"Entertainment"
        }
    ],
    "sg:phone":"+1 203 591 9293",
    "sg:postcode":"06704",
    "sg:province":"CT",
    "sg:tags":[
        "spa",
        "health"
    ],
    "wof:name":"7 Star Spa",
    "wof:placetype":"venue"
},
  "geometry": {"coordinates":[-73.01247100000001,41.575032],"type":"Point"}
}