{
  "type": "Feature",
  "properties": {
    "addr:full":"120 Clapboard Ridge Rd Danbury CT 06811",
    "addr:housenumber":"120",
    "addr:postcode":"06811",
    "addr:street":"Clapboard Ridge Rd",
    "iso:country":"US",
    "sg:address":"120 Clapboard Ridge Rd",
    "sg:city":"Danbury",
    "sg:classifiers":[
        {
            "category":"Restaurant",
            "type":"Food & Drink"
        }
    ],
    "sg:phone":"+1 203 790 9477",
    "sg:postcode":"06811",
    "sg:province":"CT",
    "sg:tags":[
        "delicatessen"
    ],
    "wof:name":"Uncle Zippy's Deli",
    "wof:placetype":"venue"
},
  "geometry": {"coordinates":[-73.497585,41.436526],"type":"Point"}
}