{
  "type": "Feature",
  "properties": {
    "addr:full":"66 4th St Stamford CT 06905",
    "addr:housenumber":"66",
    "addr:postcode":"06905",
    "addr:street":"4Th St",
    "iso:country":"US",
    "sg:address":"66 4th St",
    "sg:city":"Stamford",
    "sg:classifiers":[
        {
            "category":"Real Estate",
            "subcategory":"Architect",
            "type":"Services"
        }
    ],
    "sg:phone":"+1 203 359 4441",
    "sg:postcode":"06905",
    "sg:province":"CT",
    "wof:name":"Aivalis & Assoc Architects",
    "wof:placetype":"venue"
},
  "geometry": {"coordinates":[-73.54286,41.065423],"type":"Point"}
}