{
  "type": "Feature",
  "properties": {
    "iso:country":"US",
    "sg:address":"36 Maybury Cir",
    "sg:city":"Waterbury",
    "sg:classifiers":[
        {
            "category":"Real Estate",
            "subcategory":"Real Estate Agent",
            "type":"Services"
        }
    ],
    "sg:phone":"+1 203 754 7683",
    "sg:postcode":"06705",
    "sg:province":"CT",
    "wof:name":"Southern Development Mgt Co",
    "wof:placetype":"venue"
},
  "geometry": {"coordinates":[-73.008004,41.547002],"type":"Point"}
}