{
  "type": "Feature",
  "properties": {
    "iso:country":"US",
    "sg:address":"5 Suncrest Ln",
    "sg:city":"Farmington",
    "sg:classifiers":[
        {
            "category":"Professional",
            "subcategory":"Engineering",
            "type":"Services"
        }
    ],
    "sg:phone":"+1   ",
    "sg:postcode":"06032",
    "sg:province":"CT",
    "sg:tags":[
        "industrial",
        "engineer"
    ],
    "wof:name":"Delaney J B & Assoc",
    "wof:placetype":"venue"
},
  "geometry": {"coordinates":[-72.838409,41.706367],"type":"Point"}
}