{
  "type": "Feature",
  "properties": {
    "addr:full":"179 Buckingham Ave Milford CT 06460",
    "addr:housenumber":"179",
    "addr:postcode":"06460",
    "addr:street":"Buckingham Ave",
    "iso:country":"US",
    "sg:address":"179 Buckingham Ave",
    "sg:city":"Milford",
    "sg:classifiers":[
        {
            "category":"Wholesale",
            "subcategory":"Auto Parts",
            "type":"Manufacturing & Wholesale Goods"
        }
    ],
    "sg:phone":"+1 203 876 7572",
    "sg:postcode":"06460",
    "sg:province":"CT",
    "sg:tags":[
        "automobile",
        "rebuilt"
    ],
    "wof:name":"SVE Performance",
    "wof:placetype":"venue"
},
  "geometry": {"coordinates":[-73.04687800000001,41.223717],"type":"Point"}
}