{
  "type": "Feature",
  "properties": {
    "addr:full":"65 Weston St Hartford CT 06120",
    "addr:housenumber":"65",
    "addr:postcode":"06120",
    "addr:street":"Weston St",
    "iso:country":"US",
    "sg:address":"65 Weston St",
    "sg:city":"Hartford",
    "sg:classifiers":[
        {
            "category":"Retail",
            "subcategory":"Auto Repair",
            "type":"Services"
        }
    ],
    "sg:phone":"+1   ",
    "sg:postcode":"06120",
    "sg:province":"CT",
    "sg:tags":[
        "automotive"
    ],
    "wof:name":"Midas Muffler",
    "wof:placetype":"venue"
},
  "geometry": {"coordinates":[-72.664045,41.785918],"type":"Point"}
}