{
  "type": "Feature",
  "properties": {
    "addr:full":"2194 Main St Hartford CT 06120",
    "addr:housenumber":"2194",
    "addr:postcode":"06120",
    "addr:street":"Main St",
    "iso:country":"US",
    "sg:address":"2194 Main St",
    "sg:city":"Hartford",
    "sg:classifiers":[
        {
            "category":"Organizations",
            "subcategory":"Religious Organization",
            "type":"Services"
        }
    ],
    "sg:phone":"+1   ",
    "sg:postcode":"06120",
    "sg:province":"CT",
    "wof:name":"Ebenezer Temple Uhca",
    "wof:placetype":"venue"
},
  "geometry": {"coordinates":[-72.674654,41.784855],"type":"Point"}
}