{
  "type": "Feature",
  "properties": {
    "addr:full":"603 Newfield Ave Stamford CT 06905",
    "addr:housenumber":"603",
    "addr:postcode":"06905",
    "addr:street":"Newfield Ave",
    "iso:country":"US",
    "sg:address":"603 Newfield Ave",
    "sg:city":"Stamford",
    "sg:classifiers":[
        {
            "category":"Personal",
            "subcategory":"Beauty Salon",
            "type":"Services"
        }
    ],
    "sg:phone":"+1   ",
    "sg:postcode":"06905",
    "sg:province":"CT",
    "sg:tags":[
        "shop"
    ],
    "wof:name":"Image Salonspa",
    "wof:placetype":"venue"
},
  "geometry": {"coordinates":[-73.533911,41.07919],"type":"Point"}
}