{
  "type": "Feature",
  "properties": {
    "iso:country":"US",
    "sg:address":"32 Lafayette Pl",
    "sg:city":"Greenwich",
    "sg:classifiers":[
        {
            "category":"Real Estate",
            "subcategory":"Real Estate Operator",
            "type":"Services"
        }
    ],
    "sg:phone":"+1 203 625 0303",
    "sg:postcode":"06830",
    "sg:province":"CT",
    "sg:tags":[
        "development",
        "industrial",
        "commercial",
        "developer"
    ],
    "wof:name":"Pdl Investment Co",
    "wof:placetype":"venue"
},
  "geometry": {"coordinates":[-73.62793000000001,41.032471],"type":"Point"}
}