{
  "type": "Feature",
  "properties": {
    "iso:country":"US",
    "sg:address":"29 Battye Rd",
    "sg:city":"West Willington",
    "sg:classifiers":[
        {
            "category":"Organizations",
            "subcategory":"Non-profit Organization",
            "type":"Services"
        }
    ],
    "sg:phone":"+1   ",
    "sg:postcode":"06279",
    "sg:province":"CT",
    "sg:tags":[
        "social"
    ],
    "wof:name":"Connecticut Christmas Tre",
    "wof:placetype":"venue"
},
  "geometry": {"coordinates":[-72.30214700000001,41.84754],"type":"Point"}
}