{
  "type": "Feature",
  "properties": {
    "addr:full":"56 Hidden Brook Dr Stamford CT 06907",
    "addr:housenumber":"56",
    "addr:postcode":"06907",
    "addr:street":"Hidden Brook Dr",
    "iso:country":"US",
    "sg:address":"56 Hidden Brook Dr",
    "sg:city":"Stamford",
    "sg:classifiers":[
        {
            "category":"Professional",
            "type":"Services"
        }
    ],
    "sg:phone":"+1 203 322 6231",
    "sg:postcode":"06907",
    "sg:province":"CT",
    "wof:name":"Slfed",
    "wof:placetype":"venue"
},
  "geometry": {"coordinates":[-73.514055,41.103912],"type":"Point"}
}