{
  "type": "Feature",
  "properties": {
    "addr:full":"2162 Silas Deane Hwy Rocky Hill CT 06067",
    "addr:postcode":"2162;06067",
    "addr:street":"Silas Deane Hwy Rocky Hill Ct",
    "iso:country":"US",
    "sg:address":"2162 Silas Deane Hwy",
    "sg:city":"Rocky Hill",
    "sg:classifiers":[
        {
            "category":"Insurance",
            "subcategory":"Insurance Agent",
            "type":"Services"
        }
    ],
    "sg:phone":"+1 860 563 7283",
    "sg:postcode":"06067",
    "sg:province":"CT",
    "wof:name":"State Frm Agt Frnco Cnfaglione",
    "wof:placetype":"venue"
},
  "geometry": {"coordinates":[-72.641989,41.668835],"type":"Point"}
}