{
  "type": "Feature",
  "properties": {
    "iso:country":"US",
    "sg:address":"107 Wells Road",
    "sg:city":"Monroe",
    "sg:classifiers":[
        {
            "category":"Professional",
            "subcategory":"Computer Services",
            "type":"Services"
        }
    ],
    "sg:phone":"+1 203 788 1118",
    "sg:postcode":"06468",
    "sg:province":"CT",
    "sg:website":"http://www.fanboom.com",
    "wof:name":"FanBoom",
    "wof:placetype":"venue"
},
  "geometry": {"coordinates":[-73.235513,41.339845],"type":"Point"}
}