{
  "type": "Feature",
  "properties": {
    "addr:full":"60 Main St Westport CT 06880",
    "addr:housenumber":"60",
    "addr:postcode":"06880",
    "addr:street":"Main St",
    "iso:country":"US",
    "sg:address":"60 Main St",
    "sg:city":"Westport",
    "sg:classifiers":[
        {
            "category":"Professional",
            "type":"Services"
        }
    ],
    "sg:phone":"+1 203 222 1750",
    "sg:postcode":"06880",
    "sg:province":"CT",
    "sg:tags":[
        "establishment"
    ],
    "wof:name":"Braverman & Assoc",
    "wof:placetype":"venue"
},
  "geometry": {"coordinates":[-73.361627,41.14242],"type":"Point"}
}