{
  "type": "Feature",
  "properties": {
    "iso:country":"US",
    "sg:address":"159 Middlefield Rd",
    "sg:city":"Durham",
    "sg:classifiers":[
        {
            "category":"Farming",
            "subcategory":"Farm",
            "type":"Manufacturing & Wholesale Goods"
        }
    ],
    "sg:phone":"+1 860 349 1515",
    "sg:postcode":"06422",
    "sg:province":"CT",
    "sg:tags":[
        "crop",
        "general"
    ],
    "wof:name":"Gastler Farm",
    "wof:placetype":"venue"
},
  "geometry": {"coordinates":[-72.69032199999999,41.4898],"type":"Point"}
}