{
  "type": "Feature",
  "properties": {
    "addr:full":"220 Norwich-New London Tpke Uncasville CT 06382",
    "addr:housenumber":"220",
    "addr:postcode":"06382",
    "addr:street":"Norwich-New;Tpke Uncasville Ct",
    "iso:country":"US",
    "sg:address":"220 Norwich-New London Tpke",
    "sg:city":"Uncasville",
    "sg:classifiers":[
        {
            "category":"Insurance",
            "subcategory":"Insurance Agent",
            "type":"Services"
        }
    ],
    "sg:phone":"+1 860 367 0898",
    "sg:postcode":"06382",
    "sg:province":"CT",
    "wof:name":"MetLife",
    "wof:placetype":"venue"
},
  "geometry": {"coordinates":[-72.10986800000001,41.435503],"type":"Point"}
}