{
  "type": "Feature",
  "properties": {
    "addr:full":"1625 Main St Stratford CT 06615",
    "addr:housenumber":"1625",
    "addr:postcode":"06615",
    "addr:street":"Main St",
    "iso:country":"US",
    "sg:address":"1625 Main St",
    "sg:city":"Stratford",
    "sg:classifiers":[
        {
            "category":"Food & Beverages",
            "subcategory":"Specialty",
            "type":"Retail Goods"
        }
    ],
    "sg:phone":"+1 203 377 5551",
    "sg:postcode":"06615",
    "sg:province":"CT",
    "sg:tags":[
        "health",
        "diet"
    ],
    "wof:name":"Supplements Unlimited",
    "wof:placetype":"venue"
},
  "geometry": {"coordinates":[-73.130427,41.183314],"type":"Point"}
}