{
  "type": "Feature",
  "properties": {
    "addr:full":"173 Edgemoor Rd Bridgeport CT 06606",
    "addr:housenumber":"173",
    "addr:postcode":"06606",
    "addr:street":"Edgemoor Rd",
    "iso:country":"US",
    "sg:address":"173 Edgemoor Rd",
    "sg:city":"Bridgeport",
    "sg:classifiers":[
        {
            "category":"Professional",
            "subcategory":"Business Services",
            "type":"Services"
        }
    ],
    "sg:phone":"+1   ",
    "sg:postcode":"06606",
    "sg:province":"CT",
    "wof:name":"Web Stone By Design LLC",
    "wof:placetype":"venue"
},
  "geometry": {"coordinates":[-73.222318,41.217092],"type":"Point"}
}