{
  "type": "Feature",
  "properties": {
    "addr:full":"8 Country Squire Ln Sandy Hook CT 06482",
    "addr:housenumber":"8",
    "addr:postcode":"06482",
    "addr:street":"Country Squire Ln;Hook Ct",
    "iso:country":"US",
    "sg:address":"8 Country Squire Ln",
    "sg:city":"Sandy Hook",
    "sg:classifiers":[
        {
            "category":"Food & Beverages",
            "subcategory":"Groceries & Convenience Stores",
            "type":"Retail Goods"
        }
    ],
    "sg:phone":"+1 203 270 0647",
    "sg:postcode":"06482",
    "sg:province":"CT",
    "wof:name":"Big Y",
    "wof:placetype":"venue"
},
  "geometry": {"coordinates":[-73.20464200000001,41.379348],"type":"Point"}
}