{
  "type": "Feature",
  "properties": {
    "iso:country":"US",
    "sg:address":"518 Norwich Rd",
    "sg:city":"Plainfield",
    "sg:classifiers":[
        {
            "category":"Food & Beverages",
            "subcategory":"Groceries & Convenience Stores",
            "type":"Retail Goods"
        }
    ],
    "sg:phone":"+1 860 564 9403",
    "sg:postcode":"06374",
    "sg:province":"CT",
    "wof:name":"Plainfield Food Mart",
    "wof:placetype":"venue"
},
  "geometry": {"coordinates":[-71.914385,41.685202],"type":"Point"}
}