{
  "type": "Feature",
  "properties": {
    "addr:full":"14 Wilton Rd Rye Brook CT 10573",
    "addr:housenumber":"14",
    "addr:postcode":"10573",
    "addr:street":"Wilton Rd;Brook Ct",
    "iso:country":"US",
    "sg:address":"14 Wilton Rd",
    "sg:city":"Rye Brook",
    "sg:classifiers":[
        {
            "category":"Building & Trades",
            "subcategory":"Construction",
            "type":"Services"
        }
    ],
    "sg:phone":"+1 914 939 7116",
    "sg:postcode":"10573",
    "sg:province":"CT",
    "sg:tags":[
        "general",
        "contractor"
    ],
    "wof:name":"Paniccia Construction",
    "wof:placetype":"venue"
},
  "geometry": {"coordinates":[-73.68691099999999,41.012448],"type":"Point"}
}