{
  "type": "Feature",
  "properties": {
    "addr:full":"19 Central Row Hartford CT 06103",
    "addr:housenumber":"19",
    "addr:postcode":"06103",
    "addr:street":"Central Row",
    "iso:country":"US",
    "sg:address":"19 Central Row",
    "sg:city":"Hartford",
    "sg:classifiers":[
        {
            "category":"Bakery",
            "type":"Food & Drink"
        },
        {
            "category":"Coffee & Tea",
            "type":"Food & Drink"
        },
        {
            "category":"Bagels",
            "type":"Food & Drink"
        },
        {
            "category":"Donuts",
            "type":"Food & Drink"
        }
    ],
    "sg:menulink":"http://www.allmenus.com/ct/hartford/129887-dunkin-donuts/menu/",
    "sg:phone":"+1 860 524 9532",
    "sg:postcode":"06103",
    "sg:province":"CT",
    "sg:tags":[
        "american",
        "diner",
        "pastry"
    ],
    "wof:name":"Dunkin' Donuts",
    "wof:placetype":"venue"
},
  "geometry": {"coordinates":[-72.672217,41.765541],"type":"Point"}
}