{
  "type": "Feature",
  "properties": {
    "addr:full":"99 Limestone Rd Ridgefield CT 06877",
    "addr:housenumber":"99",
    "addr:postcode":"06877",
    "addr:street":"Limestone Rd",
    "iso:country":"US",
    "sg:address":"99 Limestone Rd",
    "sg:city":"Ridgefield",
    "sg:classifiers":[
        {
            "category":"Professional",
            "type":"Services"
        }
    ],
    "sg:phone":"+1 203 438 3405",
    "sg:postcode":"06877",
    "sg:province":"CT",
    "sg:tags":[
        "establishment"
    ],
    "wof:name":"NCS Corp",
    "wof:placetype":"venue"
},
  "geometry": {"coordinates":[-73.488293,41.314116],"type":"Point"}
}