{
  "type": "Feature",
  "properties": {
    "iso:country":"US",
    "sg:address":"55 Farmington Ave",
    "sg:city":"Hartford",
    "sg:classifiers":[
        {
            "category":"Professional",
            "subcategory":"Computer Services",
            "type":"Services"
        }
    ],
    "sg:phone":"+1   ",
    "sg:postcode":"06105",
    "sg:province":"CT",
    "sg:tags":[
        "related"
    ],
    "wof:name":"Hartford Technology Svcs Co",
    "wof:placetype":"venue"
},
  "geometry": {"coordinates":[-72.686398,41.768033],"type":"Point"}
}