{
  "type": "Feature",
  "properties": {
    "iso:country":"US",
    "sg:address":"126 Hanover St",
    "sg:city":"Meriden",
    "sg:classifiers":[
        {
            "category":"Restaurant",
            "type":"Food & Drink"
        }
    ],
    "sg:phone":"+1 203 235 1248",
    "sg:postcode":"06451",
    "sg:province":"CT",
    "wof:name":"Il Forno",
    "wof:placetype":"venue"
},
  "geometry": {"coordinates":[-72.807007,41.536115],"type":"Point"}
}