{
  "type": "Feature",
  "properties": {
    "addr:full":"2 E Putnam Ave Greenwich CT 06830",
    "addr:housenumber":"2",
    "addr:postcode":"06830",
    "addr:street":"E Putnam Ave",
    "iso:country":"US",
    "sg:address":"2 E Putnam Ave",
    "sg:city":"Greenwich",
    "sg:classifiers":[
        {
            "category":"Wholesale",
            "subcategory":"Office Equipment",
            "type":"Manufacturing & Wholesale Goods"
        }
    ],
    "sg:phone":"+1 203 324 7676",
    "sg:postcode":"06830",
    "sg:province":"CT",
    "wof:name":"Executive Business Machines",
    "wof:placetype":"venue"
},
  "geometry": {"coordinates":[-73.62568899999999,41.032191],"type":"Point"}
}