{
  "type": "Feature",
  "properties": {
    "addr:full":"457 Hemlock Point Dr Coventry CT 06238",
    "addr:housenumber":"457",
    "addr:postcode":"06238",
    "addr:street":"Hemlock Point Dr",
    "iso:country":"US",
    "sg:address":"457 Hemlock Point Dr",
    "sg:city":"Coventry",
    "sg:classifiers":[
        {
            "category":"Health Services",
            "subcategory":"Medical Lab",
            "type":"Services"
        }
    ],
    "sg:phone":"+1   ",
    "sg:postcode":"06238",
    "sg:province":"CT",
    "sg:tags":[
        "laboratory",
        "dental"
    ],
    "wof:name":"State of Art Lab LLC",
    "wof:placetype":"venue"
},
  "geometry": {"coordinates":[-72.323376,41.77663],"type":"Point"}
}