{
  "type": "Feature",
  "properties": {
    "iso:country":"US",
    "sg:address":"1 Big Shop Ln",
    "sg:city":"Ridgefield",
    "sg:classifiers":[
        {
            "category":"Shopping",
            "subcategory":"Gifts & Souvenirs",
            "type":"Retail Goods"
        }
    ],
    "sg:phone":"+1 203 431 4759",
    "sg:postcode":"06877",
    "sg:province":"CT",
    "sg:tags":[
        "shop"
    ],
    "wof:name":"Valery's",
    "wof:placetype":"venue"
},
  "geometry": {"coordinates":[-73.497159,41.282634],"type":"Point"}
}