{
  "type": "Feature",
  "properties": {
    "iso:country":"US",
    "sg:address":"1365 State St",
    "sg:city":"New Haven",
    "sg:classifiers":[
        {
            "category":"Building & Trades",
            "subcategory":"Plumbing",
            "type":"Services"
        }
    ],
    "sg:phone":"+1 203 787 4747",
    "sg:postcode":"06511",
    "sg:province":"CT",
    "sg:tags":[
        "contractor"
    ],
    "wof:name":"B & B Plumbing Heating LLC",
    "wof:placetype":"venue"
},
  "geometry": {"coordinates":[-72.897367,41.320738],"type":"Point"}
}