{
  "type": "Feature",
  "properties": {
    "iso:country":"US",
    "sg:address":"716 Pudding Hill Rd",
    "sg:city":"Hampton",
    "sg:classifiers":[
        {
            "category":"Building & Trades",
            "subcategory":"Equipment Rental",
            "type":"Services"
        }
    ],
    "sg:phone":"+1   ",
    "sg:postcode":"06247",
    "sg:province":"CT",
    "wof:name":"Shaboo Productions LLC",
    "wof:placetype":"venue"
},
  "geometry": {"coordinates":[-72.062918,41.752597],"type":"Point"}
}