{
  "type": "Feature",
  "properties": {
    "iso:country":"US",
    "sg:address":"211 Chestnut St",
    "sg:city":"Port Chester",
    "sg:classifiers":[
        {
            "category":"Building & Trades",
            "subcategory":"Construction",
            "type":"Services"
        }
    ],
    "sg:phone":"+1 914 690 9595",
    "sg:postcode":"10573",
    "sg:province":"CT",
    "sg:tags":[
        "handyman"
    ],
    "wof:name":"Helping Hand Handyman",
    "wof:placetype":"venue"
},
  "geometry": {"coordinates":[-73.664503,41.008361],"type":"Point"}
}