{
  "type": "Feature",
  "properties": {
    "iso:country":"US",
    "sg:address":"26 Beech St",
    "sg:city":"Greenwich",
    "sg:classifiers":[
        {
            "category":"Building & Trades",
            "subcategory":"Plumbing",
            "type":"Services"
        }
    ],
    "sg:phone":"+1 203 531 0515",
    "sg:postcode":"06830",
    "sg:province":"CT",
    "sg:tags":[
        "plumbing",
        "contractor"
    ],
    "wof:name":"A Bella Plumbing & Heating",
    "wof:placetype":"venue"
},
  "geometry": {"coordinates":[-73.655218,41.003632],"type":"Point"}
}