{
  "type": "Feature",
  "properties": {
    "addr:full":"2 Harvest Rd Enfield CT 06082",
    "addr:housenumber":"2",
    "addr:postcode":"06082",
    "addr:street":"Harvest Rd",
    "iso:country":"US",
    "sg:address":"2 Harvest Rd",
    "sg:city":"Enfield",
    "sg:classifiers":[
        {
            "category":"Sports & Exercise",
            "subcategory":"Race Track",
            "type":"Entertainment"
        }
    ],
    "sg:phone":"+1   ",
    "sg:postcode":"06082",
    "sg:province":"CT",
    "sg:tags":[
        "auto",
        "racing"
    ],
    "wof:name":"Pro Race Inc",
    "wof:placetype":"venue"
},
  "geometry": {"coordinates":[-72.569996,42.00165],"type":"Point"}
}