{
  "type": "Feature",
  "properties": {
    "iso:country":"US",
    "sg:address":"35 Donna Ln",
    "sg:city":"West Haven",
    "sg:classifiers":[
        {
            "category":"Building & Trades",
            "subcategory":"Construction",
            "type":"Services"
        }
    ],
    "sg:phone":"+1 203 937 6998",
    "sg:postcode":"06516",
    "sg:province":"CT",
    "sg:tags":[
        "downspouts",
        "gutter"
    ],
    "wof:name":"Bill's Gutter Cleaning & Home",
    "wof:placetype":"venue"
},
  "geometry": {"coordinates":[-72.98038200000001,41.257831],"type":"Point"}
}