{
  "type": "Feature",
  "properties": {
    "iso:country":"US",
    "sg:address":"810 Silver Ln",
    "sg:city":"East Hartford",
    "sg:classifiers":[
        {
            "category":"Professional",
            "subcategory":"Business Services",
            "type":"Services"
        }
    ],
    "sg:phone":"+1   ",
    "sg:postcode":"06118",
    "sg:province":"CT",
    "wof:name":"Rose City Auction",
    "wof:placetype":"venue"
},
  "geometry": {"coordinates":[-72.605332,41.765073],"type":"Point"}
}