{
  "type": "Feature",
  "properties": {
    "iso:country":"US",
    "sg:address":"7 Coalpit Hill Rd",
    "sg:city":"Danbury",
    "sg:classifiers":[
        {
            "category":"Government",
            "subcategory":"Fire Station",
            "type":"Public Place"
        }
    ],
    "sg:phone":"+1 203 748 7544",
    "sg:postcode":"06810",
    "sg:province":"CT",
    "sg:tags":[
        "department"
    ],
    "wof:name":"Wooster Hose Co",
    "wof:placetype":"venue"
},
  "geometry": {"coordinates":[-73.439695,41.387163],"type":"Point"}
}