{
  "type": "Feature",
  "properties": {
    "iso:country":"US",
    "sg:address":"155 Umpawaug Rd",
    "sg:city":"Redding",
    "sg:classifiers":[
        {
            "category":"Manufacturing",
            "subcategory":"Tools & Machinery",
            "type":"Manufacturing & Wholesale Goods"
        }
    ],
    "sg:phone":"+1 203 938 2488",
    "sg:postcode":"06896",
    "sg:province":"CT",
    "sg:tags":[
        "motion",
        "picture",
        "film"
    ],
    "wof:name":"Out of Woods Productions",
    "wof:placetype":"venue"
},
  "geometry": {"coordinates":[-73.420158,41.29792],"type":"Point"}
}