{
  "type": "Feature",
  "properties": {
    "addr:full":"3241 Main St Stratford CT 06614",
    "addr:housenumber":"3241",
    "addr:postcode":"06614",
    "addr:street":"Main St",
    "iso:country":"US",
    "sg:address":"3241 Main St",
    "sg:city":"Stratford",
    "sg:classifiers":[
        {
            "category":"Professional",
            "subcategory":"Management & Consulting",
            "type":"Services"
        }
    ],
    "sg:phone":"+1 203 378 1152",
    "sg:postcode":"06614",
    "sg:province":"CT",
    "sg:tags":[
        "counselor",
        "public",
        "relations"
    ],
    "sg:website":"www.jppr.com",
    "wof:name":"Jacobs & Prosek",
    "wof:placetype":"venue"
},
  "geometry": {"coordinates":[-73.131888,41.204712],"type":"Point"}
}