{
  "type": "Feature",
  "properties": {
    "addr:full":"190 Century Dr Bristol CT 06010",
    "addr:housenumber":"190",
    "addr:postcode":"06010",
    "addr:street":"Century Dr Bristol Ct",
    "iso:country":"US",
    "sg:address":"190 Century Dr",
    "sg:city":"Bristol",
    "sg:classifiers":[
        {
            "category":"Education",
            "subcategory":"Vocational School",
            "type":"Public Place"
        }
    ],
    "sg:phone":"+1   ",
    "sg:postcode":"06010",
    "sg:province":"CT",
    "sg:tags":[
        "training",
        "facility"
    ],
    "wof:name":"Startech Environmental Corp",
    "wof:placetype":"venue"
},
  "geometry": {"coordinates":[-72.91744799999999,41.653471],"type":"Point"}
}