{
  "type": "Feature",
  "properties": {
    "addr:full":"232 S Main St Colchester CT 06415",
    "addr:housenumber":"232",
    "addr:postcode":"06415",
    "addr:street":"S Main St",
    "iso:country":"US",
    "sg:address":"232 S Main St",
    "sg:city":"Colchester",
    "sg:classifiers":[
        {
            "category":"Real Estate",
            "subcategory":"Real Estate Agent",
            "type":"Services"
        }
    ],
    "sg:phone":"+1 860 537 9559",
    "sg:postcode":"06415",
    "sg:province":"CT",
    "wof:name":"Re/Max",
    "wof:placetype":"venue"
},
  "geometry": {"coordinates":[-72.329905,41.569783],"type":"Point"}
}