{
  "type": "Feature",
  "properties": {
    "addr:full":"53 Summit Ave East Lyme CT 06333",
    "addr:housenumber":"53",
    "addr:postcode":"06333",
    "addr:street":"Summit Ave",
    "iso:country":"US",
    "sg:address":"53 Summit Ave",
    "sg:city":"East Lyme",
    "sg:classifiers":[
        {
            "category":"Education",
            "subcategory":"Special Training",
            "type":"Public Place"
        }
    ],
    "sg:phone":"+1   ",
    "sg:postcode":"06333",
    "sg:province":"CT",
    "wof:name":"Yoga and Meditation Dna",
    "wof:placetype":"venue"
},
  "geometry": {"coordinates":[-72.19458400000001,41.369899],"type":"Point"}
}