{
  "type": "Feature",
  "properties": {
    "addr:full":"653 Bethmour Rd Bethany CT 06524",
    "addr:housenumber":"653",
    "addr:postcode":"06524",
    "addr:street":"Bethmour Rd Bethany Ct",
    "iso:country":"US",
    "sg:address":"653 Bethmour Rd",
    "sg:city":"Bethany",
    "sg:classifiers":[
        {
            "category":"Building & Trades",
            "subcategory":"Construction",
            "type":"Services"
        }
    ],
    "sg:phone":"+1 203 393 0169",
    "sg:postcode":"06524",
    "sg:province":"CT",
    "sg:tags":[
        "bathroom",
        "remodeling"
    ],
    "wof:name":"Mignone Tile & Bathroom Rnvtns",
    "wof:placetype":"venue"
},
  "geometry": {"coordinates":[-73.00920600000001,41.417359],"type":"Point"}
}