{
  "type": "Feature",
  "properties": {
    "addr:full":"345 Fan Hill Rd Monroe CT 06468",
    "addr:housenumber":"345",
    "addr:postcode":"06468",
    "addr:street":"Fan Hill Rd",
    "iso:country":"US",
    "sg:address":"345 Fan Hill Rd",
    "sg:city":"Monroe",
    "sg:classifiers":[
        {
            "category":"Social Services",
            "subcategory":"Child Care",
            "type":"Services"
        }
    ],
    "sg:phone":"+1   ",
    "sg:postcode":"06468",
    "sg:province":"CT",
    "sg:tags":[
        "day"
    ],
    "wof:name":"Kindertime Day Care",
    "wof:placetype":"venue"
},
  "geometry": {"coordinates":[-73.227203,41.344413],"type":"Point"}
}