{
  "type": "Feature",
  "properties": {
    "addr:full":"826 E Center St Wallingford CT 06492",
    "addr:housenumber":"826",
    "addr:postcode":"06492",
    "addr:street":"E Center St",
    "iso:country":"US",
    "sg:address":"826 E Center St",
    "sg:city":"Wallingford",
    "sg:classifiers":[
        {
            "category":"Health Services",
            "subcategory":"Doctor",
            "type":"Services"
        }
    ],
    "sg:phone":"+1   ",
    "sg:postcode":"06492",
    "sg:province":"CT",
    "wof:name":"Kenneth Roseman DMD",
    "wof:placetype":"venue"
},
  "geometry": {"coordinates":[-72.80063,41.447061],"type":"Point"}
}