{
  "type": "Feature",
  "properties": {
    "addr:full":"16 Vassar Ave Stamford CT 06902",
    "addr:housenumber":"16",
    "addr:postcode":"06902",
    "addr:street":"Vassar Ave",
    "iso:country":"US",
    "sg:address":"16 Vassar Ave",
    "sg:city":"Stamford",
    "sg:classifiers":[
        {
            "category":"Building & Trades",
            "subcategory":"Landscaping Services",
            "type":"Services"
        }
    ],
    "sg:phone":"+1 203 978 1481",
    "sg:postcode":"06902",
    "sg:province":"CT",
    "wof:name":"A Fiore Inc",
    "wof:placetype":"venue"
},
  "geometry": {"coordinates":[-73.552571,41.04239],"type":"Point"}
}