{
  "type": "Feature",
  "properties": {
    "addr:full":"475 Washington Ave North Haven CT 06473",
    "addr:housenumber":"475",
    "addr:postcode":"06473",
    "addr:street":"Washington Ave;Haven",
    "iso:country":"US",
    "sg:address":"475 Washington Ave",
    "sg:city":"North Haven",
    "sg:classifiers":[
        {
            "category":"Wholesale",
            "subcategory":"Auto Parts",
            "type":"Manufacturing & Wholesale Goods"
        }
    ],
    "sg:phone":"+1 203 234 7112",
    "sg:postcode":"06473",
    "sg:province":"CT",
    "sg:tags":[
        "automobile",
        "supply"
    ],
    "wof:name":"Brinson Co",
    "wof:placetype":"venue"
},
  "geometry": {"coordinates":[-72.84161899999999,41.412895],"type":"Point"}
}