{
  "type": "Feature",
  "properties": {
    "addr:full":"6 Sagamore Dr Simsbury CT 06070",
    "addr:housenumber":"6",
    "addr:postcode":"06070",
    "addr:street":"Sagamore Dr",
    "iso:country":"US",
    "sg:address":"6 Sagamore Dr",
    "sg:city":"Simsbury",
    "sg:classifiers":[
        {
            "category":"Professional",
            "subcategory":"Lawyer & Legal Services",
            "type":"Services"
        }
    ],
    "sg:phone":"+1 860 264 1626",
    "sg:postcode":"06070",
    "sg:province":"CT",
    "sg:tags":[
        "attorney",
        "practice",
        "plan"
    ],
    "wof:name":"The Oliver Law Firm",
    "wof:placetype":"venue"
},
  "geometry": {"coordinates":[-72.83620500000001,41.905527],"type":"Point"}
}