{
  "type": "Feature",
  "properties": {
    "addr:full":"53 Indian Ln Durham CT 06422",
    "addr:housenumber":"53",
    "addr:postcode":"06422",
    "addr:street":"Indian Ln",
    "iso:country":"US",
    "sg:address":"53 Indian Ln",
    "sg:city":"Durham",
    "sg:classifiers":[
        {
            "category":"Building & Trades",
            "subcategory":"Landscaping Services",
            "type":"Services"
        }
    ],
    "sg:phone":"+1 860 349 4401",
    "sg:postcode":"06422",
    "sg:province":"CT",
    "wof:name":"Final Phase Ldscp & Maint LLC",
    "wof:placetype":"venue"
},
  "geometry": {"coordinates":[-72.698756,41.454228],"type":"Point"}
}