{
  "type": "Feature",
  "properties": {
    "iso:country":"US",
    "sg:address":"1127 High Ridge Rd",
    "sg:city":"Stamford",
    "sg:classifiers":[
        {
            "category":"Organizations",
            "subcategory":"Membership Organization",
            "type":"Services"
        }
    ],
    "sg:phone":"+1 203 413 9608",
    "sg:postcode":"06905",
    "sg:province":"CT",
    "sg:tags":[
        "meditation",
        "instruction"
    ],
    "wof:name":"Sit In Freedom",
    "wof:placetype":"venue"
},
  "geometry": {"coordinates":[-73.54696300000001,41.109873],"type":"Point"}
}