{
  "type": "Feature",
  "properties": {
    "iso:country":"US",
    "sg:address":"160 Washington St",
    "sg:city":"Middletown",
    "sg:classifiers":[
        {
            "category":"Real Estate",
            "subcategory":"Real Estate Agent",
            "type":"Services"
        }
    ],
    "sg:phone":"+1 860 344 1000",
    "sg:postcode":"06457",
    "sg:province":"CT",
    "wof:name":"Beazley Co Realtors",
    "wof:placetype":"venue"
},
  "geometry": {"coordinates":[-72.654325,41.561174],"type":"Point"}
}