{
  "type": "Feature",
  "properties": {
    "addr:full":"182 Hanover Rd Newtown CT 06470",
    "addr:housenumber":"182",
    "addr:postcode":"06470",
    "addr:street":"Hanover Rd",
    "iso:country":"US",
    "sg:address":"182 Hanover Rd",
    "sg:city":"Newtown",
    "sg:classifiers":[
        {
            "category":"Professional",
            "subcategory":"Computer Services",
            "type":"Services"
        }
    ],
    "sg:phone":"+1   ",
    "sg:postcode":"06470",
    "sg:province":"CT",
    "sg:tags":[
        "related"
    ],
    "wof:name":"Ctpc Comp Consulting",
    "wof:placetype":"venue"
},
  "geometry": {"coordinates":[-73.32783000000001,41.464452],"type":"Point"}
}