{
  "type": "Feature",
  "properties": {
    "addr:full":"179 Elm St Enfield CT 06082",
    "addr:housenumber":"179",
    "addr:postcode":"06082",
    "addr:street":"Elm St Enfield Ct",
    "iso:country":"US",
    "sg:address":"179 Elm St",
    "sg:city":"Enfield",
    "sg:classifiers":[
        {
            "category":"Building & Trades",
            "subcategory":"Plumbing",
            "type":"Services"
        }
    ],
    "sg:phone":"+1 860 745 7177",
    "sg:postcode":"06082",
    "sg:province":"CT",
    "sg:tags":[
        "contractor"
    ],
    "wof:name":"D & D Plumbing Services LLC",
    "wof:placetype":"venue"
},
  "geometry": {"coordinates":[-72.568326,42.000468],"type":"Point"}
}