{
  "type": "Feature",
  "properties": {
    "addr:full":"2836 E Main St Waterbury CT 06705",
    "addr:housenumber":"2836",
    "addr:postcode":"06705",
    "addr:street":"E Main St",
    "iso:country":"US",
    "sg:address":"2836 E Main St",
    "sg:city":"Waterbury",
    "sg:classifiers":[
        {
            "category":"Real Estate",
            "subcategory":"Real Estate Agent",
            "type":"Services"
        }
    ],
    "sg:phone":"+1 203 755 4841",
    "sg:postcode":"06705",
    "sg:province":"CT",
    "wof:name":"Ferraro & Ferraro Real Estate",
    "wof:placetype":"venue"
},
  "geometry": {"coordinates":[-72.99266,41.542546],"type":"Point"}
}