{
  "type": "Feature",
  "properties": {
    "addr:full":"735 Old Town Rd Bridgeport CT 06606",
    "addr:housenumber":"735",
    "addr:postcode":"06606",
    "addr:street":"Old Town Rd",
    "iso:country":"US",
    "sg:address":"735 Old Town Rd",
    "sg:city":"Bridgeport",
    "sg:classifiers":[
        {
            "category":"Organizations",
            "subcategory":"Professional Association",
            "type":"Services"
        }
    ],
    "sg:phone":"+1   ",
    "sg:postcode":"06606",
    "sg:province":"CT",
    "sg:tags":[
        "business"
    ],
    "wof:name":"Americn Legn Sylvan Crest 177",
    "wof:placetype":"venue"
},
  "geometry": {"coordinates":[-73.190516,41.223254],"type":"Point"}
}