{
  "type": "Feature",
  "properties": {
    "addr:full":"102 Liberty St Newington CT 06111",
    "addr:housenumber":"102",
    "addr:postcode":"06111",
    "addr:street":"Liberty St",
    "iso:country":"US",
    "sg:address":"102 Liberty St",
    "sg:city":"Newington",
    "sg:classifiers":[
        {
            "category":"Retail",
            "subcategory":"Repair Shop",
            "type":"Services"
        }
    ],
    "sg:phone":"+1   ",
    "sg:postcode":"06111",
    "sg:province":"CT",
    "sg:tags":[
        "institutional",
        "food",
        "commercial",
        "se",
        "for"
    ],
    "wof:name":"Commercial Appliance Repr Inc",
    "wof:placetype":"venue"
},
  "geometry": {"coordinates":[-72.748041,41.684306],"type":"Point"}
}