{
  "type": "Feature",
  "properties": {
    "addr:full":"883 Paddock Ave Meriden CT 06450",
    "addr:housenumber":"883",
    "addr:postcode":"06450",
    "addr:street":"Paddock Ave",
    "iso:country":"US",
    "sg:address":"883 Paddock Ave",
    "sg:city":"Meriden",
    "sg:classifiers":[
        {
            "category":"Health Services",
            "subcategory":"Doctor",
            "type":"Services"
        }
    ],
    "sg:phone":"+1   ",
    "sg:postcode":"06450",
    "sg:province":"CT",
    "sg:tags":[
        "medical"
    ],
    "wof:name":"Alejandro Rangel MD",
    "wof:placetype":"venue"
},
  "geometry": {"coordinates":[-72.776123,41.505805],"type":"Point"}
}