{
  "type": "Feature",
  "properties": {
    "iso:country":"US",
    "sg:address":"705 Boston Post Rd",
    "sg:city":"Guilford",
    "sg:classifiers":[
        {
            "category":"Shopping",
            "subcategory":"Stationery & Office Supplies",
            "type":"Retail Goods"
        },
        {
            "category":"Shopping",
            "subcategory":"Catalog Store",
            "type":"Retail Goods"
        }
    ],
    "sg:phone":"+1 203 453 4228",
    "sg:postcode":"06437",
    "sg:province":"CT",
    "sg:tags":[
        "mail",
        "educational",
        "material",
        "merchandise",
        "house"
    ],
    "wof:name":"Teachers Together",
    "wof:placetype":"venue"
},
  "geometry": {"coordinates":[-72.673067,41.288934],"type":"Point"}
}