{
  "type": "Feature",
  "properties": {
    "iso:country":"US",
    "sg:address":"54 Broadway",
    "sg:city":"New Haven",
    "sg:classifiers":[
        {
            "category":"Professional",
            "subcategory":"Lawyer & Legal Services",
            "type":"Services"
        }
    ],
    "sg:phone":"+1 203 497 8667",
    "sg:postcode":"06511",
    "sg:province":"CT",
    "sg:tags":[
        "attorney"
    ],
    "wof:name":"Carter Mario Injury Lawyers",
    "wof:placetype":"venue"
},
  "geometry": {"coordinates":[-72.932143,41.312414],"type":"Point"}
}