{
  "type": "Feature",
  "properties": {
    "addr:full":"30 Treeland Rd Shelton CT 06484",
    "addr:housenumber":"30",
    "addr:postcode":"06484",
    "addr:street":"Treeland Rd",
    "iso:country":"US",
    "sg:address":"30 Treeland Rd",
    "sg:city":"Shelton",
    "sg:classifiers":[
        {
            "category":"Health Services",
            "subcategory":"Clinic",
            "type":"Services"
        },
        {
            "category":"Professional",
            "subcategory":"Management & Consulting",
            "type":"Services"
        }
    ],
    "sg:phone":"+1 203 944 9556",
    "sg:postcode":"06484",
    "sg:province":"CT",
    "wof:name":"Korchek Technologies LLC",
    "wof:placetype":"venue"
},
  "geometry": {"coordinates":[-73.15212099999999,41.310628],"type":"Point"}
}