{
  "type": "Feature",
  "properties": {
    "addr:full":"107 New Haven Rd Seymour CT 06483",
    "addr:housenumber":"107",
    "addr:postcode":"06483",
    "addr:street":"New Haven Rd",
    "iso:country":"US",
    "sg:address":"107 New Haven Rd",
    "sg:city":"Seymour",
    "sg:classifiers":[
        {
            "category":"Wholesale",
            "subcategory":"Auto Parts",
            "type":"Manufacturing & Wholesale Goods"
        }
    ],
    "sg:phone":"+1 203 888 2527",
    "sg:postcode":"06483",
    "sg:province":"CT",
    "sg:tags":[
        "automobile",
        "rebuilt"
    ],
    "wof:name":"Seymour Auto Wrecking Inc",
    "wof:placetype":"venue"
},
  "geometry": {"coordinates":[-73.050607,41.398156],"type":"Point"}
}