{
  "type": "Feature",
  "properties": {
    "iso:country":"US",
    "sg:address":"1815 Tuttle Ave",
    "sg:city":"Cheshire",
    "sg:classifiers":[
        {
            "category":"Restaurant",
            "type":"Food & Drink"
        }
    ],
    "sg:phone":"+1 203 387 1760",
    "sg:postcode":"06410",
    "sg:province":"CT",
    "wof:name":"New Deal Steak Place",
    "wof:placetype":"venue"
},
  "geometry": {"coordinates":[-72.882756,41.452781],"type":"Point"}
}