{
  "type": "Feature",
  "properties": {
    "addr:full":"1 Middle Tpke W Manchester CT 06040",
    "addr:housenumber":"1",
    "addr:postcode":"06040",
    "addr:street":"Middle Tpke W Manchester Ct",
    "iso:country":"US",
    "sg:address":"1 Middle Tpke W",
    "sg:city":"Manchester",
    "sg:classifiers":[
        {
            "category":"Banks & Credit Unions",
            "subcategory":"Bank",
            "type":"Services"
        }
    ],
    "sg:phone":"+1 860 647 5599",
    "sg:postcode":"06040",
    "sg:province":"CT",
    "sg:tags":[
        "national",
        "commercial"
    ],
    "wof:name":"Fleet",
    "wof:placetype":"venue"
},
  "geometry": {"coordinates":[-72.52650800000001,41.782987],"type":"Point"}
}