{
  "type": "Feature",
  "properties": {
    "addr:full":"133 Goodhouse Rd Litchfield CT 06759",
    "addr:housenumber":"133",
    "addr:postcode":"06759",
    "addr:street":"Goodhouse Rd",
    "iso:country":"US",
    "sg:address":"133 Goodhouse Rd",
    "sg:city":"Litchfield",
    "sg:classifiers":[
        {
            "category":"Wholesale",
            "subcategory":"Non-durable Goods",
            "type":"Manufacturing & Wholesale Goods"
        }
    ],
    "sg:phone":"+1 860 567 2022",
    "sg:postcode":"06759",
    "sg:province":"CT",
    "wof:name":"J D Cahill Co",
    "wof:placetype":"venue"
},
  "geometry": {"coordinates":[-73.23867,41.765768],"type":"Point"}
}