{
  "type": "Feature",
  "properties": {
    "iso:country":"US",
    "sg:address":"133 Monterey Pl",
    "sg:city":"Norwalk",
    "sg:classifiers":[
        {
            "category":"Banks & Credit Unions",
            "subcategory":"Bank",
            "type":"Services"
        }
    ],
    "sg:phone":"+1 203 838 2921",
    "sg:postcode":"06854",
    "sg:province":"CT",
    "sg:tags":[
        "loan",
        "real estate"
    ],
    "wof:name":"Monterey Village Apartments",
    "wof:placetype":"venue"
},
  "geometry": {"coordinates":[-73.41850100000001,41.089463],"type":"Point"}
}