{
  "type": "Feature",
  "properties": {
    "addr:full":"313 Joshuatown Rd Old Lyme CT 06371",
    "addr:housenumber":"313",
    "addr:postcode":"06371",
    "addr:street":"Joshuatown Rd;Lyme Ct",
    "iso:country":"US",
    "sg:address":"313 Joshuatown Rd",
    "sg:city":"Old Lyme",
    "sg:classifiers":[
        {
            "category":"Home & Garden",
            "subcategory":"Household Appliances",
            "type":"Retail Goods"
        }
    ],
    "sg:phone":"+1 860 526 9876",
    "sg:postcode":"06371",
    "sg:province":"CT",
    "sg:tags":[
        "repair"
    ],
    "wof:name":"Robinson William H Appliances",
    "wof:placetype":"venue"
},
  "geometry": {"coordinates":[-72.3927,41.402199],"type":"Point"}
}