{
  "type": "Feature",
  "properties": {
    "iso:country":"US",
    "sg:address":"1000 W Main St",
    "sg:city":"New Britain",
    "sg:classifiers":[
        {
            "category":"Food & Beverages",
            "subcategory":"Groceries & Convenience Stores",
            "type":"Retail Goods"
        }
    ],
    "sg:phone":"+1 860 229 0110",
    "sg:postcode":"06053",
    "sg:province":"CT",
    "wof:name":"Your Store",
    "wof:placetype":"venue"
},
  "geometry": {"coordinates":[-72.817922,41.668294],"type":"Point"}
}