{
  "type": "Feature",
  "properties": {
    "iso:country":"US",
    "sg:address":"400 Wethersfield Ave",
    "sg:city":"Hartford",
    "sg:classifiers":[
        {
            "category":"Education",
            "subcategory":"School",
            "type":"Public Place"
        }
    ],
    "sg:phone":"+1   ",
    "sg:postcode":"06114",
    "sg:province":"CT",
    "wof:name":"Alsred E Burr Elementary Schl",
    "wof:placetype":"venue"
},
  "geometry": {"coordinates":[-72.672895,41.744097],"type":"Point"}
}