{
  "type": "Feature",
  "properties": {
    "iso:country":"US",
    "sg:address":"4 Cook Rd",
    "sg:city":"Stamford",
    "sg:classifiers":[
        {
            "category":"Shopping",
            "subcategory":"Pharmacy",
            "type":"Retail Goods"
        }
    ],
    "sg:phone":"+1 203 325 2051",
    "sg:postcode":"06902",
    "sg:province":"CT",
    "wof:name":"Natural Apothecary",
    "wof:placetype":"venue"
},
  "geometry": {"coordinates":[-73.544085,41.031002],"type":"Point"}
}