{
  "type": "Feature",
  "properties": {
    "iso:country":"US",
    "sg:address":"77 Grassy Plain St",
    "sg:city":"Bethel",
    "sg:classifiers":[
        {
            "category":"Building & Trades",
            "subcategory":"Construction",
            "type":"Services"
        }
    ],
    "sg:phone":"+1 203 748 8601",
    "sg:postcode":"06801",
    "sg:province":"CT",
    "sg:tags":[
        "coping",
        "plastering",
        "tiling",
        "pool",
        "swimming"
    ],
    "wof:name":"George Mc Cormick Pool Svc",
    "wof:placetype":"venue"
},
  "geometry": {"coordinates":[-73.422194,41.369693],"type":"Point"}
}