{
  "type": "Feature",
  "properties": {
    "addr:full":"8 School St Woodbury CT 06798",
    "addr:housenumber":"8",
    "addr:postcode":"06798",
    "addr:street":"School St",
    "iso:country":"US",
    "sg:address":"8 School St",
    "sg:city":"Woodbury",
    "sg:classifiers":[
        {
            "category":"Home & Garden",
            "subcategory":"Garden Supply",
            "type":"Retail Goods"
        }
    ],
    "sg:phone":"+1 203 263 4948",
    "sg:postcode":"06798",
    "sg:province":"CT",
    "wof:name":"Woodbury Saw & Lawnmower",
    "wof:placetype":"venue"
},
  "geometry": {"coordinates":[-73.208884,41.547354],"type":"Point"}
}