{
  "type": "Feature",
  "properties": {
    "iso:country":"US",
    "sg:address":"703 Boston Neck Rd",
    "sg:city":"Suffield",
    "sg:classifiers":[
        {
            "category":"Shopping",
            "subcategory":"Tobacco",
            "type":"Retail Goods"
        },
        {
            "category":"Manufacturing",
            "subcategory":"Tobacco Products",
            "type":"Manufacturing & Wholesale Goods"
        }
    ],
    "sg:phone":"+1 860 668 2647",
    "sg:postcode":"06078",
    "sg:province":"CT",
    "sg:tags":[
        "accessories-wholesale",
        "cigarette",
        "cigar",
        "manufacturer"
    ],
    "wof:name":"Zacks Cigar Company",
    "wof:placetype":"venue"
},
  "geometry": {"coordinates":[-72.636726,41.96175],"type":"Point"}
}