{
  "type": "Feature",
  "properties": {
    "iso:country":"US",
    "sg:address":"323 Westport Ave",
    "sg:city":"Norwalk",
    "sg:classifiers":[
        {
            "category":"Retail",
            "subcategory":"Auto Repair",
            "type":"Services"
        }
    ],
    "sg:phone":"+1   ",
    "sg:postcode":"06851",
    "sg:province":"CT",
    "sg:tags":[
        "general"
    ],
    "wof:name":"Rons Speed & Sport Shop Inc",
    "wof:placetype":"venue"
},
  "geometry": {"coordinates":[-73.39219900000001,41.125768],"type":"Point"}
}