{
  "type": "Feature",
  "properties": {
    "addr:full":"296 Main St Newington CT 06111",
    "addr:housenumber":"296",
    "addr:postcode":"06111",
    "addr:street":"Main St",
    "iso:country":"US",
    "sg:address":"296 Main St",
    "sg:city":"Newington",
    "sg:classifiers":[
        {
            "category":"Health Services",
            "subcategory":"Doctor",
            "type":"Services"
        }
    ],
    "sg:phone":"+1   ",
    "sg:postcode":"06111",
    "sg:province":"CT",
    "sg:tags":[
        "medical"
    ],
    "wof:name":"Keith Kaplan MD",
    "wof:placetype":"venue"
},
  "geometry": {"coordinates":[-72.72581099999999,41.711565],"type":"Point"}
}