{
  "type": "Feature",
  "properties": {
    "addr:full":"63 Harvest Ln Windsor CT 06095",
    "addr:housenumber":"63",
    "addr:postcode":"06095",
    "addr:street":"Harvest Ln",
    "iso:country":"US",
    "sg:address":"63 Harvest Ln",
    "sg:city":"Windsor",
    "sg:classifiers":[
        {
            "category":"Professional",
            "subcategory":"Engineering",
            "type":"Services"
        }
    ],
    "sg:phone":"+1   ",
    "sg:postcode":"06095",
    "sg:province":"CT",
    "wof:name":"Eric Lichtsteiner",
    "wof:placetype":"venue"
},
  "geometry": {"coordinates":[-72.69298000000001,41.895809],"type":"Point"}
}