{
  "type": "Feature",
  "properties": {
    "iso:country":"US",
    "sg:address":"89 Boston Post Rd",
    "sg:city":"Orange",
    "sg:classifiers":[
        {
            "category":"Restaurant",
            "type":"Food & Drink"
        }
    ],
    "sg:phone":"+1 203 799 0880",
    "sg:postcode":"06477",
    "sg:province":"CT",
    "wof:name":"Uncle Willie's",
    "wof:placetype":"venue"
},
  "geometry": {"coordinates":[-72.98986499999999,41.276528],"type":"Point"}
}