{
  "type": "Feature",
  "properties": {
    "addr:full":"290 Broad St Manchester CT 06040",
    "addr:housenumber":"290",
    "addr:postcode":"06040",
    "addr:street":"Broad St",
    "iso:country":"US",
    "sg:address":"290 Broad St",
    "sg:city":"Manchester",
    "sg:classifiers":[
        {
            "category":"Autos & Motor Vehicles",
            "subcategory":"Automobile Sales",
            "type":"Retail Goods"
        },
        {
            "category":"Autos & Motor Vehicles",
            "subcategory":"Fuel & Gas Station",
            "type":"Retail Goods"
        },
        {
            "category":"Autos & Motor Vehicles",
            "subcategory":"Auto Supplies",
            "type":"Retail Goods"
        },
        {
            "category":"Retail",
            "subcategory":"Auto Repair",
            "type":"Services"
        }
    ],
    "sg:phone":"+1 860 783 2647",
    "sg:postcode":"06040",
    "sg:province":"CT",
    "sg:tags":[
        "wheel",
        "exhaust",
        "oil",
        "muffler",
        "balancing",
        "wheels-aligning",
        "servicing-automotive",
        "system",
        "accessory",
        "equipment",
        "lube",
        "electrical",
        "axle",
        "equipment-service",
        "alignment-frame",
        "brake",
        "inspection",
        "air conditioning"
    ],
    "sg:website":"http://www.tomtracker.com/redirect.cfm?bID=4837&hID=111353",
    "wof:name":"Meineke Car Care Center",
    "wof:placetype":"venue"
},
  "geometry": {"coordinates":[-72.53424800000001,41.77916],"type":"Point"}
}