{
  "type": "Feature",
  "properties": {
    "addr:full":"32 Ambler Ln Wilton CT 06897",
    "addr:housenumber":"32",
    "addr:postcode":"06897",
    "addr:street":"Ambler Ln",
    "iso:country":"US",
    "sg:address":"32 Ambler Ln",
    "sg:city":"Wilton",
    "sg:classifiers":[
        {
            "category":"Professional",
            "subcategory":"Computer Services",
            "type":"Services"
        },
        {
            "category":"Shopping",
            "subcategory":"Computers & Home Electronics",
            "type":"Retail Goods"
        }
    ],
    "sg:phone":"+1 203 762 3333",
    "sg:postcode":"06897",
    "sg:province":"CT",
    "sg:tags":[
        "prepackaged",
        "related",
        "software"
    ],
    "wof:name":"Computer Systems Concepts Inc",
    "wof:placetype":"venue"
},
  "geometry": {"coordinates":[-73.411807,41.210548],"type":"Point"}
}