{
  "type": "Feature",
  "properties": {
    "iso:country":"US",
    "sg:address":"27 Sachem Rd",
    "sg:city":"Greenwich",
    "sg:classifiers":[
        {
            "category":"Wholesale",
            "subcategory":"Drugs",
            "type":"Manufacturing & Wholesale Goods"
        }
    ],
    "sg:phone":"+1 203 622 9059",
    "sg:postcode":"06830",
    "sg:province":"CT",
    "wof:name":"Vida International Phrm Cons",
    "wof:placetype":"venue"
},
  "geometry": {"coordinates":[-73.603033,41.030478],"type":"Point"}
}