{
  "type": "Feature",
  "properties": {
    "iso:country":"US",
    "sg:address":"10 Country Way",
    "sg:city":"Wallingford",
    "sg:classifiers":[
        {
            "category":"Shopping",
            "subcategory":"Computers & Home Electronics",
            "type":"Retail Goods"
        }
    ],
    "sg:phone":"+1 203 287 0227",
    "sg:postcode":"06492",
    "sg:province":"CT",
    "wof:name":"Custom Built Computers",
    "wof:placetype":"venue"
},
  "geometry": {"coordinates":[-72.811785,41.415704],"type":"Point"}
}