{
  "type": "Feature",
  "properties": {
    "iso:country":"US",
    "sg:address":"27 Iron Gate Rd",
    "sg:city":"Stamford",
    "sg:classifiers":[
        {
            "category":"Health Services",
            "subcategory":"Doctor",
            "type":"Services"
        }
    ],
    "sg:phone":"+1   ",
    "sg:postcode":"06903",
    "sg:province":"CT",
    "sg:tags":[
        "medical"
    ],
    "wof:name":"Harold J Sherrington MD",
    "wof:placetype":"venue"
},
  "geometry": {"coordinates":[-73.57726599999999,41.110849],"type":"Point"}
}