{
  "type": "Feature",
  "properties": {
    "iso:country":"US",
    "sg:address":"461 Ocean Ave",
    "sg:city":"New London",
    "sg:classifiers":[
        {
            "category":"Health Services",
            "subcategory":"Doctor",
            "type":"Services"
        }
    ],
    "sg:phone":"+1   ",
    "sg:postcode":"06320",
    "sg:province":"CT",
    "wof:name":"Family Denistry",
    "wof:placetype":"venue"
},
  "geometry": {"coordinates":[-72.10437,41.333384],"type":"Point"}
}