{
  "type": "Feature",
  "properties": {
    "addr:full":"115 Main St Monroe CT 06468",
    "addr:housenumber":"115",
    "addr:postcode":"06468",
    "addr:street":"Main St",
    "iso:country":"US",
    "sg:address":"115 Main St",
    "sg:city":"Monroe",
    "sg:classifiers":[
        {
            "category":"Personal",
            "subcategory":"Beauty Salon",
            "type":"Services"
        }
    ],
    "sg:phone":"+1 203 452 9060",
    "sg:postcode":"06468",
    "sg:province":"CT",
    "sg:tags":[
        "shop"
    ],
    "wof:name":"Blain Thomas Hair Color Design",
    "wof:placetype":"venue"
},
  "geometry": {"coordinates":[-73.25367,41.303053],"type":"Point"}
}