{
  "type": "Feature",
  "properties": {
    "addr:full":"42 Drazen Dr North Haven CT 06473",
    "addr:housenumber":"42",
    "addr:postcode":"06473",
    "addr:street":"Drazen Dr;Haven",
    "iso:country":"US",
    "sg:address":"42 Drazen Dr",
    "sg:city":"North Haven",
    "sg:classifiers":[
        {
            "category":"Organizations",
            "subcategory":"Membership Organization",
            "type":"Services"
        }
    ],
    "sg:phone":"+1   ",
    "sg:postcode":"06473",
    "sg:province":"CT",
    "wof:name":"Flat Coated Retriever Society",
    "wof:placetype":"venue"
},
  "geometry": {"coordinates":[-72.834467,41.38191],"type":"Point"}
}