{
  "type": "Feature",
  "properties": {
    "addr:full":"563 Wolcott St Waterbury CT 06705",
    "addr:housenumber":"563",
    "addr:postcode":"06705",
    "addr:street":"Wolcott St Waterbury Ct",
    "iso:country":"US",
    "sg:address":"563 Wolcott St",
    "sg:city":"Waterbury",
    "sg:classifiers":[
        {
            "category":"Health Services",
            "subcategory":"Chiropractor",
            "type":"Services"
        }
    ],
    "sg:phone":"+1   ",
    "sg:postcode":"06705",
    "sg:province":"CT",
    "wof:name":"Thomas J Devito Dr",
    "wof:placetype":"venue"
},
  "geometry": {"coordinates":[-73.012361,41.558976],"type":"Point"}
}