{
  "type": "Feature",
  "properties": {
    "iso:country":"US",
    "sg:address":"1542 Stratford Ave",
    "sg:city":"Bridgeport",
    "sg:classifiers":[
        {
            "category":"Organizations",
            "subcategory":"Religious Organization",
            "type":"Services"
        }
    ],
    "sg:phone":"+1 203 331 8114",
    "sg:postcode":"06607",
    "sg:province":"CT",
    "sg:tags":[
        "church"
    ],
    "wof:name":"Love Temple Deliverance Ctr",
    "wof:placetype":"venue"
},
  "geometry": {"coordinates":[-73.161272,41.179762],"type":"Point"}
}