{
  "type": "Feature",
  "properties": {
    "iso:country":"US",
    "sg:address":"1492 High Ridge Rd",
    "sg:city":"Stamford",
    "sg:classifiers":[
        {
            "category":"Shopping",
            "type":"Retail Goods"
        }
    ],
    "sg:phone":"+1 203 329 0000",
    "sg:postcode":"06903",
    "sg:province":"CT",
    "sg:tags":[
        "art",
        "gallery",
        "dealer"
    ],
    "wof:name":"High Ridge North Art & Frame",
    "wof:placetype":"venue"
},
  "geometry": {"coordinates":[-73.54387699999999,41.120979],"type":"Point"}
}