{
  "type": "Feature",
  "properties": {
    "addr:full":"47 Cornwall Ln Guilford CT 06437",
    "addr:housenumber":"47",
    "addr:postcode":"06437",
    "addr:street":"Cornwall Ln",
    "iso:country":"US",
    "sg:address":"47 Cornwall Ln",
    "sg:city":"Guilford",
    "sg:classifiers":[
        {
            "category":"Professional",
            "subcategory":"Computer Services",
            "type":"Services"
        }
    ],
    "sg:phone":"+1 203 458 2905",
    "sg:postcode":"06437",
    "sg:province":"CT",
    "sg:tags":[
        "consultant",
        "designer"
    ],
    "sg:website":"www.moksa.com",
    "wof:name":"Moksa",
    "wof:placetype":"venue"
},
  "geometry": {"coordinates":[-72.69217,41.327426],"type":"Point"}
}