{
  "type": "Feature",
  "properties": {
    "iso:country":"US",
    "sg:address":"707 Main St",
    "sg:city":"Monroe",
    "sg:classifiers":[
        {
            "category":"Restaurant",
            "type":"Food & Drink"
        }
    ],
    "sg:phone":"+1 203 261 2652",
    "sg:postcode":"06468",
    "sg:province":"CT",
    "sg:website":"www.707onmain.net",
    "wof:name":"707 On Main",
    "wof:placetype":"venue"
},
  "geometry": {"coordinates":[-73.261816,41.341277],"type":"Point"}
}