{
  "type": "Feature",
  "properties": {
    "addr:full":"37 Seaview Ave Norwalk CT 06855",
    "addr:housenumber":"37",
    "addr:postcode":"06855",
    "addr:street":"Seaview Ave",
    "iso:country":"US",
    "sg:address":"37 Seaview Ave",
    "sg:city":"Norwalk",
    "sg:classifiers":[
        {
            "category":"Building & Trades",
            "subcategory":"Electrical",
            "type":"Services"
        }
    ],
    "sg:phone":"+1 203 838 1459",
    "sg:postcode":"06855",
    "sg:province":"CT",
    "sg:tags":[
        "electric",
        "contractor"
    ],
    "wof:name":"ARC Electric & Maintenance",
    "wof:placetype":"venue"
},
  "geometry": {"coordinates":[-73.410566,41.099682],"type":"Point"}
}