{
  "type": "Feature",
  "properties": {
    "addr:full":"124 W Putnam Ave Greenwich CT 06830",
    "addr:housenumber":"124",
    "addr:postcode":"06830",
    "addr:street":"W Putnam Ave",
    "iso:country":"US",
    "sg:address":"124 W Putnam Ave",
    "sg:city":"Greenwich",
    "sg:classifiers":[
        {
            "category":"Wholesale",
            "subcategory":"Metals & Minerals",
            "type":"Manufacturing & Wholesale Goods"
        }
    ],
    "sg:phone":"+1 203 629 8383",
    "sg:postcode":"06830",
    "sg:province":"CT",
    "sg:tags":[
        "scrap",
        "exporter",
        "ferrous"
    ],
    "wof:name":"US Ferrous Trading",
    "wof:placetype":"venue"
},
  "geometry": {"coordinates":[-73.630088,41.027456],"type":"Point"}
}