{
  "type": "Feature",
  "properties": {
    "addr:full":"68 Hope St Stamford CT 06906",
    "addr:housenumber":"68",
    "addr:postcode":"06906",
    "addr:street":"Hope St",
    "iso:country":"US",
    "sg:address":"68 Hope St",
    "sg:city":"Stamford",
    "sg:classifiers":[
        {
            "category":"Education",
            "subcategory":"Special Training",
            "type":"Public Place"
        }
    ],
    "sg:phone":"+1 203 323 5403",
    "sg:postcode":"06906",
    "sg:province":"CT",
    "sg:tags":[
        "tutoring"
    ],
    "wof:name":"Koren Tutoring",
    "wof:placetype":"venue"
},
  "geometry": {"coordinates":[-73.526456,41.061981],"type":"Point"}
}