{
  "type": "Feature",
  "properties": {
    "addr:full":"203 Mill St Riverton CT 06065",
    "addr:housenumber":"203",
    "addr:postcode":"06065",
    "addr:street":"Mill St",
    "iso:country":"US",
    "sg:address":"203 Mill St",
    "sg:city":"Riverton",
    "sg:classifiers":[
        {
            "category":"Retail",
            "subcategory":"Funeral Services",
            "type":"Services"
        }
    ],
    "sg:phone":"+1   ",
    "sg:postcode":"06065",
    "sg:province":"CT",
    "wof:name":"Michael J Lewis Home Imprv",
    "wof:placetype":"venue"
},
  "geometry": {"coordinates":[-73.00291,42.001768],"type":"Point"}
}