{
  "type": "Feature",
  "properties": {
    "iso:country":"US",
    "sg:address":"290 South St",
    "sg:city":"New Britain",
    "sg:classifiers":[
        {
            "category":"Retail",
            "subcategory":"Auto Repair",
            "type":"Services"
        }
    ],
    "sg:phone":"+1   ",
    "sg:postcode":"06051",
    "sg:province":"CT",
    "sg:tags":[
        "body"
    ],
    "wof:name":"Capital Auto Body",
    "wof:placetype":"venue"
},
  "geometry": {"coordinates":[-72.765697,41.652941],"type":"Point"}
}