{
  "type": "Feature",
  "properties": {
    "iso:country":"US",
    "sg:address":"17 Dunbar St",
    "sg:city":"Waterbury",
    "sg:classifiers":[
        {
            "category":"Building & Trades",
            "subcategory":"Construction",
            "type":"Services"
        }
    ],
    "sg:phone":"+1 203 757 7614",
    "sg:postcode":"06705",
    "sg:province":"CT",
    "sg:tags":[
        "house",
        "residential"
    ],
    "wof:name":"Joe Testas Home Improvement",
    "wof:placetype":"venue"
},
  "geometry": {"coordinates":[-73.011376,41.552223],"type":"Point"}
}