{
  "type": "Feature",
  "properties": {
    "addr:full":"184 Ansonia Rd Woodbridge CT 06525",
    "addr:housenumber":"184",
    "addr:postcode":"06525",
    "addr:street":"Ansonia Rd",
    "iso:country":"US",
    "sg:address":"184 Ansonia Rd",
    "sg:city":"Woodbridge",
    "sg:classifiers":[
        {
            "category":"Professional",
            "subcategory":"Business Services",
            "type":"Services"
        }
    ],
    "sg:phone":"+1   ",
    "sg:postcode":"06525",
    "sg:province":"CT",
    "sg:tags":[
        "interior",
        "designer"
    ],
    "wof:name":"Ispiration",
    "wof:placetype":"venue"
},
  "geometry": {"coordinates":[-73.02497700000001,41.32888],"type":"Point"}
}