{
  "type": "Feature",
  "properties": {
    "iso:country":"US",
    "sg:address":"471 Woodland St",
    "sg:city":"Windsor Locks",
    "sg:classifiers":[
        {
            "category":"Building & Trades",
            "subcategory":"Landscaping Services",
            "type":"Services"
        }
    ],
    "sg:phone":"+1 860 623 2462",
    "sg:postcode":"06096",
    "sg:province":"CT",
    "wof:name":"Andersen Lawn Service",
    "wof:placetype":"venue"
},
  "geometry": {"coordinates":[-72.661383,41.92849],"type":"Point"}
}