{
  "type": "Feature",
  "properties": {
    "iso:country":"US",
    "sg:address":"5 Riverside Rd",
    "sg:city":"Sandy Hook",
    "sg:classifiers":[
        {
            "category":"Health Services",
            "subcategory":"Doctor",
            "type":"Services"
        }
    ],
    "sg:phone":"+1   ",
    "sg:postcode":"06482",
    "sg:province":"CT",
    "sg:tags":[
        "medical"
    ],
    "wof:name":"Robert Ruxin Dr",
    "wof:placetype":"venue"
},
  "geometry": {"coordinates":[-73.279689,41.422013],"type":"Point"}
}