{
  "type": "Feature",
  "properties": {
    "addr:full":"1257 Main St Willimantic CT 06226",
    "addr:housenumber":"1257",
    "addr:postcode":"06226",
    "addr:street":"Main St",
    "iso:country":"US",
    "sg:address":"1257 Main St",
    "sg:city":"Willimantic",
    "sg:classifiers":[
        {
            "category":"Restaurant",
            "type":"Food & Drink"
        }
    ],
    "sg:menulink":"http://www.allmenus.com/ct/windham/91054-dangelo-sandwich-shops/menu/",
    "sg:phone":"+1 860 456 8970",
    "sg:postcode":"06226",
    "sg:province":"CT",
    "sg:tags":[
        "wrap",
        "soup",
        "american",
        "sandwich",
        "salad"
    ],
    "wof:name":"D'Angelo Sandwich Shops",
    "wof:placetype":"venue"
},
  "geometry": {"coordinates":[-72.227244,41.714674],"type":"Point"}
}