{
  "type": "Feature",
  "properties": {
    "addr:full":"100 Robinwood Rd Hamden CT 06517",
    "addr:housenumber":"100",
    "addr:postcode":"06517",
    "addr:street":"Robinwood Rd",
    "iso:country":"US",
    "sg:address":"100 Robinwood Rd",
    "sg:city":"Hamden",
    "sg:classifiers":[
        {
            "category":"Professional",
            "type":"Services"
        }
    ],
    "sg:phone":"+1 203 288 6759",
    "sg:postcode":"06517",
    "sg:province":"CT",
    "wof:name":"Connecticut Bldg Officials LLC",
    "wof:placetype":"venue"
},
  "geometry": {"coordinates":[-72.90151,41.349832],"type":"Point"}
}