{
  "type": "Feature",
  "properties": {
    "addr:full":"15 Ridge Rd Granby CT 06035",
    "addr:housenumber":"15",
    "addr:postcode":"06035",
    "addr:street":"Ridge Rd",
    "iso:country":"US",
    "sg:address":"15 Ridge Rd",
    "sg:city":"Granby",
    "sg:classifiers":[
        {
            "category":"Building & Trades",
            "subcategory":"Plumbing",
            "type":"Services"
        }
    ],
    "sg:phone":"+1 860 653 7637",
    "sg:postcode":"06035",
    "sg:province":"CT",
    "sg:tags":[
        "contractor"
    ],
    "wof:name":"Reliable Plumbing & Pump Svc",
    "wof:placetype":"venue"
},
  "geometry": {"coordinates":[-72.80211799999999,41.993705],"type":"Point"}
}