{
  "type": "Feature",
  "properties": {
    "addr:full":"95 E Putnam Ave Greenwich CT 06830",
    "addr:housenumber":"95",
    "addr:postcode":"06830",
    "addr:street":"E Putnam Ave",
    "iso:country":"US",
    "sg:address":"95 E Putnam Ave",
    "sg:city":"Greenwich",
    "sg:classifiers":[
        {
            "category":"Banks & Credit Unions",
            "subcategory":"Financial Services",
            "type":"Services"
        }
    ],
    "sg:phone":"+1 203 629 2612",
    "sg:postcode":"06830",
    "sg:province":"CT",
    "sg:tags":[
        "investment",
        "closed"
    ],
    "wof:name":"Chatsworth Capital Corp",
    "wof:placetype":"venue"
},
  "geometry": {"coordinates":[-73.62402400000001,41.033823],"type":"Point"}
}