{
  "type": "Feature",
  "properties": {
    "addr:full":"13 Furnace Ave Stafford Springs CT 06076",
    "addr:housenumber":"13",
    "addr:postcode":"06076",
    "addr:street":"Furnace Ave",
    "iso:country":"US",
    "sg:address":"13 Furnace Ave",
    "sg:city":"Stafford Springs",
    "sg:classifiers":[
        {
            "category":"Wholesale",
            "subcategory":"Stationery",
            "type":"Manufacturing & Wholesale Goods"
        }
    ],
    "sg:phone":"+1 860 684 2641",
    "sg:postcode":"06076",
    "sg:province":"CT",
    "sg:tags":[
        "supply"
    ],
    "wof:name":"Inspiration Station",
    "wof:placetype":"venue"
},
  "geometry": {"coordinates":[-72.302575,41.954237],"type":"Point"}
}