{
  "type": "Feature",
  "properties": {
    "addr:full":"46 W Avon Rd Avon CT 06001",
    "addr:housenumber":"46",
    "addr:postcode":"06001",
    "addr:street":"W Avon Rd",
    "iso:country":"US",
    "sg:address":"46 W Avon Rd",
    "sg:city":"Avon",
    "sg:classifiers":[
        {
            "category":"Health Services",
            "subcategory":"Dentist",
            "type":"Services"
        }
    ],
    "sg:phone":"+1 860 675 4900",
    "sg:postcode":"06001",
    "sg:province":"CT",
    "wof:name":"Sager Victoria DMD",
    "wof:placetype":"venue"
},
  "geometry": {"coordinates":[-72.867203,41.8158],"type":"Point"}
}