{
  "type": "Feature",
  "properties": {
    "iso:country":"US",
    "sg:address":"95 Rugby Rd",
    "sg:city":"Shelton",
    "sg:classifiers":[
        {
            "category":"Building & Trades",
            "subcategory":"Construction",
            "type":"Services"
        }
    ],
    "sg:phone":"+1 203 926 1926",
    "sg:postcode":"06484",
    "sg:province":"CT",
    "sg:tags":[
        "dry wall",
        "contractor"
    ],
    "wof:name":"D J Quality Drywall",
    "wof:placetype":"venue"
},
  "geometry": {"coordinates":[-73.15013,41.35394],"type":"Point"}
}