{
  "type": "Feature",
  "properties": {
    "iso:country":"US",
    "sg:address":"2388 Main St",
    "sg:city":"Bridgeport",
    "sg:classifiers":[
        {
            "category":"Food & Beverages",
            "subcategory":"Groceries & Convenience Stores",
            "type":"Retail Goods"
        }
    ],
    "sg:phone":"+1 203 331 9665",
    "sg:postcode":"06606",
    "sg:province":"CT",
    "wof:name":"Romero's Grocery Store",
    "wof:placetype":"venue"
},
  "geometry": {"coordinates":[-73.199343,41.195267],"type":"Point"}
}