{
  "type": "Feature",
  "properties": {
    "addr:full":"3 Trumbull Pl North Haven CT 06473",
    "addr:housenumber":"3",
    "addr:postcode":"06473",
    "addr:street":"Trumbull Pl;Haven",
    "iso:country":"US",
    "sg:address":"3 Trumbull Pl",
    "sg:city":"North Haven",
    "sg:classifiers":[
        {
            "category":"Social Services",
            "subcategory":"Child Care",
            "type":"Services"
        }
    ],
    "sg:phone":"+1 203 239 2799",
    "sg:postcode":"06473",
    "sg:province":"CT",
    "sg:tags":[
        "kindergarten",
        "academic",
        "school"
    ],
    "wof:name":"Playschool",
    "wof:placetype":"venue"
},
  "geometry": {"coordinates":[-72.85990099999999,41.386234],"type":"Point"}
}