{
  "type": "Feature",
  "properties": {
    "iso:country":"US",
    "sg:address":"64 US Hwy 7",
    "sg:city":"Falls Village",
    "sg:classifiers":[
        {
            "category":"Home & Garden",
            "subcategory":"Garden Supply",
            "type":"Retail Goods"
        }
    ],
    "sg:phone":"+1 203 824 0837",
    "sg:postcode":"06031",
    "sg:province":"CT",
    "sg:tags":[
        "equipment"
    ],
    "wof:name":"Battle Hill Power Equipment",
    "wof:placetype":"venue"
},
  "geometry": {"coordinates":[-73.35555100000001,41.954999],"type":"Point"}
}