{
  "type": "Feature",
  "properties": {
    "addr:full":"28 Sanford St Hartford CT 06120",
    "addr:housenumber":"28",
    "addr:postcode":"06120",
    "addr:street":"Sanford St",
    "iso:country":"US",
    "sg:address":"28 Sanford St",
    "sg:city":"Hartford",
    "sg:classifiers":[
        {
            "category":"Organizations",
            "subcategory":"Religious Organization",
            "type":"Services"
        }
    ],
    "sg:phone":"+1   ",
    "sg:postcode":"06120",
    "sg:province":"CT",
    "wof:name":"Abundant Family Center",
    "wof:placetype":"venue"
},
  "geometry": {"coordinates":[-72.67314500000001,41.78671],"type":"Point"}
}