{
  "type": "Feature",
  "properties": {
    "addr:full":"19 Cozy Hollow Rd Danbury CT 06811",
    "addr:housenumber":"19",
    "addr:postcode":"06811",
    "addr:street":"Cozy Hollow Rd",
    "iso:country":"US",
    "sg:address":"19 Cozy Hollow Rd",
    "sg:city":"Danbury",
    "sg:classifiers":[
        {
            "category":"Professional",
            "type":"Services"
        }
    ],
    "sg:phone":"+1 203 748 4049",
    "sg:postcode":"06811",
    "sg:province":"CT",
    "wof:name":"Oscar Pino",
    "wof:placetype":"venue"
},
  "geometry": {"coordinates":[-73.43947799999999,41.417167],"type":"Point"}
}