{
  "type": "Feature",
  "properties": {
    "iso:country":"US",
    "sg:address":"80 Huntington St",
    "sg:city":"Shelton",
    "sg:classifiers":[
        {
            "category":"Health Services",
            "subcategory":"Doctor",
            "type":"Services"
        }
    ],
    "sg:phone":"+1   ",
    "sg:postcode":"06484",
    "sg:province":"CT",
    "sg:tags":[
        "medical"
    ],
    "wof:name":"M Gowda MD",
    "wof:placetype":"venue"
},
  "geometry": {"coordinates":[-73.14533900000001,41.294337],"type":"Point"}
}