{
  "type": "Feature",
  "properties": {
    "iso:country":"US",
    "sg:address":"6 Meadow Dr",
    "sg:city":"Brookfield",
    "sg:classifiers":[
        {
            "category":"Professional",
            "subcategory":"Business Services",
            "type":"Services"
        }
    ],
    "sg:phone":"+1 203 775 0660",
    "sg:postcode":"06804",
    "sg:province":"CT",
    "sg:tags":[
        "engraver"
    ],
    "wof:name":"Barto Engraving & Awards",
    "wof:placetype":"venue"
},
  "geometry": {"coordinates":[-73.37420400000001,41.451275],"type":"Point"}
}