{
  "type": "Feature",
  "properties": {
    "addr:full":"347 Cowles Rd Woodbury CT 06798",
    "addr:housenumber":"347",
    "addr:postcode":"06798",
    "addr:street":"Cowles Rd",
    "iso:country":"US",
    "sg:address":"347 Cowles Rd",
    "sg:city":"Woodbury",
    "sg:classifiers":[
        {
            "category":"Professional",
            "subcategory":"Management & Consulting",
            "type":"Services"
        }
    ],
    "sg:phone":"+1   ",
    "sg:postcode":"06798",
    "sg:province":"CT",
    "sg:tags":[
        "company"
    ],
    "wof:name":"Jt Builders",
    "wof:placetype":"venue"
},
  "geometry": {"coordinates":[-73.195599,41.609505],"type":"Point"}
}