{
  "type": "Feature",
  "properties": {
    "addr:full":"140 Green Rd Meriden CT 06450",
    "addr:housenumber":"140",
    "addr:postcode":"06450",
    "addr:street":"Green Rd",
    "iso:country":"US",
    "sg:address":"140 Green Rd",
    "sg:city":"Meriden",
    "sg:classifiers":[
        {
            "category":"Health Services",
            "subcategory":"Doctor",
            "type":"Services"
        }
    ],
    "sg:phone":"+1   ",
    "sg:postcode":"06450",
    "sg:province":"CT",
    "sg:tags":[
        "medical"
    ],
    "wof:name":"Philip E Shapiro MD",
    "wof:placetype":"venue"
},
  "geometry": {"coordinates":[-72.801451,41.51486],"type":"Point"}
}