{
  "type": "Feature",
  "properties": {
    "addr:full":"225 Belden St Watertown CT 06795",
    "addr:housenumber":"225",
    "addr:postcode":"06795",
    "addr:street":"Belden St",
    "iso:country":"US",
    "sg:address":"225 Belden St",
    "sg:city":"Watertown",
    "sg:classifiers":[
        {
            "category":"Travel",
            "subcategory":"Hotels & Motels",
            "type":"Entertainment"
        }
    ],
    "sg:phone":"+1   ",
    "sg:postcode":"06795",
    "sg:province":"CT",
    "sg:tags":[
        "operation"
    ],
    "wof:name":"Eastcoast Air LLC",
    "wof:placetype":"venue"
},
  "geometry": {"coordinates":[-73.11545700000001,41.59292],"type":"Point"}
}