{
  "type": "Feature",
  "properties": {
    "iso:country":"US",
    "sg:address":"1100 Buckingham St",
    "sg:city":"Watertown",
    "sg:classifiers":[
        {
            "category":"Professional",
            "type":"Services"
        }
    ],
    "sg:phone":"+1 860 945 2206",
    "sg:postcode":"06795",
    "sg:province":"CT",
    "wof:name":"Bristol Instruments Systems Em",
    "wof:placetype":"venue"
},
  "geometry": {"coordinates":[-73.092862,41.610852],"type":"Point"}
}