{
  "type": "Feature",
  "properties": {
    "addr:full":"25 Constitution Blvd S Shelton CT 06484",
    "addr:housenumber":"25",
    "addr:postcode":"06484",
    "addr:street":"Constitution Blvd S Shelton Ct",
    "iso:country":"US",
    "sg:address":"25 Constitution Blvd S",
    "sg:city":"Shelton",
    "sg:classifiers":[
        {
            "category":"Health Services",
            "subcategory":"Health Practitioner",
            "type":"Services"
        }
    ],
    "sg:phone":"+1 203 922 9250",
    "sg:postcode":"06484",
    "sg:province":"CT",
    "sg:tags":[
        "therapist",
        "physical"
    ],
    "wof:name":"Procare Therapy & Sports Med",
    "wof:placetype":"venue"
},
  "geometry": {"coordinates":[-73.08212399999999,41.290035],"type":"Point"}
}