{
  "type": "Feature",
  "properties": {
    "addr:full":"29 Elmcroft Rd Stamford CT 06902",
    "addr:housenumber":"29",
    "addr:postcode":"06902",
    "addr:street":"Elmcroft Rd",
    "iso:country":"US",
    "sg:address":"29 Elmcroft Rd",
    "sg:city":"Stamford",
    "sg:classifiers":[
        {
            "category":"Restaurant",
            "type":"Food & Drink"
        }
    ],
    "sg:phone":"+1 203 325 9287",
    "sg:postcode":"06902",
    "sg:province":"CT",
    "sg:tags":[
        "caterer"
    ],
    "wof:name":"Tri State Chefs",
    "wof:placetype":"venue"
},
  "geometry": {"coordinates":[-73.53685900000001,41.040941],"type":"Point"}
}