{
  "type": "Feature",
  "properties": {
    "addr:full":"62 River Rd Cornwall Bridge CT 06754",
    "addr:housenumber":"62",
    "addr:postcode":"06754",
    "addr:street":"River Rd Cornwall Bridge Ct",
    "iso:country":"US",
    "sg:address":"62 River Rd",
    "sg:city":"Cornwall Bridge",
    "sg:classifiers":[
        {
            "category":"Building & Trades",
            "subcategory":"Construction",
            "type":"Services"
        }
    ],
    "sg:phone":"+1 860 672 6815",
    "sg:postcode":"06754",
    "sg:province":"CT",
    "sg:tags":[
        "excavating",
        "contractor",
        "tree",
        "care"
    ],
    "wof:name":"John A Frost Inc",
    "wof:placetype":"venue"
},
  "geometry": {"coordinates":[-73.37766999999999,41.814645],"type":"Point"}
}