{
  "type": "Feature",
  "properties": {
    "iso:country":"US",
    "sg:address":"954 Wells Pl",
    "sg:city":"Stratford",
    "sg:classifiers":[
        {
            "category":"Shopping",
            "type":"Retail Goods"
        }
    ],
    "sg:phone":"+1 203 375 1979",
    "sg:postcode":"06615",
    "sg:province":"CT",
    "sg:tags":[
        "art",
        "dealer"
    ],
    "wof:name":"Fred Hartmann Studios",
    "wof:placetype":"venue"
},
  "geometry": {"coordinates":[-73.12801,41.18537],"type":"Point"}
}