{
  "type": "Feature",
  "properties": {
    "iso:country":"US",
    "sg:address":"47 Imperial Ave",
    "sg:city":"Westport",
    "sg:classifiers":[
        {
            "category":"Professional",
            "subcategory":"Business Services",
            "type":"Services"
        }
    ],
    "sg:phone":"+1   ",
    "sg:postcode":"06880",
    "sg:province":"CT",
    "wof:name":"Lock Stock & Brrl Estate Sales",
    "wof:placetype":"venue"
},
  "geometry": {"coordinates":[-73.35859499999999,41.138001],"type":"Point"}
}