{
  "type": "Feature",
  "properties": {
    "addr:full":"253 Center St Wallingford CT 06492",
    "addr:housenumber":"253",
    "addr:postcode":"06492",
    "addr:street":"Center St",
    "iso:country":"US",
    "sg:address":"253 Center St",
    "sg:city":"Wallingford",
    "sg:classifiers":[
        {
            "category":"Professional",
            "subcategory":"Research",
            "type":"Services"
        }
    ],
    "sg:phone":"+1 203 265 4163",
    "sg:postcode":"06492",
    "sg:province":"CT",
    "sg:tags":[
        "development",
        "electronic"
    ],
    "wof:name":"Connecticut Technologies",
    "wof:placetype":"venue"
},
  "geometry": {"coordinates":[-72.818309,41.454314],"type":"Point"}
}