{
  "type": "Feature",
  "properties": {
    "iso:country":"US",
    "sg:address":"120 Old Hwy",
    "sg:city":"Wilton",
    "sg:classifiers":[
        {
            "category":"Professional",
            "subcategory":"Management & Consulting",
            "type":"Services"
        }
    ],
    "sg:phone":"+1   ",
    "sg:postcode":"06897",
    "sg:province":"CT",
    "sg:tags":[
        "development",
        "consultant",
        "training"
    ],
    "wof:name":"Dirt Camp Inc",
    "wof:placetype":"venue"
},
  "geometry": {"coordinates":[-73.415161,41.194779],"type":"Point"}
}