{
  "type": "Feature",
  "properties": {
    "iso:country":"US",
    "sg:address":"8 E Newberry Rd",
    "sg:city":"Bloomfield",
    "sg:classifiers":[
        {
            "category":"Autos & Motor Vehicles",
            "subcategory":"Fuel & Gas Station",
            "type":"Retail Goods"
        }
    ],
    "sg:phone":"+1 860 243 9114",
    "sg:postcode":"06002",
    "sg:province":"CT",
    "sg:tags":[
        "line",
        "full",
        "dealership",
        "volvo"
    ],
    "wof:name":"McDonnell Marine Service LLC",
    "wof:placetype":"venue"
},
  "geometry": {"coordinates":[-72.702921,41.86333],"type":"Point"}
}