{
  "type": "Feature",
  "properties": {
    "iso:country":"US",
    "sg:address":"700 N Salem Rd",
    "sg:city":"Ridgefield",
    "sg:classifiers":[
        {
            "category":"Professional",
            "subcategory":"Business Services",
            "type":"Services"
        }
    ],
    "sg:phone":"+1   ",
    "sg:postcode":"06877",
    "sg:province":"CT",
    "wof:name":"Banton Construction Co",
    "wof:placetype":"venue"
},
  "geometry": {"coordinates":[-73.53055999999999,41.325389],"type":"Point"}
}