{
  "type": "Feature",
  "properties": {
    "iso:country":"US",
    "sg:address":"4 Birch St",
    "sg:city":"Norwalk",
    "sg:classifiers":[
        {
            "category":"Professional",
            "subcategory":"Art Services",
            "type":"Services"
        }
    ],
    "sg:phone":"+1   ",
    "sg:postcode":"06851",
    "sg:province":"CT",
    "sg:tags":[
        "commercial",
        "photography",
        "studio"
    ],
    "wof:name":"Clarino Photography Inc",
    "wof:placetype":"venue"
},
  "geometry": {"coordinates":[-73.402682,41.119309],"type":"Point"}
}