{
  "type": "Feature",
  "properties": {
    "addr:full":"90 Park Dr Chaplin CT 06235",
    "addr:housenumber":"90",
    "addr:postcode":"06235",
    "addr:street":"Park Dr Chaplin Ct",
    "iso:country":"US",
    "sg:address":"90 Park Dr",
    "sg:city":"Chaplin",
    "sg:classifiers":[
        {
            "category":"Social Services",
            "type":"Services"
        }
    ],
    "sg:phone":"+1   ",
    "sg:postcode":"06235",
    "sg:province":"CT",
    "wof:name":"Northeastrn CT Sexual Assault",
    "wof:placetype":"venue"
},
  "geometry": {"coordinates":[-72.12772699999999,41.764354],"type":"Point"}
}