{
  "type": "Feature",
  "properties": {
    "addr:full":"25 Howard Rd Bolton CT 06043",
    "addr:housenumber":"25",
    "addr:postcode":"06043",
    "addr:street":"Howard Rd",
    "iso:country":"US",
    "sg:address":"25 Howard Rd",
    "sg:city":"Bolton",
    "sg:classifiers":[
        {
            "category":"Manufacturing",
            "subcategory":"Tools & Machinery",
            "type":"Manufacturing & Wholesale Goods"
        }
    ],
    "sg:phone":"+1 860 647 7999",
    "sg:postcode":"06043",
    "sg:province":"CT",
    "sg:tags":[
        "industrial",
        "mfg"
    ],
    "wof:name":"Blue Chip Tool",
    "wof:placetype":"venue"
},
  "geometry": {"coordinates":[-72.43680000000001,41.793622],"type":"Point"}
}