{
  "type": "Feature",
  "properties": {
    "iso:country":"US",
    "sg:address":"350 Hazard Ave",
    "sg:city":"Enfield",
    "sg:classifiers":[
        {
            "category":"Manufacturing",
            "subcategory":"Leather Goods",
            "type":"Manufacturing & Wholesale Goods"
        }
    ],
    "sg:phone":"+1 860 763 2699",
    "sg:postcode":"06082",
    "sg:province":"CT",
    "sg:tags":[
        "gift",
        "supply",
        "mfg",
        "ceramic",
        "novelty",
        "retail"
    ],
    "wof:name":"Debray Enterprises Inc",
    "wof:placetype":"venue"
},
  "geometry": {"coordinates":[-72.536494,41.986095],"type":"Point"}
}