{
  "type": "Feature",
  "properties": {
    "addr:full":"87 Shoddy Mill Rd Bolton CT 06043",
    "addr:housenumber":"87",
    "addr:postcode":"06043",
    "addr:street":"Shoddy Mill Rd",
    "iso:country":"US",
    "sg:address":"87 Shoddy Mill Rd",
    "sg:city":"Bolton",
    "sg:classifiers":[
        {
            "category":"Real Estate",
            "subcategory":"Real Estate Agent",
            "type":"Services"
        }
    ],
    "sg:phone":"+1 860 646 9898",
    "sg:postcode":"06043",
    "sg:province":"CT",
    "sg:tags":[
        "property",
        "leasing"
    ],
    "wof:name":"R & D LLC",
    "wof:placetype":"venue"
},
  "geometry": {"coordinates":[-72.406548,41.738697],"type":"Point"}
}