{
  "type": "Feature",
  "properties": {
    "addr:full":"275 Seabreeze Dr Stratford CT 06614",
    "addr:housenumber":"275",
    "addr:postcode":"06614",
    "addr:street":"Seabreeze Dr",
    "iso:country":"US",
    "sg:address":"275 Seabreeze Dr",
    "sg:city":"Stratford",
    "sg:classifiers":[
        {
            "category":"Professional",
            "subcategory":"Business Services",
            "type":"Services"
        }
    ],
    "sg:phone":"+1   ",
    "sg:postcode":"06614",
    "sg:province":"CT",
    "sg:tags":[
        "engraving"
    ],
    "wof:name":"Beta Engraving",
    "wof:placetype":"venue"
},
  "geometry": {"coordinates":[-73.14907700000001,41.222717],"type":"Point"}
}