{
  "type": "Feature",
  "properties": {
    "iso:country":"US",
    "sg:address":"4 Taft St",
    "sg:city":"Norwalk",
    "sg:classifiers":[
        {
            "category":"Home & Garden",
            "subcategory":"Furniture",
            "type":"Retail Goods"
        }
    ],
    "sg:phone":"+1 203 853 4411",
    "sg:postcode":"06854",
    "sg:province":"CT",
    "sg:tags":[
        "equipment",
        "kitchen",
        "cabinet"
    ],
    "wof:name":"Sebastian Kitchen Cabinets",
    "wof:placetype":"venue"
},
  "geometry": {"coordinates":[-73.428138,41.087068],"type":"Point"}
}