{
  "type": "Feature",
  "properties": {
    "iso:country":"US",
    "sg:address":"159 Stillwater Ave",
    "sg:city":"Stamford",
    "sg:classifiers":[
        {
            "category":"Professional",
            "subcategory":"Business Services",
            "type":"Services"
        }
    ],
    "sg:phone":"+1   ",
    "sg:postcode":"06902",
    "sg:province":"CT",
    "wof:name":"Golden Express",
    "wof:placetype":"venue"
},
  "geometry": {"coordinates":[-73.55162300000001,41.051998],"type":"Point"}
}