{
  "type": "Feature",
  "properties": {
    "iso:country":"US",
    "sg:address":"15 Omo St",
    "sg:city":"Middletown",
    "sg:classifiers":[
        {
            "category":"Retail",
            "subcategory":"Portrait Studio",
            "type":"Services"
        }
    ],
    "sg:phone":"+1   ",
    "sg:postcode":"06457",
    "sg:province":"CT",
    "sg:tags":[
        "photo"
    ],
    "wof:name":"Robert J Hennessey Photography",
    "wof:placetype":"venue"
},
  "geometry": {"coordinates":[-72.637311,41.556406],"type":"Point"}
}