{
  "type": "Feature",
  "properties": {
    "addr:full":"4 Little Ln Westport CT 06880",
    "addr:housenumber":"4",
    "addr:postcode":"06880",
    "addr:street":"Little Ln",
    "iso:country":"US",
    "sg:address":"4 Little Ln",
    "sg:city":"Westport",
    "sg:classifiers":[
        {
            "category":"Professional",
            "subcategory":"Employment Agencies",
            "type":"Services"
        }
    ],
    "sg:phone":"+1   ",
    "sg:postcode":"06880",
    "sg:province":"CT",
    "sg:tags":[
        "search",
        "executive"
    ],
    "wof:name":"Mc Leod Group Inc",
    "wof:placetype":"venue"
},
  "geometry": {"coordinates":[-73.359334,41.181496],"type":"Point"}
}