{
  "type": "Feature",
  "properties": {
    "iso:country":"US",
    "sg:address":"576 Boston Post Rd",
    "sg:city":"Milford",
    "sg:classifiers":[
        {
            "category":"Home & Garden",
            "subcategory":"Building Materials",
            "type":"Retail Goods"
        }
    ],
    "sg:phone":"+1 203 334 1000",
    "sg:postcode":"06460",
    "sg:province":"CT",
    "sg:tags":[
        "glass",
        "window",
        "plate"
    ],
    "wof:name":"Safelite Auto Glass",
    "wof:placetype":"venue"
},
  "geometry": {"coordinates":[-73.066784,41.229372],"type":"Point"}
}