{
  "type": "Feature",
  "properties": {
    "addr:full":"263 Danbury Rd Wilton CT 06897",
    "addr:housenumber":"263",
    "addr:postcode":"06897",
    "addr:street":"Danbury Rd Wilton Ct",
    "iso:country":"US",
    "sg:address":"263 Danbury Rd",
    "sg:city":"Wilton",
    "sg:classifiers":[
        {
            "category":"Home & Garden",
            "subcategory":"Home Furnishings",
            "type":"Retail Goods"
        }
    ],
    "sg:phone":"+1   ",
    "sg:postcode":"06897",
    "sg:province":"CT",
    "sg:tags":[
        "repair",
        "merchandise",
        "se"
    ],
    "wof:name":"Beardsley Fine Framing",
    "wof:placetype":"venue"
},
  "geometry": {"coordinates":[-73.42974700000001,41.193185],"type":"Point"}
}