{
  "type": "Feature",
  "properties": {
    "addr:full":"1331 State St New Haven CT 06511",
    "addr:housenumber":"1331",
    "addr:postcode":"06511",
    "addr:street":"State St",
    "iso:country":"US",
    "sg:address":"1331 State St",
    "sg:city":"New Haven",
    "sg:classifiers":[
        {
            "category":"Autos & Motor Vehicles",
            "subcategory":"Fuel & Gas Station",
            "type":"Retail Goods"
        }
    ],
    "sg:phone":"+1 203 789 9221",
    "sg:postcode":"06511",
    "sg:province":"CT",
    "sg:tags":[
        "station",
        "gasoline"
    ],
    "wof:name":"Shell",
    "wof:placetype":"venue"
},
  "geometry": {"coordinates":[-72.899308,41.318787],"type":"Point"}
}