{
  "type": "Feature",
  "properties": {
    "iso:country":"US",
    "sg:address":"62 Winfield St",
    "sg:city":"Norwalk",
    "sg:classifiers":[
        {
            "category":"Building & Trades",
            "subcategory":"Landscaping Services",
            "type":"Services"
        }
    ],
    "sg:phone":"+1 203 852 1248",
    "sg:postcode":"06855",
    "sg:province":"CT",
    "wof:name":"Ceja Lawn Maintenance LLC",
    "wof:placetype":"venue"
},
  "geometry": {"coordinates":[-73.397143,41.105948],"type":"Point"}
}