{
  "type": "Feature",
  "properties": {
    "iso:country":"US",
    "sg:address":"412 Wildwood Dr",
    "sg:city":"Orange",
    "sg:classifiers":[
        {
            "category":"Building & Trades",
            "subcategory":"Construction",
            "type":"Services"
        }
    ],
    "sg:phone":"+1 203 799 3757",
    "sg:postcode":"06477",
    "sg:province":"CT",
    "sg:tags":[
        "repair",
        "handyman",
        "maintenance",
        "home"
    ],
    "wof:name":"Hire A Husband",
    "wof:placetype":"venue"
},
  "geometry": {"coordinates":[-73.04939299999999,41.300541],"type":"Point"}
}