{
  "type": "Feature",
  "properties": {
    "iso:country":"US",
    "sg:address":"300 E Main St",
    "sg:city":"Meriden",
    "sg:classifiers":[
        {
            "category":"Restaurant",
            "type":"Food & Drink"
        }
    ],
    "sg:phone":"+1 203 237 9339",
    "sg:postcode":"06450",
    "sg:province":"CT",
    "sg:tags":[
        "pizza"
    ],
    "wof:name":"Uptown Pizza",
    "wof:placetype":"venue"
},
  "geometry": {"coordinates":[-72.792344,41.533673],"type":"Point"}
}