{
  "type": "Feature",
  "properties": {
    "iso:country":"US",
    "sg:address":"32 Elaine Dr",
    "sg:city":"Stamford",
    "sg:classifiers":[
        {
            "category":"Professional",
            "subcategory":"Detective & Security Services",
            "type":"Services"
        }
    ],
    "sg:phone":"+1   ",
    "sg:postcode":"06902",
    "sg:province":"CT",
    "sg:tags":[
        "investigation"
    ],
    "wof:name":"Chris Munger Associates",
    "wof:placetype":"venue"
},
  "geometry": {"coordinates":[-73.557338,41.089097],"type":"Point"}
}