{
  "type": "Feature",
  "properties": {
    "iso:country":"US",
    "sg:address":"38 Iron Mountain Rd",
    "sg:city":"Kent",
    "sg:classifiers":[
        {
            "category":"Building & Trades",
            "subcategory":"Construction",
            "type":"Services"
        }
    ],
    "sg:phone":"+1 860 927 5292",
    "sg:postcode":"06757",
    "sg:province":"CT",
    "sg:tags":[
        "contractor"
    ],
    "wof:name":"Cornerstone Masonry Inc",
    "wof:placetype":"venue"
},
  "geometry": {"coordinates":[-73.43203800000001,41.712144],"type":"Point"}
}