{
  "type": "Feature",
  "properties": {
    "addr:full":"810 Beaver Dam Rd Stratford CT 06614",
    "addr:housenumber":"810",
    "addr:postcode":"06614",
    "addr:street":"Beaver Dam Rd",
    "iso:country":"US",
    "sg:address":"810 Beaver Dam Rd",
    "sg:city":"Stratford",
    "sg:classifiers":[
        {
            "category":"Professional",
            "type":"Services"
        }
    ],
    "sg:phone":"+1 203 385 3871",
    "sg:postcode":"06614",
    "sg:province":"CT",
    "wof:name":"Motorcyclejackscom",
    "wof:placetype":"venue"
},
  "geometry": {"coordinates":[-73.138148,41.249607],"type":"Point"}
}