{
  "type": "Feature",
  "properties": {
    "addr:full":"174 Bridge St Groton CT 06340",
    "addr:housenumber":"174",
    "addr:postcode":"06340",
    "addr:street":"Bridge St",
    "iso:country":"US",
    "sg:address":"174 Bridge St",
    "sg:city":"Groton",
    "sg:classifiers":[
        {
            "category":"Insurance",
            "subcategory":"Insurance Agent",
            "type":"Services"
        }
    ],
    "sg:phone":"+1 860 448 2277",
    "sg:postcode":"06340",
    "sg:province":"CT",
    "wof:name":"Morin Associates",
    "wof:placetype":"venue"
},
  "geometry": {"coordinates":[-72.078227,41.36172],"type":"Point"}
}