{
  "type": "Feature",
  "properties": {
    "addr:full":"302 Tuttle Rd Woodbury CT 06798",
    "addr:housenumber":"302",
    "addr:postcode":"06798",
    "addr:street":"Tuttle Rd",
    "iso:country":"US",
    "sg:address":"302 Tuttle Rd",
    "sg:city":"Woodbury",
    "sg:classifiers":[
        {
            "category":"Real Estate",
            "subcategory":"Real Estate Operator",
            "type":"Services"
        }
    ],
    "sg:phone":"+1 203 263 3800",
    "sg:postcode":"06798",
    "sg:province":"CT",
    "sg:tags":[
        "building",
        "apartment"
    ],
    "wof:name":"Woodberry Knoll",
    "wof:placetype":"venue"
},
  "geometry": {"coordinates":[-73.18183999999999,41.531082],"type":"Point"}
}