{
  "type": "Feature",
  "properties": {
    "iso:country":"US",
    "sg:address":"85 Aetna St",
    "sg:city":"Naugatuck",
    "sg:classifiers":[
        {
            "category":"Professional",
            "subcategory":"Management & Consulting",
            "type":"Services"
        }
    ],
    "sg:phone":"+1 203 723 5904",
    "sg:postcode":"06770",
    "sg:province":"CT",
    "sg:tags":[
        "consultant",
        "construction"
    ],
    "wof:name":"Nor-Co USA",
    "wof:placetype":"venue"
},
  "geometry": {"coordinates":[-73.062414,41.488207],"type":"Point"}
}