{
  "type": "Feature",
  "properties": {
    "iso:country":"US",
    "sg:address":"4840 Durham Rd",
    "sg:city":"Guilford",
    "sg:classifiers":[
        {
            "category":"Professional",
            "subcategory":"Business Services",
            "type":"Services"
        }
    ],
    "sg:phone":"+1   ",
    "sg:postcode":"06437",
    "sg:province":"CT",
    "wof:name":"Celestial Design",
    "wof:placetype":"venue"
},
  "geometry": {"coordinates":[-72.691542,41.415302],"type":"Point"}
}