{
  "type": "Feature",
  "properties": {
    "addr:full":"54 Lafayette Pl Greenwich CT 06830",
    "addr:housenumber":"54",
    "addr:postcode":"06830",
    "addr:street":"Lafayette Pl",
    "iso:country":"US",
    "sg:address":"54 Lafayette Pl",
    "sg:city":"Greenwich",
    "sg:classifiers":[
        {
            "category":"Health Services",
            "subcategory":"Chiropractor",
            "type":"Services"
        }
    ],
    "sg:phone":"+1 203 661 6699",
    "sg:postcode":"06830",
    "sg:province":"CT",
    "wof:name":"Greenwich Chiropractic Svc",
    "wof:placetype":"venue"
},
  "geometry": {"coordinates":[-73.627182,41.031487],"type":"Point"}
}