{
  "type": "Feature",
  "properties": {
    "addr:full":"127 Carriage Crossing Ln Middletown CT 06457",
    "addr:housenumber":"127",
    "addr:postcode":"06457",
    "addr:street":"Carriage Crossing Ln",
    "iso:country":"US",
    "sg:address":"127 Carriage Crossing Ln",
    "sg:city":"Middletown",
    "sg:classifiers":[
        {
            "category":"Sports & Exercise",
            "subcategory":"Gym",
            "type":"Entertainment"
        }
    ],
    "sg:phone":"+1   ",
    "sg:postcode":"06457",
    "sg:province":"CT",
    "sg:tags":[
        "fitness",
        "physical",
        "facility"
    ],
    "wof:name":"Age Right",
    "wof:placetype":"venue"
},
  "geometry": {"coordinates":[-72.70949,41.587186],"type":"Point"}
}