{
  "type": "Feature",
  "properties": {
    "addr:full":"965 Elm Commons Dr Rocky Hill CT 06067",
    "addr:housenumber":"965",
    "addr:postcode":"06067",
    "addr:street":"Elm Commons Dr;Hill Ct",
    "iso:country":"US",
    "sg:address":"965 Elm Commons Dr",
    "sg:city":"Rocky Hill",
    "sg:classifiers":[
        {
            "category":"Real Estate",
            "subcategory":"Real Estate Operator",
            "type":"Services"
        }
    ],
    "sg:phone":"+1 860 721 1051",
    "sg:postcode":"06067",
    "sg:province":"CT",
    "sg:tags":[
        "building",
        "apartment"
    ],
    "wof:name":"Elms Common Apartments",
    "wof:placetype":"venue"
},
  "geometry": {"coordinates":[-72.673829,41.659477],"type":"Point"}
}