{
  "type": "Feature",
  "properties": {
    "iso:country":"US",
    "sg:address":"940 New Britain Ave",
    "sg:city":"Farmington",
    "sg:classifiers":[
        {
            "category":"Professional",
            "subcategory":"Business Services",
            "type":"Services"
        }
    ],
    "sg:phone":"+1   ",
    "sg:postcode":"06032",
    "sg:province":"CT",
    "wof:name":"Hyat Enterprises LLC",
    "wof:placetype":"venue"
},
  "geometry": {"coordinates":[-72.861983,41.736283],"type":"Point"}
}