{
  "type": "Feature",
  "properties": {
    "iso:country":"US",
    "sg:address":"435 Boston Post Rd",
    "sg:city":"Milford",
    "sg:classifiers":[
        {
            "category":"Retail",
            "subcategory":"Auto Repair",
            "type":"Services"
        }
    ],
    "sg:phone":"+1 203 877 4492",
    "sg:postcode":"06460",
    "sg:province":"CT",
    "sg:tags":[
        "automobile",
        "customizing"
    ],
    "wof:name":"Auto Trendz LLC",
    "wof:placetype":"venue"
},
  "geometry": {"coordinates":[-73.070047,41.226972],"type":"Point"}
}