{
  "type": "Feature",
  "properties": {
    "addr:full":"276 Hickory Cir Middletown CT 06457",
    "addr:housenumber":"276",
    "addr:postcode":"06457",
    "addr:street":"Hickory Cir",
    "iso:country":"US",
    "sg:address":"276 Hickory Cir",
    "sg:city":"Middletown",
    "sg:classifiers":[
        {
            "category":"Retail",
            "subcategory":"Auto Repair",
            "type":"Services"
        }
    ],
    "sg:phone":"+1   ",
    "sg:postcode":"06457",
    "sg:province":"CT",
    "sg:tags":[
        "general"
    ],
    "wof:name":"Newfield Auto II",
    "wof:placetype":"venue"
},
  "geometry": {"coordinates":[-72.683801,41.558086],"type":"Point"}
}