{
  "type": "Feature",
  "properties": {
    "addr:full":"145 Westbrook Rd Essex CT 06426",
    "addr:housenumber":"145",
    "addr:postcode":"06426",
    "addr:street":"Westbrook Rd",
    "iso:country":"US",
    "sg:address":"145 Westbrook Rd",
    "sg:city":"Essex",
    "sg:classifiers":[
        {
            "category":"Shopping",
            "subcategory":"Antiques",
            "type":"Retail Goods"
        }
    ],
    "sg:phone":"+1 860 767 2799",
    "sg:postcode":"06426",
    "sg:province":"CT",
    "wof:name":"Ahlberg Arne E Antiques",
    "wof:placetype":"venue"
},
  "geometry": {"coordinates":[-72.41709899999999,41.353401],"type":"Point"}
}