{
  "type": "Feature",
  "properties": {
    "iso:country":"US",
    "sg:address":"721 Ridgefield Rd",
    "sg:city":"Wilton",
    "sg:classifiers":[
        {
            "category":"Professional",
            "subcategory":"Business Services",
            "type":"Services"
        }
    ],
    "sg:phone":"+1   ",
    "sg:postcode":"06897",
    "sg:province":"CT",
    "wof:name":"Austin Interiors",
    "wof:placetype":"venue"
},
  "geometry": {"coordinates":[-73.477456,41.224716],"type":"Point"}
}