{
  "type": "Feature",
  "properties": {
    "iso:country":"US",
    "sg:address":"197 Kings Hwy",
    "sg:city":"Milford",
    "sg:classifiers":[
        {
            "category":"Professional",
            "subcategory":"Lawyer & Legal Services",
            "type":"Services"
        }
    ],
    "sg:phone":"+1   ",
    "sg:postcode":"06460",
    "sg:province":"CT",
    "wof:name":"Alderman Joel K Attrney At Law",
    "wof:placetype":"venue"
},
  "geometry": {"coordinates":[-72.997175,41.223573],"type":"Point"}
}