{
  "type": "Feature",
  "properties": {
    "iso:country":"US",
    "sg:address":"5 River Rd",
    "sg:city":"Cos Cob",
    "sg:classifiers":[
        {
            "category":"Professional",
            "subcategory":"Research",
            "type":"Services"
        }
    ],
    "sg:phone":"+1 203 661 3091",
    "sg:postcode":"06807",
    "sg:province":"CT",
    "sg:tags":[
        "environmental",
        "ecological"
    ],
    "sg:website":"www.oceanweather.com",
    "wof:name":"Oceanweather Inc",
    "wof:placetype":"venue"
},
  "geometry": {"coordinates":[-73.595602,41.034861],"type":"Point"}
}