{
  "type": "Feature",
  "properties": {
    "iso:country":"US",
    "sg:address":"39 Woodland Ave",
    "sg:city":"Stamford",
    "sg:classifiers":[
        {
            "category":"Wholesale",
            "subcategory":"Scrap",
            "type":"Manufacturing & Wholesale Goods"
        }
    ],
    "sg:phone":"+1 203 975 0488",
    "sg:postcode":"06902",
    "sg:province":"CT",
    "sg:tags":[
        "recycling",
        "center"
    ],
    "wof:name":"Southern Connecticut Recycling",
    "wof:placetype":"venue"
},
  "geometry": {"coordinates":[-73.53935199999999,41.043649],"type":"Point"}
}