{
  "type": "Feature",
  "properties": {
    "addr:full":"31 Little Acres Rd Glastonbury CT 06033",
    "addr:housenumber":"31",
    "addr:postcode":"06033",
    "addr:street":"Little Acres Rd",
    "iso:country":"US",
    "sg:address":"31 Little Acres Rd",
    "sg:city":"Glastonbury",
    "sg:classifiers":[
        {
            "category":"Professional",
            "subcategory":"Management & Consulting",
            "type":"Services"
        }
    ],
    "sg:phone":"+1   ",
    "sg:postcode":"06033",
    "sg:province":"CT",
    "wof:name":"Comar Trade Assn",
    "wof:placetype":"venue"
},
  "geometry": {"coordinates":[-72.592826,41.679587],"type":"Point"}
}