{
  "type": "Feature",
  "properties": {
    "addr:full":"7 Birch Hill Rd Weston CT 06883",
    "addr:housenumber":"7",
    "addr:postcode":"06883",
    "addr:street":"Birch Hill Rd",
    "iso:country":"US",
    "sg:address":"7 Birch Hill Rd",
    "sg:city":"Weston",
    "sg:classifiers":[
        {
            "category":"Professional",
            "subcategory":"Advertising",
            "type":"Services"
        }
    ],
    "sg:phone":"+1   ",
    "sg:postcode":"06883",
    "sg:province":"CT",
    "sg:tags":[
        "graphic",
        "design"
    ],
    "wof:name":"Young & Thomas",
    "wof:placetype":"venue"
},
  "geometry": {"coordinates":[-73.37617400000001,41.223579],"type":"Point"}
}