{
  "type": "Feature",
  "properties": {
    "addr:full":"186 Wakelee Ave Ansonia CT 06401",
    "addr:housenumber":"186",
    "addr:postcode":"06401",
    "addr:street":"Wakelee Ave",
    "iso:country":"US",
    "sg:address":"186 Wakelee Ave",
    "sg:city":"Ansonia",
    "sg:classifiers":[
        {
            "category":"Professional",
            "type":"Services"
        }
    ],
    "sg:phone":"+1 203 736 2967",
    "sg:postcode":"06401",
    "sg:province":"CT",
    "sg:tags":[
        "establishment"
    ],
    "wof:name":"Rivers Chicago",
    "wof:placetype":"venue"
},
  "geometry": {"coordinates":[-73.09070199999999,41.34504],"type":"Point"}
}