{
  "type": "Feature",
  "properties": {
    "iso:country":"US",
    "sg:address":"161 Burnham Rd",
    "sg:city":"Avon",
    "sg:classifiers":[
        {
            "category":"Professional",
            "subcategory":"Engineering",
            "type":"Services"
        }
    ],
    "sg:phone":"+1   ",
    "sg:postcode":"06001",
    "sg:province":"CT",
    "wof:name":"David Huff",
    "wof:placetype":"venue"
},
  "geometry": {"coordinates":[-72.85503799999999,41.782847],"type":"Point"}
}