{
  "type": "Feature",
  "properties": {
    "iso:country":"US",
    "sg:address":"131 Tower Rd",
    "sg:city":"Brookfield",
    "sg:classifiers":[
        {
            "category":"Wholesale",
            "subcategory":"Wine & Distilled Alcoholic Beverages",
            "type":"Manufacturing & Wholesale Goods"
        },
        {
            "category":"Food & Beverages",
            "subcategory":"Liquor & Beverages",
            "type":"Retail Goods"
        }
    ],
    "sg:phone":"+1 203 775 1616",
    "sg:postcode":"06804",
    "sg:province":"CT",
    "sg:tags":[
        "m"
    ],
    "sg:website":"www.digrazia.com",
    "wof:name":"Di Grazia Vineyards & Winery",
    "wof:placetype":"venue"
},
  "geometry": {"coordinates":[-73.371421,41.469592],"type":"Point"}
}