{
  "type": "Feature",
  "properties": {
    "iso:country":"US",
    "sg:address":"6 Yew St",
    "sg:city":"Norwalk",
    "sg:classifiers":[
        {
            "category":"Personal",
            "type":"Services"
        }
    ],
    "sg:phone":"+1   ",
    "sg:postcode":"06850",
    "sg:province":"CT",
    "wof:name":"Robbins Locations Inc",
    "wof:placetype":"venue"
},
  "geometry": {"coordinates":[-73.439032,41.148697],"type":"Point"}
}