{
  "type": "Feature",
  "properties": {
    "iso:country":"US",
    "sg:address":"24 Bittersweet Ln",
    "sg:city":"Stonington",
    "sg:classifiers":[
        {
            "category":"Professional",
            "type":"Services"
        }
    ],
    "sg:phone":"+1 860 535 3417",
    "sg:postcode":"06371",
    "sg:province":"CT",
    "wof:name":"Alejandro M Monteiro",
    "wof:placetype":"venue"
},
  "geometry": {"coordinates":[-72.328778,41.312641],"type":"Point"}
}