{
  "type": "Feature",
  "properties": {
    "addr:full":"70 Old Town Hwy Bridgewater CT 06752",
    "addr:housenumber":"70",
    "addr:postcode":"06752",
    "addr:street":"Old Town Hwy Bridgewater Ct",
    "iso:country":"US",
    "sg:address":"70 Old Town Hwy",
    "sg:city":"Bridgewater",
    "sg:classifiers":[
        {
            "category":"Building & Trades",
            "subcategory":"Landscaping Services",
            "type":"Services"
        },
        {
            "category":"Manufacturing",
            "subcategory":"Paper Products",
            "type":"Manufacturing & Wholesale Goods"
        }
    ],
    "sg:phone":"+1 203 748 6059",
    "sg:postcode":"06752",
    "sg:province":"CT",
    "sg:tags":[
        "bamboo",
        "tree"
    ],
    "wof:name":"Wright Tree Service, Inc",
    "wof:placetype":"venue"
},
  "geometry": {"coordinates":[-73.343566,41.547352],"type":"Point"}
}