{
  "type": "Feature",
  "properties": {
    "iso:country":"US",
    "sg:address":"81 Washington St",
    "sg:city":"New London",
    "sg:classifiers":[
        {
            "category":"Organizations",
            "subcategory":"Community Association",
            "type":"Services"
        }
    ],
    "sg:phone":"+1   ",
    "sg:postcode":"06320",
    "sg:province":"CT",
    "sg:tags":[
        "membership",
        "cl"
    ],
    "wof:name":"Elks Club 360",
    "wof:placetype":"venue"
},
  "geometry": {"coordinates":[-72.098995,41.352847],"type":"Point"}
}