{
  "type": "Feature",
  "properties": {
    "addr:full":"2331 Stratford Ave Stratford CT 06615",
    "addr:housenumber":"2331",
    "addr:postcode":"06615",
    "addr:street":"Stratford Ave",
    "iso:country":"US",
    "sg:address":"2331 Stratford Ave",
    "sg:city":"Stratford",
    "sg:classifiers":[
        {
            "category":"Food & Beverages",
            "subcategory":"Groceries & Convenience Stores",
            "type":"Retail Goods"
        }
    ],
    "sg:phone":"+1 203 334 9734",
    "sg:postcode":"06615",
    "sg:province":"CT",
    "wof:name":"Michelles Grocery",
    "wof:placetype":"venue"
},
  "geometry": {"coordinates":[-73.149175,41.184192],"type":"Point"}
}