{
  "type": "Feature",
  "properties": {
    "addr:full":"66 E Haddam Rd Salem CT 06420",
    "addr:housenumber":"66",
    "addr:postcode":"06420",
    "addr:street":"E Haddam Rd",
    "iso:country":"US",
    "sg:address":"66 E Haddam Rd",
    "sg:city":"Salem",
    "sg:classifiers":[
        {
            "category":"Retail",
            "subcategory":"Portrait Studio",
            "type":"Services"
        }
    ],
    "sg:phone":"+1   ",
    "sg:postcode":"06420",
    "sg:province":"CT",
    "sg:tags":[
        "photo"
    ],
    "wof:name":"Creative Photography",
    "wof:placetype":"venue"
},
  "geometry": {"coordinates":[-72.26866099999999,41.473417],"type":"Point"}
}