{
  "type": "Feature",
  "properties": {
    "iso:country":"US",
    "sg:address":"266 Opening Hill Rd",
    "sg:city":"Branford",
    "sg:classifiers":[
        {
            "category":"Professional",
            "subcategory":"Management & Consulting",
            "type":"Services"
        }
    ],
    "sg:phone":"+1   ",
    "sg:postcode":"06405",
    "sg:province":"CT",
    "sg:tags":[
        "business"
    ],
    "wof:name":"Harmanchapman Consulting LLC",
    "wof:placetype":"venue"
},
  "geometry": {"coordinates":[-72.82810600000001,41.304921],"type":"Point"}
}