{
  "type": "Feature",
  "properties": {
    "iso:country":"US",
    "sg:address":"914 Arctic St",
    "sg:city":"Bridgeport",
    "sg:classifiers":[
        {
            "category":"Shopping",
            "subcategory":"Catalog Store",
            "type":"Retail Goods"
        }
    ],
    "sg:phone":"+1 203 333 8540",
    "sg:postcode":"06608",
    "sg:province":"CT",
    "sg:tags":[
        "mail",
        "order"
    ],
    "wof:name":"Magnum Duty Free Inc",
    "wof:placetype":"venue"
},
  "geometry": {"coordinates":[-73.17313300000001,41.1888],"type":"Point"}
}