{
  "type": "Feature",
  "properties": {
    "addr:full":"29 Water St Torrington CT 06790",
    "addr:housenumber":"29",
    "addr:postcode":"06790",
    "addr:street":"Water St",
    "iso:country":"US",
    "sg:address":"29 Water St",
    "sg:city":"Torrington",
    "sg:classifiers":[
        {
            "category":"Personal",
            "type":"Services"
        }
    ],
    "sg:phone":"+1   ",
    "sg:postcode":"06790",
    "sg:province":"CT",
    "wof:name":"SNET",
    "wof:placetype":"venue"
},
  "geometry": {"coordinates":[-73.12238499999999,41.801235],"type":"Point"}
}