{
  "type": "Feature",
  "properties": {
    "addr:full":"18 Deer Run Marlborough CT 06447",
    "addr:housenumber":"18",
    "addr:postcode":"06447",
    "addr:street":"Deer Run Marlborough Ct",
    "iso:country":"US",
    "sg:address":"18 Deer Run",
    "sg:city":"Marlborough",
    "sg:classifiers":[
        {
            "category":"Building & Trades",
            "subcategory":"Construction",
            "type":"Services"
        }
    ],
    "sg:phone":"+1 860 295 6475",
    "sg:postcode":"06447",
    "sg:province":"CT",
    "sg:tags":[
        "house"
    ],
    "wof:name":"Deart Associates Inc",
    "wof:placetype":"venue"
},
  "geometry": {"coordinates":[-72.467023,41.650344],"type":"Point"}
}