{
  "type": "Feature",
  "properties": {
    "addr:full":"16 Northwood Rd Monroe CT 06468",
    "addr:housenumber":"16",
    "addr:postcode":"06468",
    "addr:street":"Northwood Rd",
    "iso:country":"US",
    "sg:address":"16 Northwood Rd",
    "sg:city":"Monroe",
    "sg:classifiers":[
        {
            "category":"Wholesale",
            "subcategory":"Electrical",
            "type":"Manufacturing & Wholesale Goods"
        }
    ],
    "sg:phone":"+1 203 650 7990",
    "sg:postcode":"06468",
    "sg:province":"CT",
    "sg:tags":[
        "equipment"
    ],
    "wof:name":"Atco Sign & Lighting LLC",
    "wof:placetype":"venue"
},
  "geometry": {"coordinates":[-73.220828,41.313912],"type":"Point"}
}