{
  "type": "Feature",
  "properties": {
    "addr:full":"11 Grandview Ave Woodbridge CT 06514",
    "addr:housenumber":"11",
    "addr:postcode":"06514",
    "addr:street":"Grandview Ave",
    "iso:country":"US",
    "sg:address":"11 Grandview Ave",
    "sg:city":"Woodbridge",
    "sg:classifiers":[
        {
            "category":"Professional",
            "type":"Services"
        }
    ],
    "sg:phone":"+1 203 387 5109",
    "sg:postcode":"06514",
    "sg:province":"CT",
    "wof:name":"Henry Vicki L Schultz An",
    "wof:placetype":"venue"
},
  "geometry": {"coordinates":[-72.932216,41.354341],"type":"Point"}
}