{
  "type": "Feature",
  "properties": {
    "addr:full":"58 Robinson Blvd Ste A Orange CT 06477",
    "addr:housenumber":"58",
    "addr:postcode":"06477",
    "addr:street":"Robinson Blvd Ste A Orange Ct",
    "iso:country":"US",
    "sg:address":"58 Robinson Blvd Ste A",
    "sg:city":"Orange",
    "sg:classifiers":[
        {
            "category":"Transit Center",
            "subcategory":"Freight",
            "type":"Transportation"
        },
        {
            "category":"Professional",
            "subcategory":"Business Services",
            "type":"Services"
        },
        {
            "category":"Taxi",
            "type":"Transportation"
        },
        {
            "category":"Government",
            "subcategory":"Post Office",
            "type":"Public Place"
        }
    ],
    "sg:phone":"+1 203 799 8011",
    "sg:postcode":"06477",
    "sg:province":"CT",
    "sg:tags":[
        "cargo",
        "courier",
        "package",
        "express",
        "shipping",
        "air",
        "delivery",
        "mail",
        "forwarding"
    ],
    "sg:website":"http://www.martrac.com",
    "wof:name":"Ups",
    "wof:placetype":"venue"
},
  "geometry": {"coordinates":[-72.992189,41.247343],"type":"Point"}
}