{
  "type": "Feature",
  "properties": {
    "addr:full":"595 Merritt St Bridgeport CT 06606",
    "addr:housenumber":"595",
    "addr:postcode":"06606",
    "addr:street":"Merritt St",
    "iso:country":"US",
    "sg:address":"595 Merritt St",
    "sg:city":"Bridgeport",
    "sg:classifiers":[
        {
            "category":"Building & Trades",
            "subcategory":"Construction",
            "type":"Services"
        }
    ],
    "sg:phone":"+1 203 373 7471",
    "sg:postcode":"06606",
    "sg:province":"CT",
    "sg:tags":[
        "painter"
    ],
    "wof:name":"Eimar Painting",
    "wof:placetype":"venue"
},
  "geometry": {"coordinates":[-73.22198400000001,41.205887],"type":"Point"}
}