{
  "type": "Feature",
  "properties": {
    "addr:full":"66 Emmett St Bristol CT 06010",
    "addr:housenumber":"66",
    "addr:postcode":"06010",
    "addr:street":"Emmett St",
    "iso:country":"US",
    "sg:address":"66 Emmett St",
    "sg:city":"Bristol",
    "sg:classifiers":[
        {
            "category":"Autos & Motor Vehicles",
            "subcategory":"Auto Supplies",
            "type":"Retail Goods"
        }
    ],
    "sg:phone":"+1 860 582 9531",
    "sg:postcode":"06010",
    "sg:province":"CT",
    "wof:name":"Bristol Auto Parts Inc",
    "wof:placetype":"venue"
},
  "geometry": {"coordinates":[-72.912986,41.672084],"type":"Point"}
}