{
  "type": "Feature",
  "properties": {
    "addr:full":"831 Oakwood Rd Orange CT 06477",
    "addr:housenumber":"831",
    "addr:postcode":"06477",
    "addr:street":"Oakwood Rd",
    "iso:country":"US",
    "sg:address":"831 Oakwood Rd",
    "sg:city":"Orange",
    "sg:classifiers":[
        {
            "category":"Professional",
            "subcategory":"Management & Consulting",
            "type":"Services"
        }
    ],
    "sg:phone":"+1   ",
    "sg:postcode":"06477",
    "sg:province":"CT",
    "wof:name":"John L Schwab & Associates Inc",
    "wof:placetype":"venue"
},
  "geometry": {"coordinates":[-73.009765,41.299547],"type":"Point"}
}