{
  "type": "Feature",
  "properties": {
    "addr:full":"22 Guyer Rd Westport CT 06880",
    "addr:housenumber":"22",
    "addr:postcode":"06880",
    "addr:street":"Guyer Rd",
    "iso:country":"US",
    "sg:address":"22 Guyer Rd",
    "sg:city":"Westport",
    "sg:classifiers":[
        {
            "category":"Wholesale",
            "subcategory":"Electrical",
            "type":"Manufacturing & Wholesale Goods"
        }
    ],
    "sg:phone":"+1 203 454 4004",
    "sg:postcode":"06880",
    "sg:province":"CT",
    "sg:tags":[
        "equipment"
    ],
    "wof:name":"Lafferty Security & Telephone",
    "wof:placetype":"venue"
},
  "geometry": {"coordinates":[-73.349743,41.126848],"type":"Point"}
}