{
  "type": "Feature",
  "properties": {
    "iso:country":"US",
    "sg:address":"26 Lincoln Ave",
    "sg:city":"Greenwich",
    "sg:classifiers":[
        {
            "category":"Wholesale",
            "subcategory":"Construction Materials",
            "type":"Manufacturing & Wholesale Goods"
        }
    ],
    "sg:phone":"+1 203 661 0113",
    "sg:postcode":"06830",
    "sg:province":"CT",
    "wof:name":"Putnam Marble & Tile",
    "wof:placetype":"venue"
},
  "geometry": {"coordinates":[-73.62373100000001,41.029876],"type":"Point"}
}