{
  "type": "Feature",
  "properties": {
    "addr:full":"218 W Main St Norwich CT 06360",
    "addr:housenumber":"218",
    "addr:postcode":"06360",
    "addr:street":"W Main St",
    "iso:country":"US",
    "sg:address":"218 W Main St",
    "sg:city":"Norwich",
    "sg:classifiers":[
        {
            "category":"Food & Beverages",
            "subcategory":"Bakery",
            "type":"Retail Goods"
        }
    ],
    "sg:phone":"+1 860 887 5256",
    "sg:postcode":"06360",
    "sg:province":"CT",
    "wof:name":"Interstate Brands Corporation",
    "wof:placetype":"venue"
},
  "geometry": {"coordinates":[-72.086302,41.523299],"type":"Point"}
}