{
  "type": "Feature",
  "properties": {
    "addr:full":"2 Dallas Ave Bristol CT 06010",
    "addr:housenumber":"2",
    "addr:postcode":"06010",
    "addr:street":"Dallas Ave Bristol Ct",
    "iso:country":"US",
    "sg:address":"2 Dallas Ave",
    "sg:city":"Bristol",
    "sg:classifiers":[
        {
            "category":"Retail",
            "subcategory":"Car Wash",
            "type":"Services"
        }
    ],
    "sg:phone":"+1   ",
    "sg:postcode":"06010",
    "sg:province":"CT",
    "sg:tags":[
        "carwash"
    ],
    "wof:name":"Flag Car Wash",
    "wof:placetype":"venue"
},
  "geometry": {"coordinates":[-72.923141,41.688435],"type":"Point"}
}