{
  "type": "Feature",
  "properties": {
    "iso:country":"US",
    "sg:address":"114 East Ave",
    "sg:city":"Norwalk",
    "sg:classifiers":[
        {
            "category":"Professional",
            "subcategory":"Management & Consulting",
            "type":"Services"
        },
        {
            "category":"Building & Trades",
            "subcategory":"Construction",
            "type":"Services"
        }
    ],
    "sg:phone":"+1 203 857 4795",
    "sg:postcode":"06851",
    "sg:province":"CT",
    "sg:tags":[
        "general",
        "contractor"
    ],
    "sg:website":"www.kaisllc.com",
    "wof:name":"Kais Custom Builders LLC",
    "wof:placetype":"venue"
},
  "geometry": {"coordinates":[-73.407735,41.114163],"type":"Point"}
}