{
  "type": "Feature",
  "properties": {
    "addr:full":"292 Spielman Hwy Burlington CT 06013",
    "addr:housenumber":"292",
    "addr:postcode":"06013",
    "addr:street":"Spielman Hwy",
    "iso:country":"US",
    "sg:address":"292 Spielman Hwy",
    "sg:city":"Burlington",
    "sg:classifiers":[
        {
            "category":"Retail",
            "subcategory":"Photofinishing",
            "type":"Services"
        },
        {
            "category":"Shopping",
            "subcategory":"Pharmacy",
            "type":"Retail Goods"
        }
    ],
    "sg:phone":"+1 860 673 8006",
    "sg:postcode":"06013",
    "sg:province":"CT",
    "sg:tags":[
        "supply",
        "photo",
        "aid",
        "finishing",
        "drugstore",
        "first"
    ],
    "sg:website":"www.cvs.com",
    "wof:name":"Cvs Pharmacy",
    "wof:placetype":"venue"
},
  "geometry": {"coordinates":[-72.969829,41.770247],"type":"Point"}
}