{
  "type": "Feature",
  "properties": {
    "iso:country":"US",
    "sg:address":"111 S Main St",
    "sg:city":"Torrington",
    "sg:classifiers":[
        {
            "category":"Building & Trades",
            "subcategory":"Cleaning & Sanitation",
            "type":"Services"
        }
    ],
    "sg:phone":"+1   ",
    "sg:postcode":"06790",
    "sg:province":"CT",
    "sg:tags":[
        "maintenance"
    ],
    "wof:name":"Quality Building Maintenance",
    "wof:placetype":"venue"
},
  "geometry": {"coordinates":[-73.120893,41.797956],"type":"Point"}
}