{
  "type": "Feature",
  "properties": {
    "iso:country":"US",
    "sg:address":"3 Enterprise Dr",
    "sg:city":"Shelton",
    "sg:classifiers":[
        {
            "category":"Restaurant",
            "type":"Food & Drink"
        }
    ],
    "sg:phone":"+1 203 926 9796",
    "sg:postcode":"06484",
    "sg:province":"CT",
    "sg:tags":[
        "eating"
    ],
    "wof:name":"Corporate Caterers",
    "wof:placetype":"venue"
},
  "geometry": {"coordinates":[-73.12379199999999,41.277261],"type":"Point"}
}