{
  "type": "Feature",
  "properties": {
    "iso:country":"US",
    "sg:address":"527 Glenbrook Rd",
    "sg:city":"Stamford",
    "sg:classifiers":[
        {
            "category":"Food & Beverages",
            "subcategory":"Groceries & Convenience Stores",
            "type":"Retail Goods"
        }
    ],
    "sg:phone":"+1 203 323 2631",
    "sg:postcode":"06906",
    "sg:province":"CT",
    "wof:name":"Sunny Mart",
    "wof:placetype":"venue"
},
  "geometry": {"coordinates":[-73.520348,41.071504],"type":"Point"}
}