{
  "type": "Feature",
  "properties": {
    "iso:country":"US",
    "sg:address":"9 Berkeley Pl",
    "sg:city":"Newington",
    "sg:classifiers":[
        {
            "category":"Building & Trades",
            "subcategory":"Landscaping Services",
            "type":"Services"
        }
    ],
    "sg:phone":"+1 860 667 2467",
    "sg:postcode":"06111",
    "sg:province":"CT",
    "sg:tags":[
        "landscape",
        "contractor"
    ],
    "wof:name":"L & L Landscaping",
    "wof:placetype":"venue"
},
  "geometry": {"coordinates":[-72.746224,41.675461],"type":"Point"}
}