{
  "type": "Feature",
  "properties": {
    "addr:full":"4 Armstrong Rd Shelton CT 06484",
    "addr:housenumber":"4",
    "addr:postcode":"06484",
    "addr:street":"Armstrong Rd",
    "iso:country":"US",
    "sg:address":"4 Armstrong Rd",
    "sg:city":"Shelton",
    "sg:classifiers":[
        {
            "category":"Utilities",
            "subcategory":"Telephone",
            "type":"Services"
        }
    ],
    "sg:phone":"+1 203 926 9899",
    "sg:postcode":"06484",
    "sg:province":"CT",
    "sg:tags":[
        "company"
    ],
    "wof:name":"Frontier Communications",
    "wof:placetype":"venue"
},
  "geometry": {"coordinates":[-73.126881,41.265687],"type":"Point"}
}