{
  "type": "Feature",
  "properties": {
    "iso:country":"US",
    "sg:address":"495 Campbell Ave",
    "sg:city":"West Haven",
    "sg:classifiers":[
        {
            "category":"Shopping",
            "subcategory":"Clothing, Apparel, & Fashions",
            "type":"Retail Goods"
        }
    ],
    "sg:phone":"+1 203 934 0028",
    "sg:postcode":"06516",
    "sg:province":"CT",
    "wof:name":"Coppolas Tailoring",
    "wof:placetype":"venue"
},
  "geometry": {"coordinates":[-72.94945199999999,41.27146],"type":"Point"}
}