{
  "type": "Feature",
  "properties": {
    "addr:full":"78 Concord Cir Wethersfield CT 06109",
    "addr:housenumber":"78",
    "addr:postcode":"06109",
    "addr:street":"Concord Cir Wethersfield Ct",
    "iso:country":"US",
    "sg:address":"78 Concord Cir",
    "sg:city":"Wethersfield",
    "sg:classifiers":[
        {
            "category":"Retail",
            "subcategory":"Repair Shop",
            "type":"Services"
        }
    ],
    "sg:phone":"+1   ",
    "sg:postcode":"06109",
    "sg:province":"CT",
    "sg:tags":[
        "refrigeration",
        "household",
        "appliance"
    ],
    "wof:name":"Appliance Doctor Connecticut",
    "wof:placetype":"venue"
},
  "geometry": {"coordinates":[-72.693583,41.712018],"type":"Point"}
}