{
  "type": "Feature",
  "properties": {
    "iso:country":"US",
    "sg:address":"9 Burtis Ave",
    "sg:city":"New Canaan",
    "sg:classifiers":[
        {
            "category":"Real Estate",
            "subcategory":"Architect",
            "type":"Services"
        }
    ],
    "sg:phone":"+1   ",
    "sg:postcode":"06840",
    "sg:province":"NY",
    "sg:tags":[
        "architectural"
    ],
    "wof:name":"Robertson & Landers",
    "wof:placetype":"venue"
},
  "geometry": {"coordinates":[-73.491979,41.146822],"type":"Point"}
}