{
  "type": "Feature",
  "properties": {
    "addr:full":"38 N Main St Norwalk CT 06854",
    "addr:housenumber":"38",
    "addr:postcode":"06854",
    "addr:street":"N Main St",
    "iso:country":"US",
    "sg:address":"38 N Main St",
    "sg:city":"Norwalk",
    "sg:classifiers":[
        {
            "category":"Travel",
            "subcategory":"Travel Agent",
            "type":"Entertainment"
        }
    ],
    "sg:phone":"+1 203 853 6356",
    "sg:postcode":"06854",
    "sg:province":"CT",
    "sg:tags":[
        "agency"
    ],
    "wof:name":"Ampar Travel Agency",
    "wof:placetype":"venue"
},
  "geometry": {"coordinates":[-73.418887,41.099084],"type":"Point"}
}