{
  "type": "Feature",
  "properties": {
    "addr:full":"206 S Main St Hartford CT 06107",
    "addr:housenumber":"206",
    "addr:postcode":"06107",
    "addr:street":"S Main St",
    "iso:country":"US",
    "sg:address":"206 S Main St",
    "sg:city":"Hartford",
    "sg:classifiers":[
        {
            "category":"Wholesale",
            "subcategory":"Machinery & Supplies",
            "type":"Manufacturing & Wholesale Goods"
        }
    ],
    "sg:phone":"+1 860 521 0704",
    "sg:postcode":"06107",
    "sg:province":"CT",
    "sg:tags":[
        "equipment",
        "industrial"
    ],
    "wof:name":"Ultra Machine Inc",
    "wof:placetype":"venue"
},
  "geometry": {"coordinates":[-72.745501,41.747052],"type":"Point"}
}