{
  "type": "Feature",
  "properties": {
    "iso:country":"US",
    "sg:address":"31 Overlook Dr",
    "sg:city":"Wallingford",
    "sg:classifiers":[
        {
            "category":"Food & Beverages",
            "subcategory":"Groceries & Convenience Stores",
            "type":"Retail Goods"
        }
    ],
    "sg:phone":"+1 203 265 1135",
    "sg:postcode":"06492",
    "sg:province":"CT",
    "wof:name":"Bert's Deli",
    "wof:placetype":"venue"
},
  "geometry": {"coordinates":[-72.800318,41.430744],"type":"Point"}
}