{
  "type": "Feature",
  "properties": {
    "addr:full":"7 Midland Ave Port Chester CT 10573",
    "addr:housenumber":"7",
    "addr:postcode":"10573",
    "addr:street":"Midland Ave;Chester",
    "iso:country":"US",
    "sg:address":"7 Midland Ave",
    "sg:city":"Port Chester",
    "sg:classifiers":[
        {
            "category":"Retail",
            "subcategory":"Auto Repair",
            "type":"Services"
        }
    ],
    "sg:phone":"+1 914 939 3893",
    "sg:postcode":"10573",
    "sg:province":"CT",
    "sg:tags":[
        "repairing",
        "automobile"
    ],
    "wof:name":"CCM Auto Repairs Inc",
    "wof:placetype":"venue"
},
  "geometry": {"coordinates":[-73.665751,40.995728],"type":"Point"}
}