{
  "type": "Feature",
  "properties": {
    "iso:country":"US",
    "sg:address":"55 Church St",
    "sg:city":"New Haven",
    "sg:classifiers":[
        {
            "category":"Utilities",
            "subcategory":"Natural Gas",
            "type":"Services"
        }
    ],
    "sg:phone":"+1 203 786 6111",
    "sg:postcode":"06510",
    "sg:province":"CT",
    "sg:tags":[
        "company"
    ],
    "wof:name":"New Haven Gas Co Southern Ct",
    "wof:placetype":"venue"
},
  "geometry": {"coordinates":[-72.926349,41.305084],"type":"Point"}
}