{
  "type": "Feature",
  "properties": {
    "addr:full":"1310 Boston Post Rd Guilford CT 06437",
    "addr:housenumber":"1310",
    "addr:postcode":"06437",
    "addr:street":"Boston Post Rd",
    "iso:country":"US",
    "sg:address":"1310 Boston Post Rd",
    "sg:city":"Guilford",
    "sg:classifiers":[
        {
            "category":"Personal",
            "subcategory":"Beauty Salon",
            "type":"Services"
        }
    ],
    "sg:phone":"+1   ",
    "sg:postcode":"06437",
    "sg:province":"CT",
    "sg:tags":[
        "shop"
    ],
    "wof:name":"Oasis Nails",
    "wof:placetype":"venue"
},
  "geometry": {"coordinates":[-72.693377,41.288534],"type":"Point"}
}