{
  "type": "Feature",
  "properties": {
    "iso:country":"US",
    "sg:address":"653 Burnside Ave",
    "sg:city":"East Hartford",
    "sg:classifiers":[
        {
            "category":"Retail",
            "subcategory":"Car Wash",
            "type":"Services"
        }
    ],
    "sg:phone":"+1   ",
    "sg:postcode":"06108",
    "sg:province":"CT",
    "sg:tags":[
        "carwash"
    ],
    "wof:name":"Classy Detailing Service",
    "wof:placetype":"venue"
},
  "geometry": {"coordinates":[-72.61219,41.778896],"type":"Point"}
}