{
  "type": "Feature",
  "properties": {
    "addr:full":"8 Old Redding Rd West Redding CT 06896",
    "addr:housenumber":"8",
    "addr:postcode":"06896",
    "addr:street":"Old Redding Rd West",
    "iso:country":"US",
    "sg:address":"8 Old Redding Rd",
    "sg:city":"West Redding",
    "sg:classifiers":[
        {
            "category":"Insurance",
            "subcategory":"Insurance Agent",
            "type":"Services"
        }
    ],
    "sg:phone":"+1 203 938 0257",
    "sg:postcode":"06896",
    "sg:province":"CT",
    "wof:name":"Affordable Health Insurance",
    "wof:placetype":"venue"
},
  "geometry": {"coordinates":[-73.448457,41.287137],"type":"Point"}
}