{
  "type": "Feature",
  "properties": {
    "iso:country":"US",
    "sg:address":"51 Tuckahoe Rd",
    "sg:city":"Easton",
    "sg:classifiers":[
        {
            "category":"Professional",
            "subcategory":"Business Services",
            "type":"Services"
        }
    ],
    "sg:phone":"+1   ",
    "sg:postcode":"06612",
    "sg:province":"CT",
    "wof:name":"Tom Natt",
    "wof:placetype":"venue"
},
  "geometry": {"coordinates":[-73.24767199999999,41.238215],"type":"Point"}
}