{
  "type": "Feature",
  "properties": {
    "iso:country":"US",
    "sg:address":"1092 N Colony Rd",
    "sg:city":"Wallingford",
    "sg:classifiers":[
        {
            "category":"Shopping",
            "subcategory":"Department Store",
            "type":"Retail Goods"
        }
    ],
    "sg:phone":"+1   ",
    "sg:postcode":"06492",
    "sg:province":"CT",
    "sg:tags":[
        "dept",
        "center",
        "vision",
        "pharmacy"
    ],
    "wof:name":"Wal-Mart",
    "wof:placetype":"venue"
},
  "geometry": {"coordinates":[-72.809394,41.494624],"type":"Point"}
}