{
  "type": "Feature",
  "properties": {
    "iso:country":"US",
    "sg:address":"3241 Main St",
    "sg:city":"Stratford",
    "sg:classifiers":[
        {
            "category":"Professional",
            "subcategory":"Lawyer & Legal Services",
            "type":"Services"
        }
    ],
    "sg:phone":"+1 203 375 6219",
    "sg:postcode":"06614",
    "sg:province":"CT",
    "sg:tags":[
        "attorney"
    ],
    "wof:name":"Sullivan Laliberte & Auguer",
    "wof:placetype":"venue"
},
  "geometry": {"coordinates":[-73.131888,41.204712],"type":"Point"}
}