{
  "type": "Feature",
  "properties": {
    "addr:full":"113 Folly Brook Blvd Wethersfield CT 06109",
    "addr:housenumber":"113",
    "addr:postcode":"06109",
    "addr:street":"Folly Brook Blvd Wethersfield Ct",
    "iso:country":"US",
    "sg:address":"113 Folly Brook Blvd",
    "sg:city":"Wethersfield",
    "sg:classifiers":[
        {
            "category":"Social Services",
            "type":"Services"
        }
    ],
    "sg:phone":"+1   ",
    "sg:postcode":"06109",
    "sg:province":"CT",
    "wof:name":"Conneticut Nutmeg Chapter",
    "wof:placetype":"venue"
},
  "geometry": {"coordinates":[-72.679889,41.725251],"type":"Point"}
}