{
  "type": "Feature",
  "properties": {
    "iso:country":"US",
    "sg:address":"287 Old Winsted Rd",
    "sg:city":"Torrington",
    "sg:classifiers":[
        {
            "category":"Retail",
            "subcategory":"Auto Repair",
            "type":"Services"
        }
    ],
    "sg:phone":"+1   ",
    "sg:postcode":"06790",
    "sg:province":"CT",
    "sg:tags":[
        "engine",
        "automotive",
        "diesel",
        "an",
        "truck",
        "general"
    ],
    "wof:name":"Torrington Diesel Corporation",
    "wof:placetype":"venue"
},
  "geometry": {"coordinates":[-73.09933599999999,41.841899],"type":"Point"}
}