{
  "type": "Feature",
  "properties": {
    "addr:full":"35 Mason St Greenwich CT 06830",
    "addr:housenumber":"35",
    "addr:postcode":"06830",
    "addr:street":"Mason St Greenwich Ct",
    "iso:country":"US",
    "sg:address":"35 Mason St",
    "sg:city":"Greenwich",
    "sg:classifiers":[
        {
            "category":"Real Estate",
            "subcategory":"Real Estate Agent",
            "type":"Services"
        },
        {
            "category":"Real Estate",
            "subcategory":"Real Estate Operator",
            "type":"Services"
        }
    ],
    "sg:phone":"+1 203 629 5100",
    "sg:postcode":"06830",
    "sg:province":"CT",
    "sg:tags":[
        "owns",
        "shopping",
        "center",
        "operates"
    ],
    "wof:name":"Gladstone Development Corp",
    "wof:placetype":"venue"
},
  "geometry": {"coordinates":[-73.62524500000001,41.031553],"type":"Point"}
}