{
  "type": "Feature",
  "properties": {
    "iso:country":"US",
    "sg:address":"2549 Boston Post Rd",
    "sg:city":"Guilford",
    "sg:classifiers":[
        {
            "category":"Retail",
            "subcategory":"Auto Repair",
            "type":"Services"
        }
    ],
    "sg:phone":"+1   ",
    "sg:postcode":"06437",
    "sg:province":"CT",
    "sg:tags":[
        "general"
    ],
    "wof:name":"Carmaster Of Guilford",
    "wof:placetype":"venue"
},
  "geometry": {"coordinates":[-72.72673899999999,41.3092],"type":"Point"}
}