{
  "type": "Feature",
  "properties": {
    "iso:country":"US",
    "sg:address":"111 Main St",
    "sg:city":"Unionville",
    "sg:classifiers":[
        {
            "category":"Retail",
            "subcategory":"Funeral Services",
            "type":"Services"
        }
    ],
    "sg:phone":"+1 860 673 2601",
    "sg:postcode":"06085",
    "sg:province":"CT",
    "sg:tags":[
        "cemetery"
    ],
    "wof:name":"Ahern Funeral Home Inc",
    "wof:placetype":"venue"
},
  "geometry": {"coordinates":[-72.891296,41.761299],"type":"Point"}
}