{
  "type": "Feature",
  "properties": {
    "iso:country":"US",
    "sg:address":"104 Myrtle Ave",
    "sg:city":"Stamford",
    "sg:classifiers":[
        {
            "category":"Retail",
            "subcategory":"Funeral Services",
            "type":"Services"
        }
    ],
    "sg:phone":"+1   ",
    "sg:postcode":"06902",
    "sg:province":"CT",
    "wof:name":"Connecticut Crematory Corp",
    "wof:placetype":"venue"
},
  "geometry": {"coordinates":[-73.52546599999999,41.053087],"type":"Point"}
}