{
  "type": "Feature",
  "properties": {
    "iso:country":"US",
    "sg:address":"1379 Enfield St",
    "sg:city":"Enfield",
    "sg:classifiers":[
        {
            "category":"Health Services",
            "subcategory":"Doctor",
            "type":"Services"
        }
    ],
    "sg:phone":"+1   ",
    "sg:postcode":"06082",
    "sg:province":"CT",
    "sg:tags":[
        "therapy",
        "center",
        "physical"
    ],
    "wof:name":"Intergrated Rehab Services",
    "wof:placetype":"venue"
},
  "geometry": {"coordinates":[-72.59267199999999,41.969669],"type":"Point"}
}