{
  "type": "Feature",
  "properties": {
    "iso:country":"US",
    "sg:address":"1247 Highland Ave",
    "sg:city":"Cheshire",
    "sg:classifiers":[
        {
            "category":"Health Services",
            "subcategory":"Clinic",
            "type":"Services"
        }
    ],
    "sg:phone":"+1 203 271 1070",
    "sg:postcode":"06410",
    "sg:province":"CT",
    "sg:tags":[
        "agency",
        "welfare"
    ],
    "wof:name":"Highland Center",
    "wof:placetype":"venue"
},
  "geometry": {"coordinates":[-72.89478699999999,41.531673],"type":"Point"}
}