{
  "type": "Feature",
  "properties": {
    "addr:full":"185 Damascus Rd Branford CT 06405",
    "addr:housenumber":"185",
    "addr:postcode":"06405",
    "addr:street":"Damascus Rd",
    "iso:country":"US",
    "sg:address":"185 Damascus Rd",
    "sg:city":"Branford",
    "sg:classifiers":[
        {
            "category":"Education",
            "subcategory":"School",
            "type":"Public Place"
        }
    ],
    "sg:phone":"+1 203 488 8317",
    "sg:postcode":"06405",
    "sg:province":"CT",
    "sg:website":"www.branford.k12.ct.us",
    "wof:name":"Francis Walsh Intermediate",
    "wof:placetype":"venue"
},
  "geometry": {"coordinates":[-72.77940700000001,41.285682],"type":"Point"}
}