{
  "type": "Feature",
  "properties": {
    "addr:full":"28 Railroad Pl Westport CT 06880",
    "addr:housenumber":"28",
    "addr:postcode":"06880",
    "addr:street":"Railroad Pl",
    "iso:country":"US",
    "sg:address":"28 Railroad Pl",
    "sg:city":"Westport",
    "sg:classifiers":[
        {
            "category":"Retail",
            "subcategory":"Laundry & Dry Cleaning",
            "type":"Services"
        }
    ],
    "sg:phone":"+1 203 227 4969",
    "sg:postcode":"06880",
    "sg:province":"CT",
    "sg:tags":[
        "garment",
        "plant",
        "mi",
        "agent",
        "drycleaning"
    ],
    "wof:name":"Caruso Cleaners",
    "wof:placetype":"venue"
},
  "geometry": {"coordinates":[-73.371621,41.119083],"type":"Point"}
}