{
  "type": "Feature",
  "properties": {
    "addr:full":"260 Andrew St Stratford CT 06614",
    "addr:housenumber":"260",
    "addr:postcode":"06614",
    "addr:street":"Andrew St",
    "iso:country":"US",
    "sg:address":"260 Andrew St",
    "sg:city":"Stratford",
    "sg:classifiers":[
        {
            "category":"Building & Trades",
            "subcategory":"Landscaping Services",
            "type":"Services"
        }
    ],
    "sg:phone":"+1 203 375 9702",
    "sg:postcode":"06614",
    "sg:province":"CT",
    "wof:name":"J&J Landscaping",
    "wof:placetype":"venue"
},
  "geometry": {"coordinates":[-73.147412,41.207085],"type":"Point"}
}