{
  "type": "Feature",
  "properties": {
    "addr:full":"723 Wethersfield Ave Hartford CT 06114",
    "addr:housenumber":"723",
    "addr:postcode":"06114",
    "addr:street":"Wethersfield Ave;Ct",
    "iso:country":"US",
    "sg:address":"723 Wethersfield Ave",
    "sg:city":"Hartford",
    "sg:classifiers":[
        {
            "category":"Personal",
            "subcategory":"Shoe Repair & Shine",
            "type":"Services"
        }
    ],
    "sg:phone":"+1   ",
    "sg:postcode":"06114",
    "sg:province":"CT",
    "sg:tags":[
        "parlor",
        "shoes"
    ],
    "wof:name":"Marios Shoe Service",
    "wof:placetype":"venue"
},
  "geometry": {"coordinates":[-72.671002,41.736926],"type":"Point"}
}