{
  "type": "Feature",
  "properties": {
    "addr:full":"120 Long Ridge Rd Stamford CT 06902",
    "addr:housenumber":"120",
    "addr:postcode":"06902",
    "addr:street":"Long Ridge Rd",
    "iso:country":"US",
    "sg:address":"120 Long Ridge Rd",
    "sg:city":"Stamford",
    "sg:classifiers":[
        {
            "category":"Banks & Credit Unions",
            "subcategory":"Bank",
            "type":"Services"
        }
    ],
    "sg:phone":"+1 203 961 2338",
    "sg:postcode":"06902",
    "sg:province":"CT",
    "sg:tags":[
        "energy",
        "financing"
    ],
    "wof:name":"GE Energy Financial Services",
    "wof:placetype":"venue"
},
  "geometry": {"coordinates":[-73.552099,41.075559],"type":"Point"}
}