{
  "type": "Feature",
  "properties": {
    "addr:full":"131 Kent Rd New Milford CT 06776",
    "addr:housenumber":"131",
    "addr:postcode":"06776",
    "addr:street":"Kent Rd",
    "iso:country":"US",
    "sg:address":"131 Kent Rd",
    "sg:city":"New Milford",
    "sg:classifiers":[
        {
            "category":"Health Services",
            "subcategory":"Clinic",
            "type":"Services"
        }
    ],
    "sg:phone":"+1   ",
    "sg:postcode":"06776",
    "sg:province":"CT",
    "sg:tags":[
        "outpatient"
    ],
    "wof:name":"HealthSouth",
    "wof:placetype":"venue"
},
  "geometry": {"coordinates":[-73.42946499999999,41.581438],"type":"Point"}
}