{
  "type": "Feature",
  "properties": {
    "addr:full":"55 Flax Hill Rd Brookfield CT 06804",
    "addr:housenumber":"55",
    "addr:postcode":"06804",
    "addr:street":"Flax Hill Rd",
    "iso:country":"US",
    "sg:address":"55 Flax Hill Rd",
    "sg:city":"Brookfield",
    "sg:classifiers":[
        {
            "category":"Professional",
            "type":"Services"
        }
    ],
    "sg:phone":"+1 203 775 7818",
    "sg:postcode":"06804",
    "sg:province":"CT",
    "wof:name":"Michael J Weiss",
    "wof:placetype":"venue"
},
  "geometry": {"coordinates":[-73.423005,41.47639],"type":"Point"}
}