{
  "type": "Feature",
  "properties": {
    "iso:country":"US",
    "sg:address":"322 Foot Hills Rd",
    "sg:city":"Durham",
    "sg:classifiers":[
        {
            "category":"Personal",
            "subcategory":"Beauty Salon",
            "type":"Services"
        }
    ],
    "sg:phone":"+1   ",
    "sg:postcode":"06422",
    "sg:province":"CT",
    "sg:tags":[
        "shop"
    ],
    "wof:name":"Rochelle J Carabetta",
    "wof:placetype":"venue"
},
  "geometry": {"coordinates":[-72.630937,41.483444],"type":"Point"}
}