{
  "type": "Feature",
  "properties": {
    "iso:country":"US",
    "sg:address":"44 Old Ridgebury Rd",
    "sg:city":"Danbury",
    "sg:classifiers":[
        {
            "category":"Banks & Credit Unions",
            "subcategory":"Bank",
            "type":"Services"
        }
    ],
    "sg:phone":"+1 203 796 1000",
    "sg:postcode":"06810",
    "sg:province":"CT",
    "sg:tags":[
        "loan",
        "institution"
    ],
    "wof:name":"GE",
    "wof:placetype":"venue"
},
  "geometry": {"coordinates":[-73.515063,41.386615],"type":"Point"}
}