{
  "type": "Feature",
  "properties": {
    "addr:full":"1178 Purchase Brook Rd Southbury CT 06488",
    "addr:housenumber":"1178",
    "addr:postcode":"06488",
    "addr:street":"Purchase Brook Rd",
    "iso:country":"US",
    "sg:address":"1178 Purchase Brook Rd",
    "sg:city":"Southbury",
    "sg:classifiers":[
        {
            "category":"Professional",
            "type":"Services"
        }
    ],
    "sg:phone":"+1 203 267 3172",
    "sg:postcode":"06488",
    "sg:province":"CT",
    "wof:name":"Mulfit LLC",
    "wof:placetype":"venue"
},
  "geometry": {"coordinates":[-73.29319,41.485837],"type":"Point"}
}