{
  "type": "Feature",
  "properties": {
    "addr:full":"502 Westside Ln Torrington CT 06790",
    "addr:housenumber":"502",
    "addr:postcode":"06790",
    "addr:street":"Westside Ln",
    "iso:country":"US",
    "sg:address":"502 Westside Ln",
    "sg:city":"Torrington",
    "sg:classifiers":[
        {
            "category":"Building & Trades",
            "subcategory":"Construction",
            "type":"Services"
        }
    ],
    "sg:phone":"+1 860 489 0426",
    "sg:postcode":"06790",
    "sg:province":"CT",
    "sg:tags":[
        "house"
    ],
    "wof:name":"Design Build Co New Milford",
    "wof:placetype":"venue"
},
  "geometry": {"coordinates":[-73.16679000000001,41.805598],"type":"Point"}
}