{
  "type": "Feature",
  "properties": {
    "addr:full":"24 Hannahs Rd Stamford CT 06903",
    "addr:housenumber":"24",
    "addr:postcode":"06903",
    "addr:street":"Hannahs Rd",
    "iso:country":"US",
    "sg:address":"24 Hannahs Rd",
    "sg:city":"Stamford",
    "sg:classifiers":[
        {
            "category":"Professional",
            "subcategory":"Computer Services",
            "type":"Services"
        }
    ],
    "sg:phone":"+1   ",
    "sg:postcode":"06903",
    "sg:province":"CT",
    "sg:tags":[
        "consultant",
        "processing",
        "datum"
    ],
    "wof:name":"Summit Systems Inc",
    "wof:placetype":"venue"
},
  "geometry": {"coordinates":[-73.55269800000001,41.137097],"type":"Point"}
}