{
  "type": "Feature",
  "properties": {
    "iso:country":"US",
    "sg:address":"13 Jean Ave",
    "sg:city":"Norwalk",
    "sg:classifiers":[
        {
            "category":"Professional",
            "subcategory":"Management & Consulting",
            "type":"Services"
        }
    ],
    "sg:phone":"+1   ",
    "sg:postcode":"06850",
    "sg:province":"CT",
    "sg:tags":[
        "business"
    ],
    "wof:name":"Group VII Consulting LLC",
    "wof:placetype":"venue"
},
  "geometry": {"coordinates":[-73.449867,41.12937],"type":"Point"}
}