{
  "type": "Feature",
  "properties": {
    "addr:full":"10 Peach Orchard Rd Prospect CT 06712",
    "addr:housenumber":"10",
    "addr:postcode":"06712",
    "addr:street":"Peach Orchard Rd",
    "iso:country":"US",
    "sg:address":"10 Peach Orchard Rd",
    "sg:city":"Prospect",
    "sg:classifiers":[
        {
            "category":"Building & Trades",
            "subcategory":"Cleaning & Sanitation",
            "type":"Services"
        }
    ],
    "sg:phone":"+1   ",
    "sg:postcode":"06712",
    "sg:province":"CT",
    "sg:tags":[
        "maintenance"
    ],
    "wof:name":"Eddies Cleaning Service",
    "wof:placetype":"venue"
},
  "geometry": {"coordinates":[-73.014549,41.517678],"type":"Point"}
}