{
  "type": "Feature",
  "properties": {
    "iso:country":"US",
    "sg:address":"122 E Putnam Ave",
    "sg:city":"Greenwich",
    "sg:classifiers":[
        {
            "category":"Shopping",
            "subcategory":"Used Merchandise",
            "type":"Retail Goods"
        }
    ],
    "sg:phone":"+1 203 618 0009",
    "sg:postcode":"06830",
    "sg:province":"CT",
    "sg:tags":[
        "sector",
        "regulation",
        "commercial"
    ],
    "wof:name":"B and D Johnson Antiques LLC",
    "wof:placetype":"venue"
},
  "geometry": {"coordinates":[-73.62317400000001,41.034519],"type":"Point"}
}