{
  "type": "Feature",
  "properties": {
    "iso:country":"US",
    "sg:address":"578 Post Rd E",
    "sg:city":"Westport",
    "sg:classifiers":[
        {
            "category":"Building & Trades",
            "subcategory":"Cleaning & Sanitation",
            "type":"Services"
        }
    ],
    "sg:phone":"+1   ",
    "sg:postcode":"06880",
    "sg:province":"CT",
    "sg:tags":[
        "maintenance"
    ],
    "wof:name":"Ace Maintenance",
    "wof:placetype":"venue"
},
  "geometry": {"coordinates":[-73.342718,41.137898],"type":"Point"}
}