{
  "type": "Feature",
  "properties": {
    "iso:country":"US",
    "sg:address":"257 Mill St",
    "sg:city":"Greenwich",
    "sg:classifiers":[
        {
            "category":"Retail",
            "subcategory":"Animal Services",
            "type":"Services"
        }
    ],
    "sg:phone":"+1 203 531 5677",
    "sg:postcode":"06830",
    "sg:province":"CT",
    "wof:name":"Professional Dog Grooming",
    "wof:placetype":"venue"
},
  "geometry": {"coordinates":[-73.656099,41.003057],"type":"Point"}
}