{
  "type": "Feature",
  "properties": {
    "iso:country":"US",
    "sg:address":"74 Batterson Park Rd",
    "sg:city":"Farmington",
    "sg:classifiers":[
        {
            "category":"Insurance",
            "subcategory":"Insurance Agent",
            "type":"Services"
        }
    ],
    "sg:phone":"+1 860 676 3030",
    "sg:postcode":"06032",
    "sg:province":"CT",
    "sg:tags":[
        "life"
    ],
    "wof:name":"Herz Financial Group",
    "wof:placetype":"venue"
},
  "geometry": {"coordinates":[-72.792278,41.714551],"type":"Point"}
}