{
  "type": "Feature",
  "properties": {
    "iso:country":"US",
    "sg:address":"145 Bank St",
    "sg:city":"Waterbury",
    "sg:classifiers":[
        {
            "category":"Banks & Credit Unions",
            "subcategory":"Financial Services",
            "type":"Services"
        }
    ],
    "sg:phone":"+1 203 578 2476",
    "sg:postcode":"06702",
    "sg:province":"CT",
    "sg:tags":[
        "company",
        "holding"
    ],
    "wof:name":"Webster Financial Corp",
    "wof:placetype":"venue"
},
  "geometry": {"coordinates":[-73.04090600000001,41.554345],"type":"Point"}
}