{
  "type": "Feature",
  "properties": {
    "iso:country":"US",
    "sg:address":"207 Asylum St",
    "sg:city":"Bridgeport",
    "sg:classifiers":[
        {
            "category":"Organizations",
            "subcategory":"Religious Organization",
            "type":"Services"
        }
    ],
    "sg:phone":"+1   ",
    "sg:postcode":"06610",
    "sg:province":"CT",
    "wof:name":"New Testament Church Of God",
    "wof:placetype":"venue"
},
  "geometry": {"coordinates":[-73.1741,41.200002],"type":"Point"}
}