{
  "type": "Feature",
  "properties": {
    "iso:country":"US",
    "sg:address":"519 Carmel Hill Rd N",
    "sg:city":"Bethlehem",
    "sg:classifiers":[
        {
            "category":"Professional",
            "subcategory":"Lawyer & Legal Services",
            "type":"Services"
        }
    ],
    "sg:phone":"+1   ",
    "sg:postcode":"06751",
    "sg:province":"CT",
    "wof:name":"Rush Thomas P Attorney At Law",
    "wof:placetype":"venue"
},
  "geometry": {"coordinates":[-73.25339,41.649264],"type":"Point"}
}