{
  "type": "Feature",
  "properties": {
    "addr:full":"144 Water St Norwalk CT 06854",
    "addr:housenumber":"144",
    "addr:postcode":"06854",
    "addr:street":"Water St",
    "iso:country":"US",
    "sg:address":"144 Water St",
    "sg:city":"Norwalk",
    "sg:classifiers":[
        {
            "category":"Recreation",
            "subcategory":"Marina",
            "type":"Entertainment"
        },
        {
            "category":"Manufacturing",
            "subcategory":"Watercraft",
            "type":"Manufacturing & Wholesale Goods"
        }
    ],
    "sg:phone":"+1 203 866 1690",
    "sg:postcode":"06854",
    "sg:province":"CT",
    "sg:tags":[
        "repairing",
        "boat"
    ],
    "wof:name":"New England Fiberglass Repair",
    "wof:placetype":"venue"
},
  "geometry": {"coordinates":[-73.415567,41.095282],"type":"Point"}
}