{
  "type": "Feature",
  "properties": {
    "addr:full":"85 Cross St Fairfield CT 06484",
    "addr:housenumber":"85",
    "addr:postcode":"06484",
    "addr:street":"Cross St",
    "iso:country":"US",
    "sg:address":"85 Cross St",
    "sg:city":"Fairfield",
    "sg:classifiers":[
        {
            "category":"Professional",
            "subcategory":"Employment Agencies",
            "type":"Services"
        }
    ],
    "sg:phone":"+1   ",
    "sg:postcode":"06484",
    "sg:province":"CT",
    "sg:tags":[
        "help",
        "supply"
    ],
    "wof:name":"Legal Temps",
    "wof:placetype":"venue"
},
  "geometry": {"coordinates":[-73.09398,41.31186],"type":"Point"}
}