{
  "type": "Feature",
  "properties": {
    "addr:full":"1587 Capitol Ave Bridgeport CT 06604",
    "addr:housenumber":"1587",
    "addr:postcode":"06604",
    "addr:street":"Capitol Ave",
    "iso:country":"US",
    "sg:address":"1587 Capitol Ave",
    "sg:city":"Bridgeport",
    "sg:classifiers":[
        {
            "category":"Shopping",
            "subcategory":"Discount & Variety Stores",
            "type":"Retail Goods"
        }
    ],
    "sg:phone":"+1 203 336 4722",
    "sg:postcode":"06604",
    "sg:province":"CT",
    "wof:name":"Capitol News & Variety",
    "wof:placetype":"venue"
},
  "geometry": {"coordinates":[-73.216865,41.188808],"type":"Point"}
}