{
  "type": "Feature",
  "properties": {
    "iso:country":"US",
    "sg:address":"218 Huntington Rd",
    "sg:city":"Bridgeport",
    "sg:classifiers":[
        {
            "category":"Professional",
            "subcategory":"Computer Services",
            "type":"Services"
        }
    ],
    "sg:phone":"+1 203 332 1524",
    "sg:postcode":"06608",
    "sg:province":"CT",
    "sg:tags":[
        "organization",
        "religious",
        "related",
        "consultant"
    ],
    "wof:name":"Associated Computer Consultant",
    "wof:placetype":"venue"
},
  "geometry": {"coordinates":[-73.18494099999999,41.196245],"type":"Point"}
}