{
  "type": "Feature",
  "properties": {
    "iso:country":"US",
    "sg:address":"7 Railroad Ave",
    "sg:city":"Beacon Falls",
    "sg:classifiers":[
        {
            "category":"Shopping",
            "type":"Retail Goods"
        }
    ],
    "sg:phone":"+1 203 729 2846",
    "sg:postcode":"06403",
    "sg:province":"CT",
    "sg:tags":[
        "material",
        "artist",
        "supply"
    ],
    "wof:name":"Stover Graphics",
    "wof:placetype":"venue"
},
  "geometry": {"coordinates":[-73.06426,41.44235],"type":"Point"}
}