{
  "type": "Feature",
  "properties": {
    "iso:country":"US",
    "sg:address":"879 Litchfield Rd",
    "sg:city":"Norfolk",
    "sg:classifiers":[
        {
            "category":"Manufacturing",
            "subcategory":"Building Materials",
            "type":"Manufacturing & Wholesale Goods"
        }
    ],
    "sg:phone":"+1 860 542 5506",
    "sg:postcode":"06058",
    "sg:province":"CT",
    "sg:tags":[
        "mfg"
    ],
    "wof:name":"White Hollow Woodworking LLC",
    "wof:placetype":"venue"
},
  "geometry": {"coordinates":[-73.208764,41.931878],"type":"Point"}
}