{
  "type": "Feature",
  "properties": {
    "addr:full":"418 Stone Rd Burlington CT 06013",
    "addr:housenumber":"418",
    "addr:postcode":"06013",
    "addr:street":"Stone Rd",
    "iso:country":"US",
    "sg:address":"418 Stone Rd",
    "sg:city":"Burlington",
    "sg:classifiers":[
        {
            "category":"Real Estate",
            "subcategory":"Real Estate Operator",
            "type":"Services"
        }
    ],
    "sg:phone":"+1 860 673 9610",
    "sg:postcode":"06013",
    "sg:province":"CT",
    "sg:tags":[
        "building",
        "nonresidential"
    ],
    "wof:name":"Bencivengo Properties 2 LLC",
    "wof:placetype":"venue"
},
  "geometry": {"coordinates":[-72.93647799999999,41.756794],"type":"Point"}
}