{
  "type": "Feature",
  "properties": {
    "iso:country":"US",
    "sg:address":"60 Brush Hill Rd",
    "sg:city":"Old Lyme",
    "sg:classifiers":[
        {
            "category":"Professional",
            "subcategory":"Management & Consulting",
            "type":"Services"
        }
    ],
    "sg:phone":"+1   ",
    "sg:postcode":"06371",
    "sg:province":"CT",
    "wof:name":"Lyme Energy Advisors LLC",
    "wof:placetype":"venue"
},
  "geometry": {"coordinates":[-72.39097099999999,41.417945],"type":"Point"}
}