{
  "type": "Feature",
  "properties": {
    "iso:country":"US",
    "sg:address":"35 New Bridge Rd",
    "sg:city":"New Milford",
    "sg:classifiers":[
        {
            "category":"Arts & Performance",
            "subcategory":"Theater",
            "type":"Entertainment"
        }
    ],
    "sg:phone":"+1   ",
    "sg:postcode":"06776",
    "sg:province":"CT",
    "sg:tags":[
        "theatrical"
    ],
    "wof:name":"McLain Assoc",
    "wof:placetype":"venue"
},
  "geometry": {"coordinates":[-73.398707,41.512376],"type":"Point"}
}