{
  "type": "Feature",
  "properties": {
    "addr:full":"9 Stott Ave Norwich CT 06360",
    "addr:housenumber":"9",
    "addr:postcode":"06360",
    "addr:street":"Stott Ave",
    "iso:country":"US",
    "sg:address":"9 Stott Ave",
    "sg:city":"Norwich",
    "sg:classifiers":[
        {
            "category":"Recreation",
            "type":"Entertainment"
        }
    ],
    "sg:phone":"+1   ",
    "sg:postcode":"06360",
    "sg:province":"CT",
    "wof:name":"Stotts At Bat",
    "wof:placetype":"venue"
},
  "geometry": {"coordinates":[-72.111507,41.57812],"type":"Point"}
}