{
  "type": "Feature",
  "properties": {
    "addr:full":"755 Capitol Ave Hartford CT 06106",
    "addr:housenumber":"755",
    "addr:postcode":"06106",
    "addr:street":"Capitol Ave;Ct",
    "iso:country":"US",
    "sg:address":"755 Capitol Ave",
    "sg:city":"Hartford",
    "sg:classifiers":[
        {
            "category":"Retail",
            "subcategory":"Auto Rental",
            "type":"Services"
        }
    ],
    "sg:phone":"+1 860 527 5251",
    "sg:postcode":"06106",
    "sg:province":"CT",
    "sg:tags":[
        "renting",
        "truck",
        "leasing"
    ],
    "wof:name":"U-Haul Co",
    "wof:placetype":"venue"
},
  "geometry": {"coordinates":[-72.702709,41.76095],"type":"Point"}
}