{
  "type": "Feature",
  "properties": {
    "iso:country":"US",
    "sg:address":"141 Kent Rd",
    "sg:city":"Cornwall Bridge",
    "sg:classifiers":[
        {
            "category":"Building & Trades",
            "subcategory":"Landscaping Services",
            "type":"Services"
        }
    ],
    "sg:phone":"+1 860 868 7456",
    "sg:postcode":"06754",
    "sg:province":"CT",
    "sg:tags":[
        "landscape"
    ],
    "wof:name":"Nicholas and Son LLC",
    "wof:placetype":"venue"
},
  "geometry": {"coordinates":[-73.37325,41.743759],"type":"Point"}
}