{
  "type": "Feature",
  "properties": {
    "iso:country":"US",
    "sg:address":"154 Minor St",
    "sg:city":"New Haven",
    "sg:classifiers":[
        {
            "category":"Social Services",
            "type":"Services"
        }
    ],
    "sg:phone":"+1   ",
    "sg:postcode":"06519",
    "sg:province":"CT",
    "wof:name":"Latino Youth & Development",
    "wof:placetype":"venue"
},
  "geometry": {"coordinates":[-72.93250500000001,41.298871],"type":"Point"}
}