{
  "type": "Feature",
  "properties": {
    "addr:full":"87 S Broad St Meriden CT 06450",
    "addr:housenumber":"87",
    "addr:postcode":"06450",
    "addr:street":"S Broad St",
    "iso:country":"US",
    "sg:address":"87 S Broad St",
    "sg:city":"Meriden",
    "sg:classifiers":[
        {
            "category":"Autos & Motor Vehicles",
            "subcategory":"Automobile Sales",
            "type":"Retail Goods"
        }
    ],
    "sg:phone":"+1 203 694 1020",
    "sg:postcode":"06450",
    "sg:province":"CT",
    "sg:tags":[
        "car",
        "dealer"
    ],
    "sg:website":"www.robertsdodge.com",
    "wof:name":"Robert's Chrysler Dodge",
    "wof:placetype":"venue"
},
  "geometry": {"coordinates":[-72.80272100000001,41.519563],"type":"Point"}
}