{
  "type": "Feature",
  "properties": {
    "iso:country":"US",
    "sg:address":"451 River Rd",
    "sg:city":"Willington",
    "sg:classifiers":[
        {
            "category":"Retail",
            "subcategory":"Veterinary Services",
            "type":"Services"
        }
    ],
    "sg:phone":"+1 860 429 5683",
    "sg:postcode":"06279",
    "sg:province":"CT",
    "sg:tags":[
        "veterinarian"
    ],
    "sg:website":"http://www.lovevetcenter.com",
    "wof:name":"Love Veterinary Center LLC",
    "wof:placetype":"venue"
},
  "geometry": {"coordinates":[-72.289444,41.89459],"type":"Point"}
}