{
  "type": "Feature",
  "properties": {
    "addr:full":"9 Chestnut Dr West Suffield CT 06093",
    "addr:housenumber":"9",
    "addr:postcode":"06093",
    "addr:street":"Chestnut Dr West",
    "iso:country":"US",
    "sg:address":"9 Chestnut Dr",
    "sg:city":"West Suffield",
    "sg:classifiers":[
        {
            "category":"Wholesale",
            "subcategory":"Machinery & Supplies",
            "type":"Manufacturing & Wholesale Goods"
        }
    ],
    "sg:phone":"+1 860 668 1447",
    "sg:postcode":"06093",
    "sg:province":"CT",
    "sg:tags":[
        "machine",
        "tool",
        "dist"
    ],
    "wof:name":"Morello & Company Machine Tool",
    "wof:placetype":"venue"
},
  "geometry": {"coordinates":[-72.752656,42.02285],"type":"Point"}
}