{
  "type": "Feature",
  "properties": {
    "iso:country":"US",
    "sg:address":"12 Paul St",
    "sg:city":"Bethel",
    "sg:classifiers":[
        {
            "category":"Wholesale",
            "subcategory":"Hardware",
            "type":"Manufacturing & Wholesale Goods"
        },
        {
            "category":"Home & Garden",
            "subcategory":"Garden Supply",
            "type":"Retail Goods"
        },
        {
            "category":"Building & Trades",
            "subcategory":"Construction",
            "type":"Services"
        }
    ],
    "sg:phone":"+1 203 743 7944",
    "sg:postcode":"06801",
    "sg:province":"CT",
    "sg:tags":[
        "excavation",
        "topsoil",
        "hardware-builders",
        "contractor"
    ],
    "wof:name":"Datin Brothers Inc",
    "wof:placetype":"venue"
},
  "geometry": {"coordinates":[-73.423271,41.37806],"type":"Point"}
}