{
  "type": "Feature",
  "properties": {
    "addr:full":"57 Eckford Ave Westbrook CT 06498",
    "addr:housenumber":"57",
    "addr:postcode":"06498",
    "addr:street":"Eckford Ave",
    "iso:country":"US",
    "sg:address":"57 Eckford Ave",
    "sg:city":"Westbrook",
    "sg:classifiers":[
        {
            "category":"Professional",
            "subcategory":"Business Services",
            "type":"Services"
        }
    ],
    "sg:phone":"+1   ",
    "sg:postcode":"06498",
    "sg:province":"CT",
    "wof:name":"Total Design Source Llc",
    "wof:placetype":"venue"
},
  "geometry": {"coordinates":[-72.461445,41.279787],"type":"Point"}
}