{
  "type": "Feature",
  "properties": {
    "addr:full":"127 E Main St Meriden CT 06450",
    "addr:housenumber":"127",
    "addr:postcode":"06450",
    "addr:street":"E Main St",
    "iso:country":"US",
    "sg:address":"127 E Main St",
    "sg:city":"Meriden",
    "sg:classifiers":[
        {
            "category":"Organizations",
            "subcategory":"Religious Organization",
            "type":"Services"
        }
    ],
    "sg:phone":"+1 203 235 2581",
    "sg:postcode":"06450",
    "sg:province":"CT",
    "sg:tags":[
        "synagogue"
    ],
    "wof:name":"Temple B'Nai Abraham",
    "wof:placetype":"venue"
},
  "geometry": {"coordinates":[-72.798641,41.5367],"type":"Point"}
}