{
  "type": "Feature",
  "properties": {
    "addr:full":"22 N Bear Hill Rd Chaplin CT 06235",
    "addr:housenumber":"22",
    "addr:postcode":"06235",
    "addr:street":"N Bear Hill Rd Chaplin Ct",
    "iso:country":"US",
    "sg:address":"22 N Bear Hill Rd",
    "sg:city":"Chaplin",
    "sg:phone":"+1 860 455 0462",
    "sg:postcode":"06235",
    "sg:province":"CT",
    "sg:tags":[
        "farm",
        "field",
        "crop"
    ],
    "wof:name":"Ireland Engineering",
    "wof:placetype":"venue"
},
  "geometry": {"coordinates":[-72.118574,41.801291],"type":"Point"}
}