{
  "type": "Feature",
  "properties": {
    "addr:full":"204 Silver Creek Ln Norwalk CT 06850",
    "addr:housenumber":"204",
    "addr:postcode":"06850",
    "addr:street":"Silver Creek Ln",
    "iso:country":"US",
    "sg:address":"204 Silver Creek Ln",
    "sg:city":"Norwalk",
    "sg:classifiers":[
        {
            "category":"Professional",
            "subcategory":"Advertising",
            "type":"Services"
        }
    ],
    "sg:phone":"+1   ",
    "sg:postcode":"06850",
    "sg:province":"CT",
    "sg:tags":[
        "agency"
    ],
    "wof:name":"Communications Partnership",
    "wof:placetype":"venue"
},
  "geometry": {"coordinates":[-73.435322,41.136199],"type":"Point"}
}