{
  "type": "Feature",
  "properties": {
    "iso:country":"US",
    "sg:address":"14 Hayes Rd",
    "sg:city":"East Hampton",
    "sg:classifiers":[
        {
            "category":"Insurance",
            "subcategory":"Insurance Agent",
            "type":"Services"
        }
    ],
    "sg:phone":"+1 860 267 0182",
    "sg:postcode":"06424",
    "sg:province":"CT",
    "wof:name":"Debt Free Solutions",
    "wof:placetype":"venue"
},
  "geometry": {"coordinates":[-72.50855,41.572539],"type":"Point"}
}