{
  "type": "Feature",
  "properties": {
    "iso:country":"US",
    "sg:address":"7 Greenwich Office Park",
    "sg:city":"Greenwich",
    "sg:classifiers":[
        {
            "category":"Banks & Credit Unions",
            "subcategory":"Investment Brokerage",
            "type":"Services"
        }
    ],
    "sg:phone":"+1 203 861 2512",
    "sg:postcode":"06831",
    "sg:province":"CT",
    "sg:tags":[
        "trust"
    ],
    "wof:name":"Carrington Mortgage Loan Trust, Series 2006-Nc3",
    "wof:placetype":"venue"
},
  "geometry": {"coordinates":[-73.646918,41.020051],"type":"Point"}
}