{
  "type": "Feature",
  "properties": {
    "iso:country":"US",
    "sg:address":"600 North Ave",
    "sg:city":"Bridgeport",
    "sg:classifiers":[
        {
            "category":"Food & Beverages",
            "subcategory":"Meat & Fish",
            "type":"Retail Goods"
        }
    ],
    "sg:phone":"+1 203 336 3474",
    "sg:postcode":"06606",
    "sg:province":"CT",
    "sg:tags":[
        "seafood"
    ],
    "wof:name":"Mc Kenzie Fish & Variety",
    "wof:placetype":"venue"
},
  "geometry": {"coordinates":[-73.193746,41.196324],"type":"Point"}
}