{
  "type": "Feature",
  "properties": {
    "addr:full":"141 North St Danielson CT 06239",
    "addr:housenumber":"141",
    "addr:postcode":"06239",
    "addr:street":"North St",
    "iso:country":"US",
    "sg:address":"141 North St",
    "sg:city":"Danielson",
    "sg:classifiers":[
        {
            "category":"Farming",
            "subcategory":"Nursery",
            "type":"Manufacturing & Wholesale Goods"
        }
    ],
    "sg:phone":"+1 860 774 8038",
    "sg:postcode":"06239",
    "sg:province":"CT",
    "sg:tags":[
        "ornamental",
        "supply"
    ],
    "wof:name":"Logees Greenhouses Ltd",
    "wof:placetype":"venue"
},
  "geometry": {"coordinates":[-71.883115,41.815968],"type":"Point"}
}