{
  "type": "Feature",
  "properties": {
    "iso:country":"US",
    "sg:address":"10 Old County Rd",
    "sg:city":"Haddam",
    "sg:classifiers":[
        {
            "category":"Professional",
            "type":"Services"
        }
    ],
    "sg:phone":"+1   ",
    "sg:postcode":"06438",
    "sg:province":"CT",
    "wof:name":"Fine Art Digital Services LLC",
    "wof:placetype":"venue"
},
  "geometry": {"coordinates":[-72.466712,41.440678],"type":"Point"}
}