{
  "type": "Feature",
  "properties": {
    "addr:full":"11 Ledgebrook Dr Mansfield Center CT 06250",
    "addr:housenumber":"11",
    "addr:postcode":"06250",
    "addr:street":"Ledgebrook Dr",
    "iso:country":"US",
    "sg:address":"11 Ledgebrook Dr",
    "sg:city":"Mansfield Center",
    "sg:classifiers":[
        {
            "category":"Professional",
            "subcategory":"Lawyer & Legal Services",
            "type":"Services"
        }
    ],
    "sg:phone":"+1 860 456 7790",
    "sg:postcode":"06250",
    "sg:province":"CT",
    "sg:website":"www.medicareadvocacy.org",
    "wof:name":"Hulin Judith Stein Atty",
    "wof:placetype":"venue"
},
  "geometry": {"coordinates":[-72.203796,41.733799],"type":"Point"}
}