{
  "type": "Feature",
  "properties": {
    "iso:country":"US",
    "sg:address":"45 Quinnipiac Ave",
    "sg:city":"North Haven",
    "sg:classifiers":[
        {
            "category":"Personal",
            "subcategory":"Beauty Salon",
            "type":"Services"
        }
    ],
    "sg:phone":"+1 203 782 1111",
    "sg:postcode":"06473",
    "sg:province":"CT",
    "wof:name":"New Trend Hair Designs",
    "wof:placetype":"venue"
},
  "geometry": {"coordinates":[-72.86377299999999,41.339363],"type":"Point"}
}