{
  "type": "Feature",
  "properties": {
    "addr:full":"158 Park Pl Cheshire CT 06410",
    "addr:housenumber":"158",
    "addr:postcode":"06410",
    "addr:street":"Park Pl",
    "iso:country":"US",
    "sg:address":"158 Park Pl",
    "sg:city":"Cheshire",
    "sg:classifiers":[
        {
            "category":"Restaurant",
            "type":"Food & Drink"
        }
    ],
    "sg:phone":"+1 203 439 0621",
    "sg:postcode":"06410",
    "sg:province":"CT",
    "wof:name":"Dinner By Design",
    "wof:placetype":"venue"
},
  "geometry": {"coordinates":[-72.90576,41.509275],"type":"Point"}
}