{
  "type": "Feature",
  "properties": {
    "addr:full":"710 Bantam Rd Bantam CT 06750",
    "addr:housenumber":"710",
    "addr:postcode":"06750",
    "addr:street":"Bantam Rd Bantam Ct",
    "iso:country":"US",
    "sg:address":"710 Bantam Rd",
    "sg:city":"Bantam",
    "sg:classifiers":[
        {
            "category":"Insurance",
            "subcategory":"Insurance Agent",
            "type":"Services"
        }
    ],
    "sg:phone":"+1 860 567 4060",
    "sg:postcode":"06750",
    "sg:province":"CT",
    "wof:name":"Farm Family Casualty Ins Co",
    "wof:placetype":"venue"
},
  "geometry": {"coordinates":[-73.23171000000001,41.725463],"type":"Point"}
}