{
  "type": "Feature",
  "properties": {
    "iso:country":"US",
    "sg:address":"50 Birchwood Rd",
    "sg:city":"Seymour",
    "sg:classifiers":[
        {
            "category":"Wholesale",
            "subcategory":"Toys & Hobbies",
            "type":"Manufacturing & Wholesale Goods"
        }
    ],
    "sg:phone":"+1 203 888 5834",
    "sg:postcode":"06483",
    "sg:province":"CT",
    "wof:name":"D J Vending Company",
    "wof:placetype":"venue"
},
  "geometry": {"coordinates":[-73.045096,41.408431],"type":"Point"}
}