{
  "type": "Feature",
  "properties": {
    "addr:full":"2015 W Main St Stamford CT 06902",
    "addr:housenumber":"2015",
    "addr:postcode":"06902",
    "addr:street":"W Main St",
    "iso:country":"US",
    "sg:address":"2015 W Main St",
    "sg:city":"Stamford",
    "sg:classifiers":[
        {
            "category":"Education",
            "subcategory":"Special Training",
            "type":"Public Place"
        }
    ],
    "sg:phone":"+1 203 359 9555",
    "sg:postcode":"06902",
    "sg:province":"CT",
    "sg:tags":[
        "tutoring"
    ],
    "wof:name":"Educational Diagnostic Svc",
    "wof:placetype":"venue"
},
  "geometry": {"coordinates":[-73.563203,41.04892],"type":"Point"}
}