{
  "type": "Feature",
  "properties": {
    "addr:full":"9 Nash Pl Norwalk CT 06854",
    "addr:housenumber":"9",
    "addr:postcode":"06854",
    "addr:street":"Nash Pl",
    "iso:country":"US",
    "sg:address":"9 Nash Pl",
    "sg:city":"Norwalk",
    "sg:classifiers":[
        {
            "category":"Building & Trades",
            "subcategory":"Cleaning & Sanitation",
            "type":"Services"
        }
    ],
    "sg:phone":"+1   ",
    "sg:postcode":"06854",
    "sg:province":"CT",
    "sg:tags":[
        "maintenance"
    ],
    "wof:name":"Bowden Cleaning Service",
    "wof:placetype":"venue"
},
  "geometry": {"coordinates":[-73.434952,41.108856],"type":"Point"}
}