{
  "type": "Feature",
  "properties": {
    "iso:country":"US",
    "sg:address":"4 Amidon Ave",
    "sg:city":"Newington",
    "sg:classifiers":[
        {
            "category":"Professional",
            "type":"Services"
        }
    ],
    "sg:phone":"+1 860 666 9639",
    "sg:postcode":"06111",
    "sg:province":"CT",
    "wof:name":"Alpine Tool Co",
    "wof:placetype":"venue"
},
  "geometry": {"coordinates":[-72.740382,41.652345],"type":"Point"}
}