{
  "type": "Feature",
  "properties": {
    "iso:country":"US",
    "sg:address":"101 Stemway Rd",
    "sg:city":"Trumbull",
    "sg:classifiers":[
        {
            "category":"Wholesale",
            "subcategory":"Non-durable Goods",
            "type":"Manufacturing & Wholesale Goods"
        }
    ],
    "sg:phone":"+1 203 268 0070",
    "sg:postcode":"06611",
    "sg:province":"CT",
    "sg:tags":[
        "picture",
        "toy",
        "jewelery",
        "frame",
        "novelty",
        "plastic"
    ],
    "wof:name":"Richer Marketing Inc",
    "wof:placetype":"venue"
},
  "geometry": {"coordinates":[-73.241316,41.271489],"type":"Point"}
}