{
  "type": "Feature",
  "properties": {
    "iso:country":"US",
    "sg:address":"575 N Roast Meat Hill Rd",
    "sg:city":"Killingworth",
    "sg:classifiers":[
        {
            "category":"Professional",
            "type":"Services"
        }
    ],
    "sg:phone":"+1 860 663 5528",
    "sg:postcode":"06419",
    "sg:province":"CT",
    "wof:name":"Eco Guard LLC",
    "wof:placetype":"venue"
},
  "geometry": {"coordinates":[-72.549768,41.396036],"type":"Point"}
}