{
  "type": "Feature",
  "properties": {
    "iso:country":"US",
    "sg:address":"73 Creston Rd",
    "sg:city":"Stratford",
    "sg:classifiers":[
        {
            "category":"Personal",
            "subcategory":"Beauty Salon",
            "type":"Services"
        }
    ],
    "sg:phone":"+1   ",
    "sg:postcode":"06614",
    "sg:province":"CT",
    "sg:tags":[
        "shop"
    ],
    "wof:name":"Sachs For Hair",
    "wof:placetype":"venue"
},
  "geometry": {"coordinates":[-73.12166499999999,41.214719],"type":"Point"}
}