{
  "type": "Feature",
  "properties": {
    "addr:full":"50 Mercer St Stratford CT 06614",
    "addr:housenumber":"50",
    "addr:postcode":"06614",
    "addr:street":"Mercer St",
    "iso:country":"US",
    "sg:address":"50 Mercer St",
    "sg:city":"Stratford",
    "sg:classifiers":[
        {
            "category":"Retail",
            "subcategory":"Repair Shop",
            "type":"Services"
        }
    ],
    "sg:phone":"+1   ",
    "sg:postcode":"06614",
    "sg:province":"CT",
    "wof:name":"Dorne TV Service",
    "wof:placetype":"venue"
},
  "geometry": {"coordinates":[-73.13999200000001,41.208068],"type":"Point"}
}