{
  "type": "Feature",
  "properties": {
    "iso:country":"US",
    "sg:address":"850 Carrington Rd",
    "sg:city":"Bethany",
    "sg:classifiers":[
        {
            "category":"Manufacturing",
            "subcategory":"Motor Vehicles & Parts",
            "type":"Manufacturing & Wholesale Goods"
        }
    ],
    "sg:phone":"+1 203 393 0328",
    "sg:postcode":"06524",
    "sg:province":"CT",
    "sg:tags":[
        "equipment",
        "truck"
    ],
    "wof:name":"Northeast Truck & Equipment",
    "wof:placetype":"venue"
},
  "geometry": {"coordinates":[-72.966497,41.459845],"type":"Point"}
}