{
  "type": "Feature",
  "properties": {
    "iso:country":"US",
    "sg:address":"1306 Boston Post Rd",
    "sg:city":"Madison",
    "sg:classifiers":[
        {
            "category":"Health Services",
            "subcategory":"Doctor",
            "type":"Services"
        }
    ],
    "sg:phone":"+1   ",
    "sg:postcode":"06443",
    "sg:province":"CT",
    "wof:name":"Harry M Eudowe DDS",
    "wof:placetype":"venue"
},
  "geometry": {"coordinates":[-72.55560699999999,41.274196],"type":"Point"}
}