{
  "type": "Feature",
  "properties": {
    "addr:full":"97 Laurel Hill Rd Brookfield CT 06804",
    "addr:housenumber":"97",
    "addr:postcode":"06804",
    "addr:street":"Laurel Hill Rd",
    "iso:country":"US",
    "sg:address":"97 Laurel Hill Rd",
    "sg:city":"Brookfield",
    "sg:classifiers":[
        {
            "category":"Building & Trades",
            "subcategory":"Construction",
            "type":"Services"
        }
    ],
    "sg:phone":"+1 203 775 3757",
    "sg:postcode":"06804",
    "sg:province":"CT",
    "sg:tags":[
        "dry wall",
        "contractor"
    ],
    "wof:name":"Roys Drywall",
    "wof:placetype":"venue"
},
  "geometry": {"coordinates":[-73.413397,41.483099],"type":"Point"}
}