{
  "type": "Feature",
  "properties": {
    "iso:country":"US",
    "sg:address":"70 Bridge St",
    "sg:city":"Shelton",
    "sg:classifiers":[
        {
            "category":"Education",
            "subcategory":"Special Training",
            "type":"Public Place"
        }
    ],
    "sg:phone":"+1 203 924 6733",
    "sg:postcode":"06484",
    "sg:province":"CT",
    "sg:tags":[
        "school",
        "instruction",
        "art"
    ],
    "wof:name":"Bob Boroski School Of Art",
    "wof:placetype":"venue"
},
  "geometry": {"coordinates":[-73.093152,41.317661],"type":"Point"}
}