{
  "type": "Feature",
  "properties": {
    "addr:full":"625 North Rd Groton CT 06340",
    "addr:housenumber":"625",
    "addr:postcode":"06340",
    "addr:street":"North Rd Groton Ct",
    "iso:country":"US",
    "sg:address":"625 North Rd",
    "sg:city":"Groton",
    "sg:classifiers":[
        {
            "category":"Coffee & Tea",
            "type":"Food & Drink"
        }
    ],
    "sg:menulink":"http://www.allmenus.com/ct/groton/108470-starbucks-coffee/menu/",
    "sg:phone":"+1 860 405 0107",
    "sg:postcode":"06340",
    "sg:province":"CT",
    "sg:tags":[
        "american"
    ],
    "wof:name":"Starbucks Coffee",
    "wof:placetype":"venue"
},
  "geometry": {"coordinates":[-72.024737,41.366166],"type":"Point"}
}