{
  "type": "Feature",
  "properties": {
    "iso:country":"US",
    "sg:address":"9 Talcott Ave",
    "sg:city":"Vernon Rockville",
    "sg:classifiers":[
        {
            "category":"Organizations",
            "subcategory":"Religious Organization",
            "type":"Services"
        }
    ],
    "sg:phone":"+1   ",
    "sg:postcode":"06066",
    "sg:province":"CT",
    "wof:name":"Edward D Campolongo",
    "wof:placetype":"venue"
},
  "geometry": {"coordinates":[-72.453827,41.869964],"type":"Point"}
}