{
  "type": "Feature",
  "properties": {
    "addr:full":"17 Pierce St Plainville CT 06062",
    "addr:housenumber":"17",
    "addr:postcode":"06062",
    "addr:street":"Pierce St",
    "iso:country":"US",
    "sg:address":"17 Pierce St",
    "sg:city":"Plainville",
    "sg:classifiers":[
        {
            "category":"Shopping",
            "subcategory":"Optical Goods",
            "type":"Retail Goods"
        }
    ],
    "sg:phone":"+1 860 793 9378",
    "sg:postcode":"06062",
    "sg:province":"CT",
    "wof:name":"Plainville Water Company",
    "wof:placetype":"venue"
},
  "geometry": {"coordinates":[-72.869657,41.669167],"type":"Point"}
}