{
  "type": "Feature",
  "properties": {
    "iso:country":"US",
    "sg:address":"48 Hickory Knoll Dr",
    "sg:city":"Easton",
    "sg:classifiers":[
        {
            "category":"Professional",
            "type":"Services"
        }
    ],
    "sg:phone":"+1 203 268 9731",
    "sg:postcode":"06612",
    "sg:province":"CT",
    "wof:name":"Thomas & Jane Logie",
    "wof:placetype":"venue"
},
  "geometry": {"coordinates":[-73.28134300000001,41.260154],"type":"Point"}
}