{
  "type": "Feature",
  "properties": {
    "iso:country":"US",
    "sg:address":"88 Orchard St",
    "sg:city":"Cos Cob",
    "sg:classifiers":[
        {
            "category":"Professional",
            "subcategory":"Business Services",
            "type":"Services"
        }
    ],
    "sg:phone":"+1 203 629 7993",
    "sg:postcode":"06807",
    "sg:province":"CT",
    "sg:tags":[
        "building",
        "inspection"
    ],
    "wof:name":"Bakewell & Haller",
    "wof:placetype":"venue"
},
  "geometry": {"coordinates":[-73.60358600000001,41.047827],"type":"Point"}
}