{
  "type": "Feature",
  "properties": {
    "iso:country":"US",
    "sg:address":"324 Fairfax Rd",
    "sg:city":"Bridgeport",
    "sg:classifiers":[
        {
            "category":"Professional",
            "subcategory":"Accounting & Tax Preparation",
            "type":"Services"
        }
    ],
    "sg:phone":"+1   ",
    "sg:postcode":"06610",
    "sg:province":"CT",
    "wof:name":"Steven Proviost Enterprises",
    "wof:placetype":"venue"
},
  "geometry": {"coordinates":[-73.16647500000001,41.218037],"type":"Point"}
}