{
  "type": "Feature",
  "properties": {
    "iso:country":"US",
    "sg:address":"11 Dorothy Ave",
    "sg:city":"Prospect",
    "sg:classifiers":[
        {
            "category":"Retail",
            "subcategory":"Repair Shop",
            "type":"Services"
        }
    ],
    "sg:phone":"+1 203 758 6339",
    "sg:postcode":"06712",
    "sg:province":"CT",
    "sg:tags":[
        "refinishing",
        "furniture"
    ],
    "wof:name":"Vintage Furniture & Rstrtn",
    "wof:placetype":"venue"
},
  "geometry": {"coordinates":[-72.99630500000001,41.507408],"type":"Point"}
}