{
  "type": "Feature",
  "properties": {
    "addr:full":"13 Woodway Ln Wilton CT 06897",
    "addr:housenumber":"13",
    "addr:postcode":"06897",
    "addr:street":"Woodway Ln",
    "iso:country":"US",
    "sg:address":"13 Woodway Ln",
    "sg:city":"Wilton",
    "sg:classifiers":[
        {
            "category":"Building & Trades",
            "subcategory":"Construction",
            "type":"Services"
        }
    ],
    "sg:phone":"+1 203 834 1761",
    "sg:postcode":"06897",
    "sg:province":"CT",
    "sg:tags":[
        "company"
    ],
    "wof:name":"Trofa Construction",
    "wof:placetype":"venue"
},
  "geometry": {"coordinates":[-73.384953,41.178514],"type":"Point"}
}