{
  "type": "Feature",
  "properties": {
    "addr:full":"275 Front Ave West Haven CT 06516",
    "addr:housenumber":"275",
    "addr:postcode":"06516",
    "addr:street":"Front Ave",
    "iso:country":"US",
    "sg:address":"275 Front Ave",
    "sg:city":"West Haven",
    "sg:classifiers":[
        {
            "category":"Retail",
            "subcategory":"Auto Repair",
            "type":"Services"
        }
    ],
    "sg:phone":"+1 203 932 3046",
    "sg:postcode":"06516",
    "sg:province":"CT",
    "sg:tags":[
        "body",
        "shop",
        "painting",
        "automobile"
    ],
    "wof:name":"Slater's Auto Body",
    "wof:placetype":"venue"
},
  "geometry": {"coordinates":[-72.951359,41.287455],"type":"Point"}
}