{
  "type": "Feature",
  "properties": {
    "iso:country":"US",
    "sg:address":"24 Roxbury Rd",
    "sg:city":"Stamford",
    "sg:classifiers":[
        {
            "category":"Organizations",
            "subcategory":"Religious Organization",
            "type":"Services"
        }
    ],
    "sg:phone":"+1   ",
    "sg:postcode":"06902",
    "sg:province":"CT",
    "wof:name":"St Leos Church",
    "wof:placetype":"venue"
},
  "geometry": {"coordinates":[-73.563485,41.08977],"type":"Point"}
}