{
  "type": "Feature",
  "properties": {
    "addr:full":"145 Cobey Rd Rocky Hill CT 06067",
    "addr:housenumber":"145",
    "addr:postcode":"06067",
    "addr:street":"Cobey Rd",
    "iso:country":"US",
    "sg:address":"145 Cobey Rd",
    "sg:city":"Rocky Hill",
    "sg:classifiers":[
        {
            "category":"Professional",
            "subcategory":"Management & Consulting",
            "type":"Services"
        }
    ],
    "sg:phone":"+1   ",
    "sg:postcode":"06067",
    "sg:province":"CT",
    "sg:tags":[
        "business"
    ],
    "wof:name":"Xionsoft",
    "wof:placetype":"venue"
},
  "geometry": {"coordinates":[-72.713759,41.649111],"type":"Point"}
}