{
  "type": "Feature",
  "properties": {
    "addr:full":"396 Main St Winsted CT 06098",
    "addr:housenumber":"396",
    "addr:postcode":"06098",
    "addr:street":"Main St",
    "iso:country":"US",
    "sg:address":"396 Main St",
    "sg:city":"Winsted",
    "sg:classifiers":[
        {
            "category":"Communications",
            "subcategory":"Newspaper",
            "type":"Services"
        }
    ],
    "sg:phone":"+1 860 738 4418",
    "sg:postcode":"06098",
    "sg:province":"CT",
    "sg:tags":[
        "print",
        "medium"
    ],
    "sg:website":"www.winstedjournal.com",
    "wof:name":"Winsted Journal",
    "wof:placetype":"venue"
},
  "geometry": {"coordinates":[-72.966031,41.874007],"type":"Point"}
}