{
  "type": "Feature",
  "properties": {
    "addr:full":"114 Main St Deep River CT 06417",
    "addr:housenumber":"114",
    "addr:postcode":"06417",
    "addr:street":"Main St",
    "iso:country":"US",
    "sg:address":"114 Main St",
    "sg:city":"Deep River",
    "sg:classifiers":[
        {
            "category":"Food & Beverages",
            "subcategory":"Liquor & Beverages",
            "type":"Retail Goods"
        }
    ],
    "sg:phone":"+1 860 526 4090",
    "sg:postcode":"06417",
    "sg:province":"CT",
    "sg:tags":[
        "beer",
        "spirit",
        "wine"
    ],
    "wof:name":"The Village Package Store",
    "wof:placetype":"venue"
},
  "geometry": {"coordinates":[-72.43849899999999,41.391499],"type":"Point"}
}