{
  "type": "Feature",
  "properties": {
    "addr:full":"96 Knapp St Stamford CT 06907",
    "addr:housenumber":"96",
    "addr:postcode":"06907",
    "addr:street":"Knapp St",
    "iso:country":"US",
    "sg:address":"96 Knapp St",
    "sg:city":"Stamford",
    "sg:classifiers":[
        {
            "category":"Building & Trades",
            "subcategory":"Plumbing",
            "type":"Services"
        }
    ],
    "sg:phone":"+1 203 325 1622",
    "sg:postcode":"06907",
    "sg:province":"CT",
    "sg:tags":[
        "plumbing",
        "contractor"
    ],
    "wof:name":"Joseph S Sabino Plumbing & Htg",
    "wof:placetype":"venue"
},
  "geometry": {"coordinates":[-73.522173,41.093918],"type":"Point"}
}