{
  "type": "Feature",
  "properties": {
    "iso:country":"US",
    "sg:address":"204 River W",
    "sg:city":"Greenwich",
    "sg:classifiers":[
        {
            "category":"Banks & Credit Unions",
            "subcategory":"Bank",
            "type":"Services"
        }
    ],
    "sg:phone":"+1 203 531 5623",
    "sg:postcode":"06831",
    "sg:province":"NY",
    "sg:tags":[
        "loan"
    ],
    "wof:name":"Private Equity Funding",
    "wof:placetype":"venue"
},
  "geometry": {"coordinates":[-73.667815,41.035263],"type":"Point"}
}