{
  "type": "Feature",
  "properties": {
    "addr:full":"205 Neuton Ave Port Chester CT 10573",
    "addr:housenumber":"205",
    "addr:postcode":"10573",
    "addr:street":"Neuton Ave;Chester",
    "iso:country":"US",
    "sg:address":"205 Neuton Ave",
    "sg:city":"Port Chester",
    "sg:phone":"+1 914 939 3979",
    "sg:postcode":"10573",
    "sg:province":"CT",
    "sg:tags":[
        "farm",
        "tobacco"
    ],
    "wof:name":"Perry Manor Estates",
    "wof:placetype":"venue"
},
  "geometry": {"coordinates":[-73.678434,41.010649],"type":"Point"}
}