{
  "type": "Feature",
  "properties": {
    "addr:full":"101 Meadowcrest Ln Watertown CT 06795",
    "addr:housenumber":"101",
    "addr:postcode":"06795",
    "addr:street":"Meadowcrest Ln",
    "iso:country":"US",
    "sg:address":"101 Meadowcrest Ln",
    "sg:city":"Watertown",
    "sg:classifiers":[
        {
            "category":"Professional",
            "subcategory":"Business Services",
            "type":"Services"
        }
    ],
    "sg:phone":"+1   ",
    "sg:postcode":"06795",
    "sg:province":"CT",
    "wof:name":"Bannon Distributors",
    "wof:placetype":"venue"
},
  "geometry": {"coordinates":[-73.126177,41.600456],"type":"Point"}
}