{
  "type": "Feature",
  "properties": {
    "iso:country":"US",
    "sg:address":"180 Main St",
    "sg:city":"West Haven",
    "sg:classifiers":[
        {
            "category":"Restaurant",
            "type":"Food & Drink"
        }
    ],
    "sg:phone":"+1 203 933 8145",
    "sg:postcode":"06516",
    "sg:province":"CT",
    "sg:tags":[
        "delicatessen"
    ],
    "wof:name":"Dairy Express",
    "wof:placetype":"venue"
},
  "geometry": {"coordinates":[-72.94493900000001,41.274],"type":"Point"}
}