{
  "type": "Feature",
  "properties": {
    "addr:full":"75 West St Simsbury CT 06070",
    "addr:housenumber":"75",
    "addr:postcode":"06070",
    "addr:street":"West St Simsbury Ct",
    "iso:country":"US",
    "sg:address":"75 West St",
    "sg:city":"Simsbury",
    "sg:classifiers":[
        {
            "category":"Real Estate",
            "subcategory":"Developer",
            "type":"Services"
        }
    ],
    "sg:phone":"+1 860 843 2001",
    "sg:postcode":"06070",
    "sg:province":"CT",
    "sg:tags":[
        "manager"
    ],
    "wof:name":"Ensign-Bickford Realty Corp",
    "wof:placetype":"venue"
},
  "geometry": {"coordinates":[-72.81246299999999,41.869963],"type":"Point"}
}