{
  "type": "Feature",
  "properties": {
    "addr:full":"16 Seymour Rd East Granby CT 06026",
    "addr:housenumber":"16",
    "addr:postcode":"06026",
    "addr:street":"Seymour Rd East Granby Ct",
    "iso:country":"US",
    "sg:address":"16 Seymour Rd",
    "sg:city":"East Granby",
    "sg:classifiers":[
        {
            "category":"Insurance",
            "subcategory":"Hazard Insurance",
            "type":"Services"
        }
    ],
    "sg:phone":"+1 860 651 1415",
    "sg:postcode":"06026",
    "sg:province":"CT",
    "sg:tags":[
        "carrier"
    ],
    "wof:name":"Blue Entps Ltd Lblty Comp",
    "wof:placetype":"venue"
},
  "geometry": {"coordinates":[-72.737038,41.916436],"type":"Point"}
}