{
  "type": "Feature",
  "properties": {
    "addr:full":"83 Spindle Hill Rd Wolcott CT 06716",
    "addr:housenumber":"83",
    "addr:postcode":"06716",
    "addr:street":"Spindle Hill Rd Wolcott Ct",
    "iso:country":"US",
    "sg:address":"83 Spindle Hill Rd",
    "sg:city":"Wolcott",
    "sg:classifiers":[
        {
            "category":"Professional",
            "subcategory":"Computer Services",
            "type":"Services"
        }
    ],
    "sg:phone":"+1   ",
    "sg:postcode":"06716",
    "sg:province":"CT",
    "sg:tags":[
        "related"
    ],
    "wof:name":"Robinson Tech LLC",
    "wof:placetype":"venue"
},
  "geometry": {"coordinates":[-73.013088,41.603838],"type":"Point"}
}