{
  "type": "Feature",
  "properties": {
    "addr:full":"35 Nutmeg Dr Trumbull CT 06611",
    "addr:housenumber":"35",
    "addr:postcode":"06611",
    "addr:street":"Nutmeg Dr",
    "iso:country":"US",
    "sg:address":"35 Nutmeg Dr",
    "sg:city":"Trumbull",
    "sg:classifiers":[
        {
            "category":"Home & Garden",
            "subcategory":"Household Appliances",
            "type":"Retail Goods"
        }
    ],
    "sg:phone":"+1 203 380 4700",
    "sg:postcode":"06611",
    "sg:province":"CT",
    "sg:tags":[
        "pump"
    ],
    "sg:website":"www.flygtus.com",
    "wof:name":"Flygt Corp",
    "wof:placetype":"venue"
},
  "geometry": {"coordinates":[-73.149269,41.241255],"type":"Point"}
}