{
  "type": "Feature",
  "properties": {
    "iso:country":"US",
    "sg:address":"105 Beacon Valley Rd",
    "sg:city":"Beacon Falls",
    "sg:classifiers":[
        {
            "category":"Organizations",
            "subcategory":"Non-profit Organization",
            "type":"Services"
        }
    ],
    "sg:phone":"+1   ",
    "sg:postcode":"06403",
    "sg:province":"CT",
    "sg:tags":[
        "social"
    ],
    "wof:name":"The Compassionate Friends",
    "wof:placetype":"venue"
},
  "geometry": {"coordinates":[-73.04602300000001,41.468782],"type":"Point"}
}