{
  "type": "Feature",
  "properties": {
    "addr:full":"90 Utica St Milford CT 06461",
    "addr:housenumber":"90",
    "addr:postcode":"06461",
    "addr:street":"Utica St",
    "iso:country":"US",
    "sg:address":"90 Utica St",
    "sg:city":"Milford",
    "sg:classifiers":[
        {
            "category":"Organizations",
            "subcategory":"Labor Organization",
            "type":"Services"
        }
    ],
    "sg:phone":"+1   ",
    "sg:postcode":"06461",
    "sg:province":"CT",
    "wof:name":"T J Management LLC",
    "wof:placetype":"venue"
},
  "geometry": {"coordinates":[-73.102172,41.211083],"type":"Point"}
}