{
  "type": "Feature",
  "properties": {
    "addr:full":"8 Redwood Dr Bethel CT 06801",
    "addr:housenumber":"8",
    "addr:postcode":"06801",
    "addr:street":"Redwood Dr Bethel Ct",
    "iso:country":"US",
    "sg:address":"8 Redwood Dr",
    "sg:city":"Bethel",
    "sg:classifiers":[
        {
            "category":"Shopping",
            "subcategory":"Pets & Pet Supplies",
            "type":"Retail Goods"
        }
    ],
    "sg:phone":"+1 203 947 5494",
    "sg:postcode":"06801",
    "sg:province":"CT",
    "sg:tags":[
        "store"
    ],
    "wof:name":"Pampered K9 Club",
    "wof:placetype":"venue"
},
  "geometry": {"coordinates":[-73.378823,41.414624],"type":"Point"}
}