{
  "type": "Feature",
  "properties": {
    "addr:full":"267 Main Ave Norwalk CT 06851",
    "addr:housenumber":"267",
    "addr:postcode":"06851",
    "addr:street":"Main Ave",
    "iso:country":"US",
    "sg:address":"267 Main Ave",
    "sg:city":"Norwalk",
    "sg:classifiers":[
        {
            "category":"Shopping",
            "type":"Retail Goods"
        }
    ],
    "sg:phone":"+1 203 849 7033",
    "sg:postcode":"06851",
    "sg:province":"CT",
    "sg:tags":[
        "merchandise"
    ],
    "wof:name":"Norwalk Discounts",
    "wof:placetype":"venue"
},
  "geometry": {"coordinates":[-73.424436,41.13422],"type":"Point"}
}