{
  "type": "Feature",
  "properties": {
    "iso:country":"US",
    "sg:address":"30 Woodland St",
    "sg:city":"Hartford",
    "sg:classifiers":[
        {
            "category":"Real Estate",
            "subcategory":"Real Estate Operator",
            "type":"Services"
        },
        {
            "category":"Organizations",
            "subcategory":"Community Association",
            "type":"Services"
        }
    ],
    "sg:phone":"+1 860 522 7687",
    "sg:postcode":"06105",
    "sg:province":"CT",
    "sg:tags":[
        "building",
        "condominium"
    ],
    "wof:name":"Regency Towers",
    "wof:placetype":"venue"
},
  "geometry": {"coordinates":[-72.70177099999999,41.769043],"type":"Point"}
}