{
  "type": "Feature",
  "properties": {
    "addr:full":"1211 High Ridge Rd Stamford CT 06905",
    "addr:housenumber":"1211",
    "addr:postcode":"06905",
    "addr:street":"High Ridge Rd",
    "iso:country":"US",
    "sg:address":"1211 High Ridge Rd",
    "sg:city":"Stamford",
    "sg:classifiers":[
        {
            "category":"Banks & Credit Unions",
            "subcategory":"Bank",
            "type":"Services"
        }
    ],
    "sg:phone":"+1 203 322 7244",
    "sg:postcode":"06905",
    "sg:province":"CT",
    "wof:name":"Wachovia Bank",
    "wof:placetype":"venue"
},
  "geometry": {"coordinates":[-73.547084,41.10949],"type":"Point"}
}