{
  "type": "Feature",
  "properties": {
    "addr:full":"20 Highgate Rd Trumbull CT 06611",
    "addr:housenumber":"20",
    "addr:postcode":"06611",
    "addr:street":"Highgate Rd",
    "iso:country":"US",
    "sg:address":"20 Highgate Rd",
    "sg:city":"Trumbull",
    "sg:classifiers":[
        {
            "category":"Professional",
            "subcategory":"Computer Services",
            "type":"Services"
        }
    ],
    "sg:phone":"+1   ",
    "sg:postcode":"06611",
    "sg:province":"CT",
    "wof:name":"Lanstatus LLC",
    "wof:placetype":"venue"
},
  "geometry": {"coordinates":[-73.215582,41.235441],"type":"Point"}
}