{
  "type": "Feature",
  "properties": {
    "iso:country":"US",
    "sg:address":"107 Osborne St",
    "sg:city":"Danbury",
    "sg:classifiers":[
        {
            "category":"Health Services",
            "subcategory":"Nursing And Care Facility",
            "type":"Services"
        }
    ],
    "sg:phone":"+1 203 792 8102",
    "sg:postcode":"06810",
    "sg:province":"CT",
    "sg:tags":[
        "home",
        "convalescent"
    ],
    "wof:name":"Danbury Health Care Ctr",
    "wof:placetype":"venue"
},
  "geometry": {"coordinates":[-73.44301400000001,41.403148],"type":"Point"}
}