{
  "type": "Feature",
  "properties": {
    "addr:full":"69 Daniel Trce Burlington CT 06013",
    "addr:housenumber":"69",
    "addr:postcode":"06013",
    "addr:street":"Daniel Trce",
    "iso:country":"US",
    "sg:address":"69 Daniel Trce",
    "sg:city":"Burlington",
    "sg:classifiers":[
        {
            "category":"Professional",
            "type":"Services"
        }
    ],
    "sg:phone":"+1 860 673 2173",
    "sg:postcode":"06013",
    "sg:province":"CT",
    "wof:name":"Ultimate LLC",
    "wof:placetype":"venue"
},
  "geometry": {"coordinates":[-72.934156,41.788882],"type":"Point"}
}