{
  "type": "Feature",
  "properties": {
    "iso:country":"US",
    "sg:address":"102 Southfield Ave",
    "sg:city":"Stamford",
    "sg:classifiers":[
        {
            "category":"Banks & Credit Unions",
            "subcategory":"Investment Brokerage",
            "type":"Services"
        },
        {
            "category":"Insurance",
            "subcategory":"Insurance Agent",
            "type":"Services"
        }
    ],
    "sg:phone":"+1 203 708 9033",
    "sg:postcode":"06902",
    "sg:province":"CT",
    "sg:tags":[
        "advisory",
        "planning",
        "financial",
        "consultant"
    ],
    "sg:website":"www.diddel.com",
    "wof:name":"Diddel & Diddel LLC",
    "wof:placetype":"venue"
},
  "geometry": {"coordinates":[-73.547668,41.034878],"type":"Point"}
}