{
  "type": "Feature",
  "properties": {
    "iso:country":"US",
    "sg:address":"8 Hazel Ter",
    "sg:city":"Woodbridge",
    "sg:classifiers":[
        {
            "category":"Professional",
            "type":"Services"
        }
    ],
    "sg:phone":"+1 203 389 5732",
    "sg:postcode":"06525",
    "sg:province":"CT",
    "sg:tags":[
        "establishment"
    ],
    "wof:name":"In Our Hands",
    "wof:placetype":"venue"
},
  "geometry": {"coordinates":[-72.983864,41.340075],"type":"Point"}
}