{
  "type": "Feature",
  "properties": {
    "addr:full":"23 Saddle Ridge Rd New Fairfield CT 06812",
    "addr:housenumber":"23",
    "addr:postcode":"06812",
    "addr:street":"Saddle Ridge Rd;Fairfield Ct",
    "iso:country":"US",
    "sg:address":"23 Saddle Ridge Rd",
    "sg:city":"New Fairfield",
    "sg:classifiers":[
        {
            "category":"Professional",
            "type":"Services"
        }
    ],
    "sg:phone":"+1 203 746 7946",
    "sg:postcode":"06812",
    "sg:province":"CT",
    "sg:tags":[
        "establishment"
    ],
    "wof:name":"Aquabears",
    "wof:placetype":"venue"
},
  "geometry": {"coordinates":[-73.53133699999999,41.449017],"type":"Point"}
}