{
  "type": "Feature",
  "properties": {
    "addr:full":"3 Robinview Ter Danbury CT 06810",
    "addr:housenumber":"3",
    "addr:postcode":"06810",
    "addr:street":"Robinview Ter Danbury Ct",
    "iso:country":"US",
    "sg:address":"3 Robinview Ter",
    "sg:city":"Danbury",
    "sg:classifiers":[
        {
            "category":"Building & Trades",
            "subcategory":"Construction",
            "type":"Services"
        }
    ],
    "sg:phone":"+1 203 778 8733",
    "sg:postcode":"06810",
    "sg:province":"CT",
    "sg:tags":[
        "house"
    ],
    "wof:name":"Building Blocks",
    "wof:placetype":"venue"
},
  "geometry": {"coordinates":[-73.45028000000001,41.38885],"type":"Point"}
}