{
  "type": "Feature",
  "properties": {
    "iso:country":"US",
    "sg:address":"21 Savarese Ln",
    "sg:city":"Burlington",
    "sg:classifiers":[
        {
            "category":"Farming",
            "subcategory":"Livestock Farm",
            "type":"Manufacturing & Wholesale Goods"
        }
    ],
    "sg:phone":"+1 860 673 2693",
    "sg:postcode":"06013",
    "sg:province":"CT",
    "sg:tags":[
        "beef",
        "feedlot",
        "cattle"
    ],
    "wof:name":"More Ledge Farm",
    "wof:placetype":"venue"
},
  "geometry": {"coordinates":[-72.96594,41.764903],"type":"Point"}
}