{
  "type": "Feature",
  "properties": {
    "iso:country":"US",
    "sg:address":"57 Colony Rd",
    "sg:city":"Westport",
    "sg:classifiers":[
        {
            "category":"Building & Trades",
            "subcategory":"Cleaning & Sanitation",
            "type":"Services"
        }
    ],
    "sg:phone":"+1 203 222 2284",
    "sg:postcode":"06880",
    "sg:province":"CT",
    "sg:tags":[
        "snow",
        "removal"
    ],
    "wof:name":"A & K Snow Plowing",
    "wof:placetype":"venue"
},
  "geometry": {"coordinates":[-73.33674499999999,41.150379],"type":"Point"}
}