{
  "type": "Feature",
  "properties": {
    "iso:country":"US",
    "sg:address":"1254 Storrs Rd",
    "sg:city":"Storrs Mansfield",
    "sg:classifiers":[
        {
            "category":"Restaurant",
            "type":"Food & Drink"
        }
    ],
    "sg:menulink":"http://www.allmenus.com/ct/mansfield/23701-tequila-cove/menu/",
    "sg:phone":"+1 860 429 5777",
    "sg:postcode":"06268",
    "sg:province":"CT",
    "sg:tags":[
        "mexican"
    ],
    "wof:name":"Tequila Cove",
    "wof:placetype":"venue"
},
  "geometry": {"coordinates":[-72.244793,41.805684],"type":"Point"}
}