{
  "type": "Feature",
  "properties": {
    "iso:country":"US",
    "sg:address":"223 Boston Post Rd",
    "sg:city":"Orange",
    "sg:classifiers":[
        {
            "category":"Shopping",
            "type":"Retail Goods"
        }
    ],
    "sg:phone":"+1 203 891 0914",
    "sg:postcode":"06477",
    "sg:province":"CT",
    "sg:tags":[
        "merchandise"
    ],
    "wof:name":"Jamie Mae Ltd",
    "wof:placetype":"venue"
},
  "geometry": {"coordinates":[-73.00012599999999,41.26787],"type":"Point"}
}