{
  "type": "Feature",
  "properties": {
    "iso:country":"US",
    "sg:address":"39 Putnam Ave",
    "sg:city":"Hamden",
    "sg:classifiers":[
        {
            "category":"Recreation",
            "type":"Entertainment"
        }
    ],
    "sg:phone":"+1 203 287 2277",
    "sg:postcode":"06517",
    "sg:province":"CT",
    "sg:tags":[
        "instruction",
        "yoga"
    ],
    "sg:website":"www.ctyogacenter.com",
    "wof:name":"Connecticut Yoga Ctr Studio",
    "wof:placetype":"venue"
},
  "geometry": {"coordinates":[-72.91389599999999,41.345892],"type":"Point"}
}