{
  "type": "Feature",
  "properties": {
    "addr:full":"1041 New Haven Rd Naugatuck CT 06770",
    "addr:housenumber":"1041",
    "addr:postcode":"06770",
    "addr:street":"New Haven Rd Naugatuck Ct",
    "iso:country":"US",
    "sg:address":"1041 New Haven Rd",
    "sg:city":"Naugatuck",
    "sg:classifiers":[
        {
            "category":"Wholesale",
            "subcategory":"Groceries",
            "type":"Manufacturing & Wholesale Goods"
        }
    ],
    "sg:phone":"+1 203 720 6004",
    "sg:postcode":"06770",
    "sg:province":"CT",
    "sg:tags":[
        "baker"
    ],
    "wof:name":"Best Foods Baking Co",
    "wof:placetype":"venue"
},
  "geometry": {"coordinates":[-73.03106200000001,41.469572],"type":"Point"}
}