{
  "type": "Feature",
  "properties": {
    "iso:country":"US",
    "sg:address":"430 N Cherry St Exd",
    "sg:city":"Wallingford",
    "sg:classifiers":[
        {
            "category":"Freight",
            "type":"Transportation"
        }
    ],
    "sg:phone":"+1 203 265 0921",
    "sg:postcode":"06492",
    "sg:province":"CT",
    "sg:tags":[
        "hauling",
        "trucking"
    ],
    "sg:website":"www.jrchristoni.com",
    "wof:name":"J R Christoni Inc",
    "wof:placetype":"venue"
},
  "geometry": {"coordinates":[-72.81848100000001,41.470499],"type":"Point"}
}