{
  "type": "Feature",
  "properties": {
    "iso:country":"US",
    "sg:address":"460 New Britain Ave",
    "sg:city":"Hartford",
    "sg:classifiers":[
        {
            "category":"Education",
            "subcategory":"Library",
            "type":"Public Place"
        }
    ],
    "sg:phone":"+1 860 695 7480",
    "sg:postcode":"06106",
    "sg:province":"CT",
    "wof:name":"Public Library",
    "wof:placetype":"venue"
},
  "geometry": {"coordinates":[-72.697557,41.739418],"type":"Point"}
}