{
  "type": "Feature",
  "properties": {
    "addr:full":"641 Scofieldtown Rd Stamford CT 06903",
    "addr:housenumber":"641",
    "addr:postcode":"06903",
    "addr:street":"Scofieldtown Rd",
    "iso:country":"US",
    "sg:address":"641 Scofieldtown Rd",
    "sg:city":"Stamford",
    "sg:classifiers":[
        {
            "category":"Education",
            "subcategory":"School",
            "type":"Public Place"
        }
    ],
    "sg:phone":"+1 203 977 2750",
    "sg:postcode":"06903",
    "sg:province":"CT",
    "wof:name":"Scofield Middle School",
    "wof:placetype":"venue"
},
  "geometry": {"coordinates":[-73.556349,41.140441],"type":"Point"}
}