{
  "type": "Feature",
  "properties": {
    "iso:country":"US",
    "sg:address":"1 Orchard Pk Rd",
    "sg:city":"Madison",
    "sg:classifiers":[
        {
            "category":"Manufacturing",
            "subcategory":"Electronics",
            "type":"Manufacturing & Wholesale Goods"
        }
    ],
    "sg:phone":"+1   ",
    "sg:postcode":"06443",
    "sg:province":"CT",
    "sg:tags":[
        "distributor",
        "audio",
        "producer"
    ],
    "wof:name":"Audio-Forum",
    "wof:placetype":"venue"
},
  "geometry": {"coordinates":[-72.624538,41.283052],"type":"Point"}
}