{
  "type": "Feature",
  "properties": {
    "addr:full":"135 Perry Ave Norwalk CT 06850",
    "addr:housenumber":"135",
    "addr:postcode":"06850",
    "addr:street":"Perry Ave",
    "iso:country":"US",
    "sg:address":"135 Perry Ave",
    "sg:city":"Norwalk",
    "sg:classifiers":[
        {
            "category":"Real Estate",
            "subcategory":"Architect",
            "type":"Services"
        }
    ],
    "sg:phone":"+1 203 849 1888",
    "sg:postcode":"06850",
    "sg:province":"CT",
    "sg:tags":[
        "building",
        "designer"
    ],
    "wof:name":"Village Craftsman Inc",
    "wof:placetype":"venue"
},
  "geometry": {"coordinates":[-73.439785,41.147376],"type":"Point"}
}