{
  "type": "Feature",
  "properties": {
    "iso:country":"US",
    "sg:address":"154 N Mountain Rd",
    "sg:city":"Canton",
    "sg:classifiers":[
        {
            "category":"Professional",
            "type":"Services"
        }
    ],
    "sg:phone":"+1 860 651 3046",
    "sg:postcode":"06019",
    "sg:province":"CT",
    "wof:name":"Diedrick Inc",
    "wof:placetype":"venue"
},
  "geometry": {"coordinates":[-72.88544400000001,41.865925],"type":"Point"}
}