{
  "type": "Feature",
  "properties": {
    "addr:full":"17 Florence Ave Ellington CT 06029",
    "addr:housenumber":"17",
    "addr:postcode":"06029",
    "addr:street":"Florence Ave Ellington Ct",
    "iso:country":"US",
    "sg:address":"17 Florence Ave",
    "sg:city":"Ellington",
    "sg:classifiers":[
        {
            "category":"Retail",
            "subcategory":"Repair Shop",
            "type":"Services"
        }
    ],
    "sg:phone":"+1   ",
    "sg:postcode":"06029",
    "sg:province":"CT",
    "sg:tags":[
        "body",
        "auto"
    ],
    "wof:name":"Kens Upholstery LLC",
    "wof:placetype":"venue"
},
  "geometry": {"coordinates":[-72.455157,41.871749],"type":"Point"}
}