{
  "type": "Feature",
  "properties": {
    "addr:full":"460 N Main St Port Chester NY 10573",
    "addr:housenumber":"460",
    "addr:postcode":"10573",
    "addr:street":"N Main St",
    "iso:country":"US",
    "sg:address":"460 N Main St",
    "sg:city":"Port Chester",
    "sg:classifiers":[
        {
            "category":"Real Estate",
            "subcategory":"Architect",
            "type":"Services"
        }
    ],
    "sg:phone":"+1 914 937 5700",
    "sg:postcode":"10573",
    "sg:province":"NY",
    "sg:tags":[
        "building",
        "designer"
    ],
    "wof:name":"Casalinda Designs",
    "wof:placetype":"venue"
},
  "geometry": {"coordinates":[-73.656783,41.008729],"type":"Point"}
}