{
  "type": "Feature",
  "properties": {
    "addr:full":"940 Grand Ave New Haven CT 06511",
    "addr:housenumber":"940",
    "addr:postcode":"06511",
    "addr:street":"Grand Ave",
    "iso:country":"US",
    "sg:address":"940 Grand Ave",
    "sg:city":"New Haven",
    "sg:classifiers":[
        {
            "category":"Food & Beverages",
            "subcategory":"Groceries & Convenience Stores",
            "type":"Retail Goods"
        }
    ],
    "sg:phone":"+1 203 562 0395",
    "sg:postcode":"06511",
    "sg:province":"CT",
    "wof:name":"Grand & Olive Food Mart",
    "wof:placetype":"venue"
},
  "geometry": {"coordinates":[-72.916192,41.307825],"type":"Point"}
}