{
  "type": "Feature",
  "properties": {
    "addr:full":"645 Post Rd E Westport CT 06880",
    "addr:housenumber":"645",
    "addr:postcode":"06880",
    "addr:street":"Post Rd E Westport Ct",
    "iso:country":"US",
    "sg:address":"645 Post Rd E",
    "sg:city":"Westport",
    "sg:classifiers":[
        {
            "category":"Personal",
            "subcategory":"Tanning Parlor",
            "type":"Services"
        }
    ],
    "sg:phone":"+1 203 226 6004",
    "sg:postcode":"06880",
    "sg:province":"CT",
    "sg:tags":[
        "salon"
    ],
    "wof:name":"Sunsations Tanning",
    "wof:placetype":"venue"
},
  "geometry": {"coordinates":[-73.345119,41.138939],"type":"Point"}
}