{
  "type": "Feature",
  "properties": {
    "iso:country":"US",
    "sg:address":"155 Winthrop Rd",
    "sg:city":"Guilford",
    "sg:classifiers":[
        {
            "category":"Professional",
            "subcategory":"Business Services",
            "type":"Services"
        }
    ],
    "sg:phone":"+1 203 458 2452",
    "sg:postcode":"06437",
    "sg:province":"CT",
    "sg:tags":[
        "event"
    ],
    "wof:name":"Truevents",
    "wof:placetype":"venue"
},
  "geometry": {"coordinates":[-72.69683999999999,41.329119],"type":"Point"}
}