{
  "type": "Feature",
  "properties": {
    "addr:full":"340 W Newberry Rd Bloomfield CT 06002",
    "addr:housenumber":"340",
    "addr:postcode":"06002",
    "addr:street":"W Newberry Rd Bloomfield Ct",
    "iso:country":"US",
    "sg:address":"340 W Newberry Rd",
    "sg:city":"Bloomfield",
    "sg:classifiers":[
        {
            "category":"Education",
            "subcategory":"Junior College",
            "type":"Public Place"
        }
    ],
    "sg:phone":"+1   ",
    "sg:postcode":"06002",
    "sg:province":"CT",
    "wof:name":"Computer Education Services",
    "wof:placetype":"venue"
},
  "geometry": {"coordinates":[-72.73687,41.871175],"type":"Point"}
}