{
  "type": "Feature",
  "properties": {
    "addr:full":"15 Town St Norwich CT 06360",
    "addr:housenumber":"15",
    "addr:postcode":"06360",
    "addr:street":"Town St Norwich Ct",
    "iso:country":"US",
    "sg:address":"15 Town St",
    "sg:city":"Norwich",
    "sg:classifiers":[
        {
            "category":"Wholesale",
            "subcategory":"Home Furnishings",
            "type":"Manufacturing & Wholesale Goods"
        }
    ],
    "sg:phone":"+1 860 887 6422",
    "sg:postcode":"06360",
    "sg:province":"CT",
    "wof:name":"Fit-2b-Tied",
    "wof:placetype":"venue"
},
  "geometry": {"coordinates":[-72.091302,41.546447],"type":"Point"}
}