{
  "type": "Feature",
  "properties": {
    "iso:country":"US",
    "sg:address":"2701 Summer St",
    "sg:city":"Stamford",
    "sg:classifiers":[
        {
            "category":"Travel",
            "subcategory":"Hotels & Motels",
            "type":"Entertainment"
        }
    ],
    "sg:phone":"+1   ",
    "sg:postcode":"06905",
    "sg:province":"CT",
    "sg:tags":[
        "operation",
        "eating",
        "drinking"
    ],
    "wof:name":"Starwood Hotels & Resorts",
    "wof:placetype":"venue"
},
  "geometry": {"coordinates":[-73.549246,41.07089],"type":"Point"}
}