{
  "type": "Feature",
  "properties": {
    "addr:full":"33 Seaview Ave Branford CT 06405",
    "addr:housenumber":"33",
    "addr:postcode":"06405",
    "addr:street":"Seaview Ave",
    "iso:country":"US",
    "sg:address":"33 Seaview Ave",
    "sg:city":"Branford",
    "sg:classifiers":[
        {
            "category":"Retail",
            "subcategory":"Animal Services",
            "type":"Services"
        }
    ],
    "sg:phone":"+1 203 481 1300",
    "sg:postcode":"06405",
    "sg:province":"CT",
    "sg:tags":[
        "pet",
        "boarding",
        "sitting"
    ],
    "wof:name":"Critter Sitters",
    "wof:placetype":"venue"
},
  "geometry": {"coordinates":[-72.787779,41.264481],"type":"Point"}
}