{
  "type": "Feature",
  "properties": {
    "iso:country":"US",
    "sg:address":"2701 Summer St",
    "sg:city":"Stamford",
    "sg:classifiers":[
        {
            "category":"Building & Trades",
            "subcategory":"Equipment Rental",
            "type":"Services"
        }
    ],
    "sg:phone":"+1 203 323 8880",
    "sg:postcode":"06905",
    "sg:province":"CT",
    "sg:tags":[
        "aircraft",
        "leasing",
        "charter"
    ],
    "wof:name":"Royal Falcon Aircraft Charter",
    "wof:placetype":"venue"
},
  "geometry": {"coordinates":[-73.549246,41.07089],"type":"Point"}
}