{
  "type": "Feature",
  "properties": {
    "iso:country":"US",
    "sg:address":"10 Peaceable St",
    "sg:city":"Redding",
    "sg:classifiers":[
        {
            "category":"Professional",
            "subcategory":"Employment Agencies",
            "type":"Services"
        }
    ],
    "sg:phone":"+1   ",
    "sg:postcode":"06896",
    "sg:province":"CT",
    "sg:tags":[
        "executive",
        "placement"
    ],
    "wof:name":"Fergus Group",
    "wof:placetype":"venue"
},
  "geometry": {"coordinates":[-73.435377,41.265888],"type":"Point"}
}