{
  "type": "Feature",
  "properties": {
    "addr:full":"58 River St Milford CT 06460",
    "addr:housenumber":"58",
    "addr:postcode":"06460",
    "addr:street":"River St",
    "iso:country":"US",
    "sg:address":"58 River St",
    "sg:city":"Milford",
    "sg:classifiers":[
        {
            "category":"Travel",
            "subcategory":"Hotels & Motels",
            "type":"Entertainment"
        }
    ],
    "sg:phone":"+1 203 878 4515",
    "sg:postcode":"06460",
    "sg:province":"CT",
    "wof:name":"Milford Office Suites LLC",
    "wof:placetype":"venue"
},
  "geometry": {"coordinates":[-73.057507,41.223817],"type":"Point"}
}