{
  "type": "Feature",
  "properties": {
    "addr:full":"93 Greenwood Ave Bethel CT 06801",
    "addr:housenumber":"93",
    "addr:postcode":"06801",
    "addr:street":"Greenwood Ave Bethel Ct",
    "iso:country":"US",
    "sg:address":"93 Greenwood Ave",
    "sg:city":"Bethel",
    "sg:classifiers":[
        {
            "category":"Professional",
            "subcategory":"Lawyer & Legal Services",
            "type":"Services"
        }
    ],
    "sg:phone":"+1   ",
    "sg:postcode":"06801",
    "sg:province":"CT",
    "wof:name":"Evans & Lewis",
    "wof:placetype":"venue"
},
  "geometry": {"coordinates":[-73.407433,41.371748],"type":"Point"}
}