{
  "type": "Feature",
  "properties": {
    "iso:country":"US",
    "sg:address":"208 Flax Hill Rd",
    "sg:city":"Norwalk",
    "sg:classifiers":[
        {
            "category":"Retail",
            "subcategory":"Portrait Studio",
            "type":"Services"
        }
    ],
    "sg:phone":"+1   ",
    "sg:postcode":"06854",
    "sg:province":"CT",
    "sg:tags":[
        "photo"
    ],
    "wof:name":"Thought and Vision LLC",
    "wof:placetype":"venue"
},
  "geometry": {"coordinates":[-73.42592399999999,41.09624],"type":"Point"}
}