{
  "type": "Feature",
  "properties": {
    "addr:full":"181 Westchester Ave Port Chester CT 10573",
    "addr:housenumber":"181",
    "addr:postcode":"10573",
    "addr:street":"Westchester Ave;Chester",
    "iso:country":"US",
    "sg:address":"181 Westchester Ave",
    "sg:city":"Port Chester",
    "sg:classifiers":[
        {
            "category":"Professional",
            "type":"Services"
        }
    ],
    "sg:phone":"+1 914 937 4615",
    "sg:postcode":"10573",
    "sg:province":"CT",
    "sg:tags":[
        "establishment"
    ],
    "wof:name":"Oxalaga International",
    "wof:placetype":"venue"
},
  "geometry": {"coordinates":[-73.666222,41.001949],"type":"Point"}
}