{
  "type": "Feature",
  "properties": {
    "iso:country":"US",
    "sg:address":"71 Elm St",
    "sg:city":"West Haven",
    "sg:classifiers":[
        {
            "category":"Restaurant",
            "type":"Food & Drink"
        }
    ],
    "sg:phone":"+1 203 934 2683",
    "sg:postcode":"06516",
    "sg:province":"CT",
    "sg:tags":[
        "eating"
    ],
    "wof:name":"Charcoal Chicken",
    "wof:placetype":"venue"
},
  "geometry": {"coordinates":[-72.944389,41.278335],"type":"Point"}
}