{
  "type": "Feature",
  "properties": {
    "addr:full":"190 Henry St Stamford CT 06902",
    "addr:housenumber":"190",
    "addr:postcode":"06902",
    "addr:street":"Henry St",
    "iso:country":"US",
    "sg:address":"190 Henry St",
    "sg:city":"Stamford",
    "sg:classifiers":[
        {
            "category":"Real Estate",
            "subcategory":"Architect",
            "type":"Services"
        }
    ],
    "sg:phone":"+1 203 325 2399",
    "sg:postcode":"06902",
    "sg:province":"CT",
    "wof:name":"ZHDC Architect & Design",
    "wof:placetype":"venue"
},
  "geometry": {"coordinates":[-73.538436,41.044626],"type":"Point"}
}