{
  "type": "Feature",
  "properties": {
    "addr:full":"396 Danbury Rd Wilton CT 06897",
    "addr:housenumber":"396",
    "addr:postcode":"06897",
    "addr:street":"Danbury Rd Wilton Ct",
    "iso:country":"US",
    "sg:address":"396 Danbury Rd",
    "sg:city":"Wilton",
    "sg:classifiers":[
        {
            "category":"Professional",
            "subcategory":"Lawyer & Legal Services",
            "type":"Services"
        }
    ],
    "sg:phone":"+1   ",
    "sg:postcode":"06897",
    "sg:province":"CT",
    "wof:name":"Meehan William A",
    "wof:placetype":"venue"
},
  "geometry": {"coordinates":[-73.431928,41.211085],"type":"Point"}
}