{
  "type": "Feature",
  "properties": {
    "addr:full":"140 Midland Ave Port Chester CT 10573",
    "addr:housenumber":"140",
    "addr:postcode":"10573",
    "addr:street":"Midland Ave;Chester",
    "iso:country":"US",
    "sg:address":"140 Midland Ave",
    "sg:city":"Port Chester",
    "sg:classifiers":[
        {
            "category":"Personal",
            "subcategory":"Beauty Salon",
            "type":"Services"
        }
    ],
    "sg:phone":"+1 914 939 5577",
    "sg:postcode":"10573",
    "sg:province":"CT",
    "wof:name":"Nail Plaza",
    "wof:placetype":"venue"
},
  "geometry": {"coordinates":[-73.667936,40.99375],"type":"Point"}
}