{
  "type": "Feature",
  "properties": {
    "addr:full":"94 Ralph St Bridgeport CT 06606",
    "addr:housenumber":"94",
    "addr:postcode":"06606",
    "addr:street":"Ralph St",
    "iso:country":"US",
    "sg:address":"94 Ralph St",
    "sg:city":"Bridgeport",
    "sg:classifiers":[
        {
            "category":"Building & Trades",
            "subcategory":"Cleaning & Sanitation",
            "type":"Services"
        }
    ],
    "sg:phone":"+1   ",
    "sg:postcode":"06606",
    "sg:province":"CT",
    "sg:tags":[
        "maintenance"
    ],
    "wof:name":"Fatima Cleaning Services",
    "wof:placetype":"venue"
},
  "geometry": {"coordinates":[-73.226815,41.221514],"type":"Point"}
}