{
  "type": "Feature",
  "properties": {
    "iso:country":"US",
    "sg:address":"27 Park Ln",
    "sg:city":"Westport",
    "sg:classifiers":[
        {
            "category":"Retail",
            "subcategory":"Veterinary Services",
            "type":"Services"
        }
    ],
    "sg:phone":"+1 203 227 5557",
    "sg:postcode":"06880",
    "sg:province":"CT",
    "sg:tags":[
        "veterinarian"
    ],
    "wof:name":"Visiting Vet Svc",
    "wof:placetype":"venue"
},
  "geometry": {"coordinates":[-73.348812,41.137264],"type":"Point"}
}