{
  "type": "Feature",
  "properties": {
    "iso:country":"US",
    "sg:address":"75 Glen Rd",
    "sg:city":"Sandy Hook",
    "sg:classifiers":[
        {
            "category":"Restaurant",
            "type":"Food & Drink"
        }
    ],
    "sg:phone":"+1 203 426 4441",
    "sg:postcode":"06482",
    "sg:province":"CT",
    "wof:name":"Firehouse Bar & Restaurant",
    "wof:placetype":"venue"
},
  "geometry": {"coordinates":[-73.275572,41.432175],"type":"Point"}
}