{
  "type": "Feature",
  "properties": {
    "iso:country":"US",
    "sg:address":"37 Water St",
    "sg:city":"Mystic",
    "sg:classifiers":[
        {
            "category":"Professional",
            "subcategory":"Computer Services",
            "type":"Services"
        }
    ],
    "sg:phone":"+1   ",
    "sg:postcode":"06355",
    "sg:province":"CT",
    "sg:tags":[
        "prepackaged",
        "software"
    ],
    "wof:name":"Baggy Chic Inc",
    "wof:placetype":"venue"
},
  "geometry": {"coordinates":[-71.972002,41.351198],"type":"Point"}
}