{
  "type": "Feature",
  "properties": {
    "iso:country":"US",
    "sg:address":"42 Woodland Ln",
    "sg:city":"New Hartford",
    "sg:classifiers":[
        {
            "category":"Building & Trades",
            "subcategory":"Construction",
            "type":"Services"
        }
    ],
    "sg:phone":"+1 860 489 0656",
    "sg:postcode":"06057",
    "sg:province":"CT",
    "sg:tags":[
        "contractor"
    ],
    "wof:name":"Jl Building & Remodeling",
    "wof:placetype":"venue"
},
  "geometry": {"coordinates":[-73.061401,41.823799],"type":"Point"}
}