{
  "type": "Feature",
  "properties": {
    "addr:full":"9 Mill Village Pentway North Stonington CT 06359",
    "addr:housenumber":"9",
    "addr:postcode":"06359",
    "addr:street":"Mill;Pentway North Stonington Ct",
    "iso:country":"US",
    "sg:address":"9 Mill Village Pentway",
    "sg:city":"North Stonington",
    "sg:classifiers":[
        {
            "category":"Building & Trades",
            "subcategory":"Construction",
            "type":"Services"
        }
    ],
    "sg:phone":"+1 860 535 3371",
    "sg:postcode":"06359",
    "sg:province":"CT",
    "sg:tags":[
        "house"
    ],
    "wof:name":"Ace Home Inspections LLC",
    "wof:placetype":"venue"
},
  "geometry": {"coordinates":[-71.882413,41.424502],"type":"Point"}
}